Workbook
Name Company: [1]UEL!$B$18:$B$20
Name Dates: [1]ONT!$N$2:$AN$2
Name DetailedCapShares: '[2]Current Cap'!$T$133
Name FAGroup: [1]UEL!$B$3:$B$15
Name IQ_CH: 110000
Name IQ_CQ: 5000
Name IQ_CY: 10000
Name IQ_DAILY: 500000
Name IQ_FH: 100000
Name IQ_FQ: 500
Name IQ_FY: 1000
Name IQ_LTM: 2000
Name IQ_MONTH: 15000
Name IQ_NTM: 6000
Name IQ_WEEK: 50000
Name IQ_YTD: 3000

Sheet D
C2: Date of NAV | D2: 44834
H3: D A S H B O A R D | L3: figures in USD Millions
D6: # Investments | E6: Committed | F6: Invested | G6: Remaining | H6: Distributions | I6: Residual Value | J6: IRR | K6: TVPI | L6: RPI | M6: DPI | Q6: A T T R I B U T I O N S U M M A R Y
C8: EQUITY | D8: =COUNTIF('Summary | 01 '!C10:C24,"*") -> 15 | E8: ='1. IRR Equity1'!AC28 -> 2063.4981 | F8: ='1. IRR Equity1'!AD28 -> 2050.9949 | G8: ='1. IRR Equity1'!AE28 -> 12.503161 | H8: ='1. IRR Equity1'!AF28 -> 5 | I8: ='1. IRR Equity1'!AG28 -> 2154.3486 | J8: ='1. IRR Equity1'!AH28 -> 0.064125332 | K8: ='1. IRR Equity1'!AI28 -> 1.0528298 | L8: ='1. IRR Equity1'!AJ28 -> 1.050392 | M8: ='1. IRR Equity1'!AK28 -> 0.0024378412 | Q8: TOP GAINERS
Q9: Heygears | R9: Equity | S9: 76.64
Q10: Flyr Inc | R10: Equity | S10: 68.08223
C11: DEBT | D11: =COUNTIF('Summary | 01 '!C28:C30,"*") -> 3 | E11: ='2. IRR Debt'!Q12 -> 10.765747 | F11: ='2. IRR Debt'!R12 -> 10.765747 | G11: ='2. IRR Debt'!S12 -> 0 | H11: ='2. IRR Debt'!T12 -> 0 | I11: ='2. IRR Debt'!U12 -> 2.8104207 | J11: ='2. IRR Debt'!V12 -> -0.40060765 | K11: ='2. IRR Debt'!W12 -> 0.26105208 | L11: ='2. IRR Debt'!X12 -> 0.26105208 | M11: ='2. IRR Debt'!Y12 -> 0 | Q11: Honor Device Co Ltd | R11: Equity | S11: 60.462713
Q12: New Space Capital Fund I | R12: Fund | S12: 10.340849
Q13: ONT plc | R13: Equity | S13: 8.1105485
C14: FUNDS | D14: =COUNTIF('Summary | 01 '!C34:C38,"*") -> 5 | E14: ='3. IRR Funds'!Q15 -> 395.37629 | F14: ='3. IRR Funds'!R15 -> 134.94959 | G14: ='3. IRR Funds'!S15 -> 261.45466 | H14: ='3. IRR Funds'!T15 -> 1.4717893 | I14: ='3. IRR Funds'!U15 -> 140.19737 | J14: ='3. IRR Funds'!V15 -> 0.027224669 | K14: ='3. IRR Funds'!W15 -> 1.0497931 | L14: ='3. IRR Funds'!X15 -> 1.0388869 | M14: ='3. IRR Funds'!Y15 -> 0.010906215 | Q14: Esyasoft Holding | R14: Equity | S14: 2.5
Q15: Beyond Limits | R15: Equity | S15: 1.0015403
C17: TOTAL | D17: =D8+D11+D14 -> 23 | E17: =E8+E11+E14 -> 2469.6401 | F17: =F8+F11+F14 -> 2196.7103 | G17: =G8+G11+G14 -> 273.95782 | H17: =H8+H11+H14 -> 6.4717893 | I17: =I8+I11+I14 -> 2297.3564 | J17: ='4.All'!N9 -> 0.054621205 | K17: =(H17+I17)/F17 -> 1.0487629 | L17: =I17/F17 -> 1.0458168 | M17: =H17/F17 -> 0.0029461279 | Q17: TOP LOSERS
Q18: Jollychic Holding Limited | R18: Equity | S18: -65
E19: =E17='Summary | 01 '!J41 -> TRUE | F19: =F17='Summary | 01 '!K41 -> TRUE | G19: =ROUND(G17,1)=ROUND('Summary | 01 '!L41,1) -> TRUE | H19: =ROUND(H17,1)=ROUND('Summary | 01 '!M41,1) -> TRUE | I19: =ROUND(I17,1)=ROUND('Summary | 01 '!N41,1) -> TRUE | Q19: vTv Therapeutics Inc. | R19: Equity | S19: -13.055785
Q20: Glass Earth Holdings LLC | R20: Debt | S20: -8
Q21: Mena Mobile Inc | R21: Equity | S21: -4.9
C22: Equity Only | D22: # Investments | E22: Committed | F22: Invested | G22: Remaining | H22: Distributions | I22: Residual Value | J22: IRR | K22: TVPI | L22: RPI | M22: DPI | Q22: North Summit Capital Fund | R22: Fund | S22: -2.866692
Q23: Sinovation Disrupt Fund, L.P. | R23: Fund | S23: -0.47118065
C24: Select Portfolio1 IRR | D24: ='1.1(P1)'!O23 -> 9 | E24: ='1.1(P1)'!P23 -> 379.99398 | F24: ='1.1(P1)'!Q23 -> 379.99398 | G24: ='1.1(P1)'!R23 -> 0 | H24: ='1.1(P1)'!S23 -> 5 | I24: ='1.1(P1)'!T23 -> 442.81028 | J24: ='1.1(P1)'!U23 -> 0.076285401 | K24: ='1.1(P1)'!V23 -> 1.1784668 | ... M24: ='1.1(P1)'!X23 -> 0.013158103 | Q24: Acies Investments Fund I, L.P. | R24: Fund | S24: -0.2834155
C26: Vintage 2019 | Equity | D26: 3 | E26: =F26 -> 83 | F26: 83 | G26: 0 | H26: 0 | I26: 81.18223 | J26: -0.0067133114 | K26: 0.97809916 | L26: 0.97809916 | M26: 0 | Q26: TOTAL MOVEMENT | S26: =SUM(S9:S24) -> 132.56081
C28: Vintage 2020 | Equity | D28: 4 | E28: =F28 -> 293.97026 | F28: 293.97026 | G28: 0 | H28: 5 | I28: 377.22235 | J28: 0.12646896 | K28: 1.3002075 | L28: 1.283199 | M28: 0.017008523
C30: Vintage 2021 | Equity | D30: 2 | E30: =F30 -> 8.0237202 | F30: 8.0237202 | G30: 0 | H30: 0 | I30: 8.0237202 | J30: 2.9802322e-09 | K30: 1 | L30: 1 | M30: 0
C34: Includes Equity, Debt, Funds
D35: # Investments | E35: Committed | F35: Invested | G35: Remaining | H35: Distributions | I35: Residual Value | J35: IRR | K35: TVPI | L35: RPI | M35: DPI
C37: Asia-China | D37: 8 | E37: 2578.854 | F37: 1528.8598 | G37: =E37-F37 -> 1049.9941 | H37: 1.4717893 | I37: 1591.9989 | J37: 0.064502594 | K37: 1.0422608 | L37: 1.0412981 | M37: 0.00096267121
C39: Rest of Asia | D39: 3 | E39: 22.911765 | F39: 22.911765 | G39: 0 | H39: 5 | I39: 20.456439 | J39: 0.082198861 | K39: 1.1110641 | L39: 0.89283557 | M39: 0.2182285
C41: Middle East | D41: 1 | E41: 300 | F41: 300 | G41: 0 | H41: 0 | I41: 300 | J41: 2.9802322e-09 | K41: 1 | L41: 1 | M41: 0
C43: USA | D43: 7 | E43: 193.1125 | F43: 174.12686 | G43: 18.985638 | H43: 0 | I43: 221.87142 | J43: 0.12701625 | K43: 1.2503351 | L43: 1.2503351 | M43: 0
C45: Europe | D45: 4 | E45: 174.76187 | F45: 170.81591 | G45: 3.9459573 | H45: 0 | I45: 189.26321 | J45: 0.048084196 | K45: 1.1080218 | L45: 1.1080218 | M45: 0
C48: Notes
C49: Select Portfolio1 includes Jollychic, Mena Mobile, Flyr, Esyasoft, BL, ONT, Heygears, Endless, Instadeep
C50: Vintage 2019 includes Jollychic, Mena Mobile, Flyr
C51: Vintage 2020 includes Esyasoft, BL, ONT, Heygears
C52: Vintage 2021 includes Endless, Instadeep

Sheet Summary | 01 
C2: As of date | D2: =D!D2 -> 44834
C6: Deals | D6: Status | E6: Lead | F6: Investing Entity | G6: Instrument | H6: Vintageἀ | I6: % | J6: Committed | K6: Invested | L6: Remaining Commitment | M6: Distributions | N6: Carrying Value | O6: TVPI | P6: IRR | Q6: Additonal Upside
C9: Direct Investments
C10: Jollychic Holding Limited | D10: Unrealized | E10: Elaine | F10: Mozn | G10: C+ Prefs | H10: 2019 | I10: ='%'!F11 -> 0.056999998 | J10: 65 | K10: =-SUMIF('CF (Equity, Debt)'!$C$3:$K$31,'Summary | 01 '!C10,'CF (Equity, Debt)'!$E$3:$E$31) -> 65 | L10: 0 | M10: =SUMIF('CF (Equity, Debt)'!$C$3:$K$31,'Summary | 01 '!C10,'CF (Equity, Debt)'!$F$3:$F$31) -> 0 | N10: =NAV!D9 -> 0 | O10: =(M10+N10)/K10 -> 0 | P10: =VLOOKUP(C10,'1. IRR Equity1'!AB12:AK26,7,0) -> NM
C11: Mena Mobile Inc | D11: Unrealized | E11: Elaine | F11: Mozn | G11: B Prefs | H11: 2019 | I11: ='%'!F12 -> 0.14 | J11: 8 | K11: =-SUMIF('CF (Equity, Debt)'!$C$3:$K$31,'Summary | 01 '!C11,'CF (Equity, Debt)'!$E$3:$E$31) -> 8 | L11: 0 | M11: =SUMIF('CF (Equity, Debt)'!$C$3:$K$31,'Summary | 01 '!C11,'CF (Equity, Debt)'!$F$3:$F$31) -> 0 | N11: =NAV!D10 -> 3.1 | O11: =(M11+N11)/K11 -> 0.3875 | P11: =VLOOKUP(C11,'1. IRR Equity1'!AB13:AK27,7,0) -> -0.23833896
C12: Flyr Inc | D12: Unrealized | E12: Sushil | F12: Mozn | G12: B-1,2 Prefs | H12: 2019 | I12: ='%'!F13 -> 0.085025485 | J12: 10 | K12: =-SUMIF('CF (Equity, Debt)'!$C$3:$K$31,'Summary | 01 '!C12,'CF (Equity, Debt)'!$E$3:$E$31) -> 10 | L12: 0 | M12: =SUMIF('CF (Equity, Debt)'!$C$3:$K$31,'Summary | 01 '!C12,'CF (Equity, Debt)'!$F$3:$F$31) -> 0 | N12: =NAV!D11 -> 78.08223 | O12: =(M12+N12)/K12 -> 7.808223 | P12: =VLOOKUP(C12,'1. IRR Equity1'!AB14:AK28,7,0) -> 0.95566303 | Q12: Flyr Warrantsa
C13: Esyasoft Holding | D13: Realized | E13: Sushil | F13: Mozn | G13: Convertible Note | H13: 2020 | I13: ='%'!F14 -> n/a | J13: 2.5 | K13: =-SUMIF('CF (Equity, Debt)'!$C$3:$K$31,'Summary | 01 '!C13,'CF (Equity, Debt)'!$E$3:$E$31) -> 2.5 | L13: 0 | M13: =SUMIF('CF (Equity, Debt)'!$C$3:$K$31,'Summary | 01 '!C13,'CF (Equity, Debt)'!$F$3:$F$31) -> 5 | N13: =NAV!D12 -> 0 | O13: =(M13+N13)/K13 -> 2 | P13: =VLOOKUP(C13,'1. IRR Equity1'!AB15:AK29,7,0) -> 0.36091766
C14: Beyond Limits | D14: Unrealized | E14: Divyesh | F14: Mozn | G14: C Prefs | H14: 2020 | I14: ='%'!F15 -> 0.09739482 | J14: 90 | K14: =-SUMIF('CF (Equity, Debt)'!$C$3:$K$31,'Summary | 01 '!C14,'CF (Equity, Debt)'!$E$3:$E$31) -> 90 | L14: 0 | M14: =SUMIF('CF (Equity, Debt)'!$C$3:$K$31,'Summary | 01 '!C14,'CF (Equity, Debt)'!$F$3:$F$31) -> 0 | N14: =NAV!D13 -> 91.00154 | O14: =(M14+N14)/K14 -> 1.0111282 | P14: =VLOOKUP(C14,'1. IRR Equity1'!AB16:AK30,7,0) -> 0.0046035081
C15: ONT plc | D15: Unrealized | E15: Divyesh | F15: Mozn | G15: Ordinary Shares | H15: 2020 | I15: ='%'!F16 -> 0.053819975 | J15: 141.47026 | K15: =-SUMIF('CF (Equity, Debt)'!$C$3:$K$31,'Summary | 01 '!C15,'CF (Equity, Debt)'!$E$3:$E$31) -> 141.47026 | L15: 0 | M15: =SUMIF('CF (Equity, Debt)'!$C$3:$K$31,'Summary | 01 '!C15,'CF (Equity, Debt)'!$F$3:$F$31) -> 0 | N15: =NAV!D14 -> 125.96279 | O15: =(M15+N15)/K15 -> 0.89038351 | P15: =VLOOKUP(C15,'1. IRR Equity1'!AB17:AK31,7,0) -> -0.049104276
C16: Heygears | D16: Unrealized | E16: Elaine | F16: Mozn | G16: Registered Capital | H16: 2020 | I16: ='%'!F17 -> 0.1438 | J16: 60 | K16: =-SUMIF('CF (Equity, Debt)'!$C$3:$K$31,'Summary | 01 '!C16,'CF (Equity, Debt)'!$E$3:$E$31) -> 60 | L16: 0 | M16: =SUMIF('CF (Equity, Debt)'!$C$3:$K$31,'Summary | 01 '!C16,'CF (Equity, Debt)'!$F$3:$F$31) -> 0 | N16: =NAV!D15 -> 136.64 | O16: =(M16+N16)/K16 -> 2.2773333 | P16: =VLOOKUP(C16,'1. IRR Equity1'!AB18:AK32,7,0) -> 0.5678354
C17: Jysan Technologies | D17: To be Exited | E17: Sushil | F17: QAZ42 | G17: A (Ordinary Shares) | H17: 2021 | I17: ='%'!F18 -> 0.03 | J17: 20 | K17: =-SUMIF('CF (Equity, Debt)'!$C$3:$K$31,'Summary | 01 '!C17,'CF (Equity, Debt)'!$E$3:$E$31) -> 20 | L17: 0 | M17: =SUMIF('CF (Equity, Debt)'!$C$3:$K$31,'Summary | 01 '!C17,'CF (Equity, Debt)'!$F$3:$F$31) -> 0 | N17: =NAV!D16 -> 20 | O17: =(M17+N17)/K17 -> 1 | P17: =VLOOKUP(C17,'1. IRR Equity1'!AB19:AK33,7,0) -> 2.9802322e-09
C18: Cerebras Systems Inc | D18: Unrealized | E18: Ignasi | F18: Mozn | G18: F Prefs | H18: 2021 | I18: ='%'!F19 -> 0.01 | J18: 40 | K18: =-SUMIF('CF (Equity, Debt)'!$C$3:$K$31,'Summary | 01 '!C18,'CF (Equity, Debt)'!$E$3:$E$31) -> 39.999983 | L18: 0 | M18: =SUMIF('CF (Equity, Debt)'!$C$3:$K$31,'Summary | 01 '!C18,'CF (Equity, Debt)'!$F$3:$F$31) -> 0 | N18: =NAV!D17 -> 39.999983 | O18: =(M18+N18)/K18 -> 1 | P18: =VLOOKUP(C18,'1. IRR Equity1'!AB20:AK34,7,0) -> 2.9802322e-09
C19: Endless Studios LLC | D19: Unrealized | E19: Sushil | F19: Mozn | G19: A Pref Units | H19: 2021 | I19: ='%'!F20 -> 0.068571429 | J19: 3 | K19: =-SUMIF('CF (Equity, Debt)'!$C$3:$K$31,'Summary | 01 '!C19,'CF (Equity, Debt)'!$E$3:$E$31) -> 3 | L19: 0 | M19: =SUMIF('CF (Equity, Debt)'!$C$3:$K$31,'Summary | 01 '!C19,'CF (Equity, Debt)'!$F$3:$F$31) -> 0 | N19: =NAV!D18 -> 3 | O19: =(M19+N19)/K19 -> 1 | P19: =VLOOKUP(C19,'1. IRR Equity1'!AB21:AK35,7,0) -> 2.9802322e-09
C20: Instadeep Limited | D20: Unrealized | E20: Ignasi | F20: Mozn | G20: B Prefs | H20: 2021 | I20: ='%'!F21 -> 0.011489406 | J20: 5.0278212 | K20: =-SUMIF('CF (Equity, Debt)'!$C$3:$K$31,'Summary | 01 '!C20,'CF (Equity, Debt)'!$E$3:$E$31) -> 5.0237202 | L20: 0 | M20: =SUMIF('CF (Equity, Debt)'!$C$3:$K$31,'Summary | 01 '!C20,'CF (Equity, Debt)'!$F$3:$F$31) -> 0 | N20: =NAV!D19 -> 5.0237202 | O20: =(M20+N20)/K20 -> 1 | P20: =VLOOKUP(C20,'1. IRR Equity1'!AB22:AK36,7,0) -> 2.9802322e-09
C21: X-fusion | D21: Unrealized | E21: Elaine | F21: Enterprise Connection | G21: Equity-TBC | H21: 2022 | I21: ='%'!F22 -> 0.05 | J21: 493.5 | K21: =-SUMIF('CF (Equity, Debt)'!$C$3:$K$31,'Summary | 01 '!C21,'CF (Equity, Debt)'!$E$3:$E$31) -> 493.50096 | L21: 0 | M21: =SUMIF('CF (Equity, Debt)'!$C$3:$K$31,'Summary | 01 '!C21,'CF (Equity, Debt)'!$F$3:$F$31) -> 0 | N21: 493.5 | O21: =(M21+N21)/K21 -> 0.99999806 | P21: =VLOOKUP(C21,'1. IRR Equity1'!AB23:AK37,7,0) -> 2.9802322e-09
C22: DriveNets | D22: Unrealized | E22: Anton | F22: G42 | G22: Equity-TBC | H22: 2022 | I22: ='%'!F23 -> 0.0943 | J22: 300 | K22: =-SUMIF('CF (Equity, Debt)'!$C$3:$K$31,'Summary | 01 '!C22,'CF (Equity, Debt)'!$E$3:$E$31) -> 300 | L22: =0 -> 0 | M22: =SUMIF('CF (Equity, Debt)'!$C$3:$K$31,'Summary | 01 '!C22,'CF (Equity, Debt)'!$F$3:$F$31) -> 0 | N22: =NAV!D21 -> 300 | O22: =(M22+N22)/K22 -> 1 | P22: =VLOOKUP(C22,'1. IRR Equity1'!AB24:AK38,7,0) -> 2.9802322e-09 | Q22: DN Warrants b
C23: vTv Therapeutics Inc. | D23: Unrealized | E23: Divyesh | F23: G42 | G23: Ordinary Shares | H23: 2022 | I23: ='%'!F24 -> 0.099316564 | J23: 25 | K23: =-SUMIF('CF (Equity, Debt)'!$C$3:$K$31,'Summary | 01 '!C23,'CF (Equity, Debt)'!$E$3:$E$31) -> 12.5 | L23: =J23-K23 -> 12.5 | M23: =SUMIF('CF (Equity, Debt)'!$C$3:$K$31,'Summary | 01 '!C23,'CF (Equity, Debt)'!$F$3:$F$31) -> 0 | N23: =NAV!D22 -> -2.4253142 | O23: =(M23+N23)/K23 -> -0.19402514 | P23: =VLOOKUP(C23,'1. IRR Equity1'!AB25:AK39,7,0) -> NM | Q23: vTv $30m milestn payment c
C24: Honor Device Co Ltd | D24: Unrealized | E24: Elaine | F24: Smart Interaction | G24: Equity-TBC | H24: 2022 | I24: ='%'!F25 -> 0.0188 | J24: =K24 -> 800 | K24: =-SUMIF('CF (Equity, Debt)'!$C$3:$K$31,'Summary | 01 '!C24,'CF (Equity, Debt)'!$E$3:$E$31) -> 800 | L24: =J24-K24 -> 0 | M24: =SUMIF('CF (Equity, Debt)'!$C$3:$K$31,'Summary | 01 '!C24,'CF (Equity, Debt)'!$F$3:$F$31) -> 0 | N24: =NAV!D23 -> 860.46271 | O24: =(M24+N24)/K24 -> 1.0755784 | P24: =VLOOKUP(C24,'1. IRR Equity1'!AB26:AK40,7,0) -> NM
J25: =SUM(J10:J24) -> 2063.4981 | K25: =SUM(K10:K24) -> 2050.9949 | L25: =SUM(L10:L24) -> 12.5 | M25: =SUM(M10:M24) -> 5 | N25: =SUM(N10:N24) -> 2154.3477 | O25: =(M25+N25)/K25 -> 1.0528294
C27: Debt Investments
C28: Glass Earth Holdings LLC | D28: In default | F28: Mozn | G28: Promissory Note | H28: 2019 | I28: NA | J28: 8 | K28: 8 | L28: 0 | M28: 0 | N28: 0 | O28: =(M28+N28)/K28 -> 0 | P28: =VLOOKUP(C28,'2. IRR Debt'!P9:Y11,7,0) -> NM
C29: Mena Mobile Inc | D29: In default | E29: Elaine | F29: Mozn | G29: Loan | H29: 2021 | I29: NA | J29: 2.353982 | K29: =J29 -> 2.353982 | L29: 0 | M29: 0 | N29: =K29 -> 2.353982 | O29: =(M29+N29)/K29 -> 1 | P29: =VLOOKUP(C29,'2. IRR Debt'!P10:Y12,7,0) -> 2.9802322e-09
C30: Esyasoft Holding | D30: Unrealized | E30: Sushil | F30: Mozn | G30: Loan | H30: 2021 | I30: NA | J30: 0.411765 | K30: 0.411765 | L30: 0 | M30: 0 | N30: =456438.682191781/1000000 -> 0.45643868 | O30: =(M30+N30)/K30 -> 1.1084932 | P30: =VLOOKUP(C30,'2. IRR Debt'!P11:Y13,7,0) -> 0.087134919
J31: =SUM(J28:J30) -> 10.765747 | K31: =SUM(K28:K30) -> 10.765747 | L31: =SUM(L28:L30) -> 0 | M31: =SUM(M28:M30) -> 0 | N31: =SUM(N28:N30) -> 2.8104207 | O31: =(M31+N31)/K31 -> 0.26105208
C33: Funds Investments
C34: New Space Capital Fund I | D34: Unrealized | E34: Sushil | F34: G42 | G34: LP | H34: 2020 | I34: NA | J34: =23.2344618712304*1.1 -> 25.557908 | K34: 21.611951 | L34: 3.9459573 | M34: 0 | N34: 31.952799 | O34: 1.4784783 | P34: 0.21877305
C35: New Space Capital SCSp | D35: Unrealized | E35: Sushil | F35: G42 | G35: GP | H35: 2020 | I35: NA | J35: =2.3/0.85 -> 2.7058824 | K35: 2.7058824 | L35: 0 | M35: 0 | N35: 2.7058824 | O35: 1 | P35: 0
C36: North Summit Capital Fund | D36: Unrealized | E36: Elaine | F36: G42 | G36: LP | H36: 2020 | I36: NA | J36: 300 | K36: 83.214653 | L36: 217.81331 | M36: 1.027961 | N36: 79.32 | O36: 0.96555063 | P36: -0.018566843
C37: Sinovation Disrupt Fund, L.P. | D37: Unrealized | E37: Elaine | F37: G42 | G37: LP | H37: 2020 | I37: NA | J37: 50 | K37: 16.790246 | L37: 33.209754 | M37: 0.44382835 | N37: 15.875237 | O37: 0.97193724 | P37: -0.01726273
C38: Acies Investments Fund I, L.P. | D38: Unrealized | E38: Divyesh | F38: G42 | G38: LP | H38: 2021 | I38: 0.33 | J38: 17.1125 | K38: 10.626862 | L38: 6.4856375 | M38: 0 | N38: 10.343447 | O38: 0.97333028 | P38: -0.050154206 | Q38: 9.9% GP | Anchor
J39: =SUM(J34:J38) -> 395.37629 | K39: =SUM(K34:K38) -> 134.94959 | L39: =SUM(L34:L38) -> 261.45466 | M39: =SUM(M34:M38) -> 1.4717893 | N39: =SUM(N34:N38) -> 140.19737 | O39: =(M39+N39)/K39 -> 1.0497931
C41: Total | J41: =J25+J31+J39 -> 2469.6401 | K41: =K25+K31+K39 -> 2196.7103 | L41: =L25+L31+L39 -> 273.95466 | M41: =M25+M31+M39 -> 6.4717893 | N41: =N25+N31+N39 -> 2297.3554 | O41: =(M41+N41)/K41 -> 1.0487624
C46: Notes: | G46: Additional Upside Section:
C47: NA = Not applicable or Not available | G47: a) Flyr: For every $1m of revenue, 194,477 shares, capped at 1,264,1000 (B-1) shares shall be issued to Mozn
C48: NM = Not meaningful | G48: b) DriveNets: Share warrants exercisable upon the achievement of target revenue of clients referred by G42, and corresponding milestones
C49: TBC = to be confirmed | G49: c) vTv Therapeutics: Potential issuance of $30m in additional shares, if FDA approval received for the drug TTP399
C50: G42 = G42 Investments AI Holding RSC Ltd | G50: d) Acies Investments Fund I LP: Being the Anchor investor, entitled to 9.9% of the aggregate carried interest earned by the GP
C51: Mozn = Mozn Holding RSC Ltd
C52: QAZ42 = QAZ42 Investment SPV RSC Ltd
C53: Smart Interaction = Smart Interaction1 Holding SPV RSC LTD
C54: Enterprise Connection = Enterprises Connection Holding RSC Ltd
C56: ἀ = Vintage corresponds to the year of the first investment made

Sheet Summary | 02
C2: As of date | D2: ='Summary | 01 '!D2 -> 44834
I4: Changes during the Period
I5: 1a | J5: 1b | K5: 1c | L5: 1d | N5: 3 | O5: 4
C6: Deals | D6: Status | E6: Lead | F6: Investing Entity | G6: Instrument | H6: Listed / Unlisted | I6: No. of securities held (Movement during the Period) | N6: Dividend / Interest | O6: For Comments Refer to Note
I7: Opening | J7: Acquired | K7: Re-organisation | L7: Sale / Transfer | M7: Closing
C9: Direct Investments
C10: Jollychic Holding Limited | D10: Unrealized | E10: Elaine | F10: Mozn | G10: C+ Prefs | I10: ='%'!D11 -> 13458655 | J10: 0 | K10: 0 | L10: 0 | M10: =I10 -> 13458655 | N10: 0 | O10: 1
C11: Mena Mobile Inc | D11: Unrealized | E11: Elaine | F11: Mozn | G11: B Prefs | I11: ='%'!D12 -> 21419829 | J11: 0 | K11: 0 | L11: 0 | M11: =I11 -> 21419829 | N11: 0 | O11: 2
C12: Flyr Inc | D12: Unrealized | E12: Sushil | F12: Mozn | G12: B-1,2 Prefs | I12: ='%'!D13 -> 5205482 | J12: 0 | K12: 0 | L12: 0 | N12: 0 | O12: 3
C13: Esyasoft Holding | D13: Realized | E13: Sushil | F13: Mozn | G13: Convertible Note | J13: 0 | K13: 0 | L13: 0 | N13: 0 | O13: 4
C14: Beyond Limits | D14: Unrealized | E14: Divyesh | F14: Mozn | G14: C Prefs | I14: ='%'!D15 -> 17670202 | J14: 0 | K14: 0 | L14: 0 | M14: =I14 -> 17670202 | N14: 0 | O14: 5
C15: ONT plc | D15: Unrealized | E15: Divyesh | F15: Mozn | G15: Ordinary Shares | H15: Listed | I15: ='%'!D16 -> 44328120 | J15: 0 | K15: 0 | L15: 0 | M15: =I15 -> 44328120 | N15: 0 | O15: 6
C16: Heygears | D16: Unrealized | E16: Elaine | F16: Mozn | G16: Registered Capital | I16: ='%'!D17 -> 3565017.2 | J16: 0 | K16: 0 | L16: 0 | M16: =I16 -> 3565017.2 | N16: 0 | O16: 7
C17: Jysan Technologies | D17: To be Exited | E17: Sushil | F17: QAZ42 | G17: A (Ordinary Shares) | I17: =NAV!F16 -> 7959497 | J17: 0 | K17: 0 | L17: 0 | M17: =I17 -> 7959497 | N17: 0 | O17: 8
C18: Cerebras Systems Inc | D18: Unrealized | E18: Ignasi | F18: Mozn | G18: F Prefs | I18: =NAV!F17 -> 1441711 | J18: 0 | K18: 0 | L18: 0 | M18: =I18 -> 1441711 | N18: 0 | O18: 9
C19: Endless Studios LLC | D19: Unrealized | E19: Sushil | F19: Mozn | G19: A Pref Units | I19: =NAV!F18 -> 3000000 | J19: 0 | K19: 0 | L19: 0 | M19: =I19 -> 3000000 | N19: 0 | O19: 10
C20: Instadeep Limited | D20: Unrealized | E20: Ignasi | F20: Mozn | G20: B Prefs | I20: =NAV!F19 -> 33267 | J20: 0 | K20: 0 | L20: 0 | M20: =I20 -> 33267 | N20: 0 | O20: 11
C21: X-fusion | D21: Unrealized | E21: Elaine | F21: Enterprise Connection | G21: Equity-TBC | O21: 12
C22: DriveNets | D22: Unrealized | E22: Anton | F22: G42 | G22: Equity-TBC | O22: 13
C23: vTv Therapeutics Inc. | D23: Unrealized | E23: Divyesh | F23: G42 | G23: Ordinary Shares | H23: Listed | I23: 10386274 | J23: 0 | K23: 0 | L23: 0 | M23: 10386274 | N23: 0 | O23: 14
C24: Honor Device Co Ltd | D24: Unrealized | E24: Elaine | F24: Smart Interaction | G24: Equity-TBC | O24: 15
C27: Debt Investments
C28: Glass Earth Holdings LLC | D28: In default | F28: Mozn | G28: Promissory Note | O28: 16
C29: Mena Mobile Inc | D29: In default | E29: Elaine | F29: Mozn | G29: Loan | O29: 17
C30: Esyasoft Holding | D30: Unrealized | E30: Sushil | F30: Mozn | G30: Loan | O30: 18
C33: Funds Investments
C34: New Space Capital Fund I | D34: Unrealized | E34: Sushil | F34: G42 | G34: LP | O34: 19
C35: New Space Capital SCSp | D35: Unrealized | E35: Sushil | F35: G42 | G35: GP | O35: 20
C36: North Summit Capital Fund | D36: Unrealized | E36: Elaine | F36: G42 | G36: LP | O36: 21
C37: Sinovation Disrupt Fund, L.P. | D37: Unrealized | E37: Elaine | F37: G42 | G37: LP | O37: 22
C38: Acies Investments Fund I, L.P. | D38: Unrealized | E38: Divyesh | F38: G42 | G38: LP | O38: 23
B45: Notes:
B46: 1 | C46: Jollychic | D46: During 2021, Jollychic Holding Ltd has filed for its liquidation. Therefore, investment is considered to be fully impaired in Dec 21.
B47: 2 | C47: Mena Mobile | D47: Investment is marked down based on the inputs received from 3rd party.
B48: 3 | C48: Flyr | D48: Within five years of the Initial Closing, for every USD 1mn of Qualifying Revenue generated, Flyr will issue, at no additional charge, 194,477 B-1 Prefs in the name of G42, up to a maximum of 1,264,100 B-1 Prefs.
B49: 4 | C49: Esyasoft Holding | D49: Investment in Esyasoft is in the form of Convertible Note which will convert to 21% interest on conversion on a fully diluted basis. As per Dec 2020 FS of Esyasoft, the CN was reflected as Debt - Exit of US$ 2.5 Mn Convertible Note @ 2.0x (MoC) i.e. US$ 5 Mn in May 22 - US$ 0.4 Mn represents Working Capital Loan
B50: 5 | C50: Beyond Limits | D50: Business targeting raising funds by the end of FY2022
B51: 6 | C51: ONT plc
B52: 7 | C52: Heygears | D52: Mozn's holding is RMB 4,753,356.29 of the Registered Capital.
B53: 8 | C53: Jysan Technologies | D53: - 50% of the investment has been financed by profit sharing loan. - Further, in case of exit of G42’s investment, 50% of the sale proceeds shall be paid to the lender as full and final settlement of the outstanding liability - Exit for this investment is under process. Buyback agreement is pending for signature internally. (Relevant documents to be perused by the consolidation / reporting team for details and corresponding implications, if any) - Dividend receivable amounting to US$ 3.2 m will be waived upon exit of this investment
B54: 9 | C54: Cerebras Systems Inc | D54: The investment is currently undergoing a CFIUS review.
B55: 10 | C55: Endless Studios LLC
B56: 11 | C56: Instadeep Limited | D56: Received an acuiqisiton bid from BioNtech
B57: 12 | C57: X-fusion | D57: RMB 80 Mn of Registered Capital for RMB 5.7 Bn
B58: 13 | C58: Drivenets | D58: Share warrants excisable upon the achievement of target revenue of clients by referred G42. The milestones of each target revenue and respective conversion were stated in the Term Sheet.
B59: 14 | C59: vTv Therapeutics : | D59: G42 Investments AI Holding RSC Ltd (G42 Investments) has been issued 10.3 million shares representing c. 10% of vTv on a fully diluted basis. 50% of the consideration has been paid and the remaining 50% will be payable within next 12 months. The promissory note to pay the second US$12.5 million has been issued by G42 Investments with an equity commitment letter/guarantee in place between Group 42 Holdings Ltd and G42 Investments with Group 42 Holdings to stand behind G42 Investments obligations under the promissory note. The agreements also provide for the potential issuance of US$ 30 million in additional shares of Class A Common Stock to G42 Investments (or cash in lieu of such issuance at the option of G42 Investments) if the United States Food and Drug Administration (the “FDA”) approves the marketing and sale of a pharmaceutical product containing TTP399 (Relevant documents to be perused by the consolidation / reporting team for details and corresponding implications, if any)
B60: 15 | C60: Honor | D60: Invested in Q3 2022
B61: 16 | C61: Glass Earth Holdings LLC | D61: Written off. Debt security of Glass Earth issued in 2019 were fully provided for.
B62: 17 | C62: Mena Mobile (Debt) | D62: Outstanding
B63: 18 | C63: Esyasoft Holding (Debt) | D63: Outstanding
B64: 19 | C64: New Space Capital Fund I | D64: G42 negotiated conversion of €2.3m GP investment into LP investment to vote in favor of new LP proposal. Final details of conversion awaited
B65: 20 | C65: New Space Capital SCSp | D65: Ibid
B66: 21 | C66: North Summit Capital | D66: Portfolio Exit Plan in Progress
B67: 22 | C67: Sinovation Disrupt Fund | D67: Expect valuation to rise as some of its portfolio companies are in the market to raise new funds
B68: 23 | C68: Acies Investments Fund I, LP
B70: 17,18,19: no comments

Sheet NAV
B2: NAV Date | C2: =D!D2 -> 44834
B5: Investments | C5: Instrument | D5: Carrying Value | E5: Carrying Value | F5: Current Shares/Units | G5: PPS | 30 Sep 2022 | H5: Comment
D6: USD, Million | E6: USD, Million | F6: # | G6: USD
D7: ="NAV | "& TEXT(C2,"dd")&" "&TEXT(C2,"mmm")&" "&TEXT(C2,"yyyy") -> NAV | 30 Sep 2022 | E7: NAV | 30 Jun 2022
B8: Direct Investments
B9: Jollychic Holding Limited | C9: ='Summary | 01 '!G10 -> C+ Prefs | D9: =F9*G9*10^-6 -> 0 | E9: 0 | F9: =SUM('CF (Equity, Debt)'!J4:J6) -> 13458655 | G9: 0 | H9: In Liquidation
B10: Mena Mobile Inc | C10: ='Summary | 01 '!G11 -> B Prefs | D10: 3.1 | E10: =D10 -> 3.1 | F10: ='CF (Equity, Debt)'!J7 -> 21419829 | H10: As per 3rd Party | Ardent Estimates
B11: Flyr Inc | C11: ='Summary | 01 '!G12 -> B-1,2 Prefs | D11: =F11*G11*10^-6*(1-20%) -> 78.08223 | E11: =D11 -> 78.08223 | F11: 5205482 | G11: 18.75 | H11: At Series C PPS $18.75/share with 20% discount
B12: Esyasoft Holding | C12: ='Summary | 01 '!G13 -> Convertible Note | D12: 0 | E12: =D12 -> 0 | F12: N/A | H12: Exit at $5m (10th May) | Residual value = 0
B13: Beyond Limits | C13: ='Summary | 01 '!G14 -> C Prefs | D13: =F13*G13*10^-6 -> 91.00154 | E13: =D13 -> 91.00154 | F13: =SUM('CF (Equity, Debt)'!J11:J14) -> 17670202 | G13: 5.15 | H13: Held at cost (as per revised management guidance)
B14: ONT plc | C14: ='Summary | 01 '!G15 -> Ordinary Shares | D14: =F14*G14*10^-6 -> 125.96279 | E14: =2.66*1.22*F14*10^-6 -> 143.85362 | F14: 44328120 | G14: =2.56*1.11 -> 2.8416 | H14: Listed & marked to market
B15: Heygears | C15: ='Summary | 01 '!G16 -> Registered Capital | D15: 136.64 | E15: =D15 -> 136.64 | F15: ='CF (Equity, Debt)'!J20 -> 4753356.3 | H15: Negotiating final terms of a new round at $1.5Bn
B16: Jysan Technologies | C16: ='Summary | 01 '!G17 -> A (Ordinary Shares) | D16: =-'CF (Equity, Debt)'!E21 -> 20 | E16: =D16 -> 20 | F16: ='CF (Equity, Debt)'!J21 -> 7959497 | G16: =D16*10^6/F16 -> 2.5127216 | H16: Held at cost. To be exited
B17: Cerebras Systems Inc | C17: ='Summary | 01 '!G18 -> F Prefs | D17: =-'CF (Equity, Debt)'!E22 -> 39.999983 | E17: =D17 -> 39.999983 | F17: ='CF (Equity, Debt)'!J22 -> 1441711 | H17: Held at cost. To be exited
B18: Endless Studios LLC | C18: ='Summary | 01 '!G19 -> A Pref Units | D18: =-'CF (Equity, Debt)'!E23 -> 3 | E18: =D18 -> 3 | F18: ='CF (Equity, Debt)'!J23 -> 3000000 | H18: Held at cost.
B19: Instadeep Limited | C19: ='Summary | 01 '!G20 -> B Prefs | D19: =-'CF (Equity, Debt)'!E24 -> 5.0237202 | E19: =D19 -> 5.0237202 | F19: ='CF (Equity, Debt)'!J24 -> 33267 | H19: Held at cost.
B20: X-fusion | C20: ='Summary | 01 '!G21 -> Equity-TBC | D20: =-'CF (Equity, Debt)'!E25 -> 493.50096 | E20: =D20 -> 493.50096 | H20: Held at cost.
B21: DriveNets | C21: ='Summary | 01 '!G22 -> Equity-TBC | D21: =-SUM('CF (Equity, Debt)'!E26:E27) -> 300 | E21: =D21 -> 300 | H21: Held at cost.
B22: vTv Therapeutics Inc. | C22: ='Summary | 01 '!G23 -> Ordinary Shares | D22: =(F22*G22)*10^-6-12.5 -> -2.4253142 | E22: =(0.75*G22)*10^-6-12.5 -> -12.499999 | F22: ='CF (Equity, Debt)'!J29 -> 10386274 | G22: 0.97 | H22: Listed & marked to market
B23: Honor Device Co Ltd | C23: ='Summary | 01 '!G24 -> Equity-TBC | D23: =310000000000/6.7731/1000000*4.7%*50%*0.8 -> 860.46271 | E23: n/a | H23: Honor is closing a new round at RMB 310B
B27: Debt Investments
B28: Glass Earth Holdings LLC | C28: Promissory Note | D28: 0
B29: Mena Mobile Inc | C29: Loan | D29: 2.353982
B30: Esyasoft Holding | C30: Loan | D30: 0.45643868
B34: Funds Investments
B35: New Space Capital Fund I | C35: LP | D35: 31.952799 | H35: Q1'22 report
B36: New Space Capital SCSp | C36: GP | D36: 2.7058824 | H36: Q1'22 report
B37: North Summit Capital Fund | C37: LP | D37: 79.32 | H37: Q1'22 report
B38: Sinovation Disrupt Fund, L.P. | C38: LP | D38: 15.875237 | H38: Q1'22 report
B39: Acies Investments Fund I, L.P. | C39: LP | D39: 10.343447 | H39: Q1'22 report
B42: Note:
B43: • For estimating the NAV the share price for ONT and vTv Therapeutics is taken as of 15/09 (the latest available as of the date)

Sheet %
C2: % OWNERSHIP
C3: As of date | D3: ='Summary | 01 '!D2 -> 44834
C8: Deals | D8: Shares | E8: Total | F8: % Ownership | G8: Source
C10: Direct Investments
C11: Jollychic Holding Limited | D11: 13458655 | E11: 236116762 | F11: =D11/E11 -> 0.056999998 | G11: Dan Kong
C12: Mena Mobile Inc | D12: 21419829 | E12: 152998776 | F12: =D12/E12 -> 0.14 | G12: Dan Kong
C13: Flyr Inc | D13: 5205482 | E13: 61222609 | F13: =D13/E13 -> 0.085025485 | G13: Cap Table
C14: Esyasoft Holding | D14: n/a | E14: n/a | F14: n/a | G14: n/a
C15: Beyond Limits | D15: 17670202 | E15: 1.8142856e+08 | F15: =D15/E15 -> 0.09739482 | G15: Cap Table
C16: ONT plc | D16: 44328120 | E16: 823636945 | F16: =D16/E16 -> 0.053819975 | G16: LSE Announcement
C17: Heygears | D17: 3565017.2 | E17: =D17/F17 -> 24791497 | F17: 0.1438 | G17: Dan Kong
C18: Jysan Technologies | D18: 7959497 | E18: 2.6531657e+08 | F18: 0.03 | G18: Txn docs
C19: Cerebras Systems Inc | D19: 1441711 | E19: n/a | F19: 0.01 | G19: Pitchbook triangulation
C20: Endless Studios LLC | D20: 3000000 | E20: 43750000 | F20: =D20/E20 -> 0.068571429 | G20: Txn docs
C21: Instadeep Limited | D21: 33267 | E21: 2895450 | F21: =D21/E21 -> 0.011489406 | G21: Txn docs
C22: X-fusion | F22: =10% * 1/2 -> 0.05 | G22: Dan Kong
C23: DriveNets | F23: 0.0943 | G23: Finance team
C24: vTv Therapeutics Inc. | D24: 10386274 | E24: =81483600+23093860 -> 104577460 | F24: =D24/E24 -> 0.099316564 | G24: 10Q report 15Aug
C25: Honor Device Co Ltd | F25: =4.7%* 0.8/2 -> 0.0188 | G25: Dan Kong
C27: Debt Investments
C28: Glass Earth Holdings LLC
C29: Mena Mobile Inc
C30: Esyasoft Holding
C33: Funds Investments
C34: New Space Capital Fund I
C35: New Space Capital SCSp
C36: North Summit Capital Fund
C37: Sinovation Disrupt Fund, L.P.
C38: Acies Investments Fund I, L.P. | F38: =1/3 -> 0.33333333

Sheet CF (Equity, Debt)
B2: E QU I T Y
B3: Accounting entity | C3: Investment | D3: Payment date | E3: Contributions (in USD, Mn) | F3: Distributions (in USD, Mn) | G3: Currency | H3: Investment Amount | I3: Investment Amount | J3: Consideration (shares) | K3: Comment
B4: Mozn | C4: Jollychic Holding Limited | D4: 43470 | E4: =-I4*10^-6 -> -30 | G4: USD | H4: 30000000 | I4: =H4 -> 30000000 | J4: 6100312 | N4: NOTES
B5: Mozn | C5: Jollychic Holding Limited | D5: 43724 | E5: =-I5*10^-6 -> -20 | G5: USD | H5: 20000000 | I5: =H5 -> 20000000 | J5: 4204767.4 | N5: USD AED | O5: 3.678
B6: Mozn | C6: Jollychic Holding Limited | D6: 43724 | E6: =-I6*10^-6 -> -15 | G6: USD | H6: 15000000 | I6: =H6 -> 15000000 | J6: 3153575.6
B7: Mozn | C7: Mena Mobile Inc | D7: 43563 | E7: =-I7*10^-6 -> -8 | G7: USD | H7: 8000000 | I7: =H7 -> 8000000 | J7: 21419829
B8: Mozn | C8: Flyr Inc | D8: 43570 | E8: =-I8*10^-6 -> -4.9999981 | G8: USD | H8: 4999998.1 | I8: =H8 -> 4999998.1 | J8: 2625467
B9: Mozn | C9: Flyr Inc | D9: 43915 | E9: =-I9*10^-6 -> -5.0000019 | G9: USD | H9: =10000000-H8 -> 5000001.9 | I9: =H9 -> 5000001.9 | J9: 2580015
B10: Mozn | C10: Esyasoft Holding | D10: 43870 | E10: =-I10*10^-6 -> -2.5 | G10: USD | H10: 2500000 | I10: =H10 -> 2500000 | J10: N/A
B11: Mozn | C11: Beyond Limits | D11: 43879 | E11: =-I11*10^-6 -> -20 | G11: USD | H11: 20000000 | I11: =H11 -> 20000000 | J11: 4084038
B12: Mozn | C12: Beyond Limits | D12: 43921 | E12: =-I12*10^-6 -> -30 | G12: USD | H12: 30000000 | I12: =H12 -> 30000000 | J12: 5822642
B13: Mozn | C13: Beyond Limits | D13: 43989 | E13: =-I13*10^-6 -> -30 | G13: USD | H13: 30000000 | I13: =H13 -> 30000000 | J13: 5822642
B14: Mozn | C14: Beyond Limits | D14: 44103 | E14: =-I14*10^-6 -> -10 | G14: USD | H14: 10000000 | I14: =H14 -> 10000000 | J14: 1940880
B15: G42 | C15: ONT plc | D15: 43968 | E15: =-I15*10^-6 -> -50 | G15: USD | H15: 50000000 | I15: 50000000 | J15: 15277680
B16: G42 | C16: ONT plc | D16: 44006 | E16: =-I16*10^-6 -> -27.268351 | G16: GBP | H16: 21029625 | I16: 27268351 | J16: 9000000
B17: G42 | C17: ONT plc | D17: 43837 | E17: =-I17*10^-6 -> -18.109441 | G17: GBP | H17: 14386480 | I17: 18109441 | J17: 6362180
B18: G42 | C18: ONT plc | D18: 43990 | E18: =-I18*10^-6 -> -34.851687 | G18: GBP | H18: 26085573 | I18: 34851687 | J18: 11381140
B19: G42 | C19: ONT plc | D19: 44315 | E19: =-I19*10^-6 -> -11.24078 | G19: GBP | H19: 8074920 | I19: 11240780 | J19: 2307120
B20: Mozn | C20: Heygears | D20: 44166 | E20: =-I20*10^-6 -> -60 | G20: USD | H20: 60000000 | I20: =H20 -> 60000000 | J20: 4753356.3
B21: QAZ42 | C21: Jysan Technologies | D21: 44363 | E21: =-I21*10^-6 -> -20 | G21: USD | H21: 20000000 | I21: =H21 -> 20000000 | J21: 7959497
B22: Mozn | C22: Cerebras Systems Inc | D22: 44488 | E22: =-I22*10^-6 -> -39.999983 | G22: USD | H22: 39999983 | I22: =H22 -> 39999983 | J22: 1441711
B23: Mozn | C23: Endless Studios LLC | D23: 44494 | E23: =-I23*10^-6 -> -3 | G23: USD | H23: 3000000 | I23: =H23 -> 3000000 | J23: 3000000
B24: Mozn | C24: Instadeep Limited | D24: 44550 | E24: =-I24*10^-6 -> -5.0237202 | G24: GBP | H24: 3679995.5 | I24: 5023720.2 | J24: 33267
B25: Enterprise Connection | C25: X-fusion | D25: 44574 | E25: =-I25*10^-6 -> -493.50096 | G25: USD | H25: 8.9350096e+08 | I25: 4.9350096e+08
B26: G42 | C26: DriveNets | D26: 44643 | E26: =-I26*10^-6 -> -200 | G26: USD | H26: 200000000 | I26: =H26 -> 200000000
B27: G42 | C27: DriveNets | D27: 44680 | E27: =-I27*10^-6 -> -100 | G27: USD | H27: 100000000 | I27: =H27 -> 100000000
B28: Mozn | C28: Esyasoft Holding | D28: 44691 | F28: 5 | G28: USD
B29: G42 | C29: vTv Therapeutics Inc. | D29: 44712 | E29: =-I29*10^-6 -> -12.5 | G29: USD | H29: 12500000 | I29: =H29 -> 12500000 | J29: 10386274
B30: Smart Interaction | C30: Honor Device Co Ltd | D30: 44769 | E30: =-I30*10^-6 -> -800 | G30: USD | H30: 800000000 | I30: =H30 -> 800000000
B32: L O AN | P R O M I S S O R Y N O T E S | D E B T
B33: Mozn | C33: Glass Earth Holdings LLC | D33: 43635 | E33: -8 | H33: 8000000
B34: Mozn | C34: Mena Mobile Inc | D34: 44293 | E34: -2.353982
B35: Mozn | C35: Esyasoft Holding | D35: 44384 | E35: =-I35*10^-6 -> -0.411765 | G35: USD | H35: 2500000 | I35: 411765 | J35: N/A

Sheet CF (Funds)
A2: Entity | B2: Investment | C2: Payment date | D2: Contributions (USD, Mn) | E2: Distributions (USD, Mn) | F2: Currency | G2: Cashflows | H2: Description
A3: G42 | B3: Sinovation Disrupt Fund, L.P. | C3: 44153 | D3: =G3 -> -10.5 | F3: USD | G3: -10.5 | H3: 1st Capital Call
A4: G42 | B4: Sinovation Disrupt Fund, L.P. | C4: 44238 | D4: =G4 -> 4.214027 | F4: USD | G4: 4.214027 | H4: Partial return of the 1st Capital Call
A5: G42 | B5: Sinovation Disrupt Fund, L.P. | C5: 44238 | E5: =G5 -> 0.05044835 | F5: USD | G5: 0.05044835 | H5: Interest Catchup
A6: G42 | B6: Sinovation Disrupt Fund, L.P. | C6: 44285 | D6: =G6 -> -6.433746 | F6: USD | G6: -6.433746 | H6: 2nd Capital Calll
A7: G42 | B7: Sinovation Disrupt Fund, L.P. | C7: 44269 | D7: =G7 -> 1.1352074 | F7: USD | G7: 1.1352074 | H7: Return of Capital fund
A8: G42 | B8: Sinovation Disrupt Fund, L.P. | C8: 44269 | E8: =G8 -> 0.0259 | F8: USD | G8: 0.0259 | H8: Interest Catchup
A9: G42 | B9: Sinovation Disrupt Fund, L.P. | C9: 44483 | D9: =G9 -> -7.567138 | F9: USD | G9: -7.567138 | H9: 3rd Capital Call
A10: G42 | B10: Sinovation Disrupt Fund, L.P. | C10: 44554 | D10: =G10 -> -7.385016 | F10: USD | G10: -7.385016 | H10: 4th Capital Call
A11: G42 | B11: Sinovation Disrupt Fund, L.P. | C11: 44554 | D11: =G11 -> 4.0733456 | F11: USD | G11: 4.0733456 | H11: Return of Capital fund
A12: G42 | B12: Sinovation Disrupt Fund, L.P. | C12: 44554 | E12: =G12 -> 0.139694 | F12: USD | G12: 0.139694 | H12: Interest Catchup
A13: G42 | B13: Sinovation Disrupt Fund, L.P. | C13: 44703 | D13: =G13 -> 5.673074 | F13: USD | G13: 5.673074 | H13: Return of Capital fund
A14: G42 | B14: Sinovation Disrupt Fund, L.P. | C14: 44703 | E14: =G14 -> 0.227786 | F14: USD | G14: 0.227786 | H14: Interest Catchup
A15: Mozn | B15: North Summit Capital Fund | C15: 43665 | D15: =G15 -> -3 | F15: USD | G15: -3 | H15: 1st Capital Call
A16: Mozn | B16: North Summit Capital Fund | C16: 43983 | D16: =G16 -> -4.485 | F16: USD | G16: -4.485 | H16: 2nd Capital Calll
A17: Mozn | B17: North Summit Capital Fund | C17: 43879 | D17: =G17 -> -9.50975 | F17: USD | G17: -9.50975 | H17: 3rd Capital Call
A18: Mozn | B18: North Summit Capital Fund | C18: 43934 | D18: =G18 -> -41.3 | F18: USD | G18: -41.3 | H18: 4th Capital Call
A19: Mozn | B19: North Summit Capital Fund | C19: 44151 | D19: =G19 -> 9.95 | F19: USD | G19: 9.95 | H19: 5th Capital Call-Partial return of the 4th Capital Call
A20: Mozn | B20: North Summit Capital Fund | C20: 44151 | D20: =G20 -> -10.455 | F20: USD | G20: -10.455 | H20: 5th Capital Call
A21: Mozn | B21: North Summit Capital Fund | C21: 44196 | D21: =G21 -> 4.975 | F21: USD | G21: 4.975 | H21: 6th Capital Call-Partial return of the 4th Capital Call
A22: Mozn | B22: North Summit Capital Fund | C22: 44196 | D22: =G22 -> -3.452293 | F22: USD | G22: -3.452293 | H22: 6th Capital Call
A23: Mozn | B23: North Summit Capital Fund | C23: 44196 | E23: =G23 -> 0.582902 | F23: USD | G23: 0.582902 | H23: 6th Capital Call-Dividends from Project Topscore
A24: Mozn | B24: North Summit Capital Fund | C24: 44370 | D24: =G24 -> -5.97 | F24: USD | G24: -5.97 | H24: 7th Capital Call
A25: Mozn | B25: North Summit Capital Fund | C25: 44400 | D25: =G25 -> -0.75 | F25: USD | G25: -0.75 | H25: 8th Capital Call
A26: Mozn | B26: North Summit Capital Fund | C26: 44400 | E26: =G26 -> 0.445059 | F26: USD | G26: 0.445059 | H26: 8th Capital Call-Dividends from Project Topscore
A27: Mozn | B27: North Summit Capital Fund | C27: 44554 | D27: =G27 -> 1.78239 | F27: USD | G27: 1.78239 | H27: 9th Capital Call-Return of Capital Fund
A28: Mozn | B28: North Summit Capital Fund | C28: 44676 | D28: =G28 -> -21 | F28: USD | G28: -21 | H28: 12th Capital Call
A29: G42 | B29: New Space Capital Fund I | C29: 44087 | D29: =G29*1.1 -> -20.917553 | F29: EUR | G29: -19.015957 | H29: Drawdown1
A30: G42 | B30: New Space Capital Fund I | C30: 44287 | D30: -0.21103182 | F30: EUR | G30: -0.21103182 | H30: Drawdown2
A31: G42 | B31: New Space Capital Fund I | C31: 44442 | D31: =1.18*G31 -> -0.23965473 | F31: EUR | G31: =-203097.23*10^-6 -> -0.20309723 | H31: Drawdown3
A32: G42 | B32: New Space Capital Fund I | C32: 44623 | D32: =1.11*G32 -> -0.25893585 | F32: EUR | G32: =-233275.54*10^-6 -> -0.23327554 | H32: Drawdown4
A33: G42 | B33: New Space Capital Fund I | C33: 44784 | D33: =1.03*G33 -> 0.015224657 | F33: EUR | G33: =14781.22*10^-6 -> 0.01478122 | H33: Return of Capital
A34: G42 | B34: New Space Capital SCSp | C34: 44087 | D34: =-'Summary | 01 '!K35 -> -2.7058824 | F34: EUR | G34: -2.125 | H34: Drawdown1
A35: G42 | B35: Acies Investments Fund I, L.P. | C35: 44540 | D35: =G35 -> -2.8053125 | F35: USD | G35: -2.8053125 | H35: 1st Capital Call
A36: G42 | B36: Acies Investments Fund I, L.P. | C36: 44602 | D36: =G36 -> -3.4075 | F36: USD | G36: -3.4075 | H36: 2nd Capital Call
A37: G42 | B37: Acies Investments Fund I, L.P. | C37: 44683 | D37: =G37 -> -1.025775 | F37: USD | G37: -1.025775 | H37: 3rd Capital Call
A38: G42 | B38: Acies Investments Fund I, L.P. | C38: 44707 | D38: =G38 -> -3.388275 | F38: USD | G38: -3.388275 | H38: 4th Capital Call

Sheet 1. IRR Equity1
B2: IRR - Equity (Individual Investments)
B4: Date of NAV | C4: =D!D2 -> 44834 | J4: Investtment Level Summary | AA4: Overall Summary
B6: (in USD, Mn)
B7: Investment | C7: Payment date | D7: Contribution | E7: Distributions | F7: Remaining Value | G7: Combined | J7: Jollychic Holding Limited | K7: Mena Mobile Inc | L7: Flyr Inc | M7: Esyasoft Holding | N7: Beyond Limits | O7: ONT plc | P7: Heygears | Q7: Jysan Technologies | R7: Cerebras Systems Inc | S7: Endless Studios LLC | T7: Instadeep Limited | U7: X-fusion | V7: DriveNets | W7: vTv Therapeutics Inc. | X7: Honor Device Co Ltd | AC7: Committed | AD7: Invested | AE7: Remaining Commitment | AF7: Distributions | AG7: Residual Value | AH7: IRR | AI7: TVPI | AJ7: RPI | AK7: DPI
B10: ='CF (Equity, Debt)'!C4 -> Jollychic Holding Limited | C10: ='CF (Equity, Debt)'!D4 -> 43470 | D10: ='CF (Equity, Debt)'!E4 -> -30 | G10: =SUM(D10:F10) -> -30 | H10: =IF(D10='CF (Equity, Debt)'!E4," ", "xxx") | J10: =D10 -> -30
B11: ='CF (Equity, Debt)'!C5 -> Jollychic Holding Limited | C11: ='CF (Equity, Debt)'!D5 -> 43724 | D11: ='CF (Equity, Debt)'!E5 -> -20 | G11: =SUM(D11:F11) -> -20 | H11: =IF(D11='CF (Equity, Debt)'!E5," ", "xxx") | J11: =D11 -> -20
B12: ='CF (Equity, Debt)'!C6 -> Jollychic Holding Limited | C12: ='CF (Equity, Debt)'!D6 -> 43724 | D12: ='CF (Equity, Debt)'!E6 -> -15 | G12: =SUM(D12:F12) -> -15 | H12: =IF(D12='CF (Equity, Debt)'!E6," ", "xxx") | J12: =D12 -> -15 | AB12: Jollychic Holding Limited | AC12: ='Summary | 01 '!J10 -> 65 | AD12: =-SUMIF($B$7:$F$103,$AB12,$D$7:$D$103) -> 65 | AE12: =AC12-AD12 -> 0 | AF12: =SUMIF($B$7:$F$103,$AB12,$E$7:$E$103) -> 0 | AG12: =SUMIF($B$7:$F$103,$AB12,$F$7:$F$103) -> 0 | AH12: =HLOOKUP(AB12,$J$7:$X$59,48,0) -> NM | AI12: =(AF12+AG12)/AD12 -> 0 | AJ12: =AG12/AD12 -> 0 | AK12: =AF12/AD12 -> 0
B13: ='CF (Equity, Debt)'!C7 -> Mena Mobile Inc | C13: ='CF (Equity, Debt)'!D7 -> 43563 | D13: ='CF (Equity, Debt)'!E7 -> -8 | G13: =SUM(D13:F13) -> -8 | H13: =IF(D13='CF (Equity, Debt)'!E7," ", "xxx") | K13: =D13 -> -8 | AB13: Mena Mobile Inc | AC13: ='Summary | 01 '!J11 -> 8 | AD13: =-SUMIF($B$7:$F$103,$AB13,$D$7:$D$103) -> 8 | AE13: =AC13-AD13 -> 0 | AF13: =SUMIF($B$7:$F$103,$AB13,$E$7:$E$103) -> 0 | AG13: =SUMIF($B$7:$F$103,$AB13,$F$7:$F$103) -> 3.1 | AH13: =HLOOKUP(AB13,$J$7:$X$59,48,0) -> -0.23833896 | AI13: =(AF13+AG13)/AD13 -> 0.3875 | AJ13: =AG13/AD13 -> 0.3875 | AK13: =AF13/AD13 -> 0
B14: ='CF (Equity, Debt)'!C8 -> Flyr Inc | C14: ='CF (Equity, Debt)'!D8 -> 43570 | D14: ='CF (Equity, Debt)'!E8 -> -4.9999981 | G14: =SUM(D14:F14) -> -4.9999981 | H14: =IF(D14='CF (Equity, Debt)'!E8," ", "xxx") | L14: =D14 -> -4.9999981 | AB14: Flyr Inc | AC14: ='Summary | 01 '!J12 -> 10 | AD14: =-SUMIF($B$7:$F$103,$AB14,$D$7:$D$103) -> 10 | AE14: =AC14-AD14 -> 0 | AF14: =SUMIF($B$7:$F$103,$AB14,$E$7:$E$103) -> 0 | AG14: =SUMIF($B$7:$F$103,$AB14,$F$7:$F$103) -> 78.08223 | AH14: =HLOOKUP(AB14,$J$7:$X$59,48,0) -> 0.95566303 | AI14: =(AF14+AG14)/AD14 -> 7.808223 | AJ14: =AG14/AD14 -> 7.808223 | AK14: =AF14/AD14 -> 0
B15: ='CF (Equity, Debt)'!C9 -> Flyr Inc | C15: ='CF (Equity, Debt)'!D9 -> 43915 | D15: ='CF (Equity, Debt)'!E9 -> -5.0000019 | G15: =SUM(D15:F15) -> -5.0000019 | H15: =IF(D15='CF (Equity, Debt)'!E9," ", "xxx") | L15: =D15 -> -5.0000019 | AB15: Esyasoft Holding | AC15: ='Summary | 01 '!J13 -> 2.5 | AD15: =-SUMIF($B$7:$F$103,$AB15,$D$7:$D$103) -> 2.5 | AE15: =AC15-AD15 -> 0 | AF15: =SUMIF($B$7:$F$103,$AB15,$E$7:$E$103) -> 5 | AG15: =SUMIF($B$7:$F$103,$AB15,$F$7:$F$103) -> 0 | AH15: =HLOOKUP(AB15,$J$7:$X$59,48,0) -> 0.36091766 | AI15: =(AF15+AG15)/AD15 -> 2 | AJ15: =AG15/AD15 -> 0 | AK15: =AF15/AD15 -> 2
B16: ='CF (Equity, Debt)'!C10 -> Esyasoft Holding | C16: ='CF (Equity, Debt)'!D10 -> 43870 | D16: ='CF (Equity, Debt)'!E10 -> -2.5 | G16: =SUM(D16:F16) -> -2.5 | H16: =IF(D16='CF (Equity, Debt)'!E10," ", "xxx") | M16: =D16 -> -2.5 | AB16: Beyond Limits | AC16: ='Summary | 01 '!J14 -> 90 | AD16: =-SUMIF($B$7:$F$103,$AB16,$D$7:$D$103) -> 90 | AE16: =AC16-AD16 -> 0 | AF16: =SUMIF($B$7:$F$103,$AB16,$E$7:$E$103) -> 0 | AG16: =SUMIF($B$7:$F$103,$AB16,$F$7:$F$103) -> 91.00154 | AH16: =HLOOKUP(AB16,$J$7:$X$59,48,0) -> 0.0046035081 | AI16: =(AF16+AG16)/AD16 -> 1.0111282 | AJ16: =AG16/AD16 -> 1.0111282 | AK16: =AF16/AD16 -> 0
B17: ='CF (Equity, Debt)'!C11 -> Beyond Limits | C17: ='CF (Equity, Debt)'!D11 -> 43879 | D17: ='CF (Equity, Debt)'!E11 -> -20 | G17: =SUM(D17:F17) -> -20 | H17: =IF(D17='CF (Equity, Debt)'!E11," ", "xxx") | N17: =D17 -> -20 | AB17: ONT plc | AC17: ='Summary | 01 '!J15 -> 141.47026 | AD17: =-SUMIF($B$7:$F$103,$AB17,$D$7:$D$103) -> 141.47026 | AE17: =AC17-AD17 -> 0 | AF17: =SUMIF($B$7:$F$103,$AB17,$E$7:$E$103) -> 0 | AG17: =SUMIF($B$7:$F$103,$AB17,$F$7:$F$103) -> 125.96279 | AH17: =HLOOKUP(AB17,$J$7:$X$59,48,0) -> -0.049104276 | AI17: =(AF17+AG17)/AD17 -> 0.89038351 | AJ17: =AG17/AD17 -> 0.89038351 | AK17: =AF17/AD17 -> 0
B18: ='CF (Equity, Debt)'!C12 -> Beyond Limits | C18: ='CF (Equity, Debt)'!D12 -> 43921 | D18: ='CF (Equity, Debt)'!E12 -> -30 | G18: =SUM(D18:F18) -> -30 | H18: =IF(D18='CF (Equity, Debt)'!E12," ", "xxx") | N18: =D18 -> -30 | AB18: Heygears | AC18: ='Summary | 01 '!J16 -> 60 | AD18: =-SUMIF($B$7:$F$103,$AB18,$D$7:$D$103) -> 60 | AE18: =AC18-AD18 -> 0 | AF18: =SUMIF($B$7:$F$103,$AB18,$E$7:$E$103) -> 0 | AG18: =SUMIF($B$7:$F$103,$AB18,$F$7:$F$103) -> 136.64 | AH18: =HLOOKUP(AB18,$J$7:$X$59,48,0) -> 0.5678354 | AI18: =(AF18+AG18)/AD18 -> 2.2773333 | AJ18: =AG18/AD18 -> 2.2773333 | AK18: =AF18/AD18 -> 0
B19: ='CF (Equity, Debt)'!C13 -> Beyond Limits | C19: ='CF (Equity, Debt)'!D13 -> 43989 | D19: ='CF (Equity, Debt)'!E13 -> -30 | G19: =SUM(D19:F19) -> -30 | H19: =IF(D19='CF (Equity, Debt)'!E13," ", "xxx") | N19: =D19 -> -30 | AB19: Jysan Technologies | AC19: ='Summary | 01 '!J17 -> 20 | AD19: =-SUMIF($B$7:$F$103,$AB19,$D$7:$D$103) -> 20 | AE19: =AC19-AD19 -> 0 | AF19: =SUMIF($B$7:$F$103,$AB19,$E$7:$E$103) -> 0 | AG19: =SUMIF($B$7:$F$103,$AB19,$F$7:$F$103) -> 20 | AH19: =HLOOKUP(AB19,$J$7:$X$59,48,0) -> 2.9802322e-09 | AI19: =(AF19+AG19)/AD19 -> 1 | AJ19: =AG19/AD19 -> 1 | AK19: =AF19/AD19 -> 0
B20: ='CF (Equity, Debt)'!C14 -> Beyond Limits | C20: ='CF (Equity, Debt)'!D14 -> 44103 | D20: ='CF (Equity, Debt)'!E14 -> -10 | G20: =SUM(D20:F20) -> -10 | H20: =IF(D20='CF (Equity, Debt)'!E14," ", "xxx") | N20: =D20 -> -10 | AB20: Cerebras Systems Inc | AC20: ='Summary | 01 '!J18 -> 40 | AD20: =-SUMIF($B$7:$F$103,$AB20,$D$7:$D$103) -> 39.999983 | AE20: =AC20-AD20 -> 1.664e-05 | AF20: =SUMIF($B$7:$F$103,$AB20,$E$7:$E$103) -> 0 | AG20: =SUMIF($B$7:$F$103,$AB20,$F$7:$F$103) -> 39.999983 | AH20: =HLOOKUP(AB20,$J$7:$X$59,48,0) -> 2.9802322e-09 | AI20: =(AF20+AG20)/AD20 -> 1 | AJ20: =AG20/AD20 -> 1 | AK20: =AF20/AD20 -> 0
B21: ='CF (Equity, Debt)'!C15 -> ONT plc | C21: ='CF (Equity, Debt)'!D15 -> 43968 | D21: ='CF (Equity, Debt)'!E15 -> -50 | G21: =SUM(D21:F21) -> -50 | H21: =IF(D21='CF (Equity, Debt)'!E15," ", "xxx") | O21: =D21 -> -50 | AB21: Endless Studios LLC | AC21: ='Summary | 01 '!J19 -> 3 | AD21: =-SUMIF($B$7:$F$103,$AB21,$D$7:$D$103) -> 3 | AE21: =AC21-AD21 -> 0 | AF21: =SUMIF($B$7:$F$103,$AB21,$E$7:$E$103) -> 0 | AG21: =SUMIF($B$7:$F$103,$AB21,$F$7:$F$103) -> 3 | AH21: =HLOOKUP(AB21,$J$7:$X$59,48,0) -> 2.9802322e-09 | AI21: =(AF21+AG21)/AD21 -> 1 | AJ21: =AG21/AD21 -> 1 | AK21: =AF21/AD21 -> 0
B22: ='CF (Equity, Debt)'!C16 -> ONT plc | C22: ='CF (Equity, Debt)'!D16 -> 44006 | D22: ='CF (Equity, Debt)'!E16 -> -27.268351 | G22: =SUM(D22:F22) -> -27.268351 | H22: =IF(D22='CF (Equity, Debt)'!E16," ", "xxx") | O22: =D22 -> -27.268351 | AB22: Instadeep Limited | AC22: ='Summary | 01 '!J20 -> 5.0278212 | AD22: =-SUMIF($B$7:$F$103,$AB22,$D$7:$D$103) -> 5.0237202 | AE22: =AC22-AD22 -> 0.0041009961 | AF22: =SUMIF($B$7:$F$103,$AB22,$E$7:$E$103) -> 0 | AG22: =SUMIF($B$7:$F$103,$AB22,$F$7:$F$103) -> 5.0237202 | AH22: =HLOOKUP(AB22,$J$7:$X$59,48,0) -> 2.9802322e-09 | AI22: =(AF22+AG22)/AD22 -> 1 | AJ22: =AG22/AD22 -> 1 | AK22: =AF22/AD22 -> 0
B23: ='CF (Equity, Debt)'!C17 -> ONT plc | C23: ='CF (Equity, Debt)'!D17 -> 43837 | D23: ='CF (Equity, Debt)'!E17 -> -18.109441 | G23: =SUM(D23:F23) -> -18.109441 | H23: =IF(D23='CF (Equity, Debt)'!E17," ", "xxx") | O23: =D23 -> -18.109441 | AB23: X-fusion | AC23: ='Summary | 01 '!J21 -> 493.5 | AD23: =-SUMIF($B$7:$F$103,$AB23,$D$7:$D$103) -> 493.50096 | AE23: =AC23-AD23 -> -0.0009562 | AF23: =SUMIF($B$7:$F$103,$AB23,$E$7:$E$103) -> 0 | AG23: =SUMIF($B$7:$F$103,$AB23,$F$7:$F$103) -> 493.50096 | AH23: =HLOOKUP(AB23,$J$7:$X$59,48,0) -> 2.9802322e-09 | AI23: =(AF23+AG23)/AD23 -> 1 | AJ23: =AG23/AD23 -> 1 | AK23: =AF23/AD23 -> 0
B24: ='CF (Equity, Debt)'!C18 -> ONT plc | C24: ='CF (Equity, Debt)'!D18 -> 43990 | D24: ='CF (Equity, Debt)'!E18 -> -34.851687 | G24: =SUM(D24:F24) -> -34.851687 | H24: =IF(D24='CF (Equity, Debt)'!E18," ", "xxx") | O24: =D24 -> -34.851687 | AB24: DriveNets | AC24: ='Summary | 01 '!J22 -> 300 | AD24: =-SUMIF($B$7:$F$103,$AB24,$D$7:$D$103) -> 300 | AE24: =AC24-AD24 -> 0 | AF24: =SUMIF($B$7:$F$103,$AB24,$E$7:$E$103) -> 0 | AG24: =SUMIF($B$7:$F$103,$AB24,$F$7:$F$103) -> 300 | AH24: =HLOOKUP(AB24,$J$7:$X$59,48,0) -> 2.9802322e-09 | AI24: =(AF24+AG24)/AD24 -> 1 | AJ24: =AG24/AD24 -> 1 | AK24: =AF24/AD24 -> 0
B25: ='CF (Equity, Debt)'!C19 -> ONT plc | C25: ='CF (Equity, Debt)'!D19 -> 44315 | D25: ='CF (Equity, Debt)'!E19 -> -11.24078 | G25: =SUM(D25:F25) -> -11.24078 | H25: =IF(D25='CF (Equity, Debt)'!E19," ", "xxx") | O25: =D25 -> -11.24078 | AB25: vTv Therapeutics Inc. | AC25: ='Summary | 01 '!J23 -> 25 | AD25: =-SUMIF($B$7:$F$103,$AB25,$D$7:$D$103) -> 12.5 | AE25: =AC25-AD25 -> 12.5 | AF25: =SUMIF($B$7:$F$103,$AB25,$E$7:$E$103) -> 0 | AG25: =SUMIF($B$7:$F$103,$AB25,$F$7:$F$103) -> -2.4253142 | AH25: =HLOOKUP(AB25,$J$7:$X$59,48,0) -> NM | AI25: =(AF25+AG25)/AD25 -> -0.19402514 | AJ25: =AG25/AD25 -> -0.19402514 | AK25: =AF25/AD25 -> 0
B26: ='CF (Equity, Debt)'!C20 -> Heygears | C26: ='CF (Equity, Debt)'!D20 -> 44166 | D26: ='CF (Equity, Debt)'!E20 -> -60 | G26: =SUM(D26:F26) -> -60 | H26: =IF(D26='CF (Equity, Debt)'!E20," ", "xxx") | P26: =D26 -> -60 | AB26: Honor Device Co Ltd | AC26: ='Summary | 01 '!J24 -> 800 | AD26: =-SUMIF($B$7:$F$103,$AB26,$D$7:$D$103) -> 800 | AE26: =AC26-AD26 -> 0 | AF26: =SUMIF($B$7:$F$103,$AB26,$E$7:$E$103) -> 0 | AG26: =SUMIF($B$7:$F$103,$AB26,$F$7:$F$103) -> 860.46271 | AH26: =HLOOKUP(AB26,$J$7:$X$59,48,0) -> NM | AI26: =(AF26+AG26)/AD26 -> 1.0755784 | AJ26: =AG26/AD26 -> 1.0755784 | AK26: =AF26/AD26 -> 0
B27: ='CF (Equity, Debt)'!C21 -> Jysan Technologies | C27: ='CF (Equity, Debt)'!D21 -> 44363 | D27: ='CF (Equity, Debt)'!E21 -> -20 | G27: =SUM(D27:F27) -> -20 | H27: =IF(D27='CF (Equity, Debt)'!E21," ", "xxx") | Q27: =D27 -> -20
B28: ='CF (Equity, Debt)'!C22 -> Cerebras Systems Inc | C28: ='CF (Equity, Debt)'!D22 -> 44488 | D28: ='CF (Equity, Debt)'!E22 -> -39.999983 | G28: =SUM(D28:F28) -> -39.999983 | H28: =IF(D28='CF (Equity, Debt)'!E22," ", "xxx") | R28: =D28 -> -39.999983 | AC28: =SUM(AC12:AC27) -> 2063.4981 | AD28: =SUM(AD12:AD27) -> 2050.9949 | AE28: =SUM(AE12:AE27) -> 12.503161 | AF28: =SUM(AF12:AF27) -> 5 | AG28: =SUM(AG12:AG27) -> 2154.3486 | AH28: =AC35 -> 0.064125332 | AI28: =(AF28+AG28)/AD28 -> 1.0528298 | AJ28: =AG28/AD28 -> 1.050392 | AK28: =AF28/AD28 -> 0.0024378412
B29: ='CF (Equity, Debt)'!C23 -> Endless Studios LLC | C29: ='CF (Equity, Debt)'!D23 -> 44494 | D29: ='CF (Equity, Debt)'!E23 -> -3 | G29: =SUM(D29:F29) -> -3 | H29: =IF(D29='CF (Equity, Debt)'!E23," ", "xxx") | S29: =D29 -> -3
B30: ='CF (Equity, Debt)'!C24 -> Instadeep Limited | C30: ='CF (Equity, Debt)'!D24 -> 44550 | D30: ='CF (Equity, Debt)'!E24 -> -5.0237202 | G30: =SUM(D30:F30) -> -5.0237202 | H30: =IF(D30='CF (Equity, Debt)'!E24," ", "xxx") | T30: =D30 -> -5.0237202
B31: ='CF (Equity, Debt)'!C25 -> X-fusion | C31: ='CF (Equity, Debt)'!D25 -> 44574 | D31: ='CF (Equity, Debt)'!E25 -> -493.50096 | G31: =SUM(D31:F31) -> -493.50096 | H31: =IF(D31='CF (Equity, Debt)'!E25," ", "xxx") | U31: =D31 -> -493.50096
B32: ='CF (Equity, Debt)'!C26 -> DriveNets | C32: ='CF (Equity, Debt)'!D26 -> 44643 | D32: ='CF (Equity, Debt)'!E26 -> -200 | G32: =SUM(D32:F32) -> -200 | H32: =IF(D32='CF (Equity, Debt)'!E26," ", "xxx") | V32: =D32 -> -200
B33: ='CF (Equity, Debt)'!C27 -> DriveNets | C33: ='CF (Equity, Debt)'!D27 -> 44680 | D33: ='CF (Equity, Debt)'!E27 -> -100 | G33: =SUM(D33:F33) -> -100 | H33: =IF(D33='CF (Equity, Debt)'!E27," ", "xxx") | V33: =D33 -> -100
B34: ='CF (Equity, Debt)'!C28 -> Esyasoft Holding | C34: ='CF (Equity, Debt)'!D28 -> 44691 | D34: ='CF (Equity, Debt)'!E28 -> 0 | E34: 5 | G34: =SUM(D34:F34) -> 5 | H34: =IF(D34='CF (Equity, Debt)'!E28," ", "xxx") | M34: =E34 -> 5
B35: ='CF (Equity, Debt)'!C29 -> vTv Therapeutics Inc. | C35: ='CF (Equity, Debt)'!D29 -> 44712 | D35: ='CF (Equity, Debt)'!E29 -> -12.5 | G35: =SUM(D35:F35) -> -12.5 | H35: =IF(D35='CF (Equity, Debt)'!E29," ", "xxx") | W35: =D35 -> -12.5 | AB35: XIRR | AC35: =XIRR(G10:G52,C10:C52) -> 0.064125332
B36: ='CF (Equity, Debt)'!C30 -> Honor Device Co Ltd | C36: ='CF (Equity, Debt)'!D30 -> 44769 | D36: ='CF (Equity, Debt)'!E30 -> -800 | G36: =SUM(D36:F36) -> -800 | H36: =IF(D36='CF (Equity, Debt)'!E30," ", "xxx") | X36: =D36 -> -800 | AB36: TVPI | AC36: =SUM(AF12:AG26)/SUM(AD12:AD26) -> 1.0528298
AB37: RPI | AC37: =SUM(AG12:AG26)/SUM(AD12:AD26) -> 1.050392
B38: Jollychic Holding Limited | C38: =$C$4 -> 44834 | F38: =NAV!D9 -> 0 | G38: =SUM(D38:F38) -> 0 | J38: =F38 -> 0 | AB38: DPI | AC38: =SUM(AF12:AF26)/SUM(AD12:AD26) -> 0.0024378412
B39: Mena Mobile Inc | C39: =$C$4 -> 44834 | F39: =NAV!D10 -> 3.1 | G39: =SUM(D39:F39) -> 3.1 | K39: =F39 -> 3.1
B40: Flyr Inc | C40: =$C$4 -> 44834 | F40: =NAV!D11 -> 78.08223 | G40: =SUM(D40:F40) -> 78.08223 | L40: =F40 -> 78.08223
B41: Esyasoft Holding | C41: =$C$4 -> 44834 | F41: =NAV!D12 -> 0 | G41: =SUM(D41:F41) -> 0
B42: Beyond Limits | C42: =$C$4 -> 44834 | F42: =NAV!D13 -> 91.00154 | G42: =SUM(D42:F42) -> 91.00154 | N42: =F42 -> 91.00154
B43: ONT plc | C43: =$C$4 -> 44834 | F43: =NAV!D14 -> 125.96279 | G43: =SUM(D43:F43) -> 125.96279 | O43: =F43 -> 125.96279
B44: Heygears | C44: =$C$4 -> 44834 | F44: =NAV!D15 -> 136.64 | G44: =SUM(D44:F44) -> 136.64 | P44: =F44 -> 136.64
B45: Jysan Technologies | C45: =$C$4 -> 44834 | F45: =NAV!D16 -> 20 | G45: =SUM(D45:F45) -> 20 | Q45: =F45 -> 20
B46: Cerebras Systems Inc | C46: =$C$4 -> 44834 | F46: =NAV!D17 -> 39.999983 | G46: =SUM(D46:F46) -> 39.999983 | R46: =F46 -> 39.999983
B47: Endless Studios LLC | C47: =$C$4 -> 44834 | F47: =NAV!D18 -> 3 | G47: =SUM(D47:F47) -> 3 | S47: =F47 -> 3
B48: Instadeep Limited | C48: =$C$4 -> 44834 | F48: =NAV!D19 -> 5.0237202 | G48: =SUM(D48:F48) -> 5.0237202 | T48: =F48 -> 5.0237202
B49: X-fusion | C49: =$C$4 -> 44834 | F49: =NAV!D20 -> 493.50096 | G49: =SUM(D49:F49) -> 493.50096 | U49: =F49 -> 493.50096
B50: DriveNets | C50: =$C$4 -> 44834 | F50: =NAV!D21 -> 300 | G50: =SUM(D50:F50) -> 300 | V50: =F50 -> 300
B51: vTv Therapeutics Inc. | C51: =$C$4 -> 44834 | F51: =NAV!D22 -> -2.4253142 | G51: =SUM(D51:F51) -> -2.4253142 | W51: =F51 -> -2.4253142
B52: Honor Device Co Ltd | C52: =$C$4 -> 44834 | F52: =NAV!D23 -> 860.46271 | G52: =SUM(D52:F52) -> 860.46271 | X52: =F52 -> 860.46271
I54: IRR | J54: =IF(ISERROR(XIRR(J10:J52,$C$10:$C$52)),"NM", XIRR(J10:J52,$C$10:$C$52)) -> NM | K54: =IF(ISERROR(XIRR(K13:K52,$C$13:$C$52)),"NM", XIRR(K13:K52,$C$13:$C$52)) -> -0.23833896 | L54: =IF(ISERROR(XIRR(L14:L52,$C$14:$C$52)),"NM", XIRR(L14:L52,$C$14:$C$52)) -> 0.95566303 | M54: =IF(ISERROR(XIRR(M16:M52,$C$16:$C$52)),"NM", XIRR(M16:M52,$C$16:$C$52)) -> 0.36091766 | N54: =IF(ISERROR(XIRR(N17:N52,$C$17:$C$52)),"NM", XIRR(N17:N52,$C$17:$C$52)) -> 0.0046035081 | O54: =IF(ISERROR(XIRR(O21:O52,$C$21:$C$52)),"NM", XIRR(O21:O52,$C$21:$C$52)) -> -0.049104276 | P54: =IF(ISERROR(XIRR(P26:P52,$C$26:$C$52)),"NM", XIRR(P26:P52,$C$26:$C$52)) -> 0.5678354 | Q54: =IF(ISERROR(XIRR(Q27:Q52,$C$27:$C$52)),"NM", XIRR(Q27:Q52,$C$27:$C$52)) -> 2.9802322e-09 | R54: =IF(ISERROR(XIRR(R28:R52,$C$28:$C$52)),"NM", XIRR(R28:R52,$C$28:$C$52)) -> 2.9802322e-09 | S54: =IF(ISERROR(XIRR(S29:S52,$C$29:$C$52)),"NM", XIRR(S29:S52,$C$29:$C$52)) -> 2.9802322e-09 | T54: =IF(ISERROR(XIRR(T30:T52,$C$30:$C$52)),"NM", XIRR(T30:T52,$C$30:$C$52)) -> 2.9802322e-09 | U54: =IF(ISERROR(XIRR(U31:U52,$C$31:$C$52)),"NM", XIRR(U31:U52,$C$31:$C$52)) -> 2.9802322e-09 | V54: =IF(ISERROR(XIRR(V32:V52,$C$32:$C$52)),"NM", XIRR(V32:V52,$C$32:$C$52)) -> 2.9802322e-09 | W54: =IF(ISERROR(XIRR(W35:W52,$C$35:$C$52)),"NM", XIRR(W35:W52,$C$35:$C$52)) -> NM | X54: =IF(ISERROR(XIRR(X36:X52,$C$35:$C$52)),"NM", "NM") -> NM
I55: TVPI | J55: =SUMIF(J$10:J$52,">0",J$10:J$52)/-SUMIF(J$10:J$52,"<0",J$10:J$36) -> 0 | K55: =SUMIF(K$10:K$52,">0",K$10:K$52)/-SUMIF(K$10:K$52,"<0",K$10:K$36) -> 0.3875 | L55: =SUMIF(L$10:L$52,">0",L$10:L$52)/-SUMIF(L$10:L$52,"<0",L$10:L$36) -> 7.808223 | M55: =SUMIF(M$10:M$52,">0",M$10:M$52)/-SUMIF(M$10:M$52,"<0",M$10:M$36) -> 2 | N55: =SUMIF(N$10:N$52,">0",N$10:N$52)/-SUMIF(N$10:N$52,"<0",N$10:N$36) -> 1.0111282 | O55: =SUMIF(O$10:O$52,">0",O$10:O$52)/-SUMIF(O$10:O$52,"<0",O$10:O$36) -> 0.89038351 | P55: =SUMIF(P$10:P$52,">0",P$10:P$52)/-SUMIF(P$10:P$52,"<0",P$10:P$36) -> 2.2773333 | Q55: =SUMIF(Q$10:Q$52,">0",Q$10:Q$52)/-SUMIF(Q$10:Q$52,"<0",Q$10:Q$36) -> 1 | ... X55: =SUMIF(X$10:X$52,">0",X$10:X$52)/-SUMIF(X$10:X$52,"<0",X$10:X$36) -> 1.0755784
I56: DPI | J56: =SUMIF(J$10:J$36,">0",J$10:J$36)/-SUMIF(J$10:J$36,"<0",J$10:J$36) -> 0 | K56: =SUMIF(K$10:K$36,">0",K$10:K$36)/-SUMIF(K$10:K$36,"<0",K$10:K$36) -> 0 | L56: =SUMIF(L$10:L$36,">0",L$10:L$36)/-SUMIF(L$10:L$36,"<0",L$10:L$36) -> 0 | M56: =SUMIF(M$10:M$36,">0",M$10:M$36)/-SUMIF(M$10:M$36,"<0",M$10:M$36) -> 2 | N56: =SUMIF(N$10:N$36,">0",N$10:N$36)/-SUMIF(N$10:N$36,"<0",N$10:N$36) -> 0 | O56: =SUMIF(O$10:O$36,">0",O$10:O$36)/-SUMIF(O$10:O$36,"<0",O$10:O$36) -> 0 | P56: =SUMIF(P$10:P$36,">0",P$10:P$36)/-SUMIF(P$10:P$36,"<0",P$10:P$36) -> 0 | Q56: =SUMIF(Q$10:Q$36,">0",Q$10:Q$36)/-SUMIF(Q$10:Q$36,"<0",Q$10:Q$36) -> 0 | ... X56: =SUMIF(X$10:X$36,">0",X$10:X$36)/-SUMIF(X$10:X$36,"<0",X$10:X$36) -> 0
I57: RVPI | J57: =SUMIF(J$36:J$52,">0",J$36:J$52)/-SUMIF(J$10:J$36,"<0",J$10:J$36) -> 0 | K57: =SUMIF(K$36:K$52,">0",K$36:K$52)/-SUMIF(K$10:K$36,"<0",K$10:K$36) -> 0.3875 | L57: =SUMIF(L$36:L$52,">0",L$36:L$52)/-SUMIF(L$10:L$36,"<0",L$10:L$36) -> 7.808223 | M57: =SUMIF(M$36:M$52,">0",M$36:M$52)/-SUMIF(M$10:M$36,"<0",M$10:M$36) -> 0 | N57: =SUMIF(N$36:N$52,">0",N$36:N$52)/-SUMIF(N$10:N$36,"<0",N$10:N$36) -> 1.0111282 | O57: =SUMIF(O$36:O$52,">0",O$36:O$52)/-SUMIF(O$10:O$36,"<0",O$10:O$36) -> 0.89038351 | P57: =SUMIF(P$36:P$52,">0",P$36:P$52)/-SUMIF(P$10:P$36,"<0",P$10:P$36) -> 2.2773333 | Q57: =SUMIF(Q$36:Q$52,">0",Q$36:Q$52)/-SUMIF(Q$10:Q$36,"<0",Q$10:Q$36) -> 1 | ... X57: =SUMIF(X$36:X$52,">0",X$36:X$52)/-SUMIF(X$10:X$36,"<0",X$10:X$36) -> 1.0755784

Sheet 1.1(P1)
B2: IRR - Equity (Select Investments)
C3: KEY PORTFOLIO IRR
C8: (in USD, Mn) | H8: Eliminated | I8: Portfolio 1
C9: Investment | D9: Payment date | E9: Contribution | F9: Distributions | G9: Remaining Value | H9: Jysan Technologies | I9: Jollychic Holding Limited
H10: Cerebras Systems Inc | I10: Mena Mobile Inc
H11: X-fusion | I11: Flyr Inc
H12: DriveNets | I12: Esyasoft Holding
H13: vTv Therapeutics Inc. | I13: Beyond Limits
H14: Honor Device Co Ltd | I14: ONT plc
I15: Heygears
I16: Endless Studios LLC
I17: Instadeep Limited
I21: Contribution | J21: Distribution | K21: Remaining Value | L21: Combined | O21: # Investments | P21: Committed | Q21: Invested | R21: Remaining Commitment | S21: Distributions | T21: Residual Value | U21: IRR | V21: TVPI | W21: RPI | X21: DPI
C22: ='CF (Equity, Debt)'!C4 -> Jollychic Holding Limited | D22: ='CF (Equity, Debt)'!D4 -> 43470 | E22: ='CF (Equity, Debt)'!E4 -> -30 | I22: =IF(ISERROR(VLOOKUP($C22,$I$9:$I$18,1,0)),0,1)*E22 -> -30 | J22: =IF(ISERROR(VLOOKUP($C22,$I$9:$I$18,1,0)),0,1)*F22 -> 0 | K22: =IF(ISERROR(VLOOKUP($C22,$I$9:$I$18,1,0)),0,1)*G22 -> 0 | L22: =SUM(I22:K22) -> -30
C23: ='CF (Equity, Debt)'!C5 -> Jollychic Holding Limited | D23: ='CF (Equity, Debt)'!D5 -> 43724 | E23: ='CF (Equity, Debt)'!E5 -> -20 | I23: =IF(ISERROR(VLOOKUP($C23,$I$9:$I$18,1,0)),0,1)*E23 -> -20 | J23: =IF(ISERROR(VLOOKUP($C23,$I$9:$I$18,1,0)),0,1)*F23 -> 0 | K23: =IF(ISERROR(VLOOKUP($C23,$I$9:$I$18,1,0)),0,1)*G23 -> 0 | L23: =SUM(I23:K23) -> -20 | O23: =COUNTIF(I9:I17,"*") -> 9 | P23: =Q23 -> 379.99398 | Q23: =-SUM(I22:I64) -> 379.99398 | R23: =P23-Q23 -> 0 | S23: =SUM(J22:J64) -> 5 | T23: =SUM(K22:K64) -> 442.81028 | U23: =J70 -> 0.076285401 | V23: =J71 -> 1.1784668 | W23: =J72 -> 1.1653087 | X23: =J73 -> 0.013158103
C24: ='CF (Equity, Debt)'!C6 -> Jollychic Holding Limited | D24: ='CF (Equity, Debt)'!D6 -> 43724 | E24: ='CF (Equity, Debt)'!E6 -> -15 | I24: =IF(ISERROR(VLOOKUP($C24,$I$9:$I$18,1,0)),0,1)*E24 -> -15 | J24: =IF(ISERROR(VLOOKUP($C24,$I$9:$I$18,1,0)),0,1)*F24 -> 0 | K24: =IF(ISERROR(VLOOKUP($C24,$I$9:$I$18,1,0)),0,1)*G24 -> 0 | L24: =SUM(I24:K24) -> -15
C25: ='CF (Equity, Debt)'!C7 -> Mena Mobile Inc | D25: ='CF (Equity, Debt)'!D7 -> 43563 | E25: ='CF (Equity, Debt)'!E7 -> -8 | I25: =IF(ISERROR(VLOOKUP($C25,$I$9:$I$18,1,0)),0,1)*E25 -> -8 | J25: =IF(ISERROR(VLOOKUP($C25,$I$9:$I$18,1,0)),0,1)*F25 -> 0 | K25: =IF(ISERROR(VLOOKUP($C25,$I$9:$I$18,1,0)),0,1)*G25 -> 0 | L25: =SUM(I25:K25) -> -8
C26: ='CF (Equity, Debt)'!C8 -> Flyr Inc | D26: ='CF (Equity, Debt)'!D8 -> 43570 | E26: ='CF (Equity, Debt)'!E8 -> -4.9999981 | I26: =IF(ISERROR(VLOOKUP($C26,$I$9:$I$18,1,0)),0,1)*E26 -> -4.9999981 | J26: =IF(ISERROR(VLOOKUP($C26,$I$9:$I$18,1,0)),0,1)*F26 -> 0 | K26: =IF(ISERROR(VLOOKUP($C26,$I$9:$I$18,1,0)),0,1)*G26 -> 0 | L26: =SUM(I26:K26) -> -4.9999981
C27: ='CF (Equity, Debt)'!C9 -> Flyr Inc | D27: ='CF (Equity, Debt)'!D9 -> 43915 | E27: ='CF (Equity, Debt)'!E9 -> -5.0000019 | I27: =IF(ISERROR(VLOOKUP($C27,$I$9:$I$18,1,0)),0,1)*E27 -> -5.0000019 | J27: =IF(ISERROR(VLOOKUP($C27,$I$9:$I$18,1,0)),0,1)*F27 -> 0 | K27: =IF(ISERROR(VLOOKUP($C27,$I$9:$I$18,1,0)),0,1)*G27 -> 0 | L27: =SUM(I27:K27) -> -5.0000019
C28: ='CF (Equity, Debt)'!C10 -> Esyasoft Holding | D28: ='CF (Equity, Debt)'!D10 -> 43870 | E28: ='CF (Equity, Debt)'!E10 -> -2.5 | I28: =IF(ISERROR(VLOOKUP($C28,$I$9:$I$18,1,0)),0,1)*E28 -> -2.5 | J28: =IF(ISERROR(VLOOKUP($C28,$I$9:$I$18,1,0)),0,1)*F28 -> 0 | K28: =IF(ISERROR(VLOOKUP($C28,$I$9:$I$18,1,0)),0,1)*G28 -> 0 | L28: =SUM(I28:K28) -> -2.5
C29: ='CF (Equity, Debt)'!C11 -> Beyond Limits | D29: ='CF (Equity, Debt)'!D11 -> 43879 | E29: ='CF (Equity, Debt)'!E11 -> -20 | I29: =IF(ISERROR(VLOOKUP($C29,$I$9:$I$18,1,0)),0,1)*E29 -> -20 | J29: =IF(ISERROR(VLOOKUP($C29,$I$9:$I$18,1,0)),0,1)*F29 -> 0 | K29: =IF(ISERROR(VLOOKUP($C29,$I$9:$I$18,1,0)),0,1)*G29 -> 0 | L29: =SUM(I29:K29) -> -20
C30: ='CF (Equity, Debt)'!C12 -> Beyond Limits | D30: ='CF (Equity, Debt)'!D12 -> 43921 | E30: ='CF (Equity, Debt)'!E12 -> -30 | I30: =IF(ISERROR(VLOOKUP($C30,$I$9:$I$18,1,0)),0,1)*E30 -> -30 | J30: =IF(ISERROR(VLOOKUP($C30,$I$9:$I$18,1,0)),0,1)*F30 -> 0 | K30: =IF(ISERROR(VLOOKUP($C30,$I$9:$I$18,1,0)),0,1)*G30 -> 0 | L30: =SUM(I30:K30) -> -30
C31: ='CF (Equity, Debt)'!C13 -> Beyond Limits | D31: ='CF (Equity, Debt)'!D13 -> 43989 | E31: ='CF (Equity, Debt)'!E13 -> -30 | I31: =IF(ISERROR(VLOOKUP($C31,$I$9:$I$18,1,0)),0,1)*E31 -> -30 | J31: =IF(ISERROR(VLOOKUP($C31,$I$9:$I$18,1,0)),0,1)*F31 -> 0 | K31: =IF(ISERROR(VLOOKUP($C31,$I$9:$I$18,1,0)),0,1)*G31 -> 0 | L31: =SUM(I31:K31) -> -30
C32: ='CF (Equity, Debt)'!C14 -> Beyond Limits | D32: ='CF (Equity, Debt)'!D14 -> 44103 | E32: ='CF (Equity, Debt)'!E14 -> -10 | I32: =IF(ISERROR(VLOOKUP($C32,$I$9:$I$18,1,0)),0,1)*E32 -> -10 | J32: =IF(ISERROR(VLOOKUP($C32,$I$9:$I$18,1,0)),0,1)*F32 -> 0 | K32: =IF(ISERROR(VLOOKUP($C32,$I$9:$I$18,1,0)),0,1)*G32 -> 0 | L32: =SUM(I32:K32) -> -10
C33: ='CF (Equity, Debt)'!C15 -> ONT plc | D33: ='CF (Equity, Debt)'!D15 -> 43968 | E33: ='CF (Equity, Debt)'!E15 -> -50 | I33: =IF(ISERROR(VLOOKUP($C33,$I$9:$I$18,1,0)),0,1)*E33 -> -50 | J33: =IF(ISERROR(VLOOKUP($C33,$I$9:$I$18,1,0)),0,1)*F33 -> 0 | K33: =IF(ISERROR(VLOOKUP($C33,$I$9:$I$18,1,0)),0,1)*G33 -> 0 | L33: =SUM(I33:K33) -> -50
C34: ='CF (Equity, Debt)'!C16 -> ONT plc | D34: ='CF (Equity, Debt)'!D16 -> 44006 | E34: ='CF (Equity, Debt)'!E16 -> -27.268351 | I34: =IF(ISERROR(VLOOKUP($C34,$I$9:$I$18,1,0)),0,1)*E34 -> -27.268351 | J34: =IF(ISERROR(VLOOKUP($C34,$I$9:$I$18,1,0)),0,1)*F34 -> 0 | K34: =IF(ISERROR(VLOOKUP($C34,$I$9:$I$18,1,0)),0,1)*G34 -> 0 | L34: =SUM(I34:K34) -> -27.268351
C35: ='CF (Equity, Debt)'!C17 -> ONT plc | D35: ='CF (Equity, Debt)'!D17 -> 43837 | E35: ='CF (Equity, Debt)'!E17 -> -18.109441 | I35: =IF(ISERROR(VLOOKUP($C35,$I$9:$I$18,1,0)),0,1)*E35 -> -18.109441 | J35: =IF(ISERROR(VLOOKUP($C35,$I$9:$I$18,1,0)),0,1)*F35 -> 0 | K35: =IF(ISERROR(VLOOKUP($C35,$I$9:$I$18,1,0)),0,1)*G35 -> 0 | L35: =SUM(I35:K35) -> -18.109441
... C38: ='CF (Equity, Debt)'!C20 -> Heygears | D38: ='CF (Equity, Debt)'!D20 -> 44166 | E38: ='CF (Equity, Debt)'!E20 -> -60 | I38: =IF(ISERROR(VLOOKUP($C38,$I$9:$I$18,1,0)),0,1)*E38 -> -60 | J38: =IF(ISERROR(VLOOKUP($C38,$I$9:$I$18,1,0)),0,1)*F38 -> 0 | K38: =IF(ISERROR(VLOOKUP($C38,$I$9:$I$18,1,0)),0,1)*G38 -> 0 | L38: =SUM(I38:K38) -> -60
C39: ='CF (Equity, Debt)'!C21 -> Jysan Technologies | D39: ='CF (Equity, Debt)'!D21 -> 44363 | E39: ='CF (Equity, Debt)'!E21 -> -20 | H39: =E39 -> -20 | I39: =IF(ISERROR(VLOOKUP($C39,$I$9:$I$18,1,0)),0,1)*E39 -> 0 | J39: =IF(ISERROR(VLOOKUP($C39,$I$9:$I$18,1,0)),0,1)*F39 -> 0 | K39: =IF(ISERROR(VLOOKUP($C39,$I$9:$I$18,1,0)),0,1)*G39 -> 0 | L39: =SUM(I39:K39) -> 0
C40: ='CF (Equity, Debt)'!C22 -> Cerebras Systems Inc | D40: ='CF (Equity, Debt)'!D22 -> 44488 | E40: ='CF (Equity, Debt)'!E22 -> -39.999983 | H40: =E40 -> -39.999983 | I40: =IF(ISERROR(VLOOKUP($C40,$I$9:$I$18,1,0)),0,1)*E40 -> 0 | J40: =IF(ISERROR(VLOOKUP($C40,$I$9:$I$18,1,0)),0,1)*F40 -> 0 | K40: =IF(ISERROR(VLOOKUP($C40,$I$9:$I$18,1,0)),0,1)*G40 -> 0 | L40: =SUM(I40:K40) -> 0
C41: ='CF (Equity, Debt)'!C23 -> Endless Studios LLC | D41: ='CF (Equity, Debt)'!D23 -> 44494 | E41: ='CF (Equity, Debt)'!E23 -> -3 | I41: =IF(ISERROR(VLOOKUP($C41,$I$9:$I$18,1,0)),0,1)*E41 -> -3 | J41: =IF(ISERROR(VLOOKUP($C41,$I$9:$I$18,1,0)),0,1)*F41 -> 0 | K41: =IF(ISERROR(VLOOKUP($C41,$I$9:$I$18,1,0)),0,1)*G41 -> 0 | L41: =SUM(I41:K41) -> -3
C42: ='CF (Equity, Debt)'!C24 -> Instadeep Limited | D42: ='CF (Equity, Debt)'!D24 -> 44550 | E42: ='CF (Equity, Debt)'!E24 -> -5.0237202 | I42: =IF(ISERROR(VLOOKUP($C42,$I$9:$I$18,1,0)),0,1)*E42 -> -5.0237202 | J42: =IF(ISERROR(VLOOKUP($C42,$I$9:$I$18,1,0)),0,1)*F42 -> 0 | K42: =IF(ISERROR(VLOOKUP($C42,$I$9:$I$18,1,0)),0,1)*G42 -> 0 | L42: =SUM(I42:K42) -> -5.0237202
C43: ='CF (Equity, Debt)'!C25 -> X-fusion | D43: ='CF (Equity, Debt)'!D25 -> 44574 | E43: ='CF (Equity, Debt)'!E25 -> -493.50096 | H43: =E43 -> -493.50096 | I43: =IF(ISERROR(VLOOKUP($C43,$I$9:$I$18,1,0)),0,1)*E43 -> 0 | J43: =IF(ISERROR(VLOOKUP($C43,$I$9:$I$18,1,0)),0,1)*F43 -> 0 | K43: =IF(ISERROR(VLOOKUP($C43,$I$9:$I$18,1,0)),0,1)*G43 -> 0 | L43: =SUM(I43:K43) -> 0
C44: ='CF (Equity, Debt)'!C26 -> DriveNets | D44: ='CF (Equity, Debt)'!D26 -> 44643 | E44: ='CF (Equity, Debt)'!E26 -> -200 | H44: =E44 -> -200 | I44: =IF(ISERROR(VLOOKUP($C44,$I$9:$I$18,1,0)),0,1)*E44 -> 0 | J44: =IF(ISERROR(VLOOKUP($C44,$I$9:$I$18,1,0)),0,1)*F44 -> 0 | K44: =IF(ISERROR(VLOOKUP($C44,$I$9:$I$18,1,0)),0,1)*G44 -> 0 | L44: =SUM(I44:K44) -> 0
C45: ='CF (Equity, Debt)'!C27 -> DriveNets | D45: ='CF (Equity, Debt)'!D27 -> 44680 | E45: ='CF (Equity, Debt)'!E27 -> -100 | H45: =E45 -> -100 | I45: =IF(ISERROR(VLOOKUP($C45,$I$9:$I$18,1,0)),0,1)*E45 -> 0 | J45: =IF(ISERROR(VLOOKUP($C45,$I$9:$I$18,1,0)),0,1)*F45 -> 0 | K45: =IF(ISERROR(VLOOKUP($C45,$I$9:$I$18,1,0)),0,1)*G45 -> 0 | L45: =SUM(I45:K45) -> 0
C46: ='CF (Equity, Debt)'!C28 -> Esyasoft Holding | D46: ='CF (Equity, Debt)'!D28 -> 44691 | E46: ='CF (Equity, Debt)'!E28 -> 0 | F46: 5 | I46: =IF(ISERROR(VLOOKUP($C46,$I$9:$I$18,1,0)),0,1)*F46 -> 5 | J46: =IF(ISERROR(VLOOKUP($C46,$I$9:$I$18,1,0)),0,1)*F46 -> 5 | K46: =IF(ISERROR(VLOOKUP($C46,$I$9:$I$18,1,0)),0,1)*G46 -> 0 | L46: =SUM(I46:K46) -> 10
C47: ='CF (Equity, Debt)'!C29 -> vTv Therapeutics Inc. | D47: ='CF (Equity, Debt)'!D29 -> 44712 | E47: ='CF (Equity, Debt)'!E29 -> -12.5 | H47: =E47 -> -12.5 | I47: =IF(ISERROR(VLOOKUP($C47,$I$9:$I$18,1,0)),0,1)*E47 -> 0 | J47: =IF(ISERROR(VLOOKUP($C47,$I$9:$I$18,1,0)),0,1)*F47 -> 0 | K47: =IF(ISERROR(VLOOKUP($C47,$I$9:$I$18,1,0)),0,1)*G47 -> 0 | L47: =SUM(I47:K47) -> 0
C48: ='CF (Equity, Debt)'!C30 -> Honor Device Co Ltd | D48: ='CF (Equity, Debt)'!D30 -> 44769 | E48: ='CF (Equity, Debt)'!E30 -> -800 | H48: =E48 -> -800 | I48: =IF(ISERROR(VLOOKUP($C48,$I$9:$I$18,1,0)),0,1)*E48 -> 0 | J48: =IF(ISERROR(VLOOKUP($C48,$I$9:$I$18,1,0)),0,1)*F48 -> 0 | K48: =IF(ISERROR(VLOOKUP($C48,$I$9:$I$18,1,0)),0,1)*G48 -> 0 | L48: =SUM(I48:K48) -> 0
I49: =IF(ISERROR(VLOOKUP($C49,$I$9:$I$18,1,0)),0,1)*E49 -> 0 | J49: =IF(ISERROR(VLOOKUP($C49,$I$9:$I$18,1,0)),0,1)*F49 -> 0 | K49: =IF(ISERROR(VLOOKUP($C49,$I$9:$I$18,1,0)),0,1)*G49 -> 0 | L49: =SUM(I49:K49) -> 0
B50: 1 | C50: Jollychic Holding Limited | D50: 44742 | G50: =VLOOKUP(C50,NAV!$B$9:$D$39,3,0) -> 0 | I50: =IF(ISERROR(VLOOKUP($C50,$I$9:$I$18,1,0)),0,1)*E50 -> 0 | J50: =IF(ISERROR(VLOOKUP($C50,$I$9:$I$18,1,0)),0,1)*F50 -> 0 | K50: =IF(ISERROR(VLOOKUP($C50,$I$9:$I$18,1,0)),0,1)*G50 -> 0 | L50: =SUM(I50:K50) -> 0
B51: 1 | C51: Mena Mobile Inc | D51: 44742 | G51: =VLOOKUP(C51,NAV!$B$9:$D$39,3,0) -> 3.1 | I51: =IF(ISERROR(VLOOKUP($C51,$I$9:$I$18,1,0)),0,1)*E51 -> 0 | J51: =IF(ISERROR(VLOOKUP($C51,$I$9:$I$18,1,0)),0,1)*F51 -> 0 | K51: =IF(ISERROR(VLOOKUP($C51,$I$9:$I$18,1,0)),0,1)*G51 -> 3.1 | L51: =SUM(I51:K51) -> 3.1
B52: 1 | C52: Flyr Inc | D52: 44742 | G52: =VLOOKUP(C52,NAV!$B$9:$D$39,3,0) -> 78.08223 | I52: =IF(ISERROR(VLOOKUP($C52,$I$9:$I$18,1,0)),0,1)*E52 -> 0 | J52: =IF(ISERROR(VLOOKUP($C52,$I$9:$I$18,1,0)),0,1)*F52 -> 0 | K52: =IF(ISERROR(VLOOKUP($C52,$I$9:$I$18,1,0)),0,1)*G52 -> 78.08223 | L52: =SUM(I52:K52) -> 78.08223
B53: 1 | C53: Esyasoft Holding | D53: 44742 | G53: =VLOOKUP(C53,NAV!$B$9:$D$39,3,0) -> 0 | I53: =IF(ISERROR(VLOOKUP($C53,$I$9:$I$18,1,0)),0,1)*E53 -> 0 | J53: =IF(ISERROR(VLOOKUP($C53,$I$9:$I$18,1,0)),0,1)*F53 -> 0 | K53: =IF(ISERROR(VLOOKUP($C53,$I$9:$I$18,1,0)),0,1)*G53 -> 0 | L53: =SUM(I53:K53) -> 0
B54: 1 | C54: Beyond Limits | D54: 44742 | G54: =VLOOKUP(C54,NAV!$B$9:$D$39,3,0) -> 91.00154 | I54: =IF(ISERROR(VLOOKUP($C54,$I$9:$I$18,1,0)),0,1)*E54 -> 0 | J54: =IF(ISERROR(VLOOKUP($C54,$I$9:$I$18,1,0)),0,1)*F54 -> 0 | K54: =IF(ISERROR(VLOOKUP($C54,$I$9:$I$18,1,0)),0,1)*G54 -> 91.00154 | L54: =SUM(I54:K54) -> 91.00154
B55: 1 | C55: ONT plc | D55: 44742 | G55: =VLOOKUP(C55,NAV!$B$9:$D$39,3,0) -> 125.96279 | I55: =IF(ISERROR(VLOOKUP($C55,$I$9:$I$18,1,0)),0,1)*E55 -> 0 | J55: =IF(ISERROR(VLOOKUP($C55,$I$9:$I$18,1,0)),0,1)*F55 -> 0 | K55: =IF(ISERROR(VLOOKUP($C55,$I$9:$I$18,1,0)),0,1)*G55 -> 125.96279 | L55: =SUM(I55:K55) -> 125.96279
B56: 1 | C56: Heygears | D56: 44742 | G56: =VLOOKUP(C56,NAV!$B$9:$D$39,3,0) -> 136.64 | I56: =IF(ISERROR(VLOOKUP($C56,$I$9:$I$18,1,0)),0,1)*E56 -> 0 | J56: =IF(ISERROR(VLOOKUP($C56,$I$9:$I$18,1,0)),0,1)*F56 -> 0 | K56: =IF(ISERROR(VLOOKUP($C56,$I$9:$I$18,1,0)),0,1)*G56 -> 136.64 | L56: =SUM(I56:K56) -> 136.64
C57: Jysan Technologies | D57: 44742 | G57: =VLOOKUP(C57,NAV!$B$9:$D$39,3,0) -> 20 | H57: =G57 -> 20 | I57: =IF(ISERROR(VLOOKUP($C57,$I$9:$I$18,1,0)),0,1)*E57 -> 0 | J57: =IF(ISERROR(VLOOKUP($C57,$I$9:$I$18,1,0)),0,1)*F57 -> 0 | K57: =IF(ISERROR(VLOOKUP($C57,$I$9:$I$18,1,0)),0,1)*G57 -> 0 | L57: =SUM(I57:K57) -> 0
C58: Cerebras Systems Inc | D58: 44742 | G58: =VLOOKUP(C58,NAV!$B$9:$D$39,3,0) -> 39.999983 | H58: =G58 -> 39.999983 | I58: =IF(ISERROR(VLOOKUP($C58,$I$9:$I$18,1,0)),0,1)*E58 -> 0 | J58: =IF(ISERROR(VLOOKUP($C58,$I$9:$I$18,1,0)),0,1)*F58 -> 0 | K58: =IF(ISERROR(VLOOKUP($C58,$I$9:$I$18,1,0)),0,1)*G58 -> 0 | L58: =SUM(I58:K58) -> 0
B59: 1 | C59: Endless Studios LLC | D59: 44742 | G59: =VLOOKUP(C59,NAV!$B$9:$D$39,3,0) -> 3 | I59: =IF(ISERROR(VLOOKUP($C59,$I$9:$I$18,1,0)),0,1)*E59 -> 0 | J59: =IF(ISERROR(VLOOKUP($C59,$I$9:$I$18,1,0)),0,1)*F59 -> 0 | K59: =IF(ISERROR(VLOOKUP($C59,$I$9:$I$18,1,0)),0,1)*G59 -> 3 | L59: =SUM(I59:K59) -> 3
B60: 1 | C60: Instadeep Limited | D60: 44742 | G60: =VLOOKUP(C60,NAV!$B$9:$D$39,3,0) -> 5.0237202 | H60: =G60 -> 5.0237202 | I60: =IF(ISERROR(VLOOKUP($C60,$I$9:$I$18,1,0)),0,1)*E60 -> 0 | J60: =IF(ISERROR(VLOOKUP($C60,$I$9:$I$18,1,0)),0,1)*F60 -> 0 | K60: =IF(ISERROR(VLOOKUP($C60,$I$9:$I$18,1,0)),0,1)*G60 -> 5.0237202 | L60: =SUM(I60:K60) -> 5.0237202
C61: X-fusion | D61: 44742 | G61: =VLOOKUP(C61,NAV!$B$9:$D$39,3,0) -> 493.50096 | H61: =G61 -> 493.50096 | I61: =IF(ISERROR(VLOOKUP($C61,$I$9:$I$18,1,0)),0,1)*E61 -> 0 | J61: =IF(ISERROR(VLOOKUP($C61,$I$9:$I$18,1,0)),0,1)*F61 -> 0 | K61: =IF(ISERROR(VLOOKUP($C61,$I$9:$I$18,1,0)),0,1)*G61 -> 0 | L61: =SUM(I61:K61) -> 0
C62: DriveNets | D62: 44742 | G62: =VLOOKUP(C62,NAV!$B$9:$D$39,3,0) -> 300 | H62: =G62 -> 300 | I62: =IF(ISERROR(VLOOKUP($C62,$I$9:$I$18,1,0)),0,1)*E62 -> 0 | J62: =IF(ISERROR(VLOOKUP($C62,$I$9:$I$18,1,0)),0,1)*F62 -> 0 | K62: =IF(ISERROR(VLOOKUP($C62,$I$9:$I$18,1,0)),0,1)*G62 -> 0 | L62: =SUM(I62:K62) -> 0
C63: vTv Therapeutics Inc. | D63: 44742 | G63: =VLOOKUP(C63,NAV!$B$9:$D$39,3,0) -> -2.4253142 | H63: =G63 -> -2.4253142 | I63: =IF(ISERROR(VLOOKUP($C63,$I$9:$I$18,1,0)),0,1)*E63 -> 0 | J63: =IF(ISERROR(VLOOKUP($C63,$I$9:$I$18,1,0)),0,1)*F63 -> 0 | K63: =IF(ISERROR(VLOOKUP($C63,$I$9:$I$18,1,0)),0,1)*G63 -> 0 | L63: =SUM(I63:K63) -> 0
C64: Honor Device Co Ltd | D64: 44742 | G64: =VLOOKUP(C64,NAV!$B$9:$D$39,3,0) -> 860.46271 | H64: =G64 -> 860.46271 | I64: =IF(ISERROR(VLOOKUP($C64,$I$9:$I$18,1,0)),0,1)*E64 -> 0 | J64: =IF(ISERROR(VLOOKUP($C64,$I$9:$I$18,1,0)),0,1)*F64 -> 0 | K64: =IF(ISERROR(VLOOKUP($C64,$I$9:$I$18,1,0)),0,1)*G64 -> 0 | L64: =SUM(I64:K64) -> 0
I70: IRR | J70: =XIRR(L22:L64,$D$22:$D$64) -> 0.076285401 | K70: =XIRR(I26:I64,$D$26:$D$64) -> 2.9802322e-09
I71: TVPI | J71: =SUM(J22:K64)/-SUM(I22:I64) -> 1.1784668 | K71: =SUMIF(I$22:I$64,">0",I$22:I$64)/-SUMIF(I$22:I$64,"<0",I$22:I$48) -> 0.012987216
I72: RVPI | J72: =SUM(K22:K64)/-SUM(I22:I64) -> 1.1653087 | K72: =SUMIF(I$48:I$64,">0",I$48:I$64)/-SUMIF(I$22:I$48,"<0",I$22:I$48) -> 0
I73: DPI | J73: =SUM(J22:J64)/-SUM(I22:I64) -> 0.013158103 | K73: =SUMIF(I$22:I$48,">0",I$22:I$48)/-SUMIF(I$22:I$48,"<0",I$22:I$48) -> 0.012987216

Sheet 2. IRR Debt
B2: IRR - Debt
B4: Date of NAV | C4: =D!D2 -> 44834 | I4: Investtment Level Summary | P4: Overall Summary
B6: USD Millions
B7: Investment | C7: Payment date | D7: Contributions | E7: Distributions | F7: Residual Value | G7: Combined | K7: Contribution | L7: Distribution | M7: Residual Value | N7: Combined | Q7: Committed | R7: Invested | S7: Remaining Commitment | T7: Distributions | U7: Residual Value | V7: IRR | W7: TVPI | X7: RPI | Y7: DPI
B8: Debt Investments
B9: Glass Earth Holdings LLC | C9: 43635 | D9: -8 | G9: =SUM(D9:F9) -> -8 | I9: Glass Earth Holdings LLC | J9: 43635 | K9: -8 | N9: =SUM(K9:M9) -> -8 | P9: Glass Earth Holdings LLC | Q9: =R9 -> 8 | R9: =-D9 -> 8 | S9: 0 | T9: =E9 -> 0 | U9: =F13 -> 0 | V9: =J12 -> NM | W9: =(T9+U9)/R9 -> 0 | X9: =U9/R9 -> 0 | Y9: =T9/R9 -> 0
B10: Mena Mobile Inc | C10: 44293 | D10: -2.353982 | G10: =SUM(D10:F10) -> -2.353982 | I10: Glass Earth Holdings LLC | J10: =$C$4 -> 44834 | M10: 0 | N10: =SUM(K10:M10) -> 0 | P10: Mena Mobile Inc | Q10: =R10 -> 2.353982 | R10: =-D10 -> 2.353982 | S10: 0 | T10: =E10 -> 0 | U10: =F14 -> 2.353982 | V10: =J22:J22 -> 2.9802322e-09 | W10: =(T10+U10)/R10 -> 1 | X10: =U10/R10 -> 1 | Y10: =T10/R10 -> 0
B11: Esyasoft Holding | C11: 44384 | D11: -0.411765 | G11: =SUM(D11:F11) -> -0.411765 | P11: Esyasoft Holding | Q11: =R11 -> 0.411765 | R11: =-D11 -> 0.411765 | S11: 0 | T11: =E11 -> 0 | U11: =F15 -> 0.45643868 | V11: =J31 -> 0.087134919 | W11: =(T11+U11)/R11 -> 1.1084932 | X11: =U11/R11 -> 1.1084932 | Y11: =T11/R11 -> 0
I12: XIRR | J12: =IF(ISERROR(XIRR(N9:N10,J9:J10)),"NM",XIRR(N9:N10,J9:J10)) -> NM | L12: Contributions | Q12: =SUM(Q9:Q11) -> 10.765747 | R12: =SUM(R9:R11) -> 10.765747 | S12: =SUM(S9:S11) -> 0 | T12: =SUM(T9:T11) -> 0 | U12: =SUM(U9:U11) -> 2.8104207 | V12: =XIRR(G9:G15,C9:C15) -> -0.40060765 | W12: =(T12+U12)/R12 -> 0.26105208 | X12: =U12/R12 -> 0.26105208 | Y12: =T12/R12 -> 0
B13: Glass Earth Holdings LLC | C13: =$C$4 -> 44834 | F13: 0 | G13: =SUM(D13:F13) -> 0 | I13: TVPI | J13: =SUM(L9:M10)/-SUM(K9:K10) -> 0 | L13: Distributions
B14: Mena Mobile Inc | C14: =$C$4 -> 44834 | F14: 2.353982 | G14: =SUM(D14:F14) -> 2.353982 | I14: RPI | J14: =SUM(M9:M10)/-SUM(K9:K10) -> 0 | L14: Residual Value
B15: Esyasoft Holding | C15: =$C$4 -> 44834 | F15: 0.45643868 | G15: =SUM(D15:F15) -> 0.45643868 | I15: DPI | J15: =SUM(L9:L10)/-SUM(K9:K10) -> 0 | P15: XIRR | Q15: =XIRR(G9:G18,C9:C18) -> -0.40060765
P16: TVPI | Q16: =SUM(T9:U11)/SUM(R9:R11) -> 0.26105208
P17: RPI | Q17: =SUM(U9:U11)/SUM(R9:R11) -> 0.26105208
P18: DPI | Q18: =SUM(T9:T11)/SUM(R9:R11) -> 0
I19: Mena Mobile Inc | J19: 44293 | K19: -2.353982 | N19: =SUM(K19:M19) -> -2.353982
I20: Mena Mobile Inc | J20: =$C$4 -> 44834 | M20: 2.353982 | N20: =SUM(K20:M20) -> 2.353982
I22: XIRR | J22: =IF(ISERROR(XIRR(N19:N20,J19:J20)),"NM",XIRR(N19:N20,J19:J20)) -> 2.9802322e-09 | L22: Contributions
I23: TVPI | J23: =SUM(L19:M20)/-SUM(K19:K20) -> 1 | L23: Distributions
I24: RPI | J24: =SUM(M19:M20)/-SUM(K19:K20) -> 1 | L24: Residual Value
I25: DPI | J25: =SUM(L19:L20)/-SUM(K19:K20) -> 0
I28: Esyasoft Holding | J28: 44384 | K28: -0.411765 | N28: =SUM(K28:M28) -> -0.411765
I29: Esyasoft Holding | J29: =$C$4 -> 44834 | M29: 0.45643868 | N29: =SUM(K29:M29) -> 0.45643868
I31: XIRR | J31: =IF(ISERROR(XIRR(N28:N29,J28:J29)),"NM",XIRR(N28:N29,J28:J29)) -> 0.087134919 | L31: Contributions
I32: TVPI | J32: =SUM(L28:M29)/-SUM(K28:K29) -> 1.1084932 | L32: Distributions
I33: RPI | J33: =SUM(M28:M29)/-SUM(K28:K29) -> 1.1084932 | L33: Residual Value
I34: DPI | J34: =SUM(L28:L29)/-SUM(K28:K29) -> 0

Sheet 3. IRR Funds
B2: IRR - FUNDS
B4: Date of NAV | C4: =D!D2 -> 44834 | I4: Fund Level Summary | P4: Overall Summary
B6: USD Millions
B7: Investment | C7: Payment date | D7: Contributions | E7: Distributions | F7: Residual Value | G7: Combined | K7: Contribution | L7: Distribution | M7: Residual Value | N7: Combined | Q7: Committed | R7: Invested | S7: Remaining Commitment | T7: Distributions | U7: Residual Value | V7: IRR | W7: TVPI | X7: RPI | Y7: DPI
B8: Sinovation Disrupt Fund, L.P. | C8: 18/11/2020 | D8: -10.5 | G8: =SUM(D8:F8) -> -10.5 | P8: Funds Investments
B9: Sinovation Disrupt Fund, L.P. | C9: 44238 | D9: 4.214027 | G9: =SUM(D9:F9) -> 4.214027 | I9: New Space Capital Fund I | J9: 44087 | K9: -20.917553 | N9: =SUM(K9:M9) -> -20.917553 | P9: New Space Capital Fund I | Q9: 25.557908 | R9: =-SUMIF($B$7:$F$103,$P9,$D$7:$D$103) -> 21.611951 | S9: =Q9-R9 -> 3.9459573 | T9: =SUMIF($B$7:$F$103,$P9,$E$7:$E$103) -> 0 | U9: =SUMIF($B$7:$F$103,$P9,$F$7:$F$103) -> 31.952799 | V9: =J16 -> 0.21387834 | W9: =(T9+U9)/R9 -> 1.4784783 | X9: =U9/R9 -> 1.4784783 | Y9: =T9/R9 -> 0
B10: Sinovation Disrupt Fund, L.P. | C10: 44238 | E10: 0.05044835 | G10: =SUM(D10:F10) -> 0.05044835 | I10: New Space Capital Fund I | J10: 44287 | K10: -0.21103182 | N10: =SUM(K10:M10) -> -0.21103182 | P10: New Space Capital SCSp | Q10: 2.7058824 | R10: =-SUMIF($B$7:$F$103,$P10,$D$7:$D$103) -> 2.7058824 | S10: =Q10-R10 -> 0 | T10: =SUMIF($B$7:$F$103,$P10,$E$7:$E$103) -> 0 | U10: =SUMIF($B$7:$F$103,$P10,$F$7:$F$103) -> 2.7058824 | V10: 0 | W10: =(T10+U10)/R10 -> 1 | X10: =U10/R10 -> 1 | Y10: =T10/R10 -> 0
B11: Sinovation Disrupt Fund, L.P. | C11: 44285 | D11: -6.433746 | G11: =SUM(D11:F11) -> -6.433746 | I11: New Space Capital Fund I | J11: 44442 | K11: -0.23965473 | N11: =SUM(K11:M11) -> -0.23965473 | P11: North Summit Capital Fund | Q11: 300 | R11: =-SUMIF($B$7:$F$103,$P11,$D$7:$D$103) -> 83.214653 | S11: =Q11-R11+T11 -> 217.81331 | T11: =SUMIF($B$7:$F$103,$P11,$E$7:$E$103) -> 1.027961 | U11: =SUMIF($B$7:$F$103,$P11,$F$7:$F$103) -> 79.32 | V11: =J48 -> -0.018174636 | W11: =(T11+U11)/R11 -> 0.96555063 | X11: =U11/R11 -> 0.95319751 | Y11: =T11/R11 -> 0.012353125
B12: Sinovation Disrupt Fund, L.P. | C12: 44269 | D12: 1.1352074 | G12: =SUM(D12:F12) -> 1.1352074 | I12: New Space Capital Fund I | J12: 44623 | K12: -0.25893585 | N12: =SUM(K12:M12) -> -0.25893585 | P12: Sinovation Disrupt Fund, L.P. | Q12: 50 | R12: =-SUMIF($B$7:$F$103,$P12,$D$7:$D$103) -> 16.790246 | S12: =Q12-R12 -> 33.209754 | T12: =SUMIF($B$7:$F$103,$P12,$E$7:$E$103) -> 0.44382835 | U12: =SUMIF($B$7:$F$103,$P12,$F$7:$F$103) -> 15.875237 | V12: =J68 -> -0.016854355 | W12: =(T12+U12)/R12 -> 0.97193724 | X12: =U12/R12 -> 0.94550354 | Y12: =T12/R12 -> 0.026433701
B13: Sinovation Disrupt Fund, L.P. | C13: 44269 | E13: 0.0259 | G13: =SUM(D13:F13) -> 0.0259 | I13: New Space Capital Fund I | J13: 44784 | K13: 0.015224657 | N13: =SUM(K13:M13) -> 0.015224657 | P13: Acies Investments Fund I, L.P. | Q13: 17.1125 | R13: =-SUMIF($B$7:$F$103,$P13,$D$7:$D$103) -> 10.626862 | S13: =Q13-R13 -> 6.4856375 | T13: =SUMIF($B$7:$F$103,$P13,$E$7:$E$103) -> 0 | U13: =SUMIF($B$7:$F$103,$P13,$F$7:$F$103) -> 10.343447 | V13: =J80 -> -0.046596518 | W13: =(T13+U13)/R13 -> 0.97333028 | X13: =U13/R13 -> 0.97333028 | Y13: =T13/R13 -> 0
B14: Sinovation Disrupt Fund, L.P. | C14: 44483 | D14: -7.567138 | G14: =SUM(D14:F14) -> -7.567138 | I14: New Space Capital Fund I | J14: =$C$4 -> 44834 | M14: 31.952799 | N14: =SUM(K14:M14) -> 31.952799
B15: Sinovation Disrupt Fund, L.P. | C15: 44554 | D15: -7.385016 | G15: =SUM(D15:F15) -> -7.385016 | P15: Total | Q15: =SUM(Q9:Q14) -> 395.37629 | R15: =SUM(R9:R14) -> 134.94959 | S15: =SUM(S9:S14) -> 261.45466 | T15: =SUM(T9:T14) -> 1.4717893 | U15: =SUM(U9:U14) -> 140.19737 | V15: =XIRR(G8:G59,C8:C59) -> 0.027224669 | W15: =(T15+U15)/R15 -> 1.0497931 | X15: =U15/R15 -> 1.0388869 | Y15: =T15/R15 -> 0.010906215
B16: Sinovation Disrupt Fund, L.P. | C16: 44554 | D16: 4.0733456 | G16: =SUM(D16:F16) -> 4.0733456 | I16: XIRR | J16: =XIRR(N9:N14,J9:J14) -> 0.21387834 | L16: Contributions | M16: =-SUM(K9:K14)='Summary | 01 '!K34 -> TRUE
B17: Sinovation Disrupt Fund, L.P. | C17: 44554 | E17: 0.139694 | G17: =SUM(D17:F17) -> 0.139694 | I17: TVPI | J17: =SUM(L9:M14)/-SUM(K9:K14) -> 1.4784783 | L17: Distributions | M17: =-SUM(L9:L15)=-'Summary | 01 '!M34 -> TRUE
B18: Sinovation Disrupt Fund, L.P. | C18: 44703 | D18: 5.673074 | G18: =SUM(D18:F18) -> 5.673074 | I18: RPI | J18: =SUM(M9:M14)/-SUM(K9:K14) -> 1.4784783 | L18: Residual Value | M18: =M14='Summary | 01 '!N34 -> TRUE | P18: XIRR | Q18: =XIRR(G8:G59,C8:C59) -> 0.027224669
B19: Sinovation Disrupt Fund, L.P. | C19: 44703 | E19: 0.227786 | G19: =SUM(D19:F19) -> 0.227786 | I19: DPI | J19: =SUM(L9:L14)/-SUM(K9:K14) -> 0 | P19: TVPI | Q19: =SUM(T9:U13)/SUM(R9:R13) -> 1.0497931
B20: North Summit Capital Fund | C20: 19/07/2019 | D20: -3 | G20: =SUM(D20:F20) -> -3 | P20: RPI | Q20: =SUM(U9:U13)/SUM(R9:R13) -> 1.0388869
B21: North Summit Capital Fund | C21: 43983 | D21: -4.485 | G21: =SUM(D21:F21) -> -4.485 | P21: DPI | Q21: =SUM(T9:T13)/SUM(R9:R13) -> 0.010906215
B22: North Summit Capital Fund | C22: 18/02/2020 | D22: -9.50975 | G22: =SUM(D22:F22) -> -9.50975
B23: North Summit Capital Fund | C23: 13/04/2020 | D23: -41.3 | G23: =SUM(D23:F23) -> -41.3 | I23: New Space Capital SCSp | J23: 44087 | K23: -2.7058824 | N23: =SUM(K23:M23) -> -2.7058824
B24: North Summit Capital Fund | C24: 16/11/2020 | D24: 9.95 | G24: =SUM(D24:F24) -> 9.95 | I24: New Space Capital SCSp | J24: 44819 | M24: 2.7058824 | N24: =SUM(K24:M24) -> 2.7058824
B25: North Summit Capital Fund | C25: 16/11/2020 | D25: -10.455 | G25: =SUM(D25:F25) -> -10.455
B26: North Summit Capital Fund | C26: 31/12/2020 | D26: 4.975 | G26: =SUM(D26:F26) -> 4.975 | I26: XIRR | J26: =XIRR(N23:N24,J23:J24) -> 2.9802322e-09 | L26: Contributions | M26: =-SUM(K23:K24)='Summary | 01 '!K35 -> TRUE
B27: North Summit Capital Fund | C27: 31/12/2020 | D27: -3.452293 | G27: =SUM(D27:F27) -> -3.452293 | I27: TVPI | J27: =SUM(L23:M24)/-SUM(K23:K24) -> 1 | L27: Distributions | M27: =-SUM(L19:L25)=-'Summary | 01 '!L35 -> TRUE
B28: North Summit Capital Fund | C28: 31/12/2020 | E28: 0.582902 | G28: =SUM(D28:F28) -> 0.582902 | I28: RPI | J28: =SUM(M23:M24)/-SUM(K23:K24) -> 1 | L28: Residual Value | M28: =M24='Summary | 01 '!N35 -> TRUE
B29: North Summit Capital Fund | C29: 44370 | D29: -5.97 | G29: =SUM(D29:F29) -> -5.97 | I29: DPI | J29: =SUM(L23:L24)/-SUM(K23:K24) -> 0
B30: North Summit Capital Fund | C30: 44400 | D30: -0.75 | G30: =SUM(D30:F30) -> -0.75
B31: North Summit Capital Fund | C31: 44400 | E31: 0.445059 | G31: =SUM(D31:F31) -> 0.445059
B32: North Summit Capital Fund | C32: 44554 | D32: 1.78239 | G32: =SUM(D32:F32) -> 1.78239 | I32: North Summit Capital Fund | J32: 19/07/2019 | K32: -3 | N32: =SUM(K32:M32) -> -3
B33: North Summit Capital Fund | C33: 44676 | D33: -21 | G33: =SUM(D33:F33) -> -21 | I33: North Summit Capital Fund | J33: 43983 | K33: -4.485 | N33: =SUM(K33:M33) -> -4.485
B34: New Space Capital Fund I | C34: 44087 | D34: -20.917553 | G34: =SUM(D34:F34) -> -20.917553 | I34: North Summit Capital Fund | J34: 18/02/2020 | K34: -9.50975 | N34: =SUM(K34:M34) -> -9.50975
B35: New Space Capital Fund I | C35: 44287 | D35: -0.21103182 | G35: =SUM(D35:F35) -> -0.21103182 | I35: North Summit Capital Fund | J35: 13/04/2020 | K35: -41.3 | N35: =SUM(K35:M35) -> -41.3
B36: New Space Capital Fund I | C36: 44442 | D36: -0.23965473 | G36: =SUM(D36:F36) -> -0.23965473 | I36: North Summit Capital Fund | J36: 16/11/2020 | K36: 9.95 | N36: =SUM(K36:M36) -> 9.95
B37: New Space Capital Fund I | C37: 44623 | D37: -0.25893585 | G37: =SUM(D37:F37) -> -0.25893585 | I37: North Summit Capital Fund | J37: 16/11/2020 | K37: -10.455 | N37: =SUM(K37:M37) -> -10.455
B38: New Space Capital Fund I | C38: 44784 | D38: 0.015224657 | G38: =SUM(D38:F38) -> 0.015224657 | I38: North Summit Capital Fund | J38: 31/12/2020 | K38: 4.975 | N38: =SUM(K38:M38) -> 4.975
B39: New Space Capital SCSp | C39: 44087 | D39: -2.7058824 | G39: =SUM(D39:F39) -> -2.7058824 | I39: North Summit Capital Fund | J39: 31/12/2020 | K39: -3.452293 | N39: =SUM(K39:M39) -> -3.452293
B40: Acies Investments Fund I, L.P. | C40: 44540 | D40: -2.8053125 | G40: =SUM(D40:F40) -> -2.8053125 | I40: North Summit Capital Fund | J40: 31/12/2020 | L40: 0.582902 | N40: =SUM(K40:M40) -> 0.582902
B41: Acies Investments Fund I, L.P. | C41: 44602 | D41: -3.4075 | G41: =SUM(D41:F41) -> -3.4075 | I41: North Summit Capital Fund | J41: 44370 | K41: -5.97 | N41: =SUM(K41:M41) -> -5.97
B42: Acies Investments Fund I, L.P. | C42: 44683 | D42: -1.025775 | G42: =SUM(D42:F42) -> -1.025775 | I42: North Summit Capital Fund | J42: 44400 | K42: -0.75 | N42: =SUM(K42:M42) -> -0.75
B43: Acies Investments Fund I, L.P. | C43: 44707 | D43: -3.388275 | G43: =SUM(D43:F43) -> -3.388275 | I43: North Summit Capital Fund | J43: 44400 | L43: 0.445059 | N43: =SUM(K43:M43) -> 0.445059
I44: North Summit Capital Fund | J44: 44554 | K44: 1.78239 | N44: =SUM(K44:M44) -> 1.78239
I45: North Summit Capital Fund | J45: 44676 | K45: -21 | N45: =SUM(K45:M45) -> -21
B46: Sinovation Disrupt Fund, L.P. | C46: =$C$4 -> 44834 | F46: 15.875237 | G46: =SUM(D46:F46) -> 15.875237 | I46: North Summit Capital Fund | J46: =$C$4 -> 44834 | M46: 79.32 | N46: =SUM(K46:M46) -> 79.32
B47: North Summit Capital Fund | C47: =$C$4 -> 44834 | F47: 79.32 | G47: =SUM(D47:F47) -> 79.32
B48: New Space Capital Fund I | C48: =$C$4 -> 44834 | F48: 31.952799 | G48: =SUM(D48:F48) -> 31.952799 | I48: XIRR | J48: =XIRR(N32:N46,J32:J46) -> -0.018174636 | L48: Contributions | M48: =-SUM(K32:K45)='Summary | 01 '!K36 -> TRUE
B49: New Space Capital SCSp | C49: =$C$4 -> 44834 | F49: 2.7058824 | G49: =SUM(D49:F49) -> 2.7058824 | I49: TVPI | J49: =SUM(L32:M46)/-SUM(K32:K46) -> 0.96555063 | L49: Distributions | M49: =-SUM(L32:L45)=-'Summary | 01 '!M36 -> TRUE
B50: Acies Investments Fund I, L.P. | C50: =$C$4 -> 44834 | F50: 10.343447 | G50: =SUM(D50:F50) -> 10.343447 | I50: RPI | J50: =SUM(M32:M46)/-SUM(K32:K46) -> 0.95319751 | L50: Residual Value | M50: =M46='Summary | 01 '!N36 -> TRUE
I51: DPI | J51: =SUM(L32:L46)/-SUM(K32:K46) -> 0.012353125
I54: Sinovation Disrupt Fund, L.P. | J54: 18/11/2020 | K54: -10.5 | N54: =SUM(K54:M54) -> -10.5
I55: Sinovation Disrupt Fund, L.P. | J55: 44238 | K55: 4.214027 | N55: =SUM(K55:M55) -> 4.214027
I56: Sinovation Disrupt Fund, L.P. | J56: 44238 | L56: 0.05044835 | N56: =SUM(K56:M56) -> 0.05044835
I57: Sinovation Disrupt Fund, L.P. | J57: 44285 | K57: -6.433746 | N57: =SUM(K57:M57) -> -6.433746
I58: Sinovation Disrupt Fund, L.P. | J58: 44269 | K58: 1.1352074 | N58: =SUM(K58:M58) -> 1.1352074
I59: Sinovation Disrupt Fund, L.P. | J59: 44269 | L59: 0.0259 | N59: =SUM(K59:M59) -> 0.0259
I60: Sinovation Disrupt Fund, L.P. | J60: 44483 | K60: -7.567138 | N60: =SUM(K60:M60) -> -7.567138
I61: Sinovation Disrupt Fund, L.P. | J61: 44554 | K61: -7.385016 | N61: =SUM(K61:M61) -> -7.385016
I62: Sinovation Disrupt Fund, L.P. | J62: 44554 | K62: 4.0733456 | N62: =SUM(K62:M62) -> 4.0733456
I63: Sinovation Disrupt Fund, L.P. | J63: 44554 | L63: 0.139694 | N63: =SUM(K63:M63) -> 0.139694
I64: Sinovation Disrupt Fund, L.P. | J64: 44703 | K64: 5.673074 | N64: =SUM(K64:M64) -> 5.673074
I65: Sinovation Disrupt Fund, L.P. | J65: 44703 | L65: 0.227786 | N65: =SUM(K65:M65) -> 0.227786
I66: Sinovation Disrupt Fund, L.P. | J66: =$C$4 -> 44834 | M66: 15.875237 | N66: =SUM(K66:M66) -> 15.875237
I68: XIRR | J68: =XIRR(N54:N66,J54:J66) -> -0.016854355 | L68: Contributions | M68: =-SUM(K54:K65)='Summary | 01 '!K37 -> TRUE
I69: TVPI | J69: =SUM(L54:M66)/-SUM(K54:K66) -> 0.97193724 | L69: Distributions | M69: =-SUM(L54:L65)=-'Summary | 01 '!M37 -> TRUE
I70: RPI | J70: =SUM(M54:M66)/-SUM(K54:K66) -> 0.94550354 | L70: Residual Value | M70: =M66='Summary | 01 '!N37 -> TRUE
I71: DPI | J71: =SUM(L54:L66)/-SUM(K54:K66) -> 0.026433701
I74: Acies Investments Fund I, L.P. | J74: 44540 | K74: -2.8053125 | N74: =SUM(K74:M74) -> -2.8053125
I75: Acies Investments Fund I, L.P. | J75: 44602 | K75: -3.4075 | N75: =SUM(K75:M75) -> -3.4075
I76: Acies Investments Fund I, L.P. | J76: 44683 | K76: -1.025775 | N76: =SUM(K76:M76) -> -1.025775
I77: Acies Investments Fund I, L.P. | J77: 44707 | K77: -3.388275 | N77: =SUM(K77:M77) -> -3.388275
I78: Acies Investments Fund I, L.P. | J78: =$C$4 -> 44834 | M78: 10.343447 | N78: =SUM(K78:M78) -> 10.343447
I80: XIRR | J80: =XIRR(N74:N78,J74:J78) -> -0.046596518 | L80: Contributions | M80: =-SUM(K74:K78)='Summary | 01 '!K38 -> TRUE
I81: TVPI | J81: =SUM(L74:M78)/-SUM(K74:K78) -> 0.97333028 | L81: Distributions | M81: =-SUM(L74:L83)=-'Summary | 01 '!M38 -> TRUE
I82: RPI | J82: =SUM(M74:M78)/-SUM(K74:K78) -> 0.97333028 | L82: Residual Value | M82: =M78='Summary | 01 '!N38 -> TRUE
I83: DPI | J83: =SUM(L74:L78)/-SUM(K74:K78) -> 0

Sheet 4.All
B2: IRR - All Investments (Equity, Debt, Funds)
B4: Date of NAV | C4: =D!D2 -> 44834
B6: (in USD, Mn)
B7: Investment | C7: Payment date | D7: Contribution | E7: Distributions | F7: Remaining Value | G7: Combined | H7: Type | J7: Invested | K7: Remaining Commitment | L7: Distributions | M7: Residual Value | N7: IRR | O7: TVPI | P7: RPI | Q7: DPI
B8: ='CF (Equity, Debt)'!C4 -> Jollychic Holding Limited | C8: ='CF (Equity, Debt)'!D4 -> 43470 | D8: ='CF (Equity, Debt)'!E4 -> -30 | G8: =SUM(D8:F8) -> -30 | H8: Equity
B9: ='CF (Equity, Debt)'!C5 -> Jollychic Holding Limited | C9: ='CF (Equity, Debt)'!D5 -> 43724 | D9: ='CF (Equity, Debt)'!E5 -> -20 | G9: =SUM(D9:F9) -> -20 | H9: Equity | J9: =-SUM(D8:D99) -> 2196.7103 | L9: =SUM(E8:E99) -> 6.4717893 | M9: =SUM(F8:F99) -> 2297.646 | N9: =XIRR(G8:G96,C8:C96) -> 0.054621205 | O9: =(L9+M9)/J9 -> 1.0488947 | P9: =M9/J9 -> 1.0459486 | Q9: =L9/J9 -> 0.0029461279
B10: ='CF (Equity, Debt)'!C6 -> Jollychic Holding Limited | C10: ='CF (Equity, Debt)'!D6 -> 43724 | D10: ='CF (Equity, Debt)'!E6 -> -15 | G10: =SUM(D10:F10) -> -15 | H10: Equity
B11: ='CF (Equity, Debt)'!C7 -> Mena Mobile Inc | C11: ='CF (Equity, Debt)'!D7 -> 43563 | D11: ='CF (Equity, Debt)'!E7 -> -8 | G11: =SUM(D11:F11) -> -8 | H11: Equity
B12: ='CF (Equity, Debt)'!C8 -> Flyr Inc | C12: ='CF (Equity, Debt)'!D8 -> 43570 | D12: ='CF (Equity, Debt)'!E8 -> -4.9999981 | G12: =SUM(D12:F12) -> -4.9999981 | H12: Equity
B13: ='CF (Equity, Debt)'!C9 -> Flyr Inc | C13: ='CF (Equity, Debt)'!D9 -> 43915 | D13: ='CF (Equity, Debt)'!E9 -> -5.0000019 | G13: =SUM(D13:F13) -> -5.0000019 | H13: Equity
B14: ='CF (Equity, Debt)'!C10 -> Esyasoft Holding | C14: ='CF (Equity, Debt)'!D10 -> 43870 | D14: ='CF (Equity, Debt)'!E10 -> -2.5 | G14: =SUM(D14:F14) -> -2.5 | H14: Equity
B15: ='CF (Equity, Debt)'!C11 -> Beyond Limits | C15: ='CF (Equity, Debt)'!D11 -> 43879 | D15: ='CF (Equity, Debt)'!E11 -> -20 | G15: =SUM(D15:F15) -> -20 | H15: Equity
B16: ='CF (Equity, Debt)'!C12 -> Beyond Limits | C16: ='CF (Equity, Debt)'!D12 -> 43921 | D16: ='CF (Equity, Debt)'!E12 -> -30 | G16: =SUM(D16:F16) -> -30 | H16: Equity
B17: ='CF (Equity, Debt)'!C13 -> Beyond Limits | C17: ='CF (Equity, Debt)'!D13 -> 43989 | D17: ='CF (Equity, Debt)'!E13 -> -30 | G17: =SUM(D17:F17) -> -30 | H17: Equity
B18: ='CF (Equity, Debt)'!C14 -> Beyond Limits | C18: ='CF (Equity, Debt)'!D14 -> 44103 | D18: ='CF (Equity, Debt)'!E14 -> -10 | G18: =SUM(D18:F18) -> -10 | H18: Equity
B19: ='CF (Equity, Debt)'!C15 -> ONT plc | C19: ='CF (Equity, Debt)'!D15 -> 43968 | D19: ='CF (Equity, Debt)'!E15 -> -50 | G19: =SUM(D19:F19) -> -50 | H19: Equity
B20: ='CF (Equity, Debt)'!C16 -> ONT plc | C20: ='CF (Equity, Debt)'!D16 -> 44006 | D20: ='CF (Equity, Debt)'!E16 -> -27.268351 | G20: =SUM(D20:F20) -> -27.268351 | H20: Equity
B21: ='CF (Equity, Debt)'!C17 -> ONT plc | C21: ='CF (Equity, Debt)'!D17 -> 43837 | D21: ='CF (Equity, Debt)'!E17 -> -18.109441 | G21: =SUM(D21:F21) -> -18.109441 | H21: Equity
... B31: ='CF (Equity, Debt)'!C27 -> DriveNets | C31: ='CF (Equity, Debt)'!D27 -> 44680 | D31: ='CF (Equity, Debt)'!E27 -> -100 | G31: =SUM(D31:F31) -> -100 | H31: Equity
B32: ='CF (Equity, Debt)'!C28 -> Esyasoft Holding | C32: ='CF (Equity, Debt)'!D28 -> 44691 | D32: ='CF (Equity, Debt)'!E28 -> 0 | E32: 5 | G32: =SUM(D32:F32) -> 5 | H32: Equity
B33: ='CF (Equity, Debt)'!C29 -> vTv Therapeutics Inc. | C33: ='CF (Equity, Debt)'!D29 -> 44712 | D33: ='CF (Equity, Debt)'!E29 -> -12.5 | G33: =SUM(D33:F33) -> -12.5 | H33: Equity
B34: ='CF (Equity, Debt)'!C30 -> Honor Device Co Ltd | C34: ='CF (Equity, Debt)'!D30 -> 44769 | D34: ='CF (Equity, Debt)'!E30 -> -800 | G34: =SUM(D34:F34) -> -800 | H34: Equity
B35: ='CF (Equity, Debt)'!C33 -> Glass Earth Holdings LLC | C35: ='CF (Equity, Debt)'!D33 -> 43635 | D35: ='CF (Equity, Debt)'!E33 -> -8 | G35: =SUM(D35:F35) -> -8 | H35: Debt
B36: ='CF (Equity, Debt)'!C34 -> Mena Mobile Inc | C36: ='CF (Equity, Debt)'!D34 -> 44293 | D36: ='CF (Equity, Debt)'!E34 -> -2.353982 | G36: =SUM(D36:F36) -> -2.353982 | H36: Debt
B37: ='CF (Equity, Debt)'!C35 -> Esyasoft Holding | C37: ='CF (Equity, Debt)'!D35 -> 44384 | D37: ='CF (Equity, Debt)'!E35 -> -0.411765 | G37: =SUM(D37:F37) -> -0.411765 | H37: Debt
B38: ='CF (Funds)'!B3 -> Sinovation Disrupt Fund, L.P. | C38: ='CF (Funds)'!C3 -> 44153 | D38: ='CF (Funds)'!D3 -> -10.5 | E38: ='CF (Funds)'!E3 -> 0 | G38: =SUM(D38:F38) -> -10.5 | H38: Fund
B39: ='CF (Funds)'!B4 -> Sinovation Disrupt Fund, L.P. | C39: ='CF (Funds)'!C4 -> 44238 | D39: ='CF (Funds)'!D4 -> 4.214027 | E39: ='CF (Funds)'!E4 -> 0 | G39: =SUM(D39:F39) -> 4.214027 | H39: Fund
B40: ='CF (Funds)'!B5 -> Sinovation Disrupt Fund, L.P. | C40: ='CF (Funds)'!C5 -> 44238 | D40: ='CF (Funds)'!D5 -> 0 | E40: ='CF (Funds)'!E5 -> 0.05044835 | G40: =SUM(D40:F40) -> 0.05044835 | H40: Fund
B41: ='CF (Funds)'!B6 -> Sinovation Disrupt Fund, L.P. | C41: ='CF (Funds)'!C6 -> 44285 | D41: ='CF (Funds)'!D6 -> -6.433746 | E41: ='CF (Funds)'!E6 -> 0 | G41: =SUM(D41:F41) -> -6.433746 | H41: Fund
B42: ='CF (Funds)'!B7 -> Sinovation Disrupt Fund, L.P. | C42: ='CF (Funds)'!C7 -> 44269 | D42: ='CF (Funds)'!D7 -> 1.1352074 | E42: ='CF (Funds)'!E7 -> 0 | G42: =SUM(D42:F42) -> 1.1352074 | H42: Fund
B43: ='CF (Funds)'!B8 -> Sinovation Disrupt Fund, L.P. | C43: ='CF (Funds)'!C8 -> 44269 | D43: ='CF (Funds)'!D8 -> 0 | E43: ='CF (Funds)'!E8 -> 0.0259 | G43: =SUM(D43:F43) -> 0.0259 | H43: Fund
B44: ='CF (Funds)'!B9 -> Sinovation Disrupt Fund, L.P. | C44: ='CF (Funds)'!C9 -> 44483 | D44: ='CF (Funds)'!D9 -> -7.567138 | E44: ='CF (Funds)'!E9 -> 0 | G44: =SUM(D44:F44) -> -7.567138 | H44: Fund
B45: ='CF (Funds)'!B10 -> Sinovation Disrupt Fund, L.P. | C45: ='CF (Funds)'!C10 -> 44554 | D45: ='CF (Funds)'!D10 -> -7.385016 | E45: ='CF (Funds)'!E10 -> 0 | G45: =SUM(D45:F45) -> -7.385016 | H45: Fund
B46: ='CF (Funds)'!B11 -> Sinovation Disrupt Fund, L.P. | C46: ='CF (Funds)'!C11 -> 44554 | D46: ='CF (Funds)'!D11 -> 4.0733456 | E46: ='CF (Funds)'!E11 -> 0 | G46: =SUM(D46:F46) -> 4.0733456 | H46: Fund
B47: ='CF (Funds)'!B12 -> Sinovation Disrupt Fund, L.P. | C47: ='CF (Funds)'!C12 -> 44554 | D47: ='CF (Funds)'!D12 -> 0 | E47: ='CF (Funds)'!E12 -> 0.139694 | G47: =SUM(D47:F47) -> 0.139694 | H47: Fund
B48: ='CF (Funds)'!B13 -> Sinovation Disrupt Fund, L.P. | C48: ='CF (Funds)'!C13 -> 44703 | D48: ='CF (Funds)'!D13 -> 5.673074 | E48: ='CF (Funds)'!E13 -> 0 | G48: =SUM(D48:F48) -> 5.673074 | H48: Fund
B49: ='CF (Funds)'!B14 -> Sinovation Disrupt Fund, L.P. | C49: ='CF (Funds)'!C14 -> 44703 | D49: ='CF (Funds)'!D14 -> 0 | E49: ='CF (Funds)'!E14 -> 0.227786 | G49: =SUM(D49:F49) -> 0.227786 | H49: Fund
... B73: ='CF (Funds)'!B38 -> Acies Investments Fund I, L.P. | C73: ='CF (Funds)'!C38 -> 44707 | D73: ='CF (Funds)'!D38 -> -3.388275 | E73: ='CF (Funds)'!E38 -> 0 | G73: =SUM(D73:F73) -> -3.388275 | H73: Fund
B74: Jollychic Holding Limited | C74: =$C$4 -> 44834 | F74: =VLOOKUP(B74,NAV!$B$9:$D$39,3,0) -> 0 | G74: =SUM(D74:F74) -> 0
B75: Mena Mobile Inc | C75: =$C$4 -> 44834 | F75: =VLOOKUP(B75,NAV!$B$9:$D$39,3,0) -> 3.1 | G75: =SUM(D75:F75) -> 3.1
B76: Flyr Inc | C76: =$C$4 -> 44834 | F76: =VLOOKUP(B76,NAV!$B$9:$D$39,3,0) -> 78.08223 | G76: =SUM(D76:F76) -> 78.08223
B77: Esyasoft Holding | C77: =$C$4 -> 44834 | F77: =VLOOKUP(B77,NAV!$B$9:$D$39,3,0) -> 0 | G77: =SUM(D77:F77) -> 0
B78: Beyond Limits | C78: =$C$4 -> 44834 | F78: =VLOOKUP(B78,NAV!$B$9:$D$39,3,0) -> 91.00154 | G78: =SUM(D78:F78) -> 91.00154
B79: ONT plc | C79: =$C$4 -> 44834 | F79: =VLOOKUP(B79,NAV!$B$9:$D$39,3,0) -> 125.96279 | G79: =SUM(D79:F79) -> 125.96279
B80: Heygears | C80: =$C$4 -> 44834 | F80: =VLOOKUP(B80,NAV!$B$9:$D$39,3,0) -> 136.64 | G80: =SUM(D80:F80) -> 136.64
B81: Jysan Technologies | C81: =$C$4 -> 44834 | F81: =VLOOKUP(B81,NAV!$B$9:$D$39,3,0) -> 20 | G81: =SUM(D81:F81) -> 20
B82: Cerebras Systems Inc | C82: =$C$4 -> 44834 | F82: =VLOOKUP(B82,NAV!$B$9:$D$39,3,0) -> 39.999983 | G82: =SUM(D82:F82) -> 39.999983
B83: Endless Studios LLC | C83: =$C$4 -> 44834 | F83: =VLOOKUP(B83,NAV!$B$9:$D$39,3,0) -> 3 | G83: =SUM(D83:F83) -> 3
B84: Instadeep Limited | C84: =$C$4 -> 44834 | F84: =VLOOKUP(B84,NAV!$B$9:$D$39,3,0) -> 5.0237202 | G84: =SUM(D84:F84) -> 5.0237202
B85: X-fusion | C85: =$C$4 -> 44834 | F85: =VLOOKUP(B85,NAV!$B$9:$D$39,3,0) -> 493.50096 | G85: =SUM(D85:F85) -> 493.50096
... B96: Acies Investments Fund I, L.P. | C96: =$C$4 -> 44834 | F96: =VLOOKUP(B96,NAV!$B$9:$D$39,3,0) -> 10.343447 | G96: =SUM(D96:F96) -> 10.343447

Sheet 4.1
F2: IRR - Select (All Investments, includes Equity, Debt, Funds)
F4: Date of NAV | G4: =D!D2 -> 44834
F6: (in USD, Mn) | Q6: (in USD, Mn)
B7: Portfolio | F7: Investment | G7: Type | H7: Geograhpy | I7: Vintage | J7: Payment date | K7: Contribution | L7: Distributions | M7: Remaining Value | N7: Combined | Q7: Investment | R7: Contribution | S7: Distributions | T7: Remaining Value | U7: Combined | X7: Count | Y7: Committed | Z7: Invested | AA7: Remaining | AB7: Distributions | AC7: Residual Value | AD7: IRR | AE7: TVPI | AF7: RPI | AG7: DPI
B8: Jollychic Holding Limited | C8: Asia-China | F8: Jollychic Holding Limited | G8: Equity | H8: =VLOOKUP(F8,'5. Geo'!$B$3:$F$26,5,0) -> Asia-China | I8: =VLOOKUP(F8,'5. Geo'!$B$3:$F$26,2,0) -> 2019 | J8: 43470 | K8: ='CF (Equity, Debt)'!E4 -> -30 | L8: ='CF (Equity, Debt)'!F4 -> 0 | N8: =SUM(K8:M8) -> -30 | P8: =IF($C$8=H8,1,0) -> 1 | Q8: Jollychic Holding Limited | R8: =$P8*K8 -> -30 | S8: =$P8*L8 -> 0 | T8: =$P8*M8 -> 0 | U8: =$P8*N8 -> -30
B9: Mena Mobile Inc | C9: USA | F9: Jollychic Holding Limited | G9: Equity | H9: =VLOOKUP(F9,'5. Geo'!$B$3:$F$26,5,0) -> Asia-China | I9: =VLOOKUP(F9,'5. Geo'!$B$3:$F$26,2,0) -> 2019 | J9: 43724 | K9: ='CF (Equity, Debt)'!E5 -> -20 | L9: ='CF (Equity, Debt)'!F5 -> 0 | N9: =SUM(K9:M9) -> -20 | P9: =IF($C$8=H9,1,0) -> 1 | Q9: Jollychic Holding Limited | R9: =$P9*K9 -> -20 | S9: =$P9*L9 -> 0 | T9: =$P9*M9 -> 0 | U9: =$P9*N9 -> -20 | X9: =SUM(P74:P97) -> 8 | Z9: =-SUM(R8:R99) -> 1528.8598 | AB9: =SUM(S8:S99) -> 1.4717893 | AC9: =SUM(T8:T99) -> 1591.9989 | AD9: =XIRR(U8:U110,J8:J110,0.1) -> 0.060739759 | AE9: =(AB9+AC9)/Z9 -> 1.0422608 | AF9: =AC9/Z9 -> 1.0412981 | AG9: =AB9/Z9 -> 0.00096267121
B10: Flyr Inc | C10: Rest of Asia | F10: Jollychic Holding Limited | G10: Equity | H10: =VLOOKUP(F10,'5. Geo'!$B$3:$F$26,5,0) -> Asia-China | I10: =VLOOKUP(F10,'5. Geo'!$B$3:$F$26,2,0) -> 2019 | J10: 43724 | K10: ='CF (Equity, Debt)'!E6 -> -15 | L10: ='CF (Equity, Debt)'!F6 -> 0 | N10: =SUM(K10:M10) -> -15 | P10: =IF($C$8=H10,1,0) -> 1 | Q10: Jollychic Holding Limited | R10: =$P10*K10 -> -15 | S10: =$P10*L10 -> 0 | T10: =$P10*M10 -> 0 | U10: =$P10*N10 -> -15
B11: Esyasoft Holding | C11: Europe | F11: Mena Mobile Inc | G11: Equity | H11: =VLOOKUP(F11,'5. Geo'!$B$3:$F$26,5,0) -> Asia-China | I11: =VLOOKUP(F11,'5. Geo'!$B$3:$F$26,2,0) -> 2019 | J11: 43563 | K11: ='CF (Equity, Debt)'!E7 -> -8 | L11: ='CF (Equity, Debt)'!F7 -> 0 | N11: =SUM(K11:M11) -> -8 | P11: =IF($C$8=H11,1,0) -> 1 | Q11: Mena Mobile Inc | R11: =$P11*K11 -> -8 | S11: =$P11*L11 -> 0 | T11: =$P11*M11 -> 0 | U11: =$P11*N11 -> -8
B12: Beyond Limits | C12: MiddleEast | F12: Flyr Inc | G12: Equity | H12: =VLOOKUP(F12,'5. Geo'!$B$3:$F$26,5,0) -> USA | I12: =VLOOKUP(F12,'5. Geo'!$B$3:$F$26,2,0) -> 2019 | J12: 43570 | K12: ='CF (Equity, Debt)'!E8 -> -4.9999981 | L12: ='CF (Equity, Debt)'!F8 -> 0 | N12: =SUM(K12:M12) -> -4.9999981 | P12: =IF($C$8=H12,1,0) -> 0 | Q12: Flyr Inc | R12: =$P12*K12 -> 0 | S12: =$P12*L12 -> 0 | T12: =$P12*M12 -> 0 | U12: =$P12*N12 -> 0
B13: ONT plc | F13: Flyr Inc | G13: Equity | H13: =VLOOKUP(F13,'5. Geo'!$B$3:$F$26,5,0) -> USA | I13: =VLOOKUP(F13,'5. Geo'!$B$3:$F$26,2,0) -> 2019 | J13: 43915 | K13: ='CF (Equity, Debt)'!E9 -> -5.0000019 | L13: ='CF (Equity, Debt)'!F9 -> 0 | N13: =SUM(K13:M13) -> -5.0000019 | P13: =IF($C$8=H13,1,0) -> 0 | Q13: Flyr Inc | R13: =$P13*K13 -> 0 | S13: =$P13*L13 -> 0 | T13: =$P13*M13 -> 0 | U13: =$P13*N13 -> 0
B14: Heygears | F14: Esyasoft Holding | G14: Equity | H14: =VLOOKUP(F14,'5. Geo'!$B$3:$F$26,5,0) -> Rest of Asia | I14: =VLOOKUP(F14,'5. Geo'!$B$3:$F$26,2,0) -> 2020 | J14: 43870 | K14: ='CF (Equity, Debt)'!E10 -> -2.5 | L14: ='CF (Equity, Debt)'!F10 -> 0 | N14: =SUM(K14:M14) -> -2.5 | P14: =IF($C$8=H14,1,0) -> 0 | Q14: Esyasoft Holding | R14: =$P14*K14 -> 0 | S14: =$P14*L14 -> 0 | T14: =$P14*M14 -> 0 | U14: =$P14*N14 -> 0
B15: Jysan Technologies | F15: Beyond Limits | G15: Equity | H15: =VLOOKUP(F15,'5. Geo'!$B$3:$F$26,5,0) -> USA | I15: =VLOOKUP(F15,'5. Geo'!$B$3:$F$26,2,0) -> 2020 | J15: 43879 | K15: ='CF (Equity, Debt)'!E11 -> -20 | L15: ='CF (Equity, Debt)'!F11 -> 0 | N15: =SUM(K15:M15) -> -20 | P15: =IF($C$8=H15,1,0) -> 0 | Q15: Beyond Limits | R15: =$P15*K15 -> 0 | S15: =$P15*L15 -> 0 | T15: =$P15*M15 -> 0 | U15: =$P15*N15 -> 0
B16: Cerebras Systems Inc | F16: Beyond Limits | G16: Equity | H16: =VLOOKUP(F16,'5. Geo'!$B$3:$F$26,5,0) -> USA | I16: =VLOOKUP(F16,'5. Geo'!$B$3:$F$26,2,0) -> 2020 | J16: 43921 | K16: ='CF (Equity, Debt)'!E12 -> -30 | L16: ='CF (Equity, Debt)'!F12 -> 0 | N16: =SUM(K16:M16) -> -30 | P16: =IF($C$8=H16,1,0) -> 0 | Q16: Beyond Limits | R16: =$P16*K16 -> 0 | S16: =$P16*L16 -> 0 | T16: =$P16*M16 -> 0 | U16: =$P16*N16 -> 0
B17: Endless Studios LLC | F17: Beyond Limits | G17: Equity | H17: =VLOOKUP(F17,'5. Geo'!$B$3:$F$26,5,0) -> USA | I17: =VLOOKUP(F17,'5. Geo'!$B$3:$F$26,2,0) -> 2020 | J17: 43989 | K17: ='CF (Equity, Debt)'!E13 -> -30 | L17: ='CF (Equity, Debt)'!F13 -> 0 | N17: =SUM(K17:M17) -> -30 | P17: =IF($C$8=H17,1,0) -> 0 | Q17: Beyond Limits | R17: =$P17*K17 -> 0 | S17: =$P17*L17 -> 0 | T17: =$P17*M17 -> 0 | U17: =$P17*N17 -> 0
B18: Instadeep Limited | F18: Beyond Limits | G18: Equity | H18: =VLOOKUP(F18,'5. Geo'!$B$3:$F$26,5,0) -> USA | I18: =VLOOKUP(F18,'5. Geo'!$B$3:$F$26,2,0) -> 2020 | J18: 44103 | K18: ='CF (Equity, Debt)'!E14 -> -10 | L18: ='CF (Equity, Debt)'!F14 -> 0 | N18: =SUM(K18:M18) -> -10 | P18: =IF($C$8=H18,1,0) -> 0 | Q18: Beyond Limits | R18: =$P18*K18 -> 0 | S18: =$P18*L18 -> 0 | T18: =$P18*M18 -> 0 | U18: =$P18*N18 -> 0
B19: X-fusion | F19: ONT plc | G19: Equity | H19: =VLOOKUP(F19,'5. Geo'!$B$3:$F$26,5,0) -> Europe | I19: =VLOOKUP(F19,'5. Geo'!$B$3:$F$26,2,0) -> 2020 | J19: 43968 | K19: ='CF (Equity, Debt)'!E15 -> -50 | L19: ='CF (Equity, Debt)'!F15 -> 0 | N19: =SUM(K19:M19) -> -50 | P19: =IF($C$8=H19,1,0) -> 0 | Q19: ONT plc | R19: =$P19*K19 -> 0 | S19: =$P19*L19 -> 0 | T19: =$P19*M19 -> 0 | U19: =$P19*N19 -> 0
B20: DriveNets | F20: ONT plc | G20: Equity | H20: =VLOOKUP(F20,'5. Geo'!$B$3:$F$26,5,0) -> Europe | I20: =VLOOKUP(F20,'5. Geo'!$B$3:$F$26,2,0) -> 2020 | J20: 44006 | K20: ='CF (Equity, Debt)'!E16 -> -27.268351 | L20: ='CF (Equity, Debt)'!F16 -> 0 | N20: =SUM(K20:M20) -> -27.268351 | P20: =IF($C$8=H20,1,0) -> 0 | Q20: ONT plc | R20: =$P20*K20 -> 0 | S20: =$P20*L20 -> 0 | T20: =$P20*M20 -> 0 | U20: =$P20*N20 -> 0
B21: vTv Therapeutics Inc. | F21: ONT plc | G21: Equity | H21: =VLOOKUP(F21,'5. Geo'!$B$3:$F$26,5,0) -> Europe | I21: =VLOOKUP(F21,'5. Geo'!$B$3:$F$26,2,0) -> 2020 | J21: 43837 | K21: ='CF (Equity, Debt)'!E17 -> -18.109441 | L21: ='CF (Equity, Debt)'!F17 -> 0 | N21: =SUM(K21:M21) -> -18.109441 | P21: =IF($C$8=H21,1,0) -> 0 | Q21: ONT plc | R21: =$P21*K21 -> 0 | S21: =$P21*L21 -> 0 | T21: =$P21*M21 -> 0 | U21: =$P21*N21 -> 0
B22: Honor Device Co Ltd | F22: ONT plc | G22: Equity | H22: =VLOOKUP(F22,'5. Geo'!$B$3:$F$26,5,0) -> Europe | I22: =VLOOKUP(F22,'5. Geo'!$B$3:$F$26,2,0) -> 2020 | J22: 43990 | K22: ='CF (Equity, Debt)'!E18 -> -34.851687 | L22: ='CF (Equity, Debt)'!F18 -> 0 | N22: =SUM(K22:M22) -> -34.851687 | P22: =IF($C$8=H22,1,0) -> 0 | Q22: ONT plc | R22: =$P22*K22 -> 0 | S22: =$P22*L22 -> 0 | T22: =$P22*M22 -> 0 | U22: =$P22*N22 -> 0
B23: Glass Earth Holdings LLC | F23: ONT plc | G23: Equity | H23: =VLOOKUP(F23,'5. Geo'!$B$3:$F$26,5,0) -> Europe | I23: =VLOOKUP(F23,'5. Geo'!$B$3:$F$26,2,0) -> 2020 | J23: 44315 | K23: ='CF (Equity, Debt)'!E19 -> -11.24078 | L23: ='CF (Equity, Debt)'!F19 -> 0 | N23: =SUM(K23:M23) -> -11.24078 | P23: =IF($C$8=H23,1,0) -> 0 | Q23: ONT plc | R23: =$P23*K23 -> 0 | S23: =$P23*L23 -> 0 | T23: =$P23*M23 -> 0 | U23: =$P23*N23 -> 0
B24: Mena Mobile Inc | F24: Heygears | G24: Equity | H24: =VLOOKUP(F24,'5. Geo'!$B$3:$F$26,5,0) -> Asia-China | I24: =VLOOKUP(F24,'5. Geo'!$B$3:$F$26,2,0) -> 2020 | J24: 44166 | K24: ='CF (Equity, Debt)'!E20 -> -60 | L24: ='CF (Equity, Debt)'!F20 -> 0 | N24: =SUM(K24:M24) -> -60 | P24: =IF($C$8=H24,1,0) -> 1 | Q24: Heygears | R24: =$P24*K24 -> -60 | S24: =$P24*L24 -> 0 | T24: =$P24*M24 -> 0 | U24: =$P24*N24 -> -60
... B30: Acies Investments Fund I, L.P. | F30: DriveNets | G30: Equity | H30: =VLOOKUP(F30,'5. Geo'!$B$3:$F$26,5,0) -> MiddleEast | I30: =VLOOKUP(F30,'5. Geo'!$B$3:$F$26,2,0) -> 2022 | J30: 44643 | K30: ='CF (Equity, Debt)'!E26 -> -200 | L30: ='CF (Equity, Debt)'!F26 -> 0 | N30: =SUM(K30:M30) -> -200 | P30: =IF($C$8=H30,1,0) -> 0 | Q30: DriveNets | R30: =$P30*K30 -> 0 | S30: =$P30*L30 -> 0 | T30: =$P30*M30 -> 0 | U30: =$P30*N30 -> 0
F31: DriveNets | G31: Equity | H31: =VLOOKUP(F31,'5. Geo'!$B$3:$F$26,5,0) -> MiddleEast | I31: =VLOOKUP(F31,'5. Geo'!$B$3:$F$26,2,0) -> 2022 | J31: 44680 | K31: ='CF (Equity, Debt)'!E27 -> -100 | L31: ='CF (Equity, Debt)'!F27 -> 0 | N31: =SUM(K31:M31) -> -100 | P31: =IF($C$8=H31,1,0) -> 0 | Q31: DriveNets | R31: =$P31*K31 -> 0 | S31: =$P31*L31 -> 0 | T31: =$P31*M31 -> 0 | U31: =$P31*N31 -> 0
F32: Esyasoft Holding | G32: Equity | H32: =VLOOKUP(F32,'5. Geo'!$B$3:$F$26,5,0) -> Rest of Asia | I32: =VLOOKUP(F32,'5. Geo'!$B$3:$F$26,2,0) -> 2020 | J32: 44691 | K32: ='CF (Equity, Debt)'!E28 -> 0 | L32: ='CF (Equity, Debt)'!F28 -> 5 | N32: =SUM(K32:M32) -> 5 | P32: =IF($C$8=H32,1,0) -> 0 | Q32: Esyasoft Holding | R32: =$P32*K32 -> 0 | S32: =$P32*L32 -> 0 | T32: =$P32*M32 -> 0 | U32: =$P32*N32 -> 0
F33: vTv Therapeutics Inc. | G33: Equity | H33: =VLOOKUP(F33,'5. Geo'!$B$3:$F$26,5,0) -> USA | I33: =VLOOKUP(F33,'5. Geo'!$B$3:$F$26,2,0) -> 2022 | J33: 44712 | K33: ='CF (Equity, Debt)'!E29 -> -12.5 | L33: ='CF (Equity, Debt)'!F29 -> 0 | N33: =SUM(K33:M33) -> -12.5 | P33: =IF($C$8=H33,1,0) -> 0 | Q33: vTv Therapeutics Inc. | R33: =$P33*K33 -> 0 | S33: =$P33*L33 -> 0 | T33: =$P33*M33 -> 0 | U33: =$P33*N33 -> 0
F34: Honor Device Co Ltd | G34: Equity | H34: =VLOOKUP(F34,'5. Geo'!$B$3:$F$26,5,0) -> Asia-China | I34: =VLOOKUP(F34,'5. Geo'!$B$3:$F$26,2,0) -> 2022 | J34: 44769 | K34: ='CF (Equity, Debt)'!E30 -> -800 | L34: ='CF (Equity, Debt)'!F30 -> 0 | N34: =SUM(K34:M34) -> -800 | P34: =IF($C$8=H34,1,0) -> 1 | Q34: Honor Device Co Ltd | R34: =$P34*K34 -> -800 | S34: =$P34*L34 -> 0 | T34: =$P34*M34 -> 0 | U34: =$P34*N34 -> -800
F35: Glass Earth Holdings LLC | G35: Debt | H35: =VLOOKUP(F35,'5. Geo'!$B$3:$F$26,5,0) -> USA | I35: =VLOOKUP(F35,'5. Geo'!$B$3:$F$26,2,0) -> 2019 | J35: 43635 | K35: ='CF (Equity, Debt)'!E33 -> -8 | L35: ='CF (Equity, Debt)'!F33 -> 0 | N35: =SUM(K35:M35) -> -8 | P35: =IF($C$8=H35,1,0) -> 0 | Q35: Glass Earth Holdings LLC | R35: =$P35*K35 -> 0 | S35: =$P35*L35 -> 0 | T35: =$P35*M35 -> 0 | U35: =$P35*N35 -> 0
F36: Mena Mobile Inc | G36: Debt | H36: =VLOOKUP(F36,'5. Geo'!$B$3:$F$26,5,0) -> Asia-China | I36: =VLOOKUP(F36,'5. Geo'!$B$3:$F$26,2,0) -> 2019 | J36: 44293 | K36: ='CF (Equity, Debt)'!E34 -> -2.353982 | L36: ='CF (Equity, Debt)'!F34 -> 0 | N36: =SUM(K36:M36) -> -2.353982 | P36: =IF($C$8=H36,1,0) -> 1 | Q36: Mena Mobile Inc | R36: =$P36*K36 -> -2.353982 | S36: =$P36*L36 -> 0 | T36: =$P36*M36 -> 0 | U36: =$P36*N36 -> -2.353982
F37: Esyasoft Holding | G37: Debt | H37: =VLOOKUP(F37,'5. Geo'!$B$3:$F$26,5,0) -> Rest of Asia | I37: =VLOOKUP(F37,'5. Geo'!$B$3:$F$26,2,0) -> 2020 | J37: 44384 | K37: ='CF (Equity, Debt)'!E35 -> -0.411765 | L37: ='CF (Equity, Debt)'!F35 -> 0 | N37: =SUM(K37:M37) -> -0.411765 | P37: =IF($C$8=H37,1,0) -> 0 | Q37: Esyasoft Holding | R37: =$P37*K37 -> 0 | S37: =$P37*L37 -> 0 | T37: =$P37*M37 -> 0 | U37: =$P37*N37 -> 0
F38: Sinovation Disrupt Fund, L.P. | G38: Fund | H38: =VLOOKUP(F38,'5. Geo'!$B$3:$F$26,5,0) -> Asia-China | I38: =VLOOKUP(F38,'5. Geo'!$B$3:$F$26,2,0) -> 2020 | J38: 18/11/2020 | K38: ='CF (Funds)'!D3 -> -10.5 | L38: ='CF (Funds)'!E3 -> 0 | N38: =SUM(K38:M38) -> -10.5 | P38: =IF($C$8=H38,1,0) -> 1 | Q38: Sinovation Disrupt Fund, L.P. | R38: =$P38*K38 -> -10.5 | S38: =$P38*L38 -> 0 | T38: =$P38*M38 -> 0 | U38: =$P38*N38 -> -10.5
F39: Sinovation Disrupt Fund, L.P. | G39: Fund | H39: =VLOOKUP(F39,'5. Geo'!$B$3:$F$26,5,0) -> Asia-China | I39: =VLOOKUP(F39,'5. Geo'!$B$3:$F$26,2,0) -> 2020 | J39: 44238 | K39: ='CF (Funds)'!D4 -> 4.214027 | L39: ='CF (Funds)'!E4 -> 0 | N39: =SUM(K39:M39) -> 4.214027 | P39: =IF($C$8=H39,1,0) -> 1 | Q39: Sinovation Disrupt Fund, L.P. | R39: =$P39*K39 -> 4.214027 | S39: =$P39*L39 -> 0 | T39: =$P39*M39 -> 0 | U39: =$P39*N39 -> 4.214027
F40: Sinovation Disrupt Fund, L.P. | G40: Fund | H40: =VLOOKUP(F40,'5. Geo'!$B$3:$F$26,5,0) -> Asia-China | I40: =VLOOKUP(F40,'5. Geo'!$B$3:$F$26,2,0) -> 2020 | J40: 44238 | K40: ='CF (Funds)'!D5 -> 0 | L40: ='CF (Funds)'!E5 -> 0.05044835 | N40: =SUM(K40:M40) -> 0.05044835 | P40: =IF($C$8=H40,1,0) -> 1 | Q40: Sinovation Disrupt Fund, L.P. | R40: =$P40*K40 -> 0 | S40: =$P40*L40 -> 0.05044835 | T40: =$P40*M40 -> 0 | U40: =$P40*N40 -> 0.05044835
F41: Sinovation Disrupt Fund, L.P. | G41: Fund | H41: =VLOOKUP(F41,'5. Geo'!$B$3:$F$26,5,0) -> Asia-China | I41: =VLOOKUP(F41,'5. Geo'!$B$3:$F$26,2,0) -> 2020 | J41: 44285 | K41: ='CF (Funds)'!D6 -> -6.433746 | L41: ='CF (Funds)'!E6 -> 0 | N41: =SUM(K41:M41) -> -6.433746 | P41: =IF($C$8=H41,1,0) -> 1 | Q41: Sinovation Disrupt Fund, L.P. | R41: =$P41*K41 -> -6.433746 | S41: =$P41*L41 -> 0 | T41: =$P41*M41 -> 0 | U41: =$P41*N41 -> -6.433746
F42: Sinovation Disrupt Fund, L.P. | G42: Fund | H42: =VLOOKUP(F42,'5. Geo'!$B$3:$F$26,5,0) -> Asia-China | I42: =VLOOKUP(F42,'5. Geo'!$B$3:$F$26,2,0) -> 2020 | J42: 44269 | K42: ='CF (Funds)'!D7 -> 1.1352074 | L42: ='CF (Funds)'!E7 -> 0 | N42: =SUM(K42:M42) -> 1.1352074 | P42: =IF($C$8=H42,1,0) -> 1 | Q42: Sinovation Disrupt Fund, L.P. | R42: =$P42*K42 -> 1.1352074 | S42: =$P42*L42 -> 0 | T42: =$P42*M42 -> 0 | U42: =$P42*N42 -> 1.1352074
F43: Sinovation Disrupt Fund, L.P. | G43: Fund | H43: =VLOOKUP(F43,'5. Geo'!$B$3:$F$26,5,0) -> Asia-China | I43: =VLOOKUP(F43,'5. Geo'!$B$3:$F$26,2,0) -> 2020 | J43: 44269 | K43: ='CF (Funds)'!D8 -> 0 | L43: ='CF (Funds)'!E8 -> 0.0259 | N43: =SUM(K43:M43) -> 0.0259 | P43: =IF($C$8=H43,1,0) -> 1 | Q43: Sinovation Disrupt Fund, L.P. | R43: =$P43*K43 -> 0 | S43: =$P43*L43 -> 0.0259 | T43: =$P43*M43 -> 0 | U43: =$P43*N43 -> 0.0259
F44: Sinovation Disrupt Fund, L.P. | G44: Fund | H44: =VLOOKUP(F44,'5. Geo'!$B$3:$F$26,5,0) -> Asia-China | I44: =VLOOKUP(F44,'5. Geo'!$B$3:$F$26,2,0) -> 2020 | J44: 44483 | K44: ='CF (Funds)'!D9 -> -7.567138 | L44: ='CF (Funds)'!E9 -> 0 | N44: =SUM(K44:M44) -> -7.567138 | P44: =IF($C$8=H44,1,0) -> 1 | Q44: Sinovation Disrupt Fund, L.P. | R44: =$P44*K44 -> -7.567138 | S44: =$P44*L44 -> 0 | T44: =$P44*M44 -> 0 | U44: =$P44*N44 -> -7.567138
F45: Sinovation Disrupt Fund, L.P. | G45: Fund | H45: =VLOOKUP(F45,'5. Geo'!$B$3:$F$26,5,0) -> Asia-China | I45: =VLOOKUP(F45,'5. Geo'!$B$3:$F$26,2,0) -> 2020 | J45: 44554 | K45: ='CF (Funds)'!D10 -> -7.385016 | L45: ='CF (Funds)'!E10 -> 0 | N45: =SUM(K45:M45) -> -7.385016 | P45: =IF($C$8=H45,1,0) -> 1 | Q45: Sinovation Disrupt Fund, L.P. | R45: =$P45*K45 -> -7.385016 | S45: =$P45*L45 -> 0 | T45: =$P45*M45 -> 0 | U45: =$P45*N45 -> -7.385016
F46: Sinovation Disrupt Fund, L.P. | G46: Fund | H46: =VLOOKUP(F46,'5. Geo'!$B$3:$F$26,5,0) -> Asia-China | I46: =VLOOKUP(F46,'5. Geo'!$B$3:$F$26,2,0) -> 2020 | J46: 44554 | K46: ='CF (Funds)'!D11 -> 4.0733456 | L46: ='CF (Funds)'!E11 -> 0 | N46: =SUM(K46:M46) -> 4.0733456 | P46: =IF($C$8=H46,1,0) -> 1 | Q46: Sinovation Disrupt Fund, L.P. | R46: =$P46*K46 -> 4.0733456 | S46: =$P46*L46 -> 0 | T46: =$P46*M46 -> 0 | U46: =$P46*N46 -> 4.0733456
F47: Sinovation Disrupt Fund, L.P. | G47: Fund | H47: =VLOOKUP(F47,'5. Geo'!$B$3:$F$26,5,0) -> Asia-China | I47: =VLOOKUP(F47,'5. Geo'!$B$3:$F$26,2,0) -> 2020 | J47: 44554 | K47: ='CF (Funds)'!D12 -> 0 | L47: ='CF (Funds)'!E12 -> 0.139694 | N47: =SUM(K47:M47) -> 0.139694 | P47: =IF($C$8=H47,1,0) -> 1 | Q47: Sinovation Disrupt Fund, L.P. | R47: =$P47*K47 -> 0 | S47: =$P47*L47 -> 0.139694 | T47: =$P47*M47 -> 0 | U47: =$P47*N47 -> 0.139694
F48: Sinovation Disrupt Fund, L.P. | G48: Fund | H48: =VLOOKUP(F48,'5. Geo'!$B$3:$F$26,5,0) -> Asia-China | I48: =VLOOKUP(F48,'5. Geo'!$B$3:$F$26,2,0) -> 2020 | J48: 44703 | K48: ='CF (Funds)'!D13 -> 5.673074 | L48: ='CF (Funds)'!E13 -> 0 | N48: =SUM(K48:M48) -> 5.673074 | P48: =IF($C$8=H48,1,0) -> 1 | Q48: Sinovation Disrupt Fund, L.P. | R48: =$P48*K48 -> 5.673074 | S48: =$P48*L48 -> 0 | T48: =$P48*M48 -> 0 | U48: =$P48*N48 -> 5.673074
F49: Sinovation Disrupt Fund, L.P. | G49: Fund | H49: =VLOOKUP(F49,'5. Geo'!$B$3:$F$26,5,0) -> Asia-China | I49: =VLOOKUP(F49,'5. Geo'!$B$3:$F$26,2,0) -> 2020 | J49: 44703 | K49: ='CF (Funds)'!D14 -> 0 | L49: ='CF (Funds)'!E14 -> 0.227786 | N49: =SUM(K49:M49) -> 0.227786 | P49: =IF($C$8=H49,1,0) -> 1 | Q49: Sinovation Disrupt Fund, L.P. | R49: =$P49*K49 -> 0 | S49: =$P49*L49 -> 0.227786 | T49: =$P49*M49 -> 0 | U49: =$P49*N49 -> 0.227786
F50: North Summit Capital Fund | G50: Fund | H50: =VLOOKUP(F50,'5. Geo'!$B$3:$F$26,5,0) -> Asia-China | I50: =VLOOKUP(F50,'5. Geo'!$B$3:$F$26,2,0) -> 2020 | J50: 19/07/2019 | K50: ='CF (Funds)'!D15 -> -3 | L50: ='CF (Funds)'!E15 -> 0 | N50: =SUM(K50:M50) -> -3 | P50: =IF($C$8=H50,1,0) -> 1 | Q50: North Summit Capital Fund | R50: =$P50*K50 -> -3 | S50: =$P50*L50 -> 0 | T50: =$P50*M50 -> 0 | U50: =$P50*N50 -> -3
F51: North Summit Capital Fund | G51: Fund | H51: =VLOOKUP(F51,'5. Geo'!$B$3:$F$26,5,0) -> Asia-China | I51: =VLOOKUP(F51,'5. Geo'!$B$3:$F$26,2,0) -> 2020 | J51: 43983 | K51: ='CF (Funds)'!D16 -> -4.485 | L51: ='CF (Funds)'!E16 -> 0 | N51: =SUM(K51:M51) -> -4.485 | P51: =IF($C$8=H51,1,0) -> 1 | Q51: North Summit Capital Fund | R51: =$P51*K51 -> -4.485 | S51: =$P51*L51 -> 0 | T51: =$P51*M51 -> 0 | U51: =$P51*N51 -> -4.485
F52: North Summit Capital Fund | G52: Fund | H52: =VLOOKUP(F52,'5. Geo'!$B$3:$F$26,5,0) -> Asia-China | I52: =VLOOKUP(F52,'5. Geo'!$B$3:$F$26,2,0) -> 2020 | J52: 18/02/2020 | K52: ='CF (Funds)'!D17 -> -9.50975 | L52: ='CF (Funds)'!E17 -> 0 | N52: =SUM(K52:M52) -> -9.50975 | P52: =IF($C$8=H52,1,0) -> 1 | Q52: North Summit Capital Fund | R52: =$P52*K52 -> -9.50975 | S52: =$P52*L52 -> 0 | T52: =$P52*M52 -> 0 | U52: =$P52*N52 -> -9.50975
F53: North Summit Capital Fund | G53: Fund | H53: =VLOOKUP(F53,'5. Geo'!$B$3:$F$26,5,0) -> Asia-China | I53: =VLOOKUP(F53,'5. Geo'!$B$3:$F$26,2,0) -> 2020 | J53: 13/04/2020 | K53: ='CF (Funds)'!D18 -> -41.3 | L53: ='CF (Funds)'!E18 -> 0 | N53: =SUM(K53:M53) -> -41.3 | P53: =IF($C$8=H53,1,0) -> 1 | Q53: North Summit Capital Fund | R53: =$P53*K53 -> -41.3 | S53: =$P53*L53 -> 0 | T53: =$P53*M53 -> 0 | U53: =$P53*N53 -> -41.3
F54: North Summit Capital Fund | G54: Fund | H54: =VLOOKUP(F54,'5. Geo'!$B$3:$F$26,5,0) -> Asia-China | I54: =VLOOKUP(F54,'5. Geo'!$B$3:$F$26,2,0) -> 2020 | J54: 16/11/2020 | K54: ='CF (Funds)'!D19 -> 9.95 | L54: ='CF (Funds)'!E19 -> 0 | N54: =SUM(K54:M54) -> 9.95 | P54: =IF($C$8=H54,1,0) -> 1 | Q54: North Summit Capital Fund | R54: =$P54*K54 -> 9.95 | S54: =$P54*L54 -> 0 | T54: =$P54*M54 -> 0 | U54: =$P54*N54 -> 9.95
F55: North Summit Capital Fund | G55: Fund | H55: =VLOOKUP(F55,'5. Geo'!$B$3:$F$26,5,0) -> Asia-China | I55: =VLOOKUP(F55,'5. Geo'!$B$3:$F$26,2,0) -> 2020 | J55: 16/11/2020 | K55: ='CF (Funds)'!D20 -> -10.455 | L55: ='CF (Funds)'!E20 -> 0 | N55: =SUM(K55:M55) -> -10.455 | P55: =IF($C$8=H55,1,0) -> 1 | Q55: North Summit Capital Fund | R55: =$P55*K55 -> -10.455 | S55: =$P55*L55 -> 0 | T55: =$P55*M55 -> 0 | U55: =$P55*N55 -> -10.455
F56: North Summit Capital Fund | G56: Fund | H56: =VLOOKUP(F56,'5. Geo'!$B$3:$F$26,5,0) -> Asia-China | I56: =VLOOKUP(F56,'5. Geo'!$B$3:$F$26,2,0) -> 2020 | J56: 31/12/2020 | K56: ='CF (Funds)'!D21 -> 4.975 | L56: ='CF (Funds)'!E21 -> 0 | N56: =SUM(K56:M56) -> 4.975 | P56: =IF($C$8=H56,1,0) -> 1 | Q56: North Summit Capital Fund | R56: =$P56*K56 -> 4.975 | S56: =$P56*L56 -> 0 | T56: =$P56*M56 -> 0 | U56: =$P56*N56 -> 4.975
F57: North Summit Capital Fund | G57: Fund | H57: =VLOOKUP(F57,'5. Geo'!$B$3:$F$26,5,0) -> Asia-China | I57: =VLOOKUP(F57,'5. Geo'!$B$3:$F$26,2,0) -> 2020 | J57: 31/12/2020 | K57: ='CF (Funds)'!D22 -> -3.452293 | L57: ='CF (Funds)'!E22 -> 0 | N57: =SUM(K57:M57) -> -3.452293 | P57: =IF($C$8=H57,1,0) -> 1 | Q57: North Summit Capital Fund | R57: =$P57*K57 -> -3.452293 | S57: =$P57*L57 -> 0 | T57: =$P57*M57 -> 0 | U57: =$P57*N57 -> -3.452293
F58: North Summit Capital Fund | G58: Fund | H58: =VLOOKUP(F58,'5. Geo'!$B$3:$F$26,5,0) -> Asia-China | I58: =VLOOKUP(F58,'5. Geo'!$B$3:$F$26,2,0) -> 2020 | J58: 31/12/2020 | K58: ='CF (Funds)'!D23 -> 0 | L58: ='CF (Funds)'!E23 -> 0.582902 | N58: =SUM(K58:M58) -> 0.582902 | P58: =IF($C$8=H58,1,0) -> 1 | Q58: North Summit Capital Fund | R58: =$P58*K58 -> 0 | S58: =$P58*L58 -> 0.582902 | T58: =$P58*M58 -> 0 | U58: =$P58*N58 -> 0.582902
F59: North Summit Capital Fund | G59: Fund | H59: =VLOOKUP(F59,'5. Geo'!$B$3:$F$26,5,0) -> Asia-China | I59: =VLOOKUP(F59,'5. Geo'!$B$3:$F$26,2,0) -> 2020 | J59: 44370 | K59: ='CF (Funds)'!D24 -> -5.97 | L59: ='CF (Funds)'!E24 -> 0 | N59: =SUM(K59:M59) -> -5.97 | P59: =IF($C$8=H59,1,0) -> 1 | Q59: North Summit Capital Fund | R59: =$P59*K59 -> -5.97 | S59: =$P59*L59 -> 0 | T59: =$P59*M59 -> 0 | U59: =$P59*N59 -> -5.97
F60: North Summit Capital Fund | G60: Fund | H60: =VLOOKUP(F60,'5. Geo'!$B$3:$F$26,5,0) -> Asia-China | I60: =VLOOKUP(F60,'5. Geo'!$B$3:$F$26,2,0) -> 2020 | J60: 44400 | K60: ='CF (Funds)'!D25 -> -0.75 | L60: ='CF (Funds)'!E25 -> 0 | N60: =SUM(K60:M60) -> -0.75 | P60: =IF($C$8=H60,1,0) -> 1 | Q60: North Summit Capital Fund | R60: =$P60*K60 -> -0.75 | S60: =$P60*L60 -> 0 | T60: =$P60*M60 -> 0 | U60: =$P60*N60 -> -0.75
F61: North Summit Capital Fund | G61: Fund | H61: =VLOOKUP(F61,'5. Geo'!$B$3:$F$26,5,0) -> Asia-China | I61: =VLOOKUP(F61,'5. Geo'!$B$3:$F$26,2,0) -> 2020 | J61: 44400 | K61: ='CF (Funds)'!D26 -> 0 | L61: ='CF (Funds)'!E26 -> 0.445059 | N61: =SUM(K61:M61) -> 0.445059 | P61: =IF($C$8=H61,1,0) -> 1 | Q61: North Summit Capital Fund | R61: =$P61*K61 -> 0 | S61: =$P61*L61 -> 0.445059 | T61: =$P61*M61 -> 0 | U61: =$P61*N61 -> 0.445059
F62: North Summit Capital Fund | G62: Fund | H62: =VLOOKUP(F62,'5. Geo'!$B$3:$F$26,5,0) -> Asia-China | I62: =VLOOKUP(F62,'5. Geo'!$B$3:$F$26,2,0) -> 2020 | J62: 44554 | K62: ='CF (Funds)'!D27 -> 1.78239 | L62: ='CF (Funds)'!E27 -> 0 | N62: =SUM(K62:M62) -> 1.78239 | P62: =IF($C$8=H62,1,0) -> 1 | Q62: North Summit Capital Fund | R62: =$P62*K62 -> 1.78239 | S62: =$P62*L62 -> 0 | T62: =$P62*M62 -> 0 | U62: =$P62*N62 -> 1.78239
F63: North Summit Capital Fund | G63: Fund | H63: =VLOOKUP(F63,'5. Geo'!$B$3:$F$26,5,0) -> Asia-China | I63: =VLOOKUP(F63,'5. Geo'!$B$3:$F$26,2,0) -> 2020 | J63: 44676 | K63: ='CF (Funds)'!D28 -> -21 | L63: ='CF (Funds)'!E28 -> 0 | N63: =SUM(K63:M63) -> -21 | P63: =IF($C$8=H63,1,0) -> 1 | Q63: North Summit Capital Fund | R63: =$P63*K63 -> -21 | S63: =$P63*L63 -> 0 | T63: =$P63*M63 -> 0 | U63: =$P63*N63 -> -21
F64: New Space Capital Fund I | G64: Fund | H64: =VLOOKUP(F64,'5. Geo'!$B$3:$F$26,5,0) -> Europe | I64: =VLOOKUP(F64,'5. Geo'!$B$3:$F$26,2,0) -> 2020 | J64: 44087 | K64: ='CF (Funds)'!D29 -> -20.917553 | L64: ='CF (Funds)'!E29 -> 0 | N64: =SUM(K64:M64) -> -20.917553 | P64: =IF($C$8=H64,1,0) -> 0 | Q64: New Space Capital Fund I | R64: =$P64*K64 -> 0 | S64: =$P64*L64 -> 0 | T64: =$P64*M64 -> 0 | U64: =$P64*N64 -> 0
F65: New Space Capital Fund I | G65: Fund | H65: =VLOOKUP(F65,'5. Geo'!$B$3:$F$26,5,0) -> Europe | I65: =VLOOKUP(F65,'5. Geo'!$B$3:$F$26,2,0) -> 2020 | J65: 44287 | K65: ='CF (Funds)'!D30 -> -0.21103182 | L65: ='CF (Funds)'!E30 -> 0 | N65: =SUM(K65:M65) -> -0.21103182 | P65: =IF($C$8=H65,1,0) -> 0 | Q65: New Space Capital Fund I | R65: =$P65*K65 -> 0 | S65: =$P65*L65 -> 0 | T65: =$P65*M65 -> 0 | U65: =$P65*N65 -> 0
F66: New Space Capital Fund I | G66: Fund | H66: =VLOOKUP(F66,'5. Geo'!$B$3:$F$26,5,0) -> Europe | I66: =VLOOKUP(F66,'5. Geo'!$B$3:$F$26,2,0) -> 2020 | J66: 44442 | K66: ='CF (Funds)'!D31 -> -0.23965473 | L66: ='CF (Funds)'!E31 -> 0 | N66: =SUM(K66:M66) -> -0.23965473 | P66: =IF($C$8=H66,1,0) -> 0 | Q66: New Space Capital Fund I | R66: =$P66*K66 -> 0 | S66: =$P66*L66 -> 0 | T66: =$P66*M66 -> 0 | U66: =$P66*N66 -> 0
F67: New Space Capital Fund I | G67: Fund | H67: =VLOOKUP(F67,'5. Geo'!$B$3:$F$26,5,0) -> Europe | I67: =VLOOKUP(F67,'5. Geo'!$B$3:$F$26,2,0) -> 2020 | J67: 44623 | K67: ='CF (Funds)'!D32 -> -0.25893585 | L67: ='CF (Funds)'!E32 -> 0 | N67: =SUM(K67:M67) -> -0.25893585 | P67: =IF($C$8=H67,1,0) -> 0 | Q67: New Space Capital Fund I | R67: =$P67*K67 -> 0 | S67: =$P67*L67 -> 0 | T67: =$P67*M67 -> 0 | U67: =$P67*N67 -> 0
F68: New Space Capital Fund I | G68: Fund | H68: =VLOOKUP(F68,'5. Geo'!$B$3:$F$26,5,0) -> Europe | I68: =VLOOKUP(F68,'5. Geo'!$B$3:$F$26,2,0) -> 2020 | J68: 44784 | K68: ='CF (Funds)'!D33 -> 0.015224657 | L68: ='CF (Funds)'!E33 -> 0 | N68: =SUM(K68:M68) -> 0.015224657 | P68: =IF($C$8=H68,1,0) -> 0 | Q68: New Space Capital Fund I | R68: =$P68*K68 -> 0 | S68: =$P68*L68 -> 0 | T68: =$P68*M68 -> 0 | U68: =$P68*N68 -> 0
F69: New Space Capital SCSp | G69: Fund | H69: =VLOOKUP(F69,'5. Geo'!$B$3:$F$26,5,0) -> Europe | I69: =VLOOKUP(F69,'5. Geo'!$B$3:$F$26,2,0) -> 2020 | J69: 44087 | K69: ='CF (Funds)'!D34 -> -2.7058824 | L69: ='CF (Funds)'!E34 -> 0 | N69: =SUM(K69:M69) -> -2.7058824 | P69: =IF($C$8=H69,1,0) -> 0 | Q69: New Space Capital SCSp | R69: =$P69*K69 -> 0 | S69: =$P69*L69 -> 0 | T69: =$P69*M69 -> 0 | U69: =$P69*N69 -> 0
F70: Acies Investments Fund I, L.P. | G70: Fund | H70: =VLOOKUP(F70,'5. Geo'!$B$3:$F$26,5,0) -> USA | I70: =VLOOKUP(F70,'5. Geo'!$B$3:$F$26,2,0) -> 2021 | J70: 44540 | K70: ='CF (Funds)'!D35 -> -2.8053125 | L70: ='CF (Funds)'!E35 -> 0 | N70: =SUM(K70:M70) -> -2.8053125 | P70: =IF($C$8=H70,1,0) -> 0 | Q70: Acies Investments Fund I, L.P. | R70: =$P70*K70 -> 0 | S70: =$P70*L70 -> 0 | T70: =$P70*M70 -> 0 | U70: =$P70*N70 -> 0
... F73: Acies Investments Fund I, L.P. | G73: Fund | H73: =VLOOKUP(F73,'5. Geo'!$B$3:$F$26,5,0) -> USA | I73: =VLOOKUP(F73,'5. Geo'!$B$3:$F$26,2,0) -> 2021 | J73: 44707 | K73: ='CF (Funds)'!D38 -> -3.388275 | L73: ='CF (Funds)'!E38 -> 0 | N73: =SUM(K73:M73) -> -3.388275 | P73: =IF($C$8=H73,1,0) -> 0 | Q73: Acies Investments Fund I, L.P. | R73: =$P73*K73 -> 0 | S73: =$P73*L73 -> 0 | T73: =$P73*M73 -> 0 | U73: =$P73*N73 -> 0
F74: Jollychic Holding Limited | H74: =VLOOKUP(F74,'5. Geo'!$B$3:$F$26,5,0) -> Asia-China | I74: =VLOOKUP(F74,'5. Geo'!$B$3:$F$26,2,0) -> 2019 | J74: =$G$4 -> 44834 | M74: =VLOOKUP(F74,NAV!$B$9:$D$39,3,0) -> 0 | N74: =SUM(K74:M74) -> 0 | P74: =IF($C$8=H74,1,0) -> 1 | Q74: Jollychic Holding Limited | R74: =$P74*K74 -> 0 | S74: =$P74*L74 -> 0 | T74: =$P74*M74 -> 0 | U74: =$P74*N74 -> 0
F75: Mena Mobile Inc | H75: =VLOOKUP(F75,'5. Geo'!$B$3:$F$26,5,0) -> Asia-China | I75: =VLOOKUP(F75,'5. Geo'!$B$3:$F$26,2,0) -> 2019 | J75: =$G$4 -> 44834 | M75: =VLOOKUP(F75,NAV!$B$9:$D$39,3,0) -> 3.1 | N75: =SUM(K75:M75) -> 3.1 | P75: =IF($C$8=H75,1,0) -> 1 | Q75: Mena Mobile Inc | R75: =$P75*K75 -> 0 | S75: =$P75*L75 -> 0 | T75: =$P75*M75 -> 3.1 | U75: =$P75*N75 -> 3.1
F76: Flyr Inc | H76: =VLOOKUP(F76,'5. Geo'!$B$3:$F$26,5,0) -> USA | I76: =VLOOKUP(F76,'5. Geo'!$B$3:$F$26,2,0) -> 2019 | J76: =$G$4 -> 44834 | M76: =VLOOKUP(F76,NAV!$B$9:$D$39,3,0) -> 78.08223 | N76: =SUM(K76:M76) -> 78.08223 | P76: =IF($C$8=H76,1,0) -> 0 | Q76: Flyr Inc | R76: =$P76*K76 -> 0 | S76: =$P76*L76 -> 0 | T76: =$P76*M76 -> 0 | U76: =$P76*N76 -> 0
F77: Esyasoft Holding | H77: =VLOOKUP(F77,'5. Geo'!$B$3:$F$26,5,0) -> Rest of Asia | I77: =VLOOKUP(F77,'5. Geo'!$B$3:$F$26,2,0) -> 2020 | J77: =$G$4 -> 44834 | M77: =VLOOKUP(F77,NAV!$B$9:$D$39,3,0) -> 0 | N77: =SUM(K77:M77) -> 0 | P77: =IF($C$8=H77,1,0) -> 0 | Q77: Esyasoft Holding | R77: =$P77*K77 -> 0 | S77: =$P77*L77 -> 0 | T77: =$P77*M77 -> 0 | U77: =$P77*N77 -> 0
F78: Beyond Limits | H78: =VLOOKUP(F78,'5. Geo'!$B$3:$F$26,5,0) -> USA | I78: =VLOOKUP(F78,'5. Geo'!$B$3:$F$26,2,0) -> 2020 | J78: =$G$4 -> 44834 | M78: =VLOOKUP(F78,NAV!$B$9:$D$39,3,0) -> 91.00154 | N78: =SUM(K78:M78) -> 91.00154 | P78: =IF($C$8=H78,1,0) -> 0 | Q78: Beyond Limits | R78: =$P78*K78 -> 0 | S78: =$P78*L78 -> 0 | T78: =$P78*M78 -> 0 | U78: =$P78*N78 -> 0
F79: ONT plc | H79: =VLOOKUP(F79,'5. Geo'!$B$3:$F$26,5,0) -> Europe | I79: =VLOOKUP(F79,'5. Geo'!$B$3:$F$26,2,0) -> 2020 | J79: =$G$4 -> 44834 | M79: =VLOOKUP(F79,NAV!$B$9:$D$39,3,0) -> 125.96279 | N79: =SUM(K79:M79) -> 125.96279 | P79: =IF($C$8=H79,1,0) -> 0 | Q79: ONT plc | R79: =$P79*K79 -> 0 | S79: =$P79*L79 -> 0 | T79: =$P79*M79 -> 0 | U79: =$P79*N79 -> 0
F80: Heygears | H80: =VLOOKUP(F80,'5. Geo'!$B$3:$F$26,5,0) -> Asia-China | I80: =VLOOKUP(F80,'5. Geo'!$B$3:$F$26,2,0) -> 2020 | J80: =$G$4 -> 44834 | M80: =VLOOKUP(F80,NAV!$B$9:$D$39,3,0) -> 136.64 | N80: =SUM(K80:M80) -> 136.64 | P80: =IF($C$8=H80,1,0) -> 1 | Q80: Heygears | R80: =$P80*K80 -> 0 | S80: =$P80*L80 -> 0 | T80: =$P80*M80 -> 136.64 | U80: =$P80*N80 -> 136.64
F81: Jysan Technologies | H81: =VLOOKUP(F81,'5. Geo'!$B$3:$F$26,5,0) -> Rest of Asia | I81: =VLOOKUP(F81,'5. Geo'!$B$3:$F$26,2,0) -> 2021 | J81: =$G$4 -> 44834 | M81: =VLOOKUP(F81,NAV!$B$9:$D$39,3,0) -> 20 | N81: =SUM(K81:M81) -> 20 | P81: =IF($C$8=H81,1,0) -> 0 | Q81: Jysan Technologies | R81: =$P81*K81 -> 0 | S81: =$P81*L81 -> 0 | T81: =$P81*M81 -> 0 | U81: =$P81*N81 -> 0
F82: Cerebras Systems Inc | H82: =VLOOKUP(F82,'5. Geo'!$B$3:$F$26,5,0) -> USA | I82: =VLOOKUP(F82,'5. Geo'!$B$3:$F$26,2,0) -> 2021 | J82: =$G$4 -> 44834 | M82: =VLOOKUP(F82,NAV!$B$9:$D$39,3,0) -> 39.999983 | N82: =SUM(K82:M82) -> 39.999983 | P82: =IF($C$8=H82,1,0) -> 0 | Q82: Cerebras Systems Inc | R82: =$P82*K82 -> 0 | S82: =$P82*L82 -> 0 | T82: =$P82*M82 -> 0 | U82: =$P82*N82 -> 0
F83: Endless Studios LLC | H83: =VLOOKUP(F83,'5. Geo'!$B$3:$F$26,5,0) -> USA | I83: =VLOOKUP(F83,'5. Geo'!$B$3:$F$26,2,0) -> 2021 | J83: =$G$4 -> 44834 | M83: =VLOOKUP(F83,NAV!$B$9:$D$39,3,0) -> 3 | N83: =SUM(K83:M83) -> 3 | P83: =IF($C$8=H83,1,0) -> 0 | Q83: Endless Studios LLC | R83: =$P83*K83 -> 0 | S83: =$P83*L83 -> 0 | T83: =$P83*M83 -> 0 | U83: =$P83*N83 -> 0
F84: Instadeep Limited | H84: =VLOOKUP(F84,'5. Geo'!$B$3:$F$26,5,0) -> Europe | I84: =VLOOKUP(F84,'5. Geo'!$B$3:$F$26,2,0) -> 2021 | J84: =$G$4 -> 44834 | M84: =VLOOKUP(F84,NAV!$B$9:$D$39,3,0) -> 5.0237202 | N84: =SUM(K84:M84) -> 5.0237202 | P84: =IF($C$8=H84,1,0) -> 0 | Q84: Instadeep Limited | R84: =$P84*K84 -> 0 | S84: =$P84*L84 -> 0 | T84: =$P84*M84 -> 0 | U84: =$P84*N84 -> 0
F85: X-fusion | H85: =VLOOKUP(F85,'5. Geo'!$B$3:$F$26,5,0) -> Asia-China | I85: =VLOOKUP(F85,'5. Geo'!$B$3:$F$26,2,0) -> 2022 | J85: =$G$4 -> 44834 | M85: =VLOOKUP(F85,NAV!$B$9:$D$39,3,0) -> 493.50096 | N85: =SUM(K85:M85) -> 493.50096 | P85: =IF($C$8=H85,1,0) -> 1 | Q85: X-fusion | R85: =$P85*K85 -> 0 | S85: =$P85*L85 -> 0 | T85: =$P85*M85 -> 493.50096 | U85: =$P85*N85 -> 493.50096
... F96: Acies Investments Fund I, L.P. | H96: =VLOOKUP(F96,'5. Geo'!$B$3:$F$26,5,0) -> USA | I96: =VLOOKUP(F96,'5. Geo'!$B$3:$F$26,2,0) -> 2021 | J96: =$G$4 -> 44834 | M96: =VLOOKUP(F96,NAV!$B$9:$D$39,3,0) -> 10.343447 | N96: =SUM(K96:M96) -> 10.343447 | P96: =IF($C$8=H96,1,0) -> 0 | Q96: Acies Investments Fund I, L.P. | R96: =$P96*K96 -> 0 | S96: =$P96*L96 -> 0 | T96: =$P96*M96 -> 0 | U96: =$P96*N96 -> 0

Sheet 4.2
C2: Investment | D2: Payment date | E2: Qtr | F2: Combined
C3: Jollychic Holding Limited | D3: 43470 | E3: ="Q"&ROUNDUP(MONTH(D3)/3,0)&" "&YEAR(D3) -> Q1 2019 | F3: -30
C4: Mena Mobile Inc | D4: 43563 | E4: ="Q"&ROUNDUP(MONTH(D4)/3,0)&" "&YEAR(D4) -> Q2 2019 | F4: -8
C5: Flyr Inc | D5: 43570 | E5: ="Q"&ROUNDUP(MONTH(D5)/3,0)&" "&YEAR(D5) -> Q2 2019 | F5: -4.9999981
C6: Glass Earth Holdings LLC | D6: 43635 | E6: ="Q"&ROUNDUP(MONTH(D6)/3,0)&" "&YEAR(D6) -> Q2 2019 | F6: -8
C7: North Summit Capital Fund | D7: 43665 | E7: ="Q"&ROUNDUP(MONTH(D7)/3,0)&" "&YEAR(D7) -> Q3 2019 | F7: -3
C8: Jollychic Holding Limited | D8: 43724 | E8: ="Q"&ROUNDUP(MONTH(D8)/3,0)&" "&YEAR(D8) -> Q3 2019 | F8: -20
C9: Jollychic Holding Limited | D9: 43724 | E9: ="Q"&ROUNDUP(MONTH(D9)/3,0)&" "&YEAR(D9) -> Q3 2019 | F9: -15
C10: ONT plc | D10: 43837 | E10: ="Q"&ROUNDUP(MONTH(D10)/3,0)&" "&YEAR(D10) -> Q1 2020 | F10: -18.109441
C11: Esyasoft Holding | D11: 43870 | E11: ="Q"&ROUNDUP(MONTH(D11)/3,0)&" "&YEAR(D11) -> Q1 2020 | F11: -2.5
C12: Beyond Limits | D12: 43879 | E12: ="Q"&ROUNDUP(MONTH(D12)/3,0)&" "&YEAR(D12) -> Q1 2020 | F12: -20
C13: North Summit Capital Fund | D13: 43879 | E13: ="Q"&ROUNDUP(MONTH(D13)/3,0)&" "&YEAR(D13) -> Q1 2020 | F13: -9.50975
C14: Flyr Inc | D14: 43915 | E14: ="Q"&ROUNDUP(MONTH(D14)/3,0)&" "&YEAR(D14) -> Q1 2020 | F14: -5.0000019
... C68: New Space Capital Fund I | D68: 44784 | E68: ="Q"&ROUNDUP(MONTH(D68)/3,0)&" "&YEAR(D68) -> Q3 2022 | F68: 0.015224657

Sheet 5. Geo
B3: Investment | C3: Vintage | D3: Type | E3: Sector | F3: Geography | G3: Committed | H3: Invested | I3: Remaining Commitment | J3: Distributions | K3: Carrying Value
B4: Jollychic Holding Limited | C4: 2019 | D4: Equity | E4: Ecommerce | F4: Asia-China | G4: 65 | H4: 65 | I4: 0 | J4: 0 | K4: 0
B5: Mena Mobile Inc | C5: 2019 | D5: Equity | E5: Mobile Gaming | F5: Asia-China | G5: 8 | H5: 8 | I5: 0 | J5: 0 | K5: 3.1 | M5: Asia-China | N5: =SUMIF(F3:K26,$M$5,G3:G26) -> 2578.854
B6: Flyr Inc | C6: 2019 | D6: Equity | E6: B2B SaaS | F6: USA | G6: 10 | H6: 10 | I6: 0 | J6: 0 | K6: 78.08223
B7: Esyasoft Holding | C7: 2020 | D7: Equity | E7: Utilities-Tech | F7: Rest of Asia | G7: 2.5 | H7: 2.5 | I7: 0 | J7: 5 | K7: 0
B8: Beyond Limits | C8: 2020 | D8: Equity | E8: Oil & Gas AI | F8: USA | G8: 90 | H8: 90 | I8: 0 | J8: 0 | K8: 91.00154
B9: ONT plc | C9: 2020 | D9: Equity | E9: BioTechnology | F9: Europe | G9: 141.47026 | H9: 141.47026 | I9: 0 | J9: 0 | K9: 149.58081
B10: Heygears | C10: 2020 | D10: Equity | E10: 3D Printing | F10: Asia-China | G10: 60 | H10: 60 | I10: 0 | J10: 0 | K10: 136.64
B11: Jysan Technologies | C11: 2021 | D11: Equity | E11: Fintech | F11: Rest of Asia | G11: 20 | H11: 20 | I11: 0 | J11: 0 | K11: 20
B12: Cerebras Systems Inc | C12: 2021 | D12: Equity | E12: Semiconductor | F12: USA | G12: 40 | H12: 40 | I12: 0 | J12: 0 | K12: 39.999983
B13: Endless Studios LLC | C13: 2021 | D13: Equity | E13: Edutech | F13: USA | G13: 3 | H13: 3 | I13: 0 | J13: 0 | K13: 3
B14: Instadeep Limited | C14: 2021 | D14: Equity | E14: B2B SaaS | F14: Europe | G14: 5.0278212 | H14: 5.0278212 | I14: 0 | J14: 0 | K14: 5.0237202
B15: X-fusion | C15: 2022 | D15: Equity | E15: Cloud Computing | F15: Asia-China | G15: 493.5 | H15: 493.5 | I15: 0 | J15: 0 | K15: 493.5
B16: DriveNets | C16: 2022 | D16: Equity | E16: Computer Networks | F16: MiddleEast | G16: 300 | H16: 300 | I16: 0 | J16: 0 | K16: 300
B17: vTv Therapeutics Inc. | C17: 2022 | D17: Equity | E17: BioTechnology | F17: USA | G17: 25 | H17: 12.5 | I17: 12.5 | J17: 0 | K17: -0.5557849
B18: Honor Device Co Ltd | C18: 2022 | D18: Equity | E18: Hardware-SmartDevices | F18: Asia-China | G18: 1600 | H18: 800 | I18: 800 | J18: 0 | K18: =1075.57839098788*0.8 -> 860.46271
B19: Glass Earth Holdings LLC | C19: 2019 | D19: Debt | E19: Consulting | F19: USA | G19: 8 | H19: 8 | I19: 0 | J19: 0 | K19: 0
B20: Mena Mobile Inc | C20: 2021 | D20: Debt | E20: Mobile Gaming | F20: Asia-China | G20: 2.353982 | H20: 2.353982 | I20: 0 | J20: 0 | K20: 2.353982
B21: Esyasoft Holding | C21: 2021 | D21: Debt | E21: Utilities-Tech | F21: Rest of Asia | G21: 0.411765 | H21: 0.411765 | I21: 0 | J21: 0 | K21: 0.45643868
B22: New Space Capital Fund I | C22: 2020 | D22: Fund | E22: Fund | F22: Europe | G22: 25.557908 | H22: 21.611951 | I22: 3.9459573 | J22: 0 | K22: 31.952799
B23: New Space Capital SCSp | C23: 2020 | D23: Fund | E23: Fund | F23: Europe | G23: 2.7058824 | H23: 2.7058824 | I23: 0 | J23: 0 | K23: 2.7058824
B24: North Summit Capital Fund | C24: 2020 | D24: Fund | E24: Fund | F24: Asia-China | G24: 300 | H24: 83.214653 | I24: 217.81331 | J24: 1.027961 | K24: 79.32
B25: Sinovation Disrupt Fund, L.P. | C25: 2020 | D25: Fund | E25: Fund | F25: Asia-China | G25: 50 | H25: 16.790246 | I25: 33.209754 | J25: 0.44382835 | K25: 15.875237
B26: Acies Investments Fund I, L.P. | C26: 2021 | D26: Fund | E26: Fund | F26: USA | G26: 17.1125 | H26: 10.626862 | I26: 6.4856375 | J26: 0 | K26: 10.343447
G28: =SUM(G4:G26) -> 3269.6401 | H28: =SUM(H4:H26) -> 2196.7134 | I28: =SUM(I4:I26) -> 1073.9547 | J28: =SUM(J4:J26) -> 6.4717893 | K28: =SUM(K4:K26) -> 2322.843

Sheet 4. CF Profile
B2: CASH DEPLOYED OVER TIME…
B5: Investment | C5: Type | D5: Payment date | E5: Period | F5: Contribution | G5: Distribution | I5: Contribution | J5: Equity | K5: Debt | L5: Fund | M5: Total | O5: Distribution | P5: Equity | Q5: Debt | R5: Fund | S5: Total
B6: Jollychic Holding Limited | C6: Equity | D6: 43470 | E6: ="Q"&ROUNDUP(MONTH(D6)/3,0)&" "&YEAR(D6) -> Q1 2019 | F6: -30 | G6: 0
B7: Jollychic Holding Limited | C7: Equity | D7: 43724 | E7: ="Q"&ROUNDUP(MONTH(D7)/3,0)&" "&YEAR(D7) -> Q3 2019 | F7: -20 | G7: 0 | I7: Q1 2019 | J7: =-SUMIFS($F$5:$F$103,$C$5:$C$103,$J$5,$E$5:$E$103,I7) -> 30 | K7: =-SUMIFS($F$5:$F$103,$C$5:$C$103,$K$5,$E$5:$E$103,I7) -> 0 | L7: =-SUMIFS($F$5:$F$103,$C$5:$C$103,"Fund",$E$5:$E$103,I7) -> 0 | M7: =-SUMIF($E$5:$G$103,$I7,$F$5:$F$103) -> 30 | O7: Q1 2019 | P7: =SUMIFS($G$5:$G$103,$C$5:$C$103,$P$5,$E$5:$E$103,I7) -> 0 | Q7: =SUMIFS($G$5:$G$103,$C$5:$C$103,$Q$5,$E$5:$E$103,I7) -> 0 | R7: =SUMIFS($G$5:$G$103,$C$5:$C$103,$R$5,$E$5:$E$103,I7) -> 0 | S7: =SUMIF($E$5:$G$103,$I7,$G$5:$G$103) -> 0
B8: Jollychic Holding Limited | C8: Equity | D8: 43724 | E8: ="Q"&ROUNDUP(MONTH(D8)/3,0)&" "&YEAR(D8) -> Q3 2019 | F8: -15 | G8: 0 | I8: Q2 2019 | J8: =-SUMIFS($F$5:$F$103,$C$5:$C$103,$J$5,$E$5:$E$103,I8) -> 12.999998 | K8: =-SUMIFS($F$5:$F$103,$C$5:$C$103,$K$5,$E$5:$E$103,I8) -> 8 | L8: =-SUMIFS($F$5:$F$103,$C$5:$C$103,"Fund",$E$5:$E$103,I8) -> 0 | M8: =-SUMIF($E$5:$G$103,$I8,$F$5:$F$103) -> 20.999998 | O8: Q2 2019 | P8: =SUMIFS($G$5:$G$103,$C$5:$C$103,$P$5,$E$5:$E$103,I8) -> 0 | Q8: =SUMIFS($G$5:$G$103,$C$5:$C$103,$Q$5,$E$5:$E$103,I8) -> 0 | R8: =SUMIFS($G$5:$G$103,$C$5:$C$103,$R$5,$E$5:$E$103,I8) -> 0 | S8: =SUMIF($E$5:$G$103,$I8,$G$5:$G$103) -> 0
B9: Mena Mobile Inc | C9: Equity | D9: 43563 | E9: ="Q"&ROUNDUP(MONTH(D9)/3,0)&" "&YEAR(D9) -> Q2 2019 | F9: -8 | G9: 0 | I9: Q3 2019 | J9: =-SUMIFS($F$5:$F$103,$C$5:$C$103,$J$5,$E$5:$E$103,I9) -> 35 | K9: =-SUMIFS($F$5:$F$103,$C$5:$C$103,$K$5,$E$5:$E$103,I9) -> 0 | L9: =-SUMIFS($F$5:$F$103,$C$5:$C$103,"Fund",$E$5:$E$103,I9) -> 3 | M9: =-SUMIF($E$5:$G$103,$I9,$F$5:$F$103) -> 38 | O9: Q3 2019 | P9: =SUMIFS($G$5:$G$103,$C$5:$C$103,$P$5,$E$5:$E$103,I9) -> 0 | Q9: =SUMIFS($G$5:$G$103,$C$5:$C$103,$Q$5,$E$5:$E$103,I9) -> 0 | R9: =SUMIFS($G$5:$G$103,$C$5:$C$103,$R$5,$E$5:$E$103,I9) -> 0 | S9: =SUMIF($E$5:$G$103,$I9,$G$5:$G$103) -> 0
B10: Flyr Inc | C10: Equity | D10: 43570 | E10: ="Q"&ROUNDUP(MONTH(D10)/3,0)&" "&YEAR(D10) -> Q2 2019 | F10: -4.9999981 | G10: 0 | I10: Q4 2019 | J10: =-SUMIFS($F$5:$F$103,$C$5:$C$103,$J$5,$E$5:$E$103,I10) -> 0 | K10: =-SUMIFS($F$5:$F$103,$C$5:$C$103,$K$5,$E$5:$E$103,I10) -> 0 | L10: =-SUMIFS($F$5:$F$103,$C$5:$C$103,"Fund",$E$5:$E$103,I10) -> 0 | M10: =-SUMIF($E$5:$G$103,$I10,$F$5:$F$103) -> 0 | O10: Q4 2019 | P10: =SUMIFS($G$5:$G$103,$C$5:$C$103,$P$5,$E$5:$E$103,I10) -> 0 | Q10: =SUMIFS($G$5:$G$103,$C$5:$C$103,$Q$5,$E$5:$E$103,I10) -> 0 | R10: =SUMIFS($G$5:$G$103,$C$5:$C$103,$R$5,$E$5:$E$103,I10) -> 0 | S10: =SUMIF($E$5:$G$103,$I10,$G$5:$G$103) -> 0
B11: Flyr Inc | C11: Equity | D11: 43915 | E11: ="Q"&ROUNDUP(MONTH(D11)/3,0)&" "&YEAR(D11) -> Q1 2020 | F11: -5.0000019 | G11: 0 | I11: Q1 2020 | J11: =-SUMIFS($F$5:$F$103,$C$5:$C$103,$J$5,$E$5:$E$103,I11) -> 75.609443 | K11: =-SUMIFS($F$5:$F$103,$C$5:$C$103,$K$5,$E$5:$E$103,I11) -> 0 | L11: =-SUMIFS($F$5:$F$103,$C$5:$C$103,"Fund",$E$5:$E$103,I11) -> 9.50975 | M11: =-SUMIF($E$5:$G$103,$I11,$F$5:$F$103) -> 85.119193 | O11: Q1 2020 | P11: =SUMIFS($G$5:$G$103,$C$5:$C$103,$P$5,$E$5:$E$103,I11) -> 0 | Q11: =SUMIFS($G$5:$G$103,$C$5:$C$103,$Q$5,$E$5:$E$103,I11) -> 0 | R11: =SUMIFS($G$5:$G$103,$C$5:$C$103,$R$5,$E$5:$E$103,I11) -> 0 | S11: =SUMIF($E$5:$G$103,$I11,$G$5:$G$103) -> 0
B12: Esyasoft Holding | C12: Equity | D12: 43870 | E12: ="Q"&ROUNDUP(MONTH(D12)/3,0)&" "&YEAR(D12) -> Q1 2020 | F12: -2.5 | G12: 0 | I12: Q2 2020 | J12: =-SUMIFS($F$5:$F$103,$C$5:$C$103,$J$5,$E$5:$E$103,I12) -> 142.12004 | K12: =-SUMIFS($F$5:$F$103,$C$5:$C$103,$K$5,$E$5:$E$103,I12) -> 0 | L12: =-SUMIFS($F$5:$F$103,$C$5:$C$103,"Fund",$E$5:$E$103,I12) -> 45.785 | M12: =-SUMIF($E$5:$G$103,$I12,$F$5:$F$103) -> 187.90504 | O12: Q2 2020 | P12: =SUMIFS($G$5:$G$103,$C$5:$C$103,$P$5,$E$5:$E$103,I12) -> 0 | Q12: =SUMIFS($G$5:$G$103,$C$5:$C$103,$Q$5,$E$5:$E$103,I12) -> 0 | R12: =SUMIFS($G$5:$G$103,$C$5:$C$103,$R$5,$E$5:$E$103,I12) -> 0 | S12: =SUMIF($E$5:$G$103,$I12,$G$5:$G$103) -> 0
B13: Beyond Limits | C13: Equity | D13: 43879 | E13: ="Q"&ROUNDUP(MONTH(D13)/3,0)&" "&YEAR(D13) -> Q1 2020 | F13: -20 | G13: 0 | I13: Q3 2020 | J13: =-SUMIFS($F$5:$F$103,$C$5:$C$103,$J$5,$E$5:$E$103,I13) -> 10 | K13: =-SUMIFS($F$5:$F$103,$C$5:$C$103,$K$5,$E$5:$E$103,I13) -> 0 | L13: =-SUMIFS($F$5:$F$103,$C$5:$C$103,"Fund",$E$5:$E$103,I13) -> 23.623435 | M13: =-SUMIF($E$5:$G$103,$I13,$F$5:$F$103) -> 33.623435 | O13: Q3 2020 | P13: =SUMIFS($G$5:$G$103,$C$5:$C$103,$P$5,$E$5:$E$103,I13) -> 0 | Q13: =SUMIFS($G$5:$G$103,$C$5:$C$103,$Q$5,$E$5:$E$103,I13) -> 0 | R13: =SUMIFS($G$5:$G$103,$C$5:$C$103,$R$5,$E$5:$E$103,I13) -> 0 | S13: =SUMIF($E$5:$G$103,$I13,$G$5:$G$103) -> 0
B14: Beyond Limits | C14: Equity | D14: 43921 | E14: ="Q"&ROUNDUP(MONTH(D14)/3,0)&" "&YEAR(D14) -> Q1 2020 | F14: -30 | G14: 0 | I14: Q4 2020 | J14: =-SUMIFS($F$5:$F$103,$C$5:$C$103,$J$5,$E$5:$E$103,I14) -> 60 | K14: =-SUMIFS($F$5:$F$103,$C$5:$C$103,$K$5,$E$5:$E$103,I14) -> 0 | L14: =-SUMIFS($F$5:$F$103,$C$5:$C$103,"Fund",$E$5:$E$103,I14) -> 9.482293 | M14: =-SUMIF($E$5:$G$103,$I14,$F$5:$F$103) -> 69.482293 | O14: Q4 2020 | P14: =SUMIFS($G$5:$G$103,$C$5:$C$103,$P$5,$E$5:$E$103,I14) -> 0 | Q14: =SUMIFS($G$5:$G$103,$C$5:$C$103,$Q$5,$E$5:$E$103,I14) -> 0 | R14: =SUMIFS($G$5:$G$103,$C$5:$C$103,$R$5,$E$5:$E$103,I14) -> 0.582902 | S14: =SUMIF($E$5:$G$103,$I14,$G$5:$G$103) -> 0.582902
B15: Beyond Limits | C15: Equity | D15: 43989 | E15: ="Q"&ROUNDUP(MONTH(D15)/3,0)&" "&YEAR(D15) -> Q2 2020 | F15: -30 | G15: 0 | I15: Q1 2021 | J15: =-SUMIFS($F$5:$F$103,$C$5:$C$103,$J$5,$E$5:$E$103,I15) -> 0 | K15: =-SUMIFS($F$5:$F$103,$C$5:$C$103,$K$5,$E$5:$E$103,I15) -> 0 | L15: =-SUMIFS($F$5:$F$103,$C$5:$C$103,"Fund",$E$5:$E$103,I15) -> 1.0845116 | M15: =-SUMIF($E$5:$G$103,$I15,$F$5:$F$103) -> 1.0845116 | O15: Q1 2021 | P15: =SUMIFS($G$5:$G$103,$C$5:$C$103,$P$5,$E$5:$E$103,I15) -> 0 | Q15: =SUMIFS($G$5:$G$103,$C$5:$C$103,$Q$5,$E$5:$E$103,I15) -> 0 | R15: =SUMIFS($G$5:$G$103,$C$5:$C$103,$R$5,$E$5:$E$103,I15) -> 0.07634835 | S15: =SUMIF($E$5:$G$103,$I15,$G$5:$G$103) -> 0.07634835
B16: Beyond Limits | C16: Equity | D16: 44103 | E16: ="Q"&ROUNDUP(MONTH(D16)/3,0)&" "&YEAR(D16) -> Q3 2020 | F16: -10 | G16: 0 | I16: Q2 2021 | J16: =-SUMIFS($F$5:$F$103,$C$5:$C$103,$J$5,$E$5:$E$103,I16) -> 31.24078 | K16: =-SUMIFS($F$5:$F$103,$C$5:$C$103,$K$5,$E$5:$E$103,I16) -> 2.353982 | L16: =-SUMIFS($F$5:$F$103,$C$5:$C$103,"Fund",$E$5:$E$103,I16) -> 6.1810318 | M16: =-SUMIF($E$5:$G$103,$I16,$F$5:$F$103) -> 39.775794 | O16: Q2 2021 | P16: =SUMIFS($G$5:$G$103,$C$5:$C$103,$P$5,$E$5:$E$103,I16) -> 0 | Q16: =SUMIFS($G$5:$G$103,$C$5:$C$103,$Q$5,$E$5:$E$103,I16) -> 0 | R16: =SUMIFS($G$5:$G$103,$C$5:$C$103,$R$5,$E$5:$E$103,I16) -> 0 | S16: =SUMIF($E$5:$G$103,$I16,$G$5:$G$103) -> 0
B17: ONT plc | C17: Equity | D17: 43968 | E17: ="Q"&ROUNDUP(MONTH(D17)/3,0)&" "&YEAR(D17) -> Q2 2020 | F17: -50 | G17: 0 | I17: Q3 2021 | J17: =-SUMIFS($F$5:$F$103,$C$5:$C$103,$J$5,$E$5:$E$103,I17) -> 0 | K17: =-SUMIFS($F$5:$F$103,$C$5:$C$103,$K$5,$E$5:$E$103,I17) -> 0.411765 | L17: =-SUMIFS($F$5:$F$103,$C$5:$C$103,"Fund",$E$5:$E$103,I17) -> 0.98965473 | M17: =-SUMIF($E$5:$G$103,$I17,$F$5:$F$103) -> 1.4014197 | O17: Q3 2021 | P17: =SUMIFS($G$5:$G$103,$C$5:$C$103,$P$5,$E$5:$E$103,I17) -> 0 | Q17: =SUMIFS($G$5:$G$103,$C$5:$C$103,$Q$5,$E$5:$E$103,I17) -> 0 | R17: =SUMIFS($G$5:$G$103,$C$5:$C$103,$R$5,$E$5:$E$103,I17) -> 0.445059 | S17: =SUMIF($E$5:$G$103,$I17,$G$5:$G$103) -> 0.445059
B18: ONT plc | C18: Equity | D18: 44006 | E18: ="Q"&ROUNDUP(MONTH(D18)/3,0)&" "&YEAR(D18) -> Q2 2020 | F18: -27.268351 | G18: 0 | I18: Q4 2021 | J18: =-SUMIFS($F$5:$F$103,$C$5:$C$103,$J$5,$E$5:$E$103,I18) -> 48.023704 | K18: =-SUMIFS($F$5:$F$103,$C$5:$C$103,$K$5,$E$5:$E$103,I18) -> 0 | L18: =-SUMIFS($F$5:$F$103,$C$5:$C$103,"Fund",$E$5:$E$103,I18) -> 11.901731 | M18: =-SUMIF($E$5:$G$103,$I18,$F$5:$F$103) -> 59.925434 | O18: Q4 2021 | P18: =SUMIFS($G$5:$G$103,$C$5:$C$103,$P$5,$E$5:$E$103,I18) -> 0 | Q18: =SUMIFS($G$5:$G$103,$C$5:$C$103,$Q$5,$E$5:$E$103,I18) -> 0 | R18: =SUMIFS($G$5:$G$103,$C$5:$C$103,$R$5,$E$5:$E$103,I18) -> 0.139694 | S18: =SUMIF($E$5:$G$103,$I18,$G$5:$G$103) -> 0.139694
... B21: ONT plc | C21: Equity | D21: 44315 | E21: ="Q"&ROUNDUP(MONTH(D21)/3,0)&" "&YEAR(D21) -> Q2 2021 | F21: -11.24078 | G21: 0 | I21: Q3 2022 | J21: =-SUMIFS($F$5:$F$103,$C$5:$C$103,$J$5,$E$5:$E$103,I21) -> 800 | K21: =-SUMIFS($F$5:$F$103,$C$5:$C$103,$K$5,$E$5:$E$103,I21) -> 0 | L21: =-SUMIFS($F$5:$F$103,$C$5:$C$103,"Fund",$E$5:$E$103,I21) -> -0.015224657 | M21: =-SUMIF($E$5:$G$103,$I21,$F$5:$F$103) -> 799.98478 | O21: Q3 2022 | P21: =SUMIFS($G$5:$G$103,$C$5:$C$103,$P$5,$E$5:$E$103,I21) -> 0 | Q21: =SUMIFS($G$5:$G$103,$C$5:$C$103,$Q$5,$E$5:$E$103,I21) -> 0 | R21: =SUMIFS($G$5:$G$103,$C$5:$C$103,$R$5,$E$5:$E$103,I21) -> 0 | S21: =SUMIF($E$5:$G$103,$I21,$G$5:$G$103) -> 0
B22: Heygears | C22: Equity | D22: 44166 | E22: ="Q"&ROUNDUP(MONTH(D22)/3,0)&" "&YEAR(D22) -> Q4 2020 | F22: -60 | G22: 0 | I22: Total | J22: =SUM(J7:J21) -> 2050.9949 | K22: =SUM(K7:K21) -> 10.765747 | L22: =SUM(L7:L21) -> 134.94959 | M22: =SUM(M7:M21) -> 2196.7103 | O22: Total | P22: =SUM(P7:P21) -> 5 | Q22: =SUM(Q7:Q21) -> 0 | R22: =SUM(R7:R21) -> 1.4717893 | S22: =SUM(S7:S21) -> 6.4717893
B23: Jysan Technologies | C23: Equity | D23: 44363 | E23: ="Q"&ROUNDUP(MONTH(D23)/3,0)&" "&YEAR(D23) -> Q2 2021 | F23: -20 | G23: 0
B24: Cerebras Systems Inc | C24: Equity | D24: 44488 | E24: ="Q"&ROUNDUP(MONTH(D24)/3,0)&" "&YEAR(D24) -> Q4 2021 | F24: -39.999983 | G24: 0 | J24: =J21=0 -> FALSE | K24: =K21=0 -> TRUE | L24: =L21=0 -> FALSE | M24: =M21=0 -> FALSE | P24: =P21=0 -> TRUE | Q24: =Q21=0 -> TRUE | R24: =R21=0 -> TRUE | S24: =S21=0 -> TRUE
B25: Endless Studios LLC | C25: Equity | D25: 44494 | E25: ="Q"&ROUNDUP(MONTH(D25)/3,0)&" "&YEAR(D25) -> Q4 2021 | F25: -3 | G25: 0
B26: Instadeep Limited | C26: Equity | D26: 44550 | E26: ="Q"&ROUNDUP(MONTH(D26)/3,0)&" "&YEAR(D26) -> Q4 2021 | F26: -5.0237202 | G26: 0
B27: X-fusion | C27: Equity | D27: 44574 | E27: ="Q"&ROUNDUP(MONTH(D27)/3,0)&" "&YEAR(D27) -> Q1 2022 | F27: -493.50096 | G27: 0
B28: DriveNets | C28: Equity | D28: 44643 | E28: ="Q"&ROUNDUP(MONTH(D28)/3,0)&" "&YEAR(D28) -> Q1 2022 | F28: -200 | G28: 0
B29: DriveNets | C29: Equity | D29: 44680 | E29: ="Q"&ROUNDUP(MONTH(D29)/3,0)&" "&YEAR(D29) -> Q2 2022 | F29: -100 | G29: 0
B30: Esyasoft Holding | C30: Equity | D30: 44691 | E30: ="Q"&ROUNDUP(MONTH(D30)/3,0)&" "&YEAR(D30) -> Q2 2022 | F30: 0 | G30: 5
B31: vTv Therapeutics Inc. | C31: Equity | D31: 44712 | E31: ="Q"&ROUNDUP(MONTH(D31)/3,0)&" "&YEAR(D31) -> Q2 2022 | F31: -12.5 | G31: 0
B32: Honor Device Co Ltd | C32: Equity | D32: 44769 | E32: ="Q"&ROUNDUP(MONTH(D32)/3,0)&" "&YEAR(D32) -> Q3 2022 | F32: -800 | G32: 0
B33: Glass Earth Holdings LLC | C33: Debt | D33: 43635 | E33: ="Q"&ROUNDUP(MONTH(D33)/3,0)&" "&YEAR(D33) -> Q2 2019 | F33: -8 | G33: 0
B34: Mena Mobile Inc | C34: Debt | D34: 44293 | E34: ="Q"&ROUNDUP(MONTH(D34)/3,0)&" "&YEAR(D34) -> Q2 2021 | F34: -2.353982 | G34: 0
B35: Esyasoft Holding | C35: Debt | D35: 44384 | E35: ="Q"&ROUNDUP(MONTH(D35)/3,0)&" "&YEAR(D35) -> Q3 2021 | F35: -0.411765 | G35: 0
B36: Sinovation Disrupt Fund, L.P. | C36: Fund | D36: 18/11/2020 | E36: ="Q"&ROUNDUP(MONTH(D36)/3,0)&" "&YEAR(D36) -> Q4 2020 | F36: -10.5 | G36: 0
B37: Sinovation Disrupt Fund, L.P. | C37: Fund | D37: 44238 | E37: ="Q"&ROUNDUP(MONTH(D37)/3,0)&" "&YEAR(D37) -> Q1 2021 | F37: 4.214027 | G37: 0
B38: Sinovation Disrupt Fund, L.P. | C38: Fund | D38: 44238 | E38: ="Q"&ROUNDUP(MONTH(D38)/3,0)&" "&YEAR(D38) -> Q1 2021 | F38: 0 | G38: 0.05044835
B39: Sinovation Disrupt Fund, L.P. | C39: Fund | D39: 44285 | E39: ="Q"&ROUNDUP(MONTH(D39)/3,0)&" "&YEAR(D39) -> Q1 2021 | F39: -6.433746 | G39: 0
B40: Sinovation Disrupt Fund, L.P. | C40: Fund | D40: 44269 | E40: ="Q"&ROUNDUP(MONTH(D40)/3,0)&" "&YEAR(D40) -> Q1 2021 | F40: 1.1352074 | G40: 0
B41: Sinovation Disrupt Fund, L.P. | C41: Fund | D41: 44269 | E41: ="Q"&ROUNDUP(MONTH(D41)/3,0)&" "&YEAR(D41) -> Q1 2021 | F41: 0 | G41: 0.0259
B42: Sinovation Disrupt Fund, L.P. | C42: Fund | D42: 44483 | E42: ="Q"&ROUNDUP(MONTH(D42)/3,0)&" "&YEAR(D42) -> Q4 2021 | F42: -7.567138 | G42: 0
B43: Sinovation Disrupt Fund, L.P. | C43: Fund | D43: 44554 | E43: ="Q"&ROUNDUP(MONTH(D43)/3,0)&" "&YEAR(D43) -> Q4 2021 | F43: -7.385016 | G43: 0
B44: Sinovation Disrupt Fund, L.P. | C44: Fund | D44: 44554 | E44: ="Q"&ROUNDUP(MONTH(D44)/3,0)&" "&YEAR(D44) -> Q4 2021 | F44: 4.0733456 | G44: 0
B45: Sinovation Disrupt Fund, L.P. | C45: Fund | D45: 44554 | E45: ="Q"&ROUNDUP(MONTH(D45)/3,0)&" "&YEAR(D45) -> Q4 2021 | F45: 0 | G45: 0.139694
B46: Sinovation Disrupt Fund, L.P. | C46: Fund | D46: 44703 | E46: ="Q"&ROUNDUP(MONTH(D46)/3,0)&" "&YEAR(D46) -> Q2 2022 | F46: 5.673074 | G46: 0
B47: Sinovation Disrupt Fund, L.P. | C47: Fund | D47: 44703 | E47: ="Q"&ROUNDUP(MONTH(D47)/3,0)&" "&YEAR(D47) -> Q2 2022 | F47: 0 | G47: 0.227786
B48: North Summit Capital Fund | C48: Fund | D48: 19/07/2019 | E48: ="Q"&ROUNDUP(MONTH(D48)/3,0)&" "&YEAR(D48) -> Q3 2019 | F48: -3 | G48: 0
B49: North Summit Capital Fund | C49: Fund | D49: 43983 | E49: ="Q"&ROUNDUP(MONTH(D49)/3,0)&" "&YEAR(D49) -> Q2 2020 | F49: -4.485 | G49: 0
B50: North Summit Capital Fund | C50: Fund | D50: 18/02/2020 | E50: ="Q"&ROUNDUP(MONTH(D50)/3,0)&" "&YEAR(D50) -> Q1 2020 | F50: -9.50975 | G50: 0
B51: North Summit Capital Fund | C51: Fund | D51: 13/04/2020 | E51: ="Q"&ROUNDUP(MONTH(D51)/3,0)&" "&YEAR(D51) -> Q2 2020 | F51: -41.3 | G51: 0
B52: North Summit Capital Fund | C52: Fund | D52: 16/11/2020 | E52: ="Q"&ROUNDUP(MONTH(D52)/3,0)&" "&YEAR(D52) -> Q4 2020 | F52: 9.95 | G52: 0
B53: North Summit Capital Fund | C53: Fund | D53: 16/11/2020 | E53: ="Q"&ROUNDUP(MONTH(D53)/3,0)&" "&YEAR(D53) -> Q4 2020 | F53: -10.455 | G53: 0
B54: North Summit Capital Fund | C54: Fund | D54: 31/12/2020 | E54: ="Q"&ROUNDUP(MONTH(D54)/3,0)&" "&YEAR(D54) -> Q4 2020 | F54: 4.975 | G54: 0
B55: North Summit Capital Fund | C55: Fund | D55: 31/12/2020 | E55: ="Q"&ROUNDUP(MONTH(D55)/3,0)&" "&YEAR(D55) -> Q4 2020 | F55: -3.452293 | G55: 0
B56: North Summit Capital Fund | C56: Fund | D56: 31/12/2020 | E56: ="Q"&ROUNDUP(MONTH(D56)/3,0)&" "&YEAR(D56) -> Q4 2020 | F56: 0 | G56: 0.582902
B57: North Summit Capital Fund | C57: Fund | D57: 44370 | E57: ="Q"&ROUNDUP(MONTH(D57)/3,0)&" "&YEAR(D57) -> Q2 2021 | F57: -5.97 | G57: 0
B58: North Summit Capital Fund | C58: Fund | D58: 44400 | E58: ="Q"&ROUNDUP(MONTH(D58)/3,0)&" "&YEAR(D58) -> Q3 2021 | F58: -0.75 | G58: 0
B59: North Summit Capital Fund | C59: Fund | D59: 44400 | E59: ="Q"&ROUNDUP(MONTH(D59)/3,0)&" "&YEAR(D59) -> Q3 2021 | F59: 0 | G59: 0.445059
B60: North Summit Capital Fund | C60: Fund | D60: 44554 | E60: ="Q"&ROUNDUP(MONTH(D60)/3,0)&" "&YEAR(D60) -> Q4 2021 | F60: 1.78239 | G60: 0
B61: North Summit Capital Fund | C61: Fund | D61: 44676 | E61: ="Q"&ROUNDUP(MONTH(D61)/3,0)&" "&YEAR(D61) -> Q2 2022 | F61: -21 | G61: 0
B62: New Space Capital Fund I | C62: Fund | D62: 44087 | E62: ="Q"&ROUNDUP(MONTH(D62)/3,0)&" "&YEAR(D62) -> Q3 2020 | F62: -20.917553 | G62: 0
B63: New Space Capital Fund I | C63: Fund | D63: 44287 | E63: ="Q"&ROUNDUP(MONTH(D63)/3,0)&" "&YEAR(D63) -> Q2 2021 | F63: -0.21103182 | G63: 0
B64: New Space Capital Fund I | C64: Fund | D64: 44442 | E64: ="Q"&ROUNDUP(MONTH(D64)/3,0)&" "&YEAR(D64) -> Q3 2021 | F64: -0.23965473 | G64: 0
B65: New Space Capital Fund I | C65: Fund | D65: 44623 | E65: ="Q"&ROUNDUP(MONTH(D65)/3,0)&" "&YEAR(D65) -> Q1 2022 | F65: -0.25893585 | G65: 0
B66: New Space Capital Fund I | C66: Fund | D66: 44784 | E66: ="Q"&ROUNDUP(MONTH(D66)/3,0)&" "&YEAR(D66) -> Q3 2022 | F66: 0.015224657 | G66: 0
B67: New Space Capital SCSp | C67: Fund | D67: 44087 | E67: ="Q"&ROUNDUP(MONTH(D67)/3,0)&" "&YEAR(D67) -> Q3 2020 | F67: -2.7058824 | G67: 0
B68: Acies Investments Fund I, L.P. | C68: Fund | D68: 44540 | E68: ="Q"&ROUNDUP(MONTH(D68)/3,0)&" "&YEAR(D68) -> Q4 2021 | F68: -2.8053125 | G68: 0
... B71: Acies Investments Fund I, L.P. | C71: Fund | D71: 44707 | E71: ="Q"&ROUNDUP(MONTH(D71)/3,0)&" "&YEAR(D71) -> Q2 2022 | F71: -3.388275 | G71: 0

Sheet 5. CF 
B2: CASHFLOW REQUIREMENT
B3: Date of NAV | C3: =D!D2 -> 44834 | Y3: Overall Summary
B6: Deals | D6: Commitment | E6: Q3-2022 | F6: Q4-2022 | G6: Q1-2023 | H6: Q2-2023 | I6: Q3-2023 | J6: Q4-2023
B9: vTv Therapeutics Inc. | C9: Equity | D9: 12.5 | H9: =D9 -> 12.5
B10: Honor Device Co Ltd | C10: Equity | D10: 1000 | F10: =D10 -> 1000
B12: New Space Capital Fund I | C12: Fund | D12: 3.9459573 | F12: 1 | G12: =D12-F12 -> 2.9459573
B13: North Summit Capital Fund | C13: Fund | D13: 217.81331
B14: Sinovation Disrupt Fund, L.P. | C14: Fund | D14: 33.209754 | F14: 10 | G14: 10 | H14: =D14-SUM(F14:G14) -> 13.209754
B15: Acies Investments Fund I, L.P. | C15: Fund | D15: 6.4856375 | F15: 2 | G15: 2 | H15: =D15-SUM(F15:G15) -> 2.4856375
D16: =SUM(D9:D15) -> 1273.9547 | F16: =SUM(F9:F15) -> 1013 | G16: =SUM(G9:G15) -> 14.945957 | H16: =SUM(H9:H15) -> 28.195392 | I16: =SUM(I9:I15) -> 0
B19: Notes
B20: No funding projected for North Summit Fund

Sheet Board
C3: Deals | D3: Board Representation ‡ | E3: Representative | F3: Notes | G3: Comments
C5: Direct Investments
C6: Jollychic Holding Limited | D6: 1 Board | F6: 1
C7: Mena Mobile Inc | D7: 1 Board | E7: Peng Xiao
C8: Flyr Inc | D8: 1 Board | E8: Martin Edelman
C9: Esyasoft Holding | D9: NR | E9: Monty Aw represented earlier | F9: 2
C10: Beyond Limits | D10: 1 Board | E10: Martin Edelman | F10: 3
C11: ONT plc | D11: 1 Board | E11: Guy Harmelin (Independent Director)
C12: Heygears | D12: 2 Board | E12: Peng Xiao, Elaine
C13: Jysan Technologies | D13: 1 Board | E13: None appointed
C14: Cerebras Systems Inc | D14: 1 Observer | E14: Eric Xing | F14: 4
C15: Endless Studios LLC | D15: 1 Board + 1 Observer | E15: Tariq (Board), Talal (Observer)
C16: Instadeep Limited | D16: 1 Observer | E16: Viktor
C17: X-fusion | D17: NR | E17: n/a
C18: DriveNets | D18: 1 Observer | E18: Guy Harmelin
C19: vTv Therapeutics Inc. | D19: 1 Observer | E19: (Dr. Fahad) TBC | G19: Confirm appoinment
C20: Honor Device Co Ltd | D20: TBC | E20: TBC | G20: Confirm appoinment
C23: Debt Investments
C24: Glass Earth Holdings LLC | D24: NR
C25: Mena Mobile Inc | D25: 1 Board | E25: Peng Xiao
C26: Esyasoft Holding | D26: NR
C29: Funds Investments
C30: New Space Capital Fund I | D30: NR
C31: New Space Capital SCSp | E31: Talal
C32: North Summit Capital Fund | D32: NR
C33: Sinovation Disrupt Fund, L.P. | D33: NR
C34: Acies Investments Fund I, L.P. | G34: Confirm appoinment
C38: NOTES:
C39: NR =No representation
C40: ‡ Board Representation : as a Board Seat, Observer, or Advisor
C41: 1. Jollychic Holding : Peng Xiao held the directorship until Jun 2021
C42: 1. Esyasoft: we held a Board seat, with Monty Aw as the representative, until Jun 2022
C43: 2. Beyond Limits: possibility of the 2nd Board seat in case we invest (an additional / an earlier committed) $10m
C44: 3. Cerebras : possibility of a Board seat, If G42 holds >10% with rights to exercise at least 20% of warrant

Sheet 6. AT1
C2: ATTRIBUTION SUMMARY
C3: As of date | D3: 44819
C6: Deals | D6: Type | E6: Gain
C7: Jollychic Holding Limited | D7: Equity | E7: -65
C8: vTv Therapeutics Inc. | D8: Equity | E8: -13.055785
C9: Glass Earth Holdings LLC | D9: Debt | E9: -8
C10: Mena Mobile Inc | D10: Equity | E10: -4.9
C11: North Summit Capital Fund | D11: Fund | E11: -2.866692
C12: Sinovation Disrupt Fund, L.P. | D12: Fund | E12: -0.47118065
C13: Acies Investments Fund I, L.P. | D13: Fund | E13: -0.2834155
C14: X-fusion | D14: Equity | E14: -0.0009562
C15: Jysan Technologies | D15: Equity | E15: 0
C16: Cerebras Systems Inc | D16: Equity | E16: 0
C17: Endless Studios LLC | D17: Equity | E17: 0
C18: Instadeep Limited | D18: Equity | E18: 0
... C29: Heygears | D29: Equity | E29: 76.64

Sheet X1
C3: ONT | G3: Heygears | K3: FLYR | O3: Instadeep | S3: vTv Therapeutics
W4: Select Cashflow for
G5: NAV Date
C6: NAV Date | D6: 44773 | O6: Post all transactions | S6: # shares | T6: 10386274 | W6: Vintage
C7: Share Price (GBP) | D7: 3.18 | G7: 44166 | H7: -60000000 | O7: B = 599,769 | P7: 599769 | S7: Price per share | T7: 1.18 | W7: Sector
C8: GBPUSD | D8: 1.22 | G8: 44773 | H8: 20000000 | K8: G42 Shares | L8: 5205482 | O8: Ordinary =1,493,575 | P8: 1493575 | S8: Value | T8: =T6*T7*10^-6 -> 12.255803 | W8: Geogrpahy
K9: Fully Diluted | L9: 61222609 | O9: Employee shares = 83,261 | P9: 83261 | W9: Asset Class Type
C10: G42 Shares | D10: 44328120 | G10: IRR | H10: =XIRR(H7:H8,G7:G8) -> -0.48346658 | K10: % ownership | L10: 0.0855 | O10: Class A = 289,048 | P10: 289048
C11: Fully Diluted | D11: 823636945 | G11: Multiple | H11: =-H8/SUM(H7) -> 0.33333333 | L11: =L8/L9 -> 0.085025485 | O11: LTIP shares | P11: 429797
C12: % ownership | D12: 0.0538 | O12: Total | P12: =SUM(P7:P11) -> 2895450 | S12: EsyaSoft, Equity
G13: Mena Mobile | K13: Share price | L13: 18.75
K14: Discount | L14: 0.2 | O14: # shares to G42 | P14: 33267 | S14: NAV Date
C15: USDAED | D15: 3.675 | G15: NAV Date | K15: Carrying Value Mn | L15: =L8*L13*(1-L14)*10^-6 -> 78.08223 | O15: % ownership | P15: =P14/P12 -> 0.011489406
C16: Date of Investment | O16: Price per share | Oct 21 | P16: 110.63 | S16: 44075 | T16: -2500000
C17: 43968 | D17: -50 | G17: 43563 | H17: -8000000 | K17: NAV Date | L17: 44773 | O17: NAV Date | P17: 44773 | S17: 44773 | T17: 5000000
C18: 44006 | D18: -27.268351 | G18: 44773 | H18: 1700000 | K18: 43570 | L18: -4999998.1
C19: 43837 | D19: -18.109441 | K19: 43915 | L19: -5000001.9 | O19: BNT Offer | 18Jul 2022 | S19: IRR | T19: =XIRR(T16:T17,S16:S17) -> 0.43686312
C20: 43990 | D20: -34.851687 | G20: IRR | H20: =XIRR(H17:H18,G17:G18) -> -0.37324778 | K20: =L17 -> 44773 | L20: =+L15*10^6 -> 78082230 | O20: Offer Mn, GBP | P20: 510 | S20: Multiple | T20: =-T17/SUM(T16) -> 2
C21: 44315 | D21: -11.24078 | G21: Multiple | H21: =-H18/SUM(H17) -> 0.2125 | O21: # shares o/s | P21: =P12 -> 2895450
C22: 44742 | D22: =NAV!D14 -> 125.96279 | K22: IRR | L22: =XIRR(L18:L20,K18:K20) -> 1.0308312 | O22: Offer price per share | P22: =P20*10^6/P21 -> 176.13842 | S22: EsyaSoft, Debt
K23: Multiple | L23: =L20/-SUM(L18:L19) -> 7.808223 | O23: Premium | P23: =P22/P16 -> 1.5921398
C24: IRR | D24: =XIRR(D17:D22,C17:C22) -> -0.054969171 | O24: GBPUSD | P24: 1.22 | S24: NAV Date
C25: Multiple | D25: =-D22/SUM(D17:D21) -> 0.89038351
S26: 44377 | T26: -411765
O27: 44550 | P27: =-18477242.89/3.68 -> -5020989.9 | S27: 44773 | T27: =(-((S27-S26)/365*T26*10%))-T26 -> 456438.68
O28: =P17 -> 44773 | P28: =P14*P22*P24 -> 7148708.3
S29: IRR | T29: =XIRR(T26:T27,S26:S27) -> 0.099591023
O30: IRR | P30: =XIRR(P27:P28,O27:O28) -> 0.78296691 | S30: Multiple | T30: =-T27/SUM(T26) -> 1.1084932
O31: Multiple | P31: =P28/-SUM(P27) -> 1.4237647

Sheet X2
D4: Investment type | E4: Monthly (25th of each month other than quarter-end) | F4: Quarterly (1st April, July and October) | G4: Annually (2nd January following year-end) | H4: Ref. to summary
D5: Listed securities on a recognised exchange | E5: 1. Number of securities held, including: | F5: 1. Number of securities held, including: | G5: 1. Number of securities held, including: | H5: 1a
E6: details of any movement in number of securities held | F6: details of any movement in number of securities held | G6: details of any movement in number of securities held | H6: 1b, 1c, 1d
E7: exercise of conversion rights | F7: exercise of conversion rights | G7: exercise of conversion rights | H7: 1c
E8: changes to the terms of the instrument | F8: changes to the terms of the instrument | G8: changes to the terms of the instrument | H8: 4
E9: amalgamation/ splitting of instrument classes | F9: amalgamation/ splitting of instrument classes | G9: amalgamation/ splitting of instrument classes | H9: 1c
E10: bonus shares | F10: bonus shares | G10: bonus shares | H10: 1c
E11: additional instruments subscribed | F11: additional instruments subscribed | G11: additional instruments subscribed | H11: 1b
E12: dividend, etc. | F12: dividend, etc. | G12: dividend, etc. | H12: 3
E13: 2. Fair value of the listed portfolio based on quoted stock exchange (MTM) price | F13: 2. Fair value of the listed portfolio based on quoted stock exchange (MTM) price | G13: 2. Fair value of the listed portfolio based on quoted stock exchange (MTM) price | H13: 2
D15: Unlisted corporate investments held | E15: 1. Number of securities held, including: | F15: 1. Number of securities held, including: | G15: 1. Number of securities held, including: | H15: 1a
E16: details of any movement in number of securities held | F16: details of any movement in number of securities held | G16: details of any movement in number of securities held | H16: 1b, 1c, 1d
E17: exercise of conversion rights | F17: exercise of conversion rights | G17: exercise of conversion rights | H17: 1c
E18: changes to the terms of the instrument | F18: changes to the terms of the instrument | G18: changes to the terms of the instrument | H18: 4
E19: amalgamation/ splitting of instrument classes | F19: amalgamation/ splitting of instrument classes | G19: amalgamation/ splitting of instrument classes | H19: 1c
E20: bonus shares | F20: bonus shares | G20: bonus shares | H20: 1c
E21: additional instruments subscribed | F21: additional instruments subscribed | G21: additional instruments subscribed | H21: 1b
E22: dividend, etc. | F22: dividend, etc. | G22: dividend, etc. | H22: 3
E23: 2. Any events or conditions that indicate significant decrease in the fair value previously recorded for individual investments | F23: 2. Any events or conditions that indicate significant increase/ decrease in the fair value previously recorded for individual investments | G23: 2. Any events or conditions that indicate significant increase/ decrease in the fair value previously recorded for individual investments | H23: 4
F24: 3. Refresh the valuation at which each investment in the portfolio is previously carried | G24: 3. Refresh the valuation at which each investment in the portfolio is previously carried | H24: 3
G25: 4. Obtain an external valuer’s report of fair value of each investment in the portfolio as at 30th September (by 30th November)
G26: 5. Carry out an internal refresh as at 31st December of the external valuer’s report of fair value (by 5th January following the year-end)
D28: Investments in Funds (closed ended) | E28: 1. Any events or conditions that indicate significant increase/ decrease in the fair value previously recorded for individual investments | F28: 1. Any events or conditions that indicate significant increase/ decrease in the fair value previously recorded for individual investments | G28: 1. Any events or conditions that indicate significant increase/ decrease in the fair value previously recorded for individual investments | H28: 2
F29: 2. Fair value of investment in each Fund based on Fund Manager’s/ General Partner’s report for the previous quarter | G29: 2. Fair value of investment in each Fund based on Fund Manager’s/ General Partner’s report for the previous quarter (by 5th January following the year-end) | H29: 1

Sheet Outlook
C3: Deals | E3: Business Outlook | F3: Financial Outlook | G3: Valuation Outlook | H3: Synergies / JV | I3: Actions
C5: Direct Investments
C6: Flyr Inc | I6: Exercise Warrants | N6: Color Code
C7: Beyond Limits
C8: Endless Studios LLC | P8: No particular view on this
C9: Instadeep Limited
C10: ONT plc | P10: Negative outlook
C11: vTv Therapeutics Inc.
C12: DriveNets | P12: Positive outlook
C14: Heygears | P14: No action / under investigation
C15: Mena Mobile Inc
C16: X-fusion | P16: No improvement or decline
C17: Honor Device Co Ltd
P18: Exited / or seeking exit
C19: Esyasoft Holding | I19: Exited
C20: Jysan Technologies | I20: Seeking Exit
C21: Cerebras Systems Inc | I21: Seeking Exit
C22: Jollychic Holding Limited | I22: In Liquidation
C26: Funds Investments
C27: New Space Capital Fund I
C28: New Space Capital SCSp
C29: North Summit Capital Fund | I29: Exit plan in progress
C30: Sinovation Disrupt Fund, L.P.
C31: Acies Investments Fund I, L.P.
