Workbook
Name Company: [1]UEL!$B$18:$B$20
Name Dates: [1]ONT!$N$2:$AN$2
Name DetailedCapShares: '[2]Current Cap'!$T$133
Name FAGroup: [1]UEL!$B$3:$B$15
Name IQ_CH: 110000
Name IQ_CQ: 5000
Name IQ_CY: 10000
Name IQ_DAILY: 500000
Name IQ_FH: 100000
Name IQ_FQ: 500
Name IQ_FY: 1000
Name IQ_LTM: 2000
Name IQ_MONTH: 15000
Name IQ_NTM: 6000
Name IQ_WEEK: 50000
Name IQ_YTD: 3000

Sheet D
C2: Date of NAV | D2: 45016
H3: D A S H B O A R D | L3: figures in USD Millions
D6: # Investments | E6: Committed | F6: Invested | G6: Remaining | H6: Distributions | I6: Residual Value | J6: IRR | K6: TVPI | L6: RPI | M6: DPI
C8: EQUITY | D8: =COUNTIF('Summary | 01 '!C10:C27,"*") -> 17 | E8: ='1. IRR Equity'!AD29 -> 2093.0293 | F8: ='1. IRR Equity'!AE29 -> 2082.7762 | G8: ='1. IRR Equity'!AF29 -> 10.253161 | H8: ='1. IRR Equity'!AG29 -> 5 | I8: ='1. IRR Equity'!AH29 -> 2082.8141 | J8: ='1. IRR Equity'!AI29 -> 0.0019109696 | K8: ='1. IRR Equity'!AJ29 -> 1.0024189 | L8: ='1. IRR Equity'!AK29 -> 1.0000182 | M8: ='1. IRR Equity'!AL29 -> 0.002400642
C11: DEBT | D11: =COUNTIF('Summary | 01 '!C30:C32,"*") -> 3 | E11: ='2. IRR Debt'!Q12 -> 10.765747 | F11: ='2. IRR Debt'!R12 -> 10.765747 | G11: ='2. IRR Debt'!S12 -> 0 | H11: ='2. IRR Debt'!T12 -> 0.47078465 | I11: ='2. IRR Debt'!U12 -> 2.353982 | J11: ='2. IRR Debt'!V12 -> -0.35001702 | K11: ='2. IRR Debt'!W12 -> 0.26238464 | L11: ='2. IRR Debt'!X12 -> 0.21865478 | M11: ='2. IRR Debt'!Y12 -> 0.043729864
C14: FUNDS | D14: =COUNTIF('Summary | 01 '!C36:C40,"*") -> 5 | E14: ='3. IRR Funds'!Q15 -> 395.37629 | F14: ='3. IRR Funds'!R15 -> 133.65097 | G14: ='3. IRR Funds'!S15 -> 262.75328 | H14: ='3. IRR Funds'!T15 -> 4.4275637 | I14: ='3. IRR Funds'!U15 -> 122.28936 | J14: ='3. IRR Funds'!V15 -> -0.02269576 | K14: ='3. IRR Funds'!W15 -> 0.94811825 | L14: ='3. IRR Funds'!X15 -> 0.91499044 | M14: ='3. IRR Funds'!Y15 -> 0.033127807
C17: TOTAL | D17: =D8+D11+D14 -> 25 | E17: =E8+E11+E14 -> 2499.1714 | F17: =F8+F11+F14 -> 2227.1929 | G17: =G8+G11+G14 -> 273.00644 | H17: =H8+H11+H14 -> 9.8983484 | I17: =I8+I11+I14 -> 2207.4575 | J17: ='4.All'!N9 -> -0.0033056326 | K17: =(H17+I17)/F17 -> 0.99558319 | L17: =I17/F17 -> 0.99113887 | M17: =H17/F17 -> 0.0044443157
E19: =E17='Summary | 01 '!J43 -> FALSE | F19: =F17='Summary | 01 '!K43 -> TRUE | G19: =ROUND(G17,1)=ROUND('Summary | 01 '!L43,1) -> FALSE | H19: =ROUND(H17,1)=ROUND('Summary | 01 '!M43,1) -> TRUE | I19: =ROUND(I17,1)=ROUND('Summary | 01 '!N43,1) -> TRUE

Sheet Summary | 01 
C2: As of date | D2: =D!D2 -> 45016
C6: Deals | D6: Status | E6: Lead | F6: Investing Entity | G6: Vintageἀ | H6: Instrument | I6: % | J6: Committed | K6: Invested | L6: Remaining Commitment | M6: Distributions | N6: Carrying Value | O6: Gain | P6: TVPI | Q6: IRRβ | R6: Additonal Upside
G7: # | I7: % | J7: $,m | K7: $,m | L7: $,m | M7: $,m | N7: $,m | O7: $,m | P7: X | Q7: %
C9: Direct Investments
C10: Jollychic Holding Limited | D10: In Liquidation | E10: Elaine | F10: Mozn | G10: 2019 | H10: C+ Prefs | I10: ='7. %'!F10 -> 0.056999998 | J10: 65 | K10: =-SUMIF('CF (Equity, Debt)'!$C$3:$K$35,'Summary | 01 '!C10,'CF (Equity, Debt)'!$E$3:$E$35) -> 65 | L10: 0 | M10: =SUMIF('CF (Equity, Debt)'!$C$3:$K$35,'Summary | 01 '!C10,'CF (Equity, Debt)'!$F$3:$F$35) -> 0 | N10: =VLOOKUP(C10,NAV!$B$4:$E$42,4,0) -> 0 | O10: =N10+M10-K10 -> -65 | P10: =(M10+N10)/K10 -> 0 | Q10: =VLOOKUP(C10,'1. IRR Equity'!$AC$12:$AL$28,7,0) -> NM
C11: Mena Mobile Inc | D11: Unrealized | E11: Elaine | F11: Mozn | G11: 2019 | H11: B Prefs | I11: ='7. %'!F11 -> 0.14 | J11: 8 | K11: =-SUMIF('CF (Equity, Debt)'!$C$3:$K$35,'Summary | 01 '!C11,'CF (Equity, Debt)'!$E$3:$E$35) -> 8 | L11: 0 | M11: =SUMIF('CF (Equity, Debt)'!$C$3:$K$35,'Summary | 01 '!C11,'CF (Equity, Debt)'!$F$3:$F$35) -> 0 | N11: =VLOOKUP(C11,NAV!$B$4:$E$42,4,0) -> 3.1 | O11: =N11+M11-K11 -> -4.9 | P11: =(M11+N11)/K11 -> 0.3875 | Q11: =VLOOKUP(C11,'1. IRR Equity'!$AC$12:$AL$28,7,0) -> -0.21191685
C12: Flyr Inc | D12: Unrealized | E12: Sushil | F12: Mozn | G12: 2019 | H12: B-1,2 Prefs | I12: ='7. %'!F12 -> 0.085025485 | J12: 10 | K12: =-SUMIF('CF (Equity, Debt)'!$C$3:$K$35,'Summary | 01 '!C12,'CF (Equity, Debt)'!$E$3:$E$35) -> 10 | L12: 0 | M12: =SUMIF('CF (Equity, Debt)'!$C$3:$K$35,'Summary | 01 '!C12,'CF (Equity, Debt)'!$F$3:$F$35) -> 0 | N12: =VLOOKUP(C12,NAV!$B$4:$E$42,4,0) -> 78.08223 | O12: =N12+M12-K12 -> 68.08223 | P12: =(M12+N12)/K12 -> 7.808223 | Q12: =VLOOKUP(C12,'1. IRR Equity'!$AC$12:$AL$28,7,0) -> 0.7832873 | R12: Flyr Warrantsa
C13: Esyasoft Holding | D13: Realized | E13: Sushil | F13: Mozn | G13: 2020 | H13: Convertible Note | I13: ='7. %'!F13 -> n/a | J13: 2.5 | K13: =-SUMIF('CF (Equity, Debt)'!$C$3:$K$35,'Summary | 01 '!C13,'CF (Equity, Debt)'!$E$3:$E$35) -> 2.5 | L13: 0 | M13: =SUMIF('CF (Equity, Debt)'!$C$3:$K$35,'Summary | 01 '!C13,'CF (Equity, Debt)'!$F$3:$F$35) -> 5 | N13: =VLOOKUP(C13,NAV!$B$4:$E$42,4,0) -> 0 | O13: =N13+M13-K13 -> 2.5 | P13: =(M13+N13)/K13 -> 2 | Q13: =VLOOKUP(C13,'1. IRR Equity'!$AC$12:$AL$28,7,0) -> 0.36091766
C14: Beyond Limits | D14: Unrealized | E14: Divyesh | F14: Mozn | G14: 2020 | H14: C Prefs | I14: ='7. %'!F14 -> 0.09739482 | J14: 90 | K14: =-SUMIF('CF (Equity, Debt)'!$C$3:$K$35,'Summary | 01 '!C14,'CF (Equity, Debt)'!$E$3:$E$35) -> 90 | L14: 0 | M14: =SUMIF('CF (Equity, Debt)'!$C$3:$K$35,'Summary | 01 '!C14,'CF (Equity, Debt)'!$F$3:$F$35) -> 0 | N14: =VLOOKUP(C14,NAV!$B$4:$E$42,4,0) -> 91.00154 | O14: =N14+M14-K14 -> 1.0015403 | P14: =(M14+N14)/K14 -> 1.0111282 | Q14: =VLOOKUP(C14,'1. IRR Equity'!$AC$12:$AL$28,7,0) -> 0.0038127035
C15: ONT plc | D15: Unrealized | E15: Divyesh | F15: Mozn | G15: 2020 | H15: Ordinary Shares | I15: ='7. %'!F15 -> 0.053819975 | J15: 141.47026 | K15: =-SUMIF('CF (Equity, Debt)'!$C$3:$K$35,'Summary | 01 '!C15,'CF (Equity, Debt)'!$E$3:$E$35) -> 141.47026 | L15: 0 | M15: =SUMIF('CF (Equity, Debt)'!$C$3:$K$35,'Summary | 01 '!C15,'CF (Equity, Debt)'!$F$3:$F$35) -> 0 | N15: =VLOOKUP(C15,NAV!$B$4:$E$42,4,0) -> 122.38019 | O15: =N15+M15-K15 -> -19.090073 | P15: =(M15+N15)/K15 -> 0.86505946 | Q15: =VLOOKUP(C15,'1. IRR Equity'!$AC$12:$AL$28,7,0) -> -0.050375113
C16: Heygears | D16: Unrealized | E16: Elaine | F16: Mozn | G16: 2020 | H16: Registered Capital | I16: ='7. %'!F16 -> 0.1438 | J16: 60 | K16: =-SUMIF('CF (Equity, Debt)'!$C$3:$K$35,'Summary | 01 '!C16,'CF (Equity, Debt)'!$E$3:$E$35) -> 60 | L16: 0 | M16: =SUMIF('CF (Equity, Debt)'!$C$3:$K$35,'Summary | 01 '!C16,'CF (Equity, Debt)'!$F$3:$F$35) -> 0 | N16: =VLOOKUP(C16,NAV!$B$4:$E$42,4,0) -> 119.2498 | O16: =N16+M16-K16 -> 59.249804 | P16: =(M16+N16)/K16 -> 1.9874967 | Q16: =VLOOKUP(C16,'1. IRR Equity'!$AC$12:$AL$28,7,0) -> 0.34306269
C17: Jysan Technologies | D17: Unrealized | E17: Sushil | F17: Mozn 1 | G17: 2021 | H17: A (Ordinary Shares) | I17: ='7. %'!F17 -> 0.03 | J17: 20 | K17: =-SUMIF('CF (Equity, Debt)'!$C$3:$K$35,'Summary | 01 '!C17,'CF (Equity, Debt)'!$E$3:$E$35) -> 20 | L17: 0 | M17: =SUMIF('CF (Equity, Debt)'!$C$3:$K$35,'Summary | 01 '!C17,'CF (Equity, Debt)'!$F$3:$F$35) -> 0 | N17: =VLOOKUP(C17,NAV!$B$4:$E$42,4,0) -> 20 | O17: =N17+M17-K17 -> 0 | P17: =(M17+N17)/K17 -> 1 | Q17: =VLOOKUP(C17,'1. IRR Equity'!$AC$12:$AL$28,7,0) -> 2.9802322e-09
C18: Cerebras Systems Inc | D18: Unrealized | E18: Ignasi | F18: Mozn | G18: 2021 | H18: F Prefs | I18: ='7. %'!F18 -> 0.01 | J18: 40 | K18: =-SUMIF('CF (Equity, Debt)'!$C$3:$K$35,'Summary | 01 '!C18,'CF (Equity, Debt)'!$E$3:$E$35) -> 39.999983 | L18: 0 | M18: =SUMIF('CF (Equity, Debt)'!$C$3:$K$35,'Summary | 01 '!C18,'CF (Equity, Debt)'!$F$3:$F$35) -> 0 | N18: =VLOOKUP(C18,NAV!$B$4:$E$42,4,0) -> 39.999983 | O18: =N18+M18-K18 -> 0 | P18: =(M18+N18)/K18 -> 1 | Q18: =VLOOKUP(C18,'1. IRR Equity'!$AC$12:$AL$28,7,0) -> 2.9802322e-09
C19: Endless Studios LLC | D19: Unrealized | E19: Sushil | F19: Mozn | G19: 2021 | H19: A Pref Units | I19: ='7. %'!F19 -> 0.068571429 | J19: 3 | K19: =-SUMIF('CF (Equity, Debt)'!$C$3:$K$35,'Summary | 01 '!C19,'CF (Equity, Debt)'!$E$3:$E$35) -> 3 | L19: 0 | M19: =SUMIF('CF (Equity, Debt)'!$C$3:$K$35,'Summary | 01 '!C19,'CF (Equity, Debt)'!$F$3:$F$35) -> 0 | N19: =VLOOKUP(C19,NAV!$B$4:$E$42,4,0) -> 3 | O19: =N19+M19-K19 -> 0 | P19: =(M19+N19)/K19 -> 1 | Q19: =VLOOKUP(C19,'1. IRR Equity'!$AC$12:$AL$28,7,0) -> 2.9802322e-09
C20: Instadeep Limited | D20: To be Exited | E20: Ignasi | F20: Mozn | G20: 2021 | H20: B Prefs | I20: ='7. %'!F20 -> 0.011489406 | J20: 5.0278212 | K20: =-SUMIF('CF (Equity, Debt)'!$C$3:$K$35,'Summary | 01 '!C20,'CF (Equity, Debt)'!$E$3:$E$35) -> 5.0237202 | L20: 0 | M20: =SUMIF('CF (Equity, Debt)'!$C$3:$K$35,'Summary | 01 '!C20,'CF (Equity, Debt)'!$F$3:$F$35) -> 0 | N20: =VLOOKUP(C20,NAV!$B$4:$E$42,4,0) -> 5.0237202 | O20: =N20+M20-K20 -> 0 | P20: =(M20+N20)/K20 -> 1 | Q20: =VLOOKUP(C20,'1. IRR Equity'!$AC$12:$AL$28,7,0) -> 2.9802322e-09
C21: X-fusion | D21: Unrealized | E21: Elaine | F21: Mozn 2 | G21: 2022 | H21: Equity-TBC | I21: ='7. %'!F21 -> 0.05 | J21: 493.5 | K21: =-SUMIF('CF (Equity, Debt)'!$C$3:$K$35,'Summary | 01 '!C21,'CF (Equity, Debt)'!$E$3:$E$35) -> 493.50096 | L21: 0 | M21: =SUMIF('CF (Equity, Debt)'!$C$3:$K$35,'Summary | 01 '!C21,'CF (Equity, Debt)'!$F$3:$F$35) -> 0 | N21: =VLOOKUP(C21,NAV!$B$4:$E$42,4,0) -> 424.06662 | O21: =N21+M21-K21 -> -69.434338 | P21: =(M21+N21)/K21 -> 0.85930253 | Q21: =VLOOKUP(C21,'1. IRR Equity'!$AC$12:$AL$28,7,0) -> NM
C22: DriveNets | D22: Unrealized | E22: Anton | F22: G42 | G22: 2022 | H22: Equity-TBC | I22: ='7. %'!F22 -> 0.0943 | J22: 300 | K22: =-SUMIF('CF (Equity, Debt)'!$C$3:$K$35,'Summary | 01 '!C22,'CF (Equity, Debt)'!$E$3:$E$35) -> 300 | L22: =0 -> 0 | M22: =SUMIF('CF (Equity, Debt)'!$C$3:$K$35,'Summary | 01 '!C22,'CF (Equity, Debt)'!$F$3:$F$35) -> 0 | N22: =VLOOKUP(C22,NAV!$B$4:$E$42,4,0) -> 300 | O22: =N22+M22-K22 -> 0 | P22: =(M22+N22)/K22 -> 1 | Q22: =VLOOKUP(C22,'1. IRR Equity'!$AC$12:$AL$28,7,0) -> NM | R22: DN Warrants b
C23: vTv Therapeutics Inc. | D23: Unrealized | E23: Divyesh | F23: G42 | G23: 2022 | H23: Ordinary Shares | I23: ='7. %'!F23 -> 0.099316564 | J23: =K23 -> 24.53125 | K23: =-SUMIF('CF (Equity, Debt)'!$C$3:$K$35,'Summary | 01 '!C23,'CF (Equity, Debt)'!$E$3:$E$35) -> 24.53125 | L23: =J23-K23 -> 0 | M23: =SUMIF('CF (Equity, Debt)'!$C$3:$K$35,'Summary | 01 '!C23,'CF (Equity, Debt)'!$F$3:$F$35) -> 0 | N23: =VLOOKUP(C23,NAV!$B$4:$E$42,4,0) -> 8.3900321 | O23: =N23+M23-K23 -> -16.141218 | P23: =(M23+N23)/K23 -> 0.34201405 | Q23: =VLOOKUP(C23,'1. IRR Equity'!$AC$12:$AL$28,7,0) -> NM | R23: vTv $30m milestn payment c
C24: Honor Device Co Ltd | D24: Unrealized | E24: Elaine | F24: G42 3 | G24: 2022 | H24: Equity-TBC | I24: ='7. %'!F24 -> 0.018823528 | J24: =K24 -> 800 | K24: =-SUMIF('CF (Equity, Debt)'!$C$3:$K$35,'Summary | 01 '!C24,'CF (Equity, Debt)'!$E$3:$E$35) -> 800 | L24: =J24-K24 -> 0 | M24: =SUMIF('CF (Equity, Debt)'!$C$3:$K$35,'Summary | 01 '!C24,'CF (Equity, Debt)'!$F$3:$F$35) -> 0 | N24: =VLOOKUP(C24,NAV!$B$4:$E$42,4,0) -> 848.76999 | O24: =N24+M24-K24 -> 48.76999 | P24: =(M24+N24)/K24 -> 1.0609625 | Q24: =VLOOKUP(C24,'1. IRR Equity'!$AC$12:$AL$28,7,0) -> NM
C25: Applied AI Corporation Limited | D25: Unrealized | E25: Anton | F25: Mozn | G25: 2022 | H25: Convertible Note | I25: n/a | J25: 15 | K25: 4.75 | L25: =J25-K25 -> 10.25 | M25: 0 | N25: =VLOOKUP(C25,NAV!$B$4:$E$42,4,0) -> 4.75 | O25: =N25+M25-K25 -> 0 | P25: =(M25+N25)/K25 -> 1 | Q25: =VLOOKUP(C25,'1. IRR Equity'!$AC$12:$AL$28,7,0) -> NM
C26: eSpace | D26: Unrealized | E26: Anton | F26: Mozn 4 | G26: 2022 | H26: SAFE note | I26: n/a | J26: 15 | K26: 15 | L26: =J26-K26 -> 0 | M26: 0 | N26: =VLOOKUP(C26,NAV!$B$4:$E$42,4,0) -> 15 | O26: =N26+M26-K26 -> 0 | P26: =(M26+N26)/K26 -> 1 | Q26: =VLOOKUP(C26,'1. IRR Equity'!$AC$12:$AL$28,7,0) -> NM
J27: =SUM(J10:J26) -> 2093.0293 | K27: =SUM(K10:K26) -> 2082.7762 | L27: =SUM(L10:L26) -> 10.25 | M27: =SUM(M10:M26) -> 5 | N27: =SUM(N10:N26) -> 2082.8141 | O27: =SUM(O10:O26) -> 5.0379353 | P27: =(M27+N27)/K27 -> 1.0024189 | Q27: ='1. IRR Equity'!AD35 -> 0.0019109696
C29: Debt Investments
C30: Glass Earth Holdings LLC | D30: In default | E30: Marty | F30: Mozn | G30: 2019 | H30: Promissory Note | I30: n/a | J30: 8 | K30: 8 | L30: 0 | M30: 0 | N30: 0 | O30: =N30+M30-K30 -> -8 | P30: =(M30+N30)/K30 -> 0 | Q30: =VLOOKUP(C30,'2. IRR Debt'!$P$9:$Y$11,7,0) -> NM
C31: Mena Mobile Inc (Debt) | D31: Unrealized | E31: Elaine | F31: Mozn | G31: 2021 | H31: Loan | I31: n/a | J31: 2.353982 | K31: =J31 -> 2.353982 | L31: 0 | M31: 0 | N31: =K31 -> 2.353982 | O31: =N31+M31-K31 -> 0 | P31: =(M31+N31)/K31 -> 1 | Q31: =VLOOKUP(C31,'2. IRR Debt'!$P$9:$Y$11,7,0) -> 2.9802322e-09
C32: Esyasoft Holding (Debt) | D32: Realized | E32: Sushil | F32: Mozn | G32: 2021 | H32: Loan | I32: n/a | J32: 0.411765 | K32: 0.411765 | L32: 0 | M32: ='CF (Equity, Debt)'!F40 -> 0.47078465 | N32: 0 | O32: =N32+M32-K32 -> 0.05901965 | P32: =(M32+N32)/K32 -> 1.1433333 | Q32: =VLOOKUP(C32,'2. IRR Debt'!$P$9:$Y$11,7,0) -> 0.075277027
J33: =SUM(J30:J32) -> 10.765747 | K33: =SUM(K30:K32) -> 10.765747 | L33: =SUM(L30:L32) -> 0 | M33: =SUM(M30:M32) -> 0.47078465 | N33: =SUM(N30:N32) -> 2.353982 | O33: =N33+M33-K33 -> -7.9409804 | P33: =(M33+N33)/K33 -> 0.26238464 | Q33: ='2. IRR Debt'!Q15 -> -0.35001702
C35: Funds Investments
C36: New Space Capital Fund I | D36: Unrealized | E36: Sushil | F36: G42 | G36: 2020 | H36: LP | I36: n/a | J36: =K36+L36 -> 28.098225 | K36: =-SUM('CF (Funds)'!D31:D37) -> 11.058035 | L36: =NAV!P33 -> 17.040191 | M36: =SUM('CF (Funds)'!E31:E37) -> 2.9557744 | N36: =VLOOKUP(C36,NAV!$B$4:$E$42,4,0) -> 14.294891 | O36: =N36+M36-K36 -> 6.1926309 | P36: 1.4784783 | Q36: =VLOOKUP(C36,'3. IRR Funds'!$P$7:$Y$15,7,0) -> 0.1090443
C37: New Space Capital SCSp | D37: Unrealized | E37: Sushil | F37: G42 | G37: 2020 | H37: GP | I37: n/a | J37: =2.3/0.85 -> 2.7058824 | K37: 2.7058824 | L37: 0 | M37: 0 | N37: =VLOOKUP(C37,NAV!$B$4:$E$42,4,0) -> 2.7058824 | O37: =N37+M37-K37 -> 0 | P37: 1 | Q37: =VLOOKUP(C37,'3. IRR Funds'!$P$7:$Y$15,7,0) -> 0
C38: North Summit Capital Fund | D38: Unrealized | E38: Elaine | F38: G42 | G38: 2020 | H38: LP | I38: n/a | J38: 300 | K38: 83.214653 | L38: 217.81331 | M38: 1.027961 | N38: =VLOOKUP(C38,NAV!$B$4:$E$42,4,0) -> 70.03 | O38: =N38+M38-K38 -> -12.156692 | P38: 0.96555063 | Q38: =VLOOKUP(C38,'3. IRR Funds'!$P$7:$Y$15,7,0) -> -0.064168629
C39: Sinovation Disrupt Fund, L.P. | D39: Unrealized | E39: Elaine | F39: G42 | G39: 2020 | H39: LP | I39: n/a | J39: 50 | K39: =-SUM('CF (Funds)'!D3:D16) -> 22.657267 | L39: =J39-K39 -> 27.342733 | M39: 0.44382835 | N39: =VLOOKUP(C39,NAV!$B$4:$E$42,4,0) -> 21.51575 | O39: =N39+M39-K39 -> -0.69768865 | P39: 0.97193724 | Q39: =VLOOKUP(C39,'3. IRR Funds'!$P$7:$Y$15,7,0) -> -0.018159524
C40: Acies Investments Fund I, L.P. | D40: Unrealized | E40: Divyesh | F40: G42 | G40: 2021 | H40: LP | I40: 0.33 | J40: 17.1125 | K40: 14.015137 | L40: =J40-K40 -> 3.0973625 | M40: 0 | N40: =VLOOKUP(C40,NAV!$B$4:$E$42,4,0) -> 13.742841 | O40: =N40+M40-K40 -> -0.2722965 | P40: 0.97333028 | Q40: =VLOOKUP(C40,'3. IRR Funds'!$P$7:$Y$15,7,0) -> -0.021553859 | R40: 9.9% GP | Anchor
J41: =SUM(J36:J40) -> 397.91661 | K41: =SUM(K36:K40) -> 133.65097 | L41: =SUM(L36:L40) -> 265.29359 | M41: =SUM(M36:M40) -> 4.4275637 | N41: =SUM(N36:N40) -> 122.28936 | O41: =N41+M41-K41 -> -6.9340462 | P41: =(M41+N41)/K41 -> 0.94811825 | Q41: ='3. IRR Funds'!Q18 -> -0.02269576
C43: Total | J43: =J27+J33+J41 -> 2501.7117 | K43: =K27+K33+K41 -> 2227.1929 | L43: =L27+L33+L41 -> 275.54359 | M43: =M27+M33+M41 -> 9.8983484 | N43: =N27+N33+N41 -> 2207.4575 | O43: =N43+M43-K43 -> -9.8370913 | P43: =(M43+N43)/K43 -> 0.99558319 | Q43: ='4.All'!N9 -> -0.0033056326
K44: =ROUND(K43,2)=ROUND('4.All'!J9,2) -> TRUE | M44: =ROUND(M43,2)=ROUND('4.All'!L9,2) -> TRUE | N44: =ROUND(N43,2)=ROUND('4.All'!M9,2) -> TRUE
C46: Additional Upside Section:
C47: a) Flyr: For every $1m of revenue, 194,477 shares, capped at 1,264,1000 (B-1) shares shall be issued to Mozn
C48: b) DriveNets: Share warrants exercisable upon the achievement of target revenue of clients referred by G42, and corresponding milestones
C49: c) vTv Therapeutics: Potential issuance of $30m in additional shares, if FDA approval received for the drug TTP399
C50: d) Acies Investments Fund I LP: Being the Anchor investor, entitled to 9.9% of the aggregate carried interest earned by the GP
C52: Definition:
C53: ἀ = Vintage corresponds to the year of the first investment made
C54: β = Excludes transaction costs from the estimate of IRR, as those are not available
C55: IRR is referred as NM when it is not meaningful
C57: Investing Entities:
C58: G42 refers to G42 Investments AI Holding RSC Ltd
C59: Mozn refers to Mozn Holding RSC Ltd
... C68: TBC = to be confirmed

Sheet S | 02
C2: As of date | E2: =D!D2 -> 45016
E5: 2 | F5: 3 | G5: 4 | H5: 5 | I5: 6 | J5: 7 | K5: 8 | L5: 9 | M5: 11 | N5: 12 | O5: 13 | Q5: 15 | R5: 14 | S5: 10
C6: Deals | D6: Type | E6: Status | F6: Lead | G6: Investing Entity | H6: Vintageἀ | I6: Instrument | J6: % | K6: Committed | L6: Invested | M6: Distributions | N6: Carrying Value | O6: Gain | P6: Gain FY21 | Q6: IRRβ | R6: TVPI | S6: Remaining Commitment | T6: Additonal Upside
I7: # | J7: % | K7: $,m | L7: $,m | M7: $,m | N7: $,m | O7: $,m | Q7: % | R7: X | S7: $,m | W7: MOZN
C9: eSpace | D9: Direct Investment | E9: =VLOOKUP($C9,'Summary | 01 '!$C$6:$R$43,E$5,0) -> Unrealized | F9: =VLOOKUP($C9,'Summary | 01 '!$C$6:$R$43,F$5,0) -> Anton | G9: =VLOOKUP($C9,'Summary | 01 '!$C$6:$R$43,G$5,0) -> Mozn 4 | H9: =VLOOKUP($C9,'Summary | 01 '!$C$6:$R$43,H$5,0) -> 2022 | I9: =VLOOKUP($C9,'Summary | 01 '!$C$6:$R$43,I$5,0) -> SAFE note | J9: =VLOOKUP($C9,'Summary | 01 '!$C$6:$R$43,J$5,0) -> n/a | K9: =VLOOKUP($C9,'Summary | 01 '!$C$6:$R$43,K$5,0) -> 15 | L9: =VLOOKUP($C9,'Summary | 01 '!$C$6:$R$43,L$5,0) -> 15 | ... O9: =VLOOKUP($C9,'Summary | 01 '!$C$6:$R$43,O$5,0) -> 0 | P9: n/a | Q9: =VLOOKUP($C9,'Summary | 01 '!$C$6:$R$43,Q$5,0) -> NM | R9: =VLOOKUP($C9,'Summary | 01 '!$C$6:$R$43,R$5,0) -> 1 | S9: =VLOOKUP($C9,'Summary | 01 '!$C$6:$R$43,S$5,0) -> 0 | W9: Invested | X9: =L27 -> 969.01067
C10: Applied AI Corporation Limited | D10: Direct Investment | E10: =VLOOKUP($C10,'Summary | 01 '!$C$6:$R$43,E$5,0) -> Unrealized | F10: =VLOOKUP($C10,'Summary | 01 '!$C$6:$R$43,F$5,0) -> Anton | G10: =VLOOKUP($C10,'Summary | 01 '!$C$6:$R$43,G$5,0) -> Mozn | H10: =VLOOKUP($C10,'Summary | 01 '!$C$6:$R$43,H$5,0) -> 2022 | I10: =VLOOKUP($C10,'Summary | 01 '!$C$6:$R$43,I$5,0) -> Convertible Note | J10: =VLOOKUP($C10,'Summary | 01 '!$C$6:$R$43,J$5,0) -> n/a | K10: =VLOOKUP($C10,'Summary | 01 '!$C$6:$R$43,K$5,0) -> 15 | L10: =VLOOKUP($C10,'Summary | 01 '!$C$6:$R$43,L$5,0) -> 4.75 | ... O10: =VLOOKUP($C10,'Summary | 01 '!$C$6:$R$43,O$5,0) -> 0 | P10: n/a | Q10: =VLOOKUP($C10,'Summary | 01 '!$C$6:$R$43,Q$5,0) -> NM | R10: =VLOOKUP($C10,'Summary | 01 '!$C$6:$R$43,R$5,0) -> 1 | S10: =VLOOKUP($C10,'Summary | 01 '!$C$6:$R$43,S$5,0) -> 10.25 | W10: NAV | X10: =N27 -> 928.00806
C11: X-fusion | D11: Direct Investment | E11: =VLOOKUP($C11,'Summary | 01 '!$C$6:$R$43,E$5,0) -> Unrealized | F11: =VLOOKUP($C11,'Summary | 01 '!$C$6:$R$43,F$5,0) -> Elaine | G11: =VLOOKUP($C11,'Summary | 01 '!$C$6:$R$43,G$5,0) -> Mozn 2 | H11: =VLOOKUP($C11,'Summary | 01 '!$C$6:$R$43,H$5,0) -> 2022 | I11: =VLOOKUP($C11,'Summary | 01 '!$C$6:$R$43,I$5,0) -> Equity-TBC | J11: =VLOOKUP($C11,'Summary | 01 '!$C$6:$R$43,J$5,0) -> 0.05 | K11: =VLOOKUP($C11,'Summary | 01 '!$C$6:$R$43,K$5,0) -> 493.5 | L11: =VLOOKUP($C11,'Summary | 01 '!$C$6:$R$43,L$5,0) -> 493.50096 | ... O11: =VLOOKUP($C11,'Summary | 01 '!$C$6:$R$43,O$5,0) -> -69.434338 | P11: n/a | Q11: =VLOOKUP($C11,'Summary | 01 '!$C$6:$R$43,Q$5,0) -> NM | R11: =VLOOKUP($C11,'Summary | 01 '!$C$6:$R$43,R$5,0) -> 0.85930253 | S11: =VLOOKUP($C11,'Summary | 01 '!$C$6:$R$43,S$5,0) -> 0 | W11: Gain | X11: =O27 -> -35.531817
C12: Mena Mobile Inc (Debt) | D12: Debt Investment | E12: =VLOOKUP($C12,'Summary | 01 '!$C$6:$R$43,E$5,0) -> Unrealized | F12: =VLOOKUP($C12,'Summary | 01 '!$C$6:$R$43,F$5,0) -> Elaine | G12: =VLOOKUP($C12,'Summary | 01 '!$C$6:$R$43,G$5,0) -> Mozn | H12: =VLOOKUP($C12,'Summary | 01 '!$C$6:$R$43,H$5,0) -> 2021 | I12: =VLOOKUP($C12,'Summary | 01 '!$C$6:$R$43,I$5,0) -> Loan | J12: =VLOOKUP($C12,'Summary | 01 '!$C$6:$R$43,J$5,0) -> n/a | K12: =VLOOKUP($C12,'Summary | 01 '!$C$6:$R$43,K$5,0) -> 2.353982 | L12: =VLOOKUP($C12,'Summary | 01 '!$C$6:$R$43,L$5,0) -> 2.353982 | ... O12: =VLOOKUP($C12,'Summary | 01 '!$C$6:$R$43,O$5,0) -> 0 | P12: 0 | Q12: =VLOOKUP($C12,'Summary | 01 '!$C$6:$R$43,Q$5,0) -> 2.9802322e-09 | R12: =VLOOKUP($C12,'Summary | 01 '!$C$6:$R$43,R$5,0) -> 1 | S12: =VLOOKUP($C12,'Summary | 01 '!$C$6:$R$43,S$5,0) -> 0 | W12: YTD Gains | X12: =X11-227.4 -> -262.93182
C13: Esyasoft Holding (Debt) | D13: Debt Investment | E13: =VLOOKUP($C13,'Summary | 01 '!$C$6:$R$43,E$5,0) -> Realized | F13: =VLOOKUP($C13,'Summary | 01 '!$C$6:$R$43,F$5,0) -> Sushil | G13: =VLOOKUP($C13,'Summary | 01 '!$C$6:$R$43,G$5,0) -> Mozn | H13: =VLOOKUP($C13,'Summary | 01 '!$C$6:$R$43,H$5,0) -> 2021 | I13: =VLOOKUP($C13,'Summary | 01 '!$C$6:$R$43,I$5,0) -> Loan | J13: =VLOOKUP($C13,'Summary | 01 '!$C$6:$R$43,J$5,0) -> n/a | K13: =VLOOKUP($C13,'Summary | 01 '!$C$6:$R$43,K$5,0) -> 0.411765 | L13: =VLOOKUP($C13,'Summary | 01 '!$C$6:$R$43,L$5,0) -> 0.411765 | ... O13: =VLOOKUP($C13,'Summary | 01 '!$C$6:$R$43,O$5,0) -> 0.05901965 | P13: 0 | Q13: =VLOOKUP($C13,'Summary | 01 '!$C$6:$R$43,Q$5,0) -> 0.075277027 | R13: =VLOOKUP($C13,'Summary | 01 '!$C$6:$R$43,R$5,0) -> 1.1433333 | S13: =VLOOKUP($C13,'Summary | 01 '!$C$6:$R$43,S$5,0) -> 0 | W13: IRR | X13: =Q27 -> -0.019320041
C14: Jysan Technologies | D14: Direct Investment | E14: =VLOOKUP($C14,'Summary | 01 '!$C$6:$R$43,E$5,0) -> Unrealized | F14: =VLOOKUP($C14,'Summary | 01 '!$C$6:$R$43,F$5,0) -> Sushil | G14: =VLOOKUP($C14,'Summary | 01 '!$C$6:$R$43,G$5,0) -> Mozn 1 | H14: =VLOOKUP($C14,'Summary | 01 '!$C$6:$R$43,H$5,0) -> 2021 | I14: =VLOOKUP($C14,'Summary | 01 '!$C$6:$R$43,I$5,0) -> A (Ordinary Shares) | J14: =VLOOKUP($C14,'Summary | 01 '!$C$6:$R$43,J$5,0) -> 0.03 | K14: =VLOOKUP($C14,'Summary | 01 '!$C$6:$R$43,K$5,0) -> 20 | L14: =VLOOKUP($C14,'Summary | 01 '!$C$6:$R$43,L$5,0) -> 20 | ... O14: =VLOOKUP($C14,'Summary | 01 '!$C$6:$R$43,O$5,0) -> 0 | P14: 0 | Q14: =VLOOKUP($C14,'Summary | 01 '!$C$6:$R$43,Q$5,0) -> 2.9802322e-09 | R14: =VLOOKUP($C14,'Summary | 01 '!$C$6:$R$43,R$5,0) -> 1 | S14: =VLOOKUP($C14,'Summary | 01 '!$C$6:$R$43,S$5,0) -> 0
C15: Instadeep Limited | D15: Direct Investment | E15: =VLOOKUP($C15,'Summary | 01 '!$C$6:$R$43,E$5,0) -> To be Exited | F15: =VLOOKUP($C15,'Summary | 01 '!$C$6:$R$43,F$5,0) -> Ignasi | G15: =VLOOKUP($C15,'Summary | 01 '!$C$6:$R$43,G$5,0) -> Mozn | H15: =VLOOKUP($C15,'Summary | 01 '!$C$6:$R$43,H$5,0) -> 2021 | I15: =VLOOKUP($C15,'Summary | 01 '!$C$6:$R$43,I$5,0) -> B Prefs | J15: =VLOOKUP($C15,'Summary | 01 '!$C$6:$R$43,J$5,0) -> 0.011489406 | K15: =VLOOKUP($C15,'Summary | 01 '!$C$6:$R$43,K$5,0) -> 5.0278212 | L15: =VLOOKUP($C15,'Summary | 01 '!$C$6:$R$43,L$5,0) -> 5.0237202 | ... O15: =VLOOKUP($C15,'Summary | 01 '!$C$6:$R$43,O$5,0) -> 0 | P15: 0 | Q15: =VLOOKUP($C15,'Summary | 01 '!$C$6:$R$43,Q$5,0) -> 2.9802322e-09 | R15: =VLOOKUP($C15,'Summary | 01 '!$C$6:$R$43,R$5,0) -> 1 | S15: =VLOOKUP($C15,'Summary | 01 '!$C$6:$R$43,S$5,0) -> 0
C16: Cerebras Systems Inc | D16: Direct Investment | E16: =VLOOKUP($C16,'Summary | 01 '!$C$6:$R$43,E$5,0) -> Unrealized | F16: =VLOOKUP($C16,'Summary | 01 '!$C$6:$R$43,F$5,0) -> Ignasi | G16: =VLOOKUP($C16,'Summary | 01 '!$C$6:$R$43,G$5,0) -> Mozn | H16: =VLOOKUP($C16,'Summary | 01 '!$C$6:$R$43,H$5,0) -> 2021 | I16: =VLOOKUP($C16,'Summary | 01 '!$C$6:$R$43,I$5,0) -> F Prefs | J16: =VLOOKUP($C16,'Summary | 01 '!$C$6:$R$43,J$5,0) -> 0.01 | K16: =VLOOKUP($C16,'Summary | 01 '!$C$6:$R$43,K$5,0) -> 40 | L16: =VLOOKUP($C16,'Summary | 01 '!$C$6:$R$43,L$5,0) -> 39.999983 | ... O16: =VLOOKUP($C16,'Summary | 01 '!$C$6:$R$43,O$5,0) -> 0 | P16: 0 | Q16: =VLOOKUP($C16,'Summary | 01 '!$C$6:$R$43,Q$5,0) -> 2.9802322e-09 | R16: =VLOOKUP($C16,'Summary | 01 '!$C$6:$R$43,R$5,0) -> 1 | S16: =VLOOKUP($C16,'Summary | 01 '!$C$6:$R$43,S$5,0) -> 0
C17: Endless Studios LLC | D17: Direct Investment | E17: =VLOOKUP($C17,'Summary | 01 '!$C$6:$R$43,E$5,0) -> Unrealized | F17: =VLOOKUP($C17,'Summary | 01 '!$C$6:$R$43,F$5,0) -> Sushil | G17: =VLOOKUP($C17,'Summary | 01 '!$C$6:$R$43,G$5,0) -> Mozn | H17: =VLOOKUP($C17,'Summary | 01 '!$C$6:$R$43,H$5,0) -> 2021 | I17: =VLOOKUP($C17,'Summary | 01 '!$C$6:$R$43,I$5,0) -> A Pref Units | J17: =VLOOKUP($C17,'Summary | 01 '!$C$6:$R$43,J$5,0) -> 0.068571429 | K17: =VLOOKUP($C17,'Summary | 01 '!$C$6:$R$43,K$5,0) -> 3 | L17: =VLOOKUP($C17,'Summary | 01 '!$C$6:$R$43,L$5,0) -> 3 | ... O17: =VLOOKUP($C17,'Summary | 01 '!$C$6:$R$43,O$5,0) -> 0 | P17: 0 | Q17: =VLOOKUP($C17,'Summary | 01 '!$C$6:$R$43,Q$5,0) -> 2.9802322e-09 | R17: =VLOOKUP($C17,'Summary | 01 '!$C$6:$R$43,R$5,0) -> 1 | S17: =VLOOKUP($C17,'Summary | 01 '!$C$6:$R$43,S$5,0) -> 0
C18: Esyasoft Holding | D18: Direct Investment | E18: =VLOOKUP($C18,'Summary | 01 '!$C$6:$R$43,E$5,0) -> Realized | F18: =VLOOKUP($C18,'Summary | 01 '!$C$6:$R$43,F$5,0) -> Sushil | G18: =VLOOKUP($C18,'Summary | 01 '!$C$6:$R$43,G$5,0) -> Mozn | H18: =VLOOKUP($C18,'Summary | 01 '!$C$6:$R$43,H$5,0) -> 2020 | I18: =VLOOKUP($C18,'Summary | 01 '!$C$6:$R$43,I$5,0) -> Convertible Note | J18: =VLOOKUP($C18,'Summary | 01 '!$C$6:$R$43,J$5,0) -> n/a | K18: =VLOOKUP($C18,'Summary | 01 '!$C$6:$R$43,K$5,0) -> 2.5 | L18: =VLOOKUP($C18,'Summary | 01 '!$C$6:$R$43,L$5,0) -> 2.5 | ... O18: =VLOOKUP($C18,'Summary | 01 '!$C$6:$R$43,O$5,0) -> 2.5 | P18: 2.5 | Q18: =VLOOKUP($C18,'Summary | 01 '!$C$6:$R$43,Q$5,0) -> 0.36091766 | R18: =VLOOKUP($C18,'Summary | 01 '!$C$6:$R$43,R$5,0) -> 2 | S18: =VLOOKUP($C18,'Summary | 01 '!$C$6:$R$43,S$5,0) -> 0
C19: Heygears | D19: Direct Investment | E19: =VLOOKUP($C19,'Summary | 01 '!$C$6:$R$43,E$5,0) -> Unrealized | F19: =VLOOKUP($C19,'Summary | 01 '!$C$6:$R$43,F$5,0) -> Elaine | G19: =VLOOKUP($C19,'Summary | 01 '!$C$6:$R$43,G$5,0) -> Mozn | H19: =VLOOKUP($C19,'Summary | 01 '!$C$6:$R$43,H$5,0) -> 2020 | I19: =VLOOKUP($C19,'Summary | 01 '!$C$6:$R$43,I$5,0) -> Registered Capital | J19: =VLOOKUP($C19,'Summary | 01 '!$C$6:$R$43,J$5,0) -> 0.1438 | K19: =VLOOKUP($C19,'Summary | 01 '!$C$6:$R$43,K$5,0) -> 60 | L19: =VLOOKUP($C19,'Summary | 01 '!$C$6:$R$43,L$5,0) -> 60 | ... O19: =VLOOKUP($C19,'Summary | 01 '!$C$6:$R$43,O$5,0) -> 59.249804 | P19: -39.7 | Q19: =VLOOKUP($C19,'Summary | 01 '!$C$6:$R$43,Q$5,0) -> 0.34306269 | R19: =VLOOKUP($C19,'Summary | 01 '!$C$6:$R$43,R$5,0) -> 1.9874967 | S19: =VLOOKUP($C19,'Summary | 01 '!$C$6:$R$43,S$5,0) -> 0
C20: Beyond Limits | D20: Direct Investment | E20: =VLOOKUP($C20,'Summary | 01 '!$C$6:$R$43,E$5,0) -> Unrealized | F20: =VLOOKUP($C20,'Summary | 01 '!$C$6:$R$43,F$5,0) -> Divyesh | G20: =VLOOKUP($C20,'Summary | 01 '!$C$6:$R$43,G$5,0) -> Mozn | H20: =VLOOKUP($C20,'Summary | 01 '!$C$6:$R$43,H$5,0) -> 2020 | I20: =VLOOKUP($C20,'Summary | 01 '!$C$6:$R$43,I$5,0) -> C Prefs | J20: =VLOOKUP($C20,'Summary | 01 '!$C$6:$R$43,J$5,0) -> 0.09739482 | K20: =VLOOKUP($C20,'Summary | 01 '!$C$6:$R$43,K$5,0) -> 90 | L20: =VLOOKUP($C20,'Summary | 01 '!$C$6:$R$43,L$5,0) -> 90 | ... O20: =VLOOKUP($C20,'Summary | 01 '!$C$6:$R$43,O$5,0) -> 1.0015403 | P20: 0 | Q20: =VLOOKUP($C20,'Summary | 01 '!$C$6:$R$43,Q$5,0) -> 0.0038127035 | R20: =VLOOKUP($C20,'Summary | 01 '!$C$6:$R$43,R$5,0) -> 1.0111282 | S20: =VLOOKUP($C20,'Summary | 01 '!$C$6:$R$43,S$5,0) -> 0
C21: ONT plc | D21: Direct Investment | E21: =VLOOKUP($C21,'Summary | 01 '!$C$6:$R$43,E$5,0) -> Unrealized | F21: =VLOOKUP($C21,'Summary | 01 '!$C$6:$R$43,F$5,0) -> Divyesh | G21: =VLOOKUP($C21,'Summary | 01 '!$C$6:$R$43,G$5,0) -> Mozn | H21: =VLOOKUP($C21,'Summary | 01 '!$C$6:$R$43,H$5,0) -> 2020 | I21: =VLOOKUP($C21,'Summary | 01 '!$C$6:$R$43,I$5,0) -> Ordinary Shares | J21: =VLOOKUP($C21,'Summary | 01 '!$C$6:$R$43,J$5,0) -> 0.053819975 | K21: =VLOOKUP($C21,'Summary | 01 '!$C$6:$R$43,K$5,0) -> 141.47026 | L21: =VLOOKUP($C21,'Summary | 01 '!$C$6:$R$43,L$5,0) -> 141.47026 | ... O21: =VLOOKUP($C21,'Summary | 01 '!$C$6:$R$43,O$5,0) -> -19.090073 | P21: 275.8 | Q21: =VLOOKUP($C21,'Summary | 01 '!$C$6:$R$43,Q$5,0) -> -0.050375113 | R21: =VLOOKUP($C21,'Summary | 01 '!$C$6:$R$43,R$5,0) -> 0.86505946 | S21: =VLOOKUP($C21,'Summary | 01 '!$C$6:$R$43,S$5,0) -> 0
C22: Flyr Inc | D22: Direct Investment | E22: =VLOOKUP($C22,'Summary | 01 '!$C$6:$R$43,E$5,0) -> Unrealized | F22: =VLOOKUP($C22,'Summary | 01 '!$C$6:$R$43,F$5,0) -> Sushil | G22: =VLOOKUP($C22,'Summary | 01 '!$C$6:$R$43,G$5,0) -> Mozn | H22: =VLOOKUP($C22,'Summary | 01 '!$C$6:$R$43,H$5,0) -> 2019 | I22: =VLOOKUP($C22,'Summary | 01 '!$C$6:$R$43,I$5,0) -> B-1,2 Prefs | J22: =VLOOKUP($C22,'Summary | 01 '!$C$6:$R$43,J$5,0) -> 0.085025485 | K22: =VLOOKUP($C22,'Summary | 01 '!$C$6:$R$43,K$5,0) -> 10 | L22: =VLOOKUP($C22,'Summary | 01 '!$C$6:$R$43,L$5,0) -> 10 | ... O22: =VLOOKUP($C22,'Summary | 01 '!$C$6:$R$43,O$5,0) -> 68.08223 | P22: 68.1 | Q22: =VLOOKUP($C22,'Summary | 01 '!$C$6:$R$43,Q$5,0) -> 0.7832873 | R22: =VLOOKUP($C22,'Summary | 01 '!$C$6:$R$43,R$5,0) -> 7.808223 | S22: =VLOOKUP($C22,'Summary | 01 '!$C$6:$R$43,S$5,0) -> 0 | T22: Flyr Warrantsa
C23: Mena Mobile Inc | D23: Direct Investment | E23: =VLOOKUP($C23,'Summary | 01 '!$C$6:$R$43,E$5,0) -> Unrealized | F23: =VLOOKUP($C23,'Summary | 01 '!$C$6:$R$43,F$5,0) -> Elaine | G23: =VLOOKUP($C23,'Summary | 01 '!$C$6:$R$43,G$5,0) -> Mozn | H23: =VLOOKUP($C23,'Summary | 01 '!$C$6:$R$43,H$5,0) -> 2019 | I23: =VLOOKUP($C23,'Summary | 01 '!$C$6:$R$43,I$5,0) -> B Prefs | J23: =VLOOKUP($C23,'Summary | 01 '!$C$6:$R$43,J$5,0) -> 0.14 | K23: =VLOOKUP($C23,'Summary | 01 '!$C$6:$R$43,K$5,0) -> 8 | L23: =VLOOKUP($C23,'Summary | 01 '!$C$6:$R$43,L$5,0) -> 8 | ... O23: =VLOOKUP($C23,'Summary | 01 '!$C$6:$R$43,O$5,0) -> -4.9 | P23: -6.3 | Q23: =VLOOKUP($C23,'Summary | 01 '!$C$6:$R$43,Q$5,0) -> -0.21191685 | R23: =VLOOKUP($C23,'Summary | 01 '!$C$6:$R$43,R$5,0) -> 0.3875 | S23: =VLOOKUP($C23,'Summary | 01 '!$C$6:$R$43,S$5,0) -> 0
C24: Glass Earth Holdings LLC | D24: Debt Investment | E24: =VLOOKUP($C24,'Summary | 01 '!$C$6:$R$43,E$5,0) -> In default | F24: =VLOOKUP($C24,'Summary | 01 '!$C$6:$R$43,F$5,0) -> Marty | G24: =VLOOKUP($C24,'Summary | 01 '!$C$6:$R$43,G$5,0) -> Mozn | H24: =VLOOKUP($C24,'Summary | 01 '!$C$6:$R$43,H$5,0) -> 2019 | I24: =VLOOKUP($C24,'Summary | 01 '!$C$6:$R$43,I$5,0) -> Promissory Note | J24: =VLOOKUP($C24,'Summary | 01 '!$C$6:$R$43,J$5,0) -> n/a | K24: =VLOOKUP($C24,'Summary | 01 '!$C$6:$R$43,K$5,0) -> 8 | L24: =VLOOKUP($C24,'Summary | 01 '!$C$6:$R$43,L$5,0) -> 8 | ... O24: =VLOOKUP($C24,'Summary | 01 '!$C$6:$R$43,O$5,0) -> -8 | P24: -8 | Q24: =VLOOKUP($C24,'Summary | 01 '!$C$6:$R$43,Q$5,0) -> NM | R24: =VLOOKUP($C24,'Summary | 01 '!$C$6:$R$43,R$5,0) -> 0 | S24: =VLOOKUP($C24,'Summary | 01 '!$C$6:$R$43,S$5,0) -> 0
C25: Jollychic Holding Limited | D25: Direct Investment | E25: =VLOOKUP($C25,'Summary | 01 '!$C$6:$R$43,E$5,0) -> In Liquidation | F25: =VLOOKUP($C25,'Summary | 01 '!$C$6:$R$43,F$5,0) -> Elaine | G25: =VLOOKUP($C25,'Summary | 01 '!$C$6:$R$43,G$5,0) -> Mozn | H25: =VLOOKUP($C25,'Summary | 01 '!$C$6:$R$43,H$5,0) -> 2019 | I25: =VLOOKUP($C25,'Summary | 01 '!$C$6:$R$43,I$5,0) -> C+ Prefs | J25: =VLOOKUP($C25,'Summary | 01 '!$C$6:$R$43,J$5,0) -> 0.056999998 | K25: =VLOOKUP($C25,'Summary | 01 '!$C$6:$R$43,K$5,0) -> 65 | L25: =VLOOKUP($C25,'Summary | 01 '!$C$6:$R$43,L$5,0) -> 65 | ... O25: =VLOOKUP($C25,'Summary | 01 '!$C$6:$R$43,O$5,0) -> -65 | P25: -65 | Q25: =VLOOKUP($C25,'Summary | 01 '!$C$6:$R$43,Q$5,0) -> NM | R25: =VLOOKUP($C25,'Summary | 01 '!$C$6:$R$43,R$5,0) -> 0 | S25: =VLOOKUP($C25,'Summary | 01 '!$C$6:$R$43,S$5,0) -> 0
K27: =SUM(K9:K25) -> 979.26383 | L27: =SUM(L9:L25) -> 969.01067 | M27: =SUM(M9:M25) -> 5.4707846 | N27: =SUM(N9:N25) -> 928.00806 | O27: =SUM(O9:O25) -> -35.531817 | P27: =SUM(P9:P26) -> 227.4 | Q27: ='4. Mozn-IRR'!L16 -> -0.019320041 | R27: =(M27+N27)/L27 -> 0.96333186 | S27: =SUM(S9:S25) -> 10.25 | T27: =N27+M27-L27 -> -35.531817
C29: Honor Device Co Ltd | D29: Direct Investment | E29: =VLOOKUP($C29,'Summary | 01 '!$C$6:$R$43,E$5,0) -> Unrealized | F29: =VLOOKUP($C29,'Summary | 01 '!$C$6:$R$43,F$5,0) -> Elaine | G29: =VLOOKUP($C29,'Summary | 01 '!$C$6:$R$43,G$5,0) -> G42 3 | H29: =VLOOKUP($C29,'Summary | 01 '!$C$6:$R$43,H$5,0) -> 2022 | I29: =VLOOKUP($C29,'Summary | 01 '!$C$6:$R$43,I$5,0) -> Equity-TBC | J29: =VLOOKUP($C29,'Summary | 01 '!$C$6:$R$43,J$5,0) -> 0.018823528 | K29: =VLOOKUP($C29,'Summary | 01 '!$C$6:$R$43,K$5,0) -> 800 | L29: =VLOOKUP($C29,'Summary | 01 '!$C$6:$R$43,L$5,0) -> 800 | ... O29: =VLOOKUP($C29,'Summary | 01 '!$C$6:$R$43,O$5,0) -> 48.76999 | P29: n/a | Q29: =VLOOKUP($C29,'Summary | 01 '!$C$6:$R$43,Q$5,0) -> NM | R29: =VLOOKUP($C29,'Summary | 01 '!$C$6:$R$43,R$5,0) -> 1.0609625 | S29: =VLOOKUP($C29,'Summary | 01 '!$C$6:$R$43,S$5,0) -> 0 | W29: G42
C30: DriveNets | D30: Direct Investment | E30: =VLOOKUP($C30,'Summary | 01 '!$C$6:$R$43,E$5,0) -> Unrealized | F30: =VLOOKUP($C30,'Summary | 01 '!$C$6:$R$43,F$5,0) -> Anton | G30: =VLOOKUP($C30,'Summary | 01 '!$C$6:$R$43,G$5,0) -> G42 | H30: =VLOOKUP($C30,'Summary | 01 '!$C$6:$R$43,H$5,0) -> 2022 | I30: =VLOOKUP($C30,'Summary | 01 '!$C$6:$R$43,I$5,0) -> Equity-TBC | J30: =VLOOKUP($C30,'Summary | 01 '!$C$6:$R$43,J$5,0) -> 0.0943 | K30: =VLOOKUP($C30,'Summary | 01 '!$C$6:$R$43,K$5,0) -> 300 | L30: =VLOOKUP($C30,'Summary | 01 '!$C$6:$R$43,L$5,0) -> 300 | ... O30: =VLOOKUP($C30,'Summary | 01 '!$C$6:$R$43,O$5,0) -> 0 | P30: n/a | Q30: =VLOOKUP($C30,'Summary | 01 '!$C$6:$R$43,Q$5,0) -> NM | R30: =VLOOKUP($C30,'Summary | 01 '!$C$6:$R$43,R$5,0) -> 1 | S30: =VLOOKUP($C30,'Summary | 01 '!$C$6:$R$43,S$5,0) -> 0 | T30: DN Warrants b
C31: vTv Therapeutics Inc. | D31: Direct Investment | E31: =VLOOKUP($C31,'Summary | 01 '!$C$6:$R$43,E$5,0) -> Unrealized | F31: =VLOOKUP($C31,'Summary | 01 '!$C$6:$R$43,F$5,0) -> Divyesh | G31: =VLOOKUP($C31,'Summary | 01 '!$C$6:$R$43,G$5,0) -> G42 | H31: =VLOOKUP($C31,'Summary | 01 '!$C$6:$R$43,H$5,0) -> 2022 | I31: =VLOOKUP($C31,'Summary | 01 '!$C$6:$R$43,I$5,0) -> Ordinary Shares | J31: =VLOOKUP($C31,'Summary | 01 '!$C$6:$R$43,J$5,0) -> 0.099316564 | K31: =VLOOKUP($C31,'Summary | 01 '!$C$6:$R$43,K$5,0) -> 24.53125 | L31: =VLOOKUP($C31,'Summary | 01 '!$C$6:$R$43,L$5,0) -> 24.53125 | ... O31: =VLOOKUP($C31,'Summary | 01 '!$C$6:$R$43,O$5,0) -> -16.141218 | P31: n/a | Q31: =VLOOKUP($C31,'Summary | 01 '!$C$6:$R$43,Q$5,0) -> NM | R31: =VLOOKUP($C31,'Summary | 01 '!$C$6:$R$43,R$5,0) -> 0.34201405 | S31: =VLOOKUP($C31,'Summary | 01 '!$C$6:$R$43,S$5,0) -> 0 | T31: vTv $30m milestn payment c | W31: Invested | X31: =K38 -> 1522.4479
C32: North Summit Capital Fund | D32: Fund Investment | E32: =VLOOKUP($C32,'Summary | 01 '!$C$6:$R$43,E$5,0) -> Unrealized | F32: =VLOOKUP($C32,'Summary | 01 '!$C$6:$R$43,F$5,0) -> Elaine | G32: =VLOOKUP($C32,'Summary | 01 '!$C$6:$R$43,G$5,0) -> G42 | H32: =VLOOKUP($C32,'Summary | 01 '!$C$6:$R$43,H$5,0) -> 2020 | I32: =VLOOKUP($C32,'Summary | 01 '!$C$6:$R$43,I$5,0) -> LP | J32: =VLOOKUP($C32,'Summary | 01 '!$C$6:$R$43,J$5,0) -> n/a | K32: =VLOOKUP($C32,'Summary | 01 '!$C$6:$R$43,K$5,0) -> 300 | L32: =VLOOKUP($C32,'Summary | 01 '!$C$6:$R$43,L$5,0) -> 83.214653 | ... O32: =VLOOKUP($C32,'Summary | 01 '!$C$6:$R$43,O$5,0) -> -12.156692 | P32: 6.6 | Q32: =VLOOKUP($C32,'Summary | 01 '!$C$6:$R$43,Q$5,0) -> -0.064168629 | R32: =VLOOKUP($C32,'Summary | 01 '!$C$6:$R$43,R$5,0) -> 0.96555063 | S32: =VLOOKUP($C32,'Summary | 01 '!$C$6:$R$43,S$5,0) -> 217.81331 | W32: NAV | X32: =N38 -> 1279.4494
C33: New Space Capital Fund I | D33: Fund Investment | E33: =VLOOKUP($C33,'Summary | 01 '!$C$6:$R$43,E$5,0) -> Unrealized | F33: =VLOOKUP($C33,'Summary | 01 '!$C$6:$R$43,F$5,0) -> Sushil | G33: =VLOOKUP($C33,'Summary | 01 '!$C$6:$R$43,G$5,0) -> G42 | H33: =VLOOKUP($C33,'Summary | 01 '!$C$6:$R$43,H$5,0) -> 2020 | I33: =VLOOKUP($C33,'Summary | 01 '!$C$6:$R$43,I$5,0) -> LP | J33: =VLOOKUP($C33,'Summary | 01 '!$C$6:$R$43,J$5,0) -> n/a | K33: =VLOOKUP($C33,'Summary | 01 '!$C$6:$R$43,K$5,0) -> 28.098225 | L33: =VLOOKUP($C33,'Summary | 01 '!$C$6:$R$43,L$5,0) -> 11.058035 | ... O33: =VLOOKUP($C33,'Summary | 01 '!$C$6:$R$43,O$5,0) -> 6.1926309 | P33: 1 | Q33: =VLOOKUP($C33,'Summary | 01 '!$C$6:$R$43,Q$5,0) -> 0.1090443 | R33: =VLOOKUP($C33,'Summary | 01 '!$C$6:$R$43,R$5,0) -> 1.4784783 | S33: =VLOOKUP($C33,'Summary | 01 '!$C$6:$R$43,S$5,0) -> 17.040191 | W33: Gain | X33: =O38 -> 25.694726
C34: New Space Capital SCSp | D34: Fund Investment | E34: =VLOOKUP($C34,'Summary | 01 '!$C$6:$R$43,E$5,0) -> Unrealized | F34: =VLOOKUP($C34,'Summary | 01 '!$C$6:$R$43,F$5,0) -> Sushil | G34: =VLOOKUP($C34,'Summary | 01 '!$C$6:$R$43,G$5,0) -> G42 | H34: =VLOOKUP($C34,'Summary | 01 '!$C$6:$R$43,H$5,0) -> 2020 | I34: =VLOOKUP($C34,'Summary | 01 '!$C$6:$R$43,I$5,0) -> GP | J34: =VLOOKUP($C34,'Summary | 01 '!$C$6:$R$43,J$5,0) -> n/a | K34: =VLOOKUP($C34,'Summary | 01 '!$C$6:$R$43,K$5,0) -> 2.7058824 | L34: =VLOOKUP($C34,'Summary | 01 '!$C$6:$R$43,L$5,0) -> 2.7058824 | ... O34: =VLOOKUP($C34,'Summary | 01 '!$C$6:$R$43,O$5,0) -> 0 | P34: 0 | Q34: =VLOOKUP($C34,'Summary | 01 '!$C$6:$R$43,Q$5,0) -> 0 | R34: =VLOOKUP($C34,'Summary | 01 '!$C$6:$R$43,R$5,0) -> 1 | S34: =VLOOKUP($C34,'Summary | 01 '!$C$6:$R$43,S$5,0) -> 0 | W34: YTD Gains | X34: =X33-11.1 -> 14.594726
C35: Sinovation Disrupt Fund, L.P. | D35: Fund Investment | E35: =VLOOKUP($C35,'Summary | 01 '!$C$6:$R$43,E$5,0) -> Unrealized | F35: =VLOOKUP($C35,'Summary | 01 '!$C$6:$R$43,F$5,0) -> Elaine | G35: =VLOOKUP($C35,'Summary | 01 '!$C$6:$R$43,G$5,0) -> G42 | H35: =VLOOKUP($C35,'Summary | 01 '!$C$6:$R$43,H$5,0) -> 2020 | I35: =VLOOKUP($C35,'Summary | 01 '!$C$6:$R$43,I$5,0) -> LP | J35: =VLOOKUP($C35,'Summary | 01 '!$C$6:$R$43,J$5,0) -> n/a | K35: =VLOOKUP($C35,'Summary | 01 '!$C$6:$R$43,K$5,0) -> 50 | L35: =VLOOKUP($C35,'Summary | 01 '!$C$6:$R$43,L$5,0) -> 22.657267 | ... O35: =VLOOKUP($C35,'Summary | 01 '!$C$6:$R$43,O$5,0) -> -0.69768865 | P35: 3.5 | Q35: =VLOOKUP($C35,'Summary | 01 '!$C$6:$R$43,Q$5,0) -> -0.018159524 | R35: =VLOOKUP($C35,'Summary | 01 '!$C$6:$R$43,R$5,0) -> 0.97193724 | S35: =VLOOKUP($C35,'Summary | 01 '!$C$6:$R$43,S$5,0) -> 27.342733 | W35: IRR | X35: =Q38 -> 0.022939894
C36: Acies Investments Fund I, L.P. | D36: Fund Investment | E36: =VLOOKUP($C36,'Summary | 01 '!$C$6:$R$43,E$5,0) -> Unrealized | F36: =VLOOKUP($C36,'Summary | 01 '!$C$6:$R$43,F$5,0) -> Divyesh | G36: =VLOOKUP($C36,'Summary | 01 '!$C$6:$R$43,G$5,0) -> G42 | H36: =VLOOKUP($C36,'Summary | 01 '!$C$6:$R$43,H$5,0) -> 2021 | I36: =VLOOKUP($C36,'Summary | 01 '!$C$6:$R$43,I$5,0) -> LP | J36: =VLOOKUP($C36,'Summary | 01 '!$C$6:$R$43,J$5,0) -> 0.33 | K36: =VLOOKUP($C36,'Summary | 01 '!$C$6:$R$43,K$5,0) -> 17.1125 | L36: =VLOOKUP($C36,'Summary | 01 '!$C$6:$R$43,L$5,0) -> 14.015137 | ... O36: =VLOOKUP($C36,'Summary | 01 '!$C$6:$R$43,O$5,0) -> -0.2722965 | P36: 0 | Q36: =VLOOKUP($C36,'Summary | 01 '!$C$6:$R$43,Q$5,0) -> -0.021553859 | R36: =VLOOKUP($C36,'Summary | 01 '!$C$6:$R$43,R$5,0) -> 0.97333028 | S36: =VLOOKUP($C36,'Summary | 01 '!$C$6:$R$43,S$5,0) -> 3.0973625 | T36: 9.9% GP | Anchor
K38: =SUM(K29:K36) -> 1522.4479 | L38: =SUM(L29:L36) -> 1258.1822 | M38: =SUM(M29:M36) -> 4.4275637 | N38: =SUM(N29:N36) -> 1279.4494 | O38: =N38+M38-L38 -> 25.694726 | P38: =SUM(P29:P36) -> 11.1 | Q38: ='4. G42-IRR'!L16 -> 0.022939894 | R38: =(M38+N38)/L38 -> 1.0204221 | S38: =SUM(S29:S36) -> 265.29359 | T38: =N38+M38-L38 -> 25.694726
K40: =K27+K38 -> 2501.7117 | L40: =L27+L38 -> 2227.1929 | M40: =M27+M38 -> 9.8983484 | N40: =N27+N38 -> 2207.4575 | O40: =O27+O38 -> -9.8370913 | R40: =(M40+N40)/L40 -> 0.99558319 | S40: =S27+S38 -> 275.54359
I43: Checks: | K43: =K40='Summary | 01 '!J43 -> TRUE | L43: =ROUND(L40,3)=ROUND('Summary | 01 '!K43,3) -> TRUE | M43: =M40='Summary | 01 '!M43 -> TRUE | N43: =N40='Summary | 01 '!N43 -> TRUE | O43: =ROUND(O40,3)=ROUND('Summary | 01 '!O43,3) -> TRUE | S43: =S40='Summary | 01 '!L43 -> TRUE
B44: For Notes, refer to Summary | 01
O45: =P27-O27 -> 262.93182
O46: =K38-L38 -> 264.26563
O47: =O38-P38 -> 14.594726
O48: =SUM(M29:N31)-SUM(L29:L31) -> 32.628772
O49: =SUM(M32:N36)-SUM(L32:L36) -> -6.9340462
O50: =K38-L38 -> 264.26563

Sheet S | 03
C2: As of date | D2: ='Summary | 01 '!D2 -> 45016
I4: Changes during the Period
I5: 1a | J5: 1b | K5: 1c | L5: 1d | N5: 3 | O5: 4
C6: Deals | D6: Status | E6: Lead | F6: Investing Entity | G6: Instrument | H6: Listed / Unlisted | I6: No. of securities held (Movement during the Period) | N6: Dividend / Interest | O6: For Comments Refer to Note
I7: Opening | J7: Acquired | K7: Re-organisation | L7: Sale / Transfer | M7: Closing
C9: Direct Investments
C10: ='Summary | 01 '!C10 -> Jollychic Holding Limited | D10: ='Summary | 01 '!D10 -> In Liquidation | E10: ='Summary | 01 '!E10 -> Elaine | F10: ='Summary | 01 '!F10 -> Mozn | G10: ='Summary | 01 '!H10 -> C+ Prefs | I10: ='7. %'!D10 -> 13458655 | J10: 0 | K10: 0 | L10: 0 | M10: =I10 -> 13458655 | N10: 0 | O10: 1
C11: ='Summary | 01 '!C11 -> Mena Mobile Inc | D11: ='Summary | 01 '!D11 -> Unrealized | E11: ='Summary | 01 '!E11 -> Elaine | F11: ='Summary | 01 '!F11 -> Mozn | G11: ='Summary | 01 '!H11 -> B Prefs | I11: ='7. %'!D11 -> 21419829 | J11: 0 | K11: 0 | L11: 0 | M11: =I11 -> 21419829 | N11: 0 | O11: 2
C12: ='Summary | 01 '!C12 -> Flyr Inc | D12: ='Summary | 01 '!D12 -> Unrealized | E12: ='Summary | 01 '!E12 -> Sushil | F12: ='Summary | 01 '!F12 -> Mozn | G12: ='Summary | 01 '!H12 -> B-1,2 Prefs | I12: ='7. %'!D12 -> 5205482 | J12: 0 | K12: 0 | L12: 0 | N12: 0 | O12: 3
C13: ='Summary | 01 '!C13 -> Esyasoft Holding | D13: ='Summary | 01 '!D13 -> Realized | E13: ='Summary | 01 '!E13 -> Sushil | F13: ='Summary | 01 '!F13 -> Mozn | G13: ='Summary | 01 '!H13 -> Convertible Note | J13: 0 | K13: 0 | L13: 0 | N13: 0 | O13: 4
C14: ='Summary | 01 '!C14 -> Beyond Limits | D14: ='Summary | 01 '!D14 -> Unrealized | E14: ='Summary | 01 '!E14 -> Divyesh | F14: ='Summary | 01 '!F14 -> Mozn | G14: ='Summary | 01 '!H14 -> C Prefs | I14: ='7. %'!D14 -> 17670202 | J14: 0 | K14: 0 | L14: 0 | M14: =I14 -> 17670202 | N14: 0 | O14: 5
C15: ='Summary | 01 '!C15 -> ONT plc | D15: ='Summary | 01 '!D15 -> Unrealized | E15: ='Summary | 01 '!E15 -> Divyesh | F15: ='Summary | 01 '!F15 -> Mozn | G15: ='Summary | 01 '!H15 -> Ordinary Shares | H15: Listed | I15: ='7. %'!D15 -> 44328120 | J15: 0 | K15: 0 | L15: 0 | M15: =I15 -> 44328120 | N15: 0 | O15: 6
C16: ='Summary | 01 '!C16 -> Heygears | D16: ='Summary | 01 '!D16 -> Unrealized | E16: ='Summary | 01 '!E16 -> Elaine | F16: ='Summary | 01 '!F16 -> Mozn | G16: ='Summary | 01 '!H16 -> Registered Capital | I16: ='7. %'!D16 -> 3565017.2 | J16: 0 | K16: 0 | L16: 0 | M16: =I16 -> 3565017.2 | N16: 0 | O16: 7
C17: ='Summary | 01 '!C17 -> Jysan Technologies | D17: ='Summary | 01 '!D17 -> Unrealized | E17: ='Summary | 01 '!E17 -> Sushil | F17: ='Summary | 01 '!F17 -> Mozn 1 | G17: ='Summary | 01 '!H17 -> A (Ordinary Shares) | I17: =NAV!F16 -> 7959497 | J17: 0 | K17: 0 | L17: 0 | M17: =I17 -> 7959497 | N17: 0 | O17: 8
C18: ='Summary | 01 '!C18 -> Cerebras Systems Inc | D18: ='Summary | 01 '!D18 -> Unrealized | E18: ='Summary | 01 '!E18 -> Ignasi | F18: ='Summary | 01 '!F18 -> Mozn | G18: ='Summary | 01 '!H18 -> F Prefs | I18: =NAV!F17 -> 1441711 | J18: 0 | K18: 0 | L18: 0 | M18: =I18 -> 1441711 | N18: 0 | O18: 9
C19: ='Summary | 01 '!C19 -> Endless Studios LLC | D19: ='Summary | 01 '!D19 -> Unrealized | E19: ='Summary | 01 '!E19 -> Sushil | F19: ='Summary | 01 '!F19 -> Mozn | G19: ='Summary | 01 '!H19 -> A Pref Units | I19: =NAV!F18 -> 3000000 | J19: 0 | K19: 0 | L19: 0 | M19: =I19 -> 3000000 | N19: 0 | O19: 10
C20: ='Summary | 01 '!C20 -> Instadeep Limited | D20: ='Summary | 01 '!D20 -> To be Exited | E20: ='Summary | 01 '!E20 -> Ignasi | F20: ='Summary | 01 '!F20 -> Mozn | G20: ='Summary | 01 '!H20 -> B Prefs | I20: =NAV!F19 -> 33267 | J20: 0 | K20: 0 | L20: 0 | M20: =I20 -> 33267 | N20: 0 | O20: 11
C21: ='Summary | 01 '!C21 -> X-fusion | D21: ='Summary | 01 '!D21 -> Unrealized | E21: ='Summary | 01 '!E21 -> Elaine | F21: ='Summary | 01 '!F21 -> Mozn 2 | G21: ='Summary | 01 '!H21 -> Equity-TBC | O21: 12
C22: ='Summary | 01 '!C22 -> DriveNets | D22: ='Summary | 01 '!D22 -> Unrealized | E22: ='Summary | 01 '!E22 -> Anton | F22: ='Summary | 01 '!F22 -> G42 | G22: ='Summary | 01 '!H22 -> Equity-TBC | O22: 13
C23: ='Summary | 01 '!C23 -> vTv Therapeutics Inc. | D23: ='Summary | 01 '!D23 -> Unrealized | E23: ='Summary | 01 '!E23 -> Divyesh | F23: ='Summary | 01 '!F23 -> G42 | G23: ='Summary | 01 '!H23 -> Ordinary Shares | H23: Listed | I23: 10386274 | J23: 0 | K23: 0 | L23: 0 | M23: 10386274 | N23: 0 | O23: 14
C24: ='Summary | 01 '!C24 -> Honor Device Co Ltd | D24: ='Summary | 01 '!D24 -> Unrealized | E24: ='Summary | 01 '!E24 -> Elaine | F24: ='Summary | 01 '!F24 -> G42 3 | G24: ='Summary | 01 '!H24 -> Equity-TBC | O24: 15
C25: ='Summary | 01 '!C25 -> Applied AI Corporation Limited | D25: ='Summary | 01 '!D25 -> Unrealized | E25: ='Summary | 01 '!E25 -> Anton | F25: ='Summary | 01 '!F25 -> Mozn | G25: ='Summary | 01 '!H25 -> Convertible Note | J25: 0 | K25: 0 | L25: 0 | N25: 0 | O25: 16
C26: ='Summary | 01 '!C26 -> eSpace | D26: ='Summary | 01 '!D26 -> Unrealized | E26: ='Summary | 01 '!E26 -> Anton | F26: ='Summary | 01 '!F26 -> Mozn 4 | G26: ='Summary | 01 '!H26 -> SAFE note | O26: 17
C29: Debt Investments
C30: Glass Earth Holdings LLC | D30: In default | F30: Mozn | G30: Promissory Note | O30: 16
C31: Mena Mobile Inc (Debt) | D31: In default | E31: Elaine | F31: Mozn | G31: Loan | O31: 17
C32: Esyasoft Holding (Debt) | D32: Unrealized | E32: Sushil | F32: Mozn | G32: Loan | O32: 18
C35: Funds Investments
C36: New Space Capital Fund I | D36: Unrealized | E36: Sushil | F36: G42 | G36: LP | O36: 19
C37: New Space Capital SCSp | D37: Unrealized | E37: Sushil | F37: G42 | G37: GP | O37: 20
C38: North Summit Capital Fund | D38: Unrealized | E38: Elaine | F38: G42 | G38: LP | O38: 21
C39: Sinovation Disrupt Fund, L.P. | D39: Unrealized | E39: Elaine | F39: G42 | G39: LP | O39: 22
C40: Acies Investments Fund I, L.P. | D40: Unrealized | E40: Divyesh | F40: G42 | G40: LP | O40: 23
B47: Notes:
B48: 1 | C48: Jollychic | D48: During 2021, Jollychic Holding Ltd has filed for its liquidation. Therefore, investment is considered to be fully impaired in Dec 21.
B49: 2 | C49: Mena Mobile | D49: Investment is marked down based on the inputs received from 3rd party.
B50: 3 | C50: Flyr | D50: Within five years of the Initial Closing, for every USD 1mn of Qualifying Revenue generated, Flyr will issue, at no additional charge, 194,477 B-1 Prefs in the name of G42, up to a maximum of 1,264,100 B-1 Prefs.
B51: 4 | C51: Esyasoft Holding | D51: Investment in Esyasoft is in the form of Convertible Note which will convert to 21% interest on conversion on a fully diluted basis. As per Dec 2020 FS of Esyasoft, the CN was reflected as Debt - Exit of US$ 2.5 Mn Convertible Note @ 2.0x (MoC) i.e. US$ 5 Mn in May 22 - US$ 0.4 Mn represents Working Capital Loan - fully exited in Dec 22
B52: 5 | C52: Beyond Limits | D52: Business targeting raising funds by the end of FY2022
B53: 6 | C53: ONT plc
B54: 7 | C54: Heygears | D54: Mozn's holding is RMB 4,753,356.29 of the Registered Capital.
B55: 8 | C55: Jysan Technologies | D55: - 50% of the investment has been financed by profit sharing loan. - Further, in case of exit of G42’s investment, 50% of the sale proceeds shall be paid to the lender as full and final settlement of the outstanding liability - Exit for this investment is under process. Buyback agreement is pending for signature internally. (Relevant documents to be perused by the consolidation / reporting team for details and corresponding implications, if any) - Dividend receivable amounting to US$ 3.2 m will be waived upon exit of this investment
B56: 9 | C56: Cerebras Systems Inc | D56: The investment is currently undergoing a CFIUS review.
B57: 10 | C57: Endless Studios LLC
B58: 11 | C58: Instadeep Limited | D58: Received an acquisition bid from BioNtech
B59: 12 | C59: X-fusion | D59: RMB 80 Mn of Registered Capital for RMB 5.7 Bn
B60: 13 | C60: Drivenets | D60: Share warrants excisable upon the achievement of target revenue of clients by referred G42. The milestones of each target revenue and respective conversion were stated in the Term Sheet.
B61: 14 | C61: vTv Therapeutics : | D61: G42 Investments AI Holding RSC Ltd (G42 Investments) has been issued 10.3 million shares representing c. 10% of vTv on a fully diluted basis. 50% of the consideration has been paid and the remaining 50% will be payable within next 12 months. The promissory note to pay the second US$12.5 million has been issued by G42 Investments with an equity commitment letter/guarantee in place between Group 42 Holdings Ltd and G42 Investments with Group 42 Holdings to stand behind G42 Investments obligations under the promissory note. The agreements also provide for the potential issuance of US$ 30 million in additional shares of Class A Common Stock to G42 Investments (or cash in lieu of such issuance at the option of G42 Investments) if the United States Food and Drug Administration (the “FDA”) approves the marketing and sale of a pharmaceutical product containing TTP399 (Relevant documents to be perused by the consolidation / reporting team for details and corresponding implications, if any)
B62: 15 | C62: Honor | D62: Invested in Q3 2022; During Dec 22, $250m was offloaded to another investor at cost
B63: 16 | C63: Glass Earth Holdings LLC | D63: Written off. Debt security of Glass Earth issued in 2019 were fully provided for.
B64: 17 | C64: Mena Mobile (Debt) | D64: Outstanding
B65: 18 | C65: Esyasoft Holding (Debt) | D65: Outstanding
B66: 19 | C66: New Space Capital Fund I | D66: G42 negotiated conversion of €2.3m GP investment into LP investment to vote in favor of new LP proposal. Final details of conversion awaited
B67: 20 | C67: New Space Capital SCSp | D67: Ibid
B68: 21 | C68: North Summit Capital | D68: Portfolio Exit Plan in Progress
B69: 22 | C69: Sinovation Disrupt Fund | D69: Expect valuation to rise as some of its portfolio companies are in the market to raise new funds
B70: 23 | C70: Acies Investments Fund I, LP
B72: 17,18,19: no comments

Sheet NAV
B2: NAV Date | C2: ='Summary | 01 '!D2 -> 45016
B5: Investments | C5: Investing Entity | D5: Instrument | E5: Carrying Value | F5: Current Shares/Units | H5: Comment
E6: USD, Million | F6: # | G6: USD | J6: Updated as on: | K6: =C2 -> 45016
E7: ="NAV | "& TEXT(C2,"dd")&" "&TEXT(C2,"mmm")&" "&TEXT(C2,"yyyy") -> NAV | 31 Mar 2023 | G7: ="PPS |" & TEXT(C2,"dd")&" "&TEXT(C2,"mmm")&" "&TEXT(C2,"yyyy") -> PPS |31 Mar 2023 | L7: source
B8: Direct Investments | J8: ONT Share price | K8: 2.225 | L8: link
B9: ='Summary | 01 '!C10 -> Jollychic Holding Limited | C9: ='Summary | 01 '!F10 -> Mozn | D9: ='Summary | 01 '!H10 -> C+ Prefs | E9: =F9*G9*10^-6 -> 0 | F9: =SUM('CF (Equity, Debt)'!J4:J6) -> 13458655 | H9: In Liquidation | J9: VTVT Share price | K9: 0.8078 | L9: link
B10: ='Summary | 01 '!C11 -> Mena Mobile Inc | C10: ='Summary | 01 '!F11 -> Mozn | D10: ='Summary | 01 '!H11 -> B Prefs | E10: 3.1 | F10: ='CF (Equity, Debt)'!J7 -> 21419829 | H10: As per 3rd Party | Ardent Estimates | J10: GBP USD | K10: 1.2408 | L10: xe.com
B11: ='Summary | 01 '!C12 -> Flyr Inc | C11: ='Summary | 01 '!F12 -> Mozn | D11: ='Summary | 01 '!H12 -> B-1,2 Prefs | E11: =F11*G11*10^-6*(1-20%) -> 78.08223 | F11: 5205482 | G11: 18.75 | H11: At Series C PPS $18.75/share with 20% discount | J11: USD RMB | K11: 6.875 | L11: xe.com
B12: ='Summary | 01 '!C13 -> Esyasoft Holding | C12: ='Summary | 01 '!F13 -> Mozn | D12: ='Summary | 01 '!H13 -> Convertible Note | E12: 0 | F12: n/a | H12: Exited at $5m (10th May) | Residual value = 0 | J12: EURUSD | K12: 1.08705 | L12: xe.com
B13: ='Summary | 01 '!C14 -> Beyond Limits | C13: ='Summary | 01 '!F14 -> Mozn | D13: ='Summary | 01 '!H14 -> C Prefs | E13: =F13*G13*10^-6 -> 91.00154 | F13: =SUM('CF (Equity, Debt)'!J11:J14) -> 17670202 | G13: 5.15 | H13: Held at cost (as per revised management guidance)
B14: ='Summary | 01 '!C15 -> ONT plc | C14: ='Summary | 01 '!F15 -> Mozn | D14: ='Summary | 01 '!H15 -> Ordinary Shares | E14: =F14*G14*10^-6 -> 122.38019 | F14: 44328120 | G14: =K8*K10 -> 2.76078 | H14: Listed & marked to market
B15: ='Summary | 01 '!C16 -> Heygears | C15: ='Summary | 01 '!F16 -> Mozn | D15: ='Summary | 01 '!H16 -> Registered Capital | E15: =K25/1000000 -> 119.2498 | F15: ='CF (Equity, Debt)'!J20 -> 4753356.3 | H15: Adjusted for currency. Negotiating final terms of a new round at $1.5Bn pre
B16: ='Summary | 01 '!C17 -> Jysan Technologies | C16: ='Summary | 01 '!F17 -> Mozn 1 | D16: ='Summary | 01 '!H17 -> A (Ordinary Shares) | E16: =-'CF (Equity, Debt)'!E21 -> 20 | F16: ='CF (Equity, Debt)'!J21 -> 7959497 | G16: =E16*10^6/F16 -> 2.5127216 | H16: Held at cost. | J16: Heygears Oct 22 | O16: New Space Capital
B17: ='Summary | 01 '!C18 -> Cerebras Systems Inc | C17: ='Summary | 01 '!F18 -> Mozn | D17: ='Summary | 01 '!H18 -> F Prefs | E17: =-'CF (Equity, Debt)'!E22 -> 39.999983 | F17: ='CF (Equity, Debt)'!J22 -> 1441711 | H17: Held at cost.
B18: ='Summary | 01 '!C19 -> Endless Studios LLC | C18: ='Summary | 01 '!F19 -> Mozn | D18: ='Summary | 01 '!H19 -> A Pref Units | E18: =-'CF (Equity, Debt)'!E23 -> 3 | F18: ='CF (Equity, Debt)'!J23 -> 3000000 | H18: Held at cost. | J18: Post Valuation closed in June 2021 (RMB) | K18: 7500000000 | O18: EUR | P18: 3Q22 | Q18: 4Q22
B19: ='Summary | 01 '!C20 -> Instadeep Limited | C19: ='Summary | 01 '!F20 -> Mozn | D19: ='Summary | 01 '!H20 -> B Prefs | E19: =-'CF (Equity, Debt)'!E24 -> 5.0237202 | F19: ='CF (Equity, Debt)'!J24 -> 33267 | H19: Held at cost. | J19: G42 Stake | K19: 0.143832 | O19: Commitment | P19: 23234462 | Q19: 23234462 | R19: source: distribution letter
B20: ='Summary | 01 '!C21 -> X-fusion | C20: ='Summary | 01 '!F21 -> Mozn 2 | D20: ='Summary | 01 '!H21 -> Equity-TBC | E20: =5810000000/K11/1000000*(1-49.82%) -> 424.06662 | H20: Held at original cost, adjusted for currency, and ownership | J20: G42 Valuation before Discount (RMB) | K20: 1078740000 | O20: Capital Contribution | P20: 19178323 | Q20: 9436936
B21: ='Summary | 01 '!C22 -> DriveNets | C21: ='Summary | 01 '!F22 -> G42 | D21: ='Summary | 01 '!H22 -> Equity-TBC | E21: =-SUM('CF (Equity, Debt)'!E26:E27) -> 300 | H21: Held at cost. | J21: Liquidity Discount | K21: 0.2 | O21: Unfunded | P21: =P19-P20 -> 4056139 | Q21: =Q19-Q20 -> 13797526
B22: ='Summary | 01 '!C23 -> vTv Therapeutics Inc. | C22: ='Summary | 01 '!F23 -> G42 | D22: ='Summary | 01 '!H23 -> Ordinary Shares | E22: =(F22*G22)*10^-6 -> 8.3900321 | F22: ='CF (Equity, Debt)'!J29 -> 10386274 | G22: =K9 -> 0.8078 | H22: Listed & marked to market | J22: Minority Holding Discount | K22: 0.05 | O22: Unrealized Gain | P22: 13103567 | Q22: 3803379
B23: ='Summary | 01 '!C24 -> Honor Device Co Ltd | C23: ='Summary | 01 '!F24 -> G42 3 | D23: ='Summary | 01 '!H24 -> Equity-TBC | E23: =310000000000/K11/1000000*4.705882%*0.8/2 -> 848.76999 | F23: n/a | H23: Closing a new round at RMB 310B. Adjusted for currency. | J23: G42 Valuation (RMB) | K23: =K20*(1-K21)*(1-K22) -> 819842400 | O23: NAV | P23: 32325017 | Q23: 13150169 | R23: source: distribution letter
B24: ='Summary | 01 '!C25 -> Applied AI Corporation Limited | C24: ='Summary | 01 '!F25 -> Mozn | D24: ='Summary | 01 '!H25 -> Convertible Note | E24: 4.75 | F24: n/a | H24: Held at cost. | J24: Exchange Rate (RMB/USD) | K24: =K11 -> 6.875 | O24: Capital Return | Q24: =P20-Q20 -> 9741387 | R24: estimated
B25: eSpace | C25: ='Summary | 01 '!F26 -> Mozn 4 | D25: ='Summary | 01 '!H26 -> SAFE note | E25: 15 | F25: n/a | H25: Held at cost. | J25: G42 Valuation (USD) | K25: =K23/K24 -> 1.192498e+08 | O25: Interest Capitalization | Q25: =Q26-Q24 -> 2728214 | R25: estimated
J26: Investment Cost of G42 (USD) | K26: 60000000 | O26: Total Distribution Received | Q26: 12469601 | R26: source: distribution letters, Gino
J27: Investment Multiple | K27: 1.9039182 | O27: Remaining Commitment | Q27: =15675627.21 -> 15675627 | R27: source: distribution letter
B29: Debt Investments
B30: Glass Earth Holdings LLC | C30: Mozn | D30: Promissory Note | E30: ='Summary | 01 '!N30 -> 0 | H30: In default | O30: in USD, Mn
B31: Mena Mobile Inc (Debt) | C31: Mozn | D31: Loan | E31: ='Summary | 01 '!N31 -> 2.353982 | H31: Held at cost. | O31: Capital Committed | P31: =P32+P33 -> 28.098225
B32: Esyasoft Holding (Debt) | C32: Mozn | D32: Loan | E32: 0 | H32: Received payment of $470,784.65 ($411K+$59K) | O32: Capital Called | P32: =-SUM('CF (Funds)'!D31:D35)-Q24*1.08341*10^-6 -> 11.058035 | Q32: =Q20*10^-6*K12 -> 10.258421
O33: Remaining | P33: =Q27*10^-6*K12 -> 17.040191
O34: NAV | P34: =Q23*10^-6*K12 -> 14.294891
J35: CHECKS
B36: Funds Investments
B37: New Space Capital Fund I | C37: G42 | D37: LP | E37: =Q23*10^-6*K12 -> 14.294891 | H37: Q3'22 reported | J37: Equity | K37: =SUM(E9:E25) -> 2082.8141
B38: New Space Capital SCSp | C38: G42 | D38: GP | E38: 2.7058824 | H38: Q3'22 at cost | J38: Debt | K38: =SUM(E30:E32) -> 2.353982
B39: North Summit Capital Fund | C39: G42 | D39: LP | E39: 70.03 | H39: Q3'22 reported | J39: Funds | K39: =SUM(E37:E41) -> 122.28936
B40: Sinovation Disrupt Fund, L.P. | C40: G42 | D40: LP | E40: =18.884222-'CF (Funds)'!D16 -> 21.51575 | H40: Q3'22 reported | J40: Total | K40: =SUM(K37:K39) -> 2207.4575
B41: Acies Investments Fund I, L.P. | C41: G42 | D41: LP | E41: =10.354566-'CF (Funds)'!D43 -> 13.742841 | H41: Q3'22 reported | K41: =K40='Summary | 01 '!N43 -> TRUE
K42: =K40='4.All'!M9 -> TRUE
B44: Note:
B45: • For estimating the NAV their listed share price for ONT and vTv Therapeutics is taken

Sheet CF (Equity, Debt)
B2: E Q U I T Y
B3: Accounting entity | C3: Investment | D3: Payment date | E3: Contributions (in USD, Mn) | F3: Distributions (in USD, Mn) | G3: Currency | H3: Investment Amt (investee currency) | I3: Investment Amount (USD) | J3: Consideration (shares) | K3: Comment
B4: =VLOOKUP(C4,'Summary | 01 '!$C$10:$F$40,4,0) -> Mozn | C4: Jollychic Holding Limited | D4: 43470 | E4: =-I4*10^-6 -> -30 | G4: USD | H4: 30000000 | I4: =H4 -> 30000000 | J4: 6100312 | N4: NOTES
B5: =VLOOKUP(C5,'Summary | 01 '!$C$10:$F$40,4,0) -> Mozn | C5: Jollychic Holding Limited | D5: 43724 | E5: =-I5*10^-6 -> -20 | G5: USD | H5: 20000000 | I5: =H5 -> 20000000 | J5: 4204767.4 | N5: USD AED | O5: 3.678
B6: =VLOOKUP(C6,'Summary | 01 '!$C$10:$F$40,4,0) -> Mozn | C6: Jollychic Holding Limited | D6: 43724 | E6: =-I6*10^-6 -> -15 | G6: USD | H6: 15000000 | I6: =H6 -> 15000000 | J6: 3153575.6
B7: =VLOOKUP(C7,'Summary | 01 '!$C$10:$F$40,4,0) -> Mozn | C7: Mena Mobile Inc | D7: 43563 | E7: =-I7*10^-6 -> -8 | G7: USD | H7: 8000000 | I7: =H7 -> 8000000 | J7: 21419829
B8: =VLOOKUP(C8,'Summary | 01 '!$C$10:$F$40,4,0) -> Mozn | C8: Flyr Inc | D8: 43570 | E8: =-I8*10^-6 -> -4.9999981 | G8: USD | H8: 4999998.1 | I8: =H8 -> 4999998.1 | J8: 2625467
B9: =VLOOKUP(C9,'Summary | 01 '!$C$10:$F$40,4,0) -> Mozn | C9: Flyr Inc | D9: 43915 | E9: =-I9*10^-6 -> -5.0000019 | G9: USD | H9: =10000000-H8 -> 5000001.9 | I9: =H9 -> 5000001.9 | J9: 2580015
B10: =VLOOKUP(C10,'Summary | 01 '!$C$10:$F$40,4,0) -> Mozn | C10: Esyasoft Holding | D10: 43870 | E10: =-I10*10^-6 -> -2.5 | G10: USD | H10: 2500000 | I10: =H10 -> 2500000 | J10: N/A
B11: =VLOOKUP(C11,'Summary | 01 '!$C$10:$F$40,4,0) -> Mozn | C11: Beyond Limits | D11: 43879 | E11: =-I11*10^-6 -> -20 | G11: USD | H11: 20000000 | I11: =H11 -> 20000000 | J11: 4084038
B12: =VLOOKUP(C12,'Summary | 01 '!$C$10:$F$40,4,0) -> Mozn | C12: Beyond Limits | D12: 43921 | E12: =-I12*10^-6 -> -30 | G12: USD | H12: 30000000 | I12: =H12 -> 30000000 | J12: 5822642
B13: =VLOOKUP(C13,'Summary | 01 '!$C$10:$F$40,4,0) -> Mozn | C13: Beyond Limits | D13: 43989 | E13: =-I13*10^-6 -> -30 | G13: USD | H13: 30000000 | I13: =H13 -> 30000000 | J13: 5822642
B14: =VLOOKUP(C14,'Summary | 01 '!$C$10:$F$40,4,0) -> Mozn | C14: Beyond Limits | D14: 44103 | E14: =-I14*10^-6 -> -10 | G14: USD | H14: 10000000 | I14: =H14 -> 10000000 | J14: 1940880
B15: =VLOOKUP(C15,'Summary | 01 '!$C$10:$F$40,4,0) -> Mozn | C15: ONT plc | D15: 43968 | E15: =-I15*10^-6 -> -50 | G15: USD | H15: 50000000 | I15: 50000000 | J15: 15277680
B16: =VLOOKUP(C16,'Summary | 01 '!$C$10:$F$40,4,0) -> Mozn | C16: ONT plc | D16: 44006 | E16: =-I16*10^-6 -> -27.268351 | G16: GBP | H16: 21029625 | I16: 27268351 | J16: 9000000
B17: =VLOOKUP(C17,'Summary | 01 '!$C$10:$F$40,4,0) -> Mozn | C17: ONT plc | D17: 43837 | E17: =-I17*10^-6 -> -18.109441 | G17: GBP | H17: 14386480 | I17: 18109441 | J17: 6362180
B18: =VLOOKUP(C18,'Summary | 01 '!$C$10:$F$40,4,0) -> Mozn | C18: ONT plc | D18: 43990 | E18: =-I18*10^-6 -> -34.851687 | G18: GBP | H18: 26085573 | I18: 34851687 | J18: 11381140
B19: =VLOOKUP(C19,'Summary | 01 '!$C$10:$F$40,4,0) -> Mozn | C19: ONT plc | D19: 44315 | E19: =-I19*10^-6 -> -11.24078 | G19: GBP | H19: 8074920 | I19: 11240780 | J19: 2307120
B20: =VLOOKUP(C20,'Summary | 01 '!$C$10:$F$40,4,0) -> Mozn | C20: Heygears | D20: 44166 | E20: =-I20*10^-6 -> -60 | G20: USD | H20: 60000000 | I20: =H20 -> 60000000 | J20: 4753356.3
B21: =VLOOKUP(C21,'Summary | 01 '!$C$10:$F$40,4,0) -> Mozn 1 | C21: Jysan Technologies | D21: 44363 | E21: =-I21*10^-6 -> -20 | G21: USD | H21: 20000000 | I21: =H21 -> 20000000 | J21: 7959497
B22: =VLOOKUP(C22,'Summary | 01 '!$C$10:$F$40,4,0) -> Mozn | C22: Cerebras Systems Inc | D22: 44488 | E22: =-I22*10^-6 -> -39.999983 | G22: USD | H22: 39999983 | I22: =H22 -> 39999983 | J22: 1441711
B23: =VLOOKUP(C23,'Summary | 01 '!$C$10:$F$40,4,0) -> Mozn | C23: Endless Studios LLC | D23: 44494 | E23: =-I23*10^-6 -> -3 | G23: USD | H23: 3000000 | I23: =H23 -> 3000000 | J23: 3000000
B24: =VLOOKUP(C24,'Summary | 01 '!$C$10:$F$40,4,0) -> Mozn | C24: Instadeep Limited | D24: 44550 | E24: =-I24*10^-6 -> -5.0237202 | G24: GBP | H24: 3679995.5 | I24: 5023720.2 | J24: 33267
B25: =VLOOKUP(C25,'Summary | 01 '!$C$10:$F$40,4,0) -> Mozn 2 | C25: X-fusion | D25: 44574 | E25: =-I25*10^-6 -> -493.50096 | G25: USD | H25: 8.9350096e+08 | I25: 4.9350096e+08
B26: =VLOOKUP(C26,'Summary | 01 '!$C$10:$F$40,4,0) -> G42 | C26: DriveNets | D26: 44643 | E26: =-I26*10^-6 -> -200 | G26: USD | H26: 200000000 | I26: =H26 -> 200000000
B27: =VLOOKUP(C27,'Summary | 01 '!$C$10:$F$40,4,0) -> G42 | C27: DriveNets | D27: 44680 | E27: =-I27*10^-6 -> -100 | G27: USD | H27: 100000000 | I27: =H27 -> 100000000
B28: =VLOOKUP(C28,'Summary | 01 '!$C$10:$F$40,4,0) -> Mozn | C28: Esyasoft Holding | D28: 44691 | F28: 5 | G28: USD
B29: =VLOOKUP(C29,'Summary | 01 '!$C$10:$F$40,4,0) -> G42 | C29: vTv Therapeutics Inc. | D29: 44712 | E29: =-I29*10^-6 -> -12.5 | G29: USD | H29: 12500000 | I29: =H29 -> 12500000 | J29: 10386274
B30: =VLOOKUP(C30,'Summary | 01 '!$C$10:$F$40,4,0) -> G42 3 | C30: Honor Device Co Ltd | D30: 44769 | E30: =-I30*10^-6 -> -600 | G30: USD | H30: 600000000 | I30: =H30 -> 600000000
B31: =VLOOKUP(C31,'Summary | 01 '!$C$10:$F$40,4,0) -> G42 3 | C31: Honor Device Co Ltd | D31: 44849 | E31: =-I31*10^-6 -> -200 | G31: USD | H31: 200000000 | I31: =H31 -> 200000000
B32: =VLOOKUP(C32,'Summary | 01 '!$C$10:$F$40,4,0) -> Mozn | C32: Applied AI Corporation Limited | D32: 44861 | E32: =-I32*10^-6 -> -4.75 | G32: USD | H32: 4750000 | I32: =H32 -> 4750000
B33: =VLOOKUP(C33,'Summary | 01 '!$C$10:$F$40,4,0) -> Mozn 4 | C33: eSpace | D33: 44892 | E33: =-I33*10^-6 -> -15 | G33: USD | H33: 15000000 | I33: =H33 -> 15000000
B34: =VLOOKUP(C34,'Summary | 01 '!$C$10:$F$40,4,0) -> G42 | C34: vTv Therapeutics Inc. | D34: 44985 | E34: =-I34*10^-6 -> -12.03125 | G34: USD | H34: 12031250 | I34: =H34 -> 12031250
B36: L O AN | P R O M I S S O R Y N O T E S | D E B T
B37: Mozn | C37: Glass Earth Holdings LLC | D37: 43635 | E37: -8 | G37: USD | H37: 8000000 | I37: =H37 -> 8000000
B38: Mozn | C38: Mena Mobile Inc (Debt) | D38: 44293 | E38: -2.353982 | G38: USD | H38: =-E38*10^6 -> 2353982 | I38: =H38 -> 2353982
B39: Mozn | C39: Esyasoft Holding (Debt) | D39: 44384 | E39: =-I39*10^-6 -> -0.411765 | G39: USD | H39: 2500000 | I39: 411765
B40: Mozn | C40: Esyasoft Holding (Debt) | D40: 44902 | F40: =(411765+59019.65)*10^-6 -> 0.47078465 | G40: USD | H40: =F40*10^6 -> 470784.65 | I40: 470784.65

Sheet CF (Funds)
A2: Entity | B2: Investment | C2: Payment date | D2: Contributions (USD, Mn) | E2: Distributions (USD, Mn) | F2: Currency | G2: Cashflows | H2: Description
A3: G42 | B3: Sinovation Disrupt Fund, L.P. | C3: 44153 | D3: =G3 -> -10.5 | F3: USD | G3: -10.5 | H3: 1st Capital Call
A4: G42 | B4: Sinovation Disrupt Fund, L.P. | C4: 44238 | D4: =G4 -> 4.214027 | F4: USD | G4: 4.214027 | H4: Partial return of the 1st Capital Call
A5: G42 | B5: Sinovation Disrupt Fund, L.P. | C5: 44238 | E5: =G5 -> 0.05044835 | F5: USD | G5: 0.05044835 | H5: Interest Catchup
A6: G42 | B6: Sinovation Disrupt Fund, L.P. | C6: 44285 | D6: =G6 -> -6.433746 | F6: USD | G6: -6.433746 | H6: 2nd Capital Calll
A7: G42 | B7: Sinovation Disrupt Fund, L.P. | C7: 44269 | D7: =G7 -> 1.1352074 | F7: USD | G7: 1.1352074 | H7: Return of Capital fund
A8: G42 | B8: Sinovation Disrupt Fund, L.P. | C8: 44269 | E8: =G8 -> 0.0259 | F8: USD | G8: 0.0259 | H8: Interest Catchup
A9: G42 | B9: Sinovation Disrupt Fund, L.P. | C9: 44483 | D9: =G9 -> -7.567138 | F9: USD | G9: -7.567138 | H9: 3rd Capital Call
A10: G42 | B10: Sinovation Disrupt Fund, L.P. | C10: 44554 | D10: =G10 -> -7.385016 | F10: USD | G10: -7.385016 | H10: 4th Capital Call
A11: G42 | B11: Sinovation Disrupt Fund, L.P. | C11: 44554 | D11: =G11 -> 4.0733456 | F11: USD | G11: 4.0733456 | H11: Return of Capital fund
A12: G42 | B12: Sinovation Disrupt Fund, L.P. | C12: 44554 | E12: =G12 -> 0.139694 | F12: USD | G12: 0.139694 | H12: Interest Catchup
A13: G42 | B13: Sinovation Disrupt Fund, L.P. | C13: 44703 | D13: =G13 -> 5.673074 | F13: USD | G13: 5.673074 | H13: Return of Capital fund
A14: G42 | B14: Sinovation Disrupt Fund, L.P. | C14: 44703 | E14: =G14 -> 0.227786 | F14: USD | G14: 0.227786 | H14: Interest Catchup
A15: G42 | B15: Sinovation Disrupt Fund, L.P. | C15: 44776 | D15: =G15 -> -3.235493 | F15: USD | G15: -3.235493 | H15: 5th Capital Call
A16: G42 | B16: Sinovation Disrupt Fund, L.P. | C16: 44960 | D16: =G16 -> -2.631528 | F16: USD | G16: -2.631528 | H16: 6th Capital Call
A17: G42 | B17: North Summit Capital Fund | C17: 43665 | D17: =G17 -> -3 | F17: USD | G17: -3 | H17: 1st Capital Call
A18: G42 | B18: North Summit Capital Fund | C18: 43983 | D18: =G18 -> -4.485 | F18: USD | G18: -4.485 | H18: 2nd Capital Calll
A19: G42 | B19: North Summit Capital Fund | C19: 43879 | D19: =G19 -> -9.50975 | F19: USD | G19: -9.50975 | H19: 3rd Capital Call
A20: G42 | B20: North Summit Capital Fund | C20: 43934 | D20: =G20 -> -41.3 | F20: USD | G20: -41.3 | H20: 4th Capital Call
A21: G42 | B21: North Summit Capital Fund | C21: 44151 | D21: =G21 -> 9.95 | F21: USD | G21: 9.95 | H21: 5th Capital Call-Partial return of the 4th Capital Call
A22: G42 | B22: North Summit Capital Fund | C22: 44151 | D22: =G22 -> -10.455 | F22: USD | G22: -10.455 | H22: 5th Capital Call
A23: G42 | B23: North Summit Capital Fund | C23: 44196 | D23: =G23 -> 4.975 | F23: USD | G23: 4.975 | H23: 6th Capital Call-Partial return of the 4th Capital Call
A24: G42 | B24: North Summit Capital Fund | C24: 44196 | D24: =G24 -> -3.452293 | F24: USD | G24: -3.452293 | H24: 6th Capital Call
A25: G42 | B25: North Summit Capital Fund | C25: 44196 | E25: =G25 -> 0.582902 | F25: USD | G25: 0.582902 | H25: 6th Capital Call-Dividends from Project Topscore
A26: G42 | B26: North Summit Capital Fund | C26: 44370 | D26: =G26 -> -5.97 | F26: USD | G26: -5.97 | H26: 7th Capital Call
A27: G42 | B27: North Summit Capital Fund | C27: 44400 | D27: =G27 -> -0.75 | F27: USD | G27: -0.75 | H27: 8th Capital Call
A28: G42 | B28: North Summit Capital Fund | C28: 44400 | E28: =G28 -> 0.445059 | F28: USD | G28: 0.445059 | H28: 8th Capital Call-Dividends from Project Topscore
A29: G42 | B29: North Summit Capital Fund | C29: 44554 | D29: =G29 -> 1.78239 | F29: USD | G29: 1.78239 | H29: 9th Capital Call-Return of Capital Fund
A30: G42 | B30: North Summit Capital Fund | C30: 44676 | D30: =G30 -> -21 | F30: USD | G30: -21 | H30: 12th Capital Call
A31: G42 | B31: New Space Capital Fund I | C31: 44087 | D31: =G31*1.1 -> -20.917553 | F31: EUR | G31: -19.015957 | H31: Drawdown1
A32: G42 | B32: New Space Capital Fund I | C32: 44287 | D32: -0.21103182 | F32: EUR | G32: -0.21103182 | H32: Drawdown2
A33: G42 | B33: New Space Capital Fund I | C33: 44442 | D33: =1.18*G33 -> -0.23965473 | F33: EUR | G33: =-203097.23*10^-6 -> -0.20309723 | H33: Drawdown3
A34: G42 | B34: New Space Capital Fund I | C34: 44623 | D34: =1.11*G34 -> -0.25893585 | F34: EUR | G34: =-233275.54*10^-6 -> -0.23327554 | H34: Drawdown4
A35: G42 | B35: New Space Capital Fund I | C35: 44784 | D35: =1.03*G35 -> 0.015224657 | F35: EUR | G35: =14781.22*10^-6 -> 0.01478122 | H35: Return of Capital
A36: G42 | B36: New Space Capital Fund I | C36: 44956 | D36: =9741387*10^-6*1.08341 -> 10.553916 | F36: EUR | G36: =9741387*10^-6 -> 9.741387 | H36: Return of Capital
A37: G42 | B37: New Space Capital Fund I | C37: 44956 | E37: =2728214.02*10^-6*1.08341 -> 2.9557744 | F37: EUR | G37: =NAV!Q25*10^-6 -> 2.728214 | H37: Distribution | Actualization Interest
A38: G42 | B38: New Space Capital SCSp | C38: 44087 | D38: =-'Summary | 01 '!K37 -> -2.7058824 | F38: EUR | G38: -2.125 | H38: Drawdown1
A39: G42 | B39: Acies Investments Fund I, L.P. | C39: 44540 | D39: =G39 -> -2.8053125 | F39: USD | G39: -2.8053125 | H39: 1st Capital Call
A40: G42 | B40: Acies Investments Fund I, L.P. | C40: 44602 | D40: =G40 -> -3.4075 | F40: USD | G40: -3.4075 | H40: 2nd Capital Call
A41: G42 | B41: Acies Investments Fund I, L.P. | C41: 44683 | D41: =G41 -> -1.025775 | F41: USD | G41: -1.025775 | H41: Catch up Capital Call
A42: G42 | B42: Acies Investments Fund I, L.P. | C42: 44707 | D42: =G42 -> -3.388275 | F42: USD | G42: -3.388275 | H42: 3rd Capital Call
A43: G42 | B43: Acies Investments Fund I, L.P. | C43: 44875 | D43: =G43 -> -3.388275 | F43: USD | G43: -3.388275 | H43: 4th Capital Call

Sheet 1. IRR Equity
B2: IRR - Equity (Individual Investments)
B4: Date of NAV | C4: =D!D2 -> 45016 | J4: Investtment Level Summary | AB4: Overall Summary
B6: (in USD, Mn)
B7: Investment | C7: Payment date | D7: Contribution | E7: Distributions | F7: Remaining Value | G7: Combined | J7: Jollychic Holding Limited | K7: Mena Mobile Inc | L7: Flyr Inc | M7: Esyasoft Holding | N7: Beyond Limits | O7: ONT plc | P7: Heygears | Q7: Jysan Technologies | R7: Cerebras Systems Inc | S7: Endless Studios LLC | T7: Instadeep Limited | U7: X-fusion | V7: DriveNets | W7: vTv Therapeutics Inc. | X7: Honor Device Co Ltd | Y7: Applied AI Corporation Limited | Z7: eSpace | AD7: Committed | AE7: Invested | AF7: Remaining Commitment | AG7: Distributions | AH7: Residual Value | AI7: IRR | AJ7: TVPI | AK7: RPI | AL7: DPI
B10: ='CF (Equity, Debt)'!C4 -> Jollychic Holding Limited | C10: ='CF (Equity, Debt)'!D4 -> 43470 | D10: ='CF (Equity, Debt)'!E4 -> -30 | G10: =SUM(D10:F10) -> -30 | H10: =IF(D10='CF (Equity, Debt)'!E4," ", "xxx") | J10: =D10 -> -30 | AI10: 55
B11: ='CF (Equity, Debt)'!C5 -> Jollychic Holding Limited | C11: ='CF (Equity, Debt)'!D5 -> 43724 | D11: ='CF (Equity, Debt)'!E5 -> -20 | G11: =SUM(D11:F11) -> -20 | H11: =IF(D11='CF (Equity, Debt)'!E5," ", "xxx") | J11: =D11 -> -20
B12: ='CF (Equity, Debt)'!C6 -> Jollychic Holding Limited | C12: ='CF (Equity, Debt)'!D6 -> 43724 | D12: ='CF (Equity, Debt)'!E6 -> -15 | G12: =SUM(D12:F12) -> -15 | H12: =IF(D12='CF (Equity, Debt)'!E6," ", "xxx") | J12: =D12 -> -15 | AC12: ='Summary | 01 '!C10 -> Jollychic Holding Limited | AD12: ='Summary | 01 '!J10 -> 65 | AE12: =-SUMIF($B$7:$F$114,$AC12,$D$7:$D$114) -> 65 | AF12: =AD12-AE12 -> 0 | AG12: =SUMIF($B$7:$F$114,$AC12,$E$7:$E$114) -> 0 | AH12: =SUMIF($B$7:$F$114,$AC12,$F$7:$F$114) -> 0 | AI12: =HLOOKUP(AC12,$J$7:$Z$70,$AI$10,0) -> NM | AJ12: =(AG12+AH12)/AE12 -> 0 | AK12: =AH12/AE12 -> 0 | AL12: =AG12/AE12 -> 0
B13: ='CF (Equity, Debt)'!C7 -> Mena Mobile Inc | C13: ='CF (Equity, Debt)'!D7 -> 43563 | D13: ='CF (Equity, Debt)'!E7 -> -8 | G13: =SUM(D13:F13) -> -8 | H13: =IF(D13='CF (Equity, Debt)'!E7," ", "xxx") | K13: =D13 -> -8 | AC13: ='Summary | 01 '!C11 -> Mena Mobile Inc | AD13: ='Summary | 01 '!J11 -> 8 | AE13: =-SUMIF($B$7:$F$114,$AC13,$D$7:$D$114) -> 8 | AF13: =AD13-AE13 -> 0 | AG13: =SUMIF($B$7:$F$114,$AC13,$E$7:$E$114) -> 0 | AH13: =SUMIF($B$7:$F$114,$AC13,$F$7:$F$114) -> 3.1 | AI13: =HLOOKUP(AC13,$J$7:$Z$70,$AI$10,0) -> -0.21191685 | AJ13: =(AG13+AH13)/AE13 -> 0.3875 | AK13: =AH13/AE13 -> 0.3875 | AL13: =AG13/AE13 -> 0
B14: ='CF (Equity, Debt)'!C8 -> Flyr Inc | C14: ='CF (Equity, Debt)'!D8 -> 43570 | D14: ='CF (Equity, Debt)'!E8 -> -4.9999981 | G14: =SUM(D14:F14) -> -4.9999981 | H14: =IF(D14='CF (Equity, Debt)'!E8," ", "xxx") | L14: =D14 -> -4.9999981 | AC14: ='Summary | 01 '!C12 -> Flyr Inc | AD14: ='Summary | 01 '!J12 -> 10 | AE14: =-SUMIF($B$7:$F$114,$AC14,$D$7:$D$114) -> 10 | AF14: =AD14-AE14 -> 0 | AG14: =SUMIF($B$7:$F$114,$AC14,$E$7:$E$114) -> 0 | AH14: =SUMIF($B$7:$F$114,$AC14,$F$7:$F$114) -> 78.08223 | AI14: =HLOOKUP(AC14,$J$7:$Z$70,$AI$10,0) -> 0.7832873 | AJ14: =(AG14+AH14)/AE14 -> 7.808223 | AK14: =AH14/AE14 -> 7.808223 | AL14: =AG14/AE14 -> 0
B15: ='CF (Equity, Debt)'!C9 -> Flyr Inc | C15: ='CF (Equity, Debt)'!D9 -> 43915 | D15: ='CF (Equity, Debt)'!E9 -> -5.0000019 | G15: =SUM(D15:F15) -> -5.0000019 | H15: =IF(D15='CF (Equity, Debt)'!E9," ", "xxx") | L15: =D15 -> -5.0000019 | AC15: ='Summary | 01 '!C13 -> Esyasoft Holding | AD15: ='Summary | 01 '!J13 -> 2.5 | AE15: =-SUMIF($B$7:$F$114,$AC15,$D$7:$D$114) -> 2.5 | AF15: =AD15-AE15 -> 0 | AG15: =SUMIF($B$7:$F$114,$AC15,$E$7:$E$114) -> 5 | AH15: =SUMIF($B$7:$F$114,$AC15,$F$7:$F$114) -> 0 | AI15: =HLOOKUP(AC15,$J$7:$Z$70,$AI$10,0) -> 0.36091766 | AJ15: =(AG15+AH15)/AE15 -> 2 | AK15: =AH15/AE15 -> 0 | AL15: =AG15/AE15 -> 2
B16: ='CF (Equity, Debt)'!C10 -> Esyasoft Holding | C16: ='CF (Equity, Debt)'!D10 -> 43870 | D16: ='CF (Equity, Debt)'!E10 -> -2.5 | G16: =SUM(D16:F16) -> -2.5 | H16: =IF(D16='CF (Equity, Debt)'!E10," ", "xxx") | M16: =D16 -> -2.5 | AC16: ='Summary | 01 '!C14 -> Beyond Limits | AD16: ='Summary | 01 '!J14 -> 90 | AE16: =-SUMIF($B$7:$F$114,$AC16,$D$7:$D$114) -> 90 | AF16: =AD16-AE16 -> 0 | AG16: =SUMIF($B$7:$F$114,$AC16,$E$7:$E$114) -> 0 | AH16: =SUMIF($B$7:$F$114,$AC16,$F$7:$F$114) -> 91.00154 | AI16: =HLOOKUP(AC16,$J$7:$Z$70,$AI$10,0) -> 0.0038127035 | AJ16: =(AG16+AH16)/AE16 -> 1.0111282 | AK16: =AH16/AE16 -> 1.0111282 | AL16: =AG16/AE16 -> 0
B17: ='CF (Equity, Debt)'!C11 -> Beyond Limits | C17: ='CF (Equity, Debt)'!D11 -> 43879 | D17: ='CF (Equity, Debt)'!E11 -> -20 | G17: =SUM(D17:F17) -> -20 | H17: =IF(D17='CF (Equity, Debt)'!E11," ", "xxx") | N17: =D17 -> -20 | AC17: ='Summary | 01 '!C15 -> ONT plc | AD17: ='Summary | 01 '!J15 -> 141.47026 | AE17: =-SUMIF($B$7:$F$114,$AC17,$D$7:$D$114) -> 141.47026 | AF17: =AD17-AE17 -> 0 | AG17: =SUMIF($B$7:$F$114,$AC17,$E$7:$E$114) -> 0 | AH17: =SUMIF($B$7:$F$114,$AC17,$F$7:$F$114) -> 122.38019 | AI17: =HLOOKUP(AC17,$J$7:$Z$70,$AI$10,0) -> -0.050375113 | AJ17: =(AG17+AH17)/AE17 -> 0.86505946 | AK17: =AH17/AE17 -> 0.86505946 | AL17: =AG17/AE17 -> 0
B18: ='CF (Equity, Debt)'!C12 -> Beyond Limits | C18: ='CF (Equity, Debt)'!D12 -> 43921 | D18: ='CF (Equity, Debt)'!E12 -> -30 | G18: =SUM(D18:F18) -> -30 | H18: =IF(D18='CF (Equity, Debt)'!E12," ", "xxx") | N18: =D18 -> -30 | AC18: ='Summary | 01 '!C16 -> Heygears | AD18: ='Summary | 01 '!J16 -> 60 | AE18: =-SUMIF($B$7:$F$114,$AC18,$D$7:$D$114) -> 60 | AF18: =AD18-AE18 -> 0 | AG18: =SUMIF($B$7:$F$114,$AC18,$E$7:$E$114) -> 0 | AH18: =SUMIF($B$7:$F$114,$AC18,$F$7:$F$114) -> 119.2498 | AI18: =HLOOKUP(AC18,$J$7:$Z$70,$AI$10,0) -> 0.34306269 | AJ18: =(AG18+AH18)/AE18 -> 1.9874967 | AK18: =AH18/AE18 -> 1.9874967 | AL18: =AG18/AE18 -> 0
B19: ='CF (Equity, Debt)'!C13 -> Beyond Limits | C19: ='CF (Equity, Debt)'!D13 -> 43989 | D19: ='CF (Equity, Debt)'!E13 -> -30 | G19: =SUM(D19:F19) -> -30 | H19: =IF(D19='CF (Equity, Debt)'!E13," ", "xxx") | N19: =D19 -> -30 | AC19: ='Summary | 01 '!C17 -> Jysan Technologies | AD19: ='Summary | 01 '!J17 -> 20 | AE19: =-SUMIF($B$7:$F$114,$AC19,$D$7:$D$114) -> 20 | AF19: =AD19-AE19 -> 0 | AG19: =SUMIF($B$7:$F$114,$AC19,$E$7:$E$114) -> 0 | AH19: =SUMIF($B$7:$F$114,$AC19,$F$7:$F$114) -> 20 | AI19: =HLOOKUP(AC19,$J$7:$Z$70,$AI$10,0) -> 2.9802322e-09 | AJ19: =(AG19+AH19)/AE19 -> 1 | AK19: =AH19/AE19 -> 1 | AL19: =AG19/AE19 -> 0
B20: ='CF (Equity, Debt)'!C14 -> Beyond Limits | C20: ='CF (Equity, Debt)'!D14 -> 44103 | D20: ='CF (Equity, Debt)'!E14 -> -10 | G20: =SUM(D20:F20) -> -10 | H20: =IF(D20='CF (Equity, Debt)'!E14," ", "xxx") | N20: =D20 -> -10 | AC20: ='Summary | 01 '!C18 -> Cerebras Systems Inc | AD20: ='Summary | 01 '!J18 -> 40 | AE20: =-SUMIF($B$7:$F$114,$AC20,$D$7:$D$114) -> 39.999983 | AF20: =AD20-AE20 -> 1.664e-05 | AG20: =SUMIF($B$7:$F$114,$AC20,$E$7:$E$114) -> 0 | AH20: =SUMIF($B$7:$F$114,$AC20,$F$7:$F$114) -> 39.999983 | AI20: =HLOOKUP(AC20,$J$7:$Z$70,$AI$10,0) -> 2.9802322e-09 | AJ20: =(AG20+AH20)/AE20 -> 1 | AK20: =AH20/AE20 -> 1 | AL20: =AG20/AE20 -> 0
B21: ='CF (Equity, Debt)'!C15 -> ONT plc | C21: ='CF (Equity, Debt)'!D15 -> 43968 | D21: ='CF (Equity, Debt)'!E15 -> -50 | G21: =SUM(D21:F21) -> -50 | H21: =IF(D21='CF (Equity, Debt)'!E15," ", "xxx") | O21: =D21 -> -50 | AC21: ='Summary | 01 '!C19 -> Endless Studios LLC | AD21: ='Summary | 01 '!J19 -> 3 | AE21: =-SUMIF($B$7:$F$114,$AC21,$D$7:$D$114) -> 3 | AF21: =AD21-AE21 -> 0 | AG21: =SUMIF($B$7:$F$114,$AC21,$E$7:$E$114) -> 0 | AH21: =SUMIF($B$7:$F$114,$AC21,$F$7:$F$114) -> 3 | AI21: =HLOOKUP(AC21,$J$7:$Z$70,$AI$10,0) -> 2.9802322e-09 | AJ21: =(AG21+AH21)/AE21 -> 1 | AK21: =AH21/AE21 -> 1 | AL21: =AG21/AE21 -> 0
B22: ='CF (Equity, Debt)'!C16 -> ONT plc | C22: ='CF (Equity, Debt)'!D16 -> 44006 | D22: ='CF (Equity, Debt)'!E16 -> -27.268351 | G22: =SUM(D22:F22) -> -27.268351 | H22: =IF(D22='CF (Equity, Debt)'!E16," ", "xxx") | O22: =D22 -> -27.268351 | AC22: ='Summary | 01 '!C20 -> Instadeep Limited | AD22: ='Summary | 01 '!J20 -> 5.0278212 | AE22: =-SUMIF($B$7:$F$114,$AC22,$D$7:$D$114) -> 5.0237202 | AF22: =AD22-AE22 -> 0.0041009961 | AG22: =SUMIF($B$7:$F$114,$AC22,$E$7:$E$114) -> 0 | AH22: =SUMIF($B$7:$F$114,$AC22,$F$7:$F$114) -> 5.0237202 | AI22: =HLOOKUP(AC22,$J$7:$Z$70,$AI$10,0) -> 2.9802322e-09 | AJ22: =(AG22+AH22)/AE22 -> 1 | AK22: =AH22/AE22 -> 1 | AL22: =AG22/AE22 -> 0
B23: ='CF (Equity, Debt)'!C17 -> ONT plc | C23: ='CF (Equity, Debt)'!D17 -> 43837 | D23: ='CF (Equity, Debt)'!E17 -> -18.109441 | G23: =SUM(D23:F23) -> -18.109441 | H23: =IF(D23='CF (Equity, Debt)'!E17," ", "xxx") | O23: =D23 -> -18.109441 | AC23: ='Summary | 01 '!C21 -> X-fusion | AD23: ='Summary | 01 '!J21 -> 493.5 | AE23: =-SUMIF($B$7:$F$114,$AC23,$D$7:$D$114) -> 493.50096 | AF23: =AD23-AE23 -> -0.0009562 | AG23: =SUMIF($B$7:$F$114,$AC23,$E$7:$E$114) -> 0 | AH23: =SUMIF($B$7:$F$114,$AC23,$F$7:$F$114) -> 424.06662 | AI23: =HLOOKUP(AC23,$J$7:$Z$70,$AI$10,0) -> NM | AJ23: =(AG23+AH23)/AE23 -> 0.85930253 | AK23: =AH23/AE23 -> 0.85930253 | AL23: =AG23/AE23 -> 0
B24: ='CF (Equity, Debt)'!C18 -> ONT plc | C24: ='CF (Equity, Debt)'!D18 -> 43990 | D24: ='CF (Equity, Debt)'!E18 -> -34.851687 | G24: =SUM(D24:F24) -> -34.851687 | H24: =IF(D24='CF (Equity, Debt)'!E18," ", "xxx") | O24: =D24 -> -34.851687 | AC24: ='Summary | 01 '!C22 -> DriveNets | AD24: ='Summary | 01 '!J22 -> 300 | AE24: =-SUMIF($B$7:$F$114,$AC24,$D$7:$D$114) -> 300 | AF24: =AD24-AE24 -> 0 | AG24: =SUMIF($B$7:$F$114,$AC24,$E$7:$E$114) -> 0 | AH24: =SUMIF($B$7:$F$114,$AC24,$F$7:$F$114) -> 300 | AI24: =HLOOKUP(AC24,$J$7:$Z$70,$AI$10,0) -> NM | AJ24: =(AG24+AH24)/AE24 -> 1 | AK24: =AH24/AE24 -> 1 | AL24: =AG24/AE24 -> 0
B25: ='CF (Equity, Debt)'!C19 -> ONT plc | C25: ='CF (Equity, Debt)'!D19 -> 44315 | D25: ='CF (Equity, Debt)'!E19 -> -11.24078 | G25: =SUM(D25:F25) -> -11.24078 | H25: =IF(D25='CF (Equity, Debt)'!E19," ", "xxx") | O25: =D25 -> -11.24078 | AC25: ='Summary | 01 '!C23 -> vTv Therapeutics Inc. | AD25: ='Summary | 01 '!J23 -> 24.53125 | AE25: =-SUMIF($B$7:$F$114,$AC25,$D$7:$D$114) -> 24.53125 | AF25: =AD25-AE25 -> 0 | AG25: =SUMIF($B$7:$F$114,$AC25,$E$7:$E$114) -> 0 | AH25: =SUMIF($B$7:$F$114,$AC25,$F$7:$F$114) -> 8.3900321 | AI25: =HLOOKUP(AC25,$J$7:$Z$70,$AI$10,0) -> NM | AJ25: =(AG25+AH25)/AE25 -> 0.34201405 | AK25: =AH25/AE25 -> 0.34201405 | AL25: =AG25/AE25 -> 0
B26: ='CF (Equity, Debt)'!C20 -> Heygears | C26: ='CF (Equity, Debt)'!D20 -> 44166 | D26: ='CF (Equity, Debt)'!E20 -> -60 | G26: =SUM(D26:F26) -> -60 | H26: =IF(D26='CF (Equity, Debt)'!E20," ", "xxx") | P26: =D26 -> -60 | AC26: ='Summary | 01 '!C24 -> Honor Device Co Ltd | AD26: ='Summary | 01 '!J24 -> 800 | AE26: =-SUMIF($B$7:$F$114,$AC26,$D$7:$D$114) -> 800 | AF26: =AD26-AE26 -> 0 | AG26: =SUMIF($B$7:$F$114,$AC26,$E$7:$E$114) -> 0 | AH26: =SUMIF($B$7:$F$114,$AC26,$F$7:$F$114) -> 848.76999 | AI26: =HLOOKUP(AC26,$J$7:$Z$70,$AI$10,0) -> NM | AJ26: =(AG26+AH26)/AE26 -> 1.0609625 | AK26: =AH26/AE26 -> 1.0609625 | AL26: =AG26/AE26 -> 0
B27: ='CF (Equity, Debt)'!C21 -> Jysan Technologies | C27: ='CF (Equity, Debt)'!D21 -> 44363 | D27: ='CF (Equity, Debt)'!E21 -> -20 | G27: =SUM(D27:F27) -> -20 | H27: =IF(D27='CF (Equity, Debt)'!E21," ", "xxx") | Q27: =D27 -> -20 | AC27: ='Summary | 01 '!C25 -> Applied AI Corporation Limited | AD27: ='Summary | 01 '!J25 -> 15 | AE27: =-SUMIF($B$7:$F$114,$AC27,$D$7:$D$114) -> 4.75 | AF27: =AD27-AE27 -> 10.25 | AG27: =SUMIF($B$7:$F$114,$AC27,$E$7:$E$114) -> 0 | AH27: =SUMIF($B$7:$F$114,$AC27,$F$7:$F$114) -> 4.75 | AI27: =HLOOKUP(AC27,$J$7:$Z$70,$AI$10,0) -> NM | AJ27: =(AG27+AH27)/AE27 -> 1 | AK27: =AH27/AE27 -> 1 | AL27: =AG27/AE27 -> 0
B28: ='CF (Equity, Debt)'!C22 -> Cerebras Systems Inc | C28: ='CF (Equity, Debt)'!D22 -> 44488 | D28: ='CF (Equity, Debt)'!E22 -> -39.999983 | G28: =SUM(D28:F28) -> -39.999983 | H28: =IF(D28='CF (Equity, Debt)'!E22," ", "xxx") | R28: =D28 -> -39.999983 | AC28: ='Summary | 01 '!C26 -> eSpace | AD28: ='Summary | 01 '!J26 -> 15 | AE28: =-SUMIF($B$7:$F$114,$AC28,$D$7:$D$114) -> 15 | AF28: =AD28-AE28 -> 0 | AG28: =SUMIF($B$7:$F$114,$AC28,$E$7:$E$114) -> 0 | AH28: =SUMIF($B$7:$F$114,$AC28,$F$7:$F$114) -> 15 | AI28: =HLOOKUP(AC28,$J$7:$Z$70,$AI$10,0) -> NM | AJ28: =(AG28+AH28)/AE28 -> 1 | AK28: =AH28/AE28 -> 1 | AL28: =AG28/AE28 -> 0
B29: ='CF (Equity, Debt)'!C23 -> Endless Studios LLC | C29: ='CF (Equity, Debt)'!D23 -> 44494 | D29: ='CF (Equity, Debt)'!E23 -> -3 | G29: =SUM(D29:F29) -> -3 | H29: =IF(D29='CF (Equity, Debt)'!E23," ", "xxx") | S29: =D29 -> -3 | AD29: =SUM(AD12:AD28) -> 2093.0293 | AE29: =SUM(AE12:AE28) -> 2082.7762 | AF29: =SUM(AF12:AF28) -> 10.253161 | AG29: =SUM(AG12:AG28) -> 5 | AH29: =SUM(AH12:AH28) -> 2082.8141 | AI29: =AD35 -> 0.0019109696 | AJ29: =(AG29+AH29)/AE29 -> 1.0024189 | AK29: =AH29/AE29 -> 1.0000182 | AL29: =AG29/AE29 -> 0.002400642
B30: ='CF (Equity, Debt)'!C24 -> Instadeep Limited | C30: ='CF (Equity, Debt)'!D24 -> 44550 | D30: ='CF (Equity, Debt)'!E24 -> -5.0237202 | G30: =SUM(D30:F30) -> -5.0237202 | H30: =IF(D30='CF (Equity, Debt)'!E24," ", "xxx") | T30: =D30 -> -5.0237202 | AD30: =ROUND('Summary | 01 '!J27,2)=ROUND(AD29,2) -> TRUE | AE30: =ROUND('Summary | 01 '!K27,2)=ROUND(AE29,2) -> TRUE | AF30: =ROUND('Summary | 01 '!L27,2)=ROUND(AF29,2) -> TRUE | AG30: =ROUND('Summary | 01 '!M27,2)=ROUND(AG29,2) -> TRUE | AH30: =ROUND('Summary | 01 '!N27,2)=ROUND(AH29,2) -> TRUE | AI30: =ROUND('Summary | 01 '!Q27,2)=ROUND(AI29,2) -> TRUE | AJ30: =ROUND('Summary | 01 '!P27,2)=ROUND(AJ29,2) -> TRUE
B31: ='CF (Equity, Debt)'!C25 -> X-fusion | C31: ='CF (Equity, Debt)'!D25 -> 44574 | D31: ='CF (Equity, Debt)'!E25 -> -493.50096 | G31: =SUM(D31:F31) -> -493.50096 | H31: =IF(D31='CF (Equity, Debt)'!E25," ", "xxx") | U31: =D31 -> -493.50096
B32: ='CF (Equity, Debt)'!C26 -> DriveNets | C32: ='CF (Equity, Debt)'!D26 -> 44643 | D32: ='CF (Equity, Debt)'!E26 -> -200 | G32: =SUM(D32:F32) -> -200 | H32: =IF(D32='CF (Equity, Debt)'!E26," ", "xxx") | V32: =D32 -> -200
B33: ='CF (Equity, Debt)'!C27 -> DriveNets | C33: ='CF (Equity, Debt)'!D27 -> 44680 | D33: ='CF (Equity, Debt)'!E27 -> -100 | G33: =SUM(D33:F33) -> -100 | H33: =IF(D33='CF (Equity, Debt)'!E27," ", "xxx") | V33: =D33 -> -100
B34: ='CF (Equity, Debt)'!C28 -> Esyasoft Holding | C34: ='CF (Equity, Debt)'!D28 -> 44691 | D34: ='CF (Equity, Debt)'!E28 -> 0 | E34: ='CF (Equity, Debt)'!F28 -> 5 | G34: =SUM(D34:F34) -> 5 | H34: =IF(D34='CF (Equity, Debt)'!E28," ", "xxx") | M34: =E34 -> 5
B35: ='CF (Equity, Debt)'!C29 -> vTv Therapeutics Inc. | C35: ='CF (Equity, Debt)'!D29 -> 44712 | D35: ='CF (Equity, Debt)'!E29 -> -12.5 | G35: =SUM(D35:F35) -> -12.5 | H35: =IF(D35='CF (Equity, Debt)'!E29," ", "xxx") | W35: =D35 -> -12.5 | AC35: XIRR | AD35: =XIRR(G10:G78,C10:C78) -> 0.0019109696
B36: ='CF (Equity, Debt)'!C30 -> Honor Device Co Ltd | C36: ='CF (Equity, Debt)'!D30 -> 44769 | D36: ='CF (Equity, Debt)'!E30 -> -600 | G36: =SUM(D36:F36) -> -600 | H36: =IF(D36='CF (Equity, Debt)'!E30," ", "xxx") | X36: =D36 -> -600 | AC36: TVPI | AD36: =SUM(AG12:AH28)/SUM(AE12:AE28) -> 1.0024189 | AE36: =AD36=AJ29 -> TRUE
B37: ='CF (Equity, Debt)'!C31 -> Honor Device Co Ltd | C37: ='CF (Equity, Debt)'!D31 -> 44849 | D37: ='CF (Equity, Debt)'!E31 -> -200 | G37: =SUM(D37:F37) -> -200 | X37: =D37 -> -200 | AC37: RPI | AD37: =SUM(AH12:AH28)/SUM(AE12:AE28) -> 1.0000182 | AE37: =AD37=AK29 -> TRUE
B38: ='CF (Equity, Debt)'!C32 -> Applied AI Corporation Limited | C38: ='CF (Equity, Debt)'!D32 -> 44861 | D38: ='CF (Equity, Debt)'!E32 -> -4.75 | G38: =SUM(D38:F38) -> -4.75 | Y38: =D38 -> -4.75 | AC38: DPI | AD38: =SUM(AG12:AG28)/SUM(AE12:AE28) -> 0.002400642 | AE38: =AD38=AL29 -> TRUE
B39: ='CF (Equity, Debt)'!C33 -> eSpace | C39: ='CF (Equity, Debt)'!D33 -> 44892 | D39: ='CF (Equity, Debt)'!E33 -> -15 | G39: =SUM(D39:F39) -> -15 | Z39: =G39 -> -15
B40: ='CF (Equity, Debt)'!C34 -> vTv Therapeutics Inc. | C40: ='CF (Equity, Debt)'!D34 -> 44985 | D40: ='CF (Equity, Debt)'!E34 -> -12.03125 | G40: =SUM(D40:F40) -> -12.03125 | W40: =G40 -> -12.03125
B42: Jollychic Holding Limited | C42: =$C$4 -> 45016 | F42: =NAV!E9 -> 0 | G42: =SUM(D42:F42) -> 0 | J42: =F42 -> 0
B43: Mena Mobile Inc | C43: =$C$4 -> 45016 | F43: =NAV!E10 -> 3.1 | G43: =SUM(D43:F43) -> 3.1 | K43: =F43 -> 3.1
B44: Flyr Inc | C44: =$C$4 -> 45016 | F44: =NAV!E11 -> 78.08223 | G44: =SUM(D44:F44) -> 78.08223 | L44: =F44 -> 78.08223
B45: Esyasoft Holding | C45: =$C$4 -> 45016 | F45: =NAV!E12 -> 0 | G45: =SUM(D45:F45) -> 0
B46: Beyond Limits | C46: =$C$4 -> 45016 | F46: =NAV!E13 -> 91.00154 | G46: =SUM(D46:F46) -> 91.00154 | N46: =F46 -> 91.00154
B47: ONT plc | C47: =$C$4 -> 45016 | F47: =NAV!E14 -> 122.38019 | G47: =SUM(D47:F47) -> 122.38019 | O47: =F47 -> 122.38019
B48: Heygears | C48: =$C$4 -> 45016 | F48: =NAV!E15 -> 119.2498 | G48: =SUM(D48:F48) -> 119.2498 | P48: =F48 -> 119.2498
B49: Jysan Technologies | C49: =$C$4 -> 45016 | F49: =NAV!E16 -> 20 | G49: =SUM(D49:F49) -> 20 | Q49: =F49 -> 20
B50: Cerebras Systems Inc | C50: =$C$4 -> 45016 | F50: =NAV!E17 -> 39.999983 | G50: =SUM(D50:F50) -> 39.999983 | R50: =F50 -> 39.999983
B51: Endless Studios LLC | C51: =$C$4 -> 45016 | F51: =NAV!E18 -> 3 | G51: =SUM(D51:F51) -> 3 | S51: =F51 -> 3
B52: Instadeep Limited | C52: =$C$4 -> 45016 | F52: =NAV!E19 -> 5.0237202 | G52: =SUM(D52:F52) -> 5.0237202 | T52: =F52 -> 5.0237202
B53: X-fusion | C53: =$C$4 -> 45016 | F53: =NAV!E20 -> 424.06662 | G53: =SUM(D53:F53) -> 424.06662 | U53: =F53 -> 424.06662
B54: DriveNets | C54: =$C$4 -> 45016 | F54: =NAV!E21 -> 300 | G54: =SUM(D54:F54) -> 300 | V54: =F54 -> 300
B55: vTv Therapeutics Inc. | C55: =$C$4 -> 45016 | F55: =NAV!E22 -> 8.3900321 | G55: =SUM(D55:F55) -> 8.3900321 | W55: =F55 -> 8.3900321
B56: Honor Device Co Ltd | C56: =$C$4 -> 45016 | F56: =NAV!E23 -> 848.76999 | G56: =SUM(D56:F56) -> 848.76999 | X56: =F56 -> 848.76999
B57: Applied AI Corporation Limited | C57: =$C$4 -> 45016 | F57: =NAV!E24 -> 4.75 | G57: =SUM(D57:F57) -> 4.75 | Y57: =F57 -> 4.75
B58: eSpace | C58: =$C$4 -> 45016 | F58: =NAV!E25 -> 15 | G58: =SUM(D58:F58) -> 15 | Z58: =G58 -> 15
I61: IRR | J61: =IF(ISERROR(XIRR(J10:J58,$C$10:$C$58)),"NM", XIRR(J10:J58,$C$10:$C$58)) -> NM | K61: =IF(ISERROR(XIRR(K13:K58,$C$13:$C$58)),"NM", XIRR(K13:K58,$C$13:$C$58)) -> -0.21191685 | L61: =IF(ISERROR(XIRR(L14:L58,$C$14:$C$58)),"NM", XIRR(L14:L58,$C$14:$C$58)) -> 0.7832873 | M61: =IF(ISERROR(XIRR(M16:M58,$C$16:$C$58)),"NM", XIRR(M16:M58,$C$16:$C$58)) -> 0.36091766 | N61: =IF(ISERROR(XIRR(N17:N58,$C$17:$C$58)),"NM", XIRR(N17:N58,$C$17:$C$58)) -> 0.0038127035 | O61: =IF(ISERROR(XIRR(O21:O58,$C$21:$C$58)),"NM", XIRR(O21:O58,$C$21:$C$58)) -> -0.050375113 | P61: =IF(ISERROR(XIRR(P26:P58,$C$26:$C$58)),"NM", XIRR(P26:P58,$C$26:$C$58)) -> 0.34306269 | Q61: =IF(ISERROR(XIRR(Q27:Q58,$C$27:$C$58)),"NM", XIRR(Q27:Q58,$C$27:$C$58)) -> 2.9802322e-09 | R61: =IF(ISERROR(XIRR(R28:R58,$C$28:$C$58)),"NM", XIRR(R28:R58,$C$28:$C$58)) -> 2.9802322e-09 | S61: =IF(ISERROR(XIRR(S29:S58,$C$29:$C$58)),"NM", XIRR(S29:S58,$C$29:$C$58)) -> 2.9802322e-09 | T61: =IF(ISERROR(XIRR(T30:T58,$C$30:$C$58)),"NM", XIRR(T30:T58,$C$30:$C$58)) -> 2.9802322e-09 | U61: =IF(ISERROR(XIRR(U32:U58,$C$32:$C$58)),"NM", "NM") -> NM | V61: =IF(ISERROR(XIRR(V32:V58,$C$32:$C$58)),"NM", "NM") -> NM | W61: =IF(ISERROR(XIRR(W32:W58,$C$32:$C$58)),"NM", "NM") -> NM | X61: =IF(ISERROR(XIRR(X36:X58,$C$35:$C$58)),"NM", "NM") -> NM | Y61: =IF(ISERROR(XIRR(Y38:Y58,$C$38:$C$58)),"NM", "NM") -> NM | Z61: =IF(ISERROR(XIRR(Z39:Z58,$C$39:$C$58)),"NM", "NM") -> NM
H62: =SUM(J62:Z62)='Summary | 01 '!K27 -> TRUE | I62: PIC | J62: =-SUMIF(J$10:J$40,"<0",J$10:J$40) -> 65 | K62: =-SUMIF(K$10:K$40,"<0",K$10:K$40) -> 8 | L62: =-SUMIF(L$10:L$40,"<0",L$10:L$40) -> 10 | M62: =-SUMIF(M$10:M$40,"<0",M$10:M$40) -> 2.5 | N62: =-SUMIF(N$10:N$40,"<0",N$10:N$40) -> 90 | O62: =-SUMIF(O$10:O$40,"<0",O$10:O$40) -> 141.47026 | P62: =-SUMIF(P$10:P$40,"<0",P$10:P$40) -> 60 | Q62: =-SUMIF(Q$10:Q$40,"<0",Q$10:Q$40) -> 20 | ... Z62: =-SUMIF(Z$10:Z$40,"<0",Z$10:Z$40) -> 15
H63: =ROUND(SUM(J63:Z63),2)=ROUND('Summary | 01 '!M27,2) -> TRUE | I63: Dist | J63: =SUMIF(J$10:J$40,">0",J$10:J$40) -> 0 | K63: =SUMIF(K$10:K$40,">0",K$10:K$40) -> 0 | L63: =SUMIF(L$10:L$40,">0",L$10:L$40) -> 0 | M63: =SUMIF(M$10:M$40,">0",M$10:M$40) -> 5 | N63: =SUMIF(N$10:N$40,">0",N$10:N$40) -> 0 | O63: =SUMIF(O$10:O$40,">0",O$10:O$40) -> 0 | P63: =SUMIF(P$10:P$40,">0",P$10:P$40) -> 0 | Q63: =SUMIF(Q$10:Q$40,">0",Q$10:Q$40) -> 0 | ... Y63: =SUMIF(Y$10:Y$40,">0",Y$10:Y$40) -> 0 | Z63: =SUMIF(Z$10:Z$39,">0",Z$10:Z$39) -> 0
H64: =ROUND(SUM(J64:Z64),2)=ROUND('Summary | 01 '!N27,2) -> TRUE | I64: RV | J64: =SUM(J$42:J$58) -> 0 | K64: =SUM(K$42:K$58) -> 3.1 | L64: =SUM(L$42:L$58) -> 78.08223 | M64: =SUM(M$42:M$58) -> 0 | N64: =SUM(N$42:N$58) -> 91.00154 | O64: =SUM(O$42:O$58) -> 122.38019 | P64: =SUM(P$42:P$58) -> 119.2498 | Q64: =SUM(Q$42:Q$58) -> 20 | ... Z64: =SUM(Z$42:Z$58) -> 15
I65: TVPI | J65: =(J63+J64)/J62 -> 0 | K65: =(K63+K64)/K62 -> 0.3875 | L65: =(L63+L64)/L62 -> 7.808223 | M65: =(M63+M64)/M62 -> 2 | N65: =(N63+N64)/N62 -> 1.0111282 | O65: =(O63+O64)/O62 -> 0.86505946 | P65: =(P63+P64)/P62 -> 1.9874967 | Q65: =(Q63+Q64)/Q62 -> 1 | ... Z65: =(Z63+Z64)/Z62 -> 1
I66: DPI | J66: =J63/J62 -> 0 | K66: =K63/K62 -> 0 | L66: =L63/L62 -> 0 | M66: =M63/M62 -> 2 | N66: =N63/N62 -> 0 | O66: =O63/O62 -> 0 | P66: =P63/P62 -> 0 | Q66: =Q63/Q62 -> 0 | ... Z66: =Z63/Z62 -> 0
I67: RVPI | J67: =J64/J62 -> 0 | K67: =K64/K62 -> 0.3875 | L67: =L64/L62 -> 7.808223 | M67: =M64/M62 -> 0 | N67: =N64/N62 -> 1.0111282 | O67: =O64/O62 -> 0.86505946 | P67: =P64/P62 -> 1.9874967 | Q67: =Q64/Q62 -> 1 | ... Z67: =Z64/Z62 -> 1

Sheet 2. IRR Debt
B2: IRR - Debt
B4: Date of NAV | C4: =D!D2 -> 45016 | I4: Investment Level Summary | P4: Overall Summary
B6: USD Millions
B7: Investment | C7: Payment date | D7: Contributions | E7: Distributions | F7: Residual Value | G7: Combined | K7: Contribution | L7: Distribution | M7: Residual Value | N7: Combined | Q7: Committed | R7: Invested | S7: Remaining Commitment | T7: Distributions | U7: Residual Value | V7: IRR | W7: TVPI | X7: RPI | Y7: DPI
B8: Debt Investments
B9: ='CF (Equity, Debt)'!C37 -> Glass Earth Holdings LLC | C9: ='CF (Equity, Debt)'!D37 -> 43635 | D9: ='CF (Equity, Debt)'!E37 -> -8 | G9: =SUM(D9:F9) -> -8 | I9: =B9 -> Glass Earth Holdings LLC | J9: =C9 -> 43635 | K9: =D9 -> -8 | N9: =SUM(K9:M9) -> -8 | P9: Glass Earth Holdings LLC | Q9: =R9 -> 8 | R9: =-D9 -> 8 | S9: 0 | T9: =E9 -> 0 | U9: =F14 -> 0 | V9: =J12 -> NM | W9: =(T9+U9)/R9 -> 0 | X9: =U9/R9 -> 0 | Y9: =T9/R9 -> 0
B10: ='CF (Equity, Debt)'!C38 -> Mena Mobile Inc (Debt) | C10: ='CF (Equity, Debt)'!D38 -> 44293 | D10: ='CF (Equity, Debt)'!E38 -> -2.353982 | G10: =SUM(D10:F10) -> -2.353982 | I10: =B14 -> Glass Earth Holdings LLC | J10: =C14 -> 45016 | M10: =F14 -> 0 | N10: =SUM(K10:M10) -> 0 | P10: Mena Mobile Inc (Debt) | Q10: =R10 -> 2.353982 | R10: =-D10 -> 2.353982 | S10: 0 | T10: =E10 -> 0 | U10: =F15 -> 2.353982 | V10: =J22:J22 -> 2.9802322e-09 | W10: =(T10+U10)/R10 -> 1 | X10: =U10/R10 -> 1 | Y10: =T10/R10 -> 0
B11: ='CF (Equity, Debt)'!C39 -> Esyasoft Holding (Debt) | C11: ='CF (Equity, Debt)'!D39 -> 44384 | D11: ='CF (Equity, Debt)'!E39 -> -0.411765 | G11: =SUM(D11:F11) -> -0.411765 | P11: Esyasoft Holding (Debt) | Q11: =R11 -> 0.411765 | R11: =-D11 -> 0.411765 | S11: 0 | T11: =E12 -> 0.47078465 | U11: =F16 -> 0 | V11: =J31 -> 0.075277027 | W11: =(T11+U11)/R11 -> 1.1433333 | X11: =U11/R11 -> 0 | Y11: =T11/R11 -> 1.1433333
B12: ='CF (Equity, Debt)'!C40 -> Esyasoft Holding (Debt) | C12: ='CF (Equity, Debt)'!D40 -> 44902 | D12: ='CF (Equity, Debt)'!E40 -> 0 | E12: ='CF (Equity, Debt)'!F40 -> 0.47078465 | G12: =SUM(D12:F12) -> 0.47078465 | I12: XIRR | J12: =IF(ISERROR(XIRR(N9:N10,J9:J10)),"NM",XIRR(N9:N10,J9:J10)) -> NM | L12: Contributions | Q12: =SUM(Q9:Q11) -> 10.765747 | R12: =SUM(R9:R11) -> 10.765747 | S12: =SUM(S9:S11) -> 0 | T12: =SUM(T9:T11) -> 0.47078465 | U12: =SUM(U9:U11) -> 2.353982 | V12: =XIRR(G9:G16,C9:C16) -> -0.35001702 | W12: =(T12+U12)/R12 -> 0.26238464 | X12: =U12/R12 -> 0.21865478 | Y12: =T12/R12 -> 0.043729864
I13: TVPI | J13: =SUM(L9:M10)/-SUM(K9:K10) -> 0 | L13: Distributions
B14: =B9 -> Glass Earth Holdings LLC | C14: =$C$4 -> 45016 | F14: =VLOOKUP(B14,NAV!$B$30:$E$32,4,0) -> 0 | G14: =SUM(D14:F14) -> 0 | I14: RPI | J14: =SUM(M9:M10)/-SUM(K9:K10) -> 0 | L14: Residual Value
B15: =B10 -> Mena Mobile Inc (Debt) | C15: =$C$4 -> 45016 | F15: =VLOOKUP(B15,NAV!$B$30:$E$32,4,0) -> 2.353982 | G15: =SUM(D15:F15) -> 2.353982 | I15: DPI | J15: =SUM(L9:L10)/-SUM(K9:K10) -> 0 | P15: XIRR | Q15: =XIRR(G9:G18,C9:C18) -> -0.35001702
B16: =B11 -> Esyasoft Holding (Debt) | C16: =$C$4 -> 45016 | F16: =VLOOKUP(B16,NAV!$B$30:$E$32,4,0) -> 0 | G16: =SUM(D16:F16) -> 0 | P16: TVPI | Q16: =SUM(T9:U11)/SUM(R9:R11) -> 0.26238464
P17: RPI | Q17: =SUM(U9:U11)/SUM(R9:R11) -> 0.21865478
P18: DPI | Q18: =SUM(T9:T11)/SUM(R9:R11) -> 0.043729864
I19: =B10 -> Mena Mobile Inc (Debt) | J19: =C10 -> 44293 | K19: -2.353982 | N19: =SUM(K19:M19) -> -2.353982
I20: =B15 -> Mena Mobile Inc (Debt) | J20: =C15 -> 45016 | M20: 2.353982 | N20: =SUM(K20:M20) -> 2.353982
I22: XIRR | J22: =IF(ISERROR(XIRR(N19:N20,J19:J20)),"NM",XIRR(N19:N20,J19:J20)) -> 2.9802322e-09 | L22: Contributions
I23: TVPI | J23: =SUM(L19:M20)/-SUM(K19:K20) -> 1 | L23: Distributions
I24: RPI | J24: =SUM(M19:M20)/-SUM(K19:K20) -> 1 | L24: Residual Value
I25: DPI | J25: =SUM(L19:L20)/-SUM(K19:K20) -> 0
I28: =B11 -> Esyasoft Holding (Debt) | J28: =C11 -> 44384 | K28: -0.411765 | N28: =SUM(K28:M28) -> -0.411765
I29: =B16 -> Esyasoft Holding (Debt) | J29: ='CF (Equity, Debt)'!D40 -> 44902 | M29: 0.45643868 | N29: =SUM(K29:M29) -> 0.45643868
I31: XIRR | J31: =IF(ISERROR(XIRR(N28:N29,J28:J29)),"NM",XIRR(N28:N29,J28:J29)) -> 0.075277027 | L31: Contributions
I32: TVPI | J32: =SUM(L28:M29)/-SUM(K28:K29) -> 1.1084932 | L32: Distributions
I33: RPI | J33: =SUM(M28:M29)/-SUM(K28:K29) -> 1.1084932 | L33: Residual Value
I34: DPI | J34: =SUM(L28:L29)/-SUM(K28:K29) -> 0

Sheet 3. IRR Funds
B2: IRR - FUNDS | E2: Test | F2: =COUNTA(B8:B48)=COUNTA('CF (Funds)'!B3:B43) -> TRUE
B4: Date of NAV | C4: =D!D2 -> 45016 | I4: Fund Level Summary | P4: Overall Summary
B6: USD Millions
B7: Investment | C7: Payment date | D7: Contributions | E7: Distributions | F7: Residual Value | G7: Combined | K7: Contribution | L7: Distribution | M7: Residual Value | N7: Combined | Q7: Committed | R7: Invested | S7: Remaining Commitment | T7: Distributions | U7: Residual Value | V7: IRR | W7: TVPI | X7: RPI | Y7: DPI
B8: ='CF (Funds)'!B3 -> Sinovation Disrupt Fund, L.P. | C8: ='CF (Funds)'!C3 -> 44153 | D8: ='CF (Funds)'!D3 -> -10.5 | E8: ='CF (Funds)'!E3 -> 0 | G8: =SUM(D8:F8) -> -10.5 | P8: Funds Investments
B9: ='CF (Funds)'!B4 -> Sinovation Disrupt Fund, L.P. | C9: ='CF (Funds)'!C4 -> 44238 | D9: ='CF (Funds)'!D4 -> 4.214027 | E9: ='CF (Funds)'!E4 -> 0 | G9: =SUM(D9:F9) -> 4.214027 | I9: =B36 -> New Space Capital Fund I | J9: =C36 -> 44087 | K9: =D36 -> -20.917553 | L9: =E36 -> 0 | M9: =F36 -> 0 | N9: =SUM(K9:M9) -> -20.917553 | P9: New Space Capital Fund I | Q9: 25.557908 | R9: =-SUMIF($B$7:$F$104,$P9,$D$7:$D$104) -> 11.058035 | S9: =Q9-R9 -> 14.499873 | T9: =SUMIF($B$7:$F$104,$P9,$E$7:$E$104) -> 2.9557744 | U9: =SUMIF($B$7:$F$104,$P9,$F$7:$F$104) -> 14.294891 | V9: =J18 -> 0.1090443 | W9: =(T9+U9)/R9 -> 1.5600119 | X9: =U9/R9 -> 1.2927154 | Y9: =T9/R9 -> 0.26729654
B10: ='CF (Funds)'!B5 -> Sinovation Disrupt Fund, L.P. | C10: ='CF (Funds)'!C5 -> 44238 | D10: ='CF (Funds)'!D5 -> 0 | E10: ='CF (Funds)'!E5 -> 0.05044835 | G10: =SUM(D10:F10) -> 0.05044835 | I10: =B37 -> New Space Capital Fund I | J10: =C37 -> 44287 | K10: =D37 -> -0.21103182 | L10: =E37 -> 0 | M10: =F37 -> 0 | N10: =SUM(K10:M10) -> -0.21103182 | P10: New Space Capital SCSp | Q10: 2.7058824 | R10: =-SUMIF($B$7:$F$104,$P10,$D$7:$D$104) -> 2.7058824 | S10: =Q10-R10 -> 0 | T10: =SUMIF($B$7:$F$104,$P10,$E$7:$E$104) -> 0 | U10: =SUMIF($B$7:$F$104,$P10,$F$7:$F$104) -> 2.7058824 | V10: 0 | W10: =(T10+U10)/R10 -> 1 | X10: =U10/R10 -> 1 | Y10: =T10/R10 -> 0
B11: ='CF (Funds)'!B6 -> Sinovation Disrupt Fund, L.P. | C11: ='CF (Funds)'!C6 -> 44285 | D11: ='CF (Funds)'!D6 -> -6.433746 | E11: ='CF (Funds)'!E6 -> 0 | G11: =SUM(D11:F11) -> -6.433746 | I11: =B38 -> New Space Capital Fund I | J11: =C38 -> 44442 | K11: =D38 -> -0.23965473 | L11: =E38 -> 0 | M11: =F38 -> 0 | N11: =SUM(K11:M11) -> -0.23965473 | P11: North Summit Capital Fund | Q11: 300 | R11: =-SUMIF($B$7:$F$104,$P11,$D$7:$D$104) -> 83.214653 | S11: =Q11-R11+T11 -> 217.81331 | T11: =SUMIF($B$7:$F$104,$P11,$E$7:$E$104) -> 1.027961 | U11: =SUMIF($B$7:$F$104,$P11,$F$7:$F$104) -> 70.03 | V11: =J49 -> -0.064168629 | W11: =(T11+U11)/R11 -> 0.85391164 | X11: =U11/R11 -> 0.84155852 | Y11: =T11/R11 -> 0.012353125
B12: ='CF (Funds)'!B7 -> Sinovation Disrupt Fund, L.P. | C12: ='CF (Funds)'!C7 -> 44269 | D12: ='CF (Funds)'!D7 -> 1.1352074 | E12: ='CF (Funds)'!E7 -> 0 | G12: =SUM(D12:F12) -> 1.1352074 | I12: =B39 -> New Space Capital Fund I | J12: =C39 -> 44623 | K12: =D39 -> -0.25893585 | L12: =E39 -> 0 | M12: =F39 -> 0 | N12: =SUM(K12:M12) -> -0.25893585 | P12: Sinovation Disrupt Fund, L.P. | Q12: 50 | R12: =-SUMIF($B$7:$F$104,$P12,$D$7:$D$104) -> 22.657267 | S12: =Q12-R12 -> 27.342733 | T12: =SUMIF($B$7:$F$104,$P12,$E$7:$E$104) -> 0.44382835 | U12: =SUMIF($B$7:$F$104,$P12,$F$7:$F$104) -> 21.51575 | V12: =J71 -> -0.018159524 | W12: =(T12+U12)/R12 -> 0.96920685 | X12: =U12/R12 -> 0.94961806 | Y12: =T12/R12 -> 0.019588786
B13: ='CF (Funds)'!B8 -> Sinovation Disrupt Fund, L.P. | C13: ='CF (Funds)'!C8 -> 44269 | D13: ='CF (Funds)'!D8 -> 0 | E13: ='CF (Funds)'!E8 -> 0.0259 | G13: =SUM(D13:F13) -> 0.0259 | I13: =B40 -> New Space Capital Fund I | J13: =C40 -> 44784 | K13: =D40 -> 0.015224657 | L13: =E40 -> 0 | M13: =F40 -> 0 | N13: =SUM(K13:M13) -> 0.015224657 | P13: Acies Investments Fund I, L.P. | Q13: 17.1125 | R13: =-SUMIF($B$7:$F$104,$P13,$D$7:$D$104) -> 14.015137 | S13: =Q13-R13 -> 3.0973625 | T13: =SUMIF($B$7:$F$104,$P13,$E$7:$E$104) -> 0 | U13: =SUMIF($B$7:$F$104,$P13,$F$7:$F$104) -> 13.742841 | V13: =J84 -> -0.021553859 | W13: =(T13+U13)/R13 -> 0.98057126 | X13: =U13/R13 -> 0.98057126 | Y13: =T13/R13 -> 0
B14: ='CF (Funds)'!B9 -> Sinovation Disrupt Fund, L.P. | C14: ='CF (Funds)'!C9 -> 44483 | D14: ='CF (Funds)'!D9 -> -7.567138 | E14: ='CF (Funds)'!E9 -> 0 | G14: =SUM(D14:F14) -> -7.567138 | I14: =B41 -> New Space Capital Fund I | J14: =C41 -> 44956 | K14: =D41 -> 10.553916 | L14: =E41 -> 0 | M14: =F41 -> 0 | N14: =SUM(K14:M14) -> 10.553916
B15: ='CF (Funds)'!B10 -> Sinovation Disrupt Fund, L.P. | C15: ='CF (Funds)'!C10 -> 44554 | D15: ='CF (Funds)'!D10 -> -7.385016 | E15: ='CF (Funds)'!E10 -> 0 | G15: =SUM(D15:F15) -> -7.385016 | I15: =B42 -> New Space Capital Fund I | J15: =C42 -> 44956 | K15: =D42 -> 0 | L15: =E42 -> 2.9557744 | M15: =F42 -> 0 | N15: =SUM(K15:M15) -> 2.9557744 | P15: Total | Q15: =SUM(Q9:Q14) -> 395.37629 | R15: =SUM(R9:R14) -> 133.65097 | S15: =SUM(S9:S14) -> 262.75328 | T15: =SUM(T9:T14) -> 4.4275637 | U15: =SUM(U9:U14) -> 122.28936 | V15: =XIRR(G8:G59,C8:C59) -> -0.02269576 | W15: =(T15+U15)/R15 -> 0.94811825 | X15: =U15/R15 -> 0.91499044 | Y15: =T15/R15 -> 0.033127807
B16: ='CF (Funds)'!B11 -> Sinovation Disrupt Fund, L.P. | C16: ='CF (Funds)'!C11 -> 44554 | D16: ='CF (Funds)'!D11 -> 4.0733456 | E16: ='CF (Funds)'!E11 -> 0 | G16: =SUM(D16:F16) -> 4.0733456 | I16: New Space Capital Fund I | J16: =$C$4 -> 45016 | M16: =F51 -> 14.294891 | N16: =SUM(K16:M16) -> 14.294891
B17: ='CF (Funds)'!B12 -> Sinovation Disrupt Fund, L.P. | C17: ='CF (Funds)'!C12 -> 44554 | D17: ='CF (Funds)'!D12 -> 0 | E17: ='CF (Funds)'!E12 -> 0.139694 | G17: =SUM(D17:F17) -> 0.139694
B18: ='CF (Funds)'!B13 -> Sinovation Disrupt Fund, L.P. | C18: ='CF (Funds)'!C13 -> 44703 | D18: ='CF (Funds)'!D13 -> 5.673074 | E18: ='CF (Funds)'!E13 -> 0 | G18: =SUM(D18:F18) -> 5.673074 | I18: XIRR | J18: =XIRR(N9:N16,J9:J16) -> 0.1090443 | L18: Contributions | M18: =-SUM(K9:K16)='Summary | 01 '!K36 -> TRUE | P18: XIRR | Q18: =XIRR(G8:G59,C8:C59) -> -0.02269576
B19: ='CF (Funds)'!B14 -> Sinovation Disrupt Fund, L.P. | C19: ='CF (Funds)'!C14 -> 44703 | D19: ='CF (Funds)'!D14 -> 0 | E19: ='CF (Funds)'!E14 -> 0.227786 | G19: =SUM(D19:F19) -> 0.227786 | I19: TVPI | J19: =SUM(L9:M16)/-SUM(K9:K16) -> 1.5600119 | L19: Distributions | M19: =-SUM(L9:L17)=-'Summary | 01 '!M36 -> TRUE | P19: TVPI | Q19: =SUM(T9:U13)/SUM(R9:R13) -> 0.94811825
B20: ='CF (Funds)'!B15 -> Sinovation Disrupt Fund, L.P. | C20: ='CF (Funds)'!C15 -> 44776 | D20: ='CF (Funds)'!D15 -> -3.235493 | E20: ='CF (Funds)'!E15 -> 0 | G20: =SUM(D20:F20) -> -3.235493 | I20: RPI | J20: =SUM(M9:M16)/-SUM(K9:K16) -> 1.2927154 | L20: Residual Value | M20: =M16='Summary | 01 '!N36 -> TRUE | P20: RPI | Q20: =SUM(U9:U13)/SUM(R9:R13) -> 0.91499044
B21: ='CF (Funds)'!B16 -> Sinovation Disrupt Fund, L.P. | C21: ='CF (Funds)'!C16 -> 44960 | D21: ='CF (Funds)'!D16 -> -2.631528 | E21: ='CF (Funds)'!E16 -> 0 | G21: =SUM(D21:F21) -> -2.631528 | I21: DPI | J21: =SUM(L9:L16)/-SUM(K9:K16) -> 0.26729654 | P21: DPI | Q21: =SUM(T9:T13)/SUM(R9:R13) -> 0.033127807
B22: ='CF (Funds)'!B17 -> North Summit Capital Fund | C22: ='CF (Funds)'!C17 -> 43665 | D22: ='CF (Funds)'!D17 -> -3 | E22: ='CF (Funds)'!E17 -> 0 | G22: =SUM(D22:F22) -> -3
B23: ='CF (Funds)'!B18 -> North Summit Capital Fund | C23: ='CF (Funds)'!C18 -> 43983 | D23: ='CF (Funds)'!D18 -> -4.485 | E23: ='CF (Funds)'!E18 -> 0 | G23: =SUM(D23:F23) -> -4.485
B24: ='CF (Funds)'!B19 -> North Summit Capital Fund | C24: ='CF (Funds)'!C19 -> 43879 | D24: ='CF (Funds)'!D19 -> -9.50975 | E24: ='CF (Funds)'!E19 -> 0 | G24: =SUM(D24:F24) -> -9.50975 | I24: =B43 -> New Space Capital SCSp | J24: =C43 -> 44087 | K24: =D43 -> -2.7058824 | N24: =SUM(K24:M24) -> -2.7058824
B25: ='CF (Funds)'!B20 -> North Summit Capital Fund | C25: ='CF (Funds)'!C20 -> 43934 | D25: ='CF (Funds)'!D20 -> -41.3 | E25: ='CF (Funds)'!E20 -> 0 | G25: =SUM(D25:F25) -> -41.3 | I25: New Space Capital SCSp | J25: =$C$4 -> 45016 | M25: =F52 -> 2.7058824 | N25: =SUM(K25:M25) -> 2.7058824
B26: ='CF (Funds)'!B21 -> North Summit Capital Fund | C26: ='CF (Funds)'!C21 -> 44151 | D26: ='CF (Funds)'!D21 -> 9.95 | E26: ='CF (Funds)'!E21 -> 0 | G26: =SUM(D26:F26) -> 9.95
B27: ='CF (Funds)'!B22 -> North Summit Capital Fund | C27: ='CF (Funds)'!C22 -> 44151 | D27: ='CF (Funds)'!D22 -> -10.455 | E27: ='CF (Funds)'!E22 -> 0 | G27: =SUM(D27:F27) -> -10.455 | I27: XIRR | J27: =XIRR(N24:N25,J24:J25) -> 2.9802322e-09 | L27: Contributions | M27: =-SUM(K24:K25)='Summary | 01 '!K37 -> TRUE
B28: ='CF (Funds)'!B23 -> North Summit Capital Fund | C28: ='CF (Funds)'!C23 -> 44196 | D28: ='CF (Funds)'!D23 -> 4.975 | E28: ='CF (Funds)'!E23 -> 0 | G28: =SUM(D28:F28) -> 4.975 | I28: TVPI | J28: =SUM(L24:M25)/-SUM(K24:K25) -> 1 | L28: Distributions | M28: =-SUM(L21:L26)=-'Summary | 01 '!L37 -> TRUE
B29: ='CF (Funds)'!B24 -> North Summit Capital Fund | C29: ='CF (Funds)'!C24 -> 44196 | D29: ='CF (Funds)'!D24 -> -3.452293 | E29: ='CF (Funds)'!E24 -> 0 | G29: =SUM(D29:F29) -> -3.452293 | I29: RPI | J29: =SUM(M24:M25)/-SUM(K24:K25) -> 1 | L29: Residual Value | M29: =M25='Summary | 01 '!N37 -> TRUE
B30: ='CF (Funds)'!B25 -> North Summit Capital Fund | C30: ='CF (Funds)'!C25 -> 44196 | D30: ='CF (Funds)'!D25 -> 0 | E30: ='CF (Funds)'!E25 -> 0.582902 | G30: =SUM(D30:F30) -> 0.582902 | I30: DPI | J30: =SUM(L24:L25)/-SUM(K24:K25) -> 0
B31: ='CF (Funds)'!B26 -> North Summit Capital Fund | C31: ='CF (Funds)'!C26 -> 44370 | D31: ='CF (Funds)'!D26 -> -5.97 | E31: ='CF (Funds)'!E26 -> 0 | G31: =SUM(D31:F31) -> -5.97
B32: ='CF (Funds)'!B27 -> North Summit Capital Fund | C32: ='CF (Funds)'!C27 -> 44400 | D32: ='CF (Funds)'!D27 -> -0.75 | E32: ='CF (Funds)'!E27 -> 0 | G32: =SUM(D32:F32) -> -0.75
B33: ='CF (Funds)'!B28 -> North Summit Capital Fund | C33: ='CF (Funds)'!C28 -> 44400 | D33: ='CF (Funds)'!D28 -> 0 | E33: ='CF (Funds)'!E28 -> 0.445059 | G33: =SUM(D33:F33) -> 0.445059 | I33: =B22 -> North Summit Capital Fund | J33: =C22 -> 43665 | K33: =D22 -> -3 | L33: =E22 -> 0 | M33: =F22 -> 0 | N33: =SUM(K33:M33) -> -3
B34: ='CF (Funds)'!B29 -> North Summit Capital Fund | C34: ='CF (Funds)'!C29 -> 44554 | D34: ='CF (Funds)'!D29 -> 1.78239 | E34: ='CF (Funds)'!E29 -> 0 | G34: =SUM(D34:F34) -> 1.78239 | I34: =B23 -> North Summit Capital Fund | J34: =C23 -> 43983 | K34: =D23 -> -4.485 | L34: =E23 -> 0 | M34: =F23 -> 0 | N34: =SUM(K34:M34) -> -4.485
B35: ='CF (Funds)'!B30 -> North Summit Capital Fund | C35: ='CF (Funds)'!C30 -> 44676 | D35: ='CF (Funds)'!D30 -> -21 | E35: ='CF (Funds)'!E30 -> 0 | G35: =SUM(D35:F35) -> -21 | I35: =B24 -> North Summit Capital Fund | J35: =C24 -> 43879 | K35: =D24 -> -9.50975 | L35: =E24 -> 0 | M35: =F24 -> 0 | N35: =SUM(K35:M35) -> -9.50975
B36: ='CF (Funds)'!B31 -> New Space Capital Fund I | C36: ='CF (Funds)'!C31 -> 44087 | D36: ='CF (Funds)'!D31 -> -20.917553 | E36: ='CF (Funds)'!E31 -> 0 | G36: =SUM(D36:F36) -> -20.917553 | I36: =B25 -> North Summit Capital Fund | J36: =C25 -> 43934 | K36: =D25 -> -41.3 | L36: =E25 -> 0 | M36: =F25 -> 0 | N36: =SUM(K36:M36) -> -41.3
B37: ='CF (Funds)'!B32 -> New Space Capital Fund I | C37: ='CF (Funds)'!C32 -> 44287 | D37: ='CF (Funds)'!D32 -> -0.21103182 | E37: ='CF (Funds)'!E32 -> 0 | G37: =SUM(D37:F37) -> -0.21103182 | I37: =B26 -> North Summit Capital Fund | J37: =C26 -> 44151 | K37: =D26 -> 9.95 | L37: =E26 -> 0 | M37: =F26 -> 0 | N37: =SUM(K37:M37) -> 9.95
B38: ='CF (Funds)'!B33 -> New Space Capital Fund I | C38: ='CF (Funds)'!C33 -> 44442 | D38: ='CF (Funds)'!D33 -> -0.23965473 | E38: ='CF (Funds)'!E33 -> 0 | G38: =SUM(D38:F38) -> -0.23965473 | I38: =B27 -> North Summit Capital Fund | J38: =C27 -> 44151 | K38: =D27 -> -10.455 | L38: =E27 -> 0 | M38: =F27 -> 0 | N38: =SUM(K38:M38) -> -10.455
B39: ='CF (Funds)'!B34 -> New Space Capital Fund I | C39: ='CF (Funds)'!C34 -> 44623 | D39: ='CF (Funds)'!D34 -> -0.25893585 | E39: ='CF (Funds)'!E34 -> 0 | G39: =SUM(D39:F39) -> -0.25893585 | I39: =B28 -> North Summit Capital Fund | J39: =C28 -> 44196 | K39: =D28 -> 4.975 | L39: =E28 -> 0 | M39: =F28 -> 0 | N39: =SUM(K39:M39) -> 4.975
B40: ='CF (Funds)'!B35 -> New Space Capital Fund I | C40: ='CF (Funds)'!C35 -> 44784 | D40: ='CF (Funds)'!D35 -> 0.015224657 | E40: ='CF (Funds)'!E35 -> 0 | G40: =SUM(D40:F40) -> 0.015224657 | I40: =B29 -> North Summit Capital Fund | J40: =C29 -> 44196 | K40: =D29 -> -3.452293 | L40: =E29 -> 0 | M40: =F29 -> 0 | N40: =SUM(K40:M40) -> -3.452293
B41: ='CF (Funds)'!B36 -> New Space Capital Fund I | C41: ='CF (Funds)'!C36 -> 44956 | D41: ='CF (Funds)'!D36 -> 10.553916 | E41: ='CF (Funds)'!E36 -> 0 | G41: =SUM(D41:F41) -> 10.553916 | I41: =B30 -> North Summit Capital Fund | J41: =C30 -> 44196 | K41: =D30 -> 0 | L41: =E30 -> 0.582902 | M41: =F30 -> 0 | N41: =SUM(K41:M41) -> 0.582902
B42: ='CF (Funds)'!B37 -> New Space Capital Fund I | C42: ='CF (Funds)'!C37 -> 44956 | D42: ='CF (Funds)'!D37 -> 0 | E42: ='CF (Funds)'!E37 -> 2.9557744 | G42: =SUM(D42:F42) -> 2.9557744 | I42: =B31 -> North Summit Capital Fund | J42: =C31 -> 44370 | K42: =D31 -> -5.97 | L42: =E31 -> 0 | M42: =F31 -> 0 | N42: =SUM(K42:M42) -> -5.97
B43: ='CF (Funds)'!B38 -> New Space Capital SCSp | C43: ='CF (Funds)'!C38 -> 44087 | D43: ='CF (Funds)'!D38 -> -2.7058824 | E43: ='CF (Funds)'!E38 -> 0 | G43: =SUM(D43:F43) -> -2.7058824 | I43: =B32 -> North Summit Capital Fund | J43: =C32 -> 44400 | K43: =D32 -> -0.75 | L43: =E32 -> 0 | M43: =F32 -> 0 | N43: =SUM(K43:M43) -> -0.75
B44: ='CF (Funds)'!B39 -> Acies Investments Fund I, L.P. | C44: ='CF (Funds)'!C39 -> 44540 | D44: ='CF (Funds)'!D39 -> -2.8053125 | E44: ='CF (Funds)'!E39 -> 0 | G44: =SUM(D44:F44) -> -2.8053125 | I44: =B33 -> North Summit Capital Fund | J44: =C33 -> 44400 | K44: =D33 -> 0 | L44: =E33 -> 0.445059 | M44: =F33 -> 0 | N44: =SUM(K44:M44) -> 0.445059
... B46: ='CF (Funds)'!B41 -> Acies Investments Fund I, L.P. | C46: ='CF (Funds)'!C41 -> 44683 | D46: ='CF (Funds)'!D41 -> -1.025775 | E46: ='CF (Funds)'!E41 -> 0 | G46: =SUM(D46:F46) -> -1.025775 | I46: =B35 -> North Summit Capital Fund | J46: =C35 -> 44676 | K46: =D35 -> -21 | L46: =E35 -> 0 | M46: =F35 -> 0 | N46: =SUM(K46:M46) -> -21
B47: ='CF (Funds)'!B42 -> Acies Investments Fund I, L.P. | C47: ='CF (Funds)'!C42 -> 44707 | D47: ='CF (Funds)'!D42 -> -3.388275 | E47: ='CF (Funds)'!E42 -> 0 | G47: =SUM(D47:F47) -> -3.388275 | I47: North Summit Capital Fund | J47: =$C$4 -> 45016 | M47: =F50 -> 70.03 | N47: =SUM(K47:M47) -> 70.03
B48: ='CF (Funds)'!B43 -> Acies Investments Fund I, L.P. | C48: ='CF (Funds)'!C43 -> 44875 | D48: ='CF (Funds)'!D43 -> -3.388275 | E48: ='CF (Funds)'!E43 -> 0 | G48: =SUM(D48:F48) -> -3.388275
B49: Sinovation Disrupt Fund, L.P. | C49: =$C$4 -> 45016 | F49: =VLOOKUP(B49,NAV!$B$2:$H$42,4,0) -> 21.51575 | G49: =SUM(D49:F49) -> 21.51575 | I49: XIRR | J49: =XIRR(N33:N47,J33:J47,-0.1) -> -0.064168629 | L49: Contributions | M49: =-SUM(K33:K46)='Summary | 01 '!K38 -> TRUE
B50: North Summit Capital Fund | C50: =$C$4 -> 45016 | F50: =VLOOKUP(B50,NAV!$B$2:$H$42,4,0) -> 70.03 | G50: =SUM(D50:F50) -> 70.03 | I50: TVPI | J50: =SUM(L33:M47)/-SUM(K33:K47) -> 0.85391164 | L50: Distributions | M50: =-SUM(L33:L46)=-'Summary | 01 '!M38 -> TRUE
B51: New Space Capital Fund I | C51: =$C$4 -> 45016 | F51: =VLOOKUP(B51,NAV!$B$2:$H$42,4,0) -> 14.294891 | G51: =SUM(D51:F51) -> 14.294891 | I51: RPI | J51: =SUM(M33:M47)/-SUM(K33:K47) -> 0.84155852 | L51: Residual Value | M51: =M47='Summary | 01 '!N38 -> TRUE
B52: New Space Capital SCSp | C52: =$C$4 -> 45016 | F52: =VLOOKUP(B52,NAV!$B$2:$H$42,4,0) -> 2.7058824 | G52: =SUM(D52:F52) -> 2.7058824 | I52: DPI | J52: =SUM(L33:L47)/-SUM(K33:K47) -> 0.012353125
B53: Acies Investments Fund I, L.P. | C53: =$C$4 -> 45016 | F53: =VLOOKUP(B53,NAV!$B$2:$H$42,4,0) -> 13.742841 | G53: =SUM(D53:F53) -> 13.742841
I55: =B8 -> Sinovation Disrupt Fund, L.P. | J55: =C8 -> 44153 | K55: =D8 -> -10.5 | L55: =E8 -> 0 | M55: =F8 -> 0 | N55: =SUM(K55:M55) -> -10.5
I56: =B9 -> Sinovation Disrupt Fund, L.P. | J56: =C9 -> 44238 | K56: =D9 -> 4.214027 | L56: =E9 -> 0 | M56: =F9 -> 0 | N56: =SUM(K56:M56) -> 4.214027
I57: =B10 -> Sinovation Disrupt Fund, L.P. | J57: =C10 -> 44238 | K57: =D10 -> 0 | L57: =E10 -> 0.05044835 | M57: =F10 -> 0 | N57: =SUM(K57:M57) -> 0.05044835
I58: =B11 -> Sinovation Disrupt Fund, L.P. | J58: =C11 -> 44285 | K58: =D11 -> -6.433746 | L58: =E11 -> 0 | M58: =F11 -> 0 | N58: =SUM(K58:M58) -> -6.433746
I59: =B12 -> Sinovation Disrupt Fund, L.P. | J59: =C12 -> 44269 | K59: =D12 -> 1.1352074 | L59: =E12 -> 0 | M59: =F12 -> 0 | N59: =SUM(K59:M59) -> 1.1352074
I60: =B13 -> Sinovation Disrupt Fund, L.P. | J60: =C13 -> 44269 | K60: =D13 -> 0 | L60: =E13 -> 0.0259 | M60: =F13 -> 0 | N60: =SUM(K60:M60) -> 0.0259
I61: =B14 -> Sinovation Disrupt Fund, L.P. | J61: =C14 -> 44483 | K61: =D14 -> -7.567138 | L61: =E14 -> 0 | M61: =F14 -> 0 | N61: =SUM(K61:M61) -> -7.567138
I62: =B15 -> Sinovation Disrupt Fund, L.P. | J62: =C15 -> 44554 | K62: =D15 -> -7.385016 | L62: =E15 -> 0 | M62: =F15 -> 0 | N62: =SUM(K62:M62) -> -7.385016
I63: =B16 -> Sinovation Disrupt Fund, L.P. | J63: =C16 -> 44554 | K63: =D16 -> 4.0733456 | L63: =E16 -> 0 | M63: =F16 -> 0 | N63: =SUM(K63:M63) -> 4.0733456
I64: =B17 -> Sinovation Disrupt Fund, L.P. | J64: =C17 -> 44554 | K64: =D17 -> 0 | L64: =E17 -> 0.139694 | M64: =F17 -> 0 | N64: =SUM(K64:M64) -> 0.139694
I65: =B18 -> Sinovation Disrupt Fund, L.P. | J65: =C18 -> 44703 | K65: =D18 -> 5.673074 | L65: =E18 -> 0 | M65: =F18 -> 0 | N65: =SUM(K65:M65) -> 5.673074
I66: =B19 -> Sinovation Disrupt Fund, L.P. | J66: =C19 -> 44703 | K66: =D19 -> 0 | L66: =E19 -> 0.227786 | M66: =F19 -> 0 | N66: =SUM(K66:M66) -> 0.227786
... I68: =B21 -> Sinovation Disrupt Fund, L.P. | J68: =C21 -> 44960 | K68: =D21 -> -2.631528 | L68: =E21 -> 0 | M68: =F21 -> 0 | N68: =SUM(K68:M68) -> -2.631528
I69: Sinovation Disrupt Fund, L.P. | J69: =$C$4 -> 45016 | M69: =F49 -> 21.51575 | N69: =SUM(K69:M69) -> 21.51575
I71: XIRR | J71: =XIRR(N55:N69,J55:J69) -> -0.018159524 | L71: Contributions | M71: =-SUM(K55:K66)='Summary | 01 '!K39 -> FALSE
I72: TVPI | J72: =SUM(L55:M69)/-SUM(K55:K69) -> 0.96920685 | L72: Distributions | M72: =-SUM(L55:L66)=-'Summary | 01 '!M39 -> TRUE
I73: RPI | J73: =SUM(M55:M69)/-SUM(K55:K69) -> 0.94961806 | L73: Residual Value | M73: =M69='Summary | 01 '!N39 -> TRUE
I74: DPI | J74: =SUM(L55:L69)/-SUM(K55:K69) -> 0.019588786
I77: =B44 -> Acies Investments Fund I, L.P. | J77: =C44 -> 44540 | K77: =D44 -> -2.8053125 | L77: =E44 -> 0 | M77: =F44 -> 0 | N77: =SUM(K77:M77) -> -2.8053125
I78: =B45 -> Acies Investments Fund I, L.P. | J78: =C45 -> 44602 | K78: =D45 -> -3.4075 | L78: =E45 -> 0 | M78: =F45 -> 0 | N78: =SUM(K78:M78) -> -3.4075
I79: =B46 -> Acies Investments Fund I, L.P. | J79: =C46 -> 44683 | K79: =D46 -> -1.025775 | L79: =E46 -> 0 | M79: =F46 -> 0 | N79: =SUM(K79:M79) -> -1.025775
I80: =B47 -> Acies Investments Fund I, L.P. | J80: =C47 -> 44707 | K80: =D47 -> -3.388275 | L80: =E47 -> 0 | M80: =F47 -> 0 | N80: =SUM(K80:M80) -> -3.388275
I81: =B48 -> Acies Investments Fund I, L.P. | J81: =C48 -> 44875 | K81: =D48 -> -3.388275 | L81: =E48 -> 0 | M81: =F48 -> 0 | N81: =SUM(K81:M81) -> -3.388275
I82: Acies Investments Fund I, L.P. | J82: =$C$4 -> 45016 | M82: =F53 -> 13.742841 | N82: =SUM(K82:M82) -> 13.742841
I84: XIRR | J84: =XIRR(N77:N82,J77:J82) -> -0.021553859 | L84: Contributions | M84: =-SUM(K77:K82)='Summary | 01 '!K40 -> TRUE
I85: TVPI | J85: =SUM(L77:M82)/-SUM(K77:K82) -> 0.98057126 | L85: Distributions | M85: =-SUM(L77:L87)=-'Summary | 01 '!M40 -> TRUE
I86: RPI | J86: =SUM(M77:M82)/-SUM(K77:K82) -> 0.98057126 | L86: Residual Value | M86: =M82='Summary | 01 '!N40 -> TRUE
I87: DPI | J87: =SUM(L77:L82)/-SUM(K77:K82) -> 0

Sheet 4.All
B2: IRR - All Investments (Equity, Debt, Funds) | H2: TEST | I2: =COUNTA(B8:B85)=COUNTA('CF (Equity, Debt)'!C4:C34)+COUNTA('CF (Equity, Debt)'!C37:C40)+COUNTA('CF (Funds)'!B3:B43) -> TRUE
B4: Date of NAV | C4: =D!D2 -> 45016
B6: (in USD, Mn)
B7: Investment | C7: Payment date | D7: Contribution | E7: Distributions | F7: Remaining Value | G7: Combined | H7: Type | J7: Invested | K7: Remaining Commitment | L7: Distributions | M7: Residual Value | N7: IRR | O7: TVPI | P7: RPI | Q7: DPI
B8: ='CF (Equity, Debt)'!C4 -> Jollychic Holding Limited | C8: ='CF (Equity, Debt)'!D4 -> 43470 | D8: ='CF (Equity, Debt)'!E4 -> -30 | G8: =SUM(D8:F8) -> -30 | H8: Equity
B9: ='CF (Equity, Debt)'!C5 -> Jollychic Holding Limited | C9: ='CF (Equity, Debt)'!D5 -> 43724 | D9: ='CF (Equity, Debt)'!E5 -> -20 | G9: =SUM(D9:F9) -> -20 | H9: Equity | J9: =-SUM(D8:D111) -> 2227.1929 | L9: =SUM(E8:E111) -> 9.8983484 | M9: =SUM(F8:F111) -> 2207.4575 | N9: =XIRR(G8:G110,C8:C110) -> -0.0033056326 | O9: =(L9+M9)/J9 -> 0.99558319 | P9: =M9/J9 -> 0.99113887 | Q9: =L9/J9 -> 0.0044443157
B10: ='CF (Equity, Debt)'!C6 -> Jollychic Holding Limited | C10: ='CF (Equity, Debt)'!D6 -> 43724 | D10: ='CF (Equity, Debt)'!E6 -> -15 | G10: =SUM(D10:F10) -> -15 | H10: Equity
B11: ='CF (Equity, Debt)'!C7 -> Mena Mobile Inc | C11: ='CF (Equity, Debt)'!D7 -> 43563 | D11: ='CF (Equity, Debt)'!E7 -> -8 | G11: =SUM(D11:F11) -> -8 | H11: Equity | J11: =ROUND(J9,2)=ROUND('Summary | 01 '!K43,2) -> TRUE | L11: =ROUND(L9,3)=ROUND('Summary | 01 '!M43,3) -> TRUE | M11: =ROUND(M9,3)=ROUND('Summary | 01 '!N43,3) -> TRUE
B12: ='CF (Equity, Debt)'!C8 -> Flyr Inc | C12: ='CF (Equity, Debt)'!D8 -> 43570 | D12: ='CF (Equity, Debt)'!E8 -> -4.9999981 | G12: =SUM(D12:F12) -> -4.9999981 | H12: Equity
B13: ='CF (Equity, Debt)'!C9 -> Flyr Inc | C13: ='CF (Equity, Debt)'!D9 -> 43915 | D13: ='CF (Equity, Debt)'!E9 -> -5.0000019 | G13: =SUM(D13:F13) -> -5.0000019 | H13: Equity
B14: ='CF (Equity, Debt)'!C10 -> Esyasoft Holding | C14: ='CF (Equity, Debt)'!D10 -> 43870 | D14: ='CF (Equity, Debt)'!E10 -> -2.5 | G14: =SUM(D14:F14) -> -2.5 | H14: Equity
B15: ='CF (Equity, Debt)'!C11 -> Beyond Limits | C15: ='CF (Equity, Debt)'!D11 -> 43879 | D15: ='CF (Equity, Debt)'!E11 -> -20 | G15: =SUM(D15:F15) -> -20 | H15: Equity
B16: ='CF (Equity, Debt)'!C12 -> Beyond Limits | C16: ='CF (Equity, Debt)'!D12 -> 43921 | D16: ='CF (Equity, Debt)'!E12 -> -30 | G16: =SUM(D16:F16) -> -30 | H16: Equity
B17: ='CF (Equity, Debt)'!C13 -> Beyond Limits | C17: ='CF (Equity, Debt)'!D13 -> 43989 | D17: ='CF (Equity, Debt)'!E13 -> -30 | G17: =SUM(D17:F17) -> -30 | H17: Equity
B18: ='CF (Equity, Debt)'!C14 -> Beyond Limits | C18: ='CF (Equity, Debt)'!D14 -> 44103 | D18: ='CF (Equity, Debt)'!E14 -> -10 | G18: =SUM(D18:F18) -> -10 | H18: Equity
B19: ='CF (Equity, Debt)'!C15 -> ONT plc | C19: ='CF (Equity, Debt)'!D15 -> 43968 | D19: ='CF (Equity, Debt)'!E15 -> -50 | G19: =SUM(D19:F19) -> -50 | H19: Equity
B20: ='CF (Equity, Debt)'!C16 -> ONT plc | C20: ='CF (Equity, Debt)'!D16 -> 44006 | D20: ='CF (Equity, Debt)'!E16 -> -27.268351 | G20: =SUM(D20:F20) -> -27.268351 | H20: Equity
B21: ='CF (Equity, Debt)'!C17 -> ONT plc | C21: ='CF (Equity, Debt)'!D17 -> 43837 | D21: ='CF (Equity, Debt)'!E17 -> -18.109441 | G21: =SUM(D21:F21) -> -18.109441 | H21: Equity
B22: ='CF (Equity, Debt)'!C18 -> ONT plc | C22: ='CF (Equity, Debt)'!D18 -> 43990 | D22: ='CF (Equity, Debt)'!E18 -> -34.851687 | G22: =SUM(D22:F22) -> -34.851687 | H22: Equity
B23: ='CF (Equity, Debt)'!C19 -> ONT plc | C23: ='CF (Equity, Debt)'!D19 -> 44315 | D23: ='CF (Equity, Debt)'!E19 -> -11.24078 | G23: =SUM(D23:F23) -> -11.24078 | H23: Equity
... B31: ='CF (Equity, Debt)'!C27 -> DriveNets | C31: ='CF (Equity, Debt)'!D27 -> 44680 | D31: ='CF (Equity, Debt)'!E27 -> -100 | G31: =SUM(D31:F31) -> -100 | H31: Equity
B32: ='CF (Equity, Debt)'!C28 -> Esyasoft Holding | C32: ='CF (Equity, Debt)'!D28 -> 44691 | D32: ='CF (Equity, Debt)'!E28 -> 0 | E32: 5 | G32: =SUM(D32:F32) -> 5 | H32: Equity
B33: ='CF (Equity, Debt)'!C29 -> vTv Therapeutics Inc. | C33: ='CF (Equity, Debt)'!D29 -> 44712 | D33: ='CF (Equity, Debt)'!E29 -> -12.5 | G33: =SUM(D33:F33) -> -12.5 | H33: Equity
B34: ='CF (Equity, Debt)'!C30 -> Honor Device Co Ltd | C34: ='CF (Equity, Debt)'!D30 -> 44769 | D34: ='CF (Equity, Debt)'!E30 -> -600 | G34: =SUM(D34:F34) -> -600 | H34: Equity
B35: ='CF (Equity, Debt)'!C31 -> Honor Device Co Ltd | C35: ='CF (Equity, Debt)'!D31 -> 44849 | D35: ='CF (Equity, Debt)'!E31 -> -200 | G35: =SUM(D35:F35) -> -200 | H35: Equity
B36: ='CF (Equity, Debt)'!C32 -> Applied AI Corporation Limited | C36: ='CF (Equity, Debt)'!D32 -> 44861 | D36: ='CF (Equity, Debt)'!E32 -> -4.75 | G36: =SUM(D36:F36) -> -4.75 | H36: Equity
B37: ='CF (Equity, Debt)'!C33 -> eSpace | C37: ='CF (Equity, Debt)'!D33 -> 44892 | D37: ='CF (Equity, Debt)'!E33 -> -15 | G37: =SUM(D37:F37) -> -15 | H37: Equity
B38: ='CF (Equity, Debt)'!C34 -> vTv Therapeutics Inc. | C38: ='CF (Equity, Debt)'!D34 -> 44985 | D38: ='CF (Equity, Debt)'!E34 -> -12.03125 | G38: =SUM(D38:F38) -> -12.03125 | H38: Equity
B40: ='CF (Equity, Debt)'!C37 -> Glass Earth Holdings LLC | C40: ='CF (Equity, Debt)'!D37 -> 43635 | D40: ='CF (Equity, Debt)'!E37 -> -8 | G40: =SUM(D40:F40) -> -8 | H40: Debt
B41: ='CF (Equity, Debt)'!C38 -> Mena Mobile Inc (Debt) | C41: ='CF (Equity, Debt)'!D38 -> 44293 | D41: ='CF (Equity, Debt)'!E38 -> -2.353982 | G41: =SUM(D41:F41) -> -2.353982 | H41: Debt
B42: ='CF (Equity, Debt)'!C39 -> Esyasoft Holding (Debt) | C42: ='CF (Equity, Debt)'!D39 -> 44384 | D42: ='CF (Equity, Debt)'!E39 -> -0.411765 | G42: =SUM(D42:F42) -> -0.411765 | H42: Debt
B43: ='CF (Equity, Debt)'!C40 -> Esyasoft Holding (Debt) | C43: ='CF (Equity, Debt)'!D40 -> 44902 | D43: ='CF (Equity, Debt)'!E40 -> 0 | E43: ='CF (Equity, Debt)'!F40 -> 0.47078465 | G43: =SUM(D43:F43) -> 0.47078465 | H43: Debt
B45: ='CF (Funds)'!B3 -> Sinovation Disrupt Fund, L.P. | C45: ='CF (Funds)'!C3 -> 44153 | D45: ='CF (Funds)'!D3 -> -10.5 | E45: ='CF (Funds)'!E3 -> 0 | G45: =SUM(D45:F45) -> -10.5 | H45: Fund
B46: ='CF (Funds)'!B4 -> Sinovation Disrupt Fund, L.P. | C46: ='CF (Funds)'!C4 -> 44238 | D46: ='CF (Funds)'!D4 -> 4.214027 | E46: ='CF (Funds)'!E4 -> 0 | G46: =SUM(D46:F46) -> 4.214027 | H46: Fund
B47: ='CF (Funds)'!B5 -> Sinovation Disrupt Fund, L.P. | C47: ='CF (Funds)'!C5 -> 44238 | D47: ='CF (Funds)'!D5 -> 0 | E47: ='CF (Funds)'!E5 -> 0.05044835 | G47: =SUM(D47:F47) -> 0.05044835 | H47: Fund
B48: ='CF (Funds)'!B6 -> Sinovation Disrupt Fund, L.P. | C48: ='CF (Funds)'!C6 -> 44285 | D48: ='CF (Funds)'!D6 -> -6.433746 | E48: ='CF (Funds)'!E6 -> 0 | G48: =SUM(D48:F48) -> -6.433746 | H48: Fund
B49: ='CF (Funds)'!B7 -> Sinovation Disrupt Fund, L.P. | C49: ='CF (Funds)'!C7 -> 44269 | D49: ='CF (Funds)'!D7 -> 1.1352074 | E49: ='CF (Funds)'!E7 -> 0 | G49: =SUM(D49:F49) -> 1.1352074 | H49: Fund
B50: ='CF (Funds)'!B8 -> Sinovation Disrupt Fund, L.P. | C50: ='CF (Funds)'!C8 -> 44269 | D50: ='CF (Funds)'!D8 -> 0 | E50: ='CF (Funds)'!E8 -> 0.0259 | G50: =SUM(D50:F50) -> 0.0259 | H50: Fund
B51: ='CF (Funds)'!B9 -> Sinovation Disrupt Fund, L.P. | C51: ='CF (Funds)'!C9 -> 44483 | D51: ='CF (Funds)'!D9 -> -7.567138 | E51: ='CF (Funds)'!E9 -> 0 | G51: =SUM(D51:F51) -> -7.567138 | H51: Fund
B52: ='CF (Funds)'!B10 -> Sinovation Disrupt Fund, L.P. | C52: ='CF (Funds)'!C10 -> 44554 | D52: ='CF (Funds)'!D10 -> -7.385016 | E52: ='CF (Funds)'!E10 -> 0 | G52: =SUM(D52:F52) -> -7.385016 | H52: Fund
B53: ='CF (Funds)'!B11 -> Sinovation Disrupt Fund, L.P. | C53: ='CF (Funds)'!C11 -> 44554 | D53: ='CF (Funds)'!D11 -> 4.0733456 | E53: ='CF (Funds)'!E11 -> 0 | G53: =SUM(D53:F53) -> 4.0733456 | H53: Fund
B54: ='CF (Funds)'!B12 -> Sinovation Disrupt Fund, L.P. | C54: ='CF (Funds)'!C12 -> 44554 | D54: ='CF (Funds)'!D12 -> 0 | E54: ='CF (Funds)'!E12 -> 0.139694 | G54: =SUM(D54:F54) -> 0.139694 | H54: Fund
B55: ='CF (Funds)'!B13 -> Sinovation Disrupt Fund, L.P. | C55: ='CF (Funds)'!C13 -> 44703 | D55: ='CF (Funds)'!D13 -> 5.673074 | E55: ='CF (Funds)'!E13 -> 0 | G55: =SUM(D55:F55) -> 5.673074 | H55: Fund
B56: ='CF (Funds)'!B14 -> Sinovation Disrupt Fund, L.P. | C56: ='CF (Funds)'!C14 -> 44703 | D56: ='CF (Funds)'!D14 -> 0 | E56: ='CF (Funds)'!E14 -> 0.227786 | G56: =SUM(D56:F56) -> 0.227786 | H56: Fund
... B85: ='CF (Funds)'!B43 -> Acies Investments Fund I, L.P. | C85: ='CF (Funds)'!C43 -> 44875 | D85: ='CF (Funds)'!D43 -> -3.388275 | E85: ='CF (Funds)'!E43 -> 0 | G85: =SUM(D85:F85) -> -3.388275 | H85: Fund
B86: Jollychic Holding Limited | C86: =$C$4 -> 45016 | F86: =VLOOKUP(B86,NAV!$B$9:$E$41,4,0) -> 0 | G86: =SUM(D86:F86) -> 0 | H86: NAV
B87: Mena Mobile Inc | C87: =$C$4 -> 45016 | F87: =VLOOKUP(B87,NAV!$B$9:$E$41,4,0) -> 3.1 | G87: =SUM(D87:F87) -> 3.1 | H87: NAV
B88: Flyr Inc | C88: =$C$4 -> 45016 | F88: =VLOOKUP(B88,NAV!$B$9:$E$41,4,0) -> 78.08223 | G88: =SUM(D88:F88) -> 78.08223 | H88: NAV
B89: Esyasoft Holding | C89: =$C$4 -> 45016 | F89: =VLOOKUP(B89,NAV!$B$9:$E$41,4,0) -> 0 | G89: =SUM(D89:F89) -> 0 | H89: NAV
B90: Beyond Limits | C90: =$C$4 -> 45016 | F90: =VLOOKUP(B90,NAV!$B$9:$E$41,4,0) -> 91.00154 | G90: =SUM(D90:F90) -> 91.00154 | H90: NAV
B91: ONT plc | C91: =$C$4 -> 45016 | F91: =VLOOKUP(B91,NAV!$B$9:$E$41,4,0) -> 122.38019 | G91: =SUM(D91:F91) -> 122.38019 | H91: NAV
B92: Heygears | C92: =$C$4 -> 45016 | F92: =VLOOKUP(B92,NAV!$B$9:$E$41,4,0) -> 119.2498 | G92: =SUM(D92:F92) -> 119.2498 | H92: NAV
B93: Jysan Technologies | C93: =$C$4 -> 45016 | F93: =VLOOKUP(B93,NAV!$B$9:$E$41,4,0) -> 20 | G93: =SUM(D93:F93) -> 20 | H93: NAV
B94: Cerebras Systems Inc | C94: =$C$4 -> 45016 | F94: =VLOOKUP(B94,NAV!$B$9:$E$41,4,0) -> 39.999983 | G94: =SUM(D94:F94) -> 39.999983 | H94: NAV
B95: Endless Studios LLC | C95: =$C$4 -> 45016 | F95: =VLOOKUP(B95,NAV!$B$9:$E$41,4,0) -> 3 | G95: =SUM(D95:F95) -> 3 | H95: NAV
B96: Instadeep Limited | C96: =$C$4 -> 45016 | F96: =VLOOKUP(B96,NAV!$B$9:$E$41,4,0) -> 5.0237202 | G96: =SUM(D96:F96) -> 5.0237202 | H96: NAV
B97: X-fusion | C97: =$C$4 -> 45016 | F97: =VLOOKUP(B97,NAV!$B$9:$E$41,4,0) -> 424.06662 | G97: =SUM(D97:F97) -> 424.06662 | H97: NAV
... B110: Acies Investments Fund I, L.P. | C110: =$C$4 -> 45016 | F110: =VLOOKUP(B110,NAV!$B$9:$E$41,4,0) -> 13.742841 | G110: =SUM(D110:F110) -> 13.742841 | H110: NAV

Sheet 4. Mozn-IRR
B2: IRR - Mozn Investments | G2: TEST | H2: =H5=H4 -> TRUE
B4: Date of NAV | E4: =D!D2 -> 45016 | H4: =COUNTIF('CF (Equity, Debt)'!$B$4:$B$50,MID('CF (Equity, Debt)'!$B$4:$B$50,1,4)) -> 26
H5: =COUNTIFS('CF (Equity, Debt)'!B4:B40,"Mozn")+COUNTIFS('CF (Funds)'!A3:A43,"Mozn") -> 26 | K5: =K9='S | 02'!L27 -> TRUE | M5: =M9='S | 02'!M27 -> TRUE | N5: =N9='S | 02'!N27 -> TRUE
K7: Invested | L7: Remaining Commitment | M7: Distributions | N7: Residual Value | O7: IRR | P7: TVPI | Q7: RPI | R7: DPI
K9: =-SUM(F12:F57) -> 969.01067 | M9: =SUM(G12:G57) -> 5.4707846 | N9: =SUM(H12:H57) -> 928.00806 | O9: =XIRR(I12:I57,E12:E57) -> -0.019320041 | P9: =(M9+N9)/K9 -> 0.96333186 | Q9: =N9/K9 -> 0.95768612 | R9: =M9/K9 -> 0.0056457424
B10: (in USD, Mn)
B11: Investment | C11: Type | D11: Entity | E11: Payment date | F11: Contribution | G11: Distributions | H11: Remaining Value | I11: Combined
B12: ='CF (Equity, Debt)'!C4 -> Jollychic Holding Limited | C12: =VLOOKUP(B12,'S | 02'!$C$6:$J$37,2,0) -> Direct Investment | D12: =VLOOKUP(B12,'S | 02'!$C$6:$J$37,5,0) -> Mozn | E12: ='CF (Equity, Debt)'!D4 -> 43470 | F12: ='CF (Equity, Debt)'!E4 -> -30 | I12: =SUM(F12:H12) -> -30 | K12: Invested | L12: =-SUM(F12:F68) -> 969.01067 | M12: ='S | 02'!L27=L12 -> TRUE
B13: ='CF (Equity, Debt)'!C5 -> Jollychic Holding Limited | C13: =VLOOKUP(B13,'S | 02'!$C$6:$J$37,2,0) -> Direct Investment | D13: =VLOOKUP(B13,'S | 02'!$C$6:$J$37,5,0) -> Mozn | E13: ='CF (Equity, Debt)'!D5 -> 43724 | F13: ='CF (Equity, Debt)'!E5 -> -20 | I13: =SUM(F13:H13) -> -20 | K13: NAV | L13: =SUM(H12:H68) -> 928.00806
B14: ='CF (Equity, Debt)'!C6 -> Jollychic Holding Limited | C14: =VLOOKUP(B14,'S | 02'!$C$6:$J$37,2,0) -> Direct Investment | D14: =VLOOKUP(B14,'S | 02'!$C$6:$J$37,5,0) -> Mozn | E14: ='CF (Equity, Debt)'!D6 -> 43724 | F14: ='CF (Equity, Debt)'!E6 -> -15 | I14: =SUM(F14:H14) -> -15 | K14: Distributions | L14: =SUM(G12:G68) -> 5.4707846
B15: ='CF (Equity, Debt)'!C7 -> Mena Mobile Inc | C15: =VLOOKUP(B15,'S | 02'!$C$6:$J$37,2,0) -> Direct Investment | D15: =VLOOKUP(B15,'S | 02'!$C$6:$J$37,5,0) -> Mozn | E15: ='CF (Equity, Debt)'!D7 -> 43563 | F15: ='CF (Equity, Debt)'!E7 -> -8 | I15: =SUM(F15:H15) -> -8 | K15: Total Gain | L15: =L14+L13-L12 -> -35.531817
B16: ='CF (Equity, Debt)'!C8 -> Flyr Inc | C16: =VLOOKUP(B16,'S | 02'!$C$6:$J$37,2,0) -> Direct Investment | D16: =VLOOKUP(B16,'S | 02'!$C$6:$J$37,5,0) -> Mozn | E16: ='CF (Equity, Debt)'!D8 -> 43570 | F16: ='CF (Equity, Debt)'!E8 -> -4.9999981 | I16: =SUM(F16:H16) -> -4.9999981 | K16: IRR | L16: =O9 -> -0.019320041
B17: ='CF (Equity, Debt)'!C9 -> Flyr Inc | C17: =VLOOKUP(B17,'S | 02'!$C$6:$J$37,2,0) -> Direct Investment | D17: =VLOOKUP(B17,'S | 02'!$C$6:$J$37,5,0) -> Mozn | E17: ='CF (Equity, Debt)'!D9 -> 43915 | F17: ='CF (Equity, Debt)'!E9 -> -5.0000019 | I17: =SUM(F17:H17) -> -5.0000019
B18: ='CF (Equity, Debt)'!C10 -> Esyasoft Holding | C18: =VLOOKUP(B18,'S | 02'!$C$6:$J$37,2,0) -> Direct Investment | D18: =VLOOKUP(B18,'S | 02'!$C$6:$J$37,5,0) -> Mozn | E18: ='CF (Equity, Debt)'!D10 -> 43870 | F18: ='CF (Equity, Debt)'!E10 -> -2.5 | I18: =SUM(F18:H18) -> -2.5
B19: ='CF (Equity, Debt)'!C11 -> Beyond Limits | C19: =VLOOKUP(B19,'S | 02'!$C$6:$J$37,2,0) -> Direct Investment | D19: =VLOOKUP(B19,'S | 02'!$C$6:$J$37,5,0) -> Mozn | E19: ='CF (Equity, Debt)'!D11 -> 43879 | F19: ='CF (Equity, Debt)'!E11 -> -20 | I19: =SUM(F19:H19) -> -20
B20: ='CF (Equity, Debt)'!C12 -> Beyond Limits | C20: =VLOOKUP(B20,'S | 02'!$C$6:$J$37,2,0) -> Direct Investment | D20: =VLOOKUP(B20,'S | 02'!$C$6:$J$37,5,0) -> Mozn | E20: ='CF (Equity, Debt)'!D12 -> 43921 | F20: ='CF (Equity, Debt)'!E12 -> -30 | I20: =SUM(F20:H20) -> -30
B21: ='CF (Equity, Debt)'!C13 -> Beyond Limits | C21: =VLOOKUP(B21,'S | 02'!$C$6:$J$37,2,0) -> Direct Investment | D21: =VLOOKUP(B21,'S | 02'!$C$6:$J$37,5,0) -> Mozn | E21: ='CF (Equity, Debt)'!D13 -> 43989 | F21: ='CF (Equity, Debt)'!E13 -> -30 | I21: =SUM(F21:H21) -> -30
B22: ='CF (Equity, Debt)'!C14 -> Beyond Limits | C22: =VLOOKUP(B22,'S | 02'!$C$6:$J$37,2,0) -> Direct Investment | D22: =VLOOKUP(B22,'S | 02'!$C$6:$J$37,5,0) -> Mozn | E22: ='CF (Equity, Debt)'!D14 -> 44103 | F22: ='CF (Equity, Debt)'!E14 -> -10 | I22: =SUM(F22:H22) -> -10
B23: ='CF (Equity, Debt)'!C15 -> ONT plc | C23: =VLOOKUP(B23,'S | 02'!$C$6:$J$37,2,0) -> Direct Investment | D23: =VLOOKUP(B23,'S | 02'!$C$6:$J$37,5,0) -> Mozn | E23: ='CF (Equity, Debt)'!D15 -> 43968 | F23: ='CF (Equity, Debt)'!E15 -> -50 | I23: =SUM(F23:H23) -> -50
B24: ='CF (Equity, Debt)'!C16 -> ONT plc | C24: =VLOOKUP(B24,'S | 02'!$C$6:$J$37,2,0) -> Direct Investment | D24: =VLOOKUP(B24,'S | 02'!$C$6:$J$37,5,0) -> Mozn | E24: ='CF (Equity, Debt)'!D16 -> 44006 | F24: ='CF (Equity, Debt)'!E16 -> -27.268351 | I24: =SUM(F24:H24) -> -27.268351
B25: ='CF (Equity, Debt)'!C17 -> ONT plc | C25: =VLOOKUP(B25,'S | 02'!$C$6:$J$37,2,0) -> Direct Investment | D25: =VLOOKUP(B25,'S | 02'!$C$6:$J$37,5,0) -> Mozn | E25: ='CF (Equity, Debt)'!D17 -> 43837 | F25: ='CF (Equity, Debt)'!E17 -> -18.109441 | I25: =SUM(F25:H25) -> -18.109441
B26: ='CF (Equity, Debt)'!C18 -> ONT plc | C26: =VLOOKUP(B26,'S | 02'!$C$6:$J$37,2,0) -> Direct Investment | D26: =VLOOKUP(B26,'S | 02'!$C$6:$J$37,5,0) -> Mozn | E26: ='CF (Equity, Debt)'!D18 -> 43990 | F26: ='CF (Equity, Debt)'!E18 -> -34.851687 | I26: =SUM(F26:H26) -> -34.851687
B27: ='CF (Equity, Debt)'!C19 -> ONT plc | C27: =VLOOKUP(B27,'S | 02'!$C$6:$J$37,2,0) -> Direct Investment | D27: =VLOOKUP(B27,'S | 02'!$C$6:$J$37,5,0) -> Mozn | E27: ='CF (Equity, Debt)'!D19 -> 44315 | F27: ='CF (Equity, Debt)'!E19 -> -11.24078 | I27: =SUM(F27:H27) -> -11.24078
B28: ='CF (Equity, Debt)'!C20 -> Heygears | C28: =VLOOKUP(B28,'S | 02'!$C$6:$J$37,2,0) -> Direct Investment | D28: =VLOOKUP(B28,'S | 02'!$C$6:$J$37,5,0) -> Mozn | E28: ='CF (Equity, Debt)'!D20 -> 44166 | F28: ='CF (Equity, Debt)'!E20 -> -60 | I28: =SUM(F28:H28) -> -60
... B33: ='CF (Equity, Debt)'!C25 -> X-fusion | C33: =VLOOKUP(B33,'S | 02'!$C$6:$J$37,2,0) -> Direct Investment | D33: =VLOOKUP(B33,'S | 02'!$C$6:$J$37,5,0) -> Mozn 2 | E33: ='CF (Equity, Debt)'!D25 -> 44574 | F33: ='CF (Equity, Debt)'!E25 -> -493.50096 | I33: =SUM(F33:H33) -> -493.50096
B34: ='CF (Equity, Debt)'!C28 -> Esyasoft Holding | C34: =VLOOKUP(B34,'S | 02'!$C$6:$J$37,2,0) -> Direct Investment | D34: =VLOOKUP(B34,'S | 02'!$C$6:$J$37,5,0) -> Mozn | E34: ='CF (Equity, Debt)'!D28 -> 44691 | F34: ='CF (Equity, Debt)'!E28 -> 0 | G34: 5 | I34: =SUM(F34:H34) -> 5
B35: ='CF (Equity, Debt)'!C32 -> Applied AI Corporation Limited | C35: =VLOOKUP(B35,'S | 02'!$C$6:$J$37,2,0) -> Direct Investment | D35: =VLOOKUP(B35,'S | 02'!$C$6:$J$37,5,0) -> Mozn | E35: ='CF (Equity, Debt)'!D32 -> 44861 | F35: ='CF (Equity, Debt)'!E32 -> -4.75 | I35: =SUM(F35:H35) -> -4.75
B36: ='CF (Equity, Debt)'!C33 -> eSpace | C36: =VLOOKUP(B36,'S | 02'!$C$6:$J$37,2,0) -> Direct Investment | D36: =VLOOKUP(B36,'S | 02'!$C$6:$J$37,5,0) -> Mozn 4 | E36: ='CF (Equity, Debt)'!D33 -> 44892 | F36: ='CF (Equity, Debt)'!E33 -> -15 | I36: =SUM(F36:H36) -> -15
B37: ='CF (Equity, Debt)'!C37 -> Glass Earth Holdings LLC | C37: =VLOOKUP(B37,'S | 02'!$C$6:$J$37,2,0) -> Debt Investment | D37: =VLOOKUP(B37,'S | 02'!$C$6:$J$37,5,0) -> Mozn | E37: ='CF (Equity, Debt)'!D37 -> 43635 | F37: ='CF (Equity, Debt)'!E37 -> -8 | I37: =SUM(F37:H37) -> -8
B38: ='CF (Equity, Debt)'!C38 -> Mena Mobile Inc (Debt) | C38: =VLOOKUP(B38,'S | 02'!$C$6:$J$37,2,0) -> Debt Investment | D38: =VLOOKUP(B38,'S | 02'!$C$6:$J$37,5,0) -> Mozn | E38: ='CF (Equity, Debt)'!D38 -> 44293 | F38: ='CF (Equity, Debt)'!E38 -> -2.353982 | I38: =SUM(F38:H38) -> -2.353982
B39: ='CF (Equity, Debt)'!C39 -> Esyasoft Holding (Debt) | C39: =VLOOKUP(B39,'S | 02'!$C$6:$J$37,2,0) -> Debt Investment | D39: =VLOOKUP(B39,'S | 02'!$C$6:$J$37,5,0) -> Mozn | E39: ='CF (Equity, Debt)'!D39 -> 44384 | F39: ='CF (Equity, Debt)'!E39 -> -0.411765 | I39: =SUM(F39:H39) -> -0.411765
B40: ='CF (Equity, Debt)'!C40 -> Esyasoft Holding (Debt) | C40: =VLOOKUP(B40,'S | 02'!$C$6:$J$37,2,0) -> Debt Investment | D40: =VLOOKUP(B40,'S | 02'!$C$6:$J$37,5,0) -> Mozn | E40: ='CF (Equity, Debt)'!D40 -> 44902 | F40: ='CF (Equity, Debt)'!E40 -> 0 | G40: ='CF (Equity, Debt)'!F40 -> 0.47078465 | I40: =SUM(F40:H40) -> 0.47078465
B42: Jollychic Holding Limited | C42: =VLOOKUP(B42,'S | 02'!$C$6:$J$37,2,0) -> Direct Investment | D42: =VLOOKUP(B42,'S | 02'!$C$6:$J$37,5,0) -> Mozn | E42: =$E$4 -> 45016 | H42: =VLOOKUP(B42,NAV!$B$9:$E$41,4,0) -> 0 | I42: =SUM(F42:H42) -> 0
B43: Mena Mobile Inc | C43: =VLOOKUP(B43,'S | 02'!$C$6:$J$37,2,0) -> Direct Investment | D43: =VLOOKUP(B43,'S | 02'!$C$6:$J$37,5,0) -> Mozn | E43: =$E$4 -> 45016 | H43: =VLOOKUP(B43,NAV!$B$9:$E$41,4,0) -> 3.1 | I43: =SUM(F43:H43) -> 3.1
B44: Flyr Inc | C44: =VLOOKUP(B44,'S | 02'!$C$6:$J$37,2,0) -> Direct Investment | D44: =VLOOKUP(B44,'S | 02'!$C$6:$J$37,5,0) -> Mozn | E44: =$E$4 -> 45016 | H44: =VLOOKUP(B44,NAV!$B$9:$E$41,4,0) -> 78.08223 | I44: =SUM(F44:H44) -> 78.08223
B45: Esyasoft Holding | C45: =VLOOKUP(B45,'S | 02'!$C$6:$J$37,2,0) -> Direct Investment | D45: =VLOOKUP(B45,'S | 02'!$C$6:$J$37,5,0) -> Mozn | E45: =$E$4 -> 45016 | H45: =VLOOKUP(B45,NAV!$B$9:$E$41,4,0) -> 0 | I45: =SUM(F45:H45) -> 0
B46: Beyond Limits | C46: =VLOOKUP(B46,'S | 02'!$C$6:$J$37,2,0) -> Direct Investment | D46: =VLOOKUP(B46,'S | 02'!$C$6:$J$37,5,0) -> Mozn | E46: =$E$4 -> 45016 | H46: =VLOOKUP(B46,NAV!$B$9:$E$41,4,0) -> 91.00154 | I46: =SUM(F46:H46) -> 91.00154
B47: ONT plc | C47: =VLOOKUP(B47,'S | 02'!$C$6:$J$37,2,0) -> Direct Investment | D47: =VLOOKUP(B47,'S | 02'!$C$6:$J$37,5,0) -> Mozn | E47: =$E$4 -> 45016 | H47: =VLOOKUP(B47,NAV!$B$9:$E$41,4,0) -> 122.38019 | I47: =SUM(F47:H47) -> 122.38019
B48: Heygears | C48: =VLOOKUP(B48,'S | 02'!$C$6:$J$37,2,0) -> Direct Investment | D48: =VLOOKUP(B48,'S | 02'!$C$6:$J$37,5,0) -> Mozn | E48: =$E$4 -> 45016 | H48: =VLOOKUP(B48,NAV!$B$9:$E$41,4,0) -> 119.2498 | I48: =SUM(F48:H48) -> 119.2498
B49: Jysan Technologies | C49: Direct Investment | D49: Mozn 1 | E49: =$E$4 -> 45016 | H49: =VLOOKUP(B49,NAV!$B$9:$E$41,4,0) -> 20 | I49: =SUM(F49:H49) -> 20
B50: Cerebras Systems Inc | C50: =VLOOKUP(B50,'S | 02'!$C$6:$J$37,2,0) -> Direct Investment | D50: =VLOOKUP(B50,'S | 02'!$C$6:$J$37,5,0) -> Mozn | E50: =$E$4 -> 45016 | H50: =VLOOKUP(B50,NAV!$B$9:$E$41,4,0) -> 39.999983 | I50: =SUM(F50:H50) -> 39.999983
B51: Endless Studios LLC | C51: =VLOOKUP(B51,'S | 02'!$C$6:$J$37,2,0) -> Direct Investment | D51: =VLOOKUP(B51,'S | 02'!$C$6:$J$37,5,0) -> Mozn | E51: =$E$4 -> 45016 | H51: =VLOOKUP(B51,NAV!$B$9:$E$41,4,0) -> 3 | I51: =SUM(F51:H51) -> 3
B52: Instadeep Limited | C52: =VLOOKUP(B52,'S | 02'!$C$6:$J$37,2,0) -> Direct Investment | D52: =VLOOKUP(B52,'S | 02'!$C$6:$J$37,5,0) -> Mozn | E52: =$E$4 -> 45016 | H52: =VLOOKUP(B52,NAV!$B$9:$E$41,4,0) -> 5.0237202 | I52: =SUM(F52:H52) -> 5.0237202
B53: X-fusion | C53: =VLOOKUP(B53,'S | 02'!$C$6:$J$37,2,0) -> Direct Investment | D53: =VLOOKUP(B53,'S | 02'!$C$6:$J$37,5,0) -> Mozn 2 | E53: =$E$4 -> 45016 | H53: =VLOOKUP(B53,NAV!$B$9:$E$41,4,0) -> 424.06662 | I53: =SUM(F53:H53) -> 424.06662
B54: Applied AI Corporation Limited | C54: =VLOOKUP(B54,'S | 02'!$C$6:$J$37,2,0) -> Direct Investment | D54: =VLOOKUP(B54,'S | 02'!$C$6:$J$37,5,0) -> Mozn | E54: =$E$4 -> 45016 | H54: =VLOOKUP(B54,NAV!$B$9:$E$41,4,0) -> 4.75 | I54: =SUM(F54:H54) -> 4.75
B55: eSpace | C55: Direct Investment | D55: =VLOOKUP(B55,'S | 02'!$C$6:$J$37,5,0) -> Mozn 4 | E55: =$E$4 -> 45016 | H55: =VLOOKUP(B55,NAV!$B$9:$E$41,4,0) -> 15 | I55: =SUM(F55:H55) -> 15
B56: Glass Earth Holdings LLC | C56: =VLOOKUP(B56,'S | 02'!$C$6:$J$37,2,0) -> Debt Investment | D56: =VLOOKUP(B56,'S | 02'!$C$6:$J$37,5,0) -> Mozn | E56: =$E$4 -> 45016 | H56: =VLOOKUP(B56,NAV!$B$9:$E$41,4,0) -> 0 | I56: =SUM(F56:H56) -> 0
B57: Mena Mobile Inc (Debt) | C57: =VLOOKUP(B57,'S | 02'!$C$6:$J$37,2,0) -> Debt Investment | D57: =VLOOKUP(B57,'S | 02'!$C$6:$J$37,5,0) -> Mozn | E57: =$E$4 -> 45016 | H57: =VLOOKUP(B57,NAV!$B$9:$E$41,4,0) -> 2.353982 | I57: =SUM(F57:H57) -> 2.353982

Sheet 4. G42-IRR
B2: IRR - G42 Investments | H2: =COUNTA(B13:B67) -> 55
B4: Date of NAV | E4: =D!D2 -> 45016
K7: Invested | L7: Remaining Commitment | M7: Distributions | N7: Residual Value | O7: IRR | P7: TVPI | Q7: RPI | R7: DPI
K9: =-SUM(F12:F67) -> 1258.1822 | M9: =SUM(G12:G67) -> 4.4275637 | N9: =SUM(H12:H67) -> 1279.4494 | O9: =XIRR(I13:I67,E13:E67) -> 0.022939894 | P9: =(M9+N9)/K9 -> 1.0204221 | Q9: =N9/K9 -> 1.0169031 | R9: =M9/K9 -> 0.0035190163
B10: (in USD, Mn)
B11: Investment | C11: Type | D11: Entity | E11: Payment date | F11: Contribution | G11: Distributions | H11: Remaining Value | I11: Combined | M11: Checks
K12: Invested | L12: =-SUM(F12:F67) -> 1258.1822 | M12: =K9='S | 02'!L38 -> TRUE
B13: ='CF (Equity, Debt)'!C26 -> DriveNets | C13: =VLOOKUP(B13,'S | 02'!$C$6:$J$37,2,0) -> Direct Investment | D13: =VLOOKUP(B13,'S | 02'!$C$6:$J$37,5,0) -> G42 | E13: ='CF (Equity, Debt)'!D26 -> 44643 | F13: ='CF (Equity, Debt)'!E26 -> -200 | I13: =SUM(F13:H13) -> -200 | K13: NAV | L13: =SUM(H12:H67) -> 1279.4494 | M13: =M9='S | 02'!M38 -> TRUE
B14: ='CF (Equity, Debt)'!C27 -> DriveNets | C14: =VLOOKUP(B14,'S | 02'!$C$6:$J$37,2,0) -> Direct Investment | D14: =VLOOKUP(B14,'S | 02'!$C$6:$J$37,5,0) -> G42 | E14: ='CF (Equity, Debt)'!D27 -> 44680 | F14: ='CF (Equity, Debt)'!E27 -> -100 | I14: =SUM(F14:H14) -> -100 | K14: Distributions | L14: =SUM(G12:G67) -> 4.4275637 | M14: =ROUND(N9,3)=ROUND('S | 02'!N38,3) -> TRUE
B15: ='CF (Equity, Debt)'!C29 -> vTv Therapeutics Inc. | C15: =VLOOKUP(B15,'S | 02'!$C$6:$J$37,2,0) -> Direct Investment | D15: =VLOOKUP(B15,'S | 02'!$C$6:$J$37,5,0) -> G42 | E15: ='CF (Equity, Debt)'!D29 -> 44712 | F15: ='CF (Equity, Debt)'!E29 -> -12.5 | I15: =SUM(F15:H15) -> -12.5 | K15: Total Gain | L15: =L14+L13-L12 -> 25.694726
B16: ='CF (Equity, Debt)'!C34 -> vTv Therapeutics Inc. | C16: =VLOOKUP(B16,'S | 02'!$C$6:$J$37,2,0) -> Direct Investment | D16: =VLOOKUP(B16,'S | 02'!$C$6:$J$37,5,0) -> G42 | E16: ='CF (Equity, Debt)'!D34 -> 44985 | F16: ='CF (Equity, Debt)'!E34 -> -12.03125 | I16: =SUM(F16:H16) -> -12.03125 | K16: IRR | L16: =O9 -> 0.022939894
B17: ='CF (Equity, Debt)'!C30 -> Honor Device Co Ltd | C17: =VLOOKUP(B17,'S | 02'!$C$6:$J$37,2,0) -> Direct Investment | D17: =VLOOKUP(B17,'S | 02'!$C$6:$J$37,5,0) -> G42 3 | E17: ='CF (Equity, Debt)'!D30 -> 44769 | F17: ='CF (Equity, Debt)'!E30 -> -600 | I17: =SUM(F17:H17) -> -600
B18: ='CF (Equity, Debt)'!C31 -> Honor Device Co Ltd | C18: =VLOOKUP(B18,'S | 02'!$C$6:$J$37,2,0) -> Direct Investment | D18: =VLOOKUP(B18,'S | 02'!$C$6:$J$37,5,0) -> G42 3 | E18: ='CF (Equity, Debt)'!D31 -> 44849 | F18: ='CF (Equity, Debt)'!E31 -> -200 | I18: =SUM(F18:H18) -> -200
B19: ='CF (Funds)'!B3 -> Sinovation Disrupt Fund, L.P. | C19: =VLOOKUP(B19,'S | 02'!$C$6:$J$37,2,0) -> Fund Investment | D19: =VLOOKUP(B19,'S | 02'!$C$6:$J$37,5,0) -> G42 | E19: ='CF (Funds)'!C3 -> 44153 | F19: ='CF (Funds)'!D3 -> -10.5 | G19: ='CF (Funds)'!E3 -> 0 | I19: =SUM(F19:H19) -> -10.5 | L19: =L15/L12 -> 0.020422102
B20: ='CF (Funds)'!B4 -> Sinovation Disrupt Fund, L.P. | C20: =VLOOKUP(B20,'S | 02'!$C$6:$J$37,2,0) -> Fund Investment | D20: =VLOOKUP(B20,'S | 02'!$C$6:$J$37,5,0) -> G42 | E20: ='CF (Funds)'!C4 -> 44238 | F20: ='CF (Funds)'!D4 -> 4.214027 | G20: ='CF (Funds)'!E4 -> 0 | I20: =SUM(F20:H20) -> 4.214027
B21: ='CF (Funds)'!B5 -> Sinovation Disrupt Fund, L.P. | C21: =VLOOKUP(B21,'S | 02'!$C$6:$J$37,2,0) -> Fund Investment | D21: =VLOOKUP(B21,'S | 02'!$C$6:$J$37,5,0) -> G42 | E21: ='CF (Funds)'!C5 -> 44238 | F21: ='CF (Funds)'!D5 -> 0 | G21: ='CF (Funds)'!E5 -> 0.05044835 | I21: =SUM(F21:H21) -> 0.05044835
B22: ='CF (Funds)'!B6 -> Sinovation Disrupt Fund, L.P. | C22: =VLOOKUP(B22,'S | 02'!$C$6:$J$37,2,0) -> Fund Investment | D22: =VLOOKUP(B22,'S | 02'!$C$6:$J$37,5,0) -> G42 | E22: ='CF (Funds)'!C6 -> 44285 | F22: ='CF (Funds)'!D6 -> -6.433746 | G22: ='CF (Funds)'!E6 -> 0 | I22: =SUM(F22:H22) -> -6.433746
B23: ='CF (Funds)'!B7 -> Sinovation Disrupt Fund, L.P. | C23: =VLOOKUP(B23,'S | 02'!$C$6:$J$37,2,0) -> Fund Investment | D23: =VLOOKUP(B23,'S | 02'!$C$6:$J$37,5,0) -> G42 | E23: ='CF (Funds)'!C7 -> 44269 | F23: ='CF (Funds)'!D7 -> 1.1352074 | G23: ='CF (Funds)'!E7 -> 0 | I23: =SUM(F23:H23) -> 1.1352074
B24: ='CF (Funds)'!B8 -> Sinovation Disrupt Fund, L.P. | C24: =VLOOKUP(B24,'S | 02'!$C$6:$J$37,2,0) -> Fund Investment | D24: =VLOOKUP(B24,'S | 02'!$C$6:$J$37,5,0) -> G42 | E24: ='CF (Funds)'!C8 -> 44269 | F24: ='CF (Funds)'!D8 -> 0 | G24: ='CF (Funds)'!E8 -> 0.0259 | I24: =SUM(F24:H24) -> 0.0259
B25: ='CF (Funds)'!B9 -> Sinovation Disrupt Fund, L.P. | C25: =VLOOKUP(B25,'S | 02'!$C$6:$J$37,2,0) -> Fund Investment | D25: =VLOOKUP(B25,'S | 02'!$C$6:$J$37,5,0) -> G42 | E25: ='CF (Funds)'!C9 -> 44483 | F25: ='CF (Funds)'!D9 -> -7.567138 | G25: ='CF (Funds)'!E9 -> 0 | I25: =SUM(F25:H25) -> -7.567138
B26: ='CF (Funds)'!B10 -> Sinovation Disrupt Fund, L.P. | C26: =VLOOKUP(B26,'S | 02'!$C$6:$J$37,2,0) -> Fund Investment | D26: =VLOOKUP(B26,'S | 02'!$C$6:$J$37,5,0) -> G42 | E26: ='CF (Funds)'!C10 -> 44554 | F26: ='CF (Funds)'!D10 -> -7.385016 | G26: ='CF (Funds)'!E10 -> 0 | I26: =SUM(F26:H26) -> -7.385016
B27: ='CF (Funds)'!B11 -> Sinovation Disrupt Fund, L.P. | C27: =VLOOKUP(B27,'S | 02'!$C$6:$J$37,2,0) -> Fund Investment | D27: =VLOOKUP(B27,'S | 02'!$C$6:$J$37,5,0) -> G42 | E27: ='CF (Funds)'!C11 -> 44554 | F27: ='CF (Funds)'!D11 -> 4.0733456 | G27: ='CF (Funds)'!E11 -> 0 | I27: =SUM(F27:H27) -> 4.0733456
B28: ='CF (Funds)'!B12 -> Sinovation Disrupt Fund, L.P. | C28: =VLOOKUP(B28,'S | 02'!$C$6:$J$37,2,0) -> Fund Investment | D28: =VLOOKUP(B28,'S | 02'!$C$6:$J$37,5,0) -> G42 | E28: ='CF (Funds)'!C12 -> 44554 | F28: ='CF (Funds)'!D12 -> 0 | G28: ='CF (Funds)'!E12 -> 0.139694 | I28: =SUM(F28:H28) -> 0.139694
B29: ='CF (Funds)'!B13 -> Sinovation Disrupt Fund, L.P. | C29: =VLOOKUP(B29,'S | 02'!$C$6:$J$37,2,0) -> Fund Investment | D29: =VLOOKUP(B29,'S | 02'!$C$6:$J$37,5,0) -> G42 | E29: ='CF (Funds)'!C13 -> 44703 | F29: ='CF (Funds)'!D13 -> 5.673074 | G29: ='CF (Funds)'!E13 -> 0 | I29: =SUM(F29:H29) -> 5.673074
B30: ='CF (Funds)'!B14 -> Sinovation Disrupt Fund, L.P. | C30: =VLOOKUP(B30,'S | 02'!$C$6:$J$37,2,0) -> Fund Investment | D30: =VLOOKUP(B30,'S | 02'!$C$6:$J$37,5,0) -> G42 | E30: ='CF (Funds)'!C14 -> 44703 | F30: ='CF (Funds)'!D14 -> 0 | G30: ='CF (Funds)'!E14 -> 0.227786 | I30: =SUM(F30:H30) -> 0.227786
B31: ='CF (Funds)'!B15 -> Sinovation Disrupt Fund, L.P. | C31: =VLOOKUP(B31,'S | 02'!$C$6:$J$37,2,0) -> Fund Investment | D31: =VLOOKUP(B31,'S | 02'!$C$6:$J$37,5,0) -> G42 | E31: ='CF (Funds)'!C15 -> 44776 | F31: ='CF (Funds)'!D15 -> -3.235493 | G31: ='CF (Funds)'!E15 -> 0 | I31: =SUM(F31:H31) -> -3.235493
... B59: ='CF (Funds)'!B43 -> Acies Investments Fund I, L.P. | C59: =VLOOKUP(B59,'S | 02'!$C$6:$J$37,2,0) -> Fund Investment | D59: =VLOOKUP(B59,'S | 02'!$C$6:$J$37,5,0) -> G42 | E59: ='CF (Funds)'!C43 -> 44875 | F59: ='CF (Funds)'!D43 -> -3.388275 | G59: ='CF (Funds)'!E43 -> 0 | I59: =SUM(F59:H59) -> -3.388275
B60: DriveNets | C60: =VLOOKUP(B60,'S | 02'!$C$6:$J$37,2,0) -> Direct Investment | D60: =VLOOKUP(B60,'S | 02'!$C$6:$J$37,5,0) -> G42 | E60: =$E$4 -> 45016 | H60: =VLOOKUP(B60,NAV!$B$9:$E$41,4,0) -> 300 | I60: =SUM(F60:H60) -> 300
B61: vTv Therapeutics Inc. | C61: =VLOOKUP(B61,'S | 02'!$C$6:$J$37,2,0) -> Direct Investment | D61: =VLOOKUP(B61,'S | 02'!$C$6:$J$37,5,0) -> G42 | E61: =$E$4 -> 45016 | H61: =VLOOKUP(B61,NAV!$B$9:$E$41,4,0) -> 8.3900321 | I61: =SUM(F61:H61) -> 8.3900321
B62: Honor Device Co Ltd | C62: =VLOOKUP(B62,'S | 02'!$C$6:$J$37,2,0) -> Direct Investment | D62: =VLOOKUP(B62,'S | 02'!$C$6:$J$37,5,0) -> G42 3 | E62: =$E$4 -> 45016 | H62: =VLOOKUP(B62,NAV!$B$9:$E$41,4,0) -> 848.76999 | I62: =SUM(F62:H62) -> 848.76999
B63: New Space Capital Fund I | C63: =VLOOKUP(B63,'S | 02'!$C$6:$J$37,2,0) -> Fund Investment | D63: =VLOOKUP(B63,'S | 02'!$C$6:$J$37,5,0) -> G42 | E63: =$E$4 -> 45016 | H63: =VLOOKUP(B63,NAV!$B$9:$E$41,4,0) -> 14.294891 | I63: =SUM(F63:H63) -> 14.294891
B64: New Space Capital SCSp | C64: =VLOOKUP(B64,'S | 02'!$C$6:$J$37,2,0) -> Fund Investment | D64: =VLOOKUP(B64,'S | 02'!$C$6:$J$37,5,0) -> G42 | E64: =$E$4 -> 45016 | H64: =VLOOKUP(B64,NAV!$B$9:$E$41,4,0) -> 2.7058824 | I64: =SUM(F64:H64) -> 2.7058824
B65: North Summit Capital Fund | C65: =VLOOKUP(B65,'S | 02'!$C$6:$J$37,2,0) -> Fund Investment | D65: =VLOOKUP(B65,'S | 02'!$C$6:$J$37,5,0) -> G42 | E65: =$E$4 -> 45016 | H65: =VLOOKUP(B65,NAV!$B$9:$E$41,4,0) -> 70.03 | I65: =SUM(F65:H65) -> 70.03
B66: Sinovation Disrupt Fund, L.P. | C66: =VLOOKUP(B66,'S | 02'!$C$6:$J$37,2,0) -> Fund Investment | D66: =VLOOKUP(B66,'S | 02'!$C$6:$J$37,5,0) -> G42 | E66: =$E$4 -> 45016 | H66: =VLOOKUP(B66,NAV!$B$9:$E$41,4,0) -> 21.51575 | I66: =SUM(F66:H66) -> 21.51575
B67: Acies Investments Fund I, L.P. | C67: =VLOOKUP(B67,'S | 02'!$C$6:$J$37,2,0) -> Fund Investment | D67: =VLOOKUP(B67,'S | 02'!$C$6:$J$37,5,0) -> G42 | E67: =$E$4 -> 45016 | H67: =VLOOKUP(B67,NAV!$B$9:$E$41,4,0) -> 13.742841 | I67: =SUM(F67:H67) -> 13.742841

Sheet 5. CF Profile
C2: CASH DEPLOYED OVER TIME…
C5: Investment | D5: Type | E5: Payment date | F5: Period | G5: Contribution | H5: Distribution | J5: Contribution | K5: Equity | L5: Debt | M5: Fund | N5: Total | P5: Distribution | Q5: Equity | R5: Debt | S5: Fund | T5: Total
B6: Equity | C6: ='CF (Equity, Debt)'!C4 -> Jollychic Holding Limited | D6: Equity | E6: ='CF (Equity, Debt)'!D4 -> 43470 | F6: ="Q"&ROUNDUP(MONTH(E6)/3,0)&" "&YEAR(E6) -> Q1 2019 | G6: ='CF (Equity, Debt)'!E4 -> -30 | H6: ='CF (Equity, Debt)'!F4 -> 0
C7: ='CF (Equity, Debt)'!C5 -> Jollychic Holding Limited | D7: Equity | E7: ='CF (Equity, Debt)'!D5 -> 43724 | F7: ="Q"&ROUNDUP(MONTH(E7)/3,0)&" "&YEAR(E7) -> Q3 2019 | G7: ='CF (Equity, Debt)'!E5 -> -20 | H7: ='CF (Equity, Debt)'!F5 -> 0 | J7: Q1 2019 | K7: =-SUMIFS($G$5:$G$111,$D$5:$D$111,$K$5,$F$5:$F$111,J7) -> 30 | L7: =-SUMIFS($G$5:$G$111,$D$5:$D$111,$L$5,$F$5:$F$111,J7) -> 0 | M7: =-SUMIFS($G$5:$G$111,$D$5:$D$111,"Fund",$F$5:$F$111,J7) -> 0 | N7: =-SUMIF($F$5:$H$111,$J7,$G$5:$G$111) -> 30 | P7: Q1 2019 | Q7: =SUMIFS($H$5:$H$111,$D$5:$D$111,$Q$5,$F$5:$F$111,J7) -> 0 | R7: =SUMIFS($H$5:$H$111,$D$5:$D$111,$R$5,$F$5:$F$111,J7) -> 0 | S7: =SUMIFS($H$5:$H$111,$D$5:$D$111,$S$5,$F$5:$F$111,J7) -> 0 | T7: =SUMIF($F$5:$H$111,$J7,$H$5:$H$111) -> 0
C8: ='CF (Equity, Debt)'!C6 -> Jollychic Holding Limited | D8: Equity | E8: ='CF (Equity, Debt)'!D6 -> 43724 | F8: ="Q"&ROUNDUP(MONTH(E8)/3,0)&" "&YEAR(E8) -> Q3 2019 | G8: ='CF (Equity, Debt)'!E6 -> -15 | H8: ='CF (Equity, Debt)'!F6 -> 0 | J8: Q2 2019 | K8: =-SUMIFS($G$5:$G$111,$D$5:$D$111,$K$5,$F$5:$F$111,J8) -> 12.999998 | L8: =-SUMIFS($G$5:$G$111,$D$5:$D$111,$L$5,$F$5:$F$111,J8) -> 8 | M8: =-SUMIFS($G$5:$G$111,$D$5:$D$111,"Fund",$F$5:$F$111,J8) -> 0 | N8: =-SUMIF($F$5:$H$111,$J8,$G$5:$G$111) -> 20.999998 | P8: Q2 2019 | Q8: =SUMIFS($H$5:$H$111,$D$5:$D$111,$Q$5,$F$5:$F$111,J8) -> 0 | R8: =SUMIFS($H$5:$H$111,$D$5:$D$111,$R$5,$F$5:$F$111,J8) -> 0 | S8: =SUMIFS($H$5:$H$111,$D$5:$D$111,$S$5,$F$5:$F$111,J8) -> 0 | T8: =SUMIF($F$5:$H$111,$J8,$H$5:$H$111) -> 0
C9: ='CF (Equity, Debt)'!C7 -> Mena Mobile Inc | D9: Equity | E9: ='CF (Equity, Debt)'!D7 -> 43563 | F9: ="Q"&ROUNDUP(MONTH(E9)/3,0)&" "&YEAR(E9) -> Q2 2019 | G9: ='CF (Equity, Debt)'!E7 -> -8 | H9: ='CF (Equity, Debt)'!F7 -> 0 | J9: Q3 2019 | K9: =-SUMIFS($G$5:$G$111,$D$5:$D$111,$K$5,$F$5:$F$111,J9) -> 35 | L9: =-SUMIFS($G$5:$G$111,$D$5:$D$111,$L$5,$F$5:$F$111,J9) -> 0 | M9: =-SUMIFS($G$5:$G$111,$D$5:$D$111,"Fund",$F$5:$F$111,J9) -> 3 | N9: =-SUMIF($F$5:$H$111,$J9,$G$5:$G$111) -> 38 | P9: Q3 2019 | Q9: =SUMIFS($H$5:$H$111,$D$5:$D$111,$Q$5,$F$5:$F$111,J9) -> 0 | R9: =SUMIFS($H$5:$H$111,$D$5:$D$111,$R$5,$F$5:$F$111,J9) -> 0 | S9: =SUMIFS($H$5:$H$111,$D$5:$D$111,$S$5,$F$5:$F$111,J9) -> 0 | T9: =SUMIF($F$5:$H$111,$J9,$H$5:$H$111) -> 0
C10: ='CF (Equity, Debt)'!C8 -> Flyr Inc | D10: Equity | E10: ='CF (Equity, Debt)'!D8 -> 43570 | F10: ="Q"&ROUNDUP(MONTH(E10)/3,0)&" "&YEAR(E10) -> Q2 2019 | G10: ='CF (Equity, Debt)'!E8 -> -4.9999981 | H10: ='CF (Equity, Debt)'!F8 -> 0 | J10: Q4 2019 | K10: =-SUMIFS($G$5:$G$111,$D$5:$D$111,$K$5,$F$5:$F$111,J10) -> 0 | L10: =-SUMIFS($G$5:$G$111,$D$5:$D$111,$L$5,$F$5:$F$111,J10) -> 0 | M10: =-SUMIFS($G$5:$G$111,$D$5:$D$111,"Fund",$F$5:$F$111,J10) -> 0 | N10: =-SUMIF($F$5:$H$111,$J10,$G$5:$G$111) -> 0 | P10: Q4 2019 | Q10: =SUMIFS($H$5:$H$111,$D$5:$D$111,$Q$5,$F$5:$F$111,J10) -> 0 | R10: =SUMIFS($H$5:$H$111,$D$5:$D$111,$R$5,$F$5:$F$111,J10) -> 0 | S10: =SUMIFS($H$5:$H$111,$D$5:$D$111,$S$5,$F$5:$F$111,J10) -> 0 | T10: =SUMIF($F$5:$H$111,$J10,$H$5:$H$111) -> 0
C11: ='CF (Equity, Debt)'!C9 -> Flyr Inc | D11: Equity | E11: ='CF (Equity, Debt)'!D9 -> 43915 | F11: ="Q"&ROUNDUP(MONTH(E11)/3,0)&" "&YEAR(E11) -> Q1 2020 | G11: ='CF (Equity, Debt)'!E9 -> -5.0000019 | H11: ='CF (Equity, Debt)'!F9 -> 0 | J11: Q1 2020 | K11: =-SUMIFS($G$5:$G$111,$D$5:$D$111,$K$5,$F$5:$F$111,J11) -> 75.609443 | L11: =-SUMIFS($G$5:$G$111,$D$5:$D$111,$L$5,$F$5:$F$111,J11) -> 0 | M11: =-SUMIFS($G$5:$G$111,$D$5:$D$111,"Fund",$F$5:$F$111,J11) -> 9.50975 | N11: =-SUMIF($F$5:$H$111,$J11,$G$5:$G$111) -> 85.119193 | P11: Q1 2020 | Q11: =SUMIFS($H$5:$H$111,$D$5:$D$111,$Q$5,$F$5:$F$111,J11) -> 0 | R11: =SUMIFS($H$5:$H$111,$D$5:$D$111,$R$5,$F$5:$F$111,J11) -> 0 | S11: =SUMIFS($H$5:$H$111,$D$5:$D$111,$S$5,$F$5:$F$111,J11) -> 0 | T11: =SUMIF($F$5:$H$111,$J11,$H$5:$H$111) -> 0
C12: ='CF (Equity, Debt)'!C10 -> Esyasoft Holding | D12: Equity | E12: ='CF (Equity, Debt)'!D10 -> 43870 | F12: ="Q"&ROUNDUP(MONTH(E12)/3,0)&" "&YEAR(E12) -> Q1 2020 | G12: ='CF (Equity, Debt)'!E10 -> -2.5 | H12: ='CF (Equity, Debt)'!F10 -> 0 | J12: Q2 2020 | K12: =-SUMIFS($G$5:$G$111,$D$5:$D$111,$K$5,$F$5:$F$111,J12) -> 142.12004 | L12: =-SUMIFS($G$5:$G$111,$D$5:$D$111,$L$5,$F$5:$F$111,J12) -> 0 | M12: =-SUMIFS($G$5:$G$111,$D$5:$D$111,"Fund",$F$5:$F$111,J12) -> 45.785 | N12: =-SUMIF($F$5:$H$111,$J12,$G$5:$G$111) -> 187.90504 | P12: Q2 2020 | Q12: =SUMIFS($H$5:$H$111,$D$5:$D$111,$Q$5,$F$5:$F$111,J12) -> 0 | R12: =SUMIFS($H$5:$H$111,$D$5:$D$111,$R$5,$F$5:$F$111,J12) -> 0 | S12: =SUMIFS($H$5:$H$111,$D$5:$D$111,$S$5,$F$5:$F$111,J12) -> 0 | T12: =SUMIF($F$5:$H$111,$J12,$H$5:$H$111) -> 0
C13: ='CF (Equity, Debt)'!C11 -> Beyond Limits | D13: Equity | E13: ='CF (Equity, Debt)'!D11 -> 43879 | F13: ="Q"&ROUNDUP(MONTH(E13)/3,0)&" "&YEAR(E13) -> Q1 2020 | G13: ='CF (Equity, Debt)'!E11 -> -20 | H13: ='CF (Equity, Debt)'!F11 -> 0 | J13: Q3 2020 | K13: =-SUMIFS($G$5:$G$111,$D$5:$D$111,$K$5,$F$5:$F$111,J13) -> 10 | L13: =-SUMIFS($G$5:$G$111,$D$5:$D$111,$L$5,$F$5:$F$111,J13) -> 0 | M13: =-SUMIFS($G$5:$G$111,$D$5:$D$111,"Fund",$F$5:$F$111,J13) -> 23.623435 | N13: =-SUMIF($F$5:$H$111,$J13,$G$5:$G$111) -> 33.623435 | P13: Q3 2020 | Q13: =SUMIFS($H$5:$H$111,$D$5:$D$111,$Q$5,$F$5:$F$111,J13) -> 0 | R13: =SUMIFS($H$5:$H$111,$D$5:$D$111,$R$5,$F$5:$F$111,J13) -> 0 | S13: =SUMIFS($H$5:$H$111,$D$5:$D$111,$S$5,$F$5:$F$111,J13) -> 0 | T13: =SUMIF($F$5:$H$111,$J13,$H$5:$H$111) -> 0
C14: ='CF (Equity, Debt)'!C12 -> Beyond Limits | D14: Equity | E14: ='CF (Equity, Debt)'!D12 -> 43921 | F14: ="Q"&ROUNDUP(MONTH(E14)/3,0)&" "&YEAR(E14) -> Q1 2020 | G14: ='CF (Equity, Debt)'!E12 -> -30 | H14: ='CF (Equity, Debt)'!F12 -> 0 | J14: Q4 2020 | K14: =-SUMIFS($G$5:$G$111,$D$5:$D$111,$K$5,$F$5:$F$111,J14) -> 60 | L14: =-SUMIFS($G$5:$G$111,$D$5:$D$111,$L$5,$F$5:$F$111,J14) -> 0 | M14: =-SUMIFS($G$5:$G$111,$D$5:$D$111,"Fund",$F$5:$F$111,J14) -> 9.482293 | N14: =-SUMIF($F$5:$H$111,$J14,$G$5:$G$111) -> 69.482293 | P14: Q4 2020 | Q14: =SUMIFS($H$5:$H$111,$D$5:$D$111,$Q$5,$F$5:$F$111,J14) -> 0 | R14: =SUMIFS($H$5:$H$111,$D$5:$D$111,$R$5,$F$5:$F$111,J14) -> 0 | S14: =SUMIFS($H$5:$H$111,$D$5:$D$111,$S$5,$F$5:$F$111,J14) -> 0.582902 | T14: =SUMIF($F$5:$H$111,$J14,$H$5:$H$111) -> 0.582902
C15: ='CF (Equity, Debt)'!C13 -> Beyond Limits | D15: Equity | E15: ='CF (Equity, Debt)'!D13 -> 43989 | F15: ="Q"&ROUNDUP(MONTH(E15)/3,0)&" "&YEAR(E15) -> Q2 2020 | G15: ='CF (Equity, Debt)'!E13 -> -30 | H15: ='CF (Equity, Debt)'!F13 -> 0 | J15: Q1 2021 | K15: =-SUMIFS($G$5:$G$111,$D$5:$D$111,$K$5,$F$5:$F$111,J15) -> 0 | L15: =-SUMIFS($G$5:$G$111,$D$5:$D$111,$L$5,$F$5:$F$111,J15) -> 0 | M15: =-SUMIFS($G$5:$G$111,$D$5:$D$111,"Fund",$F$5:$F$111,J15) -> 1.0845116 | N15: =-SUMIF($F$5:$H$111,$J15,$G$5:$G$111) -> 1.0845116 | P15: Q1 2021 | Q15: =SUMIFS($H$5:$H$111,$D$5:$D$111,$Q$5,$F$5:$F$111,J15) -> 0 | R15: =SUMIFS($H$5:$H$111,$D$5:$D$111,$R$5,$F$5:$F$111,J15) -> 0 | S15: =SUMIFS($H$5:$H$111,$D$5:$D$111,$S$5,$F$5:$F$111,J15) -> 0.07634835 | T15: =SUMIF($F$5:$H$111,$J15,$H$5:$H$111) -> 0.07634835
C16: ='CF (Equity, Debt)'!C14 -> Beyond Limits | D16: Equity | E16: ='CF (Equity, Debt)'!D14 -> 44103 | F16: ="Q"&ROUNDUP(MONTH(E16)/3,0)&" "&YEAR(E16) -> Q3 2020 | G16: ='CF (Equity, Debt)'!E14 -> -10 | H16: ='CF (Equity, Debt)'!F14 -> 0 | J16: Q2 2021 | K16: =-SUMIFS($G$5:$G$111,$D$5:$D$111,$K$5,$F$5:$F$111,J16) -> 31.24078 | L16: =-SUMIFS($G$5:$G$111,$D$5:$D$111,$L$5,$F$5:$F$111,J16) -> 2.353982 | M16: =-SUMIFS($G$5:$G$111,$D$5:$D$111,"Fund",$F$5:$F$111,J16) -> 6.1810318 | N16: =-SUMIF($F$5:$H$111,$J16,$G$5:$G$111) -> 39.775794 | P16: Q2 2021 | Q16: =SUMIFS($H$5:$H$111,$D$5:$D$111,$Q$5,$F$5:$F$111,J16) -> 0 | R16: =SUMIFS($H$5:$H$111,$D$5:$D$111,$R$5,$F$5:$F$111,J16) -> 0 | S16: =SUMIFS($H$5:$H$111,$D$5:$D$111,$S$5,$F$5:$F$111,J16) -> 0 | T16: =SUMIF($F$5:$H$111,$J16,$H$5:$H$111) -> 0
C17: ='CF (Equity, Debt)'!C15 -> ONT plc | D17: Equity | E17: ='CF (Equity, Debt)'!D15 -> 43968 | F17: ="Q"&ROUNDUP(MONTH(E17)/3,0)&" "&YEAR(E17) -> Q2 2020 | G17: ='CF (Equity, Debt)'!E15 -> -50 | H17: ='CF (Equity, Debt)'!F15 -> 0 | J17: Q3 2021 | K17: =-SUMIFS($G$5:$G$111,$D$5:$D$111,$K$5,$F$5:$F$111,J17) -> 0 | L17: =-SUMIFS($G$5:$G$111,$D$5:$D$111,$L$5,$F$5:$F$111,J17) -> 0.411765 | M17: =-SUMIFS($G$5:$G$111,$D$5:$D$111,"Fund",$F$5:$F$111,J17) -> 0.98965473 | N17: =-SUMIF($F$5:$H$111,$J17,$G$5:$G$111) -> 1.4014197 | P17: Q3 2021 | Q17: =SUMIFS($H$5:$H$111,$D$5:$D$111,$Q$5,$F$5:$F$111,J17) -> 0 | R17: =SUMIFS($H$5:$H$111,$D$5:$D$111,$R$5,$F$5:$F$111,J17) -> 0 | S17: =SUMIFS($H$5:$H$111,$D$5:$D$111,$S$5,$F$5:$F$111,J17) -> 0.445059 | T17: =SUMIF($F$5:$H$111,$J17,$H$5:$H$111) -> 0.445059
C18: ='CF (Equity, Debt)'!C16 -> ONT plc | D18: Equity | E18: ='CF (Equity, Debt)'!D16 -> 44006 | F18: ="Q"&ROUNDUP(MONTH(E18)/3,0)&" "&YEAR(E18) -> Q2 2020 | G18: ='CF (Equity, Debt)'!E16 -> -27.268351 | H18: ='CF (Equity, Debt)'!F16 -> 0 | J18: Q4 2021 | K18: =-SUMIFS($G$5:$G$111,$D$5:$D$111,$K$5,$F$5:$F$111,J18) -> 48.023704 | L18: =-SUMIFS($G$5:$G$111,$D$5:$D$111,$L$5,$F$5:$F$111,J18) -> 0 | M18: =-SUMIFS($G$5:$G$111,$D$5:$D$111,"Fund",$F$5:$F$111,J18) -> 11.901731 | N18: =-SUMIF($F$5:$H$111,$J18,$G$5:$G$111) -> 59.925434 | P18: Q4 2021 | Q18: =SUMIFS($H$5:$H$111,$D$5:$D$111,$Q$5,$F$5:$F$111,J18) -> 0 | R18: =SUMIFS($H$5:$H$111,$D$5:$D$111,$R$5,$F$5:$F$111,J18) -> 0 | S18: =SUMIFS($H$5:$H$111,$D$5:$D$111,$S$5,$F$5:$F$111,J18) -> 0.139694 | T18: =SUMIF($F$5:$H$111,$J18,$H$5:$H$111) -> 0.139694
... C23: ='CF (Equity, Debt)'!C21 -> Jysan Technologies | D23: Equity | E23: ='CF (Equity, Debt)'!D21 -> 44363 | F23: ="Q"&ROUNDUP(MONTH(E23)/3,0)&" "&YEAR(E23) -> Q2 2021 | G23: ='CF (Equity, Debt)'!E21 -> -20 | H23: ='CF (Equity, Debt)'!F21 -> 0 | J23: Q1 2023 | K23: =-SUMIFS($G$5:$G$111,$D$5:$D$111,$K$5,$F$5:$F$111,J23) -> 12.03125 | L23: =-SUMIFS($G$5:$G$111,$D$5:$D$111,$L$5,$F$5:$F$111,J23) -> 0 | M23: =-SUMIFS($G$5:$G$111,$D$5:$D$111,"Fund",$F$5:$F$111,J23) -> 2.631528 | N23: =-SUMIF($F$5:$H$111,$J23,$G$5:$G$111) -> 14.662778 | P23: Q1 2023 | Q23: =SUMIFS($H$5:$H$111,$D$5:$D$111,$Q$5,$F$5:$F$111,J23) -> 0 | R23: =SUMIFS($H$5:$H$111,$D$5:$D$111,$R$5,$F$5:$F$111,J23) -> 0 | S23: =SUMIFS($H$5:$H$111,$D$5:$D$111,$S$5,$F$5:$F$111,J23) -> 2.9557744 | T23: =SUMIF($F$5:$H$111,$J23,$H$5:$H$111) -> 2.9557744
C24: ='CF (Equity, Debt)'!C22 -> Cerebras Systems Inc | D24: Equity | E24: ='CF (Equity, Debt)'!D22 -> 44488 | F24: ="Q"&ROUNDUP(MONTH(E24)/3,0)&" "&YEAR(E24) -> Q4 2021 | G24: ='CF (Equity, Debt)'!E22 -> -39.999983 | H24: ='CF (Equity, Debt)'!F22 -> 0
C25: ='CF (Equity, Debt)'!C23 -> Endless Studios LLC | D25: Equity | E25: ='CF (Equity, Debt)'!D23 -> 44494 | F25: ="Q"&ROUNDUP(MONTH(E25)/3,0)&" "&YEAR(E25) -> Q4 2021 | G25: ='CF (Equity, Debt)'!E23 -> -3 | H25: ='CF (Equity, Debt)'!F23 -> 0
C26: ='CF (Equity, Debt)'!C24 -> Instadeep Limited | D26: Equity | E26: ='CF (Equity, Debt)'!D24 -> 44550 | F26: ="Q"&ROUNDUP(MONTH(E26)/3,0)&" "&YEAR(E26) -> Q4 2021 | G26: ='CF (Equity, Debt)'!E24 -> -5.0237202 | H26: ='CF (Equity, Debt)'!F24 -> 0 | J26: Total | K26: =SUM(K7:K25) -> 2082.7762 | L26: =SUM(L7:L25) -> 10.765747 | M26: =SUM(M7:M25) -> 144.20489 | N26: =SUM(N7:N25) -> 2237.7468 | P26: Total | Q26: =SUM(Q7:Q25) -> 5 | R26: =SUM(R7:R25) -> 0.47078465 | S26: =SUM(S7:S25) -> 4.4275637 | T26: =SUM(T7:T25) -> 9.8983484
C27: ='CF (Equity, Debt)'!C25 -> X-fusion | D27: Equity | E27: ='CF (Equity, Debt)'!D25 -> 44574 | F27: ="Q"&ROUNDUP(MONTH(E27)/3,0)&" "&YEAR(E27) -> Q1 2022 | G27: ='CF (Equity, Debt)'!E25 -> -493.50096 | H27: ='CF (Equity, Debt)'!F25 -> 0
C28: ='CF (Equity, Debt)'!C26 -> DriveNets | D28: Equity | E28: ='CF (Equity, Debt)'!D26 -> 44643 | F28: ="Q"&ROUNDUP(MONTH(E28)/3,0)&" "&YEAR(E28) -> Q1 2022 | G28: ='CF (Equity, Debt)'!E26 -> -200 | H28: ='CF (Equity, Debt)'!F26 -> 0 | Q28: =Q21=0 -> TRUE | R28: =R21=0 -> TRUE | S28: =S21=0 -> TRUE | T28: =T21=0 -> TRUE
C29: ='CF (Equity, Debt)'!C27 -> DriveNets | D29: Equity | E29: ='CF (Equity, Debt)'!D27 -> 44680 | F29: ="Q"&ROUNDUP(MONTH(E29)/3,0)&" "&YEAR(E29) -> Q2 2022 | G29: ='CF (Equity, Debt)'!E27 -> -100 | H29: ='CF (Equity, Debt)'!F27 -> 0
C30: ='CF (Equity, Debt)'!C28 -> Esyasoft Holding | D30: Equity | E30: ='CF (Equity, Debt)'!D28 -> 44691 | F30: ="Q"&ROUNDUP(MONTH(E30)/3,0)&" "&YEAR(E30) -> Q2 2022 | G30: ='CF (Equity, Debt)'!E28 -> 0 | H30: ='CF (Equity, Debt)'!F28 -> 5
C31: ='CF (Equity, Debt)'!C29 -> vTv Therapeutics Inc. | D31: Equity | E31: ='CF (Equity, Debt)'!D29 -> 44712 | F31: ="Q"&ROUNDUP(MONTH(E31)/3,0)&" "&YEAR(E31) -> Q2 2022 | G31: ='CF (Equity, Debt)'!E29 -> -12.5 | H31: ='CF (Equity, Debt)'!F29 -> 0
C32: ='CF (Equity, Debt)'!C30 -> Honor Device Co Ltd | D32: Equity | E32: ='CF (Equity, Debt)'!D30 -> 44769 | F32: ="Q"&ROUNDUP(MONTH(E32)/3,0)&" "&YEAR(E32) -> Q3 2022 | G32: ='CF (Equity, Debt)'!E30 -> -600 | H32: ='CF (Equity, Debt)'!F30 -> 0
C33: ='CF (Equity, Debt)'!C31 -> Honor Device Co Ltd | D33: Equity | E33: ='CF (Equity, Debt)'!D31 -> 44849 | F33: ="Q"&ROUNDUP(MONTH(E33)/3,0)&" "&YEAR(E33) -> Q4 2022 | G33: ='CF (Equity, Debt)'!E31 -> -200 | H33: ='CF (Equity, Debt)'!F31 -> 0
C34: ='CF (Equity, Debt)'!C32 -> Applied AI Corporation Limited | D34: Equity | E34: ='CF (Equity, Debt)'!D32 -> 44861 | F34: ="Q"&ROUNDUP(MONTH(E34)/3,0)&" "&YEAR(E34) -> Q4 2022 | G34: ='CF (Equity, Debt)'!E32 -> -4.75 | H34: ='CF (Equity, Debt)'!F32 -> 0
C35: ='CF (Equity, Debt)'!C33 -> eSpace | D35: Equity | E35: ='CF (Equity, Debt)'!D33 -> 44892 | F35: ="Q"&ROUNDUP(MONTH(E35)/3,0)&" "&YEAR(E35) -> Q4 2022 | G35: ='CF (Equity, Debt)'!E33 -> -15 | H35: ='CF (Equity, Debt)'!F33 -> 0
C36: ='CF (Equity, Debt)'!C34 -> vTv Therapeutics Inc. | D36: Equity | E36: ='CF (Equity, Debt)'!D34 -> 44985 | F36: ="Q"&ROUNDUP(MONTH(E36)/3,0)&" "&YEAR(E36) -> Q1 2023 | G36: ='CF (Equity, Debt)'!E34 -> -12.03125 | H36: ='CF (Equity, Debt)'!F34 -> 0
B38: Debt
C39: ='CF (Equity, Debt)'!C37 -> Glass Earth Holdings LLC | D39: Debt | E39: ='CF (Equity, Debt)'!D37 -> 43635 | F39: ="Q"&ROUNDUP(MONTH(E39)/3,0)&" "&YEAR(E39) -> Q2 2019 | G39: ='CF (Equity, Debt)'!E37 -> -8 | H39: ='CF (Equity, Debt)'!F37 -> 0
C40: ='CF (Equity, Debt)'!C38 -> Mena Mobile Inc (Debt) | D40: Debt | E40: ='CF (Equity, Debt)'!D38 -> 44293 | F40: ="Q"&ROUNDUP(MONTH(E40)/3,0)&" "&YEAR(E40) -> Q2 2021 | G40: ='CF (Equity, Debt)'!E38 -> -2.353982 | H40: ='CF (Equity, Debt)'!F38 -> 0
C41: ='CF (Equity, Debt)'!C39 -> Esyasoft Holding (Debt) | D41: Debt | E41: ='CF (Equity, Debt)'!D39 -> 44384 | F41: ="Q"&ROUNDUP(MONTH(E41)/3,0)&" "&YEAR(E41) -> Q3 2021 | G41: ='CF (Equity, Debt)'!E39 -> -0.411765 | H41: ='CF (Equity, Debt)'!F39 -> 0
C42: ='CF (Equity, Debt)'!C40 -> Esyasoft Holding (Debt) | D42: Debt | E42: ='CF (Equity, Debt)'!D40 -> 44902 | F42: ="Q"&ROUNDUP(MONTH(E42)/3,0)&" "&YEAR(E42) -> Q4 2022 | G42: ='CF (Equity, Debt)'!E40 -> 0 | H42: ='CF (Equity, Debt)'!F40 -> 0.47078465
B43: Funds
C44: ='CF (Funds)'!B3 -> Sinovation Disrupt Fund, L.P. | D44: Fund | E44: ='CF (Funds)'!C3 -> 44153 | F44: ="Q"&ROUNDUP(MONTH(E44)/3,0)&" "&YEAR(E44) -> Q4 2020 | G44: ='CF (Funds)'!D3 -> -10.5 | H44: ='CF (Funds)'!E3 -> 0
C45: ='CF (Funds)'!B4 -> Sinovation Disrupt Fund, L.P. | D45: Fund | E45: ='CF (Funds)'!C4 -> 44238 | F45: ="Q"&ROUNDUP(MONTH(E45)/3,0)&" "&YEAR(E45) -> Q1 2021 | G45: ='CF (Funds)'!D4 -> 4.214027 | H45: ='CF (Funds)'!E4 -> 0
C46: ='CF (Funds)'!B5 -> Sinovation Disrupt Fund, L.P. | D46: Fund | E46: ='CF (Funds)'!C5 -> 44238 | F46: ="Q"&ROUNDUP(MONTH(E46)/3,0)&" "&YEAR(E46) -> Q1 2021 | G46: ='CF (Funds)'!D5 -> 0 | H46: ='CF (Funds)'!E5 -> 0.05044835
C47: ='CF (Funds)'!B6 -> Sinovation Disrupt Fund, L.P. | D47: Fund | E47: ='CF (Funds)'!C6 -> 44285 | F47: ="Q"&ROUNDUP(MONTH(E47)/3,0)&" "&YEAR(E47) -> Q1 2021 | G47: ='CF (Funds)'!D6 -> -6.433746 | H47: ='CF (Funds)'!E6 -> 0
C48: ='CF (Funds)'!B7 -> Sinovation Disrupt Fund, L.P. | D48: Fund | E48: ='CF (Funds)'!C7 -> 44269 | F48: ="Q"&ROUNDUP(MONTH(E48)/3,0)&" "&YEAR(E48) -> Q1 2021 | G48: ='CF (Funds)'!D7 -> 1.1352074 | H48: ='CF (Funds)'!E7 -> 0
C49: ='CF (Funds)'!B8 -> Sinovation Disrupt Fund, L.P. | D49: Fund | E49: ='CF (Funds)'!C8 -> 44269 | F49: ="Q"&ROUNDUP(MONTH(E49)/3,0)&" "&YEAR(E49) -> Q1 2021 | G49: ='CF (Funds)'!D8 -> 0 | H49: ='CF (Funds)'!E8 -> 0.0259
C50: ='CF (Funds)'!B9 -> Sinovation Disrupt Fund, L.P. | D50: Fund | E50: ='CF (Funds)'!C9 -> 44483 | F50: ="Q"&ROUNDUP(MONTH(E50)/3,0)&" "&YEAR(E50) -> Q4 2021 | G50: ='CF (Funds)'!D9 -> -7.567138 | H50: ='CF (Funds)'!E9 -> 0
C51: ='CF (Funds)'!B10 -> Sinovation Disrupt Fund, L.P. | D51: Fund | E51: ='CF (Funds)'!C10 -> 44554 | F51: ="Q"&ROUNDUP(MONTH(E51)/3,0)&" "&YEAR(E51) -> Q4 2021 | G51: ='CF (Funds)'!D10 -> -7.385016 | H51: ='CF (Funds)'!E10 -> 0
C52: ='CF (Funds)'!B11 -> Sinovation Disrupt Fund, L.P. | D52: Fund | E52: ='CF (Funds)'!C11 -> 44554 | F52: ="Q"&ROUNDUP(MONTH(E52)/3,0)&" "&YEAR(E52) -> Q4 2021 | G52: ='CF (Funds)'!D11 -> 4.0733456 | H52: ='CF (Funds)'!E11 -> 0
C53: ='CF (Funds)'!B12 -> Sinovation Disrupt Fund, L.P. | D53: Fund | E53: ='CF (Funds)'!C12 -> 44554 | F53: ="Q"&ROUNDUP(MONTH(E53)/3,0)&" "&YEAR(E53) -> Q4 2021 | G53: ='CF (Funds)'!D12 -> 0 | H53: ='CF (Funds)'!E12 -> 0.139694
C54: ='CF (Funds)'!B13 -> Sinovation Disrupt Fund, L.P. | D54: Fund | E54: ='CF (Funds)'!C13 -> 44703 | F54: ="Q"&ROUNDUP(MONTH(E54)/3,0)&" "&YEAR(E54) -> Q2 2022 | G54: ='CF (Funds)'!D13 -> 5.673074 | H54: ='CF (Funds)'!E13 -> 0
C55: ='CF (Funds)'!B14 -> Sinovation Disrupt Fund, L.P. | D55: Fund | E55: ='CF (Funds)'!C14 -> 44703 | F55: ="Q"&ROUNDUP(MONTH(E55)/3,0)&" "&YEAR(E55) -> Q2 2022 | G55: ='CF (Funds)'!D14 -> 0 | H55: ='CF (Funds)'!E14 -> 0.227786
... C76: ='CF (Funds)'!B35 -> New Space Capital Fund I | D76: Fund | E76: ='CF (Funds)'!C35 -> 44784 | F76: ="Q"&ROUNDUP(MONTH(E76)/3,0)&" "&YEAR(E76) -> Q3 2022 | G76: ='CF (Funds)'!D35 -> 0.015224657 | H76: ='CF (Funds)'!E35 -> 0
C77: ='CF (Funds)'!B37 -> New Space Capital Fund I | D77: Fund | E77: ='CF (Funds)'!C37 -> 44956 | F77: ="Q"&ROUNDUP(MONTH(E77)/3,0)&" "&YEAR(E77) -> Q1 2023 | G77: ='CF (Funds)'!D37 -> 0 | H77: ='CF (Funds)'!E37 -> 2.9557744
C78: ='CF (Funds)'!B38 -> New Space Capital SCSp | D78: Fund | E78: ='CF (Funds)'!C38 -> 44087 | F78: ="Q"&ROUNDUP(MONTH(E78)/3,0)&" "&YEAR(E78) -> Q3 2020 | G78: ='CF (Funds)'!D38 -> -2.7058824 | H78: ='CF (Funds)'!E38 -> 0
C79: ='CF (Funds)'!B39 -> Acies Investments Fund I, L.P. | D79: Fund | E79: ='CF (Funds)'!C39 -> 44540 | F79: ="Q"&ROUNDUP(MONTH(E79)/3,0)&" "&YEAR(E79) -> Q4 2021 | G79: ='CF (Funds)'!D39 -> -2.8053125 | H79: ='CF (Funds)'!E39 -> 0
C80: ='CF (Funds)'!B40 -> Acies Investments Fund I, L.P. | D80: Fund | E80: ='CF (Funds)'!C40 -> 44602 | F80: ="Q"&ROUNDUP(MONTH(E80)/3,0)&" "&YEAR(E80) -> Q1 2022 | G80: ='CF (Funds)'!D40 -> -3.4075 | H80: ='CF (Funds)'!E40 -> 0
C81: ='CF (Funds)'!B41 -> Acies Investments Fund I, L.P. | D81: Fund | E81: ='CF (Funds)'!C41 -> 44683 | F81: ="Q"&ROUNDUP(MONTH(E81)/3,0)&" "&YEAR(E81) -> Q2 2022 | G81: ='CF (Funds)'!D41 -> -1.025775 | H81: ='CF (Funds)'!E41 -> 0
C82: ='CF (Funds)'!B42 -> Acies Investments Fund I, L.P. | D82: Fund | E82: ='CF (Funds)'!C42 -> 44707 | F82: ="Q"&ROUNDUP(MONTH(E82)/3,0)&" "&YEAR(E82) -> Q2 2022 | G82: ='CF (Funds)'!D42 -> -3.388275 | H82: ='CF (Funds)'!E42 -> 0
C83: ='CF (Funds)'!B43 -> Acies Investments Fund I, L.P. | D83: Fund | E83: ='CF (Funds)'!C43 -> 44875 | F83: ="Q"&ROUNDUP(MONTH(E83)/3,0)&" "&YEAR(E83) -> Q4 2022 | G83: ='CF (Funds)'!D43 -> -3.388275 | H83: ='CF (Funds)'!E43 -> 0

Sheet 5. CF 
B2: CASHFLOW REQUIREMENT
B3: Date of NAV | C3: =D!D2 -> 45016
B6: Deals | D6: Remaining Commitment | E6: Q3-2022 | F6: Q4-2022 | G6: Q1-2023 | H6: Q2-2023 | I6: Q3-2023 | J6: Q4-2023
B9: vTv Therapeutics Inc. | C9: Equity | D9: 12.5 | G9: =D9 -> 12.5
B10: Tawasol
B11: New Space Capital Fund I | C11: Fund | D11: 3.9459573 | G11: =D11-F11 -> 3.9459573
B12: North Summit Capital Fund | C12: Fund | D12: 217.81331
B13: Sinovation Disrupt Fund, L.P. | C13: Fund | D13: 33.209754
B14: Acies Investments Fund I, L.P. | C14: Fund | D14: 6.4856375
D15: =SUM(D9:D14) -> 273.95466 | F15: =SUM(F9:F14) -> 0 | G15: =SUM(G9:G14) -> 16.445957 | H15: =SUM(H9:H14) -> 0 | I15: =SUM(I9:I14) -> 0 | J15: =SUM(J9:J14) -> 0
B18: Notes
B19: No funding projected for North Summit Fund

Sheet 6. ATS
C2: ATTRIBUTION SUMMARY
D3: As of date | E3: 44819
D7: Deals | E7: Type | F7: Gain | G7: Gain till Dec 2021 | K7: MOZN Portfolio : Gains till Dec 2021 | N7: G42 Portfolio : Gains till Dec 2021
D8: Jollychic Holding Limited | E8: Equity | F8: =VLOOKUP(D8,'Summary | 01 '!$C$6:$R$43,13,0) -> -65 | G8: -65 | K8: ONT plc | L8: =VLOOKUP(K8,$D$7:$G$32,4,0) -> 275.8 | N8: Honor Device Co Ltd | O8: =VLOOKUP(N8,$D$7:$G$32,4,0) -> 0
D9: X-fusion | E9: Equity | F9: =VLOOKUP(D9,'Summary | 01 '!$C$6:$R$43,13,0) -> -69.434338 | G9: 0 | K9: Beyond Limits | L9: =VLOOKUP(K9,$D$7:$G$32,4,0) -> 0 | N9: DriveNets | O9: =VLOOKUP(N9,$D$7:$G$32,4,0) -> 0
D10: vTv Therapeutics Inc. | E10: Equity | F10: =VLOOKUP(D10,'Summary | 01 '!$C$6:$R$43,13,0) -> -16.141218 | G10: 0 | K10: Heygears | L10: =VLOOKUP(K10,$D$7:$G$32,4,0) -> -39.7 | N10: vTv Therapeutics Inc. | O10: =VLOOKUP(N10,$D$7:$G$32,4,0) -> 0
D11: Glass Earth Holdings LLC | E11: Debt | F11: =VLOOKUP(D11,'Summary | 01 '!$C$6:$R$43,13,0) -> -8 | G11: -8 | K11: Flyr Inc | L11: =VLOOKUP(K11,$D$7:$G$32,4,0) -> 68.1 | N11: North Summit Capital Fund | O11: =VLOOKUP(N11,$D$7:$G$32,4,0) -> 6.6
D12: Mena Mobile Inc | E12: Equity | F12: =VLOOKUP(D12,'Summary | 01 '!$C$6:$R$43,13,0) -> -4.9 | G12: -6.3 | K12: Mena Mobile Inc | L12: =VLOOKUP(K12,$D$7:$G$32,4,0) -> -6.3 | N12: New Space Capital Fund I | O12: =VLOOKUP(N12,$D$7:$G$32,4,0) -> 1
D13: ONT plc | E13: Equity | F13: =VLOOKUP(D13,'Summary | 01 '!$C$6:$R$43,13,0) -> -19.090073 | G13: 275.8 | K13: Endless Studios LLC | L13: =VLOOKUP(K13,$D$7:$G$32,4,0) -> 0 | N13: New Space Capital SCSp | O13: =VLOOKUP(N13,$D$7:$G$32,4,0) -> 0
D14: North Summit Capital Fund | E14: Fund | F14: =VLOOKUP(D14,'Summary | 01 '!$C$6:$R$43,13,0) -> -12.156692 | G14: 6.6 | K14: X-fusion | L14: =VLOOKUP(K14,$D$7:$G$32,4,0) -> 0 | N14: Sinovation Disrupt Fund, L.P. | O14: =VLOOKUP(N14,$D$7:$G$32,4,0) -> 3.5
D15: Sinovation Disrupt Fund, L.P. | E15: Fund | F15: =VLOOKUP(D15,'Summary | 01 '!$C$6:$R$43,13,0) -> -0.69768865 | G15: 3.5 | K15: Applied AI Corporation Limited | L15: =VLOOKUP(K15,$D$7:$G$32,4,0) -> 0 | N15: Acies Investments Fund I, L.P. | O15: =VLOOKUP(N15,$D$7:$G$32,4,0) -> 0
D16: Acies Investments Fund I, L.P. | E16: Fund | F16: =VLOOKUP(D16,'Summary | 01 '!$C$6:$R$43,13,0) -> -0.2722965 | G16: 0 | K16: eSpace | L16: =VLOOKUP(K16,$D$7:$G$32,4,0) -> 0
D17: Mena Mobile Inc (Debt) | E17: Debt | F17: =VLOOKUP(D17,'Summary | 01 '!$C$6:$R$43,13,0) -> 0 | G17: 0 | K17: Cerebras Systems Inc | L17: =VLOOKUP(K17,$D$7:$G$32,4,0) -> 0 | N17: Total | O17: =SUM(O8:O16) -> 11.1
D18: Jysan Technologies | E18: Equity | F18: =VLOOKUP(D18,'Summary | 01 '!$C$6:$R$43,13,0) -> 0 | G18: 0 | K18: Instadeep Limited | L18: =VLOOKUP(K18,$D$7:$G$32,4,0) -> 0
D19: Applied AI Corporation Limited | E19: Equity | F19: =VLOOKUP(D19,'Summary | 01 '!$C$6:$R$43,13,0) -> 0 | G19: 0 | K19: Jysan Technologies | L19: =VLOOKUP(K19,$D$7:$G$32,4,0) -> 0
D20: eSpace | E20: Equity | F20: =VLOOKUP(D20,'Summary | 01 '!$C$6:$R$43,13,0) -> 0 | G20: 0 | K20: Esyasoft Holding | L20: =VLOOKUP(K20,$D$7:$G$32,4,0) -> 2.5
D21: Cerebras Systems Inc | E21: Equity | F21: =VLOOKUP(D21,'Summary | 01 '!$C$6:$R$43,13,0) -> 0 | G21: 0 | K21: Esyasoft Holding (Debt) | L21: =VLOOKUP(K21,$D$7:$G$32,4,0) -> 0
D22: Endless Studios LLC | E22: Equity | F22: =VLOOKUP(D22,'Summary | 01 '!$C$6:$R$43,13,0) -> 0 | G22: 0 | K22: Mena Mobile Inc (Debt) | L22: =VLOOKUP(K22,$D$7:$G$32,4,0) -> 0
D23: Instadeep Limited | E23: Equity | F23: =VLOOKUP(D23,'Summary | 01 '!$C$6:$R$43,13,0) -> 0 | G23: 0 | K23: Glass Earth Holdings LLC | L23: =VLOOKUP(K23,$D$7:$G$32,4,0) -> -8
D24: DriveNets | E24: Equity | F24: =VLOOKUP(D24,'Summary | 01 '!$C$6:$R$43,13,0) -> 0 | G24: 0 | K24: Jollychic Holding Limited | L24: =VLOOKUP(K24,$D$7:$G$32,4,0) -> -65
D25: New Space Capital SCSp | E25: Fund | F25: =VLOOKUP(D25,'Summary | 01 '!$C$6:$R$43,13,0) -> 0 | G25: 0
D26: Beyond Limits | E26: Equity | F26: =VLOOKUP(D26,'Summary | 01 '!$C$6:$R$43,13,0) -> 1.0015403 | G26: 0 | K26: Gain till Dec 2021 | L26: =SUM(L8:L25) -> 227.4
D27: Esyasoft Holding (Debt) | E27: Debt | F27: =VLOOKUP(D27,'Summary | 01 '!$C$6:$R$43,13,0) -> 0.05901965 | G27: 0 | K27: Gain till Nov 2022 | L27: ='S | 02'!O27 -> -35.531817
D28: Esyasoft Holding | E28: Equity | F28: =VLOOKUP(D28,'Summary | 01 '!$C$6:$R$43,13,0) -> 2.5 | G28: 2.5 | K28: Delta Gain | L28: =L27-L26 -> -262.93182
D29: New Space Capital Fund I | E29: Fund | F29: =VLOOKUP(D29,'Summary | 01 '!$C$6:$R$43,13,0) -> 6.1926309 | G29: 1
D30: Heygears | E30: Equity | F30: =VLOOKUP(D30,'Summary | 01 '!$C$6:$R$43,13,0) -> 59.249804 | G30: -39.7
D31: Flyr Inc | E31: Equity | F31: =VLOOKUP(D31,'Summary | 01 '!$C$6:$R$43,13,0) -> 68.08223 | G31: 68.1
D32: Honor Device Co Ltd | E32: Equity | F32: =VLOOKUP(D32,'Summary | 01 '!$C$6:$R$43,13,0) -> 48.76999 | G32: 0

Sheet 7. %
C2: % OWNERSHIP
C3: As of date | D3: ='Summary | 01 '!D2 -> 45016
C7: Deals | D7: Shares | E7: Total | F7: % Ownership | G7: Source
C9: Direct Investments
C10: Jollychic Holding Limited | D10: 13458655 | E10: 236116762 | F10: =D10/E10 -> 0.056999998 | G10: Dan Kong
C11: Mena Mobile Inc | D11: 21419829 | E11: 152998776 | F11: =D11/E11 -> 0.14 | G11: Dan Kong
C12: Flyr Inc | D12: 5205482 | E12: 61222609 | F12: =D12/E12 -> 0.085025485 | G12: Cap Table
C13: Esyasoft Holding | D13: n/a | E13: n/a | F13: n/a | G13: n/a
C14: Beyond Limits | D14: 17670202 | E14: 1.8142856e+08 | F14: =D14/E14 -> 0.09739482 | G14: Cap Table
C15: ONT plc | D15: 44328120 | E15: 823636945 | F15: =D15/E15 -> 0.053819975 | G15: LSE Announcement
C16: Heygears | D16: 3565017.2 | E16: =D16/F16 -> 24791497 | F16: 0.1438 | G16: Dan Kong
C17: Jysan Technologies | D17: 7959497 | E17: 2.6531657e+08 | F17: 0.03 | G17: Txn docs
C18: Cerebras Systems Inc | D18: 1441711 | E18: n/a | F18: 0.01 | G18: Pitchbook triangulation
C19: Endless Studios LLC | D19: 3000000 | E19: 43750000 | F19: =D19/E19 -> 0.068571429 | G19: Txn docs
C20: Instadeep Limited | D20: 33267 | E20: 2895450 | F20: =D20/E20 -> 0.011489406 | G20: Txn docs
C21: X-fusion | F21: =10% * 1/2 -> 0.05 | G21: Dan Kong
C22: DriveNets | F22: 0.0943 | G22: Finance team
C23: vTv Therapeutics Inc. | D23: 10386274 | E23: =81483600+23093860 -> 104577460 | F23: =D23/E23 -> 0.099316564 | G23: 10Q report 15Aug
C24: Honor Device Co Ltd | F24: =4.705882%* 0.8/2 -> 0.018823528 | G24: Dan Kong
C25: Applied AI Corporation Limited | D25: n/a | E25: n/a | F25: n/a | G25: n/a
C27: Debt Investments
C28: Glass Earth Holdings LLC
C29: Mena Mobile Inc
C30: Esyasoft Holding
C33: Funds Investments
C34: New Space Capital Fund I
C35: New Space Capital SCSp
C36: North Summit Capital Fund
C37: Sinovation Disrupt Fund, L.P.
C38: Acies Investments Fund I, L.P. | F38: =1/3 -> 0.33333333

Sheet 8. Board
C3: Deals | D3: Board Representation ‡ | E3: Representative | F3: Notes | G3: Comments
C5: Direct Investments
C6: Mena Mobile Inc | D6: 1 Board | E6: Peng Xiao
C7: Flyr Inc | D7: 1 Board | E7: Marty
C8: Esyasoft Holding | D8: NR | E8: n/a | F8: 2 | G8: Monty Aw represented earlier
C9: Jollychic Holding Limited | D9: 1 Board | E9: Divyesh Mahajan | F9: 1
C10: Beyond Limits | D10: 1 Board | E10: Marty | F10: 3
C11: ONT plc | D11: 1 Board | E11: Guy Harmelin (Independent Director)
C12: Heygears | D12: 2 Board | E12: Peng Xiao, Elaine
C13: Jysan Technologies | D13: 1 Board | E13: None appointed
C14: Cerebras Systems Inc | D14: 1 Observer | E14: Eric Xing | F14: 4
C15: Endless Studios LLC | D15: 1 Board + 1 Observer | E15: Tariq (Board), Talal (Observer)
C16: Instadeep Limited | D16: 1 Observer | E16: Viktor
C17: X-fusion | D17: NR | E17: n/a
C18: DriveNets | D18: 1 Observer | E18: Guy Harmelin
C19: vTv Therapeutics Inc. | D19: 1 Board, 1 Observer | E19: Dr. Fahad (Board), Jon Nieman (Observer)
C20: Honor Device Co Ltd | D20: NR | E20: n/a | F20: 5
C23: Debt Investments
C24: Glass Earth Holdings LLC | D24: NR
C25: Mena Mobile Inc | D25: 1 Board | E25: Peng Xiao
C26: Esyasoft Holding | D26: NR
C29: Funds Investments
C30: New Space Capital Fund I | D30: NR
C31: New Space Capital SCSp | E31: Talal
C32: North Summit Capital Fund | D32: NR
C33: Sinovation Disrupt Fund, L.P. | D33: NR
C34: Acies Investments Fund I, L.P. | D34: Not yet appointed | E34: Advisory Board | G34: Confirm appoinment
C38: NOTES:
C39: NR =No representation
C40: ‡ Board Representation : as a Board Seat, Observer, or Advisor
B41: 1 | C41: Jollychic Holding : Peng Xiao held the directorship until Jun 2021
B42: 2 | C42: Esyasoft: we held a Board seat, with Monty Aw as the representative, until Jun 2022
B43: 3 | C43: Beyond Limits: possibility of the 2nd Board seat in case we invest (an additional / an earlier committed) $10m
B44: 4 | C44: Cerebras : possibility of a Board seat, If G42 holds >10% with rights to exercise at least 20% of warrant
B45: 5 | C45: Honor: Our board seat only kicks in once Honor is converted into a joint stock company in March 2023; there is no one appointed as yet
C47: Date of Update: 22 Nov 22

Sheet 9. Log
B2: Date Log | C2: Update
B3: October 22
C4: 1) $4.75m Signing Payment for AAICO
C5: 2) $3.4m 4th capital call Acies
C6: 3) Honor booked at $1.2B cost
C7: 4) NAV of Heygears updated to $114.2m as of Oct 22
B9: November 22
B10: 44887 | C10: 1) Updated the Board directorships info for VTVT and Honor
C11: 2) 10-Nov-2022 USD 3,388,275 Acies Investments capital call
C12: 3) 27-Nov-2022 USD 15,000,000 eSpace SAFE
C13: 4) Moved Jysan under Mozn
C14: 5) Revised carrying value of New Space Capital
B17: December 22
C18: 1) Esyasoft Loan Exit (received $471K on 07-Dec)
C19: 2) Sell down of $250m position in Honor (received 21-Dec)
C20: 3) New Space Capital restructuring ongoing
C21: 4) Instadeep exit in progress
B23: January 23
C24: 1) Received EUR 12.5m from NewSpace Capital on 30-Jan (actualization interest); revised remaining commitment
C25: 2) Sinovation issued 6th Capital Call; funded 03-Feb
C26: 3) Instadeep transaction 'completion' in progress

Sheet X1
C3: ONT | G3: Heygears | K3: FLYR | O3: Instadeep | S3: vTv Therapeutics
W4: Select Cashflow for
G5: NAV Date
C6: NAV Date | D6: 44773 | O6: Post all transactions | S6: # shares | T6: 10386274 | W6: Vintage
C7: Share Price (GBP) | D7: 3.18 | G7: 44166 | H7: -60000000 | O7: B = 599,769 | P7: 599769 | S7: Price per share | T7: 1.18 | W7: Sector
C8: GBPUSD | D8: 1.22 | G8: 44773 | H8: 20000000 | K8: G42 Shares | L8: 5205482 | O8: Ordinary =1,493,575 | P8: 1493575 | S8: Value | T8: =T6*T7*10^-6 -> 12.255803 | W8: Geogrpahy
K9: Fully Diluted | L9: 61222609 | O9: Employee shares = 83,261 | P9: 83261 | W9: Asset Class Type
C10: G42 Shares | D10: 44328120 | G10: IRR | H10: =XIRR(H7:H8,G7:G8) -> -0.48346658 | K10: % ownership | L10: 0.0855 | O10: Class A = 289,048 | P10: 289048
C11: Fully Diluted | D11: 823636945 | G11: Multiple | H11: =-H8/SUM(H7) -> 0.33333333 | L11: =L8/L9 -> 0.085025485 | O11: LTIP shares | P11: 429797
C12: % ownership | D12: 0.0538 | O12: Total | P12: =SUM(P7:P11) -> 2895450 | S12: EsyaSoft, Equity
G13: Mena Mobile | K13: Share price | L13: 18.75
K14: Discount | L14: 0.2 | O14: # shares to G42 | P14: 33267 | S14: NAV Date
C15: USDAED | D15: 3.675 | G15: NAV Date | K15: Carrying Value Mn | L15: =L8*L13*(1-L14)*10^-6 -> 78.08223 | O15: % ownership | P15: =P14/P12 -> 0.011489406
C16: Date of Investment | O16: Price per share | Oct 21 | P16: 110.63 | S16: 44075 | T16: -2500000
C17: 43968 | D17: -50 | G17: 43563 | H17: -8000000 | K17: NAV Date | L17: 44773 | O17: NAV Date | P17: 44773 | S17: 44773 | T17: 5000000
C18: 44006 | D18: -27.268351 | G18: 44773 | H18: 1700000 | K18: 43570 | L18: -4999998.1
C19: 43837 | D19: -18.109441 | K19: 43915 | L19: -5000001.9 | O19: BNT Offer | 18Jul 2022 | S19: IRR | T19: =XIRR(T16:T17,S16:S17) -> 0.43686312
C20: 43990 | D20: -34.851687 | G20: IRR | H20: =XIRR(H17:H18,G17:G18) -> -0.37324778 | K20: =L17 -> 44773 | L20: =+L15*10^6 -> 78082230 | O20: Offer Mn, GBP | P20: 510 | S20: Multiple | T20: =-T17/SUM(T16) -> 2
C21: 44315 | D21: -11.24078 | G21: Multiple | H21: =-H18/SUM(H17) -> 0.2125 | O21: # shares o/s | P21: =P12 -> 2895450
C22: 44742 | D22: =NAV!E14 -> 122.38019 | K22: IRR | L22: =XIRR(L18:L20,K18:K20) -> 1.0308312 | O22: Offer price per share | P22: =P20*10^6/P21 -> 176.13842 | S22: EsyaSoft, Debt
K23: Multiple | L23: =L20/-SUM(L18:L19) -> 7.808223 | O23: Premium | P23: =P22/P16 -> 1.5921398
C24: IRR | D24: =XIRR(D17:D22,C17:C22) -> -0.068174848 | O24: GBPUSD | P24: 1.22 | S24: NAV Date
C25: Multiple | D25: =-D22/SUM(D17:D21) -> 0.86505946
S26: 44377 | T26: -411765
O27: 44550 | P27: =-18477242.89/3.68 -> -5020989.9 | S27: 44773 | T27: =(-((S27-S26)/365*T26*10%))-T26 -> 456438.68
O28: =P17 -> 44773 | P28: =P14*P22*P24 -> 7148708.3
S29: IRR | T29: =XIRR(T26:T27,S26:S27) -> 0.099591023
O30: IRR | P30: =XIRR(P27:P28,O27:O28) -> 0.78296691 | S30: Multiple | T30: =-T27/SUM(T26) -> 1.1084932
O31: Multiple | P31: =P28/-SUM(P27) -> 1.4237647

Sheet X2
D4: Investment type | E4: Monthly (25th of each month other than quarter-end) | F4: Quarterly (1st April, July and October) | G4: Annually (2nd January following year-end) | H4: Ref. to summary
D5: Listed securities on a recognised exchange | E5: 1. Number of securities held, including: | F5: 1. Number of securities held, including: | G5: 1. Number of securities held, including: | H5: 1a
E6: details of any movement in number of securities held | F6: details of any movement in number of securities held | G6: details of any movement in number of securities held | H6: 1b, 1c, 1d
E7: exercise of conversion rights | F7: exercise of conversion rights | G7: exercise of conversion rights | H7: 1c
E8: changes to the terms of the instrument | F8: changes to the terms of the instrument | G8: changes to the terms of the instrument | H8: 4
E9: amalgamation/ splitting of instrument classes | F9: amalgamation/ splitting of instrument classes | G9: amalgamation/ splitting of instrument classes | H9: 1c
E10: bonus shares | F10: bonus shares | G10: bonus shares | H10: 1c
E11: additional instruments subscribed | F11: additional instruments subscribed | G11: additional instruments subscribed | H11: 1b
E12: dividend, etc. | F12: dividend, etc. | G12: dividend, etc. | H12: 3
E13: 2. Fair value of the listed portfolio based on quoted stock exchange (MTM) price | F13: 2. Fair value of the listed portfolio based on quoted stock exchange (MTM) price | G13: 2. Fair value of the listed portfolio based on quoted stock exchange (MTM) price | H13: 2
D15: Unlisted corporate investments held | E15: 1. Number of securities held, including: | F15: 1. Number of securities held, including: | G15: 1. Number of securities held, including: | H15: 1a
E16: details of any movement in number of securities held | F16: details of any movement in number of securities held | G16: details of any movement in number of securities held | H16: 1b, 1c, 1d
E17: exercise of conversion rights | F17: exercise of conversion rights | G17: exercise of conversion rights | H17: 1c
E18: changes to the terms of the instrument | F18: changes to the terms of the instrument | G18: changes to the terms of the instrument | H18: 4
E19: amalgamation/ splitting of instrument classes | F19: amalgamation/ splitting of instrument classes | G19: amalgamation/ splitting of instrument classes | H19: 1c
E20: bonus shares | F20: bonus shares | G20: bonus shares | H20: 1c
E21: additional instruments subscribed | F21: additional instruments subscribed | G21: additional instruments subscribed | H21: 1b
E22: dividend, etc. | F22: dividend, etc. | G22: dividend, etc. | H22: 3
E23: 2. Any events or conditions that indicate significant decrease in the fair value previously recorded for individual investments | F23: 2. Any events or conditions that indicate significant increase/ decrease in the fair value previously recorded for individual investments | G23: 2. Any events or conditions that indicate significant increase/ decrease in the fair value previously recorded for individual investments | H23: 4
F24: 3. Refresh the valuation at which each investment in the portfolio is previously carried | G24: 3. Refresh the valuation at which each investment in the portfolio is previously carried | H24: 3
G25: 4. Obtain an external valuer’s report of fair value of each investment in the portfolio as at 30th September (by 30th November)
G26: 5. Carry out an internal refresh as at 31st December of the external valuer’s report of fair value (by 5th January following the year-end)
D28: Investments in Funds (closed ended) | E28: 1. Any events or conditions that indicate significant increase/ decrease in the fair value previously recorded for individual investments | F28: 1. Any events or conditions that indicate significant increase/ decrease in the fair value previously recorded for individual investments | G28: 1. Any events or conditions that indicate significant increase/ decrease in the fair value previously recorded for individual investments | H28: 2
F29: 2. Fair value of investment in each Fund based on Fund Manager’s/ General Partner’s report for the previous quarter | G29: 2. Fair value of investment in each Fund based on Fund Manager’s/ General Partner’s report for the previous quarter (by 5th January following the year-end) | H29: 1

Sheet X3
C2: Date of NAV | D2: 44865
H3: D A S H B O A R D | L3: figures in USD Millions
D6: # Investments | E6: Committed | F6: Invested | G6: Remaining | H6: Distributions | I6: Residual Value | J6: IRR | K6: TVPI | L6: RPI | M6: DPI | Q6: A T T R I B U T I O N S U M M A R Y
C8: EQUITY | D8: =COUNTIF('Summary | 01 '!C10:C24,"*") -> 15 | E8: ='1. IRR Equity'!AD29 -> 2093.0293 | F8: ='1. IRR Equity'!AE29 -> 2082.7762 | G8: ='1. IRR Equity'!AF29 -> 10.253161 | H8: ='1. IRR Equity'!AG29 -> 5 | I8: ='1. IRR Equity'!AH29 -> 2082.8141 | J8: ='1. IRR Equity'!AI29 -> 0.0019109696 | K8: ='1. IRR Equity'!AJ29 -> 1.0024189 | L8: ='1. IRR Equity'!AK29 -> 1.0000182 | M8: ='1. IRR Equity'!AL29 -> 0.002400642 | Q8: TOP GAINERS
Q9: Heygears | R9: Equity | S9: 76.64
Q10: Flyr Inc | R10: Equity | S10: 68.08223
C11: DEBT | D11: =COUNTIF('Summary | 01 '!C30:C32,"*") -> 3 | E11: ='2. IRR Debt'!Q12 -> 10.765747 | F11: ='2. IRR Debt'!R12 -> 10.765747 | G11: ='2. IRR Debt'!S12 -> 0 | H11: ='2. IRR Debt'!T12 -> 0.47078465 | I11: ='2. IRR Debt'!U12 -> 2.353982 | J11: ='2. IRR Debt'!V12 -> -0.35001702 | K11: ='2. IRR Debt'!W12 -> 0.26238464 | L11: ='2. IRR Debt'!X12 -> 0.21865478 | M11: ='2. IRR Debt'!Y12 -> 0.043729864 | Q11: Honor Device Co Ltd | R11: Equity | S11: 60.462713
Q12: New Space Capital Fund I | R12: Fund | S12: 10.340849
Q13: ONT plc | R13: Equity | S13: 8.1105485
C14: FUNDS | D14: =COUNTIF('Summary | 01 '!C36:C40,"*") -> 5 | E14: ='3. IRR Funds'!Q15 -> 395.37629 | F14: ='3. IRR Funds'!R15 -> 133.65097 | G14: ='3. IRR Funds'!S15 -> 262.75328 | H14: ='3. IRR Funds'!T15 -> 4.4275637 | I14: ='3. IRR Funds'!U15 -> 122.28936 | J14: ='3. IRR Funds'!V15 -> -0.02269576 | K14: ='3. IRR Funds'!W15 -> 0.94811825 | L14: ='3. IRR Funds'!X15 -> 0.91499044 | M14: ='3. IRR Funds'!Y15 -> 0.033127807 | Q14: Esyasoft Holding | R14: Equity | S14: 2.5
Q15: Beyond Limits | R15: Equity | S15: 1.0015403
C17: TOTAL | D17: =D8+D11+D14 -> 23 | E17: =E8+E11+E14 -> 2499.1714 | F17: =F8+F11+F14 -> 2227.1929 | G17: =G8+G11+G14 -> 273.00644 | H17: =H8+H11+H14 -> 9.8983484 | I17: =I8+I11+I14 -> 2207.4575 | J17: ='4.All'!N9 -> -0.0033056326 | K17: =(H17+I17)/F17 -> 0.99558319 | L17: =I17/F17 -> 0.99113887 | M17: =H17/F17 -> 0.0044443157 | Q17: TOP LOSERS
Q18: Jollychic Holding Limited | R18: Equity | S18: -65
E19: =E17='Summary | 01 '!J43 -> FALSE | F19: =F17='Summary | 01 '!K43 -> TRUE | G19: =ROUND(G17,1)=ROUND('Summary | 01 '!L43,1) -> FALSE | H19: =ROUND(H17,1)=ROUND('Summary | 01 '!M43,1) -> TRUE | I19: =ROUND(I17,1)=ROUND('Summary | 01 '!N43,1) -> TRUE | Q19: vTv Therapeutics Inc. | R19: Equity | S19: -13.055785
Q20: Glass Earth Holdings LLC | R20: Debt | S20: -8
Q21: Mena Mobile Inc | R21: Equity | S21: -4.9
C22: Equity Only | D22: # Investments | E22: Committed | F22: Invested | G22: Remaining | H22: Distributions | I22: Residual Value | J22: IRR | K22: TVPI | L22: RPI | M22: DPI | Q22: North Summit Capital Fund | R22: Fund | S22: -2.866692
Q23: Sinovation Disrupt Fund, L.P. | R23: Fund | S23: -0.47118065
C24: Select Portfolio1 IRR | D24: ='1.1(P1)'!O23 -> 9 | E24: ='1.1(P1)'!P23 -> 379.99398 | F24: ='1.1(P1)'!Q23 -> 379.99398 | G24: ='1.1(P1)'!R23 -> 0 | H24: ='1.1(P1)'!S23 -> 5 | I24: ='1.1(P1)'!T23 -> #VALUE! | J24: ='1.1(P1)'!U23 -> #VALUE! | K24: ='1.1(P1)'!V23 -> #VALUE! | ... M24: ='1.1(P1)'!X23 -> 0.013158103 | Q24: Acies Investments Fund I, L.P. | R24: Fund | S24: -0.2834155
C26: Vintage 2019 | Equity | D26: 3 | E26: =F26 -> 83 | F26: 83 | G26: 0 | H26: 0 | I26: 81.18223 | J26: -0.0067133114 | K26: 0.97809916 | L26: 0.97809916 | M26: 0 | Q26: TOTAL MOVEMENT | S26: =SUM(S9:S24) -> 132.56081
C28: Vintage 2020 | Equity | D28: 4 | E28: =F28 -> 293.97026 | F28: 293.97026 | G28: 0 | H28: 5 | I28: 377.22235 | J28: 0.12646896 | K28: 1.3002075 | L28: 1.283199 | M28: 0.017008523
C30: Vintage 2021 | Equity | D30: 2 | E30: =F30 -> 8.0237202 | F30: 8.0237202 | G30: 0 | H30: 0 | I30: 8.0237202 | J30: 2.9802322e-09 | K30: 1 | L30: 1 | M30: 0
C34: Includes Equity, Debt, Funds
D35: # Investments | E35: Committed | F35: Invested | G35: Remaining | H35: Distributions | I35: Residual Value | J35: IRR | K35: TVPI | L35: RPI | M35: DPI
C37: Asia-China | D37: 8 | E37: 2578.854 | F37: 1528.8598 | G37: =E37-F37 -> 1049.9941 | H37: 1.4717893 | I37: 1591.9989 | J37: 0.064502594 | K37: 1.0422608 | L37: 1.0412981 | M37: 0.00096267121
C39: Rest of Asia | D39: 3 | E39: 22.911765 | F39: 22.911765 | G39: 0 | H39: 5 | I39: 20.456439 | J39: 0.082198861 | K39: 1.1110641 | L39: 0.89283557 | M39: 0.2182285
C41: Middle East | D41: 1 | E41: 300 | F41: 300 | G41: 0 | H41: 0 | I41: 300 | J41: 2.9802322e-09 | K41: 1 | L41: 1 | M41: 0
C43: USA | D43: 7 | E43: 193.1125 | F43: 174.12686 | G43: 18.985638 | H43: 0 | I43: 221.87142 | J43: 0.12701625 | K43: 1.2503351 | L43: 1.2503351 | M43: 0
C45: Europe | D45: 4 | E45: 174.76187 | F45: 170.81591 | G45: 3.9459573 | H45: 0 | I45: 189.26321 | J45: 0.048084196 | K45: 1.1080218 | L45: 1.1080218 | M45: 0
C48: Notes
C49: Select Portfolio1 includes Jollychic, Mena Mobile, Flyr, Esyasoft, BL, ONT, Heygears, Endless, Instadeep
C50: Vintage 2019 includes Jollychic, Mena Mobile, Flyr
C51: Vintage 2020 includes Esyasoft, BL, ONT, Heygears
C52: Vintage 2021 includes Endless, Instadeep

Sheet 4.1
F2: IRR - Select (All Investments, includes Equity, Debt, Funds)
F4: Date of NAV | G4: =D!D2 -> 45016
F6: (in USD, Mn) | Q6: (in USD, Mn)
B7: Portfolio | F7: Investment | G7: Type | H7: Geograhpy | I7: Vintage | J7: Payment date | K7: Contribution | L7: Distributions | M7: Remaining Value | N7: Combined | Q7: Investment | R7: Contribution | S7: Distributions | T7: Remaining Value | U7: Combined | X7: Count | Y7: Committed | Z7: Invested | AA7: Remaining | AB7: Distributions | AC7: Residual Value | AD7: IRR | AE7: TVPI | AF7: RPI | AG7: DPI
B8: Jollychic Holding Limited | C8: Asia-China | F8: Jollychic Holding Limited | G8: Equity | H8: =VLOOKUP(F8,'5. Geo'!$B$3:$F$26,5,0) -> Asia-China | I8: =VLOOKUP(F8,'5. Geo'!$B$3:$F$26,2,0) -> 2019 | J8: 43470 | K8: ='CF (Equity, Debt)'!E4 -> -30 | L8: ='CF (Equity, Debt)'!F4 -> 0 | N8: =SUM(K8:M8) -> -30 | P8: =IF($C$8=H8,1,0) -> 1 | Q8: Jollychic Holding Limited | R8: =$P8*K8 -> -30 | S8: =$P8*L8 -> 0 | T8: =$P8*M8 -> 0 | U8: =$P8*N8 -> -30
B9: Mena Mobile Inc | C9: USA | F9: Jollychic Holding Limited | G9: Equity | H9: =VLOOKUP(F9,'5. Geo'!$B$3:$F$26,5,0) -> Asia-China | I9: =VLOOKUP(F9,'5. Geo'!$B$3:$F$26,2,0) -> 2019 | J9: 43724 | K9: ='CF (Equity, Debt)'!E5 -> -20 | L9: ='CF (Equity, Debt)'!F5 -> 0 | N9: =SUM(K9:M9) -> -20 | P9: =IF($C$8=H9,1,0) -> 1 | Q9: Jollychic Holding Limited | R9: =$P9*K9 -> -20 | S9: =$P9*L9 -> 0 | T9: =$P9*M9 -> 0 | U9: =$P9*N9 -> -20 | X9: =SUM(P74:P97) -> 8 | Z9: =-SUM(R8:R99) -> 1328.8598 | AB9: =SUM(S8:S99) -> 1.4717893 | AC9: =SUM(T8:T99) -> #VALUE! | AD9: =XIRR(U8:U110,J8:J110,0.1) -> 2.9802322e-09 | AE9: =(AB9+AC9)/Z9 -> #VALUE! | AF9: =AC9/Z9 -> #VALUE! | AG9: =AB9/Z9 -> 0.001107558
B10: Flyr Inc | C10: Rest of Asia | F10: Jollychic Holding Limited | G10: Equity | H10: =VLOOKUP(F10,'5. Geo'!$B$3:$F$26,5,0) -> Asia-China | I10: =VLOOKUP(F10,'5. Geo'!$B$3:$F$26,2,0) -> 2019 | J10: 43724 | K10: ='CF (Equity, Debt)'!E6 -> -15 | L10: ='CF (Equity, Debt)'!F6 -> 0 | N10: =SUM(K10:M10) -> -15 | P10: =IF($C$8=H10,1,0) -> 1 | Q10: Jollychic Holding Limited | R10: =$P10*K10 -> -15 | S10: =$P10*L10 -> 0 | T10: =$P10*M10 -> 0 | U10: =$P10*N10 -> -15
B11: Esyasoft Holding | C11: Europe | F11: Mena Mobile Inc | G11: Equity | H11: =VLOOKUP(F11,'5. Geo'!$B$3:$F$26,5,0) -> Asia-China | I11: =VLOOKUP(F11,'5. Geo'!$B$3:$F$26,2,0) -> 2019 | J11: 43563 | K11: ='CF (Equity, Debt)'!E7 -> -8 | L11: ='CF (Equity, Debt)'!F7 -> 0 | N11: =SUM(K11:M11) -> -8 | P11: =IF($C$8=H11,1,0) -> 1 | Q11: Mena Mobile Inc | R11: =$P11*K11 -> -8 | S11: =$P11*L11 -> 0 | T11: =$P11*M11 -> 0 | U11: =$P11*N11 -> -8
B12: Beyond Limits | C12: MiddleEast | F12: Flyr Inc | G12: Equity | H12: =VLOOKUP(F12,'5. Geo'!$B$3:$F$26,5,0) -> USA | I12: =VLOOKUP(F12,'5. Geo'!$B$3:$F$26,2,0) -> 2019 | J12: 43570 | K12: ='CF (Equity, Debt)'!E8 -> -4.9999981 | L12: ='CF (Equity, Debt)'!F8 -> 0 | N12: =SUM(K12:M12) -> -4.9999981 | P12: =IF($C$8=H12,1,0) -> 0 | Q12: Flyr Inc | R12: =$P12*K12 -> 0 | S12: =$P12*L12 -> 0 | T12: =$P12*M12 -> 0 | U12: =$P12*N12 -> 0
B13: ONT plc | F13: Flyr Inc | G13: Equity | H13: =VLOOKUP(F13,'5. Geo'!$B$3:$F$26,5,0) -> USA | I13: =VLOOKUP(F13,'5. Geo'!$B$3:$F$26,2,0) -> 2019 | J13: 43915 | K13: ='CF (Equity, Debt)'!E9 -> -5.0000019 | L13: ='CF (Equity, Debt)'!F9 -> 0 | N13: =SUM(K13:M13) -> -5.0000019 | P13: =IF($C$8=H13,1,0) -> 0 | Q13: Flyr Inc | R13: =$P13*K13 -> 0 | S13: =$P13*L13 -> 0 | T13: =$P13*M13 -> 0 | U13: =$P13*N13 -> 0
B14: Heygears | F14: Esyasoft Holding | G14: Equity | H14: =VLOOKUP(F14,'5. Geo'!$B$3:$F$26,5,0) -> Rest of Asia | I14: =VLOOKUP(F14,'5. Geo'!$B$3:$F$26,2,0) -> 2020 | J14: 43870 | K14: ='CF (Equity, Debt)'!E10 -> -2.5 | L14: ='CF (Equity, Debt)'!F10 -> 0 | N14: =SUM(K14:M14) -> -2.5 | P14: =IF($C$8=H14,1,0) -> 0 | Q14: Esyasoft Holding | R14: =$P14*K14 -> 0 | S14: =$P14*L14 -> 0 | T14: =$P14*M14 -> 0 | U14: =$P14*N14 -> 0
B15: Jysan Technologies | F15: Beyond Limits | G15: Equity | H15: =VLOOKUP(F15,'5. Geo'!$B$3:$F$26,5,0) -> USA | I15: =VLOOKUP(F15,'5. Geo'!$B$3:$F$26,2,0) -> 2020 | J15: 43879 | K15: ='CF (Equity, Debt)'!E11 -> -20 | L15: ='CF (Equity, Debt)'!F11 -> 0 | N15: =SUM(K15:M15) -> -20 | P15: =IF($C$8=H15,1,0) -> 0 | Q15: Beyond Limits | R15: =$P15*K15 -> 0 | S15: =$P15*L15 -> 0 | T15: =$P15*M15 -> 0 | U15: =$P15*N15 -> 0
B16: Cerebras Systems Inc | F16: Beyond Limits | G16: Equity | H16: =VLOOKUP(F16,'5. Geo'!$B$3:$F$26,5,0) -> USA | I16: =VLOOKUP(F16,'5. Geo'!$B$3:$F$26,2,0) -> 2020 | J16: 43921 | K16: ='CF (Equity, Debt)'!E12 -> -30 | L16: ='CF (Equity, Debt)'!F12 -> 0 | N16: =SUM(K16:M16) -> -30 | P16: =IF($C$8=H16,1,0) -> 0 | Q16: Beyond Limits | R16: =$P16*K16 -> 0 | S16: =$P16*L16 -> 0 | T16: =$P16*M16 -> 0 | U16: =$P16*N16 -> 0
B17: Endless Studios LLC | F17: Beyond Limits | G17: Equity | H17: =VLOOKUP(F17,'5. Geo'!$B$3:$F$26,5,0) -> USA | I17: =VLOOKUP(F17,'5. Geo'!$B$3:$F$26,2,0) -> 2020 | J17: 43989 | K17: ='CF (Equity, Debt)'!E13 -> -30 | L17: ='CF (Equity, Debt)'!F13 -> 0 | N17: =SUM(K17:M17) -> -30 | P17: =IF($C$8=H17,1,0) -> 0 | Q17: Beyond Limits | R17: =$P17*K17 -> 0 | S17: =$P17*L17 -> 0 | T17: =$P17*M17 -> 0 | U17: =$P17*N17 -> 0
B18: Instadeep Limited | F18: Beyond Limits | G18: Equity | H18: =VLOOKUP(F18,'5. Geo'!$B$3:$F$26,5,0) -> USA | I18: =VLOOKUP(F18,'5. Geo'!$B$3:$F$26,2,0) -> 2020 | J18: 44103 | K18: ='CF (Equity, Debt)'!E14 -> -10 | L18: ='CF (Equity, Debt)'!F14 -> 0 | N18: =SUM(K18:M18) -> -10 | P18: =IF($C$8=H18,1,0) -> 0 | Q18: Beyond Limits | R18: =$P18*K18 -> 0 | S18: =$P18*L18 -> 0 | T18: =$P18*M18 -> 0 | U18: =$P18*N18 -> 0
B19: X-fusion | F19: ONT plc | G19: Equity | H19: =VLOOKUP(F19,'5. Geo'!$B$3:$F$26,5,0) -> Europe | I19: =VLOOKUP(F19,'5. Geo'!$B$3:$F$26,2,0) -> 2020 | J19: 43968 | K19: ='CF (Equity, Debt)'!E15 -> -50 | L19: ='CF (Equity, Debt)'!F15 -> 0 | N19: =SUM(K19:M19) -> -50 | P19: =IF($C$8=H19,1,0) -> 0 | Q19: ONT plc | R19: =$P19*K19 -> 0 | S19: =$P19*L19 -> 0 | T19: =$P19*M19 -> 0 | U19: =$P19*N19 -> 0
B20: DriveNets | F20: ONT plc | G20: Equity | H20: =VLOOKUP(F20,'5. Geo'!$B$3:$F$26,5,0) -> Europe | I20: =VLOOKUP(F20,'5. Geo'!$B$3:$F$26,2,0) -> 2020 | J20: 44006 | K20: ='CF (Equity, Debt)'!E16 -> -27.268351 | L20: ='CF (Equity, Debt)'!F16 -> 0 | N20: =SUM(K20:M20) -> -27.268351 | P20: =IF($C$8=H20,1,0) -> 0 | Q20: ONT plc | R20: =$P20*K20 -> 0 | S20: =$P20*L20 -> 0 | T20: =$P20*M20 -> 0 | U20: =$P20*N20 -> 0
B21: vTv Therapeutics Inc. | F21: ONT plc | G21: Equity | H21: =VLOOKUP(F21,'5. Geo'!$B$3:$F$26,5,0) -> Europe | I21: =VLOOKUP(F21,'5. Geo'!$B$3:$F$26,2,0) -> 2020 | J21: 43837 | K21: ='CF (Equity, Debt)'!E17 -> -18.109441 | L21: ='CF (Equity, Debt)'!F17 -> 0 | N21: =SUM(K21:M21) -> -18.109441 | P21: =IF($C$8=H21,1,0) -> 0 | Q21: ONT plc | R21: =$P21*K21 -> 0 | S21: =$P21*L21 -> 0 | T21: =$P21*M21 -> 0 | U21: =$P21*N21 -> 0
B22: Honor Device Co Ltd | F22: ONT plc | G22: Equity | H22: =VLOOKUP(F22,'5. Geo'!$B$3:$F$26,5,0) -> Europe | I22: =VLOOKUP(F22,'5. Geo'!$B$3:$F$26,2,0) -> 2020 | J22: 43990 | K22: ='CF (Equity, Debt)'!E18 -> -34.851687 | L22: ='CF (Equity, Debt)'!F18 -> 0 | N22: =SUM(K22:M22) -> -34.851687 | P22: =IF($C$8=H22,1,0) -> 0 | Q22: ONT plc | R22: =$P22*K22 -> 0 | S22: =$P22*L22 -> 0 | T22: =$P22*M22 -> 0 | U22: =$P22*N22 -> 0
B23: Glass Earth Holdings LLC | F23: ONT plc | G23: Equity | H23: =VLOOKUP(F23,'5. Geo'!$B$3:$F$26,5,0) -> Europe | I23: =VLOOKUP(F23,'5. Geo'!$B$3:$F$26,2,0) -> 2020 | J23: 44315 | K23: ='CF (Equity, Debt)'!E19 -> -11.24078 | L23: ='CF (Equity, Debt)'!F19 -> 0 | N23: =SUM(K23:M23) -> -11.24078 | P23: =IF($C$8=H23,1,0) -> 0 | Q23: ONT plc | R23: =$P23*K23 -> 0 | S23: =$P23*L23 -> 0 | T23: =$P23*M23 -> 0 | U23: =$P23*N23 -> 0
B24: Mena Mobile Inc | F24: Heygears | G24: Equity | H24: =VLOOKUP(F24,'5. Geo'!$B$3:$F$26,5,0) -> Asia-China | I24: =VLOOKUP(F24,'5. Geo'!$B$3:$F$26,2,0) -> 2020 | J24: 44166 | K24: ='CF (Equity, Debt)'!E20 -> -60 | L24: ='CF (Equity, Debt)'!F20 -> 0 | N24: =SUM(K24:M24) -> -60 | P24: =IF($C$8=H24,1,0) -> 1 | Q24: Heygears | R24: =$P24*K24 -> -60 | S24: =$P24*L24 -> 0 | T24: =$P24*M24 -> 0 | U24: =$P24*N24 -> -60
... B30: Acies Investments Fund I, L.P. | F30: DriveNets | G30: Equity | H30: =VLOOKUP(F30,'5. Geo'!$B$3:$F$26,5,0) -> MiddleEast | I30: =VLOOKUP(F30,'5. Geo'!$B$3:$F$26,2,0) -> 2022 | J30: 44643 | K30: ='CF (Equity, Debt)'!E26 -> -200 | L30: ='CF (Equity, Debt)'!F26 -> 0 | N30: =SUM(K30:M30) -> -200 | P30: =IF($C$8=H30,1,0) -> 0 | Q30: DriveNets | R30: =$P30*K30 -> 0 | S30: =$P30*L30 -> 0 | T30: =$P30*M30 -> 0 | U30: =$P30*N30 -> 0
F31: DriveNets | G31: Equity | H31: =VLOOKUP(F31,'5. Geo'!$B$3:$F$26,5,0) -> MiddleEast | I31: =VLOOKUP(F31,'5. Geo'!$B$3:$F$26,2,0) -> 2022 | J31: 44680 | K31: ='CF (Equity, Debt)'!E27 -> -100 | L31: ='CF (Equity, Debt)'!F27 -> 0 | N31: =SUM(K31:M31) -> -100 | P31: =IF($C$8=H31,1,0) -> 0 | Q31: DriveNets | R31: =$P31*K31 -> 0 | S31: =$P31*L31 -> 0 | T31: =$P31*M31 -> 0 | U31: =$P31*N31 -> 0
F32: Esyasoft Holding | G32: Equity | H32: =VLOOKUP(F32,'5. Geo'!$B$3:$F$26,5,0) -> Rest of Asia | I32: =VLOOKUP(F32,'5. Geo'!$B$3:$F$26,2,0) -> 2020 | J32: 44691 | K32: ='CF (Equity, Debt)'!E28 -> 0 | L32: ='CF (Equity, Debt)'!F28 -> 5 | N32: =SUM(K32:M32) -> 5 | P32: =IF($C$8=H32,1,0) -> 0 | Q32: Esyasoft Holding | R32: =$P32*K32 -> 0 | S32: =$P32*L32 -> 0 | T32: =$P32*M32 -> 0 | U32: =$P32*N32 -> 0
F33: vTv Therapeutics Inc. | G33: Equity | H33: =VLOOKUP(F33,'5. Geo'!$B$3:$F$26,5,0) -> USA | I33: =VLOOKUP(F33,'5. Geo'!$B$3:$F$26,2,0) -> 2022 | J33: 44712 | K33: ='CF (Equity, Debt)'!E29 -> -12.5 | L33: ='CF (Equity, Debt)'!F29 -> 0 | N33: =SUM(K33:M33) -> -12.5 | P33: =IF($C$8=H33,1,0) -> 0 | Q33: vTv Therapeutics Inc. | R33: =$P33*K33 -> 0 | S33: =$P33*L33 -> 0 | T33: =$P33*M33 -> 0 | U33: =$P33*N33 -> 0
