Workbook
Name Company: [1]UEL!$B$18:$B$20
Name Dates: [1]ONT!$N$2:$AN$2
Name DetailedCapShares: '[2]Current Cap'!$T$133
Name FAGroup: [1]UEL!$B$3:$B$15
Name IQ_CH: 110000
Name IQ_CQ: 5000
Name IQ_CY: 10000
Name IQ_DAILY: 500000
Name IQ_FH: 100000
Name IQ_FQ: 500
Name IQ_FY: 1000
Name IQ_LTM: 2000
Name IQ_MONTH: 15000
Name IQ_NTM: 6000
Name IQ_WEEK: 50000
Name IQ_YTD: 3000

Sheet D
C2: Date of NAV | D2: 45138
H3: D A S H B O A R D | L3: figures in USD Millions
D6: # Investments | E6: Committed | F6: Invested | G6: Remaining | H6: Distributions | I6: Residual Value | J6: IRR | K6: TVPI | L6: RPI | M6: DPI
C8: EQUITY | D8: =COUNTIF('S | 01 '!C10:C30,"*") -> 19 | E8: ='1. IRR Equity'!AE33 -> 2108.0362 | F8: ='1. IRR Equity'!AF33 -> 2100.533 | G8: ='1. IRR Equity'!AG33 -> 7.5031614 | H8: ='1. IRR Equity'!AH33 -> 12.820776 | I8: ='1. IRR Equity'!AI33 -> 2118.5933 | J8: ='1. IRR Equity'!AJ33 -> 0.0092234105 | K8: ='1. IRR Equity'!AK33 -> 1.0147015 | L8: ='1. IRR Equity'!AL33 -> 1.008598 | M8: ='1. IRR Equity'!AM33 -> 0.0061035822
C11: DEBT | D11: =COUNTIF('S | 01 '!C33:C35,"*") -> 3 | E11: ='2. IRR Debt'!Q12 -> 10.765747 | F11: ='2. IRR Debt'!R12 -> 10.765747 | G11: ='2. IRR Debt'!S12 -> 0 | H11: ='2. IRR Debt'!T12 -> 0.47078465 | I11: ='2. IRR Debt'!U12 -> 2.353982 | J11: ='2. IRR Debt'!V12 -> -0.32476586 | K11: ='2. IRR Debt'!W12 -> 0.26238464 | L11: ='2. IRR Debt'!X12 -> 0.21865478 | M11: ='2. IRR Debt'!Y12 -> 0.043729864
C14: FUNDS | D14: =COUNTIF('S | 01 '!C39:C43,"*") -> 5 | E14: ='3. IRR Funds'!Q15 -> 398.15519 | F14: ='3. IRR Funds'!R15 -> 131.73842 | G14: ='3. IRR Funds'!S15 -> 267.44473 | H14: ='3. IRR Funds'!T15 -> 4.4275637 | I14: ='3. IRR Funds'!U15 -> 130.91493 | J14: ='3. IRR Funds'!V15 -> 0.010083666 | K14: ='3. IRR Funds'!W15 -> 1.0273578 | L14: ='3. IRR Funds'!X15 -> 0.99374909 | M14: ='3. IRR Funds'!Y15 -> 0.033608751
C17: TOTAL | D17: =D8+D11+D14 -> 27 | E17: =E8+E11+E14 -> 2516.9571 | F17: =F8+F11+F14 -> 2243.0372 | G17: =G8+G11+G14 -> 274.9479 | H17: =H8+H11+H14 -> 17.719124 | I17: =I8+I11+I14 -> 2251.8623 | J17: ='4.All'!N9 -> 0.007097432 | K17: =(H17+I17)/F17 -> 1.011834 | L17: =I17/F17 -> 1.0039344 | M17: =H17/F17 -> 0.0078996124
E19: =E17='S | 01 '!J46 -> TRUE | F19: =F17='S | 01 '!K46 -> TRUE | G19: =ROUND(G17,1)=ROUND('S | 01 '!L46,1) -> TRUE | H19: =ROUND(H17,1)=ROUND('S | 01 '!M46,1) -> TRUE | I19: =ROUND(I17,1)=ROUND('S | 01 '!N46,1) -> TRUE

Sheet S | 01 
C2: As of date | D2: =D!D2 -> 45138
C6: Deals | D6: Status | E6: Lead | F6: Investing Entity | G6: Vintageἀ | H6: Instrument | I6: % | J6: Committed | K6: Invested | L6: Remaining Commitment | M6: Distributions | N6: Carrying Value | O6: Gain | P6: TVPI | Q6: IRRβ | R6: Additonal Upside
G7: # | I7: % | J7: $,m | K7: $,m | L7: $,m | M7: $,m | N7: $,m | O7: $,m | P7: X | Q7: %
C9: Direct Investments
C10: Jollychic Holding Limited | D10: In Liquidation | E10: Elaine | F10: Mozn | G10: 2019 | H10: C+ Prefs | I10: ='6. %'!F9 -> 0.056999998 | J10: 65 | K10: =-SUMIF('CF (Equity, Debt)'!$C$3:$K$40,'S | 01 '!C10,'CF (Equity, Debt)'!$E$3:$E$40) -> 65 | L10: 0 | M10: =SUMIF('CF (Equity, Debt)'!$C$3:$K$40,'S | 01 '!C10,'CF (Equity, Debt)'!$F$3:$F$40) -> 0 | N10: =VLOOKUP(C10,NAV!$B$4:$E$44,4,0) -> 0 | O10: =N10+M10-K10 -> -65 | P10: =(M10+N10)/K10 -> 0 | Q10: =VLOOKUP(C10,'1. IRR Equity'!$AD$12:$AM$30,7,0) -> NM
C11: Mena Mobile Inc | D11: Unrealized | E11: Elaine | F11: Mozn | G11: 2019 | H11: B Prefs | I11: ='6. %'!F10 -> 0.14 | J11: 8 | K11: =-SUMIF('CF (Equity, Debt)'!$C$3:$K$40,'S | 01 '!C11,'CF (Equity, Debt)'!$E$3:$E$40) -> 8 | L11: 0 | M11: =SUMIF('CF (Equity, Debt)'!$C$3:$K$40,'S | 01 '!C11,'CF (Equity, Debt)'!$F$3:$F$40) -> 0 | N11: =VLOOKUP(C11,NAV!$B$4:$E$44,4,0) -> 0 | O11: =N11+M11-K11 -> -8 | P11: =(M11+N11)/K11 -> 0 | Q11: =VLOOKUP(C11,'1. IRR Equity'!$AD$12:$AM$30,7,0) -> NM
C12: Flyr Inc | D12: Unrealized | E12: Sushil | F12: Mozn | G12: 2019 | H12: B-1,2 Prefs | I12: ='6. %'!F11 -> 0.085025485 | J12: 10 | K12: =-SUMIF('CF (Equity, Debt)'!$C$3:$K$40,'S | 01 '!C12,'CF (Equity, Debt)'!$E$3:$E$40) -> 10 | L12: 0 | M12: =SUMIF('CF (Equity, Debt)'!$C$3:$K$40,'S | 01 '!C12,'CF (Equity, Debt)'!$F$3:$F$40) -> 0 | N12: =VLOOKUP(C12,NAV!$B$4:$E$44,4,0) -> 78.08223 | O12: =N12+M12-K12 -> 68.08223 | P12: =(M12+N12)/K12 -> 7.808223 | Q12: =VLOOKUP(C12,'1. IRR Equity'!$AD$12:$AM$30,7,0) -> 0.69797844 | R12: Flyr Warrantsa
C13: Esyasoft Holding | D13: Realized | E13: Sushil | F13: Mozn | G13: 2020 | H13: Convertible Note | I13: ='6. %'!F12 -> n/a | J13: 2.5 | K13: =-SUMIF('CF (Equity, Debt)'!$C$3:$K$40,'S | 01 '!C13,'CF (Equity, Debt)'!$E$3:$E$40) -> 2.5 | L13: 0 | M13: =SUMIF('CF (Equity, Debt)'!$C$3:$K$40,'S | 01 '!C13,'CF (Equity, Debt)'!$F$3:$F$40) -> 5 | N13: =VLOOKUP(C13,NAV!$B$4:$E$44,4,0) -> 0 | O13: =N13+M13-K13 -> 2.5 | P13: =(M13+N13)/K13 -> 2 | Q13: =VLOOKUP(C13,'1. IRR Equity'!$AD$12:$AM$30,7,0) -> 0.36091766
C14: Beyond Limits | D14: Unrealized | E14: Divyesh | F14: Mozn | G14: 2020 | H14: C Prefs | I14: ='6. %'!F13 -> 0.097965107 | J14: 90 | K14: =-SUMIF('CF (Equity, Debt)'!$C$3:$K$40,'S | 01 '!C14,'CF (Equity, Debt)'!$E$3:$E$40) -> 90 | L14: 0 | M14: =SUMIF('CF (Equity, Debt)'!$C$3:$K$40,'S | 01 '!C14,'CF (Equity, Debt)'!$F$3:$F$40) -> 0 | N14: =VLOOKUP(C14,NAV!$B$4:$E$44,4,0) -> 91.00154 | O14: =N14+M14-K14 -> 1.0015403 | P14: =(M14+N14)/K14 -> 1.0111282 | Q14: =VLOOKUP(C14,'1. IRR Equity'!$AD$12:$AM$30,7,0) -> 0.0034190029
C15: ONT plc | D15: Unrealized | E15: Divyesh | F15: Mozn | G15: 2020 | H15: Ordinary Shares | I15: ='6. %'!F14 -> 0.053583931 | J15: 141.47026 | K15: =-SUMIF('CF (Equity, Debt)'!$C$3:$K$40,'S | 01 '!C15,'CF (Equity, Debt)'!$E$3:$E$40) -> 141.47026 | L15: 0 | M15: =SUMIF('CF (Equity, Debt)'!$C$3:$K$40,'S | 01 '!C15,'CF (Equity, Debt)'!$F$3:$F$40) -> 0 | N15: =VLOOKUP(C15,NAV!$B$4:$E$44,4,0) -> 150.40044 | O15: =N15+M15-K15 -> 8.9301789 | P15: =(M15+N15)/K15 -> 1.0631241 | Q15: =VLOOKUP(C15,'1. IRR Equity'!$AD$12:$AM$30,7,0) -> 0.019673982
C16: Heygears | D16: Unrealized | E16: Elaine | F16: Mozn | G16: 2020 | H16: Registered Capital | I16: ='6. %'!F15 -> 0.1438 | J16: 60 | K16: =-SUMIF('CF (Equity, Debt)'!$C$3:$K$40,'S | 01 '!C16,'CF (Equity, Debt)'!$E$3:$E$40) -> 60 | L16: 0 | M16: =SUMIF('CF (Equity, Debt)'!$C$3:$K$40,'S | 01 '!C16,'CF (Equity, Debt)'!$F$3:$F$40) -> 0 | N16: =VLOOKUP(C16,NAV!$B$4:$E$44,4,0) -> 151.06943 | O16: =N16+M16-K16 -> 91.069434 | P16: =(M16+N16)/K16 -> 2.5178239 | Q16: =VLOOKUP(C16,'1. IRR Equity'!$AD$12:$AM$30,7,0) -> 0.41446041
C17: Jysan Technologies | D17: Unrealized | E17: Sushil | F17: Mozn 1 | G17: 2021 | H17: A (Ordinary Shares) | I17: ='6. %'!F16 -> 0.03 | J17: 20 | K17: =-SUMIF('CF (Equity, Debt)'!$C$3:$K$40,'S | 01 '!C17,'CF (Equity, Debt)'!$E$3:$E$40) -> 20 | L17: 0 | M17: =SUMIF('CF (Equity, Debt)'!$C$3:$K$40,'S | 01 '!C17,'CF (Equity, Debt)'!$F$3:$F$40) -> 0 | N17: =VLOOKUP(C17,NAV!$B$4:$E$44,4,0) -> 20 | O17: =N17+M17-K17 -> 0 | P17: =(M17+N17)/K17 -> 1 | Q17: =VLOOKUP(C17,'1. IRR Equity'!$AD$12:$AM$30,7,0) -> 2.9802322e-09
C18: Cerebras Systems Inc | D18: Unrealized | E18: Ignasi | F18: Mozn | G18: 2021 | H18: F Prefs | I18: ='6. %'!F17 -> 0.0094767871 | J18: 40 | K18: =-SUMIF('CF (Equity, Debt)'!$C$3:$K$40,'S | 01 '!C18,'CF (Equity, Debt)'!$E$3:$E$40) -> 39.999983 | L18: 0 | M18: =SUMIF('CF (Equity, Debt)'!$C$3:$K$40,'S | 01 '!C18,'CF (Equity, Debt)'!$F$3:$F$40) -> 0 | N18: =VLOOKUP(C18,NAV!$B$4:$E$44,4,0) -> 39.999983 | O18: =N18+M18-K18 -> 0 | P18: =(M18+N18)/K18 -> 1 | Q18: =VLOOKUP(C18,'1. IRR Equity'!$AD$12:$AM$30,7,0) -> 2.9802322e-09
C19: Endless Studios LLC | D19: Unrealized | E19: Sushil | F19: Mozn | G19: 2021 | H19: A Pref Units | I19: ='6. %'!F18 -> 0.077419355 | J19: 3 | K19: =-SUMIF('CF (Equity, Debt)'!$C$3:$K$40,'S | 01 '!C19,'CF (Equity, Debt)'!$E$3:$E$40) -> 3 | L19: 0 | M19: =SUMIF('CF (Equity, Debt)'!$C$3:$K$40,'S | 01 '!C19,'CF (Equity, Debt)'!$F$3:$F$40) -> 0 | N19: =VLOOKUP(C19,NAV!$B$4:$E$44,4,0) -> 3 | O19: =N19+M19-K19 -> 0 | P19: =(M19+N19)/K19 -> 1 | Q19: =VLOOKUP(C19,'1. IRR Equity'!$AD$12:$AM$30,7,0) -> 2.9802322e-09
C20: Instadeep Limited | D20: Realized | E20: Ignasi | F20: Mozn | G20: 2021 | H20: B Prefs | I20: ='6. %'!F19 -> 0.011489406 | J20: 5.0278212 | K20: =-SUMIF('CF (Equity, Debt)'!$C$3:$K$40,'S | 01 '!C20,'CF (Equity, Debt)'!$E$3:$E$40) -> 5.0237202 | L20: 0 | M20: =SUMIF('CF (Equity, Debt)'!$C$3:$K$40,'S | 01 '!C20,'CF (Equity, Debt)'!$F$3:$F$40) -> 7.8207761 | N20: =VLOOKUP(C20,NAV!$B$4:$E$44,4,0) -> 0 | O20: =N20+M20-K20 -> 2.7970559 | P20: =(M20+N20)/K20 -> 1.5567698 | Q20: =VLOOKUP(C20,'1. IRR Equity'!$AD$12:$AM$30,7,0) -> 0.3162033
C21: X-fusion | D21: Unrealized | E21: Elaine | F21: Mozn 2 | G21: 2022 | H21: Equity-TBC | I21: ='6. %'!F20 -> 0.051 | J21: 493.5 | K21: =-SUMIF('CF (Equity, Debt)'!$C$3:$K$40,'S | 01 '!C21,'CF (Equity, Debt)'!$E$3:$E$40) -> 493.50096 | L21: 0 | M21: =SUMIF('CF (Equity, Debt)'!$C$3:$K$40,'S | 01 '!C21,'CF (Equity, Debt)'!$F$3:$F$40) -> 0 | N21: =VLOOKUP(C21,NAV!$B$4:$E$44,4,0) -> 408.28799 | O21: =N21+M21-K21 -> -85.212962 | P21: =(M21+N21)/K21 -> 0.82732969 | Q21: =VLOOKUP(C21,'1. IRR Equity'!$AD$12:$AM$30,7,0) -> -0.11544542
C22: DriveNets | D22: Unrealized | E22: Anton | F22: G42 | G22: 2022 | H22: Equity-TBC | I22: ='6. %'!F21 -> 0.11141914 | J22: 300 | K22: =-SUMIF('CF (Equity, Debt)'!$C$3:$K$40,'S | 01 '!C22,'CF (Equity, Debt)'!$E$3:$E$40) -> 300 | L22: =0 -> 0 | M22: =SUMIF('CF (Equity, Debt)'!$C$3:$K$40,'S | 01 '!C22,'CF (Equity, Debt)'!$F$3:$F$40) -> 0 | N22: =VLOOKUP(C22,NAV!$B$4:$E$44,4,0) -> 300 | O22: =N22+M22-K22 -> 0 | P22: =(M22+N22)/K22 -> 1 | Q22: =VLOOKUP(C22,'1. IRR Equity'!$AD$12:$AM$30,7,0) -> 2.9802322e-09 | R22: DN Warrants b
C23: vTv Therapeutics Inc. | D23: Unrealized | E23: Divyesh | F23: G42 | G23: 2022 | H23: Ordinary Shares | I23: ='6. %'!F22 -> 0.099316564 | J23: =K23 -> 24.53125 | K23: =-SUMIF('CF (Equity, Debt)'!$C$3:$K$40,'S | 01 '!C23,'CF (Equity, Debt)'!$E$3:$E$40) -> 24.53125 | L23: =J23-K23 -> 0 | M23: =SUMIF('CF (Equity, Debt)'!$C$3:$K$40,'S | 01 '!C23,'CF (Equity, Debt)'!$F$3:$F$40) -> 0 | N23: =VLOOKUP(C23,NAV!$B$4:$E$44,4,0) -> 7.0626663 | O23: =N23+M23-K23 -> -17.468584 | P23: =(M23+N23)/K23 -> 0.28790487 | Q23: =VLOOKUP(C23,'1. IRR Equity'!$AD$12:$AM$30,7,0) -> NM | R23: vTv $30m milestn payment c
C24: Honor Device Co Ltd | D24: Unrealized | E24: Elaine | F24: G42 3 | G24: 2022 | H24: Equity-TBC | I24: ='6. %'!F23 -> 0.018823528 | J24: =K24 -> 800 | K24: =-SUMIF('CF (Equity, Debt)'!$C$3:$K$40,'S | 01 '!C24,'CF (Equity, Debt)'!$E$3:$E$40) -> 800 | L24: =J24-K24 -> 0 | M24: =SUMIF('CF (Equity, Debt)'!$C$3:$K$40,'S | 01 '!C24,'CF (Equity, Debt)'!$F$3:$F$40) -> 0 | N24: =VLOOKUP(C24,NAV!$B$4:$E$44,4,0) -> 817.18905 | O24: =N24+M24-K24 -> 17.18905 | P24: =(M24+N24)/K24 -> 1.0214863 | Q24: =VLOOKUP(C24,'1. IRR Equity'!$AD$12:$AM$30,7,0) -> 0.022479972
C25: Applied AI Corporation Limited | D25: Unrealized | E25: Divyesh | F25: Mozn | G25: 2022 | H25: Convertible Note | I25: ='6. %'!F24 -> n/a | J25: 15 | K25: =-SUMIF('CF (Equity, Debt)'!$C$3:$K$40,'S | 01 '!C25,'CF (Equity, Debt)'!$E$3:$E$40) -> 7.5 | L25: =J25-K25 -> 7.5 | M25: 0 | N25: =VLOOKUP(C25,NAV!$B$4:$E$44,4,0) -> 7.5 | O25: =N25+M25-K25 -> 0 | P25: =(M25+N25)/K25 -> 1 | Q25: =VLOOKUP(C25,'1. IRR Equity'!$AD$12:$AM$30,7,0) -> NM
C26: eSpace | D26: Unrealized | E26: Anton | F26: Mozn 4 | G26: 2022 | H26: SAFE note | I26: ='6. %'!F25 -> n/a | J26: 15 | K26: =-SUMIF('CF (Equity, Debt)'!$C$3:$K$40,'S | 01 '!C26,'CF (Equity, Debt)'!$E$3:$E$40) -> 15 | L26: =J26-K26 -> 0 | M26: 0 | N26: =VLOOKUP(C26,NAV!$B$4:$E$44,4,0) -> 15 | O26: =N26+M26-K26 -> 0 | P26: =(M26+N26)/K26 -> 1 | Q26: =VLOOKUP(C26,'1. IRR Equity'!$AD$12:$AM$30,7,0) -> NM
C27: Tools for Humanity Corporation | D27: Unrealized | E27: Divyesh | F27: Mozn | G27: 2023 | H27: C Prefs | I27: ='6. %'!F26 -> 0.0062621983 | J27: =K27 -> 14.999999 | K27: =-SUMIF('CF (Equity, Debt)'!$C$3:$K$40,'S | 01 '!C27,'CF (Equity, Debt)'!$E$3:$E$40) -> 14.999999 | L27: =J27-K27 -> 0 | M27: =M26 -> 0 | N27: =VLOOKUP(C27,NAV!$B$4:$E$44,4,0) -> 14.999999 | O27: =N27+M27-K27 -> 0 | P27: =(M27+N27)/K27 -> 1 | Q27: =VLOOKUP(C27,'1. IRR Equity'!$AD$12:$AM$30,7,0) -> NM | R27: Token Warrants d
C28: WLD Tokens | D28: Unrealized | E28: Divyesh | F28: Mozn | G28: 2023 | H28: Tokens | I28: ='6. %'!F27 -> 0.00625 | J28: =K28 -> 0.006875 | K28: =-SUMIF('CF (Equity, Debt)'!$C$3:$K$40,'S | 01 '!C28,'CF (Equity, Debt)'!$E$3:$E$40) -> 0.006875 | L28: =J28-K28 -> 0 | M28: =M27 -> 0 | N28: =VLOOKUP(C28,NAV!$B$4:$E$44,4,0) -> 15 | O28: =N28+M28-K28 -> 14.993125 | P28: NM | Q28: =VLOOKUP(C28,'1. IRR Equity'!$AD$12:$AM$30,7,0) -> NM
J30: =SUM(J10:J28) -> 2108.0362 | K30: =SUM(K10:K28) -> 2100.533 | L30: =SUM(L10:L28) -> 7.5 | M30: =SUM(M10:M28) -> 12.820776 | N30: =SUM(N10:N28) -> 2118.5933 | O30: =SUM(O10:O28) -> 30.88107 | P30: =(M30+N30)/K30 -> 1.0147015 | Q30: ='1. IRR Equity'!AE38 -> 0.0092234105
C32: Debt Investments
C33: Glass Earth Holdings LLC | D33: In default | E33: Marty | F33: Mozn | G33: 2019 | H33: Promissory Note | I33: n/a | J33: 8 | K33: 8 | L33: 0 | M33: 0 | N33: 0 | O33: =N33+M33-K33 -> -8 | P33: =(M33+N33)/K33 -> 0 | Q33: =VLOOKUP(C33,'2. IRR Debt'!$P$9:$Y$11,7,0) -> NM
C34: Mena Mobile Inc (Debt) | D34: Unrealized | E34: Elaine | F34: Mozn | G34: 2021 | H34: Loan | I34: n/a | J34: 2.353982 | K34: =J34 -> 2.353982 | L34: 0 | M34: 0 | N34: =K34 -> 2.353982 | O34: =N34+M34-K34 -> 0 | P34: =(M34+N34)/K34 -> 1 | Q34: =VLOOKUP(C34,'2. IRR Debt'!$P$9:$Y$11,7,0) -> 2.9802322e-09
C35: Esyasoft Holding (Debt) | D35: Realized | E35: Sushil | F35: Mozn | G35: 2021 | H35: Loan | I35: n/a | J35: 0.411765 | K35: 0.411765 | L35: 0 | M35: ='CF (Equity, Debt)'!F45 -> 0.47078465 | N35: 0 | O35: =N35+M35-K35 -> 0.05901965 | P35: =(M35+N35)/K35 -> 1.1433333 | Q35: =VLOOKUP(C35,'2. IRR Debt'!$P$9:$Y$11,7,0) -> 0.075277027
J36: =SUM(J33:J35) -> 10.765747 | K36: =SUM(K33:K35) -> 10.765747 | L36: =SUM(L33:L35) -> 0 | M36: =SUM(M33:M35) -> 0.47078465 | N36: =SUM(N33:N35) -> 2.353982 | O36: =N36+M36-K36 -> -7.9409804 | P36: =(M36+N36)/K36 -> 0.26238464 | Q36: ='2. IRR Debt'!Q15 -> -0.32476586
C38: Funds Investments
C39: New Space Capital Fund I | D39: Unrealized | E39: Sushil | F39: G42 | G39: 2020 | H39: LP | I39: n/a | J39: =K39+L39 -> 28.336808 | K39: =-SUM('CF (Funds)'!D32:D38) -> 11.058035 | L39: =NAV!K49 -> 17.278774 | M39: =SUM('CF (Funds)'!E32:E38) -> 2.9557744 | N39: =VLOOKUP(C39,NAV!$B$4:$E$44,4,0) -> 13.390399 | O39: =N39+M39-K39 -> 5.2881388 | P39: 1.4784783 | Q39: =VLOOKUP(C39,'3. IRR Funds'!$P$7:$Y$15,7,0) -> 0.08799049
C40: New Space Capital GP Com SCSp | D40: Unrealized | E40: Sushil | F40: G42 | G40: 2023 | H40: LP | I40: n/a | J40: =2.3/0.85 -> 2.7058824 | K40: 2.7058824 | L40: 0 | M40: 0 | N40: =VLOOKUP(C40,NAV!$B$4:$E$44,4,0) -> 3.276608 | O40: =N40+M40-K40 -> 0.57072563 | P40: 1 | Q40: =VLOOKUP(C40,'3. IRR Funds'!$P$7:$Y$15,7,0) -> 0
C41: North Summit Capital Fund | D41: Unrealized | E41: Elaine | F41: G42 | G41: 2020 | H41: LP | I41: n/a | J41: 300 | K41: 83.214653 | L41: 217.81331 | M41: 1.027961 | N41: =VLOOKUP(C41,NAV!$B$4:$E$44,4,0) -> 81.695786 | O41: =N41+M41-K41 -> -0.490906 | P41: 0.96555063 | Q41: =VLOOKUP(C41,'3. IRR Funds'!$P$7:$Y$15,7,0) -> -0.0021562932
C42: Sinovation Disrupt Fund, L.P. | D42: Unrealized | E42: Elaine | F42: G42 | G42: 2020 | H42: LP | I42: n/a | J42: 50 | K42: =-SUM('CF (Funds)'!D3:D17) -> 20.74471 | L42: =J42-K42 -> 29.25529 | M42: 0.44382835 | N42: =VLOOKUP(C42,NAV!$B$4:$E$44,4,0) -> 19.244515 | O42: =N42+M42-K42 -> -1.0563667 | P42: 0.97193724 | Q42: =VLOOKUP(C42,'3. IRR Funds'!$P$7:$Y$15,7,0) -> -0.023361704
C43: Acies Investments Fund I, L.P. | D43: Unrealized | E43: Divyesh | F43: G42 | G43: 2021 | H43: LP | I43: 0.33 | J43: 17.1125 | K43: 14.015137 | L43: =J43-K43 -> 3.0973625 | M43: 0 | N43: =VLOOKUP(C43,NAV!$B$4:$E$44,4,0) -> 13.307625 | O43: =N43+M43-K43 -> -0.7075125 | P43: 0.97333028 | Q43: =VLOOKUP(C43,'3. IRR Funds'!$P$7:$Y$15,7,0) -> -0.04112356 | R43: 9.9% GP | Anchor e
J44: =SUM(J39:J43) -> 398.15519 | K44: =SUM(K39:K43) -> 131.73842 | L44: =SUM(L39:L43) -> 267.44473 | M44: =SUM(M39:M43) -> 4.4275637 | N44: =SUM(N39:N43) -> 130.91493 | O44: =N44+M44-K44 -> 3.6040793 | P44: =(M44+N44)/K44 -> 1.0273578 | Q44: ='3. IRR Funds'!Q18 -> 0.010083666
C46: Total | J46: =J30+J36+J44 -> 2516.9571 | K46: =K30+K36+K44 -> 2243.0372 | L46: =L30+L36+L44 -> 274.94473 | M46: =M30+M36+M44 -> 17.719124 | N46: =N30+N36+N44 -> 2251.8623 | O46: =N46+M46-K46 -> 26.544169 | P46: =(M46+N46)/K46 -> 1.011834 | Q46: ='4.All'!N9 -> 0.007097432
K47: =ROUND(K46,2)=ROUND('4.All'!J9,2) -> TRUE | M47: =ROUND(M46,2)=ROUND('4.All'!L9,2) -> TRUE | N47: =ROUND(N46,2)=ROUND('4.All'!M9,2) -> TRUE
C49: Additional Upside Section:
C50: a) Flyr: For every $1m of revenue, 194,477 shares, capped at 1,264,1000 (B-1) shares shall be issued to Mozn
C51: b) DriveNets: Share warrants exercisable upon the achievement of target revenue of clients referred by G42, and corresponding milestones
C52: c) vTv Therapeutics: Potential issuance of $30m in additional shares, if FDA approval received for the drug TTP399
C53: d) Tools for Humanity Corporation: Additional token warrants (for 62.5 million Tokens) for a consideration of $5,875.00. Additional provision for c$2K (the warrant price) kept for exercising the warrant rights.
C54: e) Acies Investments Fund I LP: Being the Anchor investor, entitled to 9.9% of the aggregate carried interest earned by the GP
C56: Definition:
C57: ἀ = Vintage corresponds to the year of the first investment made
C58: β = Excludes transaction costs from the estimate of IRR, as those are not available
C59: IRR is referred as NM when it is not meaningful
C61: Investing Entities:
C62: G42 refers to G42 Investments AI Holding RSC Ltd
... C72: TBC = to be confirmed

Sheet S | 02
C2: As of date | E2: =D!D2 -> 45138
E5: 2 | F5: 3 | G5: 4 | H5: 5 | I5: 6 | J5: 7 | K5: 8 | L5: 9 | M5: 11 | N5: 12 | O5: 13 | Q5: 15 | R5: 14 | S5: 10 | T5: 16
C6: Deals | D6: Type | E6: Status | F6: Lead | G6: Investing Entity | H6: Vintageἀ | I6: Instrument | J6: % | K6: Committed | L6: Invested | M6: Distributions | N6: Carrying Value | O6: Gain | P6: Gain till FY22 | Q6: IRRβ | R6: TVPI | S6: Remaining Commitment | T6: Additonal Upside
I7: # | J7: % | K7: $,m | L7: $,m | M7: $,m | N7: $,m | O7: $,m | Q7: % | R7: X | S7: $,m | W7: MOZN
C9: WLD Tokens | D9: Direct Investment | E9: =VLOOKUP($C9,'S | 01 '!$C$6:$R$46,E$5,0) -> Unrealized | F9: =VLOOKUP($C9,'S | 01 '!$C$6:$R$46,F$5,0) -> Divyesh | G9: =VLOOKUP($C9,'S | 01 '!$C$6:$R$46,G$5,0) -> Mozn | H9: =VLOOKUP($C9,'S | 01 '!$C$6:$R$46,H$5,0) -> 2023 | I9: =VLOOKUP($C9,'S | 01 '!$C$6:$R$46,I$5,0) -> Tokens | J9: =VLOOKUP($C9,'S | 01 '!$C$6:$R$46,J$5,0) -> 0.00625 | K9: =VLOOKUP($C9,'S | 01 '!$C$6:$R$46,K$5,0) -> 0.006875 | L9: =VLOOKUP($C9,'S | 01 '!$C$6:$R$46,L$5,0) -> 0.006875 | ... O9: =VLOOKUP($C9,'S | 01 '!$C$6:$R$46,O$5,0) -> 14.993125 | P9: n/a | Q9: =VLOOKUP($C9,'S | 01 '!$C$6:$R$46,Q$5,0) -> NM | R9: =VLOOKUP($C9,'S | 01 '!$C$6:$R$46,R$5,0) -> NM | S9: =VLOOKUP($C9,'S | 01 '!$C$6:$R$46,S$5,0) -> 0
C10: Tools for Humanity Corporation | D10: Direct Investment | E10: =VLOOKUP($C10,'S | 01 '!$C$6:$R$46,E$5,0) -> Unrealized | F10: =VLOOKUP($C10,'S | 01 '!$C$6:$R$46,F$5,0) -> Divyesh | G10: =VLOOKUP($C10,'S | 01 '!$C$6:$R$46,G$5,0) -> Mozn | H10: =VLOOKUP($C10,'S | 01 '!$C$6:$R$46,H$5,0) -> 2023 | I10: =VLOOKUP($C10,'S | 01 '!$C$6:$R$46,I$5,0) -> C Prefs | J10: =VLOOKUP($C10,'S | 01 '!$C$6:$R$46,J$5,0) -> 0.0062621983 | K10: =VLOOKUP($C10,'S | 01 '!$C$6:$R$46,K$5,0) -> 14.999999 | L10: =VLOOKUP($C10,'S | 01 '!$C$6:$R$46,L$5,0) -> 14.999999 | ... O10: =VLOOKUP($C10,'S | 01 '!$C$6:$R$46,O$5,0) -> 0 | P10: n/a | Q10: =VLOOKUP($C10,'S | 01 '!$C$6:$R$46,Q$5,0) -> NM | R10: =VLOOKUP($C10,'S | 01 '!$C$6:$R$46,R$5,0) -> 1 | S10: =VLOOKUP($C10,'S | 01 '!$C$6:$R$46,S$5,0) -> 0 | T10: Token Warrants d
C11: eSpace | D11: Direct Investment | E11: =VLOOKUP($C11,'S | 01 '!$C$6:$R$46,E$5,0) -> Unrealized | F11: =VLOOKUP($C11,'S | 01 '!$C$6:$R$46,F$5,0) -> Anton | G11: =VLOOKUP($C11,'S | 01 '!$C$6:$R$46,G$5,0) -> Mozn 4 | H11: =VLOOKUP($C11,'S | 01 '!$C$6:$R$46,H$5,0) -> 2022 | I11: =VLOOKUP($C11,'S | 01 '!$C$6:$R$46,I$5,0) -> SAFE note | J11: =VLOOKUP($C11,'S | 01 '!$C$6:$R$46,J$5,0) -> n/a | K11: =VLOOKUP($C11,'S | 01 '!$C$6:$R$46,K$5,0) -> 15 | L11: =VLOOKUP($C11,'S | 01 '!$C$6:$R$46,L$5,0) -> 15 | ... O11: =VLOOKUP($C11,'S | 01 '!$C$6:$R$46,O$5,0) -> 0 | P11: 0 | Q11: =VLOOKUP($C11,'S | 01 '!$C$6:$R$46,Q$5,0) -> NM | R11: =VLOOKUP($C11,'S | 01 '!$C$6:$R$46,R$5,0) -> 1 | S11: =VLOOKUP($C11,'S | 01 '!$C$6:$R$46,S$5,0) -> 0 | W11: Invested | X11: =L29 -> 986.76754
C12: Applied AI Corporation Limited | D12: Direct Investment | E12: =VLOOKUP($C12,'S | 01 '!$C$6:$R$46,E$5,0) -> Unrealized | F12: =VLOOKUP($C12,'S | 01 '!$C$6:$R$46,F$5,0) -> Divyesh | G12: =VLOOKUP($C12,'S | 01 '!$C$6:$R$46,G$5,0) -> Mozn | H12: =VLOOKUP($C12,'S | 01 '!$C$6:$R$46,H$5,0) -> 2022 | I12: =VLOOKUP($C12,'S | 01 '!$C$6:$R$46,I$5,0) -> Convertible Note | J12: =VLOOKUP($C12,'S | 01 '!$C$6:$R$46,J$5,0) -> n/a | K12: =VLOOKUP($C12,'S | 01 '!$C$6:$R$46,K$5,0) -> 15 | L12: =VLOOKUP($C12,'S | 01 '!$C$6:$R$46,L$5,0) -> 7.5 | ... O12: =VLOOKUP($C12,'S | 01 '!$C$6:$R$46,O$5,0) -> 0 | P12: 0 | Q12: =VLOOKUP($C12,'S | 01 '!$C$6:$R$46,Q$5,0) -> NM | R12: =VLOOKUP($C12,'S | 01 '!$C$6:$R$46,R$5,0) -> 1 | S12: =VLOOKUP($C12,'S | 01 '!$C$6:$R$46,S$5,0) -> 7.5 | W12: NAV | X12: =N29 -> 996.6956
C13: X-fusion | D13: Direct Investment | E13: =VLOOKUP($C13,'S | 01 '!$C$6:$R$46,E$5,0) -> Unrealized | F13: =VLOOKUP($C13,'S | 01 '!$C$6:$R$46,F$5,0) -> Elaine | G13: =VLOOKUP($C13,'S | 01 '!$C$6:$R$46,G$5,0) -> Mozn 2 | H13: =VLOOKUP($C13,'S | 01 '!$C$6:$R$46,H$5,0) -> 2022 | I13: =VLOOKUP($C13,'S | 01 '!$C$6:$R$46,I$5,0) -> Equity-TBC | J13: =VLOOKUP($C13,'S | 01 '!$C$6:$R$46,J$5,0) -> 0.051 | K13: =VLOOKUP($C13,'S | 01 '!$C$6:$R$46,K$5,0) -> 493.5 | L13: =VLOOKUP($C13,'S | 01 '!$C$6:$R$46,L$5,0) -> 493.50096 | ... O13: =VLOOKUP($C13,'S | 01 '!$C$6:$R$46,O$5,0) -> -85.212962 | P13: -64.391 | Q13: =VLOOKUP($C13,'S | 01 '!$C$6:$R$46,Q$5,0) -> -0.11544542 | R13: =VLOOKUP($C13,'S | 01 '!$C$6:$R$46,R$5,0) -> 0.82732969 | S13: =VLOOKUP($C13,'S | 01 '!$C$6:$R$46,S$5,0) -> 0 | W13: Gain | X13: =O29 -> 23.219623
C14: Mena Mobile Inc (Debt) | D14: Debt Investment | E14: =VLOOKUP($C14,'S | 01 '!$C$6:$R$46,E$5,0) -> Unrealized | F14: =VLOOKUP($C14,'S | 01 '!$C$6:$R$46,F$5,0) -> Elaine | G14: =VLOOKUP($C14,'S | 01 '!$C$6:$R$46,G$5,0) -> Mozn | H14: =VLOOKUP($C14,'S | 01 '!$C$6:$R$46,H$5,0) -> 2021 | I14: =VLOOKUP($C14,'S | 01 '!$C$6:$R$46,I$5,0) -> Loan | J14: =VLOOKUP($C14,'S | 01 '!$C$6:$R$46,J$5,0) -> n/a | K14: =VLOOKUP($C14,'S | 01 '!$C$6:$R$46,K$5,0) -> 2.353982 | L14: =VLOOKUP($C14,'S | 01 '!$C$6:$R$46,L$5,0) -> 2.353982 | ... O14: =VLOOKUP($C14,'S | 01 '!$C$6:$R$46,O$5,0) -> 0 | P14: 0 | Q14: =VLOOKUP($C14,'S | 01 '!$C$6:$R$46,Q$5,0) -> 2.9802322e-09 | R14: =VLOOKUP($C14,'S | 01 '!$C$6:$R$46,R$5,0) -> 1 | S14: =VLOOKUP($C14,'S | 01 '!$C$6:$R$46,S$5,0) -> 0 | W14: YTD Gains | X14: =X13-P29 -> 8.6824242
C15: Esyasoft Holding (Debt) | D15: Debt Investment | E15: =VLOOKUP($C15,'S | 01 '!$C$6:$R$46,E$5,0) -> Realized | F15: =VLOOKUP($C15,'S | 01 '!$C$6:$R$46,F$5,0) -> Sushil | G15: =VLOOKUP($C15,'S | 01 '!$C$6:$R$46,G$5,0) -> Mozn | H15: =VLOOKUP($C15,'S | 01 '!$C$6:$R$46,H$5,0) -> 2021 | I15: =VLOOKUP($C15,'S | 01 '!$C$6:$R$46,I$5,0) -> Loan | J15: =VLOOKUP($C15,'S | 01 '!$C$6:$R$46,J$5,0) -> n/a | K15: =VLOOKUP($C15,'S | 01 '!$C$6:$R$46,K$5,0) -> 0.411765 | L15: =VLOOKUP($C15,'S | 01 '!$C$6:$R$46,L$5,0) -> 0.411765 | ... O15: =VLOOKUP($C15,'S | 01 '!$C$6:$R$46,O$5,0) -> 0.05901965 | P15: 0.05901965 | Q15: =VLOOKUP($C15,'S | 01 '!$C$6:$R$46,Q$5,0) -> 0.075277027 | R15: =VLOOKUP($C15,'S | 01 '!$C$6:$R$46,R$5,0) -> 1.1433333 | S15: =VLOOKUP($C15,'S | 01 '!$C$6:$R$46,S$5,0) -> 0 | W15: IRR | X15: =Q29 -> 0.010515186
C16: Jysan Technologies | D16: Direct Investment | E16: =VLOOKUP($C16,'S | 01 '!$C$6:$R$46,E$5,0) -> Unrealized | F16: =VLOOKUP($C16,'S | 01 '!$C$6:$R$46,F$5,0) -> Sushil | G16: =VLOOKUP($C16,'S | 01 '!$C$6:$R$46,G$5,0) -> Mozn 1 | H16: =VLOOKUP($C16,'S | 01 '!$C$6:$R$46,H$5,0) -> 2021 | I16: =VLOOKUP($C16,'S | 01 '!$C$6:$R$46,I$5,0) -> A (Ordinary Shares) | J16: =VLOOKUP($C16,'S | 01 '!$C$6:$R$46,J$5,0) -> 0.03 | K16: =VLOOKUP($C16,'S | 01 '!$C$6:$R$46,K$5,0) -> 20 | L16: =VLOOKUP($C16,'S | 01 '!$C$6:$R$46,L$5,0) -> 20 | ... O16: =VLOOKUP($C16,'S | 01 '!$C$6:$R$46,O$5,0) -> 0 | P16: 0 | Q16: =VLOOKUP($C16,'S | 01 '!$C$6:$R$46,Q$5,0) -> 2.9802322e-09 | R16: =VLOOKUP($C16,'S | 01 '!$C$6:$R$46,R$5,0) -> 1 | S16: =VLOOKUP($C16,'S | 01 '!$C$6:$R$46,S$5,0) -> 0
C17: Instadeep Limited | D17: Direct Investment | E17: =VLOOKUP($C17,'S | 01 '!$C$6:$R$46,E$5,0) -> Realized | F17: =VLOOKUP($C17,'S | 01 '!$C$6:$R$46,F$5,0) -> Ignasi | G17: =VLOOKUP($C17,'S | 01 '!$C$6:$R$46,G$5,0) -> Mozn | H17: =VLOOKUP($C17,'S | 01 '!$C$6:$R$46,H$5,0) -> 2021 | I17: =VLOOKUP($C17,'S | 01 '!$C$6:$R$46,I$5,0) -> B Prefs | J17: =VLOOKUP($C17,'S | 01 '!$C$6:$R$46,J$5,0) -> 0.011489406 | K17: =VLOOKUP($C17,'S | 01 '!$C$6:$R$46,K$5,0) -> 5.0278212 | L17: =VLOOKUP($C17,'S | 01 '!$C$6:$R$46,L$5,0) -> 5.0237202 | ... O17: =VLOOKUP($C17,'S | 01 '!$C$6:$R$46,O$5,0) -> 2.7970559 | P17: 1.6721788 | Q17: =VLOOKUP($C17,'S | 01 '!$C$6:$R$46,Q$5,0) -> 0.3162033 | R17: =VLOOKUP($C17,'S | 01 '!$C$6:$R$46,R$5,0) -> 1.5567698 | S17: =VLOOKUP($C17,'S | 01 '!$C$6:$R$46,S$5,0) -> 0
C18: Cerebras Systems Inc | D18: Direct Investment | E18: =VLOOKUP($C18,'S | 01 '!$C$6:$R$46,E$5,0) -> Unrealized | F18: =VLOOKUP($C18,'S | 01 '!$C$6:$R$46,F$5,0) -> Ignasi | G18: =VLOOKUP($C18,'S | 01 '!$C$6:$R$46,G$5,0) -> Mozn | H18: =VLOOKUP($C18,'S | 01 '!$C$6:$R$46,H$5,0) -> 2021 | I18: =VLOOKUP($C18,'S | 01 '!$C$6:$R$46,I$5,0) -> F Prefs | J18: =VLOOKUP($C18,'S | 01 '!$C$6:$R$46,J$5,0) -> 0.0094767871 | K18: =VLOOKUP($C18,'S | 01 '!$C$6:$R$46,K$5,0) -> 40 | L18: =VLOOKUP($C18,'S | 01 '!$C$6:$R$46,L$5,0) -> 39.999983 | ... O18: =VLOOKUP($C18,'S | 01 '!$C$6:$R$46,O$5,0) -> 0 | P18: 0 | Q18: =VLOOKUP($C18,'S | 01 '!$C$6:$R$46,Q$5,0) -> 2.9802322e-09 | R18: =VLOOKUP($C18,'S | 01 '!$C$6:$R$46,R$5,0) -> 1 | S18: =VLOOKUP($C18,'S | 01 '!$C$6:$R$46,S$5,0) -> 0
C19: Endless Studios LLC | D19: Direct Investment | E19: =VLOOKUP($C19,'S | 01 '!$C$6:$R$46,E$5,0) -> Unrealized | F19: =VLOOKUP($C19,'S | 01 '!$C$6:$R$46,F$5,0) -> Sushil | G19: =VLOOKUP($C19,'S | 01 '!$C$6:$R$46,G$5,0) -> Mozn | H19: =VLOOKUP($C19,'S | 01 '!$C$6:$R$46,H$5,0) -> 2021 | I19: =VLOOKUP($C19,'S | 01 '!$C$6:$R$46,I$5,0) -> A Pref Units | J19: =VLOOKUP($C19,'S | 01 '!$C$6:$R$46,J$5,0) -> 0.077419355 | K19: =VLOOKUP($C19,'S | 01 '!$C$6:$R$46,K$5,0) -> 3 | L19: =VLOOKUP($C19,'S | 01 '!$C$6:$R$46,L$5,0) -> 3 | ... O19: =VLOOKUP($C19,'S | 01 '!$C$6:$R$46,O$5,0) -> 0 | P19: 0 | Q19: =VLOOKUP($C19,'S | 01 '!$C$6:$R$46,Q$5,0) -> 2.9802322e-09 | R19: =VLOOKUP($C19,'S | 01 '!$C$6:$R$46,R$5,0) -> 1 | S19: =VLOOKUP($C19,'S | 01 '!$C$6:$R$46,S$5,0) -> 0
C20: Esyasoft Holding | D20: Direct Investment | E20: =VLOOKUP($C20,'S | 01 '!$C$6:$R$46,E$5,0) -> Realized | F20: =VLOOKUP($C20,'S | 01 '!$C$6:$R$46,F$5,0) -> Sushil | G20: =VLOOKUP($C20,'S | 01 '!$C$6:$R$46,G$5,0) -> Mozn | H20: =VLOOKUP($C20,'S | 01 '!$C$6:$R$46,H$5,0) -> 2020 | I20: =VLOOKUP($C20,'S | 01 '!$C$6:$R$46,I$5,0) -> Convertible Note | J20: =VLOOKUP($C20,'S | 01 '!$C$6:$R$46,J$5,0) -> n/a | K20: =VLOOKUP($C20,'S | 01 '!$C$6:$R$46,K$5,0) -> 2.5 | L20: =VLOOKUP($C20,'S | 01 '!$C$6:$R$46,L$5,0) -> 2.5 | ... O20: =VLOOKUP($C20,'S | 01 '!$C$6:$R$46,O$5,0) -> 2.5 | P20: 2.5 | Q20: =VLOOKUP($C20,'S | 01 '!$C$6:$R$46,Q$5,0) -> 0.36091766 | R20: =VLOOKUP($C20,'S | 01 '!$C$6:$R$46,R$5,0) -> 2 | S20: =VLOOKUP($C20,'S | 01 '!$C$6:$R$46,S$5,0) -> 0
C21: Heygears | D21: Direct Investment | E21: =VLOOKUP($C21,'S | 01 '!$C$6:$R$46,E$5,0) -> Unrealized | F21: =VLOOKUP($C21,'S | 01 '!$C$6:$R$46,F$5,0) -> Elaine | G21: =VLOOKUP($C21,'S | 01 '!$C$6:$R$46,G$5,0) -> Mozn | H21: =VLOOKUP($C21,'S | 01 '!$C$6:$R$46,H$5,0) -> 2020 | I21: =VLOOKUP($C21,'S | 01 '!$C$6:$R$46,I$5,0) -> Registered Capital | J21: =VLOOKUP($C21,'S | 01 '!$C$6:$R$46,J$5,0) -> 0.1438 | K21: =VLOOKUP($C21,'S | 01 '!$C$6:$R$46,K$5,0) -> 60 | L21: =VLOOKUP($C21,'S | 01 '!$C$6:$R$46,L$5,0) -> 60 | ... O21: =VLOOKUP($C21,'S | 01 '!$C$6:$R$46,O$5,0) -> 91.069434 | P21: 96.4 | Q21: =VLOOKUP($C21,'S | 01 '!$C$6:$R$46,Q$5,0) -> 0.41446041 | R21: =VLOOKUP($C21,'S | 01 '!$C$6:$R$46,R$5,0) -> 2.5178239 | S21: =VLOOKUP($C21,'S | 01 '!$C$6:$R$46,S$5,0) -> 0
C22: Beyond Limits | D22: Direct Investment | E22: =VLOOKUP($C22,'S | 01 '!$C$6:$R$46,E$5,0) -> Unrealized | F22: =VLOOKUP($C22,'S | 01 '!$C$6:$R$46,F$5,0) -> Divyesh | G22: =VLOOKUP($C22,'S | 01 '!$C$6:$R$46,G$5,0) -> Mozn | H22: =VLOOKUP($C22,'S | 01 '!$C$6:$R$46,H$5,0) -> 2020 | I22: =VLOOKUP($C22,'S | 01 '!$C$6:$R$46,I$5,0) -> C Prefs | J22: =VLOOKUP($C22,'S | 01 '!$C$6:$R$46,J$5,0) -> 0.097965107 | K22: =VLOOKUP($C22,'S | 01 '!$C$6:$R$46,K$5,0) -> 90 | L22: =VLOOKUP($C22,'S | 01 '!$C$6:$R$46,L$5,0) -> 90 | ... O22: =VLOOKUP($C22,'S | 01 '!$C$6:$R$46,O$5,0) -> 1.0015403 | P22: 1.042 | Q22: =VLOOKUP($C22,'S | 01 '!$C$6:$R$46,Q$5,0) -> 0.0034190029 | R22: =VLOOKUP($C22,'S | 01 '!$C$6:$R$46,R$5,0) -> 1.0111282 | S22: =VLOOKUP($C22,'S | 01 '!$C$6:$R$46,S$5,0) -> 0
C23: ONT plc | D23: Direct Investment | E23: =VLOOKUP($C23,'S | 01 '!$C$6:$R$46,E$5,0) -> Unrealized | F23: =VLOOKUP($C23,'S | 01 '!$C$6:$R$46,F$5,0) -> Divyesh | G23: =VLOOKUP($C23,'S | 01 '!$C$6:$R$46,G$5,0) -> Mozn | H23: =VLOOKUP($C23,'S | 01 '!$C$6:$R$46,H$5,0) -> 2020 | I23: =VLOOKUP($C23,'S | 01 '!$C$6:$R$46,I$5,0) -> Ordinary Shares | J23: =VLOOKUP($C23,'S | 01 '!$C$6:$R$46,J$5,0) -> 0.053583931 | K23: =VLOOKUP($C23,'S | 01 '!$C$6:$R$46,K$5,0) -> 141.47026 | L23: =VLOOKUP($C23,'S | 01 '!$C$6:$R$46,L$5,0) -> 141.47026 | ... O23: =VLOOKUP($C23,'S | 01 '!$C$6:$R$46,O$5,0) -> 8.9301789 | P23: -9.845 | Q23: =VLOOKUP($C23,'S | 01 '!$C$6:$R$46,Q$5,0) -> 0.019673982 | R23: =VLOOKUP($C23,'S | 01 '!$C$6:$R$46,R$5,0) -> 1.0631241 | S23: =VLOOKUP($C23,'S | 01 '!$C$6:$R$46,S$5,0) -> 0
C24: Flyr Inc | D24: Direct Investment | E24: =VLOOKUP($C24,'S | 01 '!$C$6:$R$46,E$5,0) -> Unrealized | F24: =VLOOKUP($C24,'S | 01 '!$C$6:$R$46,F$5,0) -> Sushil | G24: =VLOOKUP($C24,'S | 01 '!$C$6:$R$46,G$5,0) -> Mozn | H24: =VLOOKUP($C24,'S | 01 '!$C$6:$R$46,H$5,0) -> 2019 | I24: =VLOOKUP($C24,'S | 01 '!$C$6:$R$46,I$5,0) -> B-1,2 Prefs | J24: =VLOOKUP($C24,'S | 01 '!$C$6:$R$46,J$5,0) -> 0.085025485 | K24: =VLOOKUP($C24,'S | 01 '!$C$6:$R$46,K$5,0) -> 10 | L24: =VLOOKUP($C24,'S | 01 '!$C$6:$R$46,L$5,0) -> 10 | ... O24: =VLOOKUP($C24,'S | 01 '!$C$6:$R$46,O$5,0) -> 68.08223 | P24: 68.1 | Q24: =VLOOKUP($C24,'S | 01 '!$C$6:$R$46,Q$5,0) -> 0.69797844 | R24: =VLOOKUP($C24,'S | 01 '!$C$6:$R$46,R$5,0) -> 7.808223 | S24: =VLOOKUP($C24,'S | 01 '!$C$6:$R$46,S$5,0) -> 0 | T24: Flyr Warrantsa
C25: Mena Mobile Inc | D25: Direct Investment | E25: =VLOOKUP($C25,'S | 01 '!$C$6:$R$46,E$5,0) -> Unrealized | F25: =VLOOKUP($C25,'S | 01 '!$C$6:$R$46,F$5,0) -> Elaine | G25: =VLOOKUP($C25,'S | 01 '!$C$6:$R$46,G$5,0) -> Mozn | H25: =VLOOKUP($C25,'S | 01 '!$C$6:$R$46,H$5,0) -> 2019 | I25: =VLOOKUP($C25,'S | 01 '!$C$6:$R$46,I$5,0) -> B Prefs | J25: =VLOOKUP($C25,'S | 01 '!$C$6:$R$46,J$5,0) -> 0.14 | K25: =VLOOKUP($C25,'S | 01 '!$C$6:$R$46,K$5,0) -> 8 | L25: =VLOOKUP($C25,'S | 01 '!$C$6:$R$46,L$5,0) -> 8 | ... O25: =VLOOKUP($C25,'S | 01 '!$C$6:$R$46,O$5,0) -> -8 | P25: -8 | Q25: =VLOOKUP($C25,'S | 01 '!$C$6:$R$46,Q$5,0) -> NM | R25: =VLOOKUP($C25,'S | 01 '!$C$6:$R$46,R$5,0) -> 0 | S25: =VLOOKUP($C25,'S | 01 '!$C$6:$R$46,S$5,0) -> 0
C26: Glass Earth Holdings LLC | D26: Debt Investment | E26: =VLOOKUP($C26,'S | 01 '!$C$6:$R$46,E$5,0) -> In default | F26: =VLOOKUP($C26,'S | 01 '!$C$6:$R$46,F$5,0) -> Marty | G26: =VLOOKUP($C26,'S | 01 '!$C$6:$R$46,G$5,0) -> Mozn | H26: =VLOOKUP($C26,'S | 01 '!$C$6:$R$46,H$5,0) -> 2019 | I26: =VLOOKUP($C26,'S | 01 '!$C$6:$R$46,I$5,0) -> Promissory Note | J26: =VLOOKUP($C26,'S | 01 '!$C$6:$R$46,J$5,0) -> n/a | K26: =VLOOKUP($C26,'S | 01 '!$C$6:$R$46,K$5,0) -> 8 | L26: =VLOOKUP($C26,'S | 01 '!$C$6:$R$46,L$5,0) -> 8 | ... O26: =VLOOKUP($C26,'S | 01 '!$C$6:$R$46,O$5,0) -> -8 | P26: -8 | Q26: =VLOOKUP($C26,'S | 01 '!$C$6:$R$46,Q$5,0) -> NM | R26: =VLOOKUP($C26,'S | 01 '!$C$6:$R$46,R$5,0) -> 0 | S26: =VLOOKUP($C26,'S | 01 '!$C$6:$R$46,S$5,0) -> 0
C27: Jollychic Holding Limited | D27: Direct Investment | E27: =VLOOKUP($C27,'S | 01 '!$C$6:$R$46,E$5,0) -> In Liquidation | F27: =VLOOKUP($C27,'S | 01 '!$C$6:$R$46,F$5,0) -> Elaine | G27: =VLOOKUP($C27,'S | 01 '!$C$6:$R$46,G$5,0) -> Mozn | H27: =VLOOKUP($C27,'S | 01 '!$C$6:$R$46,H$5,0) -> 2019 | I27: =VLOOKUP($C27,'S | 01 '!$C$6:$R$46,I$5,0) -> C+ Prefs | J27: =VLOOKUP($C27,'S | 01 '!$C$6:$R$46,J$5,0) -> 0.056999998 | K27: =VLOOKUP($C27,'S | 01 '!$C$6:$R$46,K$5,0) -> 65 | L27: =VLOOKUP($C27,'S | 01 '!$C$6:$R$46,L$5,0) -> 65 | ... O27: =VLOOKUP($C27,'S | 01 '!$C$6:$R$46,O$5,0) -> -65 | P27: -65 | Q27: =VLOOKUP($C27,'S | 01 '!$C$6:$R$46,Q$5,0) -> NM | R27: =VLOOKUP($C27,'S | 01 '!$C$6:$R$46,R$5,0) -> 0 | S27: =VLOOKUP($C27,'S | 01 '!$C$6:$R$46,S$5,0) -> 0
K29: =SUM(K9:K27) -> 994.2707 | L29: =SUM(L9:L27) -> 986.76754 | M29: =SUM(M9:M27) -> 13.291561 | N29: =SUM(N9:N27) -> 996.6956 | O29: =SUM(O9:O27) -> 23.219623 | P29: =SUM(P9:P27) -> 14.537198 | Q29: ='4. Mozn-IRR'!L16 -> 0.010515186 | R29: =(M29+N29)/L29 -> 1.023531 | S29: =SUM(S9:S27) -> 7.5
C31: Honor Device Co Ltd | D31: Direct Investment | E31: =VLOOKUP($C31,'S | 01 '!$C$6:$R$46,E$5,0) -> Unrealized | F31: =VLOOKUP($C31,'S | 01 '!$C$6:$R$46,F$5,0) -> Elaine | G31: =VLOOKUP($C31,'S | 01 '!$C$6:$R$46,G$5,0) -> G42 3 | H31: =VLOOKUP($C31,'S | 01 '!$C$6:$R$46,H$5,0) -> 2022 | I31: =VLOOKUP($C31,'S | 01 '!$C$6:$R$46,I$5,0) -> Equity-TBC | J31: =VLOOKUP($C31,'S | 01 '!$C$6:$R$46,J$5,0) -> 0.018823528 | K31: =VLOOKUP($C31,'S | 01 '!$C$6:$R$46,K$5,0) -> 800 | L31: =VLOOKUP($C31,'S | 01 '!$C$6:$R$46,L$5,0) -> 800 | ... O31: =VLOOKUP($C31,'S | 01 '!$C$6:$R$46,O$5,0) -> 17.18905 | P31: 54.67 | Q31: =VLOOKUP($C31,'S | 01 '!$C$6:$R$46,Q$5,0) -> 0.022479972 | R31: =VLOOKUP($C31,'S | 01 '!$C$6:$R$46,R$5,0) -> 1.0214863 | S31: =VLOOKUP($C31,'S | 01 '!$C$6:$R$46,S$5,0) -> 0 | W31: G42
C32: DriveNets | D32: Direct Investment | E32: =VLOOKUP($C32,'S | 01 '!$C$6:$R$46,E$5,0) -> Unrealized | F32: =VLOOKUP($C32,'S | 01 '!$C$6:$R$46,F$5,0) -> Anton | G32: =VLOOKUP($C32,'S | 01 '!$C$6:$R$46,G$5,0) -> G42 | H32: =VLOOKUP($C32,'S | 01 '!$C$6:$R$46,H$5,0) -> 2022 | I32: =VLOOKUP($C32,'S | 01 '!$C$6:$R$46,I$5,0) -> Equity-TBC | J32: =VLOOKUP($C32,'S | 01 '!$C$6:$R$46,J$5,0) -> 0.11141914 | K32: =VLOOKUP($C32,'S | 01 '!$C$6:$R$46,K$5,0) -> 300 | L32: =VLOOKUP($C32,'S | 01 '!$C$6:$R$46,L$5,0) -> 300 | ... O32: =VLOOKUP($C32,'S | 01 '!$C$6:$R$46,O$5,0) -> 0 | P32: 0 | Q32: =VLOOKUP($C32,'S | 01 '!$C$6:$R$46,Q$5,0) -> 2.9802322e-09 | R32: =VLOOKUP($C32,'S | 01 '!$C$6:$R$46,R$5,0) -> 1 | S32: =VLOOKUP($C32,'S | 01 '!$C$6:$R$46,S$5,0) -> 0 | T32: DN Warrants b
C33: vTv Therapeutics Inc. | D33: Direct Investment | E33: =VLOOKUP($C33,'S | 01 '!$C$6:$R$46,E$5,0) -> Unrealized | F33: =VLOOKUP($C33,'S | 01 '!$C$6:$R$46,F$5,0) -> Divyesh | G33: =VLOOKUP($C33,'S | 01 '!$C$6:$R$46,G$5,0) -> G42 | H33: =VLOOKUP($C33,'S | 01 '!$C$6:$R$46,H$5,0) -> 2022 | I33: =VLOOKUP($C33,'S | 01 '!$C$6:$R$46,I$5,0) -> Ordinary Shares | J33: =VLOOKUP($C33,'S | 01 '!$C$6:$R$46,J$5,0) -> 0.099316564 | K33: =VLOOKUP($C33,'S | 01 '!$C$6:$R$46,K$5,0) -> 24.53125 | L33: =VLOOKUP($C33,'S | 01 '!$C$6:$R$46,L$5,0) -> 24.53125 | ... O33: =VLOOKUP($C33,'S | 01 '!$C$6:$R$46,O$5,0) -> -17.468584 | P33: -1.348 | Q33: =VLOOKUP($C33,'S | 01 '!$C$6:$R$46,Q$5,0) -> NM | R33: =VLOOKUP($C33,'S | 01 '!$C$6:$R$46,R$5,0) -> 0.28790487 | S33: =VLOOKUP($C33,'S | 01 '!$C$6:$R$46,S$5,0) -> 0 | T33: vTv $30m milestn payment c | W33: Invested | X33: =L40 -> 1256.2697
C34: North Summit Capital Fund | D34: Fund Investment | E34: =VLOOKUP($C34,'S | 01 '!$C$6:$R$46,E$5,0) -> Unrealized | F34: =VLOOKUP($C34,'S | 01 '!$C$6:$R$46,F$5,0) -> Elaine | G34: =VLOOKUP($C34,'S | 01 '!$C$6:$R$46,G$5,0) -> G42 | H34: =VLOOKUP($C34,'S | 01 '!$C$6:$R$46,H$5,0) -> 2020 | I34: =VLOOKUP($C34,'S | 01 '!$C$6:$R$46,I$5,0) -> LP | J34: =VLOOKUP($C34,'S | 01 '!$C$6:$R$46,J$5,0) -> n/a | K34: =VLOOKUP($C34,'S | 01 '!$C$6:$R$46,K$5,0) -> 300 | L34: =VLOOKUP($C34,'S | 01 '!$C$6:$R$46,L$5,0) -> 83.214653 | ... O34: =VLOOKUP($C34,'S | 01 '!$C$6:$R$46,O$5,0) -> -0.490906 | P34: -0.306 | Q34: =VLOOKUP($C34,'S | 01 '!$C$6:$R$46,Q$5,0) -> -0.0021562932 | R34: =VLOOKUP($C34,'S | 01 '!$C$6:$R$46,R$5,0) -> 0.96555063 | S34: =VLOOKUP($C34,'S | 01 '!$C$6:$R$46,S$5,0) -> 217.81331 | W34: NAV | X34: =N40 -> 1255.1666
C35: New Space Capital Fund I | D35: Fund Investment | E35: =VLOOKUP($C35,'S | 01 '!$C$6:$R$46,E$5,0) -> Unrealized | F35: =VLOOKUP($C35,'S | 01 '!$C$6:$R$46,F$5,0) -> Sushil | G35: =VLOOKUP($C35,'S | 01 '!$C$6:$R$46,G$5,0) -> G42 | H35: =VLOOKUP($C35,'S | 01 '!$C$6:$R$46,H$5,0) -> 2020 | I35: =VLOOKUP($C35,'S | 01 '!$C$6:$R$46,I$5,0) -> LP | J35: =VLOOKUP($C35,'S | 01 '!$C$6:$R$46,J$5,0) -> n/a | K35: =VLOOKUP($C35,'S | 01 '!$C$6:$R$46,K$5,0) -> 28.336808 | L35: =VLOOKUP($C35,'S | 01 '!$C$6:$R$46,L$5,0) -> 11.058035 | ... O35: =VLOOKUP($C35,'S | 01 '!$C$6:$R$46,O$5,0) -> 5.2881388 | P35: 5.445 | Q35: =VLOOKUP($C35,'S | 01 '!$C$6:$R$46,Q$5,0) -> 0.08799049 | R35: =VLOOKUP($C35,'S | 01 '!$C$6:$R$46,R$5,0) -> 1.4784783 | S35: =VLOOKUP($C35,'S | 01 '!$C$6:$R$46,S$5,0) -> 17.278774 | W35: Gain | X35: =O40 -> 3.324546
C36: New Space Capital GP Com SCSp | D36: Fund Investment | E36: =VLOOKUP($C36,'S | 01 '!$C$6:$R$46,E$5,0) -> Unrealized | F36: =VLOOKUP($C36,'S | 01 '!$C$6:$R$46,F$5,0) -> Sushil | G36: =VLOOKUP($C36,'S | 01 '!$C$6:$R$46,G$5,0) -> G42 | H36: =VLOOKUP($C36,'S | 01 '!$C$6:$R$46,H$5,0) -> 2023 | I36: =VLOOKUP($C36,'S | 01 '!$C$6:$R$46,I$5,0) -> LP | J36: =VLOOKUP($C36,'S | 01 '!$C$6:$R$46,J$5,0) -> n/a | K36: =VLOOKUP($C36,'S | 01 '!$C$6:$R$46,K$5,0) -> 2.7058824 | L36: =VLOOKUP($C36,'S | 01 '!$C$6:$R$46,L$5,0) -> 2.7058824 | ... O36: =VLOOKUP($C36,'S | 01 '!$C$6:$R$46,O$5,0) -> 0.57072563 | P36: 0 | Q36: =VLOOKUP($C36,'S | 01 '!$C$6:$R$46,Q$5,0) -> 0 | R36: =VLOOKUP($C36,'S | 01 '!$C$6:$R$46,R$5,0) -> 1 | S36: =VLOOKUP($C36,'S | 01 '!$C$6:$R$46,S$5,0) -> 0 | W36: YTD Gains | X36: =O40-P40 -> -53.565454
C37: Sinovation Disrupt Fund, L.P. | D37: Fund Investment | E37: =VLOOKUP($C37,'S | 01 '!$C$6:$R$46,E$5,0) -> Unrealized | F37: =VLOOKUP($C37,'S | 01 '!$C$6:$R$46,F$5,0) -> Elaine | G37: =VLOOKUP($C37,'S | 01 '!$C$6:$R$46,G$5,0) -> G42 | H37: =VLOOKUP($C37,'S | 01 '!$C$6:$R$46,H$5,0) -> 2020 | I37: =VLOOKUP($C37,'S | 01 '!$C$6:$R$46,I$5,0) -> LP | J37: =VLOOKUP($C37,'S | 01 '!$C$6:$R$46,J$5,0) -> n/a | K37: =VLOOKUP($C37,'S | 01 '!$C$6:$R$46,K$5,0) -> 50 | L37: =VLOOKUP($C37,'S | 01 '!$C$6:$R$46,L$5,0) -> 20.74471 | ... O37: =VLOOKUP($C37,'S | 01 '!$C$6:$R$46,O$5,0) -> -1.0563667 | P37: -1.265 | Q37: =VLOOKUP($C37,'S | 01 '!$C$6:$R$46,Q$5,0) -> -0.023361704 | R37: =VLOOKUP($C37,'S | 01 '!$C$6:$R$46,R$5,0) -> 0.97193724 | S37: =VLOOKUP($C37,'S | 01 '!$C$6:$R$46,S$5,0) -> 29.25529 | W37: IRR | X37: =Q40 -> 0.0021642417
C38: Acies Investments Fund I, L.P. | D38: Fund Investment | E38: =VLOOKUP($C38,'S | 01 '!$C$6:$R$46,E$5,0) -> Unrealized | F38: =VLOOKUP($C38,'S | 01 '!$C$6:$R$46,F$5,0) -> Divyesh | G38: =VLOOKUP($C38,'S | 01 '!$C$6:$R$46,G$5,0) -> G42 | H38: =VLOOKUP($C38,'S | 01 '!$C$6:$R$46,H$5,0) -> 2021 | I38: =VLOOKUP($C38,'S | 01 '!$C$6:$R$46,I$5,0) -> LP | J38: =VLOOKUP($C38,'S | 01 '!$C$6:$R$46,J$5,0) -> 0.33 | K38: =VLOOKUP($C38,'S | 01 '!$C$6:$R$46,K$5,0) -> 17.1125 | L38: =VLOOKUP($C38,'S | 01 '!$C$6:$R$46,L$5,0) -> 14.015137 | ... O38: =VLOOKUP($C38,'S | 01 '!$C$6:$R$46,O$5,0) -> -0.7075125 | P38: -0.306 | Q38: =VLOOKUP($C38,'S | 01 '!$C$6:$R$46,Q$5,0) -> -0.04112356 | R38: =VLOOKUP($C38,'S | 01 '!$C$6:$R$46,R$5,0) -> 0.97333028 | S38: =VLOOKUP($C38,'S | 01 '!$C$6:$R$46,S$5,0) -> 3.0973625 | T38: 9.9% GP | Anchor
W39: =O29-P29 -> 8.6824242
K40: =SUM(K31:K38) -> 1522.6864 | L40: =SUM(L31:L38) -> 1256.2697 | M40: =SUM(M31:M38) -> 4.4275637 | N40: =SUM(N31:N38) -> 1255.1666 | O40: =N40+M40-L40 -> 3.324546 | P40: =SUM(P31:P38) -> 56.89 | Q40: ='4. G42-IRR'!L16 -> 0.0021642417 | R40: =(M40+N40)/L40 -> 1.0026464 | S40: =SUM(S31:S38) -> 267.44473 | T40: =N40+M40-L40 -> 3.324546 | W40: =K40-L40 -> 266.41677
W41: =O40-P40 -> -53.565454
K42: =K29+K40 -> 2516.9571 | L42: =L29+L40 -> 2243.0372 | M42: =M29+M40 -> 17.719124 | N42: =N29+N40 -> 2251.8623 | O42: =O29+O40 -> 26.544169 | P42: =P29+P40 -> 71.427198 | Q42: ='4.All'!N9 -> 0.007097432 | R42: =(M42+N42)/L42 -> 1.011834 | S42: =S29+S40 -> 274.94473 | W42: =SUM(M31:N33)-SUM(L31:L33) -> -0.27953332
W43: =SUM(M34:N38)-SUM(L34:L38) -> 3.6040793
W44: =K40-L40 -> 266.41677
I45: Checks: | K45: =K42='S | 01 '!J46 -> TRUE | L45: =ROUND(L42,3)=ROUND('S | 01 '!K46,3) -> TRUE | M45: =M42='S | 01 '!M46 -> TRUE | N45: =N42='S | 01 '!N46 -> TRUE | O45: =ROUND(O42,3)=ROUND('S | 01 '!O46,3) -> TRUE | S45: =S29='S | 01 '!L30 -> TRUE
B46: For Notes, refer to Summary | 01
O47: =O40-P40 -> -53.565454

Sheet S | 03
C2: As of date | D2: ='S | 01 '!D2 -> 45138
M3: n/a refers to information not available
C6: Deals | D6: Status | E6: Lead | F6: Investing Entity | G6: Instrument | H6: Listed / Unlisted | I6: Website link | J6: Pitchbook link | K6: Jurisdiction | L6: % | M6: Upside (Warrants, Milestone payments, ) | N6: For Comments Refer to Note
C8: Direct Investments
C9: ='S | 01 '!C10 -> Jollychic Holding Limited | D9: ='S | 01 '!D10 -> In Liquidation | E9: ='S | 01 '!E10 -> Elaine | F9: ='S | 01 '!F10 -> Mozn | G9: ='S | 01 '!H10 -> C+ Prefs | I9: link | J9: link | K9: =VLOOKUP(C9,'6. %'!$C$6:$J$35,6,0) -> Cayman Islands | L9: =VLOOKUP(C9,'6. %'!$C$6:$J$35,4,0) -> 0.056999998 | N9: 1
C10: ='S | 01 '!C11 -> Mena Mobile Inc | D10: ='S | 01 '!D11 -> Unrealized | E10: ='S | 01 '!E11 -> Elaine | F10: ='S | 01 '!F11 -> Mozn | G10: ='S | 01 '!H11 -> B Prefs | I10: link | J10: link | K10: =VLOOKUP(C10,'6. %'!$C$6:$J$35,6,0) -> Cayman Islands | L10: =VLOOKUP(C10,'6. %'!$C$6:$J$35,4,0) -> 0.14 | N10: 2
C11: ='S | 01 '!C12 -> Flyr Inc | D11: ='S | 01 '!D12 -> Unrealized | E11: ='S | 01 '!E12 -> Sushil | F11: ='S | 01 '!F12 -> Mozn | G11: ='S | 01 '!H12 -> B-1,2 Prefs | I11: link | J11: link | K11: =VLOOKUP(C11,'6. %'!$C$6:$J$35,6,0) -> Delaware Corporation | L11: =VLOOKUP(C11,'6. %'!$C$6:$J$35,4,0) -> 0.085025485 | M11: Flyr Warrantsa | N11: 3
C12: ='S | 01 '!C13 -> Esyasoft Holding | D12: ='S | 01 '!D13 -> Realized | E12: ='S | 01 '!E13 -> Sushil | F12: ='S | 01 '!F13 -> Mozn | G12: ='S | 01 '!H13 -> Convertible Note | I12: link | J12: n/a | K12: =VLOOKUP(C12,'6. %'!$C$6:$J$35,6,0) -> DIFC | L12: =VLOOKUP(C12,'6. %'!$C$6:$J$35,4,0) -> n/a | N12: 4
C13: ='S | 01 '!C14 -> Beyond Limits | D13: ='S | 01 '!D14 -> Unrealized | E13: ='S | 01 '!E14 -> Divyesh | F13: ='S | 01 '!F14 -> Mozn | G13: ='S | 01 '!H14 -> C Prefs | I13: link | J13: link | K13: =VLOOKUP(C13,'6. %'!$C$6:$J$35,6,0) -> Delaware Corporation | L13: =VLOOKUP(C13,'6. %'!$C$6:$J$35,4,0) -> 0.097965107 | N13: 5
C14: ='S | 01 '!C15 -> ONT plc | D14: ='S | 01 '!D15 -> Unrealized | E14: ='S | 01 '!E15 -> Divyesh | F14: ='S | 01 '!F15 -> Mozn | G14: ='S | 01 '!H15 -> Ordinary Shares | H14: Listed | I14: link | J14: link | K14: =VLOOKUP(C14,'6. %'!$C$6:$J$35,6,0) -> UK | L14: =VLOOKUP(C14,'6. %'!$C$6:$J$35,4,0) -> 0.053583931 | N14: 6
C15: ='S | 01 '!C16 -> Heygears | D15: ='S | 01 '!D16 -> Unrealized | E15: ='S | 01 '!E16 -> Elaine | F15: ='S | 01 '!F16 -> Mozn | G15: ='S | 01 '!H16 -> Registered Capital | I15: link | J15: link | K15: =VLOOKUP(C15,'6. %'!$C$6:$J$35,6,0) -> PRC | L15: =VLOOKUP(C15,'6. %'!$C$6:$J$35,4,0) -> 0.1438 | N15: 7
C16: ='S | 01 '!C17 -> Jysan Technologies | D16: ='S | 01 '!D17 -> Unrealized | E16: ='S | 01 '!E17 -> Sushil | F16: Mozn aa | G16: ='S | 01 '!H17 -> A (Ordinary Shares) | I16: link | J16: n/a | K16: =VLOOKUP(C16,'6. %'!$C$6:$J$35,6,0) -> UK | L16: =VLOOKUP(C16,'6. %'!$C$6:$J$35,4,0) -> 0.03 | N16: 8
C17: ='S | 01 '!C18 -> Cerebras Systems Inc | D17: ='S | 01 '!D18 -> Unrealized | E17: ='S | 01 '!E18 -> Ignasi | F17: ='S | 01 '!F18 -> Mozn | G17: ='S | 01 '!H18 -> F Prefs | I17: link | J17: link | K17: =VLOOKUP(C17,'6. %'!$C$6:$J$35,6,0) -> Delaware Corporation | L17: =VLOOKUP(C17,'6. %'!$C$6:$J$35,4,0) -> 0.0094767871 | N17: 9
C18: ='S | 01 '!C19 -> Endless Studios LLC | D18: ='S | 01 '!D19 -> Unrealized | E18: ='S | 01 '!E19 -> Sushil | F18: ='S | 01 '!F19 -> Mozn | G18: ='S | 01 '!H19 -> A Pref Units | I18: link | J18: link | K18: =VLOOKUP(C18,'6. %'!$C$6:$J$35,6,0) -> Delaware Corporation | L18: =VLOOKUP(C18,'6. %'!$C$6:$J$35,4,0) -> 0.077419355 | N18: 10
C19: ='S | 01 '!C20 -> Instadeep Limited | D19: ='S | 01 '!D20 -> Realized | E19: ='S | 01 '!E20 -> Ignasi | F19: ='S | 01 '!F20 -> Mozn | G19: ='S | 01 '!H20 -> B Prefs | I19: link | J19: link | K19: =VLOOKUP(C19,'6. %'!$C$6:$J$35,6,0) -> UK | L19: =VLOOKUP(C19,'6. %'!$C$6:$J$35,4,0) -> 0.011489406 | N19: 11
C20: ='S | 01 '!C21 -> X-fusion | D20: ='S | 01 '!D21 -> Unrealized | E20: ='S | 01 '!E21 -> Elaine | F20: Mozn bb | G20: ='S | 01 '!H21 -> Equity-TBC | I20: link | J20: link | K20: =VLOOKUP(C20,'6. %'!$C$6:$J$35,6,0) -> PRC | L20: =VLOOKUP(C20,'6. %'!$C$6:$J$35,4,0) -> 0.051 | N20: 12
C21: ='S | 01 '!C22 -> DriveNets | D21: ='S | 01 '!D22 -> Unrealized | E21: ='S | 01 '!E22 -> Anton | F21: ='S | 01 '!F22 -> G42 | G21: ='S | 01 '!H22 -> Equity-TBC | I21: link | J21: link | K21: =VLOOKUP(C21,'6. %'!$C$6:$J$35,6,0) -> Israeli Pvt Company | L21: =VLOOKUP(C21,'6. %'!$C$6:$J$35,4,0) -> 0.11141914 | M21: DN Warrants b | N21: 13
C22: ='S | 01 '!C23 -> vTv Therapeutics Inc. | D22: ='S | 01 '!D23 -> Unrealized | E22: ='S | 01 '!E23 -> Divyesh | F22: ='S | 01 '!F23 -> G42 | G22: ='S | 01 '!H23 -> Ordinary Shares | H22: Listed | I22: link | J22: link | K22: =VLOOKUP(C22,'6. %'!$C$6:$J$35,6,0) -> Delaware Corporation | L22: =VLOOKUP(C22,'6. %'!$C$6:$J$35,4,0) -> 0.099316564 | M22: vTv $30m milestn payment c | N22: 14
C23: ='S | 01 '!C24 -> Honor Device Co Ltd | D23: ='S | 01 '!D24 -> Unrealized | E23: ='S | 01 '!E24 -> Elaine | F23: G42 cc | G23: ='S | 01 '!H24 -> Equity-TBC | I23: link | J23: link | K23: =VLOOKUP(C23,'6. %'!$C$6:$J$35,6,0) -> PRC | L23: =VLOOKUP(C23,'6. %'!$C$6:$J$35,4,0) -> 0.018823528 | N23: 15
C24: ='S | 01 '!C25 -> Applied AI Corporation Limited | D24: ='S | 01 '!D25 -> Unrealized | E24: ='S | 01 '!E25 -> Divyesh | F24: ='S | 01 '!F25 -> Mozn | G24: ='S | 01 '!H25 -> Convertible Note | I24: link | J24: link | K24: =VLOOKUP(C24,'6. %'!$C$6:$J$35,6,0) -> ADGM | L24: =VLOOKUP(C24,'6. %'!$C$6:$J$35,4,0) -> n/a | N24: 16
C25: ='S | 01 '!C26 -> eSpace | D25: ='S | 01 '!D26 -> Unrealized | E25: ='S | 01 '!E26 -> Anton | F25: Mozn dd | G25: ='S | 01 '!H26 -> SAFE note | I25: link | J25: link | K25: =VLOOKUP(C25,'6. %'!$C$6:$J$35,6,0) -> Delaware Corporation | L25: =VLOOKUP(C25,'6. %'!$C$6:$J$35,4,0) -> n/a | N25: 17
C26: ='S | 01 '!C27 -> Tools for Humanity Corporation | D26: ='S | 01 '!D27 -> Unrealized | E26: ='S | 01 '!E27 -> Divyesh | F26: ='S | 01 '!F27 -> Mozn | G26: ='S | 01 '!H27 -> C Prefs | I26: link | J26: link | K26: =VLOOKUP(C26,'6. %'!$C$6:$J$35,6,0) -> Delaware Corporation | L26: =VLOOKUP(C26,'6. %'!$C$6:$J$35,4,0) -> 0.0062621983 | N26: 24
C27: ='S | 01 '!C28 -> WLD Tokens | D27: ='S | 01 '!D28 -> Unrealized | E27: ='S | 01 '!E28 -> Divyesh | F27: ='S | 01 '!F28 -> Mozn | G27: ='S | 01 '!H28 -> Tokens | I27: link | J27: Coinbase | K27: =VLOOKUP(C27,'6. %'!$C$6:$J$35,6,0) -> DAO | Cayman Islands | L27: =VLOOKUP(C27,'6. %'!$C$6:$J$35,4,0) -> 0.00625 | N27: 25
C30: Debt Investments
C31: Glass Earth Holdings LLC | D31: In default | F31: Mozn | G31: Promissory Note | I31: n/a | J31: n/a | K31: n/a | N31: 16
C32: Mena Mobile Inc (Debt) | D32: In default | E32: Elaine | F32: Mozn | G32: Loan | I32: link | J32: link | K32: =K10 -> Cayman Islands | N32: 17
C33: Esyasoft Holding (Debt) | D33: Unrealized | E33: Sushil | F33: Mozn | G33: Loan | I33: link | J33: n/a | K33: =K12 -> DIFC | N33: 18
C36: Funds Investments
C37: New Space Capital Fund I | D37: Unrealized | E37: Sushil | F37: G42 | G37: LP | I37: link | J37: link | K37: =VLOOKUP(C37,'6. %'!$C$6:$J$35,6,0) -> Luxembourg | L37: =VLOOKUP(C37,'6. %'!$C$6:$J$35,4,0) -> 0.22044082 | N37: 19
C38: New Space Capital GP Com SCSp | D38: Unrealized | E38: Sushil | F38: G42 | G38: GP | I38: link | J38: link | K38: =VLOOKUP(C38,'6. %'!$C$6:$J$35,6,0) -> Luxembourg | L38: =VLOOKUP(C38,'6. %'!$C$6:$J$35,4,0) -> 0.02016129 | N38: 20
C39: North Summit Capital Fund | D39: Unrealized | E39: Elaine | F39: G42 | G39: LP | I39: n/a | J39: link | K39: =VLOOKUP(C39,'6. %'!$C$6:$J$35,6,0) -> Cayman Islands | L39: =VLOOKUP(C39,'6. %'!$C$6:$J$35,4,0) -> 0.995 | N39: 21
C40: Sinovation Disrupt Fund, L.P. | D40: Unrealized | E40: Elaine | F40: G42 | G40: LP | I40: link | J40: link | K40: =VLOOKUP(C40,'6. %'!$C$6:$J$35,6,0) -> Cayman Islands | L40: =VLOOKUP(C40,'6. %'!$C$6:$J$35,4,0) -> 0.1006609 | N40: 22
C41: Acies Investments Fund I, L.P. | D41: Unrealized | E41: Divyesh | F41: G42 | G41: LP | I41: link | J41: link | K41: =VLOOKUP(C41,'6. %'!$C$6:$J$35,6,0) -> Delaware LLC | L41: =VLOOKUP(C41,'6. %'!$C$6:$J$35,4,0) -> 0.33333333 | M41: 9.9% GP | Anchor e | N41: 23
B45: Notes:
B46: 1 | C46: Jollychic | D46: During 2021, Jollychic Holding Ltd has filed for its liquidation. Therefore, investment is considered to be fully impaired in Dec 21.
B47: 2 | C47: Mena Mobile | D47: Investment is written off based on the 3rd party valuation report
B48: 3 | C48: Flyr | D48: Within five years of the Initial Closing, for every USD 1mn of Qualifying Revenue generated, Flyr will issue, at no additional charge, 194,477 B-1 Prefs in the name of G42, up to a maximum of 1,264,100 B-1 Prefs.
B49: 4 | C49: Esyasoft Holding | D49: Investment in Esyasoft is in the form of Convertible Note which will convert to 21% interest on conversion on a fully diluted basis. As per Dec 2020 FS of Esyasoft, the CN was reflected as Debt - Exit of US$ 2.5 Mn Convertible Note @ 2.0x (MoC) i.e. US$ 5 Mn in May 22 - US$ 0.4 Mn represents Working Capital Loan - fully exited in Dec 22
B50: 5 | C50: Beyond Limits | D50: Business targeting raising funds by the end of FY2022
B51: 6 | C51: ONT plc | D51: Listed
B52: 7 | C52: Heygears | D52: Mozn's holding is RMB 4,753,356.29 of the Registered Capital.
B53: 8 | C53: Jysan Technologies | D53: - 50% of the investment has been financed by profit sharing loan. - Further, in case of exit of G42’s investment, 50% of the sale proceeds shall be paid to the lender as full and final settlement of the outstanding liability - Exit for this investment is under process. Buyback agreement is pending for signature internally. (Relevant documents to be perused by the consolidation / reporting team for details and corresponding implications, if any) - Dividend receivable amounting to US$ 3.2 m will be waived upon exit of this investment
B54: 9 | C54: Cerebras Systems Inc | D54: The investment is currently undergoing a CFIUS review.
B55: 10 | C55: Endless Studios LLC
B56: 11 | C56: Instadeep Limited | D56: Fully Exited on 31st July with 1.5x returns.
B57: 12 | C57: X-fusion | D57: RMB 80 Mn of Registered Capital for RMB 5.7 Bn
B58: 13 | C58: Drivenets | D58: Share warrants excisable upon the achievement of target revenue of clients by referred G42. The milestones of each target revenue and respective conversion were stated in the Term Sheet.
B59: 14 | C59: vTv Therapeutics : | D59: Potential issuance of US$ 30 million in additional shares of Class A Common Stock to G42 Investments (or in cash, at the option of G42 Investments) if FDA approval is received for the marketing and the sale of a pharmaceutical product containing TTP399
B60: 15 | C60: Honor | D60: Invested in Q3 2022; During Dec 22, $250m was offloaded to another investor at cost
B61: 16 | C61: Glass Earth Holdings LLC | D61: Written off. Debt security of Glass Earth issued in 2019 were fully provided for.
B62: 17 | C62: Mena Mobile (Debt) | D62: Outstanding
B63: 18 | C63: Esyasoft Holding (Debt) | D63: Outstanding
B64: 19 | C64: New Space Capital Fund I | D64: G42 negotiated conversion of €2.3m GP investment into LP investment to vote in favor of new LP proposal.
B65: 20 | C65: New Space Capital SCSp | D65: Ibid
B66: 21 | C66: North Summit Capital | D66: Portfolio Exit Plan in Progress
B67: 22 | C67: Sinovation Disrupt Fund | D67: Expect valuation to rise as some of its portfolio companies are in the market to raise new funds
B68: 23 | C68: Acies Investments Fund I, LP
B69: 24 | C69: Tools for Humanity Corporation | D69: Additional token warrants (for 62.5 million Tokens) for a consideration of $5,875.00. Additional provision for c$2K (the warrant price) kept for exercising the warrant rights.
B70: 25 | C70: WLD Tokens | D70: Received 62.5M Tokens as of Jul'23
B72: 17,18,19: no comments
C75: Additional Upside Section:
C76: a) Flyr: For every $1m of revenue, 194,477 shares, capped at 1,264,1000 (B-1) shares shall be issued to Mozn
C77: b) DriveNets: Share warrants exercisable upon the achievement of target revenue of clients referred by G42, and corresponding milestones
C78: c) vTv Therapeutics: Potential issuance of $30m in additional shares, if FDA approval received for the drug TTP399
C79: d) Tools for Humanity Corporation: Additional token warrants issued for acquiring 62.5M Tokens for $5,875.00. Additional provision for c$2K (the warrant price) kept for exercising the warrant rights
C80: e) Acies Investments Fund I LP: Being the Anchor investor, entitled to 9.9% of the aggregate carried interest earned by the GP
C83: References:
C84: G42 refers to G42 Investments AI Holding RSC Ltd
C85: Mozn refers to Mozn Holding RSC Ltd
C86: PRC refers to People's Republic of China
C87: aa Invested via QAZ42 Investment SPV RSC Ltd (QAZ42)
C88: bb Invested via Enterprise Connection Holding RSC Ltd (Enterprise Connection)
... C90: dd Invested via Smart Interaction5 Holding SPV RSC LTD (Smart Interaction5)

Sheet NAV
B2: NAV Date | C2: ='S | 01 '!D2 -> 45138
B5: Investments | C5: Investing Entity | D5: Instrument | E5: Carrying Value | F5: Current Shares/Units | H5: Comment | N5: CHECKS
E6: USD, Million | F6: # | G6: USD | J6: Updated as on: | K6: =C2 -> 45138
E7: ="NAV | "& TEXT(C2,"dd")&" "&TEXT(C2,"mmm")&" "&TEXT(C2,"yyyy") -> NAV | 31 Jul 2023 | G7: ="PPS |" & TEXT(C2,"dd")&" "&TEXT(C2,"mmm")&" "&TEXT(C2,"yyyy") -> PPS |31 Jul 2023 | L7: source | N7: Equity | O7: =SUM(E9:E26) -> 2103.5933
B8: Direct Investments | J8: ONT Share price | K8: 2.638 | L8: link | N8: Debt | O8: =SUM(E32:E34) -> 2.353982
B9: ='S | 01 '!C10 -> Jollychic Holding Limited | C9: ='S | 01 '!F10 -> Mozn | D9: ='S | 01 '!H10 -> C+ Prefs | E9: =F9*G9*10^-6 -> 0 | F9: =SUM('CF (Equity, Debt)'!J4:J6) -> 13458655 | H9: In Liquidation | J9: VTVT Share price | K9: 0.68 | L9: link | N9: Funds | O9: =SUM(E39:E43) -> 130.91493
B10: ='S | 01 '!C11 -> Mena Mobile Inc | C10: ='S | 01 '!F11 -> Mozn | D10: ='S | 01 '!H11 -> B Prefs | E10: 0 | F10: ='CF (Equity, Debt)'!J7 -> 21419829 | H10: As per 3rd Party | Ardent Estimates | Equity written off | J10: GBP USD | K10: 1.28616 | L10: xe.com | N10: Total | O10: =SUM(O7:O9) -> 2236.8623
B11: ='S | 01 '!C12 -> Flyr Inc | C11: ='S | 01 '!F12 -> Mozn | D11: ='S | 01 '!H12 -> B-1,2 Prefs | E11: =F11*G11*10^-6*(1-20%) -> 78.08223 | F11: 5205482 | G11: 18.75 | H11: At Series C PPS $18.75/share with 20% discount | J11: USD RMB | K11: 7.14069 | L11: xe.com | N11: =E23/800 -> 1.0214863 | O11: =O10='S | 01 '!N46 -> FALSE
B12: ='S | 01 '!C13 -> Esyasoft Holding | C12: ='S | 01 '!F13 -> Mozn | D12: ='S | 01 '!H13 -> Convertible Note | E12: 0 | F12: n/a | H12: Exited at $5m (10th May) | Residual value = 0 | J12: EURUSD | K12: 1.10227 | L12: xe.com | O12: =O10='4.All'!M9 -> FALSE
B13: ='S | 01 '!C14 -> Beyond Limits | C13: ='S | 01 '!F14 -> Mozn | D13: ='S | 01 '!H14 -> C Prefs | E13: =F13*G13*10^-6 -> 91.00154 | F13: =SUM('CF (Equity, Debt)'!J11:J14) -> 17670202 | G13: 5.15 | H13: Held at cost (as per revised management guidance)
B14: ='S | 01 '!C15 -> ONT plc | C14: ='S | 01 '!F15 -> Mozn | D14: ='S | 01 '!H15 -> Ordinary Shares | E14: =F14*G14*10^-6 -> 150.40044 | F14: 44328120 | G14: =K8*K10 -> 3.3928901 | H14: Listed & marked to market
B15: ='S | 01 '!C16 -> Heygears | C15: ='S | 01 '!F16 -> Mozn | D15: ='S | 01 '!H16 -> Registered Capital | E15: =K25/1000000 -> 151.06943 | F15: ='CF (Equity, Debt)'!J20 -> 4753356.3 | H15: Adjusted for currency. Valued at the recent round
B16: ='S | 01 '!C17 -> Jysan Technologies | C16: ='S | 01 '!F17 -> Mozn 1 | D16: ='S | 01 '!H17 -> A (Ordinary Shares) | E16: =-'CF (Equity, Debt)'!E21 -> 20 | F16: ='CF (Equity, Debt)'!J21 -> 7959497 | G16: =E16*10^6/F16 -> 2.5127216 | H16: Held at cost. | J16: Heygears Oct 22
B17: ='S | 01 '!C18 -> Cerebras Systems Inc | C17: ='S | 01 '!F18 -> Mozn | D17: ='S | 01 '!H18 -> F Prefs | E17: =-'CF (Equity, Debt)'!E22 -> 39.999983 | F17: ='6. %'!D17 -> 1441711 | H17: Held at cost.
B18: ='S | 01 '!C19 -> Endless Studios LLC | C18: ='S | 01 '!F19 -> Mozn | D18: ='S | 01 '!H19 -> A Pref Units | E18: =-'CF (Equity, Debt)'!E23 -> 3 | F18: ='CF (Equity, Debt)'!J23 -> 3000000 | H18: Held at cost. | J18: Post Valuation closed in June 2021 (RMB) | K18: 7500000000
B19: ='S | 01 '!C20 -> Instadeep Limited | C19: ='S | 01 '!F20 -> Mozn | D19: ='S | 01 '!H20 -> B Prefs | E19: =-'CF (Equity, Debt)'!E24*G19 -> 0 | F19: ='CF (Equity, Debt)'!J24 -> 33267 | G19: 0 | H19: Exited at 1.56X | Residual Value = 0 | J19: G42 Stake | K19: 0.143832
B20: ='S | 01 '!C21 -> X-fusion | C20: ='S | 01 '!F21 -> Mozn 2 | D20: ='S | 01 '!H21 -> Equity-TBC | E20: =5810000000/K11/1000000*(1-49.82%) -> 408.28799 | F20: n/a | H20: Held at original cost, adjusted for currency, and ownership | J20: G42 Valuation before Discount (RMB) | K20: 1078740000
B21: ='S | 01 '!C22 -> DriveNets | C21: ='S | 01 '!F22 -> G42 | D21: ='S | 01 '!H22 -> Equity-TBC | E21: =-SUM('CF (Equity, Debt)'!E26:E27) -> 300 | F21: ='6. %'!D21 -> 86882669 | H21: Held at cost. | J21: Liquidity Discount | K21: 0
B22: ='S | 01 '!C23 -> vTv Therapeutics Inc. | C22: ='S | 01 '!F23 -> G42 | D22: ='S | 01 '!H23 -> Ordinary Shares | E22: =(F22*G22)*10^-6 -> 7.0626663 | F22: ='CF (Equity, Debt)'!J29 -> 10386274 | G22: =K9 -> 0.68 | H22: Listed & marked to market | J22: Minority Holding Discount | K22: 0
B23: ='S | 01 '!C24 -> Honor Device Co Ltd | C23: ='S | 01 '!F24 -> G42 3 | D23: ='S | 01 '!H24 -> Equity-TBC | E23: =310000000000/K11/1000000*4.705882%*0.8/2 -> 817.18905 | F23: n/a | H23: Closing a new round at RMB 310B. Adjusted for currency. | J23: G42 Valuation (RMB) | K23: =K20*(1-K21)*(1-K22) -> 1078740000
B24: ='S | 01 '!C25 -> Applied AI Corporation Limited | C24: ='S | 01 '!F25 -> Mozn | D24: ='S | 01 '!H25 -> Convertible Note | E24: =-'CF (Equity, Debt)'!E32-'CF (Equity, Debt)'!E38 -> 7.5 | F24: n/a | H24: Held at cost. | J24: Exchange Rate (RMB/USD) | K24: =K11 -> 7.14069
B25: ='S | 01 '!C26 -> eSpace | C25: ='S | 01 '!F26 -> Mozn 4 | D25: ='S | 01 '!H26 -> SAFE note | E25: 15 | F25: n/a | H25: Held at cost. | J25: G42 Valuation (USD) | K25: =K23/K24 -> 1.5106943e+08
B26: ='S | 01 '!C27 -> Tools for Humanity Corporation | C26: ='S | 01 '!F27 -> Mozn | D26: ='S | 01 '!H27 -> C Prefs | E26: ='S | 01 '!K27 -> 14.999999 | F26: ='6. %'!D26 -> 65413 | H26: Equity value held at cost. | J26: Investment Cost of G42 (USD) | K26: 60000000
B27: ='S | 01 '!C28 -> WLD Tokens | C27: ='S | 01 '!F28 -> Mozn | D27: ='S | 01 '!H28 -> Tokens | E27: =MAX('S | 01 '!K28,F27*G27*10^-6) -> 15 | F27: ='6. %'!D27 -> 62500000 | G27: =0.24 -> 0.24 | H27: Tokens valued at $0.3 per token taking into account the liquidity discount | J27: Investment Multiple | K27: 1.9039182
B31: Debt Investments | J31: New Space Capital
B32: Glass Earth Holdings LLC | C32: Mozn | D32: Promissory Note | E32: ='S | 01 '!N33 -> 0 | H32: In default
B33: Mena Mobile Inc (Debt) | C33: Mozn | D33: Loan | E33: ='S | 01 '!N34 -> 2.353982 | H33: Held at cost. | J33: EUR | K33: 3Q22 | L33: 4Q22 | M33: 1Q23
B34: Esyasoft Holding (Debt) | C34: Mozn | D34: Loan | E34: 0 | H34: Received payment of $470,784.65 ($411K+$59K) | J34: Commitment | K34: 23234462 | L34: 23234462 | M34: 23234462 | N34: source: distribution letter
J35: Capital Contribution | K35: 19178323 | L35: 9436936 | M35: 9626402
J36: Unfunded | K36: =K34-K35 -> 4056139 | L36: =L34-L35 -> 13797526 | M36: =M34-M35 -> 13608060
J37: Unrealized Gain | K37: 13103567 | L37: 3803379
B38: Funds Investments | J38: NAV | K38: 32325017 | L38: 12031777 | M38: 12148021 | N38: source: distribution letter
B39: New Space Capital Fund I | C39: G42 | D39: LP | E39: =M38*10^-6*K12 -> 13.390399 | H39: Q1'23 capital account statement | J39: Capital Return | L39: =K35-L35 -> 9741387 | N39: estimated
B40: New Space Capital GP Com SCSp | C40: G42 | D40: GP | E40: =E39*'S | 02'!L36/'S | 02'!L35 -> 3.276608 | H40: Q4'22 pro-rated | J40: Interest Capitalization | L40: =L42-L39 -> 2728214 | N40: estimated
B41: North Summit Capital Fund | C41: G42 | D41: LP | E41: 81.695786 | H41: Q1'23 capital account statement
B42: Sinovation Disrupt Fund, L.P. | C42: G42 | D42: LP | E42: =21.157072-'CF (Funds)'!D17 -> 19.244515 | H42: Q1'23 capital account statement | J42: Total Distribution Received | L42: 12469601 | N42: source: distribution letters, Gino
B43: Acies Investments Fund I, L.P. | C43: G42 | D43: LP | E43: 13.307625 | H43: Q1'23 capital account statement | J43: Remaining Commitment | L43: =15675627.21 -> 15675627 | N43: source: distribution letter
B46: Note: | F46: IRR | J46: in USD, Mn
B47: • For estimating the NAV their listed share price for ONT and vTv Therapeutics is taken | F47: Mozn | G47: ='S | 02'!Q29 -> 0.010515186 | J47: Capital Committed | K47: =K48+K49 -> 28.336808
F48: G42 | G48: ='S | 02'!Q40 -> 0.0021642417 | J48: Capital Called | K48: =-SUM('CF (Funds)'!D32:D36)-L39*1.08341*10^-6 -> 11.058035 | L48: =L35*10^-6*K12 -> 10.402051
F49: All | G49: ='S | 02'!Q42 -> 0.007097432 | J49: Remaining | K49: =L43*10^-6*K12 -> 17.278774
J50: NAV | K50: =L38*10^-6*K12 -> 13.262267
J51: Fund Size in Eur | K51: 105.4
J52: G42 % for 1st in Eur | K52: =M34*10^-6 -> 23.234462 | L52: =K52/K51 -> 0.22044082
J53: G42 % for 2nd in Eur | K53: 2.125 | L53: =K53/K51 -> 0.02016129

Sheet CF (Equity, Debt)
B2: E Q U I T Y
B3: Accounting entity | C3: Investment | D3: Payment date | E3: Contributions (in USD, Mn) | F3: Distributions (in USD, Mn) | G3: Currency | H3: Investment / Exit Amt (investee currency) | I3: Investment / Exit Amount (USD) | J3: Consideration (shares) | K3: Comment
B4: =VLOOKUP(C4,'S | 01 '!$C$10:$F$43,4,0) -> Mozn | C4: Jollychic Holding Limited | D4: 43470 | E4: =-I4*10^-6 -> -30 | G4: USD | H4: 30000000 | I4: =H4 -> 30000000 | J4: 6100312 | N4: NOTES
B5: =VLOOKUP(C5,'S | 01 '!$C$10:$F$43,4,0) -> Mozn | C5: Jollychic Holding Limited | D5: 43724 | E5: =-I5*10^-6 -> -20 | G5: USD | H5: 20000000 | I5: =H5 -> 20000000 | J5: 4204767.4 | N5: USD AED | O5: 3.678
B6: =VLOOKUP(C6,'S | 01 '!$C$10:$F$43,4,0) -> Mozn | C6: Jollychic Holding Limited | D6: 43724 | E6: =-I6*10^-6 -> -15 | G6: USD | H6: 15000000 | I6: =H6 -> 15000000 | J6: 3153575.6
B7: =VLOOKUP(C7,'S | 01 '!$C$10:$F$43,4,0) -> Mozn | C7: Mena Mobile Inc | D7: 43563 | E7: =-I7*10^-6 -> -8 | G7: USD | H7: 8000000 | I7: =H7 -> 8000000 | J7: 21419829
B8: =VLOOKUP(C8,'S | 01 '!$C$10:$F$43,4,0) -> Mozn | C8: Flyr Inc | D8: 43570 | E8: =-I8*10^-6 -> -4.9999981 | G8: USD | H8: 4999998.1 | I8: =H8 -> 4999998.1 | J8: 2625467
B9: =VLOOKUP(C9,'S | 01 '!$C$10:$F$43,4,0) -> Mozn | C9: Flyr Inc | D9: 43915 | E9: =-I9*10^-6 -> -5.0000019 | G9: USD | H9: =10000000-H8 -> 5000001.9 | I9: =H9 -> 5000001.9 | J9: 2580015
B10: =VLOOKUP(C10,'S | 01 '!$C$10:$F$43,4,0) -> Mozn | C10: Esyasoft Holding | D10: 43870 | E10: =-I10*10^-6 -> -2.5 | G10: USD | H10: 2500000 | I10: =H10 -> 2500000 | J10: N/A
B11: =VLOOKUP(C11,'S | 01 '!$C$10:$F$43,4,0) -> Mozn | C11: Beyond Limits | D11: 43879 | E11: =-I11*10^-6 -> -20 | G11: USD | H11: 20000000 | I11: =H11 -> 20000000 | J11: 4084038
B12: =VLOOKUP(C12,'S | 01 '!$C$10:$F$43,4,0) -> Mozn | C12: Beyond Limits | D12: 43921 | E12: =-I12*10^-6 -> -30 | G12: USD | H12: 30000000 | I12: =H12 -> 30000000 | J12: 5822642
B13: =VLOOKUP(C13,'S | 01 '!$C$10:$F$43,4,0) -> Mozn | C13: Beyond Limits | D13: 43989 | E13: =-I13*10^-6 -> -30 | G13: USD | H13: 30000000 | I13: =H13 -> 30000000 | J13: 5822642
B14: =VLOOKUP(C14,'S | 01 '!$C$10:$F$43,4,0) -> Mozn | C14: Beyond Limits | D14: 44103 | E14: =-I14*10^-6 -> -10 | G14: USD | H14: 10000000 | I14: =H14 -> 10000000 | J14: 1940880
B15: =VLOOKUP(C15,'S | 01 '!$C$10:$F$43,4,0) -> Mozn | C15: ONT plc | D15: 43968 | E15: =-I15*10^-6 -> -50 | G15: USD | H15: 50000000 | I15: 50000000 | J15: 15277680
B16: =VLOOKUP(C16,'S | 01 '!$C$10:$F$43,4,0) -> Mozn | C16: ONT plc | D16: 44006 | E16: =-I16*10^-6 -> -27.268351 | G16: GBP | H16: 21029625 | I16: 27268351 | J16: 9000000
B17: =VLOOKUP(C17,'S | 01 '!$C$10:$F$43,4,0) -> Mozn | C17: ONT plc | D17: 43837 | E17: =-I17*10^-6 -> -18.109441 | G17: GBP | H17: 14386480 | I17: 18109441 | J17: 6362180
B18: =VLOOKUP(C18,'S | 01 '!$C$10:$F$43,4,0) -> Mozn | C18: ONT plc | D18: 43990 | E18: =-I18*10^-6 -> -34.851687 | G18: GBP | H18: 26085573 | I18: 34851687 | J18: 11381140
B19: =VLOOKUP(C19,'S | 01 '!$C$10:$F$43,4,0) -> Mozn | C19: ONT plc | D19: 44315 | E19: =-I19*10^-6 -> -11.24078 | G19: GBP | H19: 8074920 | I19: 11240780 | J19: 2307120
B20: =VLOOKUP(C20,'S | 01 '!$C$10:$F$43,4,0) -> Mozn | C20: Heygears | D20: 44166 | E20: =-I20*10^-6 -> -60 | G20: USD | H20: 60000000 | I20: =H20 -> 60000000 | J20: 4753356.3
B21: =VLOOKUP(C21,'S | 01 '!$C$10:$F$43,4,0) -> Mozn 1 | C21: Jysan Technologies | D21: 44363 | E21: =-I21*10^-6 -> -20 | G21: USD | H21: 20000000 | I21: =H21 -> 20000000 | J21: 7959497
B22: =VLOOKUP(C22,'S | 01 '!$C$10:$F$43,4,0) -> Mozn | C22: Cerebras Systems Inc | D22: 44488 | E22: =-I22*10^-6 -> -39.999983 | G22: USD | H22: 39999983 | I22: =H22 -> 39999983 | J22: 1441711
B23: =VLOOKUP(C23,'S | 01 '!$C$10:$F$43,4,0) -> Mozn | C23: Endless Studios LLC | D23: 44494 | E23: =-I23*10^-6 -> -3 | G23: USD | H23: 3000000 | I23: =H23 -> 3000000 | J23: 3000000
B24: =VLOOKUP(C24,'S | 01 '!$C$10:$F$43,4,0) -> Mozn | C24: Instadeep Limited | D24: 44550 | E24: =-I24*10^-6 -> -5.0237202 | G24: GBP | H24: 3679995.5 | I24: 5023720.2 | J24: 33267
B25: =VLOOKUP(C25,'S | 01 '!$C$10:$F$43,4,0) -> Mozn 2 | C25: X-fusion | D25: 44574 | E25: =-I25*10^-6 -> -493.50096 | G25: USD | H25: 8.9350096e+08 | I25: 4.9350096e+08
B26: =VLOOKUP(C26,'S | 01 '!$C$10:$F$43,4,0) -> G42 | C26: DriveNets | D26: 44643 | E26: =-I26*10^-6 -> -200 | G26: USD | H26: 200000000 | I26: =H26 -> 200000000
B27: =VLOOKUP(C27,'S | 01 '!$C$10:$F$43,4,0) -> G42 | C27: DriveNets | D27: 44680 | E27: =-I27*10^-6 -> -100 | G27: USD | H27: 100000000 | I27: =H27 -> 100000000
B28: =VLOOKUP(C28,'S | 01 '!$C$10:$F$43,4,0) -> Mozn | C28: Esyasoft Holding | D28: 44691 | F28: 5 | G28: USD
B29: =VLOOKUP(C29,'S | 01 '!$C$10:$F$43,4,0) -> G42 | C29: vTv Therapeutics Inc. | D29: 44712 | E29: =-I29*10^-6 -> -12.5 | G29: USD | H29: 12500000 | I29: =H29 -> 12500000 | J29: 10386274
B30: =VLOOKUP(C30,'S | 01 '!$C$10:$F$43,4,0) -> G42 3 | C30: Honor Device Co Ltd | D30: 44769 | E30: =-I30*10^-6 -> -600 | G30: USD | H30: 600000000 | I30: =H30 -> 600000000
B31: =VLOOKUP(C31,'S | 01 '!$C$10:$F$43,4,0) -> G42 3 | C31: Honor Device Co Ltd | D31: 44849 | E31: =-I31*10^-6 -> -200 | G31: USD | H31: 200000000 | I31: =H31 -> 200000000
B32: =VLOOKUP(C32,'S | 01 '!$C$10:$F$43,4,0) -> Mozn | C32: Applied AI Corporation Limited | D32: 44861 | E32: =-I32*10^-6 -> -4.75 | G32: USD | H32: 4750000 | I32: =H32 -> 4750000
B33: =VLOOKUP(C33,'S | 01 '!$C$10:$F$43,4,0) -> Mozn 4 | C33: eSpace | D33: 44892 | E33: =-I33*10^-6 -> -15 | G33: USD | H33: 15000000 | I33: =H33 -> 15000000
B34: =VLOOKUP(C34,'S | 01 '!$C$10:$F$43,4,0) -> G42 | C34: vTv Therapeutics Inc. | D34: 44985 | E34: =-I34*10^-6 -> -12.03125 | G34: USD | H34: 12031250 | I34: =H34 -> 12031250 | J34: 10386274
B35: =VLOOKUP(C35,'S | 01 '!$C$10:$F$43,4,0) -> Mozn | C35: Tools for Humanity Corporation | D35: 45075 | E35: =-I35*10^-6 -> -14.999999 | G35: USD | H35: 14999999 | I35: =H35 -> 14999999
B36: =VLOOKUP(C36,'S | 01 '!$C$10:$F$43,4,0) -> Mozn | C36: WLD Tokens | D36: 45075 | E36: =-I36*10^-6 -> -0.005875 | G36: USD | I36: 5875
B37: =VLOOKUP(C37,'S | 01 '!$C$10:$F$43,4,0) -> Mozn | C37: WLD Tokens | D37: 45114 | E37: =-I37*10^-6 -> -0.001 | G37: USD | I37: 1000
B38: =VLOOKUP(C38,'S | 01 '!$C$10:$F$43,4,0) -> Mozn | C38: Applied AI Corporation Limited | D38: 45121 | E38: =-I38*10^-6 -> -2.75 | G38: USD | I38: 2750000
B39: =VLOOKUP(C39,'S | 01 '!$C$10:$F$43,4,0) -> Mozn | C39: Instadeep Limited | D39: 45138 | F39: =I39*10^-6 -> 7.8207761 | G39: USD | H39: 6090345.2 | I39: 7820776.1
B41: L O AN | P R O M I S S O R Y N O T E S | D E B T
B42: Mozn | C42: Glass Earth Holdings LLC | D42: 43635 | E42: -8 | G42: USD | H42: 8000000 | I42: =H42 -> 8000000
B43: Mozn | C43: Mena Mobile Inc (Debt) | D43: 44293 | E43: -2.353982 | G43: USD | H43: =-E43*10^6 -> 2353982 | I43: =H43 -> 2353982
B44: Mozn | C44: Esyasoft Holding (Debt) | D44: 44384 | E44: =-I44*10^-6 -> -0.411765 | G44: USD | H44: 2500000 | I44: 411765
B45: Mozn | C45: Esyasoft Holding (Debt) | D45: 44902 | F45: =(411765+59019.65)*10^-6 -> 0.47078465 | G45: USD | H45: =F45*10^6 -> 470784.65 | I45: 470784.65

Sheet CF (Funds)
A2: Entity | B2: Investment | C2: Payment date | D2: Contributions (USD, Mn) | E2: Distributions (USD, Mn) | F2: Currency | G2: Cashflows | H2: Description
A3: G42 | B3: Sinovation Disrupt Fund, L.P. | C3: 44153 | D3: =G3 -> -10.5 | F3: USD | G3: -10.5 | H3: 1st Capital Call
A4: G42 | B4: Sinovation Disrupt Fund, L.P. | C4: 44238 | D4: =G4 -> 4.214027 | F4: USD | G4: 4.214027 | H4: Partial return of the 1st Capital Call
A5: G42 | B5: Sinovation Disrupt Fund, L.P. | C5: 44238 | E5: =G5 -> 0.05044835 | F5: USD | G5: 0.05044835 | H5: Interest Catchup
A6: G42 | B6: Sinovation Disrupt Fund, L.P. | C6: 44285 | D6: =G6 -> -6.433746 | F6: USD | G6: -6.433746 | H6: 2nd Capital Calll
A7: G42 | B7: Sinovation Disrupt Fund, L.P. | C7: 44269 | D7: =G7 -> 1.1352074 | F7: USD | G7: 1.1352074 | H7: Return of Capital fund
A8: G42 | B8: Sinovation Disrupt Fund, L.P. | C8: 44269 | E8: =G8 -> 0.0259 | F8: USD | G8: 0.0259 | H8: Interest Catchup
A9: G42 | B9: Sinovation Disrupt Fund, L.P. | C9: 44483 | D9: =G9 -> -7.567138 | F9: USD | G9: -7.567138 | H9: 3rd Capital Call
A10: G42 | B10: Sinovation Disrupt Fund, L.P. | C10: 44554 | D10: =G10 -> -7.385016 | F10: USD | G10: -7.385016 | H10: 4th Capital Call
A11: G42 | B11: Sinovation Disrupt Fund, L.P. | C11: 44554 | D11: =G11 -> 4.0733456 | F11: USD | G11: 4.0733456 | H11: Return of Capital fund
A12: G42 | B12: Sinovation Disrupt Fund, L.P. | C12: 44554 | E12: =G12 -> 0.139694 | F12: USD | G12: 0.139694 | H12: Interest Catchup
A13: G42 | B13: Sinovation Disrupt Fund, L.P. | C13: 44703 | D13: =G13 -> 5.673074 | F13: USD | G13: 5.673074 | H13: Return of Capital fund
A14: G42 | B14: Sinovation Disrupt Fund, L.P. | C14: 44703 | E14: =G14 -> 0.227786 | F14: USD | G14: 0.227786 | H14: Interest Catchup
A15: G42 | B15: Sinovation Disrupt Fund, L.P. | C15: 44776 | D15: =G15 -> -3.235493 | F15: USD | G15: -3.235493 | H15: 5th Capital Call
A16: G42 | B16: Sinovation Disrupt Fund, L.P. | C16: 44960 | D16: =G16 -> -2.631528 | F16: USD | G16: -2.631528 | H16: 6th Capital Call
A17: G42 | B17: Sinovation Disrupt Fund, L.P. | C17: 45085 | D17: =G17 -> 1.912557 | F17: USD | G17: 1.912557 | H17: Return of Capital fund
A18: G42 | B18: North Summit Capital Fund | C18: 43665 | D18: =G18 -> -3 | F18: USD | G18: -3 | H18: 1st Capital Call
A19: G42 | B19: North Summit Capital Fund | C19: 43983 | D19: =G19 -> -4.485 | F19: USD | G19: -4.485 | H19: 2nd Capital Calll
A20: G42 | B20: North Summit Capital Fund | C20: 43879 | D20: =G20 -> -9.50975 | F20: USD | G20: -9.50975 | H20: 3rd Capital Call
A21: G42 | B21: North Summit Capital Fund | C21: 43934 | D21: =G21 -> -41.3 | F21: USD | G21: -41.3 | H21: 4th Capital Call
A22: G42 | B22: North Summit Capital Fund | C22: 44151 | D22: =G22 -> 9.95 | F22: USD | G22: 9.95 | H22: 5th Capital Call-Partial return of the 4th Capital Call
A23: G42 | B23: North Summit Capital Fund | C23: 44151 | D23: =G23 -> -10.455 | F23: USD | G23: -10.455 | H23: 5th Capital Call
A24: G42 | B24: North Summit Capital Fund | C24: 44196 | D24: =G24 -> 4.975 | F24: USD | G24: 4.975 | H24: 6th Capital Call-Partial return of the 4th Capital Call
A25: G42 | B25: North Summit Capital Fund | C25: 44196 | D25: =G25 -> -3.452293 | F25: USD | G25: -3.452293 | H25: 6th Capital Call
A26: G42 | B26: North Summit Capital Fund | C26: 44196 | E26: =G26 -> 0.582902 | F26: USD | G26: 0.582902 | H26: 6th Capital Call-Dividends from Project Topscore
A27: G42 | B27: North Summit Capital Fund | C27: 44370 | D27: =G27 -> -5.97 | F27: USD | G27: -5.97 | H27: 7th Capital Call
A28: G42 | B28: North Summit Capital Fund | C28: 44400 | D28: =G28 -> -0.75 | F28: USD | G28: -0.75 | H28: 8th Capital Call
A29: G42 | B29: North Summit Capital Fund | C29: 44400 | E29: =G29 -> 0.445059 | F29: USD | G29: 0.445059 | H29: 8th Capital Call-Dividends from Project Topscore
A30: G42 | B30: North Summit Capital Fund | C30: 44554 | D30: =G30 -> 1.78239 | F30: USD | G30: 1.78239 | H30: 9th Capital Call-Return of Capital Fund
A31: G42 | B31: North Summit Capital Fund | C31: 44676 | D31: =G31 -> -21 | F31: USD | G31: -21 | H31: 12th Capital Call
A32: G42 | B32: New Space Capital Fund I | C32: 44087 | D32: =G32*1.1 -> -20.917553 | F32: EUR | G32: -19.015957 | H32: Drawdown1
A33: G42 | B33: New Space Capital Fund I | C33: 44287 | D33: -0.21103182 | F33: EUR | G33: -0.21103182 | H33: Drawdown2
A34: G42 | B34: New Space Capital Fund I | C34: 44442 | D34: =1.18*G34 -> -0.23965473 | F34: EUR | G34: =-203097.23*10^-6 -> -0.20309723 | H34: Drawdown3
A35: G42 | B35: New Space Capital Fund I | C35: 44623 | D35: =1.11*G35 -> -0.25893585 | F35: EUR | G35: =-233275.54*10^-6 -> -0.23327554 | H35: Drawdown4
A36: G42 | B36: New Space Capital Fund I | C36: 44784 | D36: =1.03*G36 -> 0.015224657 | F36: EUR | G36: =14781.22*10^-6 -> 0.01478122 | H36: Return of Capital
A37: G42 | B37: New Space Capital Fund I | C37: 44956 | D37: =9741387*10^-6*1.08341 -> 10.553916 | F37: EUR | G37: =9741387*10^-6 -> 9.741387 | H37: Return of Capital
A38: G42 | B38: New Space Capital Fund I | C38: 44956 | E38: =2728214.02*10^-6*1.08341 -> 2.9557744 | F38: EUR | G38: =NAV!L40*10^-6 -> 2.728214 | H38: Distribution | Actualization Interest
A39: G42 | B39: New Space Capital GP Com SCSp | C39: 44087 | D39: =-'S | 01 '!K40 -> -2.7058824 | F39: EUR | G39: -2.125 | H39: Drawdown1
A40: G42 | B40: Acies Investments Fund I, L.P. | C40: 44540 | D40: =G40 -> -2.8053125 | F40: USD | G40: -2.8053125 | H40: 1st Capital Call
A41: G42 | B41: Acies Investments Fund I, L.P. | C41: 44602 | D41: =G41 -> -3.4075 | F41: USD | G41: -3.4075 | H41: 2nd Capital Call
A42: G42 | B42: Acies Investments Fund I, L.P. | C42: 44683 | D42: =G42 -> -1.025775 | F42: USD | G42: -1.025775 | H42: Catch up Capital Call
A43: G42 | B43: Acies Investments Fund I, L.P. | C43: 44707 | D43: =G43 -> -3.388275 | F43: USD | G43: -3.388275 | H43: 3rd Capital Call
A44: G42 | B44: Acies Investments Fund I, L.P. | C44: 44875 | D44: =G44 -> -3.388275 | F44: USD | G44: -3.388275 | H44: 4th Capital Call

Sheet 1. IRR Equity
B2: IRR - Equity (Individual Investments)
B4: Date of NAV | C4: =D!D2 -> 45138 | J4: Investtment Level Summary | AC4: Overall Summary
B6: (in USD, Mn)
B7: Investment | C7: Payment date | D7: Contribution | E7: Distributions | F7: Remaining Value | G7: Combined | J7: Jollychic Holding Limited | K7: Mena Mobile Inc | L7: Flyr Inc | M7: Esyasoft Holding | N7: Beyond Limits | O7: ONT plc | P7: Heygears | Q7: Jysan Technologies | R7: Cerebras Systems Inc | S7: Endless Studios LLC | T7: Instadeep Limited | U7: X-fusion | V7: DriveNets | W7: vTv Therapeutics Inc. | X7: Honor Device Co Ltd | Y7: Applied AI Corporation Limited | Z7: eSpace | AA7: Tools for Humanity Corporation | AB7: WLD Tokens | AE7: Committed | AF7: Invested | AG7: Remaining Commitment | AH7: Distributions | AI7: Residual Value | AJ7: IRR | AK7: TVPI | AL7: RPI | AM7: DPI
B10: ='CF (Equity, Debt)'!C4 -> Jollychic Holding Limited | C10: ='CF (Equity, Debt)'!D4 -> 43470 | D10: ='CF (Equity, Debt)'!E4 -> -30 | G10: =SUM(D10:F10) -> -30 | H10: =IF(D10='CF (Equity, Debt)'!E4," ", "xxx") | J10: =D10 -> -30 | AJ10: 62
B11: ='CF (Equity, Debt)'!C5 -> Jollychic Holding Limited | C11: ='CF (Equity, Debt)'!D5 -> 43724 | D11: ='CF (Equity, Debt)'!E5 -> -20 | G11: =SUM(D11:F11) -> -20 | H11: =IF(D11='CF (Equity, Debt)'!E5," ", "xxx") | J11: =D11 -> -20
B12: ='CF (Equity, Debt)'!C6 -> Jollychic Holding Limited | C12: ='CF (Equity, Debt)'!D6 -> 43724 | D12: ='CF (Equity, Debt)'!E6 -> -15 | G12: =SUM(D12:F12) -> -15 | H12: =IF(D12='CF (Equity, Debt)'!E6," ", "xxx") | J12: =D12 -> -15 | AD12: ='S | 01 '!C10 -> Jollychic Holding Limited | AE12: ='S | 01 '!J10 -> 65 | AF12: =-SUMIF($B$7:$F$121,$AD12,$D$7:$D$121) -> 65 | AG12: =AE12-AF12 -> 0 | AH12: =SUMIF($B$7:$F$121,$AD12,$E$7:$E$121) -> 0 | AI12: =SUMIF($B$7:$F$121,$AD12,$F$7:$F$121) -> 0 | AJ12: =HLOOKUP(AD12,$J$7:$Z$77,$AJ$10,0) -> NM | AK12: =(AH12+AI12)/AF12 -> 0 | AL12: =AI12/AF12 -> 0 | AM12: =AH12/AF12 -> 0
B13: ='CF (Equity, Debt)'!C7 -> Mena Mobile Inc | C13: ='CF (Equity, Debt)'!D7 -> 43563 | D13: ='CF (Equity, Debt)'!E7 -> -8 | G13: =SUM(D13:F13) -> -8 | H13: =IF(D13='CF (Equity, Debt)'!E7," ", "xxx") | K13: =D13 -> -8 | AD13: ='S | 01 '!C11 -> Mena Mobile Inc | AE13: ='S | 01 '!J11 -> 8 | AF13: =-SUMIF($B$7:$F$121,$AD13,$D$7:$D$121) -> 8 | AG13: =AE13-AF13 -> 0 | AH13: =SUMIF($B$7:$F$121,$AD13,$E$7:$E$121) -> 0 | AI13: =SUMIF($B$7:$F$121,$AD13,$F$7:$F$121) -> 0 | AJ13: =HLOOKUP(AD13,$J$7:$Z$77,$AJ$10,0) -> NM | AK13: =(AH13+AI13)/AF13 -> 0 | AL13: =AI13/AF13 -> 0 | AM13: =AH13/AF13 -> 0
B14: ='CF (Equity, Debt)'!C8 -> Flyr Inc | C14: ='CF (Equity, Debt)'!D8 -> 43570 | D14: ='CF (Equity, Debt)'!E8 -> -4.9999981 | G14: =SUM(D14:F14) -> -4.9999981 | H14: =IF(D14='CF (Equity, Debt)'!E8," ", "xxx") | L14: =D14 -> -4.9999981 | AD14: ='S | 01 '!C12 -> Flyr Inc | AE14: ='S | 01 '!J12 -> 10 | AF14: =-SUMIF($B$7:$F$121,$AD14,$D$7:$D$121) -> 10 | AG14: =AE14-AF14 -> 0 | AH14: =SUMIF($B$7:$F$121,$AD14,$E$7:$E$121) -> 0 | AI14: =SUMIF($B$7:$F$121,$AD14,$F$7:$F$121) -> 78.08223 | AJ14: =HLOOKUP(AD14,$J$7:$Z$77,$AJ$10,0) -> 0.69797844 | AK14: =(AH14+AI14)/AF14 -> 7.808223 | AL14: =AI14/AF14 -> 7.808223 | AM14: =AH14/AF14 -> 0
B15: ='CF (Equity, Debt)'!C9 -> Flyr Inc | C15: ='CF (Equity, Debt)'!D9 -> 43915 | D15: ='CF (Equity, Debt)'!E9 -> -5.0000019 | G15: =SUM(D15:F15) -> -5.0000019 | H15: =IF(D15='CF (Equity, Debt)'!E9," ", "xxx") | L15: =D15 -> -5.0000019 | AD15: ='S | 01 '!C13 -> Esyasoft Holding | AE15: ='S | 01 '!J13 -> 2.5 | AF15: =-SUMIF($B$7:$F$121,$AD15,$D$7:$D$121) -> 2.5 | AG15: =AE15-AF15 -> 0 | AH15: =SUMIF($B$7:$F$121,$AD15,$E$7:$E$121) -> 5 | AI15: =SUMIF($B$7:$F$121,$AD15,$F$7:$F$121) -> 0 | AJ15: =HLOOKUP(AD15,$J$7:$Z$77,$AJ$10,0) -> 0.36091766 | AK15: =(AH15+AI15)/AF15 -> 2 | AL15: =AI15/AF15 -> 0 | AM15: =AH15/AF15 -> 2
B16: ='CF (Equity, Debt)'!C10 -> Esyasoft Holding | C16: ='CF (Equity, Debt)'!D10 -> 43870 | D16: ='CF (Equity, Debt)'!E10 -> -2.5 | G16: =SUM(D16:F16) -> -2.5 | H16: =IF(D16='CF (Equity, Debt)'!E10," ", "xxx") | M16: =D16 -> -2.5 | AD16: ='S | 01 '!C14 -> Beyond Limits | AE16: ='S | 01 '!J14 -> 90 | AF16: =-SUMIF($B$7:$F$121,$AD16,$D$7:$D$121) -> 90 | AG16: =AE16-AF16 -> 0 | AH16: =SUMIF($B$7:$F$121,$AD16,$E$7:$E$121) -> 0 | AI16: =SUMIF($B$7:$F$121,$AD16,$F$7:$F$121) -> 91.00154 | AJ16: =HLOOKUP(AD16,$J$7:$Z$77,$AJ$10,0) -> 0.0034190029 | AK16: =(AH16+AI16)/AF16 -> 1.0111282 | AL16: =AI16/AF16 -> 1.0111282 | AM16: =AH16/AF16 -> 0
B17: ='CF (Equity, Debt)'!C11 -> Beyond Limits | C17: ='CF (Equity, Debt)'!D11 -> 43879 | D17: ='CF (Equity, Debt)'!E11 -> -20 | G17: =SUM(D17:F17) -> -20 | H17: =IF(D17='CF (Equity, Debt)'!E11," ", "xxx") | N17: =D17 -> -20 | AD17: ='S | 01 '!C15 -> ONT plc | AE17: ='S | 01 '!J15 -> 141.47026 | AF17: =-SUMIF($B$7:$F$121,$AD17,$D$7:$D$121) -> 141.47026 | AG17: =AE17-AF17 -> 0 | AH17: =SUMIF($B$7:$F$121,$AD17,$E$7:$E$121) -> 0 | AI17: =SUMIF($B$7:$F$121,$AD17,$F$7:$F$121) -> 150.40044 | AJ17: =HLOOKUP(AD17,$J$7:$Z$77,$AJ$10,0) -> 0.019673982 | AK17: =(AH17+AI17)/AF17 -> 1.0631241 | AL17: =AI17/AF17 -> 1.0631241 | AM17: =AH17/AF17 -> 0
B18: ='CF (Equity, Debt)'!C12 -> Beyond Limits | C18: ='CF (Equity, Debt)'!D12 -> 43921 | D18: ='CF (Equity, Debt)'!E12 -> -30 | G18: =SUM(D18:F18) -> -30 | H18: =IF(D18='CF (Equity, Debt)'!E12," ", "xxx") | N18: =D18 -> -30 | AD18: ='S | 01 '!C16 -> Heygears | AE18: ='S | 01 '!J16 -> 60 | AF18: =-SUMIF($B$7:$F$121,$AD18,$D$7:$D$121) -> 60 | AG18: =AE18-AF18 -> 0 | AH18: =SUMIF($B$7:$F$121,$AD18,$E$7:$E$121) -> 0 | AI18: =SUMIF($B$7:$F$121,$AD18,$F$7:$F$121) -> 151.06943 | AJ18: =HLOOKUP(AD18,$J$7:$Z$77,$AJ$10,0) -> 0.41446041 | AK18: =(AH18+AI18)/AF18 -> 2.5178239 | AL18: =AI18/AF18 -> 2.5178239 | AM18: =AH18/AF18 -> 0
B19: ='CF (Equity, Debt)'!C13 -> Beyond Limits | C19: ='CF (Equity, Debt)'!D13 -> 43989 | D19: ='CF (Equity, Debt)'!E13 -> -30 | G19: =SUM(D19:F19) -> -30 | H19: =IF(D19='CF (Equity, Debt)'!E13," ", "xxx") | N19: =D19 -> -30 | AD19: ='S | 01 '!C17 -> Jysan Technologies | AE19: ='S | 01 '!J17 -> 20 | AF19: =-SUMIF($B$7:$F$121,$AD19,$D$7:$D$121) -> 20 | AG19: =AE19-AF19 -> 0 | AH19: =SUMIF($B$7:$F$121,$AD19,$E$7:$E$121) -> 0 | AI19: =SUMIF($B$7:$F$121,$AD19,$F$7:$F$121) -> 20 | AJ19: =HLOOKUP(AD19,$J$7:$Z$77,$AJ$10,0) -> 2.9802322e-09 | AK19: =(AH19+AI19)/AF19 -> 1 | AL19: =AI19/AF19 -> 1 | AM19: =AH19/AF19 -> 0
B20: ='CF (Equity, Debt)'!C14 -> Beyond Limits | C20: ='CF (Equity, Debt)'!D14 -> 44103 | D20: ='CF (Equity, Debt)'!E14 -> -10 | G20: =SUM(D20:F20) -> -10 | H20: =IF(D20='CF (Equity, Debt)'!E14," ", "xxx") | N20: =D20 -> -10 | AD20: ='S | 01 '!C18 -> Cerebras Systems Inc | AE20: ='S | 01 '!J18 -> 40 | AF20: =-SUMIF($B$7:$F$121,$AD20,$D$7:$D$121) -> 39.999983 | AG20: =AE20-AF20 -> 1.664e-05 | AH20: =SUMIF($B$7:$F$121,$AD20,$E$7:$E$121) -> 0 | AI20: =SUMIF($B$7:$F$121,$AD20,$F$7:$F$121) -> 39.999983 | AJ20: =HLOOKUP(AD20,$J$7:$Z$77,$AJ$10,0) -> 2.9802322e-09 | AK20: =(AH20+AI20)/AF20 -> 1 | AL20: =AI20/AF20 -> 1 | AM20: =AH20/AF20 -> 0
B21: ='CF (Equity, Debt)'!C15 -> ONT plc | C21: ='CF (Equity, Debt)'!D15 -> 43968 | D21: ='CF (Equity, Debt)'!E15 -> -50 | G21: =SUM(D21:F21) -> -50 | H21: =IF(D21='CF (Equity, Debt)'!E15," ", "xxx") | O21: =D21 -> -50 | AD21: ='S | 01 '!C19 -> Endless Studios LLC | AE21: ='S | 01 '!J19 -> 3 | AF21: =-SUMIF($B$7:$F$121,$AD21,$D$7:$D$121) -> 3 | AG21: =AE21-AF21 -> 0 | AH21: =SUMIF($B$7:$F$121,$AD21,$E$7:$E$121) -> 0 | AI21: =SUMIF($B$7:$F$121,$AD21,$F$7:$F$121) -> 3 | AJ21: =HLOOKUP(AD21,$J$7:$Z$77,$AJ$10,0) -> 2.9802322e-09 | AK21: =(AH21+AI21)/AF21 -> 1 | AL21: =AI21/AF21 -> 1 | AM21: =AH21/AF21 -> 0
B22: ='CF (Equity, Debt)'!C16 -> ONT plc | C22: ='CF (Equity, Debt)'!D16 -> 44006 | D22: ='CF (Equity, Debt)'!E16 -> -27.268351 | G22: =SUM(D22:F22) -> -27.268351 | H22: =IF(D22='CF (Equity, Debt)'!E16," ", "xxx") | O22: =D22 -> -27.268351 | AD22: ='S | 01 '!C20 -> Instadeep Limited | AE22: ='S | 01 '!J20 -> 5.0278212 | AF22: =-SUMIF($B$7:$F$121,$AD22,$D$7:$D$121) -> 5.0237202 | AG22: =AE22-AF22 -> 0.0041009961 | AH22: =SUMIF($B$7:$F$121,$AD22,$E$7:$E$121) -> 7.8207761 | AI22: =SUMIF($B$7:$F$121,$AD22,$F$7:$F$121) -> 0 | AJ22: =HLOOKUP(AD22,$J$7:$Z$77,$AJ$10,0) -> 0.3162033 | AK22: =(AH22+AI22)/AF22 -> 1.5567698 | AL22: =AI22/AF22 -> 0 | AM22: =AH22/AF22 -> 1.5567698
B23: ='CF (Equity, Debt)'!C17 -> ONT plc | C23: ='CF (Equity, Debt)'!D17 -> 43837 | D23: ='CF (Equity, Debt)'!E17 -> -18.109441 | G23: =SUM(D23:F23) -> -18.109441 | H23: =IF(D23='CF (Equity, Debt)'!E17," ", "xxx") | O23: =D23 -> -18.109441 | AD23: ='S | 01 '!C21 -> X-fusion | AE23: ='S | 01 '!J21 -> 493.5 | AF23: =-SUMIF($B$7:$F$121,$AD23,$D$7:$D$121) -> 493.50096 | AG23: =AE23-AF23 -> -0.0009562 | AH23: =SUMIF($B$7:$F$121,$AD23,$E$7:$E$121) -> 0 | AI23: =SUMIF($B$7:$F$121,$AD23,$F$7:$F$121) -> 408.28799 | AJ23: =HLOOKUP(AD23,$J$7:$Z$77,$AJ$10,0) -> -0.11544542 | AK23: =(AH23+AI23)/AF23 -> 0.82732969 | AL23: =AI23/AF23 -> 0.82732969 | AM23: =AH23/AF23 -> 0
B24: ='CF (Equity, Debt)'!C18 -> ONT plc | C24: ='CF (Equity, Debt)'!D18 -> 43990 | D24: ='CF (Equity, Debt)'!E18 -> -34.851687 | G24: =SUM(D24:F24) -> -34.851687 | H24: =IF(D24='CF (Equity, Debt)'!E18," ", "xxx") | O24: =D24 -> -34.851687 | AD24: ='S | 01 '!C22 -> DriveNets | AE24: ='S | 01 '!J22 -> 300 | AF24: =-SUMIF($B$7:$F$121,$AD24,$D$7:$D$121) -> 300 | AG24: =AE24-AF24 -> 0 | AH24: =SUMIF($B$7:$F$121,$AD24,$E$7:$E$121) -> 0 | AI24: =SUMIF($B$7:$F$121,$AD24,$F$7:$F$121) -> 300 | AJ24: =HLOOKUP(AD24,$J$7:$Z$77,$AJ$10,0) -> 2.9802322e-09 | AK24: =(AH24+AI24)/AF24 -> 1 | AL24: =AI24/AF24 -> 1 | AM24: =AH24/AF24 -> 0
B25: ='CF (Equity, Debt)'!C19 -> ONT plc | C25: ='CF (Equity, Debt)'!D19 -> 44315 | D25: ='CF (Equity, Debt)'!E19 -> -11.24078 | G25: =SUM(D25:F25) -> -11.24078 | H25: =IF(D25='CF (Equity, Debt)'!E19," ", "xxx") | O25: =D25 -> -11.24078 | AD25: ='S | 01 '!C23 -> vTv Therapeutics Inc. | AE25: ='S | 01 '!J23 -> 24.53125 | AF25: =-SUMIF($B$7:$F$121,$AD25,$D$7:$D$121) -> 24.53125 | AG25: =AE25-AF25 -> 0 | AH25: =SUMIF($B$7:$F$121,$AD25,$E$7:$E$121) -> 0 | AI25: =SUMIF($B$7:$F$121,$AD25,$F$7:$F$121) -> 7.0626663 | AJ25: =HLOOKUP(AD25,$J$7:$Z$77,$AJ$10,0) -> NM | AK25: =(AH25+AI25)/AF25 -> 0.28790487 | AL25: =AI25/AF25 -> 0.28790487 | AM25: =AH25/AF25 -> 0
B26: ='CF (Equity, Debt)'!C20 -> Heygears | C26: ='CF (Equity, Debt)'!D20 -> 44166 | D26: ='CF (Equity, Debt)'!E20 -> -60 | G26: =SUM(D26:F26) -> -60 | H26: =IF(D26='CF (Equity, Debt)'!E20," ", "xxx") | P26: =D26 -> -60 | AD26: ='S | 01 '!C24 -> Honor Device Co Ltd | AE26: ='S | 01 '!J24 -> 800 | AF26: =-SUMIF($B$7:$F$121,$AD26,$D$7:$D$121) -> 800 | AG26: =AE26-AF26 -> 0 | AH26: =SUMIF($B$7:$F$121,$AD26,$E$7:$E$121) -> 0 | AI26: =SUMIF($B$7:$F$121,$AD26,$F$7:$F$121) -> 817.18905 | AJ26: =HLOOKUP(AD26,$J$7:$Z$77,$AJ$10,0) -> 0.022479972 | AK26: =(AH26+AI26)/AF26 -> 1.0214863 | AL26: =AI26/AF26 -> 1.0214863 | AM26: =AH26/AF26 -> 0
B27: ='CF (Equity, Debt)'!C21 -> Jysan Technologies | C27: ='CF (Equity, Debt)'!D21 -> 44363 | D27: ='CF (Equity, Debt)'!E21 -> -20 | G27: =SUM(D27:F27) -> -20 | H27: =IF(D27='CF (Equity, Debt)'!E21," ", "xxx") | Q27: =D27 -> -20 | AD27: ='S | 01 '!C25 -> Applied AI Corporation Limited | AE27: ='S | 01 '!J25 -> 15 | AF27: =-SUMIF($B$7:$F$121,$AD27,$D$7:$D$121) -> 7.5 | AG27: =AE27-AF27 -> 7.5 | AH27: =SUMIF($B$7:$F$121,$AD27,$E$7:$E$121) -> 0 | AI27: =SUMIF($B$7:$F$121,$AD27,$F$7:$F$121) -> 7.5 | AJ27: =HLOOKUP(AD27,$J$7:$Z$77,$AJ$10,0) -> NM | AK27: =(AH27+AI27)/AF27 -> 1 | AL27: =AI27/AF27 -> 1 | AM27: =AH27/AF27 -> 0
B28: ='CF (Equity, Debt)'!C22 -> Cerebras Systems Inc | C28: ='CF (Equity, Debt)'!D22 -> 44488 | D28: ='CF (Equity, Debt)'!E22 -> -39.999983 | G28: =SUM(D28:F28) -> -39.999983 | H28: =IF(D28='CF (Equity, Debt)'!E22," ", "xxx") | R28: =D28 -> -39.999983 | AD28: ='S | 01 '!C26 -> eSpace | AE28: ='S | 01 '!J26 -> 15 | AF28: =-SUMIF($B$7:$F$121,$AD28,$D$7:$D$121) -> 15 | AG28: =AE28-AF28 -> 0 | AH28: =SUMIF($B$7:$F$121,$AD28,$E$7:$E$121) -> 0 | AI28: =SUMIF($B$7:$F$121,$AD28,$F$7:$F$121) -> 15 | AJ28: =HLOOKUP(AD28,$J$7:$Z$77,$AJ$10,0) -> NM | AK28: =(AH28+AI28)/AF28 -> 1 | AL28: =AI28/AF28 -> 1 | AM28: =AH28/AF28 -> 0
B29: ='CF (Equity, Debt)'!C23 -> Endless Studios LLC | C29: ='CF (Equity, Debt)'!D23 -> 44494 | D29: ='CF (Equity, Debt)'!E23 -> -3 | G29: =SUM(D29:F29) -> -3 | H29: =IF(D29='CF (Equity, Debt)'!E23," ", "xxx") | S29: =D29 -> -3 | AD29: ='S | 01 '!C27 -> Tools for Humanity Corporation | AE29: ='S | 01 '!J27 -> 14.999999 | AF29: =-SUMIF($B$7:$F$121,$AD29,$D$7:$D$121) -> 14.999999 | AG29: =AE29-AF29 -> 0 | AH29: =SUMIF($B$7:$F$121,$AD29,$E$7:$E$121) -> 0 | AI29: =SUMIF($B$7:$F$121,$AD29,$F$7:$F$121) -> 14.999999 | AJ29: =HLOOKUP(AD29,$J$7:$AC$77,$AJ$10,0) -> NM | AK29: =(AH29+AI29)/AF29 -> 1 | AL29: =AI29/AF29 -> 1 | AM29: =AH29/AF29 -> 0
B30: ='CF (Equity, Debt)'!C24 -> Instadeep Limited | C30: ='CF (Equity, Debt)'!D24 -> 44550 | D30: ='CF (Equity, Debt)'!E24 -> -5.0237202 | G30: =SUM(D30:F30) -> -5.0237202 | H30: =IF(D30='CF (Equity, Debt)'!E24," ", "xxx") | T30: =D30 -> -5.0237202 | AD30: ='S | 01 '!C28 -> WLD Tokens | AE30: ='S | 01 '!J28 -> 0.006875 | AF30: =-SUMIF($B$7:$F$121,$AD30,$D$7:$D$121) -> 0.006875 | AG30: =AE30-AF30 -> 0 | AH30: =SUMIF($B$7:$F$121,$AD30,$E$7:$E$121) -> 0 | AI30: =SUMIF($B$7:$F$121,$AD30,$F$7:$F$121) -> 15 | AJ30: =HLOOKUP(AD30,$J$7:$AC$77,$AJ$10,0) -> NM | AK30: =(AH30+AI30)/AF30 -> 2181.8182 | AL30: =AI30/AF30 -> 2181.8182 | AM30: =AH30/AF30 -> 0
B31: ='CF (Equity, Debt)'!C25 -> X-fusion | C31: ='CF (Equity, Debt)'!D25 -> 44574 | D31: ='CF (Equity, Debt)'!E25 -> -493.50096 | G31: =SUM(D31:F31) -> -493.50096 | H31: =IF(D31='CF (Equity, Debt)'!E25," ", "xxx") | U31: =D31 -> -493.50096
B32: ='CF (Equity, Debt)'!C26 -> DriveNets | C32: ='CF (Equity, Debt)'!D26 -> 44643 | D32: ='CF (Equity, Debt)'!E26 -> -200 | G32: =SUM(D32:F32) -> -200 | H32: =IF(D32='CF (Equity, Debt)'!E26," ", "xxx") | V32: =D32 -> -200
B33: ='CF (Equity, Debt)'!C27 -> DriveNets | C33: ='CF (Equity, Debt)'!D27 -> 44680 | D33: ='CF (Equity, Debt)'!E27 -> -100 | G33: =SUM(D33:F33) -> -100 | H33: =IF(D33='CF (Equity, Debt)'!E27," ", "xxx") | V33: =D33 -> -100 | AE33: =SUM(AE12:AE30) -> 2108.0362 | AF33: =SUM(AF12:AF30) -> 2100.533 | AG33: =SUM(AG12:AG30) -> 7.5031614 | AH33: =SUM(AH12:AH30) -> 12.820776 | AI33: =SUM(AI12:AI30) -> 2118.5933 | AJ33: =AE38 -> 0.0092234105 | AK33: =(AH33+AI33)/AF33 -> 1.0147015 | AL33: =AI33/AF33 -> 1.008598 | AM33: =AH33/AF33 -> 0.0061035822
B34: ='CF (Equity, Debt)'!C28 -> Esyasoft Holding | C34: ='CF (Equity, Debt)'!D28 -> 44691 | D34: ='CF (Equity, Debt)'!E28 -> 0 | E34: ='CF (Equity, Debt)'!F28 -> 5 | G34: =SUM(D34:F34) -> 5 | H34: =IF(D34='CF (Equity, Debt)'!E28," ", "xxx") | M34: =E34 -> 5 | AE34: =ROUND('S | 01 '!J30,2)=ROUND(AE33,2) -> TRUE | AF34: =ROUND('S | 01 '!K30,2)=ROUND(AF33,2) -> TRUE | AG34: =ROUND('S | 01 '!L30,2)=ROUND(AG33,2) -> TRUE | AH34: =ROUND('S | 01 '!M30,2)=ROUND(AH33,2) -> TRUE | AI34: =ROUND('S | 01 '!N30,2)=ROUND(AI33,2) -> TRUE | AJ34: =ROUND('S | 01 '!Q30,2)=ROUND(AJ33,2) -> TRUE | AK34: =ROUND('S | 01 '!P30,2)=ROUND(AK33,2) -> TRUE
B35: ='CF (Equity, Debt)'!C29 -> vTv Therapeutics Inc. | C35: ='CF (Equity, Debt)'!D29 -> 44712 | D35: ='CF (Equity, Debt)'!E29 -> -12.5 | G35: =SUM(D35:F35) -> -12.5 | H35: =IF(D35='CF (Equity, Debt)'!E29," ", "xxx") | W35: =D35 -> -12.5
B36: ='CF (Equity, Debt)'!C30 -> Honor Device Co Ltd | C36: ='CF (Equity, Debt)'!D30 -> 44769 | D36: ='CF (Equity, Debt)'!E30 -> -600 | G36: =SUM(D36:F36) -> -600 | H36: =IF(D36='CF (Equity, Debt)'!E30," ", "xxx") | X36: =D36 -> -600
B37: ='CF (Equity, Debt)'!C31 -> Honor Device Co Ltd | C37: ='CF (Equity, Debt)'!D31 -> 44849 | D37: ='CF (Equity, Debt)'!E31 -> -200 | G37: =SUM(D37:F37) -> -200 | X37: =D37 -> -200
B38: ='CF (Equity, Debt)'!C32 -> Applied AI Corporation Limited | C38: ='CF (Equity, Debt)'!D32 -> 44861 | D38: ='CF (Equity, Debt)'!E32 -> -4.75 | G38: =SUM(D38:F38) -> -4.75 | Y38: =D38 -> -4.75 | AD38: XIRR | AE38: =XIRR(G10:G85,C10:C85) -> 0.0092234105
B39: ='CF (Equity, Debt)'!C33 -> eSpace | C39: ='CF (Equity, Debt)'!D33 -> 44892 | D39: ='CF (Equity, Debt)'!E33 -> -15 | G39: =SUM(D39:F39) -> -15 | Z39: =G39 -> -15 | AD39: TVPI | AE39: =SUM(AH12:AI28)/SUM(AF12:AF28) -> 1.0076182 | AF39: =AE39=AK33 -> FALSE
B40: ='CF (Equity, Debt)'!C34 -> vTv Therapeutics Inc. | C40: ='CF (Equity, Debt)'!D34 -> 44985 | D40: ='CF (Equity, Debt)'!E34 -> -12.03125 | G40: =SUM(D40:F40) -> -12.03125 | W40: =G40 -> -12.03125 | AD40: RPI | AE40: =SUM(AI12:AI28)/SUM(AF12:AF28) -> 1.0014707 | AF40: =AE40=AL33 -> FALSE
B41: ='CF (Equity, Debt)'!C35 -> Tools for Humanity Corporation | C41: ='CF (Equity, Debt)'!D35 -> 45075 | D41: ='CF (Equity, Debt)'!E35 -> -14.999999 | G41: =SUM(D41:F41) -> -14.999999 | AA41: =G41 -> -14.999999 | AD41: DPI | AE41: =SUM(AH12:AH28)/SUM(AF12:AF28) -> 0.0061475019 | AF41: =AE41=AM33 -> FALSE
B42: ='CF (Equity, Debt)'!C36 -> WLD Tokens | C42: ='CF (Equity, Debt)'!D36 -> 45075 | D42: ='CF (Equity, Debt)'!E36 -> -0.005875 | G42: =SUM(D42:F42) -> -0.005875 | AB42: =G42 -> -0.005875
B43: ='CF (Equity, Debt)'!C37 -> WLD Tokens | C43: ='CF (Equity, Debt)'!D37 -> 45114 | D43: ='CF (Equity, Debt)'!E37 -> -0.001 | G43: =SUM(D43:F43) -> -0.001 | AB43: =G43 -> -0.001
B44: ='CF (Equity, Debt)'!C38 -> Applied AI Corporation Limited | C44: ='CF (Equity, Debt)'!D38 -> 45121 | D44: ='CF (Equity, Debt)'!E38 -> -2.75 | G44: =SUM(D44:F44) -> -2.75 | Y44: =G44 -> -2.75
B45: ='CF (Equity, Debt)'!C39 -> Instadeep Limited | C45: ='CF (Equity, Debt)'!D39 -> 45138 | D45: ='CF (Equity, Debt)'!E39 -> 0 | E45: ='CF (Equity, Debt)'!F39 -> 7.8207761 | G45: =SUM(D45:F45) -> 7.8207761 | T45: =G45 -> 7.8207761
B47: =NAV!B9 -> Jollychic Holding Limited | C47: =$C$4 -> 45138 | F47: =NAV!E9 -> 0 | G47: =SUM(D47:F47) -> 0 | J47: =F47 -> 0
B48: =NAV!B10 -> Mena Mobile Inc | C48: =$C$4 -> 45138 | F48: =NAV!E10 -> 0 | G48: =SUM(D48:F48) -> 0 | K48: =F48 -> 0
B49: =NAV!B11 -> Flyr Inc | C49: =$C$4 -> 45138 | F49: =NAV!E11 -> 78.08223 | G49: =SUM(D49:F49) -> 78.08223 | L49: =F49 -> 78.08223
B50: =NAV!B12 -> Esyasoft Holding | C50: =$C$4 -> 45138 | F50: =NAV!E12 -> 0 | G50: =SUM(D50:F50) -> 0
B51: =NAV!B13 -> Beyond Limits | C51: =$C$4 -> 45138 | F51: =NAV!E13 -> 91.00154 | G51: =SUM(D51:F51) -> 91.00154 | N51: =F51 -> 91.00154
B52: =NAV!B14 -> ONT plc | C52: =$C$4 -> 45138 | F52: =NAV!E14 -> 150.40044 | G52: =SUM(D52:F52) -> 150.40044 | O52: =F52 -> 150.40044
B53: =NAV!B15 -> Heygears | C53: =$C$4 -> 45138 | F53: =NAV!E15 -> 151.06943 | G53: =SUM(D53:F53) -> 151.06943 | P53: =F53 -> 151.06943
B54: =NAV!B16 -> Jysan Technologies | C54: =$C$4 -> 45138 | F54: =NAV!E16 -> 20 | G54: =SUM(D54:F54) -> 20 | Q54: =F54 -> 20
B55: =NAV!B17 -> Cerebras Systems Inc | C55: =$C$4 -> 45138 | F55: =NAV!E17 -> 39.999983 | G55: =SUM(D55:F55) -> 39.999983 | R55: =F55 -> 39.999983
B56: =NAV!B18 -> Endless Studios LLC | C56: =$C$4 -> 45138 | F56: =NAV!E18 -> 3 | G56: =SUM(D56:F56) -> 3 | S56: =F56 -> 3
B57: =NAV!B19 -> Instadeep Limited | C57: =$C$4 -> 45138 | F57: =NAV!E19 -> 0 | G57: =SUM(D57:F57) -> 0 | T57: =F57 -> 0
B58: =NAV!B20 -> X-fusion | C58: =$C$4 -> 45138 | F58: =NAV!E20 -> 408.28799 | G58: =SUM(D58:F58) -> 408.28799 | U58: =F58 -> 408.28799
B59: =NAV!B21 -> DriveNets | C59: =$C$4 -> 45138 | F59: =NAV!E21 -> 300 | G59: =SUM(D59:F59) -> 300 | V59: =F59 -> 300
B60: =NAV!B22 -> vTv Therapeutics Inc. | C60: =$C$4 -> 45138 | F60: =NAV!E22 -> 7.0626663 | G60: =SUM(D60:F60) -> 7.0626663 | W60: =F60 -> 7.0626663
B61: =NAV!B23 -> Honor Device Co Ltd | C61: =$C$4 -> 45138 | F61: =NAV!E23 -> 817.18905 | G61: =SUM(D61:F61) -> 817.18905 | X61: =F61 -> 817.18905
B62: =NAV!B24 -> Applied AI Corporation Limited | C62: =$C$4 -> 45138 | F62: =NAV!E24 -> 7.5 | G62: =SUM(D62:F62) -> 7.5 | Y62: =F62 -> 7.5
B63: =NAV!B25 -> eSpace | C63: =$C$4 -> 45138 | F63: =NAV!E25 -> 15 | G63: =SUM(D63:F63) -> 15 | Z63: =G63 -> 15
B64: =NAV!B26 -> Tools for Humanity Corporation | C64: =$C$4 -> 45138 | F64: =NAV!E26 -> 14.999999 | G64: =SUM(D64:F64) -> 14.999999 | AA64: =G64 -> 14.999999
B65: =NAV!B27 -> WLD Tokens | C65: =$C$4 -> 45138 | F65: =NAV!E27 -> 15 | G65: =SUM(D65:F65) -> 15 | AB65: =G65 -> 15
I68: IRR | J68: =IF(ISERROR(XIRR(J10:J64,$C$10:$C$64)),"NM", XIRR(J10:J64,$C$10:$C$64)) -> NM | K68: =IF(ISERROR(XIRR(K13:K64,$C$13:$C$64)),"NM", XIRR(K13:K64,$C$13:$C$64)) -> NM | L68: =IF(ISERROR(XIRR(L14:L64,$C$14:$C$64)),"NM", XIRR(L14:L64,$C$14:$C$64)) -> 0.69797844 | M68: =IF(ISERROR(XIRR(M16:M64,$C$16:$C$64)),"NM", XIRR(M16:M64,$C$16:$C$64)) -> 0.36091766 | N68: =IF(ISERROR(XIRR(N17:N64,$C$17:$C$64)),"NM", XIRR(N17:N64,$C$17:$C$64)) -> 0.0034190029 | O68: =IF(ISERROR(XIRR(O21:O64,$C$21:$C$64)),"NM", XIRR(O21:O64,$C$21:$C$64)) -> 0.019673982 | P68: =IF(ISERROR(XIRR(P26:P64,$C$26:$C$64)),"NM", XIRR(P26:P64,$C$26:$C$64)) -> 0.41446041 | Q68: =IF(ISERROR(XIRR(Q27:Q64,$C$27:$C$64)),"NM", XIRR(Q27:Q64,$C$27:$C$64)) -> 2.9802322e-09 | R68: =IF(ISERROR(XIRR(R28:R64,$C$28:$C$64)),"NM", XIRR(R28:R64,$C$28:$C$64)) -> 2.9802322e-09 | S68: =IF(ISERROR(XIRR(S29:S64,$C$29:$C$64)),"NM", XIRR(S29:S64,$C$29:$C$64)) -> 2.9802322e-09 | T68: =IF(ISERROR(XIRR(T30:T64,$C$30:$C$64)),"NM", XIRR(T30:T64,$C$30:$C$64)) -> 0.3162033 | U68: =IF(ISERROR(XIRR(U31:U64,$C$31:$C$64)),"NM", XIRR(U31:U64,$C$31:$C$64)) -> -0.11544542 | V68: =IF(ISERROR(XIRR(V32:V64,$C$32:$C$64)),"NM", XIRR(V32:V64,$C$32:$C$64)) -> 2.9802322e-09 | W68: =IF(ISERROR(XIRR(W35:W64,$C$35:$C$64)),"NM", "NM") -> NM | X68: =IF(ISERROR(XIRR(X36:X64,$C$36:$C$64)),"NM", XIRR(X36:X64,$C$36:$C$64)) -> 0.022479972 | Y68: =IF(ISERROR(XIRR(Y38:Y64,$C$38:$C$64)),"NM", "NM") -> NM | Z68: =IF(ISERROR(XIRR(Z39:Z64,$C$39:$C$64)),"NM", "NM") -> NM | AA68: =IF(ISERROR(XIRR(AA41:AA64,$C$41:$C$64)),"NM", "NM") -> NM | AB68: =IF(ISERROR(XIRR(AB42:AB64,$C$42:$C$64)),"NM", "NM") -> NM
G69: =SUM(J69:AC69)-'S | 01 '!K30 -> 0 | H69: =SUM(J69:AC69)='S | 01 '!K30 -> TRUE | I69: PIC | J69: =-SUMIF(J$10:J$45,"<0",J$10:J$45) -> 65 | K69: =-SUMIF(K$10:K$45,"<0",K$10:K$45) -> 8 | L69: =-SUMIF(L$10:L$45,"<0",L$10:L$45) -> 10 | M69: =-SUMIF(M$10:M$45,"<0",M$10:M$45) -> 2.5 | N69: =-SUMIF(N$10:N$45,"<0",N$10:N$45) -> 90 | O69: =-SUMIF(O$10:O$45,"<0",O$10:O$45) -> 141.47026 | P69: =-SUMIF(P$10:P$45,"<0",P$10:P$45) -> 60 | Q69: =-SUMIF(Q$10:Q$45,"<0",Q$10:Q$45) -> 20 | ... AB69: =-SUMIF(AB$10:AB$45,"<0",AB$10:AB$45) -> 0.006875
G70: =ROUND(SUM(J70:Z70),2)-ROUND('S | 01 '!M30,2) -> 0 | H70: =ROUND(SUM(J70:Z70),2)=ROUND('S | 01 '!M30,2) -> TRUE | I70: Dist | J70: =SUMIF(J$10:J$45,">0",J$10:J$45) -> 0 | K70: =SUMIF(K$10:K$45,">0",K$10:K$45) -> 0 | L70: =SUMIF(L$10:L$45,">0",L$10:L$45) -> 0 | M70: =SUMIF(M$10:M$45,">0",M$10:M$45) -> 5 | N70: =SUMIF(N$10:N$45,">0",N$10:N$45) -> 0 | O70: =SUMIF(O$10:O$45,">0",O$10:O$45) -> 0 | P70: =SUMIF(P$10:P$45,">0",P$10:P$45) -> 0 | Q70: =SUMIF(Q$10:Q$45,">0",Q$10:Q$45) -> 0 | ... AB70: =SUMIF(AB$10:AB$45,">0",AB$10:AB$45) -> 0
G71: =ROUND(SUM(J71:AC71),2)-ROUND('S | 01 '!N30,2) -> 0 | H71: =ROUND(SUM(J71:AC71),2)=ROUND('S | 01 '!N30,2) -> TRUE | I71: RV | J71: =SUM(J$47:J$65) -> 0 | K71: =SUM(K$47:K$65) -> 0 | L71: =SUM(L$47:L$65) -> 78.08223 | M71: =SUM(M$47:M$65) -> 0 | N71: =SUM(N$47:N$65) -> 91.00154 | O71: =SUM(O$47:O$65) -> 150.40044 | P71: =SUM(P$47:P$65) -> 151.06943 | Q71: =SUM(Q$47:Q$65) -> 20 | ... AB71: =SUM(AB$47:AB$65) -> 15
I72: TVPI | J72: =(J70+J71)/J69 -> 0 | K72: =(K70+K71)/K69 -> 0 | L72: =(L70+L71)/L69 -> 7.808223 | M72: =(M70+M71)/M69 -> 2 | N72: =(N70+N71)/N69 -> 1.0111282 | O72: =(O70+O71)/O69 -> 1.0631241 | P72: =(P70+P71)/P69 -> 2.5178239 | Q72: =(Q70+Q71)/Q69 -> 1 | ... AB72: =(AB70+AB71)/AB69 -> 2181.8182
I73: DPI | J73: =J70/J69 -> 0 | K73: =K70/K69 -> 0 | L73: =L70/L69 -> 0 | M73: =M70/M69 -> 2 | N73: =N70/N69 -> 0 | O73: =O70/O69 -> 0 | P73: =P70/P69 -> 0 | Q73: =Q70/Q69 -> 0 | ... AB73: =AB70/AB69 -> 0
I74: RVPI | J74: =J71/J69 -> 0 | K74: =K71/K69 -> 0 | L74: =L71/L69 -> 7.808223 | M74: =M71/M69 -> 0 | N74: =N71/N69 -> 1.0111282 | O74: =O71/O69 -> 1.0631241 | P74: =P71/P69 -> 2.5178239 | Q74: =Q71/Q69 -> 1 | ... AB74: =AB71/AB69 -> 2181.8182

Sheet 2. IRR Debt
B2: IRR - Debt
B4: Date of NAV | C4: =D!D2 -> 45138 | I4: Investment Level Summary | P4: Overall Summary
B6: USD Millions
B7: Investment | C7: Payment date | D7: Contributions | E7: Distributions | F7: Residual Value | G7: Combined | K7: Contribution | L7: Distribution | M7: Residual Value | N7: Combined | Q7: Committed | R7: Invested | S7: Remaining Commitment | T7: Distributions | U7: Residual Value | V7: IRR | W7: TVPI | X7: RPI | Y7: DPI
B8: Debt Investments
B9: ='CF (Equity, Debt)'!C42 -> Glass Earth Holdings LLC | C9: ='CF (Equity, Debt)'!D42 -> 43635 | D9: ='CF (Equity, Debt)'!E42 -> -8 | G9: =SUM(D9:F9) -> -8 | I9: =B9 -> Glass Earth Holdings LLC | J9: =C9 -> 43635 | K9: =D9 -> -8 | N9: =SUM(K9:M9) -> -8 | P9: Glass Earth Holdings LLC | Q9: =R9 -> 8 | R9: =-D9 -> 8 | S9: 0 | T9: =E9 -> 0 | U9: =F14 -> 0 | V9: =J12 -> NM | W9: =(T9+U9)/R9 -> 0 | X9: =U9/R9 -> 0 | Y9: =T9/R9 -> 0
B10: ='CF (Equity, Debt)'!C43 -> Mena Mobile Inc (Debt) | C10: ='CF (Equity, Debt)'!D43 -> 44293 | D10: ='CF (Equity, Debt)'!E43 -> -2.353982 | G10: =SUM(D10:F10) -> -2.353982 | I10: =B14 -> Glass Earth Holdings LLC | J10: =C14 -> 45138 | M10: =F14 -> 0 | N10: =SUM(K10:M10) -> 0 | P10: Mena Mobile Inc (Debt) | Q10: =R10 -> 2.353982 | R10: =-D10 -> 2.353982 | S10: 0 | T10: =E10 -> 0 | U10: =F15 -> 2.353982 | V10: =J22:J22 -> 2.9802322e-09 | W10: =(T10+U10)/R10 -> 1 | X10: =U10/R10 -> 1 | Y10: =T10/R10 -> 0
B11: ='CF (Equity, Debt)'!C44 -> Esyasoft Holding (Debt) | C11: ='CF (Equity, Debt)'!D44 -> 44384 | D11: ='CF (Equity, Debt)'!E44 -> -0.411765 | G11: =SUM(D11:F11) -> -0.411765 | P11: Esyasoft Holding (Debt) | Q11: =R11 -> 0.411765 | R11: =-D11 -> 0.411765 | S11: 0 | T11: =E12 -> 0.47078465 | U11: =F16 -> 0 | V11: =J31 -> 0.075277027 | W11: =(T11+U11)/R11 -> 1.1433333 | X11: =U11/R11 -> 0 | Y11: =T11/R11 -> 1.1433333
B12: ='CF (Equity, Debt)'!C45 -> Esyasoft Holding (Debt) | C12: ='CF (Equity, Debt)'!D45 -> 44902 | D12: ='CF (Equity, Debt)'!E45 -> 0 | E12: ='CF (Equity, Debt)'!F45 -> 0.47078465 | G12: =SUM(D12:F12) -> 0.47078465 | I12: XIRR | J12: =IF(ISERROR(XIRR(N9:N10,J9:J10)),"NM",XIRR(N9:N10,J9:J10)) -> NM | L12: Contributions | Q12: =SUM(Q9:Q11) -> 10.765747 | R12: =SUM(R9:R11) -> 10.765747 | S12: =SUM(S9:S11) -> 0 | T12: =SUM(T9:T11) -> 0.47078465 | U12: =SUM(U9:U11) -> 2.353982 | V12: =XIRR(G9:G16,C9:C16) -> -0.32476586 | W12: =(T12+U12)/R12 -> 0.26238464 | X12: =U12/R12 -> 0.21865478 | Y12: =T12/R12 -> 0.043729864
I13: TVPI | J13: =SUM(L9:M10)/-SUM(K9:K10) -> 0 | L13: Distributions
B14: =B9 -> Glass Earth Holdings LLC | C14: =$C$4 -> 45138 | F14: =VLOOKUP(B14,NAV!$B$32:$E$34,4,0) -> 0 | G14: =SUM(D14:F14) -> 0 | I14: RPI | J14: =SUM(M9:M10)/-SUM(K9:K10) -> 0 | L14: Residual Value
B15: =B10 -> Mena Mobile Inc (Debt) | C15: =$C$4 -> 45138 | F15: =VLOOKUP(B15,NAV!$B$32:$E$34,4,0) -> 2.353982 | G15: =SUM(D15:F15) -> 2.353982 | I15: DPI | J15: =SUM(L9:L10)/-SUM(K9:K10) -> 0 | P15: XIRR | Q15: =XIRR(G9:G18,C9:C18) -> -0.32476586
B16: =B11 -> Esyasoft Holding (Debt) | C16: =$C$4 -> 45138 | F16: =VLOOKUP(B16,NAV!$B$32:$E$34,4,0) -> 0 | G16: =SUM(D16:F16) -> 0 | P16: TVPI | Q16: =SUM(T9:U11)/SUM(R9:R11) -> 0.26238464
P17: RPI | Q17: =SUM(U9:U11)/SUM(R9:R11) -> 0.21865478
P18: DPI | Q18: =SUM(T9:T11)/SUM(R9:R11) -> 0.043729864
I19: =B10 -> Mena Mobile Inc (Debt) | J19: =C10 -> 44293 | K19: -2.353982 | N19: =SUM(K19:M19) -> -2.353982
I20: =B15 -> Mena Mobile Inc (Debt) | J20: =C15 -> 45138 | M20: 2.353982 | N20: =SUM(K20:M20) -> 2.353982
I22: XIRR | J22: =IF(ISERROR(XIRR(N19:N20,J19:J20)),"NM",XIRR(N19:N20,J19:J20)) -> 2.9802322e-09 | L22: Contributions
I23: TVPI | J23: =SUM(L19:M20)/-SUM(K19:K20) -> 1 | L23: Distributions
I24: RPI | J24: =SUM(M19:M20)/-SUM(K19:K20) -> 1 | L24: Residual Value
I25: DPI | J25: =SUM(L19:L20)/-SUM(K19:K20) -> 0
I28: =B11 -> Esyasoft Holding (Debt) | J28: =C11 -> 44384 | K28: -0.411765 | N28: =SUM(K28:M28) -> -0.411765
I29: =B16 -> Esyasoft Holding (Debt) | J29: ='CF (Equity, Debt)'!D45 -> 44902 | M29: 0.45643868 | N29: =SUM(K29:M29) -> 0.45643868
I31: XIRR | J31: =IF(ISERROR(XIRR(N28:N29,J28:J29)),"NM",XIRR(N28:N29,J28:J29)) -> 0.075277027 | L31: Contributions
I32: TVPI | J32: =SUM(L28:M29)/-SUM(K28:K29) -> 1.1084932 | L32: Distributions
I33: RPI | J33: =SUM(M28:M29)/-SUM(K28:K29) -> 1.1084932 | L33: Residual Value
I34: DPI | J34: =SUM(L28:L29)/-SUM(K28:K29) -> 0

Sheet 3. IRR Funds
B2: IRR - FUNDS | E2: Test | F2: =COUNTA(B8:B49)=COUNTA('CF (Funds)'!B3:B44) -> TRUE
B4: Date of NAV | C4: =D!D2 -> 45138 | I4: Fund Level Summary | P4: Overall Summary
B6: USD Millions
B7: Investment | C7: Payment date | D7: Contributions | E7: Distributions | F7: Residual Value | G7: Combined | K7: Contribution | L7: Distribution | M7: Residual Value | N7: Combined | Q7: Committed | R7: Invested | S7: Remaining Commitment | T7: Distributions | U7: Residual Value | V7: IRR | W7: TVPI | X7: RPI | Y7: DPI
B8: ='CF (Funds)'!B3 -> Sinovation Disrupt Fund, L.P. | C8: ='CF (Funds)'!C3 -> 44153 | D8: ='CF (Funds)'!D3 -> -10.5 | E8: ='CF (Funds)'!E3 -> 0 | G8: =SUM(D8:F8) -> -10.5 | P8: Funds Investments
B9: ='CF (Funds)'!B4 -> Sinovation Disrupt Fund, L.P. | C9: ='CF (Funds)'!C4 -> 44238 | D9: ='CF (Funds)'!D4 -> 4.214027 | E9: ='CF (Funds)'!E4 -> 0 | G9: =SUM(D9:F9) -> 4.214027 | I9: =B37 -> New Space Capital Fund I | J9: =C37 -> 44087 | K9: =D37 -> -20.917553 | L9: =E37 -> 0 | M9: =F37 -> 0 | N9: =SUM(K9:M9) -> -20.917553 | P9: New Space Capital Fund I | Q9: ='S | 01 '!J39 -> 28.336808 | R9: =-SUMIF($B$7:$F$105,$P9,$D$7:$D$105) -> 11.058035 | S9: =Q9-R9 -> 17.278774 | T9: =SUMIF($B$7:$F$105,$P9,$E$7:$E$105) -> 2.9557744 | U9: =SUMIF($B$7:$F$105,$P9,$F$7:$F$105) -> 13.390399 | V9: =J18 -> 0.08799049 | W9: =(T9+U9)/R9 -> 1.4782169 | X9: =U9/R9 -> 1.2109203 | Y9: =T9/R9 -> 0.26729654
B10: ='CF (Funds)'!B5 -> Sinovation Disrupt Fund, L.P. | C10: ='CF (Funds)'!C5 -> 44238 | D10: ='CF (Funds)'!D5 -> 0 | E10: ='CF (Funds)'!E5 -> 0.05044835 | G10: =SUM(D10:F10) -> 0.05044835 | I10: =B38 -> New Space Capital Fund I | J10: =C38 -> 44287 | K10: =D38 -> -0.21103182 | L10: =E38 -> 0 | M10: =F38 -> 0 | N10: =SUM(K10:M10) -> -0.21103182 | P10: New Space Capital GP Com SCSp | Q10: ='S | 01 '!J40 -> 2.7058824 | R10: =-SUMIF($B$7:$F$105,$P10,$D$7:$D$105) -> 2.7058824 | S10: =Q10-R10 -> 0 | T10: =SUMIF($B$7:$F$105,$P10,$E$7:$E$105) -> 0 | U10: =SUMIF($B$7:$F$105,$P10,$F$7:$F$105) -> 3.276608 | V10: 0 | W10: =(T10+U10)/R10 -> 1.2109203 | X10: =U10/R10 -> 1.2109203 | Y10: =T10/R10 -> 0
B11: ='CF (Funds)'!B6 -> Sinovation Disrupt Fund, L.P. | C11: ='CF (Funds)'!C6 -> 44285 | D11: ='CF (Funds)'!D6 -> -6.433746 | E11: ='CF (Funds)'!E6 -> 0 | G11: =SUM(D11:F11) -> -6.433746 | I11: =B39 -> New Space Capital Fund I | J11: =C39 -> 44442 | K11: =D39 -> -0.23965473 | L11: =E39 -> 0 | M11: =F39 -> 0 | N11: =SUM(K11:M11) -> -0.23965473 | P11: North Summit Capital Fund | Q11: ='S | 01 '!J41 -> 300 | R11: =-SUMIF($B$7:$F$105,$P11,$D$7:$D$105) -> 83.214653 | S11: =Q11-R11+T11 -> 217.81331 | T11: =SUMIF($B$7:$F$105,$P11,$E$7:$E$105) -> 1.027961 | U11: =SUMIF($B$7:$F$105,$P11,$F$7:$F$105) -> 81.695786 | V11: =J50 -> -0.0021562932 | W11: =(T11+U11)/R11 -> 0.99410073 | X11: =U11/R11 -> 0.9817476 | Y11: =T11/R11 -> 0.012353125
B12: ='CF (Funds)'!B7 -> Sinovation Disrupt Fund, L.P. | C12: ='CF (Funds)'!C7 -> 44269 | D12: ='CF (Funds)'!D7 -> 1.1352074 | E12: ='CF (Funds)'!E7 -> 0 | G12: =SUM(D12:F12) -> 1.1352074 | I12: =B40 -> New Space Capital Fund I | J12: =C40 -> 44623 | K12: =D40 -> -0.25893585 | L12: =E40 -> 0 | M12: =F40 -> 0 | N12: =SUM(K12:M12) -> -0.25893585 | P12: Sinovation Disrupt Fund, L.P. | Q12: ='S | 01 '!J42 -> 50 | R12: =-SUMIF($B$7:$F$105,$P12,$D$7:$D$105) -> 20.74471 | S12: =Q12-R12 -> 29.25529 | T12: =SUMIF($B$7:$F$105,$P12,$E$7:$E$105) -> 0.44382835 | U12: =SUMIF($B$7:$F$105,$P12,$F$7:$F$105) -> 19.244515 | V12: =J73 -> -0.023361704 | W12: =(T12+U12)/R12 -> 0.94907778 | X12: =U12/R12 -> 0.92768301 | Y12: =T12/R12 -> 0.021394772
B13: ='CF (Funds)'!B8 -> Sinovation Disrupt Fund, L.P. | C13: ='CF (Funds)'!C8 -> 44269 | D13: ='CF (Funds)'!D8 -> 0 | E13: ='CF (Funds)'!E8 -> 0.0259 | G13: =SUM(D13:F13) -> 0.0259 | I13: =B41 -> New Space Capital Fund I | J13: =C41 -> 44784 | K13: =D41 -> 0.015224657 | L13: =E41 -> 0 | M13: =F41 -> 0 | N13: =SUM(K13:M13) -> 0.015224657 | P13: Acies Investments Fund I, L.P. | Q13: ='S | 01 '!J43 -> 17.1125 | R13: =-SUMIF($B$7:$F$105,$P13,$D$7:$D$105) -> 14.015137 | S13: =Q13-R13 -> 3.0973625 | T13: =SUMIF($B$7:$F$105,$P13,$E$7:$E$105) -> 0 | U13: =SUMIF($B$7:$F$105,$P13,$F$7:$F$105) -> 13.307625 | V13: =J85 -> -0.04112356 | W13: =(T13+U13)/R13 -> 0.94951798 | X13: =U13/R13 -> 0.94951798 | Y13: =T13/R13 -> 0
B14: ='CF (Funds)'!B9 -> Sinovation Disrupt Fund, L.P. | C14: ='CF (Funds)'!C9 -> 44483 | D14: ='CF (Funds)'!D9 -> -7.567138 | E14: ='CF (Funds)'!E9 -> 0 | G14: =SUM(D14:F14) -> -7.567138 | I14: =B42 -> New Space Capital Fund I | J14: =C42 -> 44956 | K14: =D42 -> 10.553916 | L14: =E42 -> 0 | M14: =F42 -> 0 | N14: =SUM(K14:M14) -> 10.553916
B15: ='CF (Funds)'!B10 -> Sinovation Disrupt Fund, L.P. | C15: ='CF (Funds)'!C10 -> 44554 | D15: ='CF (Funds)'!D10 -> -7.385016 | E15: ='CF (Funds)'!E10 -> 0 | G15: =SUM(D15:F15) -> -7.385016 | I15: =B43 -> New Space Capital Fund I | J15: =C43 -> 44956 | K15: =D43 -> 0 | L15: =E43 -> 2.9557744 | M15: =F43 -> 0 | N15: =SUM(K15:M15) -> 2.9557744 | P15: Total | Q15: =SUM(Q9:Q14) -> 398.15519 | R15: =SUM(R9:R14) -> 131.73842 | S15: =SUM(S9:S14) -> 267.44473 | T15: =SUM(T9:T14) -> 4.4275637 | U15: =SUM(U9:U14) -> 130.91493 | V15: =XIRR(G8:G60,C8:C60) -> 0.010083666 | W15: =(T15+U15)/R15 -> 1.0273578 | X15: =U15/R15 -> 0.99374909 | Y15: =T15/R15 -> 0.033608751
B16: ='CF (Funds)'!B11 -> Sinovation Disrupt Fund, L.P. | C16: ='CF (Funds)'!C11 -> 44554 | D16: ='CF (Funds)'!D11 -> 4.0733456 | E16: ='CF (Funds)'!E11 -> 0 | G16: =SUM(D16:F16) -> 4.0733456 | I16: New Space Capital Fund I | J16: =$C$4 -> 45138 | M16: =F52 -> 13.390399 | N16: =SUM(K16:M16) -> 13.390399
B17: ='CF (Funds)'!B12 -> Sinovation Disrupt Fund, L.P. | C17: ='CF (Funds)'!C12 -> 44554 | D17: ='CF (Funds)'!D12 -> 0 | E17: ='CF (Funds)'!E12 -> 0.139694 | G17: =SUM(D17:F17) -> 0.139694
B18: ='CF (Funds)'!B13 -> Sinovation Disrupt Fund, L.P. | C18: ='CF (Funds)'!C13 -> 44703 | D18: ='CF (Funds)'!D13 -> 5.673074 | E18: ='CF (Funds)'!E13 -> 0 | G18: =SUM(D18:F18) -> 5.673074 | I18: XIRR | J18: =XIRR(N9:N16,J9:J16) -> 0.08799049 | L18: Contributions | M18: =-SUM(K9:K16)='S | 01 '!K39 -> TRUE | P18: XIRR | Q18: =XIRR(G8:G60,C8:C60) -> 0.010083666
B19: ='CF (Funds)'!B14 -> Sinovation Disrupt Fund, L.P. | C19: ='CF (Funds)'!C14 -> 44703 | D19: ='CF (Funds)'!D14 -> 0 | E19: ='CF (Funds)'!E14 -> 0.227786 | G19: =SUM(D19:F19) -> 0.227786 | I19: TVPI | J19: =SUM(L9:M16)/-SUM(K9:K16) -> 1.4782169 | L19: Distributions | M19: =-SUM(L9:L17)=-'S | 01 '!M39 -> TRUE | P19: TVPI | Q19: =SUM(T9:U13)/SUM(R9:R13) -> 1.0273578
B20: ='CF (Funds)'!B15 -> Sinovation Disrupt Fund, L.P. | C20: ='CF (Funds)'!C15 -> 44776 | D20: ='CF (Funds)'!D15 -> -3.235493 | E20: ='CF (Funds)'!E15 -> 0 | G20: =SUM(D20:F20) -> -3.235493 | I20: RPI | J20: =SUM(M9:M16)/-SUM(K9:K16) -> 1.2109203 | L20: Residual Value | M20: =M16='S | 01 '!N39 -> TRUE | P20: RPI | Q20: =SUM(U9:U13)/SUM(R9:R13) -> 0.99374909
B21: ='CF (Funds)'!B16 -> Sinovation Disrupt Fund, L.P. | C21: ='CF (Funds)'!C16 -> 44960 | D21: ='CF (Funds)'!D16 -> -2.631528 | E21: ='CF (Funds)'!E16 -> 0 | G21: =SUM(D21:F21) -> -2.631528 | I21: DPI | J21: =SUM(L9:L16)/-SUM(K9:K16) -> 0.26729654 | P21: DPI | Q21: =SUM(T9:T13)/SUM(R9:R13) -> 0.033608751
B22: ='CF (Funds)'!B17 -> Sinovation Disrupt Fund, L.P. | C22: ='CF (Funds)'!C17 -> 45085 | D22: ='CF (Funds)'!D17 -> 1.912557 | E22: ='CF (Funds)'!E17 -> 0 | G22: =SUM(D22:F22) -> 1.912557
B23: ='CF (Funds)'!B18 -> North Summit Capital Fund | C23: ='CF (Funds)'!C18 -> 43665 | D23: ='CF (Funds)'!D18 -> -3 | E23: ='CF (Funds)'!E18 -> 0 | G23: =SUM(D23:F23) -> -3
B24: ='CF (Funds)'!B19 -> North Summit Capital Fund | C24: ='CF (Funds)'!C19 -> 43983 | D24: ='CF (Funds)'!D19 -> -4.485 | E24: ='CF (Funds)'!E19 -> 0 | G24: =SUM(D24:F24) -> -4.485
B25: ='CF (Funds)'!B20 -> North Summit Capital Fund | C25: ='CF (Funds)'!C20 -> 43879 | D25: ='CF (Funds)'!D20 -> -9.50975 | E25: ='CF (Funds)'!E20 -> 0 | G25: =SUM(D25:F25) -> -9.50975 | I25: =B44 -> New Space Capital GP Com SCSp | J25: =C44 -> 44087 | K25: =D44 -> -2.7058824 | N25: =SUM(K25:M25) -> -2.7058824
B26: ='CF (Funds)'!B21 -> North Summit Capital Fund | C26: ='CF (Funds)'!C21 -> 43934 | D26: ='CF (Funds)'!D21 -> -41.3 | E26: ='CF (Funds)'!E21 -> 0 | G26: =SUM(D26:F26) -> -41.3 | I26: New Space Capital SCSp | J26: =$C$4 -> 45138 | M26: =F53 -> 3.276608 | N26: =SUM(K26:M26) -> 3.276608
B27: ='CF (Funds)'!B22 -> North Summit Capital Fund | C27: ='CF (Funds)'!C22 -> 44151 | D27: ='CF (Funds)'!D22 -> 9.95 | E27: ='CF (Funds)'!E22 -> 0 | G27: =SUM(D27:F27) -> 9.95
B28: ='CF (Funds)'!B23 -> North Summit Capital Fund | C28: ='CF (Funds)'!C23 -> 44151 | D28: ='CF (Funds)'!D23 -> -10.455 | E28: ='CF (Funds)'!E23 -> 0 | G28: =SUM(D28:F28) -> -10.455 | I28: XIRR | J28: =XIRR(N25:N26,J25:J26) -> 0.068722782 | L28: Contributions | M28: =-SUM(K25:K26)='S | 01 '!K40 -> TRUE
B29: ='CF (Funds)'!B24 -> North Summit Capital Fund | C29: ='CF (Funds)'!C24 -> 44196 | D29: ='CF (Funds)'!D24 -> 4.975 | E29: ='CF (Funds)'!E24 -> 0 | G29: =SUM(D29:F29) -> 4.975 | I29: TVPI | J29: =SUM(L25:M26)/-SUM(K25:K26) -> 1.2109203 | L29: Distributions | M29: =-SUM(L21:L27)=-'S | 01 '!L40 -> TRUE
B30: ='CF (Funds)'!B25 -> North Summit Capital Fund | C30: ='CF (Funds)'!C25 -> 44196 | D30: ='CF (Funds)'!D25 -> -3.452293 | E30: ='CF (Funds)'!E25 -> 0 | G30: =SUM(D30:F30) -> -3.452293 | I30: RPI | J30: =SUM(M25:M26)/-SUM(K25:K26) -> 1.2109203 | L30: Residual Value | M30: =M26='S | 01 '!N40 -> TRUE
B31: ='CF (Funds)'!B26 -> North Summit Capital Fund | C31: ='CF (Funds)'!C26 -> 44196 | D31: ='CF (Funds)'!D26 -> 0 | E31: ='CF (Funds)'!E26 -> 0.582902 | G31: =SUM(D31:F31) -> 0.582902 | I31: DPI | J31: =SUM(L25:L26)/-SUM(K25:K26) -> 0
B32: ='CF (Funds)'!B27 -> North Summit Capital Fund | C32: ='CF (Funds)'!C27 -> 44370 | D32: ='CF (Funds)'!D27 -> -5.97 | E32: ='CF (Funds)'!E27 -> 0 | G32: =SUM(D32:F32) -> -5.97
B33: ='CF (Funds)'!B28 -> North Summit Capital Fund | C33: ='CF (Funds)'!C28 -> 44400 | D33: ='CF (Funds)'!D28 -> -0.75 | E33: ='CF (Funds)'!E28 -> 0 | G33: =SUM(D33:F33) -> -0.75
B34: ='CF (Funds)'!B29 -> North Summit Capital Fund | C34: ='CF (Funds)'!C29 -> 44400 | D34: ='CF (Funds)'!D29 -> 0 | E34: ='CF (Funds)'!E29 -> 0.445059 | G34: =SUM(D34:F34) -> 0.445059 | I34: =B23 -> North Summit Capital Fund | J34: =C23 -> 43665 | K34: =D23 -> -3 | L34: =E23 -> 0 | M34: =F23 -> 0 | N34: =SUM(K34:M34) -> -3
B35: ='CF (Funds)'!B30 -> North Summit Capital Fund | C35: ='CF (Funds)'!C30 -> 44554 | D35: ='CF (Funds)'!D30 -> 1.78239 | E35: ='CF (Funds)'!E30 -> 0 | G35: =SUM(D35:F35) -> 1.78239 | I35: =B24 -> North Summit Capital Fund | J35: =C24 -> 43983 | K35: =D24 -> -4.485 | L35: =E24 -> 0 | M35: =F24 -> 0 | N35: =SUM(K35:M35) -> -4.485
B36: ='CF (Funds)'!B31 -> North Summit Capital Fund | C36: ='CF (Funds)'!C31 -> 44676 | D36: ='CF (Funds)'!D31 -> -21 | E36: ='CF (Funds)'!E31 -> 0 | G36: =SUM(D36:F36) -> -21 | I36: =B25 -> North Summit Capital Fund | J36: =C25 -> 43879 | K36: =D25 -> -9.50975 | L36: =E25 -> 0 | M36: =F25 -> 0 | N36: =SUM(K36:M36) -> -9.50975
B37: ='CF (Funds)'!B32 -> New Space Capital Fund I | C37: ='CF (Funds)'!C32 -> 44087 | D37: ='CF (Funds)'!D32 -> -20.917553 | E37: ='CF (Funds)'!E32 -> 0 | G37: =SUM(D37:F37) -> -20.917553 | I37: =B26 -> North Summit Capital Fund | J37: =C26 -> 43934 | K37: =D26 -> -41.3 | L37: =E26 -> 0 | M37: =F26 -> 0 | N37: =SUM(K37:M37) -> -41.3
B38: ='CF (Funds)'!B33 -> New Space Capital Fund I | C38: ='CF (Funds)'!C33 -> 44287 | D38: ='CF (Funds)'!D33 -> -0.21103182 | E38: ='CF (Funds)'!E33 -> 0 | G38: =SUM(D38:F38) -> -0.21103182 | I38: =B27 -> North Summit Capital Fund | J38: =C27 -> 44151 | K38: =D27 -> 9.95 | L38: =E27 -> 0 | M38: =F27 -> 0 | N38: =SUM(K38:M38) -> 9.95
B39: ='CF (Funds)'!B34 -> New Space Capital Fund I | C39: ='CF (Funds)'!C34 -> 44442 | D39: ='CF (Funds)'!D34 -> -0.23965473 | E39: ='CF (Funds)'!E34 -> 0 | G39: =SUM(D39:F39) -> -0.23965473 | I39: =B28 -> North Summit Capital Fund | J39: =C28 -> 44151 | K39: =D28 -> -10.455 | L39: =E28 -> 0 | M39: =F28 -> 0 | N39: =SUM(K39:M39) -> -10.455
B40: ='CF (Funds)'!B35 -> New Space Capital Fund I | C40: ='CF (Funds)'!C35 -> 44623 | D40: ='CF (Funds)'!D35 -> -0.25893585 | E40: ='CF (Funds)'!E35 -> 0 | G40: =SUM(D40:F40) -> -0.25893585 | I40: =B29 -> North Summit Capital Fund | J40: =C29 -> 44196 | K40: =D29 -> 4.975 | L40: =E29 -> 0 | M40: =F29 -> 0 | N40: =SUM(K40:M40) -> 4.975
B41: ='CF (Funds)'!B36 -> New Space Capital Fund I | C41: ='CF (Funds)'!C36 -> 44784 | D41: ='CF (Funds)'!D36 -> 0.015224657 | E41: ='CF (Funds)'!E36 -> 0 | G41: =SUM(D41:F41) -> 0.015224657 | I41: =B30 -> North Summit Capital Fund | J41: =C30 -> 44196 | K41: =D30 -> -3.452293 | L41: =E30 -> 0 | M41: =F30 -> 0 | N41: =SUM(K41:M41) -> -3.452293
B42: ='CF (Funds)'!B37 -> New Space Capital Fund I | C42: ='CF (Funds)'!C37 -> 44956 | D42: ='CF (Funds)'!D37 -> 10.553916 | E42: ='CF (Funds)'!E37 -> 0 | G42: =SUM(D42:F42) -> 10.553916 | I42: =B31 -> North Summit Capital Fund | J42: =C31 -> 44196 | K42: =D31 -> 0 | L42: =E31 -> 0.582902 | M42: =F31 -> 0 | N42: =SUM(K42:M42) -> 0.582902
B43: ='CF (Funds)'!B38 -> New Space Capital Fund I | C43: ='CF (Funds)'!C38 -> 44956 | D43: ='CF (Funds)'!D38 -> 0 | E43: ='CF (Funds)'!E38 -> 2.9557744 | G43: =SUM(D43:F43) -> 2.9557744 | I43: =B32 -> North Summit Capital Fund | J43: =C32 -> 44370 | K43: =D32 -> -5.97 | L43: =E32 -> 0 | M43: =F32 -> 0 | N43: =SUM(K43:M43) -> -5.97
B44: ='CF (Funds)'!B39 -> New Space Capital GP Com SCSp | C44: ='CF (Funds)'!C39 -> 44087 | D44: ='CF (Funds)'!D39 -> -2.7058824 | E44: ='CF (Funds)'!E39 -> 0 | G44: =SUM(D44:F44) -> -2.7058824 | I44: =B33 -> North Summit Capital Fund | J44: =C33 -> 44400 | K44: =D33 -> -0.75 | L44: =E33 -> 0 | M44: =F33 -> 0 | N44: =SUM(K44:M44) -> -0.75
B45: ='CF (Funds)'!B40 -> Acies Investments Fund I, L.P. | C45: ='CF (Funds)'!C40 -> 44540 | D45: ='CF (Funds)'!D40 -> -2.8053125 | E45: ='CF (Funds)'!E40 -> 0 | G45: =SUM(D45:F45) -> -2.8053125 | I45: =B34 -> North Summit Capital Fund | J45: =C34 -> 44400 | K45: =D34 -> 0 | L45: =E34 -> 0.445059 | M45: =F34 -> 0 | N45: =SUM(K45:M45) -> 0.445059
... B47: ='CF (Funds)'!B42 -> Acies Investments Fund I, L.P. | C47: ='CF (Funds)'!C42 -> 44683 | D47: ='CF (Funds)'!D42 -> -1.025775 | E47: ='CF (Funds)'!E42 -> 0 | G47: =SUM(D47:F47) -> -1.025775 | I47: =B36 -> North Summit Capital Fund | J47: =C36 -> 44676 | K47: =D36 -> -21 | L47: =E36 -> 0 | M47: =F36 -> 0 | N47: =SUM(K47:M47) -> -21
B48: ='CF (Funds)'!B43 -> Acies Investments Fund I, L.P. | C48: ='CF (Funds)'!C43 -> 44707 | D48: ='CF (Funds)'!D43 -> -3.388275 | E48: ='CF (Funds)'!E43 -> 0 | G48: =SUM(D48:F48) -> -3.388275 | I48: North Summit Capital Fund | J48: =$C$4 -> 45138 | M48: =F51 -> 81.695786 | N48: =SUM(K48:M48) -> 81.695786
B49: ='CF (Funds)'!B44 -> Acies Investments Fund I, L.P. | C49: ='CF (Funds)'!C44 -> 44875 | D49: ='CF (Funds)'!D44 -> -3.388275 | E49: ='CF (Funds)'!E44 -> 0 | G49: =SUM(D49:F49) -> -3.388275
B50: Sinovation Disrupt Fund, L.P. | C50: =$C$4 -> 45138 | F50: =VLOOKUP(B50,NAV!$B$2:$H$44,4,0) -> 19.244515 | G50: =SUM(D50:F50) -> 19.244515 | I50: XIRR | J50: =XIRR(N34:N48,J34:J48,-0.1) -> -0.0021562932 | L50: Contributions | M50: =-SUM(K34:K47)='S | 01 '!K41 -> TRUE
B51: North Summit Capital Fund | C51: =$C$4 -> 45138 | F51: =VLOOKUP(B51,NAV!$B$2:$H$44,4,0) -> 81.695786 | G51: =SUM(D51:F51) -> 81.695786 | I51: TVPI | J51: =SUM(L34:M48)/-SUM(K34:K48) -> 0.99410073 | L51: Distributions | M51: =-SUM(L34:L47)=-'S | 01 '!M41 -> TRUE
B52: New Space Capital Fund I | C52: =$C$4 -> 45138 | F52: =VLOOKUP(B52,NAV!$B$2:$H$44,4,0) -> 13.390399 | G52: =SUM(D52:F52) -> 13.390399 | I52: RPI | J52: =SUM(M34:M48)/-SUM(K34:K48) -> 0.9817476 | L52: Residual Value | M52: =M48='S | 01 '!N41 -> TRUE
B53: New Space Capital GP Com SCSp | C53: =$C$4 -> 45138 | F53: =VLOOKUP(B53,NAV!$B$2:$H$44,4,0) -> 3.276608 | G53: =SUM(D53:F53) -> 3.276608 | I53: DPI | J53: =SUM(L34:L48)/-SUM(K34:K48) -> 0.012353125
B54: Acies Investments Fund I, L.P. | C54: =$C$4 -> 45138 | F54: =VLOOKUP(B54,NAV!$B$2:$H$44,4,0) -> 13.307625 | G54: =SUM(D54:F54) -> 13.307625
I56: =B8 -> Sinovation Disrupt Fund, L.P. | J56: =C8 -> 44153 | K56: =D8 -> -10.5 | L56: =E8 -> 0 | M56: =F8 -> 0 | N56: =SUM(K56:M56) -> -10.5
I57: =B9 -> Sinovation Disrupt Fund, L.P. | J57: =C9 -> 44238 | K57: =D9 -> 4.214027 | L57: =E9 -> 0 | M57: =F9 -> 0 | N57: =SUM(K57:M57) -> 4.214027
I58: =B10 -> Sinovation Disrupt Fund, L.P. | J58: =C10 -> 44238 | K58: =D10 -> 0 | L58: =E10 -> 0.05044835 | M58: =F10 -> 0 | N58: =SUM(K58:M58) -> 0.05044835
I59: =B11 -> Sinovation Disrupt Fund, L.P. | J59: =C11 -> 44285 | K59: =D11 -> -6.433746 | L59: =E11 -> 0 | M59: =F11 -> 0 | N59: =SUM(K59:M59) -> -6.433746
I60: =B12 -> Sinovation Disrupt Fund, L.P. | J60: =C12 -> 44269 | K60: =D12 -> 1.1352074 | L60: =E12 -> 0 | M60: =F12 -> 0 | N60: =SUM(K60:M60) -> 1.1352074
I61: =B13 -> Sinovation Disrupt Fund, L.P. | J61: =C13 -> 44269 | K61: =D13 -> 0 | L61: =E13 -> 0.0259 | M61: =F13 -> 0 | N61: =SUM(K61:M61) -> 0.0259
I62: =B14 -> Sinovation Disrupt Fund, L.P. | J62: =C14 -> 44483 | K62: =D14 -> -7.567138 | L62: =E14 -> 0 | M62: =F14 -> 0 | N62: =SUM(K62:M62) -> -7.567138
I63: =B15 -> Sinovation Disrupt Fund, L.P. | J63: =C15 -> 44554 | K63: =D15 -> -7.385016 | L63: =E15 -> 0 | M63: =F15 -> 0 | N63: =SUM(K63:M63) -> -7.385016
I64: =B16 -> Sinovation Disrupt Fund, L.P. | J64: =C16 -> 44554 | K64: =D16 -> 4.0733456 | L64: =E16 -> 0 | M64: =F16 -> 0 | N64: =SUM(K64:M64) -> 4.0733456
I65: =B17 -> Sinovation Disrupt Fund, L.P. | J65: =C17 -> 44554 | K65: =D17 -> 0 | L65: =E17 -> 0.139694 | M65: =F17 -> 0 | N65: =SUM(K65:M65) -> 0.139694
I66: =B18 -> Sinovation Disrupt Fund, L.P. | J66: =C18 -> 44703 | K66: =D18 -> 5.673074 | L66: =E18 -> 0 | M66: =F18 -> 0 | N66: =SUM(K66:M66) -> 5.673074
I67: =B19 -> Sinovation Disrupt Fund, L.P. | J67: =C19 -> 44703 | K67: =D19 -> 0 | L67: =E19 -> 0.227786 | M67: =F19 -> 0 | N67: =SUM(K67:M67) -> 0.227786
... I70: =B22 -> Sinovation Disrupt Fund, L.P. | J70: =C22 -> 45085 | K70: =D22 -> 1.912557 | L70: =E22 -> 0 | M70: =F22 -> 0 | N70: =SUM(K70:M70) -> 1.912557
I71: Sinovation Disrupt Fund, L.P. | J71: =$C$4 -> 45138 | M71: =F50 -> 19.244515 | N71: =SUM(K71:M71) -> 19.244515
I73: XIRR | J73: =XIRR(N56:N71,J56:J71) -> -0.023361704 | L73: Contributions | M73: =-SUM(K56:K70)='S | 01 '!K42 -> TRUE
I74: TVPI | J74: =SUM(L56:M71)/-SUM(K56:K71) -> 0.94907778 | L74: Distributions | M74: =-SUM(L56:L67)=-'S | 01 '!M42 -> TRUE
I75: RPI | J75: =SUM(M56:M71)/-SUM(K56:K71) -> 0.92768301 | L75: Residual Value | M75: =M71='S | 01 '!N42 -> TRUE
I76: DPI | J76: =SUM(L56:L71)/-SUM(K56:K71) -> 0.021394772
I78: =B45 -> Acies Investments Fund I, L.P. | J78: =C45 -> 44540 | K78: =D45 -> -2.8053125 | L78: =E45 -> 0 | M78: =F45 -> 0 | N78: =SUM(K78:M78) -> -2.8053125
I79: =B46 -> Acies Investments Fund I, L.P. | J79: =C46 -> 44602 | K79: =D46 -> -3.4075 | L79: =E46 -> 0 | M79: =F46 -> 0 | N79: =SUM(K79:M79) -> -3.4075
I80: =B47 -> Acies Investments Fund I, L.P. | J80: =C47 -> 44683 | K80: =D47 -> -1.025775 | L80: =E47 -> 0 | M80: =F47 -> 0 | N80: =SUM(K80:M80) -> -1.025775
I81: =B48 -> Acies Investments Fund I, L.P. | J81: =C48 -> 44707 | K81: =D48 -> -3.388275 | L81: =E48 -> 0 | M81: =F48 -> 0 | N81: =SUM(K81:M81) -> -3.388275
I82: =B49 -> Acies Investments Fund I, L.P. | J82: =C49 -> 44875 | K82: =D49 -> -3.388275 | L82: =E49 -> 0 | M82: =F49 -> 0 | N82: =SUM(K82:M82) -> -3.388275
I83: Acies Investments Fund I, L.P. | J83: =$C$4 -> 45138 | M83: =F54 -> 13.307625 | N83: =SUM(K83:M83) -> 13.307625
I85: XIRR | J85: =XIRR(N78:N83,J78:J83) -> -0.04112356 | L85: Contributions | M85: =-SUM(K78:K83)='S | 01 '!K43 -> TRUE
I86: TVPI | J86: =SUM(L78:M83)/-SUM(K78:K83) -> 0.94951798 | L86: Distributions | M86: =-SUM(L78:L88)=-'S | 01 '!M43 -> TRUE
I87: RPI | J87: =SUM(M78:M83)/-SUM(K78:K83) -> 0.94951798 | L87: Residual Value | M87: =M83='S | 01 '!N43 -> TRUE
I88: DPI | J88: =SUM(L78:L83)/-SUM(K78:K83) -> 0

Sheet 4.All
B2: IRR - All Investments (Equity, Debt, Funds) | H2: TEST | I2: =COUNTA(B8:B91)=COUNTA('CF (Equity, Debt)'!C4:C35)+COUNTA('CF (Equity, Debt)'!C42:C45)+COUNTA('CF (Funds)'!B3:B44) -> FALSE
B4: Date of NAV | C4: =D!D2 -> 45138
B6: (in USD, Mn)
B7: Investment | C7: Payment date | D7: Contribution | E7: Distributions | F7: Remaining Value | G7: Combined | H7: Type | J7: Invested | K7: Remaining Commitment | L7: Distributions | M7: Residual Value | N7: IRR | O7: TVPI | P7: RPI | Q7: DPI
B8: ='CF (Equity, Debt)'!C4 -> Jollychic Holding Limited | C8: ='CF (Equity, Debt)'!D4 -> 43470 | D8: ='CF (Equity, Debt)'!E4 -> -30 | G8: =SUM(D8:F8) -> -30 | H8: Equity
B9: ='CF (Equity, Debt)'!C5 -> Jollychic Holding Limited | C9: ='CF (Equity, Debt)'!D5 -> 43724 | D9: ='CF (Equity, Debt)'!E5 -> -20 | G9: =SUM(D9:F9) -> -20 | H9: Equity | J9: =-SUM(D8:D119) -> 2243.0372 | L9: =SUM(E8:E119) -> 17.719124 | M9: =SUM(F8:F119) -> 2251.8623 | N9: =XIRR(G8:G118,C8:C118) -> 0.007097432 | O9: =(L9+M9)/J9 -> 1.011834 | P9: =M9/J9 -> 1.0039344 | Q9: =L9/J9 -> 0.0078996124
B10: ='CF (Equity, Debt)'!C6 -> Jollychic Holding Limited | C10: ='CF (Equity, Debt)'!D6 -> 43724 | D10: ='CF (Equity, Debt)'!E6 -> -15 | G10: =SUM(D10:F10) -> -15 | H10: Equity
B11: ='CF (Equity, Debt)'!C7 -> Mena Mobile Inc | C11: ='CF (Equity, Debt)'!D7 -> 43563 | D11: ='CF (Equity, Debt)'!E7 -> -8 | G11: =SUM(D11:F11) -> -8 | H11: Equity | J11: =ROUND(J9,2)=ROUND('S | 01 '!K46,2) -> TRUE | L11: =ROUND(L9,3)=ROUND('S | 01 '!M46,3) -> TRUE | M11: =ROUND(M9,3)=ROUND('S | 01 '!N46,3) -> TRUE
B12: ='CF (Equity, Debt)'!C8 -> Flyr Inc | C12: ='CF (Equity, Debt)'!D8 -> 43570 | D12: ='CF (Equity, Debt)'!E8 -> -4.9999981 | G12: =SUM(D12:F12) -> -4.9999981 | H12: Equity
B13: ='CF (Equity, Debt)'!C9 -> Flyr Inc | C13: ='CF (Equity, Debt)'!D9 -> 43915 | D13: ='CF (Equity, Debt)'!E9 -> -5.0000019 | G13: =SUM(D13:F13) -> -5.0000019 | H13: Equity
B14: ='CF (Equity, Debt)'!C10 -> Esyasoft Holding | C14: ='CF (Equity, Debt)'!D10 -> 43870 | D14: ='CF (Equity, Debt)'!E10 -> -2.5 | G14: =SUM(D14:F14) -> -2.5 | H14: Equity
B15: ='CF (Equity, Debt)'!C11 -> Beyond Limits | C15: ='CF (Equity, Debt)'!D11 -> 43879 | D15: ='CF (Equity, Debt)'!E11 -> -20 | G15: =SUM(D15:F15) -> -20 | H15: Equity
B16: ='CF (Equity, Debt)'!C12 -> Beyond Limits | C16: ='CF (Equity, Debt)'!D12 -> 43921 | D16: ='CF (Equity, Debt)'!E12 -> -30 | G16: =SUM(D16:F16) -> -30 | H16: Equity
B17: ='CF (Equity, Debt)'!C13 -> Beyond Limits | C17: ='CF (Equity, Debt)'!D13 -> 43989 | D17: ='CF (Equity, Debt)'!E13 -> -30 | G17: =SUM(D17:F17) -> -30 | H17: Equity
B18: ='CF (Equity, Debt)'!C14 -> Beyond Limits | C18: ='CF (Equity, Debt)'!D14 -> 44103 | D18: ='CF (Equity, Debt)'!E14 -> -10 | G18: =SUM(D18:F18) -> -10 | H18: Equity
B19: ='CF (Equity, Debt)'!C15 -> ONT plc | C19: ='CF (Equity, Debt)'!D15 -> 43968 | D19: ='CF (Equity, Debt)'!E15 -> -50 | G19: =SUM(D19:F19) -> -50 | H19: Equity
B20: ='CF (Equity, Debt)'!C16 -> ONT plc | C20: ='CF (Equity, Debt)'!D16 -> 44006 | D20: ='CF (Equity, Debt)'!E16 -> -27.268351 | G20: =SUM(D20:F20) -> -27.268351 | H20: Equity
B21: ='CF (Equity, Debt)'!C17 -> ONT plc | C21: ='CF (Equity, Debt)'!D17 -> 43837 | D21: ='CF (Equity, Debt)'!E17 -> -18.109441 | G21: =SUM(D21:F21) -> -18.109441 | H21: Equity
B22: ='CF (Equity, Debt)'!C18 -> ONT plc | C22: ='CF (Equity, Debt)'!D18 -> 43990 | D22: ='CF (Equity, Debt)'!E18 -> -34.851687 | G22: =SUM(D22:F22) -> -34.851687 | H22: Equity
B23: ='CF (Equity, Debt)'!C19 -> ONT plc | C23: ='CF (Equity, Debt)'!D19 -> 44315 | D23: ='CF (Equity, Debt)'!E19 -> -11.24078 | G23: =SUM(D23:F23) -> -11.24078 | H23: Equity
... B31: ='CF (Equity, Debt)'!C27 -> DriveNets | C31: ='CF (Equity, Debt)'!D27 -> 44680 | D31: ='CF (Equity, Debt)'!E27 -> -100 | G31: =SUM(D31:F31) -> -100 | H31: Equity
B32: ='CF (Equity, Debt)'!C28 -> Esyasoft Holding | C32: ='CF (Equity, Debt)'!D28 -> 44691 | D32: ='CF (Equity, Debt)'!E28 -> 0 | E32: 5 | G32: =SUM(D32:F32) -> 5 | H32: Equity
B33: ='CF (Equity, Debt)'!C29 -> vTv Therapeutics Inc. | C33: ='CF (Equity, Debt)'!D29 -> 44712 | D33: ='CF (Equity, Debt)'!E29 -> -12.5 | G33: =SUM(D33:F33) -> -12.5 | H33: Equity
B34: ='CF (Equity, Debt)'!C30 -> Honor Device Co Ltd | C34: ='CF (Equity, Debt)'!D30 -> 44769 | D34: ='CF (Equity, Debt)'!E30 -> -600 | G34: =SUM(D34:F34) -> -600 | H34: Equity
B35: ='CF (Equity, Debt)'!C31 -> Honor Device Co Ltd | C35: ='CF (Equity, Debt)'!D31 -> 44849 | D35: ='CF (Equity, Debt)'!E31 -> -200 | G35: =SUM(D35:F35) -> -200 | H35: Equity
B36: ='CF (Equity, Debt)'!C32 -> Applied AI Corporation Limited | C36: ='CF (Equity, Debt)'!D32 -> 44861 | D36: ='CF (Equity, Debt)'!E32 -> -4.75 | G36: =SUM(D36:F36) -> -4.75 | H36: Equity
B37: ='CF (Equity, Debt)'!C33 -> eSpace | C37: ='CF (Equity, Debt)'!D33 -> 44892 | D37: ='CF (Equity, Debt)'!E33 -> -15 | G37: =SUM(D37:F37) -> -15 | H37: Equity
B38: ='CF (Equity, Debt)'!C34 -> vTv Therapeutics Inc. | C38: ='CF (Equity, Debt)'!D34 -> 44985 | D38: ='CF (Equity, Debt)'!E34 -> -12.03125 | G38: =SUM(D38:F38) -> -12.03125 | H38: Equity
B39: ='CF (Equity, Debt)'!C35 -> Tools for Humanity Corporation | C39: ='CF (Equity, Debt)'!D35 -> 45075 | D39: ='CF (Equity, Debt)'!E35 -> -14.999999 | G39: =SUM(D39:F39) -> -14.999999 | H39: Equity
B40: ='CF (Equity, Debt)'!C36 -> WLD Tokens | C40: ='CF (Equity, Debt)'!D36 -> 45075 | D40: ='CF (Equity, Debt)'!E36 -> -0.005875 | G40: =SUM(D40:F40) -> -0.005875 | H40: Equity
B41: ='CF (Equity, Debt)'!C37 -> WLD Tokens | C41: ='CF (Equity, Debt)'!D37 -> 45114 | D41: ='CF (Equity, Debt)'!E37 -> -0.001 | G41: =SUM(D41:F41) -> -0.001 | H41: Equity
B42: ='CF (Equity, Debt)'!C38 -> Applied AI Corporation Limited | C42: ='CF (Equity, Debt)'!D38 -> 45121 | D42: ='CF (Equity, Debt)'!E38 -> -2.75 | G42: =SUM(D42:F42) -> -2.75 | H42: Equity
B43: ='CF (Equity, Debt)'!C39 -> Instadeep Limited | C43: ='CF (Equity, Debt)'!D39 -> 45138 | D43: ='CF (Equity, Debt)'!E39 -> 0 | E43: ='CF (Equity, Debt)'!F39 -> 7.8207761 | G43: =SUM(D43:F43) -> 7.8207761 | H43: Equity
B45: ='CF (Equity, Debt)'!C42 -> Glass Earth Holdings LLC | C45: ='CF (Equity, Debt)'!D42 -> 43635 | D45: ='CF (Equity, Debt)'!E42 -> -8 | G45: =SUM(D45:F45) -> -8 | H45: Debt
B46: ='CF (Equity, Debt)'!C43 -> Mena Mobile Inc (Debt) | C46: ='CF (Equity, Debt)'!D43 -> 44293 | D46: ='CF (Equity, Debt)'!E43 -> -2.353982 | G46: =SUM(D46:F46) -> -2.353982 | H46: Debt
B47: ='CF (Equity, Debt)'!C44 -> Esyasoft Holding (Debt) | C47: ='CF (Equity, Debt)'!D44 -> 44384 | D47: ='CF (Equity, Debt)'!E44 -> -0.411765 | G47: =SUM(D47:F47) -> -0.411765 | H47: Debt
B48: ='CF (Equity, Debt)'!C45 -> Esyasoft Holding (Debt) | C48: ='CF (Equity, Debt)'!D45 -> 44902 | D48: ='CF (Equity, Debt)'!E45 -> 0 | E48: ='CF (Equity, Debt)'!F45 -> 0.47078465 | G48: =SUM(D48:F48) -> 0.47078465 | H48: Debt
B50: ='CF (Funds)'!B3 -> Sinovation Disrupt Fund, L.P. | C50: ='CF (Funds)'!C3 -> 44153 | D50: ='CF (Funds)'!D3 -> -10.5 | E50: ='CF (Funds)'!E3 -> 0 | G50: =SUM(D50:F50) -> -10.5 | H50: Fund
B51: ='CF (Funds)'!B4 -> Sinovation Disrupt Fund, L.P. | C51: ='CF (Funds)'!C4 -> 44238 | D51: ='CF (Funds)'!D4 -> 4.214027 | E51: ='CF (Funds)'!E4 -> 0 | G51: =SUM(D51:F51) -> 4.214027 | H51: Fund
B52: ='CF (Funds)'!B5 -> Sinovation Disrupt Fund, L.P. | C52: ='CF (Funds)'!C5 -> 44238 | D52: ='CF (Funds)'!D5 -> 0 | E52: ='CF (Funds)'!E5 -> 0.05044835 | G52: =SUM(D52:F52) -> 0.05044835 | H52: Fund
B53: ='CF (Funds)'!B6 -> Sinovation Disrupt Fund, L.P. | C53: ='CF (Funds)'!C6 -> 44285 | D53: ='CF (Funds)'!D6 -> -6.433746 | E53: ='CF (Funds)'!E6 -> 0 | G53: =SUM(D53:F53) -> -6.433746 | H53: Fund
B54: ='CF (Funds)'!B7 -> Sinovation Disrupt Fund, L.P. | C54: ='CF (Funds)'!C7 -> 44269 | D54: ='CF (Funds)'!D7 -> 1.1352074 | E54: ='CF (Funds)'!E7 -> 0 | G54: =SUM(D54:F54) -> 1.1352074 | H54: Fund
B55: ='CF (Funds)'!B8 -> Sinovation Disrupt Fund, L.P. | C55: ='CF (Funds)'!C8 -> 44269 | D55: ='CF (Funds)'!D8 -> 0 | E55: ='CF (Funds)'!E8 -> 0.0259 | G55: =SUM(D55:F55) -> 0.0259 | H55: Fund
B56: ='CF (Funds)'!B9 -> Sinovation Disrupt Fund, L.P. | C56: ='CF (Funds)'!C9 -> 44483 | D56: ='CF (Funds)'!D9 -> -7.567138 | E56: ='CF (Funds)'!E9 -> 0 | G56: =SUM(D56:F56) -> -7.567138 | H56: Fund
B57: ='CF (Funds)'!B10 -> Sinovation Disrupt Fund, L.P. | C57: ='CF (Funds)'!C10 -> 44554 | D57: ='CF (Funds)'!D10 -> -7.385016 | E57: ='CF (Funds)'!E10 -> 0 | G57: =SUM(D57:F57) -> -7.385016 | H57: Fund
B58: ='CF (Funds)'!B11 -> Sinovation Disrupt Fund, L.P. | C58: ='CF (Funds)'!C11 -> 44554 | D58: ='CF (Funds)'!D11 -> 4.0733456 | E58: ='CF (Funds)'!E11 -> 0 | G58: =SUM(D58:F58) -> 4.0733456 | H58: Fund
B59: ='CF (Funds)'!B12 -> Sinovation Disrupt Fund, L.P. | C59: ='CF (Funds)'!C12 -> 44554 | D59: ='CF (Funds)'!D12 -> 0 | E59: ='CF (Funds)'!E12 -> 0.139694 | G59: =SUM(D59:F59) -> 0.139694 | H59: Fund
B60: ='CF (Funds)'!B13 -> Sinovation Disrupt Fund, L.P. | C60: ='CF (Funds)'!C13 -> 44703 | D60: ='CF (Funds)'!D13 -> 5.673074 | E60: ='CF (Funds)'!E13 -> 0 | G60: =SUM(D60:F60) -> 5.673074 | H60: Fund
B61: ='CF (Funds)'!B14 -> Sinovation Disrupt Fund, L.P. | C61: ='CF (Funds)'!C14 -> 44703 | D61: ='CF (Funds)'!D14 -> 0 | E61: ='CF (Funds)'!E14 -> 0.227786 | G61: =SUM(D61:F61) -> 0.227786 | H61: Fund
... B91: ='CF (Funds)'!B44 -> Acies Investments Fund I, L.P. | C91: ='CF (Funds)'!C44 -> 44875 | D91: ='CF (Funds)'!D44 -> -3.388275 | E91: ='CF (Funds)'!E44 -> 0 | G91: =SUM(D91:F91) -> -3.388275 | H91: Fund
B92: Jollychic Holding Limited | C92: =$C$4 -> 45138 | F92: =VLOOKUP(B92,NAV!$B$9:$E$43,4,0) -> 0 | G92: =SUM(D92:F92) -> 0 | H92: NAV
B93: Mena Mobile Inc | C93: =$C$4 -> 45138 | F93: =VLOOKUP(B93,NAV!$B$9:$E$43,4,0) -> 0 | G93: =SUM(D93:F93) -> 0 | H93: NAV
B94: Flyr Inc | C94: =$C$4 -> 45138 | F94: =VLOOKUP(B94,NAV!$B$9:$E$43,4,0) -> 78.08223 | G94: =SUM(D94:F94) -> 78.08223 | H94: NAV
B95: Esyasoft Holding | C95: =$C$4 -> 45138 | F95: =VLOOKUP(B95,NAV!$B$9:$E$43,4,0) -> 0 | G95: =SUM(D95:F95) -> 0 | H95: NAV
B96: Beyond Limits | C96: =$C$4 -> 45138 | F96: =VLOOKUP(B96,NAV!$B$9:$E$43,4,0) -> 91.00154 | G96: =SUM(D96:F96) -> 91.00154 | H96: NAV
B97: ONT plc | C97: =$C$4 -> 45138 | F97: =VLOOKUP(B97,NAV!$B$9:$E$43,4,0) -> 150.40044 | G97: =SUM(D97:F97) -> 150.40044 | H97: NAV
B98: Heygears | C98: =$C$4 -> 45138 | F98: =VLOOKUP(B98,NAV!$B$9:$E$43,4,0) -> 151.06943 | G98: =SUM(D98:F98) -> 151.06943 | H98: NAV
B99: Jysan Technologies | C99: =$C$4 -> 45138 | F99: =VLOOKUP(B99,NAV!$B$9:$E$43,4,0) -> 20 | G99: =SUM(D99:F99) -> 20 | H99: NAV
B100: Cerebras Systems Inc | C100: =$C$4 -> 45138 | F100: =VLOOKUP(B100,NAV!$B$9:$E$43,4,0) -> 39.999983 | G100: =SUM(D100:F100) -> 39.999983 | H100: NAV
B101: Endless Studios LLC | C101: =$C$4 -> 45138 | F101: =VLOOKUP(B101,NAV!$B$9:$E$43,4,0) -> 3 | G101: =SUM(D101:F101) -> 3 | H101: NAV
B102: Instadeep Limited | C102: =$C$4 -> 45138 | F102: =VLOOKUP(B102,NAV!$B$9:$E$43,4,0) -> 0 | G102: =SUM(D102:F102) -> 0 | H102: NAV
B103: X-fusion | C103: =$C$4 -> 45138 | F103: =VLOOKUP(B103,NAV!$B$9:$E$43,4,0) -> 408.28799 | G103: =SUM(D103:F103) -> 408.28799 | H103: NAV
... B118: Acies Investments Fund I, L.P. | C118: =$C$4 -> 45138 | F118: =VLOOKUP(B118,NAV!$B$9:$E$43,4,0) -> 13.307625 | G118: =SUM(D118:F118) -> 13.307625 | H118: NAV

Sheet 4. Mozn-IRR
B2: IRR - Mozn Investments | G2: TEST | H2: =H5=H4 -> TRUE
B4: Date of NAV | E4: =D!D2 -> 45138 | H4: =COUNTIF('CF (Equity, Debt)'!$B$4:$B$55,MID('CF (Equity, Debt)'!$B$4:$B$55,1,4)) -> 31
H5: =COUNTIFS('CF (Equity, Debt)'!B4:B45,"Mozn")+COUNTIFS('CF (Funds)'!A3:A44,"Mozn") -> 31 | K5: =K9='S | 02'!L29 -> TRUE | M5: =M9='S | 02'!M29 -> TRUE | N5: =N9='S | 02'!N29 -> TRUE
K7: Invested | L7: Remaining Commitment | M7: Distributions | N7: Residual Value | O7: IRR | P7: TVPI | Q7: RPI | R7: DPI
K9: =-SUM(F12:F65) -> 986.76754 | M9: =SUM(G12:G65) -> 13.291561 | N9: =SUM(H12:H65) -> 996.6956 | O9: =XIRR(I12:I65,E12:E65) -> 0.010515186 | P9: =(M9+N9)/K9 -> 1.023531 | Q9: =N9/K9 -> 1.0100612 | R9: =M9/K9 -> 0.013469799
B10: (in USD, Mn)
B11: Investment | C11: Type | D11: Entity | E11: Payment date | F11: Contribution | G11: Distributions | H11: Remaining Value | I11: Combined
B12: ='CF (Equity, Debt)'!C4 -> Jollychic Holding Limited | C12: =VLOOKUP(B12,'S | 02'!$C$6:$J$39,2,0) -> Direct Investment | D12: =VLOOKUP(B12,'S | 02'!$C$6:$J$39,5,0) -> Mozn | E12: ='CF (Equity, Debt)'!D4 -> 43470 | F12: ='CF (Equity, Debt)'!E4 -> -30 | I12: =SUM(F12:H12) -> -30 | K12: Invested | L12: =-SUM(F12:F76) -> 986.76754 | M12: ='S | 02'!L29=L12 -> TRUE
B13: ='CF (Equity, Debt)'!C5 -> Jollychic Holding Limited | C13: =VLOOKUP(B13,'S | 02'!$C$6:$J$39,2,0) -> Direct Investment | D13: =VLOOKUP(B13,'S | 02'!$C$6:$J$39,5,0) -> Mozn | E13: ='CF (Equity, Debt)'!D5 -> 43724 | F13: ='CF (Equity, Debt)'!E5 -> -20 | I13: =SUM(F13:H13) -> -20 | K13: NAV | L13: =SUM(H12:H76) -> 996.6956
B14: ='CF (Equity, Debt)'!C6 -> Jollychic Holding Limited | C14: =VLOOKUP(B14,'S | 02'!$C$6:$J$39,2,0) -> Direct Investment | D14: =VLOOKUP(B14,'S | 02'!$C$6:$J$39,5,0) -> Mozn | E14: ='CF (Equity, Debt)'!D6 -> 43724 | F14: ='CF (Equity, Debt)'!E6 -> -15 | I14: =SUM(F14:H14) -> -15 | K14: Distributions | L14: =SUM(G12:G76) -> 13.291561
B15: ='CF (Equity, Debt)'!C7 -> Mena Mobile Inc | C15: =VLOOKUP(B15,'S | 02'!$C$6:$J$39,2,0) -> Direct Investment | D15: =VLOOKUP(B15,'S | 02'!$C$6:$J$39,5,0) -> Mozn | E15: ='CF (Equity, Debt)'!D7 -> 43563 | F15: ='CF (Equity, Debt)'!E7 -> -8 | I15: =SUM(F15:H15) -> -8 | K15: Total Gain | L15: =L14+L13-L12 -> 23.219623
B16: ='CF (Equity, Debt)'!C8 -> Flyr Inc | C16: =VLOOKUP(B16,'S | 02'!$C$6:$J$39,2,0) -> Direct Investment | D16: =VLOOKUP(B16,'S | 02'!$C$6:$J$39,5,0) -> Mozn | E16: ='CF (Equity, Debt)'!D8 -> 43570 | F16: ='CF (Equity, Debt)'!E8 -> -4.9999981 | I16: =SUM(F16:H16) -> -4.9999981 | K16: IRR | L16: =O9 -> 0.010515186
B17: ='CF (Equity, Debt)'!C9 -> Flyr Inc | C17: =VLOOKUP(B17,'S | 02'!$C$6:$J$39,2,0) -> Direct Investment | D17: =VLOOKUP(B17,'S | 02'!$C$6:$J$39,5,0) -> Mozn | E17: ='CF (Equity, Debt)'!D9 -> 43915 | F17: ='CF (Equity, Debt)'!E9 -> -5.0000019 | I17: =SUM(F17:H17) -> -5.0000019
B18: ='CF (Equity, Debt)'!C10 -> Esyasoft Holding | C18: =VLOOKUP(B18,'S | 02'!$C$6:$J$39,2,0) -> Direct Investment | D18: =VLOOKUP(B18,'S | 02'!$C$6:$J$39,5,0) -> Mozn | E18: ='CF (Equity, Debt)'!D10 -> 43870 | F18: ='CF (Equity, Debt)'!E10 -> -2.5 | I18: =SUM(F18:H18) -> -2.5
B19: ='CF (Equity, Debt)'!C11 -> Beyond Limits | C19: =VLOOKUP(B19,'S | 02'!$C$6:$J$39,2,0) -> Direct Investment | D19: =VLOOKUP(B19,'S | 02'!$C$6:$J$39,5,0) -> Mozn | E19: ='CF (Equity, Debt)'!D11 -> 43879 | F19: ='CF (Equity, Debt)'!E11 -> -20 | I19: =SUM(F19:H19) -> -20
B20: ='CF (Equity, Debt)'!C12 -> Beyond Limits | C20: =VLOOKUP(B20,'S | 02'!$C$6:$J$39,2,0) -> Direct Investment | D20: =VLOOKUP(B20,'S | 02'!$C$6:$J$39,5,0) -> Mozn | E20: ='CF (Equity, Debt)'!D12 -> 43921 | F20: ='CF (Equity, Debt)'!E12 -> -30 | I20: =SUM(F20:H20) -> -30
B21: ='CF (Equity, Debt)'!C13 -> Beyond Limits | C21: =VLOOKUP(B21,'S | 02'!$C$6:$J$39,2,0) -> Direct Investment | D21: =VLOOKUP(B21,'S | 02'!$C$6:$J$39,5,0) -> Mozn | E21: ='CF (Equity, Debt)'!D13 -> 43989 | F21: ='CF (Equity, Debt)'!E13 -> -30 | I21: =SUM(F21:H21) -> -30
B22: ='CF (Equity, Debt)'!C14 -> Beyond Limits | C22: =VLOOKUP(B22,'S | 02'!$C$6:$J$39,2,0) -> Direct Investment | D22: =VLOOKUP(B22,'S | 02'!$C$6:$J$39,5,0) -> Mozn | E22: ='CF (Equity, Debt)'!D14 -> 44103 | F22: ='CF (Equity, Debt)'!E14 -> -10 | I22: =SUM(F22:H22) -> -10
B23: ='CF (Equity, Debt)'!C15 -> ONT plc | C23: =VLOOKUP(B23,'S | 02'!$C$6:$J$39,2,0) -> Direct Investment | D23: =VLOOKUP(B23,'S | 02'!$C$6:$J$39,5,0) -> Mozn | E23: ='CF (Equity, Debt)'!D15 -> 43968 | F23: ='CF (Equity, Debt)'!E15 -> -50 | I23: =SUM(F23:H23) -> -50
B24: ='CF (Equity, Debt)'!C16 -> ONT plc | C24: =VLOOKUP(B24,'S | 02'!$C$6:$J$39,2,0) -> Direct Investment | D24: =VLOOKUP(B24,'S | 02'!$C$6:$J$39,5,0) -> Mozn | E24: ='CF (Equity, Debt)'!D16 -> 44006 | F24: ='CF (Equity, Debt)'!E16 -> -27.268351 | I24: =SUM(F24:H24) -> -27.268351
B25: ='CF (Equity, Debt)'!C17 -> ONT plc | C25: =VLOOKUP(B25,'S | 02'!$C$6:$J$39,2,0) -> Direct Investment | D25: =VLOOKUP(B25,'S | 02'!$C$6:$J$39,5,0) -> Mozn | E25: ='CF (Equity, Debt)'!D17 -> 43837 | F25: ='CF (Equity, Debt)'!E17 -> -18.109441 | I25: =SUM(F25:H25) -> -18.109441
B26: ='CF (Equity, Debt)'!C18 -> ONT plc | C26: =VLOOKUP(B26,'S | 02'!$C$6:$J$39,2,0) -> Direct Investment | D26: =VLOOKUP(B26,'S | 02'!$C$6:$J$39,5,0) -> Mozn | E26: ='CF (Equity, Debt)'!D18 -> 43990 | F26: ='CF (Equity, Debt)'!E18 -> -34.851687 | I26: =SUM(F26:H26) -> -34.851687
B27: ='CF (Equity, Debt)'!C19 -> ONT plc | C27: =VLOOKUP(B27,'S | 02'!$C$6:$J$39,2,0) -> Direct Investment | D27: =VLOOKUP(B27,'S | 02'!$C$6:$J$39,5,0) -> Mozn | E27: ='CF (Equity, Debt)'!D19 -> 44315 | F27: ='CF (Equity, Debt)'!E19 -> -11.24078 | I27: =SUM(F27:H27) -> -11.24078
B28: ='CF (Equity, Debt)'!C20 -> Heygears | C28: =VLOOKUP(B28,'S | 02'!$C$6:$J$39,2,0) -> Direct Investment | D28: =VLOOKUP(B28,'S | 02'!$C$6:$J$39,5,0) -> Mozn | E28: ='CF (Equity, Debt)'!D20 -> 44166 | F28: ='CF (Equity, Debt)'!E20 -> -60 | I28: =SUM(F28:H28) -> -60
... B33: ='CF (Equity, Debt)'!C25 -> X-fusion | C33: =VLOOKUP(B33,'S | 02'!$C$6:$J$39,2,0) -> Direct Investment | D33: =VLOOKUP(B33,'S | 02'!$C$6:$J$39,5,0) -> Mozn 2 | E33: ='CF (Equity, Debt)'!D25 -> 44574 | F33: ='CF (Equity, Debt)'!E25 -> -493.50096 | I33: =SUM(F33:H33) -> -493.50096
B34: ='CF (Equity, Debt)'!C28 -> Esyasoft Holding | C34: =VLOOKUP(B34,'S | 02'!$C$6:$J$39,2,0) -> Direct Investment | D34: =VLOOKUP(B34,'S | 02'!$C$6:$J$39,5,0) -> Mozn | E34: ='CF (Equity, Debt)'!D28 -> 44691 | F34: ='CF (Equity, Debt)'!E28 -> 0 | G34: 5 | I34: =SUM(F34:H34) -> 5
B35: ='CF (Equity, Debt)'!C32 -> Applied AI Corporation Limited | C35: =VLOOKUP(B35,'S | 02'!$C$6:$J$39,2,0) -> Direct Investment | D35: =VLOOKUP(B35,'S | 02'!$C$6:$J$39,5,0) -> Mozn | E35: ='CF (Equity, Debt)'!D32 -> 44861 | F35: ='CF (Equity, Debt)'!E32 -> -4.75 | I35: =SUM(F35:H35) -> -4.75
B36: ='CF (Equity, Debt)'!C33 -> eSpace | C36: =VLOOKUP(B36,'S | 02'!$C$6:$J$39,2,0) -> Direct Investment | D36: =VLOOKUP(B36,'S | 02'!$C$6:$J$39,5,0) -> Mozn 4 | E36: ='CF (Equity, Debt)'!D33 -> 44892 | F36: ='CF (Equity, Debt)'!E33 -> -15 | I36: =SUM(F36:H36) -> -15
B37: ='CF (Equity, Debt)'!C35 -> Tools for Humanity Corporation | C37: =VLOOKUP(B37,'S | 02'!$C$6:$J$39,2,0) -> Direct Investment | D37: =VLOOKUP(B37,'S | 02'!$C$6:$J$39,5,0) -> Mozn | E37: ='CF (Equity, Debt)'!D35 -> 45075 | F37: ='CF (Equity, Debt)'!E35 -> -14.999999 | I37: =SUM(F37:H37) -> -14.999999
B38: ='CF (Equity, Debt)'!C36 -> WLD Tokens | C38: =VLOOKUP(B38,'S | 02'!$C$6:$J$39,2,0) -> Direct Investment | D38: =VLOOKUP(B38,'S | 02'!$C$6:$J$39,5,0) -> Mozn | E38: ='CF (Equity, Debt)'!D36 -> 45075 | F38: ='CF (Equity, Debt)'!E36 -> -0.005875 | I38: =SUM(F38:H38) -> -0.005875
B39: ='CF (Equity, Debt)'!C37 -> WLD Tokens | C39: =VLOOKUP(B39,'S | 02'!$C$6:$J$39,2,0) -> Direct Investment | D39: =VLOOKUP(B39,'S | 02'!$C$6:$J$39,5,0) -> Mozn | E39: ='CF (Equity, Debt)'!D37 -> 45114 | F39: ='CF (Equity, Debt)'!E37 -> -0.001 | I39: =SUM(F39:H39) -> -0.001
B40: ='CF (Equity, Debt)'!C38 -> Applied AI Corporation Limited | C40: =VLOOKUP(B40,'S | 02'!$C$6:$J$39,2,0) -> Direct Investment | D40: =VLOOKUP(B40,'S | 02'!$C$6:$J$39,5,0) -> Mozn | E40: ='CF (Equity, Debt)'!D38 -> 45121 | F40: ='CF (Equity, Debt)'!E38 -> -2.75 | I40: =SUM(F40:H40) -> -2.75
B41: ='CF (Equity, Debt)'!C39 -> Instadeep Limited | C41: =VLOOKUP(B41,'S | 02'!$C$6:$J$39,2,0) -> Direct Investment | D41: =VLOOKUP(B41,'S | 02'!$C$6:$J$39,5,0) -> Mozn | E41: ='CF (Equity, Debt)'!D39 -> 45138 | F41: ='CF (Equity, Debt)'!E39 -> 0 | G41: ='CF (Equity, Debt)'!F39 -> 7.8207761 | I41: =SUM(F41:H41) -> 7.8207761
B43: ='CF (Equity, Debt)'!C42 -> Glass Earth Holdings LLC | C43: =VLOOKUP(B43,'S | 02'!$C$6:$J$39,2,0) -> Debt Investment | D43: =VLOOKUP(B43,'S | 02'!$C$6:$J$39,5,0) -> Mozn | E43: ='CF (Equity, Debt)'!D42 -> 43635 | F43: ='CF (Equity, Debt)'!E42 -> -8 | I43: =SUM(F43:H43) -> -8
B44: ='CF (Equity, Debt)'!C43 -> Mena Mobile Inc (Debt) | C44: =VLOOKUP(B44,'S | 02'!$C$6:$J$39,2,0) -> Debt Investment | D44: =VLOOKUP(B44,'S | 02'!$C$6:$J$39,5,0) -> Mozn | E44: ='CF (Equity, Debt)'!D43 -> 44293 | F44: ='CF (Equity, Debt)'!E43 -> -2.353982 | I44: =SUM(F44:H44) -> -2.353982
B45: ='CF (Equity, Debt)'!C44 -> Esyasoft Holding (Debt) | C45: =VLOOKUP(B45,'S | 02'!$C$6:$J$39,2,0) -> Debt Investment | D45: =VLOOKUP(B45,'S | 02'!$C$6:$J$39,5,0) -> Mozn | E45: ='CF (Equity, Debt)'!D44 -> 44384 | F45: ='CF (Equity, Debt)'!E44 -> -0.411765 | I45: =SUM(F45:H45) -> -0.411765
B46: ='CF (Equity, Debt)'!C45 -> Esyasoft Holding (Debt) | C46: =VLOOKUP(B46,'S | 02'!$C$6:$J$39,2,0) -> Debt Investment | D46: =VLOOKUP(B46,'S | 02'!$C$6:$J$39,5,0) -> Mozn | E46: ='CF (Equity, Debt)'!D45 -> 44902 | F46: ='CF (Equity, Debt)'!E45 -> 0 | G46: ='CF (Equity, Debt)'!F45 -> 0.47078465 | I46: =SUM(F46:H46) -> 0.47078465
B48: Jollychic Holding Limited | C48: =VLOOKUP(B48,'S | 02'!$C$6:$J$39,2,0) -> Direct Investment | D48: =VLOOKUP(B48,'S | 02'!$C$6:$J$39,5,0) -> Mozn | E48: =$E$4 -> 45138 | H48: =VLOOKUP(B48,NAV!$B$9:$E$43,4,0) -> 0 | I48: =SUM(F48:H48) -> 0
B49: Mena Mobile Inc | C49: =VLOOKUP(B49,'S | 02'!$C$6:$J$39,2,0) -> Direct Investment | D49: =VLOOKUP(B49,'S | 02'!$C$6:$J$39,5,0) -> Mozn | E49: =$E$4 -> 45138 | H49: =VLOOKUP(B49,NAV!$B$9:$E$43,4,0) -> 0 | I49: =SUM(F49:H49) -> 0
B50: Flyr Inc | C50: =VLOOKUP(B50,'S | 02'!$C$6:$J$39,2,0) -> Direct Investment | D50: =VLOOKUP(B50,'S | 02'!$C$6:$J$39,5,0) -> Mozn | E50: =$E$4 -> 45138 | H50: =VLOOKUP(B50,NAV!$B$9:$E$43,4,0) -> 78.08223 | I50: =SUM(F50:H50) -> 78.08223
B51: Esyasoft Holding | C51: =VLOOKUP(B51,'S | 02'!$C$6:$J$39,2,0) -> Direct Investment | D51: =VLOOKUP(B51,'S | 02'!$C$6:$J$39,5,0) -> Mozn | E51: =$E$4 -> 45138 | H51: =VLOOKUP(B51,NAV!$B$9:$E$43,4,0) -> 0 | I51: =SUM(F51:H51) -> 0
B52: Beyond Limits | C52: =VLOOKUP(B52,'S | 02'!$C$6:$J$39,2,0) -> Direct Investment | D52: =VLOOKUP(B52,'S | 02'!$C$6:$J$39,5,0) -> Mozn | E52: =$E$4 -> 45138 | H52: =VLOOKUP(B52,NAV!$B$9:$E$43,4,0) -> 91.00154 | I52: =SUM(F52:H52) -> 91.00154
B53: ONT plc | C53: =VLOOKUP(B53,'S | 02'!$C$6:$J$39,2,0) -> Direct Investment | D53: =VLOOKUP(B53,'S | 02'!$C$6:$J$39,5,0) -> Mozn | E53: =$E$4 -> 45138 | H53: =VLOOKUP(B53,NAV!$B$9:$E$43,4,0) -> 150.40044 | I53: =SUM(F53:H53) -> 150.40044
B54: Heygears | C54: =VLOOKUP(B54,'S | 02'!$C$6:$J$39,2,0) -> Direct Investment | D54: =VLOOKUP(B54,'S | 02'!$C$6:$J$39,5,0) -> Mozn | E54: =$E$4 -> 45138 | H54: =VLOOKUP(B54,NAV!$B$9:$E$43,4,0) -> 151.06943 | I54: =SUM(F54:H54) -> 151.06943
B55: Jysan Technologies | C55: Direct Investment | D55: Mozn 1 | E55: =$E$4 -> 45138 | H55: =VLOOKUP(B55,NAV!$B$9:$E$43,4,0) -> 20 | I55: =SUM(F55:H55) -> 20
B56: Cerebras Systems Inc | C56: =VLOOKUP(B56,'S | 02'!$C$6:$J$39,2,0) -> Direct Investment | D56: =VLOOKUP(B56,'S | 02'!$C$6:$J$39,5,0) -> Mozn | E56: =$E$4 -> 45138 | H56: =VLOOKUP(B56,NAV!$B$9:$E$43,4,0) -> 39.999983 | I56: =SUM(F56:H56) -> 39.999983
B57: Endless Studios LLC | C57: =VLOOKUP(B57,'S | 02'!$C$6:$J$39,2,0) -> Direct Investment | D57: =VLOOKUP(B57,'S | 02'!$C$6:$J$39,5,0) -> Mozn | E57: =$E$4 -> 45138 | H57: =VLOOKUP(B57,NAV!$B$9:$E$43,4,0) -> 3 | I57: =SUM(F57:H57) -> 3
B58: Instadeep Limited | C58: =VLOOKUP(B58,'S | 02'!$C$6:$J$39,2,0) -> Direct Investment | D58: =VLOOKUP(B58,'S | 02'!$C$6:$J$39,5,0) -> Mozn | E58: =$E$4 -> 45138 | H58: =VLOOKUP(B58,NAV!$B$9:$E$43,4,0) -> 0 | I58: =SUM(F58:H58) -> 0
B59: X-fusion | C59: =VLOOKUP(B59,'S | 02'!$C$6:$J$39,2,0) -> Direct Investment | D59: =VLOOKUP(B59,'S | 02'!$C$6:$J$39,5,0) -> Mozn 2 | E59: =$E$4 -> 45138 | H59: =VLOOKUP(B59,NAV!$B$9:$E$43,4,0) -> 408.28799 | I59: =SUM(F59:H59) -> 408.28799
B60: Applied AI Corporation Limited | C60: =VLOOKUP(B60,'S | 02'!$C$6:$J$39,2,0) -> Direct Investment | D60: =VLOOKUP(B60,'S | 02'!$C$6:$J$39,5,0) -> Mozn | E60: =$E$4 -> 45138 | H60: =VLOOKUP(B60,NAV!$B$9:$E$43,4,0) -> 7.5 | I60: =SUM(F60:H60) -> 7.5
B61: eSpace | C61: Direct Investment | D61: =VLOOKUP(B61,'S | 02'!$C$6:$J$39,5,0) -> Mozn 4 | E61: =$E$4 -> 45138 | H61: =VLOOKUP(B61,NAV!$B$9:$E$43,4,0) -> 15 | I61: =SUM(F61:H61) -> 15
B62: Tools for Humanity Corporation | C62: Direct Investment | D62: =VLOOKUP(B62,'S | 02'!$C$6:$J$39,5,0) -> Mozn | E62: =$E$4 -> 45138 | H62: =VLOOKUP(B62,NAV!$B$9:$E$43,4,0) -> 14.999999 | I62: =SUM(F62:H62) -> 14.999999
B63: WLD Tokens | C63: Direct Investment | D63: =VLOOKUP(B63,'S | 02'!$C$6:$J$39,5,0) -> Mozn | E63: =$E$4 -> 45138 | H63: =VLOOKUP(B63,NAV!$B$9:$E$43,4,0) -> 15 | I63: =SUM(F63:H63) -> 15
B64: Glass Earth Holdings LLC | C64: =VLOOKUP(B64,'S | 02'!$C$6:$J$39,2,0) -> Debt Investment | D64: =VLOOKUP(B64,'S | 02'!$C$6:$J$39,5,0) -> Mozn | E64: =$E$4 -> 45138 | H64: =VLOOKUP(B64,NAV!$B$9:$E$43,4,0) -> 0 | I64: =SUM(F64:H64) -> 0
B65: Mena Mobile Inc (Debt) | C65: =VLOOKUP(B65,'S | 02'!$C$6:$J$39,2,0) -> Debt Investment | D65: =VLOOKUP(B65,'S | 02'!$C$6:$J$39,5,0) -> Mozn | E65: =$E$4 -> 45138 | H65: =VLOOKUP(B65,NAV!$B$9:$E$43,4,0) -> 2.353982 | I65: =SUM(F65:H65) -> 2.353982

Sheet 4. G42-IRR
B2: IRR - G42 Investments | H2: =COUNTA(B13:B68) -> 56
B4: Date of NAV | E4: =D!D2 -> 45138
K7: Invested | L7: Remaining Commitment | M7: Distributions | N7: Residual Value | O7: IRR | P7: TVPI | Q7: RPI | R7: DPI
K9: =-SUM(F12:F68) -> 1256.2697 | M9: =SUM(G12:G68) -> 4.4275637 | N9: =SUM(H12:H68) -> 1255.1666 | O9: =XIRR(I13:I68,E13:E68) -> 0.0021642417 | P9: =(M9+N9)/K9 -> 1.0026464 | Q9: =N9/K9 -> 0.99912199 | R9: =M9/K9 -> 0.0035243736
B10: (in USD, Mn)
B11: Investment | C11: Type | D11: Entity | E11: Payment date | F11: Contribution | G11: Distributions | H11: Remaining Value | I11: Combined | M11: Checks
K12: Invested | L12: =-SUM(F12:F68) -> 1256.2697 | M12: =K9='S | 02'!L40 -> TRUE
B13: ='CF (Equity, Debt)'!C26 -> DriveNets | C13: =VLOOKUP(B13,'S | 02'!$C$6:$J$39,2,0) -> Direct Investment | D13: =VLOOKUP(B13,'S | 02'!$C$6:$J$39,5,0) -> G42 | E13: ='CF (Equity, Debt)'!D26 -> 44643 | F13: ='CF (Equity, Debt)'!E26 -> -200 | I13: =SUM(F13:H13) -> -200 | K13: NAV | L13: =SUM(H12:H68) -> 1255.1666 | M13: =M9='S | 02'!M40 -> TRUE
B14: ='CF (Equity, Debt)'!C27 -> DriveNets | C14: =VLOOKUP(B14,'S | 02'!$C$6:$J$39,2,0) -> Direct Investment | D14: =VLOOKUP(B14,'S | 02'!$C$6:$J$39,5,0) -> G42 | E14: ='CF (Equity, Debt)'!D27 -> 44680 | F14: ='CF (Equity, Debt)'!E27 -> -100 | I14: =SUM(F14:H14) -> -100 | K14: Distributions | L14: =SUM(G12:G68) -> 4.4275637 | M14: =ROUND(N9,3)=ROUND('S | 02'!N40,3) -> TRUE
B15: ='CF (Equity, Debt)'!C29 -> vTv Therapeutics Inc. | C15: =VLOOKUP(B15,'S | 02'!$C$6:$J$39,2,0) -> Direct Investment | D15: =VLOOKUP(B15,'S | 02'!$C$6:$J$39,5,0) -> G42 | E15: ='CF (Equity, Debt)'!D29 -> 44712 | F15: ='CF (Equity, Debt)'!E29 -> -12.5 | I15: =SUM(F15:H15) -> -12.5 | K15: Total Gain | L15: =L14+L13-L12 -> 3.324546
B16: ='CF (Equity, Debt)'!C34 -> vTv Therapeutics Inc. | C16: =VLOOKUP(B16,'S | 02'!$C$6:$J$39,2,0) -> Direct Investment | D16: =VLOOKUP(B16,'S | 02'!$C$6:$J$39,5,0) -> G42 | E16: ='CF (Equity, Debt)'!D34 -> 44985 | F16: ='CF (Equity, Debt)'!E34 -> -12.03125 | I16: =SUM(F16:H16) -> -12.03125 | K16: IRR | L16: =O9 -> 0.0021642417
B17: ='CF (Equity, Debt)'!C30 -> Honor Device Co Ltd | C17: =VLOOKUP(B17,'S | 02'!$C$6:$J$39,2,0) -> Direct Investment | D17: =VLOOKUP(B17,'S | 02'!$C$6:$J$39,5,0) -> G42 3 | E17: ='CF (Equity, Debt)'!D30 -> 44769 | F17: ='CF (Equity, Debt)'!E30 -> -600 | I17: =SUM(F17:H17) -> -600
B18: ='CF (Equity, Debt)'!C31 -> Honor Device Co Ltd | C18: =VLOOKUP(B18,'S | 02'!$C$6:$J$39,2,0) -> Direct Investment | D18: =VLOOKUP(B18,'S | 02'!$C$6:$J$39,5,0) -> G42 3 | E18: ='CF (Equity, Debt)'!D31 -> 44849 | F18: ='CF (Equity, Debt)'!E31 -> -200 | I18: =SUM(F18:H18) -> -200
B19: ='CF (Funds)'!B3 -> Sinovation Disrupt Fund, L.P. | C19: =VLOOKUP(B19,'S | 02'!$C$6:$J$39,2,0) -> Fund Investment | D19: =VLOOKUP(B19,'S | 02'!$C$6:$J$39,5,0) -> G42 | E19: ='CF (Funds)'!C3 -> 44153 | F19: ='CF (Funds)'!D3 -> -10.5 | G19: ='CF (Funds)'!E3 -> 0 | I19: =SUM(F19:H19) -> -10.5 | L19: =L15/L12 -> 0.0026463633
B20: ='CF (Funds)'!B4 -> Sinovation Disrupt Fund, L.P. | C20: =VLOOKUP(B20,'S | 02'!$C$6:$J$39,2,0) -> Fund Investment | D20: =VLOOKUP(B20,'S | 02'!$C$6:$J$39,5,0) -> G42 | E20: ='CF (Funds)'!C4 -> 44238 | F20: ='CF (Funds)'!D4 -> 4.214027 | G20: ='CF (Funds)'!E4 -> 0 | I20: =SUM(F20:H20) -> 4.214027
B21: ='CF (Funds)'!B5 -> Sinovation Disrupt Fund, L.P. | C21: =VLOOKUP(B21,'S | 02'!$C$6:$J$39,2,0) -> Fund Investment | D21: =VLOOKUP(B21,'S | 02'!$C$6:$J$39,5,0) -> G42 | E21: ='CF (Funds)'!C5 -> 44238 | F21: ='CF (Funds)'!D5 -> 0 | G21: ='CF (Funds)'!E5 -> 0.05044835 | I21: =SUM(F21:H21) -> 0.05044835
B22: ='CF (Funds)'!B6 -> Sinovation Disrupt Fund, L.P. | C22: =VLOOKUP(B22,'S | 02'!$C$6:$J$39,2,0) -> Fund Investment | D22: =VLOOKUP(B22,'S | 02'!$C$6:$J$39,5,0) -> G42 | E22: ='CF (Funds)'!C6 -> 44285 | F22: ='CF (Funds)'!D6 -> -6.433746 | G22: ='CF (Funds)'!E6 -> 0 | I22: =SUM(F22:H22) -> -6.433746
B23: ='CF (Funds)'!B7 -> Sinovation Disrupt Fund, L.P. | C23: =VLOOKUP(B23,'S | 02'!$C$6:$J$39,2,0) -> Fund Investment | D23: =VLOOKUP(B23,'S | 02'!$C$6:$J$39,5,0) -> G42 | E23: ='CF (Funds)'!C7 -> 44269 | F23: ='CF (Funds)'!D7 -> 1.1352074 | G23: ='CF (Funds)'!E7 -> 0 | I23: =SUM(F23:H23) -> 1.1352074
B24: ='CF (Funds)'!B8 -> Sinovation Disrupt Fund, L.P. | C24: =VLOOKUP(B24,'S | 02'!$C$6:$J$39,2,0) -> Fund Investment | D24: =VLOOKUP(B24,'S | 02'!$C$6:$J$39,5,0) -> G42 | E24: ='CF (Funds)'!C8 -> 44269 | F24: ='CF (Funds)'!D8 -> 0 | G24: ='CF (Funds)'!E8 -> 0.0259 | I24: =SUM(F24:H24) -> 0.0259
B25: ='CF (Funds)'!B9 -> Sinovation Disrupt Fund, L.P. | C25: =VLOOKUP(B25,'S | 02'!$C$6:$J$39,2,0) -> Fund Investment | D25: =VLOOKUP(B25,'S | 02'!$C$6:$J$39,5,0) -> G42 | E25: ='CF (Funds)'!C9 -> 44483 | F25: ='CF (Funds)'!D9 -> -7.567138 | G25: ='CF (Funds)'!E9 -> 0 | I25: =SUM(F25:H25) -> -7.567138
B26: ='CF (Funds)'!B10 -> Sinovation Disrupt Fund, L.P. | C26: =VLOOKUP(B26,'S | 02'!$C$6:$J$39,2,0) -> Fund Investment | D26: =VLOOKUP(B26,'S | 02'!$C$6:$J$39,5,0) -> G42 | E26: ='CF (Funds)'!C10 -> 44554 | F26: ='CF (Funds)'!D10 -> -7.385016 | G26: ='CF (Funds)'!E10 -> 0 | I26: =SUM(F26:H26) -> -7.385016
B27: ='CF (Funds)'!B11 -> Sinovation Disrupt Fund, L.P. | C27: =VLOOKUP(B27,'S | 02'!$C$6:$J$39,2,0) -> Fund Investment | D27: =VLOOKUP(B27,'S | 02'!$C$6:$J$39,5,0) -> G42 | E27: ='CF (Funds)'!C11 -> 44554 | F27: ='CF (Funds)'!D11 -> 4.0733456 | G27: ='CF (Funds)'!E11 -> 0 | I27: =SUM(F27:H27) -> 4.0733456
B28: ='CF (Funds)'!B12 -> Sinovation Disrupt Fund, L.P. | C28: =VLOOKUP(B28,'S | 02'!$C$6:$J$39,2,0) -> Fund Investment | D28: =VLOOKUP(B28,'S | 02'!$C$6:$J$39,5,0) -> G42 | E28: ='CF (Funds)'!C12 -> 44554 | F28: ='CF (Funds)'!D12 -> 0 | G28: ='CF (Funds)'!E12 -> 0.139694 | I28: =SUM(F28:H28) -> 0.139694
B29: ='CF (Funds)'!B13 -> Sinovation Disrupt Fund, L.P. | C29: =VLOOKUP(B29,'S | 02'!$C$6:$J$39,2,0) -> Fund Investment | D29: =VLOOKUP(B29,'S | 02'!$C$6:$J$39,5,0) -> G42 | E29: ='CF (Funds)'!C13 -> 44703 | F29: ='CF (Funds)'!D13 -> 5.673074 | G29: ='CF (Funds)'!E13 -> 0 | I29: =SUM(F29:H29) -> 5.673074
B30: ='CF (Funds)'!B14 -> Sinovation Disrupt Fund, L.P. | C30: =VLOOKUP(B30,'S | 02'!$C$6:$J$39,2,0) -> Fund Investment | D30: =VLOOKUP(B30,'S | 02'!$C$6:$J$39,5,0) -> G42 | E30: ='CF (Funds)'!C14 -> 44703 | F30: ='CF (Funds)'!D14 -> 0 | G30: ='CF (Funds)'!E14 -> 0.227786 | I30: =SUM(F30:H30) -> 0.227786
B31: ='CF (Funds)'!B15 -> Sinovation Disrupt Fund, L.P. | C31: =VLOOKUP(B31,'S | 02'!$C$6:$J$39,2,0) -> Fund Investment | D31: =VLOOKUP(B31,'S | 02'!$C$6:$J$39,5,0) -> G42 | E31: ='CF (Funds)'!C15 -> 44776 | F31: ='CF (Funds)'!D15 -> -3.235493 | G31: ='CF (Funds)'!E15 -> 0 | I31: =SUM(F31:H31) -> -3.235493
... B60: ='CF (Funds)'!B44 -> Acies Investments Fund I, L.P. | C60: =VLOOKUP(B60,'S | 02'!$C$6:$J$39,2,0) -> Fund Investment | D60: =VLOOKUP(B60,'S | 02'!$C$6:$J$39,5,0) -> G42 | E60: ='CF (Funds)'!C44 -> 44875 | F60: ='CF (Funds)'!D44 -> -3.388275 | G60: ='CF (Funds)'!E44 -> 0 | I60: =SUM(F60:H60) -> -3.388275
B61: DriveNets | C61: =VLOOKUP(B61,'S | 02'!$C$6:$J$39,2,0) -> Direct Investment | D61: =VLOOKUP(B61,'S | 02'!$C$6:$J$39,5,0) -> G42 | E61: =$E$4 -> 45138 | H61: =VLOOKUP(B61,NAV!$B$9:$E$43,4,0) -> 300 | I61: =SUM(F61:H61) -> 300
B62: vTv Therapeutics Inc. | C62: =VLOOKUP(B62,'S | 02'!$C$6:$J$39,2,0) -> Direct Investment | D62: =VLOOKUP(B62,'S | 02'!$C$6:$J$39,5,0) -> G42 | E62: =$E$4 -> 45138 | H62: =VLOOKUP(B62,NAV!$B$9:$E$43,4,0) -> 7.0626663 | I62: =SUM(F62:H62) -> 7.0626663
B63: Honor Device Co Ltd | C63: =VLOOKUP(B63,'S | 02'!$C$6:$J$39,2,0) -> Direct Investment | D63: =VLOOKUP(B63,'S | 02'!$C$6:$J$39,5,0) -> G42 3 | E63: =$E$4 -> 45138 | H63: =VLOOKUP(B63,NAV!$B$9:$E$43,4,0) -> 817.18905 | I63: =SUM(F63:H63) -> 817.18905
B64: New Space Capital Fund I | C64: =VLOOKUP(B64,'S | 02'!$C$6:$J$39,2,0) -> Fund Investment | D64: =VLOOKUP(B64,'S | 02'!$C$6:$J$39,5,0) -> G42 | E64: =$E$4 -> 45138 | H64: =VLOOKUP(B64,NAV!$B$9:$E$43,4,0) -> 13.390399 | I64: =SUM(F64:H64) -> 13.390399
B65: New Space Capital GP Com SCSp | C65: =VLOOKUP(B65,'S | 02'!$C$6:$J$39,2,0) -> Fund Investment | D65: =VLOOKUP(B65,'S | 02'!$C$6:$J$39,5,0) -> G42 | E65: =$E$4 -> 45138 | H65: =VLOOKUP(B65,NAV!$B$9:$E$43,4,0) -> 3.276608 | I65: =SUM(F65:H65) -> 3.276608
B66: North Summit Capital Fund | C66: =VLOOKUP(B66,'S | 02'!$C$6:$J$39,2,0) -> Fund Investment | D66: =VLOOKUP(B66,'S | 02'!$C$6:$J$39,5,0) -> G42 | E66: =$E$4 -> 45138 | H66: =VLOOKUP(B66,NAV!$B$9:$E$43,4,0) -> 81.695786 | I66: =SUM(F66:H66) -> 81.695786
B67: Sinovation Disrupt Fund, L.P. | C67: =VLOOKUP(B67,'S | 02'!$C$6:$J$39,2,0) -> Fund Investment | D67: =VLOOKUP(B67,'S | 02'!$C$6:$J$39,5,0) -> G42 | E67: =$E$4 -> 45138 | H67: =VLOOKUP(B67,NAV!$B$9:$E$43,4,0) -> 19.244515 | I67: =SUM(F67:H67) -> 19.244515
B68: Acies Investments Fund I, L.P. | C68: =VLOOKUP(B68,'S | 02'!$C$6:$J$39,2,0) -> Fund Investment | D68: =VLOOKUP(B68,'S | 02'!$C$6:$J$39,5,0) -> G42 | E68: =$E$4 -> 45138 | H68: =VLOOKUP(B68,NAV!$B$9:$E$43,4,0) -> 13.307625 | I68: =SUM(F68:H68) -> 13.307625

Sheet 5. CF Profile
C2: CASH DEPLOYED OVER TIME…
C5: Investment | D5: Type | E5: Payment date | F5: Period | G5: Contribution | H5: Distribution | J5: Contribution | K5: Equity | L5: Debt | M5: Fund | N5: Total | P5: Distribution | Q5: Equity | R5: Debt | S5: Fund | T5: Total
B6: Equity | C6: ='CF (Equity, Debt)'!C4 -> Jollychic Holding Limited | D6: Equity | E6: ='CF (Equity, Debt)'!D4 -> 43470 | F6: ="Q"&ROUNDUP(MONTH(E6)/3,0)&" "&YEAR(E6) -> Q1 2019 | G6: ='CF (Equity, Debt)'!E4 -> -30 | H6: ='CF (Equity, Debt)'!F4 -> 0
C7: ='CF (Equity, Debt)'!C5 -> Jollychic Holding Limited | D7: Equity | E7: ='CF (Equity, Debt)'!D5 -> 43724 | F7: ="Q"&ROUNDUP(MONTH(E7)/3,0)&" "&YEAR(E7) -> Q3 2019 | G7: ='CF (Equity, Debt)'!E5 -> -20 | H7: ='CF (Equity, Debt)'!F5 -> 0 | J7: Q1 2019 | K7: =-SUMIFS($G$5:$G$117,$D$5:$D$117,$K$5,$F$5:$F$117,J7) -> 30 | L7: =-SUMIFS($G$5:$G$117,$D$5:$D$117,$L$5,$F$5:$F$117,J7) -> 0 | M7: =-SUMIFS($G$5:$G$117,$D$5:$D$117,"Fund",$F$5:$F$117,J7) -> 0 | N7: =-SUMIF($F$5:$H$117,$J7,$G$5:$G$117) -> 30 | P7: Q1 2019 | Q7: =SUMIFS($H$5:$H$117,$D$5:$D$117,$Q$5,$F$5:$F$117,J7) -> 0 | R7: =SUMIFS($H$5:$H$117,$D$5:$D$117,$R$5,$F$5:$F$117,J7) -> 0 | S7: =SUMIFS($H$5:$H$117,$D$5:$D$117,$S$5,$F$5:$F$117,J7) -> 0 | T7: =SUMIF($F$5:$H$117,$J7,$H$5:$H$117) -> 0
C8: ='CF (Equity, Debt)'!C6 -> Jollychic Holding Limited | D8: Equity | E8: ='CF (Equity, Debt)'!D6 -> 43724 | F8: ="Q"&ROUNDUP(MONTH(E8)/3,0)&" "&YEAR(E8) -> Q3 2019 | G8: ='CF (Equity, Debt)'!E6 -> -15 | H8: ='CF (Equity, Debt)'!F6 -> 0 | J8: Q2 2019 | K8: =-SUMIFS($G$5:$G$117,$D$5:$D$117,$K$5,$F$5:$F$117,J8) -> 12.999998 | L8: =-SUMIFS($G$5:$G$117,$D$5:$D$117,$L$5,$F$5:$F$117,J8) -> 8 | M8: =-SUMIFS($G$5:$G$117,$D$5:$D$117,"Fund",$F$5:$F$117,J8) -> 0 | N8: =-SUMIF($F$5:$H$117,$J8,$G$5:$G$117) -> 20.999998 | P8: Q2 2019 | Q8: =SUMIFS($H$5:$H$117,$D$5:$D$117,$Q$5,$F$5:$F$117,J8) -> 0 | R8: =SUMIFS($H$5:$H$117,$D$5:$D$117,$R$5,$F$5:$F$117,J8) -> 0 | S8: =SUMIFS($H$5:$H$117,$D$5:$D$117,$S$5,$F$5:$F$117,J8) -> 0 | T8: =SUMIF($F$5:$H$117,$J8,$H$5:$H$117) -> 0
C9: ='CF (Equity, Debt)'!C7 -> Mena Mobile Inc | D9: Equity | E9: ='CF (Equity, Debt)'!D7 -> 43563 | F9: ="Q"&ROUNDUP(MONTH(E9)/3,0)&" "&YEAR(E9) -> Q2 2019 | G9: ='CF (Equity, Debt)'!E7 -> -8 | H9: ='CF (Equity, Debt)'!F7 -> 0 | J9: Q3 2019 | K9: =-SUMIFS($G$5:$G$117,$D$5:$D$117,$K$5,$F$5:$F$117,J9) -> 35 | L9: =-SUMIFS($G$5:$G$117,$D$5:$D$117,$L$5,$F$5:$F$117,J9) -> 0 | M9: =-SUMIFS($G$5:$G$117,$D$5:$D$117,"Fund",$F$5:$F$117,J9) -> 3 | N9: =-SUMIF($F$5:$H$117,$J9,$G$5:$G$117) -> 38 | P9: Q3 2019 | Q9: =SUMIFS($H$5:$H$117,$D$5:$D$117,$Q$5,$F$5:$F$117,J9) -> 0 | R9: =SUMIFS($H$5:$H$117,$D$5:$D$117,$R$5,$F$5:$F$117,J9) -> 0 | S9: =SUMIFS($H$5:$H$117,$D$5:$D$117,$S$5,$F$5:$F$117,J9) -> 0 | T9: =SUMIF($F$5:$H$117,$J9,$H$5:$H$117) -> 0
C10: ='CF (Equity, Debt)'!C8 -> Flyr Inc | D10: Equity | E10: ='CF (Equity, Debt)'!D8 -> 43570 | F10: ="Q"&ROUNDUP(MONTH(E10)/3,0)&" "&YEAR(E10) -> Q2 2019 | G10: ='CF (Equity, Debt)'!E8 -> -4.9999981 | H10: ='CF (Equity, Debt)'!F8 -> 0 | J10: Q4 2019 | K10: =-SUMIFS($G$5:$G$117,$D$5:$D$117,$K$5,$F$5:$F$117,J10) -> 0 | L10: =-SUMIFS($G$5:$G$117,$D$5:$D$117,$L$5,$F$5:$F$117,J10) -> 0 | M10: =-SUMIFS($G$5:$G$117,$D$5:$D$117,"Fund",$F$5:$F$117,J10) -> 0 | N10: =-SUMIF($F$5:$H$117,$J10,$G$5:$G$117) -> 0 | P10: Q4 2019 | Q10: =SUMIFS($H$5:$H$117,$D$5:$D$117,$Q$5,$F$5:$F$117,J10) -> 0 | R10: =SUMIFS($H$5:$H$117,$D$5:$D$117,$R$5,$F$5:$F$117,J10) -> 0 | S10: =SUMIFS($H$5:$H$117,$D$5:$D$117,$S$5,$F$5:$F$117,J10) -> 0 | T10: =SUMIF($F$5:$H$117,$J10,$H$5:$H$117) -> 0
C11: ='CF (Equity, Debt)'!C9 -> Flyr Inc | D11: Equity | E11: ='CF (Equity, Debt)'!D9 -> 43915 | F11: ="Q"&ROUNDUP(MONTH(E11)/3,0)&" "&YEAR(E11) -> Q1 2020 | G11: ='CF (Equity, Debt)'!E9 -> -5.0000019 | H11: ='CF (Equity, Debt)'!F9 -> 0 | J11: Q1 2020 | K11: =-SUMIFS($G$5:$G$117,$D$5:$D$117,$K$5,$F$5:$F$117,J11) -> 75.609443 | L11: =-SUMIFS($G$5:$G$117,$D$5:$D$117,$L$5,$F$5:$F$117,J11) -> 0 | M11: =-SUMIFS($G$5:$G$117,$D$5:$D$117,"Fund",$F$5:$F$117,J11) -> 9.50975 | N11: =-SUMIF($F$5:$H$117,$J11,$G$5:$G$117) -> 85.119193 | P11: Q1 2020 | Q11: =SUMIFS($H$5:$H$117,$D$5:$D$117,$Q$5,$F$5:$F$117,J11) -> 0 | R11: =SUMIFS($H$5:$H$117,$D$5:$D$117,$R$5,$F$5:$F$117,J11) -> 0 | S11: =SUMIFS($H$5:$H$117,$D$5:$D$117,$S$5,$F$5:$F$117,J11) -> 0 | T11: =SUMIF($F$5:$H$117,$J11,$H$5:$H$117) -> 0
C12: ='CF (Equity, Debt)'!C10 -> Esyasoft Holding | D12: Equity | E12: ='CF (Equity, Debt)'!D10 -> 43870 | F12: ="Q"&ROUNDUP(MONTH(E12)/3,0)&" "&YEAR(E12) -> Q1 2020 | G12: ='CF (Equity, Debt)'!E10 -> -2.5 | H12: ='CF (Equity, Debt)'!F10 -> 0 | J12: Q2 2020 | K12: =-SUMIFS($G$5:$G$117,$D$5:$D$117,$K$5,$F$5:$F$117,J12) -> 142.12004 | L12: =-SUMIFS($G$5:$G$117,$D$5:$D$117,$L$5,$F$5:$F$117,J12) -> 0 | M12: =-SUMIFS($G$5:$G$117,$D$5:$D$117,"Fund",$F$5:$F$117,J12) -> 45.785 | N12: =-SUMIF($F$5:$H$117,$J12,$G$5:$G$117) -> 187.90504 | P12: Q2 2020 | Q12: =SUMIFS($H$5:$H$117,$D$5:$D$117,$Q$5,$F$5:$F$117,J12) -> 0 | R12: =SUMIFS($H$5:$H$117,$D$5:$D$117,$R$5,$F$5:$F$117,J12) -> 0 | S12: =SUMIFS($H$5:$H$117,$D$5:$D$117,$S$5,$F$5:$F$117,J12) -> 0 | T12: =SUMIF($F$5:$H$117,$J12,$H$5:$H$117) -> 0
C13: ='CF (Equity, Debt)'!C11 -> Beyond Limits | D13: Equity | E13: ='CF (Equity, Debt)'!D11 -> 43879 | F13: ="Q"&ROUNDUP(MONTH(E13)/3,0)&" "&YEAR(E13) -> Q1 2020 | G13: ='CF (Equity, Debt)'!E11 -> -20 | H13: ='CF (Equity, Debt)'!F11 -> 0 | J13: Q3 2020 | K13: =-SUMIFS($G$5:$G$117,$D$5:$D$117,$K$5,$F$5:$F$117,J13) -> 10 | L13: =-SUMIFS($G$5:$G$117,$D$5:$D$117,$L$5,$F$5:$F$117,J13) -> 0 | M13: =-SUMIFS($G$5:$G$117,$D$5:$D$117,"Fund",$F$5:$F$117,J13) -> 23.623435 | N13: =-SUMIF($F$5:$H$117,$J13,$G$5:$G$117) -> 33.623435 | P13: Q3 2020 | Q13: =SUMIFS($H$5:$H$117,$D$5:$D$117,$Q$5,$F$5:$F$117,J13) -> 0 | R13: =SUMIFS($H$5:$H$117,$D$5:$D$117,$R$5,$F$5:$F$117,J13) -> 0 | S13: =SUMIFS($H$5:$H$117,$D$5:$D$117,$S$5,$F$5:$F$117,J13) -> 0 | T13: =SUMIF($F$5:$H$117,$J13,$H$5:$H$117) -> 0
C14: ='CF (Equity, Debt)'!C12 -> Beyond Limits | D14: Equity | E14: ='CF (Equity, Debt)'!D12 -> 43921 | F14: ="Q"&ROUNDUP(MONTH(E14)/3,0)&" "&YEAR(E14) -> Q1 2020 | G14: ='CF (Equity, Debt)'!E12 -> -30 | H14: ='CF (Equity, Debt)'!F12 -> 0 | J14: Q4 2020 | K14: =-SUMIFS($G$5:$G$117,$D$5:$D$117,$K$5,$F$5:$F$117,J14) -> 60 | L14: =-SUMIFS($G$5:$G$117,$D$5:$D$117,$L$5,$F$5:$F$117,J14) -> 0 | M14: =-SUMIFS($G$5:$G$117,$D$5:$D$117,"Fund",$F$5:$F$117,J14) -> 9.482293 | N14: =-SUMIF($F$5:$H$117,$J14,$G$5:$G$117) -> 69.482293 | P14: Q4 2020 | Q14: =SUMIFS($H$5:$H$117,$D$5:$D$117,$Q$5,$F$5:$F$117,J14) -> 0 | R14: =SUMIFS($H$5:$H$117,$D$5:$D$117,$R$5,$F$5:$F$117,J14) -> 0 | S14: =SUMIFS($H$5:$H$117,$D$5:$D$117,$S$5,$F$5:$F$117,J14) -> 0.582902 | T14: =SUMIF($F$5:$H$117,$J14,$H$5:$H$117) -> 0.582902
C15: ='CF (Equity, Debt)'!C13 -> Beyond Limits | D15: Equity | E15: ='CF (Equity, Debt)'!D13 -> 43989 | F15: ="Q"&ROUNDUP(MONTH(E15)/3,0)&" "&YEAR(E15) -> Q2 2020 | G15: ='CF (Equity, Debt)'!E13 -> -30 | H15: ='CF (Equity, Debt)'!F13 -> 0 | J15: Q1 2021 | K15: =-SUMIFS($G$5:$G$117,$D$5:$D$117,$K$5,$F$5:$F$117,J15) -> 0 | L15: =-SUMIFS($G$5:$G$117,$D$5:$D$117,$L$5,$F$5:$F$117,J15) -> 0 | M15: =-SUMIFS($G$5:$G$117,$D$5:$D$117,"Fund",$F$5:$F$117,J15) -> 1.0845116 | N15: =-SUMIF($F$5:$H$117,$J15,$G$5:$G$117) -> 1.0845116 | P15: Q1 2021 | Q15: =SUMIFS($H$5:$H$117,$D$5:$D$117,$Q$5,$F$5:$F$117,J15) -> 0 | R15: =SUMIFS($H$5:$H$117,$D$5:$D$117,$R$5,$F$5:$F$117,J15) -> 0 | S15: =SUMIFS($H$5:$H$117,$D$5:$D$117,$S$5,$F$5:$F$117,J15) -> 0.07634835 | T15: =SUMIF($F$5:$H$117,$J15,$H$5:$H$117) -> 0.07634835
C16: ='CF (Equity, Debt)'!C14 -> Beyond Limits | D16: Equity | E16: ='CF (Equity, Debt)'!D14 -> 44103 | F16: ="Q"&ROUNDUP(MONTH(E16)/3,0)&" "&YEAR(E16) -> Q3 2020 | G16: ='CF (Equity, Debt)'!E14 -> -10 | H16: ='CF (Equity, Debt)'!F14 -> 0 | J16: Q2 2021 | K16: =-SUMIFS($G$5:$G$117,$D$5:$D$117,$K$5,$F$5:$F$117,J16) -> 31.24078 | L16: =-SUMIFS($G$5:$G$117,$D$5:$D$117,$L$5,$F$5:$F$117,J16) -> 2.353982 | M16: =-SUMIFS($G$5:$G$117,$D$5:$D$117,"Fund",$F$5:$F$117,J16) -> 6.1810318 | N16: =-SUMIF($F$5:$H$117,$J16,$G$5:$G$117) -> 39.775794 | P16: Q2 2021 | Q16: =SUMIFS($H$5:$H$117,$D$5:$D$117,$Q$5,$F$5:$F$117,J16) -> 0 | R16: =SUMIFS($H$5:$H$117,$D$5:$D$117,$R$5,$F$5:$F$117,J16) -> 0 | S16: =SUMIFS($H$5:$H$117,$D$5:$D$117,$S$5,$F$5:$F$117,J16) -> 0 | T16: =SUMIF($F$5:$H$117,$J16,$H$5:$H$117) -> 0
C17: ='CF (Equity, Debt)'!C15 -> ONT plc | D17: Equity | E17: ='CF (Equity, Debt)'!D15 -> 43968 | F17: ="Q"&ROUNDUP(MONTH(E17)/3,0)&" "&YEAR(E17) -> Q2 2020 | G17: ='CF (Equity, Debt)'!E15 -> -50 | H17: ='CF (Equity, Debt)'!F15 -> 0 | J17: Q3 2021 | K17: =-SUMIFS($G$5:$G$117,$D$5:$D$117,$K$5,$F$5:$F$117,J17) -> 0 | L17: =-SUMIFS($G$5:$G$117,$D$5:$D$117,$L$5,$F$5:$F$117,J17) -> 0.411765 | M17: =-SUMIFS($G$5:$G$117,$D$5:$D$117,"Fund",$F$5:$F$117,J17) -> 0.98965473 | N17: =-SUMIF($F$5:$H$117,$J17,$G$5:$G$117) -> 1.4014197 | P17: Q3 2021 | Q17: =SUMIFS($H$5:$H$117,$D$5:$D$117,$Q$5,$F$5:$F$117,J17) -> 0 | R17: =SUMIFS($H$5:$H$117,$D$5:$D$117,$R$5,$F$5:$F$117,J17) -> 0 | S17: =SUMIFS($H$5:$H$117,$D$5:$D$117,$S$5,$F$5:$F$117,J17) -> 0.445059 | T17: =SUMIF($F$5:$H$117,$J17,$H$5:$H$117) -> 0.445059
C18: ='CF (Equity, Debt)'!C16 -> ONT plc | D18: Equity | E18: ='CF (Equity, Debt)'!D16 -> 44006 | F18: ="Q"&ROUNDUP(MONTH(E18)/3,0)&" "&YEAR(E18) -> Q2 2020 | G18: ='CF (Equity, Debt)'!E16 -> -27.268351 | H18: ='CF (Equity, Debt)'!F16 -> 0 | J18: Q4 2021 | K18: =-SUMIFS($G$5:$G$117,$D$5:$D$117,$K$5,$F$5:$F$117,J18) -> 48.023704 | L18: =-SUMIFS($G$5:$G$117,$D$5:$D$117,$L$5,$F$5:$F$117,J18) -> 0 | M18: =-SUMIFS($G$5:$G$117,$D$5:$D$117,"Fund",$F$5:$F$117,J18) -> 11.901731 | N18: =-SUMIF($F$5:$H$117,$J18,$G$5:$G$117) -> 59.925434 | P18: Q4 2021 | Q18: =SUMIFS($H$5:$H$117,$D$5:$D$117,$Q$5,$F$5:$F$117,J18) -> 0 | R18: =SUMIFS($H$5:$H$117,$D$5:$D$117,$R$5,$F$5:$F$117,J18) -> 0 | S18: =SUMIFS($H$5:$H$117,$D$5:$D$117,$S$5,$F$5:$F$117,J18) -> 0.139694 | T18: =SUMIF($F$5:$H$117,$J18,$H$5:$H$117) -> 0.139694
... C25: ='CF (Equity, Debt)'!C23 -> Endless Studios LLC | D25: Equity | E25: ='CF (Equity, Debt)'!D23 -> 44494 | F25: ="Q"&ROUNDUP(MONTH(E25)/3,0)&" "&YEAR(E25) -> Q4 2021 | G25: ='CF (Equity, Debt)'!E23 -> -3 | H25: ='CF (Equity, Debt)'!F23 -> 0 | J25: Q3 2023 | K25: =-SUMIFS($G$5:$G$117,$D$5:$D$117,$K$5,$F$5:$F$117,J25) -> 2.751 | L25: =-SUMIFS($G$5:$G$117,$D$5:$D$117,$L$5,$F$5:$F$117,J25) -> 0 | M25: =-SUMIFS($G$5:$G$117,$D$5:$D$117,"Fund",$F$5:$F$117,J25) -> 0 | N25: =-SUMIF($F$5:$H$117,$J25,$G$5:$G$117) -> 2.751 | P25: Q2 2023 | Q25: =SUMIFS($H$5:$H$117,$D$5:$D$117,$Q$5,$F$5:$F$117,J25) -> 7.8207761 | R25: =SUMIFS($H$5:$H$117,$D$5:$D$117,$R$5,$F$5:$F$117,J25) -> 0 | S25: =SUMIFS($H$5:$H$117,$D$5:$D$117,$S$5,$F$5:$F$117,J25) -> 0 | T25: =SUMIF($F$5:$H$117,$J25,$H$5:$H$117) -> 7.8207761
C26: ='CF (Equity, Debt)'!C24 -> Instadeep Limited | D26: Equity | E26: ='CF (Equity, Debt)'!D24 -> 44550 | F26: ="Q"&ROUNDUP(MONTH(E26)/3,0)&" "&YEAR(E26) -> Q4 2021 | G26: ='CF (Equity, Debt)'!E24 -> -5.0237202 | H26: ='CF (Equity, Debt)'!F24 -> 0
C27: ='CF (Equity, Debt)'!C25 -> X-fusion | D27: Equity | E27: ='CF (Equity, Debt)'!D25 -> 44574 | F27: ="Q"&ROUNDUP(MONTH(E27)/3,0)&" "&YEAR(E27) -> Q1 2022 | G27: ='CF (Equity, Debt)'!E25 -> -493.50096 | H27: ='CF (Equity, Debt)'!F25 -> 0 | J27: Total | K27: =SUM(K7:K25) -> 2100.533 | L27: =SUM(L7:L25) -> 10.765747 | M27: =SUM(M7:M25) -> 131.73842 | N27: =SUM(N7:N25) -> 2243.0372 | P27: Total | Q27: =SUM(Q7:Q25) -> 12.820776 | R27: =SUM(R7:R25) -> 0.47078465 | S27: =SUM(S7:S25) -> 4.4275637 | T27: =SUM(T7:T25) -> 17.719124
C28: ='CF (Equity, Debt)'!C26 -> DriveNets | D28: Equity | E28: ='CF (Equity, Debt)'!D26 -> 44643 | F28: ="Q"&ROUNDUP(MONTH(E28)/3,0)&" "&YEAR(E28) -> Q1 2022 | G28: ='CF (Equity, Debt)'!E26 -> -200 | H28: ='CF (Equity, Debt)'!F26 -> 0
C29: ='CF (Equity, Debt)'!C27 -> DriveNets | D29: Equity | E29: ='CF (Equity, Debt)'!D27 -> 44680 | F29: ="Q"&ROUNDUP(MONTH(E29)/3,0)&" "&YEAR(E29) -> Q2 2022 | G29: ='CF (Equity, Debt)'!E27 -> -100 | H29: ='CF (Equity, Debt)'!F27 -> 0 | Q29: =Q21=0 -> TRUE | R29: =R21=0 -> TRUE | S29: =S21=0 -> TRUE | T29: =T21=0 -> TRUE
C30: ='CF (Equity, Debt)'!C28 -> Esyasoft Holding | D30: Equity | E30: ='CF (Equity, Debt)'!D28 -> 44691 | F30: ="Q"&ROUNDUP(MONTH(E30)/3,0)&" "&YEAR(E30) -> Q2 2022 | G30: ='CF (Equity, Debt)'!E28 -> 0 | H30: ='CF (Equity, Debt)'!F28 -> 5
C31: ='CF (Equity, Debt)'!C29 -> vTv Therapeutics Inc. | D31: Equity | E31: ='CF (Equity, Debt)'!D29 -> 44712 | F31: ="Q"&ROUNDUP(MONTH(E31)/3,0)&" "&YEAR(E31) -> Q2 2022 | G31: ='CF (Equity, Debt)'!E29 -> -12.5 | H31: ='CF (Equity, Debt)'!F29 -> 0
C32: ='CF (Equity, Debt)'!C30 -> Honor Device Co Ltd | D32: Equity | E32: ='CF (Equity, Debt)'!D30 -> 44769 | F32: ="Q"&ROUNDUP(MONTH(E32)/3,0)&" "&YEAR(E32) -> Q3 2022 | G32: ='CF (Equity, Debt)'!E30 -> -600 | H32: ='CF (Equity, Debt)'!F30 -> 0
C33: ='CF (Equity, Debt)'!C31 -> Honor Device Co Ltd | D33: Equity | E33: ='CF (Equity, Debt)'!D31 -> 44849 | F33: ="Q"&ROUNDUP(MONTH(E33)/3,0)&" "&YEAR(E33) -> Q4 2022 | G33: ='CF (Equity, Debt)'!E31 -> -200 | H33: ='CF (Equity, Debt)'!F31 -> 0
C34: ='CF (Equity, Debt)'!C32 -> Applied AI Corporation Limited | D34: Equity | E34: ='CF (Equity, Debt)'!D32 -> 44861 | F34: ="Q"&ROUNDUP(MONTH(E34)/3,0)&" "&YEAR(E34) -> Q4 2022 | G34: ='CF (Equity, Debt)'!E32 -> -4.75 | H34: ='CF (Equity, Debt)'!F32 -> 0
C35: ='CF (Equity, Debt)'!C33 -> eSpace | D35: Equity | E35: ='CF (Equity, Debt)'!D33 -> 44892 | F35: ="Q"&ROUNDUP(MONTH(E35)/3,0)&" "&YEAR(E35) -> Q4 2022 | G35: ='CF (Equity, Debt)'!E33 -> -15 | H35: ='CF (Equity, Debt)'!F33 -> 0
C36: ='CF (Equity, Debt)'!C34 -> vTv Therapeutics Inc. | D36: Equity | E36: ='CF (Equity, Debt)'!D34 -> 44985 | F36: ="Q"&ROUNDUP(MONTH(E36)/3,0)&" "&YEAR(E36) -> Q1 2023 | G36: ='CF (Equity, Debt)'!E34 -> -12.03125 | H36: ='CF (Equity, Debt)'!F34 -> 0
C37: ='CF (Equity, Debt)'!C35 -> Tools for Humanity Corporation | D37: Equity | E37: ='CF (Equity, Debt)'!D35 -> 45075 | F37: ="Q"&ROUNDUP(MONTH(E37)/3,0)&" "&YEAR(E37) -> Q2 2023 | G37: ='CF (Equity, Debt)'!E35 -> -14.999999 | H37: ='CF (Equity, Debt)'!F35 -> 0
C38: ='CF (Equity, Debt)'!C36 -> WLD Tokens | D38: Equity | E38: ='CF (Equity, Debt)'!D36 -> 45075 | F38: ="Q"&ROUNDUP(MONTH(E38)/3,0)&" "&YEAR(E38) -> Q2 2023 | G38: ='CF (Equity, Debt)'!E36 -> -0.005875 | H38: ='CF (Equity, Debt)'!F36 -> 0
C39: ='CF (Equity, Debt)'!C37 -> WLD Tokens | D39: Equity | E39: ='CF (Equity, Debt)'!D37 -> 45114 | F39: ="Q"&ROUNDUP(MONTH(E39)/3,0)&" "&YEAR(E39) -> Q3 2023 | G39: ='CF (Equity, Debt)'!E37 -> -0.001 | H39: ='CF (Equity, Debt)'!F37 -> 0
C40: ='CF (Equity, Debt)'!C38 -> Applied AI Corporation Limited | D40: Equity | E40: ='CF (Equity, Debt)'!D38 -> 45121 | F40: ="Q"&ROUNDUP(MONTH(E40)/3,0)&" "&YEAR(E40) -> Q3 2023 | G40: ='CF (Equity, Debt)'!E38 -> -2.75 | H40: ='CF (Equity, Debt)'!F38 -> 0
C41: ='CF (Equity, Debt)'!C39 -> Instadeep Limited | D41: Equity | E41: ='CF (Equity, Debt)'!D39 -> 45138 | F41: ="Q"&ROUNDUP(MONTH(E41)/3,0)&" "&YEAR(E41) -> Q3 2023 | G41: ='CF (Equity, Debt)'!E39 -> 0 | H41: ='CF (Equity, Debt)'!F39 -> 7.8207761
B42: Debt
C43: ='CF (Equity, Debt)'!C42 -> Glass Earth Holdings LLC | D43: Debt | E43: ='CF (Equity, Debt)'!D42 -> 43635 | F43: ="Q"&ROUNDUP(MONTH(E43)/3,0)&" "&YEAR(E43) -> Q2 2019 | G43: ='CF (Equity, Debt)'!E42 -> -8 | H43: ='CF (Equity, Debt)'!F42 -> 0
C44: ='CF (Equity, Debt)'!C43 -> Mena Mobile Inc (Debt) | D44: Debt | E44: ='CF (Equity, Debt)'!D43 -> 44293 | F44: ="Q"&ROUNDUP(MONTH(E44)/3,0)&" "&YEAR(E44) -> Q2 2021 | G44: ='CF (Equity, Debt)'!E43 -> -2.353982 | H44: ='CF (Equity, Debt)'!F43 -> 0
C45: ='CF (Equity, Debt)'!C44 -> Esyasoft Holding (Debt) | D45: Debt | E45: ='CF (Equity, Debt)'!D44 -> 44384 | F45: ="Q"&ROUNDUP(MONTH(E45)/3,0)&" "&YEAR(E45) -> Q3 2021 | G45: ='CF (Equity, Debt)'!E44 -> -0.411765 | H45: ='CF (Equity, Debt)'!F44 -> 0
C46: ='CF (Equity, Debt)'!C45 -> Esyasoft Holding (Debt) | D46: Debt | E46: ='CF (Equity, Debt)'!D45 -> 44902 | F46: ="Q"&ROUNDUP(MONTH(E46)/3,0)&" "&YEAR(E46) -> Q4 2022 | G46: ='CF (Equity, Debt)'!E45 -> 0 | H46: ='CF (Equity, Debt)'!F45 -> 0.47078465
B47: Funds
C48: ='CF (Funds)'!B3 -> Sinovation Disrupt Fund, L.P. | D48: Fund | E48: ='CF (Funds)'!C3 -> 44153 | F48: ="Q"&ROUNDUP(MONTH(E48)/3,0)&" "&YEAR(E48) -> Q4 2020 | G48: ='CF (Funds)'!D3 -> -10.5 | H48: ='CF (Funds)'!E3 -> 0
C49: ='CF (Funds)'!B4 -> Sinovation Disrupt Fund, L.P. | D49: Fund | E49: ='CF (Funds)'!C4 -> 44238 | F49: ="Q"&ROUNDUP(MONTH(E49)/3,0)&" "&YEAR(E49) -> Q1 2021 | G49: ='CF (Funds)'!D4 -> 4.214027 | H49: ='CF (Funds)'!E4 -> 0
C50: ='CF (Funds)'!B5 -> Sinovation Disrupt Fund, L.P. | D50: Fund | E50: ='CF (Funds)'!C5 -> 44238 | F50: ="Q"&ROUNDUP(MONTH(E50)/3,0)&" "&YEAR(E50) -> Q1 2021 | G50: ='CF (Funds)'!D5 -> 0 | H50: ='CF (Funds)'!E5 -> 0.05044835
C51: ='CF (Funds)'!B6 -> Sinovation Disrupt Fund, L.P. | D51: Fund | E51: ='CF (Funds)'!C6 -> 44285 | F51: ="Q"&ROUNDUP(MONTH(E51)/3,0)&" "&YEAR(E51) -> Q1 2021 | G51: ='CF (Funds)'!D6 -> -6.433746 | H51: ='CF (Funds)'!E6 -> 0
C52: ='CF (Funds)'!B7 -> Sinovation Disrupt Fund, L.P. | D52: Fund | E52: ='CF (Funds)'!C7 -> 44269 | F52: ="Q"&ROUNDUP(MONTH(E52)/3,0)&" "&YEAR(E52) -> Q1 2021 | G52: ='CF (Funds)'!D7 -> 1.1352074 | H52: ='CF (Funds)'!E7 -> 0
C53: ='CF (Funds)'!B8 -> Sinovation Disrupt Fund, L.P. | D53: Fund | E53: ='CF (Funds)'!C8 -> 44269 | F53: ="Q"&ROUNDUP(MONTH(E53)/3,0)&" "&YEAR(E53) -> Q1 2021 | G53: ='CF (Funds)'!D8 -> 0 | H53: ='CF (Funds)'!E8 -> 0.0259
C54: ='CF (Funds)'!B9 -> Sinovation Disrupt Fund, L.P. | D54: Fund | E54: ='CF (Funds)'!C9 -> 44483 | F54: ="Q"&ROUNDUP(MONTH(E54)/3,0)&" "&YEAR(E54) -> Q4 2021 | G54: ='CF (Funds)'!D9 -> -7.567138 | H54: ='CF (Funds)'!E9 -> 0
C55: ='CF (Funds)'!B10 -> Sinovation Disrupt Fund, L.P. | D55: Fund | E55: ='CF (Funds)'!C10 -> 44554 | F55: ="Q"&ROUNDUP(MONTH(E55)/3,0)&" "&YEAR(E55) -> Q4 2021 | G55: ='CF (Funds)'!D10 -> -7.385016 | H55: ='CF (Funds)'!E10 -> 0
C56: ='CF (Funds)'!B11 -> Sinovation Disrupt Fund, L.P. | D56: Fund | E56: ='CF (Funds)'!C11 -> 44554 | F56: ="Q"&ROUNDUP(MONTH(E56)/3,0)&" "&YEAR(E56) -> Q4 2021 | G56: ='CF (Funds)'!D11 -> 4.0733456 | H56: ='CF (Funds)'!E11 -> 0
C57: ='CF (Funds)'!B12 -> Sinovation Disrupt Fund, L.P. | D57: Fund | E57: ='CF (Funds)'!C12 -> 44554 | F57: ="Q"&ROUNDUP(MONTH(E57)/3,0)&" "&YEAR(E57) -> Q4 2021 | G57: ='CF (Funds)'!D12 -> 0 | H57: ='CF (Funds)'!E12 -> 0.139694
C58: ='CF (Funds)'!B13 -> Sinovation Disrupt Fund, L.P. | D58: Fund | E58: ='CF (Funds)'!C13 -> 44703 | F58: ="Q"&ROUNDUP(MONTH(E58)/3,0)&" "&YEAR(E58) -> Q2 2022 | G58: ='CF (Funds)'!D13 -> 5.673074 | H58: ='CF (Funds)'!E13 -> 0
C59: ='CF (Funds)'!B14 -> Sinovation Disrupt Fund, L.P. | D59: Fund | E59: ='CF (Funds)'!C14 -> 44703 | F59: ="Q"&ROUNDUP(MONTH(E59)/3,0)&" "&YEAR(E59) -> Q2 2022 | G59: ='CF (Funds)'!D14 -> 0 | H59: ='CF (Funds)'!E14 -> 0.227786
... C89: ='CF (Funds)'!B44 -> Acies Investments Fund I, L.P. | D89: Fund | E89: ='CF (Funds)'!C44 -> 44875 | F89: ="Q"&ROUNDUP(MONTH(E89)/3,0)&" "&YEAR(E89) -> Q4 2022 | G89: ='CF (Funds)'!D44 -> -3.388275 | H89: ='CF (Funds)'!E44 -> 0

Sheet 6. %
C2: % OWNERSHIP
C3: As of date | D3: ='S | 01 '!D2 -> 45138
C6: Deals | D6: Shares | E6: Total | F6: % | G6: Source for % holding | H6: Incorporation/Jurisdiction | I6: Country
C8: Direct Investments
C9: ='S | 01 '!C10 -> Jollychic Holding Limited | D9: 13458655 | E9: 236116762 | F9: =D9/E9 -> 0.056999998 | G9: Dan Kong | H9: Cayman Islands | I9: Cayman Islands
C10: ='S | 01 '!C11 -> Mena Mobile Inc | D10: 21419829 | E10: 152998776 | F10: =D10/E10 -> 0.14 | G10: Dan Kong | H10: Cayman Islands | I10: Cayman Islands
C11: ='S | 01 '!C12 -> Flyr Inc | D11: 5205482 | E11: 61222609 | F11: =D11/E11 -> 0.085025485 | G11: Cap Table as of Jun'22 | H11: Delaware Corporation | I11: USA
C12: ='S | 01 '!C13 -> Esyasoft Holding | D12: n/a | E12: n/a | F12: n/a | G12: n/a; exited | H12: DIFC | I12: Dubai, UAE
C13: ='S | 01 '!C14 -> Beyond Limits | D13: 17670202 | E13: 180372405 | F13: =D13/E13 -> 0.097965107 | G13: Cap Table | H13: Delaware Corporation | I13: USA
C14: ='S | 01 '!C15 -> ONT plc | D14: 44328120 | E14: 827265174 | F14: =D14/E14 -> 0.053583931 | G14: LSE Announcement | H14: UK | I14: UK
C15: ='S | 01 '!C16 -> Heygears | D15: 3565017.2 | E15: =D15/F15 -> 24791497 | F15: 0.1438 | G15: Dan Kong | H15: PRC | I15: China
C16: ='S | 01 '!C17 -> Jysan Technologies | D16: 7959497 | E16: 2.6531657e+08 | F16: 0.03 | G16: Txn docs | H16: UK | I16: UK
C17: ='S | 01 '!C18 -> Cerebras Systems Inc | D17: 1441711 | E17: 152130778 | F17: =D17/E17 -> 0.0094767871 | G17: Cap table as of Dec'22 | H17: Delaware Corporation | I17: USA
C18: ='S | 01 '!C19 -> Endless Studios LLC | D18: 3000000 | E18: 38750000 | F18: =D18/E18 -> 0.077419355 | G18: Cap table as of Dec'22 | H18: Delaware Corporation | I18: USA
C19: ='S | 01 '!C20 -> Instadeep Limited | D19: 33267 | E19: 2895450 | F19: =D19/E19 -> 0.011489406 | G19: Txn docs; exit underway | H19: UK | I19: UK
C20: ='S | 01 '!C21 -> X-fusion | F20: =10% * 51% -> 0.051 | G20: Dan Kong | H20: PRC | I20: China
C21: ='S | 01 '!C22 -> DriveNets | D21: 86882669 | E21: 779782293 | F21: =D21/E21 -> 0.11141914 | G21: Cap table as of Mar'23 | H21: Israeli Pvt Company | I21: Israel
C22: ='S | 01 '!C23 -> vTv Therapeutics Inc. | D22: 10386274 | E22: =81483600+23093860 -> 104577460 | F22: =D22/E22 -> 0.099316564 | G22: 10Q report Aug'22 | H22: Delaware Corporation | I22: USA
C23: ='S | 01 '!C24 -> Honor Device Co Ltd | D23: =1517126944.34*0.8/2 -> 6.0685078e+08 | E23: 3.2238948e+10 | F23: =4.705882%* 0.8/2 -> 0.018823528 | G23: Dan Kong | H23: PRC | I23: China
C24: ='S | 01 '!C25 -> Applied AI Corporation Limited | D24: n/a | E24: n/a | F24: n/a | G24: n/a; convertible note | H24: ADGM | I24: Abu Dhabi, UAE
C25: ='S | 01 '!C26 -> eSpace | D25: n/a | E25: n/a | F25: n/a | G25: n/a; safe note | H25: Delaware Corporation | I25: USA
C26: ='S | 01 '!C27 -> Tools for Humanity Corporation | D26: 65413 | E26: 10445693 | F26: =D26/E26 -> 0.0062621983 | G26: Email: Sam Thomson | H26: Delaware Corporation | I26: USA
C27: WLD Tokens | D27: 62500000 | E27: 10000000000 | F27: =D27/E27 -> 0.00625 | G27: Email: Sam Thomson | H27: DAO | Cayman Islands | I27: Cayman Islands
C30: Funds Investments | D30: G42 Commitment | E30: Fund Size
C31: New Space Capital Fund I | D31: 23234462 | E31: 105,400,00 | F31: =NAV!L52 -> 0.22044082 | G31: Estimated as per Q1-23 NAV report | H31: Luxembourg | I31: Luxembourg
C32: New Space Capital GP Com SCSp | D32: =-'CF (Funds)'!G39*10^6 -> 2125000 | E32: 105,400,00 | F32: =NAV!L53 -> 0.02016129 | H32: Luxembourg | I32: Luxembourg
C33: North Summit Capital Fund | D33: 300000000 | E33: 301507538 | F33: =D33/E33 -> 0.995 | G33: Q4'22 Report | H33: Cayman Islands | I33: Cayman Islands
C34: Sinovation Disrupt Fund, L.P. | D34: 50000000 | E34: 496717172 | F34: =D34/E34 -> 0.1006609 | G34: Q3'22 Report | H34: Cayman Islands | I34: Cayman Islands
C35: Acies Investments Fund I, L.P. | D35: 17112500 | E35: 51337500 | F35: =D35/E35 -> 0.33333333 | G35: Q1 23 Report | H35: Delaware LLC | I35: USA

Sheet 7. Board
C3: Deals | D3: Board Representation ‡ | E3: Representative | F3: Notes | G3: Status | H3: Comments
C5: Direct Investments
C6: Mena Mobile Inc | D6: 1 Board | E6: Peng Xiao
C7: Flyr Inc | D7: 1 Board | E7: Marty
C8: Esyasoft Holding | D8: NR | E8: n/a | F8: 2 | G8: Exited | H8: Monty Aw represented earlier
C9: Jollychic Holding Limited | D9: 1 Board | E9: Divyesh Mahajan | F9: 1
C10: Beyond Limits | D10: 1 Board | E10: Marty | F10: 3
C11: ONT plc | D11: 1 Board | E11: Guy Harmelin (Independent Director)
C12: Heygears | D12: 2 Board | E12: Peng Xiao, Elaine
C13: Jysan Technologies | D13: 1 Board | E13: None appointed
C14: Cerebras Systems Inc | D14: 1 Observer | E14: Eric Xing | F14: 4
C15: Endless Studios LLC | D15: 1 Board + 1 Observer | E15: Talal (Observer)
C16: Instadeep Limited | D16: 1 Observer | E16: Viktor
C17: X-fusion | D17: NR | E17: n/a
C18: DriveNets | D18: 1 Observer | E18: Guy Harmelin
C19: vTv Therapeutics Inc. | D19: 1 Board, 1 Observer | E19: Dr. Fahad (Board), Jon Nieman (Observer)
C20: Honor Device Co Ltd | D20: NR | E20: n/a | F20: 5
C21: Applied AI Corporation Limited | D21: NR | E21: n/a
C22: eSpace | D22: NR | E22: n/a
C23: Tools for Humanity Corporation | D23: NR | E23: n/a
C27: Debt Investments
C28: Glass Earth Holdings LLC | D28: NR
C29: Mena Mobile Inc | D29: 1 Board | E29: Peng Xiao
C30: Esyasoft Holding | D30: NR
C33: Funds Investments
C34: New Space Capital Fund I | D34: NR
C35: New Space Capital GP Com SCSp | E35: Talal
C36: North Summit Capital Fund | D36: NR
C37: Sinovation Disrupt Fund, L.P. | D37: NR
C38: Acies Investments Fund I, L.P. | D38: Not yet appointed | E38: Advisory Board | H38: Confirm appoinment
C42: NOTES:
C43: NR = No Rights / No Representation
C44: n/a = not applicable or not available
C45: ‡ Board Representation : as a Board Seat, Observer, or Advisor
B46: 1 | C46: Jollychic Holding : Peng Xiao held the directorship until Jun 2021
B47: 2 | C47: Esyasoft: we held a Board seat, with Monty Aw as the representative, until Jun 2022
B48: 3 | C48: Beyond Limits: possibility of the 2nd Board seat in case we invest (an additional / an earlier committed) $10m
B49: 4 | C49: Cerebras : possibility of a Board seat, If G42 holds >10% with rights to exercise at least 20% of warrant
B50: 5 | C50: Honor: Our board seat only kicks in once Honor is converted into a joint stock company in March 2023; there is no one appointed as yet

Sheet 8. Log
B2: Date Log | D2: Update
B3: October 22
D4: 1) $4.75m Signing Payment for AAICO
D5: 2) $3.4m 4th capital call Acies
D6: 3) Honor booked at $1.2B cost
D7: 4) NAV of Heygears updated to $114.2m as of Oct 22
B9: November 22
D10: 1) Updated the Board directorships info for VTVT and Honor
D11: 2) 10-Nov-2022 USD 3,388,275 Acies Investments capital call
D12: 3) 27-Nov-2022 USD 15,000,000 eSpace SAFE
D13: 4) Moved Jysan under Mozn
D14: 5) Revised carrying value of New Space Capital
B16: December 22
D17: 1) Esyasoft Loan Exit (received $471K on 07-Dec)
D18: 2) Sell down of $250m position in Honor (received 21-Dec)
D19: 3) New Space Capital restructuring ongoing
D20: 4) Instadeep exit in progress
B22: January 23
D23: 1) Received EUR 12.5m from NewSpace Capital on 30-Jan (actualization interest); revised remaining commitment
D24: 2) Sinovation issued 6th Capital Call; funded 03-Feb
D25: 3) Instadeep transaction 'completion' in progress
B27: February 23
D28: Sinovation 6th capital call $2.6m transferred on 3-Feb
D29: vTv Therapeutics 2nd payment of $12.03m transferred on 28-Feb
B31: March 23
D32: Jusan dividend delayed
B34: April 23
D35: Re-structured investment in New Space Capital GP restructured – converted to GP commitment vehicle
D36: NAVs marked up for: Instadeep, Heygears and North Summit Capital. Mena Mobile equity value written off
B38: May 23
D39: Invested $15m in Tools for Humanity Corp equity and Worldcoin token warrants
B41: Jun 23
D42: A distribution of $1.9m as a ‘return of capital’ received from the Sinovation Fund
B44: Jul 23
D45: 7 July 2023: Paid USD 1,000 towards Worldcoin token warrant exercise fee
D46: 14 July 2023: Paid USD 2,750,000 to AAICO towards the first milestone payment
D47: 31 July 2023: Received GBP 6,090,345.22 (USD 7,820,776.10) for sell down of Instadeep

Sheet 1
E2: New Space Capital LP (conversion / restructuring summary)
E7: Figures in USD, Mn
E8: Deals | F8: New Space Capital Fund I | G8: NewSpace Capital GP Com SCSp
E9: Status | F9: Unrealized | G9: Unrealized
E10: Investing Entity | F10: G42 | G10: G42
E11: Vintageἀ | F11: 2020 | G11: 2020
E12: Instrument | F12: LP | G12: LP
E13: % | F13: n/a | G13: n/a
E14: Committed | F14: 27.691913 | G14: 2.7058824
E15: Invested | F15: 11.058035 | G15: 2.7058824
E16: Remaining Commitment | F16: 16.633878 | G16: 0
E17: Distributions | F17: 2.9557744 | G17: 0
E18: Carrying Value | F18: =NAV!E39 -> 13.390399 | G18: =G15*F18/F15 -> 3.276608
E19: Gain | F19: =F18+F17-F15 -> 5.2881388 | G19: =G18+G17-G15 -> 0.57072563
E20: Multiple | F20: =(F17+F18)/F15 -> 1.4782169 | G20: =(G17+G18)/G15 -> 1.2109203
E22: Note
E23: 1. In Q1'23 we converted GP interest equivalent to the LP via the GP commitment vehicle
E24: 2. In addition, G42 also has XX units in the GP, which presently are being carried at nil value
E33: 1799122
E34: 0.03598244
E35: =E33/E34 -> 50000000

Sheet 2
B2: CASHFLOW REQUIREMENT
B3: Date of NAV | C3: =D!D2 -> 45138
B6: Deals | D6: Remaining Commitment | E6: Q3-2022 | F6: Q4-2022 | G6: Q1-2023 | H6: Q2-2023 | I6: Q3-2023 | J6: Q4-2023
B9: AAICO
B10: New Space Capital Fund I | C10: Fund | D10: 3.9459573 | G10: =D10-F10 -> 3.9459573
B11: North Summit Capital Fund | C11: Fund | D11: 217.81331
B12: Sinovation Disrupt Fund, L.P. | C12: Fund | D12: 33.209754
B13: Acies Investments Fund I, L.P. | C13: Fund | D13: 6.4856375
D14: =SUM(D10:D13) -> 261.45466 | F14: =SUM(F10:F13) -> 0 | G14: =SUM(G10:G13) -> 3.9459573 | H14: =SUM(H10:H13) -> 0 | I14: =SUM(I10:I13) -> 0 | J14: =SUM(J10:J13) -> 0
B17: Notes
B18: No funding projected for North Summit Fund

Sheet 3
C2: ATTRIBUTION SUMMARY
D3: As of date | E3: =D!D2 -> 45138
D7: Deals | E7: Type | F7: Gain | G7: Gain till Dec 2021 | K7: MOZN Portfolio : Gains till Dec 2021 | N7: G42 Portfolio : Gains till Dec 2021
D8: X-fusion | E8: Equity | F8: =VLOOKUP(D8,'S | 01 '!$C$6:$R$46,13,0) -> -85.212962 | G8: 0 | K8: Jollychic Holding Limited | L8: =VLOOKUP(K8,$D$7:$G$33,4,0) -> -65 | N8: Honor Device Co Ltd | O8: =VLOOKUP(N8,$D$7:$G$33,4,0) -> 0
D9: Jollychic Holding Limited | E9: Equity | F9: =VLOOKUP(D9,'S | 01 '!$C$6:$R$46,13,0) -> -65 | G9: -65 | K9: Heygears | L9: =VLOOKUP(K9,$D$7:$G$33,4,0) -> -39.7 | N9: DriveNets | O9: =VLOOKUP(N9,$D$7:$G$33,4,0) -> 0
D10: vTv Therapeutics Inc. | E10: Equity | F10: =VLOOKUP(D10,'S | 01 '!$C$6:$R$46,13,0) -> -17.468584 | G10: 0 | K10: Glass Earth Holdings LLC | L10: =VLOOKUP(K10,$D$7:$G$33,4,0) -> -8 | N10: vTv Therapeutics Inc. | O10: =VLOOKUP(N10,$D$7:$G$33,4,0) -> 0
D11: Glass Earth Holdings LLC | E11: Debt | F11: =VLOOKUP(D11,'S | 01 '!$C$6:$R$46,13,0) -> -8 | G11: -8 | K11: Mena Mobile Inc | L11: =VLOOKUP(K11,$D$7:$G$33,4,0) -> -6.3 | N11: New Space Capital GP Com SCSp | O11: =VLOOKUP(N11,$D$7:$G$33,4,0) -> 0
D12: Mena Mobile Inc | E12: Equity | F12: =VLOOKUP(D12,'S | 01 '!$C$6:$R$46,13,0) -> -8 | G12: -6.3 | K12: Beyond Limits | L12: =VLOOKUP(K12,$D$7:$G$33,4,0) -> 0 | N12: Acies Investments Fund I, L.P. | O12: =VLOOKUP(N12,$D$7:$G$33,4,0) -> 0
D13: Sinovation Disrupt Fund, L.P. | E13: Fund | F13: =VLOOKUP(D13,'S | 01 '!$C$6:$R$46,13,0) -> -1.0563667 | G13: 3.5 | K13: Endless Studios LLC | L13: =VLOOKUP(K13,$D$7:$G$33,4,0) -> 0 | N13: New Space Capital Fund I | O13: =VLOOKUP(N13,$D$7:$G$33,4,0) -> 1
D14: Acies Investments Fund I, L.P. | E14: Fund | F14: =VLOOKUP(D14,'S | 01 '!$C$6:$R$46,13,0) -> -0.7075125 | G14: 0 | K14: X-fusion | L14: =VLOOKUP(K14,$D$7:$G$33,4,0) -> 0 | N14: Sinovation Disrupt Fund, L.P. | O14: =VLOOKUP(N14,$D$7:$G$33,4,0) -> 3.5
D15: North Summit Capital Fund | E15: Fund | F15: =VLOOKUP(D15,'S | 01 '!$C$6:$R$46,13,0) -> -0.490906 | G15: 6.6 | K15: Applied AI Corporation Limited | L15: =VLOOKUP(K15,$D$7:$G$33,4,0) -> 0 | N15: North Summit Capital Fund | O15: =VLOOKUP(N15,$D$7:$G$33,4,0) -> 6.6
D16: Mena Mobile Inc (Debt) | E16: Debt | F16: =VLOOKUP(D16,'S | 01 '!$C$6:$R$46,13,0) -> 0 | G16: 0 | K16: eSpace | L16: =VLOOKUP(K16,$D$7:$G$33,4,0) -> 0
D17: Jysan Technologies | E17: Equity | F17: =VLOOKUP(D17,'S | 01 '!$C$6:$R$46,13,0) -> 0 | G17: 0 | K17: Cerebras Systems Inc | L17: =VLOOKUP(K17,$D$7:$G$33,4,0) -> 0
D18: Applied AI Corporation Limited | E18: Equity | F18: =VLOOKUP(D18,'S | 01 '!$C$6:$R$46,13,0) -> 0 | G18: 0 | K18: Instadeep Limited | L18: =VLOOKUP(K18,$D$7:$G$33,4,0) -> 0
D19: eSpace | E19: Equity | F19: =VLOOKUP(D19,'S | 01 '!$C$6:$R$46,13,0) -> 0 | G19: 0 | K19: Jysan Technologies | L19: =VLOOKUP(K19,$D$7:$G$33,4,0) -> 0
D20: Cerebras Systems Inc | E20: Equity | F20: =VLOOKUP(D20,'S | 01 '!$C$6:$R$46,13,0) -> 0 | G20: 0 | K20: Esyasoft Holding (Debt) | L20: =VLOOKUP(K20,$D$7:$G$33,4,0) -> 0
D21: Endless Studios LLC | E21: Equity | F21: =VLOOKUP(D21,'S | 01 '!$C$6:$R$46,13,0) -> 0 | G21: 0 | K21: Mena Mobile Inc (Debt) | L21: =VLOOKUP(K21,$D$7:$G$33,4,0) -> 0
D22: DriveNets | E22: Equity | F22: =VLOOKUP(D22,'S | 01 '!$C$6:$R$46,13,0) -> 0 | G22: 0 | K22: Esyasoft Holding | L22: =VLOOKUP(K22,$D$7:$G$33,4,0) -> 2.5
D23: Tools for Humanity Corporation | E23: Equity | F23: =VLOOKUP(D23,'S | 01 '!$C$6:$R$46,13,0) -> 0 | G23: 69.1 | K23: Flyr Inc | L23: =VLOOKUP(K23,$D$7:$G$33,4,0) -> 68.1
D24: Esyasoft Holding (Debt) | E24: Debt | F24: =VLOOKUP(D24,'S | 01 '!$C$6:$R$46,13,0) -> 0.05901965 | G24: 0 | K24: Tools for Humanity Corporation | L24: =VLOOKUP(K24,$D$7:$G$33,4,0) -> 69.1
D25: New Space Capital GP Com SCSp | E25: Fund | F25: =VLOOKUP(D25,'S | 01 '!$C$6:$R$46,13,0) -> 0.57072563 | G25: 0 | K25: ONT plc | L25: =VLOOKUP(K25,$D$7:$G$33,4,0) -> 275.8
D26: Beyond Limits | E26: Equity | F26: =VLOOKUP(D26,'S | 01 '!$C$6:$R$46,13,0) -> 1.0015403 | G26: 0
D27: Instadeep Limited | E27: Equity | F27: =VLOOKUP(D27,'S | 01 '!$C$6:$R$46,13,0) -> 2.7970559 | G27: 0
D28: ONT plc | E28: Equity | F28: =VLOOKUP(D28,'S | 01 '!$C$6:$R$46,13,0) -> 8.9301789 | G28: 275.8
D29: Esyasoft Holding | E29: Equity | F29: =VLOOKUP(D29,'S | 01 '!$C$6:$R$46,13,0) -> 2.5 | G29: 2.5
D30: New Space Capital Fund I | E30: Fund | F30: =VLOOKUP(D30,'S | 01 '!$C$6:$R$46,13,0) -> 5.2881388 | G30: 1
D31: Honor Device Co Ltd | E31: Equity | F31: =VLOOKUP(D31,'S | 01 '!$C$6:$R$46,13,0) -> 17.18905 | G31: 0 | K31: Gain | L31: =SUM(L8:L25) -> 296.5 | N31: Total | O31: =SUM(O8:O16) -> 11.1
D32: Flyr Inc | E32: Equity | F32: =VLOOKUP(D32,'S | 01 '!$C$6:$R$46,13,0) -> 68.08223 | G32: 68.1 | K32: Gain till Nov 2022 | L32: ='S | 02'!O29 -> 23.219623
D33: Heygears | E33: Equity | F33: =VLOOKUP(D33,'S | 01 '!$C$6:$R$46,13,0) -> 91.069434 | G33: -39.7 | K33: Delta Gain | L33: =L32-L31 -> -273.28038

Sheet X1
C3: ONT | G3: Heygears | K3: FLYR | O3: Instadeep | S3: vTv Therapeutics
W4: Select Cashflow for
G5: NAV Date
C6: NAV Date | D6: 44773 | O6: Post all transactions | S6: # shares | T6: 10386274 | W6: Vintage
C7: Share Price (GBP) | D7: 3.18 | G7: 44166 | H7: -60000000 | O7: B = 599,769 | P7: 599769 | S7: Price per share | T7: 1.18 | W7: Sector
C8: GBPUSD | D8: 1.22 | G8: 44773 | H8: 20000000 | K8: G42 Shares | L8: 5205482 | O8: Ordinary =1,493,575 | P8: 1493575 | S8: Value | T8: =T6*T7*10^-6 -> 12.255803 | W8: Geogrpahy
K9: Fully Diluted | L9: 61222609 | O9: Employee shares = 83,261 | P9: 83261 | W9: Asset Class Type
C10: G42 Shares | D10: 44328120 | G10: IRR | H10: =XIRR(H7:H8,G7:G8) -> -0.48346658 | K10: % ownership | L10: 0.0855 | O10: Class A = 289,048 | P10: 289048
C11: Fully Diluted | D11: 823636945 | G11: Multiple | H11: =-H8/SUM(H7) -> 0.33333333 | L11: =L8/L9 -> 0.085025485 | O11: LTIP shares | P11: 429797
C12: % ownership | D12: 0.0538 | O12: Total | P12: =SUM(P7:P11) -> 2895450 | S12: EsyaSoft, Equity
G13: Mena Mobile | K13: Share price | L13: 18.75
K14: Discount | L14: 0.2 | O14: # shares to G42 | P14: 33267 | S14: NAV Date
C15: USDAED | D15: 3.675 | G15: NAV Date | K15: Carrying Value Mn | L15: =L8*L13*(1-L14)*10^-6 -> 78.08223 | O15: % ownership | P15: =P14/P12 -> 0.011489406
C16: Date of Investment | O16: Price per share | Oct 21 | P16: 110.63 | S16: 44075 | T16: -2500000
C17: 43968 | D17: -50 | G17: 43563 | H17: -8000000 | K17: NAV Date | L17: 44773 | O17: NAV Date | P17: 44773 | S17: 44773 | T17: 5000000
C18: 44006 | D18: -27.268351 | G18: 44773 | H18: 1700000 | K18: 43570 | L18: -4999998.1
C19: 43837 | D19: -18.109441 | K19: 43915 | L19: -5000001.9 | O19: BNT Offer | 18Jul 2022 | S19: IRR | T19: =XIRR(T16:T17,S16:S17) -> 0.43686312
C20: 43990 | D20: -34.851687 | G20: IRR | H20: =XIRR(H17:H18,G17:G18) -> -0.37324778 | K20: =L17 -> 44773 | L20: =+L15*10^6 -> 78082230 | O20: Offer Mn, GBP | P20: 510 | S20: Multiple | T20: =-T17/SUM(T16) -> 2
C21: 44315 | D21: -11.24078 | G21: Multiple | H21: =-H18/SUM(H17) -> 0.2125 | O21: # shares o/s | P21: =P12 -> 2895450
C22: 44742 | D22: =NAV!E14 -> 150.40044 | K22: IRR | L22: =XIRR(L18:L20,K18:K20) -> 1.0308312 | O22: Offer price per share | P22: =P20*10^6/P21 -> 176.13842 | S22: EsyaSoft, Debt
K23: Multiple | L23: =L20/-SUM(L18:L19) -> 7.808223 | O23: Premium | P23: =P22/P16 -> 1.5921398
C24: IRR | D24: =XIRR(D17:D22,C17:C22) -> 0.030200139 | O24: GBPUSD | P24: 1.22 | S24: NAV Date
C25: Multiple | D25: =-D22/SUM(D17:D21) -> 1.0631241
S26: 44377 | T26: -411765
O27: 44550 | P27: =-18477242.89/3.68 -> -5020989.9 | S27: 44773 | T27: =(-((S27-S26)/365*T26*10%))-T26 -> 456438.68
O28: =P17 -> 44773 | P28: =P14*P22*P24 -> 7148708.3
S29: IRR | T29: =XIRR(T26:T27,S26:S27) -> 0.099591023
O30: IRR | P30: =XIRR(P27:P28,O27:O28) -> 0.78296691 | S30: Multiple | T30: =-T27/SUM(T26) -> 1.1084932
O31: Multiple | P31: =P28/-SUM(P27) -> 1.4237647

Sheet X2
D4: Investment type | E4: Monthly (25th of each month other than quarter-end) | F4: Quarterly (1st April, July and October) | G4: Annually (2nd January following year-end) | H4: Ref. to summary
D5: Listed securities on a recognised exchange | E5: 1. Number of securities held, including: | F5: 1. Number of securities held, including: | G5: 1. Number of securities held, including: | H5: 1a
E6: details of any movement in number of securities held | F6: details of any movement in number of securities held | G6: details of any movement in number of securities held | H6: 1b, 1c, 1d
E7: exercise of conversion rights | F7: exercise of conversion rights | G7: exercise of conversion rights | H7: 1c
E8: changes to the terms of the instrument | F8: changes to the terms of the instrument | G8: changes to the terms of the instrument | H8: 4
E9: amalgamation/ splitting of instrument classes | F9: amalgamation/ splitting of instrument classes | G9: amalgamation/ splitting of instrument classes | H9: 1c
E10: bonus shares | F10: bonus shares | G10: bonus shares | H10: 1c
E11: additional instruments subscribed | F11: additional instruments subscribed | G11: additional instruments subscribed | H11: 1b
E12: dividend, etc. | F12: dividend, etc. | G12: dividend, etc. | H12: 3
E13: 2. Fair value of the listed portfolio based on quoted stock exchange (MTM) price | F13: 2. Fair value of the listed portfolio based on quoted stock exchange (MTM) price | G13: 2. Fair value of the listed portfolio based on quoted stock exchange (MTM) price | H13: 2
D15: Unlisted corporate investments held | E15: 1. Number of securities held, including: | F15: 1. Number of securities held, including: | G15: 1. Number of securities held, including: | H15: 1a
E16: details of any movement in number of securities held | F16: details of any movement in number of securities held | G16: details of any movement in number of securities held | H16: 1b, 1c, 1d
E17: exercise of conversion rights | F17: exercise of conversion rights | G17: exercise of conversion rights | H17: 1c
E18: changes to the terms of the instrument | F18: changes to the terms of the instrument | G18: changes to the terms of the instrument | H18: 4
E19: amalgamation/ splitting of instrument classes | F19: amalgamation/ splitting of instrument classes | G19: amalgamation/ splitting of instrument classes | H19: 1c
E20: bonus shares | F20: bonus shares | G20: bonus shares | H20: 1c
E21: additional instruments subscribed | F21: additional instruments subscribed | G21: additional instruments subscribed | H21: 1b
E22: dividend, etc. | F22: dividend, etc. | G22: dividend, etc. | H22: 3
E23: 2. Any events or conditions that indicate significant decrease in the fair value previously recorded for individual investments | F23: 2. Any events or conditions that indicate significant increase/ decrease in the fair value previously recorded for individual investments | G23: 2. Any events or conditions that indicate significant increase/ decrease in the fair value previously recorded for individual investments | H23: 4
F24: 3. Refresh the valuation at which each investment in the portfolio is previously carried | G24: 3. Refresh the valuation at which each investment in the portfolio is previously carried | H24: 3
G25: 4. Obtain an external valuer’s report of fair value of each investment in the portfolio as at 30th September (by 30th November)
G26: 5. Carry out an internal refresh as at 31st December of the external valuer’s report of fair value (by 5th January following the year-end)
D28: Investments in Funds (closed ended) | E28: 1. Any events or conditions that indicate significant increase/ decrease in the fair value previously recorded for individual investments | F28: 1. Any events or conditions that indicate significant increase/ decrease in the fair value previously recorded for individual investments | G28: 1. Any events or conditions that indicate significant increase/ decrease in the fair value previously recorded for individual investments | H28: 2
F29: 2. Fair value of investment in each Fund based on Fund Manager’s/ General Partner’s report for the previous quarter | G29: 2. Fair value of investment in each Fund based on Fund Manager’s/ General Partner’s report for the previous quarter (by 5th January following the year-end) | H29: 1

Sheet X3
C2: Date of NAV | D2: 44865
H3: D A S H B O A R D | L3: figures in USD Millions
D6: # Investments | E6: Committed | F6: Invested | G6: Remaining | H6: Distributions | I6: Residual Value | J6: IRR | K6: TVPI | L6: RPI | M6: DPI | Q6: A T T R I B U T I O N S U M M A R Y
C8: EQUITY | D8: =COUNTIF('S | 01 '!C10:C24,"*") -> 15 | E8: ='1. IRR Equity'!AE33 -> 2108.0362 | F8: ='1. IRR Equity'!AF33 -> 2100.533 | G8: ='1. IRR Equity'!AG33 -> 7.5031614 | H8: ='1. IRR Equity'!AH33 -> 12.820776 | I8: ='1. IRR Equity'!AI33 -> 2118.5933 | J8: ='1. IRR Equity'!AJ33 -> 0.0092234105 | K8: ='1. IRR Equity'!AK33 -> 1.0147015 | L8: ='1. IRR Equity'!AL33 -> 1.008598 | M8: ='1. IRR Equity'!AM33 -> 0.0061035822 | Q8: TOP GAINERS
Q9: Heygears | R9: Equity | S9: 76.64
Q10: Flyr Inc | R10: Equity | S10: 68.08223
