Workbook
Name Company: [1]UEL!$B$18:$B$20
Name Dates: [1]ONT!$N$2:$AN$2
Name DetailedCapShares: '[2]Current Cap'!$T$133
Name FAGroup: [1]UEL!$B$3:$B$15
Name IQ_CH: 110000
Name IQ_CQ: 5000
Name IQ_CY: 10000
Name IQ_DAILY: 500000
Name IQ_FH: 100000
Name IQ_FQ: 500
Name IQ_FY: 1000
Name IQ_LTM: 2000
Name IQ_MONTH: 15000
Name IQ_NTM: 6000
Name IQ_WEEK: 50000
Name IQ_YTD: 3000

Sheet D
C2: Date of NAV | D2: 45473 | E2: =TEXT(D2,"dddddd") -> Sunday
H4: D A S H B O A R D
B5: USD Millions
D7: # Investments | E7: Committed | F7: Invested | G7: Remaining | H7: Distributions | I7: Residual Value | J7: Gain | K7: TVPI | L7: DPI
C9: EQUITY* | D9: =COUNTIF('S | 01 '!C9:C33,"*") -> 23 | E9: ='S | 01 '!J33 -> 2151.783 | F9: ='S | 01 '!K33 -> 2148.033 | G9: ='S | 01 '!L33 -> 3.75 | H9: ='S | 01 '!M33 -> 1243.2422 | I9: ='S | 01 '!N33 -> 757.71883 | J9: =H9+I9-F9 -> -147.07202 | K9: =(H9+I9)/F9 -> 0.93153177 | L9: =H9/F9 -> 0.57878169
C12: DEBT | D12: =COUNTIF('S | 01 '!C36:C38,"*") -> 3 | E12: ='S | 01 '!J39 -> 10.765747 | F12: ='S | 01 '!K39 -> 10.765747 | G12: ='S | 01 '!L39 -> 0 | H12: ='S | 01 '!M39 -> 0.47078465 | I12: ='S | 01 '!N39 -> 0 | J12: =H12+I12-F12 -> -10.294962 | K12: =(H12+I12)/F12 -> 0.043729864 | L12: =H12/F12 -> 0.043729864
C15: FUNDS | D15: =COUNTIF('S | 01 '!C42:C46,"*") -> 5 | E15: ='S | 01 '!J47 -> 178.33516 | F15: ='S | 01 '!K47 -> 140.8735 | G15: ='S | 01 '!L47 -> 15.352483 | H15: ='S | 01 '!M47 -> 36.638861 | I15: ='S | 01 '!N47 -> 108.15165 | J15: =H15+I15-F15 -> 3.9170112 | K15: =(H15+I15)/F15 -> 1.0278052 | L15: =H15/F15 -> 0.26008341
C18: TOTAL | D18: =D9+D12+D15 -> 31 | E18: =E9+E12+E15 -> 2340.884 | F18: =F9+F12+F15 -> 2299.6723 | G18: =G9+G12+G15 -> 19.102483 | H18: =H9+H12+H15 -> 1280.3518 | I18: =I9+I12+I15 -> 865.87048 | J18: =H18+I18-F18 -> -153.44997 | K18: =(H18+I18)/F18 -> 0.93327311 | L18: =H18/F18 -> 0.55675404
C20: * Includes Convertibles | E20: =E18='S | 01 '!J49 -> TRUE | F20: =F18='S | 01 '!K49 -> TRUE | G20: =ROUND(G18,1)=ROUND('S | 01 '!L49,1) -> TRUE | H20: =ROUND(H18,1)=ROUND('S | 01 '!M49,1) -> TRUE | I20: =ROUND(I18,1)=ROUND('S | 01 '!N49,1) -> TRUE

Sheet S | 01 
C2: As of date | D2: =D!D2 -> 45473 | E2: 1
C6: Deals | D6: Status | E6: Lead | F6: Investing Entity Ϋ | G6: Vintageἀ | H6: Instrument | I6: % | J6: Committed | K6: Invested | L6: Remaining Commitment | M6: Distributions | N6: Carrying Value | O6: Gain | P6: TVPI | Q6: Additional Upside/Downside
G7: # | I7: % | J7: $,m | K7: $,m | L7: $,m | M7: $,m | N7: $,m | O7: $,m | P7: X
C8: Equity or Equity like Investments
C9: Jollychic Holding Limited | D9: Written-off | E9: Elaine | F9: Mozn | G9: 2019 | H9: C+ Prefs | I9: ='6. %'!F9 -> 0.056999998 | J9: =K9 -> 65 | K9: =-SUMIF('CF (Equity, Debt)'!$C$3:$K$53,'S | 01 '!C9,'CF (Equity, Debt)'!$E$3:$E$53) -> 65 | L9: 0 | M9: =SUMIF('CF (Equity, Debt)'!$C$3:$K$53,'S | 01 '!C9,'CF (Equity, Debt)'!$F$3:$F$53) -> 0 | N9: =VLOOKUP(C9,NAV!$B$4:$E$44,4,0) -> 0 | O9: =N9+M9-K9 -> -65 | P9: =(M9+N9)/K9 -> 0 | Q9: In Liquidation
C10: Mena Mobile Inc | D10: Written-off | E10: Elaine | F10: Mozn | G10: 2019 | H10: B Prefs | I10: ='6. %'!F10 -> 0.14 | J10: =K10 -> 8 | K10: =-SUMIF('CF (Equity, Debt)'!$C$3:$K$53,'S | 01 '!C10,'CF (Equity, Debt)'!$E$3:$E$53) -> 8 | L10: 0 | M10: =SUMIF('CF (Equity, Debt)'!$C$3:$K$53,'S | 01 '!C10,'CF (Equity, Debt)'!$F$3:$F$53) -> 0 | N10: =VLOOKUP(C10,NAV!$B$4:$E$44,4,0) -> 0 | O10: =N10+M10-K10 -> -8 | P10: =(M10+N10)/K10 -> 0 | Q10: In Liquidation
C11: Flyr Inc | D11: Unrealized | E11: Sushil | F11: Mozn | G11: 2019 | H11: B-1,2 Prefs | I11: ='6. %'!F11 -> 0.085025485 | J11: =K11 -> 10 | K11: =-SUMIF('CF (Equity, Debt)'!$C$3:$K$53,'S | 01 '!C11,'CF (Equity, Debt)'!$E$3:$E$53) -> 10 | L11: 0 | M11: =SUMIF('CF (Equity, Debt)'!$C$3:$K$53,'S | 01 '!C11,'CF (Equity, Debt)'!$F$3:$F$53) -> 0 | N11: =VLOOKUP(C11,NAV!$B$4:$E$44,4,0) -> 37.11873 | O11: =N11+M11-K11 -> 27.11873 | P11: =(M11+N11)/K11 -> 3.711873 | Q11: Flyr Warrantsa 2025 expiry
C12: Esyasoft Holding | D12: Realized | E12: Sushil | F12: Mozn | G12: 2020 | H12: Convertible Note | I12: ='6. %'!F12 -> n/a | J12: =K12 -> 2.5 | K12: =-SUMIF('CF (Equity, Debt)'!$C$3:$K$53,'S | 01 '!C12,'CF (Equity, Debt)'!$E$3:$E$53) -> 2.5 | L12: 0 | M12: =SUMIF('CF (Equity, Debt)'!$C$3:$K$53,'S | 01 '!C12,'CF (Equity, Debt)'!$F$3:$F$53) -> 5 | N12: =VLOOKUP(C12,NAV!$B$4:$E$44,4,0) -> 0 | O12: =N12+M12-K12 -> 2.5 | P12: =(M12+N12)/K12 -> 2
C13: Beyond Limits | D13: Unrealized | E13: Divyesh | F13: Mozn | G13: 2020 | H13: C Prefs | I13: ='6. %'!F13 -> 0.094347728 | J13: =K13 -> 90 | K13: =-SUMIF('CF (Equity, Debt)'!$C$3:$K$53,'S | 01 '!C13,'CF (Equity, Debt)'!$E$3:$E$53) -> 90 | L13: 0 | M13: =SUMIF('CF (Equity, Debt)'!$C$3:$K$53,'S | 01 '!C13,'CF (Equity, Debt)'!$F$3:$F$53) -> 0 | N13: =VLOOKUP(C13,NAV!$B$4:$E$44,4,0) -> 73.8 | O13: =N13+M13-K13 -> -16.2 | P13: =(M13+N13)/K13 -> 0.82
C14: ONT plc | D14: Unrealized | E14: Divyesh | F14: Mozn | G14: 2020 | H14: Ordinary Shares | I14: ='6. %'!F14 -> 0.051651565 | J14: =K14 -> 141.47026 | K14: =-SUMIF('CF (Equity, Debt)'!$C$3:$K$53,'S | 01 '!C14,'CF (Equity, Debt)'!$E$3:$E$53) -> 141.47026 | L14: 0 | M14: =SUMIF('CF (Equity, Debt)'!$C$3:$K$53,'S | 01 '!C14,'CF (Equity, Debt)'!$F$3:$F$53) -> 0 | N14: =VLOOKUP(C14,NAV!$B$4:$E$44,4,0) -> 53.000051 | O14: =N14+M14-K14 -> -88.470208 | P14: =(M14+N14)/K14 -> 0.37463741
C15: Heygears | D15: Unrealized | E15: Elaine | F15: Mozn | G15: 2020 | H15: Registered Capital | I15: ='6. %'!F15 -> 0.1438 | J15: =K15 -> 60 | K15: =-SUMIF('CF (Equity, Debt)'!$C$3:$K$53,'S | 01 '!C15,'CF (Equity, Debt)'!$E$3:$E$53) -> 60 | L15: 0 | M15: =SUMIF('CF (Equity, Debt)'!$C$3:$K$53,'S | 01 '!C15,'CF (Equity, Debt)'!$F$3:$F$53) -> 0 | N15: =VLOOKUP(C15,NAV!$B$4:$E$44,4,0) -> 149.39859 | O15: =N15+M15-K15 -> 89.398592 | P15: =(M15+N15)/K15 -> 2.4899765
C16: Jysan Technologies | D16: Realized | E16: Sushil | F16: Mozn 1 | G16: 2021 | H16: A (Ordinary Shares) | I16: ='6. %'!F16 -> 0.03 | J16: =K16 -> 20 | K16: =-SUMIF('CF (Equity, Debt)'!$C$3:$K$53,'S | 01 '!C16,'CF (Equity, Debt)'!$E$3:$E$53) -> 20 | L16: 0 | M16: =SUMIF('CF (Equity, Debt)'!$C$3:$K$53,'S | 01 '!C16,'CF (Equity, Debt)'!$F$3:$F$53) -> 24.5 | N16: =VLOOKUP(C16,NAV!$B$4:$E$44,4,0) -> 0 | O16: =N16+M16-K16 -> 4.5 | P16: =(M16+N16)/K16 -> 1.225
C17: Cerebras Systems Inc | D17: Unrealized | E17: Ignasi | F17: Mozn | G17: 2021 | H17: F Prefs | I17: ='6. %'!F17 -> 0.0091172068 | J17: =K17 -> 39.999983 | K17: =-SUMIF('CF (Equity, Debt)'!$C$3:$K$53,'S | 01 '!C17,'CF (Equity, Debt)'!$E$3:$E$53) -> 39.999983 | L17: 0 | M17: =SUMIF('CF (Equity, Debt)'!$C$3:$K$53,'S | 01 '!C17,'CF (Equity, Debt)'!$F$3:$F$53) -> 0 | N17: =VLOOKUP(C17,NAV!$B$4:$E$44,4,0) -> 21.135483 | O17: =N17+M17-K17 -> -18.8645 | P17: =(M17+N17)/K17 -> 0.5283873
C18: Endless Studios LLC | D18: Unrealized | E18: Sushil | F18: Mozn | G18: 2021 | H18: A Pref Units | I18: ='6. %'!F18 -> 0.16080402 | J18: =K18 -> 8 | K18: =-SUMIF('CF (Equity, Debt)'!$C$3:$K$53,'S | 01 '!C18,'CF (Equity, Debt)'!$E$3:$E$53) -> 8 | L18: 0 | M18: =SUMIF('CF (Equity, Debt)'!$C$3:$K$53,'S | 01 '!C18,'CF (Equity, Debt)'!$F$3:$F$53) -> 0 | N18: =VLOOKUP(C18,NAV!$B$4:$E$44,4,0) -> 8 | O18: =N18+M18-K18 -> 0 | P18: =(M18+N18)/K18 -> 1
C19: Instadeep Limited | D19: Realized | E19: Ignasi | F19: Mozn | G19: 2021 | H19: B Prefs | I19: ='6. %'!F19 -> 0.011489406 | J19: =K19 -> 5.0237202 | K19: =-SUMIF('CF (Equity, Debt)'!$C$3:$K$53,'S | 01 '!C19,'CF (Equity, Debt)'!$E$3:$E$53) -> 5.0237202 | L19: 0 | M19: =SUMIF('CF (Equity, Debt)'!$C$3:$K$53,'S | 01 '!C19,'CF (Equity, Debt)'!$F$3:$F$53) -> 7.9421925 | N19: =VLOOKUP(C19,NAV!$B$4:$E$44,4,0) -> 0 | O19: =N19+M19-K19 -> 2.9184723 | P19: =(M19+N19)/K19 -> 1.5809385
C20: X-fusion | D20: Realized | E20: Elaine | F20: Mozn 2 | G20: 2022 | H20: Equity-TBC | I20: ='6. %'!F20 -> 0.051 | J20: =K20 -> 493.50096 | K20: =-SUMIF('CF (Equity, Debt)'!$C$3:$K$53,'S | 01 '!C20,'CF (Equity, Debt)'!$E$3:$E$53) -> 493.50096 | L20: 0 | M20: =SUMIF('CF (Equity, Debt)'!$C$3:$K$53,'S | 01 '!C20,'CF (Equity, Debt)'!$F$3:$F$53) -> 403 | N20: =VLOOKUP(C20,NAV!$B$4:$E$44,4,0) -> 0 | O20: =N20+M20-K20 -> -90.500956 | P20: =(M20+N20)/K20 -> 0.81661443
C21: DriveNets | D21: Unrealized | E21: Anton | F21: G42 | G21: 2022 | H21: Equity-TBC | I21: ='6. %'!F21 -> 0.11141914 | J21: =K21 -> 300 | K21: =-SUMIF('CF (Equity, Debt)'!$C$3:$K$53,'S | 01 '!C21,'CF (Equity, Debt)'!$E$3:$E$53) -> 300 | L21: =0 -> 0 | M21: =SUMIF('CF (Equity, Debt)'!$C$3:$K$53,'S | 01 '!C21,'CF (Equity, Debt)'!$F$3:$F$53) -> 0 | N21: =VLOOKUP(C21,NAV!$B$4:$E$44,4,0) -> 204.6 | O21: =N21+M21-K21 -> -95.4 | P21: =(M21+N21)/K21 -> 0.682 | Q21: DN Warrants b
C22: vTv Therapeutics Inc. | D22: Unrealized | E22: Divyesh | F22: G42 | G22: 2022 | H22: Ordinary Shares | I22: ='6. %'!F22 -> 0.0021343582 | J22: =K22 -> 24.53125 | K22: =-SUMIF('CF (Equity, Debt)'!$C$3:$K$53,'S | 01 '!C22,'CF (Equity, Debt)'!$E$3:$E$53) -> 24.53125 | L22: =J22-K22 -> 0 | M22: =SUMIF('CF (Equity, Debt)'!$C$3:$K$53,'S | 01 '!C22,'CF (Equity, Debt)'!$F$3:$F$53) -> 0 | N22: =VLOOKUP(C22,NAV!$B$4:$E$44,4,0) -> 4.5855426 | O22: =N22+M22-K22 -> -19.945707 | P22: =(M22+N22)/K22 -> 0.18692658 | Q22: vTv $30m milestn payment c
C23: Honor Device Co Ltd | D23: Realized | E23: Elaine | F23: G42 3 | G23: 2022 | H23: Equity-TBC | I23: ='6. %'!F23 -> 0.018823528 | J23: =K23 -> 800 | K23: =-SUMIF('CF (Equity, Debt)'!$C$3:$K$53,'S | 01 '!C23,'CF (Equity, Debt)'!$E$3:$E$53) -> 800 | L23: =J23-K23 -> 0 | M23: =SUMIF('CF (Equity, Debt)'!$C$3:$K$53,'S | 01 '!C23,'CF (Equity, Debt)'!$F$3:$F$53) -> 802.8 | N23: =VLOOKUP(C23,NAV!$B$4:$E$44,4,0) -> 0 | O23: =N23+M23-K23 -> 2.8 | P23: =(M23+N23)/K23 -> 1.0035
C24: Applied AI Corporation Limited | D24: Unrealized | E24: Divyesh | F24: Mozn | G24: 2022 | H24: Convertible Note | I24: ='6. %'!F24 -> n/a | J24: 15 | K24: =-SUMIF('CF (Equity, Debt)'!$C$3:$K$53,'S | 01 '!C24,'CF (Equity, Debt)'!$E$3:$E$53) -> 11.5 | L24: =J24-K24 -> 3.5 | M24: 0 | N24: =VLOOKUP(C24,NAV!$B$4:$E$44,4,0) -> 11.5 | O24: =N24+M24-K24 -> 0 | P24: =(M24+N24)/K24 -> 1
C25: eSpace | D25: Unrealized | E25: Anton | F25: Mozn 4 | G25: 2022 | H25: B Prefs | I25: ='6. %'!F25 -> 0.027864956 | J25: =K25 -> 15 | K25: =-SUMIF('CF (Equity, Debt)'!$C$3:$K$53,'S | 01 '!C25,'CF (Equity, Debt)'!$E$3:$E$53) -> 15 | L25: =J25-K25 -> 0 | M25: 0 | N25: =VLOOKUP(C25,NAV!$B$4:$E$44,4,0) -> 20.888122 | O25: =N25+M25-K25 -> 5.8881215 | P25: =(M25+N25)/K25 -> 1.3925414
C26: Tools for Humanity Corporation | D26: Unrealized | E26: Divyesh | F26: Mozn | G26: 2023 | H26: C Prefs | I26: ='6. %'!F26 -> 0.0062621983 | J26: =K26 -> 14.999999 | K26: =-SUMIF('CF (Equity, Debt)'!$C$3:$K$53,'S | 01 '!C26,'CF (Equity, Debt)'!$E$3:$E$53) -> 14.999999 | L26: =J26-K26 -> 0 | M26: 0 | N26: =VLOOKUP(C26,NAV!$B$4:$E$44,4,0) -> 14.999999 | O26: =N26+M26-K26 -> 0 | P26: =(M26+N26)/K26 -> 1
C27: WLD Tokens | D27: Unrealized | E27: Divyesh | F27: Mozn | G27: 2023 | H27: Tokens | I27: ='6. %'!F27 -> 0.00625 | J27: =K27 -> 0.006875 | K27: =-SUMIF('CF (Equity, Debt)'!$C$3:$K$53,'S | 01 '!C27,'CF (Equity, Debt)'!$E$3:$E$53) -> 0.006875 | L27: =J27-K27 -> 0 | M27: 0 | N27: =VLOOKUP(C27,NAV!$B$4:$E$44,4,0) -> 120.19231 | O27: =N27+M27-K27 -> 120.18543 | P27: NM | Q27: Crypto Tokensd
C28: E-line Ventures LLC | D28: Unrealized | E28: Sushil | F28: Mozn | G28: 2023 | H28: B Prefs | I28: ='6. %'!F28 -> 0.11483736 | J28: =K28 -> 6 | K28: =-SUMIF('CF (Equity, Debt)'!$C$3:$K$53,'S | 01 '!C28,'CF (Equity, Debt)'!$E$3:$E$53) -> 6 | L28: =J28-K28 -> 0 | M28: 0 | N28: =VLOOKUP(C28,NAV!$B$4:$E$44,4,0) -> 6 | O28: =N28+M28-K28 -> 0 | P28: =(M28+N28)/K28 -> 1 | Q28: Optionse
C29: School Hack (AIREV Holding Limited) | D29: Unrealized | E29: Camillo | F29: Core42 5 | G29: 2024 | H29: Preferred Shares | I29: ='6. %'!F29 -> 0.25 | J29: =K29+0.25 -> 2.75 | K29: =-SUMIF('CF (Equity, Debt)'!$C$3:$K$53,'S | 01 '!C29,'CF (Equity, Debt)'!$E$3:$E$53) -> 2.5 | L29: =J29-K29 -> 0.25 | M29: 0 | N29: =VLOOKUP(C29,NAV!$B$4:$E$44,4,0) -> 2.5 | O29: =N29+M29-K29 -> 0 | P29: =(M29+N29)/K29 -> 1 | Q29: Cloud Creditg
C30: Life Biosciences LLC | D30: Unrealized | E30: Divyesh | F30: G42 Capital | G30: 2024 | H30: Convertible Note | I30: ='6. %'!F30 -> n/a | J30: =K30 -> 20 | K30: =-SUMIF('CF (Equity, Debt)'!$C$3:$K$53,'S | 01 '!C30,'CF (Equity, Debt)'!$E$3:$E$53) -> 20 | L30: =J30-K30 -> 0 | M30: 0 | N30: =VLOOKUP(C30,NAV!$B$4:$E$44,4,0) -> 20 | O30: =N30+M30-K30 -> 0 | P30: =(M30+N30)/K30 -> 1
C31: Verses AI Inc | D31: Unrealized | E31: Divyesh | F31: G42 Capital | G31: 2024 | H31: Convertible Debenture | I31: n/a | J31: 10 | K31: =-SUMIF('CF (Equity, Debt)'!$C$3:$K$53,'S | 01 '!C31,'CF (Equity, Debt)'!$E$3:$E$53) -> 10 | L31: =J31-K31 -> 0 | M31: 0 | N31: =VLOOKUP(C31,NAV!$B$4:$E$44,4,0) -> 10 | O31: =N31+M31-K31 -> 0 | P31: =(M31+N31)/K31 -> 1 | Q31: Revenue linked RSUs
J33: =SUM(J9:J31) -> 2151.783 | K33: =SUM(K9:K31) -> 2148.033 | L33: =SUM(L9:L31) -> 3.75 | M33: =SUM(M9:M31) -> 1243.2422 | N33: =SUM(N9:N31) -> 757.71883 | O33: =SUM(O9:O31) -> -147.07202 | P33: =(M33+N33)/K33 -> 0.93153177
C35: Debt Investments
C36: Glass Earth Holdings LLC | D36: Written-off | E36: Marty | F36: Mozn | G36: 2019 | H36: Promissory Note | I36: n/a | J36: 8 | K36: 8 | L36: 0 | M36: 0 | N36: 0 | O36: =N36+M36-K36 -> -8 | P36: =(M36+N36)/K36 -> 0 | Q36: In Default
C37: Mena Mobile Inc (Debt) | D37: Written-off | E37: Elaine | F37: Mozn | G37: 2021 | H37: Loan | I37: n/a | J37: 2.353982 | K37: =J37 -> 2.353982 | L37: 0 | M37: 0 | N37: =VLOOKUP(C37,NAV!$B$4:$E$44,4,0) -> 0 | O37: =N37+M37-K37 -> -2.353982 | P37: =(M37+N37)/K37 -> 0 | Q37: In Liquidation
C38: Esyasoft Holding (Debt) | D38: Realized | E38: Sushil | F38: Mozn | G38: 2021 | H38: Loan | I38: n/a | J38: 0.411765 | K38: 0.411765 | L38: 0 | M38: ='CF (Equity, Debt)'!F58 -> 0.47078465 | N38: 0 | O38: =N38+M38-K38 -> 0.05901965 | P38: =(M38+N38)/K38 -> 1.1433333
J39: =SUM(J36:J38) -> 10.765747 | K39: =SUM(K36:K38) -> 10.765747 | L39: =SUM(L36:L38) -> 0 | M39: =SUM(M36:M38) -> 0.47078465 | N39: =SUM(N36:N38) -> 0 | O39: =N39+M39-K39 -> -10.294962 | P39: =(M39+N39)/K39 -> 0.043729864
C41: Funds Investments
C42: New Space Capital Fund I | D42: Unrealized | E42: Sushil | F42: G42 Investments | G42: 2020 | H42: LP | I42: n/a | J42: ='8. NewSpace'!P7*10^-6*NAV!K21 -> 24.886432 | K42: =-SUMIF('CF (Funds)'!$C$4:$E$2011,C42,'CF (Funds)'!$E$4:$E$2011) -> 15.922439 | L42: ='8. NewSpace'!P22*10^-6*NAV!K21 -> 11.89512 | M42: =SUM('CF (Funds)'!F38:F61) -> 3.4194691 | N42: =VLOOKUP(C42,NAV!$B$4:$E$44,4,0) -> 19.274963 | O42: =N42+M42-K42 -> 6.7719935 | P42: =(M42+N42)/K42 -> 1.4253113
C43: New Space Capital GP Com SCSp | D43: Unrealized | E43: Sushil | F43: G42 Investments | G43: 2023 | H43: LP | I43: n/a | J43: =2.3/0.85 -> 2.7058824 | K43: 2.7058824 | L43: 0 | M43: 0 | N43: =VLOOKUP(C43,NAV!$B$4:$E$44,4,0) -> 3.2756152 | O43: =N43+M43-K43 -> 0.56973286 | P43: =(M43+N43)/K43 -> 1.2105534
C44: North Summit Capital Fund | D44: Unrealized | E44: Elaine | F44: G42 Investments | G44: 2020 | H44: LP | I44: n/a | J44: =K44+L44 -> 83.63035 | K44: =-SUMIF('CF (Funds)'!$C$4:$E$2011,C44,'CF (Funds)'!$E$4:$E$2011) -> 83.27035 | L44: =0.12*3 -> 0.36 | M44: =SUM('CF (Funds)'!F26:'CF (Funds)'!F36) -> 7.815871 | N44: =VLOOKUP(C44,NAV!$B$4:$E$44,4,0) -> 74.725861 | O44: =N44+M44-K44 -> -0.728618 | P44: =(M44+N44)/K44 -> 0.99124997
C45: Sinovation Disrupt Fund, L.P. | D45: Realized | E45: Elaine | F45: G42 Investments | G45: 2020 | H45: LP | I45: n/a | J45: 50 | K45: =-SUMIF('CF (Funds)'!$C$4:$E$2011,C45,'CF (Funds)'!$E$4:$E$2011) -> 24.959693 | L45: 0 | M45: =SUM('CF (Funds)'!F4:F21) -> 25.403521 | N45: =VLOOKUP(C45,NAV!$B$4:$E$44,4,0) -> 0 | O45: =N45+M45-K45 -> 0.44382835 | P45: =(M45+N45)/K45 -> 1.0177818
C46: Acies Investments Fund I, L.P. | D46: Unrealized | E46: Divyesh | F46: G42 Investments | G46: 2021 | H46: LP | I46: 0.33 | J46: 17.1125 | K46: =-SUMIF('CF (Funds)'!$C$4:$E$2011,C46,'CF (Funds)'!$E$4:$E$2011) -> 14.015137 | L46: =J46-K46 -> 3.0973625 | M46: 0 | N46: =VLOOKUP(C46,NAV!$B$4:$E$44,4,0) -> 10.875212 | O46: =N46+M46-K46 -> -3.1399255 | P46: =(M46+N46)/K46 -> 0.77596185 | Q46: 9.9% GP | Anchorf
J47: =SUM(J42:J46) -> 178.33516 | K47: =SUM(K42:K46) -> 140.8735 | L47: =SUM(L42:L46) -> 15.352483 | M47: =SUM(M42:M46) -> 36.638861 | N47: =SUM(N42:N46) -> 108.15165 | O47: =N47+M47-K47 -> 3.9170112 | P47: =(M47+N47)/K47 -> 1.0278052
C49: Total | J49: =J33+J39+J47 -> 2340.884 | K49: =K33+K39+K47 -> 2299.6723 | L49: =L33+L39+L47 -> 19.102483 | M49: =M33+M39+M47 -> 1280.3518 | N49: =N33+N39+N47 -> 865.87048 | O49: =N49+M49-K49 -> -153.44997 | P49: =(M49+N49)/K49 -> 0.93327311
C52: Additional Upside Section:
C53: a) Flyr: For every $1m of revenue, 194,477 shares, capped at 1,264,1000 (B-1) shares shall be issued to Mozn
C54: b) DriveNets: Share warrants exercisable upon the achievement of target revenue of clients referred by G42, and corresponding milestones
C55: c) vTv Therapeutics: Potential issuance of $30m in additional shares, if FDA approval received for the drug TTP399
C56: d) Tools for Humanity Corporation: An additional 62.5 million Tokens (WLD tokens) received for a consideration of $6,875.00.
C57: e) E-line Ventures LLC: Option to further acquire Series B Pref shares at max($1.34, EV/No of shares)
C58: f) Acies Investments Fund I LP: Being the Anchor investor, entitled to 9.9% of the aggregate carried interest earned by the GP
C59: g) Cloud Credit of 250K counted towards the investment cost
C60: IRR is referred as NM when it is not meaningful
C62: Definitions:
C63: ἀ = Vintage corresponds to the year of the first investment made
C64: β = Excludes transaction costs from the estimate of IRR, as those are not available
... C81: TBC = to be confirmed

Sheet S | 02
C2: As of date | D2: =D!D2 -> 45473
E5: 2 | F5: 3 | G5: 4 | H5: 5 | I5: 6 | J5: 7 | K5: 8 | L5: 9 | M5: 11 | N5: 12 | O5: 13 | Q5: 14 | R5: 10 | S5: 15
C6: Deals | D6: Type | E6: Status | F6: Lead | G6: Investing Entity | H6: Vintageἀ | I6: Instrument | J6: % | K6: Committed | L6: Invested | M6: Distributions | N6: Carrying Value | O6: Gain | P6: Gain till FY22 | Q6: TVPI | R6: Remaining Commitment | S6: Additonal Upside/Downside
I7: # | J7: % | K7: $,m | L7: $,m | M7: $,m | N7: $,m | O7: $,m | Q7: X | R7: $,m | V7: MOZN
C8: MOZN Holding RSC Ltd
C9: E-line Ventures LLC | D9: Direct Investment | E9: =VLOOKUP($C9,'S | 01 '!$C$6:$Q$49,E$5,0) -> Unrealized | F9: =VLOOKUP($C9,'S | 01 '!$C$6:$Q$49,F$5,0) -> Sushil | G9: =VLOOKUP($C9,'S | 01 '!$C$6:$Q$49,G$5,0) -> Mozn | H9: =VLOOKUP($C9,'S | 01 '!$C$6:$Q$49,H$5,0) -> 2023 | I9: =VLOOKUP($C9,'S | 01 '!$C$6:$Q$49,I$5,0) -> B Prefs | J9: =VLOOKUP($C9,'S | 01 '!$C$6:$Q$49,J$5,0) -> 0.11483736 | K9: =VLOOKUP($C9,'S | 01 '!$C$6:$Q$49,K$5,0) -> 6 | L9: =VLOOKUP($C9,'S | 01 '!$C$6:$Q$49,L$5,0) -> 6 | ... O9: =VLOOKUP($C9,'S | 01 '!$C$6:$Q$49,O$5,0) -> 0 | P9: n/a | Q9: =VLOOKUP($C9,'S | 01 '!$C$6:$Q$49,Q$5,0) -> 1 | R9: =VLOOKUP($C9,'S | 01 '!$C$6:$Q$49,R$5,0) -> 0 | S9: Optionse
C10: WLD Tokens | D10: Direct Investment | E10: =VLOOKUP($C10,'S | 01 '!$C$6:$Q$49,E$5,0) -> Unrealized | F10: =VLOOKUP($C10,'S | 01 '!$C$6:$Q$49,F$5,0) -> Divyesh | G10: =VLOOKUP($C10,'S | 01 '!$C$6:$Q$49,G$5,0) -> Mozn | H10: =VLOOKUP($C10,'S | 01 '!$C$6:$Q$49,H$5,0) -> 2023 | I10: =VLOOKUP($C10,'S | 01 '!$C$6:$Q$49,I$5,0) -> Tokens | J10: =VLOOKUP($C10,'S | 01 '!$C$6:$Q$49,J$5,0) -> 0.00625 | K10: =VLOOKUP($C10,'S | 01 '!$C$6:$Q$49,K$5,0) -> 0.006875 | L10: =VLOOKUP($C10,'S | 01 '!$C$6:$Q$49,L$5,0) -> 0.006875 | ... O10: =VLOOKUP($C10,'S | 01 '!$C$6:$Q$49,O$5,0) -> 120.18543 | P10: n/a | Q10: =VLOOKUP($C10,'S | 01 '!$C$6:$Q$49,Q$5,0) -> NM | R10: =VLOOKUP($C10,'S | 01 '!$C$6:$Q$49,R$5,0) -> 0
C11: Tools for Humanity Corporation | D11: Direct Investment | E11: =VLOOKUP($C11,'S | 01 '!$C$6:$Q$49,E$5,0) -> Unrealized | F11: =VLOOKUP($C11,'S | 01 '!$C$6:$Q$49,F$5,0) -> Divyesh | G11: =VLOOKUP($C11,'S | 01 '!$C$6:$Q$49,G$5,0) -> Mozn | H11: =VLOOKUP($C11,'S | 01 '!$C$6:$Q$49,H$5,0) -> 2023 | I11: =VLOOKUP($C11,'S | 01 '!$C$6:$Q$49,I$5,0) -> C Prefs | J11: =VLOOKUP($C11,'S | 01 '!$C$6:$Q$49,J$5,0) -> 0.0062621983 | K11: =VLOOKUP($C11,'S | 01 '!$C$6:$Q$49,K$5,0) -> 14.999999 | L11: =VLOOKUP($C11,'S | 01 '!$C$6:$Q$49,L$5,0) -> 14.999999 | ... O11: =VLOOKUP($C11,'S | 01 '!$C$6:$Q$49,O$5,0) -> 0 | P11: n/a | Q11: =VLOOKUP($C11,'S | 01 '!$C$6:$Q$49,Q$5,0) -> 1 | R11: =VLOOKUP($C11,'S | 01 '!$C$6:$Q$49,R$5,0) -> 0
C12: eSpace | D12: Direct Investment | E12: =VLOOKUP($C12,'S | 01 '!$C$6:$Q$49,E$5,0) -> Unrealized | F12: =VLOOKUP($C12,'S | 01 '!$C$6:$Q$49,F$5,0) -> Anton | G12: =VLOOKUP($C12,'S | 01 '!$C$6:$Q$49,G$5,0) -> Mozn 4 | H12: =VLOOKUP($C12,'S | 01 '!$C$6:$Q$49,H$5,0) -> 2022 | I12: =VLOOKUP($C12,'S | 01 '!$C$6:$Q$49,I$5,0) -> B Prefs | J12: =VLOOKUP($C12,'S | 01 '!$C$6:$Q$49,J$5,0) -> 0.027864956 | K12: =VLOOKUP($C12,'S | 01 '!$C$6:$Q$49,K$5,0) -> 15 | L12: =VLOOKUP($C12,'S | 01 '!$C$6:$Q$49,L$5,0) -> 15 | ... O12: =VLOOKUP($C12,'S | 01 '!$C$6:$Q$49,O$5,0) -> 5.8881215 | P12: 0 | Q12: =VLOOKUP($C12,'S | 01 '!$C$6:$Q$49,Q$5,0) -> 1.3925414 | R12: =VLOOKUP($C12,'S | 01 '!$C$6:$Q$49,R$5,0) -> 0 | V12: Invested | W12: =L30 -> 1001.7675
C13: Applied AI Corporation Limited | D13: Direct Investment | E13: =VLOOKUP($C13,'S | 01 '!$C$6:$Q$49,E$5,0) -> Unrealized | F13: =VLOOKUP($C13,'S | 01 '!$C$6:$Q$49,F$5,0) -> Divyesh | G13: =VLOOKUP($C13,'S | 01 '!$C$6:$Q$49,G$5,0) -> Mozn | H13: =VLOOKUP($C13,'S | 01 '!$C$6:$Q$49,H$5,0) -> 2022 | I13: =VLOOKUP($C13,'S | 01 '!$C$6:$Q$49,I$5,0) -> Convertible Note | J13: =VLOOKUP($C13,'S | 01 '!$C$6:$Q$49,J$5,0) -> n/a | K13: =VLOOKUP($C13,'S | 01 '!$C$6:$Q$49,K$5,0) -> 15 | L13: =VLOOKUP($C13,'S | 01 '!$C$6:$Q$49,L$5,0) -> 11.5 | ... O13: =VLOOKUP($C13,'S | 01 '!$C$6:$Q$49,O$5,0) -> 0 | P13: 0 | Q13: =VLOOKUP($C13,'S | 01 '!$C$6:$Q$49,Q$5,0) -> 1 | R13: =VLOOKUP($C13,'S | 01 '!$C$6:$Q$49,R$5,0) -> 3.5 | V13: NAV | W13: =N30 -> 516.03328
C14: X-fusion | D14: Direct Investment | E14: =VLOOKUP($C14,'S | 01 '!$C$6:$Q$49,E$5,0) -> Realized | F14: =VLOOKUP($C14,'S | 01 '!$C$6:$Q$49,F$5,0) -> Elaine | G14: =VLOOKUP($C14,'S | 01 '!$C$6:$Q$49,G$5,0) -> Mozn 2 | H14: =VLOOKUP($C14,'S | 01 '!$C$6:$Q$49,H$5,0) -> 2022 | I14: =VLOOKUP($C14,'S | 01 '!$C$6:$Q$49,I$5,0) -> Equity-TBC | J14: =VLOOKUP($C14,'S | 01 '!$C$6:$Q$49,J$5,0) -> 0.051 | K14: =VLOOKUP($C14,'S | 01 '!$C$6:$Q$49,K$5,0) -> 493.50096 | L14: =VLOOKUP($C14,'S | 01 '!$C$6:$Q$49,L$5,0) -> 493.50096 | ... O14: =VLOOKUP($C14,'S | 01 '!$C$6:$Q$49,O$5,0) -> -90.500956 | P14: -64.391 | Q14: =VLOOKUP($C14,'S | 01 '!$C$6:$Q$49,Q$5,0) -> 0.81661443 | R14: =VLOOKUP($C14,'S | 01 '!$C$6:$Q$49,R$5,0) -> 0 | S14: Full Exit | V14: Gain | W14: =O30 -> -44.821278
C15: Mena Mobile Inc (Debt) | D15: Debt Investment | E15: =VLOOKUP($C15,'S | 01 '!$C$6:$Q$49,E$5,0) -> Written-off | F15: =VLOOKUP($C15,'S | 01 '!$C$6:$Q$49,F$5,0) -> Elaine | G15: =VLOOKUP($C15,'S | 01 '!$C$6:$Q$49,G$5,0) -> Mozn | H15: =VLOOKUP($C15,'S | 01 '!$C$6:$Q$49,H$5,0) -> 2021 | I15: =VLOOKUP($C15,'S | 01 '!$C$6:$Q$49,I$5,0) -> Loan | J15: =VLOOKUP($C15,'S | 01 '!$C$6:$Q$49,J$5,0) -> n/a | K15: =VLOOKUP($C15,'S | 01 '!$C$6:$Q$49,K$5,0) -> 2.353982 | L15: =VLOOKUP($C15,'S | 01 '!$C$6:$Q$49,L$5,0) -> 2.353982 | ... O15: =VLOOKUP($C15,'S | 01 '!$C$6:$Q$49,O$5,0) -> -2.353982 | P15: 0 | Q15: =VLOOKUP($C15,'S | 01 '!$C$6:$Q$49,Q$5,0) -> 0 | R15: =VLOOKUP($C15,'S | 01 '!$C$6:$Q$49,R$5,0) -> 0 | S15: Written Off | V15: YTD Gains | W15: =W14-P30 -> -59.358477
C16: Esyasoft Holding (Debt) | D16: Debt Investment | E16: =VLOOKUP($C16,'S | 01 '!$C$6:$Q$49,E$5,0) -> Realized | F16: =VLOOKUP($C16,'S | 01 '!$C$6:$Q$49,F$5,0) -> Sushil | G16: =VLOOKUP($C16,'S | 01 '!$C$6:$Q$49,G$5,0) -> Mozn | H16: =VLOOKUP($C16,'S | 01 '!$C$6:$Q$49,H$5,0) -> 2021 | I16: =VLOOKUP($C16,'S | 01 '!$C$6:$Q$49,I$5,0) -> Loan | J16: =VLOOKUP($C16,'S | 01 '!$C$6:$Q$49,J$5,0) -> n/a | K16: =VLOOKUP($C16,'S | 01 '!$C$6:$Q$49,K$5,0) -> 0.411765 | L16: =VLOOKUP($C16,'S | 01 '!$C$6:$Q$49,L$5,0) -> 0.411765 | ... O16: =VLOOKUP($C16,'S | 01 '!$C$6:$Q$49,O$5,0) -> 0.05901965 | P16: 0.05901965 | Q16: =VLOOKUP($C16,'S | 01 '!$C$6:$Q$49,Q$5,0) -> 1.1433333 | R16: =VLOOKUP($C16,'S | 01 '!$C$6:$Q$49,R$5,0) -> 0 | S16: Full Exit | V16: IRR | W16: =#REF! -> #REF!
C17: Jysan Technologies | D17: Direct Investment | E17: =VLOOKUP($C17,'S | 01 '!$C$6:$Q$49,E$5,0) -> Realized | F17: =VLOOKUP($C17,'S | 01 '!$C$6:$Q$49,F$5,0) -> Sushil | G17: =VLOOKUP($C17,'S | 01 '!$C$6:$Q$49,G$5,0) -> Mozn 1 | H17: =VLOOKUP($C17,'S | 01 '!$C$6:$Q$49,H$5,0) -> 2021 | I17: =VLOOKUP($C17,'S | 01 '!$C$6:$Q$49,I$5,0) -> A (Ordinary Shares) | J17: =VLOOKUP($C17,'S | 01 '!$C$6:$Q$49,J$5,0) -> 0.03 | K17: =VLOOKUP($C17,'S | 01 '!$C$6:$Q$49,K$5,0) -> 20 | L17: =VLOOKUP($C17,'S | 01 '!$C$6:$Q$49,L$5,0) -> 20 | ... O17: =VLOOKUP($C17,'S | 01 '!$C$6:$Q$49,O$5,0) -> 4.5 | P17: 0 | Q17: =VLOOKUP($C17,'S | 01 '!$C$6:$Q$49,Q$5,0) -> 1.225 | R17: =VLOOKUP($C17,'S | 01 '!$C$6:$Q$49,R$5,0) -> 0 | S17: Full Exit
C18: Instadeep Limited | D18: Direct Investment | E18: =VLOOKUP($C18,'S | 01 '!$C$6:$Q$49,E$5,0) -> Realized | F18: =VLOOKUP($C18,'S | 01 '!$C$6:$Q$49,F$5,0) -> Ignasi | G18: =VLOOKUP($C18,'S | 01 '!$C$6:$Q$49,G$5,0) -> Mozn | H18: =VLOOKUP($C18,'S | 01 '!$C$6:$Q$49,H$5,0) -> 2021 | I18: =VLOOKUP($C18,'S | 01 '!$C$6:$Q$49,I$5,0) -> B Prefs | J18: =VLOOKUP($C18,'S | 01 '!$C$6:$Q$49,J$5,0) -> 0.011489406 | K18: =VLOOKUP($C18,'S | 01 '!$C$6:$Q$49,K$5,0) -> 5.0237202 | L18: =VLOOKUP($C18,'S | 01 '!$C$6:$Q$49,L$5,0) -> 5.0237202 | ... O18: =VLOOKUP($C18,'S | 01 '!$C$6:$Q$49,O$5,0) -> 2.9184723 | P18: 1.6721788 | Q18: =VLOOKUP($C18,'S | 01 '!$C$6:$Q$49,Q$5,0) -> 1.5809385 | R18: =VLOOKUP($C18,'S | 01 '!$C$6:$Q$49,R$5,0) -> 0 | S18: Full Exit
C19: Cerebras Systems Inc | D19: Direct Investment | E19: =VLOOKUP($C19,'S | 01 '!$C$6:$Q$49,E$5,0) -> Unrealized | F19: =VLOOKUP($C19,'S | 01 '!$C$6:$Q$49,F$5,0) -> Ignasi | G19: =VLOOKUP($C19,'S | 01 '!$C$6:$Q$49,G$5,0) -> Mozn | H19: =VLOOKUP($C19,'S | 01 '!$C$6:$Q$49,H$5,0) -> 2021 | I19: =VLOOKUP($C19,'S | 01 '!$C$6:$Q$49,I$5,0) -> F Prefs | J19: =VLOOKUP($C19,'S | 01 '!$C$6:$Q$49,J$5,0) -> 0.0091172068 | K19: =VLOOKUP($C19,'S | 01 '!$C$6:$Q$49,K$5,0) -> 39.999983 | L19: =VLOOKUP($C19,'S | 01 '!$C$6:$Q$49,L$5,0) -> 39.999983 | ... O19: =VLOOKUP($C19,'S | 01 '!$C$6:$Q$49,O$5,0) -> -18.8645 | P19: 0 | Q19: =VLOOKUP($C19,'S | 01 '!$C$6:$Q$49,Q$5,0) -> 0.5283873 | R19: =VLOOKUP($C19,'S | 01 '!$C$6:$Q$49,R$5,0) -> 0
C20: Endless Studios LLC | D20: Direct Investment | E20: =VLOOKUP($C20,'S | 01 '!$C$6:$Q$49,E$5,0) -> Unrealized | F20: =VLOOKUP($C20,'S | 01 '!$C$6:$Q$49,F$5,0) -> Sushil | G20: =VLOOKUP($C20,'S | 01 '!$C$6:$Q$49,G$5,0) -> Mozn | H20: =VLOOKUP($C20,'S | 01 '!$C$6:$Q$49,H$5,0) -> 2021 | I20: =VLOOKUP($C20,'S | 01 '!$C$6:$Q$49,I$5,0) -> A Pref Units | J20: =VLOOKUP($C20,'S | 01 '!$C$6:$Q$49,J$5,0) -> 0.16080402 | K20: =VLOOKUP($C20,'S | 01 '!$C$6:$Q$49,K$5,0) -> 8 | L20: =VLOOKUP($C20,'S | 01 '!$C$6:$Q$49,L$5,0) -> 8 | ... O20: =VLOOKUP($C20,'S | 01 '!$C$6:$Q$49,O$5,0) -> 0 | P20: 0 | Q20: =VLOOKUP($C20,'S | 01 '!$C$6:$Q$49,Q$5,0) -> 1 | R20: =VLOOKUP($C20,'S | 01 '!$C$6:$Q$49,R$5,0) -> 0
C21: Esyasoft Holding | D21: Direct Investment | E21: =VLOOKUP($C21,'S | 01 '!$C$6:$Q$49,E$5,0) -> Realized | F21: =VLOOKUP($C21,'S | 01 '!$C$6:$Q$49,F$5,0) -> Sushil | G21: =VLOOKUP($C21,'S | 01 '!$C$6:$Q$49,G$5,0) -> Mozn | H21: =VLOOKUP($C21,'S | 01 '!$C$6:$Q$49,H$5,0) -> 2020 | I21: =VLOOKUP($C21,'S | 01 '!$C$6:$Q$49,I$5,0) -> Convertible Note | J21: =VLOOKUP($C21,'S | 01 '!$C$6:$Q$49,J$5,0) -> n/a | K21: =VLOOKUP($C21,'S | 01 '!$C$6:$Q$49,K$5,0) -> 2.5 | L21: =VLOOKUP($C21,'S | 01 '!$C$6:$Q$49,L$5,0) -> 2.5 | ... O21: =VLOOKUP($C21,'S | 01 '!$C$6:$Q$49,O$5,0) -> 2.5 | P21: 2.5 | Q21: =VLOOKUP($C21,'S | 01 '!$C$6:$Q$49,Q$5,0) -> 2 | R21: =VLOOKUP($C21,'S | 01 '!$C$6:$Q$49,R$5,0) -> 0 | S21: Full Exit
C22: Heygears | D22: Direct Investment | E22: =VLOOKUP($C22,'S | 01 '!$C$6:$Q$49,E$5,0) -> Unrealized | F22: =VLOOKUP($C22,'S | 01 '!$C$6:$Q$49,F$5,0) -> Elaine | G22: =VLOOKUP($C22,'S | 01 '!$C$6:$Q$49,G$5,0) -> Mozn | H22: =VLOOKUP($C22,'S | 01 '!$C$6:$Q$49,H$5,0) -> 2020 | I22: =VLOOKUP($C22,'S | 01 '!$C$6:$Q$49,I$5,0) -> Registered Capital | J22: =VLOOKUP($C22,'S | 01 '!$C$6:$Q$49,J$5,0) -> 0.1438 | K22: =VLOOKUP($C22,'S | 01 '!$C$6:$Q$49,K$5,0) -> 60 | L22: =VLOOKUP($C22,'S | 01 '!$C$6:$Q$49,L$5,0) -> 60 | ... O22: =VLOOKUP($C22,'S | 01 '!$C$6:$Q$49,O$5,0) -> 89.398592 | P22: 96.4 | Q22: =VLOOKUP($C22,'S | 01 '!$C$6:$Q$49,Q$5,0) -> 2.4899765 | R22: =VLOOKUP($C22,'S | 01 '!$C$6:$Q$49,R$5,0) -> 0
C23: Beyond Limits | D23: Direct Investment | E23: =VLOOKUP($C23,'S | 01 '!$C$6:$Q$49,E$5,0) -> Unrealized | F23: =VLOOKUP($C23,'S | 01 '!$C$6:$Q$49,F$5,0) -> Divyesh | G23: =VLOOKUP($C23,'S | 01 '!$C$6:$Q$49,G$5,0) -> Mozn | H23: =VLOOKUP($C23,'S | 01 '!$C$6:$Q$49,H$5,0) -> 2020 | I23: =VLOOKUP($C23,'S | 01 '!$C$6:$Q$49,I$5,0) -> C Prefs | J23: =VLOOKUP($C23,'S | 01 '!$C$6:$Q$49,J$5,0) -> 0.094347728 | K23: =VLOOKUP($C23,'S | 01 '!$C$6:$Q$49,K$5,0) -> 90 | L23: =VLOOKUP($C23,'S | 01 '!$C$6:$Q$49,L$5,0) -> 90 | ... O23: =VLOOKUP($C23,'S | 01 '!$C$6:$Q$49,O$5,0) -> -16.2 | P23: 1.042 | Q23: =VLOOKUP($C23,'S | 01 '!$C$6:$Q$49,Q$5,0) -> 0.82 | R23: =VLOOKUP($C23,'S | 01 '!$C$6:$Q$49,R$5,0) -> 0
C24: ONT plc | D24: Direct Investment | E24: =VLOOKUP($C24,'S | 01 '!$C$6:$Q$49,E$5,0) -> Unrealized | F24: =VLOOKUP($C24,'S | 01 '!$C$6:$Q$49,F$5,0) -> Divyesh | G24: =VLOOKUP($C24,'S | 01 '!$C$6:$Q$49,G$5,0) -> Mozn | H24: =VLOOKUP($C24,'S | 01 '!$C$6:$Q$49,H$5,0) -> 2020 | I24: =VLOOKUP($C24,'S | 01 '!$C$6:$Q$49,I$5,0) -> Ordinary Shares | J24: =VLOOKUP($C24,'S | 01 '!$C$6:$Q$49,J$5,0) -> 0.051651565 | K24: =VLOOKUP($C24,'S | 01 '!$C$6:$Q$49,K$5,0) -> 141.47026 | L24: =VLOOKUP($C24,'S | 01 '!$C$6:$Q$49,L$5,0) -> 141.47026 | ... O24: =VLOOKUP($C24,'S | 01 '!$C$6:$Q$49,O$5,0) -> -88.470208 | P24: -9.845 | Q24: =VLOOKUP($C24,'S | 01 '!$C$6:$Q$49,Q$5,0) -> 0.37463741 | R24: =VLOOKUP($C24,'S | 01 '!$C$6:$Q$49,R$5,0) -> 0
C25: Flyr Inc | D25: Direct Investment | E25: =VLOOKUP($C25,'S | 01 '!$C$6:$Q$49,E$5,0) -> Unrealized | F25: =VLOOKUP($C25,'S | 01 '!$C$6:$Q$49,F$5,0) -> Sushil | G25: =VLOOKUP($C25,'S | 01 '!$C$6:$Q$49,G$5,0) -> Mozn | H25: =VLOOKUP($C25,'S | 01 '!$C$6:$Q$49,H$5,0) -> 2019 | I25: =VLOOKUP($C25,'S | 01 '!$C$6:$Q$49,I$5,0) -> B-1,2 Prefs | J25: =VLOOKUP($C25,'S | 01 '!$C$6:$Q$49,J$5,0) -> 0.085025485 | K25: =VLOOKUP($C25,'S | 01 '!$C$6:$Q$49,K$5,0) -> 10 | L25: =VLOOKUP($C25,'S | 01 '!$C$6:$Q$49,L$5,0) -> 10 | ... O25: =VLOOKUP($C25,'S | 01 '!$C$6:$Q$49,O$5,0) -> 27.11873 | P25: 68.1 | Q25: =VLOOKUP($C25,'S | 01 '!$C$6:$Q$49,Q$5,0) -> 3.711873 | R25: =VLOOKUP($C25,'S | 01 '!$C$6:$Q$49,R$5,0) -> 0 | S25: Flyr Warrantsa
C26: Mena Mobile Inc | D26: Direct Investment | E26: =VLOOKUP($C26,'S | 01 '!$C$6:$Q$49,E$5,0) -> Written-off | F26: =VLOOKUP($C26,'S | 01 '!$C$6:$Q$49,F$5,0) -> Elaine | G26: =VLOOKUP($C26,'S | 01 '!$C$6:$Q$49,G$5,0) -> Mozn | H26: =VLOOKUP($C26,'S | 01 '!$C$6:$Q$49,H$5,0) -> 2019 | I26: =VLOOKUP($C26,'S | 01 '!$C$6:$Q$49,I$5,0) -> B Prefs | J26: =VLOOKUP($C26,'S | 01 '!$C$6:$Q$49,J$5,0) -> 0.14 | K26: =VLOOKUP($C26,'S | 01 '!$C$6:$Q$49,K$5,0) -> 8 | L26: =VLOOKUP($C26,'S | 01 '!$C$6:$Q$49,L$5,0) -> 8 | ... O26: =VLOOKUP($C26,'S | 01 '!$C$6:$Q$49,O$5,0) -> -8 | P26: -8 | Q26: =VLOOKUP($C26,'S | 01 '!$C$6:$Q$49,Q$5,0) -> 0 | R26: =VLOOKUP($C26,'S | 01 '!$C$6:$Q$49,R$5,0) -> 0 | S26: Written Off
C27: Glass Earth Holdings LLC | D27: Debt Investment | E27: =VLOOKUP($C27,'S | 01 '!$C$6:$Q$49,E$5,0) -> Written-off | F27: =VLOOKUP($C27,'S | 01 '!$C$6:$Q$49,F$5,0) -> Marty | G27: =VLOOKUP($C27,'S | 01 '!$C$6:$Q$49,G$5,0) -> Mozn | H27: =VLOOKUP($C27,'S | 01 '!$C$6:$Q$49,H$5,0) -> 2019 | I27: =VLOOKUP($C27,'S | 01 '!$C$6:$Q$49,I$5,0) -> Promissory Note | J27: =VLOOKUP($C27,'S | 01 '!$C$6:$Q$49,J$5,0) -> n/a | K27: =VLOOKUP($C27,'S | 01 '!$C$6:$Q$49,K$5,0) -> 8 | L27: =VLOOKUP($C27,'S | 01 '!$C$6:$Q$49,L$5,0) -> 8 | ... O27: =VLOOKUP($C27,'S | 01 '!$C$6:$Q$49,O$5,0) -> -8 | P27: -8 | Q27: =VLOOKUP($C27,'S | 01 '!$C$6:$Q$49,Q$5,0) -> 0 | R27: =VLOOKUP($C27,'S | 01 '!$C$6:$Q$49,R$5,0) -> 0 | S27: =VLOOKUP($C27,'S | 01 '!$C$6:$Q$49,S$5,0) -> In Default
C28: Jollychic Holding Limited | D28: Direct Investment | E28: =VLOOKUP($C28,'S | 01 '!$C$6:$Q$49,E$5,0) -> Written-off | F28: =VLOOKUP($C28,'S | 01 '!$C$6:$Q$49,F$5,0) -> Elaine | G28: =VLOOKUP($C28,'S | 01 '!$C$6:$Q$49,G$5,0) -> Mozn | H28: =VLOOKUP($C28,'S | 01 '!$C$6:$Q$49,H$5,0) -> 2019 | I28: =VLOOKUP($C28,'S | 01 '!$C$6:$Q$49,I$5,0) -> C+ Prefs | J28: =VLOOKUP($C28,'S | 01 '!$C$6:$Q$49,J$5,0) -> 0.056999998 | K28: =VLOOKUP($C28,'S | 01 '!$C$6:$Q$49,K$5,0) -> 65 | L28: =VLOOKUP($C28,'S | 01 '!$C$6:$Q$49,L$5,0) -> 65 | ... O28: =VLOOKUP($C28,'S | 01 '!$C$6:$Q$49,O$5,0) -> -65 | P28: -65 | Q28: =VLOOKUP($C28,'S | 01 '!$C$6:$Q$49,Q$5,0) -> 0 | R28: =VLOOKUP($C28,'S | 01 '!$C$6:$Q$49,R$5,0) -> 0 | S28: =VLOOKUP($C28,'S | 01 '!$C$6:$Q$49,S$5,0) -> In Liquidation
K30: =SUM(K9:K28) -> 1005.2675 | L30: =SUM(L9:L28) -> 1001.7675 | M30: =SUM(M9:M28) -> 440.91298 | N30: =SUM(N9:N28) -> 516.03328 | O30: =N30+M30-L30 -> -44.821278 | P30: =SUM(P9:P28) -> 14.537198 | Q30: =(M30+N30)/L30 -> 0.95525781 | R30: =SUM(R9:R28) -> 3.5
C32: G42 Investments AI Holding RSC Ltd
C33: Honor Device Co Ltd | D33: Direct Investment | E33: =VLOOKUP($C33,'S | 01 '!$C$6:$Q$49,E$5,0) -> Realized | F33: =VLOOKUP($C33,'S | 01 '!$C$6:$Q$49,F$5,0) -> Elaine | G33: =VLOOKUP($C33,'S | 01 '!$C$6:$Q$49,G$5,0) -> G42 3 | H33: =VLOOKUP($C33,'S | 01 '!$C$6:$Q$49,H$5,0) -> 2022 | I33: =VLOOKUP($C33,'S | 01 '!$C$6:$Q$49,I$5,0) -> Equity-TBC | J33: =VLOOKUP($C33,'S | 01 '!$C$6:$Q$49,J$5,0) -> 0.018823528 | K33: =VLOOKUP($C33,'S | 01 '!$C$6:$Q$49,K$5,0) -> 800 | L33: =VLOOKUP($C33,'S | 01 '!$C$6:$Q$49,L$5,0) -> 800 | ... O33: =VLOOKUP($C33,'S | 01 '!$C$6:$Q$49,O$5,0) -> 2.8 | P33: 54.67 | Q33: =VLOOKUP($C33,'S | 01 '!$C$6:$Q$49,Q$5,0) -> 1.0035 | R33: =VLOOKUP($C33,'S | 01 '!$C$6:$Q$49,R$5,0) -> 0 | V33: G42
C34: DriveNets | D34: Direct Investment | E34: =VLOOKUP($C34,'S | 01 '!$C$6:$Q$49,E$5,0) -> Unrealized | F34: =VLOOKUP($C34,'S | 01 '!$C$6:$Q$49,F$5,0) -> Anton | G34: =VLOOKUP($C34,'S | 01 '!$C$6:$Q$49,G$5,0) -> G42 | H34: =VLOOKUP($C34,'S | 01 '!$C$6:$Q$49,H$5,0) -> 2022 | I34: =VLOOKUP($C34,'S | 01 '!$C$6:$Q$49,I$5,0) -> Equity-TBC | J34: =VLOOKUP($C34,'S | 01 '!$C$6:$Q$49,J$5,0) -> 0.11141914 | K34: =VLOOKUP($C34,'S | 01 '!$C$6:$Q$49,K$5,0) -> 300 | L34: =VLOOKUP($C34,'S | 01 '!$C$6:$Q$49,L$5,0) -> 300 | ... O34: =VLOOKUP($C34,'S | 01 '!$C$6:$Q$49,O$5,0) -> -95.4 | P34: 0 | Q34: =VLOOKUP($C34,'S | 01 '!$C$6:$Q$49,Q$5,0) -> 0.682 | R34: =VLOOKUP($C34,'S | 01 '!$C$6:$Q$49,R$5,0) -> 0 | S34: DN Warrants b
C35: vTv Therapeutics Inc. | D35: Direct Investment | E35: =VLOOKUP($C35,'S | 01 '!$C$6:$Q$49,E$5,0) -> Unrealized | F35: =VLOOKUP($C35,'S | 01 '!$C$6:$Q$49,F$5,0) -> Divyesh | G35: =VLOOKUP($C35,'S | 01 '!$C$6:$Q$49,G$5,0) -> G42 | H35: =VLOOKUP($C35,'S | 01 '!$C$6:$Q$49,H$5,0) -> 2022 | I35: =VLOOKUP($C35,'S | 01 '!$C$6:$Q$49,I$5,0) -> Ordinary Shares | J35: =VLOOKUP($C35,'S | 01 '!$C$6:$Q$49,J$5,0) -> 0.0021343582 | K35: =VLOOKUP($C35,'S | 01 '!$C$6:$Q$49,K$5,0) -> 24.53125 | L35: =VLOOKUP($C35,'S | 01 '!$C$6:$Q$49,L$5,0) -> 24.53125 | ... O35: =VLOOKUP($C35,'S | 01 '!$C$6:$Q$49,O$5,0) -> -19.945707 | P35: -1.348 | Q35: =VLOOKUP($C35,'S | 01 '!$C$6:$Q$49,Q$5,0) -> 0.18692658 | R35: =VLOOKUP($C35,'S | 01 '!$C$6:$Q$49,R$5,0) -> 0 | S35: vTv $30m milestn payment c | V35: Invested | W35: =L42 -> 1265.4048
C36: North Summit Capital Fund | D36: Fund Investment | E36: =VLOOKUP($C36,'S | 01 '!$C$6:$Q$49,E$5,0) -> Unrealized | F36: =VLOOKUP($C36,'S | 01 '!$C$6:$Q$49,F$5,0) -> Elaine | G36: =VLOOKUP($C36,'S | 01 '!$C$6:$Q$49,G$5,0) -> G42 Investments | H36: =VLOOKUP($C36,'S | 01 '!$C$6:$Q$49,H$5,0) -> 2020 | I36: =VLOOKUP($C36,'S | 01 '!$C$6:$Q$49,I$5,0) -> LP | J36: =VLOOKUP($C36,'S | 01 '!$C$6:$Q$49,J$5,0) -> n/a | K36: =VLOOKUP($C36,'S | 01 '!$C$6:$Q$49,K$5,0) -> 83.63035 | L36: =VLOOKUP($C36,'S | 01 '!$C$6:$Q$49,L$5,0) -> 83.27035 | ... O36: =VLOOKUP($C36,'S | 01 '!$C$6:$Q$49,O$5,0) -> -0.728618 | P36: -0.306 | Q36: =VLOOKUP($C36,'S | 01 '!$C$6:$Q$49,Q$5,0) -> 0.99124997 | R36: =VLOOKUP($C36,'S | 01 '!$C$6:$Q$49,R$5,0) -> 0.36 | V36: NAV | W36: =N42 -> 317.33719
C37: New Space Capital Fund I | D37: Fund Investment | E37: =VLOOKUP($C37,'S | 01 '!$C$6:$Q$49,E$5,0) -> Unrealized | F37: =VLOOKUP($C37,'S | 01 '!$C$6:$Q$49,F$5,0) -> Sushil | G37: =VLOOKUP($C37,'S | 01 '!$C$6:$Q$49,G$5,0) -> G42 Investments | H37: =VLOOKUP($C37,'S | 01 '!$C$6:$Q$49,H$5,0) -> 2020 | I37: =VLOOKUP($C37,'S | 01 '!$C$6:$Q$49,I$5,0) -> LP | J37: =VLOOKUP($C37,'S | 01 '!$C$6:$Q$49,J$5,0) -> n/a | K37: =VLOOKUP($C37,'S | 01 '!$C$6:$Q$49,K$5,0) -> 24.886432 | L37: =VLOOKUP($C37,'S | 01 '!$C$6:$Q$49,L$5,0) -> 15.922439 | ... O37: =VLOOKUP($C37,'S | 01 '!$C$6:$Q$49,O$5,0) -> 6.7719935 | P37: 5.445 | Q37: =VLOOKUP($C37,'S | 01 '!$C$6:$Q$49,Q$5,0) -> 1.4253113 | R37: =VLOOKUP($C37,'S | 01 '!$C$6:$Q$49,R$5,0) -> 11.89512 | V37: Gain | W37: =O42 -> -108.6287
C38: New Space Capital GP Com SCSp | D38: Fund Investment | E38: =VLOOKUP($C38,'S | 01 '!$C$6:$Q$49,E$5,0) -> Unrealized | F38: =VLOOKUP($C38,'S | 01 '!$C$6:$Q$49,F$5,0) -> Sushil | G38: =VLOOKUP($C38,'S | 01 '!$C$6:$Q$49,G$5,0) -> G42 Investments | H38: =VLOOKUP($C38,'S | 01 '!$C$6:$Q$49,H$5,0) -> 2023 | I38: =VLOOKUP($C38,'S | 01 '!$C$6:$Q$49,I$5,0) -> LP | J38: =VLOOKUP($C38,'S | 01 '!$C$6:$Q$49,J$5,0) -> n/a | K38: =VLOOKUP($C38,'S | 01 '!$C$6:$Q$49,K$5,0) -> 2.7058824 | L38: =VLOOKUP($C38,'S | 01 '!$C$6:$Q$49,L$5,0) -> 2.7058824 | ... O38: =VLOOKUP($C38,'S | 01 '!$C$6:$Q$49,O$5,0) -> 0.56973286 | P38: 0 | Q38: =VLOOKUP($C38,'S | 01 '!$C$6:$Q$49,Q$5,0) -> 1.2105534 | R38: =VLOOKUP($C38,'S | 01 '!$C$6:$Q$49,R$5,0) -> 0 | V38: YTD Gains | W38: =O42-P42 -> -165.5187
C39: Sinovation Disrupt Fund, L.P. | D39: Fund Investment | E39: =VLOOKUP($C39,'S | 01 '!$C$6:$Q$49,E$5,0) -> Realized | F39: =VLOOKUP($C39,'S | 01 '!$C$6:$Q$49,F$5,0) -> Elaine | G39: =VLOOKUP($C39,'S | 01 '!$C$6:$Q$49,G$5,0) -> G42 Investments | H39: =VLOOKUP($C39,'S | 01 '!$C$6:$Q$49,H$5,0) -> 2020 | I39: =VLOOKUP($C39,'S | 01 '!$C$6:$Q$49,I$5,0) -> LP | J39: =VLOOKUP($C39,'S | 01 '!$C$6:$Q$49,J$5,0) -> n/a | K39: =VLOOKUP($C39,'S | 01 '!$C$6:$Q$49,K$5,0) -> 50 | L39: =VLOOKUP($C39,'S | 01 '!$C$6:$Q$49,L$5,0) -> 24.959693 | ... O39: =VLOOKUP($C39,'S | 01 '!$C$6:$Q$49,O$5,0) -> 0.44382835 | P39: -1.265 | Q39: =VLOOKUP($C39,'S | 01 '!$C$6:$Q$49,Q$5,0) -> 1.0177818 | R39: =VLOOKUP($C39,'S | 01 '!$C$6:$Q$49,R$5,0) -> 0 | V39: IRR | W39: =#REF! -> #REF!
C40: Acies Investments Fund I, L.P. | D40: Fund Investment | E40: =VLOOKUP($C40,'S | 01 '!$C$6:$Q$49,E$5,0) -> Unrealized | F40: =VLOOKUP($C40,'S | 01 '!$C$6:$Q$49,F$5,0) -> Divyesh | G40: =VLOOKUP($C40,'S | 01 '!$C$6:$Q$49,G$5,0) -> G42 Investments | H40: =VLOOKUP($C40,'S | 01 '!$C$6:$Q$49,H$5,0) -> 2021 | I40: =VLOOKUP($C40,'S | 01 '!$C$6:$Q$49,I$5,0) -> LP | J40: =VLOOKUP($C40,'S | 01 '!$C$6:$Q$49,J$5,0) -> 0.33 | K40: =VLOOKUP($C40,'S | 01 '!$C$6:$Q$49,K$5,0) -> 17.1125 | L40: =VLOOKUP($C40,'S | 01 '!$C$6:$Q$49,L$5,0) -> 14.015137 | ... O40: =VLOOKUP($C40,'S | 01 '!$C$6:$Q$49,O$5,0) -> -3.1399255 | P40: -0.306 | Q40: =VLOOKUP($C40,'S | 01 '!$C$6:$Q$49,Q$5,0) -> 0.77596185 | R40: =VLOOKUP($C40,'S | 01 '!$C$6:$Q$49,R$5,0) -> 3.0973625 | S40: 9.9% GP | Anchorf
V41: =O30-P30 -> -59.358477
K42: =SUM(K33:K40) -> 1302.8664 | L42: =SUM(L33:L40) -> 1265.4048 | M42: =SUM(M33:M40) -> 839.43886 | N42: =SUM(N33:N40) -> 317.33719 | O42: =N42+M42-L42 -> -108.6287 | P42: =SUM(P33:P40) -> 56.89 | Q42: =(M42+N42)/L42 -> 0.91415498 | R42: =SUM(R33:R40) -> 15.352483 | S42: =N42+M42-L42 -> -108.6287 | V42: =K42-L42 -> 37.461663
V43: =O42-P42 -> -165.5187
C44: G42 Capital SPV RSC Ltd
C45: Life Biosciences LLC | D45: Direct Investment | E45: =VLOOKUP($C45,'S | 01 '!$C$6:$Q$49,E$5,0) -> Unrealized | F45: =VLOOKUP($C45,'S | 01 '!$C$6:$Q$49,F$5,0) -> Divyesh | G45: =VLOOKUP($C45,'S | 01 '!$C$6:$Q$49,G$5,0) -> G42 Capital | H45: =VLOOKUP($C45,'S | 01 '!$C$6:$Q$49,H$5,0) -> 2024 | I45: =VLOOKUP($C45,'S | 01 '!$C$6:$Q$49,I$5,0) -> Convertible Note | J45: =VLOOKUP($C45,'S | 01 '!$C$6:$Q$49,J$5,0) -> n/a | K45: =VLOOKUP($C45,'S | 01 '!$C$6:$Q$49,K$5,0) -> 20 | L45: =VLOOKUP($C45,'S | 01 '!$C$6:$Q$49,L$5,0) -> 20 | ... O45: =VLOOKUP($C45,'S | 01 '!$C$6:$Q$49,O$5,0) -> 0 | P45: 0 | Q45: =VLOOKUP($C45,'S | 01 '!$C$6:$Q$49,Q$5,0) -> 1 | R45: =VLOOKUP($C45,'S | 01 '!$C$6:$Q$49,R$5,0) -> 0
C46: Verses AI Inc | D46: Direct Investment | E46: =VLOOKUP($C46,'S | 01 '!$C$6:$Q$49,E$5,0) -> Unrealized | F46: =VLOOKUP($C46,'S | 01 '!$C$6:$Q$49,F$5,0) -> Divyesh | G46: =VLOOKUP($C46,'S | 01 '!$C$6:$Q$49,G$5,0) -> G42 Capital | H46: =VLOOKUP($C46,'S | 01 '!$C$6:$Q$49,H$5,0) -> 2024 | I46: =VLOOKUP($C46,'S | 01 '!$C$6:$Q$49,I$5,0) -> Convertible Debenture | J46: =VLOOKUP($C46,'S | 01 '!$C$6:$Q$49,J$5,0) -> n/a | K46: =VLOOKUP($C46,'S | 01 '!$C$6:$Q$49,K$5,0) -> 10 | L46: =VLOOKUP($C46,'S | 01 '!$C$6:$Q$49,L$5,0) -> 10 | ... O46: =VLOOKUP($C46,'S | 01 '!$C$6:$Q$49,O$5,0) -> 0 | P46: 0 | Q46: =VLOOKUP($C46,'S | 01 '!$C$6:$Q$49,Q$5,0) -> 1 | R46: =VLOOKUP($C46,'S | 01 '!$C$6:$Q$49,R$5,0) -> 0 | S46: =VLOOKUP($C46,'S | 01 '!$C$6:$Q$49,S$5,0) -> Revenue linked RSUs
K48: =SUM(K45:K46) -> 30 | L48: =SUM(L45:L46) -> 30 | M48: =SUM(M45:M46) -> 0 | N48: =SUM(N45:N46) -> 30 | O48: =SUM(O45:O46) -> 0 | P48: =SUM(P45:P46) -> 0 | Q48: =(M48+N48)/L48 -> 1 | R48: =SUM(R45:R46) -> 0
C50: Core42 Holding RSC Ltd
C51: School Hack (AIREV Holding Limited) | D51: Direct Investment | E51: =VLOOKUP($C51,'S | 01 '!$C$6:$Q$49,E$5,0) -> Unrealized | F51: =VLOOKUP($C51,'S | 01 '!$C$6:$Q$49,F$5,0) -> Camillo | G51: =VLOOKUP($C51,'S | 01 '!$C$6:$Q$49,G$5,0) -> Core42 5 | H51: =VLOOKUP($C51,'S | 01 '!$C$6:$Q$49,H$5,0) -> 2024 | I51: =VLOOKUP($C51,'S | 01 '!$C$6:$Q$49,I$5,0) -> Preferred Shares | J51: =VLOOKUP($C51,'S | 01 '!$C$6:$Q$49,J$5,0) -> 0.25 | K51: =VLOOKUP($C51,'S | 01 '!$C$6:$Q$49,K$5,0) -> 2.75 | L51: =VLOOKUP($C51,'S | 01 '!$C$6:$Q$49,L$5,0) -> 2.5 | ... O51: =VLOOKUP($C51,'S | 01 '!$C$6:$Q$49,O$5,0) -> 0 | P51: 0 | Q51: =VLOOKUP($C51,'S | 01 '!$C$6:$Q$49,Q$5,0) -> 1 | R51: =VLOOKUP($C51,'S | 01 '!$C$6:$Q$49,R$5,0) -> 0.25 | S51: Cloud Creditg
K53: =SUM(K51) -> 2.75 | L53: =SUM(L51) -> 2.5 | M53: =SUM(M51) -> 0 | N53: =SUM(N51) -> 2.5 | O53: =SUM(O51) -> 0 | P53: =SUM(P51) -> 0 | Q53: =(M53+N53)/L53 -> 1 | R53: =SUM(R51) -> 0.25
K55: =K30+K42+K48+K53 -> 2340.884 | L55: =L30+L42+L48+L53 -> 2299.6723 | M55: =M30+M42+M48+M53 -> 1280.3518 | N55: =N30+N42+N48+N53 -> 865.87048 | O55: =O30+O42+O48+O53 -> -153.44997 | P55: =P30+P42+P48+P53 -> 71.427198 | Q55: =(M55+N55)/L55 -> 0.93327311 | R55: =R30+R42+R48+R53 -> 19.102483 | V55: =SUM(M33:N35)-SUM(L33:L35) -> -112.54571
V56: =SUM(M36:N40)-SUM(L36:L40) -> 3.9170112
V57: =K42-L42 -> 37.461663
I58: Checks: | K58: =K55='S | 01 '!J49 -> TRUE | L58: =ROUND(L55,3)=ROUND('S | 01 '!K49,3) -> TRUE | M58: =M55='S | 01 '!M49 -> TRUE | N58: =N55='S | 01 '!N49 -> FALSE | O58: =ROUND(O55,3)=ROUND('S | 01 '!O49,3) -> TRUE | R58: =R30+R53='S | 01 '!L33 -> TRUE
C59: For Notes, refer to Summary | 01
C60: Position Exited or written off are highlighted

Sheet S | 03
C2: As of date | D2: ='S | 01 '!D2 -> 45473
P3: n/a refers to information not available
C6: Deals | D6: Status | E6: Lead | F6: Investing Entity | G6: Investing Entity (Legal Entity Name) | H6: Nature of Investing Entity | I6: Investments Tax Implication tax note 1 | J6: Instrument | K6: Listed / Unlisted | L6: Website link | M6: Pitchbook link | N6: Jurisdiction | O6: % | P6: Upside (Warrants, Milestone payments, ) | Q6: For Comments Refer to Note
C8: Direct Investments
C9: Jollychic Holding Limited | D9: Written-off | E9: Elaine | F9: Mozn | G9: Mozn Holding RSC Ltd | H9: Potential QFZP tax note 2 | I9: If qualifies for QFZP and hold the investment >= 12m, income/loss from the investee supposed to suject to 0% Corporate tax rate for Investing Entity | J9: C+ Prefs | L9: link | M9: link | N9: Cayman Islands | O9: 0.056999998 | Q9: 1
C10: Mena Mobile Inc | D10: Unrealized | E10: Elaine | F10: Mozn | G10: Mozn Holding RSC Ltd | H10: Potential QFZP tax note 2 | I10: If qualifies for QFZP and hold the investment >= 12m, income/loss from the investee supposed to suject to 0% Corporate tax rate for Investing Entity | J10: B Prefs | L10: link | M10: link | N10: Cayman Islands | O10: 0.14 | Q10: 2
C11: Flyr Inc | D11: Unrealized | E11: Sushil | F11: Mozn | G11: Mozn Holding RSC Ltd | H11: Potential QFZP tax note 2 | I11: If qualifies for QFZP and hold the investment >= 12m, income/loss from the investee supposed to suject to 0% Corporate tax rate for Investing Entity | J11: B-1,2 Prefs | L11: link | M11: link | N11: Delaware Corporation | O11: 0.085025485 | P11: Flyr Warrantsa | Q11: 3
C12: Esyasoft Holding | D12: Realized | E12: Sushil | F12: Mozn | G12: Mozn Holding RSC Ltd | H12: Potential QFZP tax note 2 | I12: If qualifies for QFZP and hold the investment >= 12m, income/loss from the investee supposed to suject to 0% Corporate tax rate for Investing Entity | J12: Convertible Note | L12: link | M12: n/a | N12: DIFC | O12: n/a | Q12: 4
C13: Beyond Limits | D13: Unrealized | E13: Divyesh | F13: Mozn | G13: Mozn Holding RSC Ltd | H13: Potential QFZP tax note 2 | I13: If qualifies for QFZP and hold the investment >= 12m, income/loss from the investee supposed to suject to 0% Corporate tax rate for Investing Entity | J13: C Prefs | L13: link | M13: link | N13: Delaware Corporation | O13: 0.097965107 | Q13: 5
C14: ONT plc | D14: Unrealized | E14: Divyesh | F14: Mozn | G14: Mozn Holding RSC Ltd | H14: Potential QFZP tax note 2 | I14: If qualifies for QFZP and hold the investment >= 12m, income/loss from the investee supposed to suject to 0% Corporate tax rate for Investing Entity | J14: Ordinary Shares | K14: Listed | L14: link | M14: link | N14: UK | O14: 0.051651565 | Q14: 6
C15: Heygears | D15: Unrealized | E15: Elaine | F15: Mozn | G15: Mozn Holding RSC Ltd | H15: Potential QFZP tax note 2 | I15: If qualifies for QFZP and hold the investment >= 12m, income/loss from the investee supposed to suject to 0% Corporate tax rate for Investing Entity | J15: Registered Capital | L15: link | M15: link | N15: PRC | O15: 0.1438 | Q15: 7
C16: Jysan Technologies | D16: Realized | E16: Sushil | F16: Mozn aa | G16: QAZ42 Investment SPV RSC Ltd | H16: Realized | I16: Realized | J16: A (Ordinary Shares) | L16: link | M16: n/a | N16: UK | O16: 0.03 | Q16: 8
C17: Cerebras Systems Inc | D17: Unrealized | E17: Ignasi | F17: Mozn | G17: Mozn Holding RSC Ltd | H17: Potential QFZP tax note 2 | I17: If qualifies for QFZP and hold the investment >= 12m, income/loss from the investee supposed to suject to 0% Corporate tax rate for Investing Entity | J17: F Prefs | L17: link | M17: link | N17: Delaware Corporation | O17: 0.0091172068 | Q17: 9
C18: Endless Studios LLC | D18: Unrealized | E18: Sushil | F18: Mozn | G18: Mozn Holding RSC Ltd | H18: Potential QFZP tax note 2 | I18: To be monitored (see Note 0) | J18: A Pref Units | L18: link | M18: link | N18: Delaware Corporation | O18: 0.16080402 | Q18: 10
C19: Instadeep Limited | D19: Realized | E19: Ignasi | F19: Mozn | G19: Mozn Holding RSC Ltd | H19: Potential QFZP tax note 2 | I19: If qualifies for QFZP and hold the investment >= 12m, income/loss from the investee supposed to suject to 0% Corporate tax rate for Investing Entity | J19: B Prefs | L19: link | M19: link | N19: UK | O19: 0.011489406 | Q19: 11
C20: X-fusion | D20: Realized | E20: Elaine | F20: Mozn bb | G20: Enterprise Connection Holding RSC Ltd | H20: Non-QFZP | I20: pending | J20: Equity-TBC | L20: link | M20: link | N20: PRC | O20: 0.051 | Q20: 12
C21: DriveNets | D21: Unrealized | E21: Anton | F21: G42 | G21: D2 Investments RSC Ltd | H21: Non-QFZP | I21: Should qualify for Participation interest | J21: Equity-TBC | L21: link | M21: link | N21: Israeli Pvt Company | O21: 0.11141914 | P21: DN Warrants b | Q21: 13
C22: vTv Therapeutics Inc. | D22: Unrealized | E22: Divyesh | F22: G42 | G22: G42 Investments AI Holdings RSC Ltd | H22: Potential QFZP tax note 2 | I22: To be monitored (see Note 0) | J22: Ordinary Shares | K22: Listed | L22: link | M22: link | N22: Delaware Corporation | O22: 0.0022129091 | P22: vTv $30m milestn payment c | Q22: 14
C23: Honor Device Co Ltd | D23: Realized | E23: Elaine | F23: G42 cc | G23: Smart Interaction1 Holding SPV RSC LTD | H23: pending | I23: pending | J23: Equity-TBC | L23: link | M23: link | N23: PRC | O23: 0.018823528 | Q23: 15
C24: Applied AI Corporation Limited | D24: Unrealized | E24: Divyesh | F24: Mozn | G24: Mozn Holding RSC Ltd | H24: Potential QFZP tax note 2 | I24: To be monitored (see Note 0) | J24: Convertible Note | L24: link | M24: link | N24: ADGM | O24: n/a | Q24: 16
C25: eSpace | D25: Unrealized | E25: Anton | F25: Mozn dd | G25: Constellation Investments SPV RSC Ltd (previously Smart Interaction5 Holding SPV RSC Ltd) | H25: Non-QFZP | I25: Taxable for only hold 2.8% of SAFE note in eSpace. | J25: B Prefs | L25: link | M25: link | N25: Delaware Corporation | O25: 0.027864956 | Q25: 17
C26: Tools for Humanity Corporation | D26: Unrealized | E26: Divyesh | F26: Mozn | G26: Mozn Holding RSC Ltd | H26: Potential QFZP tax note 2 | I26: To be monitored (see Note 0) | J26: C Prefs | L26: link | M26: link | N26: Delaware Corporation | O26: 0.0062621983 | Q26: 24
C27: WLD Tokens | D27: Unrealized | E27: Divyesh | F27: Mozn | G27: Mozn Holding RSC Ltd | H27: Potential QFZP tax note 2 | I27: To be monitored (see Note 0) | J27: Tokens | L27: link | M27: Coinbase | N27: DAO | Cayman Islands | O27: 0.00625 | Q27: 25 | T27: Preferred Shares
C28: E-line Ventures LLC | D28: Unrealized | E28: Sushil | F28: Mozn | G28: Mozn Holding RSC Ltd | H28: Potential QFZP tax note 2 | I28: To be monitored (see Note 0) | J28: B Prefs | L28: link | M28: link | N28: New Jersey, USA | O28: ='6. %'!F28 -> 0.11483736 | Q28: 26 | T28: B Prefs
C29: School Hack (AIREV Holding Limited) | D29: Unrealized | E29: Camillo | F29: Core42 | G29: Core42 Investments 1 SPV RSC LTD | H29: Potential QFZP tax note 2 | I29: To be monitored (see Note 0) | J29: Preferred Shares | L29: link | M29: NA | N29: ADGM | O29: 0.25 | Q29: 27
C30: Life Biosciences LLC | D30: Unrealized | E30: Divyesh | F30: ='S | 01 '!F30 -> G42 Capital | G30: Expansion Project Technologies Holding 7 SPV RSC Ltd | H30: Potential QFZP tax note 2 | I30: To be monitored (see Note 0) | J30: Convertible Note | L30: link | M30: link | N30: Delaware Corporation | O30: n/a | Q30: 28
C31: Verses AI Inc | D31: Unrealized | E31: Divyesh | F31: ='S | 01 '!F31 -> G42 Capital | G31: Expansion Project Technologies Holding 8 SPV RSC Ltd | H31: Potential QFZP tax note 2 | I31: To be monitored (see Note 0) | J31: Convertible Debenture | L31: link | M31: link | N31: British Columbia | O31: n/a
C35: Debt Investments
C36: Glass Earth Holdings LLC | D36: In default | F36: Mozn | G36: G42 Investments AI Holdings RSC Ltd | H36: Potential QFZP tax note 2 | I36: not equity investment, taxable | J36: Promissory Note | L36: n/a | M36: n/a | N36: n/a | Q36: 16
C37: Mena Mobile Inc (Debt) | D37: In default | E37: Elaine | F37: Mozn | G37: Mozn Holding RSC Ltd | H37: Potential QFZP tax note 2 | I37: not equity investment, taxable | J37: Loan | L37: link | M37: link | N37: =N10 -> Cayman Islands | Q37: 17
C38: Esyasoft Holding (Debt) | D38: Unrealized | E38: Sushil | F38: Mozn | G38: Mozn Holding RSC Ltd | H38: Potential QFZP tax note 2 | I38: not equity investment, taxable | J38: Loan | L38: link | M38: n/a | N38: =N12 -> DIFC | Q38: 18
C41: Funds Investments
C42: New Space Capital Fund I | D42: Unrealized | E42: Sushil | F42: G42 | G42: G42 Investments AI Holdings RSC Ltd | H42: Potential QFZP tax note 2 | I42: If qualifies for QFZP and hold the investment >= 12m, income/loss from the investee supposed to suject to 0% Corporate tax rate for Investing Entity | J42: LP | L42: link | M42: link | N42: Luxembourg | O42: 0.22044082 | Q42: 19
C43: New Space Capital GP Com SCSp | D43: Unrealized | E43: Sushil | F43: G42 | G43: G42 Investments AI Holdings RSC Ltd | H43: Potential QFZP tax note 2 | I43: If qualifies for QFZP and hold the investment >= 12m, income/loss from the investee supposed to suject to 0% Corporate tax rate for Investing Entity | J43: GP | L43: link | M43: link | N43: Luxembourg | O43: 0.02016129 | Q43: 20
C44: North Summit Capital Fund | D44: Unrealized | E44: Elaine | F44: G42 | G44: Galbot Holding RSC Ltd | H44: Non-QFZP | I44: pending | J44: LP | L44: n/a | M44: link | N44: Cayman Islands | O44: 0.995 | Q44: 21
C45: Sinovation Disrupt Fund, L.P. | D45: Unrealized | E45: Elaine | F45: G42 | G45: G42 Investments AI Holdings RSC Ltd | H45: Potential QFZP tax note 2 | I45: If qualifies for QFZP and hold the investment >= 12m, income/loss from the investee supposed to suject to 0% Corporate tax rate for Investing Entity | J45: LP | L45: link | M45: link | N45: Cayman Islands | O45: 0.1006609 | Q45: 22
C46: Acies Investments Fund I, L.P. | D46: Unrealized | E46: Divyesh | F46: G42 | G46: G42 Investments AI Holdings RSC Ltd | H46: Potential QFZP tax note 2 | I46: If qualifies for QFZP and hold the investment >= 12m, income/loss from the investee supposed to suject to 0% Corporate tax rate for Investing Entity | J46: LP | L46: link | M46: link | N46: Delaware LLC | O46: 0.33333333 | P46: 9.9% GP | Anchor e | Q46: 23
B50: Notes:
B51: 0 | C51: General | D51: If qualifies for QFZP and hold the investment >= 12m, income/loss from the investee supposed to suject to 0% Corporate tax rate for Investing Entity. Currently we have the contribution made in June 2023 need to be monitored
B52: 1 | C52: Jollychic | D52: During 2021, Jollychic Holding Ltd has filed for its liquidation. Therefore, investment is considered to be fully impaired in Dec 21.
B53: 2 | C53: Mena Mobile | D53: Investment is written off based on the 3rd party valuation report
B54: 3 | C54: Flyr | D54: Within five years of the Initial Closing, for every USD 1mn of Qualifying Revenue generated, Flyr will issue, at no additional charge, 194,477 B-1 Prefs in the name of G42, up to a maximum of 1,264,100 B-1 Prefs.
B55: 4 | C55: Esyasoft Holding | D55: Exited
B56: 5 | C56: Beyond Limits | D56: Business targeting raising funds by the end of FY2022
B57: 6 | C57: ONT plc | D57: Listed
B58: 7 | C58: Heygears | D58: Mozn's holding is RMB 4,753,356.29 of the Registered Capital.
B59: 8 | C59: Jysan Technologies | D59: - 50% of the investment has been financed by profit sharing loan. - Further, in case of exit of G42’s investment, 50% of the sale proceeds shall be paid to the lender as full and final settlement of the outstanding liability - Exit for this investment is under process. Buyback agreement is pending for signature internally. (Relevant documents to be perused by the consolidation / reporting team for details and corresponding implications, if any) - Dividend receivable amounting to US$ 3.2 m will be waived upon exit of this investment
B60: 9 | C60: Cerebras Systems Inc | D60: The investment is currently undergoing a CFIUS review.
B61: 10 | C61: Endless Studios LLC
B62: 11 | C62: Instadeep Limited | D62: Fully Exited on 31st July with 1.5x returns.
B63: 12 | C63: X-fusion | D63: RMB 80 Mn of Registered Capital for RMB 5.7 Bn
B64: 13 | C64: Drivenets | D64: Share warrants excisable upon the achievement of target revenue of clients by referred G42. The milestones of each target revenue and respective conversion were stated in the Term Sheet.
B65: 14 | C65: vTv Therapeutics : | D65: Potential issuance of US$ 30 million in additional shares of Class A Common Stock to G42 Investments (or in cash, at the option of G42 Investments) if FDA approval is received for the marketing and the sale of a pharmaceutical product containing TTP399
B66: 15 | C66: Honor | D66: Invested in Q3 2022; During Dec 22, $250m was offloaded to another investor at cost
B67: 16 | C67: Glass Earth Holdings LLC | D67: Written off. Debt security of Glass Earth issued in 2019 were fully provided for.
B68: 17 | C68: Mena Mobile (Debt) | D68: In liquidation
B69: 18 | C69: Esyasoft Holding (Debt) | D69: Outstanding
B70: 19 | C70: New Space Capital Fund I | D70: G42 negotiated conversion of €2.3m GP investment into LP investment to vote in favor of new LP proposal.
B71: 20 | C71: New Space Capital SCSp | D71: Ibid
B72: 21 | C72: North Summit Capital | D72: Portfolio Exit Plan in Progress
B73: 22 | C73: Sinovation Disrupt Fund | D73: Expect valuation to rise as some of its portfolio companies are in the market to raise new funds
B74: 23 | C74: Acies Investments Fund I, LP
B75: 24 | C75: Tools for Humanity Corporation | D75: Additional token warrants (for 62.5 million Tokens) for a consideration of $5,875.00. Additional provision for c$2K (the warrant price) kept for exercising the warrant rights.
B76: 25 | C76: WLD Tokens | D76: Received 62.5M Tokens as of Jul'23
B77: 26 | C77: E-line Ventures LLC
B78: 27 | C78: School Hack (AIREV Holding Limited) | D78: Invested via Core42
B79: 28 | C79: Life Biosciences LLC | D79: Invested via G42 Capital
C81: Additional Upside Section:
C82: a) Flyr: For every $1m of revenue, 194,477 shares, capped at 1,264,1000 (B-1) shares shall be issued to Mozn
C83: b) DriveNets: Share warrants exercisable upon the achievement of target revenue of clients referred by G42, and corresponding milestones
C84: c) vTv Therapeutics: Potential issuance of $30m in additional shares, if FDA approval received for the drug TTP399
C85: d) Tools for Humanity Corporation: Additional token warrants issued for acquiring 62.5M Tokens for $5,875.00. Additional provision for c$2K (the warrant price) kept for exercising the warrant rights
C86: e) Acies Investments Fund I LP: Being the Anchor investor, entitled to 9.9% of the aggregate carried interest earned by the GP
C88: References:
C89: G42 refers to G42 Investments AI Holding RSC Ltd
C90: Mozn refers to Mozn Holding RSC Ltd
C91: PRC refers to People's Republic of China
C92: aa Invested via QAZ42 Investment SPV RSC Ltd (QAZ42)
C93: bb Invested via Enterprise Connection Holding RSC Ltd (Enterprise Connection)
... C100: 2 Group is currently working on the process to make Mozn Holding RSC Ltd and G42 Investments AI Holdings RSC Ltd be qualified to the QFZP requirements.

Sheet NAV
B2: NAV Date | C2: ='S | 01 '!D2 -> 45473
B5: Investments | C5: Investing Entity | D5: Instrument | E5: Carrying Value | F5: Current Shares/Units | H5: Comment | J5: Date of Update | K5: 14 Apr 2024
E6: USD, Million | F6: # | G6: USD | J6: N A V R E P O R T I N G M A R 2 0 2 4 | N6: A R D E N T E S T I M A T E S M A R 2 0 2 4
E7: ="NAV | "& TEXT(C2,"dd")&" "&TEXT(C2,"mmm")&" "&TEXT(C2,"yyyy") -> NAV | 30 Jun 2024 | G7: ="PPS |" & TEXT(C2,"dd")&" "&TEXT(C2,"mmm")&" "&TEXT(C2,"yyyy") -> PPS |30 Jun 2024 | J7: Name | K7: Carrying Value, Reporting Feb 23 | L7: Carrying Value, Revised Mar 23 | M7: Delta | N7: Carrying Value as per Ardent (as of Dec 23) | O7: Low | P7: High | Q7: Average | R7: Change | S7: Rationale for Price Change
B9: Direct Investments | J9: Drive Nets | K9: 300 | L9: =Q9 -> 204.6 | M9: =L9-K9 -> -95.4 | N9: 300 | O9: 187.6 | P9: 221.6 | Q9: =AVERAGE(O9:P9) -> 204.6 | R9: =Q9-N9 -> -95.4 | S9: marked down
B10: ='S | 01 '!C9 -> Jollychic Holding Limited | C10: ='S | 01 '!F9 -> Mozn | D10: ='S | 01 '!H9 -> C+ Prefs | E10: =F10*G10*10^-6 -> 0 | F10: =VLOOKUP(B10,'6. %'!$C$6:$I$40,2,0) -> 13458655 | H10: In liquidation | J10: Flyr | K10: 78.1 | L10: =Q10 -> 62.9 | M10: =L10-K10 -> -15.2 | N10: 80.3 | O10: 56.9 | P10: 68.9 | Q10: =AVERAGE(O10:P10) -> 62.9 | R10: =Q10-N10 -> -17.4 | S10: marked down
B11: ='S | 01 '!C10 -> Mena Mobile Inc | C11: ='S | 01 '!F10 -> Mozn | D11: ='S | 01 '!H10 -> B Prefs | E11: 0 | F11: =VLOOKUP(B11,'6. %'!$C$6:$I$40,2,0) -> 21419829 | H11: As per 3rd Party | Ardent Estimates | Equity written off | J11: Beyond Limits | K11: 91 | L11: =Q11 -> 73.8 | M11: =L11-K11 -> -17.2 | N11: 102.1 | O11: 66.2 | P11: 81.4 | Q11: =AVERAGE(O11:P11) -> 73.8 | R11: =Q11-N11 -> -28.3 | S11: marked down
B12: ='S | 01 '!C11 -> Flyr Inc | C12: ='S | 01 '!F11 -> Mozn | D12: ='S | 01 '!H11 -> B-1,2 Prefs | E12: =F12*G12*10^-6 -> 37.11873 | F12: =VLOOKUP(B12,'6. %'!$C$6:$I$40,2,0) -> 5205482 | G12: 7.1307 | H12: As per the recent fund raise completed in Dec 23 | J12: Worldcoin | K12: 15 | L12: =Q12 -> 161.9 | M12: =L12-K12 -> 146.9 | N12: =5.9*10^-3 -> 0.0059 | Q12: 161.9 | R12: =Q12-N12 -> 161.8941 | S12: marked up
B13: ='S | 01 '!C12 -> Esyasoft Holding | C13: ='S | 01 '!F12 -> Mozn | D13: ='S | 01 '!H12 -> Convertible Note | E13: 0 | F13: =VLOOKUP(B13,'6. %'!$C$6:$I$40,2,0) -> n/a | H13: Exited at $5m (10th May) | Residual value = 0
B14: ='S | 01 '!C13 -> Beyond Limits | C14: ='S | 01 '!F13 -> Mozn | D14: ='S | 01 '!H13 -> C Prefs | E14: =L11 -> 73.8 | F14: =VLOOKUP(B14,'6. %'!$C$6:$I$40,2,0) -> 17670202 | G14: 5.15 | H14: Marked down as per Ardent Estimates as of Dec 23
B15: ='S | 01 '!C14 -> ONT plc | C15: ='S | 01 '!F14 -> Mozn | D15: ='S | 01 '!H14 -> Ordinary Shares | E15: =F15*G15*10^-6 -> 53.000051 | F15: =VLOOKUP(B15,'6. %'!$C$6:$I$40,2,0) -> 44328120 | G15: =K18*K20 -> 1.1956305 | H15: Listed & marked to market
B16: ='S | 01 '!C15 -> Heygears | C16: ='S | 01 '!F15 -> Mozn | D16: ='S | 01 '!H15 -> Registered Capital | E16: =K34/1000000 -> 149.39859 | F16: ='CF (Equity, Debt)'!J20 -> 3565017.2 | H16: Adjusted for currency. Valued at the recent round | J16: Updated as on: | K16: =C2 -> 45473
B17: ='S | 01 '!C16 -> Jysan Technologies | C17: ='S | 01 '!F16 -> Mozn 1 | D17: ='S | 01 '!H16 -> A (Ordinary Shares) | E17: 0 | F17: =VLOOKUP(B17,'6. %'!$C$6:$I$40,2,0) -> 7959497 | G17: =E17*10^6/F17 -> 0 | H17: Exited at $24.5m | L17: source
B18: ='S | 01 '!C17 -> Cerebras Systems Inc | C18: ='S | 01 '!F17 -> Mozn | D18: ='S | 01 '!H17 -> F Prefs | E18: =F18*G18*10^-6 -> 21.135483 | F18: =VLOOKUP(B18,'6. %'!$C$6:$I$40,2,0) -> 1441711 | G18: 14.66 | H18: Held at cost | J18: ONT Share price | K18: 0.946 | L18: link
B19: ='S | 01 '!C18 -> Endless Studios LLC | C19: ='S | 01 '!F18 -> Mozn | D19: ='S | 01 '!H18 -> A Pref Units | E19: =-'CF (Equity, Debt)'!E23-'CF (Equity, Debt)'!E41 -> 8 | F19: =VLOOKUP(B19,'6. %'!$C$6:$I$40,2,0) -> 8000000 | H19: Held at cost | J19: VTVT Share price | K19: 17.66 | L19: link
B20: ='S | 01 '!C19 -> Instadeep Limited | C20: ='S | 01 '!F19 -> Mozn | D20: ='S | 01 '!H19 -> B Prefs | E20: =-'CF (Equity, Debt)'!E24*G20 -> 0 | F20: =VLOOKUP(B20,'6. %'!$C$6:$I$40,2,0) -> 33267 | G20: 0 | H20: Exited at 1.56X | Residual Value = 0 | J20: GBP USD | K20: 1.26388 | L20: xe.com
B21: ='S | 01 '!C20 -> X-fusion | C21: ='S | 01 '!F20 -> Mozn 2 | D21: ='S | 01 '!H20 -> Equity-TBC | E21: 0 | F21: =VLOOKUP(B21,'6. %'!$C$6:$I$40,2,0) -> n/a | H21: Exited at 0.82X | J21: EUR USD | K21: 1.0711 | L21: xe.com
B22: ='S | 01 '!C21 -> DriveNets | C22: ='S | 01 '!F21 -> G42 | D22: ='S | 01 '!H21 -> Equity-TBC | E22: =L9 -> 204.6 | F22: =VLOOKUP(B22,'6. %'!$C$6:$I$40,2,0) -> 86882669 | H22: Held at cost
B23: ='S | 01 '!C22 -> vTv Therapeutics Inc. | C23: ='S | 01 '!F22 -> G42 | D23: ='S | 01 '!H22 -> Ordinary Shares | E23: =(F23*G23)*10^-6 -> 4.5855426 | F23: =VLOOKUP(B23,'6. %'!$C$6:$I$40,2,0) -> 259657 | G23: =K19 -> 17.66 | H23: Listed & marked to market
B24: ='S | 01 '!C23 -> Honor Device Co Ltd | C24: ='S | 01 '!F23 -> G42 3 | D24: ='S | 01 '!H23 -> Equity-TBC | E24: 0 | F24: =VLOOKUP(B24,'6. %'!$C$6:$I$40,2,0) -> 6.0685078e+08 | H24: Exited at 1.0X | J24: Heygears Oct 22
B25: ='S | 01 '!C24 -> Applied AI Corporation Limited | C25: ='S | 01 '!F24 -> Mozn | D25: ='S | 01 '!H24 -> Convertible Note | E25: =-'CF (Equity, Debt)'!E32-'CF (Equity, Debt)'!E38-'CF (Equity, Debt)'!E47 -> 11.5 | F25: =VLOOKUP(B25,'6. %'!$C$6:$I$40,2,0) -> n/a | H25: Held at cost | J25: USD RMB | K25: 7.22055 | L25: xe.com
B26: ='S | 01 '!C25 -> eSpace | C26: ='S | 01 '!F25 -> Mozn 4 | D26: ='S | 01 '!H25 -> B Prefs | E26: =F26*G26*10^-6 -> 20.888122 | F26: =VLOOKUP(B26,'6. %'!$C$6:$I$40,2,0) -> 417846 | G26: 49.99 | H26: Marked up, as converted as per the latest priced round | J26: Post Valuation closed in June 2021 (RMB) | K26: 7500000000
B27: ='S | 01 '!C26 -> Tools for Humanity Corporation | C27: ='S | 01 '!F26 -> Mozn | D27: ='S | 01 '!H26 -> C Prefs | E27: ='S | 01 '!K26 -> 14.999999 | F27: =VLOOKUP(B27,'6. %'!$C$6:$I$40,2,0) -> 65413 | H27: Held at cost | J27: G42 Stake | K27: 0.143832
B28: ='S | 01 '!C27 -> WLD Tokens | C28: ='S | 01 '!F27 -> Mozn | D28: ='S | 01 '!H27 -> Tokens | E28: =F28*G28*10^-6 -> 120.19231 | F28: =VLOOKUP(B28,'6. %'!$C$6:$I$40,2,0) -> 62500000 | G28: =50/26 -> 1.9230769 | H28: Tokens valued at $50m/26m (Inveniam), $2.59 (Ardent) | J28: G42 Valuation before Discount (RMB) | K28: 1078740000
B29: ='S | 01 '!C28 -> E-line Ventures LLC | C29: ='S | 01 '!F28 -> Mozn | D29: ='S | 01 '!H28 -> B Prefs | E29: =MAX('S | 01 '!K28,F29*G29*10^-6) -> 6 | F29: =VLOOKUP(B29,'6. %'!$C$6:$I$40,2,0) -> 4477612 | H29: Held at cost | J29: Liquidity Discount | K29: 0
B30: ='S | 01 '!C29 -> School Hack (AIREV Holding Limited) | C30: ='S | 01 '!F29 -> Core42 5 | D30: ='S | 01 '!H29 -> Preferred Shares | E30: =MAX('S | 01 '!K29,F30*G30*10^-6) -> 2.5 | F30: =VLOOKUP(B30,'6. %'!$C$6:$I$40,2,0) -> 25000 | H30: Held at cost | J30: Minority Holding Discount | K30: 0
B31: ='S | 01 '!C30 -> Life Biosciences LLC | C31: ='S | 01 '!F30 -> G42 Capital | D31: ='S | 01 '!H30 -> Convertible Note | E31: =-'CF (Equity, Debt)'!E49 -> 20 | F31: =VLOOKUP(B31,'6. %'!$C$6:$I$40,2,0) -> n/a | H31: Held at cost | J31: G42 Valuation (RMB) | K31: =K28*(1-K29)*(1-K30) -> 1078740000
B32: ='S | 01 '!C31 -> Verses AI Inc | C32: ='S | 01 '!F31 -> G42 Capital | D32: ='S | 01 '!H31 -> Convertible Debenture | E32: =-'CF (Equity, Debt)'!E50 -> 10 | F32: =VLOOKUP(B32,'6. %'!$C$6:$I$40,2,0) -> n/a | H32: Held at cost
J33: Exchange Rate (RMB/USD) | K33: =K25 -> 7.22055
B34: Debt Investments | J34: G42 Valuation (USD) | K34: =K31/K33 -> 1.4939859e+08
B35: Glass Earth Holdings LLC | C35: Mozn | D35: Promissory Note | E35: ='S | 01 '!N36 -> 0 | H35: In default | J35: Investment Cost of G42 (USD) | K35: 60000000
B36: Mena Mobile Inc (Debt) | C36: Mozn | D36: Loan | E36: 0 | H36: In liquidation | J36: Investment Multiple | K36: 1.9039182
B37: Esyasoft Holding (Debt) | C37: Mozn | D37: Loan | E37: 0 | H37: Exited. Received payment of $470,784.65 ($411K+$59K)
B39: Funds Investments | J39: Checks
B40: New Space Capital Fund I | C40: G42 | D40: LP | E40: ='8. NewSpace'!H38*10^-6*K21-'CF (Funds)'!F49 -> 19.274963 | H40: Q3'23 capital account statement
B41: New Space Capital GP Com SCSp | C41: G42 | D41: GP | E41: =E40*'S | 02'!L38/'S | 02'!L37 -> 3.2756152 | H41: Q3'23 pro-rated | J41: =SUM(E10:E32) -> 757.71883 | K41: =J41='S | 01 '!N33 -> TRUE
B42: North Summit Capital Fund | C42: G42 | D42: LP | E42: =81.513771 -'CF (Funds)'!F36 -> 74.725861 | H42: Q3'23 capital account statement | J42: =SUM(E35:E37) -> 0 | K42: =J42='S | 01 '!N39 -> TRUE
B43: Sinovation Disrupt Fund, L.P. | C43: G42 | D43: LP | E43: 0 | H43: Exited | J43: =SUM(E40:E44) -> 108.15165 | K43: =J43='S | 01 '!N47 -> TRUE
B44: Acies Investments Fund I, L.P. | C44: G42 | D44: LP | E44: 10.875212 | H44: Q1'24 capital account statement
B45: Note:
B46: • Respective listed share prices for ONT and vTv Therapeutics are used for estimating the NAVs
F49: 7.1307
F50: =F49*F12 -> 37118730
F51: =F50*0.8 -> 29694984

Sheet CF (Equity, Debt)
B2: E Q U I T Y
B3: Accounting entity | C3: Investment | D3: Payment date | E3: Contributions (in USD, Mn) | F3: Distributions (in USD, Mn) | G3: Currency | H3: Investment / Exit Amt (investee currency) | I3: Investment / Exit Amount (USD) | J3: Consideration (shares) | K3: Comment | N3: NOTES
B4: =VLOOKUP(C4,'S | 01 '!$C$9:$F$46,4,0) -> Mozn | C4: Jollychic Holding Limited | D4: 43470 | E4: =-I4*10^-6 -> -30 | G4: USD | H4: 30000000 | I4: =H4 -> 30000000 | J4: 6100312 | N4: USD AED | O4: 3.678
B5: =VLOOKUP(C5,'S | 01 '!$C$9:$F$46,4,0) -> Mozn | C5: Jollychic Holding Limited | D5: 43724 | E5: =-I5*10^-6 -> -20 | G5: USD | H5: 20000000 | I5: =H5 -> 20000000 | J5: 4204767.4
B6: =VLOOKUP(C6,'S | 01 '!$C$9:$F$46,4,0) -> Mozn | C6: Jollychic Holding Limited | D6: 43724 | E6: =-I6*10^-6 -> -15 | G6: USD | H6: 15000000 | I6: =H6 -> 15000000 | J6: 3153575.6
B7: =VLOOKUP(C7,'S | 01 '!$C$9:$F$46,4,0) -> Mozn | C7: Mena Mobile Inc | D7: 43563 | E7: =-I7*10^-6 -> -8 | G7: USD | H7: 8000000 | I7: =H7 -> 8000000 | J7: 21419829
B8: =VLOOKUP(C8,'S | 01 '!$C$9:$F$46,4,0) -> Mozn | C8: Flyr Inc | D8: 43570 | E8: =-I8*10^-6 -> -4.9999981 | G8: USD | H8: 4999998.1 | I8: =H8 -> 4999998.1 | J8: 2625467
B9: =VLOOKUP(C9,'S | 01 '!$C$9:$F$46,4,0) -> Mozn | C9: Flyr Inc | D9: 43915 | E9: =-I9*10^-6 -> -5.0000019 | G9: USD | H9: =10000000-H8 -> 5000001.9 | I9: =H9 -> 5000001.9 | J9: 2580015
B10: =VLOOKUP(C10,'S | 01 '!$C$9:$F$46,4,0) -> Mozn | C10: Esyasoft Holding | D10: 43870 | E10: =-I10*10^-6 -> -2.5 | G10: USD | H10: 2500000 | I10: =H10 -> 2500000 | J10: N/A
B11: =VLOOKUP(C11,'S | 01 '!$C$9:$F$46,4,0) -> Mozn | C11: Beyond Limits | D11: 43879 | E11: =-I11*10^-6 -> -20 | G11: USD | H11: 20000000 | I11: =H11 -> 20000000 | J11: 4084038
B12: =VLOOKUP(C12,'S | 01 '!$C$9:$F$46,4,0) -> Mozn | C12: Beyond Limits | D12: 43921 | E12: =-I12*10^-6 -> -30 | G12: USD | H12: 30000000 | I12: =H12 -> 30000000 | J12: 5822642
B13: =VLOOKUP(C13,'S | 01 '!$C$9:$F$46,4,0) -> Mozn | C13: Beyond Limits | D13: 43989 | E13: =-I13*10^-6 -> -30 | G13: USD | H13: 30000000 | I13: =H13 -> 30000000 | J13: 5822642
B14: =VLOOKUP(C14,'S | 01 '!$C$9:$F$46,4,0) -> Mozn | C14: Beyond Limits | D14: 44103 | E14: =-I14*10^-6 -> -10 | G14: USD | H14: 10000000 | I14: =H14 -> 10000000 | J14: 1940880
B15: =VLOOKUP(C15,'S | 01 '!$C$9:$F$46,4,0) -> Mozn | C15: ONT plc | D15: 43968 | E15: =-I15*10^-6 -> -50 | G15: USD | H15: 50000000 | I15: 50000000 | J15: 15277680
B16: =VLOOKUP(C16,'S | 01 '!$C$9:$F$46,4,0) -> Mozn | C16: ONT plc | D16: 44006 | E16: =-I16*10^-6 -> -27.268351 | G16: GBP | H16: 21029625 | I16: 27268351 | J16: 9000000
B17: =VLOOKUP(C17,'S | 01 '!$C$9:$F$46,4,0) -> Mozn | C17: ONT plc | D17: 43837 | E17: =-I17*10^-6 -> -18.109441 | G17: GBP | H17: 14386480 | I17: 18109441 | J17: 6362180
B18: =VLOOKUP(C18,'S | 01 '!$C$9:$F$46,4,0) -> Mozn | C18: ONT plc | D18: 43990 | E18: =-I18*10^-6 -> -34.851687 | G18: GBP | H18: 26085573 | I18: 34851687 | J18: 11381140
B19: =VLOOKUP(C19,'S | 01 '!$C$9:$F$46,4,0) -> Mozn | C19: ONT plc | D19: 44315 | E19: =-I19*10^-6 -> -11.24078 | G19: GBP | H19: 8074920 | I19: 11240780 | J19: 2307120
B20: =VLOOKUP(C20,'S | 01 '!$C$9:$F$46,4,0) -> Mozn | C20: Heygears | D20: 44166 | E20: =-I20*10^-6 -> -60 | G20: USD | H20: 60000000 | I20: =H20 -> 60000000 | J20: 3565017.2
B21: =VLOOKUP(C21,'S | 01 '!$C$9:$F$46,4,0) -> Mozn 1 | C21: Jysan Technologies | D21: 44363 | E21: =-I21*10^-6 -> -20 | G21: USD | H21: 20000000 | I21: =H21 -> 20000000 | J21: 7959497
B22: =VLOOKUP(C22,'S | 01 '!$C$9:$F$46,4,0) -> Mozn | C22: Cerebras Systems Inc | D22: 44488 | E22: =-I22*10^-6 -> -39.999983 | G22: USD | H22: 39999983 | I22: =H22 -> 39999983 | J22: 1441711
B23: =VLOOKUP(C23,'S | 01 '!$C$9:$F$46,4,0) -> Mozn | C23: Endless Studios LLC | D23: 44494 | E23: =-I23*10^-6 -> -3 | G23: USD | H23: 3000000 | I23: =H23 -> 3000000 | J23: 3000000
B24: =VLOOKUP(C24,'S | 01 '!$C$9:$F$46,4,0) -> Mozn | C24: Instadeep Limited | D24: 44550 | E24: =-I24*10^-6 -> -5.0237202 | G24: GBP | H24: 3679995.5 | I24: 5023720.2 | J24: 33267
B25: =VLOOKUP(C25,'S | 01 '!$C$9:$F$46,4,0) -> Mozn 2 | C25: X-fusion | D25: 44574 | E25: =-I25*10^-6 -> -493.50096 | G25: USD | H25: 8.9350096e+08 | I25: 4.9350096e+08
B26: =VLOOKUP(C26,'S | 01 '!$C$9:$F$46,4,0) -> G42 | C26: DriveNets | D26: 44643 | E26: =-I26*10^-6 -> -200 | G26: USD | H26: 200000000 | I26: =H26 -> 200000000
B27: =VLOOKUP(C27,'S | 01 '!$C$9:$F$46,4,0) -> G42 | C27: DriveNets | D27: 44680 | E27: =-I27*10^-6 -> -100 | G27: USD | H27: 100000000 | I27: =H27 -> 100000000
B28: =VLOOKUP(C28,'S | 01 '!$C$9:$F$46,4,0) -> Mozn | C28: Esyasoft Holding | D28: 44691 | F28: 5 | G28: USD
B29: =VLOOKUP(C29,'S | 01 '!$C$9:$F$46,4,0) -> G42 | C29: vTv Therapeutics Inc. | D29: 44712 | E29: =-I29*10^-6 -> -12.5 | G29: USD | H29: 12500000 | I29: =H29 -> 12500000 | J29: ='6. %'!D22 -> 259657
B30: =VLOOKUP(C30,'S | 01 '!$C$9:$F$46,4,0) -> G42 3 | C30: Honor Device Co Ltd | D30: 44769 | E30: =-I30*10^-6 -> -600 | G30: USD | H30: 600000000 | I30: =H30 -> 600000000
B31: =VLOOKUP(C31,'S | 01 '!$C$9:$F$46,4,0) -> G42 3 | C31: Honor Device Co Ltd | D31: 44849 | E31: =-I31*10^-6 -> -200 | G31: USD | H31: 200000000 | I31: =H31 -> 200000000
B32: =VLOOKUP(C32,'S | 01 '!$C$9:$F$46,4,0) -> Mozn | C32: Applied AI Corporation Limited | D32: 44861 | E32: =-I32*10^-6 -> -4.75 | G32: USD | H32: 4750000 | I32: =H32 -> 4750000
B33: =VLOOKUP(C33,'S | 01 '!$C$9:$F$46,4,0) -> Mozn 4 | C33: eSpace | D33: 44892 | E33: =-I33*10^-6 -> -15 | G33: USD | H33: 15000000 | I33: =H33 -> 15000000
B34: =VLOOKUP(C34,'S | 01 '!$C$9:$F$46,4,0) -> G42 | C34: vTv Therapeutics Inc. | D34: 44985 | E34: =-I34*10^-6 -> -12.03125 | G34: USD | H34: 12031250 | I34: =H34 -> 12031250 | J34: 10386274
B35: =VLOOKUP(C35,'S | 01 '!$C$9:$F$46,4,0) -> Mozn | C35: Tools for Humanity Corporation | D35: 45075 | E35: =-I35*10^-6 -> -14.999999 | G35: USD | H35: 14999999 | I35: =H35 -> 14999999
B36: =VLOOKUP(C36,'S | 01 '!$C$9:$F$46,4,0) -> Mozn | C36: WLD Tokens | D36: 45075 | E36: =-I36*10^-6 -> -0.005875 | G36: USD | I36: 5875
B37: =VLOOKUP(C37,'S | 01 '!$C$9:$F$46,4,0) -> Mozn | C37: WLD Tokens | D37: 45114 | E37: =-I37*10^-6 -> -0.001 | G37: USD | I37: 1000
B38: =VLOOKUP(C38,'S | 01 '!$C$9:$F$46,4,0) -> Mozn | C38: Applied AI Corporation Limited | D38: 45121 | E38: =-I38*10^-6 -> -2.75 | G38: USD | I38: 2750000
B39: =VLOOKUP(C39,'S | 01 '!$C$9:$F$46,4,0) -> Mozn | C39: Instadeep Limited | D39: 45138 | F39: =I39*10^-6 -> 7.8207761 | G39: USD | H39: 6090345.2 | I39: 7820776.1
B40: =VLOOKUP(C40,'S | 01 '!$C$9:$F$46,4,0) -> Mozn 1 | C40: Jysan Technologies | D40: 45149 | F40: 24.5 | G40: USD | I40: 24500000 | J40: 7959497
B41: =VLOOKUP(C41,'S | 01 '!$C$9:$F$46,4,0) -> Mozn | C41: Endless Studios LLC | D41: 45167 | E41: =-I41*10^-6 -> -5 | G41: USD | I41: 5000000 | J41: 5000000
B42: =VLOOKUP(C42,'S | 01 '!$C$9:$F$46,4,0) -> Mozn | C42: E-line Ventures LLC | D42: 45167 | E42: -6 | G42: USD | I42: 6000000 | J42: =I42/1.34 -> 4477611.9
B43: =VLOOKUP(C43,'S | 01 '!$C$9:$F$46,4,0) -> G42 3 | C43: Honor Device Co Ltd | D43: 45224 | F43: 2.8 | G43: USD
B44: =VLOOKUP(C44,'S | 01 '!$C$9:$F$46,4,0) -> G42 3 | C44: Honor Device Co Ltd | D44: 45224 | F44: 800 | G44: USD
B45: =VLOOKUP(C45,'S | 01 '!$C$9:$F$46,4,0) -> Mozn 2 | C45: X-fusion | D45: 45224 | F45: 403 | G45: USD
B46: =VLOOKUP(C46,'S | 01 '!$C$9:$F$46,4,0) -> Mozn | C46: Instadeep Limited | D46: 45224 | F46: 0.12141643 | G46: USD
B47: =VLOOKUP(C47,'S | 01 '!$C$9:$F$46,4,0) -> Mozn | C47: Applied AI Corporation Limited | D47: 45295 | E47: =-I47*10^-6 -> -4 | G47: USD | H47: 4000000 | I47: =H47 -> 4000000
B48: =VLOOKUP(C48,'S | 01 '!$C$9:$F$46,4,0) -> Core42 5 | C48: School Hack (AIREV Holding Limited) | D48: 45322 | E48: =-I48*10^-6 -> -2.5 | G48: USD | H48: =I48 -> 2500000 | I48: 2500000
B49: =VLOOKUP(C49,'S | 01 '!$C$9:$F$46,4,0) -> G42 Capital | C49: Life Biosciences LLC | D49: 45349 | E49: =-I49*10^-6 -> -20 | G49: USD | I49: 20000000
B50: G42 Capital | C50: Verses AI Inc | D50: 45463 | E50: -10 | G50: USD | I50: 10000000
B54: L O AN | P R O M I S S O R Y N O T E S | D E B T
B55: Mozn | C55: Glass Earth Holdings LLC | D55: 43635 | E55: -8 | G55: USD | H55: 8000000 | I55: =H55 -> 8000000
B56: Mozn | C56: Mena Mobile Inc (Debt) | D56: 44293 | E56: -2.353982 | G56: USD | H56: =-E56*10^6 -> 2353982 | I56: =H56 -> 2353982
B57: Mozn | C57: Esyasoft Holding (Debt) | D57: 44384 | E57: =-I57*10^-6 -> -0.411765 | G57: USD | H57: 2500000 | I57: 411765
B58: Mozn | C58: Esyasoft Holding (Debt) | D58: 44902 | F58: =(411765+59019.65)*10^-6 -> 0.47078465 | G58: USD | H58: =F58*10^6 -> 470784.65 | I58: 470784.65

Sheet CF (Funds)
B2: F U N D S
B3: Entity | C3: Investment | D3: Payment date | E3: Contributions (USD, Mn) | F3: Distributions (USD, Mn) | G3: Currency | H3: Cashflows | I3: Description | J3: TEST
B4: G42 | C4: Sinovation Disrupt Fund, L.P. | D4: 44153 | E4: =H4 -> -10.5 | G4: USD | H4: -10.5 | I4: 1st Capital Call | J4: =SUM(E4:E58) -> -140.8735
B5: G42 | C5: Sinovation Disrupt Fund, L.P. | D5: 44238 | E5: =H5 -> 4.214027 | G5: USD | H5: 4.214027 | I5: Partial return of the 1st Capital Call | J5: ='S | 01 '!K47 -> 140.8735
B6: G42 | C6: Sinovation Disrupt Fund, L.P. | D6: 44238 | F6: =H6 -> 0.05044835 | G6: USD | H6: 0.05044835 | I6: Interest Catchup | J6: =ROUND(J5,5)=-ROUND(J4,5) -> TRUE
B7: G42 | C7: Sinovation Disrupt Fund, L.P. | D7: 44285 | E7: =H7 -> -6.433746 | G7: USD | H7: -6.433746 | I7: 2nd Capital Calll
B8: G42 | C8: Sinovation Disrupt Fund, L.P. | D8: 44269 | E8: =H8 -> 1.1352074 | G8: USD | H8: 1.1352074 | I8: Return of Capital fund
B9: G42 | C9: Sinovation Disrupt Fund, L.P. | D9: 44269 | F9: =H9 -> 0.0259 | G9: USD | H9: 0.0259 | I9: Interest Catchup
B10: G42 | C10: Sinovation Disrupt Fund, L.P. | D10: 44483 | E10: =H10 -> -7.567138 | G10: USD | H10: -7.567138 | I10: 3rd Capital Call
B11: G42 | C11: Sinovation Disrupt Fund, L.P. | D11: 44554 | E11: =H11 -> -7.385016 | G11: USD | H11: -7.385016 | I11: 4th Capital Call
B12: G42 | C12: Sinovation Disrupt Fund, L.P. | D12: 44554 | E12: =H12 -> 4.0733456 | G12: USD | H12: 4.0733456 | I12: Return of Capital fund
B13: G42 | C13: Sinovation Disrupt Fund, L.P. | D13: 44554 | F13: =H13 -> 0.139694 | G13: USD | H13: 0.139694 | I13: Interest Catchup
B14: G42 | C14: Sinovation Disrupt Fund, L.P. | D14: 44703 | E14: =H14 -> 5.673074 | G14: USD | H14: 5.673074 | I14: Return of Capital fund
B15: G42 | C15: Sinovation Disrupt Fund, L.P. | D15: 44703 | F15: =H15 -> 0.227786 | G15: USD | H15: 0.227786 | I15: Interest Catchup
B16: G42 | C16: Sinovation Disrupt Fund, L.P. | D16: 44776 | E16: =H16 -> -3.235493 | G16: USD | H16: -3.235493 | I16: 5th Capital Call
B17: G42 | C17: Sinovation Disrupt Fund, L.P. | D17: 44960 | E17: =H17 -> -2.631528 | G17: USD | H17: -2.631528 | I17: 6th Capital Call
B18: G42 | C18: Sinovation Disrupt Fund, L.P. | D18: 45085 | E18: =H18 -> 1.912557 | G18: USD | H18: 1.912557 | I18: Return of Capital fund
B19: G42 | C19: Sinovation Disrupt Fund, L.P. | D19: 45166 | E19: -1.799122 | G19: USD | H19: -1.799122 | I19: 7th Capital Call
B20: G42 | C20: Sinovation Disrupt Fund, L.P. | D20: 45218 | E20: -2.415861 | G20: USD | H20: -2.415861 | I20: 8th Capital Call
B21: G42 | C21: Sinovation Disrupt Fund, L.P. | D21: 45323 | F21: =24.959693 -> 24.959693 | G21: USD | H21: =F21 -> 24.959693 | I21: Exit Proceeds (full and final)
B22: G42 | C22: North Summit Capital Fund | D22: 43665 | E22: =H22 -> -3 | G22: USD | H22: -3 | I22: 1st Capital Call
B23: G42 | C23: North Summit Capital Fund | D23: 43983 | E23: =H23 -> -4.485 | G23: USD | H23: -4.485 | I23: 2nd Capital Calll
B24: G42 | C24: North Summit Capital Fund | D24: 43879 | E24: =H24 -> -9.50975 | G24: USD | H24: -9.50975 | I24: 3rd Capital Call
B25: G42 | C25: North Summit Capital Fund | D25: 43934 | E25: =H25 -> -41.3 | G25: USD | H25: -41.3 | I25: 4th Capital Call
B26: G42 | C26: North Summit Capital Fund | D26: 44151 | E26: =H26 -> 9.95 | G26: USD | H26: 9.95 | I26: 5th Capital Call-Partial return of the 4th Capital Call
B27: G42 | C27: North Summit Capital Fund | D27: 44151 | E27: =H27 -> -10.455 | G27: USD | H27: -10.455 | I27: 5th Capital Call
B28: G42 | C28: North Summit Capital Fund | D28: 44196 | E28: =H28 -> 4.975 | G28: USD | H28: 4.975 | I28: 6th Capital Call-Partial return of the 4th Capital Call
B29: G42 | C29: North Summit Capital Fund | D29: 44196 | E29: =H29 -> -3.452293 | G29: USD | H29: -3.452293 | I29: 6th Capital Call
B30: G42 | C30: North Summit Capital Fund | D30: 44196 | F30: =H30 -> 0.582902 | G30: USD | H30: 0.582902 | I30: 6th Capital Call-Dividends from Project Topscore
B31: G42 | C31: North Summit Capital Fund | D31: 44370 | E31: =H31 -> -5.97 | G31: USD | H31: -5.97 | I31: 7th Capital Call
B32: G42 | C32: North Summit Capital Fund | D32: 44400 | E32: =H32 -> -0.75 | G32: USD | H32: -0.75 | I32: 8th Capital Call
B33: G42 | C33: North Summit Capital Fund | D33: 44400 | F33: =H33 -> 0.445059 | G33: USD | H33: 0.445059 | I33: 8th Capital Call-Dividends from Project Topscore
B34: G42 | C34: North Summit Capital Fund | D34: 44554 | E34: =H34 -> 1.78239 | G34: USD | H34: 1.78239 | I34: 9th Capital Call-Return of Capital Fund
B35: G42 | C35: North Summit Capital Fund | D35: 44676 | E35: =H35 -> -21 | G35: USD | H35: -21 | I35: 12th Capital Call
B36: G42 | C36: North Summit Capital Fund | D36: 45243 | F36: =H36 -> 6.78791 | G36: USD | H36: 6.78791 | I36: 13th Capital Call & Distribution #4
B37: G42 | C37: North Summit Capital Fund | D37: 45470 | E37: =H37 -> -0.055697 | G37: USD | H37: =-55697*10^-6 -> -0.055697 | I37: 14th Capital Call
B38: G42 | C38: New Space Capital Fund I | D38: 44087 | E38: =H38*1.1 -> -20.917553 | G38: EUR | H38: -19.015957 | I38: Drawdown1
B39: G42 | C39: New Space Capital Fund I | D39: 44287 | E39: -0.21103182 | G39: EUR | H39: -0.21103182 | I39: Drawdown2
B40: G42 | C40: New Space Capital Fund I | D40: 44442 | E40: =1.18*H40 -> -0.23965473 | G40: EUR | H40: =-203097.23*10^-6 -> -0.20309723 | I40: Drawdown3
B41: G42 | C41: New Space Capital Fund I | D41: 44623 | E41: =1.11*H41 -> -0.25893585 | G41: EUR | H41: =-233275.54*10^-6 -> -0.23327554 | I41: Drawdown4
B42: G42 | C42: New Space Capital Fund I | D42: 44784 | E42: =1.03*H42 -> 0.015224657 | G42: EUR | H42: =14781.22*10^-6 -> 0.01478122 | I42: Return of Capital
B43: G42 | C43: New Space Capital Fund I | D43: 44956 | E43: =9741387*10^-6*1.08341 -> 10.553916 | G43: EUR | H43: =9741387*10^-6 -> 9.741387 | I43: Return of Capital
B44: G42 | C44: New Space Capital Fund I | D44: 44956 | F44: =2728214.02*10^-6*1.08341 -> 2.9557744 | G44: EUR | H44: 2.728214 | I44: Distribution | Actualization Interest
B45: G42 | C45: New Space Capital Fund I | D45: 45170 | E45: -0.22532724 | G45: EUR | H45: -0.22532724 | I45: Drawdown (Notice 10)
B46: G42 | C46: New Space Capital Fund I | D46: 45260 | E46: -0.28531252 | G46: EUR | H46: -0.28531252 | I46: Drawdown (Notice 11)
B47: G42 | C47: New Space Capital Fund I | D47: 45321 | E47: -2.4198785 | G47: EUR | H47: -2.4198785 | I47: Drawdown (Notice 12)
B48: G42 | C48: New Space Capital Fund I | D48: 45372 | E48: -0.21649574 | G48: EUR | H48: -0.21649574 | I48: Drawdown (Notice 13)
B49: G42 | C49: New Space Capital Fund I | D49: 45454 | F49: =H49*1.0743 -> 0.46369473 | G49: EUR | H49: =431624.99*10^-6 -> 0.43162499 | I49: Drawdown 14| Actualization Interest Distribution
B50: G42 | C50: New Space Capital Fund I | D50: 45454 | E50: =H50*1.0883 -> -1.7173904 | G50: EUR | H50: =-1578048.66*10^-6 -> -1.5780487 | I50: Drawdown (Notice 15)
B51: G42 | C51: New Space Capital GP Com SCSp | D51: 44087 | E51: =-'S | 01 '!K43 -> -2.7058824 | G51: EUR | H51: -2.125 | I51: Drawdown1
B52: G42 | C52: Acies Investments Fund I, L.P. | D52: 44540 | E52: =H52 -> -2.8053125 | G52: USD | H52: -2.8053125 | I52: 1st Capital Call
B53: G42 | C53: Acies Investments Fund I, L.P. | D53: 44602 | E53: =H53 -> -3.4075 | G53: USD | H53: -3.4075 | I53: 2nd Capital Call
B54: G42 | C54: Acies Investments Fund I, L.P. | D54: 44683 | E54: =H54 -> -1.025775 | G54: USD | H54: -1.025775 | I54: Catch up Capital Call
B55: G42 | C55: Acies Investments Fund I, L.P. | D55: 44707 | E55: =H55 -> -3.388275 | G55: USD | H55: -3.388275 | I55: 3rd Capital Call
B56: G42 | C56: Acies Investments Fund I, L.P. | D56: 44875 | E56: =H56 -> -3.388275 | G56: USD | H56: -3.388275 | I56: 4th Capital Call

Sheet 5. Glossary
B2: Term | C2: Definition
B3: $ | C3: Refers to US Dollar
B4: Equity-TBC | C4: The exact class of share is not available as of date
B5: Gain | C5: Equals the total Distributions (received from the investment) plus NAV less Amount Invested
B6: G42 | C6: Refers to entity G42 Investments AI Holding RSC Ltd, and Smart Interaction1 Holding SPV RSC LTD
B7: G.P. | C7: General Partnership interest
B8: IRR | C8: Shown as Interim IRR, where the NAV of the investment is assumed as an appraised terminal value. Transaction costs are not included in the estimate of IRR
B9: L.P. | C9: Limited Partnership interest
B10: MOIC | C10: Money on invested capital
B11: Mozn | C11: Refers to entities: Mozn Holding RSC Ltd, Enterprises Connection Holding RSC Ltd, Smart Interaction5 Holding SPV RSC LTD and QAZ42 Investment SPV RSC Ltd
B12: NAV | C12: Is the measure of the carrying value of the underlying investment as of date
B13: n/a | C13: As appropriate the information is ‘not available’ or ‘not applicable’
... B28: •Written Off: | C28: Investments in Jollychic, Mena Mobile (equity) and Glass Earth are written off

Sheet 6. %
C2: % OWNERSHIP
C3: As of date | D3: ='S | 01 '!D2 -> 45473
C6: Deals | D6: Shares / Units | E6: Total | F6: % | G6: Source for % holding | H6: Incorporation/Jurisdiction | I6: Country
C8: Direct Investments
B9: Written Off | C9: ='S | 01 '!C9 -> Jollychic Holding Limited | D9: 13458655 | E9: 236116762 | F9: =D9/E9 -> 0.056999998 | G9: Dan Kong | H9: Cayman Islands | I9: Cayman Islands
B10: Written Off | C10: ='S | 01 '!C10 -> Mena Mobile Inc | D10: 21419829 | E10: 152998776 | F10: =D10/E10 -> 0.14 | G10: Dan Kong | H10: Cayman Islands | I10: Cayman Islands
C11: ='S | 01 '!C11 -> Flyr Inc | D11: 5205482 | E11: 61222609 | F11: =D11/E11 -> 0.085025485 | G11: Cap Table as of Jun'22 | H11: Delaware Corporation | I11: USA
B12: Exited | C12: ='S | 01 '!C12 -> Esyasoft Holding | D12: n/a | E12: n/a | F12: n/a | G12: n/a; exited | H12: DIFC | I12: Dubai, UAE
C13: ='S | 01 '!C13 -> Beyond Limits | D13: 17670202 | E13: 187288050 | F13: =D13/E13 -> 0.094347728 | G13: Cap Table | H13: Delaware Corporation | I13: USA
C14: ='S | 01 '!C14 -> ONT plc | D14: 44328120 | E14: =829189128+29025326 -> 858214454 | F14: =D14/E14 -> 0.051651565 | G14: LSE Announcement | H14: UK | I14: UK
C15: ='S | 01 '!C15 -> Heygears | D15: 3565017.2 | E15: =D15/F15 -> 24791497 | F15: 0.1438 | G15: Dan Kong | H15: PRC | I15: China
B16: Exited | C16: ='S | 01 '!C16 -> Jysan Technologies | D16: 7959497 | E16: 2.6531657e+08 | F16: 0.03 | G16: Txn docs | H16: UK | I16: UK
C17: ='S | 01 '!C17 -> Cerebras Systems Inc | D17: 1441711 | E17: 158130778 | F17: =D17/E17 -> 0.0091172068 | G17: Cap table as of Dec'22 | H17: Delaware Corporation | I17: USA
C18: ='S | 01 '!C18 -> Endless Studios LLC | D18: 8000000 | E18: =38750000+11000000 -> 49750000 | F18: =D18/E18 -> 0.16080402 | G18: Cap table as of Dec'22 | H18: Delaware Corporation | I18: USA
B19: Exited | C19: ='S | 01 '!C19 -> Instadeep Limited | D19: 33267 | E19: 2895450 | F19: =D19/E19 -> 0.011489406 | G19: Txn docs; exit underway | H19: UK | I19: UK
B20: Exited | C20: ='S | 01 '!C20 -> X-fusion | D20: n/a | E20: n/a | F20: =10% * 51% -> 0.051 | G20: Dan Kong | H20: PRC | I20: China
C21: ='S | 01 '!C21 -> DriveNets | D21: 86882669 | E21: 779782293 | F21: =D21/E21 -> 0.11141914 | G21: Cap table as of Mar'23 | H21: Israeli Pvt Company | I21: Israel
C22: ='S | 01 '!C22 -> vTv Therapeutics Inc. | D22: =ROUNDUP(10386274/40,0) -> 259657 | E22: =ROUNDUP(81483600+23093860+9545439+3214503,0)+464377+3853997 -> 121655776 | F22: =D22/E22 -> 0.0021343582 | G22: 10Q report Jun'23 | H22: Delaware Corporation | I22: USA
B23: Exited | C23: ='S | 01 '!C23 -> Honor Device Co Ltd | D23: =1517126944.34*0.8/2 -> 6.0685078e+08 | E23: 3.2238948e+10 | F23: =4.705882%* 0.8/2 -> 0.018823528 | G23: Dan Kong | H23: PRC | I23: China
C24: ='S | 01 '!C24 -> Applied AI Corporation Limited | D24: n/a | E24: n/a | F24: n/a | G24: n/a; convertible note | H24: ADGM | I24: Abu Dhabi, UAE | L24: Eline Estimates
C25: ='S | 01 '!C25 -> eSpace | D25: 417846 | E25: 14995394 | F25: =D25/E25 -> 0.027864956 | G25: Series B Pref | H25: Delaware Corporation | I25: USA | L25: 5400972 | M25: Common Unit
C26: ='S | 01 '!C26 -> Tools for Humanity Corporation | D26: 65413 | E26: 10445693 | F26: =D26/E26 -> 0.0062621983 | G26: Email: Sam Thomson | H26: Delaware Corporation | I26: USA | L26: 4857352 | M26: Series A
C27: ='S | 01 '!C27 -> WLD Tokens | D27: 62500000 | E27: 10000000000 | F27: =D27/E27 -> 0.00625 | G27: Email: Sam Thomson | H27: DAO | Cayman Islands | I27: Cayman Islands | L27: 16791835 | M27: Series B
C28: ='S | 01 '!C28 -> E-line Ventures LLC | D28: 4477612 | E28: =L32 -> 38990900 | F28: =D28/E28 -> 0.11483736 | G28: IAF 12Jul23 | H28: New Jersey | I28: New Jersey | L28: 1465517 | M28: Series B-S1
C29: ='S | 01 '!C29 -> School Hack (AIREV Holding Limited) | D29: 25000 | E29: 100000 | F29: =D29/E29 -> 0.25 | G29: Shareholders Resolution | H29: ADGM | I29: UAE | L29: =D28*2 -> 8955224 | M29: Seires B 2023
C30: ='S | 01 '!C30 -> Life Biosciences LLC | D30: n/a | E30: n/a | F30: n/a | G30: n/a; convertible note | H30: Delaware Corporation | I30: USA | L30: 1520000 | M30: Series B 2023 P
C31: ='S | 01 '!C31 -> Verses AI Inc | D31: n/a | E31: n/a | F31: n/a | G31: n/a; convertible debenture | H31: Victoria, British Columbia | I31: Canada
L32: =SUM(L25:L30) -> 38990900
C35: Funds Investments | D35: G42 Commitment | E35: Fund Size
C36: New Space Capital Fund I | D36: 23234462 | E36: 105,400,00 | F36: ='8. NewSpace'!#REF! -> #REF! | G36: Estimated as per Q1-23 NAV report | H36: Luxembourg | I36: Luxembourg
C37: New Space Capital GP Com SCSp | D37: =-'CF (Funds)'!H51*10^6 -> 2125000 | E37: 105,400,00 | F37: ='8. NewSpace'!#REF! -> #REF! | H37: Luxembourg | I37: Luxembourg
C38: North Summit Capital Fund | D38: 300000000 | E38: 301507538 | F38: =D38/E38 -> 0.995 | G38: Q4'22 Report | H38: Cayman Islands | I38: Cayman Islands
B39: Exited | C39: Sinovation Disrupt Fund, L.P. | D39: 50000000 | E39: 496717172 | F39: =D39/E39 -> 0.1006609 | G39: Q2'23 Report | H39: Cayman Islands | I39: Cayman Islands
C40: Acies Investments Fund I, L.P. | D40: 17112500 | E40: 51337500 | F40: =D40/E40 -> 0.33333333 | G40: Q1 23 Report | H40: Delaware LLC | I40: USA

Sheet 7. Board
C3: Deals | D3: Board Representation ‡ | E3: Representative | F3: Notes | G3: Status | H3: Comments
C5: Direct Investments
C6: Mena Mobile Inc | D6: 1 Director | E6: Peng Xiao | G6: In Liquidation
C7: Flyr Inc | D7: 1 Observer | E7: Jon Nieman | H7: Earlier 1 Director represented by Marty
C8: Esyasoft Holding | D8: NR | E8: n/a | F8: 2 | G8: Exited | H8: Monty Aw represented earlier
C9: Jollychic Holding Limited | D9: 1 Director | E9: Divyesh Mahajan | F9: 1 | G9: In Liquidation
C10: Beyond Limits | D10: 1 Director | E10: Marty | F10: 3
C11: ONT plc | D11: 1 Director | E11: Guy Harmelin (Independent Director)
C12: Heygears | D12: 2 Director | E12: Elaine | G12: Peng Resigned Jan24 | H12: PX to be replaced by XP
C13: Jysan Technologies | D13: 1 Director | E13: None appointed | G13: Exited | H13: Exited
C14: Cerebras Systems Inc | D14: 1 Observer | E14: Eric Xing | F14: 4
C15: Endless Studios LLC | D15: 1 Director 1 Observer | E15: Jon Nieman, Sushil
C16: Instadeep Limited | D16: 1 Observer | G16: Exited | H16: Exited
C17: X-fusion | D17: NR | E17: n/a | G17: Exited
C18: DriveNets | D18: 1 Observer | E18: Guy Harmelin
C19: vTv Therapeutics Inc. | D19: 1 Director, 1 Observer | E19: Dr. Fahad (Board), Jon Nieman (Observer)
C20: Honor Device Co Ltd | D20: NR | E20: n/a | F20: 5 | G20: Exited | L20: E-line Ventures LLC
C21: Applied AI Corporation Limited | D21: NR | E21: n/a | L21: School Hack (AIREV Holding Limited)
C22: eSpace | D22: NR | E22: n/a
C23: Tools for Humanity Corporation | D23: NR | E23: n/a
C24: E-line Ventures LLC
C25: School Hack (AIREV Holding Limited) | D25: 2 Director | E25: n/a
C28: Debt Investments
C29: Glass Earth Holdings LLC | D29: NR
C30: Mena Mobile Inc | D30: 1 Director | E30: Peng Xiao | G30: In Liquidation
C31: Esyasoft Holding | D31: NR
C34: Funds Investments
C35: New Space Capital Fund I | D35: 1 Director | E35: Talal
C36: New Space Capital GP Com SCSp | D36: NR
C37: North Summit Capital Fund | D37: NR
C38: Sinovation Disrupt Fund, L.P. | D38: NR | G38: Exited
C39: Acies Investments Fund I, L.P. | D39: Advisory Board | E39: Not yet appointed | H39: Confirm appoinment
C43: NOTES:
C44: NR = No Rights / No Representation
C45: n/a = not applicable or not available
C46: ‡ Board Representation : as a Board Seat, Observer, or Advisor
B47: 1 | C47: Jollychic Holding : Peng Xiao held the directorship until Jun 2021
B48: 2 | C48: Esyasoft: we held a Board seat, with Monty Aw as the representative, until Jun 2022
B49: 3 | C49: Beyond Limits: possibility of the 2nd Board seat in case we invest (an additional / an earlier committed) $10m
B50: 4 | C50: Cerebras : possibility of a Board seat, If G42 holds >10% with rights to exercise at least 20% of warrant
B51: 5 | C51: Honor: Our board seat only kicks in once Honor is converted into a joint stock company in March 2023; there is no one appointed as yet

Sheet 8. Log
B2: Date Log | C2: Update
B4: Jun'24
C5: Verses : $10m Investment in Convertible Debenture
C6: North Summit Capital : capital contribution $55.7K
C7: New Space Capital : distributions received EUR 431.6K
C8: Flyr: Carrying Value reduced to $30m from $65m
B9: May' 24
C10: No investment cash inflows or outflows to report
B11: Apr' 24
C12: No investment cash inflows or outflows to report
B13: Mar'24
C14: New Space Capital LP: Capital contribution of EUR 200,702.46 as of 21 Mar 24
C15: Carrying values of Flyr, Beyond Limits and DriveNets marked down as per Ardent guidance
B16: Feb'24
C17: Sinovation: receivedUSD 24,959,693 as full cash proceeds of from the exit
C18: Life Biosciences: issued USD 20m convertible loan note
B19: Jan’24
C20: AAICO: USD 4m second milestone payment on 4-Jan-24
C21: NewSpace: EUR 2.2M (USD 2.42M) capital call paid on 30-Jan-24
C22: SchoolHack: Made an equity investment of USD 2.5m plus 250K in cloud credits
C23: Menamobile: Under liquidation
B24: Dec’23
C25: Espace Inc: converted the SAFE to equity
C26: North Summit Capital: G42’s remaining funding capital commitments waived
B27: Nov’23
C28: North Summit Capital : USD 6.8 distribution received on 13th November
B29: Oct’23
C30: Paid USD 2.4m to Sinovation Disrupt Fund (8th capital call)
C31: Received USD 2.8m dividend for Honor and USD 800m for Honor sell-down
C32: Received USD 403m for xFusion sell-down
B33: Sep’23
C34: No cashflow movements to report
B35: Aug’23
C36: Received USD 24.5m for Jysan’s exit
C37: Funded USD 1,799,122 towards Sinovation’s capital call
C38: Invested USD 6m in E-line Ventures and USD 5m in Endless Studios
B39: Jul’23
C40: Worldcoin: token warrant exercised, received 62.5M tokens
C41: AAICO: first milestone payment called with $2.75m additional invested
C42: Instadeep: fully exited at 1.56X return over invested capital (received $7.82m)
B43: Jun’23
C44: A distribution of $1.9m as a ‘return of capital’ received from the Sinovation Disrupt Fund
B45: May’23
C46: Invested $15m in Tools for Humanity Corp equity and Worldcoin token warrants
B47: Apr’23
C48: Re-structured investment in New Space Capital GP restructured – converted to GP commitment vehicle
C49: NAVs marked up for: Instadeep, Heygears and North Summit Capital. Mena Mobile equity value written off
B50: Mar’23
C51: Jysan dividend delayed (finally fully-exited in Aug’23)
B52: Feb’23
C53: Sinovation 6th capital call $2.6m transferred on 3-Feb
C54: vTv Therapeutics 2nd payment of $12.03m transferred on 28-Feb
B55: Jan’23
C56: Received €12.5m from NewSpace Capital on 30-Jan in lieu of partial return of capital and actualization interest; NAV reported as of Q3’23
C57: Instadeep exit: transaction completion expected by Q2’23; held at cost
B58: Dec’22
C59: Esyasoft’s exit: received $412k principal plus $59k as accrued interest on 7-Dec
B60: Nov’22
C61: Capital Call from Acies Investments Fund-I of $3.4m
C62: New investment in eSpace SAFE note via Mozn of $15.0m
B63: October 22
D64: 1) $4.75m Signing Payment for AAICO
D65: 2) $3.4m 4th capital call Acies
D66: 3) Honor booked at $1.2B cost
D67: 4) NAV of Heygears updated to $114.2m as of Oct 22

Sheet D S | 01
C2: As of date | D2: 45382 | F2: DELTA SHEET AGAINST LAST MONTH >>>>>>>>>>>>>>>>>>>>>>>>>>>>>>>>>>>>>>>>>>>>>>>>>>>
C6: Deals | D6: Status | E6: Lead | F6: Investing Entity Ϋ | G6: Vintageἀ | H6: Instrument | I6: % | J6: Committed | K6: Invested | L6: Remaining Commitment | M6: Distributions | N6: Carrying Value | O6: Gain | P6: TVPI | Q6: Additonal Upside/Downside
G7: # | I7: % | J7: $,m | K7: $,m | L7: $,m | M7: $,m | N7: $,m | O7: $,m | P7: X
C8: Direct Investments
C9: Jollychic Holding Limited | D9: Written-off | E9: Elaine | F9: Mozn | G9: 2019 | H9: C+ Prefs | I9: =IF('[3]S | 01 '!I9-'S | 01 '!I9,'[3]S | 01 '!I9-'S | 01 '!I9,"") | J9: =IF('[3]S | 01 '!J9-'S | 01 '!J9,'[3]S | 01 '!J9-'S | 01 '!J9,"") | K9: =IF('[3]S | 01 '!K9-'S | 01 '!K9,'[3]S | 01 '!K9-'S | 01 '!K9,"") | L9: =IF('[3]S | 01 '!L9-'S | 01 '!L9,'[3]S | 01 '!L9-'S | 01 '!L9,"") | M9: =IF('[3]S | 01 '!M9-'S | 01 '!M9,'[3]S | 01 '!M9-'S | 01 '!M9,"") | N9: =IF('[3]S | 01 '!N9-'S | 01 '!N9,'[3]S | 01 '!N9-'S | 01 '!N9,"") | O9: =IF('[3]S | 01 '!O9-'S | 01 '!O9,'[3]S | 01 '!O9-'S | 01 '!O9,"") | P9: =IF('[3]S | 01 '!P9-'S | 01 '!P9,'[3]S | 01 '!P9-'S | 01 '!P9,"") | Q9: =IF('[3]S | 01 '!R9-'S | 01 '!Q9,'[3]S | 01 '!R9-'S | 01 '!Q9,"") -> #VALUE!
C10: Mena Mobile Inc | D10: Written-off | E10: Elaine | F10: Mozn | G10: 2019 | H10: B Prefs | I10: =IF('[3]S | 01 '!I10-'S | 01 '!I10,'[3]S | 01 '!I10-'S | 01 '!I10,"") | J10: =IF('[3]S | 01 '!J10-'S | 01 '!J10,'[3]S | 01 '!J10-'S | 01 '!J10,"") | K10: =IF('[3]S | 01 '!K10-'S | 01 '!K10,'[3]S | 01 '!K10-'S | 01 '!K10,"") | L10: =IF('[3]S | 01 '!L10-'S | 01 '!L10,'[3]S | 01 '!L10-'S | 01 '!L10,"") | M10: =IF('[3]S | 01 '!M10-'S | 01 '!M10,'[3]S | 01 '!M10-'S | 01 '!M10,"") | N10: =IF('[3]S | 01 '!N10-'S | 01 '!N10,'[3]S | 01 '!N10-'S | 01 '!N10,"") | O10: =IF('[3]S | 01 '!O10-'S | 01 '!O10,'[3]S | 01 '!O10-'S | 01 '!O10,"") | P10: =IF('[3]S | 01 '!P10-'S | 01 '!P10,'[3]S | 01 '!P10-'S | 01 '!P10,"") | Q10: =IF('[3]S | 01 '!R10-'S | 01 '!Q10,'[3]S | 01 '!R10-'S | 01 '!Q10,"") -> #VALUE!
C11: Flyr Inc | D11: Unrealized | E11: Sushil | F11: Mozn | G11: 2019 | H11: B-1,2 Prefs | I11: =IF('[3]S | 01 '!I11-'S | 01 '!I11,'[3]S | 01 '!I11-'S | 01 '!I11,"") | J11: =IF('[3]S | 01 '!J11-'S | 01 '!J11,'[3]S | 01 '!J11-'S | 01 '!J11,"") | K11: =IF('[3]S | 01 '!K11-'S | 01 '!K11,'[3]S | 01 '!K11-'S | 01 '!K11,"") | L11: =IF('[3]S | 01 '!L11-'S | 01 '!L11,'[3]S | 01 '!L11-'S | 01 '!L11,"") | M11: =IF('[3]S | 01 '!M11-'S | 01 '!M11,'[3]S | 01 '!M11-'S | 01 '!M11,"") | N11: =IF('[3]S | 01 '!N11-'S | 01 '!N11,'[3]S | 01 '!N11-'S | 01 '!N11,"") -> 25.78127 | O11: =IF('[3]S | 01 '!O11-'S | 01 '!O11,'[3]S | 01 '!O11-'S | 01 '!O11,"") -> 25.78127 | P11: =IF('[3]S | 01 '!P11-'S | 01 '!P11,'[3]S | 01 '!P11-'S | 01 '!P11,"") -> 2.578127 | Q11: =IF('[3]S | 01 '!R11-'S | 01 '!Q11,'[3]S | 01 '!R11-'S | 01 '!Q11,"") -> #VALUE!
C12: Esyasoft Holding | D12: Realized | E12: Sushil | F12: Mozn | G12: 2020 | H12: Convertible Note | I12: =IF('[3]S | 01 '!I12-'S | 01 '!I12,'[3]S | 01 '!I12-'S | 01 '!I12,"") -> #VALUE! | J12: =IF('[3]S | 01 '!J12-'S | 01 '!J12,'[3]S | 01 '!J12-'S | 01 '!J12,"") | K12: =IF('[3]S | 01 '!K12-'S | 01 '!K12,'[3]S | 01 '!K12-'S | 01 '!K12,"") | L12: =IF('[3]S | 01 '!L12-'S | 01 '!L12,'[3]S | 01 '!L12-'S | 01 '!L12,"") | M12: =IF('[3]S | 01 '!M12-'S | 01 '!M12,'[3]S | 01 '!M12-'S | 01 '!M12,"") | N12: =IF('[3]S | 01 '!N12-'S | 01 '!N12,'[3]S | 01 '!N12-'S | 01 '!N12,"") | O12: =IF('[3]S | 01 '!O12-'S | 01 '!O12,'[3]S | 01 '!O12-'S | 01 '!O12,"") | P12: =IF('[3]S | 01 '!P12-'S | 01 '!P12,'[3]S | 01 '!P12-'S | 01 '!P12,"") | Q12: =IF('[3]S | 01 '!R12-'S | 01 '!Q12,'[3]S | 01 '!R12-'S | 01 '!Q12,"")
C13: Beyond Limits | D13: Unrealized | E13: Divyesh | F13: Mozn | G13: 2020 | H13: C Prefs | I13: =IF('[3]S | 01 '!I13-'S | 01 '!I13,'[3]S | 01 '!I13-'S | 01 '!I13,"") | J13: =IF('[3]S | 01 '!J13-'S | 01 '!J13,'[3]S | 01 '!J13-'S | 01 '!J13,"") | K13: =IF('[3]S | 01 '!K13-'S | 01 '!K13,'[3]S | 01 '!K13-'S | 01 '!K13,"") | L13: =IF('[3]S | 01 '!L13-'S | 01 '!L13,'[3]S | 01 '!L13-'S | 01 '!L13,"") | M13: =IF('[3]S | 01 '!M13-'S | 01 '!M13,'[3]S | 01 '!M13-'S | 01 '!M13,"") | N13: =IF('[3]S | 01 '!N13-'S | 01 '!N13,'[3]S | 01 '!N13-'S | 01 '!N13,"") | O13: =IF('[3]S | 01 '!O13-'S | 01 '!O13,'[3]S | 01 '!O13-'S | 01 '!O13,"") | P13: =IF('[3]S | 01 '!P13-'S | 01 '!P13,'[3]S | 01 '!P13-'S | 01 '!P13,"") | Q13: =IF('[3]S | 01 '!R13-'S | 01 '!Q13,'[3]S | 01 '!R13-'S | 01 '!Q13,"")
C14: ONT plc | D14: Unrealized | E14: Divyesh | F14: Mozn | G14: 2020 | H14: Ordinary Shares | I14: =IF('[3]S | 01 '!I14-'S | 01 '!I14,'[3]S | 01 '!I14-'S | 01 '!I14,"") | J14: =IF('[3]S | 01 '!J14-'S | 01 '!J14,'[3]S | 01 '!J14-'S | 01 '!J14,"") | K14: =IF('[3]S | 01 '!K14-'S | 01 '!K14,'[3]S | 01 '!K14-'S | 01 '!K14,"") | L14: =IF('[3]S | 01 '!L14-'S | 01 '!L14,'[3]S | 01 '!L14-'S | 01 '!L14,"") | M14: =IF('[3]S | 01 '!M14-'S | 01 '!M14,'[3]S | 01 '!M14-'S | 01 '!M14,"") | N14: =IF('[3]S | 01 '!N14-'S | 01 '!N14,'[3]S | 01 '!N14-'S | 01 '!N14,"") -> 1.3401975 | O14: =IF('[3]S | 01 '!O14-'S | 01 '!O14,'[3]S | 01 '!O14-'S | 01 '!O14,"") -> 1.3401975 | P14: =IF('[3]S | 01 '!P14-'S | 01 '!P14,'[3]S | 01 '!P14-'S | 01 '!P14,"") -> 0.0094733518 | Q14: =IF('[3]S | 01 '!R14-'S | 01 '!Q14,'[3]S | 01 '!R14-'S | 01 '!Q14,"")
C15: Heygears | D15: Unrealized | E15: Elaine | F15: Mozn | G15: 2020 | H15: Registered Capital | I15: =IF('[3]S | 01 '!I15-'S | 01 '!I15,'[3]S | 01 '!I15-'S | 01 '!I15,"") | J15: =IF('[3]S | 01 '!J15-'S | 01 '!J15,'[3]S | 01 '!J15-'S | 01 '!J15,"") | K15: =IF('[3]S | 01 '!K15-'S | 01 '!K15,'[3]S | 01 '!K15-'S | 01 '!K15,"") | L15: =IF('[3]S | 01 '!L15-'S | 01 '!L15,'[3]S | 01 '!L15-'S | 01 '!L15,"") | M15: =IF('[3]S | 01 '!M15-'S | 01 '!M15,'[3]S | 01 '!M15-'S | 01 '!M15,"") | N15: =IF('[3]S | 01 '!N15-'S | 01 '!N15,'[3]S | 01 '!N15-'S | 01 '!N15,"") | O15: =IF('[3]S | 01 '!O15-'S | 01 '!O15,'[3]S | 01 '!O15-'S | 01 '!O15,"") | P15: =IF('[3]S | 01 '!P15-'S | 01 '!P15,'[3]S | 01 '!P15-'S | 01 '!P15,"") | Q15: =IF('[3]S | 01 '!R15-'S | 01 '!Q15,'[3]S | 01 '!R15-'S | 01 '!Q15,"")
C16: Jysan Technologies | D16: Realized | E16: Sushil | F16: Mozn 1 | G16: 2021 | H16: A (Ordinary Shares) | I16: =IF('[3]S | 01 '!I16-'S | 01 '!I16,'[3]S | 01 '!I16-'S | 01 '!I16,"") | J16: =IF('[3]S | 01 '!J16-'S | 01 '!J16,'[3]S | 01 '!J16-'S | 01 '!J16,"") | K16: =IF('[3]S | 01 '!K16-'S | 01 '!K16,'[3]S | 01 '!K16-'S | 01 '!K16,"") | L16: =IF('[3]S | 01 '!L16-'S | 01 '!L16,'[3]S | 01 '!L16-'S | 01 '!L16,"") | M16: =IF('[3]S | 01 '!M16-'S | 01 '!M16,'[3]S | 01 '!M16-'S | 01 '!M16,"") | N16: =IF('[3]S | 01 '!N16-'S | 01 '!N16,'[3]S | 01 '!N16-'S | 01 '!N16,"") | O16: =IF('[3]S | 01 '!O16-'S | 01 '!O16,'[3]S | 01 '!O16-'S | 01 '!O16,"") | P16: =IF('[3]S | 01 '!P16-'S | 01 '!P16,'[3]S | 01 '!P16-'S | 01 '!P16,"") | Q16: =IF('[3]S | 01 '!R16-'S | 01 '!Q16,'[3]S | 01 '!R16-'S | 01 '!Q16,"")
C17: Cerebras Systems Inc | D17: Unrealized | E17: Ignasi | F17: Mozn | G17: 2021 | H17: F Prefs | I17: =IF('[3]S | 01 '!I17-'S | 01 '!I17,'[3]S | 01 '!I17-'S | 01 '!I17,"") | J17: =IF('[3]S | 01 '!J17-'S | 01 '!J17,'[3]S | 01 '!J17-'S | 01 '!J17,"") | K17: =IF('[3]S | 01 '!K17-'S | 01 '!K17,'[3]S | 01 '!K17-'S | 01 '!K17,"") | L17: =IF('[3]S | 01 '!L17-'S | 01 '!L17,'[3]S | 01 '!L17-'S | 01 '!L17,"") | M17: =IF('[3]S | 01 '!M17-'S | 01 '!M17,'[3]S | 01 '!M17-'S | 01 '!M17,"") | N17: =IF('[3]S | 01 '!N17-'S | 01 '!N17,'[3]S | 01 '!N17-'S | 01 '!N17,"") -> 18.8645 | O17: =IF('[3]S | 01 '!O17-'S | 01 '!O17,'[3]S | 01 '!O17-'S | 01 '!O17,"") -> 18.8645 | P17: =IF('[3]S | 01 '!P17-'S | 01 '!P17,'[3]S | 01 '!P17-'S | 01 '!P17,"") -> 0.4716127 | Q17: =IF('[3]S | 01 '!R17-'S | 01 '!Q17,'[3]S | 01 '!R17-'S | 01 '!Q17,"")
C18: Endless Studios LLC | D18: Unrealized | E18: Sushil | F18: Mozn | G18: 2021 | H18: A Pref Units | I18: =IF('[3]S | 01 '!I18-'S | 01 '!I18,'[3]S | 01 '!I18-'S | 01 '!I18,"") | J18: =IF('[3]S | 01 '!J18-'S | 01 '!J18,'[3]S | 01 '!J18-'S | 01 '!J18,"") | K18: =IF('[3]S | 01 '!K18-'S | 01 '!K18,'[3]S | 01 '!K18-'S | 01 '!K18,"") | L18: =IF('[3]S | 01 '!L18-'S | 01 '!L18,'[3]S | 01 '!L18-'S | 01 '!L18,"") | M18: =IF('[3]S | 01 '!M18-'S | 01 '!M18,'[3]S | 01 '!M18-'S | 01 '!M18,"") | N18: =IF('[3]S | 01 '!N18-'S | 01 '!N18,'[3]S | 01 '!N18-'S | 01 '!N18,"") | O18: =IF('[3]S | 01 '!O18-'S | 01 '!O18,'[3]S | 01 '!O18-'S | 01 '!O18,"") | P18: =IF('[3]S | 01 '!P18-'S | 01 '!P18,'[3]S | 01 '!P18-'S | 01 '!P18,"") | Q18: =IF('[3]S | 01 '!R18-'S | 01 '!Q18,'[3]S | 01 '!R18-'S | 01 '!Q18,"")
C19: Instadeep Limited | D19: Realized | E19: Ignasi | F19: Mozn | G19: 2021 | H19: B Prefs | I19: =IF('[3]S | 01 '!I19-'S | 01 '!I19,'[3]S | 01 '!I19-'S | 01 '!I19,"") | J19: =IF('[3]S | 01 '!J19-'S | 01 '!J19,'[3]S | 01 '!J19-'S | 01 '!J19,"") | K19: =IF('[3]S | 01 '!K19-'S | 01 '!K19,'[3]S | 01 '!K19-'S | 01 '!K19,"") | L19: =IF('[3]S | 01 '!L19-'S | 01 '!L19,'[3]S | 01 '!L19-'S | 01 '!L19,"") | M19: =IF('[3]S | 01 '!M19-'S | 01 '!M19,'[3]S | 01 '!M19-'S | 01 '!M19,"") | N19: =IF('[3]S | 01 '!N19-'S | 01 '!N19,'[3]S | 01 '!N19-'S | 01 '!N19,"") | O19: =IF('[3]S | 01 '!O19-'S | 01 '!O19,'[3]S | 01 '!O19-'S | 01 '!O19,"") | P19: =IF('[3]S | 01 '!P19-'S | 01 '!P19,'[3]S | 01 '!P19-'S | 01 '!P19,"") | Q19: =IF('[3]S | 01 '!R19-'S | 01 '!Q19,'[3]S | 01 '!R19-'S | 01 '!Q19,"")
C20: X-fusion | D20: Realized | E20: Elaine | F20: Mozn 2 | G20: 2022 | H20: Equity-TBC | I20: =IF('[3]S | 01 '!I20-'S | 01 '!I20,'[3]S | 01 '!I20-'S | 01 '!I20,"") | J20: =IF('[3]S | 01 '!J20-'S | 01 '!J20,'[3]S | 01 '!J20-'S | 01 '!J20,"") | K20: =IF('[3]S | 01 '!K20-'S | 01 '!K20,'[3]S | 01 '!K20-'S | 01 '!K20,"") | L20: =IF('[3]S | 01 '!L20-'S | 01 '!L20,'[3]S | 01 '!L20-'S | 01 '!L20,"") | M20: =IF('[3]S | 01 '!M20-'S | 01 '!M20,'[3]S | 01 '!M20-'S | 01 '!M20,"") | N20: =IF('[3]S | 01 '!N20-'S | 01 '!N20,'[3]S | 01 '!N20-'S | 01 '!N20,"") | O20: =IF('[3]S | 01 '!O20-'S | 01 '!O20,'[3]S | 01 '!O20-'S | 01 '!O20,"") | P20: =IF('[3]S | 01 '!P20-'S | 01 '!P20,'[3]S | 01 '!P20-'S | 01 '!P20,"") | Q20: =IF('[3]S | 01 '!R20-'S | 01 '!Q20,'[3]S | 01 '!R20-'S | 01 '!Q20,"")
... C30: Life Biosciences LLC | D30: Unrealized | E30: Divyesh | F30: G42 Capital | G30: 2024 | H30: Convertible Note | I30: =IF('[3]S | 01 '!I30-'S | 01 '!I30,'[3]S | 01 '!I30-'S | 01 '!I30,"") -> #VALUE! | J30: =IF('[3]S | 01 '!J30-'S | 01 '!J30,'[3]S | 01 '!J30-'S | 01 '!J30,"") | K30: =IF('[3]S | 01 '!K30-'S | 01 '!K30,'[3]S | 01 '!K30-'S | 01 '!K30,"") | L30: =IF('[3]S | 01 '!L30-'S | 01 '!L30,'[3]S | 01 '!L30-'S | 01 '!L30,"") | M30: =IF('[3]S | 01 '!M30-'S | 01 '!M30,'[3]S | 01 '!M30-'S | 01 '!M30,"") | N30: =IF('[3]S | 01 '!N30-'S | 01 '!N30,'[3]S | 01 '!N30-'S | 01 '!N30,"") | O30: =IF('[3]S | 01 '!O30-'S | 01 '!O30,'[3]S | 01 '!O30-'S | 01 '!O30,"") | P30: =IF('[3]S | 01 '!P30-'S | 01 '!P30,'[3]S | 01 '!P30-'S | 01 '!P30,"") -> #VALUE! | Q30: =IF('[3]S | 01 '!R30-'S | 01 '!Q30,'[3]S | 01 '!R30-'S | 01 '!Q30,"")
I31: =IF('[3]S | 01 '!I31-'S | 01 '!I32,'[3]S | 01 '!I31-'S | 01 '!I32,"") | J31: =IF('[3]S | 01 '!J31-'S | 01 '!J32,'[3]S | 01 '!J31-'S | 01 '!J32,"") | K31: =IF('[3]S | 01 '!K31-'S | 01 '!K32,'[3]S | 01 '!K31-'S | 01 '!K32,"") | L31: =IF('[3]S | 01 '!L31-'S | 01 '!L32,'[3]S | 01 '!L31-'S | 01 '!L32,"") | M31: =IF('[3]S | 01 '!M31-'S | 01 '!M32,'[3]S | 01 '!M31-'S | 01 '!M32,"") | N31: =IF('[3]S | 01 '!N31-'S | 01 '!N32,'[3]S | 01 '!N31-'S | 01 '!N32,"") | O31: =IF('[3]S | 01 '!O31-'S | 01 '!O32,'[3]S | 01 '!O31-'S | 01 '!O32,"") | P31: =IF('[3]S | 01 '!P31-'S | 01 '!P32,'[3]S | 01 '!P31-'S | 01 '!P32,"") | Q31: =IF('[3]S | 01 '!R31-'S | 01 '!Q32,'[3]S | 01 '!R31-'S | 01 '!Q32,"")
I32: =IF('[3]S | 01 '!I32-'S | 01 '!I33,'[3]S | 01 '!I32-'S | 01 '!I33,"") | J32: =IF('[3]S | 01 '!J32-'S | 01 '!J33,'[3]S | 01 '!J32-'S | 01 '!J33,"") -> -10 | K32: =IF('[3]S | 01 '!K32-'S | 01 '!K33,'[3]S | 01 '!K32-'S | 01 '!K33,"") -> -10 | L32: =IF('[3]S | 01 '!L32-'S | 01 '!L33,'[3]S | 01 '!L32-'S | 01 '!L33,"") | M32: =IF('[3]S | 01 '!M32-'S | 01 '!M33,'[3]S | 01 '!M32-'S | 01 '!M33,"") | N32: =IF('[3]S | 01 '!N32-'S | 01 '!N33,'[3]S | 01 '!N32-'S | 01 '!N33,"") -> 38.644855 | O32: =IF('[3]S | 01 '!O32-'S | 01 '!O33,'[3]S | 01 '!O32-'S | 01 '!O33,"") -> 48.644855 | P32: =IF('[3]S | 01 '!P32-'S | 01 '!P33,'[3]S | 01 '!P32-'S | 01 '!P33,"") -> 0.022431914 | Q32: =IF('[3]S | 01 '!R32-'S | 01 '!Q33,'[3]S | 01 '!R32-'S | 01 '!Q33,"")
I33: =IF('[3]S | 01 '!I33-'S | 01 '!I34,'[3]S | 01 '!I33-'S | 01 '!I34,"") | J33: =IF('[3]S | 01 '!J33-'S | 01 '!J34,'[3]S | 01 '!J33-'S | 01 '!J34,"") | K33: =IF('[3]S | 01 '!K33-'S | 01 '!K34,'[3]S | 01 '!K33-'S | 01 '!K34,"") | L33: =IF('[3]S | 01 '!L33-'S | 01 '!L34,'[3]S | 01 '!L33-'S | 01 '!L34,"") | M33: =IF('[3]S | 01 '!M33-'S | 01 '!M34,'[3]S | 01 '!M33-'S | 01 '!M34,"") | N33: =IF('[3]S | 01 '!N33-'S | 01 '!N34,'[3]S | 01 '!N33-'S | 01 '!N34,"") | O33: =IF('[3]S | 01 '!O33-'S | 01 '!O34,'[3]S | 01 '!O33-'S | 01 '!O34,"") | P33: =IF('[3]S | 01 '!P33-'S | 01 '!P34,'[3]S | 01 '!P33-'S | 01 '!P34,"") | Q33: =IF('[3]S | 01 '!R33-'S | 01 '!Q34,'[3]S | 01 '!R33-'S | 01 '!Q34,"")
C34: Debt Investments | I34: =IF('[3]S | 01 '!I34-'S | 01 '!I35,'[3]S | 01 '!I34-'S | 01 '!I35,"") | J34: =IF('[3]S | 01 '!J34-'S | 01 '!J35,'[3]S | 01 '!J34-'S | 01 '!J35,"") | K34: =IF('[3]S | 01 '!K34-'S | 01 '!K35,'[3]S | 01 '!K34-'S | 01 '!K35,"") | L34: =IF('[3]S | 01 '!L34-'S | 01 '!L35,'[3]S | 01 '!L34-'S | 01 '!L35,"") | M34: =IF('[3]S | 01 '!M34-'S | 01 '!M35,'[3]S | 01 '!M34-'S | 01 '!M35,"") | N34: =IF('[3]S | 01 '!N34-'S | 01 '!N35,'[3]S | 01 '!N34-'S | 01 '!N35,"") | O34: =IF('[3]S | 01 '!O34-'S | 01 '!O35,'[3]S | 01 '!O34-'S | 01 '!O35,"") | P34: =IF('[3]S | 01 '!P34-'S | 01 '!P35,'[3]S | 01 '!P34-'S | 01 '!P35,"") | Q34: =IF('[3]S | 01 '!R34-'S | 01 '!Q35,'[3]S | 01 '!R34-'S | 01 '!Q35,"")
C35: Glass Earth Holdings LLC | D35: Written-off | E35: Marty | F35: Mozn | G35: 2019 | H35: Promissory Note | I35: =IF('[3]S | 01 '!I35-'S | 01 '!I36,'[3]S | 01 '!I35-'S | 01 '!I36,"") -> #VALUE! | J35: =IF('[3]S | 01 '!J35-'S | 01 '!J36,'[3]S | 01 '!J35-'S | 01 '!J36,"") | K35: =IF('[3]S | 01 '!K35-'S | 01 '!K36,'[3]S | 01 '!K35-'S | 01 '!K36,"") | L35: =IF('[3]S | 01 '!L35-'S | 01 '!L36,'[3]S | 01 '!L35-'S | 01 '!L36,"") | M35: =IF('[3]S | 01 '!M35-'S | 01 '!M36,'[3]S | 01 '!M35-'S | 01 '!M36,"") | N35: =IF('[3]S | 01 '!N35-'S | 01 '!N36,'[3]S | 01 '!N35-'S | 01 '!N36,"") | O35: =IF('[3]S | 01 '!O35-'S | 01 '!O36,'[3]S | 01 '!O35-'S | 01 '!O36,"") | P35: =IF('[3]S | 01 '!P35-'S | 01 '!P36,'[3]S | 01 '!P35-'S | 01 '!P36,"") | Q35: =IF('[3]S | 01 '!R35-'S | 01 '!Q36,'[3]S | 01 '!R35-'S | 01 '!Q36,"") -> #VALUE!
C36: Mena Mobile Inc (Debt) | D36: Written-off | E36: Elaine | F36: Mozn | G36: 2021 | H36: Loan | I36: =IF('[3]S | 01 '!I36-'S | 01 '!I37,'[3]S | 01 '!I36-'S | 01 '!I37,"") -> #VALUE! | J36: =IF('[3]S | 01 '!J36-'S | 01 '!J37,'[3]S | 01 '!J36-'S | 01 '!J37,"") | K36: =IF('[3]S | 01 '!K36-'S | 01 '!K37,'[3]S | 01 '!K36-'S | 01 '!K37,"") | L36: =IF('[3]S | 01 '!L36-'S | 01 '!L37,'[3]S | 01 '!L36-'S | 01 '!L37,"") | M36: =IF('[3]S | 01 '!M36-'S | 01 '!M37,'[3]S | 01 '!M36-'S | 01 '!M37,"") | N36: =IF('[3]S | 01 '!N36-'S | 01 '!N37,'[3]S | 01 '!N36-'S | 01 '!N37,"") | O36: =IF('[3]S | 01 '!O36-'S | 01 '!O37,'[3]S | 01 '!O36-'S | 01 '!O37,"") | P36: =IF('[3]S | 01 '!P36-'S | 01 '!P37,'[3]S | 01 '!P36-'S | 01 '!P37,"") | Q36: =IF('[3]S | 01 '!R36-'S | 01 '!Q37,'[3]S | 01 '!R36-'S | 01 '!Q37,"") -> #VALUE!
C37: Esyasoft Holding (Debt) | D37: Realized | E37: Sushil | F37: Mozn | G37: 2021 | H37: Loan | I37: =IF('[3]S | 01 '!I37-'S | 01 '!I38,'[3]S | 01 '!I37-'S | 01 '!I38,"") -> #VALUE! | J37: =IF('[3]S | 01 '!J37-'S | 01 '!J38,'[3]S | 01 '!J37-'S | 01 '!J38,"") | K37: =IF('[3]S | 01 '!K37-'S | 01 '!K38,'[3]S | 01 '!K37-'S | 01 '!K38,"") | L37: =IF('[3]S | 01 '!L37-'S | 01 '!L38,'[3]S | 01 '!L37-'S | 01 '!L38,"") | M37: =IF('[3]S | 01 '!M37-'S | 01 '!M38,'[3]S | 01 '!M37-'S | 01 '!M38,"") | N37: =IF('[3]S | 01 '!N37-'S | 01 '!N38,'[3]S | 01 '!N37-'S | 01 '!N38,"") | O37: =IF('[3]S | 01 '!O37-'S | 01 '!O38,'[3]S | 01 '!O37-'S | 01 '!O38,"") | P37: =IF('[3]S | 01 '!P37-'S | 01 '!P38,'[3]S | 01 '!P37-'S | 01 '!P38,"") | Q37: =IF('[3]S | 01 '!R37-'S | 01 '!Q38,'[3]S | 01 '!R37-'S | 01 '!Q38,"")
I38: =IF('[3]S | 01 '!I38-'S | 01 '!I39,'[3]S | 01 '!I38-'S | 01 '!I39,"") | J38: =IF('[3]S | 01 '!J38-'S | 01 '!J39,'[3]S | 01 '!J38-'S | 01 '!J39,"") | K38: =IF('[3]S | 01 '!K38-'S | 01 '!K39,'[3]S | 01 '!K38-'S | 01 '!K39,"") | L38: =IF('[3]S | 01 '!L38-'S | 01 '!L39,'[3]S | 01 '!L38-'S | 01 '!L39,"") | M38: =IF('[3]S | 01 '!M38-'S | 01 '!M39,'[3]S | 01 '!M38-'S | 01 '!M39,"") | N38: =IF('[3]S | 01 '!N38-'S | 01 '!N39,'[3]S | 01 '!N38-'S | 01 '!N39,"") | O38: =IF('[3]S | 01 '!O38-'S | 01 '!O39,'[3]S | 01 '!O38-'S | 01 '!O39,"") | P38: =IF('[3]S | 01 '!P38-'S | 01 '!P39,'[3]S | 01 '!P38-'S | 01 '!P39,"") | Q38: =IF('[3]S | 01 '!R38-'S | 01 '!Q39,'[3]S | 01 '!R38-'S | 01 '!Q39,"")
I39: =IF('[3]S | 01 '!I39-'S | 01 '!I40,'[3]S | 01 '!I39-'S | 01 '!I40,"") | J39: =IF('[3]S | 01 '!J39-'S | 01 '!J40,'[3]S | 01 '!J39-'S | 01 '!J40,"") | K39: =IF('[3]S | 01 '!K39-'S | 01 '!K40,'[3]S | 01 '!K39-'S | 01 '!K40,"") | L39: =IF('[3]S | 01 '!L39-'S | 01 '!L40,'[3]S | 01 '!L39-'S | 01 '!L40,"") | M39: =IF('[3]S | 01 '!M39-'S | 01 '!M40,'[3]S | 01 '!M39-'S | 01 '!M40,"") | N39: =IF('[3]S | 01 '!N39-'S | 01 '!N40,'[3]S | 01 '!N39-'S | 01 '!N40,"") | O39: =IF('[3]S | 01 '!O39-'S | 01 '!O40,'[3]S | 01 '!O39-'S | 01 '!O40,"") | P39: =IF('[3]S | 01 '!P39-'S | 01 '!P40,'[3]S | 01 '!P39-'S | 01 '!P40,"") | Q39: =IF('[3]S | 01 '!R39-'S | 01 '!Q40,'[3]S | 01 '!R39-'S | 01 '!Q40,"")
C40: Funds Investments | I40: =IF('[3]S | 01 '!I40-'S | 01 '!I41,'[3]S | 01 '!I40-'S | 01 '!I41,"") | J40: =IF('[3]S | 01 '!J40-'S | 01 '!J41,'[3]S | 01 '!J40-'S | 01 '!J41,"") | K40: =IF('[3]S | 01 '!K40-'S | 01 '!K41,'[3]S | 01 '!K40-'S | 01 '!K41,"") | L40: =IF('[3]S | 01 '!L40-'S | 01 '!L41,'[3]S | 01 '!L40-'S | 01 '!L41,"") | M40: =IF('[3]S | 01 '!M40-'S | 01 '!M41,'[3]S | 01 '!M40-'S | 01 '!M41,"") | N40: =IF('[3]S | 01 '!N40-'S | 01 '!N41,'[3]S | 01 '!N40-'S | 01 '!N41,"") | O40: =IF('[3]S | 01 '!O40-'S | 01 '!O41,'[3]S | 01 '!O40-'S | 01 '!O41,"") | P40: =IF('[3]S | 01 '!P40-'S | 01 '!P41,'[3]S | 01 '!P40-'S | 01 '!P41,"") | Q40: =IF('[3]S | 01 '!R40-'S | 01 '!Q41,'[3]S | 01 '!R40-'S | 01 '!Q41,"")
C41: New Space Capital Fund I | D41: Unrealized | E41: Sushil | F41: G42 Investments | G41: 2020 | H41: LP | I41: =IF('[3]S | 01 '!I41-'S | 01 '!I42,'[3]S | 01 '!I41-'S | 01 '!I42,"") -> #VALUE! | J41: =IF('[3]S | 01 '!J41-'S | 01 '!J42,'[3]S | 01 '!J41-'S | 01 '!J42,"") -> 0.98477413 | K41: =IF('[3]S | 01 '!K41-'S | 01 '!K42,'[3]S | 01 '!K41-'S | 01 '!K42,"") -> -1.7173904 | L41: =IF('[3]S | 01 '!L41-'S | 01 '!L42,'[3]S | 01 '!L41-'S | 01 '!L42,"") -> -0.22896252 | M41: =IF('[3]S | 01 '!M41-'S | 01 '!M42,'[3]S | 01 '!M41-'S | 01 '!M42,"") -> -0.46369473 | N41: =IF('[3]S | 01 '!N41-'S | 01 '!N42,'[3]S | 01 '!N41-'S | 01 '!N42,"") -> -3.1449923 | O41: =IF('[3]S | 01 '!O41-'S | 01 '!O42,'[3]S | 01 '!O41-'S | 01 '!O42,"") -> -1.8912967 | P41: =IF('[3]S | 01 '!P41-'S | 01 '!P42,'[3]S | 01 '!P41-'S | 01 '!P42,"") -> -0.081722431 | Q41: =IF('[3]S | 01 '!R41-'S | 01 '!Q42,'[3]S | 01 '!R41-'S | 01 '!Q42,"")
C42: New Space Capital GP Com SCSp | D42: Unrealized | E42: Sushil | F42: G42 Investments | G42: 2023 | H42: LP | I42: =IF('[3]S | 01 '!I42-'S | 01 '!I43,'[3]S | 01 '!I42-'S | 01 '!I43,"") -> #VALUE! | J42: =IF('[3]S | 01 '!J42-'S | 01 '!J43,'[3]S | 01 '!J42-'S | 01 '!J43,"") | K42: =IF('[3]S | 01 '!K42-'S | 01 '!K43,'[3]S | 01 '!K42-'S | 01 '!K43,"") | L42: =IF('[3]S | 01 '!L42-'S | 01 '!L43,'[3]S | 01 '!L42-'S | 01 '!L43,"") | M42: =IF('[3]S | 01 '!M42-'S | 01 '!M43,'[3]S | 01 '!M42-'S | 01 '!M43,"") | N42: =IF('[3]S | 01 '!N42-'S | 01 '!N43,'[3]S | 01 '!N42-'S | 01 '!N43,"") -> -0.20305944 | O42: =IF('[3]S | 01 '!O42-'S | 01 '!O43,'[3]S | 01 '!O42-'S | 01 '!O43,"") -> -0.20305944 | P42: =IF('[3]S | 01 '!P42-'S | 01 '!P43,'[3]S | 01 '!P42-'S | 01 '!P43,"") -> -0.075043704 | Q42: =IF('[3]S | 01 '!R42-'S | 01 '!Q43,'[3]S | 01 '!R42-'S | 01 '!Q43,"")
C43: North Summit Capital Fund | D43: Unrealized | E43: Elaine | F43: G42 Investments | G43: 2020 | H43: LP | I43: =IF('[3]S | 01 '!I43-'S | 01 '!I44,'[3]S | 01 '!I43-'S | 01 '!I44,"") -> #VALUE! | J43: =IF('[3]S | 01 '!J43-'S | 01 '!J44,'[3]S | 01 '!J43-'S | 01 '!J44,"") -> -0.295997 | K43: =IF('[3]S | 01 '!K43-'S | 01 '!K44,'[3]S | 01 '!K43-'S | 01 '!K44,"") -> -0.055697 | L43: =IF('[3]S | 01 '!L43-'S | 01 '!L44,'[3]S | 01 '!L43-'S | 01 '!L44,"") -> -0.2403 | M43: =IF('[3]S | 01 '!M43-'S | 01 '!M44,'[3]S | 01 '!M43-'S | 01 '!M44,"") | N43: =IF('[3]S | 01 '!N43-'S | 01 '!N44,'[3]S | 01 '!N43-'S | 01 '!N44,"") | O43: =IF('[3]S | 01 '!O43-'S | 01 '!O44,'[3]S | 01 '!O43-'S | 01 '!O44,"") -> 0.055697 | P43: =IF('[3]S | 01 '!P43-'S | 01 '!P44,'[3]S | 01 '!P43-'S | 01 '!P44,"") -> 0.00066346067 | Q43: =IF('[3]S | 01 '!R43-'S | 01 '!Q44,'[3]S | 01 '!R43-'S | 01 '!Q44,"")
C44: Sinovation Disrupt Fund, L.P. | D44: Realized | E44: Elaine | F44: G42 Investments | G44: 2020 | H44: LP | I44: =IF('[3]S | 01 '!I44-'S | 01 '!I45,'[3]S | 01 '!I44-'S | 01 '!I45,"") -> #VALUE! | J44: =IF('[3]S | 01 '!J44-'S | 01 '!J45,'[3]S | 01 '!J44-'S | 01 '!J45,"") | K44: =IF('[3]S | 01 '!K44-'S | 01 '!K45,'[3]S | 01 '!K44-'S | 01 '!K45,"") | L44: =IF('[3]S | 01 '!L44-'S | 01 '!L45,'[3]S | 01 '!L44-'S | 01 '!L45,"") | M44: =IF('[3]S | 01 '!M44-'S | 01 '!M45,'[3]S | 01 '!M44-'S | 01 '!M45,"") | N44: =IF('[3]S | 01 '!N44-'S | 01 '!N45,'[3]S | 01 '!N44-'S | 01 '!N45,"") | O44: =IF('[3]S | 01 '!O44-'S | 01 '!O45,'[3]S | 01 '!O44-'S | 01 '!O45,"") | P44: =IF('[3]S | 01 '!P44-'S | 01 '!P45,'[3]S | 01 '!P44-'S | 01 '!P45,"") | Q44: =IF('[3]S | 01 '!R44-'S | 01 '!Q45,'[3]S | 01 '!R44-'S | 01 '!Q45,"")
C45: Acies Investments Fund I, L.P. | D45: Unrealized | E45: Divyesh | F45: G42 Investments | G45: 2021 | H45: LP | I45: =IF('[3]S | 01 '!I45-'S | 01 '!I46,'[3]S | 01 '!I45-'S | 01 '!I46,"") | J45: =IF('[3]S | 01 '!J45-'S | 01 '!J46,'[3]S | 01 '!J45-'S | 01 '!J46,"") | K45: =IF('[3]S | 01 '!K45-'S | 01 '!K46,'[3]S | 01 '!K45-'S | 01 '!K46,"") | L45: =IF('[3]S | 01 '!L45-'S | 01 '!L46,'[3]S | 01 '!L45-'S | 01 '!L46,"") | M45: =IF('[3]S | 01 '!M45-'S | 01 '!M46,'[3]S | 01 '!M45-'S | 01 '!M46,"") | N45: =IF('[3]S | 01 '!N45-'S | 01 '!N46,'[3]S | 01 '!N45-'S | 01 '!N46,"") -> 1.435213 | O45: =IF('[3]S | 01 '!O45-'S | 01 '!O46,'[3]S | 01 '!O45-'S | 01 '!O46,"") -> 1.435213 | P45: =IF('[3]S | 01 '!P45-'S | 01 '!P46,'[3]S | 01 '!P45-'S | 01 '!P46,"") -> 0.10240449 | Q45: =IF('[3]S | 01 '!R45-'S | 01 '!Q46,'[3]S | 01 '!R45-'S | 01 '!Q46,"") -> #VALUE!
I46: =IF('[3]S | 01 '!I46-'S | 01 '!I47,'[3]S | 01 '!I46-'S | 01 '!I47,"") | J46: =IF('[3]S | 01 '!J46-'S | 01 '!J47,'[3]S | 01 '!J46-'S | 01 '!J47,"") -> 0.68877713 | K46: =IF('[3]S | 01 '!K46-'S | 01 '!K47,'[3]S | 01 '!K46-'S | 01 '!K47,"") -> -1.7730874 | L46: =IF('[3]S | 01 '!L46-'S | 01 '!L47,'[3]S | 01 '!L46-'S | 01 '!L47,"") -> -0.46926252 | M46: =IF('[3]S | 01 '!M46-'S | 01 '!M47,'[3]S | 01 '!M46-'S | 01 '!M47,"") -> -0.46369473 | N46: =IF('[3]S | 01 '!N46-'S | 01 '!N47,'[3]S | 01 '!N46-'S | 01 '!N47,"") -> -1.9128387 | O46: =IF('[3]S | 01 '!O46-'S | 01 '!O47,'[3]S | 01 '!O46-'S | 01 '!O47,"") -> -0.60344609 | P46: =IF('[3]S | 01 '!P46-'S | 01 '!P47,'[3]S | 01 '!P46-'S | 01 '!P47,"") -> -0.0039837775 | Q46: =IF('[3]S | 01 '!R46-'S | 01 '!Q47,'[3]S | 01 '!R46-'S | 01 '!Q47,"")
I47: =IF('[3]S | 01 '!I47-'S | 01 '!I48,'[3]S | 01 '!I47-'S | 01 '!I48,"") | J47: =IF('[3]S | 01 '!J47-'S | 01 '!J48,'[3]S | 01 '!J47-'S | 01 '!J48,"") | K47: =IF('[3]S | 01 '!K47-'S | 01 '!K48,'[3]S | 01 '!K47-'S | 01 '!K48,"") | L47: =IF('[3]S | 01 '!L47-'S | 01 '!L48,'[3]S | 01 '!L47-'S | 01 '!L48,"") | M47: =IF('[3]S | 01 '!M47-'S | 01 '!M48,'[3]S | 01 '!M47-'S | 01 '!M48,"") | N47: =IF('[3]S | 01 '!N47-'S | 01 '!N48,'[3]S | 01 '!N47-'S | 01 '!N48,"") | O47: =IF('[3]S | 01 '!O47-'S | 01 '!O48,'[3]S | 01 '!O47-'S | 01 '!O48,"") | P47: =IF('[3]S | 01 '!P47-'S | 01 '!P48,'[3]S | 01 '!P47-'S | 01 '!P48,"") | Q47: =IF('[3]S | 01 '!R47-'S | 01 '!Q48,'[3]S | 01 '!R47-'S | 01 '!Q48,"")
C48: Total | I48: =IF('[3]S | 01 '!I48-'S | 01 '!I49,'[3]S | 01 '!I48-'S | 01 '!I49,"") | J48: =IF('[3]S | 01 '!J48-'S | 01 '!J49,'[3]S | 01 '!J48-'S | 01 '!J49,"") -> -9.3112229 | K48: =IF('[3]S | 01 '!K48-'S | 01 '!K49,'[3]S | 01 '!K48-'S | 01 '!K49,"") -> -11.773087 | L48: =IF('[3]S | 01 '!L48-'S | 01 '!L49,'[3]S | 01 '!L48-'S | 01 '!L49,"") -> -0.46926252 | M48: =IF('[3]S | 01 '!M48-'S | 01 '!M49,'[3]S | 01 '!M48-'S | 01 '!M49,"") -> -0.46369473 | N48: =IF('[3]S | 01 '!N48-'S | 01 '!N49,'[3]S | 01 '!N48-'S | 01 '!N49,"") -> 36.732016 | O48: =IF('[3]S | 01 '!O48-'S | 01 '!O49,'[3]S | 01 '!O48-'S | 01 '!O49,"") -> 48.041409 | P48: =IF('[3]S | 01 '!P48-'S | 01 '!P49,'[3]S | 01 '!P48-'S | 01 '!P49,"") -> 0.020654681 | Q48: =IF('[3]S | 01 '!R48-'S | 01 '!Q49,'[3]S | 01 '!R48-'S | 01 '!Q49,"")
I49: =IF('[3]S | 01 '!I49-'S | 01 '!I50,'[3]S | 01 '!I49-'S | 01 '!I50,"") | J49: =IF('[3]S | 01 '!J49-'S | 01 '!J50,'[3]S | 01 '!J49-'S | 01 '!J50,"") | K49: =IF('[3]S | 01 '!K49-'S | 01 '!K50,'[3]S | 01 '!K49-'S | 01 '!K50,"") -> 1 | L49: =IF('[3]S | 01 '!L49-'S | 01 '!L50,'[3]S | 01 '!L49-'S | 01 '!L50,"") | M49: =IF('[3]S | 01 '!M49-'S | 01 '!M50,'[3]S | 01 '!M49-'S | 01 '!M50,"") -> 1 | N49: =IF('[3]S | 01 '!N49-'S | 01 '!N50,'[3]S | 01 '!N49-'S | 01 '!N50,"") -> 1 | O49: =IF('[3]S | 01 '!O49-'S | 01 '!O50,'[3]S | 01 '!O49-'S | 01 '!O50,"") | P49: =IF('[3]S | 01 '!P49-'S | 01 '!P50,'[3]S | 01 '!P49-'S | 01 '!P50,"") | Q49: =IF('[3]S | 01 '!R49-'S | 01 '!Q50,'[3]S | 01 '!R49-'S | 01 '!Q50,"")

Sheet 5. CF Profile
C2: CASH DEPLOYED OVER TIME…
C5: Investment | D5: Type | E5: Payment date | F5: Period | G5: Contribution | H5: Distribution | J5: Contribution | K5: Equity | L5: Debt | M5: Fund | N5: Total | P5: Distribution | Q5: Equity | R5: Debt | S5: Fund | T5: Total
B6: Equity | C6: ='CF (Equity, Debt)'!C4 -> Jollychic Holding Limited | D6: Equity | E6: ='CF (Equity, Debt)'!D4 -> 43470 | F6: ="Q"&ROUNDUP(MONTH(E6)/3,0)&" "&YEAR(E6) -> Q1 2019 | G6: ='CF (Equity, Debt)'!E4 -> -30 | H6: ='CF (Equity, Debt)'!F4 -> 0
C7: ='CF (Equity, Debt)'!C5 -> Jollychic Holding Limited | D7: Equity | E7: ='CF (Equity, Debt)'!D5 -> 43724 | F7: ="Q"&ROUNDUP(MONTH(E7)/3,0)&" "&YEAR(E7) -> Q3 2019 | G7: ='CF (Equity, Debt)'!E5 -> -20 | H7: ='CF (Equity, Debt)'!F5 -> 0 | J7: Q1 2019 | K7: =-SUMIFS($G$5:$G$125,$D$5:$D$125,$K$5,$F$5:$F$125,J7) -> 30 | L7: =-SUMIFS($G$5:$G$125,$D$5:$D$125,$L$5,$F$5:$F$125,J7) -> 0 | M7: =-SUMIFS($G$5:$G$125,$D$5:$D$125,"Fund",$F$5:$F$125,J7) -> 0 | N7: =-SUMIF($F$5:$H$125,$J7,$G$5:$G$125) -> 30 | P7: Q1 2019 | Q7: =SUMIFS($H$5:$H$125,$D$5:$D$125,$Q$5,$F$5:$F$125,J7) -> 0 | R7: =SUMIFS($H$5:$H$125,$D$5:$D$125,$R$5,$F$5:$F$125,J7) -> 0 | S7: =SUMIFS($H$5:$H$125,$D$5:$D$125,$S$5,$F$5:$F$125,J7) -> 0 | T7: =SUMIF($F$5:$H$125,$J7,$H$5:$H$125) -> 0
C8: ='CF (Equity, Debt)'!C6 -> Jollychic Holding Limited | D8: Equity | E8: ='CF (Equity, Debt)'!D6 -> 43724 | F8: ="Q"&ROUNDUP(MONTH(E8)/3,0)&" "&YEAR(E8) -> Q3 2019 | G8: ='CF (Equity, Debt)'!E6 -> -15 | H8: ='CF (Equity, Debt)'!F6 -> 0 | J8: Q2 2019 | K8: =-SUMIFS($G$5:$G$125,$D$5:$D$125,$K$5,$F$5:$F$125,J8) -> 12.999998 | L8: =-SUMIFS($G$5:$G$125,$D$5:$D$125,$L$5,$F$5:$F$125,J8) -> 8 | M8: =-SUMIFS($G$5:$G$125,$D$5:$D$125,"Fund",$F$5:$F$125,J8) -> 0 | N8: =-SUMIF($F$5:$H$125,$J8,$G$5:$G$125) -> 20.999998 | P8: Q2 2019 | Q8: =SUMIFS($H$5:$H$125,$D$5:$D$125,$Q$5,$F$5:$F$125,J8) -> 0 | R8: =SUMIFS($H$5:$H$125,$D$5:$D$125,$R$5,$F$5:$F$125,J8) -> 0 | S8: =SUMIFS($H$5:$H$125,$D$5:$D$125,$S$5,$F$5:$F$125,J8) -> 0 | T8: =SUMIF($F$5:$H$125,$J8,$H$5:$H$125) -> 0
C9: ='CF (Equity, Debt)'!C7 -> Mena Mobile Inc | D9: Equity | E9: ='CF (Equity, Debt)'!D7 -> 43563 | F9: ="Q"&ROUNDUP(MONTH(E9)/3,0)&" "&YEAR(E9) -> Q2 2019 | G9: ='CF (Equity, Debt)'!E7 -> -8 | H9: ='CF (Equity, Debt)'!F7 -> 0 | J9: Q3 2019 | K9: =-SUMIFS($G$5:$G$125,$D$5:$D$125,$K$5,$F$5:$F$125,J9) -> 35 | L9: =-SUMIFS($G$5:$G$125,$D$5:$D$125,$L$5,$F$5:$F$125,J9) -> 0 | M9: =-SUMIFS($G$5:$G$125,$D$5:$D$125,"Fund",$F$5:$F$125,J9) -> 3 | N9: =-SUMIF($F$5:$H$125,$J9,$G$5:$G$125) -> 38 | P9: Q3 2019 | Q9: =SUMIFS($H$5:$H$125,$D$5:$D$125,$Q$5,$F$5:$F$125,J9) -> 0 | R9: =SUMIFS($H$5:$H$125,$D$5:$D$125,$R$5,$F$5:$F$125,J9) -> 0 | S9: =SUMIFS($H$5:$H$125,$D$5:$D$125,$S$5,$F$5:$F$125,J9) -> 0 | T9: =SUMIF($F$5:$H$125,$J9,$H$5:$H$125) -> 0
C10: ='CF (Equity, Debt)'!C8 -> Flyr Inc | D10: Equity | E10: ='CF (Equity, Debt)'!D8 -> 43570 | F10: ="Q"&ROUNDUP(MONTH(E10)/3,0)&" "&YEAR(E10) -> Q2 2019 | G10: ='CF (Equity, Debt)'!E8 -> -4.9999981 | H10: ='CF (Equity, Debt)'!F8 -> 0 | J10: Q4 2019 | K10: =-SUMIFS($G$5:$G$125,$D$5:$D$125,$K$5,$F$5:$F$125,J10) -> 0 | L10: =-SUMIFS($G$5:$G$125,$D$5:$D$125,$L$5,$F$5:$F$125,J10) -> 0 | M10: =-SUMIFS($G$5:$G$125,$D$5:$D$125,"Fund",$F$5:$F$125,J10) -> 0 | N10: =-SUMIF($F$5:$H$125,$J10,$G$5:$G$125) -> 0 | P10: Q4 2019 | Q10: =SUMIFS($H$5:$H$125,$D$5:$D$125,$Q$5,$F$5:$F$125,J10) -> 0 | R10: =SUMIFS($H$5:$H$125,$D$5:$D$125,$R$5,$F$5:$F$125,J10) -> 0 | S10: =SUMIFS($H$5:$H$125,$D$5:$D$125,$S$5,$F$5:$F$125,J10) -> 0 | T10: =SUMIF($F$5:$H$125,$J10,$H$5:$H$125) -> 0
C11: ='CF (Equity, Debt)'!C9 -> Flyr Inc | D11: Equity | E11: ='CF (Equity, Debt)'!D9 -> 43915 | F11: ="Q"&ROUNDUP(MONTH(E11)/3,0)&" "&YEAR(E11) -> Q1 2020 | G11: ='CF (Equity, Debt)'!E9 -> -5.0000019 | H11: ='CF (Equity, Debt)'!F9 -> 0 | J11: Q1 2020 | K11: =-SUMIFS($G$5:$G$125,$D$5:$D$125,$K$5,$F$5:$F$125,J11) -> 75.609443 | L11: =-SUMIFS($G$5:$G$125,$D$5:$D$125,$L$5,$F$5:$F$125,J11) -> 0 | M11: =-SUMIFS($G$5:$G$125,$D$5:$D$125,"Fund",$F$5:$F$125,J11) -> 9.50975 | N11: =-SUMIF($F$5:$H$125,$J11,$G$5:$G$125) -> 85.119193 | P11: Q1 2020 | Q11: =SUMIFS($H$5:$H$125,$D$5:$D$125,$Q$5,$F$5:$F$125,J11) -> 0 | R11: =SUMIFS($H$5:$H$125,$D$5:$D$125,$R$5,$F$5:$F$125,J11) -> 0 | S11: =SUMIFS($H$5:$H$125,$D$5:$D$125,$S$5,$F$5:$F$125,J11) -> 0 | T11: =SUMIF($F$5:$H$125,$J11,$H$5:$H$125) -> 0
C12: ='CF (Equity, Debt)'!C10 -> Esyasoft Holding | D12: Equity | E12: ='CF (Equity, Debt)'!D10 -> 43870 | F12: ="Q"&ROUNDUP(MONTH(E12)/3,0)&" "&YEAR(E12) -> Q1 2020 | G12: ='CF (Equity, Debt)'!E10 -> -2.5 | H12: ='CF (Equity, Debt)'!F10 -> 0 | J12: Q2 2020 | K12: =-SUMIFS($G$5:$G$125,$D$5:$D$125,$K$5,$F$5:$F$125,J12) -> 142.12004 | L12: =-SUMIFS($G$5:$G$125,$D$5:$D$125,$L$5,$F$5:$F$125,J12) -> 0 | M12: =-SUMIFS($G$5:$G$125,$D$5:$D$125,"Fund",$F$5:$F$125,J12) -> 45.785 | N12: =-SUMIF($F$5:$H$125,$J12,$G$5:$G$125) -> 187.90504 | P12: Q2 2020 | Q12: =SUMIFS($H$5:$H$125,$D$5:$D$125,$Q$5,$F$5:$F$125,J12) -> 0 | R12: =SUMIFS($H$5:$H$125,$D$5:$D$125,$R$5,$F$5:$F$125,J12) -> 0 | S12: =SUMIFS($H$5:$H$125,$D$5:$D$125,$S$5,$F$5:$F$125,J12) -> 0 | T12: =SUMIF($F$5:$H$125,$J12,$H$5:$H$125) -> 0
C13: ='CF (Equity, Debt)'!C11 -> Beyond Limits | D13: Equity | E13: ='CF (Equity, Debt)'!D11 -> 43879 | F13: ="Q"&ROUNDUP(MONTH(E13)/3,0)&" "&YEAR(E13) -> Q1 2020 | G13: ='CF (Equity, Debt)'!E11 -> -20 | H13: ='CF (Equity, Debt)'!F11 -> 0 | J13: Q3 2020 | K13: =-SUMIFS($G$5:$G$125,$D$5:$D$125,$K$5,$F$5:$F$125,J13) -> 10 | L13: =-SUMIFS($G$5:$G$125,$D$5:$D$125,$L$5,$F$5:$F$125,J13) -> 0 | M13: =-SUMIFS($G$5:$G$125,$D$5:$D$125,"Fund",$F$5:$F$125,J13) -> 23.623435 | N13: =-SUMIF($F$5:$H$125,$J13,$G$5:$G$125) -> 33.623435 | P13: Q3 2020 | Q13: =SUMIFS($H$5:$H$125,$D$5:$D$125,$Q$5,$F$5:$F$125,J13) -> 0 | R13: =SUMIFS($H$5:$H$125,$D$5:$D$125,$R$5,$F$5:$F$125,J13) -> 0 | S13: =SUMIFS($H$5:$H$125,$D$5:$D$125,$S$5,$F$5:$F$125,J13) -> 0 | T13: =SUMIF($F$5:$H$125,$J13,$H$5:$H$125) -> 0
C14: ='CF (Equity, Debt)'!C12 -> Beyond Limits | D14: Equity | E14: ='CF (Equity, Debt)'!D12 -> 43921 | F14: ="Q"&ROUNDUP(MONTH(E14)/3,0)&" "&YEAR(E14) -> Q1 2020 | G14: ='CF (Equity, Debt)'!E12 -> -30 | H14: ='CF (Equity, Debt)'!F12 -> 0 | J14: Q4 2020 | K14: =-SUMIFS($G$5:$G$125,$D$5:$D$125,$K$5,$F$5:$F$125,J14) -> 60 | L14: =-SUMIFS($G$5:$G$125,$D$5:$D$125,$L$5,$F$5:$F$125,J14) -> 0 | M14: =-SUMIFS($G$5:$G$125,$D$5:$D$125,"Fund",$F$5:$F$125,J14) -> 9.482293 | N14: =-SUMIF($F$5:$H$125,$J14,$G$5:$G$125) -> 69.482293 | P14: Q4 2020 | Q14: =SUMIFS($H$5:$H$125,$D$5:$D$125,$Q$5,$F$5:$F$125,J14) -> 0 | R14: =SUMIFS($H$5:$H$125,$D$5:$D$125,$R$5,$F$5:$F$125,J14) -> 0 | S14: =SUMIFS($H$5:$H$125,$D$5:$D$125,$S$5,$F$5:$F$125,J14) -> 0.582902 | T14: =SUMIF($F$5:$H$125,$J14,$H$5:$H$125) -> 0.582902
C15: ='CF (Equity, Debt)'!C13 -> Beyond Limits | D15: Equity | E15: ='CF (Equity, Debt)'!D13 -> 43989 | F15: ="Q"&ROUNDUP(MONTH(E15)/3,0)&" "&YEAR(E15) -> Q2 2020 | G15: ='CF (Equity, Debt)'!E13 -> -30 | H15: ='CF (Equity, Debt)'!F13 -> 0 | J15: Q1 2021 | K15: =-SUMIFS($G$5:$G$125,$D$5:$D$125,$K$5,$F$5:$F$125,J15) -> 0 | L15: =-SUMIFS($G$5:$G$125,$D$5:$D$125,$L$5,$F$5:$F$125,J15) -> 0 | M15: =-SUMIFS($G$5:$G$125,$D$5:$D$125,"Fund",$F$5:$F$125,J15) -> 1.0845116 | N15: =-SUMIF($F$5:$H$125,$J15,$G$5:$G$125) -> 1.0845116 | P15: Q1 2021 | Q15: =SUMIFS($H$5:$H$125,$D$5:$D$125,$Q$5,$F$5:$F$125,J15) -> 0 | R15: =SUMIFS($H$5:$H$125,$D$5:$D$125,$R$5,$F$5:$F$125,J15) -> 0 | S15: =SUMIFS($H$5:$H$125,$D$5:$D$125,$S$5,$F$5:$F$125,J15) -> 0.07634835 | T15: =SUMIF($F$5:$H$125,$J15,$H$5:$H$125) -> 0.07634835
C16: ='CF (Equity, Debt)'!C14 -> Beyond Limits | D16: Equity | E16: ='CF (Equity, Debt)'!D14 -> 44103 | F16: ="Q"&ROUNDUP(MONTH(E16)/3,0)&" "&YEAR(E16) -> Q3 2020 | G16: ='CF (Equity, Debt)'!E14 -> -10 | H16: ='CF (Equity, Debt)'!F14 -> 0 | J16: Q2 2021 | K16: =-SUMIFS($G$5:$G$125,$D$5:$D$125,$K$5,$F$5:$F$125,J16) -> 31.24078 | L16: =-SUMIFS($G$5:$G$125,$D$5:$D$125,$L$5,$F$5:$F$125,J16) -> 2.353982 | M16: =-SUMIFS($G$5:$G$125,$D$5:$D$125,"Fund",$F$5:$F$125,J16) -> 6.1810318 | N16: =-SUMIF($F$5:$H$125,$J16,$G$5:$G$125) -> 39.775794 | P16: Q2 2021 | Q16: =SUMIFS($H$5:$H$125,$D$5:$D$125,$Q$5,$F$5:$F$125,J16) -> 0 | R16: =SUMIFS($H$5:$H$125,$D$5:$D$125,$R$5,$F$5:$F$125,J16) -> 0 | S16: =SUMIFS($H$5:$H$125,$D$5:$D$125,$S$5,$F$5:$F$125,J16) -> 0 | T16: =SUMIF($F$5:$H$125,$J16,$H$5:$H$125) -> 0
C17: ='CF (Equity, Debt)'!C15 -> ONT plc | D17: Equity | E17: ='CF (Equity, Debt)'!D15 -> 43968 | F17: ="Q"&ROUNDUP(MONTH(E17)/3,0)&" "&YEAR(E17) -> Q2 2020 | G17: ='CF (Equity, Debt)'!E15 -> -50 | H17: ='CF (Equity, Debt)'!F15 -> 0 | J17: Q3 2021 | K17: =-SUMIFS($G$5:$G$125,$D$5:$D$125,$K$5,$F$5:$F$125,J17) -> 0 | L17: =-SUMIFS($G$5:$G$125,$D$5:$D$125,$L$5,$F$5:$F$125,J17) -> 0.411765 | M17: =-SUMIFS($G$5:$G$125,$D$5:$D$125,"Fund",$F$5:$F$125,J17) -> 0.98965473 | N17: =-SUMIF($F$5:$H$125,$J17,$G$5:$G$125) -> 1.4014197 | P17: Q3 2021 | Q17: =SUMIFS($H$5:$H$125,$D$5:$D$125,$Q$5,$F$5:$F$125,J17) -> 0 | R17: =SUMIFS($H$5:$H$125,$D$5:$D$125,$R$5,$F$5:$F$125,J17) -> 0 | S17: =SUMIFS($H$5:$H$125,$D$5:$D$125,$S$5,$F$5:$F$125,J17) -> 0.445059 | T17: =SUMIF($F$5:$H$125,$J17,$H$5:$H$125) -> 0.445059
C18: ='CF (Equity, Debt)'!C16 -> ONT plc | D18: Equity | E18: ='CF (Equity, Debt)'!D16 -> 44006 | F18: ="Q"&ROUNDUP(MONTH(E18)/3,0)&" "&YEAR(E18) -> Q2 2020 | G18: ='CF (Equity, Debt)'!E16 -> -27.268351 | H18: ='CF (Equity, Debt)'!F16 -> 0 | J18: Q4 2021 | K18: =-SUMIFS($G$5:$G$125,$D$5:$D$125,$K$5,$F$5:$F$125,J18) -> 48.023704 | L18: =-SUMIFS($G$5:$G$125,$D$5:$D$125,$L$5,$F$5:$F$125,J18) -> 0 | M18: =-SUMIFS($G$5:$G$125,$D$5:$D$125,"Fund",$F$5:$F$125,J18) -> 11.901731 | N18: =-SUMIF($F$5:$H$125,$J18,$G$5:$G$125) -> 59.925434 | P18: Q4 2021 | Q18: =SUMIFS($H$5:$H$125,$D$5:$D$125,$Q$5,$F$5:$F$125,J18) -> 0 | R18: =SUMIFS($H$5:$H$125,$D$5:$D$125,$R$5,$F$5:$F$125,J18) -> 0 | S18: =SUMIFS($H$5:$H$125,$D$5:$D$125,$S$5,$F$5:$F$125,J18) -> 0.139694 | T18: =SUMIF($F$5:$H$125,$J18,$H$5:$H$125) -> 0.139694
... C26: ='CF (Equity, Debt)'!C24 -> Instadeep Limited | D26: Equity | E26: ='CF (Equity, Debt)'!D24 -> 44550 | F26: ="Q"&ROUNDUP(MONTH(E26)/3,0)&" "&YEAR(E26) -> Q4 2021 | G26: ='CF (Equity, Debt)'!E24 -> -5.0237202 | H26: ='CF (Equity, Debt)'!F24 -> 0 | J26: Q4 2023 | K26: =-SUMIFS($G$5:$G$125,$D$5:$D$125,$K$5,$F$5:$F$125,J26) -> 0 | L26: =-SUMIFS($G$5:$G$125,$D$5:$D$125,$L$5,$F$5:$F$125,J26) -> 0 | M26: =-SUMIFS($G$5:$G$125,$D$5:$D$125,"Fund",$F$5:$F$125,J26) -> 2.415861 | N26: =-SUMIF($F$5:$H$125,$J26,$G$5:$G$125) -> 2.415861 | P26: Q4 2023 | Q26: =SUMIFS($H$5:$H$125,$D$5:$D$125,$Q$5,$F$5:$F$125,J26) -> 1205.9214 | R26: =SUMIFS($H$5:$H$125,$D$5:$D$125,$R$5,$F$5:$F$125,J26) -> 0 | S26: =SUMIFS($H$5:$H$125,$D$5:$D$125,$S$5,$F$5:$F$125,J26) -> 0 | T26: =SUMIF($F$5:$H$125,$J26,$H$5:$H$125) -> 1205.9214
C27: ='CF (Equity, Debt)'!C25 -> X-fusion | D27: Equity | E27: ='CF (Equity, Debt)'!D25 -> 44574 | F27: ="Q"&ROUNDUP(MONTH(E27)/3,0)&" "&YEAR(E27) -> Q1 2022 | G27: ='CF (Equity, Debt)'!E25 -> -493.50096 | H27: ='CF (Equity, Debt)'!F25 -> 0 | J27: Total | K27: =SUM(K7:K26) -> 2111.533 | L27: =SUM(L7:L26) -> 10.765747 | M27: =SUM(M7:M26) -> 135.9534 | N27: =SUM(N7:N26) -> 2258.2522 | P27: Total | Q27: =SUM(Q7:Q26) -> 1243.2422 | R27: =SUM(R7:R26) -> 0.47078465 | S27: =SUM(S7:S26) -> 4.4275637 | T27: =SUM(T7:T26) -> 1248.1405
C28: ='CF (Equity, Debt)'!C26 -> DriveNets | D28: Equity | E28: ='CF (Equity, Debt)'!D26 -> 44643 | F28: ="Q"&ROUNDUP(MONTH(E28)/3,0)&" "&YEAR(E28) -> Q1 2022 | G28: ='CF (Equity, Debt)'!E26 -> -200 | H28: ='CF (Equity, Debt)'!F26 -> 0 | K28: =K27='S | 01 '!K33 -> FALSE | L28: =L27='S | 01 '!K39 -> TRUE | M28: =M27='S | 01 '!K47 -> FALSE | N28: =ROUND(N27,2)=ROUND('S | 01 '!K49,2) -> FALSE | Q28: =Q27='S | 01 '!M33 -> TRUE | R28: =R27='S | 01 '!M39 -> TRUE | S28: =S27='S | 01 '!M47 -> FALSE | T28: =T27='S | 01 '!M49 -> FALSE
C29: ='CF (Equity, Debt)'!C27 -> DriveNets | D29: Equity | E29: ='CF (Equity, Debt)'!D27 -> 44680 | F29: ="Q"&ROUNDUP(MONTH(E29)/3,0)&" "&YEAR(E29) -> Q2 2022 | G29: ='CF (Equity, Debt)'!E27 -> -100 | H29: ='CF (Equity, Debt)'!F27 -> 0
C30: ='CF (Equity, Debt)'!C28 -> Esyasoft Holding | D30: Equity | E30: ='CF (Equity, Debt)'!D28 -> 44691 | F30: ="Q"&ROUNDUP(MONTH(E30)/3,0)&" "&YEAR(E30) -> Q2 2022 | G30: ='CF (Equity, Debt)'!E28 -> 0 | H30: ='CF (Equity, Debt)'!F28 -> 5
C31: ='CF (Equity, Debt)'!C29 -> vTv Therapeutics Inc. | D31: Equity | E31: ='CF (Equity, Debt)'!D29 -> 44712 | F31: ="Q"&ROUNDUP(MONTH(E31)/3,0)&" "&YEAR(E31) -> Q2 2022 | G31: ='CF (Equity, Debt)'!E29 -> -12.5 | H31: ='CF (Equity, Debt)'!F29 -> 0
C32: ='CF (Equity, Debt)'!C30 -> Honor Device Co Ltd | D32: Equity | E32: ='CF (Equity, Debt)'!D30 -> 44769 | F32: ="Q"&ROUNDUP(MONTH(E32)/3,0)&" "&YEAR(E32) -> Q3 2022 | G32: ='CF (Equity, Debt)'!E30 -> -600 | H32: ='CF (Equity, Debt)'!F30 -> 0
C33: ='CF (Equity, Debt)'!C31 -> Honor Device Co Ltd | D33: Equity | E33: ='CF (Equity, Debt)'!D31 -> 44849 | F33: ="Q"&ROUNDUP(MONTH(E33)/3,0)&" "&YEAR(E33) -> Q4 2022 | G33: ='CF (Equity, Debt)'!E31 -> -200 | H33: ='CF (Equity, Debt)'!F31 -> 0
C34: ='CF (Equity, Debt)'!C32 -> Applied AI Corporation Limited | D34: Equity | E34: ='CF (Equity, Debt)'!D32 -> 44861 | F34: ="Q"&ROUNDUP(MONTH(E34)/3,0)&" "&YEAR(E34) -> Q4 2022 | G34: ='CF (Equity, Debt)'!E32 -> -4.75 | H34: ='CF (Equity, Debt)'!F32 -> 0
C35: ='CF (Equity, Debt)'!C33 -> eSpace | D35: Equity | E35: ='CF (Equity, Debt)'!D33 -> 44892 | F35: ="Q"&ROUNDUP(MONTH(E35)/3,0)&" "&YEAR(E35) -> Q4 2022 | G35: ='CF (Equity, Debt)'!E33 -> -15 | H35: ='CF (Equity, Debt)'!F33 -> 0
C36: ='CF (Equity, Debt)'!C34 -> vTv Therapeutics Inc. | D36: Equity | E36: ='CF (Equity, Debt)'!D34 -> 44985 | F36: ="Q"&ROUNDUP(MONTH(E36)/3,0)&" "&YEAR(E36) -> Q1 2023 | G36: ='CF (Equity, Debt)'!E34 -> -12.03125 | H36: ='CF (Equity, Debt)'!F34 -> 0
C37: ='CF (Equity, Debt)'!C35 -> Tools for Humanity Corporation | D37: Equity | E37: ='CF (Equity, Debt)'!D35 -> 45075 | F37: ="Q"&ROUNDUP(MONTH(E37)/3,0)&" "&YEAR(E37) -> Q2 2023 | G37: ='CF (Equity, Debt)'!E35 -> -14.999999 | H37: ='CF (Equity, Debt)'!F35 -> 0
C38: ='CF (Equity, Debt)'!C36 -> WLD Tokens | D38: Equity | E38: ='CF (Equity, Debt)'!D36 -> 45075 | F38: ="Q"&ROUNDUP(MONTH(E38)/3,0)&" "&YEAR(E38) -> Q2 2023 | G38: ='CF (Equity, Debt)'!E36 -> -0.005875 | H38: ='CF (Equity, Debt)'!F36 -> 0
C39: ='CF (Equity, Debt)'!C37 -> WLD Tokens | D39: Equity | E39: ='CF (Equity, Debt)'!D37 -> 45114 | F39: ="Q"&ROUNDUP(MONTH(E39)/3,0)&" "&YEAR(E39) -> Q3 2023 | G39: ='CF (Equity, Debt)'!E37 -> -0.001 | H39: ='CF (Equity, Debt)'!F37 -> 0
C40: ='CF (Equity, Debt)'!C38 -> Applied AI Corporation Limited | D40: Equity | E40: ='CF (Equity, Debt)'!D38 -> 45121 | F40: ="Q"&ROUNDUP(MONTH(E40)/3,0)&" "&YEAR(E40) -> Q3 2023 | G40: ='CF (Equity, Debt)'!E38 -> -2.75 | H40: ='CF (Equity, Debt)'!F38 -> 0
... C48: ='CF (Equity, Debt)'!C46 -> Instadeep Limited | D48: Equity | E48: ='CF (Equity, Debt)'!D46 -> 45224 | F48: ="Q"&ROUNDUP(MONTH(E48)/3,0)&" "&YEAR(E48) -> Q4 2023 | G48: ='CF (Equity, Debt)'!E46 -> 0 | H48: ='CF (Equity, Debt)'!F46 -> 0.12141643
B50: Debt
C51: ='CF (Equity, Debt)'!C55 -> Glass Earth Holdings LLC | D51: Debt | E51: ='CF (Equity, Debt)'!D55 -> 43635 | F51: ="Q"&ROUNDUP(MONTH(E51)/3,0)&" "&YEAR(E51) -> Q2 2019 | G51: ='CF (Equity, Debt)'!E55 -> -8 | H51: ='CF (Equity, Debt)'!F55 -> 0
C52: ='CF (Equity, Debt)'!C56 -> Mena Mobile Inc (Debt) | D52: Debt | E52: ='CF (Equity, Debt)'!D56 -> 44293 | F52: ="Q"&ROUNDUP(MONTH(E52)/3,0)&" "&YEAR(E52) -> Q2 2021 | G52: ='CF (Equity, Debt)'!E56 -> -2.353982 | H52: ='CF (Equity, Debt)'!F56 -> 0
C53: ='CF (Equity, Debt)'!C57 -> Esyasoft Holding (Debt) | D53: Debt | E53: ='CF (Equity, Debt)'!D57 -> 44384 | F53: ="Q"&ROUNDUP(MONTH(E53)/3,0)&" "&YEAR(E53) -> Q3 2021 | G53: ='CF (Equity, Debt)'!E57 -> -0.411765 | H53: ='CF (Equity, Debt)'!F57 -> 0
C54: ='CF (Equity, Debt)'!C58 -> Esyasoft Holding (Debt) | D54: Debt | E54: ='CF (Equity, Debt)'!D58 -> 44902 | F54: ="Q"&ROUNDUP(MONTH(E54)/3,0)&" "&YEAR(E54) -> Q4 2022 | G54: ='CF (Equity, Debt)'!E58 -> 0 | H54: ='CF (Equity, Debt)'!F58 -> 0.47078465
B55: Funds
C56: ='CF (Funds)'!C4 -> Sinovation Disrupt Fund, L.P. | D56: Fund | E56: ='CF (Funds)'!D4 -> 44153 | F56: ="Q"&ROUNDUP(MONTH(E56)/3,0)&" "&YEAR(E56) -> Q4 2020 | G56: ='CF (Funds)'!E4 -> -10.5 | H56: ='CF (Funds)'!F4 -> 0
C57: ='CF (Funds)'!C5 -> Sinovation Disrupt Fund, L.P. | D57: Fund | E57: ='CF (Funds)'!D5 -> 44238 | F57: ="Q"&ROUNDUP(MONTH(E57)/3,0)&" "&YEAR(E57) -> Q1 2021 | G57: ='CF (Funds)'!E5 -> 4.214027 | H57: ='CF (Funds)'!F5 -> 0
C58: ='CF (Funds)'!C6 -> Sinovation Disrupt Fund, L.P. | D58: Fund | E58: ='CF (Funds)'!D6 -> 44238 | F58: ="Q"&ROUNDUP(MONTH(E58)/3,0)&" "&YEAR(E58) -> Q1 2021 | G58: ='CF (Funds)'!E6 -> 0 | H58: ='CF (Funds)'!F6 -> 0.05044835
C59: ='CF (Funds)'!C7 -> Sinovation Disrupt Fund, L.P. | D59: Fund | E59: ='CF (Funds)'!D7 -> 44285 | F59: ="Q"&ROUNDUP(MONTH(E59)/3,0)&" "&YEAR(E59) -> Q1 2021 | G59: ='CF (Funds)'!E7 -> -6.433746 | H59: ='CF (Funds)'!F7 -> 0
C60: ='CF (Funds)'!C8 -> Sinovation Disrupt Fund, L.P. | D60: Fund | E60: ='CF (Funds)'!D8 -> 44269 | F60: ="Q"&ROUNDUP(MONTH(E60)/3,0)&" "&YEAR(E60) -> Q1 2021 | G60: ='CF (Funds)'!E8 -> 1.1352074 | H60: ='CF (Funds)'!F8 -> 0
C61: ='CF (Funds)'!C9 -> Sinovation Disrupt Fund, L.P. | D61: Fund | E61: ='CF (Funds)'!D9 -> 44269 | F61: ="Q"&ROUNDUP(MONTH(E61)/3,0)&" "&YEAR(E61) -> Q1 2021 | G61: ='CF (Funds)'!E9 -> 0 | H61: ='CF (Funds)'!F9 -> 0.0259
C62: ='CF (Funds)'!C10 -> Sinovation Disrupt Fund, L.P. | D62: Fund | E62: ='CF (Funds)'!D10 -> 44483 | F62: ="Q"&ROUNDUP(MONTH(E62)/3,0)&" "&YEAR(E62) -> Q4 2021 | G62: ='CF (Funds)'!E10 -> -7.567138 | H62: ='CF (Funds)'!F10 -> 0
C63: ='CF (Funds)'!C11 -> Sinovation Disrupt Fund, L.P. | D63: Fund | E63: ='CF (Funds)'!D11 -> 44554 | F63: ="Q"&ROUNDUP(MONTH(E63)/3,0)&" "&YEAR(E63) -> Q4 2021 | G63: ='CF (Funds)'!E11 -> -7.385016 | H63: ='CF (Funds)'!F11 -> 0
C64: ='CF (Funds)'!C12 -> Sinovation Disrupt Fund, L.P. | D64: Fund | E64: ='CF (Funds)'!D12 -> 44554 | F64: ="Q"&ROUNDUP(MONTH(E64)/3,0)&" "&YEAR(E64) -> Q4 2021 | G64: ='CF (Funds)'!E12 -> 4.0733456 | H64: ='CF (Funds)'!F12 -> 0
C65: ='CF (Funds)'!C13 -> Sinovation Disrupt Fund, L.P. | D65: Fund | E65: ='CF (Funds)'!D13 -> 44554 | F65: ="Q"&ROUNDUP(MONTH(E65)/3,0)&" "&YEAR(E65) -> Q4 2021 | G65: ='CF (Funds)'!E13 -> 0 | H65: ='CF (Funds)'!F13 -> 0.139694
C66: ='CF (Funds)'!C14 -> Sinovation Disrupt Fund, L.P. | D66: Fund | E66: ='CF (Funds)'!D14 -> 44703 | F66: ="Q"&ROUNDUP(MONTH(E66)/3,0)&" "&YEAR(E66) -> Q2 2022 | G66: ='CF (Funds)'!E14 -> 5.673074 | H66: ='CF (Funds)'!F14 -> 0
C67: ='CF (Funds)'!C15 -> Sinovation Disrupt Fund, L.P. | D67: Fund | E67: ='CF (Funds)'!D15 -> 44703 | F67: ="Q"&ROUNDUP(MONTH(E67)/3,0)&" "&YEAR(E67) -> Q2 2022 | G67: ='CF (Funds)'!E15 -> 0 | H67: ='CF (Funds)'!F15 -> 0.227786
... C87: ='CF (Funds)'!C35 -> North Summit Capital Fund | D87: Fund | E87: ='CF (Funds)'!D35 -> 44676 | F87: ="Q"&ROUNDUP(MONTH(E87)/3,0)&" "&YEAR(E87) -> Q2 2022 | G87: ='CF (Funds)'!E35 -> -21 | H87: ='CF (Funds)'!F35 -> 0
C88: ='CF (Funds)'!C38 -> New Space Capital Fund I | D88: Fund | E88: ='CF (Funds)'!D38 -> 44087 | F88: ="Q"&ROUNDUP(MONTH(E88)/3,0)&" "&YEAR(E88) -> Q3 2020 | G88: ='CF (Funds)'!E38 -> -20.917553 | H88: ='CF (Funds)'!F38 -> 0
C89: ='CF (Funds)'!C39 -> New Space Capital Fund I | D89: Fund | E89: ='CF (Funds)'!D39 -> 44287 | F89: ="Q"&ROUNDUP(MONTH(E89)/3,0)&" "&YEAR(E89) -> Q2 2021 | G89: ='CF (Funds)'!E39 -> -0.21103182 | H89: ='CF (Funds)'!F39 -> 0
C90: ='CF (Funds)'!C40 -> New Space Capital Fund I | D90: Fund | E90: ='CF (Funds)'!D40 -> 44442 | F90: ="Q"&ROUNDUP(MONTH(E90)/3,0)&" "&YEAR(E90) -> Q3 2021 | G90: ='CF (Funds)'!E40 -> -0.23965473 | H90: ='CF (Funds)'!F40 -> 0
C91: ='CF (Funds)'!C41 -> New Space Capital Fund I | D91: Fund | E91: ='CF (Funds)'!D41 -> 44623 | F91: ="Q"&ROUNDUP(MONTH(E91)/3,0)&" "&YEAR(E91) -> Q1 2022 | G91: ='CF (Funds)'!E41 -> -0.25893585 | H91: ='CF (Funds)'!F41 -> 0
C92: ='CF (Funds)'!C42 -> New Space Capital Fund I | D92: Fund | E92: ='CF (Funds)'!D42 -> 44784 | F92: ="Q"&ROUNDUP(MONTH(E92)/3,0)&" "&YEAR(E92) -> Q3 2022 | G92: ='CF (Funds)'!E42 -> 0.015224657 | H92: ='CF (Funds)'!F42 -> 0
C93: ='CF (Funds)'!C43 -> New Space Capital Fund I | D93: Fund | E93: ='CF (Funds)'!D43 -> 44956 | F93: ="Q"&ROUNDUP(MONTH(E93)/3,0)&" "&YEAR(E93) -> Q1 2023 | G93: ='CF (Funds)'!E43 -> 10.553916 | H93: ='CF (Funds)'!F43 -> 0
C94: ='CF (Funds)'!C44 -> New Space Capital Fund I | D94: Fund | E94: ='CF (Funds)'!D44 -> 44956 | F94: ="Q"&ROUNDUP(MONTH(E94)/3,0)&" "&YEAR(E94) -> Q1 2023 | G94: ='CF (Funds)'!E44 -> 0 | H94: ='CF (Funds)'!F44 -> 2.9557744
C95: ='CF (Funds)'!C51 -> New Space Capital GP Com SCSp | D95: Fund | E95: ='CF (Funds)'!D51 -> 44087 | F95: ="Q"&ROUNDUP(MONTH(E95)/3,0)&" "&YEAR(E95) -> Q3 2020 | G95: ='CF (Funds)'!E51 -> -2.7058824 | H95: ='CF (Funds)'!F51 -> 0
C96: ='CF (Funds)'!C52 -> Acies Investments Fund I, L.P. | D96: Fund | E96: ='CF (Funds)'!D52 -> 44540 | F96: ="Q"&ROUNDUP(MONTH(E96)/3,0)&" "&YEAR(E96) -> Q4 2021 | G96: ='CF (Funds)'!E52 -> -2.8053125 | H96: ='CF (Funds)'!F52 -> 0
C97: ='CF (Funds)'!C53 -> Acies Investments Fund I, L.P. | D97: Fund | E97: ='CF (Funds)'!D53 -> 44602 | F97: ="Q"&ROUNDUP(MONTH(E97)/3,0)&" "&YEAR(E97) -> Q1 2022 | G97: ='CF (Funds)'!E53 -> -3.4075 | H97: ='CF (Funds)'!F53 -> 0
C98: ='CF (Funds)'!C54 -> Acies Investments Fund I, L.P. | D98: Fund | E98: ='CF (Funds)'!D54 -> 44683 | F98: ="Q"&ROUNDUP(MONTH(E98)/3,0)&" "&YEAR(E98) -> Q2 2022 | G98: ='CF (Funds)'!E54 -> -1.025775 | H98: ='CF (Funds)'!F54 -> 0
C99: ='CF (Funds)'!C55 -> Acies Investments Fund I, L.P. | D99: Fund | E99: ='CF (Funds)'!D55 -> 44707 | F99: ="Q"&ROUNDUP(MONTH(E99)/3,0)&" "&YEAR(E99) -> Q2 2022 | G99: ='CF (Funds)'!E55 -> -3.388275 | H99: ='CF (Funds)'!F55 -> 0
C100: ='CF (Funds)'!C56 -> Acies Investments Fund I, L.P. | D100: Fund | E100: ='CF (Funds)'!D56 -> 44875 | F100: ="Q"&ROUNDUP(MONTH(E100)/3,0)&" "&YEAR(E100) -> Q4 2022 | G100: ='CF (Funds)'!E56 -> -3.388275 | H100: ='CF (Funds)'!F56 -> 0

Sheet 8. NewSpace
B2: New Space Capital Capital Calls | C2: 44442 | E2: 44623 | F2: 44784 | G2: 44956
T3: Figures in USD, Mn
P4: Drawdown 14
B5: EUR | C5: Drawdown 3 | D5: Drawdown 4 | E5: Drawdown 5 | G5: Drawdown 8 | H5: Drawdown 9 | I5: Drawdown 10 | J5: Drawdown 11 | K5: Drawdown 12 | L5: Drawdown 13 | M5: Drawdown 14 | N5: Drawdown 15 | P5: Distribution 2 | T5: Deals | U5: New Space Capital Fund I | V5: NewSpace Capital GP Com SCSp
B6: Date | C6: 44442 | D6: 44512 | E6: 44623 | G6: 44950 | H6: 45007 | I6: 45170 | J6: 45260 | K6: 45306 | L6: 45356 | N6: 45491 | P6: 45454 | T6: Status | U6: Unrealized | V6: Unrealized
B7: Total Commitment | C7: 19015957 | D7: 23513942 | E7: 23513942 | G7: 23234462 | H7: 23234462 | I7: 23234462 | J7: 23234462 | K7: 23234462 | L7: 23234462 | M7: 23234462 | N7: 23234462 | P7: 23234462 | T7: Investing Entity | U7: G42 | V7: G42
B8: Contributions (prior to this notice): | C8: 19226989 | D8: 19415305 | E8: 19365158 | I8: 9566817.3 | J8: =I8+I18 -> 9834193.4 | K8: =J8+J18 -> 10093474 | L8: =K8+K18 -> 12297371 | M8: =L8+L18 -> 12498073 | N8: 12128944 | P8: =P7-P9 -> 12498073 | T8: Vintageἀ | U8: 2020 | V8: 2020
B9: Remaining Commitment (prior to notice) | D9: 4098636.9 | E9: 4148784.1 | G9: 15865093 | H9: 15675627 | I9: =I7-I8 -> 13667645 | J9: =J7-J8 -> 13400268 | K9: =K7-K8 -> 13140988 | L9: =L7-L8 -> 10937091 | M9: =M7-M8 -> 10736389 | N9: =N7-N8 -> 11105518 | P9: =L22 -> 10736389 | T9: Instrument | U9: LP | V9: LP
B10: Distribution of Actualisation Interest (Distribution 1/Drawdown 8)*: | G10: -12659067 | T10: % | U10: n/a | V10: n/a
B11: Return of Capital | H11: -2067567 | T11: Committed | U11: 27.691913 | V11: 2.7058824
B12: Remaining Commitment: | H12: 13608060 | T12: Invested | U12: 11.058035 | V12: 2.7058824
T13: Remaining Commitment | U13: 16.633878 | V13: 0
T14: Distributions | U14: 2.9557744 | V14: 0
B15: Equalization -Actualization of Investments | P15: -358796.4 | T15: Carrying Value | U15: =NAV!E40 -> 19.274963 | V15: =V12*U15/U12 -> 4.7165509
B16: Equalization -Actualization of Fund Expenses | P16: -10332.76 | T16: Gain | U16: =U15+U14-U12 -> 11.172703 | V16: =V15+V14-V12 -> 2.0106686
B17: Equalization -Actualization of Interest - Investments & Fund Expenses | P17: -62495.83 | T17: Multiple | U17: =(U14+U15)/U12 -> 2.0103697 | V17: =(V14+V15)/V12 -> 1.7430732
B18: Contribution | G18: =G9-G22 -> 189466.02 | H18: =H12-H22 -> -59584.38 | I18: 267376.08 | J18: 259280.73 | K18: 2203896.7 | L18: 200702.46 | N18: 1578048.7
B19: Distribution | G19: =-G20+G18 -> 12659067 | H19: =-H20+H18 -> 1.0404619e-09 | I19: 59584.38 | T19: Note
B20: NET Amount Contributed / Distributed to us | C20: 203097.23 | D20: -444437.06 | E20: 233275.54 | G20: -12469601 | H20: -59584.38 | I20: =I18-I19 -> 207791.7 | J20: =J18-J19 -> 259280.73 | K20: =K18-K19 -> 2203896.7 | L20: =L18-L19 -> 200702.46 | N20: =N18-N19 -> 1578048.7 | P20: =SUM(P15:P17) -> -431624.99 | T20: 1. In Q1'23 we converted GP interest equivalent to the LP via the GP commitment vehicle
T21: 2. In addition, G42 also has XX units in the GP, which presently are being carried at nil value
B22: Remaining Commitment (after this notice): | C22: 0 | D22: 4163565.3 | E22: 3915508.6 | G22: 15675627 | H22: 13667645 | I22: 13400268 | J22: =J9-J20 -> 13140988 | K22: =K9-K20 -> 10937091 | L22: =L9-L20 -> 10736389 | M22: =P22 -> 11105518 | N22: =N9-N20 -> 9527469.1 | P22: =P9-P15-P16 -> 11105518
B23: Remaining Commitment (as a % of Capital Commitments): | C23: 0 | D23: 0.1771 | E23: 0.1665 | G23: 0.6747 | H23: 0.5882 | I23: 0.5767 | J23: 0.5656 | K23: 0.4707 | L23: 0.4621 | P23: 0.478
B24: CHECKS | D24: =ROUND(D22/D7,4)=D23 -> TRUE | E24: =ROUND(E22/E7,4)=E23 -> TRUE | G24: =ROUND(G22/G7,4)=G23 -> TRUE | H24: =ROUND(H22/H7,4)=H23 -> TRUE | I24: =ROUND(I22/I7,4)=I23 -> TRUE | J24: =ROUND(J22/J7,4)=J23 -> TRUE | K24: =ROUND(K22/K7,4)=K23 -> TRUE | L24: =ROUND(L22/L7,4)=L23 -> TRUE | P24: =ROUND(P22/P7,4)=P23 -> TRUE
B25: EURUSD | G25: 1.0872 | H25: 1.0773 | I25: 1.08439 | J25: 1.1004 | K25: 1.09506 | L25: 1.07869 | P25: 1.0743
G26: =-G25*G20/1000000 -> 13.55695 | H26: =-H25*H20/1000000 -> 0.064190253 | I26: =-I25*I20/1000000 -> -0.22532724 | J26: =-J25*J20/1000000 -> -0.28531252 | K26: =-K25*K20/1000000 -> -2.4133991 | L26: =-L25*L20/1000000 -> -0.21649574 | P26: =-P25*P20/1000000 -> 0.46369473
B30: Capital Account Statement
B31: New Space Capital
B33: EUR | C33: 3Q22 | D33: 4Q22 | E33: 1Q23 | F33: 2Q'23 | G33: 3Q'23 | H33: 1Q'24
B34: Commitment | C34: 23234462 | D34: 23234462 | E34: 23234462 | F34: 23234462 | G34: 23234462 | H34: =G34 -> 23234462 | P34: source: distribution letter
B35: Capital Contribution | C35: 19178323 | D35: 9436936 | E35: 9626402 | F35: 9595097 | G35: 9834193 | H35: 12498073
B36: Unfunded | C36: =C34-C35 -> 4056139 | D36: =D34-D35 -> 13797526 | E36: =E34-E35 -> 13608060 | F36: =F34-F35 -> 13639365 | G36: =G34-G35 -> 13400269 | H36: =H34-H35 -> 10736389
B37: Unrealized Gain | C37: 13103567 | D37: 3803379 | G37: =G38-G35 -> 2548651 | H37: =H38-H35 -> 5930326
B38: NAV | C38: 32325017 | D38: 12031777 | E38: 12148021 | F38: 12218930 | G38: 12382844 | H38: 18428399 | P38: source: distribution letter
B39: Capital Return | D39: =C35-D35 -> 9741387 | P39: estimated
B40: Interest Capitalization | D40: =D42-D39 -> 2728214 | P40: estimated
B42: Total Distribution Received | D42: 12469601 | P42: source: distribution letters, Gino
B43: Remaining Commitment | D43: =15675627.21 -> 15675627 | G43: =I22 -> 13400268 | P43: source: distribution letter

Sheet 1.1 Geo
B3: Investment | C3: Vintage | D3: Type | E3: Sector | F3: Geography | G3: Committed | H3: Invested | I3: Remaining Commitment | J3: Distributions | K3: Carrying Value
B4: Jollychic Holding Limited | C4: 2019 | D4: Equity | E4: Ecommerce | F4: Asia-China | G4: 65 | H4: 65 | I4: 0 | J4: 0 | K4: 0
B5: Mena Mobile Inc | C5: 2019 | D5: Equity | E5: Mobile Gaming | F5: Asia-China | G5: 8 | H5: 8 | I5: 0 | J5: 0 | K5: 3.1 | M5: Asia-China | N5: =SUMIF(F3:K26,$M$5,G3:G26) -> 2578.854
B6: Flyr Inc | C6: 2019 | D6: Equity | E6: B2B SaaS | F6: USA | G6: 10 | H6: 10 | I6: 0 | J6: 0 | K6: 78.08223
B7: Esyasoft Holding | C7: 2020 | D7: Equity | E7: Utilities-Tech | F7: Rest of Asia | G7: 2.5 | H7: 2.5 | I7: 0 | J7: 5 | K7: 0
B8: Beyond Limits | C8: 2020 | D8: Equity | E8: Oil & Gas AI | F8: USA | G8: 90 | H8: 90 | I8: 0 | J8: 0 | K8: 91.00154
B9: ONT plc | C9: 2020 | D9: Equity | E9: BioTechnology | F9: Europe | G9: 141.47026 | H9: 141.47026 | I9: 0 | J9: 0 | K9: 149.58081
B10: Heygears | C10: 2020 | D10: Equity | E10: 3D Printing | F10: Asia-China | G10: 60 | H10: 60 | I10: 0 | J10: 0 | K10: 136.64
B11: Jysan Technologies | C11: 2021 | D11: Equity | E11: Fintech | F11: Rest of Asia | G11: 20 | H11: 20 | I11: 0 | J11: 0 | K11: 20
B12: Cerebras Systems Inc | C12: 2021 | D12: Equity | E12: Semiconductor | F12: USA | G12: 40 | H12: 40 | I12: 0 | J12: 0 | K12: 39.999983
B13: Endless Studios LLC | C13: 2021 | D13: Equity | E13: Edutech | F13: USA | G13: 3 | H13: 3 | I13: 0 | J13: 0 | K13: 3
B14: Instadeep Limited | C14: 2021 | D14: Equity | E14: B2B SaaS | F14: Europe | G14: 5.0278212 | H14: 5.0278212 | I14: 0 | J14: 0 | K14: 5.0237202
B15: X-fusion | C15: 2022 | D15: Equity | E15: Cloud Computing | F15: Asia-China | G15: 493.5 | H15: 493.5 | I15: 0 | J15: 0 | K15: 493.5
B16: DriveNets | C16: 2022 | D16: Equity | E16: Computer Networks | F16: MiddleEast | G16: 300 | H16: 300 | I16: 0 | J16: 0 | K16: 300
B17: vTv Therapeutics Inc. | C17: 2022 | D17: Equity | E17: BioTechnology | F17: USA | G17: 25 | H17: 12.5 | I17: 12.5 | J17: 0 | K17: -0.5557849
B18: Honor Device Co Ltd | C18: 2022 | D18: Equity | E18: Hardware-SmartDevices | F18: Asia-China | G18: 1600 | H18: 800 | I18: 800 | J18: 0 | K18: =1075.57839098788*0.8 -> 860.46271
B19: Glass Earth Holdings LLC | C19: 2019 | D19: Debt | E19: Consulting | F19: USA | G19: 8 | H19: 8 | I19: 0 | J19: 0 | K19: 0
B20: Mena Mobile Inc | C20: 2021 | D20: Debt | E20: Mobile Gaming | F20: Asia-China | G20: 2.353982 | H20: 2.353982 | I20: 0 | J20: 0 | K20: 2.353982
B21: Esyasoft Holding | C21: 2021 | D21: Debt | E21: Utilities-Tech | F21: Rest of Asia | G21: 0.411765 | H21: 0.411765 | I21: 0 | J21: 0 | K21: 0.45643868
B22: New Space Capital Fund I | C22: 2020 | D22: Fund | E22: Fund | F22: Europe | G22: 25.557908 | H22: 21.611951 | I22: 3.9459573 | J22: 0 | K22: 31.952799
B23: New Space Capital SCSp | C23: 2020 | D23: Fund | E23: Fund | F23: Europe | G23: 2.7058824 | H23: 2.7058824 | I23: 0 | J23: 0 | K23: 2.7058824
B24: North Summit Capital Fund | C24: 2020 | D24: Fund | E24: Fund | F24: Asia-China | G24: 300 | H24: 83.214653 | I24: 217.81331 | J24: 1.027961 | K24: 79.32
B25: Sinovation Disrupt Fund, L.P. | C25: 2020 | D25: Fund | E25: Fund | F25: Asia-China | G25: 50 | H25: 16.790246 | I25: 33.209754 | J25: 0.44382835 | K25: 15.875237
B26: Acies Investments Fund I, L.P. | C26: 2021 | D26: Fund | E26: Fund | F26: USA | G26: 17.1125 | H26: 10.626862 | I26: 6.4856375 | J26: 0 | K26: 10.343447
G28: =SUM(G4:G26) -> 3269.6401 | H28: =SUM(H4:H26) -> 2196.7134 | I28: =SUM(I4:I26) -> 1073.9547 | J28: =SUM(J4:J26) -> 6.4717893 | K28: =SUM(K4:K26) -> 2322.843

Sheet 1.2 Attribution
C2: ATTRIBUTION SUMMARY
D3: As of date | E3: =D!D2 -> 45473
D7: Deals | E7: Type | F7: Gain | G7: Gain till Dec 2021 | K7: MOZN Portfolio : Gains till Dec 2021 | N7: G42 Portfolio : Gains till Dec 2021
D8: X-fusion | E8: Equity | F8: =VLOOKUP(D8,'S | 01 '!$C$6:$Q$49,13,0) -> -90.500956 | G8: 0 | K8: Jollychic Holding Limited | L8: =VLOOKUP(K8,$D$7:$G$33,4,0) -> -65 | N8: Honor Device Co Ltd | O8: =VLOOKUP(N8,$D$7:$G$33,4,0) -> 0
D9: Jollychic Holding Limited | E9: Equity | F9: =VLOOKUP(D9,'S | 01 '!$C$6:$Q$49,13,0) -> -65 | G9: -65 | K9: Heygears | L9: =VLOOKUP(K9,$D$7:$G$33,4,0) -> -39.7 | N9: DriveNets | O9: =VLOOKUP(N9,$D$7:$G$33,4,0) -> 0
D10: vTv Therapeutics Inc. | E10: Equity | F10: =VLOOKUP(D10,'S | 01 '!$C$6:$Q$49,13,0) -> -19.945707 | G10: 0 | K10: Glass Earth Holdings LLC | L10: =VLOOKUP(K10,$D$7:$G$33,4,0) -> -8 | N10: vTv Therapeutics Inc. | O10: =VLOOKUP(N10,$D$7:$G$33,4,0) -> 0
D11: Glass Earth Holdings LLC | E11: Debt | F11: =VLOOKUP(D11,'S | 01 '!$C$6:$Q$49,13,0) -> -8 | G11: -8 | K11: Mena Mobile Inc | L11: =VLOOKUP(K11,$D$7:$G$33,4,0) -> -6.3 | N11: New Space Capital GP Com SCSp | O11: =VLOOKUP(N11,$D$7:$G$33,4,0) -> 0
D12: Mena Mobile Inc | E12: Equity | F12: =VLOOKUP(D12,'S | 01 '!$C$6:$Q$49,13,0) -> -8 | G12: -6.3 | K12: Beyond Limits | L12: =VLOOKUP(K12,$D$7:$G$33,4,0) -> 0 | N12: Acies Investments Fund I, L.P. | O12: =VLOOKUP(N12,$D$7:$G$33,4,0) -> 0
D13: Sinovation Disrupt Fund, L.P. | E13: Fund | F13: =VLOOKUP(D13,'S | 01 '!$C$6:$Q$49,13,0) -> 0.44382835 | G13: 3.5 | K13: Endless Studios LLC | L13: =VLOOKUP(K13,$D$7:$G$33,4,0) -> 0 | N13: New Space Capital Fund I | O13: =VLOOKUP(N13,$D$7:$G$33,4,0) -> 1
D14: Acies Investments Fund I, L.P. | E14: Fund | F14: =VLOOKUP(D14,'S | 01 '!$C$6:$Q$49,13,0) -> -3.1399255 | G14: 0 | K14: X-fusion | L14: =VLOOKUP(K14,$D$7:$G$33,4,0) -> 0 | N14: Sinovation Disrupt Fund, L.P. | O14: =VLOOKUP(N14,$D$7:$G$33,4,0) -> 3.5
D15: North Summit Capital Fund | E15: Fund | F15: =VLOOKUP(D15,'S | 01 '!$C$6:$Q$49,13,0) -> -0.728618 | G15: 6.6 | K15: Applied AI Corporation Limited | L15: =VLOOKUP(K15,$D$7:$G$33,4,0) -> 0 | N15: North Summit Capital Fund | O15: =VLOOKUP(N15,$D$7:$G$33,4,0) -> 6.6
D16: Mena Mobile Inc (Debt) | E16: Debt | F16: =VLOOKUP(D16,'S | 01 '!$C$6:$Q$49,13,0) -> -2.353982 | G16: 0 | K16: eSpace | L16: =VLOOKUP(K16,$D$7:$G$33,4,0) -> 0
D17: Jysan Technologies | E17: Equity | F17: =VLOOKUP(D17,'S | 01 '!$C$6:$Q$49,13,0) -> 4.5 | G17: 0 | K17: Cerebras Systems Inc | L17: =VLOOKUP(K17,$D$7:$G$33,4,0) -> 0
D18: Applied AI Corporation Limited | E18: Equity | F18: =VLOOKUP(D18,'S | 01 '!$C$6:$Q$49,13,0) -> 0 | G18: 0 | K18: Instadeep Limited | L18: =VLOOKUP(K18,$D$7:$G$33,4,0) -> 0
D19: eSpace | E19: Equity | F19: =VLOOKUP(D19,'S | 01 '!$C$6:$Q$49,13,0) -> 5.8881215 | G19: 0 | K19: Jysan Technologies | L19: =VLOOKUP(K19,$D$7:$G$33,4,0) -> 0
D20: Cerebras Systems Inc | E20: Equity | F20: =VLOOKUP(D20,'S | 01 '!$C$6:$Q$49,13,0) -> -18.8645 | G20: 0 | K20: Esyasoft Holding (Debt) | L20: =VLOOKUP(K20,$D$7:$G$33,4,0) -> 0
D21: Endless Studios LLC | E21: Equity | F21: =VLOOKUP(D21,'S | 01 '!$C$6:$Q$49,13,0) -> 0 | G21: 0 | K21: Mena Mobile Inc (Debt) | L21: =VLOOKUP(K21,$D$7:$G$33,4,0) -> 0
D22: DriveNets | E22: Equity | F22: =VLOOKUP(D22,'S | 01 '!$C$6:$Q$49,13,0) -> -95.4 | G22: 0 | K22: Esyasoft Holding | L22: =VLOOKUP(K22,$D$7:$G$33,4,0) -> 2.5
D23: Tools for Humanity Corporation | E23: Equity | F23: =VLOOKUP(D23,'S | 01 '!$C$6:$Q$49,13,0) -> 0 | G23: 69.1 | K23: Flyr Inc | L23: =VLOOKUP(K23,$D$7:$G$33,4,0) -> 68.1
D24: Esyasoft Holding (Debt) | E24: Debt | F24: =VLOOKUP(D24,'S | 01 '!$C$6:$Q$49,13,0) -> 0.05901965 | G24: 0 | K24: Tools for Humanity Corporation | L24: =VLOOKUP(K24,$D$7:$G$33,4,0) -> 69.1
D25: New Space Capital GP Com SCSp | E25: Fund | F25: =VLOOKUP(D25,'S | 01 '!$C$6:$Q$49,13,0) -> 0.56973286 | G25: 0 | K25: ONT plc | L25: =VLOOKUP(K25,$D$7:$G$33,4,0) -> 275.8
D26: Beyond Limits | E26: Equity | F26: =VLOOKUP(D26,'S | 01 '!$C$6:$Q$49,13,0) -> -16.2 | G26: 0
D27: Instadeep Limited | E27: Equity | F27: =VLOOKUP(D27,'S | 01 '!$C$6:$Q$49,13,0) -> 2.9184723 | G27: 0
D28: ONT plc | E28: Equity | F28: =VLOOKUP(D28,'S | 01 '!$C$6:$Q$49,13,0) -> -88.470208 | G28: 275.8
D29: Esyasoft Holding | E29: Equity | F29: =VLOOKUP(D29,'S | 01 '!$C$6:$Q$49,13,0) -> 2.5 | G29: 2.5
D30: New Space Capital Fund I | E30: Fund | F30: =VLOOKUP(D30,'S | 01 '!$C$6:$Q$49,13,0) -> 6.7719935 | G30: 1
D31: Honor Device Co Ltd | E31: Equity | F31: =VLOOKUP(D31,'S | 01 '!$C$6:$Q$49,13,0) -> 2.8 | G31: 0 | K31: Gain | L31: =SUM(L8:L25) -> 296.5 | N31: Total | O31: =SUM(O8:O16) -> 11.1
D32: Flyr Inc | E32: Equity | F32: =VLOOKUP(D32,'S | 01 '!$C$6:$Q$49,13,0) -> 27.11873 | G32: 68.1 | K32: Gain till Nov 2022 | L32: ='S | 02'!O30 -> -44.821278
D33: Heygears | E33: Equity | F33: =VLOOKUP(D33,'S | 01 '!$C$6:$Q$49,13,0) -> 89.398592 | G33: -39.7 | K33: Delta Gain | L33: =L32-L31 -> -341.32128
