Workbook
Name Company: [1]UEL!$B$18:$B$20
Name Dates: [1]ONT!$N$2:$AN$2
Name DetailedCapShares: '[2]Current Cap'!$T$133
Name FAGroup: [1]UEL!$B$3:$B$15
Name IQ_CH: 110000
Name IQ_CQ: 5000
Name IQ_CY: 10000
Name IQ_DAILY: 500000
Name IQ_FH: 100000
Name IQ_FQ: 500
Name IQ_FY: 1000
Name IQ_LTM: 2000
Name IQ_MONTH: 15000
Name IQ_NTM: 6000
Name IQ_WEEK: 50000
Name IQ_YTD: 3000

Sheet D
C2: Date of NAV | D2: 45322 | E2: =TEXT(D2,"dddddd") -> Wednesday
H3: D A S H B O A R D | L3: figures in USD Millions
D6: # Investments | E6: Committed | F6: Invested | G6: Remaining | H6: Distributions | I6: Residual Value | J6: IRR | K6: TVPI | L6: RPI | M6: DPI
C8: EQUITY | D8: =COUNTIF('S | 01 '!C10:C32,"*") -> 21 | E8: ='1. IRR Equity'!AH35 -> 2121.7862 | F8: ='1. IRR Equity'!AI35 -> 2118.283 | G8: ='1. IRR Equity'!AJ35 -> 3.5031614 | H8: ='1. IRR Equity'!AK35 -> 1243.2422 | I8: ='1. IRR Equity'!AL35 -> 828.59461 | J8: ='1. IRR Equity'!AM35 -> -0.011569161 | K8: ='1. IRR Equity'!AN35 -> 0.97807364 | L8: ='1. IRR Equity'!AO35 -> 0.39116331 | M8: ='1. IRR Equity'!AP35 -> 0.58691033
C11: DEBT | D11: =COUNTIF('S | 01 '!C35:C37,"*") -> 3 | E11: ='2. IRR Debt'!Q12 -> 10.765747 | F11: ='2. IRR Debt'!R12 -> 10.765747 | G11: ='2. IRR Debt'!S12 -> 0 | H11: ='2. IRR Debt'!T12 -> 0.47078465 | I11: ='2. IRR Debt'!U12 -> 0 | J11: ='2. IRR Debt'!V12 -> -0.71226245 | K11: ='2. IRR Debt'!W12 -> 0.043729864 | L11: ='2. IRR Debt'!X12 -> 0 | M11: ='2. IRR Debt'!Y12 -> 0.043729864
C14: FUNDS | D14: =COUNTIF('S | 01 '!C41:C45,"*") -> 5 | E14: ='3. IRR Funds'!Q15 -> 184.17552 | F14: ='3. IRR Funds'!R15 -> 138.88392 | G14: ='3. IRR Funds'!S15 -> 53.107474 | H14: ='3. IRR Funds'!T15 -> 11.215474 | I14: ='3. IRR Funds'!U15 -> 126.55296 | J14: ='3. IRR Funds'!V15 -> 2.9802322e-09 | K14: ='3. IRR Funds'!W15 -> 0.99196821 | L14: ='3. IRR Funds'!X15 -> 0.91121391 | M14: ='3. IRR Funds'!Y15 -> 0.0807543
C17: TOTAL | D17: =D8+D11+D14 -> 29 | E17: =E8+E11+E14 -> 2316.7275 | F17: =F8+F11+F14 -> 2267.9327 | G17: =G8+G11+G14 -> 56.610636 | H17: =H8+H11+H14 -> 1254.9285 | I17: =I8+I11+I14 -> 955.14756 | J17: ='4.All'!N9 -> -0.012957468 | K17: =(H17+I17)/F17 -> 0.97448924 | L17: =I17/F17 -> 0.4211534 | M17: =H17/F17 -> 0.55333584
E19: =E17='S | 01 '!J48 -> TRUE | F19: =F17='S | 01 '!K48 -> TRUE | G19: =ROUND(G17,1)=ROUND('S | 01 '!L48,1) -> FALSE | H19: =ROUND(H17,1)=ROUND('S | 01 '!M48,1) -> TRUE | I19: =ROUND(I17,1)=ROUND('S | 01 '!N48,1) -> TRUE

Sheet S | 01 
C2: As of date | D2: =D!D2 -> 45322
C6: Deals | D6: Status | E6: Lead | F6: Investing Entity | G6: Vintageἀ | H6: Instrument | I6: % | J6: Committed | K6: Invested | L6: Remaining Commitment | M6: Distributions | N6: Carrying Value | O6: Gain | P6: TVPI | Q6: IRRβ | R6: Additonal Upside/Downside
G7: # | I7: % | J7: $,m | K7: $,m | L7: $,m | M7: $,m | N7: $,m | O7: $,m | P7: X | Q7: %
C9: Direct Investments
C10: Jollychic Holding Limited | D10: Written-off | E10: Elaine | F10: Mozn | G10: 2019 | H10: C+ Prefs | I10: ='6. %'!F9 -> 0.056999998 | J10: 65 | K10: =-SUMIF('CF (Equity, Debt)'!$C$3:$K$51,'S | 01 '!C10,'CF (Equity, Debt)'!$E$3:$E$51) -> 65 | L10: 0 | M10: =SUMIF('CF (Equity, Debt)'!$C$3:$K$51,'S | 01 '!C10,'CF (Equity, Debt)'!$F$3:$F$51) -> 0 | N10: =VLOOKUP(C10,NAV!$B$4:$E$46,4,0) -> 0 | O10: =N10+M10-K10 -> -65 | P10: =(M10+N10)/K10 -> 0 | Q10: =VLOOKUP(C10,'1. IRR Equity'!$AG$12:$AP$30,7,0) -> NM | R10: In Liquidation
C11: Mena Mobile Inc | D11: Written-off | E11: Elaine | F11: Mozn | G11: 2019 | H11: B Prefs | I11: ='6. %'!F10 -> 0.14 | J11: 8 | K11: =-SUMIF('CF (Equity, Debt)'!$C$3:$K$51,'S | 01 '!C11,'CF (Equity, Debt)'!$E$3:$E$51) -> 8 | L11: 0 | M11: =SUMIF('CF (Equity, Debt)'!$C$3:$K$51,'S | 01 '!C11,'CF (Equity, Debt)'!$F$3:$F$51) -> 0 | N11: =VLOOKUP(C11,NAV!$B$4:$E$46,4,0) -> 0 | O11: =N11+M11-K11 -> -8 | P11: =(M11+N11)/K11 -> 0 | Q11: =VLOOKUP(C11,'1. IRR Equity'!$AG$12:$AP$30,7,0) -> NM | R11: In Liquidation
C12: Flyr Inc | D12: Unrealized | E12: Sushil | F12: Mozn | G12: 2019 | H12: B-1,2 Prefs | I12: ='6. %'!F11 -> 0.085025485 | J12: 10 | K12: =-SUMIF('CF (Equity, Debt)'!$C$3:$K$51,'S | 01 '!C12,'CF (Equity, Debt)'!$E$3:$E$51) -> 10 | L12: 0 | M12: =SUMIF('CF (Equity, Debt)'!$C$3:$K$51,'S | 01 '!C12,'CF (Equity, Debt)'!$F$3:$F$51) -> 0 | N12: =VLOOKUP(C12,NAV!$B$4:$E$46,4,0) -> 78.08223 | O12: =N12+M12-K12 -> 68.08223 | P12: =(M12+N12)/K12 -> 7.808223 | Q12: =VLOOKUP(C12,'1. IRR Equity'!$AG$12:$AP$30,7,0) -> 0.59885044 | R12: Flyr Warrantsa 2025 expiry
C13: Esyasoft Holding | D13: Realized | E13: Sushil | F13: Mozn | G13: 2020 | H13: Convertible Note | I13: ='6. %'!F12 -> n/a | J13: 2.5 | K13: =-SUMIF('CF (Equity, Debt)'!$C$3:$K$51,'S | 01 '!C13,'CF (Equity, Debt)'!$E$3:$E$51) -> 2.5 | L13: 0 | M13: =SUMIF('CF (Equity, Debt)'!$C$3:$K$51,'S | 01 '!C13,'CF (Equity, Debt)'!$F$3:$F$51) -> 5 | N13: =VLOOKUP(C13,NAV!$B$4:$E$46,4,0) -> 0 | O13: =N13+M13-K13 -> 2.5 | P13: =(M13+N13)/K13 -> 2 | Q13: =VLOOKUP(C13,'1. IRR Equity'!$AG$12:$AP$30,7,0) -> 0.36091766
C14: Beyond Limits | D14: Unrealized | E14: Divyesh | F14: Mozn | G14: 2020 | H14: C Prefs | I14: ='6. %'!F13 -> 0.097965107 | J14: 90 | K14: =-SUMIF('CF (Equity, Debt)'!$C$3:$K$51,'S | 01 '!C14,'CF (Equity, Debt)'!$E$3:$E$51) -> 90 | L14: 0 | M14: =SUMIF('CF (Equity, Debt)'!$C$3:$K$51,'S | 01 '!C14,'CF (Equity, Debt)'!$F$3:$F$51) -> 0 | N14: =VLOOKUP(C14,NAV!$B$4:$E$46,4,0) -> 91.00154 | O14: =N14+M14-K14 -> 1.0015403 | P14: =(M14+N14)/K14 -> 1.0111282 | Q14: =VLOOKUP(C14,'1. IRR Equity'!$AG$12:$AP$30,7,0) -> 0.0029582828
C15: ONT plc | D15: Unrealized | E15: Divyesh | F15: Mozn | G15: 2020 | H15: Ordinary Shares | I15: ='6. %'!F14 -> 0.051651565 | J15: 141.47026 | K15: =-SUMIF('CF (Equity, Debt)'!$C$3:$K$51,'S | 01 '!C15,'CF (Equity, Debt)'!$E$3:$E$51) -> 141.47026 | L15: 0 | M15: =SUMIF('CF (Equity, Debt)'!$C$3:$K$51,'S | 01 '!C15,'CF (Equity, Debt)'!$F$3:$F$51) -> 0 | N15: =VLOOKUP(C15,NAV!$B$4:$E$46,4,0) -> 90.139175 | O15: =N15+M15-K15 -> -51.331085 | P15: =(M15+N15)/K15 -> 0.63715989 | Q15: =VLOOKUP(C15,'1. IRR Equity'!$AG$12:$AP$30,7,0) -> -0.11648149
C16: Heygears | D16: Unrealized | E16: Elaine | F16: Mozn | G16: 2020 | H16: Registered Capital | I16: ='6. %'!F15 -> 0.1438 | J16: 60 | K16: =-SUMIF('CF (Equity, Debt)'!$C$3:$K$51,'S | 01 '!C16,'CF (Equity, Debt)'!$E$3:$E$51) -> 60 | L16: 0 | M16: =SUMIF('CF (Equity, Debt)'!$C$3:$K$51,'S | 01 '!C16,'CF (Equity, Debt)'!$F$3:$F$51) -> 0 | N16: =VLOOKUP(C16,NAV!$B$4:$E$46,4,0) -> 148.04984 | O16: =N16+M16-K16 -> 88.049841 | P16: =(M16+N16)/K16 -> 2.4674974 | Q16: =VLOOKUP(C16,'1. IRR Equity'!$AG$12:$AP$30,7,0) -> 0.33000317
C17: Jysan Technologies | D17: Realized | E17: Sushil | F17: Mozn 1 | G17: 2021 | H17: A (Ordinary Shares) | I17: ='6. %'!F16 -> 0.03 | J17: 20 | K17: =-SUMIF('CF (Equity, Debt)'!$C$3:$K$51,'S | 01 '!C17,'CF (Equity, Debt)'!$E$3:$E$51) -> 20 | L17: 0 | M17: =SUMIF('CF (Equity, Debt)'!$C$3:$K$51,'S | 01 '!C17,'CF (Equity, Debt)'!$F$3:$F$51) -> 24.5 | N17: =VLOOKUP(C17,NAV!$B$4:$E$46,4,0) -> 0 | O17: =N17+M17-K17 -> 4.5 | P17: =(M17+N17)/K17 -> 1.225 | Q17: =VLOOKUP(C17,'1. IRR Equity'!$AG$12:$AP$30,7,0) -> 0.098824507
C18: Cerebras Systems Inc | D18: Unrealized | E18: Ignasi | F18: Mozn | G18: 2021 | H18: F Prefs | I18: ='6. %'!F17 -> 0.0091172068 | J18: 40 | K18: =-SUMIF('CF (Equity, Debt)'!$C$3:$K$51,'S | 01 '!C18,'CF (Equity, Debt)'!$E$3:$E$51) -> 39.999983 | L18: 0 | M18: =SUMIF('CF (Equity, Debt)'!$C$3:$K$51,'S | 01 '!C18,'CF (Equity, Debt)'!$F$3:$F$51) -> 0 | N18: =VLOOKUP(C18,NAV!$B$4:$E$46,4,0) -> 39.999983 | O18: =N18+M18-K18 -> 0 | P18: =(M18+N18)/K18 -> 1 | Q18: =VLOOKUP(C18,'1. IRR Equity'!$AG$12:$AP$30,7,0) -> 2.9802322e-09
C19: Endless Studios LLC | D19: Unrealized | E19: Sushil | F19: Mozn | G19: 2021 | H19: A Pref Units | I19: ='6. %'!F18 -> 0.16080402 | J19: =K19 -> 8 | K19: =-SUMIF('CF (Equity, Debt)'!$C$3:$K$51,'S | 01 '!C19,'CF (Equity, Debt)'!$E$3:$E$51) -> 8 | L19: 0 | M19: =SUMIF('CF (Equity, Debt)'!$C$3:$K$51,'S | 01 '!C19,'CF (Equity, Debt)'!$F$3:$F$51) -> 0 | N19: =VLOOKUP(C19,NAV!$B$4:$E$46,4,0) -> 8 | O19: =N19+M19-K19 -> 0 | P19: =(M19+N19)/K19 -> 1 | Q19: =VLOOKUP(C19,'1. IRR Equity'!$AG$12:$AP$30,7,0) -> 2.9802322e-09
C20: Instadeep Limited | D20: Realized | E20: Ignasi | F20: Mozn | G20: 2021 | H20: B Prefs | I20: ='6. %'!F19 -> 0.011489406 | J20: 5.0278212 | K20: =-SUMIF('CF (Equity, Debt)'!$C$3:$K$51,'S | 01 '!C20,'CF (Equity, Debt)'!$E$3:$E$51) -> 5.0237202 | L20: 0 | M20: =SUMIF('CF (Equity, Debt)'!$C$3:$K$51,'S | 01 '!C20,'CF (Equity, Debt)'!$F$3:$F$51) -> 7.9421925 | N20: =VLOOKUP(C20,NAV!$B$4:$E$46,4,0) -> 0 | O20: =N20+M20-K20 -> 2.9184723 | P20: =(M20+N20)/K20 -> 1.5809385 | Q20: =VLOOKUP(C20,'1. IRR Equity'!$AG$12:$AP$30,7,0) -> 0.32803498
C21: X-fusion | D21: Realized | E21: Elaine | F21: Mozn 2 | G21: 2022 | H21: Equity-TBC | I21: ='6. %'!F20 -> 0.051 | J21: 493.5 | K21: =-SUMIF('CF (Equity, Debt)'!$C$3:$K$51,'S | 01 '!C21,'CF (Equity, Debt)'!$E$3:$E$51) -> 493.50096 | L21: 0 | M21: =SUMIF('CF (Equity, Debt)'!$C$3:$K$51,'S | 01 '!C21,'CF (Equity, Debt)'!$F$3:$F$51) -> 403 | N21: =VLOOKUP(C21,NAV!$B$4:$E$46,4,0) -> 0 | O21: =N21+M21-K21 -> -90.500956 | P21: =(M21+N21)/K21 -> 0.81661443 | Q21: =VLOOKUP(C21,'1. IRR Equity'!$AG$12:$AP$30,7,0) -> -0.10752884
C22: DriveNets | D22: Unrealized | E22: Anton | F22: G42 | G22: 2022 | H22: Equity-TBC | I22: ='6. %'!F21 -> 0.11141914 | J22: 300 | K22: =-SUMIF('CF (Equity, Debt)'!$C$3:$K$51,'S | 01 '!C22,'CF (Equity, Debt)'!$E$3:$E$51) -> 300 | L22: =0 -> 0 | M22: =SUMIF('CF (Equity, Debt)'!$C$3:$K$51,'S | 01 '!C22,'CF (Equity, Debt)'!$F$3:$F$51) -> 0 | N22: =VLOOKUP(C22,NAV!$B$4:$E$46,4,0) -> 300 | O22: =N22+M22-K22 -> 0 | P22: =(M22+N22)/K22 -> 1 | Q22: =VLOOKUP(C22,'1. IRR Equity'!$AG$12:$AP$30,7,0) -> 2.9802322e-09 | R22: DN Warrants b
C23: vTv Therapeutics Inc. | D23: Unrealized | E23: Divyesh | F23: G42 | G23: 2022 | H23: Ordinary Shares | I23: ='6. %'!F22 -> 0.0022129091 | J23: =K23 -> 24.53125 | K23: =-SUMIF('CF (Equity, Debt)'!$C$3:$K$51,'S | 01 '!C23,'CF (Equity, Debt)'!$E$3:$E$51) -> 24.53125 | L23: =J23-K23 -> 0 | M23: =SUMIF('CF (Equity, Debt)'!$C$3:$K$51,'S | 01 '!C23,'CF (Equity, Debt)'!$F$3:$F$51) -> 0 | N23: =VLOOKUP(C23,NAV!$B$4:$E$46,4,0) -> 2.1837154 | O23: =N23+M23-K23 -> -22.347535 | P23: =(M23+N23)/K23 -> 0.089017697 | Q23: =VLOOKUP(C23,'1. IRR Equity'!$AG$12:$AP$30,7,0) -> -0.87320089 | R23: vTv $30m milestn payment c
C24: Honor Device Co Ltd | D24: Realized | E24: Elaine | F24: G42 3 | G24: 2022 | H24: Equity-TBC | I24: ='6. %'!F23 -> 0.018823528 | J24: =K24 -> 800 | K24: =-SUMIF('CF (Equity, Debt)'!$C$3:$K$51,'S | 01 '!C24,'CF (Equity, Debt)'!$E$3:$E$51) -> 800 | L24: =J24-K24 -> 0 | M24: =SUMIF('CF (Equity, Debt)'!$C$3:$K$51,'S | 01 '!C24,'CF (Equity, Debt)'!$F$3:$F$51) -> 802.8 | N24: =VLOOKUP(C24,NAV!$B$4:$E$46,4,0) -> 0 | O24: =N24+M24-K24 -> 2.8 | P24: =(M24+N24)/K24 -> 1.0035 | Q24: =VLOOKUP(C24,'1. IRR Equity'!$AG$12:$AP$30,7,0) -> 0.0029359251
C25: Applied AI Corporation Limited | D25: Unrealized | E25: Divyesh | F25: Mozn | G25: 2022 | H25: Convertible Note | I25: ='6. %'!F24 -> n/a | J25: 15 | K25: =-SUMIF('CF (Equity, Debt)'!$C$3:$K$51,'S | 01 '!C25,'CF (Equity, Debt)'!$E$3:$E$51) -> 11.5 | L25: =J25-K25 -> 3.5 | M25: 0 | N25: =VLOOKUP(C25,NAV!$B$4:$E$46,4,0) -> 11.5 | O25: =N25+M25-K25 -> 0 | P25: =(M25+N25)/K25 -> 1 | Q25: =VLOOKUP(C25,'1. IRR Equity'!$AG$12:$AP$30,7,0) -> 2.9802322e-09
C26: eSpace | D26: Unrealized | E26: Anton | F26: Mozn 4 | G26: 2022 | H26: B Prefs | I26: ='6. %'!F25 -> 0.027864956 | J26: 15 | K26: =-SUMIF('CF (Equity, Debt)'!$C$3:$K$51,'S | 01 '!C26,'CF (Equity, Debt)'!$E$3:$E$51) -> 15 | L26: =J26-K26 -> 0 | M26: 0 | N26: =VLOOKUP(C26,NAV!$B$4:$E$46,4,0) -> 20.888122 | O26: =N26+M26-K26 -> 5.8881215 | P26: =(M26+N26)/K26 -> 1.3925414 | Q26: =VLOOKUP(C26,'1. IRR Equity'!$AG$12:$AP$30,7,0) -> 0.32455407
C27: Tools for Humanity Corporation | D27: Unrealized | E27: Divyesh | F27: Mozn | G27: 2023 | H27: C Prefs | I27: ='6. %'!F26 -> 0.0062621983 | J27: =K27 -> 14.999999 | K27: =-SUMIF('CF (Equity, Debt)'!$C$3:$K$51,'S | 01 '!C27,'CF (Equity, Debt)'!$E$3:$E$51) -> 14.999999 | L27: =J27-K27 -> 0 | M27: =M26 -> 0 | N27: =VLOOKUP(C27,NAV!$B$4:$E$46,4,0) -> 14.999999 | O27: =N27+M27-K27 -> 0 | P27: =(M27+N27)/K27 -> 1 | Q27: =VLOOKUP(C27,'1. IRR Equity'!$AG$12:$AP$30,7,0) -> 2.9802322e-09
C28: WLD Tokens | D28: Unrealized | E28: Divyesh | F28: Mozn | G28: 2023 | H28: Tokens | I28: ='6. %'!F27 -> 0.00625 | J28: =K28 -> 0.006875 | K28: =-SUMIF('CF (Equity, Debt)'!$C$3:$K$51,'S | 01 '!C28,'CF (Equity, Debt)'!$E$3:$E$51) -> 0.006875 | L28: =J28-K28 -> 0 | M28: =M27 -> 0 | N28: =VLOOKUP(C28,NAV!$B$4:$E$46,4,0) -> 15 | O28: =N28+M28-K28 -> 14.993125 | P28: NM | Q28: =VLOOKUP(C28,'1. IRR Equity'!$AG$12:$AP$30,7,0) -> NM | R28: Crypto Tokensd
C29: E-line Ventures LLC | D29: Unrealized | E29: Sushil | F29: Mozn | G29: 2023 | H29: B Prefs | I29: ='6. %'!F28 -> 0.11483736 | J29: =K29 -> 6 | K29: =-SUMIF('CF (Equity, Debt)'!$C$3:$K$51,'S | 01 '!C29,'CF (Equity, Debt)'!$E$3:$E$51) -> 6 | L29: =J29-K29 -> 0 | M29: =M28 -> 0 | N29: =VLOOKUP(C29,NAV!$B$4:$E$46,4,0) -> 6 | O29: =N29+M29-K29 -> 0 | P29: NM | Q29: NM | R29: Optionse
C30: School Hack (AIREV Holding Limited) | D30: Unrealized | E30: Camillo | F30: Core42 | G30: 2024 | H30: Preferred Shares | I30: ='6. %'!F29 -> 0.25 | J30: 2.75 | K30: =-SUMIF('CF (Equity, Debt)'!$C$3:$K$51,'S | 01 '!C30,'CF (Equity, Debt)'!$E$3:$E$51) -> 2.75 | L30: =J30-K30 -> 0 | M30: =M29 -> 0 | N30: =VLOOKUP(C30,NAV!$B$4:$E$46,4,0) -> 2.75 | O30: =N30+M30-K30 -> 0 | P30: NM | Q30: NM | R30: Cloud Creditg
J32: =SUM(J10:J30) -> 2121.7862 | K32: =SUM(K10:K30) -> 2118.283 | L32: =SUM(L10:L30) -> 3.5 | M32: =SUM(M10:M30) -> 1243.2422 | N32: =SUM(N10:N30) -> 828.59461 | O32: =SUM(O10:O30) -> -46.446245 | P32: =(M32+N32)/K32 -> 0.97807364 | Q32: ='1. IRR Equity'!AH40 -> -0.011569161
C34: Debt Investments
C35: Glass Earth Holdings LLC | D35: Written-off | E35: Marty | F35: Mozn | G35: 2019 | H35: Promissory Note | I35: n/a | J35: 8 | K35: 8 | L35: 0 | M35: 0 | N35: 0 | O35: =N35+M35-K35 -> -8 | P35: =(M35+N35)/K35 -> 0 | Q35: =VLOOKUP(C35,'2. IRR Debt'!$P$9:$Y$11,7,0) -> NM | R35: In Default
C36: Mena Mobile Inc (Debt) | D36: Written-off | E36: Elaine | F36: Mozn | G36: 2021 | H36: Loan | I36: n/a | J36: 2.353982 | K36: =J36 -> 2.353982 | L36: 0 | M36: 0 | N36: =VLOOKUP(C36,NAV!$B$4:$E$46,4,0) -> 0 | O36: =N36+M36-K36 -> -2.353982 | P36: =(M36+N36)/K36 -> 0 | Q36: =VLOOKUP(C36,'2. IRR Debt'!$P$9:$Y$11,7,0) -> NM | R36: In Liquidation
C37: Esyasoft Holding (Debt) | D37: Realized | E37: Sushil | F37: Mozn | G37: 2021 | H37: Loan | I37: n/a | J37: 0.411765 | K37: 0.411765 | L37: 0 | M37: ='CF (Equity, Debt)'!F56 -> 0.47078465 | N37: 0 | O37: =N37+M37-K37 -> 0.05901965 | P37: =(M37+N37)/K37 -> 1.1433333 | Q37: =VLOOKUP(C37,'2. IRR Debt'!$P$9:$Y$11,7,0) -> 0.075277027
J38: =SUM(J35:J37) -> 10.765747 | K38: =SUM(K35:K37) -> 10.765747 | L38: =SUM(L35:L37) -> 0 | M38: =SUM(M35:M37) -> 0.47078465 | N38: =SUM(N35:N37) -> 0 | O38: =N38+M38-K38 -> -10.294962 | P38: =(M38+N38)/K38 -> 0.043729864 | Q38: ='2. IRR Debt'!Q15 -> -0.71226245
C40: Funds Investments
C41: New Space Capital Fund I | D41: Unrealized | E41: Sushil | F41: G42 | G41: 2020 | H41: LP | I41: n/a | J41: =K41+L41 -> 31.022787 | K41: =-SUMIF('CF (Funds)'!$B$3:$D$2006,C41,'CF (Funds)'!$D$3:$D$2006) -> 13.988553 | L41: ='5. NewSpace'!I54 -> 17.034234 | M41: =SUM('CF (Funds)'!E36:E42) -> 2.9557744 | N41: =VLOOKUP(C41,NAV!$B$4:$E$46,4,0) -> 13.277945 | O41: =N41+M41-K41 -> 2.2451661 | P41: =(M41+N41)/K41 -> 1.1605002 | Q41: =VLOOKUP(C41,'3. IRR Funds'!$P$7:$Y$15,7,0) -> 0.036116043
C42: New Space Capital GP Com SCSp | D42: Unrealized | E42: Sushil | F42: G42 | G42: 2023 | H42: LP | I42: n/a | J42: =2.3/0.85 -> 2.7058824 | K42: 2.7058824 | L42: 0 | M42: 0 | N42: =VLOOKUP(C42,NAV!$B$4:$E$46,4,0) -> 2.5684255 | O42: =N42+M42-K42 -> -0.13745685 | P42: =(M42+N42)/K42 -> 0.94920073 | Q42: =VLOOKUP(C42,'3. IRR Funds'!$P$7:$Y$15,7,0) -> 0
C43: North Summit Capital Fund | D43: Unrealized | E43: Elaine | F43: G42 | G43: 2020 | H43: LP | I43: n/a | J43: =K43+L43 -> 83.334353 | K43: =-SUMIF('CF (Funds)'!$B$3:$D$2006,C43,'CF (Funds)'!$D$3:$D$2006) -> 83.214653 | L43: =217.813308-217.693608 -> 0.1197 | M43: =SUM('CF (Funds)'!E25:'CF (Funds)'!E35) -> 7.815871 | N43: =VLOOKUP(C43,NAV!$B$4:$E$46,4,0) -> 74.725861 | O43: =N43+M43-K43 -> -0.672921 | P43: =(M43+N43)/K43 -> 0.99191343 | Q43: =VLOOKUP(C43,'3. IRR Funds'!$P$7:$Y$15,7,0) -> -0.0025177218
C44: Sinovation Disrupt Fund, L.P. | D44: Realized | E44: Elaine | F44: G42 | G44: 2020 | H44: LP | I44: n/a | J44: 50 | K44: =-SUMIF('CF (Funds)'!$B$3:$D$2006,C44,'CF (Funds)'!$D$3:$D$2006) -> 24.959693 | L44: =J44-K44 -> 25.040307 | M44: =SUM('CF (Funds)'!E3:E20) -> 0.44382835 | N44: =VLOOKUP(C44,NAV!$B$4:$E$46,4,0) -> 23.670303 | O44: =N44+M44-K44 -> -0.84556165 | P44: =(M44+N44)/K44 -> 0.96612291 | Q44: =VLOOKUP(C44,'3. IRR Funds'!$P$7:$Y$15,7,0) -> -0.014868453
C45: Acies Investments Fund I, L.P. | D45: Unrealized | E45: Divyesh | F45: G42 | G45: 2021 | H45: LP | I45: 0.33 | J45: 17.1125 | K45: =-SUMIF('CF (Funds)'!$B$3:$D$2006,C45,'CF (Funds)'!$D$3:$D$2006) -> 14.015137 | L45: =J45-K45 -> 3.0973625 | M45: 0 | N45: =VLOOKUP(C45,NAV!$B$4:$E$46,4,0) -> 12.310425 | O45: =N45+M45-K45 -> -1.7047125 | P45: =(M45+N45)/K45 -> 0.87836634 | Q45: =VLOOKUP(C45,'3. IRR Funds'!$P$7:$Y$15,7,0) -> -0.071990828 | R45: 9.9% GP | Anchorf
J46: =SUM(J41:J45) -> 184.17552 | K46: =SUM(K41:K45) -> 138.88392 | L46: =SUM(L41:L45) -> 45.291603 | M46: =SUM(M41:M45) -> 11.215474 | N46: =SUM(N41:N45) -> 126.55296 | O46: =N46+M46-K46 -> -1.1154859 | P46: =(M46+N46)/K46 -> 0.99196821 | Q46: ='3. IRR Funds'!Q18 -> 2.9802322e-09
C48: Total | J48: =J32+J38+J46 -> 2316.7275 | K48: =K32+K38+K46 -> 2267.9327 | L48: =L32+L38+L46 -> 48.791603 | M48: =M32+M38+M46 -> 1254.9285 | N48: =N32+N38+N46 -> 955.14756 | O48: =N48+M48-K48 -> -57.856694 | P48: =(M48+N48)/K48 -> 0.97448924 | Q48: ='4.All'!N9 -> -0.012957468
K49: =ROUND(K48,2)=ROUND('4.All'!J9,2) -> TRUE | M49: =ROUND(M48,2)=ROUND('4.All'!L9,2) -> TRUE | N49: =ROUND(N48,2)=ROUND('4.All'!M9,2) -> TRUE
C51: Additional Upside Section:
C52: a) Flyr: For every $1m of revenue, 194,477 shares, capped at 1,264,1000 (B-1) shares shall be issued to Mozn
C53: b) DriveNets: Share warrants exercisable upon the achievement of target revenue of clients referred by G42, and corresponding milestones
C54: c) vTv Therapeutics: Potential issuance of $30m in additional shares, if FDA approval received for the drug TTP399
C55: d) Tools for Humanity Corporation: An additional 62.5 million Tokens (WLD tokens) received for a consideration of $6,875.00.
C56: e) E-line Ventures LLC: Option to further acquire Series B Pref shares at max($1.34, EV/No of shares)
C57: f) Acies Investments Fund I LP: Being the Anchor investor, entitled to 9.9% of the aggregate carried interest earned by the GP
C58: g) Cloud Credit of 250K counted towards the investment cost
C60: Definition:
C61: ἀ = Vintage corresponds to the year of the first investment made
C62: β = Excludes transaction costs from the estimate of IRR, as those are not available
C63: IRR is referred as NM when it is not meaningful
... C76: TBC = to be confirmed

Sheet S | 02
C2: As of date | E2: =D!D2 -> 45322
E5: 2 | F5: 3 | G5: 4 | H5: 5 | I5: 6 | J5: 7 | K5: 8 | L5: 9 | M5: 11 | N5: 12 | O5: 13 | Q5: 15 | R5: 14 | S5: 10 | T5: 16
C6: Deals | D6: Type | E6: Status | F6: Lead | G6: Investing Entity | H6: Vintageἀ | I6: Instrument | J6: % | K6: Committed | L6: Invested | M6: Distributions | N6: Carrying Value | O6: Gain | P6: Gain till FY22 | Q6: IRRβ | R6: TVPI | S6: Remaining Commitment | T6: Additonal Upside/Downside
I7: # | J7: % | K7: $,m | L7: $,m | M7: $,m | N7: $,m | O7: $,m | Q7: % | R7: X | S7: $,m | W7: MOZN
C9: School Hack (AIREV Holding Limited) | D9: Direct Investment | E9: =VLOOKUP($C9,'S | 01 '!$C$6:$R$48,E$5,0) -> Unrealized | F9: =VLOOKUP($C9,'S | 01 '!$C$6:$R$48,F$5,0) -> Camillo | G9: =VLOOKUP($C9,'S | 01 '!$C$6:$R$48,G$5,0) -> Core42 | H9: =VLOOKUP($C9,'S | 01 '!$C$6:$R$48,H$5,0) -> 2024 | I9: =VLOOKUP($C9,'S | 01 '!$C$6:$R$48,I$5,0) -> Preferred Shares | J9: =VLOOKUP($C9,'S | 01 '!$C$6:$R$48,J$5,0) -> 0.25 | K9: =VLOOKUP($C9,'S | 01 '!$C$6:$R$48,K$5,0) -> 2.75 | L9: =VLOOKUP($C9,'S | 01 '!$C$6:$R$48,L$5,0) -> 2.75 | ... O9: =VLOOKUP($C9,'S | 01 '!$C$6:$R$48,O$5,0) -> 0 | P9: n/a | Q9: =VLOOKUP($C9,'S | 01 '!$C$6:$R$48,Q$5,0) -> NM | R9: =VLOOKUP($C9,'S | 01 '!$C$6:$R$48,R$5,0) -> NM | S9: =VLOOKUP($C9,'S | 01 '!$C$6:$R$48,S$5,0) -> 0 | T9: Cloud Creditg
C10: E-line Ventures LLC | D10: Direct Investment | E10: =VLOOKUP($C10,'S | 01 '!$C$6:$R$48,E$5,0) -> Unrealized | F10: =VLOOKUP($C10,'S | 01 '!$C$6:$R$48,F$5,0) -> Sushil | G10: =VLOOKUP($C10,'S | 01 '!$C$6:$R$48,G$5,0) -> Mozn | H10: =VLOOKUP($C10,'S | 01 '!$C$6:$R$48,H$5,0) -> 2023 | I10: =VLOOKUP($C10,'S | 01 '!$C$6:$R$48,I$5,0) -> B Prefs | J10: =VLOOKUP($C10,'S | 01 '!$C$6:$R$48,J$5,0) -> 0.11483736 | K10: =VLOOKUP($C10,'S | 01 '!$C$6:$R$48,K$5,0) -> 6 | L10: =VLOOKUP($C10,'S | 01 '!$C$6:$R$48,L$5,0) -> 6 | ... O10: =VLOOKUP($C10,'S | 01 '!$C$6:$R$48,O$5,0) -> 0 | P10: n/a | Q10: =VLOOKUP($C10,'S | 01 '!$C$6:$R$48,Q$5,0) -> NM | R10: =VLOOKUP($C10,'S | 01 '!$C$6:$R$48,R$5,0) -> NM | S10: =VLOOKUP($C10,'S | 01 '!$C$6:$R$48,S$5,0) -> 0 | T10: Optionse
C11: WLD Tokens | D11: Direct Investment | E11: =VLOOKUP($C11,'S | 01 '!$C$6:$R$48,E$5,0) -> Unrealized | F11: =VLOOKUP($C11,'S | 01 '!$C$6:$R$48,F$5,0) -> Divyesh | G11: =VLOOKUP($C11,'S | 01 '!$C$6:$R$48,G$5,0) -> Mozn | H11: =VLOOKUP($C11,'S | 01 '!$C$6:$R$48,H$5,0) -> 2023 | I11: =VLOOKUP($C11,'S | 01 '!$C$6:$R$48,I$5,0) -> Tokens | J11: =VLOOKUP($C11,'S | 01 '!$C$6:$R$48,J$5,0) -> 0.00625 | K11: =VLOOKUP($C11,'S | 01 '!$C$6:$R$48,K$5,0) -> 0.006875 | L11: =VLOOKUP($C11,'S | 01 '!$C$6:$R$48,L$5,0) -> 0.006875 | ... O11: =VLOOKUP($C11,'S | 01 '!$C$6:$R$48,O$5,0) -> 14.993125 | P11: n/a | Q11: =VLOOKUP($C11,'S | 01 '!$C$6:$R$48,Q$5,0) -> NM | R11: =VLOOKUP($C11,'S | 01 '!$C$6:$R$48,R$5,0) -> NM | S11: =VLOOKUP($C11,'S | 01 '!$C$6:$R$48,S$5,0) -> 0 | T11: =VLOOKUP($C11,'S | 01 '!$C$6:$R$48,T$5,0) -> Crypto Tokensd
C12: Tools for Humanity Corporation | D12: Direct Investment | E12: =VLOOKUP($C12,'S | 01 '!$C$6:$R$48,E$5,0) -> Unrealized | F12: =VLOOKUP($C12,'S | 01 '!$C$6:$R$48,F$5,0) -> Divyesh | G12: =VLOOKUP($C12,'S | 01 '!$C$6:$R$48,G$5,0) -> Mozn | H12: =VLOOKUP($C12,'S | 01 '!$C$6:$R$48,H$5,0) -> 2023 | I12: =VLOOKUP($C12,'S | 01 '!$C$6:$R$48,I$5,0) -> C Prefs | J12: =VLOOKUP($C12,'S | 01 '!$C$6:$R$48,J$5,0) -> 0.0062621983 | K12: =VLOOKUP($C12,'S | 01 '!$C$6:$R$48,K$5,0) -> 14.999999 | L12: =VLOOKUP($C12,'S | 01 '!$C$6:$R$48,L$5,0) -> 14.999999 | ... O12: =VLOOKUP($C12,'S | 01 '!$C$6:$R$48,O$5,0) -> 0 | P12: n/a | Q12: =VLOOKUP($C12,'S | 01 '!$C$6:$R$48,Q$5,0) -> 2.9802322e-09 | R12: =VLOOKUP($C12,'S | 01 '!$C$6:$R$48,R$5,0) -> 1 | S12: =VLOOKUP($C12,'S | 01 '!$C$6:$R$48,S$5,0) -> 0
C13: eSpace | D13: Direct Investment | E13: =VLOOKUP($C13,'S | 01 '!$C$6:$R$48,E$5,0) -> Unrealized | F13: =VLOOKUP($C13,'S | 01 '!$C$6:$R$48,F$5,0) -> Anton | G13: =VLOOKUP($C13,'S | 01 '!$C$6:$R$48,G$5,0) -> Mozn 4 | H13: =VLOOKUP($C13,'S | 01 '!$C$6:$R$48,H$5,0) -> 2022 | I13: =VLOOKUP($C13,'S | 01 '!$C$6:$R$48,I$5,0) -> B Prefs | J13: =VLOOKUP($C13,'S | 01 '!$C$6:$R$48,J$5,0) -> 0.027864956 | K13: =VLOOKUP($C13,'S | 01 '!$C$6:$R$48,K$5,0) -> 15 | L13: =VLOOKUP($C13,'S | 01 '!$C$6:$R$48,L$5,0) -> 15 | ... O13: =VLOOKUP($C13,'S | 01 '!$C$6:$R$48,O$5,0) -> 5.8881215 | P13: 0 | Q13: =VLOOKUP($C13,'S | 01 '!$C$6:$R$48,Q$5,0) -> 0.32455407 | R13: =VLOOKUP($C13,'S | 01 '!$C$6:$R$48,R$5,0) -> 1.3925414 | S13: =VLOOKUP($C13,'S | 01 '!$C$6:$R$48,S$5,0) -> 0 | W13: Invested | X13: =L31 -> 1004.5175
C14: Applied AI Corporation Limited | D14: Direct Investment | E14: =VLOOKUP($C14,'S | 01 '!$C$6:$R$48,E$5,0) -> Unrealized | F14: =VLOOKUP($C14,'S | 01 '!$C$6:$R$48,F$5,0) -> Divyesh | G14: =VLOOKUP($C14,'S | 01 '!$C$6:$R$48,G$5,0) -> Mozn | H14: =VLOOKUP($C14,'S | 01 '!$C$6:$R$48,H$5,0) -> 2022 | I14: =VLOOKUP($C14,'S | 01 '!$C$6:$R$48,I$5,0) -> Convertible Note | J14: =VLOOKUP($C14,'S | 01 '!$C$6:$R$48,J$5,0) -> n/a | K14: =VLOOKUP($C14,'S | 01 '!$C$6:$R$48,K$5,0) -> 15 | L14: =VLOOKUP($C14,'S | 01 '!$C$6:$R$48,L$5,0) -> 11.5 | ... O14: =VLOOKUP($C14,'S | 01 '!$C$6:$R$48,O$5,0) -> 0 | P14: 0 | Q14: =VLOOKUP($C14,'S | 01 '!$C$6:$R$48,Q$5,0) -> 2.9802322e-09 | R14: =VLOOKUP($C14,'S | 01 '!$C$6:$R$48,R$5,0) -> 1 | S14: =VLOOKUP($C14,'S | 01 '!$C$6:$R$48,S$5,0) -> 3.5 | W14: NAV | X14: =N31 -> 526.41089
C15: X-fusion | D15: Direct Investment | E15: =VLOOKUP($C15,'S | 01 '!$C$6:$R$48,E$5,0) -> Realized | F15: =VLOOKUP($C15,'S | 01 '!$C$6:$R$48,F$5,0) -> Elaine | G15: =VLOOKUP($C15,'S | 01 '!$C$6:$R$48,G$5,0) -> Mozn 2 | H15: =VLOOKUP($C15,'S | 01 '!$C$6:$R$48,H$5,0) -> 2022 | I15: =VLOOKUP($C15,'S | 01 '!$C$6:$R$48,I$5,0) -> Equity-TBC | J15: =VLOOKUP($C15,'S | 01 '!$C$6:$R$48,J$5,0) -> 0.051 | K15: =VLOOKUP($C15,'S | 01 '!$C$6:$R$48,K$5,0) -> 493.5 | L15: =VLOOKUP($C15,'S | 01 '!$C$6:$R$48,L$5,0) -> 493.50096 | ... O15: =VLOOKUP($C15,'S | 01 '!$C$6:$R$48,O$5,0) -> -90.500956 | P15: -64.391 | Q15: =VLOOKUP($C15,'S | 01 '!$C$6:$R$48,Q$5,0) -> -0.10752884 | R15: =VLOOKUP($C15,'S | 01 '!$C$6:$R$48,R$5,0) -> 0.81661443 | S15: =VLOOKUP($C15,'S | 01 '!$C$6:$R$48,S$5,0) -> 0 | W15: Gain | X15: =O31 -> -37.193673
C16: Mena Mobile Inc (Debt) | D16: Debt Investment | E16: =VLOOKUP($C16,'S | 01 '!$C$6:$R$48,E$5,0) -> Written-off | F16: =VLOOKUP($C16,'S | 01 '!$C$6:$R$48,F$5,0) -> Elaine | G16: =VLOOKUP($C16,'S | 01 '!$C$6:$R$48,G$5,0) -> Mozn | H16: =VLOOKUP($C16,'S | 01 '!$C$6:$R$48,H$5,0) -> 2021 | I16: =VLOOKUP($C16,'S | 01 '!$C$6:$R$48,I$5,0) -> Loan | J16: =VLOOKUP($C16,'S | 01 '!$C$6:$R$48,J$5,0) -> n/a | K16: =VLOOKUP($C16,'S | 01 '!$C$6:$R$48,K$5,0) -> 2.353982 | L16: =VLOOKUP($C16,'S | 01 '!$C$6:$R$48,L$5,0) -> 2.353982 | ... O16: =VLOOKUP($C16,'S | 01 '!$C$6:$R$48,O$5,0) -> -2.353982 | P16: 0 | Q16: =VLOOKUP($C16,'S | 01 '!$C$6:$R$48,Q$5,0) -> NM | R16: =VLOOKUP($C16,'S | 01 '!$C$6:$R$48,R$5,0) -> 0 | S16: =VLOOKUP($C16,'S | 01 '!$C$6:$R$48,S$5,0) -> 0 | W16: YTD Gains | X16: =X15-P31 -> -51.730871
C17: Esyasoft Holding (Debt) | D17: Debt Investment | E17: =VLOOKUP($C17,'S | 01 '!$C$6:$R$48,E$5,0) -> Realized | F17: =VLOOKUP($C17,'S | 01 '!$C$6:$R$48,F$5,0) -> Sushil | G17: =VLOOKUP($C17,'S | 01 '!$C$6:$R$48,G$5,0) -> Mozn | H17: =VLOOKUP($C17,'S | 01 '!$C$6:$R$48,H$5,0) -> 2021 | I17: =VLOOKUP($C17,'S | 01 '!$C$6:$R$48,I$5,0) -> Loan | J17: =VLOOKUP($C17,'S | 01 '!$C$6:$R$48,J$5,0) -> n/a | K17: =VLOOKUP($C17,'S | 01 '!$C$6:$R$48,K$5,0) -> 0.411765 | L17: =VLOOKUP($C17,'S | 01 '!$C$6:$R$48,L$5,0) -> 0.411765 | ... O17: =VLOOKUP($C17,'S | 01 '!$C$6:$R$48,O$5,0) -> 0.05901965 | P17: 0.05901965 | Q17: =VLOOKUP($C17,'S | 01 '!$C$6:$R$48,Q$5,0) -> 0.075277027 | R17: =VLOOKUP($C17,'S | 01 '!$C$6:$R$48,R$5,0) -> 1.1433333 | S17: =VLOOKUP($C17,'S | 01 '!$C$6:$R$48,S$5,0) -> 0 | W17: IRR | X17: =Q31 -> -0.014740654
C18: Jysan Technologies | D18: Direct Investment | E18: =VLOOKUP($C18,'S | 01 '!$C$6:$R$48,E$5,0) -> Realized | F18: =VLOOKUP($C18,'S | 01 '!$C$6:$R$48,F$5,0) -> Sushil | G18: =VLOOKUP($C18,'S | 01 '!$C$6:$R$48,G$5,0) -> Mozn 1 | H18: =VLOOKUP($C18,'S | 01 '!$C$6:$R$48,H$5,0) -> 2021 | I18: =VLOOKUP($C18,'S | 01 '!$C$6:$R$48,I$5,0) -> A (Ordinary Shares) | J18: =VLOOKUP($C18,'S | 01 '!$C$6:$R$48,J$5,0) -> 0.03 | K18: =VLOOKUP($C18,'S | 01 '!$C$6:$R$48,K$5,0) -> 20 | L18: =VLOOKUP($C18,'S | 01 '!$C$6:$R$48,L$5,0) -> 20 | ... O18: =VLOOKUP($C18,'S | 01 '!$C$6:$R$48,O$5,0) -> 4.5 | P18: 0 | Q18: =VLOOKUP($C18,'S | 01 '!$C$6:$R$48,Q$5,0) -> 0.098824507 | R18: =VLOOKUP($C18,'S | 01 '!$C$6:$R$48,R$5,0) -> 1.225 | S18: =VLOOKUP($C18,'S | 01 '!$C$6:$R$48,S$5,0) -> 0
C19: Instadeep Limited | D19: Direct Investment | E19: =VLOOKUP($C19,'S | 01 '!$C$6:$R$48,E$5,0) -> Realized | F19: =VLOOKUP($C19,'S | 01 '!$C$6:$R$48,F$5,0) -> Ignasi | G19: =VLOOKUP($C19,'S | 01 '!$C$6:$R$48,G$5,0) -> Mozn | H19: =VLOOKUP($C19,'S | 01 '!$C$6:$R$48,H$5,0) -> 2021 | I19: =VLOOKUP($C19,'S | 01 '!$C$6:$R$48,I$5,0) -> B Prefs | J19: =VLOOKUP($C19,'S | 01 '!$C$6:$R$48,J$5,0) -> 0.011489406 | K19: =VLOOKUP($C19,'S | 01 '!$C$6:$R$48,K$5,0) -> 5.0278212 | L19: =VLOOKUP($C19,'S | 01 '!$C$6:$R$48,L$5,0) -> 5.0237202 | ... O19: =VLOOKUP($C19,'S | 01 '!$C$6:$R$48,O$5,0) -> 2.9184723 | P19: 1.6721788 | Q19: =VLOOKUP($C19,'S | 01 '!$C$6:$R$48,Q$5,0) -> 0.32803498 | R19: =VLOOKUP($C19,'S | 01 '!$C$6:$R$48,R$5,0) -> 1.5809385 | S19: =VLOOKUP($C19,'S | 01 '!$C$6:$R$48,S$5,0) -> 0
C20: Cerebras Systems Inc | D20: Direct Investment | E20: =VLOOKUP($C20,'S | 01 '!$C$6:$R$48,E$5,0) -> Unrealized | F20: =VLOOKUP($C20,'S | 01 '!$C$6:$R$48,F$5,0) -> Ignasi | G20: =VLOOKUP($C20,'S | 01 '!$C$6:$R$48,G$5,0) -> Mozn | H20: =VLOOKUP($C20,'S | 01 '!$C$6:$R$48,H$5,0) -> 2021 | I20: =VLOOKUP($C20,'S | 01 '!$C$6:$R$48,I$5,0) -> F Prefs | J20: =VLOOKUP($C20,'S | 01 '!$C$6:$R$48,J$5,0) -> 0.0091172068 | K20: =VLOOKUP($C20,'S | 01 '!$C$6:$R$48,K$5,0) -> 40 | L20: =VLOOKUP($C20,'S | 01 '!$C$6:$R$48,L$5,0) -> 39.999983 | ... O20: =VLOOKUP($C20,'S | 01 '!$C$6:$R$48,O$5,0) -> 0 | P20: 0 | Q20: =VLOOKUP($C20,'S | 01 '!$C$6:$R$48,Q$5,0) -> 2.9802322e-09 | R20: =VLOOKUP($C20,'S | 01 '!$C$6:$R$48,R$5,0) -> 1 | S20: =VLOOKUP($C20,'S | 01 '!$C$6:$R$48,S$5,0) -> 0
C21: Endless Studios LLC | D21: Direct Investment | E21: =VLOOKUP($C21,'S | 01 '!$C$6:$R$48,E$5,0) -> Unrealized | F21: =VLOOKUP($C21,'S | 01 '!$C$6:$R$48,F$5,0) -> Sushil | G21: =VLOOKUP($C21,'S | 01 '!$C$6:$R$48,G$5,0) -> Mozn | H21: =VLOOKUP($C21,'S | 01 '!$C$6:$R$48,H$5,0) -> 2021 | I21: =VLOOKUP($C21,'S | 01 '!$C$6:$R$48,I$5,0) -> A Pref Units | J21: =VLOOKUP($C21,'S | 01 '!$C$6:$R$48,J$5,0) -> 0.16080402 | K21: =VLOOKUP($C21,'S | 01 '!$C$6:$R$48,K$5,0) -> 8 | L21: =VLOOKUP($C21,'S | 01 '!$C$6:$R$48,L$5,0) -> 8 | ... O21: =VLOOKUP($C21,'S | 01 '!$C$6:$R$48,O$5,0) -> 0 | P21: 0 | Q21: =VLOOKUP($C21,'S | 01 '!$C$6:$R$48,Q$5,0) -> 2.9802322e-09 | R21: =VLOOKUP($C21,'S | 01 '!$C$6:$R$48,R$5,0) -> 1 | S21: =VLOOKUP($C21,'S | 01 '!$C$6:$R$48,S$5,0) -> 0
C22: Esyasoft Holding | D22: Direct Investment | E22: =VLOOKUP($C22,'S | 01 '!$C$6:$R$48,E$5,0) -> Realized | F22: =VLOOKUP($C22,'S | 01 '!$C$6:$R$48,F$5,0) -> Sushil | G22: =VLOOKUP($C22,'S | 01 '!$C$6:$R$48,G$5,0) -> Mozn | H22: =VLOOKUP($C22,'S | 01 '!$C$6:$R$48,H$5,0) -> 2020 | I22: =VLOOKUP($C22,'S | 01 '!$C$6:$R$48,I$5,0) -> Convertible Note | J22: =VLOOKUP($C22,'S | 01 '!$C$6:$R$48,J$5,0) -> n/a | K22: =VLOOKUP($C22,'S | 01 '!$C$6:$R$48,K$5,0) -> 2.5 | L22: =VLOOKUP($C22,'S | 01 '!$C$6:$R$48,L$5,0) -> 2.5 | ... O22: =VLOOKUP($C22,'S | 01 '!$C$6:$R$48,O$5,0) -> 2.5 | P22: 2.5 | Q22: =VLOOKUP($C22,'S | 01 '!$C$6:$R$48,Q$5,0) -> 0.36091766 | R22: =VLOOKUP($C22,'S | 01 '!$C$6:$R$48,R$5,0) -> 2 | S22: =VLOOKUP($C22,'S | 01 '!$C$6:$R$48,S$5,0) -> 0
C23: Heygears | D23: Direct Investment | E23: =VLOOKUP($C23,'S | 01 '!$C$6:$R$48,E$5,0) -> Unrealized | F23: =VLOOKUP($C23,'S | 01 '!$C$6:$R$48,F$5,0) -> Elaine | G23: =VLOOKUP($C23,'S | 01 '!$C$6:$R$48,G$5,0) -> Mozn | H23: =VLOOKUP($C23,'S | 01 '!$C$6:$R$48,H$5,0) -> 2020 | I23: =VLOOKUP($C23,'S | 01 '!$C$6:$R$48,I$5,0) -> Registered Capital | J23: =VLOOKUP($C23,'S | 01 '!$C$6:$R$48,J$5,0) -> 0.1438 | K23: =VLOOKUP($C23,'S | 01 '!$C$6:$R$48,K$5,0) -> 60 | L23: =VLOOKUP($C23,'S | 01 '!$C$6:$R$48,L$5,0) -> 60 | ... O23: =VLOOKUP($C23,'S | 01 '!$C$6:$R$48,O$5,0) -> 88.049841 | P23: 96.4 | Q23: =VLOOKUP($C23,'S | 01 '!$C$6:$R$48,Q$5,0) -> 0.33000317 | R23: =VLOOKUP($C23,'S | 01 '!$C$6:$R$48,R$5,0) -> 2.4674974 | S23: =VLOOKUP($C23,'S | 01 '!$C$6:$R$48,S$5,0) -> 0
C24: Beyond Limits | D24: Direct Investment | E24: =VLOOKUP($C24,'S | 01 '!$C$6:$R$48,E$5,0) -> Unrealized | F24: =VLOOKUP($C24,'S | 01 '!$C$6:$R$48,F$5,0) -> Divyesh | G24: =VLOOKUP($C24,'S | 01 '!$C$6:$R$48,G$5,0) -> Mozn | H24: =VLOOKUP($C24,'S | 01 '!$C$6:$R$48,H$5,0) -> 2020 | I24: =VLOOKUP($C24,'S | 01 '!$C$6:$R$48,I$5,0) -> C Prefs | J24: =VLOOKUP($C24,'S | 01 '!$C$6:$R$48,J$5,0) -> 0.097965107 | K24: =VLOOKUP($C24,'S | 01 '!$C$6:$R$48,K$5,0) -> 90 | L24: =VLOOKUP($C24,'S | 01 '!$C$6:$R$48,L$5,0) -> 90 | ... O24: =VLOOKUP($C24,'S | 01 '!$C$6:$R$48,O$5,0) -> 1.0015403 | P24: 1.042 | Q24: =VLOOKUP($C24,'S | 01 '!$C$6:$R$48,Q$5,0) -> 0.0029582828 | R24: =VLOOKUP($C24,'S | 01 '!$C$6:$R$48,R$5,0) -> 1.0111282 | S24: =VLOOKUP($C24,'S | 01 '!$C$6:$R$48,S$5,0) -> 0
C25: ONT plc | D25: Direct Investment | E25: =VLOOKUP($C25,'S | 01 '!$C$6:$R$48,E$5,0) -> Unrealized | F25: =VLOOKUP($C25,'S | 01 '!$C$6:$R$48,F$5,0) -> Divyesh | G25: =VLOOKUP($C25,'S | 01 '!$C$6:$R$48,G$5,0) -> Mozn | H25: =VLOOKUP($C25,'S | 01 '!$C$6:$R$48,H$5,0) -> 2020 | I25: =VLOOKUP($C25,'S | 01 '!$C$6:$R$48,I$5,0) -> Ordinary Shares | J25: =VLOOKUP($C25,'S | 01 '!$C$6:$R$48,J$5,0) -> 0.051651565 | K25: =VLOOKUP($C25,'S | 01 '!$C$6:$R$48,K$5,0) -> 141.47026 | L25: =VLOOKUP($C25,'S | 01 '!$C$6:$R$48,L$5,0) -> 141.47026 | ... O25: =VLOOKUP($C25,'S | 01 '!$C$6:$R$48,O$5,0) -> -51.331085 | P25: -9.845 | Q25: =VLOOKUP($C25,'S | 01 '!$C$6:$R$48,Q$5,0) -> -0.11648149 | R25: =VLOOKUP($C25,'S | 01 '!$C$6:$R$48,R$5,0) -> 0.63715989 | S25: =VLOOKUP($C25,'S | 01 '!$C$6:$R$48,S$5,0) -> 0
C26: Flyr Inc | D26: Direct Investment | E26: =VLOOKUP($C26,'S | 01 '!$C$6:$R$48,E$5,0) -> Unrealized | F26: =VLOOKUP($C26,'S | 01 '!$C$6:$R$48,F$5,0) -> Sushil | G26: =VLOOKUP($C26,'S | 01 '!$C$6:$R$48,G$5,0) -> Mozn | H26: =VLOOKUP($C26,'S | 01 '!$C$6:$R$48,H$5,0) -> 2019 | I26: =VLOOKUP($C26,'S | 01 '!$C$6:$R$48,I$5,0) -> B-1,2 Prefs | J26: =VLOOKUP($C26,'S | 01 '!$C$6:$R$48,J$5,0) -> 0.085025485 | K26: =VLOOKUP($C26,'S | 01 '!$C$6:$R$48,K$5,0) -> 10 | L26: =VLOOKUP($C26,'S | 01 '!$C$6:$R$48,L$5,0) -> 10 | ... O26: =VLOOKUP($C26,'S | 01 '!$C$6:$R$48,O$5,0) -> 68.08223 | P26: 68.1 | Q26: =VLOOKUP($C26,'S | 01 '!$C$6:$R$48,Q$5,0) -> 0.59885044 | R26: =VLOOKUP($C26,'S | 01 '!$C$6:$R$48,R$5,0) -> 7.808223 | S26: =VLOOKUP($C26,'S | 01 '!$C$6:$R$48,S$5,0) -> 0 | T26: Flyr Warrantsa
C27: Mena Mobile Inc | D27: Direct Investment | E27: =VLOOKUP($C27,'S | 01 '!$C$6:$R$48,E$5,0) -> Written-off | F27: =VLOOKUP($C27,'S | 01 '!$C$6:$R$48,F$5,0) -> Elaine | G27: =VLOOKUP($C27,'S | 01 '!$C$6:$R$48,G$5,0) -> Mozn | H27: =VLOOKUP($C27,'S | 01 '!$C$6:$R$48,H$5,0) -> 2019 | I27: =VLOOKUP($C27,'S | 01 '!$C$6:$R$48,I$5,0) -> B Prefs | J27: =VLOOKUP($C27,'S | 01 '!$C$6:$R$48,J$5,0) -> 0.14 | K27: =VLOOKUP($C27,'S | 01 '!$C$6:$R$48,K$5,0) -> 8 | L27: =VLOOKUP($C27,'S | 01 '!$C$6:$R$48,L$5,0) -> 8 | ... O27: =VLOOKUP($C27,'S | 01 '!$C$6:$R$48,O$5,0) -> -8 | P27: -8 | Q27: =VLOOKUP($C27,'S | 01 '!$C$6:$R$48,Q$5,0) -> NM | R27: =VLOOKUP($C27,'S | 01 '!$C$6:$R$48,R$5,0) -> 0 | S27: =VLOOKUP($C27,'S | 01 '!$C$6:$R$48,S$5,0) -> 0
C28: Glass Earth Holdings LLC | D28: Debt Investment | E28: =VLOOKUP($C28,'S | 01 '!$C$6:$R$48,E$5,0) -> Written-off | F28: =VLOOKUP($C28,'S | 01 '!$C$6:$R$48,F$5,0) -> Marty | G28: =VLOOKUP($C28,'S | 01 '!$C$6:$R$48,G$5,0) -> Mozn | H28: =VLOOKUP($C28,'S | 01 '!$C$6:$R$48,H$5,0) -> 2019 | I28: =VLOOKUP($C28,'S | 01 '!$C$6:$R$48,I$5,0) -> Promissory Note | J28: =VLOOKUP($C28,'S | 01 '!$C$6:$R$48,J$5,0) -> n/a | K28: =VLOOKUP($C28,'S | 01 '!$C$6:$R$48,K$5,0) -> 8 | L28: =VLOOKUP($C28,'S | 01 '!$C$6:$R$48,L$5,0) -> 8 | ... O28: =VLOOKUP($C28,'S | 01 '!$C$6:$R$48,O$5,0) -> -8 | P28: -8 | Q28: =VLOOKUP($C28,'S | 01 '!$C$6:$R$48,Q$5,0) -> NM | R28: =VLOOKUP($C28,'S | 01 '!$C$6:$R$48,R$5,0) -> 0 | S28: =VLOOKUP($C28,'S | 01 '!$C$6:$R$48,S$5,0) -> 0 | T28: =VLOOKUP($C28,'S | 01 '!$C$6:$R$48,T$5,0) -> In Default
C29: Jollychic Holding Limited | D29: Direct Investment | E29: =VLOOKUP($C29,'S | 01 '!$C$6:$R$48,E$5,0) -> Written-off | F29: =VLOOKUP($C29,'S | 01 '!$C$6:$R$48,F$5,0) -> Elaine | G29: =VLOOKUP($C29,'S | 01 '!$C$6:$R$48,G$5,0) -> Mozn | H29: =VLOOKUP($C29,'S | 01 '!$C$6:$R$48,H$5,0) -> 2019 | I29: =VLOOKUP($C29,'S | 01 '!$C$6:$R$48,I$5,0) -> C+ Prefs | J29: =VLOOKUP($C29,'S | 01 '!$C$6:$R$48,J$5,0) -> 0.056999998 | K29: =VLOOKUP($C29,'S | 01 '!$C$6:$R$48,K$5,0) -> 65 | L29: =VLOOKUP($C29,'S | 01 '!$C$6:$R$48,L$5,0) -> 65 | ... O29: =VLOOKUP($C29,'S | 01 '!$C$6:$R$48,O$5,0) -> -65 | P29: -65 | Q29: =VLOOKUP($C29,'S | 01 '!$C$6:$R$48,Q$5,0) -> NM | R29: =VLOOKUP($C29,'S | 01 '!$C$6:$R$48,R$5,0) -> 0 | S29: =VLOOKUP($C29,'S | 01 '!$C$6:$R$48,S$5,0) -> 0 | T29: =VLOOKUP($C29,'S | 01 '!$C$6:$R$48,T$5,0) -> In Liquidation
K31: =SUM(K9:K29) -> 1008.0207 | L31: =SUM(L9:L29) -> 1004.5175 | M31: =SUM(M9:M29) -> 440.91298 | N31: =SUM(N9:N29) -> 526.41089 | O31: =N31+M31-L31 -> -37.193673 | P31: =SUM(P9:P29) -> 14.537198 | Q31: ='4. Mozn-IRR'!L16 -> -0.014740654 | R31: =(M31+N31)/L31 -> 0.9629736 | S31: =SUM(S10:S29) -> 3.5
C33: Honor Device Co Ltd | D33: Direct Investment | E33: =VLOOKUP($C33,'S | 01 '!$C$6:$R$48,E$5,0) -> Realized | F33: =VLOOKUP($C33,'S | 01 '!$C$6:$R$48,F$5,0) -> Elaine | G33: =VLOOKUP($C33,'S | 01 '!$C$6:$R$48,G$5,0) -> G42 3 | H33: =VLOOKUP($C33,'S | 01 '!$C$6:$R$48,H$5,0) -> 2022 | I33: =VLOOKUP($C33,'S | 01 '!$C$6:$R$48,I$5,0) -> Equity-TBC | J33: =VLOOKUP($C33,'S | 01 '!$C$6:$R$48,J$5,0) -> 0.018823528 | K33: =VLOOKUP($C33,'S | 01 '!$C$6:$R$48,K$5,0) -> 800 | L33: =VLOOKUP($C33,'S | 01 '!$C$6:$R$48,L$5,0) -> 800 | ... O33: =VLOOKUP($C33,'S | 01 '!$C$6:$R$48,O$5,0) -> 2.8 | P33: 54.67 | Q33: =VLOOKUP($C33,'S | 01 '!$C$6:$R$48,Q$5,0) -> 0.0029359251 | R33: =VLOOKUP($C33,'S | 01 '!$C$6:$R$48,R$5,0) -> 1.0035 | S33: =VLOOKUP($C33,'S | 01 '!$C$6:$R$48,S$5,0) -> 0 | W33: G42
C34: DriveNets | D34: Direct Investment | E34: =VLOOKUP($C34,'S | 01 '!$C$6:$R$48,E$5,0) -> Unrealized | F34: =VLOOKUP($C34,'S | 01 '!$C$6:$R$48,F$5,0) -> Anton | G34: =VLOOKUP($C34,'S | 01 '!$C$6:$R$48,G$5,0) -> G42 | H34: =VLOOKUP($C34,'S | 01 '!$C$6:$R$48,H$5,0) -> 2022 | I34: =VLOOKUP($C34,'S | 01 '!$C$6:$R$48,I$5,0) -> Equity-TBC | J34: =VLOOKUP($C34,'S | 01 '!$C$6:$R$48,J$5,0) -> 0.11141914 | K34: =VLOOKUP($C34,'S | 01 '!$C$6:$R$48,K$5,0) -> 300 | L34: =VLOOKUP($C34,'S | 01 '!$C$6:$R$48,L$5,0) -> 300 | ... O34: =VLOOKUP($C34,'S | 01 '!$C$6:$R$48,O$5,0) -> 0 | P34: 0 | Q34: =VLOOKUP($C34,'S | 01 '!$C$6:$R$48,Q$5,0) -> 2.9802322e-09 | R34: =VLOOKUP($C34,'S | 01 '!$C$6:$R$48,R$5,0) -> 1 | S34: =VLOOKUP($C34,'S | 01 '!$C$6:$R$48,S$5,0) -> 0 | T34: DN Warrants b
C35: vTv Therapeutics Inc. | D35: Direct Investment | E35: =VLOOKUP($C35,'S | 01 '!$C$6:$R$48,E$5,0) -> Unrealized | F35: =VLOOKUP($C35,'S | 01 '!$C$6:$R$48,F$5,0) -> Divyesh | G35: =VLOOKUP($C35,'S | 01 '!$C$6:$R$48,G$5,0) -> G42 | H35: =VLOOKUP($C35,'S | 01 '!$C$6:$R$48,H$5,0) -> 2022 | I35: =VLOOKUP($C35,'S | 01 '!$C$6:$R$48,I$5,0) -> Ordinary Shares | J35: =VLOOKUP($C35,'S | 01 '!$C$6:$R$48,J$5,0) -> 0.0022129091 | K35: =VLOOKUP($C35,'S | 01 '!$C$6:$R$48,K$5,0) -> 24.53125 | L35: =VLOOKUP($C35,'S | 01 '!$C$6:$R$48,L$5,0) -> 24.53125 | ... O35: =VLOOKUP($C35,'S | 01 '!$C$6:$R$48,O$5,0) -> -22.347535 | P35: -1.348 | Q35: =VLOOKUP($C35,'S | 01 '!$C$6:$R$48,Q$5,0) -> -0.87320089 | R35: =VLOOKUP($C35,'S | 01 '!$C$6:$R$48,R$5,0) -> 0.089017697 | S35: =VLOOKUP($C35,'S | 01 '!$C$6:$R$48,S$5,0) -> 0 | T35: vTv $30m milestn payment c | W35: Invested | X35: =L42 -> 1263.4152
C36: North Summit Capital Fund | D36: Fund Investment | E36: =VLOOKUP($C36,'S | 01 '!$C$6:$R$48,E$5,0) -> Unrealized | F36: =VLOOKUP($C36,'S | 01 '!$C$6:$R$48,F$5,0) -> Elaine | G36: =VLOOKUP($C36,'S | 01 '!$C$6:$R$48,G$5,0) -> G42 | H36: =VLOOKUP($C36,'S | 01 '!$C$6:$R$48,H$5,0) -> 2020 | I36: =VLOOKUP($C36,'S | 01 '!$C$6:$R$48,I$5,0) -> LP | J36: =VLOOKUP($C36,'S | 01 '!$C$6:$R$48,J$5,0) -> n/a | K36: =VLOOKUP($C36,'S | 01 '!$C$6:$R$48,K$5,0) -> 83.334353 | L36: =VLOOKUP($C36,'S | 01 '!$C$6:$R$48,L$5,0) -> 83.214653 | ... O36: =VLOOKUP($C36,'S | 01 '!$C$6:$R$48,O$5,0) -> -0.672921 | P36: -0.306 | Q36: =VLOOKUP($C36,'S | 01 '!$C$6:$R$48,Q$5,0) -> -0.0025177218 | R36: =VLOOKUP($C36,'S | 01 '!$C$6:$R$48,R$5,0) -> 0.99191343 | S36: =VLOOKUP($C36,'S | 01 '!$C$6:$R$48,S$5,0) -> 0.1197 | W36: NAV | X36: =N42 -> 428.73667
C37: New Space Capital Fund I | D37: Fund Investment | E37: =VLOOKUP($C37,'S | 01 '!$C$6:$R$48,E$5,0) -> Unrealized | F37: =VLOOKUP($C37,'S | 01 '!$C$6:$R$48,F$5,0) -> Sushil | G37: =VLOOKUP($C37,'S | 01 '!$C$6:$R$48,G$5,0) -> G42 | H37: =VLOOKUP($C37,'S | 01 '!$C$6:$R$48,H$5,0) -> 2020 | I37: =VLOOKUP($C37,'S | 01 '!$C$6:$R$48,I$5,0) -> LP | J37: =VLOOKUP($C37,'S | 01 '!$C$6:$R$48,J$5,0) -> n/a | K37: =VLOOKUP($C37,'S | 01 '!$C$6:$R$48,K$5,0) -> 31.022787 | L37: =VLOOKUP($C37,'S | 01 '!$C$6:$R$48,L$5,0) -> 13.988553 | ... O37: =VLOOKUP($C37,'S | 01 '!$C$6:$R$48,O$5,0) -> 2.2451661 | P37: 5.445 | Q37: =VLOOKUP($C37,'S | 01 '!$C$6:$R$48,Q$5,0) -> 0.036116043 | R37: =VLOOKUP($C37,'S | 01 '!$C$6:$R$48,R$5,0) -> 1.1605002 | S37: =VLOOKUP($C37,'S | 01 '!$C$6:$R$48,S$5,0) -> 17.034234 | W37: Gain | X37: =O42 -> -20.663021
C38: New Space Capital GP Com SCSp | D38: Fund Investment | E38: =VLOOKUP($C38,'S | 01 '!$C$6:$R$48,E$5,0) -> Unrealized | F38: =VLOOKUP($C38,'S | 01 '!$C$6:$R$48,F$5,0) -> Sushil | G38: =VLOOKUP($C38,'S | 01 '!$C$6:$R$48,G$5,0) -> G42 | H38: =VLOOKUP($C38,'S | 01 '!$C$6:$R$48,H$5,0) -> 2023 | I38: =VLOOKUP($C38,'S | 01 '!$C$6:$R$48,I$5,0) -> LP | J38: =VLOOKUP($C38,'S | 01 '!$C$6:$R$48,J$5,0) -> n/a | K38: =VLOOKUP($C38,'S | 01 '!$C$6:$R$48,K$5,0) -> 2.7058824 | L38: =VLOOKUP($C38,'S | 01 '!$C$6:$R$48,L$5,0) -> 2.7058824 | ... O38: =VLOOKUP($C38,'S | 01 '!$C$6:$R$48,O$5,0) -> -0.13745685 | P38: 0 | Q38: =VLOOKUP($C38,'S | 01 '!$C$6:$R$48,Q$5,0) -> 0 | R38: =VLOOKUP($C38,'S | 01 '!$C$6:$R$48,R$5,0) -> 0.94920073 | S38: =VLOOKUP($C38,'S | 01 '!$C$6:$R$48,S$5,0) -> 0 | W38: YTD Gains | X38: =O42-P42 -> -77.553021
C39: Sinovation Disrupt Fund, L.P. | D39: Fund Investment | E39: =VLOOKUP($C39,'S | 01 '!$C$6:$R$48,E$5,0) -> Realized | F39: =VLOOKUP($C39,'S | 01 '!$C$6:$R$48,F$5,0) -> Elaine | G39: =VLOOKUP($C39,'S | 01 '!$C$6:$R$48,G$5,0) -> G42 | H39: =VLOOKUP($C39,'S | 01 '!$C$6:$R$48,H$5,0) -> 2020 | I39: =VLOOKUP($C39,'S | 01 '!$C$6:$R$48,I$5,0) -> LP | J39: =VLOOKUP($C39,'S | 01 '!$C$6:$R$48,J$5,0) -> n/a | K39: =VLOOKUP($C39,'S | 01 '!$C$6:$R$48,K$5,0) -> 50 | L39: =VLOOKUP($C39,'S | 01 '!$C$6:$R$48,L$5,0) -> 24.959693 | ... O39: =VLOOKUP($C39,'S | 01 '!$C$6:$R$48,O$5,0) -> -0.84556165 | P39: -1.265 | Q39: =VLOOKUP($C39,'S | 01 '!$C$6:$R$48,Q$5,0) -> -0.014868453 | R39: =VLOOKUP($C39,'S | 01 '!$C$6:$R$48,R$5,0) -> 0.96612291 | S39: =VLOOKUP($C39,'S | 01 '!$C$6:$R$48,S$5,0) -> 25.040307 | W39: IRR | X39: =Q42 -> -0.017151204
C40: Acies Investments Fund I, L.P. | D40: Fund Investment | E40: =VLOOKUP($C40,'S | 01 '!$C$6:$R$48,E$5,0) -> Unrealized | F40: =VLOOKUP($C40,'S | 01 '!$C$6:$R$48,F$5,0) -> Divyesh | G40: =VLOOKUP($C40,'S | 01 '!$C$6:$R$48,G$5,0) -> G42 | H40: =VLOOKUP($C40,'S | 01 '!$C$6:$R$48,H$5,0) -> 2021 | I40: =VLOOKUP($C40,'S | 01 '!$C$6:$R$48,I$5,0) -> LP | J40: =VLOOKUP($C40,'S | 01 '!$C$6:$R$48,J$5,0) -> 0.33 | K40: =VLOOKUP($C40,'S | 01 '!$C$6:$R$48,K$5,0) -> 17.1125 | L40: =VLOOKUP($C40,'S | 01 '!$C$6:$R$48,L$5,0) -> 14.015137 | ... O40: =VLOOKUP($C40,'S | 01 '!$C$6:$R$48,O$5,0) -> -1.7047125 | P40: -0.306 | Q40: =VLOOKUP($C40,'S | 01 '!$C$6:$R$48,Q$5,0) -> -0.071990828 | R40: =VLOOKUP($C40,'S | 01 '!$C$6:$R$48,R$5,0) -> 0.87836634 | S40: =VLOOKUP($C40,'S | 01 '!$C$6:$R$48,S$5,0) -> 3.0973625 | T40: 9.9% GP | Anchorf
W41: =O31-P31 -> -51.730871
K42: =SUM(K33:K40) -> 1308.7068 | L42: =SUM(L33:L40) -> 1263.4152 | M42: =SUM(M33:M40) -> 814.01547 | N42: =SUM(N33:N40) -> 428.73667 | O42: =N42+M42-L42 -> -20.663021 | P42: =SUM(P33:P40) -> 56.89 | Q42: ='4. G42-IRR'!L16 -> -0.017151204 | R42: =(M42+N42)/L42 -> 0.98364511 | S42: =SUM(S33:S40) -> 45.291603 | T42: =N42+M42-L42 -> -20.663021 | W42: =K42-L42 -> 45.291603
W43: =O42-P42 -> -77.553021
K44: =K31+K42 -> 2316.7275 | L44: =L31+L42 -> 2267.9327 | M44: =M31+M42 -> 1254.9285 | N44: =N31+N42 -> 955.14756 | O44: =O31+O42 -> -57.856694 | P44: =P31+P42 -> 71.427198 | Q44: ='4.All'!N9 -> -0.012957468 | R44: =(M44+N44)/L44 -> 0.97448924 | S44: =S31+S42 -> 48.791603 | W44: =SUM(M33:N35)-SUM(L33:L35) -> -19.547535
W45: =SUM(M36:N40)-SUM(L36:L40) -> -1.1154859
W46: =K42-L42 -> 45.291603
I47: Checks: | K47: =K44='S | 01 '!J48 -> TRUE | L47: =ROUND(L44,3)=ROUND('S | 01 '!K48,3) -> TRUE | M47: =M44='S | 01 '!M48 -> TRUE | N47: =N44='S | 01 '!N48 -> TRUE | O47: =ROUND(O44,3)=ROUND('S | 01 '!O48,3) -> TRUE | S47: =S31='S | 01 '!L32 -> TRUE
C48: For Notes, refer to Summary | 01
C49: Position Exited or written off are highlighted in Yellow

Sheet S | 03
C2: As of date | D2: ='S | 01 '!D2 -> 45322
P3: n/a refers to information not available
C6: Deals | D6: Status | E6: Lead | F6: Investing Entity | G6: Investing Entity (Legal Entity Name) | H6: Nature of Investing Entity | I6: Investments Tax Implication tax note 1 | J6: Instrument | K6: Listed / Unlisted | L6: Website link | M6: Pitchbook link | N6: Jurisdiction | O6: % | P6: Upside (Warrants, Milestone payments, ) | Q6: For Comments Refer to Note
C8: Direct Investments
C9: Jollychic Holding Limited | D9: Written-off | E9: Elaine | F9: Mozn | G9: Mozn Holding RSC Ltd | H9: Potential QFZP tax note 2 | I9: If qualifies for QFZP and hold the investment >= 12m, income/loss from the investee supposed to suject to 0% Corporate tax rate for Investing Entity | J9: C+ Prefs | L9: link | M9: link | N9: Cayman Islands | O9: 0.056999998 | Q9: 1
C10: Mena Mobile Inc | D10: Unrealized | E10: Elaine | F10: Mozn | G10: Mozn Holding RSC Ltd | H10: Potential QFZP tax note 2 | I10: If qualifies for QFZP and hold the investment >= 12m, income/loss from the investee supposed to suject to 0% Corporate tax rate for Investing Entity | J10: B Prefs | L10: link | M10: link | N10: Cayman Islands | O10: 0.14 | Q10: 2
C11: Flyr Inc | D11: Unrealized | E11: Sushil | F11: Mozn | G11: Mozn Holding RSC Ltd | H11: Potential QFZP tax note 2 | I11: If qualifies for QFZP and hold the investment >= 12m, income/loss from the investee supposed to suject to 0% Corporate tax rate for Investing Entity | J11: B-1,2 Prefs | L11: link | M11: link | N11: Delaware Corporation | O11: 0.085025485 | P11: Flyr Warrantsa | Q11: 3
C12: Esyasoft Holding | D12: Realized | E12: Sushil | F12: Mozn | G12: Mozn Holding RSC Ltd | H12: Potential QFZP tax note 2 | I12: If qualifies for QFZP and hold the investment >= 12m, income/loss from the investee supposed to suject to 0% Corporate tax rate for Investing Entity | J12: Convertible Note | L12: link | M12: n/a | N12: DIFC | O12: n/a | Q12: 4
C13: Beyond Limits | D13: Unrealized | E13: Divyesh | F13: Mozn | G13: Mozn Holding RSC Ltd | H13: Potential QFZP tax note 2 | I13: If qualifies for QFZP and hold the investment >= 12m, income/loss from the investee supposed to suject to 0% Corporate tax rate for Investing Entity | J13: C Prefs | L13: link | M13: link | N13: Delaware Corporation | O13: 0.097965107 | Q13: 5
C14: ONT plc | D14: Unrealized | E14: Divyesh | F14: Mozn | G14: Mozn Holding RSC Ltd | H14: Potential QFZP tax note 2 | I14: If qualifies for QFZP and hold the investment >= 12m, income/loss from the investee supposed to suject to 0% Corporate tax rate for Investing Entity | J14: Ordinary Shares | K14: Listed | L14: link | M14: link | N14: UK | O14: 0.051651565 | Q14: 6
C15: Heygears | D15: Unrealized | E15: Elaine | F15: Mozn | G15: Mozn Holding RSC Ltd | H15: Potential QFZP tax note 2 | I15: If qualifies for QFZP and hold the investment >= 12m, income/loss from the investee supposed to suject to 0% Corporate tax rate for Investing Entity | J15: Registered Capital | L15: link | M15: link | N15: PRC | O15: 0.1438 | Q15: 7
C16: Jysan Technologies | D16: Realized | E16: Sushil | F16: Mozn aa | G16: QAZ42 Investment SPV RSC Ltd | H16: Realized | I16: Realized | J16: A (Ordinary Shares) | L16: link | M16: n/a | N16: UK | O16: 0.03 | Q16: 8
C17: Cerebras Systems Inc | D17: Unrealized | E17: Ignasi | F17: Mozn | G17: Mozn Holding RSC Ltd | H17: Potential QFZP tax note 2 | I17: If qualifies for QFZP and hold the investment >= 12m, income/loss from the investee supposed to suject to 0% Corporate tax rate for Investing Entity | J17: F Prefs | L17: link | M17: link | N17: Delaware Corporation | O17: 0.0091172068 | Q17: 9
C18: Endless Studios LLC | D18: Unrealized | E18: Sushil | F18: Mozn | G18: Mozn Holding RSC Ltd | H18: Potential QFZP tax note 2 | I18: If qualifies for QFZP and hold the investment >= 12m, income/loss from the investee supposed to suject to 0% Corporate tax rate for Investing Entity. Currently we have one contribution made in Aug 2023 need to be monitored | J18: A Pref Units | L18: link | M18: link | N18: Delaware Corporation | O18: 0.16080402 | Q18: 10
C19: Instadeep Limited | D19: Realized | E19: Ignasi | F19: Mozn | G19: Mozn Holding RSC Ltd | H19: Potential QFZP tax note 2 | I19: If qualifies for QFZP and hold the investment >= 12m, income/loss from the investee supposed to suject to 0% Corporate tax rate for Investing Entity | J19: B Prefs | L19: link | M19: link | N19: UK | O19: 0.011489406 | Q19: 11
C20: X-fusion | D20: Realized | E20: Elaine | F20: Mozn bb | G20: Enterprise Connection Holding RSC Ltd | H20: Non-QFZP | I20: pending | J20: Equity-TBC | L20: link | M20: link | N20: PRC | O20: 0.051 | Q20: 12
C21: DriveNets | D21: Unrealized | E21: Anton | F21: G42 | G21: D2 Investments RSC Ltd | H21: Non-QFZP | I21: Should qualify for Participation interest | J21: Equity-TBC | L21: link | M21: link | N21: Israeli Pvt Company | O21: 0.11141914 | P21: DN Warrants b | Q21: 13
C22: vTv Therapeutics Inc. | D22: Unrealized | E22: Divyesh | F22: G42 | G22: G42 Investments AI Holdings RSC Ltd | H22: Potential QFZP tax note 2 | I22: If qualifies for QFZP and hold the investment >= 12m, income/loss from the investee supposed to suject to 0% Corporate tax rate for Investing Entity. Currently we have one contribution made in Feb 2023 need to be monitored | J22: Ordinary Shares | K22: Listed | L22: link | M22: link | N22: Delaware Corporation | O22: 0.0022129091 | P22: vTv $30m milestn payment c | Q22: 14
C23: Honor Device Co Ltd | D23: Realized | E23: Elaine | F23: G42 cc | G23: Smart Interaction1 Holding SPV RSC LTD | H23: pending | I23: pending | J23: Equity-TBC | L23: link | M23: link | N23: PRC | O23: 0.018823528 | Q23: 15
C24: Applied AI Corporation Limited | D24: Unrealized | E24: Divyesh | F24: Mozn | G24: Mozn Holding RSC Ltd | H24: Potential QFZP tax note 2 | I24: If qualifies for QFZP and hold the investment >= 12m, income/loss from the investee supposed to suject to 0% Corporate tax rate for Investing Entity. Currently we have one contribution made in July 2023 need to be monitored | J24: Convertible Note | L24: link | M24: link | N24: ADGM | O24: n/a | Q24: 16
C25: eSpace | D25: Unrealized | E25: Anton | F25: Mozn dd | G25: Constellation Investments SPV RSC Ltd (previously Smart Interaction5 Holding SPV RSC Ltd) | H25: Non-QFZP | I25: Taxable for only hold 2.8% of SAFE note in eSpace. | J25: B Prefs | L25: link | M25: link | N25: Delaware Corporation | O25: 0.027864956 | Q25: 17
C26: Tools for Humanity Corporation | D26: Unrealized | E26: Divyesh | F26: Mozn | G26: Mozn Holding RSC Ltd | H26: Potential QFZP tax note 2 | I26: If qualifies for QFZP and hold the investment >= 12m, income/loss from the investee supposed to suject to 0% Corporate tax rate for Investing Entity. Currently we have the contribution made in May 2023 need to be monitored | J26: C Prefs | L26: link | M26: link | N26: Delaware Corporation | O26: 0.0062621983 | Q26: 24
C27: WLD Tokens | D27: Unrealized | E27: Divyesh | F27: Mozn | G27: Mozn Holding RSC Ltd | H27: Potential QFZP tax note 2 | I27: If qualifies for QFZP and hold the investment >= 12m, income/loss from the investee supposed to suject to 0% Corporate tax rate for Investing Entity. Currently we have the Tokens. Future contributions need to be monitored | J27: Tokens | L27: link | M27: Coinbase | N27: DAO | Cayman Islands | O27: 0.00625 | Q27: 25 | T27: Preferred Shares
C28: E-line Ventures LLC | D28: Unrealized | E28: Sushil | F28: Mozn | G28: Mozn Holding RSC Ltd | H28: Potential QFZP tax note 2 | I28: If qualifies for QFZP and hold the investment >= 12m, income/loss from the investee supposed to suject to 0% Corporate tax rate for Investing Entity. Currently we have the contribution made in June 2023 need to be monitored | J28: B Prefs | L28: link | M28: link | N28: New Jersey, USA | O28: ='6. %'!F28 -> 0.11483736 | Q28: 26 | T28: B Prefs
C29: School Hack (AIREV Holding Limited) | D29: Unrealized | E29: Camillo | F29: Core42 | G29: Core42 Investments 1 SPV RSC LTD | J29: Preferred Shares | L29: link | M29: NA | N29: ADGM | O29: 0.25 | Q29: 27
C32: Debt Investments
C33: Glass Earth Holdings LLC | D33: In default | F33: Mozn | G33: G42 Investments AI Holdings RSC Ltd | H33: Potential QFZP tax note 2 | I33: not equity investment, taxable | J33: Promissory Note | L33: n/a | M33: n/a | N33: n/a | Q33: 16
C34: Mena Mobile Inc (Debt) | D34: In default | E34: Elaine | F34: Mozn | G34: Mozn Holding RSC Ltd | H34: Potential QFZP tax note 2 | I34: not equity investment, taxable | J34: Loan | L34: link | M34: link | N34: =N10 -> Cayman Islands | Q34: 17
C35: Esyasoft Holding (Debt) | D35: Unrealized | E35: Sushil | F35: Mozn | G35: Mozn Holding RSC Ltd | H35: Potential QFZP tax note 2 | I35: not equity investment, taxable | J35: Loan | L35: link | M35: n/a | N35: =N12 -> DIFC | Q35: 18
C38: Funds Investments
C39: New Space Capital Fund I | D39: Unrealized | E39: Sushil | F39: G42 | G39: G42 Investments AI Holdings RSC Ltd | H39: Potential QFZP tax note 2 | I39: If qualifies for QFZP and hold the investment >= 12m, income/loss from the investee supposed to suject to 0% Corporate tax rate for Investing Entity | J39: LP | L39: link | M39: link | N39: Luxembourg | O39: 0.22044082 | Q39: 19
C40: New Space Capital GP Com SCSp | D40: Unrealized | E40: Sushil | F40: G42 | G40: G42 Investments AI Holdings RSC Ltd | H40: Potential QFZP tax note 2 | I40: If qualifies for QFZP and hold the investment >= 12m, income/loss from the investee supposed to suject to 0% Corporate tax rate for Investing Entity | J40: GP | L40: link | M40: link | N40: Luxembourg | O40: 0.02016129 | Q40: 20
C41: North Summit Capital Fund | D41: Unrealized | E41: Elaine | F41: G42 | G41: Galbot Holding RSC Ltd | H41: Non-QFZP | I41: pending | J41: LP | L41: n/a | M41: link | N41: Cayman Islands | O41: 0.995 | Q41: 21
C42: Sinovation Disrupt Fund, L.P. | D42: Unrealized | E42: Elaine | F42: G42 | G42: G42 Investments AI Holdings RSC Ltd | H42: Potential QFZP tax note 2 | I42: If qualifies for QFZP and hold the investment >= 12m, income/loss from the investee supposed to suject to 0% Corporate tax rate for Investing Entity | J42: LP | L42: link | M42: link | N42: Cayman Islands | O42: 0.1006609 | Q42: 22
C43: Acies Investments Fund I, L.P. | D43: Unrealized | E43: Divyesh | F43: G42 | G43: G42 Investments AI Holdings RSC Ltd | H43: Potential QFZP tax note 2 | I43: If qualifies for QFZP and hold the investment >= 12m, income/loss from the investee supposed to suject to 0% Corporate tax rate for Investing Entity | J43: LP | L43: link | M43: link | N43: Delaware LLC | O43: 0.33333333 | P43: 9.9% GP | Anchor e | Q43: 23
B47: Notes:
B48: 1 | C48: Jollychic | D48: During 2021, Jollychic Holding Ltd has filed for its liquidation. Therefore, investment is considered to be fully impaired in Dec 21.
B49: 2 | C49: Mena Mobile | D49: Investment is written off based on the 3rd party valuation report
B50: 3 | C50: Flyr | D50: Within five years of the Initial Closing, for every USD 1mn of Qualifying Revenue generated, Flyr will issue, at no additional charge, 194,477 B-1 Prefs in the name of G42, up to a maximum of 1,264,100 B-1 Prefs.
B51: 4 | C51: Esyasoft Holding | D51: Investment in Esyasoft is in the form of Convertible Note which will convert to 21% interest on conversion on a fully diluted basis. As per Dec 2020 FS of Esyasoft, the CN was reflected as Debt - Exit of US$ 2.5 Mn Convertible Note @ 2.0x (MoC) i.e. US$ 5 Mn in May 22 - US$ 0.4 Mn represents Working Capital Loan - fully exited in Dec 22
B52: 5 | C52: Beyond Limits | D52: Business targeting raising funds by the end of FY2022
B53: 6 | C53: ONT plc | D53: Listed
B54: 7 | C54: Heygears | D54: Mozn's holding is RMB 4,753,356.29 of the Registered Capital.
B55: 8 | C55: Jysan Technologies | D55: - 50% of the investment has been financed by profit sharing loan. - Further, in case of exit of G42’s investment, 50% of the sale proceeds shall be paid to the lender as full and final settlement of the outstanding liability - Exit for this investment is under process. Buyback agreement is pending for signature internally. (Relevant documents to be perused by the consolidation / reporting team for details and corresponding implications, if any) - Dividend receivable amounting to US$ 3.2 m will be waived upon exit of this investment
B56: 9 | C56: Cerebras Systems Inc | D56: The investment is currently undergoing a CFIUS review.
B57: 10 | C57: Endless Studios LLC
B58: 11 | C58: Instadeep Limited | D58: Fully Exited on 31st July with 1.5x returns.
B59: 12 | C59: X-fusion | D59: RMB 80 Mn of Registered Capital for RMB 5.7 Bn
B60: 13 | C60: Drivenets | D60: Share warrants excisable upon the achievement of target revenue of clients by referred G42. The milestones of each target revenue and respective conversion were stated in the Term Sheet.
B61: 14 | C61: vTv Therapeutics : | D61: Potential issuance of US$ 30 million in additional shares of Class A Common Stock to G42 Investments (or in cash, at the option of G42 Investments) if FDA approval is received for the marketing and the sale of a pharmaceutical product containing TTP399
B62: 15 | C62: Honor | D62: Invested in Q3 2022; During Dec 22, $250m was offloaded to another investor at cost
B63: 16 | C63: Glass Earth Holdings LLC | D63: Written off. Debt security of Glass Earth issued in 2019 were fully provided for.
B64: 17 | C64: Mena Mobile (Debt) | D64: In liquidation
B65: 18 | C65: Esyasoft Holding (Debt) | D65: Outstanding
B66: 19 | C66: New Space Capital Fund I | D66: G42 negotiated conversion of €2.3m GP investment into LP investment to vote in favor of new LP proposal.
B67: 20 | C67: New Space Capital SCSp | D67: Ibid
B68: 21 | C68: North Summit Capital | D68: Portfolio Exit Plan in Progress
B69: 22 | C69: Sinovation Disrupt Fund | D69: Expect valuation to rise as some of its portfolio companies are in the market to raise new funds
B70: 23 | C70: Acies Investments Fund I, LP
B71: 24 | C71: Tools for Humanity Corporation | D71: Additional token warrants (for 62.5 million Tokens) for a consideration of $5,875.00. Additional provision for c$2K (the warrant price) kept for exercising the warrant rights.
B72: 25 | C72: WLD Tokens | D72: Received 62.5M Tokens as of Jul'23
B73: 26 | C73: E-line Ventures LLC
B74: 27 | C74: School Hack (AIREV Holding Limited)
B75: 28
C79: Additional Upside Section:
C80: a) Flyr: For every $1m of revenue, 194,477 shares, capped at 1,264,1000 (B-1) shares shall be issued to Mozn
C81: b) DriveNets: Share warrants exercisable upon the achievement of target revenue of clients referred by G42, and corresponding milestones
C82: c) vTv Therapeutics: Potential issuance of $30m in additional shares, if FDA approval received for the drug TTP399
C83: d) Tools for Humanity Corporation: Additional token warrants issued for acquiring 62.5M Tokens for $5,875.00. Additional provision for c$2K (the warrant price) kept for exercising the warrant rights
C84: e) Acies Investments Fund I LP: Being the Anchor investor, entitled to 9.9% of the aggregate carried interest earned by the GP
C87: References:
C88: G42 refers to G42 Investments AI Holding RSC Ltd
C89: Mozn refers to Mozn Holding RSC Ltd
C90: PRC refers to People's Republic of China
C91: aa Invested via QAZ42 Investment SPV RSC Ltd (QAZ42)
C92: bb Invested via Enterprise Connection Holding RSC Ltd (Enterprise Connection)
... C99: 2 Group is currently working on the process to make Mozn Holding RSC Ltd and G42 Investments AI Holdings RSC Ltd be qualified to the QFZP requirements.

Sheet NAV
B2: NAV Date | C2: ='S | 01 '!D2 -> 45322
B5: Investments | C5: Investing Entity | D5: Instrument | E5: Carrying Value | F5: Current Shares/Units | H5: Comment
E6: USD, Million | F6: # | G6: USD | J6: Updated as on: | K6: =C2 -> 45322
E7: ="NAV | "& TEXT(C2,"dd")&" "&TEXT(C2,"mmm")&" "&TEXT(C2,"yyyy") -> NAV | 31 Jan 2024 | G7: ="PPS |" & TEXT(C2,"dd")&" "&TEXT(C2,"mmm")&" "&TEXT(C2,"yyyy") -> PPS |31 Jan 2024 | L7: source
B8: Direct Investments | J8: ONT Share price | K8: 1.603 | L8: link | N8: Xfusion | O8: =5810000000/K15/1000000*(1-49.82%) -> 400.12709
B9: ='S | 01 '!C10 -> Jollychic Holding Limited | C9: ='S | 01 '!F10 -> Mozn | D9: ='S | 01 '!H10 -> C+ Prefs | E9: =F9*G9*10^-6 -> 0 | F9: =SUM('CF (Equity, Debt)'!J4:J6) -> 13458655 | H9: In liquidation | J9: VTVT Share price | K9: 8.41 | L9: link | N9: Honor | O9: =MAX(800,310000000000/K15/1000000*4.705882%*0.8/2) -> 800.85498
B10: ='S | 01 '!C11 -> Mena Mobile Inc | C10: ='S | 01 '!F11 -> Mozn | D10: ='S | 01 '!H11 -> B Prefs | E10: 0 | F10: ='CF (Equity, Debt)'!J7 -> 21419829 | H10: As per 3rd Party | Ardent Estimates | Equity written off | J10: GBP USD | K10: 1.26853 | L10: xe.com
B11: ='S | 01 '!C12 -> Flyr Inc | C11: ='S | 01 '!F12 -> Mozn | D11: ='S | 01 '!H12 -> B-1,2 Prefs | E11: =F11*G11*10^-6*(1-20%) -> 78.08223 | F11: 5205482 | G11: 18.75 | H11: At Series C PPS $18.75/share with 20% discount | J11: EUR USD | K11: 1.08667 | L11: xe.com
B12: ='S | 01 '!C13 -> Esyasoft Holding | C12: ='S | 01 '!F13 -> Mozn | D12: ='S | 01 '!H13 -> Convertible Note | E12: 0 | F12: n/a | H12: Exited at $5m (10th May) | Residual value = 0
B13: ='S | 01 '!C14 -> Beyond Limits | C13: ='S | 01 '!F14 -> Mozn | D13: ='S | 01 '!H14 -> C Prefs | E13: =F13*G13*10^-6 -> 91.00154 | F13: =SUM('CF (Equity, Debt)'!J11:J14) -> 17670202 | G13: 5.15 | H13: Held at cost (as per revised management guidance)
B14: ='S | 01 '!C15 -> ONT plc | C14: ='S | 01 '!F15 -> Mozn | D14: ='S | 01 '!H15 -> Ordinary Shares | E14: =F14*G14*10^-6 -> 90.139175 | F14: 44328120 | G14: =K8*K10 -> 2.0334536 | H14: Listed & marked to market | J14: Heygears Oct 22
B15: ='S | 01 '!C16 -> Heygears | C15: ='S | 01 '!F16 -> Mozn | D15: ='S | 01 '!H16 -> Registered Capital | E15: =K23/1000000 -> 148.04984 | F15: ='CF (Equity, Debt)'!J20 -> 4753356.3 | H15: Adjusted for currency. Valued at the recent round | J15: USD RMB | K15: 7.28633 | L15: xe.com
B16: ='S | 01 '!C17 -> Jysan Technologies | C16: ='S | 01 '!F17 -> Mozn 1 | D16: ='S | 01 '!H17 -> A (Ordinary Shares) | E16: 0 | F16: ='CF (Equity, Debt)'!J21 -> 7959497 | G16: =E16*10^6/F16 -> 0 | H16: Exited at $24.5m | J16: Post Valuation closed in June 2021 (RMB) | K16: 7500000000
B17: ='S | 01 '!C18 -> Cerebras Systems Inc | C17: ='S | 01 '!F18 -> Mozn | D17: ='S | 01 '!H18 -> F Prefs | E17: =-'CF (Equity, Debt)'!E22 -> 39.999983 | F17: ='6. %'!D17 -> 1441711 | H17: Held at cost. | J17: G42 Stake | K17: 0.143832
B18: ='S | 01 '!C19 -> Endless Studios LLC | C18: ='S | 01 '!F19 -> Mozn | D18: ='S | 01 '!H19 -> A Pref Units | E18: =-'CF (Equity, Debt)'!E23-'CF (Equity, Debt)'!E41 -> 8 | F18: ='CF (Equity, Debt)'!J23+'CF (Equity, Debt)'!J41 -> 8000000 | H18: Held at cost. | J18: G42 Valuation before Discount (RMB) | K18: 1078740000
B19: ='S | 01 '!C20 -> Instadeep Limited | C19: ='S | 01 '!F20 -> Mozn | D19: ='S | 01 '!H20 -> B Prefs | E19: =-'CF (Equity, Debt)'!E24*G19 -> 0 | F19: ='CF (Equity, Debt)'!J24 -> 33267 | G19: 0 | H19: Exited at 1.56X | Residual Value = 0 | J19: Liquidity Discount | K19: 0
B20: ='S | 01 '!C21 -> X-fusion | C20: ='S | 01 '!F21 -> Mozn 2 | D20: ='S | 01 '!H21 -> Equity-TBC | E20: 0 | F20: n/a | H20: Exited at 0.82X | J20: Minority Holding Discount | K20: 0
B21: ='S | 01 '!C22 -> DriveNets | C21: ='S | 01 '!F22 -> G42 | D21: ='S | 01 '!H22 -> Equity-TBC | E21: =-SUM('CF (Equity, Debt)'!E26:E27) -> 300 | F21: ='6. %'!D21 -> 86882669 | H21: Held at cost. | J21: G42 Valuation (RMB) | K21: =K18*(1-K19)*(1-K20) -> 1078740000
B22: ='S | 01 '!C23 -> vTv Therapeutics Inc. | C22: ='S | 01 '!F23 -> G42 | D22: ='S | 01 '!H23 -> Ordinary Shares | E22: =(F22*G22)*10^-6 -> 2.1837154 | F22: ='CF (Equity, Debt)'!J29 -> 259657 | G22: =K9 -> 8.41 | H22: Listed & marked to market | J22: Exchange Rate (RMB/USD) | K22: =K15 -> 7.28633
B23: ='S | 01 '!C24 -> Honor Device Co Ltd | C23: ='S | 01 '!F24 -> G42 3 | D23: ='S | 01 '!H24 -> Equity-TBC | E23: 0 | F23: n/a | H23: Exited at 1.0X | J23: G42 Valuation (USD) | K23: =K21/K22 -> 1.4804984e+08
B24: ='S | 01 '!C25 -> Applied AI Corporation Limited | C24: ='S | 01 '!F25 -> Mozn | D24: ='S | 01 '!H25 -> Convertible Note | E24: =-'CF (Equity, Debt)'!E32-'CF (Equity, Debt)'!E38-'CF (Equity, Debt)'!E47 -> 11.5 | F24: n/a | H24: Held at cost. | J24: Investment Cost of G42 (USD) | K24: 60000000
B25: ='S | 01 '!C26 -> eSpace | C25: ='S | 01 '!F26 -> Mozn 4 | D25: ='S | 01 '!H26 -> B Prefs | E25: =F25*G25*10^-6 -> 20.888122 | F25: 417846 | G25: 49.99 | H25: Marked up. | J25: Investment Multiple | K25: 1.9039182
B26: ='S | 01 '!C27 -> Tools for Humanity Corporation | C26: ='S | 01 '!F27 -> Mozn | D26: ='S | 01 '!H27 -> C Prefs | E26: ='S | 01 '!K27 -> 14.999999 | F26: ='6. %'!D26 -> 65413 | H26: Held at cost.
B27: ='S | 01 '!C28 -> WLD Tokens | C27: ='S | 01 '!F28 -> Mozn | D27: ='S | 01 '!H28 -> Tokens | E27: =MAX('S | 01 '!K28,F27*G27*10^-6) -> 15 | F27: ='6. %'!D27 -> 62500000 | G27: =0.24 -> 0.24 | H27: Tokens valued at $0.3 per token (volatility discount, lock-up discount etc)
B28: E-line Ventures LLC | C28: Mozn | D28: B Prefs | E28: =MAX('S | 01 '!K29,F28*G28*10^-6) -> 6 | H28: Held at cost.
B29: School Hack (AIREV Holding Limited) | C29: Core42 | D29: Preferred Shares | E29: =2.5+0.25 -> 2.75 | F29: 25000 | H29: Held at cost
B33: Debt Investments
B34: Glass Earth Holdings LLC | C34: Mozn | D34: Promissory Note | E34: ='S | 01 '!N35 -> 0 | H34: In default
B35: Mena Mobile Inc (Debt) | C35: Mozn | D35: Loan | E35: 0 | H35: In liquidation
B36: Esyasoft Holding (Debt) | C36: Mozn | D36: Loan | E36: 0 | H36: Exited. Received payment of $470,784.65 ($411K+$59K)
B40: Funds Investments
B41: New Space Capital Fund I | C41: G42 | D41: LP | E41: ='5. NewSpace'!L43*10^-6*K11 -> 13.277945 | H41: Q3'23 capital account statement
B42: New Space Capital GP Com SCSp | C42: G42 | D42: GP | E42: =E41*'S | 02'!L38/'S | 02'!L37 -> 2.5684255 | H42: Q2'23 pro-rated
B43: North Summit Capital Fund | C43: G42 | D43: LP | E43: =81.513771 -'CF (Funds)'!E35 -> 74.725861 | H43: Q3'23 capital account statement
B44: Sinovation Disrupt Fund, L.P. | C44: G42 | D44: LP | E44: =21.254442-'CF (Funds)'!D19 -> 23.670303 | H44: Q2'23 capital account statement
B45: Acies Investments Fund I, L.P. | C45: G42 | D45: LP | E45: 12.310425 | H45: Q3'23 capital account statement
B48: Note: | F48: IRR
B49: • For estimating the NAV their listed share price for ONT and vTv Therapeutics is taken | F49: Mozn | G49: ='S | 02'!Q31 -> -0.014740654
F50: G42 | G50: ='S | 02'!Q42 -> -0.017151204
F51: All | G51: ='S | 02'!Q44 -> -0.012957468
E54: 12310425

Sheet CF (Equity, Debt)
B2: E Q U I T Y
B3: Accounting entity | C3: Investment | D3: Payment date | E3: Contributions (in USD, Mn) | F3: Distributions (in USD, Mn) | G3: Currency | H3: Investment / Exit Amt (investee currency) | I3: Investment / Exit Amount (USD) | J3: Consideration (shares) | K3: Comment
B4: =VLOOKUP(C4,'S | 01 '!$C$10:$F$45,4,0) -> Mozn | C4: Jollychic Holding Limited | D4: 43470 | E4: =-I4*10^-6 -> -30 | G4: USD | H4: 30000000 | I4: =H4 -> 30000000 | J4: 6100312 | N4: NOTES
B5: =VLOOKUP(C5,'S | 01 '!$C$10:$F$45,4,0) -> Mozn | C5: Jollychic Holding Limited | D5: 43724 | E5: =-I5*10^-6 -> -20 | G5: USD | H5: 20000000 | I5: =H5 -> 20000000 | J5: 4204767.4 | N5: USD AED | O5: 3.678
B6: =VLOOKUP(C6,'S | 01 '!$C$10:$F$45,4,0) -> Mozn | C6: Jollychic Holding Limited | D6: 43724 | E6: =-I6*10^-6 -> -15 | G6: USD | H6: 15000000 | I6: =H6 -> 15000000 | J6: 3153575.6
B7: =VLOOKUP(C7,'S | 01 '!$C$10:$F$45,4,0) -> Mozn | C7: Mena Mobile Inc | D7: 43563 | E7: =-I7*10^-6 -> -8 | G7: USD | H7: 8000000 | I7: =H7 -> 8000000 | J7: 21419829
B8: =VLOOKUP(C8,'S | 01 '!$C$10:$F$45,4,0) -> Mozn | C8: Flyr Inc | D8: 43570 | E8: =-I8*10^-6 -> -4.9999981 | G8: USD | H8: 4999998.1 | I8: =H8 -> 4999998.1 | J8: 2625467
B9: =VLOOKUP(C9,'S | 01 '!$C$10:$F$45,4,0) -> Mozn | C9: Flyr Inc | D9: 43915 | E9: =-I9*10^-6 -> -5.0000019 | G9: USD | H9: =10000000-H8 -> 5000001.9 | I9: =H9 -> 5000001.9 | J9: 2580015
B10: =VLOOKUP(C10,'S | 01 '!$C$10:$F$45,4,0) -> Mozn | C10: Esyasoft Holding | D10: 43870 | E10: =-I10*10^-6 -> -2.5 | G10: USD | H10: 2500000 | I10: =H10 -> 2500000 | J10: N/A
B11: =VLOOKUP(C11,'S | 01 '!$C$10:$F$45,4,0) -> Mozn | C11: Beyond Limits | D11: 43879 | E11: =-I11*10^-6 -> -20 | G11: USD | H11: 20000000 | I11: =H11 -> 20000000 | J11: 4084038
B12: =VLOOKUP(C12,'S | 01 '!$C$10:$F$45,4,0) -> Mozn | C12: Beyond Limits | D12: 43921 | E12: =-I12*10^-6 -> -30 | G12: USD | H12: 30000000 | I12: =H12 -> 30000000 | J12: 5822642
B13: =VLOOKUP(C13,'S | 01 '!$C$10:$F$45,4,0) -> Mozn | C13: Beyond Limits | D13: 43989 | E13: =-I13*10^-6 -> -30 | G13: USD | H13: 30000000 | I13: =H13 -> 30000000 | J13: 5822642
B14: =VLOOKUP(C14,'S | 01 '!$C$10:$F$45,4,0) -> Mozn | C14: Beyond Limits | D14: 44103 | E14: =-I14*10^-6 -> -10 | G14: USD | H14: 10000000 | I14: =H14 -> 10000000 | J14: 1940880
B15: =VLOOKUP(C15,'S | 01 '!$C$10:$F$45,4,0) -> Mozn | C15: ONT plc | D15: 43968 | E15: =-I15*10^-6 -> -50 | G15: USD | H15: 50000000 | I15: 50000000 | J15: 15277680
B16: =VLOOKUP(C16,'S | 01 '!$C$10:$F$45,4,0) -> Mozn | C16: ONT plc | D16: 44006 | E16: =-I16*10^-6 -> -27.268351 | G16: GBP | H16: 21029625 | I16: 27268351 | J16: 9000000
B17: =VLOOKUP(C17,'S | 01 '!$C$10:$F$45,4,0) -> Mozn | C17: ONT plc | D17: 43837 | E17: =-I17*10^-6 -> -18.109441 | G17: GBP | H17: 14386480 | I17: 18109441 | J17: 6362180
B18: =VLOOKUP(C18,'S | 01 '!$C$10:$F$45,4,0) -> Mozn | C18: ONT plc | D18: 43990 | E18: =-I18*10^-6 -> -34.851687 | G18: GBP | H18: 26085573 | I18: 34851687 | J18: 11381140
B19: =VLOOKUP(C19,'S | 01 '!$C$10:$F$45,4,0) -> Mozn | C19: ONT plc | D19: 44315 | E19: =-I19*10^-6 -> -11.24078 | G19: GBP | H19: 8074920 | I19: 11240780 | J19: 2307120
B20: =VLOOKUP(C20,'S | 01 '!$C$10:$F$45,4,0) -> Mozn | C20: Heygears | D20: 44166 | E20: =-I20*10^-6 -> -60 | G20: USD | H20: 60000000 | I20: =H20 -> 60000000 | J20: 4753356.3
B21: =VLOOKUP(C21,'S | 01 '!$C$10:$F$45,4,0) -> Mozn 1 | C21: Jysan Technologies | D21: 44363 | E21: =-I21*10^-6 -> -20 | G21: USD | H21: 20000000 | I21: =H21 -> 20000000 | J21: 7959497
B22: =VLOOKUP(C22,'S | 01 '!$C$10:$F$45,4,0) -> Mozn | C22: Cerebras Systems Inc | D22: 44488 | E22: =-I22*10^-6 -> -39.999983 | G22: USD | H22: 39999983 | I22: =H22 -> 39999983 | J22: 1441711
B23: =VLOOKUP(C23,'S | 01 '!$C$10:$F$45,4,0) -> Mozn | C23: Endless Studios LLC | D23: 44494 | E23: =-I23*10^-6 -> -3 | G23: USD | H23: 3000000 | I23: =H23 -> 3000000 | J23: 3000000
B24: =VLOOKUP(C24,'S | 01 '!$C$10:$F$45,4,0) -> Mozn | C24: Instadeep Limited | D24: 44550 | E24: =-I24*10^-6 -> -5.0237202 | G24: GBP | H24: 3679995.5 | I24: 5023720.2 | J24: 33267
B25: =VLOOKUP(C25,'S | 01 '!$C$10:$F$45,4,0) -> Mozn 2 | C25: X-fusion | D25: 44574 | E25: =-I25*10^-6 -> -493.50096 | G25: USD | H25: 8.9350096e+08 | I25: 4.9350096e+08
B26: =VLOOKUP(C26,'S | 01 '!$C$10:$F$45,4,0) -> G42 | C26: DriveNets | D26: 44643 | E26: =-I26*10^-6 -> -200 | G26: USD | H26: 200000000 | I26: =H26 -> 200000000
B27: =VLOOKUP(C27,'S | 01 '!$C$10:$F$45,4,0) -> G42 | C27: DriveNets | D27: 44680 | E27: =-I27*10^-6 -> -100 | G27: USD | H27: 100000000 | I27: =H27 -> 100000000
B28: =VLOOKUP(C28,'S | 01 '!$C$10:$F$45,4,0) -> Mozn | C28: Esyasoft Holding | D28: 44691 | F28: 5 | G28: USD
B29: =VLOOKUP(C29,'S | 01 '!$C$10:$F$45,4,0) -> G42 | C29: vTv Therapeutics Inc. | D29: 44712 | E29: =-I29*10^-6 -> -12.5 | G29: USD | H29: 12500000 | I29: =H29 -> 12500000 | J29: ='6. %'!D22 -> 259657
B30: =VLOOKUP(C30,'S | 01 '!$C$10:$F$45,4,0) -> G42 3 | C30: Honor Device Co Ltd | D30: 44769 | E30: =-I30*10^-6 -> -600 | G30: USD | H30: 600000000 | I30: =H30 -> 600000000
B31: =VLOOKUP(C31,'S | 01 '!$C$10:$F$45,4,0) -> G42 3 | C31: Honor Device Co Ltd | D31: 44849 | E31: =-I31*10^-6 -> -200 | G31: USD | H31: 200000000 | I31: =H31 -> 200000000
B32: =VLOOKUP(C32,'S | 01 '!$C$10:$F$45,4,0) -> Mozn | C32: Applied AI Corporation Limited | D32: 44861 | E32: =-I32*10^-6 -> -4.75 | G32: USD | H32: 4750000 | I32: =H32 -> 4750000
B33: =VLOOKUP(C33,'S | 01 '!$C$10:$F$45,4,0) -> Mozn 4 | C33: eSpace | D33: 44892 | E33: =-I33*10^-6 -> -15 | G33: USD | H33: 15000000 | I33: =H33 -> 15000000
B34: =VLOOKUP(C34,'S | 01 '!$C$10:$F$45,4,0) -> G42 | C34: vTv Therapeutics Inc. | D34: 44985 | E34: =-I34*10^-6 -> -12.03125 | G34: USD | H34: 12031250 | I34: =H34 -> 12031250 | J34: 10386274
B35: =VLOOKUP(C35,'S | 01 '!$C$10:$F$45,4,0) -> Mozn | C35: Tools for Humanity Corporation | D35: 45075 | E35: =-I35*10^-6 -> -14.999999 | G35: USD | H35: 14999999 | I35: =H35 -> 14999999
B36: =VLOOKUP(C36,'S | 01 '!$C$10:$F$45,4,0) -> Mozn | C36: WLD Tokens | D36: 45075 | E36: =-I36*10^-6 -> -0.005875 | G36: USD | I36: 5875
B37: =VLOOKUP(C37,'S | 01 '!$C$10:$F$45,4,0) -> Mozn | C37: WLD Tokens | D37: 45114 | E37: =-I37*10^-6 -> -0.001 | G37: USD | I37: 1000
B38: =VLOOKUP(C38,'S | 01 '!$C$10:$F$45,4,0) -> Mozn | C38: Applied AI Corporation Limited | D38: 45121 | E38: =-I38*10^-6 -> -2.75 | G38: USD | I38: 2750000
B39: =VLOOKUP(C39,'S | 01 '!$C$10:$F$45,4,0) -> Mozn | C39: Instadeep Limited | D39: 45138 | F39: =I39*10^-6 -> 7.8207761 | G39: USD | H39: 6090345.2 | I39: 7820776.1
B40: =VLOOKUP(C40,'S | 01 '!$C$10:$F$45,4,0) -> Mozn 1 | C40: Jysan Technologies | D40: 45149 | F40: 24.5 | G40: USD | I40: 24500000 | J40: 7959497
B41: =VLOOKUP(C41,'S | 01 '!$C$10:$F$45,4,0) -> Mozn | C41: Endless Studios LLC | D41: 45167 | E41: =-I41*10^-6 -> -5 | G41: USD | I41: 5000000 | J41: 5000000
B42: =VLOOKUP(C42,'S | 01 '!$C$10:$F$45,4,0) -> Mozn | C42: E-line Ventures LLC | D42: 45167 | E42: -6 | G42: USD | I42: 6000000 | J42: =I42/1.34 -> 4477611.9
B43: =VLOOKUP(C43,'S | 01 '!$C$10:$F$45,4,0) -> G42 3 | C43: Honor Device Co Ltd | D43: 45224 | F43: 2.8 | G43: USD
B44: =VLOOKUP(C44,'S | 01 '!$C$10:$F$45,4,0) -> G42 3 | C44: Honor Device Co Ltd | D44: 45224 | F44: 800 | G44: USD
B45: =VLOOKUP(C45,'S | 01 '!$C$10:$F$45,4,0) -> Mozn 2 | C45: X-fusion | D45: 45224 | F45: 403 | G45: USD
B46: =VLOOKUP(C46,'S | 01 '!$C$10:$F$45,4,0) -> Mozn | C46: Instadeep Limited | D46: 45224 | F46: 0.12141643 | G46: USD
B47: =VLOOKUP(C47,'S | 01 '!$C$10:$F$45,4,0) -> Mozn | C47: Applied AI Corporation Limited | D47: 45295 | E47: =-I47*10^-6 -> -4 | G47: USD | H47: 4000000 | I47: =H47 -> 4000000
B48: =VLOOKUP(C48,'S | 01 '!$C$10:$F$45,4,0) -> Core42 | C48: School Hack (AIREV Holding Limited) | D48: 45322 | E48: =-I48*10^-6 -> -2.75 | G48: USD | H48: 2750000 | I48: 2750000
B52: L O AN | P R O M I S S O R Y N O T E S | D E B T
B53: Mozn | C53: Glass Earth Holdings LLC | D53: 43635 | E53: -8 | G53: USD | H53: 8000000 | I53: =H53 -> 8000000
B54: Mozn | C54: Mena Mobile Inc (Debt) | D54: 44293 | E54: -2.353982 | G54: USD | H54: =-E54*10^6 -> 2353982 | I54: =H54 -> 2353982
B55: Mozn | C55: Esyasoft Holding (Debt) | D55: 44384 | E55: =-I55*10^-6 -> -0.411765 | G55: USD | H55: 2500000 | I55: 411765
B56: Mozn | C56: Esyasoft Holding (Debt) | D56: 44902 | F56: =(411765+59019.65)*10^-6 -> 0.47078465 | G56: USD | H56: =F56*10^6 -> 470784.65 | I56: 470784.65

Sheet CF (Funds)
A2: Entity | B2: Investment | C2: Payment date | D2: Contributions (USD, Mn) | E2: Distributions (USD, Mn) | F2: Currency | G2: Cashflows | H2: Description | K2: TEST
A3: G42 | B3: Sinovation Disrupt Fund, L.P. | C3: 44153 | D3: =G3 -> -10.5 | F3: USD | G3: -10.5 | H3: 1st Capital Call | K3: =SUM(D3:D53) -> -138.88392
A4: G42 | B4: Sinovation Disrupt Fund, L.P. | C4: 44238 | D4: =G4 -> 4.214027 | F4: USD | G4: 4.214027 | H4: Partial return of the 1st Capital Call | K4: ='S | 01 '!K46 -> 138.88392
A5: G42 | B5: Sinovation Disrupt Fund, L.P. | C5: 44238 | E5: =G5 -> 0.05044835 | F5: USD | G5: 0.05044835 | H5: Interest Catchup | K5: =ROUND(K4,5)=-ROUND(K3,5) -> TRUE
A6: G42 | B6: Sinovation Disrupt Fund, L.P. | C6: 44285 | D6: =G6 -> -6.433746 | F6: USD | G6: -6.433746 | H6: 2nd Capital Calll
A7: G42 | B7: Sinovation Disrupt Fund, L.P. | C7: 44269 | D7: =G7 -> 1.1352074 | F7: USD | G7: 1.1352074 | H7: Return of Capital fund
A8: G42 | B8: Sinovation Disrupt Fund, L.P. | C8: 44269 | E8: =G8 -> 0.0259 | F8: USD | G8: 0.0259 | H8: Interest Catchup
A9: G42 | B9: Sinovation Disrupt Fund, L.P. | C9: 44483 | D9: =G9 -> -7.567138 | F9: USD | G9: -7.567138 | H9: 3rd Capital Call
A10: G42 | B10: Sinovation Disrupt Fund, L.P. | C10: 44554 | D10: =G10 -> -7.385016 | F10: USD | G10: -7.385016 | H10: 4th Capital Call
A11: G42 | B11: Sinovation Disrupt Fund, L.P. | C11: 44554 | D11: =G11 -> 4.0733456 | F11: USD | G11: 4.0733456 | H11: Return of Capital fund
A12: G42 | B12: Sinovation Disrupt Fund, L.P. | C12: 44554 | E12: =G12 -> 0.139694 | F12: USD | G12: 0.139694 | H12: Interest Catchup
A13: G42 | B13: Sinovation Disrupt Fund, L.P. | C13: 44703 | D13: =G13 -> 5.673074 | F13: USD | G13: 5.673074 | H13: Return of Capital fund
A14: G42 | B14: Sinovation Disrupt Fund, L.P. | C14: 44703 | E14: =G14 -> 0.227786 | F14: USD | G14: 0.227786 | H14: Interest Catchup
A15: G42 | B15: Sinovation Disrupt Fund, L.P. | C15: 44776 | D15: =G15 -> -3.235493 | F15: USD | G15: -3.235493 | H15: 5th Capital Call
A16: G42 | B16: Sinovation Disrupt Fund, L.P. | C16: 44960 | D16: =G16 -> -2.631528 | F16: USD | G16: -2.631528 | H16: 6th Capital Call
A17: G42 | B17: Sinovation Disrupt Fund, L.P. | C17: 45085 | D17: =G17 -> 1.912557 | F17: USD | G17: 1.912557 | H17: Return of Capital fund
A18: G42 | B18: Sinovation Disrupt Fund, L.P. | C18: 45166 | D18: -1.799122 | F18: USD | G18: -1.799122 | H18: 7th Capital Call
A19: G42 | B19: Sinovation Disrupt Fund, L.P. | C19: 45218 | D19: -2.415861 | F19: USD | G19: -2.415861 | H19: 8th Capital Call
A20: G42 | B20: Sinovation Disrupt Fund, L.P.
A21: G42 | B21: North Summit Capital Fund | C21: 43665 | D21: =G21 -> -3 | F21: USD | G21: -3 | H21: 1st Capital Call
A22: G42 | B22: North Summit Capital Fund | C22: 43983 | D22: =G22 -> -4.485 | F22: USD | G22: -4.485 | H22: 2nd Capital Calll
A23: G42 | B23: North Summit Capital Fund | C23: 43879 | D23: =G23 -> -9.50975 | F23: USD | G23: -9.50975 | H23: 3rd Capital Call
A24: G42 | B24: North Summit Capital Fund | C24: 43934 | D24: =G24 -> -41.3 | F24: USD | G24: -41.3 | H24: 4th Capital Call
A25: G42 | B25: North Summit Capital Fund | C25: 44151 | D25: =G25 -> 9.95 | F25: USD | G25: 9.95 | H25: 5th Capital Call-Partial return of the 4th Capital Call
A26: G42 | B26: North Summit Capital Fund | C26: 44151 | D26: =G26 -> -10.455 | F26: USD | G26: -10.455 | H26: 5th Capital Call
A27: G42 | B27: North Summit Capital Fund | C27: 44196 | D27: =G27 -> 4.975 | F27: USD | G27: 4.975 | H27: 6th Capital Call-Partial return of the 4th Capital Call
A28: G42 | B28: North Summit Capital Fund | C28: 44196 | D28: =G28 -> -3.452293 | F28: USD | G28: -3.452293 | H28: 6th Capital Call
A29: G42 | B29: North Summit Capital Fund | C29: 44196 | E29: =G29 -> 0.582902 | F29: USD | G29: 0.582902 | H29: 6th Capital Call-Dividends from Project Topscore
A30: G42 | B30: North Summit Capital Fund | C30: 44370 | D30: =G30 -> -5.97 | F30: USD | G30: -5.97 | H30: 7th Capital Call
A31: G42 | B31: North Summit Capital Fund | C31: 44400 | D31: =G31 -> -0.75 | F31: USD | G31: -0.75 | H31: 8th Capital Call
A32: G42 | B32: North Summit Capital Fund | C32: 44400 | E32: =G32 -> 0.445059 | F32: USD | G32: 0.445059 | H32: 8th Capital Call-Dividends from Project Topscore
A33: G42 | B33: North Summit Capital Fund | C33: 44554 | D33: =G33 -> 1.78239 | F33: USD | G33: 1.78239 | H33: 9th Capital Call-Return of Capital Fund
A34: G42 | B34: North Summit Capital Fund | C34: 44676 | D34: =G34 -> -21 | F34: USD | G34: -21 | H34: 12th Capital Call
A35: G42 | B35: North Summit Capital Fund | C35: 45243 | E35: =G35 -> 6.78791 | F35: USD | G35: 6.78791 | H35: 13th Capital Call & Distribution #4
A36: G42 | B36: New Space Capital Fund I | C36: 44087 | D36: =G36*1.1 -> -20.917553 | F36: EUR | G36: -19.015957 | H36: Drawdown1
A37: G42 | B37: New Space Capital Fund I | C37: 44287 | D37: -0.21103182 | F37: EUR | G37: -0.21103182 | H37: Drawdown2
A38: G42 | B38: New Space Capital Fund I | C38: 44442 | D38: =1.18*G38 -> -0.23965473 | F38: EUR | G38: =-203097.23*10^-6 -> -0.20309723 | H38: Drawdown3
A39: G42 | B39: New Space Capital Fund I | C39: 44623 | D39: =1.11*G39 -> -0.25893585 | F39: EUR | G39: =-233275.54*10^-6 -> -0.23327554 | H39: Drawdown4
A40: G42 | B40: New Space Capital Fund I | C40: 44784 | D40: =1.03*G40 -> 0.015224657 | F40: EUR | G40: =14781.22*10^-6 -> 0.01478122 | H40: Return of Capital
A41: G42 | B41: New Space Capital Fund I | C41: 44956 | D41: =9741387*10^-6*1.08341 -> 10.553916 | F41: EUR | G41: =9741387*10^-6 -> 9.741387 | H41: Return of Capital
A42: G42 | B42: New Space Capital Fund I | C42: 44956 | E42: =2728214.02*10^-6*1.08341 -> 2.9557744 | F42: EUR | G42: 2.728214 | H42: Distribution | Actualization Interest
A43: G42 | B43: New Space Capital Fund I | C43: 45170 | D43: -0.22532724 | F43: EUR | G43: 0.2077917 | H43: Drawdown (Notice 10)
A44: G42 | B44: New Space Capital Fund I | C44: 45260 | D44: -0.28531252 | F44: EUR | G44: 0.25928073 | H44: Drawdown (Notice 11)
A45: G42 | B45: New Space Capital Fund I | C45: 45321 | D45: -2.4198785 | F45: EUR | G45: 2.2038966 | H45: Drawdown (Notice 12)
A46: G42 | B46: New Space Capital GP Com SCSp | C46: 44087 | D46: =-'S | 01 '!K42 -> -2.7058824 | F46: EUR | G46: -2.125 | H46: Drawdown1
A47: G42 | B47: Acies Investments Fund I, L.P. | C47: 44540 | D47: =G47 -> -2.8053125 | F47: USD | G47: -2.8053125 | H47: 1st Capital Call
A48: G42 | B48: Acies Investments Fund I, L.P. | C48: 44602 | D48: =G48 -> -3.4075 | F48: USD | G48: -3.4075 | H48: 2nd Capital Call
A49: G42 | B49: Acies Investments Fund I, L.P. | C49: 44683 | D49: =G49 -> -1.025775 | F49: USD | G49: -1.025775 | H49: Catch up Capital Call
A50: G42 | B50: Acies Investments Fund I, L.P. | C50: 44707 | D50: =G50 -> -3.388275 | F50: USD | G50: -3.388275 | H50: 3rd Capital Call
A51: G42 | B51: Acies Investments Fund I, L.P. | C51: 44875 | D51: =G51 -> -3.388275 | F51: USD | G51: -3.388275 | H51: 4th Capital Call

Sheet 1. IRR Equity
B2: IRR - Equity (Individual Investments)
B4: Date of NAV | C4: =D!D2 -> 45322 | J4: Investtment Level Summary | AF4: Overall Summary
B6: (in USD, Mn)
B7: Investment | C7: Payment date | D7: Contribution | E7: Distributions | F7: Remaining Value | G7: Combined | J7: Jollychic Holding Limited | K7: Mena Mobile Inc | L7: Flyr Inc | M7: Esyasoft Holding | N7: Beyond Limits | O7: ONT plc | P7: Heygears | Q7: Jysan Technologies | R7: Cerebras Systems Inc | S7: Endless Studios LLC | T7: Instadeep Limited | U7: X-fusion | V7: DriveNets | W7: vTv Therapeutics Inc. | X7: Honor Device Co Ltd | Y7: Applied AI Corporation Limited | Z7: eSpace | AA7: Tools for Humanity Corporation | AB7: WLD Tokens | AC7: E-line Ventures LLC | AD7: School Hack (AIREV Holding Limited) | AH7: Committed | AI7: Invested | AJ7: Remaining Commitment | AK7: Distributions | AL7: Residual Value | AM7: IRR | AN7: TVPI | AO7: RPI | AP7: DPI
B10: ='CF (Equity, Debt)'!C4 -> Jollychic Holding Limited | C10: ='CF (Equity, Debt)'!D4 -> 43470 | D10: ='CF (Equity, Debt)'!E4 -> -30 | G10: =SUM(D10:F10) -> -30 | H10: =IF(D10='CF (Equity, Debt)'!E4," ", "xxx") | J10: =D10 -> -30 | AM10: =81-6 -> 75
B11: ='CF (Equity, Debt)'!C5 -> Jollychic Holding Limited | C11: ='CF (Equity, Debt)'!D5 -> 43724 | D11: ='CF (Equity, Debt)'!E5 -> -20 | G11: =SUM(D11:F11) -> -20 | H11: =IF(D11='CF (Equity, Debt)'!E5," ", "xxx") | J11: =D11 -> -20
B12: ='CF (Equity, Debt)'!C6 -> Jollychic Holding Limited | C12: ='CF (Equity, Debt)'!D6 -> 43724 | D12: ='CF (Equity, Debt)'!E6 -> -15 | G12: =SUM(D12:F12) -> -15 | H12: =IF(D12='CF (Equity, Debt)'!E6," ", "xxx") | J12: =D12 -> -15 | AG12: ='S | 01 '!C10 -> Jollychic Holding Limited | AH12: ='S | 01 '!J10 -> 65 | AI12: =-SUMIF($B$7:$F$134,$AG12,$D$7:$D$134) -> 65 | AJ12: =AH12-AI12 -> 0 | AK12: =SUMIF($B$7:$F$134,$AG12,$E$7:$E$134) -> 0 | AL12: =SUMIF($B$7:$F$134,$AG12,$F$7:$F$134) -> 0 | AM12: =HLOOKUP(AG12,$J$7:$AE$90,$AM$10,0) -> NM | AN12: =(AK12+AL12)/AI12 -> 0 | AO12: =AL12/AI12 -> 0 | AP12: =AK12/AI12 -> 0
B13: ='CF (Equity, Debt)'!C7 -> Mena Mobile Inc | C13: ='CF (Equity, Debt)'!D7 -> 43563 | D13: ='CF (Equity, Debt)'!E7 -> -8 | G13: =SUM(D13:F13) -> -8 | H13: =IF(D13='CF (Equity, Debt)'!E7," ", "xxx") | K13: =D13 -> -8 | AG13: ='S | 01 '!C11 -> Mena Mobile Inc | AH13: ='S | 01 '!J11 -> 8 | AI13: =-SUMIF($B$7:$F$134,$AG13,$D$7:$D$134) -> 8 | AJ13: =AH13-AI13 -> 0 | AK13: =SUMIF($B$7:$F$134,$AG13,$E$7:$E$134) -> 0 | AL13: =SUMIF($B$7:$F$134,$AG13,$F$7:$F$134) -> 0 | AM13: =HLOOKUP(AG13,$J$7:$Z$90,$AM$10,0) -> NM | AN13: =(AK13+AL13)/AI13 -> 0 | AO13: =AL13/AI13 -> 0 | AP13: =AK13/AI13 -> 0
B14: ='CF (Equity, Debt)'!C8 -> Flyr Inc | C14: ='CF (Equity, Debt)'!D8 -> 43570 | D14: ='CF (Equity, Debt)'!E8 -> -4.9999981 | G14: =SUM(D14:F14) -> -4.9999981 | H14: =IF(D14='CF (Equity, Debt)'!E8," ", "xxx") | L14: =D14 -> -4.9999981 | AG14: ='S | 01 '!C12 -> Flyr Inc | AH14: ='S | 01 '!J12 -> 10 | AI14: =-SUMIF($B$7:$F$134,$AG14,$D$7:$D$134) -> 10 | AJ14: =AH14-AI14 -> 0 | AK14: =SUMIF($B$7:$F$134,$AG14,$E$7:$E$134) -> 0 | AL14: =SUMIF($B$7:$F$134,$AG14,$F$7:$F$134) -> 78.08223 | AM14: =HLOOKUP(AG14,$J$7:$Z$90,$AM$10,0) -> 0.59885044 | AN14: =(AK14+AL14)/AI14 -> 7.808223 | AO14: =AL14/AI14 -> 7.808223 | AP14: =AK14/AI14 -> 0
B15: ='CF (Equity, Debt)'!C9 -> Flyr Inc | C15: ='CF (Equity, Debt)'!D9 -> 43915 | D15: ='CF (Equity, Debt)'!E9 -> -5.0000019 | G15: =SUM(D15:F15) -> -5.0000019 | H15: =IF(D15='CF (Equity, Debt)'!E9," ", "xxx") | L15: =D15 -> -5.0000019 | AG15: ='S | 01 '!C13 -> Esyasoft Holding | AH15: ='S | 01 '!J13 -> 2.5 | AI15: =-SUMIF($B$7:$F$134,$AG15,$D$7:$D$134) -> 2.5 | AJ15: =AH15-AI15 -> 0 | AK15: =SUMIF($B$7:$F$134,$AG15,$E$7:$E$134) -> 5 | AL15: =SUMIF($B$7:$F$134,$AG15,$F$7:$F$134) -> 0 | AM15: =HLOOKUP(AG15,$J$7:$Z$90,$AM$10,0) -> 0.36091766 | AN15: =(AK15+AL15)/AI15 -> 2 | AO15: =AL15/AI15 -> 0 | AP15: =AK15/AI15 -> 2
B16: ='CF (Equity, Debt)'!C10 -> Esyasoft Holding | C16: ='CF (Equity, Debt)'!D10 -> 43870 | D16: ='CF (Equity, Debt)'!E10 -> -2.5 | G16: =SUM(D16:F16) -> -2.5 | H16: =IF(D16='CF (Equity, Debt)'!E10," ", "xxx") | M16: =D16 -> -2.5 | AG16: ='S | 01 '!C14 -> Beyond Limits | AH16: ='S | 01 '!J14 -> 90 | AI16: =-SUMIF($B$7:$F$134,$AG16,$D$7:$D$134) -> 90 | AJ16: =AH16-AI16 -> 0 | AK16: =SUMIF($B$7:$F$134,$AG16,$E$7:$E$134) -> 0 | AL16: =SUMIF($B$7:$F$134,$AG16,$F$7:$F$134) -> 91.00154 | AM16: =HLOOKUP(AG16,$J$7:$Z$90,$AM$10,0) -> 0.0029582828 | AN16: =(AK16+AL16)/AI16 -> 1.0111282 | AO16: =AL16/AI16 -> 1.0111282 | AP16: =AK16/AI16 -> 0
B17: ='CF (Equity, Debt)'!C11 -> Beyond Limits | C17: ='CF (Equity, Debt)'!D11 -> 43879 | D17: ='CF (Equity, Debt)'!E11 -> -20 | G17: =SUM(D17:F17) -> -20 | H17: =IF(D17='CF (Equity, Debt)'!E11," ", "xxx") | N17: =D17 -> -20 | AG17: ='S | 01 '!C15 -> ONT plc | AH17: ='S | 01 '!J15 -> 141.47026 | AI17: =-SUMIF($B$7:$F$134,$AG17,$D$7:$D$134) -> 141.47026 | AJ17: =AH17-AI17 -> 0 | AK17: =SUMIF($B$7:$F$134,$AG17,$E$7:$E$134) -> 0 | AL17: =SUMIF($B$7:$F$134,$AG17,$F$7:$F$134) -> 90.139175 | AM17: =HLOOKUP(AG17,$J$7:$Z$90,$AM$10,0) -> -0.11648149 | AN17: =(AK17+AL17)/AI17 -> 0.63715989 | AO17: =AL17/AI17 -> 0.63715989 | AP17: =AK17/AI17 -> 0
B18: ='CF (Equity, Debt)'!C12 -> Beyond Limits | C18: ='CF (Equity, Debt)'!D12 -> 43921 | D18: ='CF (Equity, Debt)'!E12 -> -30 | G18: =SUM(D18:F18) -> -30 | H18: =IF(D18='CF (Equity, Debt)'!E12," ", "xxx") | N18: =D18 -> -30 | AG18: ='S | 01 '!C16 -> Heygears | AH18: ='S | 01 '!J16 -> 60 | AI18: =-SUMIF($B$7:$F$134,$AG18,$D$7:$D$134) -> 60 | AJ18: =AH18-AI18 -> 0 | AK18: =SUMIF($B$7:$F$134,$AG18,$E$7:$E$134) -> 0 | AL18: =SUMIF($B$7:$F$134,$AG18,$F$7:$F$134) -> 148.04984 | AM18: =HLOOKUP(AG18,$J$7:$Z$90,$AM$10,0) -> 0.33000317 | AN18: =(AK18+AL18)/AI18 -> 2.4674974 | AO18: =AL18/AI18 -> 2.4674974 | AP18: =AK18/AI18 -> 0
B19: ='CF (Equity, Debt)'!C13 -> Beyond Limits | C19: ='CF (Equity, Debt)'!D13 -> 43989 | D19: ='CF (Equity, Debt)'!E13 -> -30 | G19: =SUM(D19:F19) -> -30 | H19: =IF(D19='CF (Equity, Debt)'!E13," ", "xxx") | N19: =D19 -> -30 | AG19: ='S | 01 '!C17 -> Jysan Technologies | AH19: ='S | 01 '!J17 -> 20 | AI19: =-SUMIF($B$7:$F$134,$AG19,$D$7:$D$134) -> 20 | AJ19: =AH19-AI19 -> 0 | AK19: =SUMIF($B$7:$F$134,$AG19,$E$7:$E$134) -> 24.5 | AL19: =SUMIF($B$7:$F$134,$AG19,$F$7:$F$134) -> 0 | AM19: =HLOOKUP(AG19,$J$7:$Z$90,$AM$10,0) -> 0.098824507 | AN19: =(AK19+AL19)/AI19 -> 1.225 | AO19: =AL19/AI19 -> 0 | AP19: =AK19/AI19 -> 1.225
B20: ='CF (Equity, Debt)'!C14 -> Beyond Limits | C20: ='CF (Equity, Debt)'!D14 -> 44103 | D20: ='CF (Equity, Debt)'!E14 -> -10 | G20: =SUM(D20:F20) -> -10 | H20: =IF(D20='CF (Equity, Debt)'!E14," ", "xxx") | N20: =D20 -> -10 | AG20: ='S | 01 '!C18 -> Cerebras Systems Inc | AH20: ='S | 01 '!J18 -> 40 | AI20: =-SUMIF($B$7:$F$134,$AG20,$D$7:$D$134) -> 39.999983 | AJ20: =AH20-AI20 -> 1.664e-05 | AK20: =SUMIF($B$7:$F$134,$AG20,$E$7:$E$134) -> 0 | AL20: =SUMIF($B$7:$F$134,$AG20,$F$7:$F$134) -> 39.999983 | AM20: =HLOOKUP(AG20,$J$7:$Z$90,$AM$10,0) -> 2.9802322e-09 | AN20: =(AK20+AL20)/AI20 -> 1 | AO20: =AL20/AI20 -> 1 | AP20: =AK20/AI20 -> 0
B21: ='CF (Equity, Debt)'!C15 -> ONT plc | C21: ='CF (Equity, Debt)'!D15 -> 43968 | D21: ='CF (Equity, Debt)'!E15 -> -50 | G21: =SUM(D21:F21) -> -50 | H21: =IF(D21='CF (Equity, Debt)'!E15," ", "xxx") | O21: =D21 -> -50 | AG21: ='S | 01 '!C19 -> Endless Studios LLC | AH21: ='S | 01 '!J19 -> 8 | AI21: =-SUMIF($B$7:$F$134,$AG21,$D$7:$D$134) -> 8 | AJ21: =AH21-AI21 -> 0 | AK21: =SUMIF($B$7:$F$134,$AG21,$E$7:$E$134) -> 0 | AL21: =SUMIF($B$7:$F$134,$AG21,$F$7:$F$134) -> 8 | AM21: =HLOOKUP(AG21,$J$7:$Z$90,$AM$10,0) -> 2.9802322e-09 | AN21: =(AK21+AL21)/AI21 -> 1 | AO21: =AL21/AI21 -> 1 | AP21: =AK21/AI21 -> 0
B22: ='CF (Equity, Debt)'!C16 -> ONT plc | C22: ='CF (Equity, Debt)'!D16 -> 44006 | D22: ='CF (Equity, Debt)'!E16 -> -27.268351 | G22: =SUM(D22:F22) -> -27.268351 | H22: =IF(D22='CF (Equity, Debt)'!E16," ", "xxx") | O22: =D22 -> -27.268351 | AG22: ='S | 01 '!C20 -> Instadeep Limited | AH22: ='S | 01 '!J20 -> 5.0278212 | AI22: =-SUMIF($B$7:$F$134,$AG22,$D$7:$D$134) -> 5.0237202 | AJ22: =AH22-AI22 -> 0.0041009961 | AK22: =SUMIF($B$7:$F$134,$AG22,$E$7:$E$134) -> 7.9421925 | AL22: =SUMIF($B$7:$F$134,$AG22,$F$7:$F$134) -> 0 | AM22: =HLOOKUP(AG22,$J$7:$Z$90,$AM$10,0) -> 0.32803498 | AN22: =(AK22+AL22)/AI22 -> 1.5809385 | AO22: =AL22/AI22 -> 0 | AP22: =AK22/AI22 -> 1.5809385
B23: ='CF (Equity, Debt)'!C17 -> ONT plc | C23: ='CF (Equity, Debt)'!D17 -> 43837 | D23: ='CF (Equity, Debt)'!E17 -> -18.109441 | G23: =SUM(D23:F23) -> -18.109441 | H23: =IF(D23='CF (Equity, Debt)'!E17," ", "xxx") | O23: =D23 -> -18.109441 | AG23: ='S | 01 '!C21 -> X-fusion | AH23: ='S | 01 '!J21 -> 493.5 | AI23: =-SUMIF($B$7:$F$134,$AG23,$D$7:$D$134) -> 493.50096 | AJ23: =AH23-AI23 -> -0.0009562 | AK23: =SUMIF($B$7:$F$134,$AG23,$E$7:$E$134) -> 403 | AL23: =SUMIF($B$7:$F$134,$AG23,$F$7:$F$134) -> 0 | AM23: =HLOOKUP(AG23,$J$7:$Z$90,$AM$10,0) -> -0.10752884 | AN23: =(AK23+AL23)/AI23 -> 0.81661443 | AO23: =AL23/AI23 -> 0 | AP23: =AK23/AI23 -> 0.81661443
B24: ='CF (Equity, Debt)'!C18 -> ONT plc | C24: ='CF (Equity, Debt)'!D18 -> 43990 | D24: ='CF (Equity, Debt)'!E18 -> -34.851687 | G24: =SUM(D24:F24) -> -34.851687 | H24: =IF(D24='CF (Equity, Debt)'!E18," ", "xxx") | O24: =D24 -> -34.851687 | AG24: ='S | 01 '!C22 -> DriveNets | AH24: ='S | 01 '!J22 -> 300 | AI24: =-SUMIF($B$7:$F$134,$AG24,$D$7:$D$134) -> 300 | AJ24: =AH24-AI24 -> 0 | AK24: =SUMIF($B$7:$F$134,$AG24,$E$7:$E$134) -> 0 | AL24: =SUMIF($B$7:$F$134,$AG24,$F$7:$F$134) -> 300 | AM24: =HLOOKUP(AG24,$J$7:$Z$90,$AM$10,0) -> 2.9802322e-09 | AN24: =(AK24+AL24)/AI24 -> 1 | AO24: =AL24/AI24 -> 1 | AP24: =AK24/AI24 -> 0
B25: ='CF (Equity, Debt)'!C19 -> ONT plc | C25: ='CF (Equity, Debt)'!D19 -> 44315 | D25: ='CF (Equity, Debt)'!E19 -> -11.24078 | G25: =SUM(D25:F25) -> -11.24078 | H25: =IF(D25='CF (Equity, Debt)'!E19," ", "xxx") | O25: =D25 -> -11.24078 | AG25: ='S | 01 '!C23 -> vTv Therapeutics Inc. | AH25: ='S | 01 '!J23 -> 24.53125 | AI25: =-SUMIF($B$7:$F$134,$AG25,$D$7:$D$134) -> 24.53125 | AJ25: =AH25-AI25 -> 0 | AK25: =SUMIF($B$7:$F$134,$AG25,$E$7:$E$134) -> 0 | AL25: =SUMIF($B$7:$F$134,$AG25,$F$7:$F$134) -> 2.1837154 | AM25: =HLOOKUP(AG25,$J$7:$Z$90,$AM$10,0) -> -0.87320089 | AN25: =(AK25+AL25)/AI25 -> 0.089017697 | AO25: =AL25/AI25 -> 0.089017697 | AP25: =AK25/AI25 -> 0
B26: ='CF (Equity, Debt)'!C20 -> Heygears | C26: ='CF (Equity, Debt)'!D20 -> 44166 | D26: ='CF (Equity, Debt)'!E20 -> -60 | G26: =SUM(D26:F26) -> -60 | H26: =IF(D26='CF (Equity, Debt)'!E20," ", "xxx") | P26: =D26 -> -60 | AG26: ='S | 01 '!C24 -> Honor Device Co Ltd | AH26: ='S | 01 '!J24 -> 800 | AI26: =-SUMIF($B$7:$F$134,$AG26,$D$7:$D$134) -> 800 | AJ26: =AH26-AI26 -> 0 | AK26: =SUMIF($B$7:$F$134,$AG26,$E$7:$E$134) -> 802.8 | AL26: =SUMIF($B$7:$F$134,$AG26,$F$7:$F$134) -> 0 | AM26: =HLOOKUP(AG26,$J$7:$Z$90,$AM$10,0) -> 0.0029359251 | AN26: =(AK26+AL26)/AI26 -> 1.0035 | AO26: =AL26/AI26 -> 0 | AP26: =AK26/AI26 -> 1.0035
B27: ='CF (Equity, Debt)'!C21 -> Jysan Technologies | C27: ='CF (Equity, Debt)'!D21 -> 44363 | D27: ='CF (Equity, Debt)'!E21 -> -20 | G27: =SUM(D27:F27) -> -20 | H27: =IF(D27='CF (Equity, Debt)'!E21," ", "xxx") | Q27: =D27 -> -20 | AG27: ='S | 01 '!C25 -> Applied AI Corporation Limited | AH27: ='S | 01 '!J25 -> 15 | AI27: =-SUMIF($B$7:$F$134,$AG27,$D$7:$D$134) -> 11.5 | AJ27: =AH27-AI27 -> 3.5 | AK27: =SUMIF($B$7:$F$134,$AG27,$E$7:$E$134) -> 0 | AL27: =SUMIF($B$7:$F$134,$AG27,$F$7:$F$134) -> 11.5 | AM27: =HLOOKUP(AG27,$J$7:$Z$90,$AM$10,0) -> 2.9802322e-09 | AN27: =(AK27+AL27)/AI27 -> 1 | AO27: =AL27/AI27 -> 1 | AP27: =AK27/AI27 -> 0
B28: ='CF (Equity, Debt)'!C22 -> Cerebras Systems Inc | C28: ='CF (Equity, Debt)'!D22 -> 44488 | D28: ='CF (Equity, Debt)'!E22 -> -39.999983 | G28: =SUM(D28:F28) -> -39.999983 | H28: =IF(D28='CF (Equity, Debt)'!E22," ", "xxx") | R28: =D28 -> -39.999983 | AG28: ='S | 01 '!C26 -> eSpace | AH28: ='S | 01 '!J26 -> 15 | AI28: =-SUMIF($B$7:$F$134,$AG28,$D$7:$D$134) -> 15 | AJ28: =AH28-AI28 -> 0 | AK28: =SUMIF($B$7:$F$134,$AG28,$E$7:$E$134) -> 0 | AL28: =SUMIF($B$7:$F$134,$AG28,$F$7:$F$134) -> 20.888122 | AM28: =HLOOKUP(AG28,$J$7:$Z$90,$AM$10,0) -> 0.32455407 | AN28: =(AK28+AL28)/AI28 -> 1.3925414 | AO28: =AL28/AI28 -> 1.3925414 | AP28: =AK28/AI28 -> 0
B29: ='CF (Equity, Debt)'!C23 -> Endless Studios LLC | C29: ='CF (Equity, Debt)'!D23 -> 44494 | D29: ='CF (Equity, Debt)'!E23 -> -3 | G29: =SUM(D29:F29) -> -3 | H29: =IF(D29='CF (Equity, Debt)'!E23," ", "xxx") | S29: =D29 -> -3 | AG29: ='S | 01 '!C27 -> Tools for Humanity Corporation | AH29: ='S | 01 '!J27 -> 14.999999 | AI29: =-SUMIF($B$7:$F$134,$AG29,$D$7:$D$134) -> 14.999999 | AJ29: =AH29-AI29 -> 0 | AK29: =SUMIF($B$7:$F$134,$AG29,$E$7:$E$134) -> 0 | AL29: =SUMIF($B$7:$F$134,$AG29,$F$7:$F$134) -> 14.999999 | AM29: =HLOOKUP(AG29,$J$7:$AF$90,$AM$10,0) -> 2.9802322e-09 | AN29: =(AK29+AL29)/AI29 -> 1 | AO29: =AL29/AI29 -> 1 | AP29: =AK29/AI29 -> 0
B30: ='CF (Equity, Debt)'!C24 -> Instadeep Limited | C30: ='CF (Equity, Debt)'!D24 -> 44550 | D30: ='CF (Equity, Debt)'!E24 -> -5.0237202 | G30: =SUM(D30:F30) -> -5.0237202 | H30: =IF(D30='CF (Equity, Debt)'!E24," ", "xxx") | T30: =D30 -> -5.0237202 | AG30: ='S | 01 '!C28 -> WLD Tokens | AH30: ='S | 01 '!J28 -> 0.006875 | AI30: =-SUMIF($B$7:$F$134,$AG30,$D$7:$D$134) -> 0.006875 | AJ30: =AH30-AI30 -> 0 | AK30: =SUMIF($B$7:$F$134,$AG30,$E$7:$E$134) -> 0 | AL30: =SUMIF($B$7:$F$134,$AG30,$F$7:$F$134) -> 15 | AM30: =HLOOKUP(AG30,$J$7:$AF$90,$AM$10,0) -> NM | AN30: =(AK30+AL30)/AI30 -> 2181.8182 | AO30: =AL30/AI30 -> 2181.8182 | AP30: =AK30/AI30 -> 0
B31: ='CF (Equity, Debt)'!C25 -> X-fusion | C31: ='CF (Equity, Debt)'!D25 -> 44574 | D31: ='CF (Equity, Debt)'!E25 -> -493.50096 | G31: =SUM(D31:F31) -> -493.50096 | H31: =IF(D31='CF (Equity, Debt)'!E25," ", "xxx") | U31: =D31 -> -493.50096 | AG31: ='S | 01 '!C29 -> E-line Ventures LLC | AH31: ='S | 01 '!J29 -> 6 | AI31: =-SUMIF($B$7:$F$134,$AG31,$D$7:$D$134) -> 6 | AJ31: =AH31-AI31 -> 0 | AK31: =SUMIF($B$7:$F$134,$AG31,$E$7:$E$134) -> 0 | AL31: =SUMIF($B$7:$F$134,$AG31,$F$7:$F$134) -> 6 | AM31: =HLOOKUP(AG31,$J$7:$AF$90,$AM$10,0) -> NM | AN31: =(AK31+AL31)/AI31 -> 1 | AO31: =AL31/AI31 -> 1 | AP31: =AK31/AI31 -> 0
B32: ='CF (Equity, Debt)'!C26 -> DriveNets | C32: ='CF (Equity, Debt)'!D26 -> 44643 | D32: ='CF (Equity, Debt)'!E26 -> -200 | G32: =SUM(D32:F32) -> -200 | H32: =IF(D32='CF (Equity, Debt)'!E26," ", "xxx") | V32: =D32 -> -200 | AG32: ='S | 01 '!C30 -> School Hack (AIREV Holding Limited) | AH32: ='S | 01 '!J30 -> 2.75 | AI32: =-SUMIF($B$7:$F$134,$AG32,$D$7:$D$134) -> 2.75 | AJ32: =AH32-AI32 -> 0 | AK32: =SUMIF($B$7:$F$134,$AG32,$E$7:$E$134) -> 0 | AL32: =SUMIF($B$7:$F$134,$AG32,$F$7:$F$134) -> 2.75 | AM32: =HLOOKUP(AG32,$J$7:$AF$90,$AM$10,0) -> NM | AN32: =(AK32+AL32)/AI32 -> 1 | AO32: =AL32/AI32 -> 1 | AP32: =AK32/AI32 -> 0
B33: ='CF (Equity, Debt)'!C27 -> DriveNets | C33: ='CF (Equity, Debt)'!D27 -> 44680 | D33: ='CF (Equity, Debt)'!E27 -> -100 | G33: =SUM(D33:F33) -> -100 | H33: =IF(D33='CF (Equity, Debt)'!E27," ", "xxx") | V33: =D33 -> -100
B34: ='CF (Equity, Debt)'!C28 -> Esyasoft Holding | C34: ='CF (Equity, Debt)'!D28 -> 44691 | D34: ='CF (Equity, Debt)'!E28 -> 0 | E34: ='CF (Equity, Debt)'!F28 -> 5 | G34: =SUM(D34:F34) -> 5 | H34: =IF(D34='CF (Equity, Debt)'!E28," ", "xxx") | M34: =E34 -> 5
B35: ='CF (Equity, Debt)'!C29 -> vTv Therapeutics Inc. | C35: ='CF (Equity, Debt)'!D29 -> 44712 | D35: ='CF (Equity, Debt)'!E29 -> -12.5 | G35: =SUM(D35:F35) -> -12.5 | H35: =IF(D35='CF (Equity, Debt)'!E29," ", "xxx") | W35: =D35 -> -12.5 | AH35: =SUM(AH12:AH32) -> 2121.7862 | AI35: =SUM(AI12:AI32) -> 2118.283 | AJ35: =SUM(AJ12:AJ32) -> 3.5031614 | AK35: =SUM(AK12:AK32) -> 1243.2422 | AL35: =SUM(AL12:AL32) -> 828.59461 | AM35: =AH40 -> -0.011569161 | AN35: =(AK35+AL35)/AI35 -> 0.97807364 | AO35: =AL35/AI35 -> 0.39116331 | AP35: =AK35/AI35 -> 0.58691033
B36: ='CF (Equity, Debt)'!C30 -> Honor Device Co Ltd | C36: ='CF (Equity, Debt)'!D30 -> 44769 | D36: ='CF (Equity, Debt)'!E30 -> -600 | G36: =SUM(D36:F36) -> -600 | H36: =IF(D36='CF (Equity, Debt)'!E30," ", "xxx") | X36: =D36 -> -600 | AH36: =ROUND('S | 01 '!J32,2)=ROUND(AH35,2) -> TRUE | AI36: =ROUND('S | 01 '!K32,2)=ROUND(AI35,2) -> TRUE | AJ36: =ROUND('S | 01 '!L32,2)=ROUND(AJ35,2) -> TRUE | AK36: =ROUND('S | 01 '!M32,2)=ROUND(AK35,2) -> TRUE | AL36: =ROUND('S | 01 '!N32,2)=ROUND(AL35,2) -> TRUE | AM36: =ROUND('S | 01 '!Q32,2)=ROUND(AM35,2) -> TRUE | AN36: =ROUND('S | 01 '!P32,2)=ROUND(AN35,2) -> TRUE
B37: ='CF (Equity, Debt)'!C31 -> Honor Device Co Ltd | C37: ='CF (Equity, Debt)'!D31 -> 44849 | D37: ='CF (Equity, Debt)'!E31 -> -200 | G37: =SUM(D37:F37) -> -200 | X37: =D37 -> -200
B38: ='CF (Equity, Debt)'!C32 -> Applied AI Corporation Limited | C38: ='CF (Equity, Debt)'!D32 -> 44861 | D38: ='CF (Equity, Debt)'!E32 -> -4.75 | G38: =SUM(D38:F38) -> -4.75 | Y38: =D38 -> -4.75
B39: ='CF (Equity, Debt)'!C33 -> eSpace | C39: ='CF (Equity, Debt)'!D33 -> 44892 | D39: ='CF (Equity, Debt)'!E33 -> -15 | G39: =SUM(D39:F39) -> -15 | Z39: =G39 -> -15
B40: ='CF (Equity, Debt)'!C34 -> vTv Therapeutics Inc. | C40: ='CF (Equity, Debt)'!D34 -> 44985 | D40: ='CF (Equity, Debt)'!E34 -> -12.03125 | G40: =SUM(D40:F40) -> -12.03125 | W40: =G40 -> -12.03125 | AG40: XIRR | AH40: =XIRR(G10:G98,C10:C98) -> -0.011569161
B41: ='CF (Equity, Debt)'!C35 -> Tools for Humanity Corporation | C41: ='CF (Equity, Debt)'!D35 -> 45075 | D41: ='CF (Equity, Debt)'!E35 -> -14.999999 | G41: =SUM(D41:F41) -> -14.999999 | AA41: =G41 -> -14.999999 | AG41: TVPI | AH41: =SUM(AK12:AL32)/SUM(AI12:AI32) -> 0.97807364 | AI41: =ROUND(AH41,5)=ROUND(AN35,5) -> TRUE
B42: ='CF (Equity, Debt)'!C36 -> WLD Tokens | C42: ='CF (Equity, Debt)'!D36 -> 45075 | D42: ='CF (Equity, Debt)'!E36 -> -0.005875 | G42: =SUM(D42:F42) -> -0.005875 | AB42: =G42 -> -0.005875 | AG42: RPI | AH42: =SUM(AL12:AL32)/SUM(AI12:AI32) -> 0.39116331 | AI42: =ROUND(AH42,5)=ROUND(AO35,5) -> TRUE
B43: ='CF (Equity, Debt)'!C37 -> WLD Tokens | C43: ='CF (Equity, Debt)'!D37 -> 45114 | D43: ='CF (Equity, Debt)'!E37 -> -0.001 | G43: =SUM(D43:F43) -> -0.001 | AB43: =G43 -> -0.001 | AG43: DPI | AH43: =SUM(AK12:AK32)/SUM(AI12:AI32) -> 0.58691033 | AI43: =ROUND(AH43,5)=ROUND(AP35,5) -> TRUE
B44: ='CF (Equity, Debt)'!C38 -> Applied AI Corporation Limited | C44: ='CF (Equity, Debt)'!D38 -> 45121 | D44: ='CF (Equity, Debt)'!E38 -> -2.75 | G44: =SUM(D44:F44) -> -2.75 | Y44: =G44 -> -2.75
B45: ='CF (Equity, Debt)'!C39 -> Instadeep Limited | C45: ='CF (Equity, Debt)'!D39 -> 45138 | D45: ='CF (Equity, Debt)'!E39 -> 0 | E45: ='CF (Equity, Debt)'!F39 -> 7.8207761 | G45: =SUM(D45:F45) -> 7.8207761 | T45: =G45 -> 7.8207761
B46: ='CF (Equity, Debt)'!C40 -> Jysan Technologies | C46: ='CF (Equity, Debt)'!D40 -> 45149 | D46: ='CF (Equity, Debt)'!E40 -> 0 | E46: ='CF (Equity, Debt)'!F40 -> 24.5 | G46: =SUM(D46:F46) -> 24.5 | Q46: =E46 -> 24.5
B47: ='CF (Equity, Debt)'!C41 -> Endless Studios LLC | C47: ='CF (Equity, Debt)'!D41 -> 45167 | D47: ='CF (Equity, Debt)'!E41 -> -5 | E47: ='CF (Equity, Debt)'!F41 -> 0 | G47: =SUM(D47:F47) -> -5 | S47: =D47 -> -5
B48: ='CF (Equity, Debt)'!C42 -> E-line Ventures LLC | C48: ='CF (Equity, Debt)'!D42 -> 45167 | D48: ='CF (Equity, Debt)'!E42 -> -6 | E48: ='CF (Equity, Debt)'!F42 -> 0 | G48: =SUM(D48:F48) -> -6 | AC48: =D48 -> -6
B49: ='CF (Equity, Debt)'!C43 -> Honor Device Co Ltd | C49: ='CF (Equity, Debt)'!D43 -> 45224 | D49: ='CF (Equity, Debt)'!E43 -> 0 | E49: ='CF (Equity, Debt)'!F43 -> 2.8 | G49: =SUM(D49:F49) -> 2.8 | X49: =G49 -> 2.8
B50: ='CF (Equity, Debt)'!C44 -> Honor Device Co Ltd | C50: ='CF (Equity, Debt)'!D44 -> 45224 | D50: ='CF (Equity, Debt)'!E44 -> 0 | E50: ='CF (Equity, Debt)'!F44 -> 800 | G50: =SUM(D50:F50) -> 800 | X50: =G50 -> 800
B51: ='CF (Equity, Debt)'!C45 -> X-fusion | C51: ='CF (Equity, Debt)'!D45 -> 45224 | D51: ='CF (Equity, Debt)'!E45 -> 0 | E51: ='CF (Equity, Debt)'!F45 -> 403 | G51: =SUM(D51:F51) -> 403 | U51: =G51 -> 403
B52: ='CF (Equity, Debt)'!C46 -> Instadeep Limited | C52: ='CF (Equity, Debt)'!D46 -> 45224 | D52: ='CF (Equity, Debt)'!E46 -> 0 | E52: ='CF (Equity, Debt)'!F46 -> 0.12141643 | G52: =SUM(D52:F52) -> 0.12141643 | T52: =G52 -> 0.12141643
B53: ='CF (Equity, Debt)'!C47 -> Applied AI Corporation Limited | C53: ='CF (Equity, Debt)'!D47 -> 45295 | D53: ='CF (Equity, Debt)'!E47 -> -4 | E53: ='CF (Equity, Debt)'!F47 -> 0 | G53: =SUM(D53:F53) -> -4 | Y53: =G53 -> -4
B54: ='CF (Equity, Debt)'!C48 -> School Hack (AIREV Holding Limited) | C54: ='CF (Equity, Debt)'!D48 -> 45322 | D54: ='CF (Equity, Debt)'!E48 -> -2.75 | E54: ='CF (Equity, Debt)'!F48 -> 0 | G54: =SUM(D54:F54) -> -2.75 | AD54: =G54 -> -2.75
B57: =NAV!B9 -> Jollychic Holding Limited | C57: =$C$4 -> 45322 | F57: =NAV!E9 -> 0 | G57: =SUM(D57:F57) -> 0 | J57: =F57 -> 0
B58: =NAV!B10 -> Mena Mobile Inc | C58: =$C$4 -> 45322 | F58: =NAV!E10 -> 0 | G58: =SUM(D58:F58) -> 0 | K58: =F58 -> 0
B59: =NAV!B11 -> Flyr Inc | C59: =$C$4 -> 45322 | F59: =NAV!E11 -> 78.08223 | G59: =SUM(D59:F59) -> 78.08223 | L59: =F59 -> 78.08223
B60: =NAV!B12 -> Esyasoft Holding | C60: =$C$4 -> 45322 | F60: =NAV!E12 -> 0 | G60: =SUM(D60:F60) -> 0
B61: =NAV!B13 -> Beyond Limits | C61: =$C$4 -> 45322 | F61: =NAV!E13 -> 91.00154 | G61: =SUM(D61:F61) -> 91.00154 | N61: =F61 -> 91.00154
B62: =NAV!B14 -> ONT plc | C62: =$C$4 -> 45322 | F62: =NAV!E14 -> 90.139175 | G62: =SUM(D62:F62) -> 90.139175 | O62: =F62 -> 90.139175
B63: =NAV!B15 -> Heygears | C63: =$C$4 -> 45322 | F63: =NAV!E15 -> 148.04984 | G63: =SUM(D63:F63) -> 148.04984 | P63: =F63 -> 148.04984
B64: =NAV!B16 -> Jysan Technologies | C64: =$C$4 -> 45322 | F64: =NAV!E16 -> 0 | G64: =SUM(D64:F64) -> 0 | Q64: =F64 -> 0
B65: =NAV!B17 -> Cerebras Systems Inc | C65: =$C$4 -> 45322 | F65: =NAV!E17 -> 39.999983 | G65: =SUM(D65:F65) -> 39.999983 | R65: =F65 -> 39.999983
B66: =NAV!B18 -> Endless Studios LLC | C66: =$C$4 -> 45322 | F66: =NAV!E18 -> 8 | G66: =SUM(D66:F66) -> 8 | S66: =F66 -> 8
B67: =NAV!B19 -> Instadeep Limited | C67: =$C$4 -> 45322 | F67: =NAV!E19 -> 0 | G67: =SUM(D67:F67) -> 0 | T67: =F67 -> 0
B68: =NAV!B20 -> X-fusion | C68: =$C$4 -> 45322 | F68: =NAV!E20 -> 0 | G68: =SUM(D68:F68) -> 0 | U68: =F68 -> 0
B69: =NAV!B21 -> DriveNets | C69: =$C$4 -> 45322 | F69: =NAV!E21 -> 300 | G69: =SUM(D69:F69) -> 300 | V69: =F69 -> 300
B70: =NAV!B22 -> vTv Therapeutics Inc. | C70: =$C$4 -> 45322 | F70: =NAV!E22 -> 2.1837154 | G70: =SUM(D70:F70) -> 2.1837154 | W70: =F70 -> 2.1837154
B71: =NAV!B23 -> Honor Device Co Ltd | C71: =$C$4 -> 45322 | F71: =NAV!E23 -> 0 | G71: =SUM(D71:F71) -> 0 | X71: =F71 -> 0
B72: =NAV!B24 -> Applied AI Corporation Limited | C72: =$C$4 -> 45322 | F72: =NAV!E24 -> 11.5 | G72: =SUM(D72:F72) -> 11.5 | Y72: =F72 -> 11.5
B73: =NAV!B25 -> eSpace | C73: =$C$4 -> 45322 | F73: =NAV!E25 -> 20.888122 | G73: =SUM(D73:F73) -> 20.888122 | Z73: =G73 -> 20.888122
B74: =NAV!B26 -> Tools for Humanity Corporation | C74: =$C$4 -> 45322 | F74: =NAV!E26 -> 14.999999 | G74: =SUM(D74:F74) -> 14.999999 | AA74: =G74 -> 14.999999
B75: =NAV!B27 -> WLD Tokens | C75: =$C$4 -> 45322 | F75: =NAV!E27 -> 15 | G75: =SUM(D75:F75) -> 15 | AB75: =G75 -> 15
B76: =NAV!B28 -> E-line Ventures LLC | C76: =$C$4 -> 45322 | F76: =NAV!E28 -> 6 | G76: =SUM(D76:F76) -> 6 | AC76: =G76 -> 6
B77: =NAV!B29 -> School Hack (AIREV Holding Limited) | C77: =$C$4 -> 45322 | F77: =NAV!E29 -> 2.75 | G77: =SUM(D77:F77) -> 2.75 | AD77: =G77 -> 2.75
I81: IRR | J81: =IF(ISERROR(XIRR(J10:J77,$C$10:$C$77)),"NM", XIRR(J10:J77,$C$10:$C$77)) -> NM | K81: =IF(ISERROR(XIRR(K13:K77,$C$13:$C$77)),"NM", XIRR(K13:K77,$C$13:$C$77)) -> NM | L81: =IF(ISERROR(XIRR(L14:L77,$C$14:$C$77)),"NM", XIRR(L14:L77,$C$14:$C$77)) -> 0.59885044 | M81: =IF(ISERROR(XIRR(M16:M77,$C$16:$C$77)),"NM", XIRR(M16:M77,$C$16:$C$77)) -> 0.36091766 | N81: =IF(ISERROR(XIRR(N17:N77,$C$17:$C$77)),"NM", XIRR(N17:N77,$C$17:$C$77)) -> 0.0029582828 | O81: =IF(ISERROR(XIRR(O21:O77,$C$21:$C$77)),"NM", XIRR(O21:O77,$C$21:$C$77)) -> -0.11648149 | P81: =IF(ISERROR(XIRR(P26:P77,$C$26:$C$77)),"NM", XIRR(P26:P77,$C$26:$C$77)) -> 0.33000317 | Q81: =IF(ISERROR(XIRR(Q27:Q77,$C$27:$C$77)),"NM", XIRR(Q27:Q77,$C$27:$C$77)) -> 0.098824507 | R81: =IF(ISERROR(XIRR(R28:R77,$C$28:$C$77)),"NM", XIRR(R28:R77,$C$28:$C$77)) -> 2.9802322e-09 | S81: =IF(ISERROR(XIRR(S29:S77,$C$29:$C$77)),"NM", XIRR(S29:S77,$C$29:$C$77)) -> 2.9802322e-09 | T81: =IF(ISERROR(XIRR(T30:T77,$C$30:$C$77)),"NM", XIRR(T30:T77,$C$30:$C$77)) -> 0.32803498 | U81: =IF(ISERROR(XIRR(U31:U77,$C$31:$C$77)),"NM", XIRR(U31:U77,$C$31:$C$77)) -> -0.10752884 | V81: =IF(ISERROR(XIRR(V32:V77,$C$32:$C$77)),"NM", XIRR(V32:V77,$C$32:$C$77)) -> 2.9802322e-09 | W81: =IF(ISERROR(XIRR(W35:W77,$C$35:$C$77)),"NM", XIRR(W35:W77,$C$35:$C$77)) -> -0.87320089 | X81: =IF(ISERROR(XIRR(X36:X77,$C$36:$C$77)),"NM", XIRR(X36:X77,$C$36:$C$77)) -> 0.0029359251 | Y81: =IF(ISERROR(XIRR(Y38:Y77,$C$38:$C$77)),"NM", XIRR(Y38:Y77,$C$38:$C$77)) -> 2.9802322e-09 | Z81: =IF(ISERROR(XIRR(Z39:Z77,$C$39:$C$77)),"NM", XIRR(Z39:Z77,$C$39:$C$77)) -> 0.32455407 | AA81: =IF(ISERROR(XIRR(AA41:AA77,$C$41:$C$77)),"NM", XIRR(AA41:AA77,$C$41:$C$77)) -> 2.9802322e-09 | AB81: =IF(ISERROR(XIRR(AB42:AB77,$C$42:$C$77)),"NM", XIRR(AB42:AB77,$C$42:$C$77)) -> NM | AC81: NM | AD81: NM
F82: ='S | 01 '!K32 -> 2118.283 | G82: =SUM(J82:AF82)-'S | 01 '!K32 -> 0 | H82: =SUM(J82:AF82)='S | 01 '!K32 -> TRUE | I82: PIC | J82: =-SUMIF(J$10:J$55,"<0",J$10:J$55) -> 65 | K82: =-SUMIF(K$10:K$55,"<0",K$10:K$55) -> 8 | L82: =-SUMIF(L$10:L$55,"<0",L$10:L$55) -> 10 | M82: =-SUMIF(M$10:M$55,"<0",M$10:M$55) -> 2.5 | N82: =-SUMIF(N$10:N$55,"<0",N$10:N$55) -> 90 | O82: =-SUMIF(O$10:O$55,"<0",O$10:O$55) -> 141.47026 | P82: =-SUMIF(P$10:P$55,"<0",P$10:P$55) -> 60 | Q82: =-SUMIF(Q$10:Q$55,"<0",Q$10:Q$55) -> 20 | ... AD82: =-SUMIF(AD$10:AD$55,"<0",AD$10:AD$55) -> 2.75
G83: =ROUND(SUM(J83:Z83),2)-ROUND('S | 01 '!M32,2) -> 0 | H83: =ROUND(SUM(J83:Z83),2)=ROUND('S | 01 '!M32,2) -> TRUE | I83: Dist | J83: =SUMIF(J$10:J$55,">0",J$10:J$55) -> 0 | K83: =SUMIF(K$10:K$55,">0",K$10:K$55) -> 0 | L83: =SUMIF(L$10:L$55,">0",L$10:L$55) -> 0 | M83: =SUMIF(M$10:M$55,">0",M$10:M$55) -> 5 | N83: =SUMIF(N$10:N$55,">0",N$10:N$55) -> 0 | O83: =SUMIF(O$10:O$55,">0",O$10:O$55) -> 0 | P83: =SUMIF(P$10:P$55,">0",P$10:P$55) -> 0 | Q83: =SUMIF(Q$10:Q$55,">0",Q$10:Q$55) -> 24.5 | ... AD83: =SUMIF(AD$10:AD$55,">0",AD$10:AD$55) -> 0
G84: =ROUND(SUM(J84:AF84),2)-ROUND('S | 01 '!N32,2) -> 0 | H84: =ROUND(SUM(J84:AF84),2)=ROUND('S | 01 '!N32,2) -> TRUE | I84: RV | J84: =SUM(J$57:J$77) -> 0 | K84: =SUM(K$57:K$77) -> 0 | L84: =SUM(L$57:L$77) -> 78.08223 | M84: =SUM(M$57:M$77) -> 0 | N84: =SUM(N$57:N$77) -> 91.00154 | O84: =SUM(O$57:O$77) -> 90.139175 | P84: =SUM(P$57:P$77) -> 148.04984 | Q84: =SUM(Q$57:Q$77) -> 0 | ... AD84: =SUM(AD$57:AD$77) -> 2.75
I85: TVPI | J85: =(J83+J84)/J82 -> 0 | K85: =(K83+K84)/K82 -> 0 | L85: =(L83+L84)/L82 -> 7.808223 | M85: =(M83+M84)/M82 -> 2 | N85: =(N83+N84)/N82 -> 1.0111282 | O85: =(O83+O84)/O82 -> 0.63715989 | P85: =(P83+P84)/P82 -> 2.4674974 | Q85: =(Q83+Q84)/Q82 -> 1.225 | ... AD85: =(AD83+AD84)/AD82 -> 1
I86: DPI | J86: =J83/J82 -> 0 | K86: =K83/K82 -> 0 | L86: =L83/L82 -> 0 | M86: =M83/M82 -> 2 | N86: =N83/N82 -> 0 | O86: =O83/O82 -> 0 | P86: =P83/P82 -> 0 | Q86: =Q83/Q82 -> 1.225 | ... AD86: =AD83/AD82 -> 0
I87: RVPI | J87: =J84/J82 -> 0 | K87: =K84/K82 -> 0 | L87: =L84/L82 -> 7.808223 | M87: =M84/M82 -> 0 | N87: =N84/N82 -> 1.0111282 | O87: =O84/O82 -> 0.63715989 | P87: =P84/P82 -> 2.4674974 | Q87: =Q84/Q82 -> 0 | ... AD87: =AD84/AD82 -> 1

Sheet 2. IRR Debt
B2: IRR - Debt
B4: Date of NAV | C4: =D!D2 -> 45322 | I4: Investment Level Summary | P4: Overall Summary
B6: USD Millions
B7: Investment | C7: Payment date | D7: Contributions | E7: Distributions | F7: Residual Value | G7: Combined | K7: Contribution | L7: Distribution | M7: Residual Value | N7: Combined | Q7: Committed | R7: Invested | S7: Remaining Commitment | T7: Distributions | U7: Residual Value | V7: IRR | W7: TVPI | X7: RPI | Y7: DPI
B8: Debt Investments
B9: ='CF (Equity, Debt)'!C53 -> Glass Earth Holdings LLC | C9: ='CF (Equity, Debt)'!D53 -> 43635 | D9: ='CF (Equity, Debt)'!E53 -> -8 | G9: =SUM(D9:F9) -> -8 | I9: =B9 -> Glass Earth Holdings LLC | J9: =C9 -> 43635 | K9: =D9 -> -8 | N9: =SUM(K9:M9) -> -8 | P9: Glass Earth Holdings LLC | Q9: =R9 -> 8 | R9: =-D9 -> 8 | S9: 0 | T9: =E9 -> 0 | U9: =F14 -> 0 | V9: =J12 -> NM | W9: =(T9+U9)/R9 -> 0 | X9: =U9/R9 -> 0 | Y9: =T9/R9 -> 0
B10: ='CF (Equity, Debt)'!C54 -> Mena Mobile Inc (Debt) | C10: ='CF (Equity, Debt)'!D54 -> 44293 | D10: ='CF (Equity, Debt)'!E54 -> -2.353982 | G10: =SUM(D10:F10) -> -2.353982 | I10: =B14 -> Glass Earth Holdings LLC | J10: =C14 -> 45322 | M10: =F14 -> 0 | N10: =SUM(K10:M10) -> 0 | P10: Mena Mobile Inc (Debt) | Q10: =R10 -> 2.353982 | R10: =-D10 -> 2.353982 | S10: 0 | T10: =E10 -> 0 | U10: =F15 -> 0 | V10: =J22:J22 -> NM | W10: =(T10+U10)/R10 -> 0 | X10: =U10/R10 -> 0 | Y10: =T10/R10 -> 0
B11: ='CF (Equity, Debt)'!C55 -> Esyasoft Holding (Debt) | C11: ='CF (Equity, Debt)'!D55 -> 44384 | D11: ='CF (Equity, Debt)'!E55 -> -0.411765 | G11: =SUM(D11:F11) -> -0.411765 | P11: Esyasoft Holding (Debt) | Q11: =R11 -> 0.411765 | R11: =-D11 -> 0.411765 | S11: 0 | T11: =E12 -> 0.47078465 | U11: =F16 -> 0 | V11: =J31 -> 0.075277027 | W11: =(T11+U11)/R11 -> 1.1433333 | X11: =U11/R11 -> 0 | Y11: =T11/R11 -> 1.1433333
B12: ='CF (Equity, Debt)'!C56 -> Esyasoft Holding (Debt) | C12: ='CF (Equity, Debt)'!D56 -> 44902 | D12: ='CF (Equity, Debt)'!E56 -> 0 | E12: ='CF (Equity, Debt)'!F56 -> 0.47078465 | G12: =SUM(D12:F12) -> 0.47078465 | I12: XIRR | J12: =IF(ISERROR(XIRR(N9:N10,J9:J10)),"NM",XIRR(N9:N10,J9:J10)) -> NM | L12: Contributions | Q12: =SUM(Q9:Q11) -> 10.765747 | R12: =SUM(R9:R11) -> 10.765747 | S12: =SUM(S9:S11) -> 0 | T12: =SUM(T9:T11) -> 0.47078465 | U12: =SUM(U9:U11) -> 0 | V12: =XIRR(G9:G16,C9:C16) -> -0.71226245 | W12: =(T12+U12)/R12 -> 0.043729864 | X12: =U12/R12 -> 0 | Y12: =T12/R12 -> 0.043729864
I13: TVPI | J13: =SUM(L9:M10)/-SUM(K9:K10) -> 0 | L13: Distributions
B14: =B9 -> Glass Earth Holdings LLC | C14: =$C$4 -> 45322 | F14: =VLOOKUP(B14,NAV!$B$34:$E$36,4,0) -> 0 | G14: =SUM(D14:F14) -> 0 | I14: RPI | J14: =SUM(M9:M10)/-SUM(K9:K10) -> 0 | L14: Residual Value
B15: =B10 -> Mena Mobile Inc (Debt) | C15: =$C$4 -> 45322 | F15: =VLOOKUP(B15,NAV!$B$34:$E$36,4,0) -> 0 | G15: =SUM(D15:F15) -> 0 | I15: DPI | J15: =SUM(L9:L10)/-SUM(K9:K10) -> 0 | P15: XIRR | Q15: =XIRR(G9:G18,C9:C18) -> -0.71226245
B16: =B11 -> Esyasoft Holding (Debt) | C16: =$C$4 -> 45322 | F16: =VLOOKUP(B16,NAV!$B$34:$E$36,4,0) -> 0 | G16: =SUM(D16:F16) -> 0 | P16: TVPI | Q16: =SUM(T9:U11)/SUM(R9:R11) -> 0.043729864
P17: RPI | Q17: =SUM(U9:U11)/SUM(R9:R11) -> 0
P18: DPI | Q18: =SUM(T9:T11)/SUM(R9:R11) -> 0.043729864
I19: =B10 -> Mena Mobile Inc (Debt) | J19: =C10 -> 44293 | K19: -2.353982 | N19: =SUM(K19:M19) -> -2.353982
I20: =B15 -> Mena Mobile Inc (Debt) | J20: =C15 -> 45322 | M20: 0 | N20: =SUM(K20:M20) -> 0
I22: XIRR | J22: =IF(ISERROR(XIRR(N19:N20,J19:J20)),"NM",XIRR(N19:N20,J19:J20)) -> NM | L22: Contributions
I23: TVPI | J23: =SUM(L19:M20)/-SUM(K19:K20) -> 0 | L23: Distributions
I24: RPI | J24: =SUM(M19:M20)/-SUM(K19:K20) -> 0 | L24: Residual Value
I25: DPI | J25: =SUM(L19:L20)/-SUM(K19:K20) -> 0
I28: =B11 -> Esyasoft Holding (Debt) | J28: =C11 -> 44384 | K28: -0.411765 | N28: =SUM(K28:M28) -> -0.411765
I29: =B16 -> Esyasoft Holding (Debt) | J29: ='CF (Equity, Debt)'!D56 -> 44902 | M29: 0.45643868 | N29: =SUM(K29:M29) -> 0.45643868
I31: XIRR | J31: =IF(ISERROR(XIRR(N28:N29,J28:J29)),"NM",XIRR(N28:N29,J28:J29)) -> 0.075277027 | L31: Contributions
I32: TVPI | J32: =SUM(L28:M29)/-SUM(K28:K29) -> 1.1084932 | L32: Distributions
I33: RPI | J33: =SUM(M28:M29)/-SUM(K28:K29) -> 1.1084932 | L33: Residual Value
I34: DPI | J34: =SUM(L28:L29)/-SUM(K28:K29) -> 0

Sheet 3. IRR Funds
B2: IRR - FUNDS | E2: Test | F2: =COUNTA(B8:B56)=COUNTA('CF (Funds)'!B3:B51) -> TRUE
B4: Date of NAV | C4: =D!D2 -> 45322 | I4: Fund Level Summary | P4: Overall Summary
B6: USD Millions
B7: Investment | C7: Payment date | D7: Contributions | E7: Distributions | F7: Residual Value | G7: Combined | K7: Contribution | L7: Distribution | M7: Residual Value | N7: Combined | Q7: Committed | R7: Invested | S7: Remaining Commitment | T7: Distributions | U7: Residual Value | V7: IRR | W7: TVPI | X7: RPI | Y7: DPI
B8: ='CF (Funds)'!B3 -> Sinovation Disrupt Fund, L.P. | C8: ='CF (Funds)'!C3 -> 44153 | D8: ='CF (Funds)'!D3 -> -10.5 | E8: ='CF (Funds)'!E3 -> 0 | G8: =SUM(D8:F8) -> -10.5 | P8: Funds Investments
B9: ='CF (Funds)'!B4 -> Sinovation Disrupt Fund, L.P. | C9: ='CF (Funds)'!C4 -> 44238 | D9: ='CF (Funds)'!D4 -> 4.214027 | E9: ='CF (Funds)'!E4 -> 0 | G9: =SUM(D9:F9) -> 4.214027 | I9: =B41 -> New Space Capital Fund I | J9: =C41 -> 44087 | K9: =D41 -> -20.917553 | L9: =E41 -> 0 | M9: =F41 -> 0 | N9: =SUM(K9:M9) -> -20.917553 | P9: New Space Capital Fund I | Q9: ='S | 01 '!J41 -> 31.022787 | R9: =-SUMIF($B$7:$F$109,$P9,$D$7:$D$109) -> 13.988553 | S9: =Q9-R9 -> 17.034234 | T9: =SUMIF($B$7:$F$109,$P9,$E$7:$E$109) -> 2.9557744 | U9: =SUMIF($B$7:$F$109,$P9,$F$7:$F$109) -> 13.277945 | V9: =J21 -> 0.036116043 | W9: =(T9+U9)/R9 -> 1.1605002 | X9: =U9/R9 -> 0.94920073 | Y9: =T9/R9 -> 0.21129951
B10: ='CF (Funds)'!B5 -> Sinovation Disrupt Fund, L.P. | C10: ='CF (Funds)'!C5 -> 44238 | D10: ='CF (Funds)'!D5 -> 0 | E10: ='CF (Funds)'!E5 -> 0.05044835 | G10: =SUM(D10:F10) -> 0.05044835 | I10: =B42 -> New Space Capital Fund I | J10: =C42 -> 44287 | K10: =D42 -> -0.21103182 | L10: =E42 -> 0 | M10: =F42 -> 0 | N10: =SUM(K10:M10) -> -0.21103182 | P10: New Space Capital GP Com SCSp | Q10: ='S | 01 '!J42 -> 2.7058824 | R10: =-SUMIF($B$7:$F$109,$P10,$D$7:$D$109) -> 2.7058824 | S10: =Q10-R10 -> 0 | T10: =SUMIF($B$7:$F$109,$P10,$E$7:$E$109) -> 0 | U10: =SUMIF($B$7:$F$109,$P10,$F$7:$F$109) -> 2.5684255 | V10: 0 | W10: =(T10+U10)/R10 -> 0.94920073 | X10: =U10/R10 -> 0.94920073 | Y10: =T10/R10 -> 0
B11: ='CF (Funds)'!B6 -> Sinovation Disrupt Fund, L.P. | C11: ='CF (Funds)'!C6 -> 44285 | D11: ='CF (Funds)'!D6 -> -6.433746 | E11: ='CF (Funds)'!E6 -> 0 | G11: =SUM(D11:F11) -> -6.433746 | I11: =B43 -> New Space Capital Fund I | J11: =C43 -> 44442 | K11: =D43 -> -0.23965473 | L11: =E43 -> 0 | M11: =F43 -> 0 | N11: =SUM(K11:M11) -> -0.23965473 | P11: North Summit Capital Fund | Q11: ='S | 01 '!J43 -> 83.334353 | R11: =-SUMIF($B$7:$F$109,$P11,$D$7:$D$109) -> 83.214653 | S11: =Q11-R11+T11 -> 7.935571 | T11: =SUMIF($B$7:$F$109,$P11,$E$7:$E$109) -> 7.815871 | U11: =SUMIF($B$7:$F$109,$P11,$F$7:$F$109) -> 74.725861 | V11: =J57 -> -0.0025177218 | W11: =(T11+U11)/R11 -> 0.99191343 | X11: =U11/R11 -> 0.89798922 | Y11: =T11/R11 -> 0.093924215
B12: ='CF (Funds)'!B7 -> Sinovation Disrupt Fund, L.P. | C12: ='CF (Funds)'!C7 -> 44269 | D12: ='CF (Funds)'!D7 -> 1.1352074 | E12: ='CF (Funds)'!E7 -> 0 | G12: =SUM(D12:F12) -> 1.1352074 | I12: =B44 -> New Space Capital Fund I | J12: =C44 -> 44623 | K12: =D44 -> -0.25893585 | L12: =E44 -> 0 | M12: =F44 -> 0 | N12: =SUM(K12:M12) -> -0.25893585 | P12: Sinovation Disrupt Fund, L.P. | Q12: ='S | 01 '!J44 -> 50 | R12: =-SUMIF($B$7:$F$109,$P12,$D$7:$D$109) -> 24.959693 | S12: =Q12-R12 -> 25.040307 | T12: =SUMIF($B$7:$F$109,$P12,$E$7:$E$109) -> 0.44382835 | U12: =SUMIF($B$7:$F$109,$P12,$F$7:$F$109) -> 23.670303 | V12: =J83 -> -0.014868453 | W12: =(T12+U12)/R12 -> 0.96612291 | X12: =U12/R12 -> 0.94834111 | Y12: =T12/R12 -> 0.017781803
B13: ='CF (Funds)'!B8 -> Sinovation Disrupt Fund, L.P. | C13: ='CF (Funds)'!C8 -> 44269 | D13: ='CF (Funds)'!D8 -> 0 | E13: ='CF (Funds)'!E8 -> 0.0259 | G13: =SUM(D13:F13) -> 0.0259 | I13: =B45 -> New Space Capital Fund I | J13: =C45 -> 44784 | K13: =D45 -> 0.015224657 | L13: =E45 -> 0 | M13: =F45 -> 0 | N13: =SUM(K13:M13) -> 0.015224657 | P13: Acies Investments Fund I, L.P. | Q13: ='S | 01 '!J45 -> 17.1125 | R13: =-SUMIF($B$7:$F$109,$P13,$D$7:$D$109) -> 14.015137 | S13: =Q13-R13 -> 3.0973625 | T13: =SUMIF($B$7:$F$109,$P13,$E$7:$E$109) -> 0 | U13: =SUMIF($B$7:$F$109,$P13,$F$7:$F$109) -> 12.310425 | V13: =J95 -> -0.071990828 | W13: =(T13+U13)/R13 -> 0.87836634 | X13: =U13/R13 -> 0.87836634 | Y13: =T13/R13 -> 0
B14: ='CF (Funds)'!B9 -> Sinovation Disrupt Fund, L.P. | C14: ='CF (Funds)'!C9 -> 44483 | D14: ='CF (Funds)'!D9 -> -7.567138 | E14: ='CF (Funds)'!E9 -> 0 | G14: =SUM(D14:F14) -> -7.567138 | I14: =B46 -> New Space Capital Fund I | J14: =C46 -> 44956 | K14: =D46 -> 10.553916 | L14: =E46 -> 0 | M14: =F46 -> 0 | N14: =SUM(K14:M14) -> 10.553916
B15: ='CF (Funds)'!B10 -> Sinovation Disrupt Fund, L.P. | C15: ='CF (Funds)'!C10 -> 44554 | D15: ='CF (Funds)'!D10 -> -7.385016 | E15: ='CF (Funds)'!E10 -> 0 | G15: =SUM(D15:F15) -> -7.385016 | I15: =B47 -> New Space Capital Fund I | J15: =C47 -> 44956 | K15: =D47 -> 0 | L15: =E47 -> 2.9557744 | M15: =F47 -> 0 | N15: =SUM(K15:M15) -> 2.9557744 | P15: Total | Q15: =SUM(Q9:Q14) -> 184.17552 | R15: =SUM(R9:R14) -> 138.88392 | S15: =SUM(S9:S14) -> 53.107474 | T15: =SUM(T9:T14) -> 11.215474 | U15: =SUM(U9:U14) -> 126.55296 | V15: =XIRR(G8:G50,C8:C50) -> 2.9802322e-09 | W15: =(T15+U15)/R15 -> 0.99196821 | X15: =U15/R15 -> 0.91121391 | Y15: =T15/R15 -> 0.0807543
B16: ='CF (Funds)'!B11 -> Sinovation Disrupt Fund, L.P. | C16: ='CF (Funds)'!C11 -> 44554 | D16: ='CF (Funds)'!D11 -> 4.0733456 | E16: ='CF (Funds)'!E11 -> 0 | G16: =SUM(D16:F16) -> 4.0733456 | I16: =B48 -> New Space Capital Fund I | J16: =C48 -> 45170 | K16: =D48 -> -0.22532724 | L16: =E48 -> 0 | M16: =F48 -> 0 | N16: =SUM(K16:M16) -> -0.22532724 | Q16: ='S | 01 '!J46 -> 184.17552 | R16: ='S | 01 '!K46 -> 138.88392 | S16: ='S | 01 '!L46 -> 45.291603 | T16: ='S | 01 '!M46 -> 11.215474 | U16: ='S | 01 '!N46 -> 126.55296
B17: ='CF (Funds)'!B12 -> Sinovation Disrupt Fund, L.P. | C17: ='CF (Funds)'!C12 -> 44554 | D17: ='CF (Funds)'!D12 -> 0 | E17: ='CF (Funds)'!E12 -> 0.139694 | G17: =SUM(D17:F17) -> 0.139694 | I17: =B49 -> New Space Capital Fund I | J17: =C49 -> 45260 | K17: =D49 -> -0.28531252 | L17: =E49 -> 0 | M17: =F49 -> 0 | N17: =SUM(K17:M17) -> -0.28531252
B18: ='CF (Funds)'!B13 -> Sinovation Disrupt Fund, L.P. | C18: ='CF (Funds)'!C13 -> 44703 | D18: ='CF (Funds)'!D13 -> 5.673074 | E18: ='CF (Funds)'!E13 -> 0 | G18: =SUM(D18:F18) -> 5.673074 | I18: =B50 -> New Space Capital Fund I | J18: =C50 -> 45321 | K18: =D50 -> -2.4198785 | L18: =E50 -> 0 | M18: =F50 -> 0 | N18: =SUM(K18:M18) -> -2.4198785 | P18: XIRR | Q18: =XIRR(G8:G50,C8:C50) -> 2.9802322e-09
B19: ='CF (Funds)'!B14 -> Sinovation Disrupt Fund, L.P. | C19: ='CF (Funds)'!C14 -> 44703 | D19: ='CF (Funds)'!D14 -> 0 | E19: ='CF (Funds)'!E14 -> 0.227786 | G19: =SUM(D19:F19) -> 0.227786 | I19: New Space Capital Fund I | J19: =$C$4 -> 45322 | M19: =F59 -> 13.277945 | N19: =SUM(K19:M19) -> 13.277945 | P19: TVPI | Q19: =SUM(T9:U13)/SUM(R9:R13) -> 0.99196821
B20: ='CF (Funds)'!B15 -> Sinovation Disrupt Fund, L.P. | C20: ='CF (Funds)'!C15 -> 44776 | D20: ='CF (Funds)'!D15 -> -3.235493 | E20: ='CF (Funds)'!E15 -> 0 | G20: =SUM(D20:F20) -> -3.235493 | P20: RPI | Q20: =SUM(U9:U13)/SUM(R9:R13) -> 0.91121391
B21: ='CF (Funds)'!B16 -> Sinovation Disrupt Fund, L.P. | C21: ='CF (Funds)'!C16 -> 44960 | D21: ='CF (Funds)'!D16 -> -2.631528 | E21: ='CF (Funds)'!E16 -> 0 | G21: =SUM(D21:F21) -> -2.631528 | I21: XIRR | J21: =XIRR(N9:N19,J9:J19) -> 0.036116043 | L21: Contributions | M21: =-SUM(K9:K19)='S | 01 '!K41 -> TRUE | P21: DPI | Q21: =SUM(T9:T13)/SUM(R9:R13) -> 0.0807543
B22: ='CF (Funds)'!B17 -> Sinovation Disrupt Fund, L.P. | C22: ='CF (Funds)'!C17 -> 45085 | D22: ='CF (Funds)'!D17 -> 1.912557 | E22: ='CF (Funds)'!E17 -> 0 | G22: =SUM(D22:F22) -> 1.912557 | I22: TVPI | J22: =SUM(L9:M19)/-SUM(K9:K19) -> 1.1605002 | L22: Distributions | M22: =-SUM(L9:L20)=-'S | 01 '!M41 -> TRUE
B23: ='CF (Funds)'!B18 -> Sinovation Disrupt Fund, L.P. | C23: ='CF (Funds)'!C18 -> 45166 | D23: ='CF (Funds)'!D18 -> -1.799122 | E23: ='CF (Funds)'!E18 -> 0 | G23: =SUM(D23:F23) -> -1.799122 | I23: RPI | J23: =SUM(M9:M19)/-SUM(K9:K19) -> 0.94920073 | L23: Residual Value | M23: =M19='S | 01 '!N41 -> TRUE
B24: ='CF (Funds)'!B19 -> Sinovation Disrupt Fund, L.P. | C24: ='CF (Funds)'!C19 -> 45218 | D24: ='CF (Funds)'!D19 -> -2.415861 | E24: ='CF (Funds)'!E19 -> 0 | G24: =SUM(D24:F24) -> -2.415861 | I24: DPI | J24: =SUM(L9:L19)/-SUM(K9:K19) -> 0.21129951
B25: ='CF (Funds)'!B20 -> Sinovation Disrupt Fund, L.P. | C25: ='CF (Funds)'!C20 -> 0 | D25: ='CF (Funds)'!D20 -> 0 | E25: ='CF (Funds)'!E20 -> 0 | G25: =SUM(D25:F25) -> 0
B26: ='CF (Funds)'!B21 -> North Summit Capital Fund | C26: ='CF (Funds)'!C21 -> 43665 | D26: ='CF (Funds)'!D21 -> -3 | E26: ='CF (Funds)'!E21 -> 0 | G26: =SUM(D26:F26) -> -3
B27: ='CF (Funds)'!B22 -> North Summit Capital Fund | C27: ='CF (Funds)'!C22 -> 43983 | D27: ='CF (Funds)'!D22 -> -4.485 | E27: ='CF (Funds)'!E22 -> 0 | G27: =SUM(D27:F27) -> -4.485
B28: ='CF (Funds)'!B23 -> North Summit Capital Fund | C28: ='CF (Funds)'!C23 -> 43879 | D28: ='CF (Funds)'!D23 -> -9.50975 | E28: ='CF (Funds)'!E23 -> 0 | G28: =SUM(D28:F28) -> -9.50975
B29: ='CF (Funds)'!B24 -> North Summit Capital Fund | C29: ='CF (Funds)'!C24 -> 43934 | D29: ='CF (Funds)'!D24 -> -41.3 | E29: ='CF (Funds)'!E24 -> 0 | G29: =SUM(D29:F29) -> -41.3
B30: ='CF (Funds)'!B25 -> North Summit Capital Fund | C30: ='CF (Funds)'!C25 -> 44151 | D30: ='CF (Funds)'!D25 -> 9.95 | E30: ='CF (Funds)'!E25 -> 0 | G30: =SUM(D30:F30) -> 9.95 | I30: =B51 -> New Space Capital GP Com SCSp | J30: =C51 -> 44087 | K30: =D51 -> -2.7058824 | N30: =SUM(K30:M30) -> -2.7058824
B31: ='CF (Funds)'!B26 -> North Summit Capital Fund | C31: ='CF (Funds)'!C26 -> 44151 | D31: ='CF (Funds)'!D26 -> -10.455 | E31: ='CF (Funds)'!E26 -> 0 | G31: =SUM(D31:F31) -> -10.455 | I31: New Space Capital SCSp | J31: =$C$4 -> 45322 | M31: =F60 -> 2.5684255 | N31: =SUM(K31:M31) -> 2.5684255
B32: ='CF (Funds)'!B27 -> North Summit Capital Fund | C32: ='CF (Funds)'!C27 -> 44196 | D32: ='CF (Funds)'!D27 -> 4.975 | E32: ='CF (Funds)'!E27 -> 0 | G32: =SUM(D32:F32) -> 4.975
B33: ='CF (Funds)'!B28 -> North Summit Capital Fund | C33: ='CF (Funds)'!C28 -> 44196 | D33: ='CF (Funds)'!D28 -> -3.452293 | E33: ='CF (Funds)'!E28 -> 0 | G33: =SUM(D33:F33) -> -3.452293 | I33: XIRR | J33: =XIRR(N30:N31,J30:J31) -> -0.015290216 | L33: Contributions | M33: =-SUM(K30:K31)='S | 01 '!K42 -> TRUE
B34: ='CF (Funds)'!B29 -> North Summit Capital Fund | C34: ='CF (Funds)'!C29 -> 44196 | D34: ='CF (Funds)'!D29 -> 0 | E34: ='CF (Funds)'!E29 -> 0.582902 | G34: =SUM(D34:F34) -> 0.582902 | I34: TVPI | J34: =SUM(L30:M31)/-SUM(K30:K31) -> 0.94920073 | L34: Distributions | M34: =-SUM(L24:L32)=-'S | 01 '!L42 -> TRUE
B35: ='CF (Funds)'!B30 -> North Summit Capital Fund | C35: ='CF (Funds)'!C30 -> 44370 | D35: ='CF (Funds)'!D30 -> -5.97 | E35: ='CF (Funds)'!E30 -> 0 | G35: =SUM(D35:F35) -> -5.97 | I35: RPI | J35: =SUM(M30:M31)/-SUM(K30:K31) -> 0.94920073 | L35: Residual Value | M35: =M31='S | 01 '!N42 -> TRUE
B36: ='CF (Funds)'!B31 -> North Summit Capital Fund | C36: ='CF (Funds)'!C31 -> 44400 | D36: ='CF (Funds)'!D31 -> -0.75 | E36: ='CF (Funds)'!E31 -> 0 | G36: =SUM(D36:F36) -> -0.75 | I36: DPI | J36: =SUM(L30:L31)/-SUM(K30:K31) -> 0
B37: ='CF (Funds)'!B32 -> North Summit Capital Fund | C37: ='CF (Funds)'!C32 -> 44400 | D37: ='CF (Funds)'!D32 -> 0 | E37: ='CF (Funds)'!E32 -> 0.445059 | G37: =SUM(D37:F37) -> 0.445059
B38: ='CF (Funds)'!B33 -> North Summit Capital Fund | C38: ='CF (Funds)'!C33 -> 44554 | D38: ='CF (Funds)'!D33 -> 1.78239 | E38: ='CF (Funds)'!E33 -> 0 | G38: =SUM(D38:F38) -> 1.78239
B39: ='CF (Funds)'!B34 -> North Summit Capital Fund | C39: ='CF (Funds)'!C34 -> 44676 | D39: ='CF (Funds)'!D34 -> -21 | E39: ='CF (Funds)'!E34 -> 0 | G39: =SUM(D39:F39) -> -21 | I39: =B26 -> North Summit Capital Fund | J39: =C26 -> 43665 | K39: =D26 -> -3 | L39: =E26 -> 0 | M39: =F26 -> 0 | N39: =SUM(K39:M39) -> -3
B40: ='CF (Funds)'!B35 -> North Summit Capital Fund | C40: ='CF (Funds)'!C35 -> 45243 | E40: ='CF (Funds)'!E35 -> 6.78791 | G40: =SUM(D40:F40) -> 6.78791 | I40: =B27 -> North Summit Capital Fund | J40: =C27 -> 43983 | K40: =D27 -> -4.485 | L40: =E27 -> 0 | M40: =F27 -> 0 | N40: =SUM(K40:M40) -> -4.485
B41: ='CF (Funds)'!B36 -> New Space Capital Fund I | C41: ='CF (Funds)'!C36 -> 44087 | D41: ='CF (Funds)'!D36 -> -20.917553 | E41: ='CF (Funds)'!E36 -> 0 | G41: =SUM(D41:F41) -> -20.917553 | I41: =B28 -> North Summit Capital Fund | J41: =C28 -> 43879 | K41: =D28 -> -9.50975 | L41: =E28 -> 0 | M41: =F28 -> 0 | N41: =SUM(K41:M41) -> -9.50975
B42: ='CF (Funds)'!B37 -> New Space Capital Fund I | C42: ='CF (Funds)'!C37 -> 44287 | D42: ='CF (Funds)'!D37 -> -0.21103182 | E42: ='CF (Funds)'!E37 -> 0 | G42: =SUM(D42:F42) -> -0.21103182 | I42: =B29 -> North Summit Capital Fund | J42: =C29 -> 43934 | K42: =D29 -> -41.3 | L42: =E29 -> 0 | M42: =F29 -> 0 | N42: =SUM(K42:M42) -> -41.3
B43: ='CF (Funds)'!B38 -> New Space Capital Fund I | C43: ='CF (Funds)'!C38 -> 44442 | D43: ='CF (Funds)'!D38 -> -0.23965473 | E43: ='CF (Funds)'!E38 -> 0 | G43: =SUM(D43:F43) -> -0.23965473 | I43: =B30 -> North Summit Capital Fund | J43: =C30 -> 44151 | K43: =D30 -> 9.95 | L43: =E30 -> 0 | M43: =F30 -> 0 | N43: =SUM(K43:M43) -> 9.95
B44: ='CF (Funds)'!B39 -> New Space Capital Fund I | C44: ='CF (Funds)'!C39 -> 44623 | D44: ='CF (Funds)'!D39 -> -0.25893585 | E44: ='CF (Funds)'!E39 -> 0 | G44: =SUM(D44:F44) -> -0.25893585 | I44: =B31 -> North Summit Capital Fund | J44: =C31 -> 44151 | K44: =D31 -> -10.455 | L44: =E31 -> 0 | M44: =F31 -> 0 | N44: =SUM(K44:M44) -> -10.455
B45: ='CF (Funds)'!B40 -> New Space Capital Fund I | C45: ='CF (Funds)'!C40 -> 44784 | D45: ='CF (Funds)'!D40 -> 0.015224657 | E45: ='CF (Funds)'!E40 -> 0 | G45: =SUM(D45:F45) -> 0.015224657 | I45: =B32 -> North Summit Capital Fund | J45: =C32 -> 44196 | K45: =D32 -> 4.975 | L45: =E32 -> 0 | M45: =F32 -> 0 | N45: =SUM(K45:M45) -> 4.975
B46: ='CF (Funds)'!B41 -> New Space Capital Fund I | C46: ='CF (Funds)'!C41 -> 44956 | D46: ='CF (Funds)'!D41 -> 10.553916 | E46: ='CF (Funds)'!E41 -> 0 | G46: =SUM(D46:F46) -> 10.553916 | I46: =B33 -> North Summit Capital Fund | J46: =C33 -> 44196 | K46: =D33 -> -3.452293 | L46: =E33 -> 0 | M46: =F33 -> 0 | N46: =SUM(K46:M46) -> -3.452293
B47: ='CF (Funds)'!B42 -> New Space Capital Fund I | C47: ='CF (Funds)'!C42 -> 44956 | D47: ='CF (Funds)'!D42 -> 0 | E47: ='CF (Funds)'!E42 -> 2.9557744 | G47: =SUM(D47:F47) -> 2.9557744 | I47: =B34 -> North Summit Capital Fund | J47: =C34 -> 44196 | K47: =D34 -> 0 | L47: =E34 -> 0.582902 | M47: =F34 -> 0 | N47: =SUM(K47:M47) -> 0.582902
B48: ='CF (Funds)'!B43 -> New Space Capital Fund I | C48: ='CF (Funds)'!C43 -> 45170 | D48: ='CF (Funds)'!D43 -> -0.22532724 | E48: ='CF (Funds)'!E43 -> 0 | G48: =SUM(D48:F48) -> -0.22532724 | I48: =B35 -> North Summit Capital Fund | J48: =C35 -> 44370 | K48: =D35 -> -5.97 | L48: =E35 -> 0 | M48: =F35 -> 0 | N48: =SUM(K48:M48) -> -5.97
B49: ='CF (Funds)'!B44 -> New Space Capital Fund I | C49: ='CF (Funds)'!C44 -> 45260 | D49: ='CF (Funds)'!D44 -> -0.28531252 | E49: ='CF (Funds)'!E44 -> 0 | G49: =SUM(D49:F49) -> -0.28531252 | I49: =B36 -> North Summit Capital Fund | J49: =C36 -> 44400 | K49: =D36 -> -0.75 | L49: =E36 -> 0 | M49: =F36 -> 0 | N49: =SUM(K49:M49) -> -0.75
B50: ='CF (Funds)'!B45 -> New Space Capital Fund I | C50: ='CF (Funds)'!C45 -> 45321 | D50: ='CF (Funds)'!D45 -> -2.4198785 | E50: ='CF (Funds)'!E45 -> 0 | G50: =SUM(D50:F50) -> -2.4198785 | I50: =B37 -> North Summit Capital Fund | J50: =C37 -> 44400 | K50: =D37 -> 0 | L50: =E37 -> 0.445059 | M50: =F37 -> 0 | N50: =SUM(K50:M50) -> 0.445059
B51: ='CF (Funds)'!B46 -> New Space Capital GP Com SCSp | C51: ='CF (Funds)'!C46 -> 44087 | D51: ='CF (Funds)'!D46 -> -2.7058824 | E51: ='CF (Funds)'!E46 -> 0 | G51: =SUM(D51:F51) -> -2.7058824 | I51: =B38 -> North Summit Capital Fund | J51: =C38 -> 44554 | K51: =D38 -> 1.78239 | L51: =E38 -> 0 | M51: =F38 -> 0 | N51: =SUM(K51:M51) -> 1.78239
B52: ='CF (Funds)'!B47 -> Acies Investments Fund I, L.P. | C52: ='CF (Funds)'!C47 -> 44540 | D52: ='CF (Funds)'!D47 -> -2.8053125 | E52: ='CF (Funds)'!E47 -> 0 | G52: =SUM(D52:F52) -> -2.8053125 | I52: =B39 -> North Summit Capital Fund | J52: =C39 -> 44676 | K52: =D39 -> -21 | L52: =E39 -> 0 | M52: =F39 -> 0 | N52: =SUM(K52:M52) -> -21
B53: ='CF (Funds)'!B48 -> Acies Investments Fund I, L.P. | C53: ='CF (Funds)'!C48 -> 44602 | D53: ='CF (Funds)'!D48 -> -3.4075 | E53: ='CF (Funds)'!E48 -> 0 | G53: =SUM(D53:F53) -> -3.4075 | I53: =B40 -> North Summit Capital Fund | J53: =C40 -> 45243 | K53: =D40 -> 0 | L53: =E40 -> 6.78791 | M53: =F40 -> 0 | N53: =SUM(K53:M53) -> 6.78791
B54: ='CF (Funds)'!B49 -> Acies Investments Fund I, L.P. | C54: ='CF (Funds)'!C49 -> 44683 | D54: ='CF (Funds)'!D49 -> -1.025775 | E54: ='CF (Funds)'!E49 -> 0 | G54: =SUM(D54:F54) -> -1.025775 | I54: North Summit Capital Fund | J54: =$C$4 -> 45322 | M54: =F58 -> 74.725861 | N54: =SUM(K54:M54) -> 74.725861
B55: ='CF (Funds)'!B50 -> Acies Investments Fund I, L.P. | C55: ='CF (Funds)'!C50 -> 44707 | D55: ='CF (Funds)'!D50 -> -3.388275 | E55: ='CF (Funds)'!E50 -> 0 | G55: =SUM(D55:F55) -> -3.388275
B56: ='CF (Funds)'!B51 -> Acies Investments Fund I, L.P. | C56: ='CF (Funds)'!C51 -> 44875 | D56: ='CF (Funds)'!D51 -> -3.388275 | E56: ='CF (Funds)'!E51 -> 0 | G56: =SUM(D56:F56) -> -3.388275
B57: Sinovation Disrupt Fund, L.P. | C57: =$C$4 -> 45322 | F57: =VLOOKUP(B57,NAV!$B$2:$H$46,4,0) -> 23.670303 | G57: =SUM(D57:F57) -> 23.670303 | I57: XIRR | J57: =XIRR(N39:N54,J39:J54,-0.1) -> -0.0025177218 | L57: Contributions | M57: =-SUM(K39:K52)='S | 01 '!K43 -> TRUE
B58: North Summit Capital Fund | C58: =$C$4 -> 45322 | F58: =VLOOKUP(B58,NAV!$B$2:$H$46,4,0) -> 74.725861 | G58: =SUM(D58:F58) -> 74.725861 | I58: TVPI | J58: =SUM(L39:M54)/-SUM(K39:K54) -> 0.99191343 | L58: Distributions | M58: =-SUM(L39:L53)=-'S | 01 '!M43 -> TRUE
B59: New Space Capital Fund I | C59: =$C$4 -> 45322 | F59: =VLOOKUP(B59,NAV!$B$2:$H$46,4,0) -> 13.277945 | G59: =SUM(D59:F59) -> 13.277945 | I59: RPI | J59: =SUM(M39:M54)/-SUM(K39:K54) -> 0.89798922 | L59: Residual Value | M59: =M54='S | 01 '!N43 -> TRUE
B60: New Space Capital GP Com SCSp | C60: =$C$4 -> 45322 | F60: =VLOOKUP(B60,NAV!$B$2:$H$46,4,0) -> 2.5684255 | G60: =SUM(D60:F60) -> 2.5684255 | I60: DPI | J60: =SUM(L39:L54)/-SUM(K39:K54) -> 0.093924215
B61: Acies Investments Fund I, L.P. | C61: =$C$4 -> 45322 | F61: =VLOOKUP(B61,NAV!$B$2:$H$46,4,0) -> 12.310425 | G61: =SUM(D61:F61) -> 12.310425
I63: =B8 -> Sinovation Disrupt Fund, L.P. | J63: =C8 -> 44153 | K63: =D8 -> -10.5 | L63: =E8 -> 0 | M63: =F8 -> 0 | N63: =SUM(K63:M63) -> -10.5
I64: =B9 -> Sinovation Disrupt Fund, L.P. | J64: =C9 -> 44238 | K64: =D9 -> 4.214027 | L64: =E9 -> 0 | M64: =F9 -> 0 | N64: =SUM(K64:M64) -> 4.214027
I65: =B10 -> Sinovation Disrupt Fund, L.P. | J65: =C10 -> 44238 | K65: =D10 -> 0 | L65: =E10 -> 0.05044835 | M65: =F10 -> 0 | N65: =SUM(K65:M65) -> 0.05044835
I66: =B11 -> Sinovation Disrupt Fund, L.P. | J66: =C11 -> 44285 | K66: =D11 -> -6.433746 | L66: =E11 -> 0 | M66: =F11 -> 0 | N66: =SUM(K66:M66) -> -6.433746
I67: =B12 -> Sinovation Disrupt Fund, L.P. | J67: =C12 -> 44269 | K67: =D12 -> 1.1352074 | L67: =E12 -> 0 | M67: =F12 -> 0 | N67: =SUM(K67:M67) -> 1.1352074
I68: =B13 -> Sinovation Disrupt Fund, L.P. | J68: =C13 -> 44269 | K68: =D13 -> 0 | L68: =E13 -> 0.0259 | M68: =F13 -> 0 | N68: =SUM(K68:M68) -> 0.0259
I69: =B14 -> Sinovation Disrupt Fund, L.P. | J69: =C14 -> 44483 | K69: =D14 -> -7.567138 | L69: =E14 -> 0 | M69: =F14 -> 0 | N69: =SUM(K69:M69) -> -7.567138
I70: =B15 -> Sinovation Disrupt Fund, L.P. | J70: =C15 -> 44554 | K70: =D15 -> -7.385016 | L70: =E15 -> 0 | M70: =F15 -> 0 | N70: =SUM(K70:M70) -> -7.385016
I71: =B16 -> Sinovation Disrupt Fund, L.P. | J71: =C16 -> 44554 | K71: =D16 -> 4.0733456 | L71: =E16 -> 0 | M71: =F16 -> 0 | N71: =SUM(K71:M71) -> 4.0733456
I72: =B17 -> Sinovation Disrupt Fund, L.P. | J72: =C17 -> 44554 | K72: =D17 -> 0 | L72: =E17 -> 0.139694 | M72: =F17 -> 0 | N72: =SUM(K72:M72) -> 0.139694
I73: =B18 -> Sinovation Disrupt Fund, L.P. | J73: =C18 -> 44703 | K73: =D18 -> 5.673074 | L73: =E18 -> 0 | M73: =F18 -> 0 | N73: =SUM(K73:M73) -> 5.673074
I74: =B19 -> Sinovation Disrupt Fund, L.P. | J74: =C19 -> 44703 | K74: =D19 -> 0 | L74: =E19 -> 0.227786 | M74: =F19 -> 0 | N74: =SUM(K74:M74) -> 0.227786
... I80: =B25 -> Sinovation Disrupt Fund, L.P. | J80: =C25 -> 0 | K80: =D25 -> 0 | L80: =E25 -> 0 | M80: =F25 -> 0 | N80: =SUM(K80:M80) -> 0
I81: Sinovation Disrupt Fund, L.P. | J81: =$C$4 -> 45322 | M81: =F57 -> 23.670303 | N81: =SUM(K81:M81) -> 23.670303
I83: XIRR | J83: =XIRR(N63:N81,J63:J81) -> -0.014868453 | L83: Contributions | M83: =-SUM(K63:K80)='S | 01 '!K44 -> TRUE
I84: TVPI | J84: =SUM(L63:M81)/-SUM(K63:K81) -> 0.96612291 | L84: Distributions | M84: =-SUM(L63:L80)=-'S | 01 '!M44 -> TRUE
I85: RPI | J85: =SUM(M63:M81)/-SUM(K63:K81) -> 0.94834111 | L85: Residual Value | M85: =M81='S | 01 '!N44 -> TRUE
I86: DPI | J86: =SUM(L63:L81)/-SUM(K63:K81) -> 0.017781803
I88: =B52 -> Acies Investments Fund I, L.P. | J88: =C52 -> 44540 | K88: =D52 -> -2.8053125 | L88: =E52 -> 0 | M88: =F52 -> 0 | N88: =SUM(K88:M88) -> -2.8053125
I89: =B53 -> Acies Investments Fund I, L.P. | J89: =C53 -> 44602 | K89: =D53 -> -3.4075 | L89: =E53 -> 0 | M89: =F53 -> 0 | N89: =SUM(K89:M89) -> -3.4075
I90: =B54 -> Acies Investments Fund I, L.P. | J90: =C54 -> 44683 | K90: =D54 -> -1.025775 | L90: =E54 -> 0 | M90: =F54 -> 0 | N90: =SUM(K90:M90) -> -1.025775
I91: =B55 -> Acies Investments Fund I, L.P. | J91: =C55 -> 44707 | K91: =D55 -> -3.388275 | L91: =E55 -> 0 | M91: =F55 -> 0 | N91: =SUM(K91:M91) -> -3.388275
I92: =B56 -> Acies Investments Fund I, L.P. | J92: =C56 -> 44875 | K92: =D56 -> -3.388275 | L92: =E56 -> 0 | M92: =F56 -> 0 | N92: =SUM(K92:M92) -> -3.388275
I93: Acies Investments Fund I, L.P. | J93: =$C$4 -> 45322 | M93: =F61 -> 12.310425 | N93: =SUM(K93:M93) -> 12.310425
I95: XIRR | J95: =XIRR(N88:N93,J88:J93) -> -0.071990828 | L95: Contributions | M95: =-SUM(K88:K93)='S | 01 '!K45 -> TRUE
I96: TVPI | J96: =SUM(L88:M93)/-SUM(K88:K93) -> 0.87836634 | L96: Distributions | M96: =-SUM(L88:L98)=-'S | 01 '!M45 -> TRUE
I97: RPI | J97: =SUM(M88:M93)/-SUM(K88:K93) -> 0.87836634 | L97: Residual Value | M97: =M93='S | 01 '!N45 -> TRUE
I98: DPI | J98: =SUM(L88:L93)/-SUM(K88:K93) -> 0

Sheet 4.All
B2: IRR - All Investments (Equity, Debt, Funds) | H2: TEST | I2: =COUNTA(B8:B107)=COUNTA('CF (Equity, Debt)'!C4:C42)+COUNTA('CF (Equity, Debt)'!C53:C56)+COUNTA('CF (Funds)'!B3:B51) -> FALSE
B4: Date of NAV | C4: =D!D2 -> 45322
B6: (in USD, Mn)
B7: Investment | C7: Payment date | D7: Contribution | E7: Distributions | F7: Remaining Value | G7: Combined | H7: Type | J7: Invested | K7: Remaining Commitment | L7: Distributions | M7: Residual Value | N7: IRR | O7: TVPI | P7: RPI | Q7: DPI
B8: ='CF (Equity, Debt)'!C4 -> Jollychic Holding Limited | C8: ='CF (Equity, Debt)'!D4 -> 43470 | D8: ='CF (Equity, Debt)'!E4 -> -30 | G8: =SUM(D8:F8) -> -30 | H8: Equity
B9: ='CF (Equity, Debt)'!C5 -> Jollychic Holding Limited | C9: ='CF (Equity, Debt)'!D5 -> 43724 | D9: ='CF (Equity, Debt)'!E5 -> -20 | G9: =SUM(D9:F9) -> -20 | H9: Equity | J9: =-SUM(D8:D138) -> 2267.9327 | L9: =SUM(E8:E138) -> 1254.9285 | M9: =SUM(F8:F138) -> 955.14756 | N9: =XIRR(G8:G137,C8:C137) -> -0.012957468 | O9: =(L9+M9)/J9 -> 0.97448924 | P9: =M9/J9 -> 0.4211534 | Q9: =L9/J9 -> 0.55333584
B10: ='CF (Equity, Debt)'!C6 -> Jollychic Holding Limited | C10: ='CF (Equity, Debt)'!D6 -> 43724 | D10: ='CF (Equity, Debt)'!E6 -> -15 | G10: =SUM(D10:F10) -> -15 | H10: Equity
B11: ='CF (Equity, Debt)'!C7 -> Mena Mobile Inc | C11: ='CF (Equity, Debt)'!D7 -> 43563 | D11: ='CF (Equity, Debt)'!E7 -> -8 | G11: =SUM(D11:F11) -> -8 | H11: Equity | J11: =ROUND(J9,2)=ROUND('S | 01 '!K48,2) -> TRUE | L11: =ROUND(L9,3)=ROUND('S | 01 '!M48,3) -> TRUE | M11: =ROUND(M9,3)=ROUND('S | 01 '!N48,3) -> TRUE
B12: ='CF (Equity, Debt)'!C8 -> Flyr Inc | C12: ='CF (Equity, Debt)'!D8 -> 43570 | D12: ='CF (Equity, Debt)'!E8 -> -4.9999981 | G12: =SUM(D12:F12) -> -4.9999981 | H12: Equity
B13: ='CF (Equity, Debt)'!C9 -> Flyr Inc | C13: ='CF (Equity, Debt)'!D9 -> 43915 | D13: ='CF (Equity, Debt)'!E9 -> -5.0000019 | G13: =SUM(D13:F13) -> -5.0000019 | H13: Equity
B14: ='CF (Equity, Debt)'!C10 -> Esyasoft Holding | C14: ='CF (Equity, Debt)'!D10 -> 43870 | D14: ='CF (Equity, Debt)'!E10 -> -2.5 | G14: =SUM(D14:F14) -> -2.5 | H14: Equity
B15: ='CF (Equity, Debt)'!C11 -> Beyond Limits | C15: ='CF (Equity, Debt)'!D11 -> 43879 | D15: ='CF (Equity, Debt)'!E11 -> -20 | G15: =SUM(D15:F15) -> -20 | H15: Equity
B16: ='CF (Equity, Debt)'!C12 -> Beyond Limits | C16: ='CF (Equity, Debt)'!D12 -> 43921 | D16: ='CF (Equity, Debt)'!E12 -> -30 | G16: =SUM(D16:F16) -> -30 | H16: Equity
B17: ='CF (Equity, Debt)'!C13 -> Beyond Limits | C17: ='CF (Equity, Debt)'!D13 -> 43989 | D17: ='CF (Equity, Debt)'!E13 -> -30 | G17: =SUM(D17:F17) -> -30 | H17: Equity
B18: ='CF (Equity, Debt)'!C14 -> Beyond Limits | C18: ='CF (Equity, Debt)'!D14 -> 44103 | D18: ='CF (Equity, Debt)'!E14 -> -10 | G18: =SUM(D18:F18) -> -10 | H18: Equity
B19: ='CF (Equity, Debt)'!C15 -> ONT plc | C19: ='CF (Equity, Debt)'!D15 -> 43968 | D19: ='CF (Equity, Debt)'!E15 -> -50 | G19: =SUM(D19:F19) -> -50 | H19: Equity
B20: ='CF (Equity, Debt)'!C16 -> ONT plc | C20: ='CF (Equity, Debt)'!D16 -> 44006 | D20: ='CF (Equity, Debt)'!E16 -> -27.268351 | G20: =SUM(D20:F20) -> -27.268351 | H20: Equity
B21: ='CF (Equity, Debt)'!C17 -> ONT plc | C21: ='CF (Equity, Debt)'!D17 -> 43837 | D21: ='CF (Equity, Debt)'!E17 -> -18.109441 | G21: =SUM(D21:F21) -> -18.109441 | H21: Equity
B22: ='CF (Equity, Debt)'!C18 -> ONT plc | C22: ='CF (Equity, Debt)'!D18 -> 43990 | D22: ='CF (Equity, Debt)'!E18 -> -34.851687 | G22: =SUM(D22:F22) -> -34.851687 | H22: Equity
B23: ='CF (Equity, Debt)'!C19 -> ONT plc | C23: ='CF (Equity, Debt)'!D19 -> 44315 | D23: ='CF (Equity, Debt)'!E19 -> -11.24078 | G23: =SUM(D23:F23) -> -11.24078 | H23: Equity
... B31: ='CF (Equity, Debt)'!C27 -> DriveNets | C31: ='CF (Equity, Debt)'!D27 -> 44680 | D31: ='CF (Equity, Debt)'!E27 -> -100 | G31: =SUM(D31:F31) -> -100 | H31: Equity
B32: ='CF (Equity, Debt)'!C28 -> Esyasoft Holding | C32: ='CF (Equity, Debt)'!D28 -> 44691 | D32: ='CF (Equity, Debt)'!E28 -> 0 | E32: 5 | G32: =SUM(D32:F32) -> 5 | H32: Equity
B33: ='CF (Equity, Debt)'!C29 -> vTv Therapeutics Inc. | C33: ='CF (Equity, Debt)'!D29 -> 44712 | D33: ='CF (Equity, Debt)'!E29 -> -12.5 | G33: =SUM(D33:F33) -> -12.5 | H33: Equity
B34: ='CF (Equity, Debt)'!C30 -> Honor Device Co Ltd | C34: ='CF (Equity, Debt)'!D30 -> 44769 | D34: ='CF (Equity, Debt)'!E30 -> -600 | G34: =SUM(D34:F34) -> -600 | H34: Equity
B35: ='CF (Equity, Debt)'!C31 -> Honor Device Co Ltd | C35: ='CF (Equity, Debt)'!D31 -> 44849 | D35: ='CF (Equity, Debt)'!E31 -> -200 | G35: =SUM(D35:F35) -> -200 | H35: Equity
B36: ='CF (Equity, Debt)'!C32 -> Applied AI Corporation Limited | C36: ='CF (Equity, Debt)'!D32 -> 44861 | D36: ='CF (Equity, Debt)'!E32 -> -4.75 | G36: =SUM(D36:F36) -> -4.75 | H36: Equity
B37: ='CF (Equity, Debt)'!C33 -> eSpace | C37: ='CF (Equity, Debt)'!D33 -> 44892 | D37: ='CF (Equity, Debt)'!E33 -> -15 | G37: =SUM(D37:F37) -> -15 | H37: Equity
B38: ='CF (Equity, Debt)'!C34 -> vTv Therapeutics Inc. | C38: ='CF (Equity, Debt)'!D34 -> 44985 | D38: ='CF (Equity, Debt)'!E34 -> -12.03125 | G38: =SUM(D38:F38) -> -12.03125 | H38: Equity
B39: ='CF (Equity, Debt)'!C35 -> Tools for Humanity Corporation | C39: ='CF (Equity, Debt)'!D35 -> 45075 | D39: ='CF (Equity, Debt)'!E35 -> -14.999999 | G39: =SUM(D39:F39) -> -14.999999 | H39: Equity
B40: ='CF (Equity, Debt)'!C36 -> WLD Tokens | C40: ='CF (Equity, Debt)'!D36 -> 45075 | D40: ='CF (Equity, Debt)'!E36 -> -0.005875 | G40: =SUM(D40:F40) -> -0.005875 | H40: Equity
B41: ='CF (Equity, Debt)'!C37 -> WLD Tokens | C41: ='CF (Equity, Debt)'!D37 -> 45114 | D41: ='CF (Equity, Debt)'!E37 -> -0.001 | G41: =SUM(D41:F41) -> -0.001 | H41: Equity
B42: ='CF (Equity, Debt)'!C38 -> Applied AI Corporation Limited | C42: ='CF (Equity, Debt)'!D38 -> 45121 | D42: ='CF (Equity, Debt)'!E38 -> -2.75 | G42: =SUM(D42:F42) -> -2.75 | H42: Equity
B43: ='CF (Equity, Debt)'!C39 -> Instadeep Limited | C43: ='CF (Equity, Debt)'!D39 -> 45138 | D43: ='CF (Equity, Debt)'!E39 -> 0 | E43: ='CF (Equity, Debt)'!F39 -> 7.8207761 | G43: =SUM(D43:F43) -> 7.8207761 | H43: Equity
B44: ='CF (Equity, Debt)'!C40 -> Jysan Technologies | C44: ='CF (Equity, Debt)'!D40 -> 45149 | D44: ='CF (Equity, Debt)'!E40 -> 0 | E44: ='CF (Equity, Debt)'!F40 -> 24.5 | G44: =SUM(D44:F44) -> 24.5 | H44: Equity
B45: ='CF (Equity, Debt)'!C41 -> Endless Studios LLC | C45: ='CF (Equity, Debt)'!D41 -> 45167 | D45: ='CF (Equity, Debt)'!E41 -> -5 | E45: ='CF (Equity, Debt)'!F41 -> 0 | G45: =SUM(D45:F45) -> -5 | H45: Equity
B46: ='CF (Equity, Debt)'!C42 -> E-line Ventures LLC | C46: ='CF (Equity, Debt)'!D42 -> 45167 | D46: ='CF (Equity, Debt)'!E42 -> -6 | E46: ='CF (Equity, Debt)'!F42 -> 0 | G46: =SUM(D46:F46) -> -6 | H46: Equity
B47: ='CF (Equity, Debt)'!C43 -> Honor Device Co Ltd | C47: ='CF (Equity, Debt)'!D43 -> 45224 | D47: ='CF (Equity, Debt)'!E43 -> 0 | E47: ='CF (Equity, Debt)'!F43 -> 2.8 | G47: =SUM(D47:F47) -> 2.8 | H47: Equity
B48: ='CF (Equity, Debt)'!C44 -> Honor Device Co Ltd | C48: ='CF (Equity, Debt)'!D44 -> 45224 | D48: ='CF (Equity, Debt)'!E44 -> 0 | E48: ='CF (Equity, Debt)'!F44 -> 800 | G48: =SUM(D48:F48) -> 800 | H48: Equity
B49: ='CF (Equity, Debt)'!C45 -> X-fusion | C49: ='CF (Equity, Debt)'!D45 -> 45224 | D49: ='CF (Equity, Debt)'!E45 -> 0 | E49: ='CF (Equity, Debt)'!F45 -> 403 | G49: =SUM(D49:F49) -> 403 | H49: Equity
B50: ='CF (Equity, Debt)'!C46 -> Instadeep Limited | C50: ='CF (Equity, Debt)'!D46 -> 45224 | D50: ='CF (Equity, Debt)'!E46 -> 0 | E50: ='CF (Equity, Debt)'!F46 -> 0.12141643 | G50: =SUM(D50:F50) -> 0.12141643 | H50: Equity
B51: ='CF (Equity, Debt)'!C47 -> Applied AI Corporation Limited | C51: ='CF (Equity, Debt)'!D47 -> 45295 | D51: ='CF (Equity, Debt)'!E47 -> -4 | E51: ='CF (Equity, Debt)'!F47 -> 0 | G51: =SUM(D51:F51) -> -4 | H51: Equity
B52: ='CF (Equity, Debt)'!C48 -> School Hack (AIREV Holding Limited) | C52: ='CF (Equity, Debt)'!D48 -> 45322 | D52: ='CF (Equity, Debt)'!E48 -> -2.75 | E52: ='CF (Equity, Debt)'!F48 -> 0 | G52: =SUM(D52:F52) -> -2.75 | H52: Equity
B54: ='CF (Equity, Debt)'!C53 -> Glass Earth Holdings LLC | C54: ='CF (Equity, Debt)'!D53 -> 43635 | D54: ='CF (Equity, Debt)'!E53 -> -8 | G54: =SUM(D54:F54) -> -8 | H54: Debt
B55: ='CF (Equity, Debt)'!C54 -> Mena Mobile Inc (Debt) | C55: ='CF (Equity, Debt)'!D54 -> 44293 | D55: ='CF (Equity, Debt)'!E54 -> -2.353982 | G55: =SUM(D55:F55) -> -2.353982 | H55: Debt
B56: ='CF (Equity, Debt)'!C55 -> Esyasoft Holding (Debt) | C56: ='CF (Equity, Debt)'!D55 -> 44384 | D56: ='CF (Equity, Debt)'!E55 -> -0.411765 | G56: =SUM(D56:F56) -> -0.411765 | H56: Debt
B57: ='CF (Equity, Debt)'!C56 -> Esyasoft Holding (Debt) | C57: ='CF (Equity, Debt)'!D56 -> 44902 | D57: ='CF (Equity, Debt)'!E56 -> 0 | E57: ='CF (Equity, Debt)'!F56 -> 0.47078465 | G57: =SUM(D57:F57) -> 0.47078465 | H57: Debt
B59: ='CF (Funds)'!B3 -> Sinovation Disrupt Fund, L.P. | C59: ='CF (Funds)'!C3 -> 44153 | D59: ='CF (Funds)'!D3 -> -10.5 | E59: ='CF (Funds)'!E3 -> 0 | G59: =SUM(D59:F59) -> -10.5 | H59: Fund
B60: ='CF (Funds)'!B4 -> Sinovation Disrupt Fund, L.P. | C60: ='CF (Funds)'!C4 -> 44238 | D60: ='CF (Funds)'!D4 -> 4.214027 | E60: ='CF (Funds)'!E4 -> 0 | G60: =SUM(D60:F60) -> 4.214027 | H60: Fund
B61: ='CF (Funds)'!B5 -> Sinovation Disrupt Fund, L.P. | C61: ='CF (Funds)'!C5 -> 44238 | D61: ='CF (Funds)'!D5 -> 0 | E61: ='CF (Funds)'!E5 -> 0.05044835 | G61: =SUM(D61:F61) -> 0.05044835 | H61: Fund
B62: ='CF (Funds)'!B6 -> Sinovation Disrupt Fund, L.P. | C62: ='CF (Funds)'!C6 -> 44285 | D62: ='CF (Funds)'!D6 -> -6.433746 | E62: ='CF (Funds)'!E6 -> 0 | G62: =SUM(D62:F62) -> -6.433746 | H62: Fund
B63: ='CF (Funds)'!B7 -> Sinovation Disrupt Fund, L.P. | C63: ='CF (Funds)'!C7 -> 44269 | D63: ='CF (Funds)'!D7 -> 1.1352074 | E63: ='CF (Funds)'!E7 -> 0 | G63: =SUM(D63:F63) -> 1.1352074 | H63: Fund
B64: ='CF (Funds)'!B8 -> Sinovation Disrupt Fund, L.P. | C64: ='CF (Funds)'!C8 -> 44269 | D64: ='CF (Funds)'!D8 -> 0 | E64: ='CF (Funds)'!E8 -> 0.0259 | G64: =SUM(D64:F64) -> 0.0259 | H64: Fund
B65: ='CF (Funds)'!B9 -> Sinovation Disrupt Fund, L.P. | C65: ='CF (Funds)'!C9 -> 44483 | D65: ='CF (Funds)'!D9 -> -7.567138 | E65: ='CF (Funds)'!E9 -> 0 | G65: =SUM(D65:F65) -> -7.567138 | H65: Fund
B66: ='CF (Funds)'!B10 -> Sinovation Disrupt Fund, L.P. | C66: ='CF (Funds)'!C10 -> 44554 | D66: ='CF (Funds)'!D10 -> -7.385016 | E66: ='CF (Funds)'!E10 -> 0 | G66: =SUM(D66:F66) -> -7.385016 | H66: Fund
B67: ='CF (Funds)'!B11 -> Sinovation Disrupt Fund, L.P. | C67: ='CF (Funds)'!C11 -> 44554 | D67: ='CF (Funds)'!D11 -> 4.0733456 | E67: ='CF (Funds)'!E11 -> 0 | G67: =SUM(D67:F67) -> 4.0733456 | H67: Fund
B68: ='CF (Funds)'!B12 -> Sinovation Disrupt Fund, L.P. | C68: ='CF (Funds)'!C12 -> 44554 | D68: ='CF (Funds)'!D12 -> 0 | E68: ='CF (Funds)'!E12 -> 0.139694 | G68: =SUM(D68:F68) -> 0.139694 | H68: Fund
B69: ='CF (Funds)'!B13 -> Sinovation Disrupt Fund, L.P. | C69: ='CF (Funds)'!C13 -> 44703 | D69: ='CF (Funds)'!D13 -> 5.673074 | E69: ='CF (Funds)'!E13 -> 0 | G69: =SUM(D69:F69) -> 5.673074 | H69: Fund
B70: ='CF (Funds)'!B14 -> Sinovation Disrupt Fund, L.P. | C70: ='CF (Funds)'!C14 -> 44703 | D70: ='CF (Funds)'!D14 -> 0 | E70: ='CF (Funds)'!E14 -> 0.227786 | G70: =SUM(D70:F70) -> 0.227786 | H70: Fund
... B107: ='CF (Funds)'!B51 -> Acies Investments Fund I, L.P. | C107: ='CF (Funds)'!C51 -> 44875 | D107: ='CF (Funds)'!D51 -> -3.388275 | E107: ='CF (Funds)'!E51 -> 0 | G107: =SUM(D107:F107) -> -3.388275 | H107: Fund
B108: Jollychic Holding Limited | C108: =$C$4 -> 45322 | F108: =VLOOKUP(B108,NAV!$B$9:$E$45,4,0) -> 0 | G108: =SUM(D108:F108) -> 0 | H108: NAV
B109: Mena Mobile Inc | C109: =$C$4 -> 45322 | F109: =VLOOKUP(B109,NAV!$B$9:$E$45,4,0) -> 0 | G109: =SUM(D109:F109) -> 0 | H109: NAV
B110: Flyr Inc | C110: =$C$4 -> 45322 | F110: =VLOOKUP(B110,NAV!$B$9:$E$45,4,0) -> 78.08223 | G110: =SUM(D110:F110) -> 78.08223 | H110: NAV
B111: Esyasoft Holding | C111: =$C$4 -> 45322 | F111: =VLOOKUP(B111,NAV!$B$9:$E$45,4,0) -> 0 | G111: =SUM(D111:F111) -> 0 | H111: NAV
B112: Beyond Limits | C112: =$C$4 -> 45322 | F112: =VLOOKUP(B112,NAV!$B$9:$E$45,4,0) -> 91.00154 | G112: =SUM(D112:F112) -> 91.00154 | H112: NAV
B113: ONT plc | C113: =$C$4 -> 45322 | F113: =VLOOKUP(B113,NAV!$B$9:$E$45,4,0) -> 90.139175 | G113: =SUM(D113:F113) -> 90.139175 | H113: NAV
B114: Heygears | C114: =$C$4 -> 45322 | F114: =VLOOKUP(B114,NAV!$B$9:$E$45,4,0) -> 148.04984 | G114: =SUM(D114:F114) -> 148.04984 | H114: NAV
B115: Jysan Technologies | C115: =$C$4 -> 45322 | F115: =VLOOKUP(B115,NAV!$B$9:$E$45,4,0) -> 0 | G115: =SUM(D115:F115) -> 0 | H115: NAV
B116: Cerebras Systems Inc | C116: =$C$4 -> 45322 | F116: =VLOOKUP(B116,NAV!$B$9:$E$45,4,0) -> 39.999983 | G116: =SUM(D116:F116) -> 39.999983 | H116: NAV
B117: Endless Studios LLC | C117: =$C$4 -> 45322 | F117: =VLOOKUP(B117,NAV!$B$9:$E$45,4,0) -> 8 | G117: =SUM(D117:F117) -> 8 | H117: NAV
B118: Instadeep Limited | C118: =$C$4 -> 45322 | F118: =VLOOKUP(B118,NAV!$B$9:$E$45,4,0) -> 0 | G118: =SUM(D118:F118) -> 0 | H118: NAV
B119: X-fusion | C119: =$C$4 -> 45322 | F119: =VLOOKUP(B119,NAV!$B$9:$E$45,4,0) -> 0 | G119: =SUM(D119:F119) -> 0 | H119: NAV
... B137: Acies Investments Fund I, L.P. | C137: =$C$4 -> 45322 | F137: =VLOOKUP(B137,NAV!$B$9:$E$45,4,0) -> 12.310425 | G137: =SUM(D137:F137) -> 12.310425 | H137: NAV

Sheet 4. Mozn-IRR
B2: IRR - Mozn Investments | G2: TEST | H2: =H5=H4 -> TRUE
B4: Date of NAV | E4: =D!D2 -> 45322 | H4: =COUNTIF('CF (Equity, Debt)'!$B$4:$B$66,MID('CF (Equity, Debt)'!$B$4:$B$66,1,4)) -> 35
H5: =COUNTIFS('CF (Equity, Debt)'!B4:B56,"Mozn")+COUNTIFS('CF (Funds)'!A3:A51,"Mozn") -> 35 | K5: =K9='S | 02'!L31 -> TRUE | M5: =M9='S | 02'!M31 -> TRUE | N5: =N9='S | 02'!N31 -> TRUE
K7: Invested | L7: Remaining Commitment | M7: Distributions | N7: Residual Value | O7: IRR | P7: TVPI | Q7: RPI | R7: DPI
K9: =-SUM(F12:F73) -> 1004.5175 | M9: =SUM(G12:G73) -> 440.91298 | N9: =SUM(H12:H73) -> 526.41089 | O9: =XIRR(I12:I73,E12:E73) -> -0.014740654 | P9: =(M9+N9)/K9 -> 0.9629736 | Q9: =N9/K9 -> 0.5240435 | R9: =M9/K9 -> 0.43893009
B10: (in USD, Mn)
B11: Investment | C11: Type | D11: Entity | E11: Payment date | F11: Contribution | G11: Distributions | H11: Remaining Value | I11: Combined
B12: ='CF (Equity, Debt)'!C4 -> Jollychic Holding Limited | C12: =VLOOKUP(B12,'S | 02'!$C$6:$J$41,2,0) -> Direct Investment | D12: =VLOOKUP(B12,'S | 02'!$C$6:$J$41,5,0) -> Mozn | E12: ='CF (Equity, Debt)'!D4 -> 43470 | F12: ='CF (Equity, Debt)'!E4 -> -30 | I12: =SUM(F12:H12) -> -30 | K12: Invested | L12: =-SUM(F12:F85) -> 1004.5175 | M12: ='S | 02'!L31=L12 -> TRUE
B13: ='CF (Equity, Debt)'!C5 -> Jollychic Holding Limited | C13: =VLOOKUP(B13,'S | 02'!$C$6:$J$41,2,0) -> Direct Investment | D13: =VLOOKUP(B13,'S | 02'!$C$6:$J$41,5,0) -> Mozn | E13: ='CF (Equity, Debt)'!D5 -> 43724 | F13: ='CF (Equity, Debt)'!E5 -> -20 | I13: =SUM(F13:H13) -> -20 | K13: NAV | L13: =SUM(H12:H85) -> 526.41089
B14: ='CF (Equity, Debt)'!C6 -> Jollychic Holding Limited | C14: =VLOOKUP(B14,'S | 02'!$C$6:$J$41,2,0) -> Direct Investment | D14: =VLOOKUP(B14,'S | 02'!$C$6:$J$41,5,0) -> Mozn | E14: ='CF (Equity, Debt)'!D6 -> 43724 | F14: ='CF (Equity, Debt)'!E6 -> -15 | I14: =SUM(F14:H14) -> -15 | K14: Distributions | L14: =SUM(G12:G85) -> 440.91298
B15: ='CF (Equity, Debt)'!C7 -> Mena Mobile Inc | C15: =VLOOKUP(B15,'S | 02'!$C$6:$J$41,2,0) -> Direct Investment | D15: =VLOOKUP(B15,'S | 02'!$C$6:$J$41,5,0) -> Mozn | E15: ='CF (Equity, Debt)'!D7 -> 43563 | F15: ='CF (Equity, Debt)'!E7 -> -8 | I15: =SUM(F15:H15) -> -8 | K15: Total Gain | L15: =L14+L13-L12 -> -37.193673
B16: ='CF (Equity, Debt)'!C8 -> Flyr Inc | C16: =VLOOKUP(B16,'S | 02'!$C$6:$J$41,2,0) -> Direct Investment | D16: =VLOOKUP(B16,'S | 02'!$C$6:$J$41,5,0) -> Mozn | E16: ='CF (Equity, Debt)'!D8 -> 43570 | F16: ='CF (Equity, Debt)'!E8 -> -4.9999981 | I16: =SUM(F16:H16) -> -4.9999981 | K16: IRR | L16: =O9 -> -0.014740654
B17: ='CF (Equity, Debt)'!C9 -> Flyr Inc | C17: =VLOOKUP(B17,'S | 02'!$C$6:$J$41,2,0) -> Direct Investment | D17: =VLOOKUP(B17,'S | 02'!$C$6:$J$41,5,0) -> Mozn | E17: ='CF (Equity, Debt)'!D9 -> 43915 | F17: ='CF (Equity, Debt)'!E9 -> -5.0000019 | I17: =SUM(F17:H17) -> -5.0000019
B18: ='CF (Equity, Debt)'!C10 -> Esyasoft Holding | C18: =VLOOKUP(B18,'S | 02'!$C$6:$J$41,2,0) -> Direct Investment | D18: =VLOOKUP(B18,'S | 02'!$C$6:$J$41,5,0) -> Mozn | E18: ='CF (Equity, Debt)'!D10 -> 43870 | F18: ='CF (Equity, Debt)'!E10 -> -2.5 | I18: =SUM(F18:H18) -> -2.5
B19: ='CF (Equity, Debt)'!C11 -> Beyond Limits | C19: =VLOOKUP(B19,'S | 02'!$C$6:$J$41,2,0) -> Direct Investment | D19: =VLOOKUP(B19,'S | 02'!$C$6:$J$41,5,0) -> Mozn | E19: ='CF (Equity, Debt)'!D11 -> 43879 | F19: ='CF (Equity, Debt)'!E11 -> -20 | I19: =SUM(F19:H19) -> -20
B20: ='CF (Equity, Debt)'!C12 -> Beyond Limits | C20: =VLOOKUP(B20,'S | 02'!$C$6:$J$41,2,0) -> Direct Investment | D20: =VLOOKUP(B20,'S | 02'!$C$6:$J$41,5,0) -> Mozn | E20: ='CF (Equity, Debt)'!D12 -> 43921 | F20: ='CF (Equity, Debt)'!E12 -> -30 | I20: =SUM(F20:H20) -> -30
B21: ='CF (Equity, Debt)'!C13 -> Beyond Limits | C21: =VLOOKUP(B21,'S | 02'!$C$6:$J$41,2,0) -> Direct Investment | D21: =VLOOKUP(B21,'S | 02'!$C$6:$J$41,5,0) -> Mozn | E21: ='CF (Equity, Debt)'!D13 -> 43989 | F21: ='CF (Equity, Debt)'!E13 -> -30 | I21: =SUM(F21:H21) -> -30
B22: ='CF (Equity, Debt)'!C14 -> Beyond Limits | C22: =VLOOKUP(B22,'S | 02'!$C$6:$J$41,2,0) -> Direct Investment | D22: =VLOOKUP(B22,'S | 02'!$C$6:$J$41,5,0) -> Mozn | E22: ='CF (Equity, Debt)'!D14 -> 44103 | F22: ='CF (Equity, Debt)'!E14 -> -10 | I22: =SUM(F22:H22) -> -10
B23: ='CF (Equity, Debt)'!C15 -> ONT plc | C23: =VLOOKUP(B23,'S | 02'!$C$6:$J$41,2,0) -> Direct Investment | D23: =VLOOKUP(B23,'S | 02'!$C$6:$J$41,5,0) -> Mozn | E23: ='CF (Equity, Debt)'!D15 -> 43968 | F23: ='CF (Equity, Debt)'!E15 -> -50 | I23: =SUM(F23:H23) -> -50
B24: ='CF (Equity, Debt)'!C16 -> ONT plc | C24: =VLOOKUP(B24,'S | 02'!$C$6:$J$41,2,0) -> Direct Investment | D24: =VLOOKUP(B24,'S | 02'!$C$6:$J$41,5,0) -> Mozn | E24: ='CF (Equity, Debt)'!D16 -> 44006 | F24: ='CF (Equity, Debt)'!E16 -> -27.268351 | I24: =SUM(F24:H24) -> -27.268351
B25: ='CF (Equity, Debt)'!C17 -> ONT plc | C25: =VLOOKUP(B25,'S | 02'!$C$6:$J$41,2,0) -> Direct Investment | D25: =VLOOKUP(B25,'S | 02'!$C$6:$J$41,5,0) -> Mozn | E25: ='CF (Equity, Debt)'!D17 -> 43837 | F25: ='CF (Equity, Debt)'!E17 -> -18.109441 | I25: =SUM(F25:H25) -> -18.109441
B26: ='CF (Equity, Debt)'!C18 -> ONT plc | C26: =VLOOKUP(B26,'S | 02'!$C$6:$J$41,2,0) -> Direct Investment | D26: =VLOOKUP(B26,'S | 02'!$C$6:$J$41,5,0) -> Mozn | E26: ='CF (Equity, Debt)'!D18 -> 43990 | F26: ='CF (Equity, Debt)'!E18 -> -34.851687 | I26: =SUM(F26:H26) -> -34.851687
B27: ='CF (Equity, Debt)'!C19 -> ONT plc | C27: =VLOOKUP(B27,'S | 02'!$C$6:$J$41,2,0) -> Direct Investment | D27: =VLOOKUP(B27,'S | 02'!$C$6:$J$41,5,0) -> Mozn | E27: ='CF (Equity, Debt)'!D19 -> 44315 | F27: ='CF (Equity, Debt)'!E19 -> -11.24078 | I27: =SUM(F27:H27) -> -11.24078
B28: ='CF (Equity, Debt)'!C20 -> Heygears | C28: =VLOOKUP(B28,'S | 02'!$C$6:$J$41,2,0) -> Direct Investment | D28: =VLOOKUP(B28,'S | 02'!$C$6:$J$41,5,0) -> Mozn | E28: ='CF (Equity, Debt)'!D20 -> 44166 | F28: ='CF (Equity, Debt)'!E20 -> -60 | I28: =SUM(F28:H28) -> -60
... B33: ='CF (Equity, Debt)'!C25 -> X-fusion | C33: =VLOOKUP(B33,'S | 02'!$C$6:$J$41,2,0) -> Direct Investment | D33: =VLOOKUP(B33,'S | 02'!$C$6:$J$41,5,0) -> Mozn 2 | E33: ='CF (Equity, Debt)'!D25 -> 44574 | F33: ='CF (Equity, Debt)'!E25 -> -493.50096 | I33: =SUM(F33:H33) -> -493.50096
B34: ='CF (Equity, Debt)'!C28 -> Esyasoft Holding | C34: =VLOOKUP(B34,'S | 02'!$C$6:$J$41,2,0) -> Direct Investment | D34: =VLOOKUP(B34,'S | 02'!$C$6:$J$41,5,0) -> Mozn | E34: ='CF (Equity, Debt)'!D28 -> 44691 | F34: ='CF (Equity, Debt)'!E28 -> 0 | G34: 5 | I34: =SUM(F34:H34) -> 5
B35: ='CF (Equity, Debt)'!C32 -> Applied AI Corporation Limited | C35: =VLOOKUP(B35,'S | 02'!$C$6:$J$41,2,0) -> Direct Investment | D35: =VLOOKUP(B35,'S | 02'!$C$6:$J$41,5,0) -> Mozn | E35: ='CF (Equity, Debt)'!D32 -> 44861 | F35: ='CF (Equity, Debt)'!E32 -> -4.75 | I35: =SUM(F35:H35) -> -4.75
B36: ='CF (Equity, Debt)'!C33 -> eSpace | C36: =VLOOKUP(B36,'S | 02'!$C$6:$J$41,2,0) -> Direct Investment | D36: =VLOOKUP(B36,'S | 02'!$C$6:$J$41,5,0) -> Mozn 4 | E36: ='CF (Equity, Debt)'!D33 -> 44892 | F36: ='CF (Equity, Debt)'!E33 -> -15 | I36: =SUM(F36:H36) -> -15
B37: ='CF (Equity, Debt)'!C35 -> Tools for Humanity Corporation | C37: =VLOOKUP(B37,'S | 02'!$C$6:$J$41,2,0) -> Direct Investment | D37: =VLOOKUP(B37,'S | 02'!$C$6:$J$41,5,0) -> Mozn | E37: ='CF (Equity, Debt)'!D35 -> 45075 | F37: ='CF (Equity, Debt)'!E35 -> -14.999999 | I37: =SUM(F37:H37) -> -14.999999
B38: ='CF (Equity, Debt)'!C36 -> WLD Tokens | C38: =VLOOKUP(B38,'S | 02'!$C$6:$J$41,2,0) -> Direct Investment | D38: =VLOOKUP(B38,'S | 02'!$C$6:$J$41,5,0) -> Mozn | E38: ='CF (Equity, Debt)'!D36 -> 45075 | F38: ='CF (Equity, Debt)'!E36 -> -0.005875 | I38: =SUM(F38:H38) -> -0.005875
B39: ='CF (Equity, Debt)'!C37 -> WLD Tokens | C39: =VLOOKUP(B39,'S | 02'!$C$6:$J$41,2,0) -> Direct Investment | D39: =VLOOKUP(B39,'S | 02'!$C$6:$J$41,5,0) -> Mozn | E39: ='CF (Equity, Debt)'!D37 -> 45114 | F39: ='CF (Equity, Debt)'!E37 -> -0.001 | I39: =SUM(F39:H39) -> -0.001
B40: ='CF (Equity, Debt)'!C38 -> Applied AI Corporation Limited | C40: =VLOOKUP(B40,'S | 02'!$C$6:$J$41,2,0) -> Direct Investment | D40: =VLOOKUP(B40,'S | 02'!$C$6:$J$41,5,0) -> Mozn | E40: ='CF (Equity, Debt)'!D38 -> 45121 | F40: ='CF (Equity, Debt)'!E38 -> -2.75 | I40: =SUM(F40:H40) -> -2.75
B41: ='CF (Equity, Debt)'!C39 -> Instadeep Limited | C41: =VLOOKUP(B41,'S | 02'!$C$6:$J$41,2,0) -> Direct Investment | D41: =VLOOKUP(B41,'S | 02'!$C$6:$J$41,5,0) -> Mozn | E41: ='CF (Equity, Debt)'!D39 -> 45138 | F41: ='CF (Equity, Debt)'!E39 -> 0 | G41: ='CF (Equity, Debt)'!F39 -> 7.8207761 | I41: =SUM(F41:H41) -> 7.8207761
B42: ='CF (Equity, Debt)'!C40 -> Jysan Technologies | C42: =VLOOKUP(B42,'S | 02'!$C$6:$J$41,2,0) -> Direct Investment | D42: =VLOOKUP(B42,'S | 02'!$C$6:$J$41,5,0) -> Mozn 1 | E42: ='CF (Equity, Debt)'!D40 -> 45149 | F42: ='CF (Equity, Debt)'!E40 -> 0 | G42: ='CF (Equity, Debt)'!F40 -> 24.5 | I42: =SUM(F42:H42) -> 24.5
B43: ='CF (Equity, Debt)'!C41 -> Endless Studios LLC | C43: =VLOOKUP(B43,'S | 02'!$C$6:$J$41,2,0) -> Direct Investment | D43: =VLOOKUP(B43,'S | 02'!$C$6:$J$41,5,0) -> Mozn | E43: ='CF (Equity, Debt)'!D41 -> 45167 | F43: ='CF (Equity, Debt)'!E41 -> -5 | G43: ='CF (Equity, Debt)'!F41 -> 0 | I43: =SUM(F43:H43) -> -5
B44: ='CF (Equity, Debt)'!C42 -> E-line Ventures LLC | C44: =VLOOKUP(B44,'S | 02'!$C$6:$J$41,2,0) -> Direct Investment | D44: =VLOOKUP(B44,'S | 02'!$C$6:$J$41,5,0) -> Mozn | E44: ='CF (Equity, Debt)'!D42 -> 45167 | F44: ='CF (Equity, Debt)'!E42 -> -6 | G44: ='CF (Equity, Debt)'!F42 -> 0 | I44: =SUM(F44:H44) -> -6
B45: ='CF (Equity, Debt)'!C45 -> X-fusion | C45: =VLOOKUP(B45,'S | 02'!$C$6:$J$41,2,0) -> Direct Investment | D45: =VLOOKUP(B45,'S | 02'!$C$6:$J$41,5,0) -> Mozn 2 | E45: ='CF (Equity, Debt)'!D45 -> 45224 | F45: ='CF (Equity, Debt)'!E45 -> 0 | G45: ='CF (Equity, Debt)'!F45 -> 403 | I45: =SUM(F45:H45) -> 403
B46: ='CF (Equity, Debt)'!C46 -> Instadeep Limited | C46: =VLOOKUP(B46,'S | 02'!$C$6:$J$41,2,0) -> Direct Investment | D46: =VLOOKUP(B46,'S | 02'!$C$6:$J$41,5,0) -> Mozn | E46: ='CF (Equity, Debt)'!D46 -> 45224 | F46: ='CF (Equity, Debt)'!E46 -> 0 | G46: ='CF (Equity, Debt)'!F46 -> 0.12141643 | I46: =SUM(F46:H46) -> 0.12141643
B47: ='CF (Equity, Debt)'!C47 -> Applied AI Corporation Limited | C47: =VLOOKUP(B47,'S | 02'!$C$6:$J$41,2,0) -> Direct Investment | D47: =VLOOKUP(B47,'S | 02'!$C$6:$J$41,5,0) -> Mozn | E47: ='CF (Equity, Debt)'!D47 -> 45295 | F47: ='CF (Equity, Debt)'!E47 -> -4 | G47: ='CF (Equity, Debt)'!F47 -> 0 | I47: =SUM(F47:H47) -> -4
B48: ='CF (Equity, Debt)'!C48 -> School Hack (AIREV Holding Limited) | C48: =VLOOKUP(B48,'S | 02'!$C$6:$J$41,2,0) -> Direct Investment | D48: =VLOOKUP(B48,'S | 02'!$C$6:$J$41,5,0) -> Core42 | E48: ='CF (Equity, Debt)'!D48 -> 45322 | F48: ='CF (Equity, Debt)'!E48 -> -2.75 | G48: ='CF (Equity, Debt)'!F48 -> 0 | I48: =SUM(F48:H48) -> -2.75
B49: ='CF (Equity, Debt)'!C53 -> Glass Earth Holdings LLC | C49: =VLOOKUP(B49,'S | 02'!$C$6:$J$41,2,0) -> Debt Investment | D49: =VLOOKUP(B49,'S | 02'!$C$6:$J$41,5,0) -> Mozn | E49: ='CF (Equity, Debt)'!D53 -> 43635 | F49: ='CF (Equity, Debt)'!E53 -> -8 | I49: =SUM(F49:H49) -> -8
B50: ='CF (Equity, Debt)'!C54 -> Mena Mobile Inc (Debt) | C50: =VLOOKUP(B50,'S | 02'!$C$6:$J$41,2,0) -> Debt Investment | D50: =VLOOKUP(B50,'S | 02'!$C$6:$J$41,5,0) -> Mozn | E50: ='CF (Equity, Debt)'!D54 -> 44293 | F50: ='CF (Equity, Debt)'!E54 -> -2.353982 | I50: =SUM(F50:H50) -> -2.353982
B51: ='CF (Equity, Debt)'!C55 -> Esyasoft Holding (Debt) | C51: =VLOOKUP(B51,'S | 02'!$C$6:$J$41,2,0) -> Debt Investment | D51: =VLOOKUP(B51,'S | 02'!$C$6:$J$41,5,0) -> Mozn | E51: ='CF (Equity, Debt)'!D55 -> 44384 | F51: ='CF (Equity, Debt)'!E55 -> -0.411765 | I51: =SUM(F51:H51) -> -0.411765
B52: ='CF (Equity, Debt)'!C56 -> Esyasoft Holding (Debt) | C52: =VLOOKUP(B52,'S | 02'!$C$6:$J$41,2,0) -> Debt Investment | D52: =VLOOKUP(B52,'S | 02'!$C$6:$J$41,5,0) -> Mozn | E52: ='CF (Equity, Debt)'!D56 -> 44902 | F52: ='CF (Equity, Debt)'!E56 -> 0 | G52: ='CF (Equity, Debt)'!F56 -> 0.47078465 | I52: =SUM(F52:H52) -> 0.47078465
B54: Jollychic Holding Limited | C54: =VLOOKUP(B54,'S | 02'!$C$6:$J$41,2,0) -> Direct Investment | D54: =VLOOKUP(B54,'S | 02'!$C$6:$J$41,5,0) -> Mozn | E54: =$E$4 -> 45322 | H54: =VLOOKUP(B54,NAV!$B$9:$E$45,4,0) -> 0 | I54: =SUM(F54:H54) -> 0
B55: Mena Mobile Inc | C55: =VLOOKUP(B55,'S | 02'!$C$6:$J$41,2,0) -> Direct Investment | D55: =VLOOKUP(B55,'S | 02'!$C$6:$J$41,5,0) -> Mozn | E55: =$E$4 -> 45322 | H55: =VLOOKUP(B55,NAV!$B$9:$E$45,4,0) -> 0 | I55: =SUM(F55:H55) -> 0
B56: Flyr Inc | C56: =VLOOKUP(B56,'S | 02'!$C$6:$J$41,2,0) -> Direct Investment | D56: =VLOOKUP(B56,'S | 02'!$C$6:$J$41,5,0) -> Mozn | E56: =$E$4 -> 45322 | H56: =VLOOKUP(B56,NAV!$B$9:$E$45,4,0) -> 78.08223 | I56: =SUM(F56:H56) -> 78.08223
B57: Esyasoft Holding | C57: =VLOOKUP(B57,'S | 02'!$C$6:$J$41,2,0) -> Direct Investment | D57: =VLOOKUP(B57,'S | 02'!$C$6:$J$41,5,0) -> Mozn | E57: =$E$4 -> 45322 | H57: =VLOOKUP(B57,NAV!$B$9:$E$45,4,0) -> 0 | I57: =SUM(F57:H57) -> 0
B58: Beyond Limits | C58: =VLOOKUP(B58,'S | 02'!$C$6:$J$41,2,0) -> Direct Investment | D58: =VLOOKUP(B58,'S | 02'!$C$6:$J$41,5,0) -> Mozn | E58: =$E$4 -> 45322 | H58: =VLOOKUP(B58,NAV!$B$9:$E$45,4,0) -> 91.00154 | I58: =SUM(F58:H58) -> 91.00154
B59: ONT plc | C59: =VLOOKUP(B59,'S | 02'!$C$6:$J$41,2,0) -> Direct Investment | D59: =VLOOKUP(B59,'S | 02'!$C$6:$J$41,5,0) -> Mozn | E59: =$E$4 -> 45322 | H59: =VLOOKUP(B59,NAV!$B$9:$E$45,4,0) -> 90.139175 | I59: =SUM(F59:H59) -> 90.139175
B60: Heygears | C60: =VLOOKUP(B60,'S | 02'!$C$6:$J$41,2,0) -> Direct Investment | D60: =VLOOKUP(B60,'S | 02'!$C$6:$J$41,5,0) -> Mozn | E60: =$E$4 -> 45322 | H60: =VLOOKUP(B60,NAV!$B$9:$E$45,4,0) -> 148.04984 | I60: =SUM(F60:H60) -> 148.04984
B61: Jysan Technologies | C61: Direct Investment | D61: Mozn 1 | E61: =$E$4 -> 45322 | H61: =VLOOKUP(B61,NAV!$B$9:$E$45,4,0) -> 0 | I61: =SUM(F61:H61) -> 0
B62: Cerebras Systems Inc | C62: =VLOOKUP(B62,'S | 02'!$C$6:$J$41,2,0) -> Direct Investment | D62: =VLOOKUP(B62,'S | 02'!$C$6:$J$41,5,0) -> Mozn | E62: =$E$4 -> 45322 | H62: =VLOOKUP(B62,NAV!$B$9:$E$45,4,0) -> 39.999983 | I62: =SUM(F62:H62) -> 39.999983
B63: Endless Studios LLC | C63: =VLOOKUP(B63,'S | 02'!$C$6:$J$41,2,0) -> Direct Investment | D63: =VLOOKUP(B63,'S | 02'!$C$6:$J$41,5,0) -> Mozn | E63: =$E$4 -> 45322 | H63: =VLOOKUP(B63,NAV!$B$9:$E$45,4,0) -> 8 | I63: =SUM(F63:H63) -> 8
B64: Instadeep Limited | C64: =VLOOKUP(B64,'S | 02'!$C$6:$J$41,2,0) -> Direct Investment | D64: =VLOOKUP(B64,'S | 02'!$C$6:$J$41,5,0) -> Mozn | E64: =$E$4 -> 45322 | H64: =VLOOKUP(B64,NAV!$B$9:$E$45,4,0) -> 0 | I64: =SUM(F64:H64) -> 0
B65: X-fusion | C65: =VLOOKUP(B65,'S | 02'!$C$6:$J$41,2,0) -> Direct Investment | D65: =VLOOKUP(B65,'S | 02'!$C$6:$J$41,5,0) -> Mozn 2 | E65: =$E$4 -> 45322 | H65: =VLOOKUP(B65,NAV!$B$9:$E$45,4,0) -> 0 | I65: =SUM(F65:H65) -> 0
B66: Applied AI Corporation Limited | C66: =VLOOKUP(B66,'S | 02'!$C$6:$J$41,2,0) -> Direct Investment | D66: =VLOOKUP(B66,'S | 02'!$C$6:$J$41,5,0) -> Mozn | E66: =$E$4 -> 45322 | H66: =VLOOKUP(B66,NAV!$B$9:$E$45,4,0) -> 11.5 | I66: =SUM(F66:H66) -> 11.5
B67: eSpace | C67: Direct Investment | D67: =VLOOKUP(B67,'S | 02'!$C$6:$J$41,5,0) -> Mozn 4 | E67: =$E$4 -> 45322 | H67: =VLOOKUP(B67,NAV!$B$9:$E$45,4,0) -> 20.888122 | I67: =SUM(F67:H67) -> 20.888122
B68: Tools for Humanity Corporation | C68: Direct Investment | D68: =VLOOKUP(B68,'S | 02'!$C$6:$J$41,5,0) -> Mozn | E68: =$E$4 -> 45322 | H68: =VLOOKUP(B68,NAV!$B$9:$E$45,4,0) -> 14.999999 | I68: =SUM(F68:H68) -> 14.999999
B69: WLD Tokens | C69: Direct Investment | D69: =VLOOKUP(B69,'S | 02'!$C$6:$J$41,5,0) -> Mozn | E69: =$E$4 -> 45322 | H69: =VLOOKUP(B69,NAV!$B$9:$E$45,4,0) -> 15 | I69: =SUM(F69:H69) -> 15
B70: E-line Ventures LLC | C70: Direct Investment | D70: =VLOOKUP(B70,'S | 02'!$C$6:$J$41,5,0) -> Mozn | E70: =$E$4 -> 45322 | H70: =VLOOKUP(B70,NAV!$B$9:$E$45,4,0) -> 6 | I70: =SUM(F70:H70) -> 6
B71: School Hack (AIREV Holding Limited) | C71: Direct Investment | D71: =VLOOKUP(B71,'S | 02'!$C$6:$J$41,5,0) -> Core42 | E71: =$E$4 -> 45322 | H71: =VLOOKUP(B71,NAV!$B$9:$E$45,4,0) -> 2.75 | I71: =SUM(F71:H71) -> 2.75
B72: Glass Earth Holdings LLC | C72: =VLOOKUP(B72,'S | 02'!$C$6:$J$41,2,0) -> Debt Investment | D72: =VLOOKUP(B72,'S | 02'!$C$6:$J$41,5,0) -> Mozn | E72: =$E$4 -> 45322 | H72: =VLOOKUP(B72,NAV!$B$9:$E$45,4,0) -> 0 | I72: =SUM(F72:H72) -> 0
B73: Mena Mobile Inc (Debt) | C73: =VLOOKUP(B73,'S | 02'!$C$6:$J$41,2,0) -> Debt Investment | D73: =VLOOKUP(B73,'S | 02'!$C$6:$J$41,5,0) -> Mozn | E73: =$E$4 -> 45322 | H73: =VLOOKUP(B73,NAV!$B$9:$E$45,4,0) -> 0 | I73: =SUM(F73:H73) -> 0

Sheet 4. G42-IRR
B2: IRR - G42 Investments | H2: =COUNTA(B13:B78) -> 65
B4: Date of NAV | E4: =D!D2 -> 45322
K7: Invested | L7: Remaining Commitment | M7: Distributions | N7: Residual Value | O7: IRR | P7: TVPI | Q7: RPI | R7: DPI
K9: =-SUM(F12:F78) -> 1263.4152 | M9: =SUM(G12:G78) -> 814.01547 | N9: =SUM(H12:H78) -> 428.73667 | O9: =XIRR(I13:I78,E13:E78) -> -0.017151204 | P9: =(M9+N9)/K9 -> 0.98364511 | Q9: =N9/K9 -> 0.33934742 | R9: =M9/K9 -> 0.64429769
B10: (in USD, Mn)
B11: Investment | C11: Type | D11: Entity | E11: Payment date | F11: Contribution | G11: Distributions | H11: Remaining Value | I11: Combined | M11: Checks
K12: Invested | L12: =-SUM(F12:F78) -> 1263.4152 | M12: =K9='S | 02'!L42 -> TRUE
B13: ='CF (Equity, Debt)'!C26 -> DriveNets | C13: =VLOOKUP(B13,'S | 02'!$C$6:$J$41,2,0) -> Direct Investment | D13: =VLOOKUP(B13,'S | 02'!$C$6:$J$41,5,0) -> G42 | E13: ='CF (Equity, Debt)'!D26 -> 44643 | F13: ='CF (Equity, Debt)'!E26 -> -200 | I13: =SUM(F13:H13) -> -200 | K13: NAV | L13: =SUM(H12:H78) -> 428.73667 | M13: =M9='S | 02'!M42 -> TRUE
B14: ='CF (Equity, Debt)'!C27 -> DriveNets | C14: =VLOOKUP(B14,'S | 02'!$C$6:$J$41,2,0) -> Direct Investment | D14: =VLOOKUP(B14,'S | 02'!$C$6:$J$41,5,0) -> G42 | E14: ='CF (Equity, Debt)'!D27 -> 44680 | F14: ='CF (Equity, Debt)'!E27 -> -100 | I14: =SUM(F14:H14) -> -100 | K14: Distributions | L14: =SUM(G12:G78) -> 814.01547 | M14: =ROUND(N9,3)=ROUND('S | 02'!N42,3) -> TRUE
B15: ='CF (Equity, Debt)'!C29 -> vTv Therapeutics Inc. | C15: =VLOOKUP(B15,'S | 02'!$C$6:$J$41,2,0) -> Direct Investment | D15: =VLOOKUP(B15,'S | 02'!$C$6:$J$41,5,0) -> G42 | E15: ='CF (Equity, Debt)'!D29 -> 44712 | F15: ='CF (Equity, Debt)'!E29 -> -12.5 | I15: =SUM(F15:H15) -> -12.5 | K15: Total Gain | L15: =L14+L13-L12 -> -20.663021
B16: ='CF (Equity, Debt)'!C34 -> vTv Therapeutics Inc. | C16: =VLOOKUP(B16,'S | 02'!$C$6:$J$41,2,0) -> Direct Investment | D16: =VLOOKUP(B16,'S | 02'!$C$6:$J$41,5,0) -> G42 | E16: ='CF (Equity, Debt)'!D34 -> 44985 | F16: ='CF (Equity, Debt)'!E34 -> -12.03125 | I16: =SUM(F16:H16) -> -12.03125 | K16: IRR | L16: =O9 -> -0.017151204
B17: ='CF (Equity, Debt)'!C30 -> Honor Device Co Ltd | C17: =VLOOKUP(B17,'S | 02'!$C$6:$J$41,2,0) -> Direct Investment | D17: =VLOOKUP(B17,'S | 02'!$C$6:$J$41,5,0) -> G42 3 | E17: ='CF (Equity, Debt)'!D30 -> 44769 | F17: ='CF (Equity, Debt)'!E30 -> -600 | I17: =SUM(F17:H17) -> -600
B18: ='CF (Equity, Debt)'!C31 -> Honor Device Co Ltd | C18: =VLOOKUP(B18,'S | 02'!$C$6:$J$41,2,0) -> Direct Investment | D18: =VLOOKUP(B18,'S | 02'!$C$6:$J$41,5,0) -> G42 3 | E18: ='CF (Equity, Debt)'!D31 -> 44849 | F18: ='CF (Equity, Debt)'!E31 -> -200 | I18: =SUM(F18:H18) -> -200
B19: ='CF (Equity, Debt)'!C43 -> Honor Device Co Ltd | C19: =VLOOKUP(B19,'S | 02'!$C$6:$J$41,2,0) -> Direct Investment | D19: =VLOOKUP(B19,'S | 02'!$C$6:$J$41,5,0) -> G42 3 | E19: ='CF (Equity, Debt)'!D32 -> 44861 | F19: ='CF (Equity, Debt)'!E43 -> 0 | G19: ='CF (Equity, Debt)'!F43 -> 2.8 | I19: =SUM(F19:H19) -> 2.8
B20: ='CF (Equity, Debt)'!C44 -> Honor Device Co Ltd | C20: =VLOOKUP(B20,'S | 02'!$C$6:$J$41,2,0) -> Direct Investment | D20: =VLOOKUP(B20,'S | 02'!$C$6:$J$41,5,0) -> G42 3 | E20: ='CF (Equity, Debt)'!D33 -> 44892 | F20: ='CF (Equity, Debt)'!E44 -> 0 | G20: ='CF (Equity, Debt)'!F44 -> 800 | I20: =SUM(F20:H20) -> 800
B21: ='CF (Funds)'!B3 -> Sinovation Disrupt Fund, L.P. | C21: =VLOOKUP(B21,'S | 02'!$C$6:$J$41,2,0) -> Fund Investment | D21: =VLOOKUP(B21,'S | 02'!$C$6:$J$41,5,0) -> G42 | E21: ='CF (Funds)'!C3 -> 44153 | F21: ='CF (Funds)'!D3 -> -10.5 | G21: ='CF (Funds)'!E3 -> 0 | I21: =SUM(F21:H21) -> -10.5 | L21: =L15/L12 -> -0.016354894
B22: ='CF (Funds)'!B4 -> Sinovation Disrupt Fund, L.P. | C22: =VLOOKUP(B22,'S | 02'!$C$6:$J$41,2,0) -> Fund Investment | D22: =VLOOKUP(B22,'S | 02'!$C$6:$J$41,5,0) -> G42 | E22: ='CF (Funds)'!C4 -> 44238 | F22: ='CF (Funds)'!D4 -> 4.214027 | G22: ='CF (Funds)'!E4 -> 0 | I22: =SUM(F22:H22) -> 4.214027
B23: ='CF (Funds)'!B5 -> Sinovation Disrupt Fund, L.P. | C23: =VLOOKUP(B23,'S | 02'!$C$6:$J$41,2,0) -> Fund Investment | D23: =VLOOKUP(B23,'S | 02'!$C$6:$J$41,5,0) -> G42 | E23: ='CF (Funds)'!C5 -> 44238 | F23: ='CF (Funds)'!D5 -> 0 | G23: ='CF (Funds)'!E5 -> 0.05044835 | I23: =SUM(F23:H23) -> 0.05044835
B24: ='CF (Funds)'!B6 -> Sinovation Disrupt Fund, L.P. | C24: =VLOOKUP(B24,'S | 02'!$C$6:$J$41,2,0) -> Fund Investment | D24: =VLOOKUP(B24,'S | 02'!$C$6:$J$41,5,0) -> G42 | E24: ='CF (Funds)'!C6 -> 44285 | F24: ='CF (Funds)'!D6 -> -6.433746 | G24: ='CF (Funds)'!E6 -> 0 | I24: =SUM(F24:H24) -> -6.433746
B25: ='CF (Funds)'!B7 -> Sinovation Disrupt Fund, L.P. | C25: =VLOOKUP(B25,'S | 02'!$C$6:$J$41,2,0) -> Fund Investment | D25: =VLOOKUP(B25,'S | 02'!$C$6:$J$41,5,0) -> G42 | E25: ='CF (Funds)'!C7 -> 44269 | F25: ='CF (Funds)'!D7 -> 1.1352074 | G25: ='CF (Funds)'!E7 -> 0 | I25: =SUM(F25:H25) -> 1.1352074
B26: ='CF (Funds)'!B8 -> Sinovation Disrupt Fund, L.P. | C26: =VLOOKUP(B26,'S | 02'!$C$6:$J$41,2,0) -> Fund Investment | D26: =VLOOKUP(B26,'S | 02'!$C$6:$J$41,5,0) -> G42 | E26: ='CF (Funds)'!C8 -> 44269 | F26: ='CF (Funds)'!D8 -> 0 | G26: ='CF (Funds)'!E8 -> 0.0259 | I26: =SUM(F26:H26) -> 0.0259
B27: ='CF (Funds)'!B9 -> Sinovation Disrupt Fund, L.P. | C27: =VLOOKUP(B27,'S | 02'!$C$6:$J$41,2,0) -> Fund Investment | D27: =VLOOKUP(B27,'S | 02'!$C$6:$J$41,5,0) -> G42 | E27: ='CF (Funds)'!C9 -> 44483 | F27: ='CF (Funds)'!D9 -> -7.567138 | G27: ='CF (Funds)'!E9 -> 0 | I27: =SUM(F27:H27) -> -7.567138
B28: ='CF (Funds)'!B10 -> Sinovation Disrupt Fund, L.P. | C28: =VLOOKUP(B28,'S | 02'!$C$6:$J$41,2,0) -> Fund Investment | D28: =VLOOKUP(B28,'S | 02'!$C$6:$J$41,5,0) -> G42 | E28: ='CF (Funds)'!C10 -> 44554 | F28: ='CF (Funds)'!D10 -> -7.385016 | G28: ='CF (Funds)'!E10 -> 0 | I28: =SUM(F28:H28) -> -7.385016
B29: ='CF (Funds)'!B11 -> Sinovation Disrupt Fund, L.P. | C29: =VLOOKUP(B29,'S | 02'!$C$6:$J$41,2,0) -> Fund Investment | D29: =VLOOKUP(B29,'S | 02'!$C$6:$J$41,5,0) -> G42 | E29: ='CF (Funds)'!C11 -> 44554 | F29: ='CF (Funds)'!D11 -> 4.0733456 | G29: ='CF (Funds)'!E11 -> 0 | I29: =SUM(F29:H29) -> 4.0733456
B30: ='CF (Funds)'!B12 -> Sinovation Disrupt Fund, L.P. | C30: =VLOOKUP(B30,'S | 02'!$C$6:$J$41,2,0) -> Fund Investment | D30: =VLOOKUP(B30,'S | 02'!$C$6:$J$41,5,0) -> G42 | E30: ='CF (Funds)'!C12 -> 44554 | F30: ='CF (Funds)'!D12 -> 0 | G30: ='CF (Funds)'!E12 -> 0.139694 | I30: =SUM(F30:H30) -> 0.139694
B31: ='CF (Funds)'!B13 -> Sinovation Disrupt Fund, L.P. | C31: =VLOOKUP(B31,'S | 02'!$C$6:$J$41,2,0) -> Fund Investment | D31: =VLOOKUP(B31,'S | 02'!$C$6:$J$41,5,0) -> G42 | E31: ='CF (Funds)'!C13 -> 44703 | F31: ='CF (Funds)'!D13 -> 5.673074 | G31: ='CF (Funds)'!E13 -> 0 | I31: =SUM(F31:H31) -> 5.673074
B32: ='CF (Funds)'!B14 -> Sinovation Disrupt Fund, L.P. | C32: =VLOOKUP(B32,'S | 02'!$C$6:$J$41,2,0) -> Fund Investment | D32: =VLOOKUP(B32,'S | 02'!$C$6:$J$41,5,0) -> G42 | E32: ='CF (Funds)'!C14 -> 44703 | F32: ='CF (Funds)'!D14 -> 0 | G32: ='CF (Funds)'!E14 -> 0.227786 | I32: =SUM(F32:H32) -> 0.227786
B33: ='CF (Funds)'!B15 -> Sinovation Disrupt Fund, L.P. | C33: =VLOOKUP(B33,'S | 02'!$C$6:$J$41,2,0) -> Fund Investment | D33: =VLOOKUP(B33,'S | 02'!$C$6:$J$41,5,0) -> G42 | E33: ='CF (Funds)'!C15 -> 44776 | F33: ='CF (Funds)'!D15 -> -3.235493 | G33: ='CF (Funds)'!E15 -> 0 | I33: =SUM(F33:H33) -> -3.235493
... B53: ='CF (Funds)'!B35 -> North Summit Capital Fund | C53: =VLOOKUP(B53,'S | 02'!$C$6:$J$41,2,0) -> Fund Investment | D53: =VLOOKUP(B53,'S | 02'!$C$6:$J$41,5,0) -> G42 | E53: ='CF (Funds)'!C35 -> 45243 | F53: ='CF (Funds)'!D35 -> 0 | G53: ='CF (Funds)'!E35 -> 6.78791 | I53: =SUM(F53:H53) -> 6.78791
B55: ='CF (Funds)'!B36 -> New Space Capital Fund I | C55: =VLOOKUP(B55,'S | 02'!$C$6:$J$41,2,0) -> Fund Investment | D55: =VLOOKUP(B55,'S | 02'!$C$6:$J$41,5,0) -> G42 | E55: ='CF (Funds)'!C36 -> 44087 | F55: ='CF (Funds)'!D36 -> -20.917553 | G55: ='CF (Funds)'!E36 -> 0 | I55: =SUM(F55:H55) -> -20.917553
B56: ='CF (Funds)'!B37 -> New Space Capital Fund I | C56: =VLOOKUP(B56,'S | 02'!$C$6:$J$41,2,0) -> Fund Investment | D56: =VLOOKUP(B56,'S | 02'!$C$6:$J$41,5,0) -> G42 | E56: ='CF (Funds)'!C37 -> 44287 | F56: ='CF (Funds)'!D37 -> -0.21103182 | G56: ='CF (Funds)'!E37 -> 0 | I56: =SUM(F56:H56) -> -0.21103182
B57: ='CF (Funds)'!B38 -> New Space Capital Fund I | C57: =VLOOKUP(B57,'S | 02'!$C$6:$J$41,2,0) -> Fund Investment | D57: =VLOOKUP(B57,'S | 02'!$C$6:$J$41,5,0) -> G42 | E57: ='CF (Funds)'!C38 -> 44442 | F57: ='CF (Funds)'!D38 -> -0.23965473 | G57: ='CF (Funds)'!E38 -> 0 | I57: =SUM(F57:H57) -> -0.23965473
B58: ='CF (Funds)'!B39 -> New Space Capital Fund I | C58: =VLOOKUP(B58,'S | 02'!$C$6:$J$41,2,0) -> Fund Investment | D58: =VLOOKUP(B58,'S | 02'!$C$6:$J$41,5,0) -> G42 | E58: ='CF (Funds)'!C39 -> 44623 | F58: ='CF (Funds)'!D39 -> -0.25893585 | G58: ='CF (Funds)'!E39 -> 0 | I58: =SUM(F58:H58) -> -0.25893585
B59: ='CF (Funds)'!B40 -> New Space Capital Fund I | C59: =VLOOKUP(B59,'S | 02'!$C$6:$J$41,2,0) -> Fund Investment | D59: =VLOOKUP(B59,'S | 02'!$C$6:$J$41,5,0) -> G42 | E59: ='CF (Funds)'!C40 -> 44784 | F59: ='CF (Funds)'!D40 -> 0.015224657 | G59: ='CF (Funds)'!E40 -> 0 | I59: =SUM(F59:H59) -> 0.015224657
B60: ='CF (Funds)'!B41 -> New Space Capital Fund I | C60: =VLOOKUP(B60,'S | 02'!$C$6:$J$41,2,0) -> Fund Investment | D60: =VLOOKUP(B60,'S | 02'!$C$6:$J$41,5,0) -> G42 | E60: ='CF (Funds)'!C41 -> 44956 | F60: ='CF (Funds)'!D41 -> 10.553916 | G60: ='CF (Funds)'!E41 -> 0 | I60: =SUM(F60:H60) -> 10.553916
B61: ='CF (Funds)'!B42 -> New Space Capital Fund I | C61: =VLOOKUP(B61,'S | 02'!$C$6:$J$41,2,0) -> Fund Investment | D61: =VLOOKUP(B61,'S | 02'!$C$6:$J$41,5,0) -> G42 | E61: ='CF (Funds)'!C42 -> 44956 | F61: ='CF (Funds)'!D42 -> 0 | G61: ='CF (Funds)'!E42 -> 2.9557744 | I61: =SUM(F61:H61) -> 2.9557744
B62: ='CF (Funds)'!B43 -> New Space Capital Fund I | C62: =VLOOKUP(B62,'S | 02'!$C$6:$J$41,2,0) -> Fund Investment | D62: =VLOOKUP(B62,'S | 02'!$C$6:$J$41,5,0) -> G42 | E62: ='CF (Funds)'!C43 -> 45170 | F62: ='CF (Funds)'!D43 -> -0.22532724 | G62: ='CF (Funds)'!E43 -> 0 | I62: =SUM(F62:H62) -> -0.22532724
B63: ='CF (Funds)'!B44 -> New Space Capital Fund I | C63: =VLOOKUP(B63,'S | 02'!$C$6:$J$41,2,0) -> Fund Investment | D63: =VLOOKUP(B63,'S | 02'!$C$6:$J$41,5,0) -> G42 | E63: ='CF (Funds)'!C44 -> 45260 | F63: ='CF (Funds)'!D44 -> -0.28531252 | G63: ='CF (Funds)'!E44 -> 0 | I63: =SUM(F63:H63) -> -0.28531252
B64: ='CF (Funds)'!B45 -> New Space Capital Fund I | C64: =VLOOKUP(B64,'S | 02'!$C$6:$J$41,2,0) -> Fund Investment | D64: =VLOOKUP(B64,'S | 02'!$C$6:$J$41,5,0) -> G42 | E64: ='CF (Funds)'!C45 -> 45321 | F64: ='CF (Funds)'!D45 -> -2.4198785 | G64: ='CF (Funds)'!E45 -> 0 | I64: =SUM(F64:H64) -> -2.4198785
B65: ='CF (Funds)'!B46 -> New Space Capital GP Com SCSp | C65: =VLOOKUP(B65,'S | 02'!$C$6:$J$41,2,0) -> Fund Investment | D65: =VLOOKUP(B65,'S | 02'!$C$6:$J$41,5,0) -> G42 | E65: ='CF (Funds)'!C46 -> 44087 | F65: ='CF (Funds)'!D46 -> -2.7058824 | G65: ='CF (Funds)'!E46 -> 0 | I65: =SUM(F65:H65) -> -2.7058824
B66: ='CF (Funds)'!B47 -> Acies Investments Fund I, L.P. | C66: =VLOOKUP(B66,'S | 02'!$C$6:$J$41,2,0) -> Fund Investment | D66: =VLOOKUP(B66,'S | 02'!$C$6:$J$41,5,0) -> G42 | E66: ='CF (Funds)'!C47 -> 44540 | F66: ='CF (Funds)'!D47 -> -2.8053125 | G66: ='CF (Funds)'!E47 -> 0 | I66: =SUM(F66:H66) -> -2.8053125
... B70: ='CF (Funds)'!B51 -> Acies Investments Fund I, L.P. | C70: =VLOOKUP(B70,'S | 02'!$C$6:$J$41,2,0) -> Fund Investment | D70: =VLOOKUP(B70,'S | 02'!$C$6:$J$41,5,0) -> G42 | E70: ='CF (Funds)'!C51 -> 44875 | F70: ='CF (Funds)'!D51 -> -3.388275 | G70: ='CF (Funds)'!E51 -> 0 | I70: =SUM(F70:H70) -> -3.388275
B71: DriveNets | C71: =VLOOKUP(B71,'S | 02'!$C$6:$J$41,2,0) -> Direct Investment | D71: =VLOOKUP(B71,'S | 02'!$C$6:$J$41,5,0) -> G42 | E71: =$E$4 -> 45322 | H71: =VLOOKUP(B71,NAV!$B$9:$E$45,4,0) -> 300 | I71: =SUM(F71:H71) -> 300
B72: vTv Therapeutics Inc. | C72: =VLOOKUP(B72,'S | 02'!$C$6:$J$41,2,0) -> Direct Investment | D72: =VLOOKUP(B72,'S | 02'!$C$6:$J$41,5,0) -> G42 | E72: =$E$4 -> 45322 | H72: =VLOOKUP(B72,NAV!$B$9:$E$45,4,0) -> 2.1837154 | I72: =SUM(F72:H72) -> 2.1837154
B73: Honor Device Co Ltd | C73: =VLOOKUP(B73,'S | 02'!$C$6:$J$41,2,0) -> Direct Investment | D73: =VLOOKUP(B73,'S | 02'!$C$6:$J$41,5,0) -> G42 3 | E73: =$E$4 -> 45322 | H73: =VLOOKUP(B73,NAV!$B$9:$E$45,4,0) -> 0 | I73: =SUM(F73:H73) -> 0
B74: New Space Capital Fund I | C74: =VLOOKUP(B74,'S | 02'!$C$6:$J$41,2,0) -> Fund Investment | D74: =VLOOKUP(B74,'S | 02'!$C$6:$J$41,5,0) -> G42 | E74: =$E$4 -> 45322 | H74: =VLOOKUP(B74,NAV!$B$9:$E$45,4,0) -> 13.277945 | I74: =SUM(F74:H74) -> 13.277945
B75: New Space Capital GP Com SCSp | C75: =VLOOKUP(B75,'S | 02'!$C$6:$J$41,2,0) -> Fund Investment | D75: =VLOOKUP(B75,'S | 02'!$C$6:$J$41,5,0) -> G42 | E75: =$E$4 -> 45322 | H75: =VLOOKUP(B75,NAV!$B$9:$E$45,4,0) -> 2.5684255 | I75: =SUM(F75:H75) -> 2.5684255
B76: North Summit Capital Fund | C76: =VLOOKUP(B76,'S | 02'!$C$6:$J$41,2,0) -> Fund Investment | D76: =VLOOKUP(B76,'S | 02'!$C$6:$J$41,5,0) -> G42 | E76: =$E$4 -> 45322 | H76: =VLOOKUP(B76,NAV!$B$9:$E$45,4,0) -> 74.725861 | I76: =SUM(F76:H76) -> 74.725861
B77: Sinovation Disrupt Fund, L.P. | C77: =VLOOKUP(B77,'S | 02'!$C$6:$J$41,2,0) -> Fund Investment | D77: =VLOOKUP(B77,'S | 02'!$C$6:$J$41,5,0) -> G42 | E77: =$E$4 -> 45322 | H77: =VLOOKUP(B77,NAV!$B$9:$E$45,4,0) -> 23.670303 | I77: =SUM(F77:H77) -> 23.670303
B78: Acies Investments Fund I, L.P. | C78: =VLOOKUP(B78,'S | 02'!$C$6:$J$41,2,0) -> Fund Investment | D78: =VLOOKUP(B78,'S | 02'!$C$6:$J$41,5,0) -> G42 | E78: =$E$4 -> 45322 | H78: =VLOOKUP(B78,NAV!$B$9:$E$45,4,0) -> 12.310425 | I78: =SUM(F78:H78) -> 12.310425

Sheet 5. Glossary
B2: Term | C2: Definition
B3: $ | C3: Refers to US Dollar
B4: Equity-TBC | C4: The exact class of share is not available as of date
B5: Gain | C5: Equals the total Distributions (received from the investment) plus NAV less Amount Invested
B6: G42 | C6: Refers to entity G42 Investments AI Holding RSC Ltd, and Smart Interaction1 Holding SPV RSC LTD
B7: G.P. | C7: General Partnership interest
B8: IRR | C8: Shown as Interim IRR, where the NAV of the investment is assumed as an appraised terminal value. Transaction costs are not included in the estimate of IRR
B9: L.P. | C9: Limited Partnership interest
B10: MOIC | C10: Money on invested capital
B11: Mozn | C11: Refers to entities: Mozn Holding RSC Ltd, Enterprises Connection Holding RSC Ltd, Smart Interaction5 Holding SPV RSC LTD and QAZ42 Investment SPV RSC Ltd
B12: NAV | C12: Is the measure of the carrying value of the underlying investment as of date
B13: n/a | C13: As appropriate the information is ‘not available’ or ‘not applicable’
... B28: •Written Off: | C28: Investments in Jollychic, Mena Mobile (equity) and Glass Earth are written off

Sheet 6. %
C2: % OWNERSHIP
C3: As of date | D3: ='S | 01 '!D2 -> 45322
C6: Deals | D6: Shares / Units | E6: Total | F6: % | G6: Source for % holding | H6: Incorporation/Jurisdiction | I6: Country
C8: Direct Investments
B9: Written Off | C9: ='S | 01 '!C10 -> Jollychic Holding Limited | D9: 13458655 | E9: 236116762 | F9: =D9/E9 -> 0.056999998 | G9: Dan Kong | H9: Cayman Islands | I9: Cayman Islands
B10: Written Off | C10: ='S | 01 '!C11 -> Mena Mobile Inc | D10: 21419829 | E10: 152998776 | F10: =D10/E10 -> 0.14 | G10: Dan Kong | H10: Cayman Islands | I10: Cayman Islands
C11: ='S | 01 '!C12 -> Flyr Inc | D11: 5205482 | E11: 61222609 | F11: =D11/E11 -> 0.085025485 | G11: Cap Table as of Jun'22 | H11: Delaware Corporation | I11: USA
B12: Exited | C12: ='S | 01 '!C13 -> Esyasoft Holding | D12: n/a | E12: n/a | F12: n/a | G12: n/a; exited | H12: DIFC | I12: Dubai, UAE
C13: ='S | 01 '!C14 -> Beyond Limits | D13: 17670202 | E13: 180372405 | F13: =D13/E13 -> 0.097965107 | G13: Cap Table | H13: Delaware Corporation | I13: USA
C14: ='S | 01 '!C15 -> ONT plc | D14: 44328120 | E14: =829189128+29025326 -> 858214454 | F14: =D14/E14 -> 0.051651565 | G14: LSE Announcement | H14: UK | I14: UK
C15: ='S | 01 '!C16 -> Heygears | D15: 3565017.2 | E15: =D15/F15 -> 24791497 | F15: 0.1438 | G15: Dan Kong | H15: PRC | I15: China
B16: Exited | C16: ='S | 01 '!C17 -> Jysan Technologies | D16: 7959497 | E16: 2.6531657e+08 | F16: 0.03 | G16: Txn docs | H16: UK | I16: UK
C17: ='S | 01 '!C18 -> Cerebras Systems Inc | D17: 1441711 | E17: 158130778 | F17: =D17/E17 -> 0.0091172068 | G17: Cap table as of Dec'22 | H17: Delaware Corporation | I17: USA
C18: ='S | 01 '!C19 -> Endless Studios LLC | D18: 8000000 | E18: =38750000+11000000 -> 49750000 | F18: =D18/E18 -> 0.16080402 | G18: Cap table as of Dec'22 | H18: Delaware Corporation | I18: USA
B19: Exited | C19: ='S | 01 '!C20 -> Instadeep Limited | D19: 33267 | E19: 2895450 | F19: =D19/E19 -> 0.011489406 | G19: Txn docs; exit underway | H19: UK | I19: UK
B20: Exited | C20: ='S | 01 '!C21 -> X-fusion | F20: =10% * 51% -> 0.051 | G20: Dan Kong | H20: PRC | I20: China
C21: ='S | 01 '!C22 -> DriveNets | D21: 86882669 | E21: 779782293 | F21: =D21/E21 -> 0.11141914 | G21: Cap table as of Mar'23 | H21: Israeli Pvt Company | I21: Israel
C22: ='S | 01 '!C23 -> vTv Therapeutics Inc. | D22: =ROUNDUP(10386274/40,0) -> 259657 | E22: =ROUNDUP(81483600+23093860+9545439+3214503,0) -> 117337402 | F22: =D22/E22 -> 0.0022129091 | G22: 10Q report Jun'23 | H22: Delaware Corporation | I22: USA
B23: Exited | C23: ='S | 01 '!C24 -> Honor Device Co Ltd | D23: =1517126944.34*0.8/2 -> 6.0685078e+08 | E23: 3.2238948e+10 | F23: =4.705882%* 0.8/2 -> 0.018823528 | G23: Dan Kong | H23: PRC | I23: China
C24: ='S | 01 '!C25 -> Applied AI Corporation Limited | D24: n/a | E24: n/a | F24: n/a | G24: n/a; convertible note | H24: ADGM | I24: Abu Dhabi, UAE | L24: Eline Estimates
C25: ='S | 01 '!C26 -> eSpace | D25: 417846 | E25: 14995394 | F25: =D25/E25 -> 0.027864956 | G25: Series B Pref | H25: Delaware Corporation | I25: USA | L25: 5400972 | M25: Common Unit
C26: ='S | 01 '!C27 -> Tools for Humanity Corporation | D26: 65413 | E26: 10445693 | F26: =D26/E26 -> 0.0062621983 | G26: Email: Sam Thomson | H26: Delaware Corporation | I26: USA | L26: 4857352 | M26: Series A
C27: ='S | 01 '!C28 -> WLD Tokens | D27: 62500000 | E27: 10000000000 | F27: =D27/E27 -> 0.00625 | G27: Email: Sam Thomson | H27: DAO | Cayman Islands | I27: Cayman Islands | L27: 16791835 | M27: Series B
C28: ='S | 01 '!C29 -> E-line Ventures LLC | D28: 4477612 | E28: =L33 -> 38990900 | F28: =D28/E28 -> 0.11483736 | G28: IAF 12Jul23 | H28: New Jersey | I28: New Jersey | L28: 1465517 | M28: Series B-S1
C29: ='S | 01 '!C30 -> School Hack (AIREV Holding Limited) | D29: 25000 | E29: 100000 | F29: =D29/E29 -> 0.25 | G29: Shareholders Resolution | H29: ADGM | I29: UAE
L31: =D28*2 -> 8955224 | M31: Seires B 2023
L32: 1520000 | M32: Series B 2023 P
L33: =SUM(L25:L32) -> 38990900
C34: Funds Investments | D34: G42 Commitment | E34: Fund Size
C35: New Space Capital Fund I | D35: 23234462 | E35: 105,400,00 | F35: ='5. NewSpace'!J57 -> 0.22044082 | G35: Estimated as per Q1-23 NAV report | H35: Luxembourg | I35: Luxembourg
C36: New Space Capital GP Com SCSp | D36: =-'CF (Funds)'!G46*10^6 -> 2125000 | E36: 105,400,00 | F36: ='5. NewSpace'!J58 -> 0.02016129 | H36: Luxembourg | I36: Luxembourg
C37: North Summit Capital Fund | D37: 300000000 | E37: 301507538 | F37: =D37/E37 -> 0.995 | G37: Q4'22 Report | H37: Cayman Islands | I37: Cayman Islands
B38: Exited | C38: Sinovation Disrupt Fund, L.P. | D38: 50000000 | E38: 496717172 | F38: =D38/E38 -> 0.1006609 | G38: Q2'23 Report | H38: Cayman Islands | I38: Cayman Islands
C39: Acies Investments Fund I, L.P. | D39: 17112500 | E39: 51337500 | F39: =D39/E39 -> 0.33333333 | G39: Q1 23 Report | H39: Delaware LLC | I39: USA

Sheet 7. Board
C3: Deals | D3: Board Representation ‡ | E3: Representative | F3: Notes | G3: Status | H3: Comments
C5: Direct Investments
C6: Mena Mobile Inc | D6: 1 Board | E6: Peng Xiao | G6: In Liquidation | H6: To be replaced by JN
C7: Flyr Inc | D7: 1 Board | E7: Marty
C8: Esyasoft Holding | D8: NR | E8: n/a | F8: 2 | G8: Exited | H8: Monty Aw represented earlier
C9: Jollychic Holding Limited | D9: 1 Board | E9: Divyesh Mahajan | F9: 1 | G9: In Liquidation
C10: Beyond Limits | D10: 1 Board | E10: Marty | F10: 3
C11: ONT plc | D11: 1 Board | E11: Guy Harmelin (Independent Director)
C12: Heygears | D12: 2 Board | E12: Elaine | G12: Peng Resigned Jan24 | H12: PX to be replaced by XP
C13: Jysan Technologies | D13: 1 Board | E13: None appointed | G13: Exited | H13: Exited
C14: Cerebras Systems Inc | D14: 1 Observer | E14: Eric Xing | F14: 4
C15: Endless Studios LLC | D15: 1 Board | E15: Jon Nieman
C16: Instadeep Limited | D16: 1 Observer | G16: Exited | H16: Exited
C17: X-fusion | D17: NR | E17: n/a | G17: Exited
C18: DriveNets | D18: 1 Observer | E18: Guy Harmelin
C19: vTv Therapeutics Inc. | D19: 1 Board, 1 Observer | E19: Dr. Fahad (Board), Jon Nieman (Observer)
C20: Honor Device Co Ltd | D20: NR | E20: n/a | F20: 5 | G20: Exited | L20: E-line Ventures LLC
C21: Applied AI Corporation Limited | D21: NR | E21: n/a | L21: School Hack (AIREV Holding Limited)
C22: eSpace | D22: NR | E22: n/a
C23: Tools for Humanity Corporation | D23: NR | E23: n/a
C24: E-line Ventures LLC
C25: School Hack (AIREV Holding Limited) | D25: 2 Board | E25: n/a
C28: Debt Investments
C29: Glass Earth Holdings LLC | D29: NR
C30: Mena Mobile Inc | D30: 1 Board | E30: Peng Xiao | G30: In Liquidation
C31: Esyasoft Holding | D31: NR
C34: Funds Investments
C35: New Space Capital Fund I | D35: NR
C36: New Space Capital GP Com SCSp | E36: Talal
C37: North Summit Capital Fund | D37: NR
C38: Sinovation Disrupt Fund, L.P. | D38: NR | G38: Exited
C39: Acies Investments Fund I, L.P. | D39: Not yet appointed | E39: Advisory Board | H39: Confirm appoinment
C43: NOTES:
C44: NR = No Rights / No Representation
C45: n/a = not applicable or not available
C46: ‡ Board Representation : as a Board Seat, Observer, or Advisor
B47: 1 | C47: Jollychic Holding : Peng Xiao held the directorship until Jun 2021
B48: 2 | C48: Esyasoft: we held a Board seat, with Monty Aw as the representative, until Jun 2022
B49: 3 | C49: Beyond Limits: possibility of the 2nd Board seat in case we invest (an additional / an earlier committed) $10m
B50: 4 | C50: Cerebras : possibility of a Board seat, If G42 holds >10% with rights to exercise at least 20% of warrant
B51: 5 | C51: Honor: Our board seat only kicks in once Honor is converted into a joint stock company in March 2023; there is no one appointed as yet

Sheet 8. Log
B3: Date Log | D3: Update
B5: Jan’24
C6: AAICO: USD 4m second milestone payment on 4-Jan-24
C7: NewSpace: EUR 2.2M (USD 2.42M) capital call paid on 30-Jan-24
C8: SchoolHack: Made an equity investment of USD 2.5m plus 250K in cloud credits
C9: Menamobile: Under liquidation
B10: Dec’23
C11: Espace Inc: converted the SAFE to equity
C12: North Summit Capital: G42’s remaining funding capital commitments waived
B13: Nov’23
C14: North Summit Capital : USD 6.8 distribution received on 13th November
B15: Oct’23
C16: Paid USD 2.4m to Sinovation Disrupt Fund (8th capital call)
C17: Received USD 2.8m dividend for Honor and USD 800m for Honor sell-down
C18: Received USD 403m for xFusion sell-down
B19: Sep’23
C20: No cashflow movements to report
B21: Aug’23
C22: Received USD 24.5m for Jysan’s exit
C23: Funded USD 1,799,122 towards Sinovation’s capital call
C24: Invested USD 6m in E-line Ventures and USD 5m in Endless Studios
B25: Jul’23
C26: Worldcoin: token warrant exercised, received 62.5M tokens
C27: AAICO: first milestone payment called with $2.75m additional invested
C28: Instadeep: fully exited at 1.56X return over invested capital (received $7.82m)
B29: Jun’23
C30: A distribution of $1.9m as a ‘return of capital’ received from the Sinovation Disrupt Fund
B31: May’23
C32: Invested $15m in Tools for Humanity Corp equity and Worldcoin token warrants
B33: Apr’23
C34: Re-structured investment in New Space Capital GP restructured – converted to GP commitment vehicle
C35: NAVs marked up for: Instadeep, Heygears and North Summit Capital. Mena Mobile equity value written off
B36: Mar’23
C37: Jysan dividend delayed (finally fully-exited in Aug’23)
B38: Feb’23
C39: Sinovation 6th capital call $2.6m transferred on 3-Feb
C40: vTv Therapeutics 2nd payment of $12.03m transferred on 28-Feb
B41: Jan’23
C42: Received €12.5m from NewSpace Capital on 30-Jan in lieu of partial return of capital and actualization interest; NAV reported as of Q3’23
C43: Instadeep exit: transaction completion expected by Q2’23; held at cost
B44: Dec’22
C45: Esyasoft’s exit: received $412k principal plus $59k as accrued interest on 7-Dec
B46: Nov’22
C47: Capital Call from Acies Investments Fund-I of $3.4m
C48: New investment in eSpace SAFE note via Mozn of $15.0m
B49: October 22
D50: 1) $4.75m Signing Payment for AAICO
D51: 2) $3.4m 4th capital call Acies
D52: 3) Honor booked at $1.2B cost
D53: 4) NAV of Heygears updated to $114.2m as of Oct 22

Sheet 5. CF Profile
C2: CASH DEPLOYED OVER TIME…
C5: Investment | D5: Type | E5: Payment date | F5: Period | G5: Contribution | H5: Distribution | J5: Contribution | K5: Equity | L5: Debt | M5: Fund | N5: Total | P5: Distribution | Q5: Equity | R5: Debt | S5: Fund | T5: Total
B6: Equity | C6: ='CF (Equity, Debt)'!C4 -> Jollychic Holding Limited | D6: Equity | E6: ='CF (Equity, Debt)'!D4 -> 43470 | F6: ="Q"&ROUNDUP(MONTH(E6)/3,0)&" "&YEAR(E6) -> Q1 2019 | G6: ='CF (Equity, Debt)'!E4 -> -30 | H6: ='CF (Equity, Debt)'!F4 -> 0
C7: ='CF (Equity, Debt)'!C5 -> Jollychic Holding Limited | D7: Equity | E7: ='CF (Equity, Debt)'!D5 -> 43724 | F7: ="Q"&ROUNDUP(MONTH(E7)/3,0)&" "&YEAR(E7) -> Q3 2019 | G7: ='CF (Equity, Debt)'!E5 -> -20 | H7: ='CF (Equity, Debt)'!F5 -> 0 | J7: Q1 2019 | K7: =-SUMIFS($G$5:$G$125,$D$5:$D$125,$K$5,$F$5:$F$125,J7) -> 30 | L7: =-SUMIFS($G$5:$G$125,$D$5:$D$125,$L$5,$F$5:$F$125,J7) -> 0 | M7: =-SUMIFS($G$5:$G$125,$D$5:$D$125,"Fund",$F$5:$F$125,J7) -> 0 | N7: =-SUMIF($F$5:$H$125,$J7,$G$5:$G$125) -> 30 | P7: Q1 2019 | Q7: =SUMIFS($H$5:$H$125,$D$5:$D$125,$Q$5,$F$5:$F$125,J7) -> 0 | R7: =SUMIFS($H$5:$H$125,$D$5:$D$125,$R$5,$F$5:$F$125,J7) -> 0 | S7: =SUMIFS($H$5:$H$125,$D$5:$D$125,$S$5,$F$5:$F$125,J7) -> 0 | T7: =SUMIF($F$5:$H$125,$J7,$H$5:$H$125) -> 0
C8: ='CF (Equity, Debt)'!C6 -> Jollychic Holding Limited | D8: Equity | E8: ='CF (Equity, Debt)'!D6 -> 43724 | F8: ="Q"&ROUNDUP(MONTH(E8)/3,0)&" "&YEAR(E8) -> Q3 2019 | G8: ='CF (Equity, Debt)'!E6 -> -15 | H8: ='CF (Equity, Debt)'!F6 -> 0 | J8: Q2 2019 | K8: =-SUMIFS($G$5:$G$125,$D$5:$D$125,$K$5,$F$5:$F$125,J8) -> 12.999998 | L8: =-SUMIFS($G$5:$G$125,$D$5:$D$125,$L$5,$F$5:$F$125,J8) -> 8 | M8: =-SUMIFS($G$5:$G$125,$D$5:$D$125,"Fund",$F$5:$F$125,J8) -> 0 | N8: =-SUMIF($F$5:$H$125,$J8,$G$5:$G$125) -> 20.999998 | P8: Q2 2019 | Q8: =SUMIFS($H$5:$H$125,$D$5:$D$125,$Q$5,$F$5:$F$125,J8) -> 0 | R8: =SUMIFS($H$5:$H$125,$D$5:$D$125,$R$5,$F$5:$F$125,J8) -> 0 | S8: =SUMIFS($H$5:$H$125,$D$5:$D$125,$S$5,$F$5:$F$125,J8) -> 0 | T8: =SUMIF($F$5:$H$125,$J8,$H$5:$H$125) -> 0
C9: ='CF (Equity, Debt)'!C7 -> Mena Mobile Inc | D9: Equity | E9: ='CF (Equity, Debt)'!D7 -> 43563 | F9: ="Q"&ROUNDUP(MONTH(E9)/3,0)&" "&YEAR(E9) -> Q2 2019 | G9: ='CF (Equity, Debt)'!E7 -> -8 | H9: ='CF (Equity, Debt)'!F7 -> 0 | J9: Q3 2019 | K9: =-SUMIFS($G$5:$G$125,$D$5:$D$125,$K$5,$F$5:$F$125,J9) -> 35 | L9: =-SUMIFS($G$5:$G$125,$D$5:$D$125,$L$5,$F$5:$F$125,J9) -> 0 | M9: =-SUMIFS($G$5:$G$125,$D$5:$D$125,"Fund",$F$5:$F$125,J9) -> 3 | N9: =-SUMIF($F$5:$H$125,$J9,$G$5:$G$125) -> 38 | P9: Q3 2019 | Q9: =SUMIFS($H$5:$H$125,$D$5:$D$125,$Q$5,$F$5:$F$125,J9) -> 0 | R9: =SUMIFS($H$5:$H$125,$D$5:$D$125,$R$5,$F$5:$F$125,J9) -> 0 | S9: =SUMIFS($H$5:$H$125,$D$5:$D$125,$S$5,$F$5:$F$125,J9) -> 0 | T9: =SUMIF($F$5:$H$125,$J9,$H$5:$H$125) -> 0
C10: ='CF (Equity, Debt)'!C8 -> Flyr Inc | D10: Equity | E10: ='CF (Equity, Debt)'!D8 -> 43570 | F10: ="Q"&ROUNDUP(MONTH(E10)/3,0)&" "&YEAR(E10) -> Q2 2019 | G10: ='CF (Equity, Debt)'!E8 -> -4.9999981 | H10: ='CF (Equity, Debt)'!F8 -> 0 | J10: Q4 2019 | K10: =-SUMIFS($G$5:$G$125,$D$5:$D$125,$K$5,$F$5:$F$125,J10) -> 0 | L10: =-SUMIFS($G$5:$G$125,$D$5:$D$125,$L$5,$F$5:$F$125,J10) -> 0 | M10: =-SUMIFS($G$5:$G$125,$D$5:$D$125,"Fund",$F$5:$F$125,J10) -> 0 | N10: =-SUMIF($F$5:$H$125,$J10,$G$5:$G$125) -> 0 | P10: Q4 2019 | Q10: =SUMIFS($H$5:$H$125,$D$5:$D$125,$Q$5,$F$5:$F$125,J10) -> 0 | R10: =SUMIFS($H$5:$H$125,$D$5:$D$125,$R$5,$F$5:$F$125,J10) -> 0 | S10: =SUMIFS($H$5:$H$125,$D$5:$D$125,$S$5,$F$5:$F$125,J10) -> 0 | T10: =SUMIF($F$5:$H$125,$J10,$H$5:$H$125) -> 0
C11: ='CF (Equity, Debt)'!C9 -> Flyr Inc | D11: Equity | E11: ='CF (Equity, Debt)'!D9 -> 43915 | F11: ="Q"&ROUNDUP(MONTH(E11)/3,0)&" "&YEAR(E11) -> Q1 2020 | G11: ='CF (Equity, Debt)'!E9 -> -5.0000019 | H11: ='CF (Equity, Debt)'!F9 -> 0 | J11: Q1 2020 | K11: =-SUMIFS($G$5:$G$125,$D$5:$D$125,$K$5,$F$5:$F$125,J11) -> 75.609443 | L11: =-SUMIFS($G$5:$G$125,$D$5:$D$125,$L$5,$F$5:$F$125,J11) -> 0 | M11: =-SUMIFS($G$5:$G$125,$D$5:$D$125,"Fund",$F$5:$F$125,J11) -> 9.50975 | N11: =-SUMIF($F$5:$H$125,$J11,$G$5:$G$125) -> 85.119193 | P11: Q1 2020 | Q11: =SUMIFS($H$5:$H$125,$D$5:$D$125,$Q$5,$F$5:$F$125,J11) -> 0 | R11: =SUMIFS($H$5:$H$125,$D$5:$D$125,$R$5,$F$5:$F$125,J11) -> 0 | S11: =SUMIFS($H$5:$H$125,$D$5:$D$125,$S$5,$F$5:$F$125,J11) -> 0 | T11: =SUMIF($F$5:$H$125,$J11,$H$5:$H$125) -> 0
C12: ='CF (Equity, Debt)'!C10 -> Esyasoft Holding | D12: Equity | E12: ='CF (Equity, Debt)'!D10 -> 43870 | F12: ="Q"&ROUNDUP(MONTH(E12)/3,0)&" "&YEAR(E12) -> Q1 2020 | G12: ='CF (Equity, Debt)'!E10 -> -2.5 | H12: ='CF (Equity, Debt)'!F10 -> 0 | J12: Q2 2020 | K12: =-SUMIFS($G$5:$G$125,$D$5:$D$125,$K$5,$F$5:$F$125,J12) -> 142.12004 | L12: =-SUMIFS($G$5:$G$125,$D$5:$D$125,$L$5,$F$5:$F$125,J12) -> 0 | M12: =-SUMIFS($G$5:$G$125,$D$5:$D$125,"Fund",$F$5:$F$125,J12) -> 45.785 | N12: =-SUMIF($F$5:$H$125,$J12,$G$5:$G$125) -> 187.90504 | P12: Q2 2020 | Q12: =SUMIFS($H$5:$H$125,$D$5:$D$125,$Q$5,$F$5:$F$125,J12) -> 0 | R12: =SUMIFS($H$5:$H$125,$D$5:$D$125,$R$5,$F$5:$F$125,J12) -> 0 | S12: =SUMIFS($H$5:$H$125,$D$5:$D$125,$S$5,$F$5:$F$125,J12) -> 0 | T12: =SUMIF($F$5:$H$125,$J12,$H$5:$H$125) -> 0
C13: ='CF (Equity, Debt)'!C11 -> Beyond Limits | D13: Equity | E13: ='CF (Equity, Debt)'!D11 -> 43879 | F13: ="Q"&ROUNDUP(MONTH(E13)/3,0)&" "&YEAR(E13) -> Q1 2020 | G13: ='CF (Equity, Debt)'!E11 -> -20 | H13: ='CF (Equity, Debt)'!F11 -> 0 | J13: Q3 2020 | K13: =-SUMIFS($G$5:$G$125,$D$5:$D$125,$K$5,$F$5:$F$125,J13) -> 10 | L13: =-SUMIFS($G$5:$G$125,$D$5:$D$125,$L$5,$F$5:$F$125,J13) -> 0 | M13: =-SUMIFS($G$5:$G$125,$D$5:$D$125,"Fund",$F$5:$F$125,J13) -> 23.623435 | N13: =-SUMIF($F$5:$H$125,$J13,$G$5:$G$125) -> 33.623435 | P13: Q3 2020 | Q13: =SUMIFS($H$5:$H$125,$D$5:$D$125,$Q$5,$F$5:$F$125,J13) -> 0 | R13: =SUMIFS($H$5:$H$125,$D$5:$D$125,$R$5,$F$5:$F$125,J13) -> 0 | S13: =SUMIFS($H$5:$H$125,$D$5:$D$125,$S$5,$F$5:$F$125,J13) -> 0 | T13: =SUMIF($F$5:$H$125,$J13,$H$5:$H$125) -> 0
C14: ='CF (Equity, Debt)'!C12 -> Beyond Limits | D14: Equity | E14: ='CF (Equity, Debt)'!D12 -> 43921 | F14: ="Q"&ROUNDUP(MONTH(E14)/3,0)&" "&YEAR(E14) -> Q1 2020 | G14: ='CF (Equity, Debt)'!E12 -> -30 | H14: ='CF (Equity, Debt)'!F12 -> 0 | J14: Q4 2020 | K14: =-SUMIFS($G$5:$G$125,$D$5:$D$125,$K$5,$F$5:$F$125,J14) -> 60 | L14: =-SUMIFS($G$5:$G$125,$D$5:$D$125,$L$5,$F$5:$F$125,J14) -> 0 | M14: =-SUMIFS($G$5:$G$125,$D$5:$D$125,"Fund",$F$5:$F$125,J14) -> 9.482293 | N14: =-SUMIF($F$5:$H$125,$J14,$G$5:$G$125) -> 69.482293 | P14: Q4 2020 | Q14: =SUMIFS($H$5:$H$125,$D$5:$D$125,$Q$5,$F$5:$F$125,J14) -> 0 | R14: =SUMIFS($H$5:$H$125,$D$5:$D$125,$R$5,$F$5:$F$125,J14) -> 0 | S14: =SUMIFS($H$5:$H$125,$D$5:$D$125,$S$5,$F$5:$F$125,J14) -> 0.582902 | T14: =SUMIF($F$5:$H$125,$J14,$H$5:$H$125) -> 0.582902
C15: ='CF (Equity, Debt)'!C13 -> Beyond Limits | D15: Equity | E15: ='CF (Equity, Debt)'!D13 -> 43989 | F15: ="Q"&ROUNDUP(MONTH(E15)/3,0)&" "&YEAR(E15) -> Q2 2020 | G15: ='CF (Equity, Debt)'!E13 -> -30 | H15: ='CF (Equity, Debt)'!F13 -> 0 | J15: Q1 2021 | K15: =-SUMIFS($G$5:$G$125,$D$5:$D$125,$K$5,$F$5:$F$125,J15) -> 0 | L15: =-SUMIFS($G$5:$G$125,$D$5:$D$125,$L$5,$F$5:$F$125,J15) -> 0 | M15: =-SUMIFS($G$5:$G$125,$D$5:$D$125,"Fund",$F$5:$F$125,J15) -> 1.0845116 | N15: =-SUMIF($F$5:$H$125,$J15,$G$5:$G$125) -> 1.0845116 | P15: Q1 2021 | Q15: =SUMIFS($H$5:$H$125,$D$5:$D$125,$Q$5,$F$5:$F$125,J15) -> 0 | R15: =SUMIFS($H$5:$H$125,$D$5:$D$125,$R$5,$F$5:$F$125,J15) -> 0 | S15: =SUMIFS($H$5:$H$125,$D$5:$D$125,$S$5,$F$5:$F$125,J15) -> 0.07634835 | T15: =SUMIF($F$5:$H$125,$J15,$H$5:$H$125) -> 0.07634835
C16: ='CF (Equity, Debt)'!C14 -> Beyond Limits | D16: Equity | E16: ='CF (Equity, Debt)'!D14 -> 44103 | F16: ="Q"&ROUNDUP(MONTH(E16)/3,0)&" "&YEAR(E16) -> Q3 2020 | G16: ='CF (Equity, Debt)'!E14 -> -10 | H16: ='CF (Equity, Debt)'!F14 -> 0 | J16: Q2 2021 | K16: =-SUMIFS($G$5:$G$125,$D$5:$D$125,$K$5,$F$5:$F$125,J16) -> 31.24078 | L16: =-SUMIFS($G$5:$G$125,$D$5:$D$125,$L$5,$F$5:$F$125,J16) -> 2.353982 | M16: =-SUMIFS($G$5:$G$125,$D$5:$D$125,"Fund",$F$5:$F$125,J16) -> 6.1810318 | N16: =-SUMIF($F$5:$H$125,$J16,$G$5:$G$125) -> 39.775794 | P16: Q2 2021 | Q16: =SUMIFS($H$5:$H$125,$D$5:$D$125,$Q$5,$F$5:$F$125,J16) -> 0 | R16: =SUMIFS($H$5:$H$125,$D$5:$D$125,$R$5,$F$5:$F$125,J16) -> 0 | S16: =SUMIFS($H$5:$H$125,$D$5:$D$125,$S$5,$F$5:$F$125,J16) -> 0 | T16: =SUMIF($F$5:$H$125,$J16,$H$5:$H$125) -> 0
