Workbook
Name Company: #REF!
Name Dates: #REF!
Name DetailedCapShares: #REF!
Name FAGroup: #REF!
Name IQ_CH: 110000
Name IQ_CQ: 5000
Name IQ_CY: 10000
Name IQ_DAILY: 500000
Name IQ_FH: 100000
Name IQ_FQ: 500
Name IQ_FY: 1000
Name IQ_LTM: 2000
Name IQ_MONTH: 15000
Name IQ_NTM: 6000
Name IQ_WEEK: 50000
Name IQ_YTD: 3000
Name UNLOCKED_PERCENT_FAST: _xludf.LAMBDA(start_date, date, IF(start_date="",0,MIN(1,MAX(0,(date-EDATE(start_date,12)+1)/(EDATE(start_date,36)-EDATE(start_date,12))))))
Name UNLOCKED_PERCENT_SLOW: _xludf.LAMBDA(start_date, date, IF(start_date="",0, MIN(1,MAX(0,(date-EDATE(start_date,12)+1)/(EDATE(start_date,60)-EDATE(start_date,12))))))

Sheet D1
B2: Date of NAV | D2: 45900 | E2: =TEXT(D2,"dddddd") -> Sunday
H4: D A S H B O A R D
B6: L I V E D E A L S (includes unrealized or partially realized investments)
E8: # Investments | F8: Committed | G8: Invested | H8: Remaining | I8: Distributions | J8: Residual Value | K8: Gain | L8: TVPI | M8: DPI
E9: # | F9: USD, Mn | G9: USD, Mn | H9: USD, Mn | I9: USD, Mn | J9: USD, Mn | K9: USD, Mn | L9: X | M9: X
C11: EQUITY* | D11: Direct Investment | E11: =COUNTIF('1. Live'!$D$1:D25,$D11) -> 12 | F11: =SUMIF('1. Live'!$D$1:$D$110,$D11,'1. Live'!K$1:K$110) -> 1106.018 | G11: =SUMIF('1. Live'!$D$1:$D$110,$D11,'1. Live'!L$1:L$110) -> 947.50137 | H11: =SUMIF('1. Live'!$D$1:$D$110,$D11,'1. Live'!M$1:M$110) -> 158.51663 | I11: =SUMIF('1. Live'!$D$1:$D$110,$D11,'1. Live'!N$1:N$110) -> 85.304451 | J11: =SUMIF('1. Live'!$D$1:$D$110,$D11,'1. Live'!O$1:O$110) -> 878.23664 | K11: =SUMIF('1. Live'!$D$1:$D$110,$D11,'1. Live'!P$1:P$110) -> 16.039713 | L11: =IFERROR((I11+J11)/G11,"") -> 1.0169284 | M11: =IFERROR(I11/G11,"") -> 0.090030952
C13: DEBT | D13: Debt Investment | E13: =COUNTIF('1. Live'!$D$1:D27,$D13) -> 0 | F13: =SUMIF('1. Live'!$D$1:$D$110,$D13,'1. Live'!K$1:K$110) -> 0 | G13: =SUMIF('1. Live'!$D$1:$D$110,$D13,'1. Live'!L$1:L$110) -> 0 | H13: =SUMIF('1. Live'!$D$1:$D$110,$D13,'1. Live'!M$1:M$110) -> 0 | I13: =SUMIF('1. Live'!$D$1:$D$110,$D13,'1. Live'!N$1:N$110) -> 0 | J13: =SUMIF('1. Live'!$D$1:$D$110,$D13,'1. Live'!O$1:O$110) -> 0 | K13: =SUMIF('1. Live'!$D$1:$D$110,$D13,'1. Live'!P$1:P$110) -> 0 | L13: =IFERROR((I13+J13)/G13,"") | M13: =IFERROR(I13/G13,"")
C15: FUNDS | D15: Fund Investment | E15: =COUNTIF('1. Live'!$D$1:D29,$D15) -> 4 | F15: =SUMIF('1. Live'!$D$1:$D$110,$D15,'1. Live'!K$1:K$110) -> 132.83985 | G15: =SUMIF('1. Live'!$D$1:$D$110,$D15,'1. Live'!L$1:L$110) -> 120.90243 | H15: =SUMIF('1. Live'!$D$1:$D$110,$D15,'1. Live'!M$1:M$110) -> 11.937429 | I15: =SUMIF('1. Live'!$D$1:$D$110,$D15,'1. Live'!N$1:N$110) -> 11.668277 | J15: =SUMIF('1. Live'!$D$1:$D$110,$D15,'1. Live'!O$1:O$110) -> 106.52706 | K15: =SUMIF('1. Live'!$D$1:$D$110,$D15,'1. Live'!P$1:P$110) -> -2.7070901 | L15: =IFERROR((I15+J15)/G15,"") -> 0.9776093 | M15: =IFERROR(I15/G15,"") -> 0.096509869
C17: MGX | D17: MGX related | E17: 4 | F17: ='1. Live'!K52 -> 2000 | G17: ='1. Live'!L52 -> 547.72831 | H17: ='1. Live'!M52 -> 1452.2717 | I17: ='1. Live'!N52 -> 0 | J17: ='1. Live'!O52 -> 747.273 | K17: ='1. Live'!P52 -> 199.5447 | L17: =IFERROR((I17+J17)/G17,"") -> 1.3643133 | M17: =IFERROR(I17/G17,"") -> 0
C19: TOTAL | E19: =E11+E13+E15 -> 16 | F19: =F11+F13+F15+F17 -> 3238.8579 | G19: =G11+G13+G15+G17 -> 1616.1321 | H19: =H11+H13+H15+H17 -> 1622.7258 | I19: =I11+I13+I15+I17 -> 96.972728 | J19: =J11+J13+J15+J17 -> 1732.0367 | K19: =K11+K13+K15+K17 -> 212.87732 | L19: =IFERROR((I19+J19)/G19,"") -> 1.1317202 | M19: =IFERROR(I19/G19,"") -> 0.060002971
B22: E X I T E D D E A L S (includes liquidated, written-off or completely exited investments)
E24: # Investments | F24: Committed | G24: Invested | H24: Remaining | I24: Distributions | J24: Residual Value | K24: Gain | L24: TVPI | M24: DPI
E25: # | F25: USD, Mn | G25: USD, Mn | H25: USD, Mn | I25: USD, Mn | J25: USD, Mn | K25: USD, Mn | L25: X | M25: X
C27: EQUITY* | D27: Direct Investment | E27: =COUNTIF('2. Exited'!$D$1:D41,$D27) -> 8 | F27: =SUMIF('2. Exited'!$D$1:$D$41,$D27,'2. Exited'!K$1:K$41) -> 1394.0316 | G27: =SUMIF('2. Exited'!$D$1:$D$41,$D27,'2. Exited'!L$1:L$41) -> 1394.0316 | H27: =SUMIF('2. Exited'!$D$1:$D$41,$D27,'2. Exited'!M$1:M$41) -> 0 | I27: =SUMIF('2. Exited'!$D$1:$D$41,$D27,'2. Exited'!N$1:N$41) -> 1343.2422 | J27: =SUMIF('2. Exited'!$D$1:$D$41,$D27,'2. Exited'!O$1:O$41) -> 0 | K27: =SUMIF('2. Exited'!$D$1:$D$41,$D27,'2. Exited'!P$1:P$41) -> -50.789359 | L27: =IFERROR((I27+J27)/G27,"") -> 0.96356656 | M27: =IFERROR(I27/G27,"") -> 0.96356656
C29: DEBT | D29: Debt Investment | E29: =COUNTIF('2. Exited'!$D$1:D43,$D29) -> 3 | F29: =SUMIF('2. Exited'!$D$1:$D$41,$D29,'2. Exited'!K$1:K$41) -> 10.765747 | G29: =SUMIF('2. Exited'!$D$1:$D$41,$D29,'2. Exited'!L$1:L$41) -> 10.765747 | H29: =SUMIF('2. Exited'!$D$1:$D$41,$D29,'2. Exited'!M$1:M$41) -> 0 | I29: =SUMIF('2. Exited'!$D$1:$D$41,$D29,'2. Exited'!N$1:N$41) -> 0.47078465 | J29: =SUMIF('2. Exited'!$D$1:$D$41,$D29,'2. Exited'!O$1:O$41) -> 0 | K29: =SUMIF('2. Exited'!$D$1:$D$41,$D29,'2. Exited'!P$1:P$41) -> -10.294962 | L29: =IFERROR((I29+J29)/G29,"") -> 0.043729864 | M29: =IFERROR(I29/G29,"") -> 0.043729864
C31: FUNDS | D31: Fund Investment | E31: =COUNTIF('2. Exited'!$D$1:D45,$D31) -> 1 | F31: =SUMIF('2. Exited'!$D$1:$D$41,$D31,'2. Exited'!K$1:K$41) -> 50 | G31: =SUMIF('2. Exited'!$D$1:$D$41,$D31,'2. Exited'!L$1:L$41) -> 24.959693 | H31: =SUMIF('2. Exited'!$D$1:$D$41,$D31,'2. Exited'!M$1:M$41) -> 0 | I31: =SUMIF('2. Exited'!$D$1:$D$41,$D31,'2. Exited'!N$1:N$41) -> 25.403521 | J31: =SUMIF('2. Exited'!$D$1:$D$41,$D31,'2. Exited'!O$1:O$41) -> 0 | K31: =SUMIF('2. Exited'!$D$1:$D$41,$D31,'2. Exited'!P$1:P$41) -> 0.44382835 | L31: =IFERROR((I31+J31)/G31,"") -> 1.0177818 | M31: =IFERROR(I31/G31,"") -> 1.0177818
C33: TOTAL | E33: =E27+E29+E31 -> 12 | F33: =F27+F29+F31 -> 1454.7973 | G33: =G27+G29+G31 -> 1429.757 | H33: =H27+H29+H31 -> 0 | I33: =I27+I29+I31 -> 1369.1165 | J33: =J27+J29+J31 -> 0 | K33: =K27+K29+K31 -> -60.640493 | L33: =IFERROR((I33+J33)/G33,"") -> 0.95758685 | M33: =IFERROR(I33/G33,"") -> 0.95758685
B36: * Includes Convertibles
E38: CHECKS | F38: =ROUND(F19,5)=ROUND('1. Live'!K54,5) -> TRUE | G38: =ROUND(G19,5)=ROUND('1. Live'!L54,5) -> TRUE | H38: =ROUND(H19,5)=ROUND('1. Live'!M54,5) -> TRUE | I38: =ROUND(I19,5)=ROUND('1. Live'!N54,5) -> TRUE | J38: =ROUND(J19,5)=ROUND('1. Live'!O54,5) -> TRUE | K38: =ROUND(K19,5)=ROUND('1. Live'!P54,5) -> TRUE
F39: =F33='2. Exited'!K36 -> TRUE | G39: =G33='2. Exited'!L36 -> TRUE | H39: =H33='2. Exited'!M36 -> TRUE | I39: =I33='2. Exited'!N36 -> TRUE | J39: =J33='2. Exited'!O36 -> TRUE | K39: =K33='2. Exited'!P36 -> TRUE
F40: TRUE | G40: TRUE | H40: TRUE | I40: TRUE | J40: TRUE | K40: TRUE

Sheet 1. Live
C2: As of date | D2: ='D1'!D2 -> 45900
E5: 2 | F5: 3 | G5: 4 | H5: 5 | I5: 6 | J5: 7 | K5: 8 | L5: 9 | M5: 10 | N5: 11 | O5: 12 | P5: 13 | R5: 14 | S5: 15
C6: Deals | D6: Type | E6: Status | F6: Lead | G6: Investing Entity | H6: Vintageἀ | I6: Instrument | J6: % | K6: Committed | L6: Invested | M6: Remaining Commitment | N6: Distributions | O6: Carrying Value | P6: Gain | Q6: Gain till FY22 | R6: TVPI | S6: Additonal Upside/Downside
I7: # | J7: % | K7: $,m | L7: $,m | M7: $,m | N7: $,m | O7: $,m | P7: $,m | R7: X
C8: MOZN Holding RSC Ltd
C9: E-line Ventures LLC | D9: Direct Investment | E9: =VLOOKUP($C9,'A. All deals (a)'!$C$6:$Q$58,E$5,0) -> Unrealized | F9: =VLOOKUP($C9,'A. All deals (a)'!$C$6:$Q$58,F$5,0) -> 0 | G9: =VLOOKUP($C9,'A. All deals (a)'!$C$6:$Q$58,G$5,0) -> Mozn | H9: =VLOOKUP($C9,'A. All deals (a)'!$C$6:$Q$58,H$5,0) -> 2023 | I9: =VLOOKUP($C9,'A. All deals (a)'!$C$6:$Q$58,I$5,0) -> B Prefs | J9: =VLOOKUP($C9,'A. All deals (a)'!$C$6:$Q$58,J$5,0) -> 0.11483736 | K9: =VLOOKUP($C9,'A. All deals (a)'!$C$6:$Q$58,K$5,0) -> 6 | L9: =VLOOKUP($C9,'A. All deals (a)'!$C$6:$Q$58,L$5,0) -> 6 | ... P9: =VLOOKUP($C9,'A. All deals (a)'!$C$6:$Q$58,P$5,0) -> 9.3 | Q9: n/a | R9: =VLOOKUP($C9,'A. All deals (a)'!$C$6:$Q$58,R$5,0) -> 2.55 | S9: Optionse
C10: Tools for Humanity Corporation | D10: Direct Investment | E10: =VLOOKUP($C10,'A. All deals (a)'!$C$6:$Q$58,E$5,0) -> Unrealized | F10: =VLOOKUP($C10,'A. All deals (a)'!$C$6:$Q$58,F$5,0) -> 0 | G10: =VLOOKUP($C10,'A. All deals (a)'!$C$6:$Q$58,G$5,0) -> Mozn | H10: =VLOOKUP($C10,'A. All deals (a)'!$C$6:$Q$58,H$5,0) -> 2023 | I10: =VLOOKUP($C10,'A. All deals (a)'!$C$6:$Q$58,I$5,0) -> C Prefs | J10: =VLOOKUP($C10,'A. All deals (a)'!$C$6:$Q$58,J$5,0) -> 0.00626608 | K10: =VLOOKUP($C10,'A. All deals (a)'!$C$6:$Q$58,K$5,0) -> 14.999999 | L10: =VLOOKUP($C10,'A. All deals (a)'!$C$6:$Q$58,L$5,0) -> 14.999999 | ... P10: =VLOOKUP($C10,'A. All deals (a)'!$C$6:$Q$58,P$5,0) -> -12.599999 | Q10: n/a | R10: =VLOOKUP($C10,'A. All deals (a)'!$C$6:$Q$58,R$5,0) -> 0.16000001
C11: eSpace | D11: Direct Investment | E11: =VLOOKUP($C11,'A. All deals (a)'!$C$6:$Q$58,E$5,0) -> Unrealized | F11: =VLOOKUP($C11,'A. All deals (a)'!$C$6:$Q$58,F$5,0) -> 0 | G11: =VLOOKUP($C11,'A. All deals (a)'!$C$6:$Q$58,G$5,0) -> Mozn 4 | H11: =VLOOKUP($C11,'A. All deals (a)'!$C$6:$Q$58,H$5,0) -> 2022 | I11: =VLOOKUP($C11,'A. All deals (a)'!$C$6:$Q$58,I$5,0) -> B Prefs | J11: =VLOOKUP($C11,'A. All deals (a)'!$C$6:$Q$58,J$5,0) -> 0.026056201 | K11: =VLOOKUP($C11,'A. All deals (a)'!$C$6:$Q$58,K$5,0) -> 15 | L11: =VLOOKUP($C11,'A. All deals (a)'!$C$6:$Q$58,L$5,0) -> 15 | ... P11: =VLOOKUP($C11,'A. All deals (a)'!$C$6:$Q$58,P$5,0) -> 17.34128 | Q11: 0 | R11: =VLOOKUP($C11,'A. All deals (a)'!$C$6:$Q$58,R$5,0) -> 2.1560854
C12: Applied AI Corporation Limited | D12: Direct Investment | E12: =VLOOKUP($C12,'A. All deals (a)'!$C$6:$Q$58,E$5,0) -> Unrealized | F12: =VLOOKUP($C12,'A. All deals (a)'!$C$6:$Q$58,F$5,0) -> 0 | G12: =VLOOKUP($C12,'A. All deals (a)'!$C$6:$Q$58,G$5,0) -> Mozn | H12: =VLOOKUP($C12,'A. All deals (a)'!$C$6:$Q$58,H$5,0) -> 2022 | I12: =VLOOKUP($C12,'A. All deals (a)'!$C$6:$Q$58,I$5,0) -> A Prefs | J12: =VLOOKUP($C12,'A. All deals (a)'!$C$6:$Q$58,J$5,0) -> 0.12121516 | K12: =VLOOKUP($C12,'A. All deals (a)'!$C$6:$Q$58,K$5,0) -> 15 | L12: =VLOOKUP($C12,'A. All deals (a)'!$C$6:$Q$58,L$5,0) -> 15 | ... P12: =VLOOKUP($C12,'A. All deals (a)'!$C$6:$Q$58,P$5,0) -> 23.46473 | Q12: 0 | R12: =VLOOKUP($C12,'A. All deals (a)'!$C$6:$Q$58,R$5,0) -> 2.5643153
C13: Cerebras Systems Inc | D13: Direct Investment | E13: =VLOOKUP($C13,'A. All deals (a)'!$C$6:$Q$58,E$5,0) -> Unrealized | F13: =VLOOKUP($C13,'A. All deals (a)'!$C$6:$Q$58,F$5,0) -> 0 | G13: =VLOOKUP($C13,'A. All deals (a)'!$C$6:$Q$58,G$5,0) -> Mozn | H13: =VLOOKUP($C13,'A. All deals (a)'!$C$6:$Q$58,H$5,0) -> 2021 | I13: =VLOOKUP($C13,'A. All deals (a)'!$C$6:$Q$58,I$5,0) -> F Prefs | J13: =VLOOKUP($C13,'A. All deals (a)'!$C$6:$Q$58,J$5,0) -> 0.0081 | K13: =VLOOKUP($C13,'A. All deals (a)'!$C$6:$Q$58,K$5,0) -> 39.999983 | L13: =VLOOKUP($C13,'A. All deals (a)'!$C$6:$Q$58,L$5,0) -> 39.999983 | ... P13: =VLOOKUP($C13,'A. All deals (a)'!$C$6:$Q$58,P$5,0) -> -18.8645 | Q13: 0 | R13: =VLOOKUP($C13,'A. All deals (a)'!$C$6:$Q$58,R$5,0) -> 0.5283873
C14: Endless Studios LLC | D14: Direct Investment | E14: =VLOOKUP($C14,'A. All deals (a)'!$C$6:$Q$58,E$5,0) -> Unrealized | F14: =VLOOKUP($C14,'A. All deals (a)'!$C$6:$Q$58,F$5,0) -> 0 | G14: =VLOOKUP($C14,'A. All deals (a)'!$C$6:$Q$58,G$5,0) -> Mozn | H14: =VLOOKUP($C14,'A. All deals (a)'!$C$6:$Q$58,H$5,0) -> 2021 | I14: =VLOOKUP($C14,'A. All deals (a)'!$C$6:$Q$58,I$5,0) -> A Pref Units | J14: =VLOOKUP($C14,'A. All deals (a)'!$C$6:$Q$58,J$5,0) -> 0.15458937 | K14: =VLOOKUP($C14,'A. All deals (a)'!$C$6:$Q$58,K$5,0) -> 8 | L14: =VLOOKUP($C14,'A. All deals (a)'!$C$6:$Q$58,L$5,0) -> 8 | ... P14: =VLOOKUP($C14,'A. All deals (a)'!$C$6:$Q$58,P$5,0) -> -3.3 | Q14: 0 | R14: =VLOOKUP($C14,'A. All deals (a)'!$C$6:$Q$58,R$5,0) -> 0.5875
C15: Heygears | D15: Direct Investment | E15: =VLOOKUP($C15,'A. All deals (a)'!$C$6:$Q$58,E$5,0) -> Unrealized | F15: =VLOOKUP($C15,'A. All deals (a)'!$C$6:$Q$58,F$5,0) -> 0 | G15: =VLOOKUP($C15,'A. All deals (a)'!$C$6:$Q$58,G$5,0) -> Mozn | H15: =VLOOKUP($C15,'A. All deals (a)'!$C$6:$Q$58,H$5,0) -> 2020 | I15: =VLOOKUP($C15,'A. All deals (a)'!$C$6:$Q$58,I$5,0) -> Registered Capital | J15: =VLOOKUP($C15,'A. All deals (a)'!$C$6:$Q$58,J$5,0) -> 0.14383199 | K15: =VLOOKUP($C15,'A. All deals (a)'!$C$6:$Q$58,K$5,0) -> 60 | L15: =VLOOKUP($C15,'A. All deals (a)'!$C$6:$Q$58,L$5,0) -> 60 | ... P15: =VLOOKUP($C15,'A. All deals (a)'!$C$6:$Q$58,P$5,0) -> -19.7 | Q15: 96.4 | R15: =VLOOKUP($C15,'A. All deals (a)'!$C$6:$Q$58,R$5,0) -> 0.67166667
C16: Beyond Limits | D16: Direct Investment | E16: =VLOOKUP($C16,'A. All deals (a)'!$C$6:$Q$58,E$5,0) -> Unrealized | F16: =VLOOKUP($C16,'A. All deals (a)'!$C$6:$Q$58,F$5,0) -> 0 | G16: =VLOOKUP($C16,'A. All deals (a)'!$C$6:$Q$58,G$5,0) -> Mozn | H16: =VLOOKUP($C16,'A. All deals (a)'!$C$6:$Q$58,H$5,0) -> 2020 | I16: =VLOOKUP($C16,'A. All deals (a)'!$C$6:$Q$58,I$5,0) -> C Prefs | J16: =VLOOKUP($C16,'A. All deals (a)'!$C$6:$Q$58,J$5,0) -> 0.094347728 | K16: =VLOOKUP($C16,'A. All deals (a)'!$C$6:$Q$58,K$5,0) -> 90 | L16: =VLOOKUP($C16,'A. All deals (a)'!$C$6:$Q$58,L$5,0) -> 90 | ... P16: =VLOOKUP($C16,'A. All deals (a)'!$C$6:$Q$58,P$5,0) -> -48.996296 | Q16: 1.042 | R16: =VLOOKUP($C16,'A. All deals (a)'!$C$6:$Q$58,R$5,0) -> 0.45559671
C17: ONT plc | D17: Direct Investment | E17: =VLOOKUP($C17,'A. All deals (a)'!$C$6:$Q$58,E$5,0) -> Unrealized | F17: =VLOOKUP($C17,'A. All deals (a)'!$C$6:$Q$58,F$5,0) -> 0 | G17: =VLOOKUP($C17,'A. All deals (a)'!$C$6:$Q$58,G$5,0) -> Mozn | H17: =VLOOKUP($C17,'A. All deals (a)'!$C$6:$Q$58,H$5,0) -> 2020 | I17: =VLOOKUP($C17,'A. All deals (a)'!$C$6:$Q$58,I$5,0) -> Ordinary Shares | J17: =VLOOKUP($C17,'A. All deals (a)'!$C$6:$Q$58,J$5,0) -> 0.046395018 | K17: =VLOOKUP($C17,'A. All deals (a)'!$C$6:$Q$58,K$5,0) -> 141.47026 | L17: =VLOOKUP($C17,'A. All deals (a)'!$C$6:$Q$58,L$5,0) -> 141.47026 | ... P17: =VLOOKUP($C17,'A. All deals (a)'!$C$6:$Q$58,P$5,0) -> -33.190285 | Q17: -9.845 | R17: =VLOOKUP($C17,'A. All deals (a)'!$C$6:$Q$58,R$5,0) -> 0.76539038
C18: Flyr Inc | D18: Direct Investment | E18: =VLOOKUP($C18,'A. All deals (a)'!$C$6:$Q$58,E$5,0) -> Unrealized | F18: =VLOOKUP($C18,'A. All deals (a)'!$C$6:$Q$58,F$5,0) -> 0 | G18: =VLOOKUP($C18,'A. All deals (a)'!$C$6:$Q$58,G$5,0) -> Mozn | H18: =VLOOKUP($C18,'A. All deals (a)'!$C$6:$Q$58,H$5,0) -> 2019 | I18: =VLOOKUP($C18,'A. All deals (a)'!$C$6:$Q$58,I$5,0) -> B-1,2 Prefs | J18: =VLOOKUP($C18,'A. All deals (a)'!$C$6:$Q$58,J$5,0) -> 0.035329982 | K18: =VLOOKUP($C18,'A. All deals (a)'!$C$6:$Q$58,K$5,0) -> 10 | L18: =VLOOKUP($C18,'A. All deals (a)'!$C$6:$Q$58,L$5,0) -> 10 | ... P18: =VLOOKUP($C18,'A. All deals (a)'!$C$6:$Q$58,P$5,0) -> 18.213712 | Q18: 68.1 | R18: =VLOOKUP($C18,'A. All deals (a)'!$C$6:$Q$58,R$5,0) -> 2.8213712 | S18: Flyr Warrantsa
K20: =SUM(K9:K18) -> 400.47024 | L20: =SUM(L9:L18) -> 400.47024 | M20: =SUM(M9:M18) -> 0 | N20: =SUM(N9:N18) -> 0 | O20: =SUM(O9:O18) -> 332.13889 | P20: =O20+N20-L20 -> -68.331357 | Q20: =SUM(Q9:Q18) -> 155.697 | R20: =(N20+O20)/L20 -> 0.8293722
C22: G42 Investments AI Holding RSC Ltd
C23: DriveNets | D23: Direct Investment | E23: =VLOOKUP($C23,'A. All deals (a)'!$C$6:$Q$58,E$5,0) -> Partially Realized | F23: =VLOOKUP($C23,'A. All deals (a)'!$C$6:$Q$58,F$5,0) -> 0 | G23: =VLOOKUP($C23,'A. All deals (a)'!$C$6:$Q$58,G$5,0) -> G42 Investments | H23: =VLOOKUP($C23,'A. All deals (a)'!$C$6:$Q$58,H$5,0) -> 2022 | I23: =VLOOKUP($C23,'A. All deals (a)'!$C$6:$Q$58,I$5,0) -> Equity-TBC | J23: =VLOOKUP($C23,'A. All deals (a)'!$C$6:$Q$58,J$5,0) -> 0.0878 | K23: =VLOOKUP($C23,'A. All deals (a)'!$C$6:$Q$58,K$5,0) -> 300 | L23: =VLOOKUP($C23,'A. All deals (a)'!$C$6:$Q$58,L$5,0) -> 300 | ... P23: =VLOOKUP($C23,'A. All deals (a)'!$C$6:$Q$58,P$5,0) -> 110.59541 | Q23: 0 | R23: =VLOOKUP($C23,'A. All deals (a)'!$C$6:$Q$58,R$5,0) -> 1.3686514 | S23: DN Warrants b
C24: vTv Therapeutics Inc. | D24: Direct Investment | E24: =VLOOKUP($C24,'A. All deals (a)'!$C$6:$Q$58,E$5,0) -> Unrealized | F24: =VLOOKUP($C24,'A. All deals (a)'!$C$6:$Q$58,F$5,0) -> 0 | G24: =VLOOKUP($C24,'A. All deals (a)'!$C$6:$Q$58,G$5,0) -> G42 Investments | H24: =VLOOKUP($C24,'A. All deals (a)'!$C$6:$Q$58,H$5,0) -> 2022 | I24: =VLOOKUP($C24,'A. All deals (a)'!$C$6:$Q$58,I$5,0) -> Ordinary Shares | J24: =VLOOKUP($C24,'A. All deals (a)'!$C$6:$Q$58,J$5,0) -> 0.081407233 | K24: =VLOOKUP($C24,'A. All deals (a)'!$C$6:$Q$58,K$5,0) -> 24.53125 | L24: =VLOOKUP($C24,'A. All deals (a)'!$C$6:$Q$58,L$5,0) -> 24.53125 | ... P24: =VLOOKUP($C24,'A. All deals (a)'!$C$6:$Q$58,P$5,0) -> -20.584464 | Q24: -1.348 | R24: =VLOOKUP($C24,'A. All deals (a)'!$C$6:$Q$58,R$5,0) -> 0.16088811 | S24: vTv $30m milestn payment c
C25: North Summit Capital Fund | D25: Fund Investment | E25: =VLOOKUP($C25,'A. All deals (a)'!$C$6:$Q$58,E$5,0) -> Unrealized | F25: =VLOOKUP($C25,'A. All deals (a)'!$C$6:$Q$58,F$5,0) -> 0 | G25: =VLOOKUP($C25,'A. All deals (a)'!$C$6:$Q$58,G$5,0) -> G42 Investments | H25: =VLOOKUP($C25,'A. All deals (a)'!$C$6:$Q$58,H$5,0) -> 2020 | I25: =VLOOKUP($C25,'A. All deals (a)'!$C$6:$Q$58,I$5,0) -> LP | J25: =VLOOKUP($C25,'A. All deals (a)'!$C$6:$Q$58,J$5,0) -> n/a | K25: =VLOOKUP($C25,'A. All deals (a)'!$C$6:$Q$58,K$5,0) -> 83.361611 | L25: =VLOOKUP($C25,'A. All deals (a)'!$C$6:$Q$58,L$5,0) -> 83.361611 | ... P25: =VLOOKUP($C25,'A. All deals (a)'!$C$6:$Q$58,P$5,0) -> -11.257966 | Q25: -0.306 | R25: =VLOOKUP($C25,'A. All deals (a)'!$C$6:$Q$58,R$5,0) -> 0.86495023
C26: New Space Capital Fund I | D26: Fund Investment | E26: =VLOOKUP($C26,'A. All deals (a)'!$C$6:$Q$58,E$5,0) -> Unrealized | F26: =VLOOKUP($C26,'A. All deals (a)'!$C$6:$Q$58,F$5,0) -> 0 | G26: =VLOOKUP($C26,'A. All deals (a)'!$C$6:$Q$58,G$5,0) -> G42 Investments | H26: =VLOOKUP($C26,'A. All deals (a)'!$C$6:$Q$58,H$5,0) -> 2020 | I26: =VLOOKUP($C26,'A. All deals (a)'!$C$6:$Q$58,I$5,0) -> LP | J26: =VLOOKUP($C26,'A. All deals (a)'!$C$6:$Q$58,J$5,0) -> n/a | K26: =VLOOKUP($C26,'A. All deals (a)'!$C$6:$Q$58,K$5,0) -> 29.659861 | L26: =VLOOKUP($C26,'A. All deals (a)'!$C$6:$Q$58,L$5,0) -> 19.108545 | ... P26: =VLOOKUP($C26,'A. All deals (a)'!$C$6:$Q$58,P$5,0) -> 10.299548 | Q26: 5.445 | R26: =VLOOKUP($C26,'A. All deals (a)'!$C$6:$Q$58,R$5,0) -> 1.5390022
C27: New Space Capital GP Com SCSp | D27: Fund Investment | E27: =VLOOKUP($C27,'A. All deals (a)'!$C$6:$Q$58,E$5,0) -> Unrealized | F27: =VLOOKUP($C27,'A. All deals (a)'!$C$6:$Q$58,F$5,0) -> 0 | G27: =VLOOKUP($C27,'A. All deals (a)'!$C$6:$Q$58,G$5,0) -> G42 Investments | H27: =VLOOKUP($C27,'A. All deals (a)'!$C$6:$Q$58,H$5,0) -> 2023 | I27: =VLOOKUP($C27,'A. All deals (a)'!$C$6:$Q$58,I$5,0) -> LP | J27: =VLOOKUP($C27,'A. All deals (a)'!$C$6:$Q$58,J$5,0) -> n/a | K27: =VLOOKUP($C27,'A. All deals (a)'!$C$6:$Q$58,K$5,0) -> 2.7058824 | L27: =VLOOKUP($C27,'A. All deals (a)'!$C$6:$Q$58,L$5,0) -> 2.7058824 | ... P27: =VLOOKUP($C27,'A. All deals (a)'!$C$6:$Q$58,P$5,0) -> 0.9214071 | Q27: 0 | R27: =VLOOKUP($C27,'A. All deals (a)'!$C$6:$Q$58,R$5,0) -> 1.34052
C28: Acies Investments Fund I, L.P. | D28: Fund Investment | E28: =VLOOKUP($C28,'A. All deals (a)'!$C$6:$Q$58,E$5,0) -> Unrealized | F28: =VLOOKUP($C28,'A. All deals (a)'!$C$6:$Q$58,F$5,0) -> 0 | G28: =VLOOKUP($C28,'A. All deals (a)'!$C$6:$Q$58,G$5,0) -> G42 Investments | H28: =VLOOKUP($C28,'A. All deals (a)'!$C$6:$Q$58,H$5,0) -> 2021 | I28: =VLOOKUP($C28,'A. All deals (a)'!$C$6:$Q$58,I$5,0) -> LP | J28: =VLOOKUP($C28,'A. All deals (a)'!$C$6:$Q$58,J$5,0) -> 0.33 | K28: =VLOOKUP($C28,'A. All deals (a)'!$C$6:$Q$58,K$5,0) -> 17.1125 | L28: =VLOOKUP($C28,'A. All deals (a)'!$C$6:$Q$58,L$5,0) -> 15.726387 | ... P28: =VLOOKUP($C28,'A. All deals (a)'!$C$6:$Q$58,P$5,0) -> -2.6700795 | Q28: -0.306 | R28: =VLOOKUP($C28,'A. All deals (a)'!$C$6:$Q$58,R$5,0) -> 0.8302166 | S28: 9.9% GP | Anchorf
K30: =SUM(K23:K28) -> 457.3711 | L30: =SUM(L23:L28) -> 445.43368 | M30: =SUM(M23:M28) -> 11.937429 | N30: =SUM(N23:N28) -> 96.472763 | O30: =SUM(O23:O28) -> 436.26476 | P30: =O30+N30-L30 -> 87.303852 | Q30: =SUM(Q23:Q28) -> 3.485 | R30: =(N30+O30)/L30 -> 1.1959974
C32: G42 Capital SPV RSC Ltd
C33: Life Biosciences LLC | D33: Direct Investment | E33: =VLOOKUP($C33,'A. All deals (a)'!$C$6:$Q$58,E$5,0) -> Unrealized | F33: =VLOOKUP($C33,'A. All deals (a)'!$C$6:$Q$58,F$5,0) -> 0 | G33: =VLOOKUP($C33,'A. All deals (a)'!$C$6:$Q$58,G$5,0) -> G42 Capital | H33: =VLOOKUP($C33,'A. All deals (a)'!$C$6:$Q$58,H$5,0) -> 2024 | I33: =VLOOKUP($C33,'A. All deals (a)'!$C$6:$Q$58,I$5,0) -> D Prefs | J33: =VLOOKUP($C33,'A. All deals (a)'!$C$6:$Q$58,J$5,0) -> 0.072996903 | K33: =VLOOKUP($C33,'A. All deals (a)'!$C$6:$Q$58,K$5,0) -> 40 | L33: =VLOOKUP($C33,'A. All deals (a)'!$C$6:$Q$58,L$5,0) -> 40 | ... P33: =VLOOKUP($C33,'A. All deals (a)'!$C$6:$Q$58,P$5,0) -> 0.94739371 | Q33: 0 | R33: =VLOOKUP($C33,'A. All deals (a)'!$C$6:$Q$58,R$5,0) -> 1.0236848 | S33: EPTH7
C34: Cerebras Systems Inc F1 | D34: Direct Investment | E34: =VLOOKUP($C34,'A. All deals (a)'!$C$6:$Q$58,E$5,0) -> Not Completed | F34: =VLOOKUP($C34,'A. All deals (a)'!$C$6:$Q$58,F$5,0) -> 0 | G34: =VLOOKUP($C34,'A. All deals (a)'!$C$6:$Q$58,G$5,0) -> G42 Capital | H34: =VLOOKUP($C34,'A. All deals (a)'!$C$6:$Q$58,H$5,0) -> 2025 | I34: =VLOOKUP($C34,'A. All deals (a)'!$C$6:$Q$58,I$5,0) -> Series F-1 | J34: =VLOOKUP($C34,'A. All deals (a)'!$C$6:$Q$58,J$5,0) -> TBD | K34: =VLOOKUP($C34,'A. All deals (a)'!$C$6:$Q$58,K$5,0) -> 111.66667 | L34: =VLOOKUP($C34,'A. All deals (a)'!$C$6:$Q$58,L$5,0) -> 0 | ... P34: =VLOOKUP($C34,'A. All deals (a)'!$C$6:$Q$58,P$5,0) -> 0 | Q34: 0 | R34: =VLOOKUP($C34,'A. All deals (a)'!$C$6:$Q$58,R$5,0) -> NM | S34: EPTH8; option to buy more
C35: Verses AI Inc | D35: Direct Investment | E35: =VLOOKUP($C35,'A. All deals (a)'!$C$6:$Q$58,E$5,0) -> Unrealized | F35: =VLOOKUP($C35,'A. All deals (a)'!$C$6:$Q$58,F$5,0) -> 0 | G35: =VLOOKUP($C35,'A. All deals (a)'!$C$6:$Q$58,G$5,0) -> G42 Capital | H35: =VLOOKUP($C35,'A. All deals (a)'!$C$6:$Q$58,H$5,0) -> 2024 | I35: Ordinary Shares | J35: =VLOOKUP($C35,'A. All deals (a)'!$C$6:$Q$58,J$5,0) -> 0.0523 | K35: =VLOOKUP($C35,'A. All deals (a)'!$C$6:$Q$58,K$5,0) -> 10 | L35: =VLOOKUP($C35,'A. All deals (a)'!$C$6:$Q$58,L$5,0) -> 10 | M35: =VLOOKUP($C35,'A. All deals (a)'!$C$6:$Q$58,M$5,0) -> 0 | N35: =VLOOKUP($C35,'A. All deals (a)'!$C$6:$Q$58,N$5,0) -> 0 | O35: =VLOOKUP($C35,'A. All deals (a)'!$C$6:$Q$58,O$5,0) -> 2.9127687 | P35: =VLOOKUP($C35,'A. All deals (a)'!$C$6:$Q$58,P$5,0) -> -7.0872313 | Q35: 0 | R35: =VLOOKUP($C35,'A. All deals (a)'!$C$6:$Q$58,R$5,0) -> 0.29127687 | S35: ="EPTH9 "& VLOOKUP($C35,'A. All deals (a)'!$C$6:$Q$58,S$5,0) -> EPTH9 Revenue linked RSUs
C36: Inveniam Ltd | D36: Direct Investment | E36: =VLOOKUP($C36,'A. All deals (a)'!$C$6:$Q$58,E$5,0) -> Unrealized | F36: =VLOOKUP($C36,'A. All deals (a)'!$C$6:$Q$58,F$5,0) -> 0 | G36: =VLOOKUP($C36,'A. All deals (a)'!$C$6:$Q$58,G$5,0) -> G42 Capital | H36: =VLOOKUP($C36,'A. All deals (a)'!$C$6:$Q$58,H$5,0) -> 2024 | I36: =VLOOKUP($C36,'A. All deals (a)'!$C$6:$Q$58,I$5,0) -> SAR | J36: =VLOOKUP($C36,'A. All deals (a)'!$C$6:$Q$58,J$5,0) -> 20% Eq | K36: =VLOOKUP($C36,'A. All deals (a)'!$C$6:$Q$58,K$5,0) -> 100 | L36: =VLOOKUP($C36,'A. All deals (a)'!$C$6:$Q$58,L$5,0) -> 100 | ... P36: =VLOOKUP($C36,'A. All deals (a)'!$C$6:$Q$58,P$5,0) -> 0.499965 | Q36: 0 | R36: =VLOOKUP($C36,'A. All deals (a)'!$C$6:$Q$58,R$5,0) -> 1.0049997 | S36: ="EPTH10 "& VLOOKUP($C36,'A. All deals (a)'!$C$6:$Q$58,S$5,0) -> EPTH10 Upside if Tokens sold > $2.5 per token
C37: Liquid AI | D37: Direct Investment | E37: =VLOOKUP($C37,'A. All deals (a)'!$C$6:$Q$58,E$5,0) -> Unrealized | F37: =VLOOKUP($C37,'A. All deals (a)'!$C$6:$Q$58,F$5,0) -> 0 | G37: =VLOOKUP($C37,'A. All deals (a)'!$C$6:$Q$58,G$5,0) -> G42 Capital | H37: =VLOOKUP($C37,'A. All deals (a)'!$C$6:$Q$58,H$5,0) -> 2024 | I37: =VLOOKUP($C37,'A. All deals (a)'!$C$6:$Q$58,I$5,0) -> Series A | J37: =VLOOKUP($C37,'A. All deals (a)'!$C$6:$Q$58,J$5,0) -> 0.006278547 | K37: =VLOOKUP($C37,'A. All deals (a)'!$C$6:$Q$58,K$5,0) -> 66.599843 | L37: =VLOOKUP($C37,'A. All deals (a)'!$C$6:$Q$58,L$5,0) -> 19.999882 | ... P37: =VLOOKUP($C37,'A. All deals (a)'!$C$6:$Q$58,P$5,0) -> 0 | Q37: 0 | R37: =VLOOKUP($C37,'A. All deals (a)'!$C$6:$Q$58,R$5,0) -> 1 | S37: EPTH11 option to buy $45m more
C38: Neuralink | D38: Direct Investment | E38: =VLOOKUP($C38,'A. All deals (a)'!$C$6:$Q$58,E$5,0) -> Unrealized | F38: =VLOOKUP($C38,'A. All deals (a)'!$C$6:$Q$58,F$5,0) -> 0 | G38: =VLOOKUP($C38,'A. All deals (a)'!$C$6:$Q$58,G$5,0) -> G42 Capital | H38: =VLOOKUP($C38,'A. All deals (a)'!$C$6:$Q$58,H$5,0) -> 2025 | I38: =VLOOKUP($C38,'A. All deals (a)'!$C$6:$Q$58,I$5,0) -> Series E | J38: =VLOOKUP($C38,'A. All deals (a)'!$C$6:$Q$58,J$5,0) -> 0.0051805228 | K38: =VLOOKUP($C38,'A. All deals (a)'!$C$6:$Q$58,K$5,0) -> 50 | L38: =VLOOKUP($C38,'A. All deals (a)'!$C$6:$Q$58,L$5,0) -> 50 | ... P38: =VLOOKUP($C38,'A. All deals (a)'!$C$6:$Q$58,P$5,0) -> 5e-07 | Q38: 0 | R38: =VLOOKUP($C38,'A. All deals (a)'!$C$6:$Q$58,R$5,0) -> 1 | S38: EPTH12
K40: =SUM(K33:K38) -> 378.26651 | L40: =SUM(L33:L38) -> 219.99988 | M40: =SUM(M33:M38) -> 158.26663 | N40: =SUM(N33:N38) -> 0.499965 | O40: =SUM(O33:O38) -> 213.86004 | P40: =SUM(P33:P37) -> -5.6398726 | Q40: =SUM(Q33:Q35) -> 0 | R40: =(N40+O40)/L40 -> 0.9743642
C42: Core42 Holding RSC Ltd
C43: School Hack (AIREV Holding Limited) | D43: Direct Investment | E43: =VLOOKUP($C43,'A. All deals (a)'!$C$6:$Q$58,E$5,0) -> Unrealized | F43: =VLOOKUP($C43,'A. All deals (a)'!$C$6:$Q$58,F$5,0) -> 0 | G43: =VLOOKUP($C43,'A. All deals (a)'!$C$6:$Q$58,G$5,0) -> Core42 5 | H43: =VLOOKUP($C43,'A. All deals (a)'!$C$6:$Q$58,H$5,0) -> 2024 | I43: =VLOOKUP($C43,'A. All deals (a)'!$C$6:$Q$58,I$5,0) -> Preferred Shares | J43: =VLOOKUP($C43,'A. All deals (a)'!$C$6:$Q$58,J$5,0) -> 0.25 | K43: =VLOOKUP($C43,'A. All deals (a)'!$C$6:$Q$58,K$5,0) -> 2.75 | L43: =VLOOKUP($C43,'A. All deals (a)'!$C$6:$Q$58,L$5,0) -> 2.5 | ... P43: =VLOOKUP($C43,'A. All deals (a)'!$C$6:$Q$58,P$5,0) -> 0 | Q43: 0 | R43: =VLOOKUP($C43,'A. All deals (a)'!$C$6:$Q$58,R$5,0) -> 1 | S43: Cloud Creditg
K45: =SUM(K43) -> 2.75 | L45: =SUM(L43) -> 2.5 | M45: =SUM(M43) -> 0.25 | N45: =SUM(N43) -> 0 | O45: =SUM(O43) -> 2.5 | P45: =SUM(P43) -> 0 | Q45: =SUM(Q43) -> 0 | R45: =(N45+O45)/L45 -> 1
C47: GX Investments Ltd : MGX and Related Investments
C48: MGX I LP | D48: MGX LP | E48: =VLOOKUP($C48,'A. All deals (a)'!$C$6:$Q$58,E$5,0) -> Unrealized | F48: =VLOOKUP($C48,'A. All deals (a)'!$C$6:$Q$58,F$5,0) -> 0 | G48: =VLOOKUP($C48,'A. All deals (a)'!$C$6:$Q$58,G$5,0) -> G42 Holding | H48: =VLOOKUP($C48,'A. All deals (a)'!$C$6:$Q$58,H$5,0) -> 2024 | I48: =VLOOKUP($C48,'A. All deals (a)'!$C$6:$Q$58,I$5,0) -> LP | J48: =VLOOKUP($C48,'A. All deals (a)'!$C$6:$Q$58,J$5,0) -> 0.03125 | K48: =VLOOKUP($C48,'A. All deals (a)'!$C$6:$Q$58,K$5,0) -> 1200 | L48: =VLOOKUP($C48,'A. All deals (a)'!$C$6:$Q$58,L$5,0) -> 210.22875 | ... P48: =VLOOKUP($C48,'A. All deals (a)'!$C$6:$Q$58,P$5,0) -> 115.98065 | Q48: 0 | R48: =VLOOKUP($C48,'A. All deals (a)'!$C$6:$Q$58,R$5,0) -> 1.5516879
C49: MGX 1 Strategic Co-invest | D49: MGX Co-Invest LP | E49: =VLOOKUP($C49,'A. All deals (a)'!$C$6:$Q$58,E$5,0) -> Unrealized | F49: =VLOOKUP($C49,'A. All deals (a)'!$C$6:$Q$58,F$5,0) -> 0 | G49: =VLOOKUP($C49,'A. All deals (a)'!$C$6:$Q$58,G$5,0) -> G42 Holding | H49: =VLOOKUP($C49,'A. All deals (a)'!$C$6:$Q$58,H$5,0) -> 2024 | I49: =VLOOKUP($C49,'A. All deals (a)'!$C$6:$Q$58,I$5,0) -> LP | J49: =VLOOKUP($C49,'A. All deals (a)'!$C$6:$Q$58,J$5,0) -> 0.5 | K49: =VLOOKUP($C49,'A. All deals (a)'!$C$6:$Q$58,K$5,0) -> 775 | L49: =VLOOKUP($C49,'A. All deals (a)'!$C$6:$Q$58,L$5,0) -> 312.49956 | ... P49: =VLOOKUP($C49,'A. All deals (a)'!$C$6:$Q$58,P$5,0) -> 83.564042 | Q49: 0 | R49: =VLOOKUP($C49,'A. All deals (a)'!$C$6:$Q$58,R$5,0) -> 1.2674053
C50: MGX Group Holding 1 Ltd (GP) | D50: MGX GP | E50: =VLOOKUP($C50,'A. All deals (a)'!$C$6:$Q$58,E$5,0) -> Unrealized | F50: =VLOOKUP($C50,'A. All deals (a)'!$C$6:$Q$58,F$5,0) -> 0 | G50: =VLOOKUP($C50,'A. All deals (a)'!$C$6:$Q$58,G$5,0) -> G42 Holding | H50: =VLOOKUP($C50,'A. All deals (a)'!$C$6:$Q$58,H$5,0) -> 2024 | I50: =VLOOKUP($C50,'A. All deals (a)'!$C$6:$Q$58,I$5,0) -> Equity | J50: =VLOOKUP($C50,'A. All deals (a)'!$C$6:$Q$58,J$5,0) -> 0 | K50: =VLOOKUP($C50,'A. All deals (a)'!$C$6:$Q$58,K$5,0) -> 25 | L50: =VLOOKUP($C50,'A. All deals (a)'!$C$6:$Q$58,L$5,0) -> 25 | ... P50: =VLOOKUP($C50,'A. All deals (a)'!$C$6:$Q$58,P$5,0) -> 0 | Q50: 0 | R50: =VLOOKUP($C50,'A. All deals (a)'!$C$6:$Q$58,R$5,0) -> 1
K52: =SUM(K48:K50) -> 2000 | L52: =SUM(L48:L50) -> 547.72831 | M52: =SUM(M48:M50) -> 1452.2717 | N52: =SUM(N48:N50) -> 0 | O52: =SUM(O48:O50) -> 747.273 | P52: =SUM(P48:P50) -> 199.5447 | Q52: =SUM(Q48:Q48) -> 0 | R52: =(N52+O52)/L52 -> 1.3643133
K54: =K20+K30+K40+K45+K52 -> 3238.8579 | L54: =L20+L30+L40+L45+L52 -> 1616.1321 | M54: =M20+M30+M40+M45+M52 -> 1622.7258 | N54: =N20+N30+N40+N45+N52 -> 96.972728 | O54: =O20+O30+O40+O45+O52 -> 1732.0367 | P54: =P20+P30+P40+P45+P52 -> 212.87732 | Q54: =Q20+Q30+Q40+Q45 -> 159.182 | R54: =(N54+O54)/L54 -> 1.1317202
I57: Checks: | Q57: =Q20+'2. Exited'!Q20=#REF! -> #REF!
C58: For Notes, refer to 9. All deals (a) | Q58: =ROUND(Q30+'2. Exited'!Q26,5)=ROUND(#REF!,5) -> #REF!
C59: Position Exited or written off are highlighted | Q59: =ROUND(Q54+'2. Exited'!Q36,5)=ROUND(#REF!,5) -> #REF!

Sheet 2. Exited
C2: As of date | D2: ='D1'!D2 -> 45900
C3: EXITED INVESTMENTS
E5: 2 | F5: 3 | G5: 4 | H5: 5 | I5: 6 | J5: 7 | K5: 8 | L5: 9 | M5: 10 | N5: 11 | O5: 12 | P5: 13 | R5: 14 | S5: 15
C6: Deals | D6: Type | E6: Status | F6: Lead | G6: Investing Entity | H6: Vintageἀ | I6: Instrument | J6: % | K6: Committed | L6: Invested | M6: Remaining Commitment | N6: Distributions | O6: Carrying Value | P6: Gain | Q6: Gain till FY22 | R6: TVPI | S6: Additonal Upside/Downside
I7: # | J7: % | K7: $,m | L7: $,m | M7: $,m | N7: $,m | O7: $,m | P7: $,m | R7: X
C8: MOZN Holding RSC Ltd
C9: WLD Tokens | D9: Direct Investment | E9: =VLOOKUP($C9,'A. All deals (a)'!$C$6:$Q$58,E$5,0) -> Unrealized | F9: =VLOOKUP($C9,'A. All deals (a)'!$C$6:$Q$58,F$5,0) -> 0 | G9: =VLOOKUP($C9,'A. All deals (a)'!$C$6:$Q$58,G$5,0) -> Mozn | H9: =VLOOKUP($C9,'A. All deals (a)'!$C$6:$Q$58,H$5,0) -> 2023 | I9: =VLOOKUP($C9,'A. All deals (a)'!$C$6:$Q$58,I$5,0) -> Tokens | J9: =VLOOKUP($C9,'A. All deals (a)'!$C$6:$Q$58,J$5,0) -> 0.00625 | K9: =VLOOKUP($C9,'A. All deals (a)'!$C$6:$Q$58,K$5,0) -> 0.006875 | L9: =VLOOKUP($C9,'A. All deals (a)'!$C$6:$Q$58,L$5,0) -> 0.006875 | ... P9: =VLOOKUP($C9,'A. All deals (a)'!$C$6:$Q$58,P$5,0) -> 99.993125 | Q9: n/a | R9: =VLOOKUP($C9,'A. All deals (a)'!$C$6:$Q$58,R$5,0) -> NM | S9: Full Exit for Inveniam SAR
C10: X-fusion | D10: Direct Investment | E10: =VLOOKUP($C10,'A. All deals (a)'!$C$6:$Q$58,E$5,0) -> Realized | F10: =VLOOKUP($C10,'A. All deals (a)'!$C$6:$Q$58,F$5,0) -> 0 | G10: =VLOOKUP($C10,'A. All deals (a)'!$C$6:$Q$58,G$5,0) -> Mozn 2 | H10: =VLOOKUP($C10,'A. All deals (a)'!$C$6:$Q$58,H$5,0) -> 2022 | I10: =VLOOKUP($C10,'A. All deals (a)'!$C$6:$Q$58,I$5,0) -> Equity-TBC | J10: =VLOOKUP($C10,'A. All deals (a)'!$C$6:$Q$58,J$5,0) -> 0.051 | K10: =VLOOKUP($C10,'A. All deals (a)'!$C$6:$Q$58,K$5,0) -> 493.50096 | L10: =VLOOKUP($C10,'A. All deals (a)'!$C$6:$Q$58,L$5,0) -> 493.50096 | ... P10: =VLOOKUP($C10,'A. All deals (a)'!$C$6:$Q$58,P$5,0) -> -90.500956 | Q10: -64.391 | R10: =VLOOKUP($C10,'A. All deals (a)'!$C$6:$Q$58,R$5,0) -> 0.81661443 | S10: Full Exit
C11: Mena Mobile Inc (Debt) | D11: Debt Investment | E11: =VLOOKUP($C11,'A. All deals (a)'!$C$6:$Q$58,E$5,0) -> Written-off | F11: =VLOOKUP($C11,'A. All deals (a)'!$C$6:$Q$58,F$5,0) -> 0 | G11: =VLOOKUP($C11,'A. All deals (a)'!$C$6:$Q$58,G$5,0) -> Mozn | H11: =VLOOKUP($C11,'A. All deals (a)'!$C$6:$Q$58,H$5,0) -> 2021 | I11: =VLOOKUP($C11,'A. All deals (a)'!$C$6:$Q$58,I$5,0) -> Loan | J11: =VLOOKUP($C11,'A. All deals (a)'!$C$6:$Q$58,J$5,0) -> n/a | K11: =VLOOKUP($C11,'A. All deals (a)'!$C$6:$Q$58,K$5,0) -> 2.353982 | L11: =VLOOKUP($C11,'A. All deals (a)'!$C$6:$Q$58,L$5,0) -> 2.353982 | ... P11: =VLOOKUP($C11,'A. All deals (a)'!$C$6:$Q$58,P$5,0) -> -2.353982 | Q11: 0 | R11: =VLOOKUP($C11,'A. All deals (a)'!$C$6:$Q$58,R$5,0) -> 0 | S11: Written Off
C12: Esyasoft Holding (Debt) | D12: Debt Investment | E12: =VLOOKUP($C12,'A. All deals (a)'!$C$6:$Q$58,E$5,0) -> Realized | F12: =VLOOKUP($C12,'A. All deals (a)'!$C$6:$Q$58,F$5,0) -> 0 | G12: =VLOOKUP($C12,'A. All deals (a)'!$C$6:$Q$58,G$5,0) -> Mozn | H12: =VLOOKUP($C12,'A. All deals (a)'!$C$6:$Q$58,H$5,0) -> 2021 | I12: =VLOOKUP($C12,'A. All deals (a)'!$C$6:$Q$58,I$5,0) -> Loan | J12: =VLOOKUP($C12,'A. All deals (a)'!$C$6:$Q$58,J$5,0) -> n/a | K12: =VLOOKUP($C12,'A. All deals (a)'!$C$6:$Q$58,K$5,0) -> 0.411765 | L12: =VLOOKUP($C12,'A. All deals (a)'!$C$6:$Q$58,L$5,0) -> 0.411765 | ... P12: =VLOOKUP($C12,'A. All deals (a)'!$C$6:$Q$58,P$5,0) -> 0.05901965 | Q12: 0.05901965 | R12: =VLOOKUP($C12,'A. All deals (a)'!$C$6:$Q$58,R$5,0) -> 1.1433333 | S12: Full Exit
C13: Jysan Technologies | D13: Direct Investment | E13: =VLOOKUP($C13,'A. All deals (a)'!$C$6:$Q$58,E$5,0) -> Realized | F13: =VLOOKUP($C13,'A. All deals (a)'!$C$6:$Q$58,F$5,0) -> 0 | G13: =VLOOKUP($C13,'A. All deals (a)'!$C$6:$Q$58,G$5,0) -> Mozn 1 | H13: =VLOOKUP($C13,'A. All deals (a)'!$C$6:$Q$58,H$5,0) -> 2021 | I13: =VLOOKUP($C13,'A. All deals (a)'!$C$6:$Q$58,I$5,0) -> A (Ordinary Shares) | J13: =VLOOKUP($C13,'A. All deals (a)'!$C$6:$Q$58,J$5,0) -> 0.03 | K13: =VLOOKUP($C13,'A. All deals (a)'!$C$6:$Q$58,K$5,0) -> 20 | L13: =VLOOKUP($C13,'A. All deals (a)'!$C$6:$Q$58,L$5,0) -> 20 | ... P13: =VLOOKUP($C13,'A. All deals (a)'!$C$6:$Q$58,P$5,0) -> 4.5 | Q13: 0 | R13: =VLOOKUP($C13,'A. All deals (a)'!$C$6:$Q$58,R$5,0) -> 1.225 | S13: Full Exit
C14: Instadeep Limited | D14: Direct Investment | E14: =VLOOKUP($C14,'A. All deals (a)'!$C$6:$Q$58,E$5,0) -> Realized | F14: =VLOOKUP($C14,'A. All deals (a)'!$C$6:$Q$58,F$5,0) -> 0 | G14: =VLOOKUP($C14,'A. All deals (a)'!$C$6:$Q$58,G$5,0) -> Mozn | H14: =VLOOKUP($C14,'A. All deals (a)'!$C$6:$Q$58,H$5,0) -> 2021 | I14: =VLOOKUP($C14,'A. All deals (a)'!$C$6:$Q$58,I$5,0) -> B Prefs | J14: =VLOOKUP($C14,'A. All deals (a)'!$C$6:$Q$58,J$5,0) -> 0.011489406 | K14: =VLOOKUP($C14,'A. All deals (a)'!$C$6:$Q$58,K$5,0) -> 5.0237202 | L14: =VLOOKUP($C14,'A. All deals (a)'!$C$6:$Q$58,L$5,0) -> 5.0237202 | ... P14: =VLOOKUP($C14,'A. All deals (a)'!$C$6:$Q$58,P$5,0) -> 2.9184723 | Q14: 1.6721788 | R14: =VLOOKUP($C14,'A. All deals (a)'!$C$6:$Q$58,R$5,0) -> 1.5809385 | S14: Full Exit
C15: Esyasoft Holding | D15: Direct Investment | E15: =VLOOKUP($C15,'A. All deals (a)'!$C$6:$Q$58,E$5,0) -> Realized | F15: =VLOOKUP($C15,'A. All deals (a)'!$C$6:$Q$58,F$5,0) -> 0 | G15: =VLOOKUP($C15,'A. All deals (a)'!$C$6:$Q$58,G$5,0) -> Mozn | H15: =VLOOKUP($C15,'A. All deals (a)'!$C$6:$Q$58,H$5,0) -> 2020 | I15: =VLOOKUP($C15,'A. All deals (a)'!$C$6:$Q$58,I$5,0) -> Convertible Note | J15: =VLOOKUP($C15,'A. All deals (a)'!$C$6:$Q$58,J$5,0) -> n/a | K15: =VLOOKUP($C15,'A. All deals (a)'!$C$6:$Q$58,K$5,0) -> 2.5 | L15: =VLOOKUP($C15,'A. All deals (a)'!$C$6:$Q$58,L$5,0) -> 2.5 | ... P15: =VLOOKUP($C15,'A. All deals (a)'!$C$6:$Q$58,P$5,0) -> 2.5 | Q15: 2.5 | R15: =VLOOKUP($C15,'A. All deals (a)'!$C$6:$Q$58,R$5,0) -> 2 | S15: Full Exit
C16: Mena Mobile Inc | D16: Direct Investment | E16: =VLOOKUP($C16,'A. All deals (a)'!$C$6:$Q$58,E$5,0) -> Written-off | F16: =VLOOKUP($C16,'A. All deals (a)'!$C$6:$Q$58,F$5,0) -> 0 | G16: =VLOOKUP($C16,'A. All deals (a)'!$C$6:$Q$58,G$5,0) -> Mozn | H16: =VLOOKUP($C16,'A. All deals (a)'!$C$6:$Q$58,H$5,0) -> 2019 | I16: =VLOOKUP($C16,'A. All deals (a)'!$C$6:$Q$58,I$5,0) -> B Prefs | J16: =VLOOKUP($C16,'A. All deals (a)'!$C$6:$Q$58,J$5,0) -> 0.14 | K16: =VLOOKUP($C16,'A. All deals (a)'!$C$6:$Q$58,K$5,0) -> 8 | L16: =VLOOKUP($C16,'A. All deals (a)'!$C$6:$Q$58,L$5,0) -> 8 | ... P16: =VLOOKUP($C16,'A. All deals (a)'!$C$6:$Q$58,P$5,0) -> -8 | Q16: -8 | R16: =VLOOKUP($C16,'A. All deals (a)'!$C$6:$Q$58,R$5,0) -> 0 | S16: Written Off
C17: Glass Earth Holdings LLC | D17: Debt Investment | E17: =VLOOKUP($C17,'A. All deals (a)'!$C$6:$Q$58,E$5,0) -> Written-off | F17: =VLOOKUP($C17,'A. All deals (a)'!$C$6:$Q$58,F$5,0) -> 0 | G17: =VLOOKUP($C17,'A. All deals (a)'!$C$6:$Q$58,G$5,0) -> Mozn | H17: =VLOOKUP($C17,'A. All deals (a)'!$C$6:$Q$58,H$5,0) -> 2019 | I17: =VLOOKUP($C17,'A. All deals (a)'!$C$6:$Q$58,I$5,0) -> Promissory Note | J17: =VLOOKUP($C17,'A. All deals (a)'!$C$6:$Q$58,J$5,0) -> n/a | K17: =VLOOKUP($C17,'A. All deals (a)'!$C$6:$Q$58,K$5,0) -> 8 | L17: =VLOOKUP($C17,'A. All deals (a)'!$C$6:$Q$58,L$5,0) -> 8 | ... P17: =VLOOKUP($C17,'A. All deals (a)'!$C$6:$Q$58,P$5,0) -> -8 | Q17: -8 | R17: =VLOOKUP($C17,'A. All deals (a)'!$C$6:$Q$58,R$5,0) -> 0 | S17: =VLOOKUP($C17,'A. All deals (a)'!$C$6:$Q$58,S$5,0) -> In Default
C18: Jollychic Holding Limited | D18: Direct Investment | E18: =VLOOKUP($C18,'A. All deals (a)'!$C$6:$Q$58,E$5,0) -> Written-off | F18: =VLOOKUP($C18,'A. All deals (a)'!$C$6:$Q$58,F$5,0) -> 0 | G18: =VLOOKUP($C18,'A. All deals (a)'!$C$6:$Q$58,G$5,0) -> Mozn | H18: =VLOOKUP($C18,'A. All deals (a)'!$C$6:$Q$58,H$5,0) -> 2019 | I18: =VLOOKUP($C18,'A. All deals (a)'!$C$6:$Q$58,I$5,0) -> C+ Prefs | J18: =VLOOKUP($C18,'A. All deals (a)'!$C$6:$Q$58,J$5,0) -> 0.056999998 | K18: =VLOOKUP($C18,'A. All deals (a)'!$C$6:$Q$58,K$5,0) -> 65 | L18: =VLOOKUP($C18,'A. All deals (a)'!$C$6:$Q$58,L$5,0) -> 65 | ... P18: =VLOOKUP($C18,'A. All deals (a)'!$C$6:$Q$58,P$5,0) -> -65 | Q18: -65 | R18: =VLOOKUP($C18,'A. All deals (a)'!$C$6:$Q$58,R$5,0) -> 0 | S18: =VLOOKUP($C18,'A. All deals (a)'!$C$6:$Q$58,S$5,0) -> In Liquidation
K20: =SUM(K9:K18) -> 604.7973 | L20: =SUM(L9:L18) -> 604.7973 | M20: =SUM(M9:M18) -> 0 | N20: =SUM(N9:N18) -> 540.91298 | O20: =SUM(O9:O18) -> 0 | P20: =SUM(P9:P18) -> -63.884321 | Q20: =SUM(Q10:Q18) -> -141.1598 | R20: =(N20+O20)/L20 -> 0.89437069
C22: G42 Investments AI Holding RSC Ltd
C23: Honor Device Co Ltd | D23: Direct Investment | E23: =VLOOKUP($C23,'A. All deals (a)'!$C$6:$Q$58,E$5,0) -> Realized | F23: =VLOOKUP($C23,'A. All deals (a)'!$C$6:$Q$58,F$5,0) -> 0 | G23: =VLOOKUP($C23,'A. All deals (a)'!$C$6:$Q$58,G$5,0) -> G42 3 | H23: =VLOOKUP($C23,'A. All deals (a)'!$C$6:$Q$58,H$5,0) -> 2022 | I23: =VLOOKUP($C23,'A. All deals (a)'!$C$6:$Q$58,I$5,0) -> Equity-TBC | J23: =VLOOKUP($C23,'A. All deals (a)'!$C$6:$Q$58,J$5,0) -> 0.018823528 | K23: =VLOOKUP($C23,'A. All deals (a)'!$C$6:$Q$58,K$5,0) -> 800 | L23: =VLOOKUP($C23,'A. All deals (a)'!$C$6:$Q$58,L$5,0) -> 800 | ... P23: =VLOOKUP($C23,'A. All deals (a)'!$C$6:$Q$58,P$5,0) -> 2.8 | Q23: 54.67 | R23: =VLOOKUP($C23,'A. All deals (a)'!$C$6:$Q$58,R$5,0) -> 1.0035
C24: Sinovation Disrupt Fund, L.P. | D24: Fund Investment | E24: =VLOOKUP($C24,'A. All deals (a)'!$C$6:$Q$58,E$5,0) -> Realized | F24: =VLOOKUP($C24,'A. All deals (a)'!$C$6:$Q$58,F$5,0) -> 0 | G24: =VLOOKUP($C24,'A. All deals (a)'!$C$6:$Q$58,G$5,0) -> G42 Investments | H24: =VLOOKUP($C24,'A. All deals (a)'!$C$6:$Q$58,H$5,0) -> 2020 | I24: =VLOOKUP($C24,'A. All deals (a)'!$C$6:$Q$58,I$5,0) -> LP | J24: =VLOOKUP($C24,'A. All deals (a)'!$C$6:$Q$58,J$5,0) -> n/a | K24: =VLOOKUP($C24,'A. All deals (a)'!$C$6:$Q$58,K$5,0) -> 50 | L24: =VLOOKUP($C24,'A. All deals (a)'!$C$6:$Q$58,L$5,0) -> 24.959693 | ... P24: =VLOOKUP($C24,'A. All deals (a)'!$C$6:$Q$58,P$5,0) -> 0.44382835 | Q24: -1.265 | R24: =VLOOKUP($C24,'A. All deals (a)'!$C$6:$Q$58,R$5,0) -> 1.0177818
K26: =SUM(K23:K24) -> 850 | L26: =SUM(L23:L24) -> 824.95969 | M26: =SUM(M23:M24) -> 0 | N26: =SUM(N23:N24) -> 828.20352 | O26: =SUM(O23:O24) -> 0 | P26: =SUM(P23:P24) -> 3.2438283 | Q26: =SUM(Q23:Q24) -> 53.405 | R26: =(N26+O26)/L26 -> 1.0039321 | S26: =O26+N26-L26 -> 3.2438283
C28: G42 Capital SPV RSC Ltd
C32: Core42 Holding RSC Ltd
K36: =K20+K26+K30+K34 -> 1454.7973 | L36: =L20+L26+L30+L34 -> 1429.757 | M36: =M20+M26+M30+M34 -> 0 | N36: =N20+N26+N30+N34 -> 1369.1165 | O36: =O20+O26+O30+O34 -> 0 | P36: =P20+P26+P30+P34 -> -60.640493 | Q36: =Q20+Q26+Q30+Q34 -> -87.754802 | R36: =(N36+O36)/L36 -> 0.95758685
C40: For Notes, refer to 9. All deals (a)
C41: Position Exited or written off are highlighted

Sheet CF (Equity, Debt)
B2: E Q U I T Y
B3: Accounting entity | C3: Investment | D3: Payment date | E3: Contributions (in USD, Mn) | F3: Distributions (in USD, Mn) | G3: Currency | H3: Investment / Exit Amt (investee currency) | I3: Investment / Exit Amount (USD) | J3: Consideration (shares) | K3: Comment | N3: NOTES
B4: =VLOOKUP(C4,'A. All deals (a)'!$C$9:$F$49,4,0) -> Mozn | C4: Jollychic Holding Limited | D4: 43470 | E4: =-I4*10^-6 -> -30 | G4: USD | H4: 30000000 | I4: =H4 -> 30000000 | J4: 6100312 | N4: USD AED | O4: 3.678
B5: =VLOOKUP(C5,'A. All deals (a)'!$C$9:$F$49,4,0) -> Mozn | C5: Jollychic Holding Limited | D5: 43724 | E5: =-I5*10^-6 -> -20 | G5: USD | H5: 20000000 | I5: =H5 -> 20000000 | J5: 4204767.4
B6: =VLOOKUP(C6,'A. All deals (a)'!$C$9:$F$49,4,0) -> Mozn | C6: Jollychic Holding Limited | D6: 43724 | E6: =-I6*10^-6 -> -15 | G6: USD | H6: 15000000 | I6: =H6 -> 15000000 | J6: 3153575.6
B7: =VLOOKUP(C7,'A. All deals (a)'!$C$9:$F$49,4,0) -> Mozn | C7: Mena Mobile Inc | D7: 43563 | E7: =-I7*10^-6 -> -8 | G7: USD | H7: 8000000 | I7: =H7 -> 8000000 | J7: 21419829
B8: =VLOOKUP(C8,'A. All deals (a)'!$C$9:$F$49,4,0) -> Mozn | C8: Flyr Inc | D8: 43570 | E8: =-I8*10^-6 -> -4.9999981 | G8: USD | H8: 4999998.1 | I8: =H8 -> 4999998.1 | J8: 2625467
B9: =VLOOKUP(C9,'A. All deals (a)'!$C$9:$F$49,4,0) -> Mozn | C9: Flyr Inc | D9: 43915 | E9: =-I9*10^-6 -> -5.0000019 | G9: USD | H9: =10000000-H8 -> 5000001.9 | I9: =H9 -> 5000001.9 | J9: 2580015
B10: =VLOOKUP(C10,'A. All deals (a)'!$C$9:$F$49,4,0) -> Mozn | C10: Esyasoft Holding | D10: 43870 | E10: =-I10*10^-6 -> -2.5 | G10: USD | H10: 2500000 | I10: =H10 -> 2500000 | J10: N/A
B11: =VLOOKUP(C11,'A. All deals (a)'!$C$9:$F$49,4,0) -> Mozn | C11: Beyond Limits | D11: 43879 | E11: =-I11*10^-6 -> -20 | G11: USD | H11: 20000000 | I11: =H11 -> 20000000 | J11: 4084038
B12: =VLOOKUP(C12,'A. All deals (a)'!$C$9:$F$49,4,0) -> Mozn | C12: Beyond Limits | D12: 43921 | E12: =-I12*10^-6 -> -30 | G12: USD | H12: 30000000 | I12: =H12 -> 30000000 | J12: 5822642
B13: =VLOOKUP(C13,'A. All deals (a)'!$C$9:$F$49,4,0) -> Mozn | C13: Beyond Limits | D13: 43989 | E13: =-I13*10^-6 -> -30 | G13: USD | H13: 30000000 | I13: =H13 -> 30000000 | J13: 5822642
B14: =VLOOKUP(C14,'A. All deals (a)'!$C$9:$F$49,4,0) -> Mozn | C14: Beyond Limits | D14: 44103 | E14: =-I14*10^-6 -> -10 | G14: USD | H14: 10000000 | I14: =H14 -> 10000000 | J14: 1940880
B15: =VLOOKUP(C15,'A. All deals (a)'!$C$9:$F$49,4,0) -> Mozn | C15: ONT plc | D15: 43968 | E15: =-I15*10^-6 -> -50 | G15: USD | H15: 50000000 | I15: 50000000 | J15: 15277680
B16: =VLOOKUP(C16,'A. All deals (a)'!$C$9:$F$49,4,0) -> Mozn | C16: ONT plc | D16: 44006 | E16: =-I16*10^-6 -> -27.268351 | G16: GBP | H16: 21029625 | I16: 27268351 | J16: 9000000
B17: =VLOOKUP(C17,'A. All deals (a)'!$C$9:$F$49,4,0) -> Mozn | C17: ONT plc | D17: 43837 | E17: =-I17*10^-6 -> -18.109441 | G17: GBP | H17: 14386480 | I17: 18109441 | J17: 6362180
B18: =VLOOKUP(C18,'A. All deals (a)'!$C$9:$F$49,4,0) -> Mozn | C18: ONT plc | D18: 43990 | E18: =-I18*10^-6 -> -34.851687 | G18: GBP | H18: 26085573 | I18: 34851687 | J18: 11381140
B19: =VLOOKUP(C19,'A. All deals (a)'!$C$9:$F$49,4,0) -> Mozn | C19: ONT plc | D19: 44315 | E19: =-I19*10^-6 -> -11.24078 | G19: GBP | H19: 8074920 | I19: 11240780 | J19: 2307120
B20: =VLOOKUP(C20,'A. All deals (a)'!$C$9:$F$49,4,0) -> Mozn | C20: Heygears | D20: 44166 | E20: =-I20*10^-6 -> -60 | G20: USD | H20: 60000000 | I20: =H20 -> 60000000 | J20: 3565017.2
B21: =VLOOKUP(C21,'A. All deals (a)'!$C$9:$F$49,4,0) -> Mozn 1 | C21: Jysan Technologies | D21: 44363 | E21: =-I21*10^-6 -> -20 | G21: USD | H21: 20000000 | I21: =H21 -> 20000000 | J21: 7959497
B22: =VLOOKUP(C22,'A. All deals (a)'!$C$9:$F$49,4,0) -> Mozn | C22: Cerebras Systems Inc | D22: 44488 | E22: =-I22*10^-6 -> -39.999983 | G22: USD | H22: 39999983 | I22: =H22 -> 39999983 | J22: 1441711
B23: =VLOOKUP(C23,'A. All deals (a)'!$C$9:$F$49,4,0) -> Mozn | C23: Endless Studios LLC | D23: 44494 | E23: =-I23*10^-6 -> -3 | G23: USD | H23: 3000000 | I23: =H23 -> 3000000 | J23: 3000000
B24: =VLOOKUP(C24,'A. All deals (a)'!$C$9:$F$49,4,0) -> Mozn | C24: Instadeep Limited | D24: 44550 | E24: =-I24*10^-6 -> -5.0237202 | G24: GBP | H24: 3679995.5 | I24: 5023720.2 | J24: 33267
B25: =VLOOKUP(C25,'A. All deals (a)'!$C$9:$F$49,4,0) -> Mozn 2 | C25: X-fusion | D25: 44574 | E25: =-I25*10^-6 -> -493.50096 | G25: USD | H25: 8.9350096e+08 | I25: 4.9350096e+08
B26: =VLOOKUP(C26,'A. All deals (a)'!$C$9:$F$49,4,0) -> G42 Investments | C26: DriveNets | D26: 44643 | E26: =-I26*10^-6 -> -200 | G26: USD | H26: 200000000 | I26: =H26 -> 200000000
B27: =VLOOKUP(C27,'A. All deals (a)'!$C$9:$F$49,4,0) -> G42 Investments | C27: DriveNets | D27: 44680 | E27: =-I27*10^-6 -> -100 | G27: USD | H27: 100000000 | I27: =H27 -> 100000000
B28: =VLOOKUP(C28,'A. All deals (a)'!$C$9:$F$49,4,0) -> Mozn | C28: Esyasoft Holding | D28: 44691 | F28: 5 | G28: USD
B29: =VLOOKUP(C29,'A. All deals (a)'!$C$9:$F$49,4,0) -> G42 Investments | C29: vTv Therapeutics Inc. | D29: 44712 | E29: =-I29*10^-6 -> -12.5 | G29: USD | H29: 12500000 | I29: =H29 -> 12500000 | J29: ='B. %'!D22 -> 259657
B30: =VLOOKUP(C30,'A. All deals (a)'!$C$9:$F$49,4,0) -> G42 3 | C30: Honor Device Co Ltd | D30: 44769 | E30: =-I30*10^-6 -> -600 | G30: USD | H30: 600000000 | I30: =H30 -> 600000000
B31: =VLOOKUP(C31,'A. All deals (a)'!$C$9:$F$49,4,0) -> G42 3 | C31: Honor Device Co Ltd | D31: 44849 | E31: =-I31*10^-6 -> -200 | G31: USD | H31: 200000000 | I31: =H31 -> 200000000
B32: =VLOOKUP(C32,'A. All deals (a)'!$C$9:$F$49,4,0) -> Mozn | C32: Applied AI Corporation Limited | D32: 44861 | E32: =-I32*10^-6 -> -4.75 | G32: USD | H32: 4750000 | I32: =H32 -> 4750000
B33: =VLOOKUP(C33,'A. All deals (a)'!$C$9:$F$49,4,0) -> Mozn 4 | C33: eSpace | D33: 44892 | E33: =-I33*10^-6 -> -15 | G33: USD | H33: 15000000 | I33: =H33 -> 15000000
B34: =VLOOKUP(C34,'A. All deals (a)'!$C$9:$F$49,4,0) -> G42 Investments | C34: vTv Therapeutics Inc. | D34: 44985 | E34: =-I34*10^-6 -> -12.03125 | G34: USD | H34: 12031250 | I34: =H34 -> 12031250 | J34: 10386274
B35: =VLOOKUP(C35,'A. All deals (a)'!$C$9:$F$49,4,0) -> Mozn | C35: Tools for Humanity Corporation | D35: 45075 | E35: =-I35*10^-6 -> -14.999999 | G35: USD | H35: 14999999 | I35: =H35 -> 14999999
B36: =VLOOKUP(C36,'A. All deals (a)'!$C$9:$F$49,4,0) -> Mozn | C36: WLD Tokens | D36: 45075 | E36: =-I36*10^-6 -> -0.005875 | G36: USD | I36: 5875
B37: =VLOOKUP(C37,'A. All deals (a)'!$C$9:$F$49,4,0) -> Mozn | C37: WLD Tokens | D37: 45114 | E37: =-I37*10^-6 -> -0.001 | G37: USD | I37: 1000
B38: =VLOOKUP(C38,'A. All deals (a)'!$C$9:$F$49,4,0) -> Mozn | C38: Applied AI Corporation Limited | D38: 45121 | E38: =-I38*10^-6 -> -2.75 | G38: USD | I38: 2750000
B39: =VLOOKUP(C39,'A. All deals (a)'!$C$9:$F$49,4,0) -> Mozn | C39: Instadeep Limited | D39: 45138 | F39: =I39*10^-6 -> 7.8207761 | G39: USD | H39: 6090345.2 | I39: 7820776.1
B40: =VLOOKUP(C40,'A. All deals (a)'!$C$9:$F$49,4,0) -> Mozn 1 | C40: Jysan Technologies | D40: 45149 | F40: 24.5 | G40: USD | I40: 24500000 | J40: 7959497
B41: =VLOOKUP(C41,'A. All deals (a)'!$C$9:$F$49,4,0) -> Mozn | C41: Endless Studios LLC | D41: 45167 | E41: =-I41*10^-6 -> -5 | G41: USD | I41: 5000000 | J41: 5000000
B42: =VLOOKUP(C42,'A. All deals (a)'!$C$9:$F$49,4,0) -> Mozn | C42: E-line Ventures LLC | D42: 45167 | E42: -6 | G42: USD | I42: 6000000 | J42: =I42/1.34 -> 4477611.9
B43: =VLOOKUP(C43,'A. All deals (a)'!$C$9:$F$49,4,0) -> G42 3 | C43: Honor Device Co Ltd | D43: 45224 | F43: 2.8 | G43: USD
B44: =VLOOKUP(C44,'A. All deals (a)'!$C$9:$F$49,4,0) -> G42 3 | C44: Honor Device Co Ltd | D44: 45224 | F44: 800 | G44: USD
B45: =VLOOKUP(C45,'A. All deals (a)'!$C$9:$F$49,4,0) -> Mozn 2 | C45: X-fusion | D45: 45224 | F45: 403 | G45: USD
B46: =VLOOKUP(C46,'A. All deals (a)'!$C$9:$F$49,4,0) -> Mozn | C46: Instadeep Limited | D46: 45224 | F46: 0.12141643 | G46: USD
B47: =VLOOKUP(C47,'A. All deals (a)'!$C$9:$F$49,4,0) -> Mozn | C47: Applied AI Corporation Limited | D47: 45295 | E47: =-I47*10^-6 -> -4 | G47: USD | H47: 4000000 | I47: =H47 -> 4000000
B48: =VLOOKUP(C48,'A. All deals (a)'!$C$9:$F$49,4,0) -> Core42 5 | C48: School Hack (AIREV Holding Limited) | D48: 45322 | E48: =-I48*10^-6 -> -2.5 | G48: USD | H48: =I48 -> 2500000 | I48: 2500000
B49: =VLOOKUP(C49,'A. All deals (a)'!$C$9:$F$49,4,0) -> G42 Capital | C49: Life Biosciences LLC | D49: 45349 | E49: =-I49*10^-6 -> -20 | G49: USD | I49: 20000000
B50: G42 Capital | C50: Verses AI Inc | D50: 45463 | E50: -10 | G50: USD | I50: 10000000
B51: =VLOOKUP(C51,'A. All deals (a)'!$C$9:$F$49,4,0) -> G42 Capital | C51: Life Biosciences LLC | D51: 45596 | E51: =-I51*10^-6 -> -20 | G51: USD | I51: 20000000 | M51: =D51-D49 -> 247 | N51: =M51/365 -> 0.67671233
B52: Mozn | C52: WLD Tokens | D52: 45610 | F52: 100 | G52: USD | I52: 100000000 | N52: =7% -> 0.07
B53: G42 Capital | C53: Inveniam Ltd | D53: 45611 | E53: -100 | G53: USD | I53: 100000000 | N53: =N52*N51 -> 0.047369863
B54: Mozn | C54: Applied AI Corporation Limited | D54: 45617 | E54: =-I54*10^-6 -> -3.5 | G54: USD | H54: 3500000 | I54: =H54 -> 3500000 | N54: =20*10^6*N53 -> 947397.26
B55: G42 Capital | C55: Inveniam Ltd | D55: 45645 | F55: 0.499965 | G55: USD | H55: 499965 | I55: 499965
B56: G42 Capital | C56: Liquid AI | D56: 45737 | E56: =-I56*10^-6 -> -19.999882 | G56: USD | I56: 19999882
B57: G42 | C57: DriveNets | D57: 45769 | F57: =I57/1000000 -> 84.804486 | G57: USD | I57: 84804486
B58: G42 Capital | C58: Neuralink | D58: 45812 | E58: =-I58*10^-6 -> -50 | G58: USD | I58: 50000000
B62: L O AN | P R O M I S S O R Y N O T E S | D E B T
B63: Mozn | C63: Glass Earth Holdings LLC | D63: 43635 | E63: -8 | G63: USD | H63: 8000000 | I63: =H63 -> 8000000
B64: Mozn | C64: Mena Mobile Inc (Debt) | D64: 44293 | E64: -2.353982 | G64: USD | H64: =-E64*10^6 -> 2353982 | I64: =H64 -> 2353982
B65: Mozn | C65: Esyasoft Holding (Debt) | D65: 44384 | E65: =-I65*10^-6 -> -0.411765 | G65: USD | H65: 2500000 | I65: 411765
B66: Mozn | C66: Esyasoft Holding (Debt) | D66: 44902 | F66: =(411765+59019.65)*10^-6 -> 0.47078465 | G66: USD | H66: =F66*10^6 -> 470784.65 | I66: 470784.65

Sheet CF (Funds)
B2: F U N D S
B3: Entity | C3: Investment | D3: Payment date | E3: Contributions (USD, Mn) | F3: Distributions (USD, Mn) | G3: Currency | H3: Cashflows | I3: Description | J3: TEST
B4: G42 | C4: Sinovation Disrupt Fund, L.P. | D4: 44153 | E4: =H4 -> -10.5 | G4: USD | H4: -10.5 | I4: 1st Capital Call | J4: =SUM(E4:E65) -> -148.74911
B5: G42 | C5: Sinovation Disrupt Fund, L.P. | D5: 44238 | E5: =H5 -> 4.214027 | G5: USD | H5: 4.214027 | I5: Partial return of the 1st Capital Call | J5: ='A. All deals (a)'!K50 -> 145.86212
B6: G42 | C6: Sinovation Disrupt Fund, L.P. | D6: 44238 | F6: =H6 -> 0.05044835 | G6: USD | H6: 0.05044835 | I6: Interest Catchup | J6: =ROUND(J5,5)=-ROUND(J4,5) -> FALSE
B7: G42 | C7: Sinovation Disrupt Fund, L.P. | D7: 44285 | E7: =H7 -> -6.433746 | G7: USD | H7: -6.433746 | I7: 2nd Capital Calll
B8: G42 | C8: Sinovation Disrupt Fund, L.P. | D8: 44269 | E8: =H8 -> 1.1352074 | G8: USD | H8: 1.1352074 | I8: Return of Capital fund
B9: G42 | C9: Sinovation Disrupt Fund, L.P. | D9: 44269 | F9: =H9 -> 0.0259 | G9: USD | H9: 0.0259 | I9: Interest Catchup
B10: G42 | C10: Sinovation Disrupt Fund, L.P. | D10: 44483 | E10: =H10 -> -7.567138 | G10: USD | H10: -7.567138 | I10: 3rd Capital Call
B11: G42 | C11: Sinovation Disrupt Fund, L.P. | D11: 44554 | E11: =H11 -> -7.385016 | G11: USD | H11: -7.385016 | I11: 4th Capital Call
B12: G42 | C12: Sinovation Disrupt Fund, L.P. | D12: 44554 | E12: =H12 -> 4.0733456 | G12: USD | H12: 4.0733456 | I12: Return of Capital fund
B13: G42 | C13: Sinovation Disrupt Fund, L.P. | D13: 44554 | F13: =H13 -> 0.139694 | G13: USD | H13: 0.139694 | I13: Interest Catchup
B14: G42 | C14: Sinovation Disrupt Fund, L.P. | D14: 44703 | E14: =H14 -> 5.673074 | G14: USD | H14: 5.673074 | I14: Return of Capital fund
B15: G42 | C15: Sinovation Disrupt Fund, L.P. | D15: 44703 | F15: =H15 -> 0.227786 | G15: USD | H15: 0.227786 | I15: Interest Catchup
B16: G42 | C16: Sinovation Disrupt Fund, L.P. | D16: 44776 | E16: =H16 -> -3.235493 | G16: USD | H16: -3.235493 | I16: 5th Capital Call
B17: G42 | C17: Sinovation Disrupt Fund, L.P. | D17: 44960 | E17: =H17 -> -2.631528 | G17: USD | H17: -2.631528 | I17: 6th Capital Call
B18: G42 | C18: Sinovation Disrupt Fund, L.P. | D18: 45085 | E18: =H18 -> 1.912557 | G18: USD | H18: 1.912557 | I18: Return of Capital fund
B19: G42 | C19: Sinovation Disrupt Fund, L.P. | D19: 45166 | E19: -1.799122 | G19: USD | H19: -1.799122 | I19: 7th Capital Call
B20: G42 | C20: Sinovation Disrupt Fund, L.P. | D20: 45218 | E20: -2.415861 | G20: USD | H20: -2.415861 | I20: 8th Capital Call
B21: G42 | C21: Sinovation Disrupt Fund, L.P. | D21: 45323 | F21: =24.959693 -> 24.959693 | G21: USD | H21: =F21 -> 24.959693 | I21: Exit Proceeds (full and final)
B22: G42 | C22: North Summit Capital Fund | D22: 43665 | E22: =H22 -> -3 | G22: USD | H22: -3 | I22: 1st Capital Call
B23: G42 | C23: North Summit Capital Fund | D23: 43983 | E23: =H23 -> -4.485 | G23: USD | H23: -4.485 | I23: 2nd Capital Calll
B24: G42 | C24: North Summit Capital Fund | D24: 43879 | E24: =H24 -> -9.50975 | G24: USD | H24: -9.50975 | I24: 3rd Capital Call
B25: G42 | C25: North Summit Capital Fund | D25: 43934 | E25: =H25 -> -41.3 | G25: USD | H25: -41.3 | I25: 4th Capital Call
B26: G42 | C26: North Summit Capital Fund | D26: 44151 | E26: =H26 -> 9.95 | G26: USD | H26: 9.95 | I26: 5th Capital Call-Partial return of the 4th Capital Call
B27: G42 | C27: North Summit Capital Fund | D27: 44151 | E27: =H27 -> -10.455 | G27: USD | H27: -10.455 | I27: 5th Capital Call
B28: G42 | C28: North Summit Capital Fund | D28: 44196 | E28: =H28 -> 4.975 | G28: USD | H28: 4.975 | I28: 6th Capital Call-Partial return of the 4th Capital Call
B29: G42 | C29: North Summit Capital Fund | D29: 44196 | E29: =H29 -> -3.452293 | G29: USD | H29: -3.452293 | I29: 6th Capital Call
B30: G42 | C30: North Summit Capital Fund | D30: 44196 | F30: =H30 -> 0.582902 | G30: USD | H30: 0.582902 | I30: 6th Capital Call-Dividends from Project Topscore
B31: G42 | C31: North Summit Capital Fund | D31: 44370 | E31: =H31 -> -5.97 | G31: USD | H31: -5.97 | I31: 7th Capital Call
B32: G42 | C32: North Summit Capital Fund | D32: 44400 | E32: =H32 -> -0.75 | G32: USD | H32: -0.75 | I32: 8th Capital Call
B33: G42 | C33: North Summit Capital Fund | D33: 44400 | F33: =H33 -> 0.445059 | G33: USD | H33: 0.445059 | I33: 8th Capital Call-Dividends from Project Topscore
B34: G42 | C34: North Summit Capital Fund | D34: 44554 | E34: =H34 -> 1.78239 | G34: USD | H34: 1.78239 | I34: 9th Capital Call-Return of Capital Fund
B35: G42 | C35: North Summit Capital Fund | D35: 44676 | E35: =H35 -> -21 | G35: USD | H35: -21 | I35: 12th Capital Call
B36: G42 | C36: North Summit Capital Fund | D36: 45243 | F36: =H36 -> 6.78791 | G36: USD | H36: 6.78791 | I36: 13th Capital Call & Distribution #4
B37: G42 | C37: North Summit Capital Fund | D37: 45470 | E37: =H37 -> -0.055697 | G37: USD | H37: =-55697*10^-6 -> -0.055697 | I37: 14th Capital Call
B38: G42 | C38: North Summit Capital Fund | D38: 45611 | E38: =H38 -> -0.031561 | G38: USD | H38: =-31561*10^-6 -> -0.031561 | I38: 15th Capital Call
B39: G42 | C39: New Space Capital Fund I | D39: 44087 | E39: =H39*1.1 -> -20.917553 | G39: EUR | H39: -19.015957 | I39: Drawdown1
B40: G42 | C40: New Space Capital Fund I | D40: 44287 | E40: -0.21103182 | G40: EUR | H40: -0.21103182 | I40: Drawdown2
B41: G42 | C41: New Space Capital Fund I | D41: 44442 | E41: =1.18*H41 -> -0.23965473 | G41: EUR | H41: =-203097.23*10^-6 -> -0.20309723 | I41: Drawdown3
B42: G42 | C42: New Space Capital Fund I | D42: 44623 | E42: =1.11*H42 -> -0.25893585 | G42: EUR | H42: =-233275.54*10^-6 -> -0.23327554 | I42: Drawdown4
B43: G42 | C43: New Space Capital Fund I | D43: 44784 | E43: =1.03*H43 -> 0.015224657 | G43: EUR | H43: =14781.22*10^-6 -> 0.01478122 | I43: Return of Capital
B44: G42 | C44: New Space Capital Fund I | D44: 44956 | E44: =9741387*10^-6*1.08341 -> 10.553916 | G44: EUR | H44: =9741387*10^-6 -> 9.741387 | I44: Return of Capital
B45: G42 | C45: New Space Capital Fund I | D45: 44956 | F45: =2728214.02*10^-6*1.08341 -> 2.9557744 | G45: EUR | H45: 2.728214 | I45: Distribution | Actualization Interest
B46: G42 | C46: New Space Capital Fund I | D46: 45170 | E46: -0.22532724 | G46: EUR | H46: -0.22532724 | I46: Drawdown (Notice 10)
B47: G42 | C47: New Space Capital Fund I | D47: 45260 | E47: -0.28531252 | G47: EUR | H47: -0.28531252 | I47: Drawdown (Notice 11)
B48: G42 | C48: New Space Capital Fund I | D48: 45321 | E48: -2.4198785 | G48: EUR | H48: -2.4198785 | I48: Drawdown (Notice 12)
B49: G42 | C49: New Space Capital Fund I | D49: 45372 | E49: -0.21649574 | G49: EUR | H49: -0.21649574 | I49: Drawdown (Notice 13)
B50: G42 | C50: New Space Capital Fund I | D50: 45454 | F50: =H50*1.0743 -> 0.46369473 | G50: EUR | H50: =431624.99*10^-6 -> 0.43162499 | I50: Drawdown 14| Actualization Interest Distribution
B51: G42 | C51: New Space Capital Fund I | D51: 45505 | E51: =H51*1.0883 -> -1.7173904 | G51: EUR | H51: =-1578048.66*10^-6 -> -1.5780487 | I51: Drawdown (Notice 15)
B52: G42 | C52: New Space Capital Fund I | D52: 45604 | E52: =H52*1.07205 -> -1.8749406 | G52: EUR | H52: =-1748930.22*10^-6 -> -1.7489302 | I52: Drawdown (Notice 16)
B53: G42 | C53: New Space Capital Fund I | D53: 45692 | E53: =(H53-0.34559)*1.08 -> 2.1803052 | F53: =0.34559*1.08 -> 0.3732372 | G53: EUR | H53: 2.3643911 | I53: Drawdown (Notice 17)
B54: G42 | C54: New Space Capital Fund I | D54: 45736 | E54: =H54*1.08579 -> -0.77167877 | G54: EUR | H54: -0.7107072 | I54: Drawdown (Notice 18)
B55: G42 | C55: New Space Capital Fund I | D55: 45834 | E55: =H55*1.16999 -> -2.7197917 | G55: EUR | H55: =-'8. NewSpace'!R18*10^-6 -> -2.3246282 | I55: Drawdown (Notice 19)
B56: G42 | C56: New Space Capital Fund I | D56: TBC | E56: =H56*1.16999 -> -5.1370022 | G56: EUR | H56: =('8. NewSpace'!S15+'8. NewSpace'!S16)*10^-6 -> -4.3906377 | I56: Drawdown (Notice 20) | Return of Capital
B57: G42 | C57: New Space Capital Fund I | D57: TBC | F57: -0.91406649 | G57: EUR | H57: ='8. NewSpace'!S17*10^-6 -> -0.78126009 | I57: Drawdown (Notice 20) Equalization Interest
B58: G42 | C58: New Space Capital Fund I | D58: TBC | E58: =H58*1.16999 -> 2.1903083 | G58: EUR | H58: ='8. NewSpace'!S18*10^-6 -> 1.8720744 | I58: Drawdown (Notice 20) | Capital Call
B59: G42 | C59: New Space Capital GP Com SCSp | D59: 44087 | E59: =-'A. All deals (a)'!K46 -> -2.7058824 | G59: EUR | H59: -2.125 | I59: Drawdown1
B60: G42 | C60: Acies Investments Fund I, L.P. | D60: 44540 | E60: =H60 -> -2.8053125 | G60: USD | H60: -2.8053125 | I60: 1st Capital Call
B61: G42 | C61: Acies Investments Fund I, L.P. | D61: 44602 | E61: =H61 -> -3.4075 | G61: USD | H61: -3.4075 | I61: 2nd Capital Call
B62: G42 | C62: Acies Investments Fund I, L.P. | D62: 44683 | E62: =H62 -> -1.025775 | G62: USD | H62: -1.025775 | I62: Catch up Capital Call
B63: G42 | C63: Acies Investments Fund I, L.P. | D63: 44707 | E63: =H63 -> -3.388275 | G63: USD | H63: -3.388275 | I63: 3rd Capital Call
B64: G42 | C64: Acies Investments Fund I, L.P. | D64: 44875 | E64: =H64 -> -3.388275 | G64: USD | H64: -3.388275 | I64: 4th Capital Call
B65: G42 | C65: Acies Investments Fund I, L.P. | D65: 45760 | E65: =H65 -> -1.71125 | G65: USD | H65: -1.71125 | I65: 5th Capital Call
B67: GXI | C67: MGX HoldCo | D67: 45547 | E67: -25 | G67: USD | H67: =E67+F67 -> -25 | I67: Share Capital
B69: GXI | C69: MGX I LP | D69: 45645 | E69: -20.20202 | G69: USD | H69: =E69+F69 -> -20.20202 | I69: Open AI
B70: GXI | C70: MGX I LP | D70: 45645 | E70: -20.20202 | G70: USD | H70: =E70+F70 -> -20.20202 | I70: X.AI
B71: GXI | C71: MGX I LP | D71: 45645 | E71: -42.880735 | G71: USD | H71: =E71+F71 -> -42.880735 | I71: Anthropic
B72: GXI | C72: MGX I LP | D72: 45645 | E72: -32.32323 | G72: USD | H72: =E72+F72 -> -32.32323 | I72: Databricks
B73: GXI | C73: MGX I LP | D73: 45645 | E73: -0.458978 | G73: USD | H73: =E73+F73 -> -0.458978 | I73: Organisational Expenses (8m)
B74: GXI | C74: MGX I LP | D74: 45645 | E74: -0.030303 | G74: USD | H74: =E74+F74 -> -0.030303 | I74: Operating Expenses
B75: GXI | C75: MGX I LP | D75: 45712 | E75: -2.020202 | G75: USD | H75: =E75+F75 -> -2.020202 | I75: Open AI
B76: GXI | C76: MGX I LP | D76: 45712 | E76: -8.080808 | G76: USD | H76: =E76+F76 -> -8.080808 | I76: Databricks
B77: GXI | C77: MGX I LP | D77: 45712 | E77: -59.841678 | G77: USD | H77: =E77+F77 -> -59.841678 | I77: Khazna
B78: GXI | C78: MGX I LP | D78: 45713 | E78: -8.080737 | G78: USD | H78: =E78+F78 -> -8.080737 | I78: Safe Superintelligence Inc.
B79: GXI | C79: MGX I LP | D79: 45712 | E79: -0.28127 | G79: USD | H79: =E79+F79 -> -0.28127 | I79: Operating Expenses
B80: GXI | C80: MGX I LP | D80: 45770 | E80: -2.0539744 | G80: USD | H80: =E80+F80 -> -2.0539744 | I80: TBD
B81: GXI | C81: MGX I LP | E81: -6.1824409 | G81: USD | H81: =E81+F81 -> -6.1824409 | I81: Capital Call
B82: GXI | C82: MGX I LP | E82: 57.059152 | G82: USD | H82: =E82+F82 -> 57.059152 | I82: Return of Capital
B83: GXI | C83: MGX Denali (AIV) | D83: 45454 | E83: -4.440212 | G83: USD | H83: =E83+F83 -> -4.440212 | I83: Vantage
B84: GXI | C84: MGX Denali (AIV) | D84: 45468 | E84: -0.856702 | G84: USD | H84: =E84+F84 -> -0.856702 | I84: Vantage
B85: GXI | C85: MGX Denali (AIV) | D85: 45562 | E85: -1.766018 | G85: USD | H85: =E85+F85 -> -1.766018 | I85: Vantage
B86: GXI | C86: MGX Denali (AIV) | D86: 45581 | E86: -0.125982 | G86: USD | H86: =E86+F86 -> -0.125982 | I86: Vantage
B87: GXI | C87: MGX Denali (AIV) | D87: 45645 | E87: -3.257177 | G87: USD | H87: =E87+F87 -> -3.257177 | I87: Vantage
B88: GXI | C88: MGX Denali (AIV) | D88: 45726 | E88: -8.201327 | G88: USD | H88: =E88+F88 -> -8.201327 | I88: Vantage
B90: GXI | C90: MGX Strategic Co-Invest | D90: 45562 | E90: 250 | G90: USD | H90: =E90+F90 -> 250 | I90: Open AI
B91: GXI | C91: MGX Strategic Co-Invest | D91: 45618 | E91: 250 | G91: USD | H91: =E91+F91 -> 250 | I91: X.AI
B92: GXI | C92: MGX Strategic Co-Invest | D92: 45645 | E92: -125 | G92: USD | H92: =E92+F92 -> -125 | I92: Open AI
B93: GXI | C93: MGX Strategic Co-Invest | D93: 45645 | E93: -125 | G93: USD | H93: =E93+F93 -> -125 | I93: X.AI
B94: GXI | C94: MGX Strategic Co-Invest | D94: 45712 | E94: 12.5 | G94: USD | H94: =E94+F94 -> 12.5 | I94: Open AI
B95: GXI | C95: MGX Strategic Co-Invest | D95: 45713 | E95: 49.99956 | G95: USD | H95: =E95+F95 -> 49.99956 | I95: Safe Superintelligence Inc.

Sheet NAV
B2: NAV Date | C2: ='A. All deals (a)'!D2 -> 45900
B5: Investments | C5: Investing Entity | D5: Instrument | E5: Carrying Value | F5: Current Shares/Units | H5: Comment
E6: USD, Million | F6: # | G6: USD
E7: ="NAV | "& TEXT(C2,"dd")&" "&TEXT(C2,"mmm")&" "&TEXT(C2,"yyyy") -> NAV | 31 Aug 2025 | G7: ="PPS |" & TEXT(C2,"dd")&" "&TEXT(C2,"mmm")&" "&TEXT(C2,"yyyy") -> PPS |31 Aug 2025
B9: Direct Investments
B10: ='A. All deals (a)'!C9 -> Jollychic Holding Limited | C10: ='A. All deals (a)'!F9 -> Mozn | D10: ='A. All deals (a)'!H9 -> C+ Prefs | E10: =F10*G10*10^-6 -> 0 | F10: =VLOOKUP(B10,'B. %'!$C$6:$I$42,2,0) -> 13458655 | H10: In liquidation
B11: ='A. All deals (a)'!C10 -> Mena Mobile Inc | C11: ='A. All deals (a)'!F10 -> Mozn | D11: ='A. All deals (a)'!H10 -> B Prefs | E11: 0 | F11: =VLOOKUP(B11,'B. %'!$C$6:$I$42,2,0) -> 21419829 | H11: As per 3rd Party | Ardent Estimates | Equity written off | K11: =STOCKHISTORY(J18,$K$16,$K$16,0,0)
B12: ='A. All deals (a)'!C11 -> Flyr Inc | C12: ='A. All deals (a)'!F11 -> Mozn | D12: ='A. All deals (a)'!H11 -> B-1,2 Prefs | E12: =F12*G12*10^-6 -> 28.213712 | F12: =VLOOKUP(B12,'B. %'!$C$6:$I$42,2,0) -> 5205482 | G12: 5.42 | H12: As per the recent fund raise for Series D
B13: ='A. All deals (a)'!C12 -> Esyasoft Holding | C13: ='A. All deals (a)'!F12 -> Mozn | D13: ='A. All deals (a)'!H12 -> Convertible Note | E13: 0 | F13: =VLOOKUP(B13,'B. %'!$C$6:$I$42,2,0) -> n/a | H13: Exited at $5m (10th May) | Residual value = 0
B14: ='A. All deals (a)'!C13 -> Beyond Limits | C14: ='A. All deals (a)'!F13 -> Mozn | D14: ='A. All deals (a)'!H13 -> C Prefs | E14: =F14*G14/2/1000000 -> 41.003704 | F14: =VLOOKUP(B14,'B. %'!$C$6:$I$42,2,0) -> 17670202 | G14: 4.641 | H14: Marked down as per new round discussion Aug'24
B15: ='A. All deals (a)'!C14 -> ONT plc | C15: ='A. All deals (a)'!F14 -> Mozn | D15: ='A. All deals (a)'!H14 -> Ordinary Shares | E15: =F15*G15*10^-6 -> 108.27998 | F15: =VLOOKUP(B15,'B. %'!$C$6:$I$42,2,0) -> 44328120 | G15: =L18*L21/100 -> 2.4426927 | H15: Listed & marked to market | K15: =TEXT(K16,"ddd") -> Sun | R15: Heygears Oct 22
B16: ='A. All deals (a)'!C15 -> Heygears | C16: ='A. All deals (a)'!F15 -> Mozn | D16: ='A. All deals (a)'!H15 -> Registered Capital | E16: 40.3 | F16: ='CF (Equity, Debt)'!J20 -> 3565017.2 | H16: As per 3rd Party Ardent Estimates | Equity marked down | J16: Updated as on: | K16: =C2 -> 45900 | L16: source | R16: Post Valuation closed in June 2021 (RMB) | S16: 7500000000
B17: ='A. All deals (a)'!C16 -> Jysan Technologies | C17: ='A. All deals (a)'!F16 -> Mozn 1 | D17: ='A. All deals (a)'!H16 -> A (Ordinary Shares) | E17: 0 | F17: =VLOOKUP(B17,'B. %'!$C$6:$I$42,2,0) -> 7959497 | G17: =E17*10^6/F17 -> 0 | H17: Exited at $24.5m | R17: G42 Stake | S17: 0.143832
B18: ='A. All deals (a)'!C17 -> Cerebras Systems Inc | C18: ='A. All deals (a)'!F17 -> Mozn | D18: ='A. All deals (a)'!H17 -> F Prefs | E18: =F18*G18*10^-6 -> 21.135483 | F18: =VLOOKUP(B18,'B. %'!$C$6:$I$42,2,0) -> 1441711 | G18: 14.66 | H18: Marked down to the latest round | J18: ONT | K18: 45898 | L18: 180.9 | R18: G42 Valuation before Discount (RMB) | S18: 1078740000
B19: ='A. All deals (a)'!C18 -> Endless Studios LLC | C19: ='A. All deals (a)'!F18 -> Mozn | D19: ='A. All deals (a)'!H18 -> A Pref Units | E19: 4.7 | F19: =VLOOKUP(B19,'B. %'!$C$6:$I$42,2,0) -> 8000000 | H19: Ardent Valuation as of 31 Dec 24 | J19: VTVT | K19: 45898 | L19: 15.2 | R19: Liquidity Discount | S19: 0
B20: ='A. All deals (a)'!C19 -> Instadeep Limited | C20: ='A. All deals (a)'!F19 -> Mozn | D20: ='A. All deals (a)'!H19 -> B Prefs | E20: =-'CF (Equity, Debt)'!E24*G20 -> 0 | F20: =VLOOKUP(B20,'B. %'!$C$6:$I$42,2,0) -> 33267 | G20: 0 | H20: Exited at 1.56X | Residual Value = 0 | J20: VRSSF | K20: 45898 | L20: 5.66 | R20: Minority Holding Discount | S20: 0
B21: ='A. All deals (a)'!C20 -> X-fusion | C21: ='A. All deals (a)'!F20 -> Mozn 2 | D21: ='A. All deals (a)'!H20 -> Equity-TBC | E21: 0 | F21: =VLOOKUP(B21,'B. %'!$C$6:$I$42,2,0) -> n/a | H21: Exited at 0.82X | J21: GBPUSD | K21: 45898 | L21: 1.3503 | R21: G42 Valuation (RMB) | S21: =S18*(1-S19)*(1-S20) -> 1078740000
B22: ='A. All deals (a)'!C21 -> DriveNets | C22: ='A. All deals (a)'!F21 -> G42 Investments | D22: ='A. All deals (a)'!H21 -> Equity-TBC | E22: =(24403771*4.5712+44523131*4.8118)*10^-6 -> 325.79092 | F22: =VLOOKUP(B22,'B. %'!$C$6:$I$42,2,0) -> 68926902 | H22: New round/Secondary sale Q1 25 | J22: USDCNY | K22: 45898 | L22: 7.1304 | R22: Exchange Rate (RMB/USD) | S22: =K22 -> 45898
B23: ='A. All deals (a)'!C22 -> vTv Therapeutics Inc. | C23: ='A. All deals (a)'!F22 -> G42 Investments | D23: ='A. All deals (a)'!H22 -> Ordinary Shares | E23: =(F23*G23)*10^-6 -> 3.9467864 | F23: =VLOOKUP(B23,'B. %'!$C$6:$I$42,2,0) -> 259657 | G23: =L19 -> 15.2 | H23: Listed & marked to market | J23: EURUSD | K23: 45898 | L23: 1.1684 | R23: G42 Valuation (USD) | S23: =S21/S22 -> 23502.985
B24: ='A. All deals (a)'!C23 -> Honor Device Co Ltd | C24: ='A. All deals (a)'!F23 -> G42 3 | D24: ='A. All deals (a)'!H23 -> Equity-TBC | E24: 0 | F24: =VLOOKUP(B24,'B. %'!$C$6:$I$42,2,0) -> 6.0685078e+08 | H24: Exited at 1.0X | R24: Investment Cost of G42 (USD) | S24: 60000000
B25: ='A. All deals (a)'!C24 -> Applied AI Corporation Limited | C25: ='A. All deals (a)'!F24 -> Mozn | D25: ='A. All deals (a)'!H24 -> A Prefs | E25: 38.46473 | F25: =VLOOKUP(B25,'B. %'!$C$6:$I$42,2,0) -> 211519 | H25: Held at 2.27X
B26: ='A. All deals (a)'!C25 -> eSpace | C26: ='A. All deals (a)'!F25 -> Mozn 4 | D26: ='A. All deals (a)'!H25 -> B Prefs | E26: =F26*G26*10^-6 -> 32.34128 | F26: =VLOOKUP(B26,'B. %'!$C$6:$I$42,2,0) -> 417846 | G26: 77.4 | H26: Marked up, as converted as per the latest priced round | J26: Checks
B27: ='A. All deals (a)'!C26 -> Tools for Humanity Corporation | C27: ='A. All deals (a)'!F26 -> Mozn | D27: ='A. All deals (a)'!H26 -> C Prefs | E27: 2.4 | F27: =VLOOKUP(B27,'B. %'!$C$6:$I$42,2,0) -> 65413 | H27: Ardent Valuation as of 31 Dec 24
B28: ='A. All deals (a)'!C27 -> WLD Tokens | C28: ='A. All deals (a)'!F27 -> Mozn | D28: ='A. All deals (a)'!H27 -> Tokens | E28: =F28*G28*10^-6 -> 0 | F28: 0 | G28: =K17 -> 0 | H28: source: coinmarket cap | J28: =SUM(E10:E35) -> 878.23664 | K28: =J28='A. All deals (a)'!N36 -> TRUE
B29: ='A. All deals (a)'!C28 -> E-line Ventures LLC | C29: ='A. All deals (a)'!F28 -> Mozn | D29: ='A. All deals (a)'!H28 -> B Prefs | E29: 15.3 | F29: =VLOOKUP(B29,'B. %'!$C$6:$I$42,2,0) -> 4477612 | H29: Ardent Valuation as of 31 Dec 24 | J29: =SUM(E38:E40) -> 0 | K29: =J29='A. All deals (a)'!N42 -> TRUE
B30: ='A. All deals (a)'!C29 -> School Hack (AIREV Holding Limited) | C30: ='A. All deals (a)'!F29 -> Core42 5 | D30: ='A. All deals (a)'!H29 -> Preferred Shares | E30: =MAX('A. All deals (a)'!K29,F30*G30*10^-6) -> 2.5 | F30: =VLOOKUP(B30,'B. %'!$C$6:$I$42,2,0) -> 25000 | H30: Held at cost | J30: =SUM(E43:E47) -> 106.52706 | K30: =J30='A. All deals (a)'!N50 -> TRUE
B31: ='A. All deals (a)'!C30 -> Life Biosciences LLC | C31: ='A. All deals (a)'!F30 -> G42 Capital | D31: ='A. All deals (a)'!H30 -> D Prefs | E31: =(F31*G31*10^-6) -> 40.947394 | F31: =VLOOKUP(B31,'B. %'!$C$6:$I$42,2,0) -> 14178755 | G31: 2.88794 | H31: Held at cost
B32: ='A. All deals (a)'!C31 -> Verses AI Inc | C32: ='A. All deals (a)'!F31 -> G42 Capital | D32: ='A. All deals (a)'!H31 -> Ordinary Shares | E32: =F32*L20*10^-6 -> 2.9127687 | F32: =VLOOKUP(B32,'B. %'!$C$6:$I$42,2,0) -> 514623.44 | H32: Listed & marked to market
B33: ='A. All deals (a)'!C32 -> Inveniam Ltd | C33: G42 Capital | D33: SAR | E33: 100 | F33: =VLOOKUP(B33,'B. %'!$C$6:$I$42,2,0) -> n/a | H33: Held at cost
B34: Liquid AI | C34: G42 Capital | D34: Series A | E34: ='CF (Equity, Debt)'!I56*10^-6 -> 19.999882 | F34: n/a | H34: Held at cost
B35: Neuralink | C35: G42 Capital | D35: Series E | E35: =50 -> 50 | F35: n/a | H35: Held at cost
B37: Debt Investments
B38: Glass Earth Holdings LLC | C38: Mozn | D38: Promissory Note | E38: ='A. All deals (a)'!N39 -> 0 | H38: In default
B39: Mena Mobile Inc (Debt) | C39: Mozn | D39: Loan | E39: 0 | H39: In liquidation
B40: Esyasoft Holding (Debt) | C40: Mozn | D40: Loan | E40: 0 | H40: Exited. Received payment of $470,784.65 ($411K+$59K)
B42: Funds Investments
B43: New Space Capital Fund I | C43: G42 | D43: LP | E43: ='8. NewSpace'!M38*10^-6*L23 -> 25.615387 | H43: Q2'25 capital account statement
B44: New Space Capital GP Com SCSp | C44: G42 | D44: GP | E44: =E43*'1. Live'!L27/'1. Live'!L26 -> 3.6272895 | H44: Q2'25 capital account statement
B45: North Summit Capital Fund | C45: G42 | D45: LP | E45: =64.228074 -> 64.228074 | H45: Q2'25 capital account statement
B46: Sinovation Disrupt Fund, L.P. | C46: G42 | D46: LP | E46: 0 | H46: Exited
B47: Acies Investments Fund I, L.P. | C47: G42 | D47: LP | E47: 13.056308 | H47: Q2'25 capital account statement
B49: MGX I LP | E49: =MGX!H14 -> 326.2094 | H49: Q2'25 capital account statement
B50: MGX1 Co-invest | C50: GXI | D50: LP | E50: 396.0636 | H50: Q2'25 capital account statement
B52: Note:
B53: • Respective listed share prices for ONT and vTv Therapeutics are used for estimating the NAVs
E54: 39.740951

Sheet B. %
C2: % OWNERSHIP
C3: As of date | D3: ='A. All deals (a)'!D2 -> 45900
C6: Deals | D6: Shares / Units | E6: Total | F6: % | G6: Source for % holding | H6: Incorporation/Jurisdiction | I6: Country
C8: Direct Investments
B9: Written Off | C9: ='A. All deals (a)'!C9 -> Jollychic Holding Limited | D9: 13458655 | E9: 236116762 | F9: =D9/E9 -> 0.056999998 | G9: Dan Kong | H9: Cayman Islands | I9: Cayman Islands
B10: Written Off | C10: ='A. All deals (a)'!C10 -> Mena Mobile Inc | D10: 21419829 | E10: 152998776 | F10: =D10/E10 -> 0.14 | G10: Dan Kong | H10: Cayman Islands | I10: Cayman Islands
C11: ='A. All deals (a)'!C11 -> Flyr Inc | D11: 5205482 | E11: =147338939 -> 147338939 | F11: =D11/E11 -> 0.035329982 | G11: Cap Table as of May'25 | H11: Delaware Corporation | I11: USA
B12: Exited | C12: ='A. All deals (a)'!C12 -> Esyasoft Holding | D12: n/a | E12: n/a | F12: n/a | G12: n/a; exited | H12: DIFC | I12: Dubai, UAE
C13: ='A. All deals (a)'!C13 -> Beyond Limits | D13: 17670202 | E13: 187288050 | F13: =D13/E13 -> 0.094347728 | G13: Cap Table | H13: Delaware Corporation | I13: USA
C14: ='A. All deals (a)'!C14 -> ONT plc | D14: 44328120 | E14: =955.45*10^6 -> 955450000 | F14: =D14/E14 -> 0.046395018 | G14: LSE Announcement | H14: UK | I14: UK
C15: ='A. All deals (a)'!C15 -> Heygears | D15: 3565017.2 | E15: 24785982 | F15: =D15/E15 -> 0.14383199 | G15: Dan Kong | H15: PRC | I15: China
B16: Exited | C16: ='A. All deals (a)'!C16 -> Jysan Technologies | D16: 7959497 | E16: 2.6531657e+08 | F16: 0.03 | G16: Txn docs | H16: UK | I16: UK
C17: ='A. All deals (a)'!C17 -> Cerebras Systems Inc | D17: 1441711 | E17: =D17/F17 -> 1.7798901e+08 | F17: 0.0081 | G17: Cap table as of Dec'22 | H17: Delaware Corporation | I17: USA
C18: ='A. All deals (a)'!C18 -> Endless Studios LLC | D18: 8000000 | E18: =38750000+11000000+2000000 -> 51750000 | F18: =D18/E18 -> 0.15458937 | G18: Cap table as of Dec'22 | H18: Delaware Corporation | I18: USA
B19: Exited | C19: ='A. All deals (a)'!C19 -> Instadeep Limited | D19: 33267 | E19: 2895450 | F19: =D19/E19 -> 0.011489406 | G19: Txn docs; exit underway | H19: UK | I19: UK
B20: Exited | C20: ='A. All deals (a)'!C20 -> X-fusion | D20: n/a | E20: n/a | F20: =10% * 51% -> 0.051 | G20: Dan Kong | H20: PRC | I20: China
C21: ='A. All deals (a)'!C21 -> DriveNets | D21: =24403771+44523131 -> 68926902 | E21: =D21/F21 -> 7.8504444e+08 | F21: 0.0878 | G21: Cap table as of Mar'23 | H21: Israeli Pvt Company | I21: Israel
C22: ='A. All deals (a)'!C22 -> vTv Therapeutics Inc. | D22: =ROUNDUP(10386274/40,0) -> 259657 | E22: =2612257+577349 -> 3189606 | F22: =D22/E22 -> 0.081407233 | G22: 10Q report Jun'23 | H22: Delaware Corporation | I22: USA
B23: Exited | C23: ='A. All deals (a)'!C23 -> Honor Device Co Ltd | D23: =1517126944.34*0.8/2 -> 6.0685078e+08 | E23: 3.2238948e+10 | F23: =4.705882%* 0.8/2 -> 0.018823528 | G23: Dan Kong | H23: PRC | I23: China
C24: ='A. All deals (a)'!C24 -> Applied AI Corporation Limited | D24: =44133+39500+54863+73023 -> 211519 | E24: 1744988 | F24: =D24/E24 -> 0.12121516 | G24: n/a; convertible note | H24: ADGM | I24: Abu Dhabi, UAE | L24: Eline Estimates
C25: ='A. All deals (a)'!C25 -> eSpace | D25: 417846 | E25: 16036336 | F25: =D25/E25 -> 0.026056201 | G25: Series B Pref | H25: Delaware Corporation | I25: USA | L25: 5400972 | M25: Common Unit
C26: ='A. All deals (a)'!C26 -> Tools for Humanity Corporation | D26: 65413 | E26: 10439222 | F26: =D26/E26 -> 0.00626608 | G26: Email: Sam Thomson | H26: Delaware Corporation | I26: USA | L26: 4857352 | M26: Series A
C27: ='A. All deals (a)'!C27 -> WLD Tokens | D27: 62500000 | E27: 10000000000 | F27: =D27/E27 -> 0.00625 | G27: Email: Sam Thomson | H27: DAO | Cayman Islands | I27: Cayman Islands | L27: 16791835 | M27: Series B
C28: ='A. All deals (a)'!C28 -> E-line Ventures LLC | D28: 4477612 | E28: =L31 -> 38990900 | F28: =D28/E28 -> 0.11483736 | G28: IAF 12Jul23 | H28: New Jersey | I28: New Jersey | L28: 1465517 | M28: Series B-S1
C29: ='A. All deals (a)'!C29 -> School Hack (AIREV Holding Limited) | D29: 25000 | E29: 100000 | F29: =D29/E29 -> 0.25 | G29: Shareholders Resolution | H29: ADGM | I29: UAE | L29: =D28*2 -> 8955224 | M29: Seires B 2023
C30: ='A. All deals (a)'!C30 -> Life Biosciences LLC | D30: 14178755 | E30: 194237760 | F30: =D30/E30 -> 0.072996903 | G30: n/a; convertible note | H30: Delaware Corporation | I30: USA | L30: 1520000 | M30: Series B 2023 P
C31: ='A. All deals (a)'!C31 -> Verses AI Inc | D31: =13894833*1/9*1/3 -> 514623.44 | E31: =D31/F31 -> 9839836.4 | F31: 0.0523 | G31: n/a; convertible debenture | H31: Victoria, British Columbia | I31: Canada | L31: =SUM(L25:L30) -> 38990900
C32: ='A. All deals (a)'!C32 -> Inveniam Ltd | D32: n/a | E32: =13481499/0.2 -> 67407495 | F32: 20% Eq | G32: equity interest held via SAR | H32: Gibraltor | I32: British Overseas Territory
C33: Liquid AI | D33: 165082 | E33: 26293026 | F33: =D33/E33 -> 0.006278547 | G33: Cap Table | H33: Delaware Corporation | I33: USA
C34: Neuralink | D34: 990099 | E34: 191119513 | F34: =D34/E34 -> 0.0051805228 | G34: Cap Table | I34: USA
C37: Funds Investments | D37: G42 Commitment | E37: Fund Size
C38: New Space Capital Fund I | D38: 23234462 | E38: 105400000 | F38: =D38/E38 -> 0.22044082 | G38: Estimated as per Q1-23 NAV report | H38: Luxembourg | I38: Luxembourg
C39: New Space Capital GP Com SCSp | D39: =-'CF (Funds)'!H59*10^6 -> 2125000 | E39: 105400000 | F39: =D39/E39 -> 0.02016129 | H39: Luxembourg | I39: Luxembourg
C40: North Summit Capital Fund | D40: 300000000 | E40: 301507538 | F40: =D40/E40 -> 0.995 | G40: Q4'22 Report | H40: Cayman Islands | I40: Cayman Islands
B41: Exited | C41: Sinovation Disrupt Fund, L.P. | D41: 50000000 | E41: 496717172 | F41: =D41/E41 -> 0.1006609 | G41: Q2'23 Report | H41: Cayman Islands | I41: Cayman Islands
C42: Acies Investments Fund I, L.P. | D42: 17112500 | E42: 51337500 | F42: =D42/E42 -> 0.33333333 | G42: Q1 23 Report | H42: Delaware LLC | I42: USA
C43: MGX I LP | D43: 1200000000 | E43: 38400000000 | F43: =D43/E43 -> 0.03125

Sheet E. Board
C3: Deals | D3: Board Representation ‡ | E3: Representative | F3: Notes | G3: Status | H3: Comments
C5: Direct Investments
C6: Mena Mobile Inc | D6: 1 Director | E6: Peng Xiao | G6: In Liquidation
C7: Flyr Inc | D7: 1 Observer | E7: Jon Nieman | H7: Earlier 1 Director represented by Marty
C8: Esyasoft Holding | D8: NR | E8: n/a | F8: 2 | G8: Exited | H8: Monty Aw represented earlier
C9: Jollychic Holding Limited | D9: 1 Director | E9: Divyesh Mahajan | F9: 1 | G9: In Liquidation
C10: Beyond Limits | D10: 1 Director | E10: Jon Nieman | F10: 3
C11: ONT plc | D11: 1 Director | E11: Guy Harmelin (Independent Director)
C12: Heygears | D12: 2 Director | E12: Elaine | G12: Peng Resigned Jan24 | H12: PX to be replaced by XP
C13: Jysan Technologies | D13: 1 Director | E13: None appointed | G13: Exited | H13: Exited
C14: Cerebras Systems Inc | D14: 1 Observer | E14: Eric Xing | F14: 4
C15: Endless Studios LLC | D15: 1 Director 1 Observer | E15: Jon Nieman
C16: Instadeep Limited | D16: 1 Observer | G16: Exited | H16: Exited
C17: X-fusion | D17: NR | E17: n/a | G17: Exited
C18: DriveNets | D18: 1 Observer | E18: Guy Harmelin
C19: vTv Therapeutics Inc. | D19: 1 Director, 1 Observer | E19: Dr. Fahad (Board), Jon Nieman (Observer)
C20: Honor Device Co Ltd | D20: NR | E20: n/a | F20: 5 | G20: Exited
C21: Applied AI Corporation Limited | D21: NR | E21: n/a
C22: eSpace | D22: NR | E22: n/a
C23: Tools for Humanity Corporation | D23: NR | E23: n/a
C24: E-line Ventures LLC
C25: School Hack (AIREV Holding Limited) | D25: 2 Director | E25: n/a
C28: Debt Investments
C29: Glass Earth Holdings LLC | D29: NR
C30: Mena Mobile Inc | D30: 1 Director | E30: Peng Xiao | G30: In Liquidation
C31: Esyasoft Holding | D31: NR
C34: Funds Investments
C35: New Space Capital Fund I | D35: 1 Director | E35: Jon Nieman
C36: New Space Capital GP Com SCSp | D36: NR
C37: North Summit Capital Fund | D37: NR
C38: Sinovation Disrupt Fund, L.P. | D38: NR | G38: Exited
C39: Acies Investments Fund I, L.P. | D39: Advisory Board | E39: Not yet appointed | H39: Confirm appoinment
C43: NOTES:
C44: NR = No Rights / No Representation
C45: n/a = not applicable or not available
C46: ‡ Board Representation : as a Board Seat, Observer, or Advisor
B47: 1 | C47: Jollychic Holding : Peng Xiao held the directorship until Jun 2021
B48: 2 | C48: Esyasoft: we held a Board seat, with Monty Aw as the representative, until Jun 2022
B49: 3 | C49: Beyond Limits: possibility of the 2nd Board seat in case we invest (an additional / an earlier committed) $10m
B50: 4 | C50: Cerebras : possibility of a Board seat, If G42 holds >10% with rights to exercise at least 20% of warrant
B51: 5 | C51: Honor: Our board seat only kicks in once Honor is converted into a joint stock company in March 2023; there is no one appointed as yet

Sheet A. All deals (a)
C2: As of date | D2: ='D1'!D2 -> 45900
C6: Deals | D6: Status | F6: Investing Entity Ϋ | G6: Vintageἀ | H6: Instrument | I6: % | J6: Committed | K6: Invested | L6: Remaining Commitment | M6: Distributions | N6: Carrying Value | O6: Gain | P6: TVPI | Q6: Additional Upside/Downside
G7: # | I7: % | J7: $,m | K7: $,m | L7: $,m | M7: $,m | N7: $,m | O7: $,m | P7: X
C8: Equity or Equity like Investments
C9: Jollychic Holding Limited | D9: Written-off | F9: Mozn | G9: 2019 | H9: C+ Prefs | I9: ='B. %'!F9 -> 0.056999998 | J9: =K9 -> 65 | K9: =-SUMIF('CF (Equity, Debt)'!$C$3:$K$61,'A. All deals (a)'!C9,'CF (Equity, Debt)'!$E$3:$E$61) -> 65 | L9: 0 | M9: =SUMIF('CF (Equity, Debt)'!$C$3:$K$61,'A. All deals (a)'!C9,'CF (Equity, Debt)'!$F$3:$F$61) -> 0 | N9: =VLOOKUP(C9,NAV!$B$4:$E$47,4,0) -> 0 | O9: =N9+M9-K9 -> -65 | P9: =(M9+N9)/K9 -> 0 | Q9: In Liquidation
C10: Mena Mobile Inc | D10: Written-off | F10: Mozn | G10: 2019 | H10: B Prefs | I10: ='B. %'!F10 -> 0.14 | J10: =K10 -> 8 | K10: =-SUMIF('CF (Equity, Debt)'!$C$3:$K$61,'A. All deals (a)'!C10,'CF (Equity, Debt)'!$E$3:$E$61) -> 8 | L10: 0 | M10: =SUMIF('CF (Equity, Debt)'!$C$3:$K$61,'A. All deals (a)'!C10,'CF (Equity, Debt)'!$F$3:$F$61) -> 0 | N10: =VLOOKUP(C10,NAV!$B$4:$E$47,4,0) -> 0 | O10: =N10+M10-K10 -> -8 | P10: =(M10+N10)/K10 -> 0 | Q10: In Liquidation
C11: Flyr Inc | D11: Unrealized | F11: Mozn | G11: 2019 | H11: B-1,2 Prefs | I11: ='B. %'!F11 -> 0.035329982 | J11: =K11 -> 10 | K11: =-SUMIF('CF (Equity, Debt)'!$C$3:$K$61,'A. All deals (a)'!C11,'CF (Equity, Debt)'!$E$3:$E$61) -> 10 | L11: 0 | M11: =SUMIF('CF (Equity, Debt)'!$C$3:$K$61,'A. All deals (a)'!C11,'CF (Equity, Debt)'!$F$3:$F$61) -> 0 | N11: =VLOOKUP(C11,NAV!$B$4:$E$47,4,0) -> 28.213712 | O11: =N11+M11-K11 -> 18.213712 | P11: =(M11+N11)/K11 -> 2.8213712 | Q11: Flyr Warrantsa 2025 expiry
C12: Esyasoft Holding | D12: Realized | F12: Mozn | G12: 2020 | H12: Convertible Note | I12: ='B. %'!F12 -> n/a | J12: =K12 -> 2.5 | K12: =-SUMIF('CF (Equity, Debt)'!$C$3:$K$61,'A. All deals (a)'!C12,'CF (Equity, Debt)'!$E$3:$E$61) -> 2.5 | L12: 0 | M12: =SUMIF('CF (Equity, Debt)'!$C$3:$K$61,'A. All deals (a)'!C12,'CF (Equity, Debt)'!$F$3:$F$61) -> 5 | N12: =VLOOKUP(C12,NAV!$B$4:$E$47,4,0) -> 0 | O12: =N12+M12-K12 -> 2.5 | P12: =(M12+N12)/K12 -> 2
C13: Beyond Limits | D13: Unrealized | F13: Mozn | G13: 2020 | H13: C Prefs | I13: ='B. %'!F13 -> 0.094347728 | J13: =K13 -> 90 | K13: =-SUMIF('CF (Equity, Debt)'!$C$3:$K$61,'A. All deals (a)'!C13,'CF (Equity, Debt)'!$E$3:$E$61) -> 90 | L13: 0 | M13: =SUMIF('CF (Equity, Debt)'!$C$3:$K$61,'A. All deals (a)'!C13,'CF (Equity, Debt)'!$F$3:$F$61) -> 0 | N13: =VLOOKUP(C13,NAV!$B$4:$E$47,4,0) -> 41.003704 | O13: =N13+M13-K13 -> -48.996296 | P13: =(M13+N13)/K13 -> 0.45559671
C14: ONT plc | D14: Unrealized | F14: Mozn | G14: 2020 | H14: Ordinary Shares | I14: ='B. %'!F14 -> 0.046395018 | J14: =K14 -> 141.47026 | K14: =-SUMIF('CF (Equity, Debt)'!$C$3:$K$61,'A. All deals (a)'!C14,'CF (Equity, Debt)'!$E$3:$E$61) -> 141.47026 | L14: 0 | M14: =SUMIF('CF (Equity, Debt)'!$C$3:$K$61,'A. All deals (a)'!C14,'CF (Equity, Debt)'!$F$3:$F$61) -> 0 | N14: =VLOOKUP(C14,NAV!$B$4:$E$47,4,0) -> 108.27998 | O14: =N14+M14-K14 -> -33.190285 | P14: =(M14+N14)/K14 -> 0.76539038
C15: Heygears | D15: Unrealized | F15: Mozn | G15: 2020 | H15: Registered Capital | I15: ='B. %'!F15 -> 0.14383199 | J15: =K15 -> 60 | K15: =-SUMIF('CF (Equity, Debt)'!$C$3:$K$61,'A. All deals (a)'!C15,'CF (Equity, Debt)'!$E$3:$E$61) -> 60 | L15: 0 | M15: =SUMIF('CF (Equity, Debt)'!$C$3:$K$61,'A. All deals (a)'!C15,'CF (Equity, Debt)'!$F$3:$F$61) -> 0 | N15: =VLOOKUP(C15,NAV!$B$4:$E$47,4,0) -> 40.3 | O15: =N15+M15-K15 -> -19.7 | P15: =(M15+N15)/K15 -> 0.67166667
C16: Jysan Technologies | D16: Realized | F16: Mozn 1 | G16: 2021 | H16: A (Ordinary Shares) | I16: ='B. %'!F16 -> 0.03 | J16: =K16 -> 20 | K16: =-SUMIF('CF (Equity, Debt)'!$C$3:$K$61,'A. All deals (a)'!C16,'CF (Equity, Debt)'!$E$3:$E$61) -> 20 | L16: 0 | M16: =SUMIF('CF (Equity, Debt)'!$C$3:$K$61,'A. All deals (a)'!C16,'CF (Equity, Debt)'!$F$3:$F$61) -> 24.5 | N16: =VLOOKUP(C16,NAV!$B$4:$E$47,4,0) -> 0 | O16: =N16+M16-K16 -> 4.5 | P16: =(M16+N16)/K16 -> 1.225
C17: Cerebras Systems Inc | D17: Unrealized | F17: Mozn | G17: 2021 | H17: F Prefs | I17: ='B. %'!F17 -> 0.0081 | J17: =K17 -> 39.999983 | K17: =-SUMIF('CF (Equity, Debt)'!$C$3:$K$61,'A. All deals (a)'!C17,'CF (Equity, Debt)'!$E$3:$E$61) -> 39.999983 | L17: 0 | M17: =SUMIF('CF (Equity, Debt)'!$C$3:$K$61,'A. All deals (a)'!C17,'CF (Equity, Debt)'!$F$3:$F$61) -> 0 | N17: =VLOOKUP(C17,NAV!$B$4:$E$47,4,0) -> 21.135483 | O17: =N17+M17-K17 -> -18.8645 | P17: =(M17+N17)/K17 -> 0.5283873
C18: Endless Studios LLC | D18: Unrealized | F18: Mozn | G18: 2021 | H18: A Pref Units | I18: ='B. %'!F18 -> 0.15458937 | J18: =K18 -> 8 | K18: =-SUMIF('CF (Equity, Debt)'!$C$3:$K$61,'A. All deals (a)'!C18,'CF (Equity, Debt)'!$E$3:$E$61) -> 8 | L18: 0 | M18: =SUMIF('CF (Equity, Debt)'!$C$3:$K$61,'A. All deals (a)'!C18,'CF (Equity, Debt)'!$F$3:$F$61) -> 0 | N18: =VLOOKUP(C18,NAV!$B$4:$E$47,4,0) -> 4.7 | O18: =N18+M18-K18 -> -3.3 | P18: =(M18+N18)/K18 -> 0.5875
C19: Instadeep Limited | D19: Realized | F19: Mozn | G19: 2021 | H19: B Prefs | I19: ='B. %'!F19 -> 0.011489406 | J19: =K19 -> 5.0237202 | K19: =-SUMIF('CF (Equity, Debt)'!$C$3:$K$61,'A. All deals (a)'!C19,'CF (Equity, Debt)'!$E$3:$E$61) -> 5.0237202 | L19: 0 | M19: =SUMIF('CF (Equity, Debt)'!$C$3:$K$61,'A. All deals (a)'!C19,'CF (Equity, Debt)'!$F$3:$F$61) -> 7.9421925 | N19: =VLOOKUP(C19,NAV!$B$4:$E$47,4,0) -> 0 | O19: =N19+M19-K19 -> 2.9184723 | P19: =(M19+N19)/K19 -> 1.5809385
C20: X-fusion | D20: Realized | F20: Mozn 2 | G20: 2022 | H20: Equity-TBC | I20: ='B. %'!F20 -> 0.051 | J20: =K20 -> 493.50096 | K20: =-SUMIF('CF (Equity, Debt)'!$C$3:$K$61,'A. All deals (a)'!C20,'CF (Equity, Debt)'!$E$3:$E$61) -> 493.50096 | L20: 0 | M20: =SUMIF('CF (Equity, Debt)'!$C$3:$K$61,'A. All deals (a)'!C20,'CF (Equity, Debt)'!$F$3:$F$61) -> 403 | N20: =VLOOKUP(C20,NAV!$B$4:$E$47,4,0) -> 0 | O20: =N20+M20-K20 -> -90.500956 | P20: =(M20+N20)/K20 -> 0.81661443
C21: DriveNets | D21: Partially Realized | F21: G42 Investments | G21: 2022 | H21: Equity-TBC | I21: ='B. %'!F21 -> 0.0878 | J21: =K21 -> 300 | K21: =-SUMIF('CF (Equity, Debt)'!$C$3:$K$61,'A. All deals (a)'!C21,'CF (Equity, Debt)'!$E$3:$E$61) -> 300 | L21: =0 -> 0 | M21: =SUMIF('CF (Equity, Debt)'!$C$3:$K$61,'A. All deals (a)'!C21,'CF (Equity, Debt)'!$F$3:$F$61) -> 84.804486 | N21: =VLOOKUP(C21,NAV!$B$4:$E$47,4,0) -> 325.79092 | O21: =N21+M21-K21 -> 110.59541 | P21: =(M21+N21)/K21 -> 1.3686514 | Q21: DN Warrants b
C22: vTv Therapeutics Inc. | D22: Unrealized | F22: G42 Investments | G22: 2022 | H22: Ordinary Shares | I22: ='B. %'!F22 -> 0.081407233 | J22: =K22 -> 24.53125 | K22: =-SUMIF('CF (Equity, Debt)'!$C$3:$K$61,'A. All deals (a)'!C22,'CF (Equity, Debt)'!$E$3:$E$61) -> 24.53125 | L22: =J22-K22 -> 0 | M22: =SUMIF('CF (Equity, Debt)'!$C$3:$K$61,'A. All deals (a)'!C22,'CF (Equity, Debt)'!$F$3:$F$61) -> 0 | N22: =VLOOKUP(C22,NAV!$B$4:$E$47,4,0) -> 3.9467864 | O22: =N22+M22-K22 -> -20.584464 | P22: =(M22+N22)/K22 -> 0.16088811 | Q22: vTv $30m milestn payment c
C23: Honor Device Co Ltd | D23: Realized | F23: G42 3 | G23: 2022 | H23: Equity-TBC | I23: ='B. %'!F23 -> 0.018823528 | J23: =K23 -> 800 | K23: =-SUMIF('CF (Equity, Debt)'!$C$3:$K$61,'A. All deals (a)'!C23,'CF (Equity, Debt)'!$E$3:$E$61) -> 800 | L23: =J23-K23 -> 0 | M23: =SUMIF('CF (Equity, Debt)'!$C$3:$K$61,'A. All deals (a)'!C23,'CF (Equity, Debt)'!$F$3:$F$61) -> 802.8 | N23: =VLOOKUP(C23,NAV!$B$4:$E$47,4,0) -> 0 | O23: =N23+M23-K23 -> 2.8 | P23: =(M23+N23)/K23 -> 1.0035
C24: Applied AI Corporation Limited | D24: Unrealized | F24: Mozn | G24: 2022 | H24: A Prefs | I24: ='B. %'!F24 -> 0.12121516 | J24: 15 | K24: =-SUMIF('CF (Equity, Debt)'!$C$3:$K$61,'A. All deals (a)'!C24,'CF (Equity, Debt)'!$E$3:$E$61) -> 15 | L24: =J24-K24 -> 0 | M24: =SUMIF('CF (Equity, Debt)'!$C$3:$K$61,'A. All deals (a)'!C24,'CF (Equity, Debt)'!$F$3:$F$61) -> 0 | N24: =VLOOKUP(C24,NAV!$B$4:$E$47,4,0) -> 38.46473 | O24: =N24+M24-K24 -> 23.46473 | P24: =(M24+N24)/K24 -> 2.5643153
C25: eSpace | D25: Unrealized | F25: Mozn 4 | G25: 2022 | H25: B Prefs | I25: ='B. %'!F25 -> 0.026056201 | J25: =K25 -> 15 | K25: =-SUMIF('CF (Equity, Debt)'!$C$3:$K$61,'A. All deals (a)'!C25,'CF (Equity, Debt)'!$E$3:$E$61) -> 15 | L25: =J25-K25 -> 0 | M25: =SUMIF('CF (Equity, Debt)'!$C$3:$K$61,'A. All deals (a)'!C25,'CF (Equity, Debt)'!$F$3:$F$61) -> 0 | N25: =VLOOKUP(C25,NAV!$B$4:$E$47,4,0) -> 32.34128 | O25: =N25+M25-K25 -> 17.34128 | P25: =(M25+N25)/K25 -> 2.1560854
C26: Tools for Humanity Corporation | D26: Unrealized | F26: Mozn | G26: 2023 | H26: C Prefs | I26: ='B. %'!F26 -> 0.00626608 | J26: =K26 -> 14.999999 | K26: =-SUMIF('CF (Equity, Debt)'!$C$3:$K$61,'A. All deals (a)'!C26,'CF (Equity, Debt)'!$E$3:$E$61) -> 14.999999 | L26: =J26-K26 -> 0 | M26: =SUMIF('CF (Equity, Debt)'!$C$3:$K$61,'A. All deals (a)'!C26,'CF (Equity, Debt)'!$F$3:$F$61) -> 0 | N26: =VLOOKUP(C26,NAV!$B$4:$E$47,4,0) -> 2.4 | O26: =N26+M26-K26 -> -12.599999 | P26: =(M26+N26)/K26 -> 0.16000001
C27: WLD Tokens | D27: Unrealized | F27: Mozn | G27: 2023 | H27: Tokens | I27: ='B. %'!F27 -> 0.00625 | J27: =K27 -> 0.006875 | K27: =-SUMIF('CF (Equity, Debt)'!$C$3:$K$61,'A. All deals (a)'!C27,'CF (Equity, Debt)'!$E$3:$E$61) -> 0.006875 | L27: =J27-K27 -> 0 | M27: =SUMIF('CF (Equity, Debt)'!$C$3:$K$61,'A. All deals (a)'!C27,'CF (Equity, Debt)'!$F$3:$F$61) -> 100 | N27: =VLOOKUP(C27,NAV!$B$4:$E$47,4,0) -> 0 | O27: =N27+M27-K27 -> 99.993125 | P27: NM | Q27: Crypto Tokensd
C28: E-line Ventures LLC | D28: Unrealized | F28: Mozn | G28: 2023 | H28: B Prefs | I28: ='B. %'!F28 -> 0.11483736 | J28: =K28 -> 6 | K28: =-SUMIF('CF (Equity, Debt)'!$C$3:$K$61,'A. All deals (a)'!C28,'CF (Equity, Debt)'!$E$3:$E$61) -> 6 | L28: =J28-K28 -> 0 | M28: =SUMIF('CF (Equity, Debt)'!$C$3:$K$61,'A. All deals (a)'!C28,'CF (Equity, Debt)'!$F$3:$F$61) -> 0 | N28: =VLOOKUP(C28,NAV!$B$4:$E$47,4,0) -> 15.3 | O28: =N28+M28-K28 -> 9.3 | P28: =(M28+N28)/K28 -> 2.55 | Q28: Optionse
C29: School Hack (AIREV Holding Limited) | D29: Unrealized | F29: Core42 5 | G29: 2024 | H29: Preferred Shares | I29: ='B. %'!F29 -> 0.25 | J29: =K29+0.25 -> 2.75 | K29: =-SUMIF('CF (Equity, Debt)'!$C$3:$K$61,'A. All deals (a)'!C29,'CF (Equity, Debt)'!$E$3:$E$61) -> 2.5 | L29: =J29-K29 -> 0.25 | M29: =SUMIF('CF (Equity, Debt)'!$C$3:$K$61,'A. All deals (a)'!C29,'CF (Equity, Debt)'!$F$3:$F$61) -> 0 | N29: =VLOOKUP(C29,NAV!$B$4:$E$47,4,0) -> 2.5 | O29: =N29+M29-K29 -> 0 | P29: =(M29+N29)/K29 -> 1 | Q29: Cloud Creditg
C30: Life Biosciences LLC | D30: Unrealized | F30: G42 Capital | G30: 2024 | H30: D Prefs | I30: ='B. %'!F30 -> 0.072996903 | J30: =K30 -> 40 | K30: =-SUMIF('CF (Equity, Debt)'!$C$3:$K$61,'A. All deals (a)'!C30,'CF (Equity, Debt)'!$E$3:$E$61) -> 40 | L30: =J30-K30 -> 0 | M30: =SUMIF('CF (Equity, Debt)'!$C$3:$K$61,'A. All deals (a)'!C30,'CF (Equity, Debt)'!$F$3:$F$61) -> 0 | N30: =VLOOKUP(C30,NAV!$B$4:$E$47,4,0) -> 40.947394 | O30: =N30+M30-K30 -> 0.94739371 | P30: =(M30+N30)/K30 -> 1.0236848
C31: Verses AI Inc | D31: Unrealized | F31: G42 Capital | G31: 2024 | H31: Ordinary Shares | I31: ='B. %'!F31 -> 0.0523 | J31: 10 | K31: =-SUMIF('CF (Equity, Debt)'!$C$3:$K$61,'A. All deals (a)'!C31,'CF (Equity, Debt)'!$E$3:$E$61) -> 10 | L31: =J31-K31 -> 0 | M31: =SUMIF('CF (Equity, Debt)'!$C$3:$K$61,'A. All deals (a)'!C31,'CF (Equity, Debt)'!$F$3:$F$61) -> 0 | N31: =VLOOKUP(C31,NAV!$B$4:$E$47,4,0) -> 2.9127687 | O31: =N31+M31-K31 -> -7.0872313 | P31: =(M31+N31)/K31 -> 0.29127687 | Q31: Revenue linked RSUs
C32: Inveniam Ltd | D32: Unrealized | F32: G42 Capital | G32: 2024 | H32: SAR | I32: ='B. %'!F32 -> 20% Eq | J32: 100 | K32: =-SUMIF('CF (Equity, Debt)'!$C$3:$K$61,'A. All deals (a)'!C32,'CF (Equity, Debt)'!$E$3:$E$61) -> 100 | L32: =J32-K32 -> 0 | M32: =SUMIF('CF (Equity, Debt)'!$C$3:$K$61,'A. All deals (a)'!C32,'CF (Equity, Debt)'!$F$3:$F$61) -> 0.499965 | N32: =VLOOKUP(C32,NAV!$B$4:$E$47,4,0) -> 100 | O32: =N32+M32-K32 -> 0.499965 | P32: =(M32+N32)/K32 -> 1.0049997 | Q32: Upside if Tokens sold > $2.5 per token
C33: Liquid AI | D33: Unrealized | F33: G42 Capital | G33: 2024 | H33: Series A | I33: ='B. %'!F33 -> 0.006278547 | J33: =(165082+384643)*10^-6*121.1512 -> 66.599843 | K33: =-SUMIF('CF (Equity, Debt)'!$C$3:$K$61,'A. All deals (a)'!C33,'CF (Equity, Debt)'!$E$3:$E$61) -> 19.999882 | L33: =J33-K33 -> 46.599961 | M33: 0 | N33: =VLOOKUP(C33,NAV!$B$4:$E$47,4,0) -> 19.999882 | O33: =N33+M33-K33 -> 0 | P33: =(M33+N33)/K33 -> 1 | Q33: Awaiting CFIUS clearance; option to buy $45m more
C34: Cerebras Systems Inc F1 | D34: Not Completed | F34: G42 Capital | G34: 2025 | H34: Series F-1 | I34: TBD | J34: =335/3 -> 111.66667 | K34: 0 | L34: =J34 -> 111.66667 | M34: 0 | N34: 0 | O34: =N34+M34-K34 -> 0 | P34: NM | Q34: Awaiting CFIUS clearance
C35: Neuralink | D35: Unrealized | F35: G42 Capital | G35: 2025 | H35: Series E | I35: ='B. %'!F34 -> 0.0051805228 | J35: =K35 -> 50 | K35: =-SUMIF('CF (Equity, Debt)'!$C$3:$K$61,'A. All deals (a)'!C35,'CF (Equity, Debt)'!$E$3:$E$61) -> 50 | L35: 0 | M35: 0 | N35: 50 | O35: =N35+M35-K35 -> 5e-07 | P35: =(M35+N35)/K35 -> 1
J36: =SUM(J9:J35) -> 2500.0496 | K36: =SUM(K9:K35) -> 2341.5329 | L36: =SUM(L9:L35) -> 158.51663 | M36: =SUM(M9:M35) -> 1428.5466 | N36: =SUM(N9:N35) -> 878.23664 | O36: =SUM(O9:O35) -> -34.749646 | P36: =(M36+N36)/K36 -> 0.98515945
C38: Debt Investments
C39: Glass Earth Holdings LLC | D39: Written-off | F39: Mozn | G39: 2019 | H39: Promissory Note | I39: n/a | J39: 8 | K39: 8 | L39: 0 | M39: 0 | N39: 0 | O39: =N39+M39-K39 -> -8 | P39: =(M39+N39)/K39 -> 0 | Q39: In Default
C40: Mena Mobile Inc (Debt) | D40: Written-off | F40: Mozn | G40: 2021 | H40: Loan | I40: n/a | J40: 2.353982 | K40: =J40 -> 2.353982 | L40: 0 | M40: 0 | N40: =VLOOKUP(C40,NAV!$B$4:$E$47,4,0) -> 0 | O40: =N40+M40-K40 -> -2.353982 | P40: =(M40+N40)/K40 -> 0 | Q40: In Liquidation
C41: Esyasoft Holding (Debt) | D41: Realized | F41: Mozn | G41: 2021 | H41: Loan | I41: n/a | J41: 0.411765 | K41: 0.411765 | L41: 0 | M41: ='CF (Equity, Debt)'!F66 -> 0.47078465 | N41: 0 | O41: =N41+M41-K41 -> 0.05901965 | P41: =(M41+N41)/K41 -> 1.1433333
J42: =SUM(J39:J41) -> 10.765747 | K42: =SUM(K39:K41) -> 10.765747 | L42: =SUM(L39:L41) -> 0 | M42: =SUM(M39:M41) -> 0.47078465 | N42: =SUM(N39:N41) -> 0 | O42: =N42+M42-K42 -> -10.294962 | P42: =(M42+N42)/K42 -> 0.043729864
C44: Funds Investments
C45: New Space Capital Fund I | D45: Unrealized | F45: G42 Investments | G45: 2020 | H45: LP | I45: n/a | J45: =K45+L45 -> 29.659861 | K45: =-SUMIF('CF (Funds)'!$C$4:$E$55,C45,'CF (Funds)'!$E$4:$E$55) -> 19.108545 | L45: ='8. NewSpace'!L36*10^-6*NAV!L23 -> 10.551316 | M45: =SUM('CF (Funds)'!F39:F54) -> 3.7927063 | N45: =VLOOKUP(C45,NAV!$B$4:$E$47,4,0) -> 25.615387 | O45: =N45+M45-K45 -> 10.299548 | P45: =(M45+N45)/K45 -> 1.5390022
C46: New Space Capital GP Com SCSp | D46: Unrealized | F46: G42 Investments | G46: 2023 | H46: LP | I46: n/a | J46: =2.3/0.85 -> 2.7058824 | K46: 2.7058824 | L46: 0 | M46: 0 | N46: =VLOOKUP(C46,NAV!$B$4:$E$47,4,0) -> 3.6272895 | O46: =N46+M46-K46 -> 0.9214071 | P46: =(M46+N46)/K46 -> 1.34052
C47: North Summit Capital Fund | D47: Unrealized | F47: G42 Investments | G47: 2020 | H47: LP | I47: n/a | J47: =K47+L47 -> 83.361611 | K47: 83.361611 | L47: 0 | M47: 7.875571 | N47: =NAV!E45 -> 64.228074 | O47: =N47+M47-K47 -> -11.257966 | P47: =(M47+N47)/K47 -> 0.86495023
C48: Sinovation Disrupt Fund, L.P. | D48: Realized | F48: G42 Investments | G48: 2020 | H48: LP | I48: n/a | J48: 50 | K48: =-SUMIF('CF (Funds)'!$C$4:$E$2017,C48,'CF (Funds)'!$E$4:$E$2017) -> 24.959693 | L48: 0 | M48: =SUM('CF (Funds)'!F4:F21) -> 25.403521 | N48: =VLOOKUP(C48,NAV!$B$4:$E$47,4,0) -> 0 | O48: =N48+M48-K48 -> 0.44382835 | P48: =(M48+N48)/K48 -> 1.0177818
C49: Acies Investments Fund I, L.P. | D49: Unrealized | F49: G42 Investments | G49: 2021 | H49: LP | I49: 0.33 | J49: 17.1125 | K49: =-SUMIF('CF (Funds)'!$C$4:$E$2017,C49,'CF (Funds)'!$E$4:$E$2017) -> 15.726387 | L49: =J49-K49 -> 1.3861125 | M49: 0 | N49: =VLOOKUP(C49,NAV!$B$4:$E$47,4,0) -> 13.056308 | O49: =N49+M49-K49 -> -2.6700795 | P49: =(M49+N49)/K49 -> 0.8302166 | Q49: 9.9% GP | Anchorf
J50: =SUM(J45:J49) -> 182.83985 | K50: =SUM(K45:K49) -> 145.86212 | L50: =SUM(L45:L49) -> 11.937429 | M50: =SUM(M45:M49) -> 37.071799 | N50: =SUM(N45:N49) -> 106.52706 | O50: =N50+M50-K50 -> -2.2632617 | P50: =(M50+N50)/K50 -> 0.98448355
C52: MGX & Related Investments
C53: MGX I LP | D53: Unrealized | F53: G42 Holding | G53: 2024 | H53: LP | I53: ='B. %'!F43 -> 0.03125 | J53: 1200 | K53: =MGX!C34 -> 210.22875 | L53: =J53-K53 -> 989.77125 | M53: 0 | N53: =NAV!E49 -> 326.2094 | O53: =N53-K53 -> 115.98065 | P53: =(M53+N53)/K53 -> 1.5516879
C54: MGX 1 Strategic Co-invest | D54: Unrealized | F54: G42 Holding | G54: 2024 | H54: LP | I54: 0.5 | J54: 775 | K54: =SUM('CF (Funds)'!E90:E95) -> 312.49956 | L54: =J54-K54 -> 462.50044 | M54: 0 | N54: =NAV!E50 -> 396.0636 | O54: =N54-K54 -> 83.564042 | P54: =(M54+N54)/K54 -> 1.2674053
C55: MGX Group Holding 1 Ltd (GP) | D55: Unrealized | F55: G42 Holding | G55: 2024 | H55: Equity | J55: 25 | K55: 25 | L55: =J55-K55 -> 0 | M55: 0 | N55: =K55 -> 25 | O55: =N55-K55 -> 0 | P55: =(M55+N55)/K55 -> 1
J56: =SUM(J53:J55) -> 2000 | K56: =SUM(K53:K55) -> 547.72831 | L56: =SUM(L53:L55) -> 1452.2717 | M56: =SUM(M53:M55) -> 0 | N56: =SUM(N53:N55) -> 747.273 | O56: =SUM(O53:O55) -> 199.5447 | P56: =(M56+N56)/K56 -> 1.3643133
C58: Total | J58: =J36+J42+J50+J56 -> 4693.6552 | K58: =K36+K42+K50+K56 -> 3045.8891 | L58: =L36+L42+L50+L56 -> 1622.7258 | M58: =M36+M42+M50+M56 -> 1466.0892 | N58: =N36+N42+N50+N56 -> 1732.0367 | O58: =O36+O42+O50+O56 -> 152.23683 | P58: =(M58+N58)/K58 -> 1.0499811
C61: Additional Upside Section:
C62: a) Flyr: For every $1m of revenue, 194,477 shares, capped at 1,264,1000 (B-1) shares shall be issued to Mozn
C63: b) DriveNets: Share warrants exercisable upon the achievement of target revenue of clients referred by G42, and corresponding milestones
C64: c) vTv Therapeutics: Potential issuance of $30m in additional shares, if FDA approval received for the drug TTP399
C65: d) Tools for Humanity Corporation: An additional 62.5 million Tokens (WLD tokens) received for a consideration of $6,875.00.
C66: e) E-line Ventures LLC: Option to further acquire Series B Pref shares at max($1.34, EV/No of shares)
C67: f) Acies Investments Fund I LP: Being the Anchor investor, entitled to 9.9% of the aggregate carried interest earned by the GP
C68: g) Cloud Credit of 250K counted towards the investment cost
C69: h) Inveniam: 60% upside if Tokens sold $2.5+, Anti Dilution protection
C70: IRR is referred as NM when it is not meaningful
C72: Definitions:
C73: ἀ = Vintage corresponds to the year of the first investment made
... C91: TBC = to be confirmed

Sheet 9. All deals (b)
C2: As of date | D2: ='A. All deals (a)'!D2 -> 45900
P3: n/a refers to information not available
C6: Deals | D6: Status | E6: Lead | F6: Investing Entity | G6: Investing Entity (Legal Entity Name) | H6: Nature of Investing Entity | I6: Investments Tax Implication tax note 1 | J6: Instrument | K6: Listed / Unlisted | L6: Website link | M6: Pitchbook link | N6: Jurisdiction | O6: % | P6: Upside (Warrants, Milestone payments, ) | Q6: For Comments Refer to Note
C8: Direct Investments
C9: Jollychic Holding Limited | D9: Written-off | E9: Elaine | F9: Mozn | G9: Mozn Holding RSC Ltd | H9: Potential QFZP tax note 2 | I9: If qualifies for QFZP and hold the investment >= 12m, income/loss from the investee supposed to suject to 0% Corporate tax rate for Investing Entity | J9: C+ Prefs | L9: link | M9: link | N9: Cayman Islands | O9: 0.056999998 | Q9: 1
C10: Mena Mobile Inc | D10: Unrealized | E10: Elaine | F10: Mozn | G10: Mozn Holding RSC Ltd | H10: Potential QFZP tax note 2 | I10: If qualifies for QFZP and hold the investment >= 12m, income/loss from the investee supposed to suject to 0% Corporate tax rate for Investing Entity | J10: B Prefs | L10: link | M10: link | N10: Cayman Islands | O10: 0.14 | Q10: 2
C11: Flyr Inc | D11: Unrealized | E11: Sushil | F11: Mozn | G11: Mozn Holding RSC Ltd | H11: Potential QFZP tax note 2 | I11: If qualifies for QFZP and hold the investment >= 12m, income/loss from the investee supposed to suject to 0% Corporate tax rate for Investing Entity | J11: B-1,2 Prefs | L11: link | M11: link | N11: Delaware Corporation | O11: 0.085025485 | P11: Flyr Warrantsa | Q11: 3
C12: Esyasoft Holding | D12: Realized | E12: Sushil | F12: Mozn | G12: Mozn Holding RSC Ltd | H12: Potential QFZP tax note 2 | I12: If qualifies for QFZP and hold the investment >= 12m, income/loss from the investee supposed to suject to 0% Corporate tax rate for Investing Entity | J12: Convertible Note | L12: link | M12: n/a | N12: DIFC | O12: n/a | Q12: 4
C13: Beyond Limits | D13: Unrealized | E13: Divyesh | F13: Mozn | G13: Mozn Holding RSC Ltd | H13: Potential QFZP tax note 2 | I13: If qualifies for QFZP and hold the investment >= 12m, income/loss from the investee supposed to suject to 0% Corporate tax rate for Investing Entity | J13: C Prefs | L13: link | M13: link | N13: Delaware Corporation | O13: 0.097965107 | Q13: 5
C14: ONT plc | D14: Unrealized | E14: Divyesh | F14: Mozn | G14: Mozn Holding RSC Ltd | H14: Potential QFZP tax note 2 | I14: If qualifies for QFZP and hold the investment >= 12m, income/loss from the investee supposed to suject to 0% Corporate tax rate for Investing Entity | J14: Ordinary Shares | K14: Listed | L14: link | M14: link | N14: UK | O14: 0.051651565 | Q14: 6
C15: Heygears | D15: Unrealized | E15: Elaine | F15: Mozn | G15: Mozn Holding RSC Ltd | H15: Potential QFZP tax note 2 | I15: If qualifies for QFZP and hold the investment >= 12m, income/loss from the investee supposed to suject to 0% Corporate tax rate for Investing Entity | J15: Registered Capital | L15: link | M15: link | N15: PRC | O15: 0.1438 | Q15: 7
C16: Jysan Technologies | D16: Realized | E16: Sushil | F16: Mozn aa | G16: QAZ42 Investment SPV RSC Ltd | H16: Realized | I16: Realized | J16: A (Ordinary Shares) | L16: link | M16: n/a | N16: UK | O16: 0.03 | Q16: 8
C17: Cerebras Systems Inc | D17: Unrealized | E17: Ignasi | F17: Mozn | G17: Mozn Holding RSC Ltd | H17: Potential QFZP tax note 2 | I17: If qualifies for QFZP and hold the investment >= 12m, income/loss from the investee supposed to suject to 0% Corporate tax rate for Investing Entity | J17: F Prefs | L17: link | M17: link | N17: Delaware Corporation | O17: 0.0091172068 | Q17: 9
C18: Endless Studios LLC | D18: Unrealized | E18: Sushil | F18: Mozn | G18: Mozn Holding RSC Ltd | H18: Potential QFZP tax note 2 | I18: To be monitored (see Note 0) | J18: A Pref Units | L18: link | M18: link | N18: Delaware Corporation | O18: 0.16080402 | Q18: 10
C19: Instadeep Limited | D19: Realized | E19: Ignasi | F19: Mozn | G19: Mozn Holding RSC Ltd | H19: Potential QFZP tax note 2 | I19: If qualifies for QFZP and hold the investment >= 12m, income/loss from the investee supposed to suject to 0% Corporate tax rate for Investing Entity | J19: B Prefs | L19: link | M19: link | N19: UK | O19: 0.011489406 | Q19: 11
C20: X-fusion | D20: Realized | E20: Elaine | F20: Mozn bb | G20: Enterprise Connection Holding RSC Ltd | H20: Non-QFZP | I20: pending | J20: Equity-TBC | L20: link | M20: link | N20: PRC | O20: 0.051 | Q20: 12
C21: DriveNets | D21: Unrealized | E21: Anton | F21: G42 | G21: D2 Investments RSC Ltd | H21: Non-QFZP | I21: Should qualify for Participation interest | J21: Equity-TBC | L21: link | M21: link | N21: Israeli Pvt Company | O21: 0.11141914 | P21: DN Warrants b | Q21: 13
C22: vTv Therapeutics Inc. | D22: Unrealized | E22: Divyesh | F22: G42 | G22: G42 Investments AI Holdings RSC Ltd | H22: Potential QFZP tax note 2 | I22: To be monitored (see Note 0) | J22: Ordinary Shares | K22: Listed | L22: link | M22: link | N22: Delaware Corporation | O22: 0.0022129091 | P22: vTv $30m milestn payment c | Q22: 14
C23: Honor Device Co Ltd | D23: Realized | E23: Elaine | F23: G42 cc | G23: Smart Interaction1 Holding SPV RSC LTD | H23: pending | I23: pending | J23: Equity-TBC | L23: link | M23: link | N23: PRC | O23: 0.018823528 | Q23: 15
C24: Applied AI Corporation Limited | D24: Unrealized | E24: Divyesh | F24: Mozn | G24: Mozn Holding RSC Ltd | H24: Potential QFZP tax note 2 | I24: To be monitored (see Note 0) | J24: Convertible Note | L24: link | M24: link | N24: ADGM | O24: n/a | Q24: 16
C25: eSpace | D25: Unrealized | E25: Anton | F25: Mozn dd | G25: Constellation Investments SPV RSC Ltd (previously Smart Interaction5 Holding SPV RSC Ltd) | H25: Non-QFZP | I25: Taxable for only hold 2.8% of SAFE note in eSpace. | J25: B Prefs | L25: link | M25: link | N25: Delaware Corporation | O25: 0.027864956 | Q25: 17
C26: Tools for Humanity Corporation | D26: Unrealized | E26: Divyesh | F26: Mozn | G26: Mozn Holding RSC Ltd | H26: Potential QFZP tax note 2 | I26: To be monitored (see Note 0) | J26: C Prefs | L26: link | M26: link | N26: Delaware Corporation | O26: 0.0062621983 | Q26: 24
C27: WLD Tokens | D27: Unrealized | E27: Divyesh | F27: Mozn | G27: Mozn Holding RSC Ltd | H27: Potential QFZP tax note 2 | I27: To be monitored (see Note 0) | J27: Tokens | L27: link | M27: Coinbase | N27: DAO | Cayman Islands | O27: 0.00625 | Q27: 25 | T27: Preferred Shares
C28: E-line Ventures LLC | D28: Unrealized | E28: Sushil | F28: Mozn | G28: Mozn Holding RSC Ltd | H28: Potential QFZP tax note 2 | I28: To be monitored (see Note 0) | J28: B Prefs | L28: link | M28: link | N28: New Jersey, USA | O28: ='B. %'!F28 -> 0.11483736 | Q28: 26 | T28: B Prefs
C29: School Hack (AIREV Holding Limited) | D29: Unrealized | E29: Camillo | F29: Core42 | G29: Core42 Investments 1 SPV RSC LTD | H29: Potential QFZP tax note 2 | I29: To be monitored (see Note 0) | J29: Preferred Shares | L29: link | M29: NA | N29: ADGM | O29: 0.25 | Q29: 27
C30: Life Biosciences LLC | D30: Unrealized | E30: Divyesh | F30: ='A. All deals (a)'!F30 -> G42 Capital | G30: Expansion Project Technologies Holding 7 SPV RSC Ltd | H30: Potential QFZP tax note 2 | I30: To be monitored (see Note 0) | J30: Convertible Note | L30: link | M30: link | N30: Delaware Corporation | O30: n/a | Q30: 28
C31: Verses AI Inc | D31: Unrealized | E31: Divyesh | F31: ='A. All deals (a)'!F31 -> G42 Capital | G31: Expansion Project Technologies Holding 9 SPV RSC Ltd | H31: Potential QFZP tax note 2 | I31: To be monitored (see Note 0) | J31: Convertible Debenture | L31: link | M31: link | N31: British Columbia | O31: n/a
C32: Inveniam | D32: Unrealized | E32: Divyesh | F32: ='A. All deals (a)'!F35 -> G42 Capital | G32: Expansion Project Technologies Holding 10 SPV RSC Ltd | H32: Potential QFZP tax note 2 | I32: To be monitored (see Note 0) | J32: SAR | L32: llink | M32: link | N32: Gibraltor | O32: 20% equivalent
C36: Debt Investments
C37: Glass Earth Holdings LLC | D37: In default | F37: Mozn | G37: G42 Investments AI Holdings RSC Ltd | H37: Potential QFZP tax note 2 | I37: not equity investment, taxable | J37: Promissory Note | L37: n/a | M37: n/a | N37: n/a | Q37: 16
C38: Mena Mobile Inc (Debt) | D38: In default | E38: Elaine | F38: Mozn | G38: Mozn Holding RSC Ltd | H38: Potential QFZP tax note 2 | I38: not equity investment, taxable | J38: Loan | L38: link | M38: link | N38: =N10 -> Cayman Islands | Q38: 17
C39: Esyasoft Holding (Debt) | D39: Unrealized | E39: Sushil | F39: Mozn | G39: Mozn Holding RSC Ltd | H39: Potential QFZP tax note 2 | I39: not equity investment, taxable | J39: Loan | L39: link | M39: n/a | N39: =N12 -> DIFC | Q39: 18
C42: Funds Investments
C43: New Space Capital Fund I | D43: Unrealized | E43: Sushil | F43: G42 | G43: G42 Investments AI Holdings RSC Ltd | H43: Potential QFZP tax note 2 | I43: If qualifies for QFZP and hold the investment >= 12m, income/loss from the investee supposed to suject to 0% Corporate tax rate for Investing Entity | J43: LP | L43: link | M43: link | N43: Luxembourg | O43: 0.22044082 | Q43: 19
C44: New Space Capital GP Com SCSp | D44: Unrealized | E44: Sushil | F44: G42 | G44: G42 Investments AI Holdings RSC Ltd | H44: Potential QFZP tax note 2 | I44: If qualifies for QFZP and hold the investment >= 12m, income/loss from the investee supposed to suject to 0% Corporate tax rate for Investing Entity | J44: GP | L44: link | M44: link | N44: Luxembourg | O44: 0.02016129 | Q44: 20
C45: North Summit Capital Fund | D45: Unrealized | E45: Elaine | F45: G42 | G45: Galbot Holding RSC Ltd | H45: Non-QFZP | I45: pending | J45: LP | L45: n/a | M45: link | N45: Cayman Islands | O45: 0.995 | Q45: 21
C46: Sinovation Disrupt Fund, L.P. | D46: Unrealized | E46: Elaine | F46: G42 | G46: G42 Investments AI Holdings RSC Ltd | H46: Potential QFZP tax note 2 | I46: If qualifies for QFZP and hold the investment >= 12m, income/loss from the investee supposed to suject to 0% Corporate tax rate for Investing Entity | J46: LP | L46: link | M46: link | N46: Cayman Islands | O46: 0.1006609 | Q46: 22
C47: Acies Investments Fund I, L.P. | D47: Unrealized | E47: Divyesh | F47: G42 | G47: G42 Investments AI Holdings RSC Ltd | H47: Potential QFZP tax note 2 | I47: If qualifies for QFZP and hold the investment >= 12m, income/loss from the investee supposed to suject to 0% Corporate tax rate for Investing Entity | J47: LP | L47: link | M47: link | N47: Delaware LLC | O47: 0.33333333 | P47: 9.9% GP | Anchor e | Q47: 23
B51: Notes:
B52: 0 | C52: General | D52: If qualifies for QFZP and hold the investment >= 12m, income/loss from the investee supposed to suject to 0% Corporate tax rate for Investing Entity. Currently we have the contribution made in June 2023 need to be monitored
B53: 1 | C53: Jollychic | D53: During 2021, Jollychic Holding Ltd has filed for its liquidation. Therefore, investment is considered to be fully impaired in Dec 21.
B54: 2 | C54: Mena Mobile | D54: Investment is written off based on the 3rd party valuation report
B55: 3 | C55: Flyr | D55: Within five years of the Initial Closing, for every USD 1mn of Qualifying Revenue generated, Flyr will issue, at no additional charge, 194,477 B-1 Prefs in the name of G42, up to a maximum of 1,264,100 B-1 Prefs.
B56: 4 | C56: Esyasoft Holding | D56: Exited
B57: 5 | C57: Beyond Limits | D57: Business targeting raising funds by the end of FY2022
B58: 6 | C58: ONT plc | D58: Listed
B59: 7 | C59: Heygears | D59: Mozn's holding is RMB 4,753,356.29 of the Registered Capital.
B60: 8 | C60: Jysan Technologies | D60: - 50% of the investment has been financed by profit sharing loan. - Further, in case of exit of G42’s investment, 50% of the sale proceeds shall be paid to the lender as full and final settlement of the outstanding liability - Exit for this investment is under process. Buyback agreement is pending for signature internally. (Relevant documents to be perused by the consolidation / reporting team for details and corresponding implications, if any) - Dividend receivable amounting to US$ 3.2 m will be waived upon exit of this investment
B61: 9 | C61: Cerebras Systems Inc | D61: The investment is currently undergoing a CFIUS review.
B62: 10 | C62: Endless Studios LLC
B63: 11 | C63: Instadeep Limited | D63: Fully Exited on 31st July with 1.5x returns.
B64: 12 | C64: X-fusion | D64: RMB 80 Mn of Registered Capital for RMB 5.7 Bn
B65: 13 | C65: Drivenets | D65: Share warrants excisable upon the achievement of target revenue of clients by referred G42. The milestones of each target revenue and respective conversion were stated in the Term Sheet.
B66: 14 | C66: vTv Therapeutics : | D66: Potential issuance of US$ 30 million in additional shares of Class A Common Stock to G42 Investments (or in cash, at the option of G42 Investments) if FDA approval is received for the marketing and the sale of a pharmaceutical product containing TTP399
B67: 15 | C67: Honor | D67: Invested in Q3 2022; During Dec 22, $250m was offloaded to another investor at cost
B68: 16 | C68: Glass Earth Holdings LLC | D68: Written off. Debt security of Glass Earth issued in 2019 were fully provided for.
B69: 17 | C69: Mena Mobile (Debt) | D69: In liquidation
B70: 18 | C70: Esyasoft Holding (Debt) | D70: Outstanding
B71: 19 | C71: New Space Capital Fund I | D71: G42 negotiated conversion of €2.3m GP investment into LP investment to vote in favor of new LP proposal.
B72: 20 | C72: New Space Capital SCSp | D72: Ibid
B73: 21 | C73: North Summit Capital | D73: Portfolio Exit Plan in Progress
B74: 22 | C74: Sinovation Disrupt Fund | D74: Expect valuation to rise as some of its portfolio companies are in the market to raise new funds
B75: 23 | C75: Acies Investments Fund I, LP
B76: 24 | C76: Tools for Humanity Corporation | D76: Additional token warrants (for 62.5 million Tokens) for a consideration of $5,875.00. Additional provision for c$2K (the warrant price) kept for exercising the warrant rights.
B77: 25 | C77: WLD Tokens | D77: Received 62.5M Tokens as of Jul'23
B78: 26 | C78: E-line Ventures LLC
B79: 27 | C79: School Hack (AIREV Holding Limited) | D79: Invested via Core42
B80: 28 | C80: Life Biosciences LLC | D80: Invested via G42 Capital
C82: Additional Upside Section:
C83: a) Flyr: For every $1m of revenue, 194,477 shares, capped at 1,264,1000 (B-1) shares shall be issued to Mozn
C84: b) DriveNets: Share warrants exercisable upon the achievement of target revenue of clients referred by G42, and corresponding milestones
C85: c) vTv Therapeutics: Potential issuance of $30m in additional shares, if FDA approval received for the drug TTP399
C86: d) Tools for Humanity Corporation: Additional token warrants issued for acquiring 62.5M Tokens for $5,875.00. Additional provision for c$2K (the warrant price) kept for exercising the warrant rights
C87: e) Acies Investments Fund I LP: Being the Anchor investor, entitled to 9.9% of the aggregate carried interest earned by the GP
C89: References:
C90: G42 refers to G42 Investments AI Holding RSC Ltd
C91: Mozn refers to Mozn Holding RSC Ltd
C92: PRC refers to People's Republic of China
C93: aa Invested via QAZ42 Investment SPV RSC Ltd (QAZ42)
C94: bb Invested via Enterprise Connection Holding RSC Ltd (Enterprise Connection)
... C101: 2 Group is currently working on the process to make Mozn Holding RSC Ltd and G42 Investments AI Holdings RSC Ltd be qualified to the QFZP requirements.

Sheet 8. WLD Grant C-133
A1: Investor Unlock Chart
A3: Investor | B3: MOZN Holding RSC Ltd
A4: Grant # | B4: C-133
A5: Investor Group | B5: MOZN Holding RSC Ltd
D7: Date | E7: Day Of Week | F7: Cumulative Tokens Unlocked | G7: Daily Tokens Unlocked | H7: Weekly Tokens Distributed | I7: Biweekly Tokens Unlocked
A8: Input (Investor-Specific) | D8: 45497 | E8: Wednesday | F8: 46205.92 | G8: 46205.92 | H8: 46205.92 | I8: 0
A9: Token Grant Amount (WLD) | B9: 62500000 | D9: 45498 | E9: Thursday | F9: 92411.84 | G9: 46205.92 | H9: 0 | I9: 0
A10: Unlock Start Date | B10: 45131 | D10: 45499 | E10: Friday | F10: 138617.76 | G10: 46205.92 | H10: 0 | I10: 0
A11: Total Investor Group Tokens | B11: 62500000 | D11: 45500 | E11: Saturday | F11: 184823.68 | G11: 46205.92 | H11: 0 | I11: 0
A12: Percent of this Grant | B12: 1 | D12: 45501 | E12: Sunday | F12: 231029.6 | G12: 46205.92 | H12: 0 | I12: 0
A13: Custody Provider | B13: Bitgo (Unconfirmed) | D13: 45502 | E13: Monday | F13: 277235.52 | G13: 46205.92 | H13: 0 | I13: 0
A14: Unlock Cadence | B14: Daily | D14: 45503 | E14: Tuesday | F14: 323441.44 | G14: 46205.92 | H14: 0 | I14: 0
D15: 45504 | E15: Wednesday | F15: 369647.36 | G15: 46205.92 | H15: 323441.44 | I15: 369647.36
D16: 45505 | E16: Thursday | F16: 415853.28 | G16: 46205.92 | H16: 0 | I16: 0
A17: Calculation (Intermediate) | D17: 45506 | E17: Friday | F17: 462059.2 | G17: 46205.92 | H17: 0 | I17: 0
A18: Day in Linear unlock period (Fast) | B18: 730 | D18: 45507 | E18: Saturday | F18: 508265.12 | G18: 46205.92 | H18: 0 | I18: 0
A19: Days in Linear unlock period (Slow) | B19: 1461 | D19: 45508 | E19: Sunday | F19: 554471.04 | G19: 46205.92 | H19: 0 | I19: 0
A20: Unlocking | B20: Fast + Slow | D20: 45509 | E20: Monday | F20: 600676.96 | G20: 46205.92 | H20: 0 | I20: 0
A21: Day of Week Disbursement | B21: Wednesday | D21: 45510 | E21: Tuesday | F21: 646882.88 | G21: 46205.92 | H21: 0 | I21: 0
D22: 45511 | E22: Wednesday | F22: 693088.8 | G22: 46205.92 | H22: 323441.44 | I22: 0
D23: 45512 | E23: Thursday | F23: 739294.72 | G23: 46205.92 | H23: 0 | I23: 0
D24: 45513 | E24: Friday | F24: 785500.64 | G24: 46205.92 | H24: 0 | I24: 0
D25: 45514 | E25: Saturday | F25: 831706.56 | G25: 46205.92 | H25: 0 | I25: 0
D26: 45515 | E26: Sunday | F26: 877912.48 | G26: 46205.92 | H26: 0 | I26: 0
D27: 45516 | E27: Monday | F27: 924118.4 | G27: 46205.92 | H27: 0 | I27: 0
D28: 45517 | E28: Tuesday | F28: 970324.32 | G28: 46205.92 | H28: 0 | I28: 0
D29: 45518 | E29: Wednesday | F29: 1016530.2 | G29: 46205.92 | H29: 323441.44 | I29: 646882.88
D30: 45519 | E30: Thursday | F30: 1062736.2 | G30: 46205.92 | H30: 0 | I30: 0
D31: 45520 | E31: Friday | F31: 1108942.1 | G31: 46205.92 | H31: 0 | I31: 0
D32: 45521 | E32: Saturday | F32: 1155148 | G32: 46205.92 | H32: 0 | I32: 0
D33: 45522 | E33: Sunday | F33: 1201353.9 | G33: 46205.92 | H33: 0 | I33: 0
... D1834: 47323 | E1834: Tuesday | F1834: 62500000 | G1834: 0 | H1834: 0 | I1834: 0

Sheet 8. NewSpace
B2: New Space Capital Capital Calls | C2: 44442 | E2: 44623 | F2: 44784 | G2: 44956
X3: Figures in USD, Mn
T4: Drawdown 14
B5: EUR | C5: Drawdown 3 | D5: Drawdown 4 | E5: Drawdown 5 | G5: Drawdown 8 | H5: Drawdown 9 | I5: Drawdown 10 | J5: Drawdown 11 | K5: Drawdown 12 | L5: Drawdown 13 | M5: Drawdown 14 | N5: Drawdown 15 | O5: Drawdown 16 | P5: Drawdown 17 | Q5: Drawdown 18 | R5: Drawdown 19 | S5: Drawdown 20 | T5: Distribution 2 | X5: Deals | Y5: New Space Capital Fund I | Z5: NewSpace Capital GP Com SCSp
B6: Date | C6: 44442 | D6: 44512 | E6: 44623 | G6: 44950 | H6: 45007 | I6: 45170 | J6: 45260 | K6: 45306 | L6: 45356 | M6: 45429 | N6: 45491 | O6: 45590 | P6: 45670 | Q6: 45721 | R6: 45821 | S6: 45874 | T6: 45454 | X6: Status | Y6: Unrealized | Z6: Unrealized
B7: Total Commitment | C7: 19015957 | D7: 23513942 | E7: 23513942 | G7: 23234462 | H7: 23234462 | I7: 23234462 | J7: 23234462 | K7: 23234462 | L7: 23234462 | M7: 23234462 | N7: 23234462 | O7: 23234462 | P7: 23234462 | Q7: 23234462 | R7: 23234462 | S7: =R7 -> 23234462 | T7: 23234462 | X7: Investing Entity | Y7: G42 | Z7: G42
B8: Contributions (prior to this notice): | C8: 19226989 | D8: 19415305 | E8: 19365158 | I8: 9566817.3 | J8: =I8+I18 -> 9834193.4 | K8: =J8+J18 -> 10093474 | L8: =K8+K18 -> 12297371 | M8: =L8+L18 -> 12498073 | N8: 12128944 | O8: 13706993 | P8: 15511986 | Q8: 13493186 | R8: =L35 -> 14203894 | S8: 16528522 | T8: =T7-T9 -> 12498073 | X8: Vintageἀ | Y8: 2020 | Z8: 2020
B9: Remaining Commitment (prior to notice) | D9: 4098636.9 | E9: 4148784.1 | G9: 15865093 | H9: 15675627 | I9: =I7-I8 -> 13667645 | J9: =J7-J8 -> 13400268 | K9: =K7-K8 -> 13140988 | L9: =L7-L8 -> 10937091 | M9: =M7-M8 -> 10736389 | N9: =N7-N8 -> 11105518 | O9: =O7-O8 -> 9527469.1 | P9: =P7-P8 -> 7722475.5 | ... S9: =S7-S8 -> 6705940.3 | T9: =L22 -> 10736389 | X9: Instrument | Y9: LP | Z9: LP
B10: Distribution of Actualisation Interest (Distribution 1/Drawdown 8)*: | G10: -12659067 | X10: % | Y10: n/a | Z10: n/a
B11: Return of Capital | H11: -2067567 | X11: Committed | Y11: 27.691913 | Z11: 2.7058824
B12: Remaining Commitment: | H12: 13608060 | X12: Invested | Y12: 11.058035 | Z12: 2.7058824
X13: Remaining Commitment | Y13: 16.633878 | Z13: 0
X14: Distributions | Y14: 2.9557744 | Z14: 0
B15: Equalization -Actualization of Investments | S15: -4288037.9 | T15: -358796.4 | X15: Carrying Value | Y15: =NAV!E43 -> 25.615387 | Z15: =Z12*Y15/Y12 -> 6.2680418
B16: Equalization -Actualization of Fund Expenses | S16: -102599.82 | T16: -10332.76 | X16: Gain | Y16: =Y15+Y14-Y12 -> 17.513127 | Z16: =Z15+Z14-Z12 -> 3.5621595
B17: Equalization -Actualization of Interest - Investments & Fund Expenses | O17: -56063.44 | P17: -345590.9 | S17: -781260.09 | T17: -62495.83 | X17: Multiple | Y17: =(Y14+Y15)/Y12 -> 2.5837468 | Z17: =(Z14+Z15)/Z12 -> 2.3164502
B18: Contribution | G18: =G9-G22 -> 189466.02 | H18: =H12-H22 -> -59584.38 | I18: 267376.08 | J18: 259280.73 | K18: 2203896.7 | L18: 200702.46 | N18: 1578048.7 | O18: 1748930.2 | Q18: 710707.2 | R18: 2324628.2 | S18: =-51671.6+6200.89+1665803.07+186376.92+65365.1 -> 1872074.4
B19: Distribution | G19: =-G20+G18 -> 12659067 | H19: =-H20+H18 -> 1.0404619e-09 | I19: 59584.38 | X19: Note
B20: NET Amount Contributed / Distributed to us | C20: 203097.23 | D20: -444437.06 | E20: 233275.54 | G20: -12469601 | H20: -59584.38 | I20: =I18-I19 -> 207791.7 | J20: =J18-J19 -> 259280.73 | K20: =K18-K19 -> 2203896.7 | L20: =L18-L19 -> 200702.46 | N20: =N18-N19 -> 1578048.7 | O20: =O18-O19 -> 1748930.2 | P20: -2364391.1 | S20: -3299823.5 | T20: =SUM(T15:T17) -> -431624.99 | X20: 1. In Q1'23 we converted GP interest equivalent to the LP via the GP commitment vehicle
X21: 2. In addition, G42 also has XX units in the GP, which presently are being carried at nil value
B22: Remaining Commitment (after this notice): | C22: 0 | D22: 4163565.3 | E22: 3915508.6 | G22: 15675627 | H22: 13667645 | I22: 13400268 | J22: =J9-J20 -> 13140988 | K22: =K9-K20 -> 10937091 | L22: =L9-L20 -> 10736389 | M22: =T22 -> 11105518 | N22: =N9-N20 -> 9527469.1 | O22: =O9+O17-O20 -> 7722475.5 | P22: =P9+P17-P20 -> 9741275.6 | Q22: =P22-Q18 -> 9030568.4 | R22: =Q22-R18 -> 6705940.3 | S22: 9224503.6 | T22: =T9-T15-T16 -> 11105518
B23: Remaining Commitment (as a % of Capital Commitments): | C23: 0 | D23: 0.1771 | E23: 0.1665 | G23: 0.6747 | H23: 0.5882 | I23: 0.5767 | J23: 0.5656 | K23: 0.4707 | L23: 0.4621 | M23: 0.478 | N23: 0.4101 | O23: 0.3324 | P23: 0.4193 | Q23: 0.3887 | R23: 0.2886 | S23: 0.397 | T23: 0.478
B24: CHECKS | D24: =ROUND(D22/D7,4)=D23 -> TRUE | E24: =ROUND(E22/E7,4)=E23 -> TRUE | G24: =ROUND(G22/G7,4)=G23 -> TRUE | H24: =ROUND(H22/H7,4)=H23 -> TRUE | I24: =ROUND(I22/I7,4)=I23 -> TRUE | J24: =ROUND(J22/J7,4)=J23 -> TRUE | K24: =ROUND(K22/K7,4)=K23 -> TRUE | L24: =ROUND(L22/L7,4)=L23 -> TRUE | M24: =ROUND(M22/M7,4)=M23 -> TRUE | N24: =ROUND(N22/N7,4)=N23 -> TRUE | ... T24: =ROUND(T22/T7,4)=T23 -> TRUE
B25: EURUSD | G25: 1.0872 | H25: 1.0773 | I25: 1.08439 | J25: 1.1004 | K25: 1.09506 | L25: 1.07869 | M25: 1.07869 | N25: 1.07869 | O25: 1.07205 | T25: 1.0743
G26: =-G25*G20/1000000 -> 13.55695 | H26: =-H25*H20/1000000 -> 0.064190253 | I26: =-I25*I20/1000000 -> -0.22532724 | J26: =-J25*J20/1000000 -> -0.28531252 | K26: =-K25*K20/1000000 -> -2.4133991 | L26: =-L25*L20/1000000 -> -0.21649574 | M26: =-M25*M20/1000000 -> 0 | N26: =-N25*N20/1000000 -> -1.7022253 | O26: =-O25*O20/1000000 -> -1.8749406 | T26: =-T25*T20/1000000 -> 0.46369473
B28: Checks | S28: =SUM(S15:S18)=S20 -> TRUE
S29: =S22-S9+S18=-S15-S16 -> TRUE
B30: Capital Account Statement
B31: New Space Capital
B33: EUR | C33: 3Q22 | D33: 4Q22 | E33: 1Q23 | F33: 2Q'23 | G33: 3Q'23 | H33: 1Q'24 | I33: 2Q'24 | J33: 3Q'24 | K33: To Q4'24… | L33: Q1'25 | M33: Q2'25
B34: Commitment | C34: 23234462 | D34: 23234462 | E34: 23234462 | F34: 23234462 | G34: 23234462 | H34: =G34 -> 23234462 | I34: =H34 -> 23234462 | J34: =I34 -> 23234462 | K34: =J34 -> 23234462 | L34: =K34 -> 23234462 | M34: =L34 -> 23234462 | T34: source: distribution letter
B35: Capital Contribution | C35: 19178323 | D35: 9436936 | E35: 9626402 | F35: 9595097 | G35: 9834193 | H35: 12498073 | I35: 12128944 | J35: 13706993 | K35: =J35+O18 -> 15455923 | L35: 14203894 | M35: 16528522
B36: Unfunded | C36: =C34-C35 -> 4056139 | D36: =D34-D35 -> 13797526 | E36: =E34-E35 -> 13608060 | F36: =F34-F35 -> 13639365 | G36: =G34-G35 -> 13400269 | H36: =H34-H35 -> 10736389 | I36: =I34-I35 -> 11105518 | J36: =J34-J35 -> 9527469 | K36: =O22 -> 7722475.5 | L36: =L34-L35 -> 9030568.4 | M36: =M34-M35 -> 6705940
B37: Unrealized Gain | C37: 13103567 | D37: 3803379 | G37: =G38-G35 -> 2548651 | H37: =H38-H35 -> 5930326 | I37: =I38-I35 -> 5735230 | J37: =J38-J35 -> 5712270 | K37: =K38-K35 -> 5712270 | L37: =L38-L35 -> 5012213.4 | M37: =M38-M35 -> 5394952
B38: NAV (after carried interest) | C38: 32325017 | D38: 12031777 | E38: 12148021 | F38: 12218930 | G38: 12382844 | H38: 18428399 | I38: 17864174 | J38: 19419263 | K38: =J38+O18 -> 21168193 | L38: =19216107 -> 19216107 | M38: 21923474 | T38: source: distribution letter
B39: Capital Return | D39: =C35-D35 -> 9741387 | T39: estimated
B40: Interest Capitalization | D40: =D42-D39 -> 2728214 | T40: estimated
B42: Total Distribution Received | D42: 12469601 | T42: source: distribution letters, Gino
B43: Remaining Commitment | D43: =15675627.21 -> 15675627 | G43: =I22 -> 13400268 | T43: source: distribution letter

Sheet MGX
O3: Notice | P3: Date of Notice | Q3: Capital Commitment | R3: Amount Invested | S3: Capital Contributed | T3: Unfunded Capital Commitment
B4: Source: Capital Account Statement Q2 25 | N4: Fund
D5: Committed | E5: Invested | F5: Remaining Commitment | G5: Distributions | H5: Carrying Value | I5: Gain | J5: Gain till FY22 | K5: TVPI | N5: Share Capital | O5: MGX HoldCo | Q5: 45547 | R5: 25000000 | S5: Share Capital | T5: 25000000
B6: MGX I LP | C6: 0.03125 | D6: 1200 | E6: 196.45596 | F6: 1003.544 | G6: 0 | H6: 383.34912 | I6: =H6-E6 -> 186.89316 | K6: =(H6+G6)/E6 -> 1.9513235 | S6: Total | T6: 25000000 | U6: 0
B7: MGX I LP Denali | E7: 18.647417 | G7: 0 | H7: 44.017114 | I7: =H7-E7 -> 25.369697 | K7: =(H7+G7)/E7 -> 2.3604939 | N7: Open AI | O7: MGX Fund I LP | P7: Drawdown Notice No. 1 - 19/12/2024 | Q7: 45645 | R7: 1200000000 | S7: Open AI | T7: 20202020
B8: MGX 1 Strategic Co-invest | D8: 775 | E8: 312.49956 | F8: 462.50044 | G8: 0 | H8: 396.0636 | I8: 59.161648 | J8: 0 | K8: =(H8+G8)/E8 -> 1.2674053 | N8: X.AI | O8: MGX Fund I LP | P8: Drawdown Notice No. 1 - 19/12/2024 | Q8: 45645 | S8: X.AI | T8: 20202020
B9: MGX Group Holding 1 Ltd (GP) | D9: 25 | E9: 25 | F9: 0 | G9: 0 | H9: 25 | I9: 0 | J9: 0 | K9: =(H9+G9)/E9 -> 1 | N9: Anthropic | O9: MGX Fund I LP | P9: Drawdown Notice No. 1 - 19/12/2024 | Q9: 45645 | S9: Anthropic | T9: 42880735
N10: Databricks | O10: MGX Fund I LP | P10: Drawdown Notice No. 1 - 19/12/2024 | Q10: 45645 | S10: Databricks | T10: 32323230
N11: Expenses | O11: MGX Fund I LP | P11: Drawdown Notice No. 1 - 19/12/2024 | Q11: 45645 | S11: Organisational Expenses (8m) | T11: 458978
B12: Aug 25 | Estimated | N12: Expenses | O12: MGX Fund I LP | P12: Drawdown Notice No. 1 - 19/12/2024 | Q12: 45645 | S12: Operating Expenses | T12: 30303
D13: Committed | E13: Invested | F13: Remaining Commitment | G13: Distributions | H13: Carrying Value | I13: Gain | J13: Gain till FY22 | K13: TVPI | N13: Open AI | O13: MGX Fund I LP | P13: Drawdown Notice No. 2 - 24/02/2025 | Q13: 45712 | S13: Open AI | T13: 2020202
B14: MGX I LP | C14: 0.03125 | D14: 1200 | E14: =C34 -> 210.22875 | F14: =D14-E14 -> 989.77125 | G14: 0 | H14: =C37 -> 326.2094 | I14: =H14-E14 -> 115.98065 | J14: 0 | K14: =(G14+H14)/E14 -> 1.5516879 | N14: Databricks | O14: MGX Fund I LP | P14: Drawdown Notice No. 2 - 24/02/2025 | Q14: 45712 | S14: Databricks | T14: 8080808
B15: MGX 1 Strategic Co-invest | D15: 775 | E15: 312.49956 | F15: =D15-E15 -> 462.50044 | G15: 0 | H15: 371.66121 | I15: =H15-E15 -> 59.161648 | J15: 0 | K15: 1.1893175 | N15: Khazna | O15: MGX Fund I LP | P15: Drawdown Notice No. 2 - 24/02/2025 | Q15: 45712 | S15: Khazna | T15: 59841678
B16: MGX Group Holding 1 Ltd (GP) | D16: 25 | E16: 25 | F16: =D16-E16 -> 0 | G16: 0 | H16: 25 | I16: =H16-E16 -> 0 | J16: 0 | K16: 1 | N16: Safe Superintelligence Inc. | O16: MGX Fund I LP | P16: Drawdown Notice No. 3 - 25/02/2025 | Q16: 45713 | S16: Safe Superintelligence Inc. | T16: 8080737
N17: Expenses | O17: MGX Fund I LP | P17: Drawdown Notice No. 2 - 24/02/2025 | Q17: 45712 | S17: Operating Expenses | T17: 281270
B18: MGX 1 LP | N18: Expenses | O18: MGX Fund I LP | P18: Drawdown Notice No. 4 - 10/04/2025 | Q18: 45757 | S18: Partnership expenses | T18: 1649907
B19: Total Capital Called | C19: =C20+C21 -> 185.42965 | N19: Databricks | O19: MGX Fund I LP | P19: Drawdown Notice No. 4 - 10/04/2025 | Q19: 45757 | S19: Databricks | T19: 14
B20: Capital Contributed upto Q2'25 | C20: =SUM(T7:T30)*10^-6 -> 139.3968 | D20: cashflows | N20: Open AI | O20: MGX Fund I LP | P20: Drawdown Notice No. 4 - 10/04/2025 | Q20: 45757 | S20: Open AI | T20: 404053
B21: Capital Contributed during Jul, Aug 25 | C21: =SUM(T31:T35)*10^-6 -> 46.032852 | N21: Open AI | O21: MGX Fund I LP | P21: Drawdown Notice No. 5 – 20/06/2025 | Q21: 45828 | S21: Open AI | T21: -13876271
B22: Pro Rata NAV | C22: =C20/E6*H6 -> 272.00825 | N22: X.AI | O22: MGX Fund I LP | P22: Drawdown Notice No. 5 – 20/06/2025 | Q22: 45828 | S22: X.AI | T22: -12389520
N23: Anthropic | O23: MGX Fund I LP | P23: Drawdown Notice No. 5 – 20/06/2025 | Q23: 45828 | S23: Anthropic | T23: -26297951
B24: NAV | C24: =C22+C21 -> 318.0411 | N24: Databricks | O24: MGX Fund I LP | P24: Drawdown Notice No. 5 – 20/06/2025 | Q24: 45828 | S24: Databricks | T24: -24779048
N25: Khazna | O25: MGX Fund I LP | P25: Drawdown Notice No. 5 – 20/06/2025 | Q25: 45828 | S25: Khazna | T25: -36699779
B26: Denali | N26: Safe Superintelligence Inc. | O26: MGX Fund I LP | P26: Drawdown Notice No. 5 – 20/06/2025 | Q26: 45828 | S26: SSI | T26: -4955764
B27: Total Capital Called | C27: =C28+C29 -> 24.799092 | N27: Binance | O27: MGX Fund I LP | P27: Drawdown Notice No. 5 – 20/06/2025 | Q27: 45828 | S27: Binance | T27: 62500000
B28: Capital Contributed upto Q2'25 | C28: =SUM(T37:T49)*10^-6 -> 22.961783 | N28: Expenses | O28: MGX Fund I LP | P28: Drawdown Notice No. 5 – 20/06/2025 | Q28: 45828 | S28: Organisational Expenses (8m) | T28: -281482
B29: Capital Contributed during Jul, Aug 25 | C29: =SUM(T50:T51)*10^-6 -> 1.837309 | N29: Expenses | O29: MGX Fund I LP | P29: Drawdown Notice No. 5 – 20/06/2025 | Q29: 45828 | S29: Partnership expenses | T29: -1202939
B30: Pro Rata NAV | C30: =C28/E7*H7 -> 54.201149 | N30: Expenses | O30: MGX Fund I LP | P30: Drawdown Notice No. 5 – 20/06/2025 | Q30: 45828 | S30: Finance Expenses | T30: 923602
N31: Expenses | O31: MGX Fund I LP | P31: Drawdown Notice No. 6 – 09/07/2025 | Q31: 45847 | S31: Partnership expenses | T31: 30766
N32: Altera Corporation | O32: MGX Fund I LP | P32: Drawdown Notice No. 7 – 19/08/2025 | Q32: 45888 | S32: Altera Corporation | T32: 16454597
B33: Combined (MGX 1 + Denali) | N33: Campus AI | O33: MGX Fund I LP | P33: Drawdown Notice No. 7 – 19/08/2025 | Q33: 45888 | S33: Campus AI | T33: 341406
B34: Total Capital Called | C34: =C19+C27 -> 210.22875 | N34: Open AI | O34: MGX Fund I LP | P34: Drawdown Notice No. 7 – 19/08/2025 | Q34: 45888 | S34: OpenAI Global, LLC | T34: 29093750
B35: Capital Contributed upto Q2'25 | C35: =C20+C28 -> 162.35859 | N35: Expenses | O35: MGX Fund I LP | P35: Drawdown Notice No. 7 – 19/08/2025 | Q35: 45888 | S35: Finance Expenses | T35: 112333
B36: Capital Contributed during Jul, Aug 25 | C36: =C21+C29 -> 47.870161
B37: Pro Rata NAV | C37: =C22+C30 -> 326.2094 | D37: =C37/C34 -> 1.5516879 | N37: Vantage | O37: MGX Denali (AIV) | P37: Capital Call Notice - 11/06/2024 | Q37: 45454 | S37: Vantage | T37: 4440212
N38: Vantage | O38: MGX Denali (AIV) | P38: Capital Call Notice - 25/06/2024 | Q38: 45468 | S38: Vantage | T38: 856702
N39: Vantage | O39: MGX Denali (AIV) | P39: Capital Call Notice - 27/09/2024 | Q39: 45562 | S39: Vantage | T39: 1766018
N40: Expenses | O40: MGX Denali (AIV) | P40: Capital Call Notice - 16/10/2024 | Q40: 45581 | S40: Partnership expenses | T40: 125982
N41: Vantage | O41: MGX Denali (AIV) | P41: Capital Call Notice - 19/12/2024 | Q41: 45645 | S41: Vantage | T41: 3257177
N42: Vantage | O42: MGX Denali (AIV) | P42: Drawdown Notice No. 6 - 10/03/2025 | Q42: 45726 | S42: Vantage | T42: 8068966
N43: Expenses | O43: MGX Denali (AIV) | P43: Drawdown Notice No. 6 - 10/03/2025 | Q43: 45726 | S43: Organisation Expenses | T43: 67182
N44: Expenses | O44: MGX Denali (AIV) | P44: Drawdown Notice No. 6 - 10/03/2025 | Q44: 45726 | S44: Partnership Expenses | T44: 65179
N45: Vantage | O45: MGX Denali (AIV) | P45: Drawdown Notice No. 6 - 10/03/2025 | Q45: 45828 | S45: Vantage | T45: -11354937
N46: Vantage | O46: MGX Denali (AIV) | P46: Drawdown Notice No. 8 - 20/06/2025 | Q46: 45828 | S46: Vantage | T46: 14527596
N47: Expenses | O47: MGX Denali (AIV) | P47: Drawdown Notice No. 8 - 20/06/2025 | Q47: 45828 | S47: Organisational Expenses | T47: -41202
N48: Expenses | O48: MGX Denali (AIV) | P48: Drawdown Notice No. 8 - 20/06/2025 | Q48: 45828 | S48: Partnership expenses | T48: -39973
N49: Expenses | O49: MGX Denali (AIV) | P49: Drawdown Notice No. 8 - 20/06/2025 | Q49: 45828 | S49: Finance Expenses | T49: 1222881
... N51: Vantage | O51: MGX Denali (AIV) | P51: Drawdown Notice No. 9 - 09/07/2025 | Q51: 45847 | S51: Vantage | T51: 1836934
S52: Total | T52: 210228747 | U52: 989771253
N53: Open AI | O53: MGX Strategic Co-Invest | P53: Capital Call Notice - 27/09/2024 | Q53: 45562 | R53: 775000000 | S53: Open AI | T53: 250000000
N54: X.AI | O54: MGX Strategic Co-Invest | P54: Capital Call Notice - 22/11/2024 | Q54: 45618 | S54: X.AI | T54: 249999998
N55: Open AI | O55: MGX Strategic Co-Invest | P55: Distribution Notice No. 1 - 19/12/2024 | Q55: 45645 | S55: Open AI | T55: -125000000
N56: X.AI | O56: MGX Strategic Co-Invest | P56: Distribution Notice No. 1 - 19/12/2024 | Q56: 45645 | S56: X.AI | T56: -124999999
N57: Open AI | O57: MGX Strategic Co-Invest | P57: Drawdown Notice No. 3 - 24/02/2025 | Q57: 45712 | S57: Open AI | T57: 12500000
N58: Safe Superintelligence Inc. | O58: MGX Strategic Co-Invest | P58: Drawdown Notice No. 4 - 25/02/2025 | Q58: 45713 | S58: Safe Superintelligence Inc. | T58: 49999560
Q59: Total | R59: 2000000000 | S59: Total | T59: 312499559 | U59: 462500441

Sheet C. Log
B2: Date Log | C2: Update
B3: Aug' 25
C5: Flyr | D5: revalued at $5.42 per share
C6: North Summit Capital Fund | D6: removed new funding requirement
B8: Jul'25
C9: MGX | D9: MGX capital calls paid USD 6,182,440.92, MGX equalization refund received USD 57,059,152.35
B11: Jun'25
C12: New Space Capital | D12: Funded a capital call of EUR 2.3m
B14: May'25
C15: Neuralink | D15: $50m investment
C16: Flyr, Drivenets | D16: Updated % ownership details
C17: Cerebras | D17: Revised Commitment to $111.7m (from $335m)
C18: eSpace | D18: Revised valuation as per round B6 (refer Carta)
B20: Apr'25
C21: Drivenets | D21: Received distribution of $84.8m from partial exit
C22: MGX | D22: Funded $2.1m for the capital call
C23: Heygears | D23: Valuation revised, as per the guidance by Ardent, Dec'24
B25: Mar'25 | Expected developments during March 2025, which are still in progress
C26: New Space Capital | D26: Additional Capital Call EUR 711K
C27: Acies | D27: Additional Capital Call, USD 1.7m
C28: MGX | D28: Additional Capital Call, USD c150m across the main fund and co-investments
C29: Liquid AI | D29: Invested $20m, for the first closing
C30: Eline | D30: Valuation revised, as per the guidance by Ardent, Dec'24
C31: Endless | D31: Valuation revised, as per the guidance by Ardent, Dec'24
C32: Drivenets | D32: Valuation revised, as per the guidance by Ardent, Dec'24
B34: Feb'25
C35: New Space Capital | D35: Actualization Interest + Return of Capital Distribution of EUR 2.4m received
B37: Jan'25
C38: Liquid AI | D38: Subjected to CFIUS approval; new investment w/ $65m commitment and an option to invest a further $40m
C39: Cerebras F1 | D39: Subjected to CFIUS clearance, $335m commitment to invest in the series F1
C40: MGX and associated investments | D40: $2Bn of commitments across the fund, and the co-investment vehicles
C41: Verses | D41: Received $320K of the transaction costs, but not included in the distributions, as it is an offset to the transaction costs
B42: Dec'24
C43: AAICO | D43: carrying value marked up to $39M (or 2.27X of cost)
C44: eSpace | D44: carrying value marked up to $58.44 per share
C45: Inveniam | D45: recevied a distribution of $499K in lieu of profit share for Surplus Worldcoin Token Proceeds
B46: Nov'24
C47: WLD coin | D47: Divested all 62.5M tokens for $100M
C48: Inveniam | D48: Acquired 20% equivalent equity via SAR, in exchange for WLD valued at $100M
C49: AAICO: | D49: Accelerated Milestone 3 investment of $3.5m, released on 21 Nov 24
C50: New Space Capital | D50: Capital Call No. 16 of EUR1.75M. Q3-24 NAV at EUR 19.42M
C51: North Summit Capital | D51: Capital Call No. 15 of $ 31,561. Q3-24 NAV at $81.6M
C52: Flyr | D52: NAV marked to the recent Series D raised at $7.1307 per share
C53: BL | D53: Successfully raised loan from shareholders of $12.9M
B54: Oct'24
C55: Lifebio : Invested additional $20m, and converted the outstanding $20m CLN.
B56: Sep'24
C57: No investment cash inflows or outflows to report
B58: Aug'24
C59: New Space Capital capital call of EUR 2.1m funded
C60: Beyond Limits carrying value marked down
B61: Jul'24
C62: No investment cash inflows or outflows to report
B63: Jun'24
C64: Verses : $10m Investment in Convertible Debenture
C65: North Summit Capital : capital contribution $55.7K
C66: New Space Capital : distributions received EUR 431.6K
C67: Flyr: Carrying Value reduced to $30m from $65m
B68: May' 24
C69: No investment cash inflows or outflows to report
B70: Apr' 24
C71: No investment cash inflows or outflows to report
B72: Mar'24
C73: New Space Capital LP: Capital contribution of EUR 200,702.46 as of 21 Mar 24
C74: Carrying values of Flyr, Beyond Limits and DriveNets marked down as per Ardent guidance
B75: Feb'24
C76: Sinovation: receivedUSD 24,959,693 as full cash proceeds of from the exit
C77: Life Biosciences: issued USD 20m convertible loan note
B78: Jan’24
C79: AAICO: USD 4m second milestone payment on 4-Jan-24
C80: NewSpace: EUR 2.2M (USD 2.42M) capital call paid on 30-Jan-24
C81: SchoolHack: Made an equity investment of USD 2.5m plus 250K in cloud credits
C82: Menamobile: Under liquidation
B83: Dec’23
C84: Espace Inc: converted the SAFE to equity
C85: North Summit Capital: G42’s remaining funding capital commitments waived
B86: Nov’23
C87: North Summit Capital : USD 6.8 distribution received on 13th November
B88: Oct’23
C89: Paid USD 2.4m to Sinovation Disrupt Fund (8th capital call)
C90: Received USD 2.8m dividend for Honor and USD 800m for Honor sell-down
C91: Received USD 403m for xFusion sell-down
B92: Sep’23
C93: No cashflow movements to report
B94: Aug’23
C95: Received USD 24.5m for Jysan’s exit
C96: Funded USD 1,799,122 towards Sinovation’s capital call
C97: Invested USD 6m in E-line Ventures and USD 5m in Endless Studios
B98: Jul’23
C99: Worldcoin: token warrant exercised, received 62.5M tokens
C100: AAICO: first milestone payment called with $2.75m additional invested
C101: Instadeep: fully exited at 1.56X return over invested capital (received $7.82m)
B102: Jun’23
C103: A distribution of $1.9m as a ‘return of capital’ received from the Sinovation Disrupt Fund
B104: May’23
C105: Invested $15m in Tools for Humanity Corp equity and Worldcoin token warrants
B106: Apr’23
C107: Re-structured investment in New Space Capital GP restructured – converted to GP commitment vehicle
C108: NAVs marked up for: Instadeep, Heygears and North Summit Capital. Mena Mobile equity value written off
B109: Mar’23
...

Sheet check-Jul25
C2: As of date | D2: 45869
E5: 2 | F5: 3 | G5: 4 | H5: 5 | I5: 6 | J5: 7 | K5: 8 | L5: 9 | M5: 10 | N5: 11 | O5: 12 | P5: 13 | R5: 14 | S5: 15
C6: Deals | D6: Type | E6: Status | F6: Lead | G6: Investing Entity | H6: Vintageἀ | I6: Instrument | J6: % | K6: Committed | L6: Invested | M6: Remaining Commitment | N6: Distributions | O6: Carrying Value | P6: Gain | Q6: Gain till FY22 | R6: TVPI | S6: Additonal Upside/Downside
I7: # | J7: % | K7: $,m | L7: $,m | M7: $,m | N7: $,m | O7: $,m | P7: $,m | R7: X
C8: MOZN Holding RSC Ltd
C9: E-line Ventures LLC | D9: Direct Investment | E9: Unrealized | F9: 0 | G9: Mozn | H9: 2023 | I9: B Prefs | J9: 0.11483736 | K9: 6 | L9: 6 | M9: 0 | N9: 0 | O9: 15.3 | P9: 9.3 | Q9: n/a | R9: 2.55 | S9: Optionse
C10: Tools for Humanity Corporation | D10: Direct Investment | E10: Unrealized | F10: 0 | G10: Mozn | H10: 2023 | I10: C Prefs | J10: 0.00626608 | K10: 14.999999 | L10: 14.999999 | M10: 0 | N10: 0 | O10: 2.4 | P10: -12.599999 | Q10: n/a | R10: 0.16000001
C11: eSpace | D11: Direct Investment | E11: Unrealized | F11: 0 | G11: Mozn 4 | H11: 2022 | I11: B Prefs | J11: 0.026056201 | K11: 15 | L11: 15 | M11: 0 | N11: 0 | O11: 32.34128 | P11: 17.34128 | Q11: 0 | R11: 2.1560854
C12: Applied AI Corporation Limited | D12: Direct Investment | E12: Unrealized | F12: 0 | G12: Mozn | H12: 2022 | I12: A Prefs | J12: 0.12121516 | K12: 15 | L12: 15 | M12: 0 | N12: 0 | O12: 38.46473 | P12: 23.46473 | Q12: 0 | R12: 2.5643153
C13: Cerebras Systems Inc | D13: Direct Investment | E13: Unrealized | F13: 0 | G13: Mozn | H13: 2021 | I13: F Prefs | J13: 0.0081 | K13: 39.999983 | L13: 39.999983 | M13: 0 | N13: 0 | O13: 21.135483 | P13: -18.8645 | Q13: 0 | R13: 0.5283873
C14: Endless Studios LLC | D14: Direct Investment | E14: Unrealized | F14: 0 | G14: Mozn | H14: 2021 | I14: A Pref Units | J14: 0.15458937 | K14: 8 | L14: 8 | M14: 0 | N14: 0 | O14: 4.7 | P14: -3.3 | Q14: 0 | R14: 0.5875
C15: Heygears | D15: Direct Investment | E15: Unrealized | F15: 0 | G15: Mozn | H15: 2020 | I15: Registered Capital | J15: 0.14383199 | K15: 60 | L15: 60 | M15: 0 | N15: 0 | O15: 40.3 | P15: -19.7 | Q15: 96.4 | R15: 0.67166667
C16: Beyond Limits | D16: Direct Investment | E16: Unrealized | F16: 0 | G16: Mozn | H16: 2020 | I16: C Prefs | J16: 0.094347728 | K16: 90 | L16: 90 | M16: 0 | N16: 0 | O16: 41.003704 | P16: -48.996296 | Q16: 1.042 | R16: 0.45559671
C17: ONT plc | D17: Direct Investment | E17: Unrealized | F17: 0 | G17: Mozn | H17: 2020 | I17: Ordinary Shares | J17: 0.046395018 | K17: 141.47026 | L17: 141.47026 | M17: 0 | N17: 0 | O17: 119.41198 | P17: -22.058283 | Q17: -9.845 | R17: 0.8440783
C18: Flyr Inc | D18: Direct Investment | E18: Unrealized | F18: 0 | G18: Mozn | H18: 2019 | I18: B-1,2 Prefs | J18: 0.035329982 | K18: 10 | L18: 10 | M18: 0 | N18: 0 | O18: 37.11873 | P18: 27.11873 | Q18: 68.1 | R18: 3.711873 | S18: Flyr Warrantsa
K20: 400.47024 | L20: 400.47024 | M20: 0 | N20: 0 | O20: 352.1759 | P20: -48.294338 | Q20: 155.697 | R20: 0.87940593
C22: G42 Investments AI Holding RSC Ltd
C23: DriveNets | D23: Direct Investment | E23: Partially Realized | F23: 0 | G23: G42 Investments | H23: 2022 | I23: Equity-TBC | J23: 0.0878 | K23: 300 | L23: 300 | M23: 0 | N23: 84.804486 | O23: 325.79092 | P23: 110.59541 | Q23: 0 | R23: 1.3686514 | S23: DN Warrants b
C24: vTv Therapeutics Inc. | D24: Direct Investment | E24: Unrealized | F24: 0 | G24: G42 Investments | H24: 2022 | I24: Ordinary Shares | J24: 0.081407233 | K24: 24.53125 | L24: 24.53125 | M24: 0 | N24: 0 | O24: 3.8818721 | P24: -20.649378 | Q24: -1.348 | R24: 0.15824192 | S24: vTv $30m milestn payment c
C25: North Summit Capital Fund | D25: Fund Investment | E25: Unrealized | F25: 0 | G25: G42 Investments | H25: 2020 | I25: LP | J25: n/a | K25: 83.721611 | L25: 83.361611 | M25: 0.36 | N25: 7.875571 | O25: 59.421576 | P25: -16.064464 | Q25: -0.306 | R25: 0.80729182
C26: New Space Capital Fund I | D26: Fund Investment | E26: Unrealized | F26: 0 | G26: G42 Investments | H26: 2020 | I26: LP | J26: n/a | K26: 29.416939 | L26: 19.108545 | M26: 10.308394 | N26: 3.7927063 | O26: 24.654978 | P26: 9.3391392 | Q26: 5.445 | R26: 1.4887415
C27: New Space Capital GP Com SCSp | D27: Fund Investment | E27: Unrealized | F27: 0 | G27: G42 Investments | H27: 2023 | I27: LP | J27: n/a | K27: 2.7058824 | L27: 2.7058824 | M27: 0 | N27: 0 | O27: 3.4912899 | P27: 0.78540752 | Q27: 0 | R27: 1.2902593
C28: Acies Investments Fund I, L.P. | D28: Fund Investment | E28: Unrealized | F28: 0 | G28: G42 Investments | H28: 2021 | I28: LP | J28: 0.33 | K28: 17.1125 | L28: 15.726387 | M28: 1.3861125 | N28: 0 | O28: 12.873463 | P28: -2.8529245 | Q28: -0.306 | R28: 0.81858997 | S28: 9.9% GP | Anchorf
K30: 457.48818 | L30: 445.43368 | M30: 12.054506 | N30: 96.472763 | O30: 430.1141 | P30: 81.153186 | Q30: 3.485 | R30: 1.1821892
C32: G42 Capital SPV RSC Ltd
C33: Life Biosciences LLC | D33: Direct Investment | E33: Unrealized | F33: 0 | G33: G42 Capital | H33: 2024 | I33: D Prefs | J33: 0.072996903 | K33: 40 | L33: 40 | M33: 0 | N33: 0 | O33: 40.947394 | P33: 0.94739371 | Q33: 0 | R33: 1.0236848 | S33: EPTH7
C34: Cerebras Systems Inc F1 | D34: Direct Investment | E34: Not Completed | F34: 0 | G34: G42 Capital | H34: 2025 | I34: Series F-1 | J34: TBD | K34: 111.66667 | L34: 0 | M34: 111.66667 | N34: 0 | O34: 0 | P34: 0 | Q34: 0 | R34: NM | S34: EPTH8; option to buy more
C35: Verses AI Inc | D35: Direct Investment | E35: Unrealized | F35: 0 | G35: G42 Capital | H35: 2024 | J35: 0.065761781 | K35: 10 | L35: 10 | M35: 0 | N35: 0 | O35: 3.0867114 | P35: -6.9132886 | Q35: 0 | R35: 0.30867114 | S35: EPTH9 Revenue linked RSUs
C36: Inveniam Ltd | D36: Direct Investment | E36: Unrealized | F36: 0 | G36: G42 Capital | H36: 2024 | I36: SAR | J36: 20% Eq | K36: 100 | L36: 100 | M36: 0 | N36: 0.499965 | O36: 100 | P36: 0.499965 | Q36: 0 | R36: 1.0049997 | S36: EPTH10 Upside if Tokens sold > $2.5 per token
C37: Liquid AI | D37: Direct Investment | E37: Unrealized | F37: 0 | G37: G42 Capital | H37: 2024 | I37: Series A | J37: TBD | K37: 66.599843 | L37: 19.999882 | M37: 46.599961 | N37: 0 | O37: 19.999882 | P37: 0 | Q37: 0 | R37: 1 | S37: EPTH11 option to buy $45m more
C38: Neuralink | D38: Direct Investment | E38: Unrealized | F38: 0 | G38: G42 Capital | H38: 2025 | I38: Series E | J38: 0.0051805228 | K38: 50 | L38: 50 | M38: 0 | N38: 0 | O38: 50 | P38: 5e-07 | Q38: 0 | R38: 1 | S38: EPTH12
K40: 378.26651 | L40: 219.99988 | M40: 158.26663 | N40: 0.499965 | O40: 214.03399 | P40: -5.4659299 | Q40: 0 | R40: 0.97515485
C42: Core42 Holding RSC Ltd
C43: School Hack (AIREV Holding Limited) | D43: Direct Investment | E43: Unrealized | F43: 0 | G43: Core42 5 | H43: 2024 | I43: Preferred Shares | J43: 0.25 | K43: 2.75 | L43: 2.5 | M43: 0.25 | N43: 0 | O43: 2.5 | P43: 0 | Q43: 0 | R43: 1 | S43: Cloud Creditg
K45: 2.75 | L45: 2.5 | M45: 0.25 | N45: 0 | O45: 2.5 | P45: 0 | Q45: 0 | R45: 1
C47: GX Investments Ltd : MGX and Related Investments
C48: MGX I LP | D48: MGX LP | E48: Unrealized | F48: 0 | G48: G42 Holding | H48: 2024 | I48: LP | J48: 0.061685164 | K48: 1200 | L48: 164.22666 | M48: 1035.7733 | N48: 0 | O48: 199.45127 | P48: 35.224605 | Q48: 0 | R48: 1.2144877
C49: MGX 1 Strategic Co-invest | D49: MGX Co-Invest LP | E49: Unrealized | F49: 0 | G49: G42 Holding | H49: 2024 | I49: LP | J49: 0.5 | K49: 775 | L49: 312.49956 | M49: 462.50044 | N49: 0 | O49: 371.66121 | P49: 59.161648 | Q49: 0 | R49: 1.1893175
C50: MGX Group Holding 1 Ltd (GP) | D50: MGX GP | E50: Unrealized | F50: 0 | G50: G42 Holding | H50: 2024 | I50: Equity | J50: 0 | K50: 25 | L50: 25 | M50: 0 | N50: 0 | O50: 25 | P50: 0 | Q50: 0 | R50: 1
K52: 2000 | L52: 501.72622 | M52: 1498.2738 | N52: 0 | O52: 596.11247 | P52: 94.386253 | Q52: 0 | R52: 1.188123
K54: 3238.9749 | L54: 1570.13 | M54: 1668.8449 | N54: 96.972728 | O54: 1594.9365 | P54: 121.77917 | Q54: 159.182 | R54: 1.0775599
I57: Checks: | K57: TRUE | L57: TRUE | M57: TRUE | N57: TRUE | O57: TRUE | P57: TRUE | Q57: TRUE
C58: For Notes, refer to 9. All deals (a) | K58: TRUE | L58: TRUE | M58: TRUE | N58: TRUE | O58: TRUE | P58: TRUE | Q58: TRUE
C59: Position Exited or written off are highlighted | K59: TRUE | L59: TRUE | M59: TRUE | N59: TRUE | O59: TRUE | P59: TRUE | Q59: TRUE

Sheet check-diff
C2: As of date | D2: 45869
E5: 2 | F5: 3 | G5: 4 | H5: 5 | I5: 6
C6: Deals | D6: Type | E6: Status | F6: Lead | G6: Investing Entity | H6: Vintageἀ | I6: Instrument | J6: % | K6: Committed | L6: Invested | M6: Remaining Commitment | N6: Distributions | O6: Carrying Value | P6: Gain | Q6: Gain till FY22 | R6: TVPI | S6: Additonal Upside/Downside
I7: #
C8: MOZN Holding RSC Ltd
C9: E-line Ventures LLC | D9: Direct Investment | E9: Unrealized | F9: 0 | G9: Mozn | H9: 2023 | I9: B Prefs | J9: =IF('1. Live'!J9='check-Jul25'!J9,"",'1. Live'!J9-'check-Jul25'!J9) | K9: =IF('1. Live'!K9='check-Jul25'!K9,"",'1. Live'!K9-'check-Jul25'!K9) | L9: =IF('1. Live'!L9='check-Jul25'!L9,"",'1. Live'!L9-'check-Jul25'!L9) | M9: =IF('1. Live'!M9='check-Jul25'!M9,"",'1. Live'!M9-'check-Jul25'!M9) | N9: =IF('1. Live'!N9='check-Jul25'!N9,"",'1. Live'!N9-'check-Jul25'!N9) | O9: =IF('1. Live'!O9='check-Jul25'!O9,"",'1. Live'!O9-'check-Jul25'!O9) | P9: =IF('1. Live'!P9='check-Jul25'!P9,"",'1. Live'!P9-'check-Jul25'!P9) | Q9: =IF('1. Live'!Q9='check-Jul25'!Q9,"",'1. Live'!Q9-'check-Jul25'!Q9) | ... CW9: =IF('1. Live'!CW9='check-Jul25'!CW9,"",'1. Live'!CW9-'check-Jul25'!CW9)
C10: Tools for Humanity Corporation | D10: Direct Investment | E10: Unrealized | F10: 0 | G10: Mozn | H10: 2023 | I10: C Prefs | J10: =IF('1. Live'!J10='check-Jul25'!J10,"",'1. Live'!J10-'check-Jul25'!J10) | K10: =IF('1. Live'!K10='check-Jul25'!K10,"",'1. Live'!K10-'check-Jul25'!K10) | L10: =IF('1. Live'!L10='check-Jul25'!L10,"",'1. Live'!L10-'check-Jul25'!L10) | M10: =IF('1. Live'!M10='check-Jul25'!M10,"",'1. Live'!M10-'check-Jul25'!M10) | N10: =IF('1. Live'!N10='check-Jul25'!N10,"",'1. Live'!N10-'check-Jul25'!N10) | O10: =IF('1. Live'!O10='check-Jul25'!O10,"",'1. Live'!O10-'check-Jul25'!O10) | P10: =IF('1. Live'!P10='check-Jul25'!P10,"",'1. Live'!P10-'check-Jul25'!P10) | Q10: =IF('1. Live'!Q10='check-Jul25'!Q10,"",'1. Live'!Q10-'check-Jul25'!Q10) | ... CW10: =IF('1. Live'!CW10='check-Jul25'!CW10,"",'1. Live'!CW10-'check-Jul25'!CW10)
C11: eSpace | D11: Direct Investment | E11: Unrealized | F11: 0 | G11: Mozn 4 | H11: 2022 | I11: B Prefs | J11: =IF('1. Live'!J11='check-Jul25'!J11,"",'1. Live'!J11-'check-Jul25'!J11) | K11: =IF('1. Live'!K11='check-Jul25'!K11,"",'1. Live'!K11-'check-Jul25'!K11) | L11: =IF('1. Live'!L11='check-Jul25'!L11,"",'1. Live'!L11-'check-Jul25'!L11) | M11: =IF('1. Live'!M11='check-Jul25'!M11,"",'1. Live'!M11-'check-Jul25'!M11) | N11: =IF('1. Live'!N11='check-Jul25'!N11,"",'1. Live'!N11-'check-Jul25'!N11) | O11: =IF('1. Live'!O11='check-Jul25'!O11,"",'1. Live'!O11-'check-Jul25'!O11) | P11: =IF('1. Live'!P11='check-Jul25'!P11,"",'1. Live'!P11-'check-Jul25'!P11) | Q11: =IF('1. Live'!Q11='check-Jul25'!Q11,"",'1. Live'!Q11-'check-Jul25'!Q11) | ... CW11: =IF('1. Live'!CW11='check-Jul25'!CW11,"",'1. Live'!CW11-'check-Jul25'!CW11)
C12: Applied AI Corporation Limited | D12: Direct Investment | E12: Unrealized | F12: 0 | G12: Mozn | H12: 2022 | I12: A Prefs | J12: =IF('1. Live'!J12='check-Jul25'!J12,"",'1. Live'!J12-'check-Jul25'!J12) | K12: =IF('1. Live'!K12='check-Jul25'!K12,"",'1. Live'!K12-'check-Jul25'!K12) | L12: =IF('1. Live'!L12='check-Jul25'!L12,"",'1. Live'!L12-'check-Jul25'!L12) | M12: =IF('1. Live'!M12='check-Jul25'!M12,"",'1. Live'!M12-'check-Jul25'!M12) | N12: =IF('1. Live'!N12='check-Jul25'!N12,"",'1. Live'!N12-'check-Jul25'!N12) | O12: =IF('1. Live'!O12='check-Jul25'!O12,"",'1. Live'!O12-'check-Jul25'!O12) | P12: =IF('1. Live'!P12='check-Jul25'!P12,"",'1. Live'!P12-'check-Jul25'!P12) | Q12: =IF('1. Live'!Q12='check-Jul25'!Q12,"",'1. Live'!Q12-'check-Jul25'!Q12) | ... CW12: =IF('1. Live'!CW12='check-Jul25'!CW12,"",'1. Live'!CW12-'check-Jul25'!CW12)
C13: Cerebras Systems Inc | D13: Direct Investment | E13: Unrealized | F13: 0 | G13: Mozn | H13: 2021 | I13: F Prefs | J13: =IF('1. Live'!J13='check-Jul25'!J13,"",'1. Live'!J13-'check-Jul25'!J13) | K13: =IF('1. Live'!K13='check-Jul25'!K13,"",'1. Live'!K13-'check-Jul25'!K13) | L13: =IF('1. Live'!L13='check-Jul25'!L13,"",'1. Live'!L13-'check-Jul25'!L13) | M13: =IF('1. Live'!M13='check-Jul25'!M13,"",'1. Live'!M13-'check-Jul25'!M13) | N13: =IF('1. Live'!N13='check-Jul25'!N13,"",'1. Live'!N13-'check-Jul25'!N13) | O13: =IF('1. Live'!O13='check-Jul25'!O13,"",'1. Live'!O13-'check-Jul25'!O13) | P13: =IF('1. Live'!P13='check-Jul25'!P13,"",'1. Live'!P13-'check-Jul25'!P13) | Q13: =IF('1. Live'!Q13='check-Jul25'!Q13,"",'1. Live'!Q13-'check-Jul25'!Q13) | ... CW13: =IF('1. Live'!CW13='check-Jul25'!CW13,"",'1. Live'!CW13-'check-Jul25'!CW13)
C14: Endless Studios LLC | D14: Direct Investment | E14: Unrealized | F14: 0 | G14: Mozn | H14: 2021 | I14: A Pref Units | J14: =IF('1. Live'!J14='check-Jul25'!J14,"",'1. Live'!J14-'check-Jul25'!J14) | K14: =IF('1. Live'!K14='check-Jul25'!K14,"",'1. Live'!K14-'check-Jul25'!K14) | L14: =IF('1. Live'!L14='check-Jul25'!L14,"",'1. Live'!L14-'check-Jul25'!L14) | M14: =IF('1. Live'!M14='check-Jul25'!M14,"",'1. Live'!M14-'check-Jul25'!M14) | N14: =IF('1. Live'!N14='check-Jul25'!N14,"",'1. Live'!N14-'check-Jul25'!N14) | O14: =IF('1. Live'!O14='check-Jul25'!O14,"",'1. Live'!O14-'check-Jul25'!O14) | P14: =IF('1. Live'!P14='check-Jul25'!P14,"",'1. Live'!P14-'check-Jul25'!P14) | Q14: =IF('1. Live'!Q14='check-Jul25'!Q14,"",'1. Live'!Q14-'check-Jul25'!Q14) | ... CW14: =IF('1. Live'!CW14='check-Jul25'!CW14,"",'1. Live'!CW14-'check-Jul25'!CW14)
C15: Heygears | D15: Direct Investment | E15: Unrealized | F15: 0 | G15: Mozn | H15: 2020 | I15: Registered Capital | J15: =IF('1. Live'!J15='check-Jul25'!J15,"",'1. Live'!J15-'check-Jul25'!J15) | K15: =IF('1. Live'!K15='check-Jul25'!K15,"",'1. Live'!K15-'check-Jul25'!K15) | L15: =IF('1. Live'!L15='check-Jul25'!L15,"",'1. Live'!L15-'check-Jul25'!L15) | M15: =IF('1. Live'!M15='check-Jul25'!M15,"",'1. Live'!M15-'check-Jul25'!M15) | N15: =IF('1. Live'!N15='check-Jul25'!N15,"",'1. Live'!N15-'check-Jul25'!N15) | O15: =IF('1. Live'!O15='check-Jul25'!O15,"",'1. Live'!O15-'check-Jul25'!O15) | P15: =IF('1. Live'!P15='check-Jul25'!P15,"",'1. Live'!P15-'check-Jul25'!P15) | Q15: =IF('1. Live'!Q15='check-Jul25'!Q15,"",'1. Live'!Q15-'check-Jul25'!Q15) | ... CW15: =IF('1. Live'!CW15='check-Jul25'!CW15,"",'1. Live'!CW15-'check-Jul25'!CW15)
C16: Beyond Limits | D16: Direct Investment | E16: Unrealized | F16: 0 | G16: Mozn | H16: 2020 | I16: C Prefs | J16: =IF('1. Live'!J16='check-Jul25'!J16,"",'1. Live'!J16-'check-Jul25'!J16) | K16: =IF('1. Live'!K16='check-Jul25'!K16,"",'1. Live'!K16-'check-Jul25'!K16) | L16: =IF('1. Live'!L16='check-Jul25'!L16,"",'1. Live'!L16-'check-Jul25'!L16) | M16: =IF('1. Live'!M16='check-Jul25'!M16,"",'1. Live'!M16-'check-Jul25'!M16) | N16: =IF('1. Live'!N16='check-Jul25'!N16,"",'1. Live'!N16-'check-Jul25'!N16) | O16: =IF('1. Live'!O16='check-Jul25'!O16,"",'1. Live'!O16-'check-Jul25'!O16) | P16: =IF('1. Live'!P16='check-Jul25'!P16,"",'1. Live'!P16-'check-Jul25'!P16) | Q16: =IF('1. Live'!Q16='check-Jul25'!Q16,"",'1. Live'!Q16-'check-Jul25'!Q16) | ... CW16: =IF('1. Live'!CW16='check-Jul25'!CW16,"",'1. Live'!CW16-'check-Jul25'!CW16)
C17: ONT plc | D17: Direct Investment | E17: Unrealized | F17: 0 | G17: Mozn | H17: 2020 | I17: Ordinary Shares | J17: =IF('1. Live'!J17='check-Jul25'!J17,"",'1. Live'!J17-'check-Jul25'!J17) | K17: =IF('1. Live'!K17='check-Jul25'!K17,"",'1. Live'!K17-'check-Jul25'!K17) | L17: =IF('1. Live'!L17='check-Jul25'!L17,"",'1. Live'!L17-'check-Jul25'!L17) | M17: =IF('1. Live'!M17='check-Jul25'!M17,"",'1. Live'!M17-'check-Jul25'!M17) | N17: =IF('1. Live'!N17='check-Jul25'!N17,"",'1. Live'!N17-'check-Jul25'!N17) | O17: =IF('1. Live'!O17='check-Jul25'!O17,"",'1. Live'!O17-'check-Jul25'!O17) -> -11.132001 | P17: =IF('1. Live'!P17='check-Jul25'!P17,"",'1. Live'!P17-'check-Jul25'!P17) -> -11.132001 | Q17: =IF('1. Live'!Q17='check-Jul25'!Q17,"",'1. Live'!Q17-'check-Jul25'!Q17) | ... CW17: =IF('1. Live'!CW17='check-Jul25'!CW17,"",'1. Live'!CW17-'check-Jul25'!CW17)
C18: Flyr Inc | D18: Direct Investment | E18: Unrealized | F18: 0 | G18: Mozn | H18: 2019 | I18: B-1,2 Prefs | J18: =IF('1. Live'!J18='check-Jul25'!J18,"",'1. Live'!J18-'check-Jul25'!J18) | K18: =IF('1. Live'!K18='check-Jul25'!K18,"",'1. Live'!K18-'check-Jul25'!K18) | L18: =IF('1. Live'!L18='check-Jul25'!L18,"",'1. Live'!L18-'check-Jul25'!L18) | M18: =IF('1. Live'!M18='check-Jul25'!M18,"",'1. Live'!M18-'check-Jul25'!M18) | N18: =IF('1. Live'!N18='check-Jul25'!N18,"",'1. Live'!N18-'check-Jul25'!N18) | O18: =IF('1. Live'!O18='check-Jul25'!O18,"",'1. Live'!O18-'check-Jul25'!O18) -> -8.9050181 | P18: =IF('1. Live'!P18='check-Jul25'!P18,"",'1. Live'!P18-'check-Jul25'!P18) -> -8.9050181 | Q18: =IF('1. Live'!Q18='check-Jul25'!Q18,"",'1. Live'!Q18-'check-Jul25'!Q18) | ... CW18: =IF('1. Live'!CW18='check-Jul25'!CW18,"",'1. Live'!CW18-'check-Jul25'!CW18)
J19: =IF('1. Live'!J19='check-Jul25'!J19,"",'1. Live'!J19-'check-Jul25'!J19) | K19: =IF('1. Live'!K19='check-Jul25'!K19,"",'1. Live'!K19-'check-Jul25'!K19) | L19: =IF('1. Live'!L19='check-Jul25'!L19,"",'1. Live'!L19-'check-Jul25'!L19) | M19: =IF('1. Live'!M19='check-Jul25'!M19,"",'1. Live'!M19-'check-Jul25'!M19) | N19: =IF('1. Live'!N19='check-Jul25'!N19,"",'1. Live'!N19-'check-Jul25'!N19) | O19: =IF('1. Live'!O19='check-Jul25'!O19,"",'1. Live'!O19-'check-Jul25'!O19) | P19: =IF('1. Live'!P19='check-Jul25'!P19,"",'1. Live'!P19-'check-Jul25'!P19) | Q19: =IF('1. Live'!Q19='check-Jul25'!Q19,"",'1. Live'!Q19-'check-Jul25'!Q19) | ... CW19: =IF('1. Live'!CW19='check-Jul25'!CW19,"",'1. Live'!CW19-'check-Jul25'!CW19)
J20: =IF('1. Live'!J20='check-Jul25'!J20,"",'1. Live'!J20-'check-Jul25'!J20) | K20: =IF('1. Live'!K20='check-Jul25'!K20,"",'1. Live'!K20-'check-Jul25'!K20) | L20: =IF('1. Live'!L20='check-Jul25'!L20,"",'1. Live'!L20-'check-Jul25'!L20) | M20: =IF('1. Live'!M20='check-Jul25'!M20,"",'1. Live'!M20-'check-Jul25'!M20) | N20: =IF('1. Live'!N20='check-Jul25'!N20,"",'1. Live'!N20-'check-Jul25'!N20) | O20: =IF('1. Live'!O20='check-Jul25'!O20,"",'1. Live'!O20-'check-Jul25'!O20) -> -20.037019 | P20: =IF('1. Live'!P20='check-Jul25'!P20,"",'1. Live'!P20-'check-Jul25'!P20) -> -20.037019 | Q20: =IF('1. Live'!Q20='check-Jul25'!Q20,"",'1. Live'!Q20-'check-Jul25'!Q20) | ... CW20: =IF('1. Live'!CW20='check-Jul25'!CW20,"",'1. Live'!CW20-'check-Jul25'!CW20)
J21: =IF('1. Live'!J21='check-Jul25'!J21,"",'1. Live'!J21-'check-Jul25'!J21) | K21: =IF('1. Live'!K21='check-Jul25'!K21,"",'1. Live'!K21-'check-Jul25'!K21) | L21: =IF('1. Live'!L21='check-Jul25'!L21,"",'1. Live'!L21-'check-Jul25'!L21) | M21: =IF('1. Live'!M21='check-Jul25'!M21,"",'1. Live'!M21-'check-Jul25'!M21) | N21: =IF('1. Live'!N21='check-Jul25'!N21,"",'1. Live'!N21-'check-Jul25'!N21) | O21: =IF('1. Live'!O21='check-Jul25'!O21,"",'1. Live'!O21-'check-Jul25'!O21) | P21: =IF('1. Live'!P21='check-Jul25'!P21,"",'1. Live'!P21-'check-Jul25'!P21) | Q21: =IF('1. Live'!Q21='check-Jul25'!Q21,"",'1. Live'!Q21-'check-Jul25'!Q21) | ... CW21: =IF('1. Live'!CW21='check-Jul25'!CW21,"",'1. Live'!CW21-'check-Jul25'!CW21)
C22: G42 Investments AI Holding RSC Ltd | J22: =IF('1. Live'!J22='check-Jul25'!J22,"",'1. Live'!J22-'check-Jul25'!J22) | K22: =IF('1. Live'!K22='check-Jul25'!K22,"",'1. Live'!K22-'check-Jul25'!K22) | L22: =IF('1. Live'!L22='check-Jul25'!L22,"",'1. Live'!L22-'check-Jul25'!L22) | M22: =IF('1. Live'!M22='check-Jul25'!M22,"",'1. Live'!M22-'check-Jul25'!M22) | N22: =IF('1. Live'!N22='check-Jul25'!N22,"",'1. Live'!N22-'check-Jul25'!N22) | O22: =IF('1. Live'!O22='check-Jul25'!O22,"",'1. Live'!O22-'check-Jul25'!O22) | P22: =IF('1. Live'!P22='check-Jul25'!P22,"",'1. Live'!P22-'check-Jul25'!P22) | Q22: =IF('1. Live'!Q22='check-Jul25'!Q22,"",'1. Live'!Q22-'check-Jul25'!Q22) | ... CW22: =IF('1. Live'!CW22='check-Jul25'!CW22,"",'1. Live'!CW22-'check-Jul25'!CW22)
C23: DriveNets | D23: Direct Investment | E23: Partially Realized | F23: 0 | G23: G42 Investments | H23: 2022 | I23: Equity-TBC | J23: =IF('1. Live'!J23='check-Jul25'!J23,"",'1. Live'!J23-'check-Jul25'!J23) | K23: =IF('1. Live'!K23='check-Jul25'!K23,"",'1. Live'!K23-'check-Jul25'!K23) | L23: =IF('1. Live'!L23='check-Jul25'!L23,"",'1. Live'!L23-'check-Jul25'!L23) | M23: =IF('1. Live'!M23='check-Jul25'!M23,"",'1. Live'!M23-'check-Jul25'!M23) | N23: =IF('1. Live'!N23='check-Jul25'!N23,"",'1. Live'!N23-'check-Jul25'!N23) | O23: =IF('1. Live'!O23='check-Jul25'!O23,"",'1. Live'!O23-'check-Jul25'!O23) | P23: =IF('1. Live'!P23='check-Jul25'!P23,"",'1. Live'!P23-'check-Jul25'!P23) | Q23: =IF('1. Live'!Q23='check-Jul25'!Q23,"",'1. Live'!Q23-'check-Jul25'!Q23) | ... CW23: =IF('1. Live'!CW23='check-Jul25'!CW23,"",'1. Live'!CW23-'check-Jul25'!CW23)
C24: vTv Therapeutics Inc. | D24: Direct Investment | E24: Unrealized | F24: 0 | G24: G42 Investments | H24: 2022 | I24: Ordinary Shares | J24: =IF('1. Live'!J24='check-Jul25'!J24,"",'1. Live'!J24-'check-Jul25'!J24) | K24: =IF('1. Live'!K24='check-Jul25'!K24,"",'1. Live'!K24-'check-Jul25'!K24) | L24: =IF('1. Live'!L24='check-Jul25'!L24,"",'1. Live'!L24-'check-Jul25'!L24) | M24: =IF('1. Live'!M24='check-Jul25'!M24,"",'1. Live'!M24-'check-Jul25'!M24) | N24: =IF('1. Live'!N24='check-Jul25'!N24,"",'1. Live'!N24-'check-Jul25'!N24) | O24: =IF('1. Live'!O24='check-Jul25'!O24,"",'1. Live'!O24-'check-Jul25'!O24) -> 0.06491425 | P24: =IF('1. Live'!P24='check-Jul25'!P24,"",'1. Live'!P24-'check-Jul25'!P24) -> 0.06491425 | Q24: =IF('1. Live'!Q24='check-Jul25'!Q24,"",'1. Live'!Q24-'check-Jul25'!Q24) | ... CW24: =IF('1. Live'!CW24='check-Jul25'!CW24,"",'1. Live'!CW24-'check-Jul25'!CW24)
C25: North Summit Capital Fund | D25: Fund Investment | E25: Unrealized | F25: 0 | G25: G42 Investments | H25: 2020 | I25: LP | J25: =IF('1. Live'!J25='check-Jul25'!J25,"",'1. Live'!J25-'check-Jul25'!J25) | K25: =IF('1. Live'!K25='check-Jul25'!K25,"",'1. Live'!K25-'check-Jul25'!K25) -> -0.36 | L25: =IF('1. Live'!L25='check-Jul25'!L25,"",'1. Live'!L25-'check-Jul25'!L25) | M25: =IF('1. Live'!M25='check-Jul25'!M25,"",'1. Live'!M25-'check-Jul25'!M25) -> -0.36 | N25: =IF('1. Live'!N25='check-Jul25'!N25,"",'1. Live'!N25-'check-Jul25'!N25) | O25: =IF('1. Live'!O25='check-Jul25'!O25,"",'1. Live'!O25-'check-Jul25'!O25) -> 4.806498 | P25: =IF('1. Live'!P25='check-Jul25'!P25,"",'1. Live'!P25-'check-Jul25'!P25) -> 4.806498 | Q25: =IF('1. Live'!Q25='check-Jul25'!Q25,"",'1. Live'!Q25-'check-Jul25'!Q25) | ... CW25: =IF('1. Live'!CW25='check-Jul25'!CW25,"",'1. Live'!CW25-'check-Jul25'!CW25)
C26: New Space Capital Fund I | D26: Fund Investment | E26: Unrealized | F26: 0 | G26: G42 Investments | H26: 2020 | I26: LP | J26: =IF('1. Live'!J26='check-Jul25'!J26,"",'1. Live'!J26-'check-Jul25'!J26) | K26: =IF('1. Live'!K26='check-Jul25'!K26,"",'1. Live'!K26-'check-Jul25'!K26) -> 0.24292229 | L26: =IF('1. Live'!L26='check-Jul25'!L26,"",'1. Live'!L26-'check-Jul25'!L26) | M26: =IF('1. Live'!M26='check-Jul25'!M26,"",'1. Live'!M26-'check-Jul25'!M26) -> 0.24292229 | N26: =IF('1. Live'!N26='check-Jul25'!N26,"",'1. Live'!N26-'check-Jul25'!N26) | O26: =IF('1. Live'!O26='check-Jul25'!O26,"",'1. Live'!O26-'check-Jul25'!O26) -> 0.96040918 | P26: =IF('1. Live'!P26='check-Jul25'!P26,"",'1. Live'!P26-'check-Jul25'!P26) -> 0.96040918 | Q26: =IF('1. Live'!Q26='check-Jul25'!Q26,"",'1. Live'!Q26-'check-Jul25'!Q26) | ... CW26: =IF('1. Live'!CW26='check-Jul25'!CW26,"",'1. Live'!CW26-'check-Jul25'!CW26)
C27: New Space Capital GP Com SCSp | D27: Fund Investment | E27: Unrealized | F27: 0 | G27: G42 Investments | H27: 2023 | I27: LP | J27: =IF('1. Live'!J27='check-Jul25'!J27,"",'1. Live'!J27-'check-Jul25'!J27) | K27: =IF('1. Live'!K27='check-Jul25'!K27,"",'1. Live'!K27-'check-Jul25'!K27) | L27: =IF('1. Live'!L27='check-Jul25'!L27,"",'1. Live'!L27-'check-Jul25'!L27) | M27: =IF('1. Live'!M27='check-Jul25'!M27,"",'1. Live'!M27-'check-Jul25'!M27) | N27: =IF('1. Live'!N27='check-Jul25'!N27,"",'1. Live'!N27-'check-Jul25'!N27) | O27: =IF('1. Live'!O27='check-Jul25'!O27,"",'1. Live'!O27-'check-Jul25'!O27) -> 0.13599959 | P27: =IF('1. Live'!P27='check-Jul25'!P27,"",'1. Live'!P27-'check-Jul25'!P27) -> 0.13599959 | Q27: =IF('1. Live'!Q27='check-Jul25'!Q27,"",'1. Live'!Q27-'check-Jul25'!Q27) | ... CW27: =IF('1. Live'!CW27='check-Jul25'!CW27,"",'1. Live'!CW27-'check-Jul25'!CW27)
C28: Acies Investments Fund I, L.P. | D28: Fund Investment | E28: Unrealized | F28: 0 | G28: G42 Investments | H28: 2021 | I28: LP | J28: =IF('1. Live'!J28='check-Jul25'!J28,"",'1. Live'!J28-'check-Jul25'!J28) | K28: =IF('1. Live'!K28='check-Jul25'!K28,"",'1. Live'!K28-'check-Jul25'!K28) | L28: =IF('1. Live'!L28='check-Jul25'!L28,"",'1. Live'!L28-'check-Jul25'!L28) | M28: =IF('1. Live'!M28='check-Jul25'!M28,"",'1. Live'!M28-'check-Jul25'!M28) | N28: =IF('1. Live'!N28='check-Jul25'!N28,"",'1. Live'!N28-'check-Jul25'!N28) | O28: =IF('1. Live'!O28='check-Jul25'!O28,"",'1. Live'!O28-'check-Jul25'!O28) -> 0.182845 | P28: =IF('1. Live'!P28='check-Jul25'!P28,"",'1. Live'!P28-'check-Jul25'!P28) -> 0.182845 | Q28: =IF('1. Live'!Q28='check-Jul25'!Q28,"",'1. Live'!Q28-'check-Jul25'!Q28) | ... CW28: =IF('1. Live'!CW28='check-Jul25'!CW28,"",'1. Live'!CW28-'check-Jul25'!CW28)
J29: =IF('1. Live'!J29='check-Jul25'!J29,"",'1. Live'!J29-'check-Jul25'!J29) | K29: =IF('1. Live'!K29='check-Jul25'!K29,"",'1. Live'!K29-'check-Jul25'!K29) | L29: =IF('1. Live'!L29='check-Jul25'!L29,"",'1. Live'!L29-'check-Jul25'!L29) | M29: =IF('1. Live'!M29='check-Jul25'!M29,"",'1. Live'!M29-'check-Jul25'!M29) | N29: =IF('1. Live'!N29='check-Jul25'!N29,"",'1. Live'!N29-'check-Jul25'!N29) | O29: =IF('1. Live'!O29='check-Jul25'!O29,"",'1. Live'!O29-'check-Jul25'!O29) | P29: =IF('1. Live'!P29='check-Jul25'!P29,"",'1. Live'!P29-'check-Jul25'!P29) | Q29: =IF('1. Live'!Q29='check-Jul25'!Q29,"",'1. Live'!Q29-'check-Jul25'!Q29) | ... CW29: =IF('1. Live'!CW29='check-Jul25'!CW29,"",'1. Live'!CW29-'check-Jul25'!CW29)
J30: =IF('1. Live'!J30='check-Jul25'!J30,"",'1. Live'!J30-'check-Jul25'!J30) | K30: =IF('1. Live'!K30='check-Jul25'!K30,"",'1. Live'!K30-'check-Jul25'!K30) -> -0.11707771 | L30: =IF('1. Live'!L30='check-Jul25'!L30,"",'1. Live'!L30-'check-Jul25'!L30) | M30: =IF('1. Live'!M30='check-Jul25'!M30,"",'1. Live'!M30-'check-Jul25'!M30) -> -0.11707771 | N30: =IF('1. Live'!N30='check-Jul25'!N30,"",'1. Live'!N30-'check-Jul25'!N30) | O30: =IF('1. Live'!O30='check-Jul25'!O30,"",'1. Live'!O30-'check-Jul25'!O30) -> 6.150666 | P30: =IF('1. Live'!P30='check-Jul25'!P30,"",'1. Live'!P30-'check-Jul25'!P30) -> 6.150666 | Q30: =IF('1. Live'!Q30='check-Jul25'!Q30,"",'1. Live'!Q30-'check-Jul25'!Q30) | ... CW30: =IF('1. Live'!CW30='check-Jul25'!CW30,"",'1. Live'!CW30-'check-Jul25'!CW30)
J31: =IF('1. Live'!J31='check-Jul25'!J31,"",'1. Live'!J31-'check-Jul25'!J31) | K31: =IF('1. Live'!K31='check-Jul25'!K31,"",'1. Live'!K31-'check-Jul25'!K31) | L31: =IF('1. Live'!L31='check-Jul25'!L31,"",'1. Live'!L31-'check-Jul25'!L31) | M31: =IF('1. Live'!M31='check-Jul25'!M31,"",'1. Live'!M31-'check-Jul25'!M31) | N31: =IF('1. Live'!N31='check-Jul25'!N31,"",'1. Live'!N31-'check-Jul25'!N31) | O31: =IF('1. Live'!O31='check-Jul25'!O31,"",'1. Live'!O31-'check-Jul25'!O31) | P31: =IF('1. Live'!P31='check-Jul25'!P31,"",'1. Live'!P31-'check-Jul25'!P31) | Q31: =IF('1. Live'!Q31='check-Jul25'!Q31,"",'1. Live'!Q31-'check-Jul25'!Q31) | ... CW31: =IF('1. Live'!CW31='check-Jul25'!CW31,"",'1. Live'!CW31-'check-Jul25'!CW31)
C32: G42 Capital SPV RSC Ltd | J32: =IF('1. Live'!J32='check-Jul25'!J32,"",'1. Live'!J32-'check-Jul25'!J32) | K32: =IF('1. Live'!K32='check-Jul25'!K32,"",'1. Live'!K32-'check-Jul25'!K32) | L32: =IF('1. Live'!L32='check-Jul25'!L32,"",'1. Live'!L32-'check-Jul25'!L32) | M32: =IF('1. Live'!M32='check-Jul25'!M32,"",'1. Live'!M32-'check-Jul25'!M32) | N32: =IF('1. Live'!N32='check-Jul25'!N32,"",'1. Live'!N32-'check-Jul25'!N32) | O32: =IF('1. Live'!O32='check-Jul25'!O32,"",'1. Live'!O32-'check-Jul25'!O32) | P32: =IF('1. Live'!P32='check-Jul25'!P32,"",'1. Live'!P32-'check-Jul25'!P32) | Q32: =IF('1. Live'!Q32='check-Jul25'!Q32,"",'1. Live'!Q32-'check-Jul25'!Q32) | ... CW32: =IF('1. Live'!CW32='check-Jul25'!CW32,"",'1. Live'!CW32-'check-Jul25'!CW32)
C33: Life Biosciences LLC | D33: Direct Investment | E33: Unrealized | F33: 0 | G33: G42 Capital | H33: 2024 | I33: D Prefs | J33: =IF('1. Live'!J33='check-Jul25'!J33,"",'1. Live'!J33-'check-Jul25'!J33) | K33: =IF('1. Live'!K33='check-Jul25'!K33,"",'1. Live'!K33-'check-Jul25'!K33) | L33: =IF('1. Live'!L33='check-Jul25'!L33,"",'1. Live'!L33-'check-Jul25'!L33) | M33: =IF('1. Live'!M33='check-Jul25'!M33,"",'1. Live'!M33-'check-Jul25'!M33) | N33: =IF('1. Live'!N33='check-Jul25'!N33,"",'1. Live'!N33-'check-Jul25'!N33) | O33: =IF('1. Live'!O33='check-Jul25'!O33,"",'1. Live'!O33-'check-Jul25'!O33) | P33: =IF('1. Live'!P33='check-Jul25'!P33,"",'1. Live'!P33-'check-Jul25'!P33) | Q33: =IF('1. Live'!Q33='check-Jul25'!Q33,"",'1. Live'!Q33-'check-Jul25'!Q33) | ... CW33: =IF('1. Live'!CW33='check-Jul25'!CW33,"",'1. Live'!CW33-'check-Jul25'!CW33)
C34: Cerebras Systems Inc F1 | D34: Direct Investment | E34: Not Completed | F34: 0 | G34: G42 Capital | H34: 2025 | I34: Series F-1 | J34: =IF('1. Live'!J34='check-Jul25'!J34,"",'1. Live'!J34-'check-Jul25'!J34) | K34: =IF('1. Live'!K34='check-Jul25'!K34,"",'1. Live'!K34-'check-Jul25'!K34) | L34: =IF('1. Live'!L34='check-Jul25'!L34,"",'1. Live'!L34-'check-Jul25'!L34) | M34: =IF('1. Live'!M34='check-Jul25'!M34,"",'1. Live'!M34-'check-Jul25'!M34) | N34: =IF('1. Live'!N34='check-Jul25'!N34,"",'1. Live'!N34-'check-Jul25'!N34) | O34: =IF('1. Live'!O34='check-Jul25'!O34,"",'1. Live'!O34-'check-Jul25'!O34) | P34: =IF('1. Live'!P34='check-Jul25'!P34,"",'1. Live'!P34-'check-Jul25'!P34) | Q34: =IF('1. Live'!Q34='check-Jul25'!Q34,"",'1. Live'!Q34-'check-Jul25'!Q34) | ... CW34: =IF('1. Live'!CW34='check-Jul25'!CW34,"",'1. Live'!CW34-'check-Jul25'!CW34)
C35: Verses AI Inc | D35: Direct Investment | E35: Unrealized | F35: 0 | G35: G42 Capital | H35: 2024 | J35: =IF('1. Live'!J35='check-Jul25'!J35,"",'1. Live'!J35-'check-Jul25'!J35) -> -0.013461781 | K35: =IF('1. Live'!K35='check-Jul25'!K35,"",'1. Live'!K35-'check-Jul25'!K35) | L35: =IF('1. Live'!L35='check-Jul25'!L35,"",'1. Live'!L35-'check-Jul25'!L35) | M35: =IF('1. Live'!M35='check-Jul25'!M35,"",'1. Live'!M35-'check-Jul25'!M35) | N35: =IF('1. Live'!N35='check-Jul25'!N35,"",'1. Live'!N35-'check-Jul25'!N35) | O35: =IF('1. Live'!O35='check-Jul25'!O35,"",'1. Live'!O35-'check-Jul25'!O35) -> -0.17394272 | P35: =IF('1. Live'!P35='check-Jul25'!P35,"",'1. Live'!P35-'check-Jul25'!P35) -> -0.17394272 | Q35: =IF('1. Live'!Q35='check-Jul25'!Q35,"",'1. Live'!Q35-'check-Jul25'!Q35) | ... CW35: =IF('1. Live'!CW35='check-Jul25'!CW35,"",'1. Live'!CW35-'check-Jul25'!CW35)
C36: Inveniam Ltd | D36: Direct Investment | E36: Unrealized | F36: 0 | G36: G42 Capital | H36: 2024 | I36: SAR | J36: =IF('1. Live'!J36='check-Jul25'!J36,"",'1. Live'!J36-'check-Jul25'!J36) | K36: =IF('1. Live'!K36='check-Jul25'!K36,"",'1. Live'!K36-'check-Jul25'!K36) | L36: =IF('1. Live'!L36='check-Jul25'!L36,"",'1. Live'!L36-'check-Jul25'!L36) | M36: =IF('1. Live'!M36='check-Jul25'!M36,"",'1. Live'!M36-'check-Jul25'!M36) | N36: =IF('1. Live'!N36='check-Jul25'!N36,"",'1. Live'!N36-'check-Jul25'!N36) | O36: =IF('1. Live'!O36='check-Jul25'!O36,"",'1. Live'!O36-'check-Jul25'!O36) | P36: =IF('1. Live'!P36='check-Jul25'!P36,"",'1. Live'!P36-'check-Jul25'!P36) | Q36: =IF('1. Live'!Q36='check-Jul25'!Q36,"",'1. Live'!Q36-'check-Jul25'!Q36) | ... CW36: =IF('1. Live'!CW36='check-Jul25'!CW36,"",'1. Live'!CW36-'check-Jul25'!CW36)
C37: Liquid AI | D37: Direct Investment | E37: Unrealized | F37: 0 | G37: G42 Capital | H37: 2024 | I37: Series A | J37: =IF('1. Live'!J37='check-Jul25'!J37,"",'1. Live'!J37-'check-Jul25'!J37) -> #VALUE! | K37: =IF('1. Live'!K37='check-Jul25'!K37,"",'1. Live'!K37-'check-Jul25'!K37) | L37: =IF('1. Live'!L37='check-Jul25'!L37,"",'1. Live'!L37-'check-Jul25'!L37) | M37: =IF('1. Live'!M37='check-Jul25'!M37,"",'1. Live'!M37-'check-Jul25'!M37) | N37: =IF('1. Live'!N37='check-Jul25'!N37,"",'1. Live'!N37-'check-Jul25'!N37) | O37: =IF('1. Live'!O37='check-Jul25'!O37,"",'1. Live'!O37-'check-Jul25'!O37) | P37: =IF('1. Live'!P37='check-Jul25'!P37,"",'1. Live'!P37-'check-Jul25'!P37) | Q37: =IF('1. Live'!Q37='check-Jul25'!Q37,"",'1. Live'!Q37-'check-Jul25'!Q37) | ... CW37: =IF('1. Live'!CW37='check-Jul25'!CW37,"",'1. Live'!CW37-'check-Jul25'!CW37)
C38: Neuralink | D38: Direct Investment | E38: Unrealized | F38: 0 | G38: G42 Capital | H38: 2025 | I38: Series E | J38: =IF('1. Live'!J38='check-Jul25'!J38,"",'1. Live'!J38-'check-Jul25'!J38) | K38: =IF('1. Live'!K38='check-Jul25'!K38,"",'1. Live'!K38-'check-Jul25'!K38) | L38: =IF('1. Live'!L38='check-Jul25'!L38,"",'1. Live'!L38-'check-Jul25'!L38) | M38: =IF('1. Live'!M38='check-Jul25'!M38,"",'1. Live'!M38-'check-Jul25'!M38) | N38: =IF('1. Live'!N38='check-Jul25'!N38,"",'1. Live'!N38-'check-Jul25'!N38) | O38: =IF('1. Live'!O38='check-Jul25'!O38,"",'1. Live'!O38-'check-Jul25'!O38) | P38: =IF('1. Live'!P38='check-Jul25'!P38,"",'1. Live'!P38-'check-Jul25'!P38) | Q38: =IF('1. Live'!Q38='check-Jul25'!Q38,"",'1. Live'!Q38-'check-Jul25'!Q38) | ... CW38: =IF('1. Live'!CW38='check-Jul25'!CW38,"",'1. Live'!CW38-'check-Jul25'!CW38)
J39: =IF('1. Live'!J39='check-Jul25'!J39,"",'1. Live'!J39-'check-Jul25'!J39) | K39: =IF('1. Live'!K39='check-Jul25'!K39,"",'1. Live'!K39-'check-Jul25'!K39) | L39: =IF('1. Live'!L39='check-Jul25'!L39,"",'1. Live'!L39-'check-Jul25'!L39) | M39: =IF('1. Live'!M39='check-Jul25'!M39,"",'1. Live'!M39-'check-Jul25'!M39) | N39: =IF('1. Live'!N39='check-Jul25'!N39,"",'1. Live'!N39-'check-Jul25'!N39) | O39: =IF('1. Live'!O39='check-Jul25'!O39,"",'1. Live'!O39-'check-Jul25'!O39) | P39: =IF('1. Live'!P39='check-Jul25'!P39,"",'1. Live'!P39-'check-Jul25'!P39) | Q39: =IF('1. Live'!Q39='check-Jul25'!Q39,"",'1. Live'!Q39-'check-Jul25'!Q39) | ... CW39: =IF('1. Live'!CW39='check-Jul25'!CW39,"",'1. Live'!CW39-'check-Jul25'!CW39)
J40: =IF('1. Live'!J40='check-Jul25'!J40,"",'1. Live'!J40-'check-Jul25'!J40) | K40: =IF('1. Live'!K40='check-Jul25'!K40,"",'1. Live'!K40-'check-Jul25'!K40) | L40: =IF('1. Live'!L40='check-Jul25'!L40,"",'1. Live'!L40-'check-Jul25'!L40) | M40: =IF('1. Live'!M40='check-Jul25'!M40,"",'1. Live'!M40-'check-Jul25'!M40) | N40: =IF('1. Live'!N40='check-Jul25'!N40,"",'1. Live'!N40-'check-Jul25'!N40) | O40: =IF('1. Live'!O40='check-Jul25'!O40,"",'1. Live'!O40-'check-Jul25'!O40) -> -0.17394272 | P40: =IF('1. Live'!P40='check-Jul25'!P40,"",'1. Live'!P40-'check-Jul25'!P40) -> -0.17394272 | Q40: =IF('1. Live'!Q40='check-Jul25'!Q40,"",'1. Live'!Q40-'check-Jul25'!Q40) | ... CW40: =IF('1. Live'!CW40='check-Jul25'!CW40,"",'1. Live'!CW40-'check-Jul25'!CW40)
J41: =IF('1. Live'!J41='check-Jul25'!J41,"",'1. Live'!J41-'check-Jul25'!J41) | K41: =IF('1. Live'!K41='check-Jul25'!K41,"",'1. Live'!K41-'check-Jul25'!K41) | L41: =IF('1. Live'!L41='check-Jul25'!L41,"",'1. Live'!L41-'check-Jul25'!L41) | M41: =IF('1. Live'!M41='check-Jul25'!M41,"",'1. Live'!M41-'check-Jul25'!M41) | N41: =IF('1. Live'!N41='check-Jul25'!N41,"",'1. Live'!N41-'check-Jul25'!N41) | O41: =IF('1. Live'!O41='check-Jul25'!O41,"",'1. Live'!O41-'check-Jul25'!O41) | P41: =IF('1. Live'!P41='check-Jul25'!P41,"",'1. Live'!P41-'check-Jul25'!P41) | Q41: =IF('1. Live'!Q41='check-Jul25'!Q41,"",'1. Live'!Q41-'check-Jul25'!Q41) | ... CW41: =IF('1. Live'!CW41='check-Jul25'!CW41,"",'1. Live'!CW41-'check-Jul25'!CW41)
C42: Core42 Holding RSC Ltd | J42: =IF('1. Live'!J42='check-Jul25'!J42,"",'1. Live'!J42-'check-Jul25'!J42) | K42: =IF('1. Live'!K42='check-Jul25'!K42,"",'1. Live'!K42-'check-Jul25'!K42) | L42: =IF('1. Live'!L42='check-Jul25'!L42,"",'1. Live'!L42-'check-Jul25'!L42) | M42: =IF('1. Live'!M42='check-Jul25'!M42,"",'1. Live'!M42-'check-Jul25'!M42) | N42: =IF('1. Live'!N42='check-Jul25'!N42,"",'1. Live'!N42-'check-Jul25'!N42) | O42: =IF('1. Live'!O42='check-Jul25'!O42,"",'1. Live'!O42-'check-Jul25'!O42) | P42: =IF('1. Live'!P42='check-Jul25'!P42,"",'1. Live'!P42-'check-Jul25'!P42) | Q42: =IF('1. Live'!Q42='check-Jul25'!Q42,"",'1. Live'!Q42-'check-Jul25'!Q42) | ... CW42: =IF('1. Live'!CW42='check-Jul25'!CW42,"",'1. Live'!CW42-'check-Jul25'!CW42)
C43: School Hack (AIREV Holding Limited) | D43: Direct Investment | E43: Unrealized | F43: 0 | G43: Core42 5 | H43: 2024 | I43: Preferred Shares | J43: =IF('1. Live'!J43='check-Jul25'!J43,"",'1. Live'!J43-'check-Jul25'!J43) | K43: =IF('1. Live'!K43='check-Jul25'!K43,"",'1. Live'!K43-'check-Jul25'!K43) | L43: =IF('1. Live'!L43='check-Jul25'!L43,"",'1. Live'!L43-'check-Jul25'!L43) | M43: =IF('1. Live'!M43='check-Jul25'!M43,"",'1. Live'!M43-'check-Jul25'!M43) | N43: =IF('1. Live'!N43='check-Jul25'!N43,"",'1. Live'!N43-'check-Jul25'!N43) | O43: =IF('1. Live'!O43='check-Jul25'!O43,"",'1. Live'!O43-'check-Jul25'!O43) | P43: =IF('1. Live'!P43='check-Jul25'!P43,"",'1. Live'!P43-'check-Jul25'!P43) | Q43: =IF('1. Live'!Q43='check-Jul25'!Q43,"",'1. Live'!Q43-'check-Jul25'!Q43) | ... CW43: =IF('1. Live'!CW43='check-Jul25'!CW43,"",'1. Live'!CW43-'check-Jul25'!CW43)
J44: =IF('1. Live'!J44='check-Jul25'!J44,"",'1. Live'!J44-'check-Jul25'!J44) | K44: =IF('1. Live'!K44='check-Jul25'!K44,"",'1. Live'!K44-'check-Jul25'!K44) | L44: =IF('1. Live'!L44='check-Jul25'!L44,"",'1. Live'!L44-'check-Jul25'!L44) | M44: =IF('1. Live'!M44='check-Jul25'!M44,"",'1. Live'!M44-'check-Jul25'!M44) | N44: =IF('1. Live'!N44='check-Jul25'!N44,"",'1. Live'!N44-'check-Jul25'!N44) | O44: =IF('1. Live'!O44='check-Jul25'!O44,"",'1. Live'!O44-'check-Jul25'!O44) | P44: =IF('1. Live'!P44='check-Jul25'!P44,"",'1. Live'!P44-'check-Jul25'!P44) | Q44: =IF('1. Live'!Q44='check-Jul25'!Q44,"",'1. Live'!Q44-'check-Jul25'!Q44) | ... CW44: =IF('1. Live'!CW44='check-Jul25'!CW44,"",'1. Live'!CW44-'check-Jul25'!CW44)
J45: =IF('1. Live'!J45='check-Jul25'!J45,"",'1. Live'!J45-'check-Jul25'!J45) | K45: =IF('1. Live'!K45='check-Jul25'!K45,"",'1. Live'!K45-'check-Jul25'!K45) | L45: =IF('1. Live'!L45='check-Jul25'!L45,"",'1. Live'!L45-'check-Jul25'!L45) | M45: =IF('1. Live'!M45='check-Jul25'!M45,"",'1. Live'!M45-'check-Jul25'!M45) | N45: =IF('1. Live'!N45='check-Jul25'!N45,"",'1. Live'!N45-'check-Jul25'!N45) | O45: =IF('1. Live'!O45='check-Jul25'!O45,"",'1. Live'!O45-'check-Jul25'!O45) | P45: =IF('1. Live'!P45='check-Jul25'!P45,"",'1. Live'!P45-'check-Jul25'!P45) | Q45: =IF('1. Live'!Q45='check-Jul25'!Q45,"",'1. Live'!Q45-'check-Jul25'!Q45) | ... CW45: =IF('1. Live'!CW45='check-Jul25'!CW45,"",'1. Live'!CW45-'check-Jul25'!CW45)
J46: =IF('1. Live'!J46='check-Jul25'!J46,"",'1. Live'!J46-'check-Jul25'!J46) | K46: =IF('1. Live'!K46='check-Jul25'!K46,"",'1. Live'!K46-'check-Jul25'!K46) | L46: =IF('1. Live'!L46='check-Jul25'!L46,"",'1. Live'!L46-'check-Jul25'!L46) | M46: =IF('1. Live'!M46='check-Jul25'!M46,"",'1. Live'!M46-'check-Jul25'!M46) | N46: =IF('1. Live'!N46='check-Jul25'!N46,"",'1. Live'!N46-'check-Jul25'!N46) | O46: =IF('1. Live'!O46='check-Jul25'!O46,"",'1. Live'!O46-'check-Jul25'!O46) | P46: =IF('1. Live'!P46='check-Jul25'!P46,"",'1. Live'!P46-'check-Jul25'!P46) | Q46: =IF('1. Live'!Q46='check-Jul25'!Q46,"",'1. Live'!Q46-'check-Jul25'!Q46) | ... CW46: =IF('1. Live'!CW46='check-Jul25'!CW46,"",'1. Live'!CW46-'check-Jul25'!CW46)
C47: GX Investments Ltd : MGX and Related Investments | J47: =IF('1. Live'!J47='check-Jul25'!J47,"",'1. Live'!J47-'check-Jul25'!J47) | K47: =IF('1. Live'!K47='check-Jul25'!K47,"",'1. Live'!K47-'check-Jul25'!K47) | L47: =IF('1. Live'!L47='check-Jul25'!L47,"",'1. Live'!L47-'check-Jul25'!L47) | M47: =IF('1. Live'!M47='check-Jul25'!M47,"",'1. Live'!M47-'check-Jul25'!M47) | N47: =IF('1. Live'!N47='check-Jul25'!N47,"",'1. Live'!N47-'check-Jul25'!N47) | O47: =IF('1. Live'!O47='check-Jul25'!O47,"",'1. Live'!O47-'check-Jul25'!O47) | P47: =IF('1. Live'!P47='check-Jul25'!P47,"",'1. Live'!P47-'check-Jul25'!P47) | Q47: =IF('1. Live'!Q47='check-Jul25'!Q47,"",'1. Live'!Q47-'check-Jul25'!Q47) | ... CW47: =IF('1. Live'!CW47='check-Jul25'!CW47,"",'1. Live'!CW47-'check-Jul25'!CW47)
C48: MGX I LP | D48: MGX LP | E48: Unrealized | F48: 0 | G48: G42 Holding | H48: 2024 | I48: LP | J48: =IF('1. Live'!J48='check-Jul25'!J48,"",'1. Live'!J48-'check-Jul25'!J48) -> -0.030435164 | K48: =IF('1. Live'!K48='check-Jul25'!K48,"",'1. Live'!K48-'check-Jul25'!K48) | L48: =IF('1. Live'!L48='check-Jul25'!L48,"",'1. Live'!L48-'check-Jul25'!L48) -> 46.002085 | M48: =IF('1. Live'!M48='check-Jul25'!M48,"",'1. Live'!M48-'check-Jul25'!M48) -> -46.002085 | N48: =IF('1. Live'!N48='check-Jul25'!N48,"",'1. Live'!N48-'check-Jul25'!N48) | O48: =IF('1. Live'!O48='check-Jul25'!O48,"",'1. Live'!O48-'check-Jul25'!O48) -> 126.75813 | P48: =IF('1. Live'!P48='check-Jul25'!P48,"",'1. Live'!P48-'check-Jul25'!P48) -> 80.75605 | Q48: =IF('1. Live'!Q48='check-Jul25'!Q48,"",'1. Live'!Q48-'check-Jul25'!Q48) | ... CW48: =IF('1. Live'!CW48='check-Jul25'!CW48,"",'1. Live'!CW48-'check-Jul25'!CW48)
C49: MGX 1 Strategic Co-invest | D49: MGX Co-Invest LP | E49: Unrealized | F49: 0 | G49: G42 Holding | H49: 2024 | I49: LP | J49: =IF('1. Live'!J49='check-Jul25'!J49,"",'1. Live'!J49-'check-Jul25'!J49) | K49: =IF('1. Live'!K49='check-Jul25'!K49,"",'1. Live'!K49-'check-Jul25'!K49) | L49: =IF('1. Live'!L49='check-Jul25'!L49,"",'1. Live'!L49-'check-Jul25'!L49) | M49: =IF('1. Live'!M49='check-Jul25'!M49,"",'1. Live'!M49-'check-Jul25'!M49) | N49: =IF('1. Live'!N49='check-Jul25'!N49,"",'1. Live'!N49-'check-Jul25'!N49) | O49: =IF('1. Live'!O49='check-Jul25'!O49,"",'1. Live'!O49-'check-Jul25'!O49) -> 24.402394 | P49: =IF('1. Live'!P49='check-Jul25'!P49,"",'1. Live'!P49-'check-Jul25'!P49) -> 24.402394 | Q49: =IF('1. Live'!Q49='check-Jul25'!Q49,"",'1. Live'!Q49-'check-Jul25'!Q49) | ... CW49: =IF('1. Live'!CW49='check-Jul25'!CW49,"",'1. Live'!CW49-'check-Jul25'!CW49)
C50: MGX Group Holding 1 Ltd (GP) | D50: MGX GP | E50: Unrealized | F50: 0 | G50: G42 Holding | H50: 2024 | I50: Equity | J50: =IF('1. Live'!J50='check-Jul25'!J50,"",'1. Live'!J50-'check-Jul25'!J50) | K50: =IF('1. Live'!K50='check-Jul25'!K50,"",'1. Live'!K50-'check-Jul25'!K50) | L50: =IF('1. Live'!L50='check-Jul25'!L50,"",'1. Live'!L50-'check-Jul25'!L50) | M50: =IF('1. Live'!M50='check-Jul25'!M50,"",'1. Live'!M50-'check-Jul25'!M50) | N50: =IF('1. Live'!N50='check-Jul25'!N50,"",'1. Live'!N50-'check-Jul25'!N50) | O50: =IF('1. Live'!O50='check-Jul25'!O50,"",'1. Live'!O50-'check-Jul25'!O50) | P50: =IF('1. Live'!P50='check-Jul25'!P50,"",'1. Live'!P50-'check-Jul25'!P50) | Q50: =IF('1. Live'!Q50='check-Jul25'!Q50,"",'1. Live'!Q50-'check-Jul25'!Q50) | ... CW50: =IF('1. Live'!CW50='check-Jul25'!CW50,"",'1. Live'!CW50-'check-Jul25'!CW50)
J51: =IF('1. Live'!J51='check-Jul25'!J51,"",'1. Live'!J51-'check-Jul25'!J51) | K51: =IF('1. Live'!K51='check-Jul25'!K51,"",'1. Live'!K51-'check-Jul25'!K51) | L51: =IF('1. Live'!L51='check-Jul25'!L51,"",'1. Live'!L51-'check-Jul25'!L51) | M51: =IF('1. Live'!M51='check-Jul25'!M51,"",'1. Live'!M51-'check-Jul25'!M51) | N51: =IF('1. Live'!N51='check-Jul25'!N51,"",'1. Live'!N51-'check-Jul25'!N51) | O51: =IF('1. Live'!O51='check-Jul25'!O51,"",'1. Live'!O51-'check-Jul25'!O51) | P51: =IF('1. Live'!P51='check-Jul25'!P51,"",'1. Live'!P51-'check-Jul25'!P51) | Q51: =IF('1. Live'!Q51='check-Jul25'!Q51,"",'1. Live'!Q51-'check-Jul25'!Q51) | ... CW51: =IF('1. Live'!CW51='check-Jul25'!CW51,"",'1. Live'!CW51-'check-Jul25'!CW51)
J52: =IF('1. Live'!J52='check-Jul25'!J52,"",'1. Live'!J52-'check-Jul25'!J52) | K52: =IF('1. Live'!K52='check-Jul25'!K52,"",'1. Live'!K52-'check-Jul25'!K52) | L52: =IF('1. Live'!L52='check-Jul25'!L52,"",'1. Live'!L52-'check-Jul25'!L52) -> 46.002085 | M52: =IF('1. Live'!M52='check-Jul25'!M52,"",'1. Live'!M52-'check-Jul25'!M52) -> -46.002085 | N52: =IF('1. Live'!N52='check-Jul25'!N52,"",'1. Live'!N52-'check-Jul25'!N52) | O52: =IF('1. Live'!O52='check-Jul25'!O52,"",'1. Live'!O52-'check-Jul25'!O52) -> 151.16053 | P52: =IF('1. Live'!P52='check-Jul25'!P52,"",'1. Live'!P52-'check-Jul25'!P52) -> 105.15844 | Q52: =IF('1. Live'!Q52='check-Jul25'!Q52,"",'1. Live'!Q52-'check-Jul25'!Q52) | ... CW52: =IF('1. Live'!CW52='check-Jul25'!CW52,"",'1. Live'!CW52-'check-Jul25'!CW52)
J53: =IF('1. Live'!J53='check-Jul25'!J53,"",'1. Live'!J53-'check-Jul25'!J53) | K53: =IF('1. Live'!K53='check-Jul25'!K53,"",'1. Live'!K53-'check-Jul25'!K53) | L53: =IF('1. Live'!L53='check-Jul25'!L53,"",'1. Live'!L53-'check-Jul25'!L53) | M53: =IF('1. Live'!M53='check-Jul25'!M53,"",'1. Live'!M53-'check-Jul25'!M53) | N53: =IF('1. Live'!N53='check-Jul25'!N53,"",'1. Live'!N53-'check-Jul25'!N53) | O53: =IF('1. Live'!O53='check-Jul25'!O53,"",'1. Live'!O53-'check-Jul25'!O53) | P53: =IF('1. Live'!P53='check-Jul25'!P53,"",'1. Live'!P53-'check-Jul25'!P53) | Q53: =IF('1. Live'!Q53='check-Jul25'!Q53,"",'1. Live'!Q53-'check-Jul25'!Q53) | ... CW53: =IF('1. Live'!CW53='check-Jul25'!CW53,"",'1. Live'!CW53-'check-Jul25'!CW53)
J54: =IF('1. Live'!J54='check-Jul25'!J54,"",'1. Live'!J54-'check-Jul25'!J54) | K54: =IF('1. Live'!K54='check-Jul25'!K54,"",'1. Live'!K54-'check-Jul25'!K54) -> -0.11707771 | L54: =IF('1. Live'!L54='check-Jul25'!L54,"",'1. Live'!L54-'check-Jul25'!L54) -> 46.002085 | M54: =IF('1. Live'!M54='check-Jul25'!M54,"",'1. Live'!M54-'check-Jul25'!M54) -> -46.119163 | N54: =IF('1. Live'!N54='check-Jul25'!N54,"",'1. Live'!N54-'check-Jul25'!N54) | O54: =IF('1. Live'!O54='check-Jul25'!O54,"",'1. Live'!O54-'check-Jul25'!O54) -> 137.10023 | P54: =IF('1. Live'!P54='check-Jul25'!P54,"",'1. Live'!P54-'check-Jul25'!P54) -> 91.098148 | Q54: =IF('1. Live'!Q54='check-Jul25'!Q54,"",'1. Live'!Q54-'check-Jul25'!Q54) | ... CW54: =IF('1. Live'!CW54='check-Jul25'!CW54,"",'1. Live'!CW54-'check-Jul25'!CW54)
J55: =IF('1. Live'!J55='check-Jul25'!J55,"",'1. Live'!J55-'check-Jul25'!J55) | K55: =IF('1. Live'!K55='check-Jul25'!K55,"",'1. Live'!K55-'check-Jul25'!K55) | L55: =IF('1. Live'!L55='check-Jul25'!L55,"",'1. Live'!L55-'check-Jul25'!L55) | M55: =IF('1. Live'!M55='check-Jul25'!M55,"",'1. Live'!M55-'check-Jul25'!M55) | N55: =IF('1. Live'!N55='check-Jul25'!N55,"",'1. Live'!N55-'check-Jul25'!N55) | O55: =IF('1. Live'!O55='check-Jul25'!O55,"",'1. Live'!O55-'check-Jul25'!O55) | P55: =IF('1. Live'!P55='check-Jul25'!P55,"",'1. Live'!P55-'check-Jul25'!P55) | Q55: =IF('1. Live'!Q55='check-Jul25'!Q55,"",'1. Live'!Q55-'check-Jul25'!Q55) | ... CW55: =IF('1. Live'!CW55='check-Jul25'!CW55,"",'1. Live'!CW55-'check-Jul25'!CW55)
J56: =IF('1. Live'!J56='check-Jul25'!J56,"",'1. Live'!J56-'check-Jul25'!J56) | K56: =IF('1. Live'!K56='check-Jul25'!K56,"",'1. Live'!K56-'check-Jul25'!K56) | L56: =IF('1. Live'!L56='check-Jul25'!L56,"",'1. Live'!L56-'check-Jul25'!L56) | M56: =IF('1. Live'!M56='check-Jul25'!M56,"",'1. Live'!M56-'check-Jul25'!M56) | N56: =IF('1. Live'!N56='check-Jul25'!N56,"",'1. Live'!N56-'check-Jul25'!N56) | O56: =IF('1. Live'!O56='check-Jul25'!O56,"",'1. Live'!O56-'check-Jul25'!O56) | P56: =IF('1. Live'!P56='check-Jul25'!P56,"",'1. Live'!P56-'check-Jul25'!P56) | Q56: =IF('1. Live'!Q56='check-Jul25'!Q56,"",'1. Live'!Q56-'check-Jul25'!Q56) | ... CW56: =IF('1. Live'!CW56='check-Jul25'!CW56,"",'1. Live'!CW56-'check-Jul25'!CW56)
J61: =IF('1. Live'!J61='check-Jul25'!J61,"",'1. Live'!J61-'check-Jul25'!J61) | K61: =IF('1. Live'!K61='check-Jul25'!K61,"",'1. Live'!K61-'check-Jul25'!K61) | L61: =IF('1. Live'!L61='check-Jul25'!L61,"",'1. Live'!L61-'check-Jul25'!L61) | M61: =IF('1. Live'!M61='check-Jul25'!M61,"",'1. Live'!M61-'check-Jul25'!M61) | N61: =IF('1. Live'!N61='check-Jul25'!N61,"",'1. Live'!N61-'check-Jul25'!N61) | O61: =IF('1. Live'!O61='check-Jul25'!O61,"",'1. Live'!O61-'check-Jul25'!O61) | P61: =IF('1. Live'!P61='check-Jul25'!P61,"",'1. Live'!P61-'check-Jul25'!P61) | Q61: =IF('1. Live'!Q61='check-Jul25'!Q61,"",'1. Live'!Q61-'check-Jul25'!Q61) | ... CW61: =IF('1. Live'!CW61='check-Jul25'!CW61,"",'1. Live'!CW61-'check-Jul25'!CW61)
J62: =IF('1. Live'!J62='check-Jul25'!J62,"",'1. Live'!J62-'check-Jul25'!J62) | K62: =IF('1. Live'!K62='check-Jul25'!K62,"",'1. Live'!K62-'check-Jul25'!K62) | L62: =IF('1. Live'!L62='check-Jul25'!L62,"",'1. Live'!L62-'check-Jul25'!L62) | M62: =IF('1. Live'!M62='check-Jul25'!M62,"",'1. Live'!M62-'check-Jul25'!M62) | N62: =IF('1. Live'!N62='check-Jul25'!N62,"",'1. Live'!N62-'check-Jul25'!N62) | O62: =IF('1. Live'!O62='check-Jul25'!O62,"",'1. Live'!O62-'check-Jul25'!O62) | P62: =IF('1. Live'!P62='check-Jul25'!P62,"",'1. Live'!P62-'check-Jul25'!P62) | Q62: =IF('1. Live'!Q62='check-Jul25'!Q62,"",'1. Live'!Q62-'check-Jul25'!Q62) | ... CW62: =IF('1. Live'!CW62='check-Jul25'!CW62,"",'1. Live'!CW62-'check-Jul25'!CW62)
J63: =IF('1. Live'!J63='check-Jul25'!J63,"",'1. Live'!J63-'check-Jul25'!J63) | K63: =IF('1. Live'!K63='check-Jul25'!K63,"",'1. Live'!K63-'check-Jul25'!K63) | L63: =IF('1. Live'!L63='check-Jul25'!L63,"",'1. Live'!L63-'check-Jul25'!L63) | M63: =IF('1. Live'!M63='check-Jul25'!M63,"",'1. Live'!M63-'check-Jul25'!M63) | N63: =IF('1. Live'!N63='check-Jul25'!N63,"",'1. Live'!N63-'check-Jul25'!N63) | O63: =IF('1. Live'!O63='check-Jul25'!O63,"",'1. Live'!O63-'check-Jul25'!O63) | P63: =IF('1. Live'!P63='check-Jul25'!P63,"",'1. Live'!P63-'check-Jul25'!P63) | Q63: =IF('1. Live'!Q63='check-Jul25'!Q63,"",'1. Live'!Q63-'check-Jul25'!Q63) | ... CW63: =IF('1. Live'!CW63='check-Jul25'!CW63,"",'1. Live'!CW63-'check-Jul25'!CW63)
J64: =IF('1. Live'!J64='check-Jul25'!J64,"",'1. Live'!J64-'check-Jul25'!J64) | K64: =IF('1. Live'!K64='check-Jul25'!K64,"",'1. Live'!K64-'check-Jul25'!K64) | L64: =IF('1. Live'!L64='check-Jul25'!L64,"",'1. Live'!L64-'check-Jul25'!L64) | M64: =IF('1. Live'!M64='check-Jul25'!M64,"",'1. Live'!M64-'check-Jul25'!M64) | N64: =IF('1. Live'!N64='check-Jul25'!N64,"",'1. Live'!N64-'check-Jul25'!N64) | O64: =IF('1. Live'!O64='check-Jul25'!O64,"",'1. Live'!O64-'check-Jul25'!O64) | P64: =IF('1. Live'!P64='check-Jul25'!P64,"",'1. Live'!P64-'check-Jul25'!P64) | Q64: =IF('1. Live'!Q64='check-Jul25'!Q64,"",'1. Live'!Q64-'check-Jul25'!Q64) | ... CW64: =IF('1. Live'!CW64='check-Jul25'!CW64,"",'1. Live'!CW64-'check-Jul25'!CW64)
J65: =IF('1. Live'!J65='check-Jul25'!J65,"",'1. Live'!J65-'check-Jul25'!J65) | K65: =IF('1. Live'!K65='check-Jul25'!K65,"",'1. Live'!K65-'check-Jul25'!K65) | L65: =IF('1. Live'!L65='check-Jul25'!L65,"",'1. Live'!L65-'check-Jul25'!L65) | M65: =IF('1. Live'!M65='check-Jul25'!M65,"",'1. Live'!M65-'check-Jul25'!M65) | N65: =IF('1. Live'!N65='check-Jul25'!N65,"",'1. Live'!N65-'check-Jul25'!N65) | O65: =IF('1. Live'!O65='check-Jul25'!O65,"",'1. Live'!O65-'check-Jul25'!O65) | P65: =IF('1. Live'!P65='check-Jul25'!P65,"",'1. Live'!P65-'check-Jul25'!P65) | Q65: =IF('1. Live'!Q65='check-Jul25'!Q65,"",'1. Live'!Q65-'check-Jul25'!Q65) | ... CW65: =IF('1. Live'!CW65='check-Jul25'!CW65,"",'1. Live'!CW65-'check-Jul25'!CW65)
J66: =IF('1. Live'!J66='check-Jul25'!J66,"",'1. Live'!J66-'check-Jul25'!J66) | K66: =IF('1. Live'!K66='check-Jul25'!K66,"",'1. Live'!K66-'check-Jul25'!K66) | L66: =IF('1. Live'!L66='check-Jul25'!L66,"",'1. Live'!L66-'check-Jul25'!L66) | M66: =IF('1. Live'!M66='check-Jul25'!M66,"",'1. Live'!M66-'check-Jul25'!M66) | N66: =IF('1. Live'!N66='check-Jul25'!N66,"",'1. Live'!N66-'check-Jul25'!N66) | O66: =IF('1. Live'!O66='check-Jul25'!O66,"",'1. Live'!O66-'check-Jul25'!O66) | P66: =IF('1. Live'!P66='check-Jul25'!P66,"",'1. Live'!P66-'check-Jul25'!P66) | Q66: =IF('1. Live'!Q66='check-Jul25'!Q66,"",'1. Live'!Q66-'check-Jul25'!Q66) | ... CW66: =IF('1. Live'!CW66='check-Jul25'!CW66,"",'1. Live'!CW66-'check-Jul25'!CW66)
... J437: =IF('1. Live'!J437='check-Jul25'!J437,"",'1. Live'!J437-'check-Jul25'!J437) | K437: =IF('1. Live'!K437='check-Jul25'!K437,"",'1. Live'!K437-'check-Jul25'!K437) | L437: =IF('1. Live'!L437='check-Jul25'!L437,"",'1. Live'!L437-'check-Jul25'!L437) | M437: =IF('1. Live'!M437='check-Jul25'!M437,"",'1. Live'!M437-'check-Jul25'!M437) | N437: =IF('1. Live'!N437='check-Jul25'!N437,"",'1. Live'!N437-'check-Jul25'!N437) | O437: =IF('1. Live'!O437='check-Jul25'!O437,"",'1. Live'!O437-'check-Jul25'!O437) | P437: =IF('1. Live'!P437='check-Jul25'!P437,"",'1. Live'!P437-'check-Jul25'!P437) | Q437: =IF('1. Live'!Q437='check-Jul25'!Q437,"",'1. Live'!Q437-'check-Jul25'!Q437) | ... CW437: =IF('1. Live'!CW437='check-Jul25'!CW437,"",'1. Live'!CW437-'check-Jul25'!CW437)

Sheet 8. Glossary
B2: Term | C2: Definition
B3: $ | C3: Refers to US Dollar
B4: Equity-TBC | C4: The exact class of share is not available as of date
B5: Gain | C5: Equals the total Distributions (received from the investment) plus NAV less Amount Invested
B6: G42 | C6: Refers to entity G42 Investments AI Holding RSC Ltd, and Smart Interaction1 Holding SPV RSC LTD
B7: G.P. | C7: General Partnership interest
B8: IRR | C8: Shown as Interim IRR, where the NAV of the investment is assumed as an appraised terminal value. Transaction costs are not included in the estimate of IRR
B9: L.P. | C9: Limited Partnership interest
B10: MOIC | C10: Money on invested capital
B11: Mozn | C11: Refers to entities: Mozn Holding RSC Ltd, Enterprises Connection Holding RSC Ltd, Smart Interaction5 Holding SPV RSC LTD and QAZ42 Investment SPV RSC Ltd
B12: NAV | C12: Is the measure of the carrying value of the underlying investment as of date
B13: n/a | C13: As appropriate the information is ‘not available’ or ‘not applicable’
... B28: •Written Off: | C28: Investments in Jollychic, Mena Mobile (equity) and Glass Earth are written off
