Workbook
Name Company: #REF!
Name Dates: #REF!
Name DetailedCapShares: #REF!
Name FAGroup: #REF!
Name IQ_CH: 110000
Name IQ_CQ: 5000
Name IQ_CY: 10000
Name IQ_DAILY: 500000
Name IQ_FH: 100000
Name IQ_FQ: 500
Name IQ_FY: 1000
Name IQ_LTM: 2000
Name IQ_MONTH: 15000
Name IQ_NTM: 6000
Name IQ_WEEK: 50000
Name IQ_YTD: 3000
Name UNLOCKED_PERCENT_FAST: _xludf.LAMBDA(start_date, date, IF(start_date="",0,MIN(1,MAX(0,(date-EDATE(start_date,12)+1)/(EDATE(start_date,36)-EDATE(start_date,12))))))
Name UNLOCKED_PERCENT_SLOW: _xludf.LAMBDA(start_date, date, IF(start_date="",0, MIN(1,MAX(0,(date-EDATE(start_date,12)+1)/(EDATE(start_date,60)-EDATE(start_date,12))))))

Sheet D1
B2: Date of NAV | D2: 46265 | E2: =TEXT(D2,"dddddd") -> Monday
H4: D A S H B O A R D
B6: L I V E D E A L S (includes unrealized or partially realized investments)
E8: # Investments | F8: Committed | G8: Invested | H8: Remaining | I8: Distributions | J8: Residual Value | K8: Gain | L8: TVPI | M8: DPI
E9: # | F9: USD, Mn | G9: USD, Mn | H9: USD, Mn | I9: USD, Mn | J9: USD, Mn | K9: USD, Mn | L9: X | M9: X
C11: EQUITY* | D11: Direct Investment | E11: =COUNTIF('1. Live'!$I$1:I110,$D11) -> 19 | F11: =SUMIF('1. Live'!$I$1:$I$110,$D11,'1. Live'!O$1:O$110) -> 988.60649 | G11: =SUMIF('1. Live'!$I$1:$I$110,$D11,'1. Live'!P$1:P$110) -> 988.35649 | H11: =SUMIF('1. Live'!$I$1:$I$110,$D11,'1. Live'!Q$1:Q$110) -> 0.25 | I11: =SUMIF('1. Live'!$I$1:$I$110,$D11,'1. Live'!R$1:R$110) -> 85.304451 | J11: =SUMIF('1. Live'!$I$1:$I$110,$D11,'1. Live'!S$1:S$110) -> 2175.5555 | K11: =SUMIF('1. Live'!$I$1:$I$110,$D11,'1. Live'!T$1:T$110) -> 1272.5035 | L11: =IFERROR((I11+J11)/G11,"") -> 2.2874944 | M11: =IFERROR(I11/G11,"") -> 0.086309396
C13: DEBT | D13: Debt Investment | E13: =COUNTIF('1. Live'!$I$1:I110,$D13) -> 0 | F13: =SUMIF('1. Live'!$I$1:$I$110,$D13,'1. Live'!O$1:O$110) -> 0 | G13: =SUMIF('1. Live'!$I$1:$I$110,$D13,'1. Live'!P$1:P$110) -> 0 | H13: =SUMIF('1. Live'!$I$1:$I$110,$D13,'1. Live'!Q$1:Q$110) -> 0 | I13: =SUMIF('1. Live'!$I$1:$I$110,$D13,'1. Live'!R$1:R$110) -> 0 | J13: =SUMIF('1. Live'!$I$1:$I$110,$D13,'1. Live'!S$1:S$110) -> 0 | K13: =SUMIF('1. Live'!$I$1:$I$110,$D13,'1. Live'!T$1:T$110) -> 0 | L13: =IFERROR((I13+J13)/G13,"") | M13: =IFERROR(I13/G13,"")
C15: FUNDS | D15: Fund Investment | E15: =COUNTIF('1. Live'!$I$1:I110,$D15) -> 4 | F15: =SUMIF('1. Live'!$I$1:$I$110,$D15,'1. Live'!O$1:O$110) -> 130.17124 | G15: =SUMIF('1. Live'!$I$1:$I$110,$D15,'1. Live'!P$1:P$110) -> 118.80356 | H15: =SUMIF('1. Live'!$I$1:$I$110,$D15,'1. Live'!Q$1:Q$110) -> 11.367673 | I15: =SUMIF('1. Live'!$I$1:$I$110,$D15,'1. Live'!R$1:R$110) -> 14.653505 | J15: =SUMIF('1. Live'!$I$1:$I$110,$D15,'1. Live'!S$1:S$110) -> 150.49907 | K15: =SUMIF('1. Live'!$I$1:$I$110,$D15,'1. Live'!T$1:T$110) -> 46.349013 | L15: =IFERROR((I15+J15)/G15,"") -> 1.3901315 | M15: =IFERROR(I15/G15,"") -> 0.1233423
C17: MGX | D17: MGX related | E17: 4 | F17: ='1. Live'!O52 -> 1881.4 | G17: ='1. Live'!P52 -> 705.75142 | H17: ='1. Live'!Q52 -> 1175.6486 | I17: ='1. Live'!R52 -> 14.688852 | J17: ='1. Live'!S52 -> 2216.6516 | K17: ='1. Live'!T52 -> 1510.9002 | L17: =IFERROR((I17+J17)/G17,"") -> 3.1616521 | M17: =IFERROR(I17/G17,"") -> 0.020813068
C19: TOTAL | E19: =E11+E13+E15 -> 23 | F19: =F11+F13+F15+F17 -> 3000.1777 | G19: =G11+G13+G15+G17 -> 1812.9115 | H19: =H11+H13+H15+H17 -> 1187.2663 | I19: =I11+I13+I15+I17 -> 114.64681 | J19: =J11+J13+J15+J17 -> 4542.7062 | K19: =K11+K13+K15+K17 -> 2829.7527 | L19: =IFERROR((I19+J19)/G19,"") -> 2.5689909 | M19: =IFERROR(I19/G19,"") -> 0.063239055
B22: E X I T E D D E A L S (includes liquidated, written-off or completely exited investments)
E24: # Investments | F24: Committed | G24: Invested | H24: Remaining | I24: Distributions | J24: Residual Value | K24: Gain | L24: TVPI | M24: DPI
E25: # | F25: USD, Mn | G25: USD, Mn | H25: USD, Mn | I25: USD, Mn | J25: USD, Mn | K25: USD, Mn | L25: X | M25: X
C27: EQUITY* | D27: Direct Investment | E27: =COUNTIF('2. Exited'!$D$1:D41,$D27) -> 8 | F27: =SUMIF('2. Exited'!$D$1:$D$41,$D27,'2. Exited'!K$1:K$41) -> 1394.0316 | G27: =SUMIF('2. Exited'!$D$1:$D$41,$D27,'2. Exited'!L$1:L$41) -> 1394.0316 | H27: =SUMIF('2. Exited'!$D$1:$D$41,$D27,'2. Exited'!M$1:M$41) -> 0 | I27: =SUMIF('2. Exited'!$D$1:$D$41,$D27,'2. Exited'!N$1:N$41) -> 1343.2422 | J27: =SUMIF('2. Exited'!$D$1:$D$41,$D27,'2. Exited'!O$1:O$41) -> 0 | K27: =SUMIF('2. Exited'!$D$1:$D$41,$D27,'2. Exited'!P$1:P$41) -> -50.789359 | L27: =IFERROR((I27+J27)/G27,"") -> 0.96356656 | M27: =IFERROR(I27/G27,"") -> 0.96356656
C29: DEBT | D29: Debt Investment | E29: =COUNTIF('2. Exited'!$D$1:D43,$D29) -> 3 | F29: =SUMIF('2. Exited'!$D$1:$D$41,$D29,'2. Exited'!K$1:K$41) -> 10.765747 | G29: =SUMIF('2. Exited'!$D$1:$D$41,$D29,'2. Exited'!L$1:L$41) -> 10.765747 | H29: =SUMIF('2. Exited'!$D$1:$D$41,$D29,'2. Exited'!M$1:M$41) -> 0 | I29: =SUMIF('2. Exited'!$D$1:$D$41,$D29,'2. Exited'!N$1:N$41) -> 0.47078465 | J29: =SUMIF('2. Exited'!$D$1:$D$41,$D29,'2. Exited'!O$1:O$41) -> 0 | K29: =SUMIF('2. Exited'!$D$1:$D$41,$D29,'2. Exited'!P$1:P$41) -> -10.294962 | L29: =IFERROR((I29+J29)/G29,"") -> 0.043729864 | M29: =IFERROR(I29/G29,"") -> 0.043729864
C31: FUNDS | D31: Fund Investment | E31: =COUNTIF('2. Exited'!$D$1:D45,$D31) -> 1 | F31: =SUMIF('2. Exited'!$D$1:$D$41,$D31,'2. Exited'!K$1:K$41) -> 50 | G31: =SUMIF('2. Exited'!$D$1:$D$41,$D31,'2. Exited'!L$1:L$41) -> 24.959693 | H31: =SUMIF('2. Exited'!$D$1:$D$41,$D31,'2. Exited'!M$1:M$41) -> 0 | I31: =SUMIF('2. Exited'!$D$1:$D$41,$D31,'2. Exited'!N$1:N$41) -> 25.403521 | J31: =SUMIF('2. Exited'!$D$1:$D$41,$D31,'2. Exited'!O$1:O$41) -> 0 | K31: =SUMIF('2. Exited'!$D$1:$D$41,$D31,'2. Exited'!P$1:P$41) -> 0.44382835 | L31: =IFERROR((I31+J31)/G31,"") -> 1.0177818 | M31: =IFERROR(I31/G31,"") -> 1.0177818
C33: TOTAL | E33: =E27+E29+E31 -> 12 | F33: =F27+F29+F31 -> 1454.7973 | G33: =G27+G29+G31 -> 1429.757 | H33: =H27+H29+H31 -> 0 | I33: =I27+I29+I31 -> 1369.1165 | J33: =J27+J29+J31 -> 0 | K33: =K27+K29+K31 -> -60.640493 | L33: =IFERROR((I33+J33)/G33,"") -> 0.95758685 | M33: =IFERROR(I33/G33,"") -> 0.95758685
B36: * Includes Convertibles
E38: CHECKS | F38: =ROUND(F19,5)=ROUND('1. Live'!O54,5) -> TRUE | G38: =ROUND(G19,5)=ROUND('1. Live'!P54,5) -> TRUE | H38: =ROUND(H19,5)=ROUND('1. Live'!Q54,5) -> TRUE | I38: =ROUND(I19,5)=ROUND('1. Live'!R54,5) -> TRUE | J38: =ROUND(J19,5)=ROUND('1. Live'!S54,5) -> TRUE | K38: =ROUND(K19,5)=ROUND('1. Live'!T54,5) -> TRUE
F39: =F33='2. Exited'!K36 -> TRUE | G39: =G33='2. Exited'!L36 -> TRUE | H39: =H33='2. Exited'!M36 -> TRUE | I39: =I33='2. Exited'!N36 -> TRUE | J39: =J33='2. Exited'!O36 -> TRUE | K39: =K33='2. Exited'!P36 -> TRUE
F40: TRUE | G40: TRUE | H40: TRUE | I40: TRUE | J40: TRUE | K40: TRUE

Sheet 1. Live
C2: As of date
C3: ='D1'!D2 -> 46265
J5: 2 | K5: 4 | L5: 5 | M5: 6 | N5: 7 | O5: 8 | P5: 9 | Q5: 10 | R5: 11 | S5: 12 | T5: 13 | U5: 14 | V5: 15
C6: Deals | D6: Key Person | E6: G42 Sponsor | F6: Geography | G6: Sector | H6: Last Series | I6: Type | J6: Status | K6: Investing Entity | L6: Vintageἀ | M6: Instrument | N6: % | O6: Committed | P6: Invested | Q6: Remaining Commitment | R6: Distributions | S6: Carrying Value | T6: Gain | U6: TVPI | V6: Additonal Upside/Downside
M7: # | N7: % | O7: $,m | P7: $,m | Q7: $,m | R7: $,m | S7: $,m | T7: $,m | U7: X
C8: MOZN Holding RSC Ltd
C9: E-line Ventures LLC | D9: Sushil | E9: Peng | F9: USA | G9: Education | H9: B Prefs | I9: Direct Investment | J9: =VLOOKUP($C9,'A. All deals (a)'!$C$6:$Q$58,J$5,0) -> Unrealized | K9: =VLOOKUP($C9,'A. All deals (a)'!$C$6:$Q$58,K$5,0) -> Mozn | L9: =VLOOKUP($C9,'A. All deals (a)'!$C$6:$Q$58,L$5,0) -> 2023 | M9: =VLOOKUP($C9,'A. All deals (a)'!$C$6:$Q$58,M$5,0) -> B Prefs | N9: =VLOOKUP($C9,'A. All deals (a)'!$C$6:$Q$58,N$5,0) -> 0.1163 | O9: =VLOOKUP($C9,'A. All deals (a)'!$C$6:$Q$58,O$5,0) -> 6 | P9: =VLOOKUP($C9,'A. All deals (a)'!$C$6:$Q$58,P$5,0) -> 6 | Q9: =VLOOKUP($C9,'A. All deals (a)'!$C$6:$Q$58,Q$5,0) -> 0 | ... U9: =VLOOKUP($C9,'A. All deals (a)'!$C$6:$Q$58,U$5,0) -> 1.1833333 | V9: Optionse
C10: Tools for Humanity Corporation | D10: Divyesh | E10: Peng | F10: USA | G10: Biometrics | H10: C Prefs | I10: Direct Investment | J10: =VLOOKUP($C10,'A. All deals (a)'!$C$6:$Q$58,J$5,0) -> Unrealized | K10: =VLOOKUP($C10,'A. All deals (a)'!$C$6:$Q$58,K$5,0) -> Mozn | L10: =VLOOKUP($C10,'A. All deals (a)'!$C$6:$Q$58,L$5,0) -> 2023 | M10: =VLOOKUP($C10,'A. All deals (a)'!$C$6:$Q$58,M$5,0) -> C Prefs | N10: =VLOOKUP($C10,'A. All deals (a)'!$C$6:$Q$58,N$5,0) -> 0.00626608 | O10: =VLOOKUP($C10,'A. All deals (a)'!$C$6:$Q$58,O$5,0) -> 14.999999 | P10: =VLOOKUP($C10,'A. All deals (a)'!$C$6:$Q$58,P$5,0) -> 14.999999 | Q10: =VLOOKUP($C10,'A. All deals (a)'!$C$6:$Q$58,Q$5,0) -> 0 | ... U10: =VLOOKUP($C10,'A. All deals (a)'!$C$6:$Q$58,U$5,0) -> 0.080000006
C11: eSpace | D11: Sushil | E11: Peng | F11: USA | G11: Space | H11: C Prefs | I11: Direct Investment | J11: =VLOOKUP($C11,'A. All deals (a)'!$C$6:$Q$58,J$5,0) -> Unrealized | K11: =VLOOKUP($C11,'A. All deals (a)'!$C$6:$Q$58,K$5,0) -> Mozn 4 | L11: =VLOOKUP($C11,'A. All deals (a)'!$C$6:$Q$58,L$5,0) -> 2022 | M11: =VLOOKUP($C11,'A. All deals (a)'!$C$6:$Q$58,M$5,0) -> B Prefs | N11: =VLOOKUP($C11,'A. All deals (a)'!$C$6:$Q$58,N$5,0) -> 0.02481 | O11: =VLOOKUP($C11,'A. All deals (a)'!$C$6:$Q$58,O$5,0) -> 15 | P11: =VLOOKUP($C11,'A. All deals (a)'!$C$6:$Q$58,P$5,0) -> 15 | Q11: =VLOOKUP($C11,'A. All deals (a)'!$C$6:$Q$58,Q$5,0) -> 0 | ... U11: =VLOOKUP($C11,'A. All deals (a)'!$C$6:$Q$58,U$5,0) -> 15.333834
C12: Applied AI Corporation Limited | D12: Divyesh | E12: HE Tariq | F12: UAE/UK | G12: AI Software | H12: Convertible | I12: Direct Investment | J12: =VLOOKUP($C12,'A. All deals (a)'!$C$6:$Q$58,J$5,0) -> Unrealized | K12: =VLOOKUP($C12,'A. All deals (a)'!$C$6:$Q$58,K$5,0) -> Mozn | L12: =VLOOKUP($C12,'A. All deals (a)'!$C$6:$Q$58,L$5,0) -> 2022 | M12: =VLOOKUP($C12,'A. All deals (a)'!$C$6:$Q$58,M$5,0) -> A Prefs | N12: =VLOOKUP($C12,'A. All deals (a)'!$C$6:$Q$58,N$5,0) -> 0.12121516 | O12: =VLOOKUP($C12,'A. All deals (a)'!$C$6:$Q$58,O$5,0) -> 15 | P12: =VLOOKUP($C12,'A. All deals (a)'!$C$6:$Q$58,P$5,0) -> 15 | Q12: =VLOOKUP($C12,'A. All deals (a)'!$C$6:$Q$58,Q$5,0) -> 0 | ... U12: =VLOOKUP($C12,'A. All deals (a)'!$C$6:$Q$58,U$5,0) -> 2.5643153
C13: Cerebras Systems Inc (1) | D13: Divyesh | E13: Peng | F13: USA | G13: Semiconductors | H13: Listed | I13: Direct Investment | J13: =VLOOKUP($C13,'A. All deals (a)'!$C$6:$Q$58,J$5,0) -> Unrealized | K13: =VLOOKUP($C13,'A. All deals (a)'!$C$6:$Q$58,K$5,0) -> Mozn | L13: =VLOOKUP($C13,'A. All deals (a)'!$C$6:$Q$58,L$5,0) -> 2021 | M13: Class A/B | N13: =VLOOKUP($C13,'A. All deals (a)'!$C$6:$Q$58,N$5,0) -> 0.0065613279 | O13: =VLOOKUP($C13,'A. All deals (a)'!$C$6:$Q$58,O$5,0) -> 39.999983 | P13: =VLOOKUP($C13,'A. All deals (a)'!$C$6:$Q$58,P$5,0) -> 39.999983 | Q13: =VLOOKUP($C13,'A. All deals (a)'!$C$6:$Q$58,Q$5,0) -> 0 | R13: =VLOOKUP($C13,'A. All deals (a)'!$C$6:$Q$58,R$5,0) -> 0 | S13: =VLOOKUP($C13,'A. All deals (a)'!$C$6:$Q$58,S$5,0) -> 265.62083 | T13: =VLOOKUP($C13,'A. All deals (a)'!$C$6:$Q$58,T$5,0) -> 225.62085 | U13: =VLOOKUP($C13,'A. All deals (a)'!$C$6:$Q$58,U$5,0) -> 6.6405236
C14: Endless Studios LLC | D14: Sushil | E14: Peng | F14: USA | G14: Gaming | H14: A Pref Units | I14: Direct Investment | J14: =VLOOKUP($C14,'A. All deals (a)'!$C$6:$Q$58,J$5,0) -> Unrealized | K14: =VLOOKUP($C14,'A. All deals (a)'!$C$6:$Q$58,K$5,0) -> Mozn | L14: =VLOOKUP($C14,'A. All deals (a)'!$C$6:$Q$58,L$5,0) -> 2021 | M14: =VLOOKUP($C14,'A. All deals (a)'!$C$6:$Q$58,M$5,0) -> A Pref Units | N14: =VLOOKUP($C14,'A. All deals (a)'!$C$6:$Q$58,N$5,0) -> 0.16016016 | O14: =VLOOKUP($C14,'A. All deals (a)'!$C$6:$Q$58,O$5,0) -> 8 | P14: =VLOOKUP($C14,'A. All deals (a)'!$C$6:$Q$58,P$5,0) -> 8 | Q14: =VLOOKUP($C14,'A. All deals (a)'!$C$6:$Q$58,Q$5,0) -> 0 | ... U14: =VLOOKUP($C14,'A. All deals (a)'!$C$6:$Q$58,U$5,0) -> 0.8125
C15: Heygears | D15: Divyesh | E15: Peng | F15: PRC | G15: 3D Printing | H15: Series D | I15: Direct Investment | J15: =VLOOKUP($C15,'A. All deals (a)'!$C$6:$Q$58,J$5,0) -> Unrealized | K15: =VLOOKUP($C15,'A. All deals (a)'!$C$6:$Q$58,K$5,0) -> Mozn | L15: =VLOOKUP($C15,'A. All deals (a)'!$C$6:$Q$58,L$5,0) -> 2020 | M15: =VLOOKUP($C15,'A. All deals (a)'!$C$6:$Q$58,M$5,0) -> Registered Capital | N15: =VLOOKUP($C15,'A. All deals (a)'!$C$6:$Q$58,N$5,0) -> 0.14383199 | O15: =VLOOKUP($C15,'A. All deals (a)'!$C$6:$Q$58,O$5,0) -> 60 | P15: =VLOOKUP($C15,'A. All deals (a)'!$C$6:$Q$58,P$5,0) -> 60 | Q15: =VLOOKUP($C15,'A. All deals (a)'!$C$6:$Q$58,Q$5,0) -> 0 | ... U15: =VLOOKUP($C15,'A. All deals (a)'!$C$6:$Q$58,U$5,0) -> 1.1986474
C16: Beyond Limits | D16: Sushil | E16: Peng | F16: USA | G16: AI Software | H16: C Prefs | I16: Direct Investment | J16: =VLOOKUP($C16,'A. All deals (a)'!$C$6:$Q$58,J$5,0) -> Unrealized | K16: =VLOOKUP($C16,'A. All deals (a)'!$C$6:$Q$58,K$5,0) -> Mozn | L16: =VLOOKUP($C16,'A. All deals (a)'!$C$6:$Q$58,L$5,0) -> 2020 | M16: =VLOOKUP($C16,'A. All deals (a)'!$C$6:$Q$58,M$5,0) -> C Prefs | N16: =VLOOKUP($C16,'A. All deals (a)'!$C$6:$Q$58,N$5,0) -> 0.065 | O16: =VLOOKUP($C16,'A. All deals (a)'!$C$6:$Q$58,O$5,0) -> 90 | P16: =VLOOKUP($C16,'A. All deals (a)'!$C$6:$Q$58,P$5,0) -> 90 | Q16: =VLOOKUP($C16,'A. All deals (a)'!$C$6:$Q$58,Q$5,0) -> 0 | ... U16: =VLOOKUP($C16,'A. All deals (a)'!$C$6:$Q$58,U$5,0) -> 0.24111111
C17: ONT plc | D17: Divyesh | E17: Peng | F17: UK | G17: Genome Sequencing | H17: Ordinary Shares | I17: Direct Investment | J17: =VLOOKUP($C17,'A. All deals (a)'!$C$6:$Q$58,J$5,0) -> Unrealized | K17: =VLOOKUP($C17,'A. All deals (a)'!$C$6:$Q$58,K$5,0) -> Mozn | L17: =VLOOKUP($C17,'A. All deals (a)'!$C$6:$Q$58,L$5,0) -> 2020 | M17: =VLOOKUP($C17,'A. All deals (a)'!$C$6:$Q$58,M$5,0) -> Ordinary Shares | N17: =VLOOKUP($C17,'A. All deals (a)'!$C$6:$Q$58,N$5,0) -> 0.045562985 | O17: =VLOOKUP($C17,'A. All deals (a)'!$C$6:$Q$58,O$5,0) -> 141.47026 | P17: =VLOOKUP($C17,'A. All deals (a)'!$C$6:$Q$58,P$5,0) -> 141.47026 | Q17: =VLOOKUP($C17,'A. All deals (a)'!$C$6:$Q$58,Q$5,0) -> 0 | ... U17: =VLOOKUP($C17,'A. All deals (a)'!$C$6:$Q$58,U$5,0) -> 0.74381239
C18: Flyr Inc | D18: Divyesh | E18: Peng | F18: USA | G18: Aviation | H18: B-1,2 Prefs | I18: Direct Investment | J18: =VLOOKUP($C18,'A. All deals (a)'!$C$6:$Q$58,J$5,0) -> Unrealized | K18: =VLOOKUP($C18,'A. All deals (a)'!$C$6:$Q$58,K$5,0) -> Mozn | L18: =VLOOKUP($C18,'A. All deals (a)'!$C$6:$Q$58,L$5,0) -> 2019 | M18: =VLOOKUP($C18,'A. All deals (a)'!$C$6:$Q$58,M$5,0) -> B-1,2 Prefs | N18: =VLOOKUP($C18,'A. All deals (a)'!$C$6:$Q$58,N$5,0) -> 0.0334 | O18: =VLOOKUP($C18,'A. All deals (a)'!$C$6:$Q$58,O$5,0) -> 10 | P18: =VLOOKUP($C18,'A. All deals (a)'!$C$6:$Q$58,P$5,0) -> 10 | Q18: =VLOOKUP($C18,'A. All deals (a)'!$C$6:$Q$58,Q$5,0) -> 0 | ... U18: =VLOOKUP($C18,'A. All deals (a)'!$C$6:$Q$58,U$5,0) -> 1.46 | V18: Flyr Warrantsa
O20: =SUM(O9:O18) -> 400.47024 | P20: =SUM(P9:P18) -> 400.47024 | Q20: =SUM(Q9:Q18) -> 0 | R20: =SUM(R9:R18) -> 0 | S20: =SUM(S9:S18) -> 762.33925 | T20: =S20+R20-P20 -> 361.86901 | U20: =(R20+S20)/P20 -> 1.9036102
C22: G42 Investments AI Holding RSC Ltd
C23: DriveNets | D23: Sushil | E23: HE Tariq | F23: Israel | G23: Networking | I23: Direct Investment | J23: =VLOOKUP($C23,'A. All deals (a)'!$C$6:$Q$58,J$5,0) -> Partially Realized | K23: =VLOOKUP($C23,'A. All deals (a)'!$C$6:$Q$58,K$5,0) -> G42 Investments | L23: =VLOOKUP($C23,'A. All deals (a)'!$C$6:$Q$58,L$5,0) -> 2022 | M23: =VLOOKUP($C23,'A. All deals (a)'!$C$6:$Q$58,M$5,0) -> Equity-TBC | N23: =VLOOKUP($C23,'A. All deals (a)'!$C$6:$Q$58,N$5,0) -> 0.0655 | O23: =VLOOKUP($C23,'A. All deals (a)'!$C$6:$Q$58,O$5,0) -> 300 | P23: =VLOOKUP($C23,'A. All deals (a)'!$C$6:$Q$58,P$5,0) -> 300 | Q23: =VLOOKUP($C23,'A. All deals (a)'!$C$6:$Q$58,Q$5,0) -> 0 | ... U23: =VLOOKUP($C23,'A. All deals (a)'!$C$6:$Q$58,U$5,0) -> 1.9411318 | V23: DN Warrants b
C24: vTv Therapeutics Inc. | D24: Divyesh | E24: Dr. Fahed, M42 | F24: USA | G24: Healthcare | I24: Direct Investment | J24: =VLOOKUP($C24,'A. All deals (a)'!$C$6:$Q$58,J$5,0) -> Unrealized | K24: =VLOOKUP($C24,'A. All deals (a)'!$C$6:$Q$58,K$5,0) -> G42 Investments | L24: =VLOOKUP($C24,'A. All deals (a)'!$C$6:$Q$58,L$5,0) -> 2022 | M24: =VLOOKUP($C24,'A. All deals (a)'!$C$6:$Q$58,M$5,0) -> Ordinary Shares | N24: =VLOOKUP($C24,'A. All deals (a)'!$C$6:$Q$58,N$5,0) -> 0.020924424 | O24: =VLOOKUP($C24,'A. All deals (a)'!$C$6:$Q$58,O$5,0) -> 24.53125 | P24: =VLOOKUP($C24,'A. All deals (a)'!$C$6:$Q$58,P$5,0) -> 24.53125 | Q24: =VLOOKUP($C24,'A. All deals (a)'!$C$6:$Q$58,Q$5,0) -> 0 | ... U24: =VLOOKUP($C24,'A. All deals (a)'!$C$6:$Q$58,U$5,0) -> 0.33871181 | V24: vTv $30m milestn payment c
C25: North Summit Capital Fund | D25: Divyesh | E25: Peng | F25: Cayman | G25: Fund | I25: Fund Investment | J25: =VLOOKUP($C25,'A. All deals (a)'!$C$6:$Q$58,J$5,0) -> Unrealized | K25: =VLOOKUP($C25,'A. All deals (a)'!$C$6:$Q$58,K$5,0) -> G42 Investments | L25: =VLOOKUP($C25,'A. All deals (a)'!$C$6:$Q$58,L$5,0) -> 2020 | M25: =VLOOKUP($C25,'A. All deals (a)'!$C$6:$Q$58,M$5,0) -> LP | N25: =VLOOKUP($C25,'A. All deals (a)'!$C$6:$Q$58,N$5,0) -> n/a | O25: =VLOOKUP($C25,'A. All deals (a)'!$C$6:$Q$58,O$5,0) -> 83.361611 | P25: =VLOOKUP($C25,'A. All deals (a)'!$C$6:$Q$58,P$5,0) -> 83.361611 | Q25: =VLOOKUP($C25,'A. All deals (a)'!$C$6:$Q$58,Q$5,0) -> 0 | ... U25: =VLOOKUP($C25,'A. All deals (a)'!$C$6:$Q$58,U$5,0) -> 0.96497411
C26: New Space Capital Fund I | D26: Sushil | E26: Peng | F26: Luxembourg | G26: Fund | I26: Fund Investment | J26: =VLOOKUP($C26,'A. All deals (a)'!$C$6:$Q$58,J$5,0) -> Unrealized | K26: =VLOOKUP($C26,'A. All deals (a)'!$C$6:$Q$58,K$5,0) -> G42 Investments | L26: =VLOOKUP($C26,'A. All deals (a)'!$C$6:$Q$58,L$5,0) -> 2020 | M26: =VLOOKUP($C26,'A. All deals (a)'!$C$6:$Q$58,M$5,0) -> LP | N26: =VLOOKUP($C26,'A. All deals (a)'!$C$6:$Q$58,N$5,0) -> n/a | O26: =VLOOKUP($C26,'A. All deals (a)'!$C$6:$Q$58,O$5,0) -> 26.991242 | P26: =VLOOKUP($C26,'A. All deals (a)'!$C$6:$Q$58,P$5,0) -> 17.009681 | Q26: =VLOOKUP($C26,'A. All deals (a)'!$C$6:$Q$58,Q$5,0) -> 9.9815607 | ... U26: =VLOOKUP($C26,'A. All deals (a)'!$C$6:$Q$58,U$5,0) -> 3.7586897
C27: New Space Capital GP Com SCSp | D27: Sushil | E27: Peng | F27: Luxembourg | G27: Fund | I27: Fund Investment | J27: =VLOOKUP($C27,'A. All deals (a)'!$C$6:$Q$58,J$5,0) -> Unrealized | K27: =VLOOKUP($C27,'A. All deals (a)'!$C$6:$Q$58,K$5,0) -> G42 Investments | L27: =VLOOKUP($C27,'A. All deals (a)'!$C$6:$Q$58,L$5,0) -> 2023 | M27: =VLOOKUP($C27,'A. All deals (a)'!$C$6:$Q$58,M$5,0) -> LP | N27: =VLOOKUP($C27,'A. All deals (a)'!$C$6:$Q$58,N$5,0) -> n/a | O27: =VLOOKUP($C27,'A. All deals (a)'!$C$6:$Q$58,O$5,0) -> 2.7058824 | P27: =VLOOKUP($C27,'A. All deals (a)'!$C$6:$Q$58,P$5,0) -> 2.7058824 | Q27: =VLOOKUP($C27,'A. All deals (a)'!$C$6:$Q$58,Q$5,0) -> 0 | ... U27: =VLOOKUP($C27,'A. All deals (a)'!$C$6:$Q$58,U$5,0) -> 2.4915204
C28: Acies Investments Fund I, L.P. | D28: Divyesh | E28: Peng | F28: USA | G28: Fund | I28: Fund Investment | J28: =VLOOKUP($C28,'A. All deals (a)'!$C$6:$Q$58,J$5,0) -> Unrealized | K28: =VLOOKUP($C28,'A. All deals (a)'!$C$6:$Q$58,K$5,0) -> G42 Investments | L28: =VLOOKUP($C28,'A. All deals (a)'!$C$6:$Q$58,L$5,0) -> 2021 | M28: =VLOOKUP($C28,'A. All deals (a)'!$C$6:$Q$58,M$5,0) -> LP | N28: =VLOOKUP($C28,'A. All deals (a)'!$C$6:$Q$58,N$5,0) -> 0.33 | O28: =VLOOKUP($C28,'A. All deals (a)'!$C$6:$Q$58,O$5,0) -> 17.1125 | P28: =VLOOKUP($C28,'A. All deals (a)'!$C$6:$Q$58,P$5,0) -> 15.726387 | Q28: =VLOOKUP($C28,'A. All deals (a)'!$C$6:$Q$58,Q$5,0) -> 1.3861125 | ... U28: =VLOOKUP($C28,'A. All deals (a)'!$C$6:$Q$58,U$5,0) -> 0.89244291 | V28: 9.9% GP | Anchorf
O30: =SUM(O23:O28) -> 454.70249 | P30: =SUM(P23:P28) -> 443.33481 | Q30: =SUM(Q23:Q28) -> 11.367673 | R30: =SUM(R23:R28) -> 99.457991 | S30: =SUM(S23:S28) -> 656.34315 | T30: =S30+R30-P30 -> 312.46633 | U30: =(R30+S30)/P30 -> 1.7048089
C32: G42 Capital SPV RSC Ltd
C33: Life Biosciences LLC | D33: Divyesh | E33: Peng/XP | F33: USA | G33: Healthcare | I33: Direct Investment | J33: =VLOOKUP($C33,'A. All deals (a)'!$C$6:$Q$58,J$5,0) -> Unrealized | K33: =VLOOKUP($C33,'A. All deals (a)'!$C$6:$Q$58,K$5,0) -> G42 Capital | L33: =VLOOKUP($C33,'A. All deals (a)'!$C$6:$Q$58,L$5,0) -> 2024 | M33: =VLOOKUP($C33,'A. All deals (a)'!$C$6:$Q$58,M$5,0) -> D Prefs | N33: =VLOOKUP($C33,'A. All deals (a)'!$C$6:$Q$58,N$5,0) -> 0.0639 | O33: =VLOOKUP($C33,'A. All deals (a)'!$C$6:$Q$58,O$5,0) -> 40 | P33: =VLOOKUP($C33,'A. All deals (a)'!$C$6:$Q$58,P$5,0) -> 40 | Q33: =VLOOKUP($C33,'A. All deals (a)'!$C$6:$Q$58,Q$5,0) -> 0 | ... U33: =VLOOKUP($C33,'A. All deals (a)'!$C$6:$Q$58,U$5,0) -> 1.0236848 | V33: EPTH7
C34: Verses AI Inc | D34: Divyesh | E34: Peng/XP | F34: Canada | G34: AI Software | I34: Direct Investment | J34: =VLOOKUP($C34,'A. All deals (a)'!$C$6:$Q$58,J$5,0) -> Unrealized | K34: =VLOOKUP($C34,'A. All deals (a)'!$C$6:$Q$58,K$5,0) -> G42 Capital | L34: =VLOOKUP($C34,'A. All deals (a)'!$C$6:$Q$58,L$5,0) -> 2024 | M34: Ordinary Shares | N34: =VLOOKUP($C34,'A. All deals (a)'!$C$6:$Q$58,N$5,0) -> 0.035972427 | O34: =VLOOKUP($C34,'A. All deals (a)'!$C$6:$Q$58,O$5,0) -> 10 | P34: =VLOOKUP($C34,'A. All deals (a)'!$C$6:$Q$58,P$5,0) -> 10 | Q34: =VLOOKUP($C34,'A. All deals (a)'!$C$6:$Q$58,Q$5,0) -> 0 | R34: =VLOOKUP($C34,'A. All deals (a)'!$C$6:$Q$58,R$5,0) -> 0 | S34: =VLOOKUP($C34,'A. All deals (a)'!$C$6:$Q$58,S$5,0) -> 0 | T34: =VLOOKUP($C34,'A. All deals (a)'!$C$6:$Q$58,T$5,0) -> -10 | U34: =VLOOKUP($C34,'A. All deals (a)'!$C$6:$Q$58,U$5,0) -> 0 | V34: ="EPTH9 "& VLOOKUP($C34,'A. All deals (a)'!$C$6:$Q$58,V$5,0) -> EPTH9 Revenue linked RSUs
C35: Inveniam Ltd | D35: Divyesh | E35: Jon Nieman | F35: USA | G35: AI Software | I35: Direct Investment | J35: =VLOOKUP($C35,'A. All deals (a)'!$C$6:$Q$58,J$5,0) -> Unrealized | K35: =VLOOKUP($C35,'A. All deals (a)'!$C$6:$Q$58,K$5,0) -> G42 Capital | L35: =VLOOKUP($C35,'A. All deals (a)'!$C$6:$Q$58,L$5,0) -> 2024 | M35: =VLOOKUP($C35,'A. All deals (a)'!$C$6:$Q$58,M$5,0) -> SAR | N35: =VLOOKUP($C35,'A. All deals (a)'!$C$6:$Q$58,N$5,0) -> NA | O35: =VLOOKUP($C35,'A. All deals (a)'!$C$6:$Q$58,O$5,0) -> 100 | P35: =VLOOKUP($C35,'A. All deals (a)'!$C$6:$Q$58,P$5,0) -> 100 | Q35: =VLOOKUP($C35,'A. All deals (a)'!$C$6:$Q$58,Q$5,0) -> 0 | ... U35: =VLOOKUP($C35,'A. All deals (a)'!$C$6:$Q$58,U$5,0) -> 1.0049997 | V35: ="EPTH10 "& VLOOKUP($C35,'A. All deals (a)'!$C$6:$Q$58,V$5,0) -> EPTH10 Upside if Tokens sold > $2.5 per token
C36: Liquid AI | D36: Divyesh | E36: Peng | F36: USA | G36: Foundation Model | I36: Direct Investment | J36: =VLOOKUP($C36,'A. All deals (a)'!$C$6:$Q$58,J$5,0) -> Unrealized | K36: =VLOOKUP($C36,'A. All deals (a)'!$C$6:$Q$58,K$5,0) -> G42 Capital | L36: =VLOOKUP($C36,'A. All deals (a)'!$C$6:$Q$58,L$5,0) -> 2025 | M36: =VLOOKUP($C36,'A. All deals (a)'!$C$6:$Q$58,M$5,0) -> Series A | N36: =VLOOKUP($C36,'A. All deals (a)'!$C$6:$Q$58,N$5,0) -> 0.030216555 | O36: =VLOOKUP($C36,'A. All deals (a)'!$C$6:$Q$58,O$5,0) -> 60.819863 | P36: =VLOOKUP($C36,'A. All deals (a)'!$C$6:$Q$58,P$5,0) -> 60.819863 | Q36: =VLOOKUP($C36,'A. All deals (a)'!$C$6:$Q$58,Q$5,0) -> 0 | ... U36: =VLOOKUP($C36,'A. All deals (a)'!$C$6:$Q$58,U$5,0) -> 1.0950236 | V36: EPTH11
C37: Neuralink | D37: Divyesh | E37: Peng | F37: USA | G37: Healthcare | I37: Direct Investment | J37: =VLOOKUP($C37,'A. All deals (a)'!$C$6:$Q$58,J$5,0) -> Unrealized | K37: =VLOOKUP($C37,'A. All deals (a)'!$C$6:$Q$58,K$5,0) -> G42 Capital | L37: =VLOOKUP($C37,'A. All deals (a)'!$C$6:$Q$58,L$5,0) -> 2025 | M37: =VLOOKUP($C37,'A. All deals (a)'!$C$6:$Q$58,M$5,0) -> Series E | N37: =VLOOKUP($C37,'A. All deals (a)'!$C$6:$Q$58,N$5,0) -> 0.0051805228 | O37: =VLOOKUP($C37,'A. All deals (a)'!$C$6:$Q$58,O$5,0) -> 50 | P37: =VLOOKUP($C37,'A. All deals (a)'!$C$6:$Q$58,P$5,0) -> 50 | Q37: =VLOOKUP($C37,'A. All deals (a)'!$C$6:$Q$58,Q$5,0) -> 0 | ... U37: =VLOOKUP($C37,'A. All deals (a)'!$C$6:$Q$58,U$5,0) -> 1 | V37: EPTH12
C38: Cerebras Systems Inc (2) | D38: Divyesh | E38: Peng | F38: USA | G38: Semiconductors | I38: Direct Investment | J38: =VLOOKUP($C38,'A. All deals (a)'!$C$6:$Q$58,J$5,0) -> Unrealized | K38: =VLOOKUP($C38,'A. All deals (a)'!$C$6:$Q$58,K$5,0) -> G42 Capital | L38: =VLOOKUP($C38,'A. All deals (a)'!$C$6:$Q$58,L$5,0) -> 2026 | M38: Class A/B | N38: =VLOOKUP($C38,'A. All deals (a)'!$C$6:$Q$58,N$5,0) -> 0.015990144 | O38: =VLOOKUP($C38,'A. All deals (a)'!$C$6:$Q$58,O$5,0) -> 0.03513491 | P38: =VLOOKUP($C38,'A. All deals (a)'!$C$6:$Q$58,P$5,0) -> 0.03513491 | Q38: =VLOOKUP($C38,'A. All deals (a)'!$C$6:$Q$58,Q$5,0) -> 0 | R38: =VLOOKUP($C38,'A. All deals (a)'!$C$6:$Q$58,R$5,0) -> 0 | S38: =VLOOKUP($C38,'A. All deals (a)'!$C$6:$Q$58,S$5,0) -> 647.32558 | T38: =VLOOKUP($C38,'A. All deals (a)'!$C$6:$Q$58,T$5,0) -> 647.29045 | U38: =IF(VLOOKUP($C38,'A. All deals (a)'!$C$6:$Q$58,U$5,0)>10,">10x",VLOOKUP($C38,'A. All deals (a)'!$C$6:$Q$58,U$5,0)) -> >10x | V38: EPTH8 (1.86m shares W1 plus 1.66m shares W2)
O40: =SUM(O33:O38) -> 260.855 | P40: =SUM(P33:P38) -> 260.855 | Q40: =SUM(Q33:Q38) -> 0 | R40: =SUM(R33:R38) -> 0.499965 | S40: =SUM(S33:S38) -> 904.87216 | T40: =SUM(T33:T38) -> 644.51713 | U40: =(R40+S40)/P40 -> 3.470787
C42: Core42 Holding RSC Ltd
C43: School Hack (AIREV Holding Limited) | D43: Divyesh | E43: Peng | F43: UAE | G43: AI Software | I43: Direct Investment | J43: =VLOOKUP($C43,'A. All deals (a)'!$C$6:$Q$58,J$5,0) -> Unrealized | K43: =VLOOKUP($C43,'A. All deals (a)'!$C$6:$Q$58,K$5,0) -> Core42 5 | L43: =VLOOKUP($C43,'A. All deals (a)'!$C$6:$Q$58,L$5,0) -> 2024 | M43: =VLOOKUP($C43,'A. All deals (a)'!$C$6:$Q$58,M$5,0) -> Preferred Shares | N43: =VLOOKUP($C43,'A. All deals (a)'!$C$6:$Q$58,N$5,0) -> 0.23 | O43: =VLOOKUP($C43,'A. All deals (a)'!$C$6:$Q$58,O$5,0) -> 2.75 | P43: =VLOOKUP($C43,'A. All deals (a)'!$C$6:$Q$58,P$5,0) -> 2.5 | Q43: =VLOOKUP($C43,'A. All deals (a)'!$C$6:$Q$58,Q$5,0) -> 0.25 | ... U43: =VLOOKUP($C43,'A. All deals (a)'!$C$6:$Q$58,U$5,0) -> 1 | V43: Cloud Creditg
O45: =SUM(O43) -> 2.75 | P45: =SUM(P43) -> 2.5 | Q45: =SUM(Q43) -> 0.25 | R45: =SUM(R43) -> 0 | S45: =SUM(S43) -> 2.5 | T45: =SUM(T43) -> 0 | U45: =(R45+S45)/P45 -> 1
C47: GX Investments Ltd : MGX and Related Investments
C48: MGX I LP + Denali | D48: Nitesh/Gino | E48: Peng | F48: UAE | G48: Fund | I48: MGX LP | J48: =VLOOKUP($C48,'A. All deals (a)'!$C$6:$Q$58,J$5,0) -> Unrealized | K48: =VLOOKUP($C48,'A. All deals (a)'!$C$6:$Q$58,K$5,0) -> G42 Holding | L48: =VLOOKUP($C48,'A. All deals (a)'!$C$6:$Q$58,L$5,0) -> 2024 | M48: =VLOOKUP($C48,'A. All deals (a)'!$C$6:$Q$58,M$5,0) -> LP | N48: =VLOOKUP($C48,'A. All deals (a)'!$C$6:$Q$58,N$5,0) -> 0.03125 | O48: =VLOOKUP($C48,'A. All deals (a)'!$C$6:$Q$58,O$5,0) -> 1559.798 | P48: =VLOOKUP($C48,'A. All deals (a)'!$C$6:$Q$58,P$5,0) -> 386.49987 | Q48: =VLOOKUP($C48,'A. All deals (a)'!$C$6:$Q$58,Q$5,0) -> 1173.2982 | ... U48: =VLOOKUP($C48,'A. All deals (a)'!$C$6:$Q$58,U$5,0) -> 2.6545083
C49: MGX 1 Strategic Co-invest | D49: Nitesh/Gino | E49: Peng | F49: UAE | G49: Fund | I49: MGX Co-Invest LP | J49: =VLOOKUP($C49,'A. All deals (a)'!$C$6:$Q$58,J$5,0) -> Unrealized | K49: =VLOOKUP($C49,'A. All deals (a)'!$C$6:$Q$58,K$5,0) -> G42 Holding | L49: =VLOOKUP($C49,'A. All deals (a)'!$C$6:$Q$58,L$5,0) -> 2024 | M49: =VLOOKUP($C49,'A. All deals (a)'!$C$6:$Q$58,M$5,0) -> LP | N49: =VLOOKUP($C49,'A. All deals (a)'!$C$6:$Q$58,N$5,0) -> 0.5 | O49: =VLOOKUP($C49,'A. All deals (a)'!$C$6:$Q$58,O$5,0) -> 296.60196 | P49: =VLOOKUP($C49,'A. All deals (a)'!$C$6:$Q$58,P$5,0) -> 294.25155 | Q49: =VLOOKUP($C49,'A. All deals (a)'!$C$6:$Q$58,Q$5,0) -> 2.350415 | ... U49: =VLOOKUP($C49,'A. All deals (a)'!$C$6:$Q$58,U$5,0) -> 4.0114431
C50: MGX Group Holding 1 Ltd (GP) | D50: Nitesh/Gino | E50: Peng | F50: UAE | G50: Fund | I50: MGX GP | J50: =VLOOKUP($C50,'A. All deals (a)'!$C$6:$Q$58,J$5,0) -> Unrealized | K50: =VLOOKUP($C50,'A. All deals (a)'!$C$6:$Q$58,K$5,0) -> G42 Holding | L50: =VLOOKUP($C50,'A. All deals (a)'!$C$6:$Q$58,L$5,0) -> 2024 | M50: =VLOOKUP($C50,'A. All deals (a)'!$C$6:$Q$58,M$5,0) -> Equity | N50: =VLOOKUP($C50,'A. All deals (a)'!$C$6:$Q$58,N$5,0) -> 0 | O50: =VLOOKUP($C50,'A. All deals (a)'!$C$6:$Q$58,O$5,0) -> 25 | P50: =VLOOKUP($C50,'A. All deals (a)'!$C$6:$Q$58,P$5,0) -> 25 | Q50: =VLOOKUP($C50,'A. All deals (a)'!$C$6:$Q$58,Q$5,0) -> 0 | ... U50: =VLOOKUP($C50,'A. All deals (a)'!$C$6:$Q$58,U$5,0) -> 1
O52: =SUM(O48:O50) -> 1881.4 | P52: =SUM(P48:P50) -> 705.75142 | Q52: =SUM(Q48:Q50) -> 1175.6486 | R52: =SUM(R48:R50) -> 14.688852 | S52: =SUM(S48:S50) -> 2216.6516 | T52: =SUM(T48:T50) -> 1510.9002 | U52: =(R52+S52)/P52 -> 3.1616521
O54: =O20+O30+O40+O45+O52 -> 3000.1777 | P54: =P20+P30+P40+P45+P52 -> 1812.9115 | Q54: =Q20+Q30+Q40+Q45+Q52 -> 1187.2663 | R54: =R20+R30+R40+R45+R52 -> 114.64681 | S54: =S20+S30+S40+S45+S52 -> 4542.7062 | T54: =T20+T30+T40+T45+T52 -> 2829.7527 | U54: =(R54+S54)/P54 -> 2.5689909
C58: For Notes, refer to 9. All deals (a)
C59: Position Exited or written off are highlighted

Sheet 2. Exited
C2: As of date | D2: ='D1'!D2 -> 46265
C3: EXITED INVESTMENTS
E5: 2 | G5: 4 | H5: 5 | I5: 6 | J5: 7 | K5: 8 | L5: 9 | M5: 10 | N5: 11 | O5: 12 | P5: 13 | R5: 14 | S5: 15
C6: Deals | D6: Type | E6: Status | G6: Investing Entity | H6: Vintageἀ | I6: Instrument | J6: % | K6: Committed | L6: Invested | M6: Remaining Commitment | N6: Distributions | O6: Carrying Value | P6: Gain | Q6: Gain till FY22 | R6: TVPI | S6: Additonal Upside/Downside
I7: # | J7: % | K7: $,m | L7: $,m | M7: $,m | N7: $,m | O7: $,m | P7: $,m | R7: X
C8: MOZN Holding RSC Ltd
C9: WLD Tokens | D9: Direct Investment | E9: =VLOOKUP($C9,'A. All deals (a)'!$C$6:$Q$58,E$5,0) -> Unrealized | G9: =VLOOKUP($C9,'A. All deals (a)'!$C$6:$Q$58,G$5,0) -> Mozn | H9: =VLOOKUP($C9,'A. All deals (a)'!$C$6:$Q$58,H$5,0) -> 2023 | I9: =VLOOKUP($C9,'A. All deals (a)'!$C$6:$Q$58,I$5,0) -> Tokens | J9: =VLOOKUP($C9,'A. All deals (a)'!$C$6:$Q$58,J$5,0) -> NA | K9: =VLOOKUP($C9,'A. All deals (a)'!$C$6:$Q$58,K$5,0) -> 0.006875 | L9: =VLOOKUP($C9,'A. All deals (a)'!$C$6:$Q$58,L$5,0) -> 0.006875 | M9: =VLOOKUP($C9,'A. All deals (a)'!$C$6:$Q$58,M$5,0) -> 0 | N9: =VLOOKUP($C9,'A. All deals (a)'!$C$6:$Q$58,N$5,0) -> 100 | ... P9: =VLOOKUP($C9,'A. All deals (a)'!$C$6:$Q$58,P$5,0) -> 99.993125 | Q9: n/a | R9: =VLOOKUP($C9,'A. All deals (a)'!$C$6:$Q$58,R$5,0) -> NM | S9: Full Exit for Inveniam SAR
C10: X-fusion | D10: Direct Investment | E10: =VLOOKUP($C10,'A. All deals (a)'!$C$6:$Q$58,E$5,0) -> Realized | G10: =VLOOKUP($C10,'A. All deals (a)'!$C$6:$Q$58,G$5,0) -> Mozn 2 | H10: =VLOOKUP($C10,'A. All deals (a)'!$C$6:$Q$58,H$5,0) -> 2022 | I10: =VLOOKUP($C10,'A. All deals (a)'!$C$6:$Q$58,I$5,0) -> Equity-TBC | J10: =VLOOKUP($C10,'A. All deals (a)'!$C$6:$Q$58,J$5,0) -> NA | K10: =VLOOKUP($C10,'A. All deals (a)'!$C$6:$Q$58,K$5,0) -> 493.50096 | L10: =VLOOKUP($C10,'A. All deals (a)'!$C$6:$Q$58,L$5,0) -> 493.50096 | M10: =VLOOKUP($C10,'A. All deals (a)'!$C$6:$Q$58,M$5,0) -> 0 | N10: =VLOOKUP($C10,'A. All deals (a)'!$C$6:$Q$58,N$5,0) -> 403 | ... P10: =VLOOKUP($C10,'A. All deals (a)'!$C$6:$Q$58,P$5,0) -> -90.500956 | Q10: -64.391 | R10: =VLOOKUP($C10,'A. All deals (a)'!$C$6:$Q$58,R$5,0) -> 0.81661443 | S10: Full Exit
C11: Mena Mobile Inc (Debt) | D11: Debt Investment | E11: =VLOOKUP($C11,'A. All deals (a)'!$C$6:$Q$58,E$5,0) -> Written-off | G11: =VLOOKUP($C11,'A. All deals (a)'!$C$6:$Q$58,G$5,0) -> Mozn | H11: =VLOOKUP($C11,'A. All deals (a)'!$C$6:$Q$58,H$5,0) -> 2021 | I11: =VLOOKUP($C11,'A. All deals (a)'!$C$6:$Q$58,I$5,0) -> Loan | J11: =VLOOKUP($C11,'A. All deals (a)'!$C$6:$Q$58,J$5,0) -> n/a | K11: =VLOOKUP($C11,'A. All deals (a)'!$C$6:$Q$58,K$5,0) -> 2.353982 | L11: =VLOOKUP($C11,'A. All deals (a)'!$C$6:$Q$58,L$5,0) -> 2.353982 | M11: =VLOOKUP($C11,'A. All deals (a)'!$C$6:$Q$58,M$5,0) -> 0 | N11: =VLOOKUP($C11,'A. All deals (a)'!$C$6:$Q$58,N$5,0) -> 0 | ... P11: =VLOOKUP($C11,'A. All deals (a)'!$C$6:$Q$58,P$5,0) -> -2.353982 | Q11: 0 | R11: =VLOOKUP($C11,'A. All deals (a)'!$C$6:$Q$58,R$5,0) -> 0 | S11: Written Off
C12: Esyasoft Holding (Debt) | D12: Debt Investment | E12: =VLOOKUP($C12,'A. All deals (a)'!$C$6:$Q$58,E$5,0) -> Realized | G12: =VLOOKUP($C12,'A. All deals (a)'!$C$6:$Q$58,G$5,0) -> Mozn | H12: =VLOOKUP($C12,'A. All deals (a)'!$C$6:$Q$58,H$5,0) -> 2021 | I12: =VLOOKUP($C12,'A. All deals (a)'!$C$6:$Q$58,I$5,0) -> Loan | J12: =VLOOKUP($C12,'A. All deals (a)'!$C$6:$Q$58,J$5,0) -> n/a | K12: =VLOOKUP($C12,'A. All deals (a)'!$C$6:$Q$58,K$5,0) -> 0.411765 | L12: =VLOOKUP($C12,'A. All deals (a)'!$C$6:$Q$58,L$5,0) -> 0.411765 | M12: =VLOOKUP($C12,'A. All deals (a)'!$C$6:$Q$58,M$5,0) -> 0 | N12: =VLOOKUP($C12,'A. All deals (a)'!$C$6:$Q$58,N$5,0) -> 0.47078465 | ... P12: =VLOOKUP($C12,'A. All deals (a)'!$C$6:$Q$58,P$5,0) -> 0.05901965 | Q12: 0.05901965 | R12: =VLOOKUP($C12,'A. All deals (a)'!$C$6:$Q$58,R$5,0) -> 1.1433333 | S12: Full Exit
C13: Jysan Technologies | D13: Direct Investment | E13: =VLOOKUP($C13,'A. All deals (a)'!$C$6:$Q$58,E$5,0) -> Realized | G13: =VLOOKUP($C13,'A. All deals (a)'!$C$6:$Q$58,G$5,0) -> Mozn 1 | H13: =VLOOKUP($C13,'A. All deals (a)'!$C$6:$Q$58,H$5,0) -> 2021 | I13: =VLOOKUP($C13,'A. All deals (a)'!$C$6:$Q$58,I$5,0) -> A (Ordinary Shares) | J13: =VLOOKUP($C13,'A. All deals (a)'!$C$6:$Q$58,J$5,0) -> 0.03 | K13: =VLOOKUP($C13,'A. All deals (a)'!$C$6:$Q$58,K$5,0) -> 20 | L13: =VLOOKUP($C13,'A. All deals (a)'!$C$6:$Q$58,L$5,0) -> 20 | M13: =VLOOKUP($C13,'A. All deals (a)'!$C$6:$Q$58,M$5,0) -> 0 | N13: =VLOOKUP($C13,'A. All deals (a)'!$C$6:$Q$58,N$5,0) -> 24.5 | ... P13: =VLOOKUP($C13,'A. All deals (a)'!$C$6:$Q$58,P$5,0) -> 4.5 | Q13: 0 | R13: =VLOOKUP($C13,'A. All deals (a)'!$C$6:$Q$58,R$5,0) -> 1.225 | S13: Full Exit
C14: Instadeep Limited | D14: Direct Investment | E14: =VLOOKUP($C14,'A. All deals (a)'!$C$6:$Q$58,E$5,0) -> Realized | G14: =VLOOKUP($C14,'A. All deals (a)'!$C$6:$Q$58,G$5,0) -> Mozn | H14: =VLOOKUP($C14,'A. All deals (a)'!$C$6:$Q$58,H$5,0) -> 2021 | I14: =VLOOKUP($C14,'A. All deals (a)'!$C$6:$Q$58,I$5,0) -> B Prefs | J14: =VLOOKUP($C14,'A. All deals (a)'!$C$6:$Q$58,J$5,0) -> NA | K14: =VLOOKUP($C14,'A. All deals (a)'!$C$6:$Q$58,K$5,0) -> 5.0237202 | L14: =VLOOKUP($C14,'A. All deals (a)'!$C$6:$Q$58,L$5,0) -> 5.0237202 | M14: =VLOOKUP($C14,'A. All deals (a)'!$C$6:$Q$58,M$5,0) -> 0 | N14: =VLOOKUP($C14,'A. All deals (a)'!$C$6:$Q$58,N$5,0) -> 7.9421925 | ... P14: =VLOOKUP($C14,'A. All deals (a)'!$C$6:$Q$58,P$5,0) -> 2.9184723 | Q14: 1.6721788 | R14: =VLOOKUP($C14,'A. All deals (a)'!$C$6:$Q$58,R$5,0) -> 1.5809385 | S14: Full Exit
C15: Esyasoft Holding | D15: Direct Investment | E15: =VLOOKUP($C15,'A. All deals (a)'!$C$6:$Q$58,E$5,0) -> Realized | G15: =VLOOKUP($C15,'A. All deals (a)'!$C$6:$Q$58,G$5,0) -> Mozn | H15: =VLOOKUP($C15,'A. All deals (a)'!$C$6:$Q$58,H$5,0) -> 2020 | I15: =VLOOKUP($C15,'A. All deals (a)'!$C$6:$Q$58,I$5,0) -> Convertible Note | J15: =VLOOKUP($C15,'A. All deals (a)'!$C$6:$Q$58,J$5,0) -> NA | K15: =VLOOKUP($C15,'A. All deals (a)'!$C$6:$Q$58,K$5,0) -> 2.5 | L15: =VLOOKUP($C15,'A. All deals (a)'!$C$6:$Q$58,L$5,0) -> 2.5 | M15: =VLOOKUP($C15,'A. All deals (a)'!$C$6:$Q$58,M$5,0) -> 0 | N15: =VLOOKUP($C15,'A. All deals (a)'!$C$6:$Q$58,N$5,0) -> 5 | ... P15: =VLOOKUP($C15,'A. All deals (a)'!$C$6:$Q$58,P$5,0) -> 2.5 | Q15: 2.5 | R15: =VLOOKUP($C15,'A. All deals (a)'!$C$6:$Q$58,R$5,0) -> 2 | S15: Full Exit
C16: Mena Mobile Inc | D16: Direct Investment | E16: =VLOOKUP($C16,'A. All deals (a)'!$C$6:$Q$58,E$5,0) -> Written-off | G16: =VLOOKUP($C16,'A. All deals (a)'!$C$6:$Q$58,G$5,0) -> Mozn | H16: =VLOOKUP($C16,'A. All deals (a)'!$C$6:$Q$58,H$5,0) -> 2019 | I16: =VLOOKUP($C16,'A. All deals (a)'!$C$6:$Q$58,I$5,0) -> B Prefs | J16: =VLOOKUP($C16,'A. All deals (a)'!$C$6:$Q$58,J$5,0) -> 0.14 | K16: =VLOOKUP($C16,'A. All deals (a)'!$C$6:$Q$58,K$5,0) -> 8 | L16: =VLOOKUP($C16,'A. All deals (a)'!$C$6:$Q$58,L$5,0) -> 8 | M16: =VLOOKUP($C16,'A. All deals (a)'!$C$6:$Q$58,M$5,0) -> 0 | N16: =VLOOKUP($C16,'A. All deals (a)'!$C$6:$Q$58,N$5,0) -> 0 | ... P16: =VLOOKUP($C16,'A. All deals (a)'!$C$6:$Q$58,P$5,0) -> -8 | Q16: -8 | R16: =VLOOKUP($C16,'A. All deals (a)'!$C$6:$Q$58,R$5,0) -> 0 | S16: Written Off
C17: Glass Earth Holdings LLC | D17: Debt Investment | E17: =VLOOKUP($C17,'A. All deals (a)'!$C$6:$Q$58,E$5,0) -> Written-off | G17: =VLOOKUP($C17,'A. All deals (a)'!$C$6:$Q$58,G$5,0) -> Mozn | H17: =VLOOKUP($C17,'A. All deals (a)'!$C$6:$Q$58,H$5,0) -> 2019 | I17: =VLOOKUP($C17,'A. All deals (a)'!$C$6:$Q$58,I$5,0) -> Promissory Note | J17: =VLOOKUP($C17,'A. All deals (a)'!$C$6:$Q$58,J$5,0) -> n/a | K17: =VLOOKUP($C17,'A. All deals (a)'!$C$6:$Q$58,K$5,0) -> 8 | L17: =VLOOKUP($C17,'A. All deals (a)'!$C$6:$Q$58,L$5,0) -> 8 | M17: =VLOOKUP($C17,'A. All deals (a)'!$C$6:$Q$58,M$5,0) -> 0 | N17: =VLOOKUP($C17,'A. All deals (a)'!$C$6:$Q$58,N$5,0) -> 0 | ... P17: =VLOOKUP($C17,'A. All deals (a)'!$C$6:$Q$58,P$5,0) -> -8 | Q17: -8 | R17: =VLOOKUP($C17,'A. All deals (a)'!$C$6:$Q$58,R$5,0) -> 0 | S17: =VLOOKUP($C17,'A. All deals (a)'!$C$6:$Q$58,S$5,0) -> In Default
C18: Jollychic Holding Limited | D18: Direct Investment | E18: =VLOOKUP($C18,'A. All deals (a)'!$C$6:$Q$58,E$5,0) -> Written-off | G18: =VLOOKUP($C18,'A. All deals (a)'!$C$6:$Q$58,G$5,0) -> Mozn | H18: =VLOOKUP($C18,'A. All deals (a)'!$C$6:$Q$58,H$5,0) -> 2019 | I18: =VLOOKUP($C18,'A. All deals (a)'!$C$6:$Q$58,I$5,0) -> C+ Prefs | J18: =VLOOKUP($C18,'A. All deals (a)'!$C$6:$Q$58,J$5,0) -> 0.056999998 | K18: =VLOOKUP($C18,'A. All deals (a)'!$C$6:$Q$58,K$5,0) -> 65 | L18: =VLOOKUP($C18,'A. All deals (a)'!$C$6:$Q$58,L$5,0) -> 65 | M18: =VLOOKUP($C18,'A. All deals (a)'!$C$6:$Q$58,M$5,0) -> 0 | N18: =VLOOKUP($C18,'A. All deals (a)'!$C$6:$Q$58,N$5,0) -> 0 | ... P18: =VLOOKUP($C18,'A. All deals (a)'!$C$6:$Q$58,P$5,0) -> -65 | Q18: -65 | R18: =VLOOKUP($C18,'A. All deals (a)'!$C$6:$Q$58,R$5,0) -> 0 | S18: =VLOOKUP($C18,'A. All deals (a)'!$C$6:$Q$58,S$5,0) -> In Liquidation
K20: =SUM(K9:K18) -> 604.7973 | L20: =SUM(L9:L18) -> 604.7973 | M20: =SUM(M9:M18) -> 0 | N20: =SUM(N9:N18) -> 540.91298 | O20: =SUM(O9:O18) -> 0 | P20: =SUM(P9:P18) -> -63.884321 | Q20: =SUM(Q10:Q18) -> -141.1598 | R20: =(N20+O20)/L20 -> 0.89437069
C22: G42 Investments AI Holding RSC Ltd
C23: Honor Device Co Ltd | D23: Direct Investment | E23: =VLOOKUP($C23,'A. All deals (a)'!$C$6:$Q$58,E$5,0) -> Realized | G23: =VLOOKUP($C23,'A. All deals (a)'!$C$6:$Q$58,G$5,0) -> G42 3 | H23: =VLOOKUP($C23,'A. All deals (a)'!$C$6:$Q$58,H$5,0) -> 2022 | I23: =VLOOKUP($C23,'A. All deals (a)'!$C$6:$Q$58,I$5,0) -> Equity-TBC | J23: =VLOOKUP($C23,'A. All deals (a)'!$C$6:$Q$58,J$5,0) -> NA | K23: =VLOOKUP($C23,'A. All deals (a)'!$C$6:$Q$58,K$5,0) -> 800 | L23: =VLOOKUP($C23,'A. All deals (a)'!$C$6:$Q$58,L$5,0) -> 800 | M23: =VLOOKUP($C23,'A. All deals (a)'!$C$6:$Q$58,M$5,0) -> 0 | N23: =VLOOKUP($C23,'A. All deals (a)'!$C$6:$Q$58,N$5,0) -> 802.8 | ... P23: =VLOOKUP($C23,'A. All deals (a)'!$C$6:$Q$58,P$5,0) -> 2.8 | Q23: 54.67 | R23: =VLOOKUP($C23,'A. All deals (a)'!$C$6:$Q$58,R$5,0) -> 1.0035
C24: Sinovation Disrupt Fund, L.P. | D24: Fund Investment | E24: =VLOOKUP($C24,'A. All deals (a)'!$C$6:$Q$58,E$5,0) -> Realized | G24: =VLOOKUP($C24,'A. All deals (a)'!$C$6:$Q$58,G$5,0) -> G42 Investments | H24: =VLOOKUP($C24,'A. All deals (a)'!$C$6:$Q$58,H$5,0) -> 2020 | I24: =VLOOKUP($C24,'A. All deals (a)'!$C$6:$Q$58,I$5,0) -> LP | J24: =VLOOKUP($C24,'A. All deals (a)'!$C$6:$Q$58,J$5,0) -> n/a | K24: =VLOOKUP($C24,'A. All deals (a)'!$C$6:$Q$58,K$5,0) -> 50 | L24: =VLOOKUP($C24,'A. All deals (a)'!$C$6:$Q$58,L$5,0) -> 24.959693 | M24: =VLOOKUP($C24,'A. All deals (a)'!$C$6:$Q$58,M$5,0) -> 0 | N24: =VLOOKUP($C24,'A. All deals (a)'!$C$6:$Q$58,N$5,0) -> 25.403521 | ... P24: =VLOOKUP($C24,'A. All deals (a)'!$C$6:$Q$58,P$5,0) -> 0.44382835 | Q24: -1.265 | R24: =VLOOKUP($C24,'A. All deals (a)'!$C$6:$Q$58,R$5,0) -> 1.0177818
K26: =SUM(K23:K24) -> 850 | L26: =SUM(L23:L24) -> 824.95969 | M26: =SUM(M23:M24) -> 0 | N26: =SUM(N23:N24) -> 828.20352 | O26: =SUM(O23:O24) -> 0 | P26: =SUM(P23:P24) -> 3.2438283 | Q26: =SUM(Q23:Q24) -> 53.405 | R26: =(N26+O26)/L26 -> 1.0039321 | S26: =O26+N26-L26 -> 3.2438283
C28: G42 Capital SPV RSC Ltd
C32: Core42 Holding RSC Ltd
K36: =K20+K26+K30+K34 -> 1454.7973 | L36: =L20+L26+L30+L34 -> 1429.757 | M36: =M20+M26+M30+M34 -> 0 | N36: =N20+N26+N30+N34 -> 1369.1165 | O36: =O20+O26+O30+O34 -> 0 | P36: =P20+P26+P30+P34 -> -60.640493 | Q36: =Q20+Q26+Q30+Q34 -> -87.754802 | R36: =(N36+O36)/L36 -> 0.95758685
C40: For Notes, refer to 9. All deals (a)
C41: Position Exited or written off are highlighted

Sheet CF (Equity, Debt)
B2: E Q U I T Y
B3: Accounting entity | C3: Investment | D3: Payment date | E3: Contributions (in USD, Mn) | F3: Distributions (in USD, Mn) | G3: Currency | H3: Investment / Exit Amt (investee currency) | I3: Investment / Exit Amount (USD) | J3: Consideration (shares) | K3: Comment
B4: =VLOOKUP(C4,'A. All deals (a)'!$C$9:$F$49,4,0) -> Mozn | C4: Jollychic Holding Limited | D4: 43470 | E4: =-I4*10^-6 -> -30 | G4: USD | H4: 30000000 | I4: =H4 -> 30000000 | J4: 6100312
B5: =VLOOKUP(C5,'A. All deals (a)'!$C$9:$F$49,4,0) -> Mozn | C5: Jollychic Holding Limited | D5: 43724 | E5: =-I5*10^-6 -> -20 | G5: USD | H5: 20000000 | I5: =H5 -> 20000000 | J5: 4204767.4
B6: =VLOOKUP(C6,'A. All deals (a)'!$C$9:$F$49,4,0) -> Mozn | C6: Jollychic Holding Limited | D6: 43724 | E6: =-I6*10^-6 -> -15 | G6: USD | H6: 15000000 | I6: =H6 -> 15000000 | J6: 3153575.6
B7: =VLOOKUP(C7,'A. All deals (a)'!$C$9:$F$49,4,0) -> Mozn | C7: Mena Mobile Inc | D7: 43563 | E7: =-I7*10^-6 -> -8 | G7: USD | H7: 8000000 | I7: =H7 -> 8000000 | J7: 21419829
B8: =VLOOKUP(C8,'A. All deals (a)'!$C$9:$F$49,4,0) -> Mozn | C8: Flyr Inc | D8: 43570 | E8: =-I8*10^-6 -> -4.9999981 | G8: USD | H8: 4999998.1 | I8: =H8 -> 4999998.1 | J8: 2625467
B9: =VLOOKUP(C9,'A. All deals (a)'!$C$9:$F$49,4,0) -> Mozn | C9: Flyr Inc | D9: 43915 | E9: =-I9*10^-6 -> -5.0000019 | G9: USD | H9: =10000000-H8 -> 5000001.9 | I9: =H9 -> 5000001.9 | J9: 2580015
B10: =VLOOKUP(C10,'A. All deals (a)'!$C$9:$F$49,4,0) -> Mozn | C10: Esyasoft Holding | D10: 43870 | E10: =-I10*10^-6 -> -2.5 | G10: USD | H10: 2500000 | I10: =H10 -> 2500000 | J10: N/A
B11: =VLOOKUP(C11,'A. All deals (a)'!$C$9:$F$49,4,0) -> Mozn | C11: Beyond Limits | D11: 43879 | E11: =-I11*10^-6 -> -20 | G11: USD | H11: 20000000 | I11: =H11 -> 20000000 | J11: 4084038
B12: =VLOOKUP(C12,'A. All deals (a)'!$C$9:$F$49,4,0) -> Mozn | C12: Beyond Limits | D12: 43921 | E12: =-I12*10^-6 -> -30 | G12: USD | H12: 30000000 | I12: =H12 -> 30000000 | J12: 5822642
B13: =VLOOKUP(C13,'A. All deals (a)'!$C$9:$F$49,4,0) -> Mozn | C13: Beyond Limits | D13: 43989 | E13: =-I13*10^-6 -> -30 | G13: USD | H13: 30000000 | I13: =H13 -> 30000000 | J13: 5822642
B14: =VLOOKUP(C14,'A. All deals (a)'!$C$9:$F$49,4,0) -> Mozn | C14: Beyond Limits | D14: 44103 | E14: =-I14*10^-6 -> -10 | G14: USD | H14: 10000000 | I14: =H14 -> 10000000 | J14: 1940880
B15: =VLOOKUP(C15,'A. All deals (a)'!$C$9:$F$49,4,0) -> Mozn | C15: ONT plc | D15: 43968 | E15: =-I15*10^-6 -> -50 | G15: USD | H15: 50000000 | I15: 50000000 | J15: 15277680
B16: =VLOOKUP(C16,'A. All deals (a)'!$C$9:$F$49,4,0) -> Mozn | C16: ONT plc | D16: 44006 | E16: =-I16*10^-6 -> -27.268351 | G16: GBP | H16: 21029625 | I16: 27268351 | J16: 9000000
B17: =VLOOKUP(C17,'A. All deals (a)'!$C$9:$F$49,4,0) -> Mozn | C17: ONT plc | D17: 43837 | E17: =-I17*10^-6 -> -18.109441 | G17: GBP | H17: 14386480 | I17: 18109441 | J17: 6362180
B18: =VLOOKUP(C18,'A. All deals (a)'!$C$9:$F$49,4,0) -> Mozn | C18: ONT plc | D18: 43990 | E18: =-I18*10^-6 -> -34.851687 | G18: GBP | H18: 26085573 | I18: 34851687 | J18: 11381140
B19: =VLOOKUP(C19,'A. All deals (a)'!$C$9:$F$49,4,0) -> Mozn | C19: ONT plc | D19: 44315 | E19: =-I19*10^-6 -> -11.24078 | G19: GBP | H19: 8074920 | I19: 11240780 | J19: 2307120
B20: =VLOOKUP(C20,'A. All deals (a)'!$C$9:$F$49,4,0) -> Mozn | C20: Heygears | D20: 44166 | E20: =-I20*10^-6 -> -60 | G20: USD | H20: 60000000 | I20: =H20 -> 60000000 | J20: 3565017.2
B21: =VLOOKUP(C21,'A. All deals (a)'!$C$9:$F$49,4,0) -> Mozn 1 | C21: Jysan Technologies | D21: 44363 | E21: =-I21*10^-6 -> -20 | G21: USD | H21: 20000000 | I21: =H21 -> 20000000 | J21: 7959497
B22: =VLOOKUP(C22,'A. All deals (a)'!$C$9:$F$49,4,0) -> Mozn | C22: Cerebras Systems Inc (1) | D22: 44488 | E22: =-I22*10^-6 -> -39.999983 | G22: USD | H22: 39999983 | I22: =H22 -> 39999983 | J22: 1441711
B23: =VLOOKUP(C23,'A. All deals (a)'!$C$9:$F$49,4,0) -> Mozn | C23: Endless Studios LLC | D23: 44494 | E23: =-I23*10^-6 -> -3 | G23: USD | H23: 3000000 | I23: =H23 -> 3000000 | J23: 3000000
B24: =VLOOKUP(C24,'A. All deals (a)'!$C$9:$F$49,4,0) -> Mozn | C24: Instadeep Limited | D24: 44550 | E24: =-I24*10^-6 -> -5.0237202 | G24: GBP | H24: 3679995.5 | I24: 5023720.2 | J24: 33267
B25: =VLOOKUP(C25,'A. All deals (a)'!$C$9:$F$49,4,0) -> Mozn 2 | C25: X-fusion | D25: 44574 | E25: =-I25*10^-6 -> -493.50096 | G25: USD | H25: 8.9350096e+08 | I25: 4.9350096e+08
B26: =VLOOKUP(C26,'A. All deals (a)'!$C$9:$F$49,4,0) -> G42 Investments | C26: DriveNets | D26: 44643 | E26: =-I26*10^-6 -> -200 | G26: USD | H26: 200000000 | I26: =H26 -> 200000000
B27: =VLOOKUP(C27,'A. All deals (a)'!$C$9:$F$49,4,0) -> G42 Investments | C27: DriveNets | D27: 44680 | E27: =-I27*10^-6 -> -100 | G27: USD | H27: 100000000 | I27: =H27 -> 100000000
B28: =VLOOKUP(C28,'A. All deals (a)'!$C$9:$F$49,4,0) -> Mozn | C28: Esyasoft Holding | D28: 44691 | F28: 5 | G28: USD
B29: =VLOOKUP(C29,'A. All deals (a)'!$C$9:$F$49,4,0) -> G42 Investments | C29: vTv Therapeutics Inc. | D29: 44712 | E29: =-I29*10^-6 -> -12.5 | G29: USD | H29: 12500000 | I29: =H29 -> 12500000 | J29: ='%'!D22 -> 259657
B30: =VLOOKUP(C30,'A. All deals (a)'!$C$9:$F$49,4,0) -> G42 3 | C30: Honor Device Co Ltd | D30: 44769 | E30: =-I30*10^-6 -> -600 | G30: USD | H30: 600000000 | I30: =H30 -> 600000000
B31: =VLOOKUP(C31,'A. All deals (a)'!$C$9:$F$49,4,0) -> G42 3 | C31: Honor Device Co Ltd | D31: 44849 | E31: =-I31*10^-6 -> -200 | G31: USD | H31: 200000000 | I31: =H31 -> 200000000
B32: =VLOOKUP(C32,'A. All deals (a)'!$C$9:$F$49,4,0) -> Mozn | C32: Applied AI Corporation Limited | D32: 44861 | E32: =-I32*10^-6 -> -4.75 | G32: USD | H32: 4750000 | I32: =H32 -> 4750000
B33: =VLOOKUP(C33,'A. All deals (a)'!$C$9:$F$49,4,0) -> Mozn 4 | C33: eSpace | D33: 44892 | E33: =-I33*10^-6 -> -15 | G33: USD | H33: 15000000 | I33: =H33 -> 15000000
B34: =VLOOKUP(C34,'A. All deals (a)'!$C$9:$F$49,4,0) -> G42 Investments | C34: vTv Therapeutics Inc. | D34: 44985 | E34: =-I34*10^-6 -> -12.03125 | G34: USD | H34: 12031250 | I34: =H34 -> 12031250 | J34: 10386274
B35: =VLOOKUP(C35,'A. All deals (a)'!$C$9:$F$49,4,0) -> Mozn | C35: Tools for Humanity Corporation | D35: 45075 | E35: =-I35*10^-6 -> -14.999999 | G35: USD | H35: 14999999 | I35: =H35 -> 14999999
B36: =VLOOKUP(C36,'A. All deals (a)'!$C$9:$F$49,4,0) -> Mozn | C36: WLD Tokens | D36: 45075 | E36: =-I36*10^-6 -> -0.005875 | G36: USD | I36: 5875
B37: =VLOOKUP(C37,'A. All deals (a)'!$C$9:$F$49,4,0) -> Mozn | C37: WLD Tokens | D37: 45114 | E37: =-I37*10^-6 -> -0.001 | G37: USD | I37: 1000
B38: =VLOOKUP(C38,'A. All deals (a)'!$C$9:$F$49,4,0) -> Mozn | C38: Applied AI Corporation Limited | D38: 45121 | E38: =-I38*10^-6 -> -2.75 | G38: USD | I38: 2750000
B39: =VLOOKUP(C39,'A. All deals (a)'!$C$9:$F$49,4,0) -> Mozn | C39: Instadeep Limited | D39: 45138 | F39: =I39*10^-6 -> 7.8207761 | G39: USD | H39: 6090345.2 | I39: 7820776.1
B40: =VLOOKUP(C40,'A. All deals (a)'!$C$9:$F$49,4,0) -> Mozn 1 | C40: Jysan Technologies | D40: 45149 | F40: 24.5 | G40: USD | I40: 24500000 | J40: 7959497
B41: =VLOOKUP(C41,'A. All deals (a)'!$C$9:$F$49,4,0) -> Mozn | C41: Endless Studios LLC | D41: 45167 | E41: =-I41*10^-6 -> -5 | G41: USD | I41: 5000000 | J41: 5000000
B42: =VLOOKUP(C42,'A. All deals (a)'!$C$9:$F$49,4,0) -> Mozn | C42: E-line Ventures LLC | D42: 45167 | E42: -6 | G42: USD | I42: 6000000 | J42: =I42/1.34 -> 4477611.9
B43: =VLOOKUP(C43,'A. All deals (a)'!$C$9:$F$49,4,0) -> G42 3 | C43: Honor Device Co Ltd | D43: 45224 | F43: 2.8 | G43: USD
B44: =VLOOKUP(C44,'A. All deals (a)'!$C$9:$F$49,4,0) -> G42 3 | C44: Honor Device Co Ltd | D44: 45224 | F44: 800 | G44: USD
B45: =VLOOKUP(C45,'A. All deals (a)'!$C$9:$F$49,4,0) -> Mozn 2 | C45: X-fusion | D45: 45224 | F45: 403 | G45: USD
B46: =VLOOKUP(C46,'A. All deals (a)'!$C$9:$F$49,4,0) -> Mozn | C46: Instadeep Limited | D46: 45224 | F46: 0.12141643 | G46: USD
B47: =VLOOKUP(C47,'A. All deals (a)'!$C$9:$F$49,4,0) -> Mozn | C47: Applied AI Corporation Limited | D47: 45295 | E47: =-I47*10^-6 -> -4 | G47: USD | H47: 4000000 | I47: =H47 -> 4000000
B48: =VLOOKUP(C48,'A. All deals (a)'!$C$9:$F$49,4,0) -> Core42 5 | C48: School Hack (AIREV Holding Limited) | D48: 45322 | E48: =-I48*10^-6 -> -2.5 | G48: USD | H48: =I48 -> 2500000 | I48: 2500000
B49: =VLOOKUP(C49,'A. All deals (a)'!$C$9:$F$49,4,0) -> G42 Capital | C49: Life Biosciences LLC | D49: 45349 | E49: =-I49*10^-6 -> -20 | G49: USD | I49: 20000000
B50: G42 Capital | C50: Verses AI Inc | D50: 45463 | E50: -10 | G50: USD | I50: 10000000
B51: =VLOOKUP(C51,'A. All deals (a)'!$C$9:$F$49,4,0) -> G42 Capital | C51: Life Biosciences LLC | D51: 45596 | E51: =-I51*10^-6 -> -20 | G51: USD | I51: 20000000
B52: Mozn | C52: WLD Tokens | D52: 45610 | F52: 100 | G52: USD | I52: 100000000
B53: G42 Capital | C53: Inveniam Ltd | D53: 45611 | E53: -100 | G53: USD | I53: 100000000
B54: Mozn | C54: Applied AI Corporation Limited | D54: 45617 | E54: =-I54*10^-6 -> -3.5 | G54: USD | H54: 3500000 | I54: =H54 -> 3500000
B55: G42 Capital | C55: Inveniam Ltd | D55: 45645 | F55: 0.499965 | G55: USD | H55: 499965 | I55: 499965
B56: G42 Capital | C56: Liquid AI | D56: 45737 | E56: =-I56*10^-6 -> -19.999882 | G56: USD | I56: 19999882
B57: G42 | C57: DriveNets | D57: 45769 | F57: =I57/1000000 -> 84.804486 | G57: USD | I57: 84804486
B58: G42 Capital | C58: Neuralink | D58: 45812 | E58: =-I58*10^-6 -> -50 | G58: USD | I58: 50000000
B59: G42 Capital | C59: Cerebras Systems Inc (2) | D59: 46027 | E59: =-I59/1000000 -> -0.01857516 | G59: USD | I59: 18575.16
B60: G42 Capital | C60: Liquid AI | D60: 46063 | E60: =-I60/1000000 -> -40.819981 | G60: USD | I60: 40819981
B61: G42 Capital | C61: Cerebras Systems Inc (2) | D61: 46129 | E61: =-I61/1000000 -> -0.01655975 | G61: USD | I61: 16559.75
B64: L O AN | P R O M I S S O R Y N O T E S | D E B T
B65: Mozn | C65: Glass Earth Holdings LLC | D65: 43635 | E65: -8 | G65: USD | H65: 8000000 | I65: =H65 -> 8000000
B66: Mozn | C66: Mena Mobile Inc (Debt) | D66: 44293 | E66: -2.353982 | G66: USD | H66: =-E66*10^6 -> 2353982 | I66: =H66 -> 2353982
B67: Mozn | C67: Esyasoft Holding (Debt) | D67: 44384 | E67: =-I67*10^-6 -> -0.411765 | G67: USD | H67: 2500000 | I67: 411765
B68: Mozn | C68: Esyasoft Holding (Debt) | D68: 44902 | F68: =(411765+59019.65)*10^-6 -> 0.47078465 | G68: USD | H68: =F68*10^6 -> 470784.65 | I68: 470784.65

Sheet CF (Funds)
B2: F U N D S
B3: Entity | C3: Investment | D3: Payment date | E3: Contributions (USD, Mn) | F3: Distributions (USD, Mn) | G3: Currency | H3: Cashflows | I3: Description
B4: G42 | C4: Sinovation Disrupt Fund, L.P. | D4: 44153 | E4: =H4 -> -10.5 | G4: USD | H4: -10.5 | I4: 1st Capital Call
B5: G42 | C5: Sinovation Disrupt Fund, L.P. | D5: 44238 | E5: =H5 -> 4.214027 | G5: USD | H5: 4.214027 | I5: Partial return of the 1st Capital Call
B6: G42 | C6: Sinovation Disrupt Fund, L.P. | D6: 44238 | F6: =H6 -> 0.05044835 | G6: USD | H6: 0.05044835 | I6: Interest Catchup
B7: G42 | C7: Sinovation Disrupt Fund, L.P. | D7: 44285 | E7: =H7 -> -6.433746 | G7: USD | H7: -6.433746 | I7: 2nd Capital Calll
B8: G42 | C8: Sinovation Disrupt Fund, L.P. | D8: 44269 | E8: =H8 -> 1.1352074 | G8: USD | H8: 1.1352074 | I8: Return of Capital fund
B9: G42 | C9: Sinovation Disrupt Fund, L.P. | D9: 44269 | F9: =H9 -> 0.0259 | G9: USD | H9: 0.0259 | I9: Interest Catchup
B10: G42 | C10: Sinovation Disrupt Fund, L.P. | D10: 44483 | E10: =H10 -> -7.567138 | G10: USD | H10: -7.567138 | I10: 3rd Capital Call
B11: G42 | C11: Sinovation Disrupt Fund, L.P. | D11: 44554 | E11: =H11 -> -7.385016 | G11: USD | H11: -7.385016 | I11: 4th Capital Call
B12: G42 | C12: Sinovation Disrupt Fund, L.P. | D12: 44554 | E12: =H12 -> 4.0733456 | G12: USD | H12: 4.0733456 | I12: Return of Capital fund
B13: G42 | C13: Sinovation Disrupt Fund, L.P. | D13: 44554 | F13: =H13 -> 0.139694 | G13: USD | H13: 0.139694 | I13: Interest Catchup
B14: G42 | C14: Sinovation Disrupt Fund, L.P. | D14: 44703 | E14: =H14 -> 5.673074 | G14: USD | H14: 5.673074 | I14: Return of Capital fund
B15: G42 | C15: Sinovation Disrupt Fund, L.P. | D15: 44703 | F15: =H15 -> 0.227786 | G15: USD | H15: 0.227786 | I15: Interest Catchup
B16: G42 | C16: Sinovation Disrupt Fund, L.P. | D16: 44776 | E16: =H16 -> -3.235493 | G16: USD | H16: -3.235493 | I16: 5th Capital Call
B17: G42 | C17: Sinovation Disrupt Fund, L.P. | D17: 44960 | E17: =H17 -> -2.631528 | G17: USD | H17: -2.631528 | I17: 6th Capital Call
B18: G42 | C18: Sinovation Disrupt Fund, L.P. | D18: 45085 | E18: =H18 -> 1.912557 | G18: USD | H18: 1.912557 | I18: Return of Capital fund
B19: G42 | C19: Sinovation Disrupt Fund, L.P. | D19: 45166 | E19: -1.799122 | G19: USD | H19: -1.799122 | I19: 7th Capital Call
B20: G42 | C20: Sinovation Disrupt Fund, L.P. | D20: 45218 | E20: -2.415861 | G20: USD | H20: -2.415861 | I20: 8th Capital Call
B21: G42 | C21: Sinovation Disrupt Fund, L.P. | D21: 45323 | F21: =24.959693 -> 24.959693 | G21: USD | H21: =F21 -> 24.959693 | I21: Exit Proceeds (full and final)
B22: G42 | C22: North Summit Capital Fund | D22: 43665 | E22: =H22 -> -3 | G22: USD | H22: -3 | I22: 1st Capital Call
B23: G42 | C23: North Summit Capital Fund | D23: 43983 | E23: =H23 -> -4.485 | G23: USD | H23: -4.485 | I23: 2nd Capital Calll
B24: G42 | C24: North Summit Capital Fund | D24: 43879 | E24: =H24 -> -9.50975 | G24: USD | H24: -9.50975 | I24: 3rd Capital Call
B25: G42 | C25: North Summit Capital Fund | D25: 43934 | E25: =H25 -> -41.3 | G25: USD | H25: -41.3 | I25: 4th Capital Call
B26: G42 | C26: North Summit Capital Fund | D26: 44151 | E26: =H26 -> 9.95 | G26: USD | H26: 9.95 | I26: 5th Capital Call-Partial return of the 4th Capital Call
B27: G42 | C27: North Summit Capital Fund | D27: 44151 | E27: =H27 -> -10.455 | G27: USD | H27: -10.455 | I27: 5th Capital Call
B28: G42 | C28: North Summit Capital Fund | D28: 44196 | E28: =H28 -> 4.975 | G28: USD | H28: 4.975 | I28: 6th Capital Call-Partial return of the 4th Capital Call
B29: G42 | C29: North Summit Capital Fund | D29: 44196 | E29: =H29 -> -3.452293 | G29: USD | H29: -3.452293 | I29: 6th Capital Call
B30: G42 | C30: North Summit Capital Fund | D30: 44196 | F30: =H30 -> 0.582902 | G30: USD | H30: 0.582902 | I30: 6th Capital Call-Dividends from Project Topscore
B31: G42 | C31: North Summit Capital Fund | D31: 44370 | E31: =H31 -> -5.97 | G31: USD | H31: -5.97 | I31: 7th Capital Call
B32: G42 | C32: North Summit Capital Fund | D32: 44400 | E32: =H32 -> -0.75 | G32: USD | H32: -0.75 | I32: 8th Capital Call
B33: G42 | C33: North Summit Capital Fund | D33: 44400 | F33: =H33 -> 0.445059 | G33: USD | H33: 0.445059 | I33: 8th Capital Call-Dividends from Project Topscore
B34: G42 | C34: North Summit Capital Fund | D34: 44554 | E34: =H34 -> 1.78239 | G34: USD | H34: 1.78239 | I34: 9th Capital Call-Return of Capital Fund
B35: G42 | C35: North Summit Capital Fund | D35: 44676 | E35: =H35 -> -21 | G35: USD | H35: -21 | I35: 12th Capital Call
B36: G42 | C36: North Summit Capital Fund | D36: 45243 | F36: =H36 -> 6.78791 | G36: USD | H36: 6.78791 | I36: 13th Capital Call & Distribution #4
B37: G42 | C37: North Summit Capital Fund | D37: 45470 | E37: =H37 -> -0.055697 | G37: USD | H37: =-55697*10^-6 -> -0.055697 | I37: 14th Capital Call
B38: G42 | C38: North Summit Capital Fund | D38: 45611 | E38: =H38 -> -0.031561 | G38: USD | H38: =-31561*10^-6 -> -0.031561 | I38: 15th Capital Call
B39: G42 | C39: New Space Capital Fund I | D39: 44087 | E39: =H39*1.1 -> -20.917553 | G39: EUR | H39: -19.015957 | I39: Drawdown1
B40: G42 | C40: New Space Capital Fund I | D40: 44287 | E40: -0.21103182 | G40: EUR | H40: -0.21103182 | I40: Drawdown2
B41: G42 | C41: New Space Capital Fund I | D41: 44442 | E41: =1.18*H41 -> -0.23965473 | G41: EUR | H41: =-203097.23*10^-6 -> -0.20309723 | I41: Drawdown3
B42: G42 | C42: New Space Capital Fund I | D42: 44623 | E42: =1.11*H42 -> -0.25893585 | G42: EUR | H42: =-233275.54*10^-6 -> -0.23327554 | I42: Drawdown4
B43: G42 | C43: New Space Capital Fund I | D43: 44784 | E43: =1.03*H43 -> 0.015224657 | G43: EUR | H43: =14781.22*10^-6 -> 0.01478122 | I43: Return of Capital
B44: G42 | C44: New Space Capital Fund I | D44: 44956 | E44: =9741387*10^-6*1.08341 -> 10.553916 | G44: EUR | H44: =9741387*10^-6 -> 9.741387 | I44: Return of Capital
B45: G42 | C45: New Space Capital Fund I | D45: 44956 | F45: =2728214.02*10^-6*1.08341 -> 2.9557744 | G45: EUR | H45: 2.728214 | I45: Distribution | Actualization Interest
B46: G42 | C46: New Space Capital Fund I | D46: 45170 | E46: -0.22532724 | G46: EUR | H46: -0.22532724 | I46: Drawdown (Notice 10)
B47: G42 | C47: New Space Capital Fund I | D47: 45260 | E47: -0.28531252 | G47: EUR | H47: -0.28531252 | I47: Drawdown (Notice 11)
B48: G42 | C48: New Space Capital Fund I | D48: 45321 | E48: -2.4198785 | G48: EUR | H48: -2.4198785 | I48: Drawdown (Notice 12)
B49: G42 | C49: New Space Capital Fund I | D49: 45372 | E49: -0.21649574 | G49: EUR | H49: -0.21649574 | I49: Drawdown (Notice 13)
B50: G42 | C50: New Space Capital Fund I | D50: 45454 | F50: =H50*1.0743 -> 0.46369473 | G50: EUR | H50: =431624.99*10^-6 -> 0.43162499 | I50: Drawdown 14| Actualization Interest Distribution
B51: G42 | C51: New Space Capital Fund I | D51: 45505 | E51: =H51*1.0883 -> -1.7173904 | G51: EUR | H51: =-1578048.66*10^-6 -> -1.5780487 | I51: Drawdown (Notice 15)
B52: G42 | C52: New Space Capital Fund I | D52: 45604 | E52: =H52*1.07205 -> -1.8749406 | G52: EUR | H52: =-1748930.22*10^-6 -> -1.7489302 | I52: Drawdown (Notice 16)
B53: G42 | C53: New Space Capital Fund I | D53: 45692 | E53: =(H53-0.34559)*1.08 -> 2.1803052 | F53: =0.34559*1.08 -> 0.3732372 | G53: EUR | H53: 2.3643911 | I53: Drawdown (Notice 17)
B54: G42 | C54: New Space Capital Fund I | D54: 45736 | E54: =H54*1.08579 -> -0.77167877 | G54: EUR | H54: -0.7107072 | I54: Drawdown (Notice 18)
B55: G42 | C55: New Space Capital Fund I | D55: 45834 | E55: =H55*1.16999 -> -2.7197917 | G55: EUR | H55: =-'8. NewSpace'!R18*10^-6 -> -2.3246282 | I55: Drawdown (Notice 19)
B56: G42 | C56: New Space Capital Fund I | D56: 45874 | E56: =-H56*1.16999 -> 5.1370022 | G56: EUR | H56: =('8. NewSpace'!S15+'8. NewSpace'!S16)*10^-6 -> -4.3906377 | I56: Drawdown (Notice 20) | Return of Capital
B57: G42 | C57: New Space Capital Fund I | D57: 45874 | F57: 0.91406649 | G57: EUR | H57: ='8. NewSpace'!S17*10^-6 -> -0.78126009 | I57: Drawdown (Notice 20) Equalization Interest
B58: G42 | C58: New Space Capital Fund I | D58: 45874 | E58: =-H58*1.16999 -> -2.1903083 | G58: EUR | H58: ='8. NewSpace'!S18*10^-6 -> 1.8720744 | I58: Drawdown (Notice 20) | Capital Call
B59: G42 | C59: New Space Capital Fund I | D59: 46021 | E59: =-H59*1.16999 -> -0.73970042 | G59: EUR | H59: ='8. NewSpace'!U18*10^-6 -> 0.63222798 | I59: Drawdown (Notice 21) | Capital Call
B60: G42 | C60: New Space Capital Fund I | D60: 46021 | E60: =-H60*1.16999 -> 2.0711612 | F60: =E60 -> 2.0711612 | G60: EUR | H60: ='8. NewSpace'!U20*10^-6 -> -1.7702383 | I60: Distribution (Notice 21)
B61: G42 | C61: New Space Capital Fund I | D61: 46146 | E61: =-H61*1.16999 -> 0 | G61: EUR | H61: ='8. NewSpace'!U21*10^-6 -> 0 | I61: Distribution (Notice 21)
B63: G42 | C63: New Space Capital GP Com SCSp | D63: 44087 | E63: =-'A. All deals (a)'!K46 -> -2.7058824 | G63: EUR | H63: -2.125 | I63: Drawdown1
B64: G42 | C64: New Space Capital GP Com SCSp | D64: 46021 | E64: =H64*1.18 -> 0.20678021 | F64: =E64 -> 0.20678021 | G64: EUR | H64: =175237.47*10^-6 -> 0.17523747 | I64: Distribution (Notice 1)
B65: G42 | C65: Acies Investments Fund I, L.P. | D65: 44540 | E65: =H65 -> -2.8053125 | G65: USD | H65: -2.8053125 | I65: 1st Capital Call
B66: G42 | C66: Acies Investments Fund I, L.P. | D66: 44602 | E66: =H66 -> -3.4075 | G66: USD | H66: -3.4075 | I66: 2nd Capital Call
B67: G42 | C67: Acies Investments Fund I, L.P. | D67: 44683 | E67: =H67 -> -1.025775 | G67: USD | H67: -1.025775 | I67: Catch up Capital Call
B68: G42 | C68: Acies Investments Fund I, L.P. | D68: 44707 | E68: =H68 -> -3.388275 | G68: USD | H68: -3.388275 | I68: 3rd Capital Call
B69: G42 | C69: Acies Investments Fund I, L.P. | D69: 44875 | E69: =H69 -> -3.388275 | G69: USD | H69: -3.388275 | I69: 4th Capital Call
B70: G42 | C70: Acies Investments Fund I, L.P. | D70: 45760 | E70: =H70 -> -1.71125 | G70: USD | H70: -1.71125 | I70: 5th Capital Call
B72: GXI | C72: MGX HoldCo | D72: 45547 | E72: -25 | G72: USD | H72: =E72+F72 -> -25 | I72: Share Capital
B74: GXI | C74: MGX I LP | D74: 45652 | E74: -116.09729 | G74: USD | H74: =E74+F74 -> -116.09729 | I74: Capital Call
B75: GXI | C75: MGX I LP | D75: 45726 | E75: -78.304695 | G75: USD | H75: =E75+F75 -> -78.304695 | I75: Capital Call
B76: GXI | C76: MGX I LP | D76: 45770 | E76: -2.0539744 | G76: USD | H76: =E76+F76 -> -2.0539744 | I76: Capital Call
B77: GXI | C77: MGX I LP | D77: 45853 | E77: 57.059152 | G77: USD | H77: =E77+F77 -> 57.059152 | I77: Return of Capital
B78: GXI | C78: MGX I LP | D78: 45861 | E78: -0.03076632 | G78: USD | H78: =E78+F78 -> -0.03076632 | I78: Capital Call
B79: GXI | C79: MGX I LP | D79: 45902 | E79: -46.002087 | G79: USD | H79: =E79+F79 -> -46.002087 | I79: Capital Call
B80: GXI | C80: MGX I LP | D80: 46006 | E80: -0.01 | G80: USD | H80: =E80+F80 -> -0.01 | I80: Capital Call
B81: GXI | C81: MGX I LP | D81: 46077 | E81: =-85727395.84 *10^-6 -> -85.727396 | G81: USD | H81: =E81+F81 -> -85.727396 | I81: Capital Call
B82: GXI | C82: MGX I LP | D82: 46092 | E82: 14.688852 | G82: USD | H82: =E82+F82 -> 14.688852 | I82: Distribution
B83: GXI | C83: MGX I LP | D83: 46094 | E83: -70.445873 | G83: USD | H83: =E83+F83 -> -70.445873 | I83: Capital Call
B84: GXI | C84: MGX I LP | D84: 46149 | E84: -38.408359 | G84: USD | H84: =E84+F84 -> -38.408359 | I84: Capital Call
B85: GXI | C85: MGX I LP | D85: 46160 | E85: =-3440.72*10^-6 -> -0.00344072 | G85: USD | H85: =E85+F85 -> -0.00344072 | I85: Capital Call
B86: GXI | C86: MGX I LP | D86: 46159 | E86: 19.305945 | G86: USD | H86: =E86+F86 -> 19.305945 | I86: Return of Capital
B88: GXI | C88: MGX Denali (AIV) | D88: 45454 | E88: -4.440212 | G88: USD | H88: =E88+F88 -> -4.440212 | I88: Capital Call
B89: GXI | C89: MGX Denali (AIV) | D89: 45468 | E89: -0.856702 | G89: USD | H89: =E89+F89 -> -0.856702 | I89: Capital Call
B90: GXI | C90: MGX Denali (AIV) | D90: 45562 | E90: -1.766018 | G90: USD | H90: =E90+F90 -> -1.766018 | I90: Capital Call
B91: GXI | C91: MGX Denali (AIV) | D91: 45581 | E91: -0.125982 | G91: USD | H91: =E91+F91 -> -0.125982 | I91: Capital Call
B92: GXI | C92: MGX Denali (AIV) | D92: 45645 | E92: -3.257177 | G92: USD | H92: =E92+F92 -> -3.257177 | I92: Capital Call
B93: GXI | C93: MGX Denali (AIV) | D93: 45726 | E93: -8.201327 | G93: USD | H93: =E93+F93 -> -8.201327 | I93: Capital Call
B94: GXI | C94: MGX I Denali (AIV) | D94: 45841 | E94: -4.3143661 | G94: USD | H94: =E94+F94 -> -4.3143661 | I94: Capital Call
B95: GXI | C95: MGX I Denali (AIV) | D95: 45861 | E95: -1.8373085 | G95: USD | H95: =E95+F95 -> -1.8373085 | I95: Capital Call
B96: GXI | C96: MGX I Denali (AIV) | D96: 45919 | E96: -2.8736578 | G96: USD | H96: =E96+F96 -> -2.8736578 | I96: Capital Call
B98: GXI | C98: MGX Strategic Co-Invest | D98: 45565 | E98: -250 | G98: USD | H98: =E98+F98 -> -250 | I98: Capital Call
B99: GXI | C99: MGX Strategic Co-Invest | D99: 45618 | E99: -250 | G99: USD | H99: =E99+F99 -> -250 | I99: Capital Call
... B101: GXI | C101: MGX Strategic Co-Invest | D101: 45726 | E101: -62.49956 | G101: USD | H101: =E101+F101 -> -62.49956 | I101: Capital Call

Sheet NAV
B2: NAV Date | C2: ='A. All deals (a)'!D2 -> 46265 | D2: =TEXT(C2,"ddd") -> Mon
B5: Investments | C5: Investing Entity | D5: Instrument | E5: Carrying Value | F5: Current Shares/Units | H5: Comment
E6: USD, Million | F6: # | G6: USD
E7: ="NAV | "& TEXT(C2,"dd")&" "&TEXT(C2,"mmm")&" "&TEXT(C2,"yyyy") -> NAV | 31 Aug 2026 | G7: ="PPS |" & TEXT(C2,"dd")&" "&TEXT(C2,"mmm")&" "&TEXT(C2,"yyyy") -> PPS |31 Aug 2026
B9: Direct Investments
B10: ='A. All deals (a)'!C9 -> Jollychic Holding Limited | C10: ='A. All deals (a)'!F9 -> Mozn | D10: ='A. All deals (a)'!H9 -> C+ Prefs | E10: =F10*G10*10^-6 -> 0 | F10: =VLOOKUP(B10,'%'!$C$6:$I$43,2,0) -> 13458655 | H10: Exited/Liquidated
B11: ='A. All deals (a)'!C10 -> Mena Mobile Inc | C11: ='A. All deals (a)'!F10 -> Mozn | D11: ='A. All deals (a)'!H10 -> B Prefs | E11: 0 | F11: =VLOOKUP(B11,'%'!$C$6:$I$43,2,0) -> 21419829 | H11: As per 3rd Party | Ardent Estimates | Equity written off | K11: =STOCKHISTORY(J18,$K$16,$K$16,0,0)
B12: ='A. All deals (a)'!C12 -> Esyasoft Holding | C12: ='A. All deals (a)'!F12 -> Mozn | D12: ='A. All deals (a)'!H12 -> Convertible Note | E12: 0 | F12: =VLOOKUP(B12,'%'!$C$6:$I$43,2,0) -> n/a | H12: Exited at $5m (10th May) | Residual value = 0
B13: ='A. All deals (a)'!C16 -> Jysan Technologies | C13: ='A. All deals (a)'!F16 -> Mozn 1 | D13: ='A. All deals (a)'!H16 -> A (Ordinary Shares) | E13: 0 | F13: =VLOOKUP(B13,'%'!$C$6:$I$43,2,0) -> 7959497 | G13: =E13*10^6/F13 -> 0 | H13: Exited at $24.5m
B14: ='A. All deals (a)'!C19 -> Instadeep Limited | C14: ='A. All deals (a)'!F19 -> Mozn | D14: ='A. All deals (a)'!H19 -> B Prefs | E14: =-'CF (Equity, Debt)'!E24*G14 -> 0 | F14: =VLOOKUP(B14,'%'!$C$6:$I$43,2,0) -> 33267 | G14: 0 | H14: Exited at 1.56X | Residual Value = 0
B15: ='A. All deals (a)'!C20 -> X-fusion | C15: ='A. All deals (a)'!F20 -> Mozn 2 | D15: ='A. All deals (a)'!H20 -> Equity-TBC | E15: 0 | F15: =VLOOKUP(B15,'%'!$C$6:$I$43,2,0) -> n/a | H15: Exited at 0.82X | K15: =TEXT(K16,"ddd") -> Mon | S15: Heygears Oct 22
B16: ='A. All deals (a)'!C23 -> Honor Device Co Ltd | C16: ='A. All deals (a)'!F23 -> G42 3 | D16: ='A. All deals (a)'!H23 -> Equity-TBC | E16: 0 | F16: =VLOOKUP(B16,'%'!$C$6:$I$43,2,0) -> 6.0685078e+08 | H16: Exited at 1.0X | J16: Updated as on: | K16: =C2 -> 46265 | M16: source | S16: Post Valuation closed in June 2021 (RMB) | T16: 7500000000
B17: ='A. All deals (a)'!C27 -> WLD Tokens | C17: ='A. All deals (a)'!F27 -> Mozn | D17: ='A. All deals (a)'!H27 -> Tokens | E17: =F17*G17*10^-6 -> 0 | F17: 0 | G17: =K17 -> 0 | H17: source: coinmarket cap | S17: G42 Stake | T17: 0.143832
B18: ='A. All deals (a)'!C14 -> ONT plc | C18: ='A. All deals (a)'!F14 -> Mozn | D18: ='A. All deals (a)'!H14 -> Ordinary Shares | E18: =F18*G18*10^-6 -> 105.22733 | F18: =VLOOKUP(B18,'%'!$C$6:$I$43,2,0) -> 44328120 | G18: =M18*M22/100 -> 2.373828 | H18: Listed & marked to market | J18: ONT | K18: {=_xlfn.STOCKHISTORY(J18,$K$16,$K$16,0,0)} -> 46265 | L18: 16.72 | M18: 176.1 | S18: G42 Valuation before Discount (RMB) | T18: 1078740000
B19: ='A. All deals (a)'!C22 -> vTv Therapeutics Inc. | C19: ='A. All deals (a)'!F22 -> G42 Investments | D19: ='A. All deals (a)'!H22 -> Ordinary Shares | E19: =(F19*G19)*10^-6 -> 8.309024 | F19: =VLOOKUP(B19,'%'!$C$6:$I$43,2,0) -> 259657 | G19: =M19 -> 32 | H19: Listed & marked to market | J19: VTVT | K19: {=_xlfn.STOCKHISTORY(J19,$K$16,$K$16,0,0)} -> 46265 | L19: 32 | M19: 32 | S19: Liquidity Discount | T19: 0
B20: ='A. All deals (a)'!C31 -> Verses AI Inc | C20: ='A. All deals (a)'!F31 -> G42 Capital | D20: ='A. All deals (a)'!H31 -> Ordinary Shares | E20: =(F20*G20)*10^-6 -> 0 | F20: =VLOOKUP(B20,'%'!$C$6:$I$43,2,0) -> 514623.44 | G20: =M21 -> 0 | H20: Listed & marked to market | J20: CBRS | K20: {=_xlfn.STOCKHISTORY(J20,$K$16,$K$16,0,0)} -> 46265 | L20: 184.24 | M20: 184.24 | S20: Minority Holding Discount | T20: 0
B21: ='A. All deals (a)'!C17 -> Cerebras Systems Inc (1) | C21: ='A. All deals (a)'!F17 -> Mozn | D21: ='A. All deals (a)'!H17 -> F Prefs | E21: =F21*G21*10^-6 -> 265.62083 | F21: =VLOOKUP(B21,'%'!$C$6:$I$43,2,0) -> 1441711 | G21: =M20 -> 184.24 | H21: Listed & marked to market | J21: VRSSF | K21: {=_xlfn.STOCKHISTORY(J21,$K$16,$K$16,0,0)} -> 46265 | L21: #N/A | M21: 0 | S21: G42 Valuation (RMB) | T21: =T18*(1-T19)*(1-T20) -> 1078740000
B22: ='A. All deals (a)'!C35 -> Cerebras Systems Inc (2) | C22: G42 Capital | D22: ='A. All deals (a)'!H29 -> Preferred Shares | E22: =F22*G22*10^-6 -> 647.32558 | F22: =1857516+1655975 -> 3513491 | G22: =M20 -> 184.24 | H22: Listed & marked to market | J22: GBPUSD | K22: {=_xlfn.STOCKHISTORY(J22,$K$16,$K$16,0,0)} -> 46265 | L22: 1.3547 | M22: 1.348 | S22: Exchange Rate (RMB/USD) | T22: =K23 -> 46265
B23: ='A. All deals (a)'!C11 -> Flyr Inc | C23: ='A. All deals (a)'!F11 -> Mozn | D23: ='A. All deals (a)'!H11 -> B-1,2 Prefs | E23: 14.6 | F23: =VLOOKUP(B23,'%'!$C$6:$I$43,2,0) -> 5205482 | H23: As per the recent fund raise for Series D | J23: USDCNY | K23: {=_xlfn.STOCKHISTORY(J23,$K$16,$K$16,0,0)} -> 46265 | L23: 6.7197 | M23: 6.7237 | S23: G42 Valuation (USD) | T23: =T21/T22 -> 23316.546
B24: ='A. All deals (a)'!C13 -> Beyond Limits | C24: ='A. All deals (a)'!F13 -> Mozn | D24: ='A. All deals (a)'!H13 -> C Prefs | E24: 21.7 | F24: =VLOOKUP(B24,'%'!$C$6:$I$43,2,0) -> 17670202 | G24: =5.152 * 50% -> 2.576 | H24: Ardent Dec'25 | 50% haircut recent convertible price during Q4'25 | J24: EURUSD | K24: {=_xlfn.STOCKHISTORY(J24,$K$16,$K$16,0,0)} -> 46265 | L24: 1.1616 | M24: 1.16169 | S24: Investment Cost of G42 (USD) | T24: 60000000
B25: ='A. All deals (a)'!C15 -> Heygears | C25: ='A. All deals (a)'!F15 -> Mozn | D25: ='A. All deals (a)'!H15 -> Registered Capital | E25: =F25*G25*10^-6 -> 71.918846 | F25: ='CF (Equity, Debt)'!J20 -> 3565017.2 | G25: =141.2/$K$44 -> 20.173492 | H25: Priced round at RMB 141.2 per share | Mar'26
B26: ='A. All deals (a)'!C18 -> Endless Studios LLC | C26: ='A. All deals (a)'!F18 -> Mozn | D26: ='A. All deals (a)'!H18 -> A Pref Units | E26: 6.5 | F26: =VLOOKUP(B26,'%'!$C$6:$I$43,2,0) -> 8000000 | H26: Ardent Valuation as of 31 Dec 25
B27: ='A. All deals (a)'!C28 -> E-line Ventures LLC | C27: ='A. All deals (a)'!F28 -> Mozn | D27: ='A. All deals (a)'!H28 -> B Prefs | E27: 7.1 | F27: =VLOOKUP(B27,'%'!$C$6:$I$43,2,0) -> 4477612 | H27: Ardent Valuation as of 31 Dec 25 | J27: Checks
B28: ='A. All deals (a)'!C21 -> DriveNets | C28: ='A. All deals (a)'!F21 -> G42 Investments | D28: ='A. All deals (a)'!H21 -> Equity-TBC | E28: =F28*G28*10^-6 -> 497.53506 | F28: =VLOOKUP(B28,'%'!$C$6:$I$43,2,0) -> 68926902 | G28: 7.2183 | H28: Priced round at US$7.35 per share | Mar'26
B29: ='A. All deals (a)'!C24 -> Applied AI Corporation Limited | C29: ='A. All deals (a)'!F24 -> Mozn | D29: ='A. All deals (a)'!H24 -> A Prefs | E29: 38.46473 | F29: =VLOOKUP(B29,'%'!$C$6:$I$43,2,0) -> 211519 | H29: Marked up, being held at 2.27X as per the last round | J29: =SUM(E10:E36) -> 2175.5555 | K29: =J29='A. All deals (a)'!N36 -> TRUE
B30: ='A. All deals (a)'!C25 -> eSpace | C30: ='A. All deals (a)'!F25 -> Mozn 4 | D30: ='A. All deals (a)'!H25 -> B Prefs | E30: =F30*G30*10^-6 -> 230.00751 | F30: =VLOOKUP(B30,'%'!$C$6:$I$43,2,0) -> 417846 | G30: 550.46 | H30: Marked up, as converted as per the latest priced round | J30: =SUM(E41:E43) -> 0 | K30: =J30='A. All deals (a)'!N42 -> TRUE
B31: ='A. All deals (a)'!C26 -> Tools for Humanity Corporation | C31: ='A. All deals (a)'!F26 -> Mozn | D31: ='A. All deals (a)'!H26 -> C Prefs | E31: 1.2 | F31: =VLOOKUP(B31,'%'!$C$6:$I$43,2,0) -> 65413 | H31: Ardent Valuation as of 31 Dec 25 | J31: =SUM(E46:E50) -> 150.49907 | K31: =J31='A. All deals (a)'!N50 -> TRUE
B32: ='A. All deals (a)'!C29 -> School Hack (AIREV Holding Limited) | C32: ='A. All deals (a)'!F29 -> Core42 5 | D32: ='A. All deals (a)'!H29 -> Preferred Shares | E32: =MAX('A. All deals (a)'!K29,F32*G32*10^-6) -> 2.5 | F32: =VLOOKUP(B32,'%'!$C$6:$I$43,2,0) -> 434782.61 | H32: Held at cost
B33: ='A. All deals (a)'!C30 -> Life Biosciences LLC | C33: ='A. All deals (a)'!F30 -> G42 Capital | D33: ='A. All deals (a)'!H30 -> D Prefs | E33: =(F33*G33*10^-6) -> 40.947394 | F33: =VLOOKUP(B33,'%'!$C$6:$I$43,2,0) -> 14178755 | G33: 2.88794 | H33: Held at cost
B34: ='A. All deals (a)'!C32 -> Inveniam Ltd | C34: G42 Capital | D34: ='A. All deals (a)'!H31 -> Ordinary Shares | E34: 100 | F34: =VLOOKUP(B34,'%'!$C$6:$I$43,2,0) -> NA | H34: Held at cost
B35: ='A. All deals (a)'!C33 -> Liquid AI | C35: G42 Capital | D35: Series A | E35: =F35*G35*10^-6 -> 66.599184 | F35: ='%'!D33 -> 549725 | G35: 121.15 | H35: Held at cost
B36: ='A. All deals (a)'!C34 -> Neuralink | C36: G42 Capital | D36: Series E | E36: =50 -> 50 | F36: n/a | H36: Held at cost
B40: Debt Investments | J40: Heygears
B41: Glass Earth Holdings LLC | C41: Mozn | D41: Promissory Note | E41: ='A. All deals (a)'!N39 -> 0 | H41: In default | J41: Price | K41: 141.2
B42: Mena Mobile Inc (Debt) | C42: Mozn | D42: Loan | E42: 0 | H42: In liquidation | J42: Shares | K42: 24.785
B43: Esyasoft Holding (Debt) | C43: Mozn | D43: Loan | E43: 0 | H43: Exited. Received payment of $470,784.65 ($411K+$59K) | J43: Value | K43: =K41*K42/1000 -> 3.499642
J44: Conversion Rate | K44: =K43/0.5 -> 6.999284
B45: Funds Investments
B46: New Space Capital Fund I | C46: G42 | D46: LP | E46: ='8. NewSpace'!R38*10^-6*M24 -> 57.156181 | H46: Q2'26 capital account statement
B47: New Space Capital GP Com SCSp | C47: G42 | D47: GP | E47: ='1. Live'!O27/'1. Live'!O26*E46+0.871*M24 -> 6.741761 | H47: Q2'26 NSC Fund 1 and Q3'25 capital account statement of GP
B48: North Summit Capital Fund | C48: G42 | D48: LP | E48: 72.566225 | H48: Q2'26 capital account statement
B49: Acies Investments Fund I, L.P. | C49: G42 | D49: LP | E49: 14.034903 | H49: Q2'26 capital account statement
B50: Sinovation Disrupt Fund, L.P. | C50: G42 | D50: LP | E50: 0 | H50: Exited
B52: MGX I LP | E52: =MGX!H41 -> 644.14726 | H52: Q4'25 capital account statement
B53: MGX 1 Strategic Co-invest | E53: =MGX!H35 -> 741.85679 | H53: Q4'25 capital account statement
B54: MGX Group Holding 1 Ltd (GP) | C54: GXI | D54: LP | E54: =MGX!H36 -> 25 | H54: Q4'25 capital account statement
B56: Note:
B57: • Respective listed share prices for ONT and vTv Therapeutics are used for estimating the NAVs

Sheet %
C2: % OWNERSHIP
C3: As of date | D3: ='A. All deals (a)'!D2 -> 46265
E5: Fully diluted | F5: Fully diluted
C6: Deals | D6: Shares / Units | E6: Total | F6: % | G6: Source for % holding | H6: Incorporation/Jurisdiction | I6: Country
C8: Direct Investments
B9: Written Off | C9: ='A. All deals (a)'!C9 -> Jollychic Holding Limited | D9: 13458655 | E9: 236116762 | F9: =D9/E9 -> 0.056999998 | G9: Dan Kong | H9: Cayman Islands | I9: Cayman Islands
B10: Written Off | C10: ='A. All deals (a)'!C10 -> Mena Mobile Inc | D10: 21419829 | E10: 152998776 | F10: =D10/E10 -> 0.14 | G10: Dan Kong | H10: Cayman Islands | I10: Cayman Islands
C11: ='A. All deals (a)'!C11 -> Flyr Inc | D11: 5205482 | E11: =D11/F11 -> 1.5585275e+08 | F11: 0.0334 | G11: Est as of 31 Dec 25 | H11: Delaware Corporation | I11: USA
B12: Exited | C12: ='A. All deals (a)'!C12 -> Esyasoft Holding | D12: n/a | E12: n/a | F12: NA | G12: n/a; exited | H12: DIFC | I12: Dubai, UAE
C13: ='A. All deals (a)'!C13 -> Beyond Limits | D13: 17670202 | E13: =D13/F13 -> 2.7184926e+08 | F13: 0.065 | G13: Est as of 31 Dec 25 | H13: Delaware Corporation | I13: USA
C14: ='A. All deals (a)'!C14 -> ONT plc | D14: 44328120 | E14: 972897623 | F14: =D14/E14 -> 0.045562985 | G14: Capital IQ | H14: UK | I14: UK
C15: ='A. All deals (a)'!C15 -> Heygears | D15: 3565017.2 | E15: 24785982 | F15: =D15/E15 -> 0.14383199 | G15: Txn docs for FY26 Fund Raise | H15: PRC | I15: China
B16: Exited | C16: ='A. All deals (a)'!C16 -> Jysan Technologies | D16: 7959497 | E16: 2.6531657e+08 | F16: 0.03 | G16: n/a; exited | H16: UK | I16: UK
C17: ='A. All deals (a)'!C17 -> Cerebras Systems Inc (1) | D17: 1441711 | E17: 219728541 | F17: =D17/E17 -> 0.0065613279 | G17: Estimated, Feb'26 fund raise | H17: Delaware Corporation | I17: USA
C18: ='A. All deals (a)'!C18 -> Endless Studios LLC | D18: 8000000 | E18: =D18/F18 -> 49950000 | F18: 0.16016016 | G18: Est as of 31 Dec 25 | H18: Delaware Corporation | I18: USA
B19: Exited | C19: ='A. All deals (a)'!C19 -> Instadeep Limited | D19: 33267 | E19: 2895450 | F19: NA | G19: n/a; exited | H19: UK | I19: UK
B20: Exited | C20: ='A. All deals (a)'!C20 -> X-fusion | D20: n/a | E20: n/a | F20: NA | G20: n/a; exited | H20: PRC | I20: China
C21: ='A. All deals (a)'!C21 -> DriveNets | D21: =24403771+44523131 -> 68926902 | E21: 1.0750459e+09 | F21: 0.0655 | G21: Est as of 31 Dec 25 | H21: Israeli Pvt Company | I21: Israel
C22: ='A. All deals (a)'!C22 -> vTv Therapeutics Inc. | D22: =ROUNDUP(10386274/40,0) -> 259657 | E22: 12409278 | F22: =D22/E22 -> 0.020924424 | G22: Company Reproting | link | H22: Delaware Corporation | I22: USA
B23: Exited | C23: ='A. All deals (a)'!C23 -> Honor Device Co Ltd | D23: =1517126944.34*0.8/2 -> 6.0685078e+08 | E23: 3.2238948e+10 | F23: NA | G23: n/a; exited | H23: PRC | I23: China
C24: ='A. All deals (a)'!C24 -> Applied AI Corporation Limited | D24: =44133+39500+54863+73023 -> 211519 | E24: 1744988 | F24: =D24/E24 -> 0.12121516 | G24: n/a; convertible note | H24: ADGM | I24: Abu Dhabi, UAE
C25: ='A. All deals (a)'!C25 -> eSpace | D25: 417846 | E25: =D25/F25 -> 16841838 | F25: 0.02481 | G25: Est as of 31 Dec 25 | H25: Delaware Corporation | I25: USA
C26: ='A. All deals (a)'!C26 -> Tools for Humanity Corporation | D26: 65413 | E26: 10439222 | F26: =D26/E26 -> 0.00626608 | G26: Est as of 31 Dec 25 | H26: Delaware Corporation | I26: USA
C27: ='A. All deals (a)'!C27 -> WLD Tokens | D27: 62500000 | E27: 10000000000 | F27: NA | G27: n/a; exited | H27: DAO | Cayman Islands | I27: Cayman Islands
C28: ='A. All deals (a)'!C28 -> E-line Ventures LLC | D28: 4477612 | E28: =D28/F28 -> 38500533 | F28: 0.1163 | G28: Est as of 31 Dec 25 | H28: New Jersey | I28: New Jersey
C29: ='A. All deals (a)'!C29 -> School Hack (AIREV Holding Limited) | D29: =E29/F29 -> 434782.61 | E29: 100000 | F29: 0.23 | G29: Shareholders Resolution | H29: ADGM | I29: UAE
C30: ='A. All deals (a)'!C30 -> Life Biosciences LLC | D30: 14178755 | E30: 194237760 | F30: 0.0639 | G30: Est as of 31 Dec 25 | H30: Delaware Corporation | I30: USA
C31: ='A. All deals (a)'!C31 -> Verses AI Inc | D31: =13894833*1/9*1/3 -> 514623.44 | E31: 14306053 | F31: =D31/E31 -> 0.035972427 | G31: Company Reporting | link | H31: Victoria, British Columbia | I31: Canada
C32: ='A. All deals (a)'!C32 -> Inveniam Ltd | D32: NA | E32: =13481499/0.2 -> 67407495 | F32: NA | G32: equity interest held via SAR | H32: Gibraltor | I32: British Overseas Territory
C33: ='A. All deals (a)'!C33 -> Liquid AI | D33: =165082+384643 -> 549725 | E33: =17808198.4897519+384643 -> 18192841 | F33: =D33/E33 -> 0.030216555 | G33: Est as of Feb26 | H33: Delaware Corporation | I33: USA
C34: ='A. All deals (a)'!C34 -> Neuralink | D34: 990099 | E34: 191119513 | F34: =D34/E34 -> 0.0051805228 | G34: Cap Table | H34: Nevada | I34: USA
C35: ='A. All deals (a)'!C35 -> Cerebras Systems Inc (2) | D35: 3513491 | E35: =E17 -> 219728541 | F35: =D35/E35 -> 0.015990144 | G35: Estimated, Feb'26 fund raise | H35: Delaware Corporation | I35: USA
C38: Funds Investments | D38: G42 Commitment | E38: Fund Size
C39: New Space Capital Fund I | D39: 23234462 | E39: 130300000 | F39: =D39/E39 -> 0.17831513 | G39: Estimated as per Q1-23 NAV report | H39: Luxembourg | I39: Luxembourg
C40: New Space Capital GP Com SCSp | D40: =-'CF (Funds)'!H63*10^6 -> 2125000 | E40: =E39 -> 130300000 | F40: =D40/E40 -> 0.016308519 | H40: Luxembourg | I40: Luxembourg
C41: North Summit Capital Fund | D41: 300000000 | E41: 301507538 | F41: =D41/E41 -> 0.995 | G41: Q4'22 Report | H41: Cayman Islands | I41: Cayman Islands
B42: Exited | C42: Sinovation Disrupt Fund, L.P. | D42: 50000000 | E42: 496717172 | F42: =D42/E42 -> 0.1006609 | G42: Q2'23 Report | H42: Cayman Islands | I42: Cayman Islands
C43: Acies Investments Fund I, L.P. | D43: 17112500 | E43: 51337500 | F43: =D43/E43 -> 0.33333333 | G43: Q1 23 Report | H43: Delaware LLC | I43: USA
C44: MGX I LP | D44: 1200000000 | E44: 38400000000 | F44: =D44/E44 -> 0.03125

Sheet E. Board
C3: Deals | D3: Board Representation ‡ | E3: Representative | F3: Notes | G3: Status | H3: Comments
C5: Direct Investments
C6: Mena Mobile Inc | D6: 1 Director | E6: Peng Xiao | G6: In Liquidation
C7: Flyr Inc | D7: 1 Observer | E7: Jon Nieman | H7: Earlier 1 Director represented by Marty
C8: Esyasoft Holding | D8: NR | E8: n/a | F8: 2 | G8: Exited | H8: Monty Aw represented earlier
C9: Jollychic Holding Limited | D9: 1 Director | E9: Divyesh Mahajan | F9: 1 | G9: In Liquidation
C10: Beyond Limits | D10: 1 Director | E10: Jon Nieman | F10: 3
C11: ONT plc | D11: 1 Director | E11: Guy Harmelin (Independent Director)
C12: Heygears | D12: 2 Director | E12: Elaine | G12: Peng Resigned Jan24 | H12: PX to be replaced by XP
C13: Jysan Technologies | D13: 1 Director | E13: None appointed | G13: Exited | H13: Exited
C14: Cerebras Systems Inc | D14: 1 Observer | E14: Eric Xing | F14: 4
C15: Endless Studios LLC | D15: 1 Director 1 Observer | E15: Jon Nieman
C16: Instadeep Limited | D16: 1 Observer | G16: Exited | H16: Exited
C17: X-fusion | D17: NR | E17: n/a | G17: Exited
C18: DriveNets | D18: 1 Observer | E18: Guy Harmelin
C19: vTv Therapeutics Inc. | D19: 1 Director, 1 Observer | E19: Dr. Fahad (Board), Jon Nieman (Observer)
C20: Honor Device Co Ltd | D20: NR | E20: n/a | F20: 5 | G20: Exited
C21: Applied AI Corporation Limited | D21: NR | E21: n/a
C22: eSpace | D22: NR | E22: n/a
C23: Tools for Humanity Corporation | D23: NR | E23: n/a
C24: E-line Ventures LLC
C25: School Hack (AIREV Holding Limited) | D25: 2 Director | E25: n/a
C28: Debt Investments
C29: Glass Earth Holdings LLC | D29: NR
C30: Mena Mobile Inc | D30: 1 Director | E30: Peng Xiao | G30: In Liquidation
C31: Esyasoft Holding | D31: NR
C34: Funds Investments
C35: New Space Capital Fund I | D35: 1 Director | E35: Jon Nieman
C36: New Space Capital GP Com SCSp | D36: NR
C37: North Summit Capital Fund | D37: NR
C38: Sinovation Disrupt Fund, L.P. | D38: NR | G38: Exited
C39: Acies Investments Fund I, L.P. | D39: Advisory Board | E39: Not yet appointed | H39: Confirm appoinment
C43: NOTES:
C44: NR = No Rights / No Representation
C45: n/a = not applicable or not available
C46: ‡ Board Representation : as a Board Seat, Observer, or Advisor
B47: 1 | C47: Jollychic Holding : Peng Xiao held the directorship until Jun 2021
B48: 2 | C48: Esyasoft: we held a Board seat, with Monty Aw as the representative, until Jun 2022
B49: 3 | C49: Beyond Limits: possibility of the 2nd Board seat in case we invest (an additional / an earlier committed) $10m
B50: 4 | C50: Cerebras : possibility of a Board seat, If G42 holds >10% with rights to exercise at least 20% of warrant
B51: 5 | C51: Honor: Our board seat only kicks in once Honor is converted into a joint stock company in March 2023; there is no one appointed as yet

Sheet A. All deals (a)
C2: As of date | D2: ='D1'!D2 -> 46265
C6: Deals | D6: Status | F6: Investing Entity Ϋ | G6: Vintageἀ | H6: Instrument | I6: % | J6: Committed | K6: Invested | L6: Remaining Commitment | M6: Distributions | N6: Carrying Value | O6: Gain | P6: TVPI | Q6: Additional Upside/Downside
G7: # | I7: % | J7: $,m | K7: $,m | L7: $,m | M7: $,m | N7: $,m | O7: $,m | P7: X
C8: Equity or Equity like Investments
C9: Jollychic Holding Limited | D9: Written-off | F9: Mozn | G9: 2019 | H9: C+ Prefs | I9: ='%'!F9 -> 0.056999998 | J9: =K9 -> 65 | K9: =-SUMIF('CF (Equity, Debt)'!$C$3:$K$63,'A. All deals (a)'!C9,'CF (Equity, Debt)'!$E$3:$E$63) -> 65 | L9: 0 | M9: =SUMIF('CF (Equity, Debt)'!$C$3:$K$63,'A. All deals (a)'!C9,'CF (Equity, Debt)'!$F$3:$F$63) -> 0 | N9: =VLOOKUP(C9,NAV!$B$4:$E$50,4,0) -> 0 | O9: =N9+M9-K9 -> -65 | P9: =(M9+N9)/K9 -> 0 | Q9: In Liquidation
C10: Mena Mobile Inc | D10: Written-off | F10: Mozn | G10: 2019 | H10: B Prefs | I10: ='%'!F10 -> 0.14 | J10: =K10 -> 8 | K10: =-SUMIF('CF (Equity, Debt)'!$C$3:$K$63,'A. All deals (a)'!C10,'CF (Equity, Debt)'!$E$3:$E$63) -> 8 | L10: 0 | M10: =SUMIF('CF (Equity, Debt)'!$C$3:$K$63,'A. All deals (a)'!C10,'CF (Equity, Debt)'!$F$3:$F$63) -> 0 | N10: =VLOOKUP(C10,NAV!$B$4:$E$50,4,0) -> 0 | O10: =N10+M10-K10 -> -8 | P10: =(M10+N10)/K10 -> 0 | Q10: In Liquidation
C11: Flyr Inc | D11: Unrealized | F11: Mozn | G11: 2019 | H11: B-1,2 Prefs | I11: ='%'!F11 -> 0.0334 | J11: =K11 -> 10 | K11: =-SUMIF('CF (Equity, Debt)'!$C$3:$K$63,'A. All deals (a)'!C11,'CF (Equity, Debt)'!$E$3:$E$63) -> 10 | L11: 0 | M11: =SUMIF('CF (Equity, Debt)'!$C$3:$K$63,'A. All deals (a)'!C11,'CF (Equity, Debt)'!$F$3:$F$63) -> 0 | N11: =VLOOKUP(C11,NAV!$B$4:$E$50,4,0) -> 14.6 | O11: =N11+M11-K11 -> 4.6 | P11: =(M11+N11)/K11 -> 1.46 | Q11: Flyr Warrantsa 2025 expiry
C12: Esyasoft Holding | D12: Realized | F12: Mozn | G12: 2020 | H12: Convertible Note | I12: ='%'!F12 -> NA | J12: =K12 -> 2.5 | K12: =-SUMIF('CF (Equity, Debt)'!$C$3:$K$63,'A. All deals (a)'!C12,'CF (Equity, Debt)'!$E$3:$E$63) -> 2.5 | L12: 0 | M12: =SUMIF('CF (Equity, Debt)'!$C$3:$K$63,'A. All deals (a)'!C12,'CF (Equity, Debt)'!$F$3:$F$63) -> 5 | N12: =VLOOKUP(C12,NAV!$B$4:$E$50,4,0) -> 0 | O12: =N12+M12-K12 -> 2.5 | P12: =(M12+N12)/K12 -> 2
C13: Beyond Limits | D13: Unrealized | F13: Mozn | G13: 2020 | H13: C Prefs | I13: ='%'!F13 -> 0.065 | J13: =K13 -> 90 | K13: =-SUMIF('CF (Equity, Debt)'!$C$3:$K$63,'A. All deals (a)'!C13,'CF (Equity, Debt)'!$E$3:$E$63) -> 90 | L13: 0 | M13: =SUMIF('CF (Equity, Debt)'!$C$3:$K$63,'A. All deals (a)'!C13,'CF (Equity, Debt)'!$F$3:$F$63) -> 0 | N13: =VLOOKUP(C13,NAV!$B$4:$E$50,4,0) -> 21.7 | O13: =N13+M13-K13 -> -68.3 | P13: =(M13+N13)/K13 -> 0.24111111
C14: ONT plc | D14: Unrealized | F14: Mozn | G14: 2020 | H14: Ordinary Shares | I14: ='%'!F14 -> 0.045562985 | J14: =K14 -> 141.47026 | K14: =-SUMIF('CF (Equity, Debt)'!$C$3:$K$63,'A. All deals (a)'!C14,'CF (Equity, Debt)'!$E$3:$E$63) -> 141.47026 | L14: 0 | M14: =SUMIF('CF (Equity, Debt)'!$C$3:$K$63,'A. All deals (a)'!C14,'CF (Equity, Debt)'!$F$3:$F$63) -> 0 | N14: =VLOOKUP(C14,NAV!$B$4:$E$50,4,0) -> 105.22733 | O14: =N14+M14-K14 -> -36.242927 | P14: =(M14+N14)/K14 -> 0.74381239
C15: Heygears | D15: Unrealized | F15: Mozn | G15: 2020 | H15: Registered Capital | I15: ='%'!F15 -> 0.14383199 | J15: =K15 -> 60 | K15: =-SUMIF('CF (Equity, Debt)'!$C$3:$K$63,'A. All deals (a)'!C15,'CF (Equity, Debt)'!$E$3:$E$63) -> 60 | L15: 0 | M15: =SUMIF('CF (Equity, Debt)'!$C$3:$K$63,'A. All deals (a)'!C15,'CF (Equity, Debt)'!$F$3:$F$63) -> 0 | N15: =VLOOKUP(C15,NAV!$B$4:$E$50,4,0) -> 71.918846 | O15: =N15+M15-K15 -> 11.918846 | P15: =(M15+N15)/K15 -> 1.1986474
C16: Jysan Technologies | D16: Realized | F16: Mozn 1 | G16: 2021 | H16: A (Ordinary Shares) | I16: ='%'!F16 -> 0.03 | J16: =K16 -> 20 | K16: =-SUMIF('CF (Equity, Debt)'!$C$3:$K$63,'A. All deals (a)'!C16,'CF (Equity, Debt)'!$E$3:$E$63) -> 20 | L16: 0 | M16: =SUMIF('CF (Equity, Debt)'!$C$3:$K$63,'A. All deals (a)'!C16,'CF (Equity, Debt)'!$F$3:$F$63) -> 24.5 | N16: =VLOOKUP(C16,NAV!$B$4:$E$50,4,0) -> 0 | O16: =N16+M16-K16 -> 4.5 | P16: =(M16+N16)/K16 -> 1.225
C17: Cerebras Systems Inc (1) | D17: Unrealized | F17: Mozn | G17: 2021 | H17: F Prefs | I17: ='%'!F17 -> 0.0065613279 | J17: =K17 -> 39.999983 | K17: =-SUMIF('CF (Equity, Debt)'!$C$3:$K$63,'A. All deals (a)'!C17,'CF (Equity, Debt)'!$E$3:$E$63) -> 39.999983 | L17: 0 | M17: =SUMIF('CF (Equity, Debt)'!$C$3:$K$63,'A. All deals (a)'!C17,'CF (Equity, Debt)'!$F$3:$F$63) -> 0 | N17: =VLOOKUP(C17,NAV!$B$4:$E$50,4,0) -> 265.62083 | O17: =N17+M17-K17 -> 225.62085 | P17: =(M17+N17)/K17 -> 6.6405236 | Q17: Warrants i
C18: Endless Studios LLC | D18: Unrealized | F18: Mozn | G18: 2021 | H18: A Pref Units | I18: ='%'!F18 -> 0.16016016 | J18: =K18 -> 8 | K18: =-SUMIF('CF (Equity, Debt)'!$C$3:$K$63,'A. All deals (a)'!C18,'CF (Equity, Debt)'!$E$3:$E$63) -> 8 | L18: 0 | M18: =SUMIF('CF (Equity, Debt)'!$C$3:$K$63,'A. All deals (a)'!C18,'CF (Equity, Debt)'!$F$3:$F$63) -> 0 | N18: =VLOOKUP(C18,NAV!$B$4:$E$50,4,0) -> 6.5 | O18: =N18+M18-K18 -> -1.5 | P18: =(M18+N18)/K18 -> 0.8125
C19: Instadeep Limited | D19: Realized | F19: Mozn | G19: 2021 | H19: B Prefs | I19: ='%'!F19 -> NA | J19: =K19 -> 5.0237202 | K19: =-SUMIF('CF (Equity, Debt)'!$C$3:$K$63,'A. All deals (a)'!C19,'CF (Equity, Debt)'!$E$3:$E$63) -> 5.0237202 | L19: 0 | M19: =SUMIF('CF (Equity, Debt)'!$C$3:$K$63,'A. All deals (a)'!C19,'CF (Equity, Debt)'!$F$3:$F$63) -> 7.9421925 | N19: =VLOOKUP(C19,NAV!$B$4:$E$50,4,0) -> 0 | O19: =N19+M19-K19 -> 2.9184723 | P19: =(M19+N19)/K19 -> 1.5809385
C20: X-fusion | D20: Realized | F20: Mozn 2 | G20: 2022 | H20: Equity-TBC | I20: ='%'!F20 -> NA | J20: =K20 -> 493.50096 | K20: =-SUMIF('CF (Equity, Debt)'!$C$3:$K$63,'A. All deals (a)'!C20,'CF (Equity, Debt)'!$E$3:$E$63) -> 493.50096 | L20: 0 | M20: =SUMIF('CF (Equity, Debt)'!$C$3:$K$63,'A. All deals (a)'!C20,'CF (Equity, Debt)'!$F$3:$F$63) -> 403 | N20: =VLOOKUP(C20,NAV!$B$4:$E$50,4,0) -> 0 | O20: =N20+M20-K20 -> -90.500956 | P20: =(M20+N20)/K20 -> 0.81661443
C21: DriveNets | D21: Partially Realized | F21: G42 Investments | G21: 2022 | H21: Equity-TBC | I21: ='%'!F21 -> 0.0655 | J21: =K21 -> 300 | K21: =-SUMIF('CF (Equity, Debt)'!$C$3:$K$63,'A. All deals (a)'!C21,'CF (Equity, Debt)'!$E$3:$E$63) -> 300 | L21: =0 -> 0 | M21: =SUMIF('CF (Equity, Debt)'!$C$3:$K$63,'A. All deals (a)'!C21,'CF (Equity, Debt)'!$F$3:$F$63) -> 84.804486 | N21: =VLOOKUP(C21,NAV!$B$4:$E$50,4,0) -> 497.53506 | O21: =N21+M21-K21 -> 282.33954 | P21: =(M21+N21)/K21 -> 1.9411318 | Q21: DN Warrants b
C22: vTv Therapeutics Inc. | D22: Unrealized | F22: G42 Investments | G22: 2022 | H22: Ordinary Shares | I22: ='%'!F22 -> 0.020924424 | J22: =K22 -> 24.53125 | K22: =-SUMIF('CF (Equity, Debt)'!$C$3:$K$63,'A. All deals (a)'!C22,'CF (Equity, Debt)'!$E$3:$E$63) -> 24.53125 | L22: =J22-K22 -> 0 | M22: =SUMIF('CF (Equity, Debt)'!$C$3:$K$63,'A. All deals (a)'!C22,'CF (Equity, Debt)'!$F$3:$F$63) -> 0 | N22: =VLOOKUP(C22,NAV!$B$4:$E$50,4,0) -> 8.309024 | O22: =N22+M22-K22 -> -16.222226 | P22: =(M22+N22)/K22 -> 0.33871181 | Q22: vTv $30m milestn payment c
C23: Honor Device Co Ltd | D23: Realized | F23: G42 3 | G23: 2022 | H23: Equity-TBC | I23: ='%'!F23 -> NA | J23: =K23 -> 800 | K23: =-SUMIF('CF (Equity, Debt)'!$C$3:$K$63,'A. All deals (a)'!C23,'CF (Equity, Debt)'!$E$3:$E$63) -> 800 | L23: =J23-K23 -> 0 | M23: =SUMIF('CF (Equity, Debt)'!$C$3:$K$63,'A. All deals (a)'!C23,'CF (Equity, Debt)'!$F$3:$F$63) -> 802.8 | N23: =VLOOKUP(C23,NAV!$B$4:$E$50,4,0) -> 0 | O23: =N23+M23-K23 -> 2.8 | P23: =(M23+N23)/K23 -> 1.0035
C24: Applied AI Corporation Limited | D24: Unrealized | F24: Mozn | G24: 2022 | H24: A Prefs | I24: ='%'!F24 -> 0.12121516 | J24: 15 | K24: =-SUMIF('CF (Equity, Debt)'!$C$3:$K$63,'A. All deals (a)'!C24,'CF (Equity, Debt)'!$E$3:$E$63) -> 15 | L24: =J24-K24 -> 0 | M24: =SUMIF('CF (Equity, Debt)'!$C$3:$K$63,'A. All deals (a)'!C24,'CF (Equity, Debt)'!$F$3:$F$63) -> 0 | N24: =VLOOKUP(C24,NAV!$B$4:$E$50,4,0) -> 38.46473 | O24: =N24+M24-K24 -> 23.46473 | P24: =(M24+N24)/K24 -> 2.5643153
C25: eSpace | D25: Unrealized | F25: Mozn 4 | G25: 2022 | H25: B Prefs | I25: ='%'!F25 -> 0.02481 | J25: =K25 -> 15 | K25: =-SUMIF('CF (Equity, Debt)'!$C$3:$K$63,'A. All deals (a)'!C25,'CF (Equity, Debt)'!$E$3:$E$63) -> 15 | L25: =J25-K25 -> 0 | M25: =SUMIF('CF (Equity, Debt)'!$C$3:$K$63,'A. All deals (a)'!C25,'CF (Equity, Debt)'!$F$3:$F$63) -> 0 | N25: =VLOOKUP(C25,NAV!$B$4:$E$50,4,0) -> 230.00751 | O25: =N25+M25-K25 -> 215.00751 | P25: =(M25+N25)/K25 -> 15.333834
C26: Tools for Humanity Corporation | D26: Unrealized | F26: Mozn | G26: 2023 | H26: C Prefs | I26: ='%'!F26 -> 0.00626608 | J26: =K26 -> 14.999999 | K26: =-SUMIF('CF (Equity, Debt)'!$C$3:$K$63,'A. All deals (a)'!C26,'CF (Equity, Debt)'!$E$3:$E$63) -> 14.999999 | L26: =J26-K26 -> 0 | M26: =SUMIF('CF (Equity, Debt)'!$C$3:$K$63,'A. All deals (a)'!C26,'CF (Equity, Debt)'!$F$3:$F$63) -> 0 | N26: =VLOOKUP(C26,NAV!$B$4:$E$50,4,0) -> 1.2 | O26: =N26+M26-K26 -> -13.799999 | P26: =(M26+N26)/K26 -> 0.080000006
C27: WLD Tokens | D27: Unrealized | F27: Mozn | G27: 2023 | H27: Tokens | I27: ='%'!F27 -> NA | J27: =K27 -> 0.006875 | K27: =-SUMIF('CF (Equity, Debt)'!$C$3:$K$63,'A. All deals (a)'!C27,'CF (Equity, Debt)'!$E$3:$E$63) -> 0.006875 | L27: =J27-K27 -> 0 | M27: =SUMIF('CF (Equity, Debt)'!$C$3:$K$63,'A. All deals (a)'!C27,'CF (Equity, Debt)'!$F$3:$F$63) -> 100 | N27: =VLOOKUP(C27,NAV!$B$4:$E$50,4,0) -> 0 | O27: =N27+M27-K27 -> 99.993125 | P27: NM | Q27: Crypto Tokensd
C28: E-line Ventures LLC | D28: Unrealized | F28: Mozn | G28: 2023 | H28: B Prefs | I28: ='%'!F28 -> 0.1163 | J28: =K28 -> 6 | K28: =-SUMIF('CF (Equity, Debt)'!$C$3:$K$63,'A. All deals (a)'!C28,'CF (Equity, Debt)'!$E$3:$E$63) -> 6 | L28: =J28-K28 -> 0 | M28: =SUMIF('CF (Equity, Debt)'!$C$3:$K$63,'A. All deals (a)'!C28,'CF (Equity, Debt)'!$F$3:$F$63) -> 0 | N28: =VLOOKUP(C28,NAV!$B$4:$E$50,4,0) -> 7.1 | O28: =N28+M28-K28 -> 1.1 | P28: =(M28+N28)/K28 -> 1.1833333 | Q28: Optionse
C29: School Hack (AIREV Holding Limited) | D29: Unrealized | F29: Core42 5 | G29: 2024 | H29: Preferred Shares | I29: ='%'!F29 -> 0.23 | J29: =K29+0.25 -> 2.75 | K29: =-SUMIF('CF (Equity, Debt)'!$C$3:$K$63,'A. All deals (a)'!C29,'CF (Equity, Debt)'!$E$3:$E$63) -> 2.5 | L29: =J29-K29 -> 0.25 | M29: =SUMIF('CF (Equity, Debt)'!$C$3:$K$63,'A. All deals (a)'!C29,'CF (Equity, Debt)'!$F$3:$F$63) -> 0 | N29: =VLOOKUP(C29,NAV!$B$4:$E$50,4,0) -> 2.5 | O29: =N29+M29-K29 -> 0 | P29: =(M29+N29)/K29 -> 1 | Q29: Cloud Creditg
C30: Life Biosciences LLC | D30: Unrealized | F30: G42 Capital | G30: 2024 | H30: D Prefs | I30: ='%'!F30 -> 0.0639 | J30: =K30 -> 40 | K30: =-SUMIF('CF (Equity, Debt)'!$C$3:$K$63,'A. All deals (a)'!C30,'CF (Equity, Debt)'!$E$3:$E$63) -> 40 | L30: =J30-K30 -> 0 | M30: =SUMIF('CF (Equity, Debt)'!$C$3:$K$63,'A. All deals (a)'!C30,'CF (Equity, Debt)'!$F$3:$F$63) -> 0 | N30: =VLOOKUP(C30,NAV!$B$4:$E$50,4,0) -> 40.947394 | O30: =N30+M30-K30 -> 0.94739371 | P30: =(M30+N30)/K30 -> 1.0236848
C31: Verses AI Inc | D31: Unrealized | F31: G42 Capital | G31: 2024 | H31: Ordinary Shares | I31: ='%'!F31 -> 0.035972427 | J31: 10 | K31: =-SUMIF('CF (Equity, Debt)'!$C$3:$K$63,'A. All deals (a)'!C31,'CF (Equity, Debt)'!$E$3:$E$63) -> 10 | L31: =J31-K31 -> 0 | M31: =SUMIF('CF (Equity, Debt)'!$C$3:$K$63,'A. All deals (a)'!C31,'CF (Equity, Debt)'!$F$3:$F$63) -> 0 | N31: =VLOOKUP(C31,NAV!$B$4:$E$50,4,0) -> 0 | O31: =N31+M31-K31 -> -10 | P31: =(M31+N31)/K31 -> 0 | Q31: Revenue linked RSUs
C32: Inveniam Ltd | D32: Unrealized | F32: G42 Capital | G32: 2024 | H32: SAR | I32: ='%'!F32 -> NA | J32: 100 | K32: =-SUMIF('CF (Equity, Debt)'!$C$3:$K$63,'A. All deals (a)'!C32,'CF (Equity, Debt)'!$E$3:$E$63) -> 100 | L32: =J32-K32 -> 0 | M32: =SUMIF('CF (Equity, Debt)'!$C$3:$K$63,'A. All deals (a)'!C32,'CF (Equity, Debt)'!$F$3:$F$63) -> 0.499965 | N32: =VLOOKUP(C32,NAV!$B$4:$E$50,4,0) -> 100 | O32: =N32+M32-K32 -> 0.499965 | P32: =(M32+N32)/K32 -> 1.0049997 | Q32: Upside if Tokens sold > $2.5 per token
C33: Liquid AI | D33: Unrealized | F33: G42 Capital | G33: 2025 | H33: Series A | I33: ='%'!F33 -> 0.030216555 | J33: =K33+L33 -> 60.819863 | K33: =-SUMIF('CF (Equity, Debt)'!$C$3:$K$63,'A. All deals (a)'!C33,'CF (Equity, Debt)'!$E$3:$E$63) -> 60.819863 | L33: 0 | M33: 0 | N33: =VLOOKUP(C33,NAV!$B$4:$E$50,4,0) -> 66.599184 | O33: =N33+M33-K33 -> 5.7793208 | P33: =(M33+N33)/K33 -> 1.0950236
C34: Neuralink | D34: Unrealized | F34: G42 Capital | G34: 2025 | H34: Series E | I34: ='%'!F34 -> 0.0051805228 | J34: =K34 -> 50 | K34: =-SUMIF('CF (Equity, Debt)'!$C$3:$K$63,'A. All deals (a)'!C34,'CF (Equity, Debt)'!$E$3:$E$63) -> 50 | L34: 0 | M34: 0 | N34: 50 | O34: =N34+M34-K34 -> 5e-07 | P34: =(M34+N34)/K34 -> 1
C35: Cerebras Systems Inc (2) | D35: Unrealized | F35: G42 Capital | G35: 2026 | H35: Class N | I35: ='%'!F35 -> 0.015990144 | J35: =K35 -> 0.03513491 | K35: =-SUMIF('CF (Equity, Debt)'!$C$3:$K$63,'A. All deals (a)'!C35,'CF (Equity, Debt)'!$E$3:$E$63) -> 0.03513491 | L35: 0 | M35: =SUMIF('CF (Equity, Debt)'!$C$3:$K$63,'A. All deals (a)'!C35,'CF (Equity, Debt)'!$F$3:$F$63) -> 0 | N35: =VLOOKUP(C35,NAV!$B$4:$E$50,4,0) -> 647.32558 | O35: =N35+M35-K35 -> 647.29045 | P35: =(M35+N35)/K35 -> 18424 | Q35: Warrants i
J36: =SUM(J9:J35) -> 2382.638 | K36: =SUM(K9:K35) -> 2382.388 | L36: =SUM(L9:L35) -> 0.25 | M36: =SUM(M9:M35) -> 1428.5466 | N36: =SUM(N9:N35) -> 2175.5555 | O36: =SUM(O9:O35) -> 1221.7141 | P36: =(M36+N36)/K36 -> 1.5128107
C38: Debt Investments
C39: Glass Earth Holdings LLC | D39: Written-off | F39: Mozn | G39: 2019 | H39: Promissory Note | I39: n/a | J39: 8 | K39: 8 | L39: 0 | M39: 0 | N39: 0 | O39: =N39+M39-K39 -> -8 | P39: =(M39+N39)/K39 -> 0 | Q39: In Default
C40: Mena Mobile Inc (Debt) | D40: Written-off | F40: Mozn | G40: 2021 | H40: Loan | I40: n/a | J40: 2.353982 | K40: =J40 -> 2.353982 | L40: 0 | M40: 0 | N40: =VLOOKUP(C40,NAV!$B$4:$E$50,4,0) -> 0 | O40: =N40+M40-K40 -> -2.353982 | P40: =(M40+N40)/K40 -> 0 | Q40: In Liquidation
C41: Esyasoft Holding (Debt) | D41: Realized | F41: Mozn | G41: 2021 | H41: Loan | I41: n/a | J41: 0.411765 | K41: 0.411765 | L41: 0 | M41: ='CF (Equity, Debt)'!F68 -> 0.47078465 | N41: 0 | O41: =N41+M41-K41 -> 0.05901965 | P41: =(M41+N41)/K41 -> 1.1433333
J42: =SUM(J39:J41) -> 10.765747 | K42: =SUM(K39:K41) -> 10.765747 | L42: =SUM(L39:L41) -> 0 | M42: =SUM(M39:M41) -> 0.47078465 | N42: =SUM(N39:N41) -> 0 | O42: =N42+M42-K42 -> -10.294962 | P42: =(M42+N42)/K42 -> 0.043729864
C44: Funds Investments
C45: New Space Capital Fund I | D45: Unrealized | F45: G42 Investments | G45: 2020 | H45: LP | I45: n/a | J45: =K45+L45 -> 26.991242 | K45: ='8. NewSpace'!O35*'8. NewSpace'!L48/1000000 -> 17.009681 | L45: ='8. NewSpace'!O36*'8. NewSpace'!L48/1000000 -> 9.9815607 | M45: =SUM('CF (Funds)'!F39:F63) -> 6.7779339 | N45: =VLOOKUP(C45,NAV!$B$4:$E$50,4,0) -> 57.156181 | O45: =N45+M45-K45 -> 46.924434 | P45: =(M45+N45)/K45 -> 3.7586897
C46: New Space Capital GP Com SCSp | D46: Unrealized | F46: G42 Investments | G46: 2023 | H46: LP | I46: n/a | J46: =2.3/0.85 -> 2.7058824 | K46: 2.7058824 | L46: 0 | M46: 0 | N46: =VLOOKUP(C46,NAV!$B$4:$E$50,4,0) -> 6.741761 | O46: =N46+M46-K46 -> 4.0358787 | P46: =(M46+N46)/K46 -> 2.4915204
C47: North Summit Capital Fund | D47: Unrealized | F47: G42 Investments | G47: 2020 | H47: LP | I47: n/a | J47: =K47+L47 -> 83.361611 | K47: 83.361611 | L47: 0 | M47: 7.875571 | N47: =NAV!E48 -> 72.566225 | O47: =N47+M47-K47 -> -2.919815 | P47: =(M47+N47)/K47 -> 0.96497411
C48: Sinovation Disrupt Fund, L.P. | D48: Realized | F48: G42 Investments | G48: 2020 | H48: LP | I48: n/a | J48: 50 | K48: =-SUMIF('CF (Funds)'!$C$4:$E$1989,C48,'CF (Funds)'!$E$4:$E$1989) -> 24.959693 | L48: 0 | M48: =SUM('CF (Funds)'!F4:F21) -> 25.403521 | N48: =VLOOKUP(C48,NAV!$B$4:$E$50,4,0) -> 0 | O48: =N48+M48-K48 -> 0.44382835 | P48: =(M48+N48)/K48 -> 1.0177818
C49: Acies Investments Fund I, L.P. | D49: Unrealized | F49: G42 Investments | G49: 2021 | H49: LP | I49: 0.33 | J49: 17.1125 | K49: =-SUMIF('CF (Funds)'!$C$4:$E$1989,C49,'CF (Funds)'!$E$4:$E$1989) -> 15.726387 | L49: =J49-K49 -> 1.3861125 | M49: 0 | N49: =VLOOKUP(C49,NAV!$B$4:$E$50,4,0) -> 14.034903 | O49: =N49+M49-K49 -> -1.6914845 | P49: =(M49+N49)/K49 -> 0.89244291 | Q49: 9.9% GP | Anchorf
J50: =SUM(J45:J49) -> 180.17124 | K50: =SUM(K45:K49) -> 143.76326 | L50: =SUM(L45:L49) -> 11.367673 | M50: =SUM(M45:M49) -> 40.057026 | N50: =SUM(N45:N49) -> 150.49907 | O50: =N50+M50-K50 -> 46.792841 | P50: =(M50+N50)/K50 -> 1.3254854
C52: MGX & Related Investments
C53: MGX I LP + Denali | D53: Unrealized | F53: G42 Holding | G53: 2024 | H53: LP | I53: ='%'!F44 -> 0.03125 | J53: =MGX!D47+MGX!D48 -> 1559.798 | K53: =MGX!E47+MGX!E48 -> 386.49987 | L53: =MGX!F47+MGX!F48 -> 1173.2982 | M53: =MGX!G47+MGX!G48 -> 14.688852 | N53: =MGX!H47+MGX!H48 -> 1011.2783 | O53: =MGX!I47+MGX!I48 -> 624.77841 | P53: =(M53+N53)/K53 -> 2.6545083
C54: MGX 1 Strategic Co-invest | D54: Unrealized | F54: G42 Holding | G54: 2024 | H54: LP | I54: 0.5 | J54: =MGX!D49 -> 296.60196 | K54: =MGX!E49 -> 294.25155 | L54: =MGX!F49 -> 2.350415 | M54: =MGX!G49 -> 0 | N54: =MGX!H49 -> 1180.3733 | O54: =MGX!I49 -> 886.12179 | P54: =(M54+N54)/K54 -> 4.0114431
C55: MGX Group Holding 1 Ltd (GP) | D55: Unrealized | F55: G42 Holding | G55: 2024 | H55: Equity | J55: =MGX!D50 -> 25 | K55: =MGX!E50 -> 25 | L55: =MGX!F50 -> 0 | M55: =MGX!G50 -> 0 | N55: =MGX!H50 -> 25 | O55: =MGX!I50 -> 0 | P55: =(M55+N55)/K55 -> 1
J56: =SUM(J53:J55) -> 1881.4 | K56: =SUM(K53:K55) -> 705.75142 | L56: =SUM(L53:L55) -> 1175.6486 | M56: =SUM(M53:M55) -> 14.688852 | N56: =SUM(N53:N55) -> 2216.6516 | O56: =SUM(O53:O55) -> 1510.9002 | P56: =(M56+N56)/K56 -> 3.1616521
C58: Total | J58: =J36+J42+J50+J56 -> 4454.975 | K58: =K36+K42+K50+K56 -> 3242.6685 | L58: =L36+L42+L50+L56 -> 1187.2663 | M58: =M36+M42+M50+M56 -> 1483.7633 | N58: =N36+N42+N50+N56 -> 4542.7062 | O58: =O36+O42+O50+O56 -> 2769.1122 | P58: =(M58+N58)/K58 -> 1.8584908
C61: Additional Upside Section:
C62: a) Flyr: For every $1m of revenue, 194,477 shares, capped at 1,264,1000 (B-1) shares shall be issued to Mozn
C63: b) DriveNets: Share warrants exercisable upon the achievement of target revenue of clients referred by G42, and corresponding milestones
C64: c) vTv Therapeutics: Potential issuance of $30m in additional shares, if FDA approval received for the drug TTP399
C65: d) Tools for Humanity Corporation: An additional 62.5 million Tokens (WLD tokens) received for a consideration of $6,875.00.
C66: e) E-line Ventures LLC: Option to further acquire Series B Pref shares at max($1.34, EV/No of shares)
C67: f) Acies Investments Fund I LP: Being the Anchor investor, entitled to 9.9% of the aggregate carried interest earned by the GP
C68: g) Cloud Credit of 250K counted towards the investment cost
C69: h) Inveniam: 60% upside if Tokens sold $2.5+, Anti Dilution protection
C70: i) Cererbras: 1,857,516 shares received in Jan'26
C71: IRR is referred as NM when it is not meaningful
C73: Definitions:
... C92: TBC = to be confirmed

Sheet 9. All deals (b)
C2: As of date | D2: ='A. All deals (a)'!D2 -> 46265
P3: n/a refers to information not available
C6: Deals | D6: Status | E6: Lead | F6: Investing Entity | G6: Investing Entity (Legal Entity Name) | H6: Nature of Investing Entity | I6: Investments Tax Implication tax note 1 | J6: Instrument | K6: Listed / Unlisted | L6: Website link | M6: Pitchbook link | N6: Jurisdiction | O6: % | P6: Upside (Warrants, Milestone payments, ) | Q6: For Comments Refer to Note
C8: Direct Investments
C9: Jollychic Holding Limited | D9: Written-off | E9: Elaine | F9: Mozn | G9: Mozn Holding RSC Ltd | H9: Potential QFZP tax note 2 | I9: If qualifies for QFZP and hold the investment >= 12m, income/loss from the investee supposed to suject to 0% Corporate tax rate for Investing Entity | J9: C+ Prefs | L9: link | M9: link | N9: Cayman Islands | O9: 0.056999998 | Q9: 1
C10: Mena Mobile Inc | D10: Unrealized | E10: Elaine | F10: Mozn | G10: Mozn Holding RSC Ltd | H10: Potential QFZP tax note 2 | I10: If qualifies for QFZP and hold the investment >= 12m, income/loss from the investee supposed to suject to 0% Corporate tax rate for Investing Entity | J10: B Prefs | L10: link | M10: link | N10: Cayman Islands | O10: 0.14 | Q10: 2
C11: Flyr Inc | D11: Unrealized | E11: Sushil | F11: Mozn | G11: Mozn Holding RSC Ltd | H11: Potential QFZP tax note 2 | I11: If qualifies for QFZP and hold the investment >= 12m, income/loss from the investee supposed to suject to 0% Corporate tax rate for Investing Entity | J11: B-1,2 Prefs | L11: link | M11: link | N11: Delaware Corporation | O11: 0.085025485 | P11: Flyr Warrantsa | Q11: 3
C12: Esyasoft Holding | D12: Realized | E12: Sushil | F12: Mozn | G12: Mozn Holding RSC Ltd | H12: Potential QFZP tax note 2 | I12: If qualifies for QFZP and hold the investment >= 12m, income/loss from the investee supposed to suject to 0% Corporate tax rate for Investing Entity | J12: Convertible Note | L12: link | M12: n/a | N12: DIFC | O12: n/a | Q12: 4
C13: Beyond Limits | D13: Unrealized | E13: Divyesh | F13: Mozn | G13: Mozn Holding RSC Ltd | H13: Potential QFZP tax note 2 | I13: If qualifies for QFZP and hold the investment >= 12m, income/loss from the investee supposed to suject to 0% Corporate tax rate for Investing Entity | J13: C Prefs | L13: link | M13: link | N13: Delaware Corporation | O13: 0.097965107 | Q13: 5
C14: ONT plc | D14: Unrealized | E14: Divyesh | F14: Mozn | G14: Mozn Holding RSC Ltd | H14: Potential QFZP tax note 2 | I14: If qualifies for QFZP and hold the investment >= 12m, income/loss from the investee supposed to suject to 0% Corporate tax rate for Investing Entity | J14: Ordinary Shares | K14: Listed | L14: link | M14: link | N14: UK | O14: 0.051651565 | Q14: 6
C15: Heygears | D15: Unrealized | E15: Elaine | F15: Mozn | G15: Mozn Holding RSC Ltd | H15: Potential QFZP tax note 2 | I15: If qualifies for QFZP and hold the investment >= 12m, income/loss from the investee supposed to suject to 0% Corporate tax rate for Investing Entity | J15: Registered Capital | L15: link | M15: link | N15: PRC | O15: 0.1438 | Q15: 7
C16: Jysan Technologies | D16: Realized | E16: Sushil | F16: Mozn aa | G16: QAZ42 Investment SPV RSC Ltd | H16: Realized | I16: Realized | J16: A (Ordinary Shares) | L16: link | M16: n/a | N16: UK | O16: 0.03 | Q16: 8
C17: Cerebras Systems Inc | D17: Unrealized | E17: Ignasi | F17: Mozn | G17: Mozn Holding RSC Ltd | H17: Potential QFZP tax note 2 | I17: If qualifies for QFZP and hold the investment >= 12m, income/loss from the investee supposed to suject to 0% Corporate tax rate for Investing Entity | J17: F Prefs | L17: link | M17: link | N17: Delaware Corporation | O17: 0.0091172068 | Q17: 9
C18: Endless Studios LLC | D18: Unrealized | E18: Sushil | F18: Mozn | G18: Mozn Holding RSC Ltd | H18: Potential QFZP tax note 2 | I18: To be monitored (see Note 0) | J18: A Pref Units | L18: link | M18: link | N18: Delaware Corporation | O18: 0.16080402 | Q18: 10
C19: Instadeep Limited | D19: Realized | E19: Ignasi | F19: Mozn | G19: Mozn Holding RSC Ltd | H19: Potential QFZP tax note 2 | I19: If qualifies for QFZP and hold the investment >= 12m, income/loss from the investee supposed to suject to 0% Corporate tax rate for Investing Entity | J19: B Prefs | L19: link | M19: link | N19: UK | O19: 0.011489406 | Q19: 11
C20: X-fusion | D20: Realized | E20: Elaine | F20: Mozn bb | G20: Enterprise Connection Holding RSC Ltd | H20: Non-QFZP | I20: pending | J20: Equity-TBC | L20: link | M20: link | N20: PRC | O20: 0.051 | Q20: 12
C21: DriveNets | D21: Unrealized | E21: Anton | F21: G42 | G21: D2 Investments RSC Ltd | H21: Non-QFZP | I21: Should qualify for Participation interest | J21: Equity-TBC | L21: link | M21: link | N21: Israeli Pvt Company | O21: 0.11141914 | P21: DN Warrants b | Q21: 13
C22: vTv Therapeutics Inc. | D22: Unrealized | E22: Divyesh | F22: G42 | G22: G42 Investments AI Holdings RSC Ltd | H22: Potential QFZP tax note 2 | I22: To be monitored (see Note 0) | J22: Ordinary Shares | K22: Listed | L22: link | M22: link | N22: Delaware Corporation | O22: 0.0022129091 | P22: vTv $30m milestn payment c | Q22: 14
C23: Honor Device Co Ltd | D23: Realized | E23: Elaine | F23: G42 cc | G23: Smart Interaction1 Holding SPV RSC LTD | H23: pending | I23: pending | J23: Equity-TBC | L23: link | M23: link | N23: PRC | O23: 0.018823528 | Q23: 15
C24: Applied AI Corporation Limited | D24: Unrealized | E24: Divyesh | F24: Mozn | G24: Mozn Holding RSC Ltd | H24: Potential QFZP tax note 2 | I24: To be monitored (see Note 0) | J24: Convertible Note | L24: link | M24: link | N24: ADGM | O24: n/a | Q24: 16
C25: eSpace | D25: Unrealized | E25: Anton | F25: Mozn dd | G25: Constellation Investments SPV RSC Ltd (previously Smart Interaction5 Holding SPV RSC Ltd) | H25: Non-QFZP | I25: Taxable for only hold 2.8% of SAFE note in eSpace. | J25: B Prefs | L25: link | M25: link | N25: Delaware Corporation | O25: 0.027864956 | Q25: 17
C26: Tools for Humanity Corporation | D26: Unrealized | E26: Divyesh | F26: Mozn | G26: Mozn Holding RSC Ltd | H26: Potential QFZP tax note 2 | I26: To be monitored (see Note 0) | J26: C Prefs | L26: link | M26: link | N26: Delaware Corporation | O26: 0.0062621983 | Q26: 24
C27: WLD Tokens | D27: Unrealized | E27: Divyesh | F27: Mozn | G27: Mozn Holding RSC Ltd | H27: Potential QFZP tax note 2 | I27: To be monitored (see Note 0) | J27: Tokens | L27: link | M27: Coinbase | N27: DAO | Cayman Islands | O27: 0.00625 | Q27: 25 | T27: Preferred Shares
C28: E-line Ventures LLC | D28: Unrealized | E28: Sushil | F28: Mozn | G28: Mozn Holding RSC Ltd | H28: Potential QFZP tax note 2 | I28: To be monitored (see Note 0) | J28: B Prefs | L28: link | M28: link | N28: New Jersey, USA | O28: ='%'!F28 -> 0.1163 | Q28: 26 | T28: B Prefs
C29: School Hack (AIREV Holding Limited) | D29: Unrealized | E29: Camillo | F29: Core42 | G29: Core42 Investments 1 SPV RSC LTD | H29: Potential QFZP tax note 2 | I29: To be monitored (see Note 0) | J29: Preferred Shares | L29: link | M29: NA | N29: ADGM | O29: 0.25 | Q29: 27
C30: Life Biosciences LLC | D30: Unrealized | E30: Divyesh | F30: ='A. All deals (a)'!F30 -> G42 Capital | G30: Expansion Project Technologies Holding 7 SPV RSC Ltd | H30: Potential QFZP tax note 2 | I30: To be monitored (see Note 0) | J30: Convertible Note | L30: link | M30: link | N30: Delaware Corporation | O30: n/a | Q30: 28
C31: Verses AI Inc | D31: Unrealized | E31: Divyesh | F31: ='A. All deals (a)'!F31 -> G42 Capital | G31: Expansion Project Technologies Holding 9 SPV RSC Ltd | H31: Potential QFZP tax note 2 | I31: To be monitored (see Note 0) | J31: Convertible Debenture | L31: link | M31: link | N31: British Columbia | O31: n/a
C32: Inveniam | D32: Unrealized | E32: Divyesh | F32: ='A. All deals (a)'!F34 -> G42 Capital | G32: Expansion Project Technologies Holding 10 SPV RSC Ltd | H32: Potential QFZP tax note 2 | I32: To be monitored (see Note 0) | J32: SAR | L32: llink | M32: link | N32: Gibraltor | O32: 20% equivalent
C36: Debt Investments
C37: Glass Earth Holdings LLC | D37: In default | F37: Mozn | G37: G42 Investments AI Holdings RSC Ltd | H37: Potential QFZP tax note 2 | I37: not equity investment, taxable | J37: Promissory Note | L37: n/a | M37: n/a | N37: n/a | Q37: 16
C38: Mena Mobile Inc (Debt) | D38: In default | E38: Elaine | F38: Mozn | G38: Mozn Holding RSC Ltd | H38: Potential QFZP tax note 2 | I38: not equity investment, taxable | J38: Loan | L38: link | M38: link | N38: =N10 -> Cayman Islands | Q38: 17
C39: Esyasoft Holding (Debt) | D39: Unrealized | E39: Sushil | F39: Mozn | G39: Mozn Holding RSC Ltd | H39: Potential QFZP tax note 2 | I39: not equity investment, taxable | J39: Loan | L39: link | M39: n/a | N39: =N12 -> DIFC | Q39: 18
C42: Funds Investments
C43: New Space Capital Fund I | D43: Unrealized | E43: Sushil | F43: G42 | G43: G42 Investments AI Holdings RSC Ltd | H43: Potential QFZP tax note 2 | I43: If qualifies for QFZP and hold the investment >= 12m, income/loss from the investee supposed to suject to 0% Corporate tax rate for Investing Entity | J43: LP | L43: link | M43: link | N43: Luxembourg | O43: 0.22044082 | Q43: 19
C44: New Space Capital GP Com SCSp | D44: Unrealized | E44: Sushil | F44: G42 | G44: G42 Investments AI Holdings RSC Ltd | H44: Potential QFZP tax note 2 | I44: If qualifies for QFZP and hold the investment >= 12m, income/loss from the investee supposed to suject to 0% Corporate tax rate for Investing Entity | J44: GP | L44: link | M44: link | N44: Luxembourg | O44: 0.02016129 | Q44: 20
C45: North Summit Capital Fund | D45: Unrealized | E45: Elaine | F45: G42 | G45: Galbot Holding RSC Ltd | H45: Non-QFZP | I45: pending | J45: LP | L45: n/a | M45: link | N45: Cayman Islands | O45: 0.995 | Q45: 21
C46: Sinovation Disrupt Fund, L.P. | D46: Unrealized | E46: Elaine | F46: G42 | G46: G42 Investments AI Holdings RSC Ltd | H46: Potential QFZP tax note 2 | I46: If qualifies for QFZP and hold the investment >= 12m, income/loss from the investee supposed to suject to 0% Corporate tax rate for Investing Entity | J46: LP | L46: link | M46: link | N46: Cayman Islands | O46: 0.1006609 | Q46: 22
C47: Acies Investments Fund I, L.P. | D47: Unrealized | E47: Divyesh | F47: G42 | G47: G42 Investments AI Holdings RSC Ltd | H47: Potential QFZP tax note 2 | I47: If qualifies for QFZP and hold the investment >= 12m, income/loss from the investee supposed to suject to 0% Corporate tax rate for Investing Entity | J47: LP | L47: link | M47: link | N47: Delaware LLC | O47: 0.33333333 | P47: 9.9% GP | Anchor e | Q47: 23
B51: Notes:
B52: 0 | C52: General | D52: If qualifies for QFZP and hold the investment >= 12m, income/loss from the investee supposed to suject to 0% Corporate tax rate for Investing Entity. Currently we have the contribution made in June 2023 need to be monitored
B53: 1 | C53: Jollychic | D53: During 2021, Jollychic Holding Ltd has filed for its liquidation. Therefore, investment is considered to be fully impaired in Dec 21.
B54: 2 | C54: Mena Mobile | D54: Investment is written off based on the 3rd party valuation report
B55: 3 | C55: Flyr | D55: Within five years of the Initial Closing, for every USD 1mn of Qualifying Revenue generated, Flyr will issue, at no additional charge, 194,477 B-1 Prefs in the name of G42, up to a maximum of 1,264,100 B-1 Prefs.
B56: 4 | C56: Esyasoft Holding | D56: Exited
B57: 5 | C57: Beyond Limits | D57: Business targeting raising funds by the end of FY2022
B58: 6 | C58: ONT plc | D58: Listed
B59: 7 | C59: Heygears | D59: Mozn's holding is RMB 4,753,356.29 of the Registered Capital.
B60: 8 | C60: Jysan Technologies | D60: - 50% of the investment has been financed by profit sharing loan. - Further, in case of exit of G42’s investment, 50% of the sale proceeds shall be paid to the lender as full and final settlement of the outstanding liability - Exit for this investment is under process. Buyback agreement is pending for signature internally. (Relevant documents to be perused by the consolidation / reporting team for details and corresponding implications, if any) - Dividend receivable amounting to US$ 3.2 m will be waived upon exit of this investment
B61: 9 | C61: Cerebras Systems Inc | D61: The investment is currently undergoing a CFIUS review.
B62: 10 | C62: Endless Studios LLC
B63: 11 | C63: Instadeep Limited | D63: Fully Exited on 31st July with 1.5x returns.
B64: 12 | C64: X-fusion | D64: RMB 80 Mn of Registered Capital for RMB 5.7 Bn
B65: 13 | C65: Drivenets | D65: Share warrants excisable upon the achievement of target revenue of clients by referred G42. The milestones of each target revenue and respective conversion were stated in the Term Sheet.
B66: 14 | C66: vTv Therapeutics : | D66: Potential issuance of US$ 30 million in additional shares of Class A Common Stock to G42 Investments (or in cash, at the option of G42 Investments) if FDA approval is received for the marketing and the sale of a pharmaceutical product containing TTP399
B67: 15 | C67: Honor | D67: Invested in Q3 2022; During Dec 22, $250m was offloaded to another investor at cost
B68: 16 | C68: Glass Earth Holdings LLC | D68: Written off. Debt security of Glass Earth issued in 2019 were fully provided for.
B69: 17 | C69: Mena Mobile (Debt) | D69: In liquidation
B70: 18 | C70: Esyasoft Holding (Debt) | D70: Outstanding
B71: 19 | C71: New Space Capital Fund I | D71: G42 negotiated conversion of €2.3m GP investment into LP investment to vote in favor of new LP proposal.
B72: 20 | C72: New Space Capital SCSp | D72: Ibid
B73: 21 | C73: North Summit Capital | D73: Portfolio Exit Plan in Progress
B74: 22 | C74: Sinovation Disrupt Fund | D74: Expect valuation to rise as some of its portfolio companies are in the market to raise new funds
B75: 23 | C75: Acies Investments Fund I, LP
B76: 24 | C76: Tools for Humanity Corporation | D76: Additional token warrants (for 62.5 million Tokens) for a consideration of $5,875.00. Additional provision for c$2K (the warrant price) kept for exercising the warrant rights.
B77: 25 | C77: WLD Tokens | D77: Received 62.5M Tokens as of Jul'23
B78: 26 | C78: E-line Ventures LLC
B79: 27 | C79: School Hack (AIREV Holding Limited) | D79: Invested via Core42
B80: 28 | C80: Life Biosciences LLC | D80: Invested via G42 Capital
C82: Additional Upside Section:
C83: a) Flyr: For every $1m of revenue, 194,477 shares, capped at 1,264,1000 (B-1) shares shall be issued to Mozn
C84: b) DriveNets: Share warrants exercisable upon the achievement of target revenue of clients referred by G42, and corresponding milestones
C85: c) vTv Therapeutics: Potential issuance of $30m in additional shares, if FDA approval received for the drug TTP399
C86: d) Tools for Humanity Corporation: Additional token warrants issued for acquiring 62.5M Tokens for $5,875.00. Additional provision for c$2K (the warrant price) kept for exercising the warrant rights
C87: e) Acies Investments Fund I LP: Being the Anchor investor, entitled to 9.9% of the aggregate carried interest earned by the GP
C89: References:
C90: G42 refers to G42 Investments AI Holding RSC Ltd
C91: Mozn refers to Mozn Holding RSC Ltd
C92: PRC refers to People's Republic of China
C93: aa Invested via QAZ42 Investment SPV RSC Ltd (QAZ42)
C94: bb Invested via Enterprise Connection Holding RSC Ltd (Enterprise Connection)
... C101: 2 Group is currently working on the process to make Mozn Holding RSC Ltd and G42 Investments AI Holdings RSC Ltd be qualified to the QFZP requirements.

Sheet 8. WLD Grant C-133
A1: Investor Unlock Chart
A3: Investor | B3: MOZN Holding RSC Ltd
A4: Grant # | B4: C-133
A5: Investor Group | B5: MOZN Holding RSC Ltd
D7: Date | E7: Day Of Week | F7: Cumulative Tokens Unlocked | G7: Daily Tokens Unlocked | H7: Weekly Tokens Distributed | I7: Biweekly Tokens Unlocked | N7: Date | O7: Day Of Week | P7: Cumulative Tokens Unlocked | Q7: Biweekly Tokens Unlocked
A8: Input (Investor-Specific) | D8: 45497 | E8: Wednesday | F8: 46205.92 | G8: 46205.92 | H8: 46205.92 | I8: 0 | N8: 45504 | O8: Wednesday | P8: 369647.36 | Q8: 369647.36
A9: Token Grant Amount (WLD) | B9: 62500000 | D9: 45498 | E9: Thursday | F9: 92411.84 | G9: 46205.92 | H9: 0 | I9: 0 | N9: 45518 | O9: Wednesday | P9: 1016530.2 | Q9: 646882.88
A10: Unlock Start Date | B10: 45131 | D10: 45499 | E10: Friday | F10: 138617.76 | G10: 46205.92 | H10: 0 | I10: 0 | N10: 45532 | O10: Wednesday | P10: 1663413.1 | Q10: 646882.88
A11: Total Investor Group Tokens | B11: 62500000 | D11: 45500 | E11: Saturday | F11: 184823.68 | G11: 46205.92 | H11: 0 | I11: 0 | N11: 45546 | O11: Wednesday | P11: 2310296 | Q11: 646882.88
A12: Percent of this Grant | B12: 1 | D12: 45501 | E12: Sunday | F12: 231029.6 | G12: 46205.92 | H12: 0 | I12: 0 | N12: 45560 | O12: Wednesday | P12: 2957178.9 | Q12: 646882.88
A13: Custody Provider | B13: Bitgo (Unconfirmed) | D13: 45502 | E13: Monday | F13: 277235.52 | G13: 46205.92 | H13: 0 | I13: 0 | N13: 45574 | O13: Wednesday | P13: 3604061.8 | Q13: 646882.89
A14: Unlock Cadence | B14: Daily | D14: 45503 | E14: Tuesday | F14: 323441.44 | G14: 46205.92 | H14: 0 | I14: 0 | N14: 45588 | O14: Wednesday | P14: 4250944.7 | Q14: 646882.88
D15: 45504 | E15: Wednesday | F15: 369647.36 | G15: 46205.92 | H15: 323441.44 | I15: 369647.36 | N15: 45602 | O15: Wednesday | P15: 4897827.5 | Q15: 646882.88
D16: 45505 | E16: Thursday | F16: 415853.28 | G16: 46205.92 | H16: 0 | I16: 0 | N16: 45616 | O16: Wednesday | P16: 5544710.4 | Q16: 646882.88
A17: Calculation (Intermediate) | D17: 45506 | E17: Friday | F17: 462059.2 | G17: 46205.92 | H17: 0 | I17: 0 | N17: 45630 | O17: Wednesday | P17: 6191593.3 | Q17: 646882.88
A18: Day in Linear unlock period (Fast) | B18: 730 | D18: 45507 | E18: Saturday | F18: 508265.12 | G18: 46205.92 | H18: 0 | I18: 0 | N18: 45644 | O18: Wednesday | P18: 6838476.2 | Q18: 646882.88
A19: Days in Linear unlock period (Slow) | B19: 1461 | D19: 45508 | E19: Sunday | F19: 554471.04 | G19: 46205.92 | H19: 0 | I19: 0 | N19: 45658 | O19: Wednesday | P19: 7485359.1 | Q19: 646882.89
A20: Unlocking | B20: Fast + Slow | D20: 45509 | E20: Monday | F20: 600676.96 | G20: 46205.92 | H20: 0 | I20: 0 | N20: 45672 | O20: Wednesday | P20: 8132241.9 | Q20: 646882.88
A21: Day of Week Disbursement | B21: Wednesday | D21: 45510 | E21: Tuesday | F21: 646882.88 | G21: 46205.92 | H21: 0 | I21: 0 | N21: 45686 | O21: Wednesday | P21: 8779124.8 | Q21: 646882.88
D22: 45511 | E22: Wednesday | F22: 693088.8 | G22: 46205.92 | H22: 323441.44 | I22: 0 | N22: 45700 | O22: Wednesday | P22: 9426007.7 | Q22: 646882.88
D23: 45512 | E23: Thursday | F23: 739294.72 | G23: 46205.92 | H23: 0 | I23: 0 | N23: 45714 | O23: Wednesday | P23: 10072891 | Q23: 646882.88
D24: 45513 | E24: Friday | F24: 785500.64 | G24: 46205.92 | H24: 0 | I24: 0 | N24: 45728 | O24: Wednesday | P24: 10719773 | Q24: 646882.89
D25: 45514 | E25: Saturday | F25: 831706.56 | G25: 46205.92 | H25: 0 | I25: 0 | N25: 45742 | O25: Wednesday | P25: 11366656 | Q25: 646882.88
D26: 45515 | E26: Sunday | F26: 877912.48 | G26: 46205.92 | H26: 0 | I26: 0 | N26: 45756 | O26: Wednesday | P26: 12013539 | Q26: 646882.88
D27: 45516 | E27: Monday | F27: 924118.4 | G27: 46205.92 | H27: 0 | I27: 0 | N27: 45770 | O27: Wednesday | P27: 12660422 | Q27: 646882.88
D28: 45517 | E28: Tuesday | F28: 970324.32 | G28: 46205.92 | H28: 0 | I28: 0 | N28: 45784 | O28: Wednesday | P28: 13307305 | Q28: 646882.88
D29: 45518 | E29: Wednesday | F29: 1016530.2 | G29: 46205.92 | H29: 323441.44 | I29: 646882.88 | N29: 45798 | O29: Wednesday | P29: 13954188 | Q29: 646882.89
D30: 45519 | E30: Thursday | F30: 1062736.2 | G30: 46205.92 | H30: 0 | I30: 0 | N30: 45812 | O30: Wednesday | P30: 14601071 | Q30: 646882.88
D31: 45520 | E31: Friday | F31: 1108942.1 | G31: 46205.92 | H31: 0 | I31: 0 | N31: 45826 | O31: Wednesday | P31: 15247954 | Q31: 646882.88
D32: 45521 | E32: Saturday | F32: 1155148 | G32: 46205.92 | H32: 0 | I32: 0 | N32: 45840 | O32: Wednesday | P32: 15894837 | Q32: 646882.88
D33: 45522 | E33: Sunday | F33: 1201353.9 | G33: 46205.92 | H33: 0 | I33: 0 | N33: 45854 | O33: Wednesday | P33: 16541719 | Q33: 646882.88
... D111: 45600 | E111: Monday | F111: 4805415.7 | G111: 46205.92 | H111: 0 | I111: 0 | N111: 46946 | O111: Wednesday | P111: 62067077 | Q111: 550992.47
D112: 45601 | E112: Tuesday | F112: 4851621.6 | G112: 46205.92 | H112: 0 | I112: 0 | N112: 46960 | O112: Wednesday | P112: 62500000 | Q112: 432922.66 | R112: =P112 -> 62500000
D113: 45602 | E113: Wednesday | F113: 4897827.5 | G113: 46205.92 | H113: 323441.44 | I113: 646882.88
D114: 45603 | E114: Thursday | F114: 4944033.5 | G114: 46205.92 | H114: 0 | I114: 0
D115: 45604 | E115: Friday | F115: 4990239.4 | G115: 46205.92 | H115: 0 | I115: 0
D116: 45605 | E116: Saturday | F116: 5036445.3 | G116: 46205.92 | H116: 0 | I116: 0
D117: 45606 | E117: Sunday | F117: 5082651.2 | G117: 46205.92 | H117: 0 | I117: 0
D118: 45607 | E118: Monday | F118: 5128857.1 | G118: 46205.92 | H118: 0 | I118: 0
D119: 45608 | E119: Tuesday | F119: 5175063 | G119: 46205.92 | H119: 0 | I119: 0
D120: 45609 | E120: Wednesday | F120: 5221269 | G120: 46205.92 | H120: 323441.44 | I120: 0
D121: 45610 | E121: Thursday | F121: 5267474.9 | G121: 46205.92 | H121: 0 | I121: 0
D122: 45611 | E122: Friday | F122: 5313680.8 | G122: 46205.92 | H122: 0 | I122: 0
D123: 45612 | E123: Saturday | F123: 5359886.7 | G123: 46205.92 | H123: 0 | I123: 0
D124: 45613 | E124: Sunday | F124: 5406092.7 | G124: 46205.92 | H124: 0 | I124: 0
... D1834: 47323 | E1834: Tuesday | F1834: 62500000 | G1834: 0 | H1834: 0 | I1834: 0

Sheet 8. NewSpace
B2: New Space Capital Capital Calls | C2: 44442 | E2: 44623 | F2: 44784 | G2: 44956
Z3: Figures in USD, Mn
T4: Drawdown 14
B5: EUR | C5: Drawdown 3 | D5: Drawdown 4 | E5: Drawdown 5 | G5: Drawdown 8 | H5: Drawdown 9 | I5: Drawdown 10 | J5: Drawdown 11 | K5: Drawdown 12 | L5: Drawdown 13 | M5: Drawdown 14 | N5: Drawdown 15 | O5: Drawdown 16 | P5: Drawdown 17 | Q5: Drawdown 18 | R5: Drawdown 19 | S5: Drawdown 20 | T5: Distribution 2 | U5: Distribution | V5: Drawdown22 | W5: Drawdown 23 | Z5: Deals | AA5: New Space Capital Fund I | AB5: NewSpace Capital GP Com SCSp
B6: Date | C6: 44442 | D6: 44512 | E6: 44623 | G6: 44950 | H6: 45007 | I6: 45170 | J6: 45260 | K6: 45306 | L6: 45356 | M6: 45429 | N6: 45491 | O6: 45590 | P6: 45670 | Q6: 45721 | R6: 45821 | S6: 45874 | T6: 45454 | U6: 46021 | V6: 46146 | W6: 46211 | Z6: Status | AA6: Unrealized | AB6: Unrealized
B7: Total Commitment | C7: 19015957 | D7: 23513942 | E7: 23513942 | G7: 23234462 | H7: 23234462 | I7: 23234462 | J7: 23234462 | K7: 23234462 | L7: 23234462 | M7: 23234462 | N7: 23234462 | O7: 23234462 | P7: 23234462 | Q7: 23234462 | R7: 23234462 | S7: =R7 -> 23234462 | T7: 23234462 | U7: =T7 -> 23234462 | V7: =U7 -> 23234462 | W7: =V7 -> 23234462 | Z7: Investing Entity | AA7: G42 | AB7: G42
B8: Contributions (prior to this notice): | C8: 19226989 | D8: 19415305 | E8: 19365158 | I8: 9566817.3 | J8: =I8+I18 -> 9834193.4 | K8: =J8+J18 -> 10093474 | L8: =K8+K18 -> 12297371 | M8: =L8+L18 -> 12498073 | N8: 12128944 | O8: 13706993 | P8: 15511986 | Q8: 13493186 | R8: =L35 -> 14203894 | S8: 16528522 | T8: =T7-T9 -> 12498073 | U8: =N35 -> 14009958 | V8: 14642186 | W8: 15479709 | Z8: Vintageἀ | AA8: 2020 | AB8: 2020
B9: Remaining Commitment (prior to notice) | D9: 4098636.9 | E9: 4148784.1 | G9: 15865093 | H9: 15675627 | I9: =I7-I8 -> 13667645 | J9: =J7-J8 -> 13400268 | K9: =K7-K8 -> 13140988 | L9: =L7-L8 -> 10937091 | M9: =M7-M8 -> 10736389 | N9: =N7-N8 -> 11105518 | O9: =O7-O8 -> 9527469.1 | P9: =P7-P8 -> 7722475.5 | ... S9: =S7-S8 -> 6705940.3 | T9: =L22 -> 10736389 | U9: =U7-U8 -> 9224503.5 | V9: =V7-V8 -> 8592275.9 | W9: =W7-W8 -> 7754752.4 | Z9: Instrument | AA9: LP | AB9: LP
B10: Distribution of Actualisation Interest (Distribution 1/Drawdown 8)*: | G10: -12659067 | Z10: % | AA10: n/a | AB10: n/a
B11: Return of Capital | H11: -2067567 | Z11: Committed | AA11: 27.691913 | AB11: 2.7058824
B12: Remaining Commitment: | H12: 13608060 | Z12: Invested | AA12: 11.058035 | AB12: 2.7058824
Z13: Remaining Commitment | AA13: 16.633878 | AB13: 0
Z14: Distributions | AA14: 2.9557744 | AB14: 0
B15: Equalization -Actualization of Investments | S15: -4288037.9 | T15: -358796.4 | Z15: Carrying Value | AA15: =NAV!E46 -> 57.156181 | AB15: =AB12*AA15/AA12 -> 13.986021
B16: Equalization -Actualization of Fund Expenses | S16: -102599.82 | T16: -10332.76 | Z16: Gain | AA16: =AA15+AA14-AA12 -> 49.053921 | AB16: =AB15+AB14-AB12 -> 11.280138
B17: Equalization -Actualization of Interest - Investments & Fund Expenses | O17: -56063.44 | P17: -345590.9 | S17: -781260.09 | T17: -62495.83 | Z17: Multiple | AA17: =(AA14+AA15)/AA12 -> 5.4360433 | AB17: =(AB14+AB15)/AB12 -> 5.1687468
B18: Contribution | G18: =G9-G22 -> 189466.02 | H18: =H12-H22 -> -59584.38 | I18: 267376.08 | J18: 259280.73 | K18: 2203896.7 | L18: 200702.46 | N18: 1578048.7 | O18: 1748930.2 | Q18: 710707.2 | R18: 2324628.2 | S18: =-51671.6+6200.89+1665803.07+186376.92+65365.1 -> 1872074.4 | U18: =1770238.35*5/14 -> 632227.98 | V18: =V9-V22 -> 837523.85 | W18: 1660407.4
B19: Distribution | G19: =-G20+G18 -> 12659067 | H19: =-H20+H18 -> 1.0404619e-09 | I19: 59584.38 | U19: =-1770238.35*19/14 -> -2402466.3 | Z19: Note
B20: NET Amount Contributed / Distributed to us | C20: 203097.23 | D20: -444437.06 | E20: 233275.54 | G20: -12469601 | H20: -59584.38 | I20: =I18-I19 -> 207791.7 | J20: =J18-J19 -> 259280.73 | K20: =K18-K19 -> 2203896.7 | L20: =L18-L19 -> 200702.46 | N20: =N18-N19 -> 1578048.7 | O20: =O18-O19 -> 1748930.2 | P20: -2364391.1 | S20: -3299823.5 | T20: =SUM(T15:T17) -> -431624.99 | U20: =U18+U19 -> -1770238.3 | V20: =V18+V19 -> 837523.85 | W20: =W18+W19 -> 1660407.4 | Z20: 1. In Q1'23 we converted GP interest equivalent to the LP via the GP commitment vehicle
Z21: 2. In addition, G42 also has XX units in the GP, which presently are being carried at nil value
B22: Remaining Commitment (after this notice): | C22: 0 | D22: 4163565.3 | E22: 3915508.6 | G22: 15675627 | H22: 13667645 | I22: 13400268 | J22: =J9-J20 -> 13140988 | K22: =K9-K20 -> 10937091 | L22: =L9-L20 -> 10736389 | M22: =T22 -> 11105518 | N22: =N9-N20 -> 9527469.1 | O22: =O9+O17-O20 -> 7722475.5 | P22: =P9+P17-P20 -> 9741275.6 | Q22: =P22-Q18 -> 9030568.4 | R22: =Q22-R18 -> 6705940.3 | S22: 9224503.6 | T22: =T9-T15-T16 -> 11105518 | U22: =O34-U8-U18 -> 8592275.7 | V22: 7754752 | W22: =Q34-W8-W18 -> 6094345.2
B23: Remaining Commitment (as a % of Capital Commitments): | C23: 0 | D23: 0.1771 | E23: 0.1665 | G23: 0.6747 | H23: 0.5882 | I23: 0.5767 | J23: 0.5656 | K23: 0.4707 | L23: 0.4621 | M23: 0.478 | N23: 0.4101 | O23: 0.3324 | P23: 0.4193 | Q23: 0.3887 | R23: 0.2886 | S23: 0.397 | T23: 0.478 | U23: =U22/U7 -> 0.36980739
B24: CHECKS | D24: =ROUND(D22/D7,4)=D23 -> TRUE | E24: =ROUND(E22/E7,4)=E23 -> TRUE | G24: =ROUND(G22/G7,4)=G23 -> TRUE | H24: =ROUND(H22/H7,4)=H23 -> TRUE | I24: =ROUND(I22/I7,4)=I23 -> TRUE | J24: =ROUND(J22/J7,4)=J23 -> TRUE | K24: =ROUND(K22/K7,4)=K23 -> TRUE | L24: =ROUND(L22/L7,4)=L23 -> TRUE | M24: =ROUND(M22/M7,4)=M23 -> TRUE | N24: =ROUND(N22/N7,4)=N23 -> TRUE | ... T24: =ROUND(T22/T7,4)=T23 -> TRUE
B25: EURUSD | G25: 1.0872 | H25: 1.0773 | I25: 1.08439 | J25: 1.1004 | K25: 1.09506 | L25: 1.07869 | M25: 1.07869 | N25: 1.07869 | O25: 1.07205 | T25: 1.0743
G26: =-G25*G20/1000000 -> 13.55695 | H26: =-H25*H20/1000000 -> 0.064190253 | I26: =-I25*I20/1000000 -> -0.22532724 | J26: =-J25*J20/1000000 -> -0.28531252 | K26: =-K25*K20/1000000 -> -2.4133991 | L26: =-L25*L20/1000000 -> -0.21649574 | M26: =-M25*M20/1000000 -> 0 | N26: =-N25*N20/1000000 -> -1.7022253 | O26: =-O25*O20/1000000 -> -1.8749406 | T26: =-T25*T20/1000000 -> 0.46369473
B28: Checks | S28: =SUM(S15:S18)=S20 -> TRUE
S29: =S22-S9+S18=-S15-S16 -> TRUE
B30: Capital Account Statement | S30: =-S15-S16 -> 4390637.7
B31: New Space Capital
B33: EUR | C33: 3Q22 | D33: 4Q22 | E33: 1Q23 | F33: 2Q'23 | G33: 3Q'23 | H33: 1Q'24 | I33: 2Q'24 | J33: 3Q'24 | K33: To Q4'24… | L33: Q1'25 | M33: Q2'25 | N33: Q3'25 | O33: 46022 | P33: Q1'26 | Q33: May'26 Est | R33: Aug'26 Act
B34: Commitment | C34: 23234462 | D34: 23234462 | E34: 23234462 | F34: 23234462 | G34: 23234462 | H34: =G34 -> 23234462 | I34: =H34 -> 23234462 | J34: =I34 -> 23234462 | K34: =J34 -> 23234462 | L34: =K34 -> 23234462 | M34: =L34 -> 23234462 | N34: =M34 -> 23234462 | O34: =N34 -> 23234462 | ... R34: =Q34 -> 23234462 | T34: source: distribution letter
B35: Capital Contribution | C35: 19178323 | D35: 9436936 | E35: 9626402 | F35: 9595097 | G35: 9834193 | H35: 12498073 | I35: 12128944 | J35: 13706993 | K35: =J35+O18 -> 15455923 | L35: 14203894 | M35: 16528522 | N35: =N34-N36 -> 14009958 | O35: =N35+U18 -> 14642186 | P35: =O35 -> 14642186 | Q35: =P35+V18 -> 15479710 | R35: =R34-R36 -> 17140117
B36: Unfunded | C36: =C34-C35 -> 4056139 | D36: =D34-D35 -> 13797526 | E36: =E34-E35 -> 13608060 | F36: =F34-F35 -> 13639365 | G36: =G34-G35 -> 13400269 | H36: =H34-H35 -> 10736389 | I36: =I34-I35 -> 11105518 | J36: =J34-J35 -> 9527469 | K36: =O22 -> 7722475.5 | L36: =L34-L35 -> 9030568.4 | M36: =M34-M35 -> 6705940 | N36: =S22 -> 9224503.6 | O36: =O34-O35 -> 8592275.7 | P36: =P34-P35 -> 8592275.7 | Q36: =Q34-Q35 -> 7754751.8 | R36: =W22 -> 6094345.2
B37: Unrealized Gain | C37: 13103567 | D37: 3803379 | G37: =G38-G35 -> 2548651 | H37: =H38-H35 -> 5930326 | I37: =I38-I35 -> 5735230 | J37: =J38-J35 -> 5712270 | K37: =K38-K35 -> 5712270 | L37: =L38-L35 -> 5012213.4 | M37: =M38-M35 -> 5394952 | N37: =N38-N35 -> 3961836.7 | ... R37: =R38-R35 -> 32060773
B38: NAV (after carried interest) | C38: 32325017 | D38: 12031777 | E38: 12148021 | F38: 12218930 | G38: 12382844 | H38: 18428399 | I38: 17864174 | J38: 19419263 | K38: =J38+O18 -> 21168193 | L38: =19216107 -> 19216107 | M38: 21923474 | N38: =T55 -> 17971795 | O38: 21830651 | P38: 22011609 | Q38: =P38+V18 -> 22849133 | R38: =47540482+W18 -> 49200889 | T38: source: distribution letter
B39: Capital Return | D39: =C35-D35 -> 9741387 | T39: estimated
B40: Interest Capitalization | D40: =D42-D39 -> 2728214 | T40: estimated
B42: Total Distribution Received | D42: 12469601 | T42: source: distribution letters, Gino
B43: Remaining Commitment | D43: =15675627.21 -> 15675627 | G43: =I22 -> 13400268 | T43: source: distribution letter
K48: EUR USD | L48: =NAV!M24 -> 1.16169
S49: Contributions | T49: =S8 -> 16528522
S50: Returned | T50: =S15+S16 -> -4390637.7
S51: New capital call | T51: =S18 -> 1872074.4
T52: =SUM(T49:T51) -> 14009958
S53: NAV ratio | T53: =(T49+T50)/T49 -> 0.73435992
S54: NAV Q225 | T54: =M38 -> 21923474
S55: NAV readjusted | T55: =T53*T54+T51 -> 17971795

Sheet MGX
B3: Source: Capital Account Statement Q3 25
D4: Committed | E4: Invested | F4: Remaining Commitment | G4: Distributions | H4: Carrying Value | I4: Gain | J4: TVPI
B5: MGX I LP | C5: 0.03125 | D5: 1172.3273 | E5: 185.42966 | F5: =D5-E5 -> 986.89759 | G5: 0 | H5: =315.811679 -> 315.81168 | I5: =H5-E5 -> 130.38202 | J5: =(H5+G5)/E5 -> 1.7031347
B6: MGX I LP Denali | D6: 27.672749 | E6: =D6 -> 27.672749 | G6: 0 | H6: 41.59405 | I6: =H6-E6 -> 13.921301 | J6: =(H6+G6)/E6 -> 1.503069
B7: MGX 1 Strategic Co-invest | D7: 775 | E7: 312.49956 | F7: 462.50044 | G7: 0 | H7: 520.74653 | I7: =H7-E7 -> 208.24698 | J7: =(H7+G7)/E7 -> 1.6663913
B8: MGX Group Holding 1 Ltd (GP) | D8: 25 | E8: 25 | F8: 0 | G8: 0 | H8: 25 | I8: 0 | J8: =(H8+G8)/E8 -> 1
B11: Nov25 | Estimated
D12: Committed | E12: Invested | F12: Remaining Commitment | G12: Distributions | H12: Carrying Value | I12: Gain | J12: TVPI
B13: MGX I LP | C13: 0.03125 | D13: =D5+D6 -> 1200 | E13: =E5+E6 -> 213.10241 | F13: =F5+F6 -> 986.89759 | G13: =G5+G6 -> 0 | H13: =H5+H6 -> 357.40573 | I13: =I5+I6 -> 144.30332 | J13: =(G13+H13)/E13 -> 1.6771548
B14: MGX 1 Strategic Co-invest | D14: =D7 -> 775 | E14: =E7 -> 312.49956 | F14: =F7 -> 462.50044 | G14: =G7 -> 0 | H14: =H7 -> 520.74653 | I14: =I7 -> 208.24698 | J14: =(G14+H14)/E14 -> 1.6663913
B15: MGX Group Holding 1 Ltd (GP) | D15: =D8 -> 25 | E15: =E8 -> 25 | F15: =F8 -> 0 | G15: =G8 -> 0 | H15: =H8 -> 25 | I15: =I8 -> 0 | J15: =(G15+H15)/E15 -> 1
B16: Contributions | D16: =10526.59*10^-6 -> 0.01052659
B18: Dec25 | Estimated
D19: Committed | E19: Invested | F19: Remaining Commitment | G19: Distributions | H19: Carrying Value | I19: Gain | J19: TVPI
B20: MGX I LP | C20: 0.03125 | D20: =D13 -> 1200 | E20: =E13+D16 -> 213.11293 | F20: =D20-E20 -> 986.88707 | G20: =G13 -> 0 | H20: =(L20+L22)/1000000 -> 413.11111 | I20: =G20+H20-E20 -> 199.99818 | J20: =(G20+H20)/E20 -> 1.938461 | L20: 364626350
B21: MGX 1 Strategic Co-invest | D21: =D14 -> 775 | E21: =E14 -> 312.49956 | F21: =F14 -> 462.50044 | G21: =G14 -> 0 | H21: =L21/1000000 -> 741.85679 | I21: =G21+H21-E21 -> 429.35723 | J21: =(G21+H21)/E21 -> 2.3739451 | L21: 741856786
B22: MGX Group Holding 1 Ltd (GP) | D22: =D15 -> 25 | E22: =E15 -> 25 | F22: =F15 -> 0 | G22: =G15 -> 0 | H22: =D22 -> 25 | I22: =G22+H22-E22 -> 0 | J22: =(G22+H22)/E22 -> 1 | L22: 48484763
B24: Capital Called | C24: 85.727396
B25: Feb'26 | Estimated
D26: Committed | E26: Invested | F26: Remaining Commitment | G26: Distributions | H26: Carrying Value | I26: Gain | J26: TVPI
B27: MGX I LP | C27: 0.03125 | D27: =D20 -> 1200 | E27: =E20+$C$24 -> 298.84033 | F27: =D27-E27 -> 901.15967 | G27: =G20 -> 0 | H27: =H20+$C$24 -> 498.83851 | I27: =G27+H27-E27 -> 199.99818 | J27: =(G27+H27)/E27 -> 1.6692476
B28: MGX 1 Strategic Co-invest | D28: =D21 -> 775 | E28: =E21 -> 312.49956 | F28: =F21 -> 462.50044 | G28: =G21 -> 0 | H28: =H21 -> 741.85679 | I28: =G28+H28-E28 -> 429.35723 | J28: =(G28+H28)/E28 -> 2.3739451
B29: MGX Group Holding 1 Ltd (GP) | D29: =D22 -> 25 | E29: =E22 -> 25 | F29: =F22 -> 0 | G29: =G22 -> 0 | H29: =H22 -> 25 | I29: =G29+H29-E29 -> 0 | J29: =(G29+H29)/E29 -> 1
B31: Capital Call | C31: 70.445873 | D31: Distribution Received | E31: 14.688852
B32: Feb'26 | Estimated
D33: Committed | E33: Invested | F33: Remaining Commitment | G33: Distributions | H33: Carrying Value | I33: Gain | J33: TVPI
B34: MGX I LP | C34: 0.03125 | D34: =D27 -> 1200 | E34: =E27+$C$31 -> 369.2862 | F34: =D34-E34 -> 830.7138 | G34: =E31 -> 14.688852 | H34: =H27+C31-E31 -> 554.59553 | I34: =G34+H34-E34 -> 199.99818 | J34: =(G34+H34)/E34 -> 1.5415804
B35: MGX 1 Strategic Co-invest | D35: =D28 -> 775 | E35: =E28 -> 312.49956 | F35: =F28 -> 462.50044 | G35: =G28 -> 0 | H35: =H28 -> 741.85679 | I35: =G35+H35-E35 -> 429.35723 | J35: =(G35+H35)/E35 -> 2.3739451
B36: MGX Group Holding 1 Ltd (GP) | D36: =D29 -> 25 | E36: =E29 -> 25 | F36: =F29 -> 0 | G36: =G29 -> 0 | H36: =H29 -> 25 | I36: =G36+H36-E36 -> 0 | J36: =(G36+H36)/E36 -> 1
E38: =-('CF (Funds)'!E84+'CF (Funds)'!E85) -> 38.4118 | F38: =-'CF (Funds)'!E86 -> -19.305945
B39: May'26 | Estimated
D40: Committed | E40: Invested | F40: Remaining Commitment | G40: Distributions | H40: Carrying Value | I40: Gain | J40: TVPI
B41: MGX I LP | C41: 0.03125 | D41: =D34 -> 1200 | E41: =E34+$C$31+E38+F38 -> 458.83793 | F41: =D41-E41 -> 741.16207 | G41: =G34 -> 14.688852 | H41: =H34+E38+F38+C31 -> 644.14726 | I41: =G41+H41-E41 -> 199.99818 | J41: =(G41+H41)/E41 -> 1.4358798
B42: MGX 1 Strategic Co-invest | D42: =D35 -> 775 | E42: =E35 -> 312.49956 | F42: =F35 -> 462.50044 | G42: =G35 -> 0 | H42: =H35 -> 741.85679 | I42: =G42+H42-E42 -> 429.35723 | J42: =(G42+H42)/E42 -> 2.3739451
B43: MGX Group Holding 1 Ltd (GP) | D43: =D36 -> 25 | E43: =E36 -> 25 | F43: =F36 -> 0 | G43: =G36 -> 0 | H43: =H36 -> 25 | I43: =G43+H43-E43 -> 0 | J43: =(G43+H43)/E43 -> 1
B45: Aug'26 | Estimated
D46: Committed | E46: Invested | F46: Remaining Commitment | G46: Distributions | H46: Carrying Value | I46: Gain | J46: TVPI
B47: MGX I LP | C47: 0.03125 | D47: 1524.1451 | E47: =D47-F47 -> 350.84691 | F47: 1173.2982 | G47: 14.688852 | H47: 948.48425 | I47: =H47-E47 -> 597.63734 | J47: =(H47+G47)/E47 -> 2.7452803
B48: MGX I LP Denali | D48: 35.652964 | E48: 35.652964 | F48: =D48-E48 -> 0 | G48: 0 | H48: 62.794035 | I48: =H48-E48 -> 27.141071 | J48: =(H48+G48)/E48 -> 1.7612571
B49: MGX 1 Strategic Co-invest | D49: 296.60196 | E49: =D49-F49 -> 294.25155 | F49: 2.350415 | G49: 0 | H49: 1180.3733 | I49: =H49-E49 -> 886.12179 | J49: =(H49+G49)/E49 -> 4.0114431
B50: MGX Group Holding 1 Ltd (GP) | D50: =D43 -> 25 | E50: =E43 -> 25 | F50: =F43 -> 0 | G50: =G43 -> 0 | H50: =H43 -> 25 | I50: 0 | J50: =(H50+G50)/E50 -> 1

Sheet Log
B2: Date Log | C2: Update
B3: Aug'26
C4: MGX, North Summit Capital | D4: revised NAV for Q2'26
C5: New Space Capital, Acies | D5: revised NAV for Q2'26
B7: Jul'26
C8: Drivenets | D8: NAV updated
C9: New Space Capital | D9: Capital Call EUR 1.66m
B10: Jun'26
B12: May'26
C13: New Space | D13: funded capital call of EUR 0.84M
C14: MGX | D14: Funded capital calls of US$38.4m and $0.003m, received $19.3m of equalization refund
B16: Apr'26
C17: Cerebras | D17: Received additional c1.66m shares upon conversion of Warrant2
C18: New Space Capital | D18: NAV revised
B20: Mar'26
C21: Heygears | D21: Valuation re-priced round at RMB 141.2 per share
C22: Drivenets | D22: Valuation re-priced round at US$7.35 per share
C23: MGX | D23: Distributions received
B25: Feb'26
C26: Liquid AI | D26: $40.8m invested in Liquid
C27: MGX | D27: $85.7m invested in MGX on 24 Feb
C28: NAV updated | D28: NAVs for Flyr, Beyond Limits, Eline, Endless aligned with the latest agreed with auditors
B30: Jan'26
C31: Cerebras | D31: Valuation increased to $89.02per share, as per the latest funding round
C32: New Space Capital SCSp | D32: received EUR 175,237.47 distribution
C33: Liquid AI | D33: updated commitment to 41m in exchange of additional 384,643 shares (to be completed in Feb'26)
B35: Dec'25
C36: Heygears | D36: Valuation revised down to $24.4m
C37: Espace | D37: Revised valuation as per last round (refer Carta)
C38: Cerebras | D38: Received Warrant1 for 1.86m shares
B40: Nov'25
C41: Cerebras | D41: Removed capital commitment of $117.5m
B43: Oct' 25
B45: Sep' 25
C46: MGX | D46: Capital Call USD 48,875,744.38
C47: New Space Capital distribution | D47: EUR 3,299,823.45
C48: Cerebras | D48: Revised valuation as per the last financing round
B50: Aug' 25
C51: North Summit Capital Fund | D51: removed new funding requirement
B53: Jul'25
C54: MGX | D54: MGX capital calls paid USD 6,182,440.92, MGX equalization refund received USD 57,059,152.35
B56: Jun'25
C57: New Space Capital | D57: Funded a capital call of EUR 2.3m
B59: May'25
C60: Neuralink | D60: $50m investment
C61: Flyr, Drivenets | D61: Updated % ownership details
C62: Cerebras | D62: Revised Commitment to $111.7m (from $335m)
C63: ESpace | D63: Revised valuation as per round B6 (refer Carta)
B65: Apr'25
C66: Drivenets | D66: Received distribution of $84.8m from partial exit
C67: MGX | D67: Funded $2.1m for the capital call
C68: Heygears | D68: Valuation revised, as per the guidance by Ardent, Dec'24
B70: Mar'25 | Expected developments during March 2025, which are still in progress
C71: New Space Capital | D71: Additional Capital Call EUR 711K
C72: Acies | D72: Additional Capital Call, USD 1.7m
C73: MGX | D73: Additional Capital Call, USD c150m across the main fund and co-investments
C74: Liquid AI | D74: Invested $20m, for the first closing
C75: Eline | D75: Valuation revised, as per the guidance by Ardent, Dec'24
C76: Endless | D76: Valuation revised, as per the guidance by Ardent, Dec'24
C77: Drivenets | D77: Valuation revised, as per the guidance by Ardent, Dec'24
B79: Feb'25
C80: New Space Capital | D80: Actualization Interest + Return of Capital Distribution of EUR 2.4m received
B82: Jan'25
C83: Liquid AI | D83: Subjected to CFIUS approval; new investment w/ $65m commitment and an option to invest a further $40m
C84: Cerebras F1 | D84: Subjected to CFIUS clearance, $335m commitment to invest in the series F1
C85: MGX and associated investments | D85: $2Bn of commitments across the fund, and the co-investment vehicles
C86: Verses | D86: Received $320K of the transaction costs, but not included in the distributions, as it is an offset to the transaction costs
B87: Dec'24
C88: AAICO | D88: carrying value marked up to $39M (or 2.27X of cost)
C89: eSpace | D89: carrying value marked up to $58.44 per share
C90: Inveniam | D90: recevied a distribution of $499K in lieu of profit share for Surplus Worldcoin Token Proceeds
B91: Nov'24
C92: WLD coin | D92: Divested all 62.5M tokens for $100M
C93: Inveniam | D93: Acquired 20% equivalent equity via SAR, in exchange for WLD valued at $100M
C94: AAICO: | D94: Accelerated Milestone 3 investment of $3.5m, released on 21 Nov 24
C95: New Space Capital | D95: Capital Call No. 16 of EUR1.75M. Q3-24 NAV at EUR 19.42M
C96: North Summit Capital | D96: Capital Call No. 15 of $ 31,561. Q3-24 NAV at $81.6M
C97: Flyr | D97: NAV marked to the recent Series D raised at $7.1307 per share
C98: BL | D98: Successfully raised loan from shareholders of $12.9M
B99: Oct'24
C100: Lifebio : Invested additional $20m, and converted the outstanding $20m CLN.
B101: Sep'24
C102: No investment cash inflows or outflows to report
B103: Aug'24
C104: New Space Capital capital call of EUR 2.1m funded
C105: Beyond Limits carrying value marked down
B106: Jul'24
C107: No investment cash inflows or outflows to report
B108: Jun'24
C109: Verses : $10m Investment in Convertible Debenture
C110: North Summit Capital : capital contribution $55.7K
C111: New Space Capital : distributions received EUR 431.6K
C112: Flyr: Carrying Value reduced to $30m from $65m
B113: May' 24
C114: No investment cash inflows or outflows to report
B115: Apr' 24
C116: No investment cash inflows or outflows to report
B117: Mar'24
C118: New Space Capital LP: Capital contribution of EUR 200,702.46 as of 21 Mar 24
C119: Carrying values of Flyr, Beyond Limits and DriveNets marked down as per Ardent guidance
...

Sheet check-Jul'26
C2: As of date
C3: 46234
J5: 2 | K5: 4 | L5: 5 | M5: 6 | N5: 7 | O5: 8 | P5: 9 | Q5: 10 | R5: 11 | S5: 12 | T5: 13 | U5: 14 | V5: 15
C6: Deals | D6: Key Person | E6: G42 Sponsor | F6: Geography | G6: Sector | H6: Last Series | I6: Type | J6: Status | K6: Investing Entity | L6: Vintageἀ | M6: Instrument | N6: % | O6: Committed | P6: Invested | Q6: Remaining Commitment | R6: Distributions | S6: Carrying Value | T6: Gain | U6: TVPI | V6: Additonal Upside/Downside
M7: # | N7: % | O7: $,m | P7: $,m | Q7: $,m | R7: $,m | S7: $,m | T7: $,m | U7: X
C8: MOZN Holding RSC Ltd
C9: E-line Ventures LLC | D9: Sushil | E9: Peng | F9: USA | G9: Education | H9: B Prefs | I9: Direct Investment | J9: Unrealized | K9: Mozn | L9: 2023 | M9: B Prefs | N9: 0.1163 | O9: 6 | P9: 6 | Q9: 0 | R9: 0 | S9: 7.1 | T9: 1.1 | U9: 1.1833333 | V9: Optionse
C10: Tools for Humanity Corporation | D10: Divyesh | E10: Peng | F10: USA | G10: Biometrics | H10: C Prefs | I10: Direct Investment | J10: Unrealized | K10: Mozn | L10: 2023 | M10: C Prefs | N10: 0.00626608 | O10: 14.999999 | P10: 14.999999 | Q10: 0 | R10: 0 | S10: 1.2 | T10: -13.799999 | U10: 0.080000006
C11: eSpace | D11: Sushil | E11: Peng | F11: USA | G11: Space | H11: C Prefs | I11: Direct Investment | J11: Unrealized | K11: Mozn 4 | L11: 2022 | M11: B Prefs | N11: 0.02481 | O11: 15 | P11: 15 | Q11: 0 | R11: 0 | S11: 230.00751 | T11: 215.00751 | U11: 15.333834
C12: Applied AI Corporation Limited | D12: Divyesh | E12: HE Tariq | F12: UAE/UK | G12: AI Software | H12: Convertible | I12: Direct Investment | J12: Unrealized | K12: Mozn | L12: 2022 | M12: A Prefs | N12: 0.12121516 | O12: 15 | P12: 15 | Q12: 0 | R12: 0 | S12: 38.46473 | T12: 23.46473 | U12: 2.5643153
C13: Cerebras Systems Inc (1) | D13: Divyesh | E13: Peng | F13: USA | G13: Semiconductors | H13: Listed | I13: Direct Investment | J13: Unrealized | K13: Mozn | L13: 2021 | M13: Class A/B | N13: 0.0065613279 | O13: 39.999983 | P13: 39.999983 | Q13: 0 | R13: 0 | S13: 286.48239 | T13: 246.48241 | U13: 7.1620628
C14: Endless Studios LLC | D14: Sushil | E14: Peng | F14: USA | G14: Gaming | H14: A Pref Units | I14: Direct Investment | J14: Unrealized | K14: Mozn | L14: 2021 | M14: A Pref Units | N14: 0.16016016 | O14: 8 | P14: 8 | Q14: 0 | R14: 0 | S14: 6.5 | T14: -1.5 | U14: 0.8125
C15: Heygears | D15: Divyesh | E15: Peng | F15: PRC | G15: 3D Printing | H15: Series D | I15: Direct Investment | J15: Unrealized | K15: Mozn | L15: 2020 | M15: Registered Capital | N15: 0.14383199 | O15: 60 | P15: 60 | Q15: 0 | R15: 0 | S15: 71.918846 | T15: 11.918846 | U15: 1.1986474
C16: Beyond Limits | D16: Sushil | E16: Peng | F16: USA | G16: AI Software | H16: C Prefs | I16: Direct Investment | J16: Unrealized | K16: Mozn | L16: 2020 | M16: C Prefs | N16: 0.065 | O16: 90 | P16: 90 | Q16: 0 | R16: 0 | S16: 21.7 | T16: -68.3 | U16: 0.24111111
C17: ONT plc | D17: Divyesh | E17: Peng | F17: UK | G17: Genome Sequencing | H17: Ordinary Shares | I17: Direct Investment | J17: Unrealized | K17: Mozn | L17: 2020 | M17: Ordinary Shares | N17: 0.045562985 | O17: 141.47026 | P17: 141.47026 | Q17: 0 | R17: 0 | S17: 67.522366 | T17: -73.947894 | U17: 0.47729018
C18: Flyr Inc | D18: Divyesh | E18: Peng | F18: USA | G18: Aviation | H18: B-1,2 Prefs | I18: Direct Investment | J18: Unrealized | K18: Mozn | L18: 2019 | M18: B-1,2 Prefs | N18: 0.0334 | O18: 10 | P18: 10 | Q18: 0 | R18: 0 | S18: 14.6 | T18: 4.6 | U18: 1.46 | V18: Flyr Warrantsa
O20: 400.47024 | P20: 400.47024 | Q20: 0 | R20: 0 | S20: 745.49584 | T20: 345.0256 | U20: 1.8615512
C22: G42 Investments AI Holding RSC Ltd
C23: DriveNets | D23: Sushil | E23: HE Tariq | F23: Israel | G23: Networking | I23: Direct Investment | J23: Partially Realized | K23: G42 Investments | L23: 2022 | M23: Equity-TBC | N23: 0.0655 | O23: 300 | P23: 300 | Q23: 0 | R23: 84.804486 | S23: 497.53506 | T23: 282.33954 | U23: 1.9411318 | V23: DN Warrants b
C24: vTv Therapeutics Inc. | D24: Divyesh | E24: Dr. Fahed, M42 | F24: USA | G24: Healthcare | I24: Direct Investment | J24: Unrealized | K24: G42 Investments | L24: 2022 | M24: Ordinary Shares | N24: 0.020924424 | O24: 24.53125 | P24: 24.53125 | Q24: 0 | R24: 0 | S24: 8.399904 | T24: -16.131346 | U24: 0.34241647 | V24: vTv $30m milestn payment c
C25: North Summit Capital Fund | D25: Divyesh | E25: Peng | F25: Cayman | G25: Fund | I25: Fund Investment | J25: Unrealized | K25: G42 Investments | L25: 2020 | M25: LP | N25: n/a | O25: 83.361611 | P25: 83.361611 | Q25: 0 | R25: 7.875571 | S25: 69.985053 | T25: -5.500987 | U25: 0.93401055
C26: New Space Capital Fund I | D26: Sushil | E26: Peng | F26: Luxembourg | G26: Fund | I26: Fund Investment | J26: Unrealized | K26: G42 Investments | L26: 2020 | M26: LP | N26: n/a | O26: 26.782364 | P26: 16.878048 | Q26: 9.9043162 | R26: 6.7779339 | S26: 28.252147 | T26: 18.152033 | U26: 2.0754817
C27: New Space Capital GP Com SCSp | D27: Sushil | E27: Peng | F27: Luxembourg | G27: Fund | I27: Fund Investment | J27: Unrealized | K27: G42 Investments | L27: 2023 | M27: LP | N27: n/a | O27: 2.7058824 | P27: 2.7058824 | Q27: 0 | R27: 0 | S27: 3.8583795 | T27: 1.1524971 | U27: 1.4259229
C28: Acies Investments Fund I, L.P. | D28: Divyesh | E28: Peng | F28: USA | G28: Fund | I28: Fund Investment | J28: Unrealized | K28: G42 Investments | L28: 2021 | M28: LP | N28: 0.33 | O28: 17.1125 | P28: 15.726387 | Q28: 1.3861125 | R28: 0 | S28: 12.683716 | T28: -3.0426715 | U28: 0.80652445 | V28: 9.9% GP | Anchorf
O30: 454.49361 | P30: 443.20318 | Q30: 11.290429 | R30: 99.457991 | S30: 620.71426 | T30: 276.96907 | U30: 1.6249257
C32: G42 Capital SPV RSC Ltd
C33: Life Biosciences LLC | D33: Divyesh | E33: Peng/XP | F33: USA | G33: Healthcare | I33: Direct Investment | J33: Unrealized | K33: G42 Capital | L33: 2024 | M33: D Prefs | N33: 0.0639 | O33: 40 | P33: 40 | Q33: 0 | R33: 0 | S33: 40.947394 | T33: 0.94739371 | U33: 1.0236848 | V33: EPTH7
C34: Verses AI Inc | D34: Divyesh | E34: Peng/XP | F34: Canada | G34: AI Software | I34: Direct Investment | J34: Unrealized | K34: G42 Capital | L34: 2024 | M34: Ordinary Shares | N34: 0.035972427 | O34: 10 | P34: 10 | Q34: 0 | R34: 0 | S34: 0 | T34: -10 | U34: 0 | V34: EPTH9 Revenue linked RSUs
C35: Inveniam Ltd | D35: Divyesh | E35: Jon Nieman | F35: USA | G35: AI Software | I35: Direct Investment | J35: Unrealized | K35: G42 Capital | L35: 2024 | M35: SAR | N35: NA | O35: 100 | P35: 100 | Q35: 0 | R35: 0.499965 | S35: 100 | T35: 0.499965 | U35: 1.0049997 | V35: EPTH10 Upside if Tokens sold > $2.5 per token
C36: Liquid AI | D36: Divyesh | E36: Peng | F36: USA | G36: Foundation Model | I36: Direct Investment | J36: Unrealized | K36: G42 Capital | L36: 2025 | M36: Series A | N36: 0.030216555 | O36: 60.819863 | P36: 60.819863 | Q36: 0 | R36: 0 | S36: 66.599184 | T36: 5.7793208 | U36: 1.0950236 | V36: EPTH11
C37: Neuralink | D37: Divyesh | E37: Peng | F37: USA | G37: Healthcare | I37: Direct Investment | J37: Unrealized | K37: G42 Capital | L37: 2025 | M37: Series E | N37: 0.0051805228 | O37: 50 | P37: 50 | Q37: 0 | R37: 0 | S37: 50 | T37: 5e-07 | U37: 1 | V37: EPTH12
C38: Cerebras Systems Inc (2) | D38: Divyesh | E38: Peng | F38: USA | G38: Semiconductors | I38: Direct Investment | J38: Unrealized | K38: G42 Capital | L38: 2026 | M38: Class A/B | N38: 0.015990144 | O38: 0.03513491 | P38: 0.03513491 | Q38: 0 | R38: 0 | S38: 698.1658 | T38: 698.13066 | U38: >10x | V38: EPTH8 (1.86m shares W1 plus 1.66m shares W2)
O40: 260.855 | P40: 260.855 | Q40: 0 | R40: 0.499965 | S40: 955.71237 | T40: 695.35734 | U40: 3.6656853
C42: Core42 Holding RSC Ltd
C43: School Hack (AIREV Holding Limited) | D43: Divyesh | E43: Peng | F43: UAE | G43: AI Software | I43: Direct Investment | J43: Unrealized | K43: Core42 5 | L43: 2024 | M43: Preferred Shares | N43: 0.23 | O43: 2.75 | P43: 2.5 | Q43: 0.25 | R43: 0 | S43: 2.5 | T43: 0 | U43: 1 | V43: Cloud Creditg
O45: 2.75 | P45: 2.5 | Q45: 0.25 | R45: 0 | S45: 2.5 | T45: 0 | U45: 1
C47: GX Investments Ltd : MGX and Related Investments
C48: MGX I LP | D48: Nitesh/Gino | E48: Peng | F48: UAE | G48: Fund | I48: MGX LP | J48: Unrealized | K48: G42 Holding | L48: 2024 | M48: LP | N48: 0.03125 | O48: 1200 | P48: 458.83793 | Q48: 741.16207 | R48: 14.688852 | S48: 644.14726 | T48: 199.99818 | U48: 1.4358798
C49: MGX 1 Strategic Co-invest | D49: Nitesh/Gino | E49: Peng | F49: UAE | G49: Fund | I49: MGX Co-Invest LP | J49: Unrealized | K49: G42 Holding | L49: 2024 | M49: LP | N49: 0.5 | O49: 775 | P49: 312.49956 | Q49: 462.50044 | R49: 0 | S49: 741.85679 | T49: 429.35723 | U49: 2.3739451
C50: MGX Group Holding 1 Ltd (GP) | D50: Nitesh/Gino | E50: Peng | F50: UAE | G50: Fund | I50: MGX GP | J50: Unrealized | K50: G42 Holding | L50: 2024 | M50: Equity | N50: 0 | O50: 25 | P50: 25 | Q50: 0 | R50: 0 | S50: 25 | T50: 0 | U50: 1
O52: 2000 | P52: 796.33749 | Q52: 1203.6625 | R52: 14.688852 | S52: 1411.004 | T52: 629.35541 | U52: 1.7903124
O54: 3118.5688 | P54: 1903.3659 | Q54: 1215.2029 | R54: 114.64681 | S54: 3735.4265 | T54: 1946.7074 | U54: 2.022771
M57: Checks:
C58: For Notes, refer to 9. All deals (a)
C59: Position Exited or written off are highlighted

Sheet check-diff
C2: As of date
C3: 45869
C5: Deals
C6: Deals | D6: Key Person | E6: G42 Sponsor | F6: Geography | G6: Sector | H6: Last Series | I6: Type | J6: Status | K6: Investing Entity | L6: Vintageἀ | M6: Instrument | N6: % | O6: Committed | P6: Invested | Q6: Remaining Commitment | R6: Distributions | S6: Carrying Value | T6: Gain | U6: TVPI | V6: Additonal Upside/Downside
M7: #
C8: MOZN Holding RSC Ltd
C9: E-line Ventures LLC | D9: Sushil | E9: Peng | F9: USA | G9: Education | H9: B Prefs | I9: Direct Investment | J9: Unrealized | K9: Mozn | L9: 2023 | M9: B Prefs | N9: =IF('1. Live'!N9='check-Jul''26'!N9,"",'1. Live'!N9-'check-Jul''26'!N9) | O9: =IF('1. Live'!O9='check-Jul''26'!O9,"",'1. Live'!O9-'check-Jul''26'!O9) | P9: =IF('1. Live'!P9='check-Jul''26'!P9,"",'1. Live'!P9-'check-Jul''26'!P9) | Q9: =IF('1. Live'!Q9='check-Jul''26'!Q9,"",'1. Live'!Q9-'check-Jul''26'!Q9) | R9: =IF('1. Live'!R9='check-Jul''26'!R9,"",'1. Live'!R9-'check-Jul''26'!R9) | S9: =IF('1. Live'!S9='check-Jul''26'!S9,"",'1. Live'!S9-'check-Jul''26'!S9) | T9: =IF('1. Live'!T9='check-Jul''26'!T9,"",'1. Live'!T9-'check-Jul''26'!T9) | U9: =IF('1. Live'!U9='check-Jul''26'!U9,"",'1. Live'!U9-'check-Jul''26'!U9) | V9: =IF('1. Live'!V9='check-Jul''26'!V9,"",'1. Live'!V9-'check-Jul''26'!V9) | AA9: =IF('1. Live'!AA9='check-Jul''26'!W9,"",'1. Live'!AA9-'check-Jul''26'!W9) | AB9: =IF('1. Live'!AF9='check-Jul''26'!AB9,"",'1. Live'!AF9-'check-Jul''26'!AB9) | AC9: =IF('1. Live'!AG9='check-Jul''26'!AC9,"",'1. Live'!AG9-'check-Jul''26'!AC9) | AD9: =IF('1. Live'!AH9='check-Jul''26'!AD9,"",'1. Live'!AH9-'check-Jul''26'!AD9) | AE9: =IF('1. Live'!AI9='check-Jul''26'!AE9,"",'1. Live'!AI9-'check-Jul''26'!AE9) | AF9: =IF('1. Live'!AJ9='check-Jul''26'!AF9,"",'1. Live'!AJ9-'check-Jul''26'!AF9) | AG9: =IF('1. Live'!AK9='check-Jul''26'!AG9,"",'1. Live'!AK9-'check-Jul''26'!AG9) | AH9: =IF('1. Live'!AL9='check-Jul''26'!AH9,"",'1. Live'!AL9-'check-Jul''26'!AH9) | AI9: =IF('1. Live'!AM9='check-Jul''26'!AI9,"",'1. Live'!AM9-'check-Jul''26'!AI9) | ... CV9: =IF('1. Live'!CZ9='check-Jul''26'!CV9,"",'1. Live'!CZ9-'check-Jul''26'!CV9)
C10: Tools for Humanity Corporation | D10: Divyesh | E10: Peng | F10: USA | G10: Biometrics | H10: C Prefs | I10: Direct Investment | J10: Unrealized | K10: Mozn | L10: 2023 | M10: C Prefs | N10: =IF('1. Live'!N10='check-Jul''26'!N10,"",'1. Live'!N10-'check-Jul''26'!N10) | O10: =IF('1. Live'!O10='check-Jul''26'!O10,"",'1. Live'!O10-'check-Jul''26'!O10) | P10: =IF('1. Live'!P10='check-Jul''26'!P10,"",'1. Live'!P10-'check-Jul''26'!P10) | Q10: =IF('1. Live'!Q10='check-Jul''26'!Q10,"",'1. Live'!Q10-'check-Jul''26'!Q10) | R10: =IF('1. Live'!R10='check-Jul''26'!R10,"",'1. Live'!R10-'check-Jul''26'!R10) | S10: =IF('1. Live'!S10='check-Jul''26'!S10,"",'1. Live'!S10-'check-Jul''26'!S10) | T10: =IF('1. Live'!T10='check-Jul''26'!T10,"",'1. Live'!T10-'check-Jul''26'!T10) | U10: =IF('1. Live'!U10='check-Jul''26'!U10,"",'1. Live'!U10-'check-Jul''26'!U10) | V10: =IF('1. Live'!V10='check-Jul''26'!V10,"",'1. Live'!V10-'check-Jul''26'!V10) | AA10: =IF('1. Live'!AA10='check-Jul''26'!W10,"",'1. Live'!AA10-'check-Jul''26'!W10) | AB10: =IF('1. Live'!AF10='check-Jul''26'!AB10,"",'1. Live'!AF10-'check-Jul''26'!AB10) | AC10: =IF('1. Live'!AG10='check-Jul''26'!AC10,"",'1. Live'!AG10-'check-Jul''26'!AC10) | AD10: =IF('1. Live'!AH10='check-Jul''26'!AD10,"",'1. Live'!AH10-'check-Jul''26'!AD10) | AE10: =IF('1. Live'!AI10='check-Jul''26'!AE10,"",'1. Live'!AI10-'check-Jul''26'!AE10) | AF10: =IF('1. Live'!AJ10='check-Jul''26'!AF10,"",'1. Live'!AJ10-'check-Jul''26'!AF10) | AG10: =IF('1. Live'!AK10='check-Jul''26'!AG10,"",'1. Live'!AK10-'check-Jul''26'!AG10) | AH10: =IF('1. Live'!AL10='check-Jul''26'!AH10,"",'1. Live'!AL10-'check-Jul''26'!AH10) | AI10: =IF('1. Live'!AM10='check-Jul''26'!AI10,"",'1. Live'!AM10-'check-Jul''26'!AI10) | ... CV10: =IF('1. Live'!CZ10='check-Jul''26'!CV10,"",'1. Live'!CZ10-'check-Jul''26'!CV10)
C11: eSpace | D11: Sushil | E11: Peng | F11: USA | G11: Space | H11: C Prefs | I11: Direct Investment | J11: Unrealized | K11: Mozn 4 | L11: 2022 | M11: B Prefs | N11: =IF('1. Live'!N11='check-Jul''26'!N11,"",'1. Live'!N11-'check-Jul''26'!N11) | O11: =IF('1. Live'!O11='check-Jul''26'!O11,"",'1. Live'!O11-'check-Jul''26'!O11) | P11: =IF('1. Live'!P11='check-Jul''26'!P11,"",'1. Live'!P11-'check-Jul''26'!P11) | Q11: =IF('1. Live'!Q11='check-Jul''26'!Q11,"",'1. Live'!Q11-'check-Jul''26'!Q11) | R11: =IF('1. Live'!R11='check-Jul''26'!R11,"",'1. Live'!R11-'check-Jul''26'!R11) | S11: =IF('1. Live'!S11='check-Jul''26'!S11,"",'1. Live'!S11-'check-Jul''26'!S11) | T11: =IF('1. Live'!T11='check-Jul''26'!T11,"",'1. Live'!T11-'check-Jul''26'!T11) | U11: =IF('1. Live'!U11='check-Jul''26'!U11,"",'1. Live'!U11-'check-Jul''26'!U11) | V11: =IF('1. Live'!V11='check-Jul''26'!V11,"",'1. Live'!V11-'check-Jul''26'!V11) | AA11: =IF('1. Live'!AA11='check-Jul''26'!W11,"",'1. Live'!AA11-'check-Jul''26'!W11) | AB11: =IF('1. Live'!AF11='check-Jul''26'!AB11,"",'1. Live'!AF11-'check-Jul''26'!AB11) | AC11: =IF('1. Live'!AG11='check-Jul''26'!AC11,"",'1. Live'!AG11-'check-Jul''26'!AC11) | AD11: =IF('1. Live'!AH11='check-Jul''26'!AD11,"",'1. Live'!AH11-'check-Jul''26'!AD11) | AE11: =IF('1. Live'!AI11='check-Jul''26'!AE11,"",'1. Live'!AI11-'check-Jul''26'!AE11) | AF11: =IF('1. Live'!AJ11='check-Jul''26'!AF11,"",'1. Live'!AJ11-'check-Jul''26'!AF11) | AG11: =IF('1. Live'!AK11='check-Jul''26'!AG11,"",'1. Live'!AK11-'check-Jul''26'!AG11) | AH11: =IF('1. Live'!AL11='check-Jul''26'!AH11,"",'1. Live'!AL11-'check-Jul''26'!AH11) | AI11: =IF('1. Live'!AM11='check-Jul''26'!AI11,"",'1. Live'!AM11-'check-Jul''26'!AI11) | ... CV11: =IF('1. Live'!CZ11='check-Jul''26'!CV11,"",'1. Live'!CZ11-'check-Jul''26'!CV11)
C12: Applied AI Corporation Limited | D12: Divyesh | E12: HE Tariq | F12: UAE/UK | G12: AI Software | H12: Convertible | I12: Direct Investment | J12: Unrealized | K12: Mozn | L12: 2022 | M12: A Prefs | N12: =IF('1. Live'!N12='check-Jul''26'!N12,"",'1. Live'!N12-'check-Jul''26'!N12) | O12: =IF('1. Live'!O12='check-Jul''26'!O12,"",'1. Live'!O12-'check-Jul''26'!O12) | P12: =IF('1. Live'!P12='check-Jul''26'!P12,"",'1. Live'!P12-'check-Jul''26'!P12) | Q12: =IF('1. Live'!Q12='check-Jul''26'!Q12,"",'1. Live'!Q12-'check-Jul''26'!Q12) | R12: =IF('1. Live'!R12='check-Jul''26'!R12,"",'1. Live'!R12-'check-Jul''26'!R12) | S12: =IF('1. Live'!S12='check-Jul''26'!S12,"",'1. Live'!S12-'check-Jul''26'!S12) | T12: =IF('1. Live'!T12='check-Jul''26'!T12,"",'1. Live'!T12-'check-Jul''26'!T12) | U12: =IF('1. Live'!U12='check-Jul''26'!U12,"",'1. Live'!U12-'check-Jul''26'!U12) | V12: =IF('1. Live'!V12='check-Jul''26'!V12,"",'1. Live'!V12-'check-Jul''26'!V12) | AA12: =IF('1. Live'!AA12='check-Jul''26'!W12,"",'1. Live'!AA12-'check-Jul''26'!W12) | AB12: =IF('1. Live'!AF12='check-Jul''26'!AB12,"",'1. Live'!AF12-'check-Jul''26'!AB12) | AC12: =IF('1. Live'!AG12='check-Jul''26'!AC12,"",'1. Live'!AG12-'check-Jul''26'!AC12) | AD12: =IF('1. Live'!AH12='check-Jul''26'!AD12,"",'1. Live'!AH12-'check-Jul''26'!AD12) | AE12: =IF('1. Live'!AI12='check-Jul''26'!AE12,"",'1. Live'!AI12-'check-Jul''26'!AE12) | AF12: =IF('1. Live'!AJ12='check-Jul''26'!AF12,"",'1. Live'!AJ12-'check-Jul''26'!AF12) | AG12: =IF('1. Live'!AK12='check-Jul''26'!AG12,"",'1. Live'!AK12-'check-Jul''26'!AG12) | AH12: =IF('1. Live'!AL12='check-Jul''26'!AH12,"",'1. Live'!AL12-'check-Jul''26'!AH12) | AI12: =IF('1. Live'!AM12='check-Jul''26'!AI12,"",'1. Live'!AM12-'check-Jul''26'!AI12) | ... CV12: =IF('1. Live'!CZ12='check-Jul''26'!CV12,"",'1. Live'!CZ12-'check-Jul''26'!CV12)
C13: Cerebras Systems Inc (1) | D13: Divyesh | E13: Peng | F13: USA | G13: Semiconductors | H13: Listed | I13: Direct Investment | J13: Unrealized | K13: Mozn | L13: 2021 | M13: F Prefs | N13: =IF('1. Live'!N13='check-Jul''26'!N13,"",'1. Live'!N13-'check-Jul''26'!N13) | O13: =IF('1. Live'!O13='check-Jul''26'!O13,"",'1. Live'!O13-'check-Jul''26'!O13) | P13: =IF('1. Live'!P13='check-Jul''26'!P13,"",'1. Live'!P13-'check-Jul''26'!P13) | Q13: =IF('1. Live'!Q13='check-Jul''26'!Q13,"",'1. Live'!Q13-'check-Jul''26'!Q13) | R13: =IF('1. Live'!R13='check-Jul''26'!R13,"",'1. Live'!R13-'check-Jul''26'!R13) | S13: =IF('1. Live'!S13='check-Jul''26'!S13,"",'1. Live'!S13-'check-Jul''26'!S13) -> -20.861558 | T13: =IF('1. Live'!T13='check-Jul''26'!T13,"",'1. Live'!T13-'check-Jul''26'!T13) -> -20.861558 | U13: =IF('1. Live'!U13='check-Jul''26'!U13,"",'1. Live'!U13-'check-Jul''26'!U13) -> -0.52153917 | V13: =IF('1. Live'!V13='check-Jul''26'!V13,"",'1. Live'!V13-'check-Jul''26'!V13) | AA13: =IF('1. Live'!AA13='check-Jul''26'!W13,"",'1. Live'!AA13-'check-Jul''26'!W13) | AB13: =IF('1. Live'!AF13='check-Jul''26'!AB13,"",'1. Live'!AF13-'check-Jul''26'!AB13) | AC13: =IF('1. Live'!AG13='check-Jul''26'!AC13,"",'1. Live'!AG13-'check-Jul''26'!AC13) | AD13: =IF('1. Live'!AH13='check-Jul''26'!AD13,"",'1. Live'!AH13-'check-Jul''26'!AD13) | AE13: =IF('1. Live'!AI13='check-Jul''26'!AE13,"",'1. Live'!AI13-'check-Jul''26'!AE13) | AF13: =IF('1. Live'!AJ13='check-Jul''26'!AF13,"",'1. Live'!AJ13-'check-Jul''26'!AF13) | AG13: =IF('1. Live'!AK13='check-Jul''26'!AG13,"",'1. Live'!AK13-'check-Jul''26'!AG13) | AH13: =IF('1. Live'!AL13='check-Jul''26'!AH13,"",'1. Live'!AL13-'check-Jul''26'!AH13) | AI13: =IF('1. Live'!AM13='check-Jul''26'!AI13,"",'1. Live'!AM13-'check-Jul''26'!AI13) | ... CV13: =IF('1. Live'!CZ13='check-Jul''26'!CV13,"",'1. Live'!CZ13-'check-Jul''26'!CV13)
C14: Endless Studios LLC | D14: Sushil | E14: Peng | F14: USA | G14: Gaming | H14: A Pref Units | I14: Direct Investment | J14: Unrealized | K14: Mozn | L14: 2021 | M14: A Pref Units | N14: =IF('1. Live'!N14='check-Jul''26'!N14,"",'1. Live'!N14-'check-Jul''26'!N14) | O14: =IF('1. Live'!O14='check-Jul''26'!O14,"",'1. Live'!O14-'check-Jul''26'!O14) | P14: =IF('1. Live'!P14='check-Jul''26'!P14,"",'1. Live'!P14-'check-Jul''26'!P14) | Q14: =IF('1. Live'!Q14='check-Jul''26'!Q14,"",'1. Live'!Q14-'check-Jul''26'!Q14) | R14: =IF('1. Live'!R14='check-Jul''26'!R14,"",'1. Live'!R14-'check-Jul''26'!R14) | S14: =IF('1. Live'!S14='check-Jul''26'!S14,"",'1. Live'!S14-'check-Jul''26'!S14) | T14: =IF('1. Live'!T14='check-Jul''26'!T14,"",'1. Live'!T14-'check-Jul''26'!T14) | U14: =IF('1. Live'!U14='check-Jul''26'!U14,"",'1. Live'!U14-'check-Jul''26'!U14) | V14: =IF('1. Live'!V14='check-Jul''26'!V14,"",'1. Live'!V14-'check-Jul''26'!V14) | AA14: =IF('1. Live'!AA14='check-Jul''26'!W14,"",'1. Live'!AA14-'check-Jul''26'!W14) | AB14: =IF('1. Live'!AF14='check-Jul''26'!AB14,"",'1. Live'!AF14-'check-Jul''26'!AB14) | AC14: =IF('1. Live'!AG14='check-Jul''26'!AC14,"",'1. Live'!AG14-'check-Jul''26'!AC14) | AD14: =IF('1. Live'!AH14='check-Jul''26'!AD14,"",'1. Live'!AH14-'check-Jul''26'!AD14) | AE14: =IF('1. Live'!AI14='check-Jul''26'!AE14,"",'1. Live'!AI14-'check-Jul''26'!AE14) | AF14: =IF('1. Live'!AJ14='check-Jul''26'!AF14,"",'1. Live'!AJ14-'check-Jul''26'!AF14) | AG14: =IF('1. Live'!AK14='check-Jul''26'!AG14,"",'1. Live'!AK14-'check-Jul''26'!AG14) | AH14: =IF('1. Live'!AL14='check-Jul''26'!AH14,"",'1. Live'!AL14-'check-Jul''26'!AH14) | AI14: =IF('1. Live'!AM14='check-Jul''26'!AI14,"",'1. Live'!AM14-'check-Jul''26'!AI14) | ... CV14: =IF('1. Live'!CZ14='check-Jul''26'!CV14,"",'1. Live'!CZ14-'check-Jul''26'!CV14)
C15: Heygears | D15: Divyesh | E15: Peng | F15: PRC | G15: 3D Printing | H15: Series D | I15: Direct Investment | J15: Unrealized | K15: Mozn | L15: 2020 | M15: Registered Capital | N15: =IF('1. Live'!N15='check-Jul''26'!N15,"",'1. Live'!N15-'check-Jul''26'!N15) | O15: =IF('1. Live'!O15='check-Jul''26'!O15,"",'1. Live'!O15-'check-Jul''26'!O15) | P15: =IF('1. Live'!P15='check-Jul''26'!P15,"",'1. Live'!P15-'check-Jul''26'!P15) | Q15: =IF('1. Live'!Q15='check-Jul''26'!Q15,"",'1. Live'!Q15-'check-Jul''26'!Q15) | R15: =IF('1. Live'!R15='check-Jul''26'!R15,"",'1. Live'!R15-'check-Jul''26'!R15) | S15: =IF('1. Live'!S15='check-Jul''26'!S15,"",'1. Live'!S15-'check-Jul''26'!S15) | T15: =IF('1. Live'!T15='check-Jul''26'!T15,"",'1. Live'!T15-'check-Jul''26'!T15) | U15: =IF('1. Live'!U15='check-Jul''26'!U15,"",'1. Live'!U15-'check-Jul''26'!U15) | V15: =IF('1. Live'!V15='check-Jul''26'!V15,"",'1. Live'!V15-'check-Jul''26'!V15) | AA15: =IF('1. Live'!AA15='check-Jul''26'!W15,"",'1. Live'!AA15-'check-Jul''26'!W15) | AB15: =IF('1. Live'!AF15='check-Jul''26'!AB15,"",'1. Live'!AF15-'check-Jul''26'!AB15) | AC15: =IF('1. Live'!AG15='check-Jul''26'!AC15,"",'1. Live'!AG15-'check-Jul''26'!AC15) | AD15: =IF('1. Live'!AH15='check-Jul''26'!AD15,"",'1. Live'!AH15-'check-Jul''26'!AD15) | AE15: =IF('1. Live'!AI15='check-Jul''26'!AE15,"",'1. Live'!AI15-'check-Jul''26'!AE15) | AF15: =IF('1. Live'!AJ15='check-Jul''26'!AF15,"",'1. Live'!AJ15-'check-Jul''26'!AF15) | AG15: =IF('1. Live'!AK15='check-Jul''26'!AG15,"",'1. Live'!AK15-'check-Jul''26'!AG15) | AH15: =IF('1. Live'!AL15='check-Jul''26'!AH15,"",'1. Live'!AL15-'check-Jul''26'!AH15) | AI15: =IF('1. Live'!AM15='check-Jul''26'!AI15,"",'1. Live'!AM15-'check-Jul''26'!AI15) | ... CV15: =IF('1. Live'!CZ15='check-Jul''26'!CV15,"",'1. Live'!CZ15-'check-Jul''26'!CV15)
C16: Beyond Limits | D16: Sushil | E16: Peng | F16: USA | G16: AI Software | H16: C Prefs | I16: Direct Investment | J16: Unrealized | K16: Mozn | L16: 2020 | M16: C Prefs | N16: =IF('1. Live'!N16='check-Jul''26'!N16,"",'1. Live'!N16-'check-Jul''26'!N16) | O16: =IF('1. Live'!O16='check-Jul''26'!O16,"",'1. Live'!O16-'check-Jul''26'!O16) | P16: =IF('1. Live'!P16='check-Jul''26'!P16,"",'1. Live'!P16-'check-Jul''26'!P16) | Q16: =IF('1. Live'!Q16='check-Jul''26'!Q16,"",'1. Live'!Q16-'check-Jul''26'!Q16) | R16: =IF('1. Live'!R16='check-Jul''26'!R16,"",'1. Live'!R16-'check-Jul''26'!R16) | S16: =IF('1. Live'!S16='check-Jul''26'!S16,"",'1. Live'!S16-'check-Jul''26'!S16) | T16: =IF('1. Live'!T16='check-Jul''26'!T16,"",'1. Live'!T16-'check-Jul''26'!T16) | U16: =IF('1. Live'!U16='check-Jul''26'!U16,"",'1. Live'!U16-'check-Jul''26'!U16) | V16: =IF('1. Live'!V16='check-Jul''26'!V16,"",'1. Live'!V16-'check-Jul''26'!V16) | AA16: =IF('1. Live'!AA16='check-Jul''26'!W16,"",'1. Live'!AA16-'check-Jul''26'!W16) | AB16: =IF('1. Live'!AF16='check-Jul''26'!AB16,"",'1. Live'!AF16-'check-Jul''26'!AB16) | AC16: =IF('1. Live'!AG16='check-Jul''26'!AC16,"",'1. Live'!AG16-'check-Jul''26'!AC16) | AD16: =IF('1. Live'!AH16='check-Jul''26'!AD16,"",'1. Live'!AH16-'check-Jul''26'!AD16) | AE16: =IF('1. Live'!AI16='check-Jul''26'!AE16,"",'1. Live'!AI16-'check-Jul''26'!AE16) | AF16: =IF('1. Live'!AJ16='check-Jul''26'!AF16,"",'1. Live'!AJ16-'check-Jul''26'!AF16) | AG16: =IF('1. Live'!AK16='check-Jul''26'!AG16,"",'1. Live'!AK16-'check-Jul''26'!AG16) | AH16: =IF('1. Live'!AL16='check-Jul''26'!AH16,"",'1. Live'!AL16-'check-Jul''26'!AH16) | AI16: =IF('1. Live'!AM16='check-Jul''26'!AI16,"",'1. Live'!AM16-'check-Jul''26'!AI16) | ... CV16: =IF('1. Live'!CZ16='check-Jul''26'!CV16,"",'1. Live'!CZ16-'check-Jul''26'!CV16)
C17: ONT plc | D17: Divyesh | E17: Peng | F17: UK | G17: Genome Sequencing | H17: Ordinary Shares | I17: Direct Investment | J17: Unrealized | K17: Mozn | L17: 2020 | M17: Ordinary Shares | N17: =IF('1. Live'!N17='check-Jul''26'!N17,"",'1. Live'!N17-'check-Jul''26'!N17) | O17: =IF('1. Live'!O17='check-Jul''26'!O17,"",'1. Live'!O17-'check-Jul''26'!O17) | P17: =IF('1. Live'!P17='check-Jul''26'!P17,"",'1. Live'!P17-'check-Jul''26'!P17) | Q17: =IF('1. Live'!Q17='check-Jul''26'!Q17,"",'1. Live'!Q17-'check-Jul''26'!Q17) | R17: =IF('1. Live'!R17='check-Jul''26'!R17,"",'1. Live'!R17-'check-Jul''26'!R17) | S17: =IF('1. Live'!S17='check-Jul''26'!S17,"",'1. Live'!S17-'check-Jul''26'!S17) -> 37.704967 | T17: =IF('1. Live'!T17='check-Jul''26'!T17,"",'1. Live'!T17-'check-Jul''26'!T17) -> 37.704967 | U17: =IF('1. Live'!U17='check-Jul''26'!U17,"",'1. Live'!U17-'check-Jul''26'!U17) -> 0.26652221 | V17: =IF('1. Live'!V17='check-Jul''26'!V17,"",'1. Live'!V17-'check-Jul''26'!V17) | AA17: =IF('1. Live'!AA17='check-Jul''26'!W17,"",'1. Live'!AA17-'check-Jul''26'!W17) | AB17: =IF('1. Live'!AF17='check-Jul''26'!AB17,"",'1. Live'!AF17-'check-Jul''26'!AB17) | AC17: =IF('1. Live'!AG17='check-Jul''26'!AC17,"",'1. Live'!AG17-'check-Jul''26'!AC17) | AD17: =IF('1. Live'!AH17='check-Jul''26'!AD17,"",'1. Live'!AH17-'check-Jul''26'!AD17) | AE17: =IF('1. Live'!AI17='check-Jul''26'!AE17,"",'1. Live'!AI17-'check-Jul''26'!AE17) | AF17: =IF('1. Live'!AJ17='check-Jul''26'!AF17,"",'1. Live'!AJ17-'check-Jul''26'!AF17) | AG17: =IF('1. Live'!AK17='check-Jul''26'!AG17,"",'1. Live'!AK17-'check-Jul''26'!AG17) | AH17: =IF('1. Live'!AL17='check-Jul''26'!AH17,"",'1. Live'!AL17-'check-Jul''26'!AH17) | AI17: =IF('1. Live'!AM17='check-Jul''26'!AI17,"",'1. Live'!AM17-'check-Jul''26'!AI17) | ... CV17: =IF('1. Live'!CZ17='check-Jul''26'!CV17,"",'1. Live'!CZ17-'check-Jul''26'!CV17)
C18: Flyr Inc | D18: Divyesh | E18: Peng | F18: USA | G18: Aviation | H18: B-1,2 Prefs | I18: Direct Investment | J18: Unrealized | K18: Mozn | L18: 2019 | M18: B-1,2 Prefs | N18: =IF('1. Live'!N18='check-Jul''26'!N18,"",'1. Live'!N18-'check-Jul''26'!N18) | O18: =IF('1. Live'!O18='check-Jul''26'!O18,"",'1. Live'!O18-'check-Jul''26'!O18) | P18: =IF('1. Live'!P18='check-Jul''26'!P18,"",'1. Live'!P18-'check-Jul''26'!P18) | Q18: =IF('1. Live'!Q18='check-Jul''26'!Q18,"",'1. Live'!Q18-'check-Jul''26'!Q18) | R18: =IF('1. Live'!R18='check-Jul''26'!R18,"",'1. Live'!R18-'check-Jul''26'!R18) | S18: =IF('1. Live'!S18='check-Jul''26'!S18,"",'1. Live'!S18-'check-Jul''26'!S18) | T18: =IF('1. Live'!T18='check-Jul''26'!T18,"",'1. Live'!T18-'check-Jul''26'!T18) | U18: =IF('1. Live'!U18='check-Jul''26'!U18,"",'1. Live'!U18-'check-Jul''26'!U18) | V18: =IF('1. Live'!V18='check-Jul''26'!V18,"",'1. Live'!V18-'check-Jul''26'!V18) | AA18: =IF('1. Live'!AA18='check-Jul''26'!W18,"",'1. Live'!AA18-'check-Jul''26'!W18) | AB18: =IF('1. Live'!AF18='check-Jul''26'!AB18,"",'1. Live'!AF18-'check-Jul''26'!AB18) | AC18: =IF('1. Live'!AG18='check-Jul''26'!AC18,"",'1. Live'!AG18-'check-Jul''26'!AC18) | AD18: =IF('1. Live'!AH18='check-Jul''26'!AD18,"",'1. Live'!AH18-'check-Jul''26'!AD18) | AE18: =IF('1. Live'!AI18='check-Jul''26'!AE18,"",'1. Live'!AI18-'check-Jul''26'!AE18) | AF18: =IF('1. Live'!AJ18='check-Jul''26'!AF18,"",'1. Live'!AJ18-'check-Jul''26'!AF18) | AG18: =IF('1. Live'!AK18='check-Jul''26'!AG18,"",'1. Live'!AK18-'check-Jul''26'!AG18) | AH18: =IF('1. Live'!AL18='check-Jul''26'!AH18,"",'1. Live'!AL18-'check-Jul''26'!AH18) | AI18: =IF('1. Live'!AM18='check-Jul''26'!AI18,"",'1. Live'!AM18-'check-Jul''26'!AI18) | ... CV18: =IF('1. Live'!CZ18='check-Jul''26'!CV18,"",'1. Live'!CZ18-'check-Jul''26'!CV18)
N19: =IF('1. Live'!N19='check-Jul''26'!N19,"",'1. Live'!N19-'check-Jul''26'!N19) | O19: =IF('1. Live'!O19='check-Jul''26'!O19,"",'1. Live'!O19-'check-Jul''26'!O19) | P19: =IF('1. Live'!P19='check-Jul''26'!P19,"",'1. Live'!P19-'check-Jul''26'!P19) | Q19: =IF('1. Live'!Q19='check-Jul''26'!Q19,"",'1. Live'!Q19-'check-Jul''26'!Q19) | R19: =IF('1. Live'!R19='check-Jul''26'!R19,"",'1. Live'!R19-'check-Jul''26'!R19) | S19: =IF('1. Live'!S19='check-Jul''26'!S19,"",'1. Live'!S19-'check-Jul''26'!S19) | T19: =IF('1. Live'!T19='check-Jul''26'!T19,"",'1. Live'!T19-'check-Jul''26'!T19) | U19: =IF('1. Live'!U19='check-Jul''26'!U19,"",'1. Live'!U19-'check-Jul''26'!U19) | V19: =IF('1. Live'!V19='check-Jul''26'!V19,"",'1. Live'!V19-'check-Jul''26'!V19) | AA19: =IF('1. Live'!AA19='check-Jul''26'!W19,"",'1. Live'!AA19-'check-Jul''26'!W19) | AB19: =IF('1. Live'!AF19='check-Jul''26'!AB19,"",'1. Live'!AF19-'check-Jul''26'!AB19) | AC19: =IF('1. Live'!AG19='check-Jul''26'!AC19,"",'1. Live'!AG19-'check-Jul''26'!AC19) | AD19: =IF('1. Live'!AH19='check-Jul''26'!AD19,"",'1. Live'!AH19-'check-Jul''26'!AD19) | AE19: =IF('1. Live'!AI19='check-Jul''26'!AE19,"",'1. Live'!AI19-'check-Jul''26'!AE19) | AF19: =IF('1. Live'!AJ19='check-Jul''26'!AF19,"",'1. Live'!AJ19-'check-Jul''26'!AF19) | AG19: =IF('1. Live'!AK19='check-Jul''26'!AG19,"",'1. Live'!AK19-'check-Jul''26'!AG19) | AH19: =IF('1. Live'!AL19='check-Jul''26'!AH19,"",'1. Live'!AL19-'check-Jul''26'!AH19) | AI19: =IF('1. Live'!AM19='check-Jul''26'!AI19,"",'1. Live'!AM19-'check-Jul''26'!AI19) | ... CV19: =IF('1. Live'!CZ19='check-Jul''26'!CV19,"",'1. Live'!CZ19-'check-Jul''26'!CV19)
N20: =IF('1. Live'!N20='check-Jul''26'!N20,"",'1. Live'!N20-'check-Jul''26'!N20) | O20: =IF('1. Live'!O20='check-Jul''26'!O20,"",'1. Live'!O20-'check-Jul''26'!O20) | P20: =IF('1. Live'!P20='check-Jul''26'!P20,"",'1. Live'!P20-'check-Jul''26'!P20) | Q20: =IF('1. Live'!Q20='check-Jul''26'!Q20,"",'1. Live'!Q20-'check-Jul''26'!Q20) | R20: =IF('1. Live'!R20='check-Jul''26'!R20,"",'1. Live'!R20-'check-Jul''26'!R20) | S20: =IF('1. Live'!S20='check-Jul''26'!S20,"",'1. Live'!S20-'check-Jul''26'!S20) -> 16.843409 | T20: =IF('1. Live'!T20='check-Jul''26'!T20,"",'1. Live'!T20-'check-Jul''26'!T20) -> 16.843409 | U20: =IF('1. Live'!U20='check-Jul''26'!U20,"",'1. Live'!U20-'check-Jul''26'!U20) -> 0.042059077 | V20: =IF('1. Live'!V20='check-Jul''26'!V20,"",'1. Live'!V20-'check-Jul''26'!V20) | AA20: =IF('1. Live'!AA20='check-Jul''26'!W20,"",'1. Live'!AA20-'check-Jul''26'!W20) | AB20: =IF('1. Live'!AF20='check-Jul''26'!AB20,"",'1. Live'!AF20-'check-Jul''26'!AB20) | AC20: =IF('1. Live'!AG20='check-Jul''26'!AC20,"",'1. Live'!AG20-'check-Jul''26'!AC20) | AD20: =IF('1. Live'!AH20='check-Jul''26'!AD20,"",'1. Live'!AH20-'check-Jul''26'!AD20) | AE20: =IF('1. Live'!AI20='check-Jul''26'!AE20,"",'1. Live'!AI20-'check-Jul''26'!AE20) | AF20: =IF('1. Live'!AJ20='check-Jul''26'!AF20,"",'1. Live'!AJ20-'check-Jul''26'!AF20) | AG20: =IF('1. Live'!AK20='check-Jul''26'!AG20,"",'1. Live'!AK20-'check-Jul''26'!AG20) | AH20: =IF('1. Live'!AL20='check-Jul''26'!AH20,"",'1. Live'!AL20-'check-Jul''26'!AH20) | AI20: =IF('1. Live'!AM20='check-Jul''26'!AI20,"",'1. Live'!AM20-'check-Jul''26'!AI20) | ... CV20: =IF('1. Live'!CZ20='check-Jul''26'!CV20,"",'1. Live'!CZ20-'check-Jul''26'!CV20)
N21: =IF('1. Live'!N21='check-Jul''26'!N21,"",'1. Live'!N21-'check-Jul''26'!N21) | O21: =IF('1. Live'!O21='check-Jul''26'!O21,"",'1. Live'!O21-'check-Jul''26'!O21) | P21: =IF('1. Live'!P21='check-Jul''26'!P21,"",'1. Live'!P21-'check-Jul''26'!P21) | Q21: =IF('1. Live'!Q21='check-Jul''26'!Q21,"",'1. Live'!Q21-'check-Jul''26'!Q21) | R21: =IF('1. Live'!R21='check-Jul''26'!R21,"",'1. Live'!R21-'check-Jul''26'!R21) | S21: =IF('1. Live'!S21='check-Jul''26'!S21,"",'1. Live'!S21-'check-Jul''26'!S21) | T21: =IF('1. Live'!T21='check-Jul''26'!T21,"",'1. Live'!T21-'check-Jul''26'!T21) | U21: =IF('1. Live'!U21='check-Jul''26'!U21,"",'1. Live'!U21-'check-Jul''26'!U21) | V21: =IF('1. Live'!V21='check-Jul''26'!V21,"",'1. Live'!V21-'check-Jul''26'!V21) | AA21: =IF('1. Live'!AA21='check-Jul''26'!W21,"",'1. Live'!AA21-'check-Jul''26'!W21) | AB21: =IF('1. Live'!AF21='check-Jul''26'!AB21,"",'1. Live'!AF21-'check-Jul''26'!AB21) | AC21: =IF('1. Live'!AG21='check-Jul''26'!AC21,"",'1. Live'!AG21-'check-Jul''26'!AC21) | AD21: =IF('1. Live'!AH21='check-Jul''26'!AD21,"",'1. Live'!AH21-'check-Jul''26'!AD21) | AE21: =IF('1. Live'!AI21='check-Jul''26'!AE21,"",'1. Live'!AI21-'check-Jul''26'!AE21) | AF21: =IF('1. Live'!AJ21='check-Jul''26'!AF21,"",'1. Live'!AJ21-'check-Jul''26'!AF21) | AG21: =IF('1. Live'!AK21='check-Jul''26'!AG21,"",'1. Live'!AK21-'check-Jul''26'!AG21) | AH21: =IF('1. Live'!AL21='check-Jul''26'!AH21,"",'1. Live'!AL21-'check-Jul''26'!AH21) | AI21: =IF('1. Live'!AM21='check-Jul''26'!AI21,"",'1. Live'!AM21-'check-Jul''26'!AI21) | ... CV21: =IF('1. Live'!CZ21='check-Jul''26'!CV21,"",'1. Live'!CZ21-'check-Jul''26'!CV21)
C22: G42 Investments AI Holding RSC Ltd | N22: =IF('1. Live'!N22='check-Jul''26'!N22,"",'1. Live'!N22-'check-Jul''26'!N22) | O22: =IF('1. Live'!O22='check-Jul''26'!O22,"",'1. Live'!O22-'check-Jul''26'!O22) | P22: =IF('1. Live'!P22='check-Jul''26'!P22,"",'1. Live'!P22-'check-Jul''26'!P22) | Q22: =IF('1. Live'!Q22='check-Jul''26'!Q22,"",'1. Live'!Q22-'check-Jul''26'!Q22) | R22: =IF('1. Live'!R22='check-Jul''26'!R22,"",'1. Live'!R22-'check-Jul''26'!R22) | S22: =IF('1. Live'!S22='check-Jul''26'!S22,"",'1. Live'!S22-'check-Jul''26'!S22) | T22: =IF('1. Live'!T22='check-Jul''26'!T22,"",'1. Live'!T22-'check-Jul''26'!T22) | U22: =IF('1. Live'!U22='check-Jul''26'!U22,"",'1. Live'!U22-'check-Jul''26'!U22) | V22: =IF('1. Live'!V22='check-Jul''26'!V22,"",'1. Live'!V22-'check-Jul''26'!V22) | AA22: =IF('1. Live'!AA22='check-Jul''26'!W22,"",'1. Live'!AA22-'check-Jul''26'!W22) | AB22: =IF('1. Live'!AF22='check-Jul''26'!AB22,"",'1. Live'!AF22-'check-Jul''26'!AB22) | AC22: =IF('1. Live'!AG22='check-Jul''26'!AC22,"",'1. Live'!AG22-'check-Jul''26'!AC22) | AD22: =IF('1. Live'!AH22='check-Jul''26'!AD22,"",'1. Live'!AH22-'check-Jul''26'!AD22) | AE22: =IF('1. Live'!AI22='check-Jul''26'!AE22,"",'1. Live'!AI22-'check-Jul''26'!AE22) | AF22: =IF('1. Live'!AJ22='check-Jul''26'!AF22,"",'1. Live'!AJ22-'check-Jul''26'!AF22) | AG22: =IF('1. Live'!AK22='check-Jul''26'!AG22,"",'1. Live'!AK22-'check-Jul''26'!AG22) | AH22: =IF('1. Live'!AL22='check-Jul''26'!AH22,"",'1. Live'!AL22-'check-Jul''26'!AH22) | AI22: =IF('1. Live'!AM22='check-Jul''26'!AI22,"",'1. Live'!AM22-'check-Jul''26'!AI22) | ... CV22: =IF('1. Live'!CZ22='check-Jul''26'!CV22,"",'1. Live'!CZ22-'check-Jul''26'!CV22)
C23: DriveNets | D23: Sushil | E23: HE Tariq | F23: Israel | G23: Networking | I23: Direct Investment | J23: Partially Realized | K23: G42 Investments | L23: 2022 | M23: Equity-TBC | N23: =IF('1. Live'!N23='check-Jul''26'!N23,"",'1. Live'!N23-'check-Jul''26'!N23) | O23: =IF('1. Live'!O23='check-Jul''26'!O23,"",'1. Live'!O23-'check-Jul''26'!O23) | P23: =IF('1. Live'!P23='check-Jul''26'!P23,"",'1. Live'!P23-'check-Jul''26'!P23) | Q23: =IF('1. Live'!Q23='check-Jul''26'!Q23,"",'1. Live'!Q23-'check-Jul''26'!Q23) | R23: =IF('1. Live'!R23='check-Jul''26'!R23,"",'1. Live'!R23-'check-Jul''26'!R23) | S23: =IF('1. Live'!S23='check-Jul''26'!S23,"",'1. Live'!S23-'check-Jul''26'!S23) | T23: =IF('1. Live'!T23='check-Jul''26'!T23,"",'1. Live'!T23-'check-Jul''26'!T23) | U23: =IF('1. Live'!U23='check-Jul''26'!U23,"",'1. Live'!U23-'check-Jul''26'!U23) | V23: =IF('1. Live'!V23='check-Jul''26'!V23,"",'1. Live'!V23-'check-Jul''26'!V23) | AA23: =IF('1. Live'!AA23='check-Jul''26'!W23,"",'1. Live'!AA23-'check-Jul''26'!W23) | AB23: =IF('1. Live'!AF23='check-Jul''26'!AB23,"",'1. Live'!AF23-'check-Jul''26'!AB23) | AC23: =IF('1. Live'!AG23='check-Jul''26'!AC23,"",'1. Live'!AG23-'check-Jul''26'!AC23) | AD23: =IF('1. Live'!AH23='check-Jul''26'!AD23,"",'1. Live'!AH23-'check-Jul''26'!AD23) | AE23: =IF('1. Live'!AI23='check-Jul''26'!AE23,"",'1. Live'!AI23-'check-Jul''26'!AE23) | AF23: =IF('1. Live'!AJ23='check-Jul''26'!AF23,"",'1. Live'!AJ23-'check-Jul''26'!AF23) | AG23: =IF('1. Live'!AK23='check-Jul''26'!AG23,"",'1. Live'!AK23-'check-Jul''26'!AG23) | AH23: =IF('1. Live'!AL23='check-Jul''26'!AH23,"",'1. Live'!AL23-'check-Jul''26'!AH23) | AI23: =IF('1. Live'!AM23='check-Jul''26'!AI23,"",'1. Live'!AM23-'check-Jul''26'!AI23) | ... CV23: =IF('1. Live'!CZ23='check-Jul''26'!CV23,"",'1. Live'!CZ23-'check-Jul''26'!CV23)
C24: vTv Therapeutics Inc. | D24: Divyesh | E24: Dr. Fahed, M42 | F24: USA | G24: Healthcare | I24: Direct Investment | J24: Unrealized | K24: G42 Investments | L24: 2022 | M24: Ordinary Shares | N24: =IF('1. Live'!N24='check-Jul''26'!N24,"",'1. Live'!N24-'check-Jul''26'!N24) | O24: =IF('1. Live'!O24='check-Jul''26'!O24,"",'1. Live'!O24-'check-Jul''26'!O24) | P24: =IF('1. Live'!P24='check-Jul''26'!P24,"",'1. Live'!P24-'check-Jul''26'!P24) | Q24: =IF('1. Live'!Q24='check-Jul''26'!Q24,"",'1. Live'!Q24-'check-Jul''26'!Q24) | R24: =IF('1. Live'!R24='check-Jul''26'!R24,"",'1. Live'!R24-'check-Jul''26'!R24) | S24: =IF('1. Live'!S24='check-Jul''26'!S24,"",'1. Live'!S24-'check-Jul''26'!S24) -> -0.09087995 | T24: =IF('1. Live'!T24='check-Jul''26'!T24,"",'1. Live'!T24-'check-Jul''26'!T24) -> -0.09087995 | U24: =IF('1. Live'!U24='check-Jul''26'!U24,"",'1. Live'!U24-'check-Jul''26'!U24) -> -0.0037046604 | V24: =IF('1. Live'!V24='check-Jul''26'!V24,"",'1. Live'!V24-'check-Jul''26'!V24) | AA24: =IF('1. Live'!AA24='check-Jul''26'!W24,"",'1. Live'!AA24-'check-Jul''26'!W24) | AB24: =IF('1. Live'!AF24='check-Jul''26'!AB24,"",'1. Live'!AF24-'check-Jul''26'!AB24) | AC24: =IF('1. Live'!AG24='check-Jul''26'!AC24,"",'1. Live'!AG24-'check-Jul''26'!AC24) | AD24: =IF('1. Live'!AH24='check-Jul''26'!AD24,"",'1. Live'!AH24-'check-Jul''26'!AD24) | AE24: =IF('1. Live'!AI24='check-Jul''26'!AE24,"",'1. Live'!AI24-'check-Jul''26'!AE24) | AF24: =IF('1. Live'!AJ24='check-Jul''26'!AF24,"",'1. Live'!AJ24-'check-Jul''26'!AF24) | AG24: =IF('1. Live'!AK24='check-Jul''26'!AG24,"",'1. Live'!AK24-'check-Jul''26'!AG24) | AH24: =IF('1. Live'!AL24='check-Jul''26'!AH24,"",'1. Live'!AL24-'check-Jul''26'!AH24) | AI24: =IF('1. Live'!AM24='check-Jul''26'!AI24,"",'1. Live'!AM24-'check-Jul''26'!AI24) | ... CV24: =IF('1. Live'!CZ24='check-Jul''26'!CV24,"",'1. Live'!CZ24-'check-Jul''26'!CV24)
C25: North Summit Capital Fund | D25: Divyesh | E25: Peng | F25: Cayman | G25: Fund | I25: Fund Investment | J25: Unrealized | K25: G42 Investments | L25: 2020 | M25: LP | N25: =IF('1. Live'!N25='check-Jul''26'!N25,"",'1. Live'!N25-'check-Jul''26'!N25) | O25: =IF('1. Live'!O25='check-Jul''26'!O25,"",'1. Live'!O25-'check-Jul''26'!O25) | P25: =IF('1. Live'!P25='check-Jul''26'!P25,"",'1. Live'!P25-'check-Jul''26'!P25) | Q25: =IF('1. Live'!Q25='check-Jul''26'!Q25,"",'1. Live'!Q25-'check-Jul''26'!Q25) | R25: =IF('1. Live'!R25='check-Jul''26'!R25,"",'1. Live'!R25-'check-Jul''26'!R25) | S25: =IF('1. Live'!S25='check-Jul''26'!S25,"",'1. Live'!S25-'check-Jul''26'!S25) -> 2.581172 | T25: =IF('1. Live'!T25='check-Jul''26'!T25,"",'1. Live'!T25-'check-Jul''26'!T25) -> 2.581172 | U25: =IF('1. Live'!U25='check-Jul''26'!U25,"",'1. Live'!U25-'check-Jul''26'!U25) -> 0.030963557 | V25: =IF('1. Live'!V25='check-Jul''26'!V25,"",'1. Live'!V25-'check-Jul''26'!V25) | AA25: =IF('1. Live'!AA25='check-Jul''26'!W25,"",'1. Live'!AA25-'check-Jul''26'!W25) | AB25: =IF('1. Live'!AF25='check-Jul''26'!AB25,"",'1. Live'!AF25-'check-Jul''26'!AB25) | AC25: =IF('1. Live'!AG25='check-Jul''26'!AC25,"",'1. Live'!AG25-'check-Jul''26'!AC25) | AD25: =IF('1. Live'!AH25='check-Jul''26'!AD25,"",'1. Live'!AH25-'check-Jul''26'!AD25) | AE25: =IF('1. Live'!AI25='check-Jul''26'!AE25,"",'1. Live'!AI25-'check-Jul''26'!AE25) | AF25: =IF('1. Live'!AJ25='check-Jul''26'!AF25,"",'1. Live'!AJ25-'check-Jul''26'!AF25) | AG25: =IF('1. Live'!AK25='check-Jul''26'!AG25,"",'1. Live'!AK25-'check-Jul''26'!AG25) | AH25: =IF('1. Live'!AL25='check-Jul''26'!AH25,"",'1. Live'!AL25-'check-Jul''26'!AH25) | AI25: =IF('1. Live'!AM25='check-Jul''26'!AI25,"",'1. Live'!AM25-'check-Jul''26'!AI25) | ... CV25: =IF('1. Live'!CZ25='check-Jul''26'!CV25,"",'1. Live'!CZ25-'check-Jul''26'!CV25)
C26: New Space Capital Fund I | D26: Sushil | E26: Peng | F26: Luxembourg | G26: Fund | I26: Fund Investment | J26: Unrealized | K26: G42 Investments | L26: 2020 | M26: LP | N26: =IF('1. Live'!N26='check-Jul''26'!N26,"",'1. Live'!N26-'check-Jul''26'!N26) | O26: =IF('1. Live'!O26='check-Jul''26'!O26,"",'1. Live'!O26-'check-Jul''26'!O26) -> 0.20887781 | P26: =IF('1. Live'!P26='check-Jul''26'!P26,"",'1. Live'!P26-'check-Jul''26'!P26) -> 0.13163326 | Q26: =IF('1. Live'!Q26='check-Jul''26'!Q26,"",'1. Live'!Q26-'check-Jul''26'!Q26) -> 0.077244558 | R26: =IF('1. Live'!R26='check-Jul''26'!R26,"",'1. Live'!R26-'check-Jul''26'!R26) | S26: =IF('1. Live'!S26='check-Jul''26'!S26,"",'1. Live'!S26-'check-Jul''26'!S26) -> 28.904034 | T26: =IF('1. Live'!T26='check-Jul''26'!T26,"",'1. Live'!T26-'check-Jul''26'!T26) -> 28.772401 | U26: =IF('1. Live'!U26='check-Jul''26'!U26,"",'1. Live'!U26-'check-Jul''26'!U26) -> 1.683208 | V26: =IF('1. Live'!V26='check-Jul''26'!V26,"",'1. Live'!V26-'check-Jul''26'!V26) | AA26: =IF('1. Live'!AA26='check-Jul''26'!W26,"",'1. Live'!AA26-'check-Jul''26'!W26) | AB26: =IF('1. Live'!AF26='check-Jul''26'!AB26,"",'1. Live'!AF26-'check-Jul''26'!AB26) | AC26: =IF('1. Live'!AG26='check-Jul''26'!AC26,"",'1. Live'!AG26-'check-Jul''26'!AC26) | AD26: =IF('1. Live'!AH26='check-Jul''26'!AD26,"",'1. Live'!AH26-'check-Jul''26'!AD26) | AE26: =IF('1. Live'!AI26='check-Jul''26'!AE26,"",'1. Live'!AI26-'check-Jul''26'!AE26) | AF26: =IF('1. Live'!AJ26='check-Jul''26'!AF26,"",'1. Live'!AJ26-'check-Jul''26'!AF26) | AG26: =IF('1. Live'!AK26='check-Jul''26'!AG26,"",'1. Live'!AK26-'check-Jul''26'!AG26) | AH26: =IF('1. Live'!AL26='check-Jul''26'!AH26,"",'1. Live'!AL26-'check-Jul''26'!AH26) | AI26: =IF('1. Live'!AM26='check-Jul''26'!AI26,"",'1. Live'!AM26-'check-Jul''26'!AI26) | ... CV26: =IF('1. Live'!CZ26='check-Jul''26'!CV26,"",'1. Live'!CZ26-'check-Jul''26'!CV26)
C27: New Space Capital GP Com SCSp | D27: Sushil | E27: Peng | F27: Luxembourg | G27: Fund | I27: Fund Investment | J27: Unrealized | K27: G42 Investments | L27: 2023 | M27: LP | N27: =IF('1. Live'!N27='check-Jul''26'!N27,"",'1. Live'!N27-'check-Jul''26'!N27) | O27: =IF('1. Live'!O27='check-Jul''26'!O27,"",'1. Live'!O27-'check-Jul''26'!O27) | P27: =IF('1. Live'!P27='check-Jul''26'!P27,"",'1. Live'!P27-'check-Jul''26'!P27) | Q27: =IF('1. Live'!Q27='check-Jul''26'!Q27,"",'1. Live'!Q27-'check-Jul''26'!Q27) | R27: =IF('1. Live'!R27='check-Jul''26'!R27,"",'1. Live'!R27-'check-Jul''26'!R27) | S27: =IF('1. Live'!S27='check-Jul''26'!S27,"",'1. Live'!S27-'check-Jul''26'!S27) -> 2.8833815 | T27: =IF('1. Live'!T27='check-Jul''26'!T27,"",'1. Live'!T27-'check-Jul''26'!T27) -> 2.8833815 | U27: =IF('1. Live'!U27='check-Jul''26'!U27,"",'1. Live'!U27-'check-Jul''26'!U27) -> 1.0655975 | V27: =IF('1. Live'!V27='check-Jul''26'!V27,"",'1. Live'!V27-'check-Jul''26'!V27) | AA27: =IF('1. Live'!AA27='check-Jul''26'!W27,"",'1. Live'!AA27-'check-Jul''26'!W27) | AB27: =IF('1. Live'!AF27='check-Jul''26'!AB27,"",'1. Live'!AF27-'check-Jul''26'!AB27) | AC27: =IF('1. Live'!AG27='check-Jul''26'!AC27,"",'1. Live'!AG27-'check-Jul''26'!AC27) | AD27: =IF('1. Live'!AH27='check-Jul''26'!AD27,"",'1. Live'!AH27-'check-Jul''26'!AD27) | AE27: =IF('1. Live'!AI27='check-Jul''26'!AE27,"",'1. Live'!AI27-'check-Jul''26'!AE27) | AF27: =IF('1. Live'!AJ27='check-Jul''26'!AF27,"",'1. Live'!AJ27-'check-Jul''26'!AF27) | AG27: =IF('1. Live'!AK27='check-Jul''26'!AG27,"",'1. Live'!AK27-'check-Jul''26'!AG27) | AH27: =IF('1. Live'!AL27='check-Jul''26'!AH27,"",'1. Live'!AL27-'check-Jul''26'!AH27) | AI27: =IF('1. Live'!AM27='check-Jul''26'!AI27,"",'1. Live'!AM27-'check-Jul''26'!AI27) | ... CV27: =IF('1. Live'!CZ27='check-Jul''26'!CV27,"",'1. Live'!CZ27-'check-Jul''26'!CV27)
C28: Acies Investments Fund I, L.P. | D28: Divyesh | E28: Peng | F28: USA | G28: Fund | I28: Fund Investment | J28: Unrealized | K28: G42 Investments | L28: 2021 | M28: LP | N28: =IF('1. Live'!N28='check-Jul''26'!N28,"",'1. Live'!N28-'check-Jul''26'!N28) | O28: =IF('1. Live'!O28='check-Jul''26'!O28,"",'1. Live'!O28-'check-Jul''26'!O28) | P28: =IF('1. Live'!P28='check-Jul''26'!P28,"",'1. Live'!P28-'check-Jul''26'!P28) | Q28: =IF('1. Live'!Q28='check-Jul''26'!Q28,"",'1. Live'!Q28-'check-Jul''26'!Q28) | R28: =IF('1. Live'!R28='check-Jul''26'!R28,"",'1. Live'!R28-'check-Jul''26'!R28) | S28: =IF('1. Live'!S28='check-Jul''26'!S28,"",'1. Live'!S28-'check-Jul''26'!S28) -> 1.351187 | T28: =IF('1. Live'!T28='check-Jul''26'!T28,"",'1. Live'!T28-'check-Jul''26'!T28) -> 1.351187 | U28: =IF('1. Live'!U28='check-Jul''26'!U28,"",'1. Live'!U28-'check-Jul''26'!U28) -> 0.08591846 | V28: =IF('1. Live'!V28='check-Jul''26'!V28,"",'1. Live'!V28-'check-Jul''26'!V28) | AA28: =IF('1. Live'!AA28='check-Jul''26'!W28,"",'1. Live'!AA28-'check-Jul''26'!W28) | AB28: =IF('1. Live'!AF28='check-Jul''26'!AB28,"",'1. Live'!AF28-'check-Jul''26'!AB28) | AC28: =IF('1. Live'!AG28='check-Jul''26'!AC28,"",'1. Live'!AG28-'check-Jul''26'!AC28) | AD28: =IF('1. Live'!AH28='check-Jul''26'!AD28,"",'1. Live'!AH28-'check-Jul''26'!AD28) | AE28: =IF('1. Live'!AI28='check-Jul''26'!AE28,"",'1. Live'!AI28-'check-Jul''26'!AE28) | AF28: =IF('1. Live'!AJ28='check-Jul''26'!AF28,"",'1. Live'!AJ28-'check-Jul''26'!AF28) | AG28: =IF('1. Live'!AK28='check-Jul''26'!AG28,"",'1. Live'!AK28-'check-Jul''26'!AG28) | AH28: =IF('1. Live'!AL28='check-Jul''26'!AH28,"",'1. Live'!AL28-'check-Jul''26'!AH28) | AI28: =IF('1. Live'!AM28='check-Jul''26'!AI28,"",'1. Live'!AM28-'check-Jul''26'!AI28) | ... CV28: =IF('1. Live'!CZ28='check-Jul''26'!CV28,"",'1. Live'!CZ28-'check-Jul''26'!CV28)
N29: =IF('1. Live'!N29='check-Jul''26'!N29,"",'1. Live'!N29-'check-Jul''26'!N29) | O29: =IF('1. Live'!O29='check-Jul''26'!O29,"",'1. Live'!O29-'check-Jul''26'!O29) | P29: =IF('1. Live'!P29='check-Jul''26'!P29,"",'1. Live'!P29-'check-Jul''26'!P29) | Q29: =IF('1. Live'!Q29='check-Jul''26'!Q29,"",'1. Live'!Q29-'check-Jul''26'!Q29) | R29: =IF('1. Live'!R29='check-Jul''26'!R29,"",'1. Live'!R29-'check-Jul''26'!R29) | S29: =IF('1. Live'!S29='check-Jul''26'!S29,"",'1. Live'!S29-'check-Jul''26'!S29) | T29: =IF('1. Live'!T29='check-Jul''26'!T29,"",'1. Live'!T29-'check-Jul''26'!T29) | U29: =IF('1. Live'!U29='check-Jul''26'!U29,"",'1. Live'!U29-'check-Jul''26'!U29) | V29: =IF('1. Live'!V29='check-Jul''26'!V29,"",'1. Live'!V29-'check-Jul''26'!V29) | AA29: =IF('1. Live'!AA29='check-Jul''26'!W29,"",'1. Live'!AA29-'check-Jul''26'!W29) | AB29: =IF('1. Live'!AF29='check-Jul''26'!AB29,"",'1. Live'!AF29-'check-Jul''26'!AB29) | AC29: =IF('1. Live'!AG29='check-Jul''26'!AC29,"",'1. Live'!AG29-'check-Jul''26'!AC29) | AD29: =IF('1. Live'!AH29='check-Jul''26'!AD29,"",'1. Live'!AH29-'check-Jul''26'!AD29) | AE29: =IF('1. Live'!AI29='check-Jul''26'!AE29,"",'1. Live'!AI29-'check-Jul''26'!AE29) | AF29: =IF('1. Live'!AJ29='check-Jul''26'!AF29,"",'1. Live'!AJ29-'check-Jul''26'!AF29) | AG29: =IF('1. Live'!AK29='check-Jul''26'!AG29,"",'1. Live'!AK29-'check-Jul''26'!AG29) | AH29: =IF('1. Live'!AL29='check-Jul''26'!AH29,"",'1. Live'!AL29-'check-Jul''26'!AH29) | AI29: =IF('1. Live'!AM29='check-Jul''26'!AI29,"",'1. Live'!AM29-'check-Jul''26'!AI29) | ... CV29: =IF('1. Live'!CZ29='check-Jul''26'!CV29,"",'1. Live'!CZ29-'check-Jul''26'!CV29)
N30: =IF('1. Live'!N30='check-Jul''26'!N30,"",'1. Live'!N30-'check-Jul''26'!N30) | O30: =IF('1. Live'!O30='check-Jul''26'!O30,"",'1. Live'!O30-'check-Jul''26'!O30) -> 0.20887781 | P30: =IF('1. Live'!P30='check-Jul''26'!P30,"",'1. Live'!P30-'check-Jul''26'!P30) -> 0.13163326 | Q30: =IF('1. Live'!Q30='check-Jul''26'!Q30,"",'1. Live'!Q30-'check-Jul''26'!Q30) -> 0.077244558 | R30: =IF('1. Live'!R30='check-Jul''26'!R30,"",'1. Live'!R30-'check-Jul''26'!R30) | S30: =IF('1. Live'!S30='check-Jul''26'!S30,"",'1. Live'!S30-'check-Jul''26'!S30) -> 35.628895 | T30: =IF('1. Live'!T30='check-Jul''26'!T30,"",'1. Live'!T30-'check-Jul''26'!T30) -> 35.497261 | U30: =IF('1. Live'!U30='check-Jul''26'!U30,"",'1. Live'!U30-'check-Jul''26'!U30) -> 0.079883193 | V30: =IF('1. Live'!V30='check-Jul''26'!V30,"",'1. Live'!V30-'check-Jul''26'!V30) | AA30: =IF('1. Live'!AA30='check-Jul''26'!W30,"",'1. Live'!AA30-'check-Jul''26'!W30) | AB30: =IF('1. Live'!AF30='check-Jul''26'!AB30,"",'1. Live'!AF30-'check-Jul''26'!AB30) | AC30: =IF('1. Live'!AG30='check-Jul''26'!AC30,"",'1. Live'!AG30-'check-Jul''26'!AC30) | AD30: =IF('1. Live'!AH30='check-Jul''26'!AD30,"",'1. Live'!AH30-'check-Jul''26'!AD30) | AE30: =IF('1. Live'!AI30='check-Jul''26'!AE30,"",'1. Live'!AI30-'check-Jul''26'!AE30) | AF30: =IF('1. Live'!AJ30='check-Jul''26'!AF30,"",'1. Live'!AJ30-'check-Jul''26'!AF30) | AG30: =IF('1. Live'!AK30='check-Jul''26'!AG30,"",'1. Live'!AK30-'check-Jul''26'!AG30) | AH30: =IF('1. Live'!AL30='check-Jul''26'!AH30,"",'1. Live'!AL30-'check-Jul''26'!AH30) | AI30: =IF('1. Live'!AM30='check-Jul''26'!AI30,"",'1. Live'!AM30-'check-Jul''26'!AI30) | ... CV30: =IF('1. Live'!CZ30='check-Jul''26'!CV30,"",'1. Live'!CZ30-'check-Jul''26'!CV30)
N31: =IF('1. Live'!N31='check-Jul''26'!N31,"",'1. Live'!N31-'check-Jul''26'!N31) | O31: =IF('1. Live'!O31='check-Jul''26'!O31,"",'1. Live'!O31-'check-Jul''26'!O31) | P31: =IF('1. Live'!P31='check-Jul''26'!P31,"",'1. Live'!P31-'check-Jul''26'!P31) | Q31: =IF('1. Live'!Q31='check-Jul''26'!Q31,"",'1. Live'!Q31-'check-Jul''26'!Q31) | R31: =IF('1. Live'!R31='check-Jul''26'!R31,"",'1. Live'!R31-'check-Jul''26'!R31) | S31: =IF('1. Live'!S31='check-Jul''26'!S31,"",'1. Live'!S31-'check-Jul''26'!S31) | T31: =IF('1. Live'!T31='check-Jul''26'!T31,"",'1. Live'!T31-'check-Jul''26'!T31) | U31: =IF('1. Live'!U31='check-Jul''26'!U31,"",'1. Live'!U31-'check-Jul''26'!U31) | V31: =IF('1. Live'!V31='check-Jul''26'!V31,"",'1. Live'!V31-'check-Jul''26'!V31) | AA31: =IF('1. Live'!AA31='check-Jul''26'!W31,"",'1. Live'!AA31-'check-Jul''26'!W31) | AB31: =IF('1. Live'!AF31='check-Jul''26'!AB31,"",'1. Live'!AF31-'check-Jul''26'!AB31) | AC31: =IF('1. Live'!AG31='check-Jul''26'!AC31,"",'1. Live'!AG31-'check-Jul''26'!AC31) | AD31: =IF('1. Live'!AH31='check-Jul''26'!AD31,"",'1. Live'!AH31-'check-Jul''26'!AD31) | AE31: =IF('1. Live'!AI31='check-Jul''26'!AE31,"",'1. Live'!AI31-'check-Jul''26'!AE31) | AF31: =IF('1. Live'!AJ31='check-Jul''26'!AF31,"",'1. Live'!AJ31-'check-Jul''26'!AF31) | AG31: =IF('1. Live'!AK31='check-Jul''26'!AG31,"",'1. Live'!AK31-'check-Jul''26'!AG31) | AH31: =IF('1. Live'!AL31='check-Jul''26'!AH31,"",'1. Live'!AL31-'check-Jul''26'!AH31) | AI31: =IF('1. Live'!AM31='check-Jul''26'!AI31,"",'1. Live'!AM31-'check-Jul''26'!AI31) | ... CV31: =IF('1. Live'!CZ31='check-Jul''26'!CV31,"",'1. Live'!CZ31-'check-Jul''26'!CV31)
C32: G42 Capital SPV RSC Ltd | N32: =IF('1. Live'!N32='check-Jul''26'!N32,"",'1. Live'!N32-'check-Jul''26'!N32) | O32: =IF('1. Live'!O32='check-Jul''26'!O32,"",'1. Live'!O32-'check-Jul''26'!O32) | P32: =IF('1. Live'!P32='check-Jul''26'!P32,"",'1. Live'!P32-'check-Jul''26'!P32) | Q32: =IF('1. Live'!Q32='check-Jul''26'!Q32,"",'1. Live'!Q32-'check-Jul''26'!Q32) | R32: =IF('1. Live'!R32='check-Jul''26'!R32,"",'1. Live'!R32-'check-Jul''26'!R32) | S32: =IF('1. Live'!S32='check-Jul''26'!S32,"",'1. Live'!S32-'check-Jul''26'!S32) | T32: =IF('1. Live'!T32='check-Jul''26'!T32,"",'1. Live'!T32-'check-Jul''26'!T32) | U32: =IF('1. Live'!U32='check-Jul''26'!U32,"",'1. Live'!U32-'check-Jul''26'!U32) | V32: =IF('1. Live'!V32='check-Jul''26'!V32,"",'1. Live'!V32-'check-Jul''26'!V32) | AA32: =IF('1. Live'!AA32='check-Jul''26'!W32,"",'1. Live'!AA32-'check-Jul''26'!W32) | AB32: =IF('1. Live'!AF32='check-Jul''26'!AB32,"",'1. Live'!AF32-'check-Jul''26'!AB32) | AC32: =IF('1. Live'!AG32='check-Jul''26'!AC32,"",'1. Live'!AG32-'check-Jul''26'!AC32) | AD32: =IF('1. Live'!AH32='check-Jul''26'!AD32,"",'1. Live'!AH32-'check-Jul''26'!AD32) | AE32: =IF('1. Live'!AI32='check-Jul''26'!AE32,"",'1. Live'!AI32-'check-Jul''26'!AE32) | AF32: =IF('1. Live'!AJ32='check-Jul''26'!AF32,"",'1. Live'!AJ32-'check-Jul''26'!AF32) | AG32: =IF('1. Live'!AK32='check-Jul''26'!AG32,"",'1. Live'!AK32-'check-Jul''26'!AG32) | AH32: =IF('1. Live'!AL32='check-Jul''26'!AH32,"",'1. Live'!AL32-'check-Jul''26'!AH32) | AI32: =IF('1. Live'!AM32='check-Jul''26'!AI32,"",'1. Live'!AM32-'check-Jul''26'!AI32) | ... CV32: =IF('1. Live'!CZ32='check-Jul''26'!CV32,"",'1. Live'!CZ32-'check-Jul''26'!CV32)
C33: Life Biosciences LLC | D33: Divyesh | E33: Peng/XP | F33: USA | G33: Healthcare | I33: Direct Investment | J33: Unrealized | K33: G42 Capital | L33: 2024 | M33: D Prefs | N33: =IF('1. Live'!N33='check-Jul''26'!N33,"",'1. Live'!N33-'check-Jul''26'!N33) | O33: =IF('1. Live'!O33='check-Jul''26'!O33,"",'1. Live'!O33-'check-Jul''26'!O33) | P33: =IF('1. Live'!P33='check-Jul''26'!P33,"",'1. Live'!P33-'check-Jul''26'!P33) | Q33: =IF('1. Live'!Q33='check-Jul''26'!Q33,"",'1. Live'!Q33-'check-Jul''26'!Q33) | R33: =IF('1. Live'!R33='check-Jul''26'!R33,"",'1. Live'!R33-'check-Jul''26'!R33) | S33: =IF('1. Live'!S33='check-Jul''26'!S33,"",'1. Live'!S33-'check-Jul''26'!S33) | T33: =IF('1. Live'!T33='check-Jul''26'!T33,"",'1. Live'!T33-'check-Jul''26'!T33) | U33: =IF('1. Live'!U33='check-Jul''26'!U33,"",'1. Live'!U33-'check-Jul''26'!U33) | V33: =IF('1. Live'!V33='check-Jul''26'!V33,"",'1. Live'!V33-'check-Jul''26'!V33) | AA33: =IF('1. Live'!AA33='check-Jul''26'!W33,"",'1. Live'!AA33-'check-Jul''26'!W33) | AB33: =IF('1. Live'!AF33='check-Jul''26'!AB33,"",'1. Live'!AF33-'check-Jul''26'!AB33) | AC33: =IF('1. Live'!AG33='check-Jul''26'!AC33,"",'1. Live'!AG33-'check-Jul''26'!AC33) | AD33: =IF('1. Live'!AH33='check-Jul''26'!AD33,"",'1. Live'!AH33-'check-Jul''26'!AD33) | AE33: =IF('1. Live'!AI33='check-Jul''26'!AE33,"",'1. Live'!AI33-'check-Jul''26'!AE33) | AF33: =IF('1. Live'!AJ33='check-Jul''26'!AF33,"",'1. Live'!AJ33-'check-Jul''26'!AF33) | AG33: =IF('1. Live'!AK33='check-Jul''26'!AG33,"",'1. Live'!AK33-'check-Jul''26'!AG33) | AH33: =IF('1. Live'!AL33='check-Jul''26'!AH33,"",'1. Live'!AL33-'check-Jul''26'!AH33) | AI33: =IF('1. Live'!AM33='check-Jul''26'!AI33,"",'1. Live'!AM33-'check-Jul''26'!AI33) | ... CV33: =IF('1. Live'!CZ33='check-Jul''26'!CV33,"",'1. Live'!CZ33-'check-Jul''26'!CV33)
C34: Verses AI Inc | D34: Divyesh | E34: Peng/XP | F34: Canada | G34: AI Software | I34: Direct Investment | J34: Unrealized | K34: G42 Capital | L34: 2024 | N34: =IF('1. Live'!N34='check-Jul''26'!N34,"",'1. Live'!N34-'check-Jul''26'!N34) | O34: =IF('1. Live'!O34='check-Jul''26'!O34,"",'1. Live'!O34-'check-Jul''26'!O34) | P34: =IF('1. Live'!P34='check-Jul''26'!P34,"",'1. Live'!P34-'check-Jul''26'!P34) | Q34: =IF('1. Live'!Q34='check-Jul''26'!Q34,"",'1. Live'!Q34-'check-Jul''26'!Q34) | R34: =IF('1. Live'!R34='check-Jul''26'!R34,"",'1. Live'!R34-'check-Jul''26'!R34) | S34: =IF('1. Live'!S34='check-Jul''26'!S34,"",'1. Live'!S34-'check-Jul''26'!S34) | T34: =IF('1. Live'!T34='check-Jul''26'!T34,"",'1. Live'!T34-'check-Jul''26'!T34) | U34: =IF('1. Live'!U34='check-Jul''26'!U34,"",'1. Live'!U34-'check-Jul''26'!U34) | V34: =IF('1. Live'!V34='check-Jul''26'!V34,"",'1. Live'!V34-'check-Jul''26'!V34) | AA34: =IF('1. Live'!AA34='check-Jul''26'!W35,"",'1. Live'!AA34-'check-Jul''26'!W35) | AB34: =IF('1. Live'!AF34='check-Jul''26'!AB35,"",'1. Live'!AF34-'check-Jul''26'!AB35) | AC34: =IF('1. Live'!AG34='check-Jul''26'!AC35,"",'1. Live'!AG34-'check-Jul''26'!AC35) | AD34: =IF('1. Live'!AH34='check-Jul''26'!AD35,"",'1. Live'!AH34-'check-Jul''26'!AD35) | AE34: =IF('1. Live'!AI34='check-Jul''26'!AE35,"",'1. Live'!AI34-'check-Jul''26'!AE35) | AF34: =IF('1. Live'!AJ34='check-Jul''26'!AF35,"",'1. Live'!AJ34-'check-Jul''26'!AF35) | AG34: =IF('1. Live'!AK34='check-Jul''26'!AG35,"",'1. Live'!AK34-'check-Jul''26'!AG35) | AH34: =IF('1. Live'!AL34='check-Jul''26'!AH35,"",'1. Live'!AL34-'check-Jul''26'!AH35) | AI34: =IF('1. Live'!AM34='check-Jul''26'!AI35,"",'1. Live'!AM34-'check-Jul''26'!AI35) | ... CV34: =IF('1. Live'!CZ34='check-Jul''26'!CV35,"",'1. Live'!CZ34-'check-Jul''26'!CV35)
